Workbook

Sheet Vu_khi
A1: id | B1: ten_that | C1: ho_id | D1: bien_the_id | E1: dong_vu_khi_id | F1: nhom | G1: co_mm | H1: dau_no_kg | I1: cong_suat_kw | J1: nang_luong_mj | K1: loai_sat_thuong | L1: xuyen | M1: dang_dan | N1: so_nong | O1: che_do_nong | P1: so_phat_moi_loat | Q1: khoang_phat_trong_loat_s | R1: thoi_gian_nap_s | S1: bang_dan | T1: nap_bang_s | U1: so_loat_mang | V1: nap_lai_kho_s | W1: sat_thuong_moi_phat | X1: loi_m | Y1: ria_m | Z1: toc_do_dan_m_s | AA1: tam_m | AB1: tam_toi_thieu_m | AC1: muc_tieu | AD1: tran_ban_m | AE1: do_tan | AF1: bac_no | AG1: danh_noc | AH1: bay_cong | AI1: nhiet_ap | AJ1: chi_danh_chan | AK1: dat_boi_boss | AL1: tia | AM1: dan_huong | AN1: kich_co | AO1: so_vien_mang_may_bay | AP1: bac_co | AQ1: ke_thua_tu | AR1: dan_thay_the | AS1: cua_ai | AT1: mang_boi | AU1: so_don_vi_mang | AV1: ten_be | AW1: thoi_gian_canh_bao_s | AX1: co_vong_canh_bao | AY1: lech_nong_s | AZ1: thoi_gian_bay_toi_tam_s | BA1: thoi_gian_bay_toi_tam_s_game | BB1: ngoai_doi_phat_phut_toi_da | BC1: ngoai_doi_phat_phut_duy_tri | BD1: ngoai_doi_loai | BE1: ngoai_doi_nguon | BF1: ly_do_sua | BG1: so_voi_ban_goc | BH1: sat_thuong_moi_phat_truoc | BI1: sat_thuong_moi_phat_sau | BJ1: thoi_gian_nap_s_truoc | BK1: thoi_gian_nap_s_sau | BL1: tam_m_truoc | BM1: tam_m_sau | BN1: loi_m_truoc | BO1: loi_m_sau | BP1: ria_m_truoc | BQ1: ria_m_sau | BR1: toc_do_dan_m_s_truoc | BS1: toc_do_dan_m_s_sau | BT1: so_phat_moi_loat_truoc | BU1: so_phat_moi_loat_sau | BV1: khoang_phat_trong_loat_s_truoc | BW1: khoang_phat_trong_loat_s_sau | BX1: so_nong_truoc | BY1: so_nong_sau | BZ1: che_do_nong_truoc | CA1: che_do_nong_sau | CB1: xuyen_truoc | CC1: xuyen_sau | CD1: loai_sat_thuong_truoc | CE1: loai_sat_thuong_sau | CF1: bang_dan_truoc | CG1: bang_dan_sau | CH1: nap_bang_s_truoc | CI1: nap_bang_s_sau | CJ1: dang_dan_truoc | CK1: dang_dan_sau | CL1: muc_tieu_truoc | CM1: muc_tieu_sau | CN1: ammo | CO1: barrels | CP1: beam | CQ1: bonuses | CR1: burst | CS1: burst_interval_s | CT1: caliber_mm | CU1: ceiling_m | CV1: charge | CW1: clip | CX1: clip_reload_s | CY1: cluster_count | CZ1: cluster_damage | DA1: cluster_radius_m | DB1: cluster_splash_m | DC1: cluster_tier | DD1: cooldown_s | DE1: damage | DF1: damage_type | DG1: edge_m | DH1: elite | DI1: energy_mj | DJ1: family | DK1: flare_resist | DL1: flight_profile | DM1: for | DN1: form | DO1: ground_min_reach_m | DP1: guided | DQ1: he | DR1: impact_scale | DS1: impact_tier | DT1: inherits | DU1: intercept_only | DV1: laid | DW1: load | DX1: lobs | DY1: melee | DZ1: min_range_m | EA1: mrsi | EB1: pen | EC1: pierce | ED1: pierce_max | EE1: piercing | EF1: power_kw | EG1: prey | EH1: projectile | EI1: projectile_model | EJ1: projectile_scale | EK1: projectile_speed_m_s | EL1: ramp_from | EM1: ramp_grace_s | EN1: ramp_seconds_s | EO1: ramp_to | EP1: range_m | EQ1: real | ER1: reload_s | ES1: round | ET1: round_length | EU1: round_of | EV1: round_weight | EW1: salvo_mode | EX1: size | EY1: splash_m | EZ1: spread | FA1: stick_anchor | FB1: stick_bay_open_s | FC1: stick_bombs | FD1: stick_drop | FE1: stick_exit_m | FF1: stick_fall_time_s | FG1: stick_heading_deg | FH1: stick_interval_s | FI1: stick_jitter_across_m | FJ1: stick_jitter_along_m | FK1: stick_lead_m | FL1: stick_length_m | FM1: stick_min_targets | FN1: stick_mode | FO1: stick_overlap | FP1: stick_release_speed_m_s | FQ1: stick_safety_m | FR1: stick_spacing_m | FS1: stick_straight_time_s | FT1: stick_warn_shape | FU1: stick_width_m | FV1: swarm | FW1: targets | FX1: thermobaric | FY1: top_attack | FZ1: warhead_kg | GA1: weapon_family | GB1: weapon_family_id | GC1: weapon_variant_id | GD1: nguon | GE1: raw_json
A2: aa_25_triple | B2: Type 96 25 mm (triple) | C2: cal_25 | D2: flak | F2: autocannon | G2: 25 | K2: Fragmentation | L2: 1 | M2: Bullet | N2: 1 | O2: RIPPLE | P2: 1 | Q2: 0.1 | R2: 0.05 | S2: 15 | T2: 2.4 | U2: 0 | V2: 0 | W2: 17 | X2: 0 | Y2: 0 | Z2: 240 | AA2: 42 | AB2: 0 | AC2: Air | AE2: 1.6 | AF2: Small | AG2: FALSE | AH2: FALSE | AI2: FALSE | AJ2: FALSE | AK2: FALSE | AL2: FALSE | AM2: FALSE | AN2: 25 | AO2: 0 | AP2: T1 | AQ2: zu23 | AR2: aa_25_triple_ap | AS2: boss | AT2: kraken;leviathan | AU2: 2 | AV2: kraken:10;kraken:11;kraken:12;kraken:13;kraken:14;kraken:7;kraken:8;kraken:9;leviathan:10;leviathan:11;leviathan:12;leviathan:13;leviathan:14;leviathan:7;leviathan:8;leviathan:9 | AW2: 0 | AX2: FALSE | AZ2: =IF(AND($AX$2,$AW$2>$AA$2/$Z$2),$AW$2,$AA$2/$Z$2) | BA2: 0.175 | BB2: 260 | BC2: 130 | BD2: aa | BE2: Wikipedia 'Type 96 25 mm AT/AA gun': 220-260 rpm a barrel | BG2: giong | CO2: 1 | CT2: 25 | CW2: 15 | CX2: 2.4 | DD2: 0.05 | DE2: 17 | DJ2: autocannon | DT2: zu23 | EB2: 1 | EP2: 42 | EQ2: Type 96 25 mm (triple) | EX2: 25 | FW2: Air | GB2: cal_25 | GC2: flak | GD2: Assets/MachineBrigade/Resources/Data/balance.json: weapons[290] | GE2: {"id":"aa_25_triple","inherits":"zu23","barrels":1,"weaponFamilyId":"cal_25","weaponVariantId":"flak","real":"Type 96 25 mm (triple)","family":"autocannon","size":25,"caliberMm":25,"pen":1,"damage":17,"cooldown":0.05,"range":42,"targets":"Air","clip":15,"clipReload":2.4}
A3: aa_25_triple_ap | B3: Type 96 25 mm AP (triple) | C3: cal_25 | F3: autocannon | G3: 25 | K3: Kinetic | L3: 2 | M3: Bullet | N3: 1 | O3: RIPPLE | P3: 1 | Q3: 0.1 | R3: 0.05 | S3: 15 | T3: 2.4 | U3: 0 | V3: 0 | W3: 17 | X3: 0 | Y3: 0 | Z3: 240 | AA3: 42 | AB3: 0 | AC3: Ground | AE3: 1.6 | AF3: Small | AG3: FALSE | AH3: FALSE | AI3: FALSE | AJ3: FALSE | AK3: FALSE | AL3: FALSE | AM3: FALSE | AN3: 25 | AO3: 0 | AP3: T1 | AQ3: aa_25_triple | AU3: 0 | AW3: 0 | AX3: FALSE | AZ3: =IF(AND($AX$3,$AW$3>$AA$3/$Z$3),$AW$3,$AA$3/$Z$3) | BA3: 0.175 | BB3: 260 | BC3: 130 | BD3: aa | BE3: Wikipedia 'Type 96 25 mm AT/AA gun': 220-260 rpm a barrel | BG3: giong | DE3: 17 | DF3: Kinetic | DM3: ground | DN3: BeltedAutocannon | DT3: aa_25_triple | EB3: 2 | EE3: TRUE | EQ3: Type 96 25 mm AP (triple) | ES3: ap | EU3: aa_25_triple | EY3: 0 | FW3: Ground | GD3: Assets/MachineBrigade/Resources/Data/balance.json: secondRounds.rounds[0] | GE3: {"id":"aa_25_triple_ap","roundOf":"aa_25_triple","inherits":"aa_25_triple","weaponVariantId":"","weaponFamily":"","round":"ap","for":["ground"],"real":"Type 96 25 mm AP (triple)","damageType":"Kinetic","pen":2,"damage":17,"splash":0,"form":"BeltedAutocannon","piercing":true,"targets":"Ground"}
A4: agl_40 | B4: Mk 19 40 mm | C4: gl_40 | E4: mk_19_40_mm | F4: grenade | G4: 40 | K4: HighExplosive | L4: 2 | M4: Bullet | N4: 1 | O4: RIPPLE | P4: 6 | Q4: 0.2 | R4: 3.2 | S4: 0 | T4: 0 | U4: 0 | V4: 0 | W4: 26 | X4: 2 | Y4: 0 | Z4: 70 | AA4: 30 | AB4: 0 | AC4: Ground | AE4: 2.2 | AF4: Small | AG4: FALSE | AH4: FALSE | AI4: FALSE | AJ4: FALSE | AK4: FALSE | AL4: FALSE | AM4: FALSE | AN4: 40 | AO4: 0 | AP4: T1 | AS4: xe | AT4: river_patrol_boat;twin_rotor_gunship | AU4: 2 | AV4: river_patrol_boat:1;twin_rotor_gunship:1 | AW4: 0 | AX4: FALSE | AZ4: =IF(AND($AX$4,$AW$4>$AA$4/$Z$4),$AW$4,$AA$4/$Z$4) | BA4: 0.42857143 | BB4: 375 | BC4: 60 | BD4: ac | BE4: US Army FM 3-22.27: 325-375 cyclic, 60 rapid | BG4: giong | CR4: 6 | CS4: 0.2 | CT4: 40 | DD4: 3.2 | DE4: 26 | DF4: HighExplosive | DJ4: grenade | DS4: Small | EB4: 2 | EH4: Bullet | EP4: 30 | EQ4: Mk 19 40 mm | EX4: 40 | EZ4: 2.2 | GA4: mk_19_40_mm | GB4: gl_40 | GD4: Assets/MachineBrigade/Resources/Data/balance.json: weapons[234] | GE4: {"id":"agl_40","weaponFamilyId":"gl_40","weaponFamily":"mk_19_40_mm","real":"Mk 19 40 mm","family":"grenade","size":40,"caliberMm":40,"pen":2,"damageType":"HighExplosive","damage":26,"cooldown":3.2,"range":30,"spread":2.2,"impactTier":"Small","projectile":"Bullet","burst":6,"burstInterval":0.2}
A5: air_cruise_missile | B5: Kh-101 (400 kg) | C5: cruise_kh_101 | F5: cruise | H5: 400 | K5: HighExplosive | L5: 3 | M5: Missile | N5: 1 | O5: RIPPLE | P5: 1 | Q5: 0.1 | R5: 11.2 | S5: 0 | T5: 0 | U5: 0 | V5: 0 | W5: 378 | X5: 9 | Y5: 0 | Z5: 65 | AA5: 110 | AB5: 0 | AC5: Ground | AE5: 0 | AF5: Huge | AG5: FALSE | AH5: FALSE | AI5: FALSE | AJ5: FALSE | AK5: FALSE | AL5: FALSE | AM5: FALSE | AN5: 400 | AO5: 2 | AP5: T4 | AS5: xe | AT5: heavy_bomber | AU5: 1 | AV5: heavy_bomber:2 | AW5: 2.5 | AX5: FALSE | AZ5: =IF(AND($AX$5,$AW$5>$AA$5/$Z$5),$AW$5,$AA$5/$Z$5) | BA5: 1.6923077 | BB5: 20 | BC5: 6 | BD5: missile | BE5: cruise missiles: ~3 s between launches (est.) | BG5: doi | BR5: 22 | BS5: 65 | DD5: 11.2 | DE5: 378 | DF5: HighExplosive | DJ5: cruise | DS5: Huge | DW5: 2 | EB5: 3 | EH5: Missile | EI5: cruise_missile | EK5: 65 | EP5: 110 | EQ5: Kh-101 (400 kg) | EV5: 450 | EX5: 400 | EY5: 9 | FZ5: 400 | GB5: cruise_kh_101 | GD5: Assets/MachineBrigade/Resources/Data/balance.json: weapons[68] | GE5: {"id":"air_cruise_missile","weaponFamilyId":"cruise_kh_101","load":2,"real":"Kh-101 (400 kg)","family":"cruise","size":400,"warheadKg":400,"pen":3,"projectileModel":"cruise_missile","damageType":"HighExplosive","damage":378,"cooldown":11.2,"range":110,"projectileSpeed":65,"splash":9,"impactTier":"Huge","projectile":"Missile","roundWeight":450}
A6: air_to_air | B6: AIM-120 AMRAAM | C6: sam_aim_120_amraam | F6: aa_missile | H6: 20 | K6: Fragmentation | L6: 3 | M6: Missile | N6: 1 | O6: RIPPLE | P6: 1 | Q6: 0.1 | R6: 3.99 | S6: 0 | T6: 0 | U6: 0 | V6: 0 | W6: 294 | X6: 2 | Y6: 0 | Z6: 300 | AA6: 60 | AB6: 0 | AC6: Air | AD6: high | AE6: 0 | AF6: Medium | AG6: FALSE | AH6: FALSE | AI6: FALSE | AJ6: FALSE | AK6: FALSE | AL6: FALSE | AM6: FALSE | AN6: 20 | AO6: 4 | AP6: T2 | AS6: xe | AT6: fighter_jet;stealth_fighter | AU6: 2 | AV6: fighter_jet:0;stealth_fighter:0 | AW6: 0 | AX6: FALSE | AZ6: =IF(AND($AX$6,$AW$6>$AA$6/$Z$6),$AW$6,$AA$6/$Z$6) | BA6: 0.2 | BB6: 60 | BD6: missile | BE6: air-to-air: ~1 s between launches (est.) | BG6: doi | BR6: 60 | BS6: 300 | CU6: high | DD6: 3.99 | DE6: 294 | DF6: Fragmentation | DJ6: aa_missile | DS6: Medium | DW6: 4 | EB6: 3 | EH6: Missile | EI6: aim120 | EJ6: 0.85 | EK6: 300 | EP6: 60 | EQ6: AIM-120 AMRAAM | EV6: 351 | EX6: 20 | EY6: 2 | FW6: Air | FZ6: 20 | GB6: sam_aim_120_amraam | GD6: Assets/MachineBrigade/Resources/Data/balance.json: weapons[62] | GE6: {"id":"air_to_air","weaponFamilyId":"sam_aim_120_amraam","ceiling":"high","load":4,"real":"AIM-120 AMRAAM","family":"aa_missile","size":20,"warheadKg":20,"pen":3,"projectileModel":"aim120","projectileScale":0.85,"damageType":"Fragmentation","damage":294,"cooldown":3.99,"range":60,"projectileSpeed":300,"splash":2,"impactTier":"Medium","projectile":"Missile","targets":"Air","roundWeight":351}
A7: airship_drones | B7: FPV drone (1.5 kg) | C7: drone_fpv_drone | E7: fpv_drone | F7: drone | H7: 1.5 | K7: ShapedCharge | L7: 3 | M7: Drone | N7: 1 | O7: RIPPLE | P7: 3 | Q7: 0.35 | R7: 8.35 | S7: 0 | T7: 0 | U7: 0 | V7: 0 | W7: 140 | X7: 2.5 | Y7: 0 | Z7: 26 | AA7: 70 | AB7: 0 | AC7: Ground | AE7: 0 | AF7: Large | AG7: TRUE | AH7: FALSE | AI7: FALSE | AJ7: FALSE | AK7: FALSE | AL7: FALSE | AM7: FALSE | AN7: 1.5 | AO7: 0 | AP7: T2 | AU7: 0 | AW7: 0 | AX7: FALSE | AZ7: =IF(AND($AX$7,$AW$7>$AA$7/$Z$7),$AW$7,$AA$7/$Z$7) | BA7: 2.6923077 | BB7: NEED_SOURCE | BC7: NEED_SOURCE | BE7: NEED_SOURCE | BG7: giong | CR7: 3 | CS7: 0.35 | DD7: 8.35 | DE7: 140 | DF7: ShapedCharge | DJ7: drone | DS7: Large | EB7: 3 | EE7: TRUE | EH7: Drone | EP7: 70 | EQ7: FPV drone (1.5 kg) | EX7: 1.5 | FY7: TRUE | FZ7: 1.5 | GA7: fpv_drone | GB7: drone_fpv_drone | GD7: Assets/MachineBrigade/Resources/Data/balance.json: weapons[246] | GE7: {"id":"airship_drones","weaponFamilyId":"drone_fpv_drone","weaponFamily":"fpv_drone","real":"FPV drone (1.5 kg)","family":"drone","size":1.5,"warheadKg":1.5,"pen":3,"topAttack":true,"piercing":true,"damageType":"ShapedCharge","damage":140,"cooldown":8.35,"range":70,"impactTier":"Large","projectile":"Drone","burst":3,"burstInterval":0.35}
A8: airship_flak | B8: S-60 57 mm | C8: cal_57 | D8: flak | F8: autocannon | G8: 57 | K8: Fragmentation | L8: 2 | M8: Bullet | N8: 1 | O8: RIPPLE | P8: 1 | Q8: 0.1 | R8: 0.5 | S8: 8 | T8: 1.38 | U8: 0 | V8: 0 | W8: 70 | X8: 3 | Y8: 0 | Z8: 280 | AA8: 48 | AB8: 0 | AC8: All | AE8: 1.4 | AF8: Medium | AG8: FALSE | AH8: FALSE | AI8: FALSE | AJ8: FALSE | AK8: FALSE | AL8: FALSE | AM8: FALSE | AN8: 57 | AO8: 0 | AP8: T2 | AU8: 0 | AW8: 0 | AX8: FALSE | AZ8: =IF(AND($AX$8,$AW$8>$AA$8/$Z$8),$AW$8,$AA$8/$Z$8) | BA8: 0.17142857 | BB8: 120 | BC8: 70 | BD8: aa | BE8: Wikipedia 'AZP S-60': 105-120 cyclic, 70 practical | BG8: giong | CT8: 57 | CW8: 8 | CX8: 1.38 | DD8: 0.5 | DE8: 70 | DF8: Fragmentation | DJ8: autocannon | DS8: Medium | EB8: 2 | EH8: Bullet | EK8: 280 | EP8: 48 | EQ8: S-60 57 mm | EX8: 57 | EY8: 3 | EZ8: 1.4 | FW8: All | GB8: cal_57 | GC8: flak | GD8: Assets/MachineBrigade/Resources/Data/balance.json: weapons[245] | GE8: {"id":"airship_flak","weaponFamilyId":"cal_57","weaponVariantId":"flak","real":"S-60 57 mm","family":"autocannon","size":57,"caliberMm":57,"pen":2,"damageType":"Fragmentation","damage":70,"cooldown":0.5,"range":48,"projectileSpeed":280,"splash":3,"spread":1.4,"impactTier":"Medium","projectile":"Bullet","targets":"All","clip":8,"clipReload":1.38}
A9: amos_120 | B9: 120 mm AMOS (twin) | C9: cal_120_he | D9: mortar | F9: mortar | G9: 120 | K9: HighExplosive | L9: 2 | M9: Shell | N9: 1 | O9: RIPPLE | P9: 4 | Q9: 0.25 | R9: 14.607 | S9: 0 | T9: 0 | U9: 0 | V9: 0 | W9: 214 | X9: 5 | Y9: 0 | Z9: 60 | AA9: 60 | AB9: 10 | AC9: Ground | AE9: 4.5 | AF9: Large | AG9: FALSE | AH9: FALSE | AI9: FALSE | AJ9: FALSE | AK9: FALSE | AL9: FALSE | AM9: FALSE | AN9: 120 | AO9: 0 | AP9: T3 | AS9: xe | AT9: sp_mortar | AU9: 1 | AV9: sp_mortar:0 | AW9: 0 | AX9: FALSE | AZ9: =IF(AND($AX$9,$AW$9>$AA$9/$Z$9),$AW$9,$AA$9/$Z$9) | BA9: 1 | BB9: 13 | BC9: 10 | BD9: gun | BE9: Wikipedia 'AMOS': 26 rpm the twin-barrel turret | BG9: doi | BH9: 150 | BI9: 214 | BJ9: 10 | BK9: 14.607 | BR9: 32 | BS9: 60 | CR9: 4 | CS9: 0.25 | CT9: 120 | DD9: 14.607 | DE9: 214 | DF9: HighExplosive | DJ9: mortar | DS9: Large | DZ9: 10 | EA9: TRUE | EB9: 2 | EI9: mortar_bomb | EK9: 60 | EP9: 60 | EQ9: 120 mm AMOS (twin) | EX9: 120 | EY9: 5 | EZ9: 4.5 | GB9: cal_120_he | GC9: mortar | GD9: Assets/MachineBrigade/Resources/Data/balance.json: weapons[281] | GE9: {"id":"amos_120","weaponFamilyId":"cal_120_he","weaponVariantId":"mortar","real":"120 mm AMOS (twin)","family":"mortar","size":120,"caliberMm":120,"pen":2,"damageType":"HighExplosive","damage":214,"burst":4,"burstInterval":0.25,"cooldown":14.607,"range":60,"minRange":10,"projectileSpeed":60,"splash":5,"spread":4.5,"impactTier":"Large","projectileModel":"mortar_bomb","mrsi":true}
A10: anti_ship_missile | B10: NSM / P-800 Oniks | C10: msl_nsm_p_800_oniks | E10: nsm_oniks | F10: missile | H10: 250 | K10: HighExplosive | L10: 4 | M10: Missile | N10: 1 | O10: RIPPLE | P10: 1 | Q10: 0.1 | R10: 30 | S10: 0 | T10: 0 | U10: 0 | V10: 0 | W10: 450 | X10: 7 | Y10: 0 | Z10: 225 | AA10: 140 | AB10: 0 | AC10: Ground | AE10: 0 | AF10: Huge | AG10: FALSE | AH10: FALSE | AI10: FALSE | AJ10: FALSE | AK10: FALSE | AL10: FALSE | AM10: FALSE | AN10: 680 | AO10: 0 | AP10: T4 | AU10: 0 | AW10: 2.5 | AX10: FALSE | AZ10: =IF(AND($AX$10,$AW$10>$AA$10/$Z$10),$AW$10,$AA$10/$Z$10) | BA10: 0.62222222 | BB10: 20 | BC10: 6 | BD10: missile | BE10: cruise missiles: ~3 s between launches (est.) | BG10: doi | BR10: 30 | BS10: 225 | DD10: 30 | DE10: 450 | DF10: HighExplosive | DJ10: missile | DS10: Huge | EB10: 4 | EH10: Missile | EI10: nsm_oniks | EK10: 30 | EP10: 140 | EQ10: NSM / P-800 Oniks | ET10: 3.17 | EX10: 680 | EY10: 7 | FZ10: 250 | GA10: nsm_oniks | GB10: msl_nsm_p_800_oniks | GD10: Assets/MachineBrigade/Resources/Data/balance.json: weapons[292] | GE10: {"id":"anti_ship_missile","weaponFamilyId":"msl_nsm_p_800_oniks","real":"NSM / P-800 Oniks","weaponFamily":"nsm_oniks","family":"missile","size":680,"warheadKg":250,"pen":4,"damageType":"HighExplosive","damage":450,"cooldown":30,"range":140,"projectileSpeed":30,"splash":7,"impactTier":"Huge","projectile":"Missile","projectileModel":"nsm_oniks","roundLength":3.17}
A11: apkws_rocket | B11: APKWS (laser-guided Hydra 70) | C11: rkt_70_80 | D11: guided | E11: apkws | F11: rocket | G11: 70 | K11: ShapedCharge | L11: 2 | M11: Rocket | N11: 1 | O11: RIPPLE | P11: 1 | Q11: 0.1 | R11: 1 | S11: 0 | T11: 0 | U11: 0 | V11: 0 | W11: 90 | X11: 2 | Y11: 0 | Z11: 180 | AA11: 40 | AB11: 0 | AC11: All | AE11: 0 | AF11: Medium | AG11: FALSE | AH11: FALSE | AI11: FALSE | AJ11: FALSE | AK11: FALSE | AL11: FALSE | AM11: FALSE | AN11: 70 | AO11: 0 | AP11: T2 | AS11: xe | AT11: attack_helicopter | AU11: 1 | AV11: attack_helicopter:4 | AW11: 0 | AX11: FALSE | AZ11: =IF(AND($AX$11,$AW$11>$AA$11/$Z$11),$AW$11,$AA$11/$Z$11) | BA11: 0.22222222 | BB11: 900 | BD11: rocket | BE11: rocket pods: ripples of 0.05-0.12 s (DECISIONS 19R) | BG11: doi | BR11: 45 | BS11: 180 | CT11: 70 | DD11: 1 | DE11: 90 | DF11: ShapedCharge | DJ11: rocket | DS11: Medium | EB11: 2 | EH11: Rocket | EI11: apkws | EK11: 45 | EP11: 40 | EQ11: APKWS (laser-guided Hydra 70) | ET11: 0.8 | EX11: 70 | EY11: 2 | FW11: All | GA11: apkws | GB11: rkt_70_80 | GC11: guided | GD11: Assets/MachineBrigade/Resources/Data/balance.json: weapons[291] | GE11: {"id":"apkws_rocket","weaponFamilyId":"rkt_70_80","weaponVariantId":"guided","real":"APKWS (laser-guided Hydra 70)","weaponFamily":"apkws","family":"rocket","size":70,"caliberMm":70,"pen":2,"damageType":"ShapedCharge","damage":90,"cooldown":1,"range":40,"projectileSpeed":45,"splash":2,"impactTier":"Medium","projectile":"Rocket","projectileModel":"apkws","roundLength":0.8,"targets":"All"}
A12: atgm | B12: BGM-71 TOW-2 | C12: atgm_bgm_71_tow_2 | F12: atgm | H12: 5.9 | K12: ShapedCharge | L12: 4 | M12: Missile | N12: 1 | O12: RIPPLE | P12: 1 | Q12: 0.1 | R12: 12.33 | S12: 0 | T12: 0 | U12: 0 | V12: 0 | W12: 190 | X12: 0 | Y12: 0 | Z12: 80 | AA12: 40 | AB12: 0 | AC12: Ground | AE12: 0 | AF12: Medium | AG12: FALSE | AH12: FALSE | AI12: FALSE | AJ12: FALSE | AK12: FALSE | AL12: FALSE | AM12: FALSE | AN12: 22.6 | AO12: 0 | AP12: T2 | AS12: xe | AT12: elite_apc;ifv;titan_tank | AU12: 3 | AV12: elite_apc:2;ifv:2;titan_tank:3 | AW12: 0 | AX12: FALSE | AZ12: =IF(AND($AX$12,$AW$12>$AA$12/$Z$12),$AW$12,$AA$12/$Z$12) | BA12: 0.5 | BB12: 3 | BC12: 2 | BD12: atgm | BE12: Wikipedia 'BGM-71 TOW': ~3 rpm | BG12: doi | BR12: 20 | BS12: 80 | DD12: 12.33 | DE12: 190 | DF12: ShapedCharge | DJ12: atgm | DS12: Medium | EB12: 4 | EE12: TRUE | EH12: Missile | EI12: atgm_tow | EJ12: 0.8 | EK12: 80 | EP12: 40 | EQ12: BGM-71 TOW-2 | EX12: 22.6 | FZ12: 5.9 | GB12: atgm_bgm_71_tow_2 | GD12: Assets/MachineBrigade/Resources/Data/balance.json: weapons[13] | GE12: {"id":"atgm","weaponFamilyId":"atgm_bgm_71_tow_2","real":"BGM-71 TOW-2","family":"atgm","size":22.6,"warheadKg":5.9,"pen":4,"piercing":true,"projectileModel":"atgm_tow","projectileScale":0.8,"damageType":"ShapedCharge","damage":190,"cooldown":12.33,"range":40,"projectileSpeed":80,"impactTier":"Medium","projectile":"Missile"}
A13: atgm_heavy | B13: 9M133 Kornet | C13: atgm_kornet | E13: 9m133_kornet | F13: atgm | H13: 7 | K13: ShapedCharge | L13: 4 | M13: Missile | N13: 1 | O13: RIPPLE | P13: 2 | Q13: 0.7 | R13: 6.8 | S13: 0 | T13: 0 | U13: 0 | V13: 0 | W13: 230 | X13: 0 | Y13: 0 | Z13: 80 | AA13: 42 | AB13: 0 | AC13: Ground | AE13: 0 | AF13: Medium | AG13: FALSE | AH13: FALSE | AI13: FALSE | AJ13: FALSE | AK13: FALSE | AL13: FALSE | AM13: FALSE | AN13: 29 | AO13: 0 | AP13: T2 | AU13: 0 | AW13: 0 | AX13: FALSE | AZ13: =IF(AND($AX$13,$AW$13>$AA$13/$Z$13),$AW$13,$AA$13/$Z$13) | BA13: 0.525 | BB13: 3 | BC13: 3 | BD13: atgm | BE13: Wikipedia '9M133 Kornet': 2-3 rpm | BG13: doi | BR13: 22 | BS13: 80 | CR13: 2 | CS13: 0.7 | DD13: 6.8 | DE13: 230 | DF13: ShapedCharge | DJ13: atgm | DS13: Medium | EB13: 4 | EE13: TRUE | EH13: Missile | EP13: 42 | EQ13: 9M133 Kornet | EX13: 29 | FZ13: 7 | GA13: 9m133_kornet | GB13: atgm_kornet | GD13: Assets/MachineBrigade/Resources/Data/balance.json: weapons[34] | GE13: {"id":"atgm_heavy","weaponFamilyId":"atgm_kornet","weaponFamily":"9m133_kornet","real":"9M133 Kornet","family":"atgm","size":29,"warheadKg":7,"pen":4,"piercing":true,"damageType":"ShapedCharge","damage":230,"cooldown":6.8,"range":42,"impactTier":"Medium","projectile":"Missile","burst":2,"burstInterval":0.7}
A14: atgm_post | B14: 9M113 Konkurs | C14: atgm_9m113_konkurs | F14: atgm | H14: 2.7 | K14: ShapedCharge | L14: 3 | M14: Missile | N14: 1 | O14: RIPPLE | P14: 1 | Q14: 0.1 | R14: 12.1 | S14: 0 | T14: 0 | U14: 0 | V14: 0 | W14: 190 | X14: 0 | Y14: 0 | Z14: 60 | AA14: 34 | AB14: 0 | AC14: Ground | AE14: 0 | AF14: Medium | AG14: FALSE | AH14: FALSE | AI14: FALSE | AJ14: FALSE | AK14: FALSE | AL14: FALSE | AM14: FALSE | AN14: 25 | AO14: 0 | AP14: T2 | AU14: 0 | AW14: 0 | AX14: FALSE | AZ14: =IF(AND($AX$14,$AW$14>$AA$14/$Z$14),$AW$14,$AA$14/$Z$14) | BA14: 0.56666667 | BB14: 3 | BC14: 2 | BD14: atgm | BE14: Wikipedia '9M113 Konkurs': 2-3 rpm | BG14: doi | BR14: 19 | BS14: 60 | DD14: 12.1 | DE14: 190 | DF14: ShapedCharge | DJ14: atgm | DS14: Medium | EB14: 3 | EE14: TRUE | EH14: Missile | EI14: atgm_kornet | EK14: 60 | EP14: 34 | EQ14: 9M113 Konkurs | EX14: 25 | FZ14: 2.7 | GB14: atgm_9m113_konkurs | GD14: Assets/MachineBrigade/Resources/Data/balance.json: weapons[237] | GE14: {"id":"atgm_post","weaponFamilyId":"atgm_9m113_konkurs","real":"9M113 Konkurs","family":"atgm","size":25,"warheadKg":2.7,"pen":3,"piercing":true,"projectileModel":"atgm_kornet","damageType":"ShapedCharge","damage":190,"cooldown":12.1,"range":34,"projectileSpeed":60,"impactTier":"Medium","projectile":"Missile"}
A15: autocannon_25 | B15: M242 Bushmaster 25 mm | C15: cal_25 | E15: m242_bushmaster_25_mm | F15: autocannon | G15: 25 | K15: Kinetic | L15: 2 | M15: Bullet | N15: 1 | O15: RIPPLE | P15: 8 | Q15: 0.1667 | R15: 1.4667 | S15: 0 | T15: 0 | U15: 0 | V15: 0 | W15: 17 | X15: 0 | Y15: 0 | Z15: 210 | AA15: 30 | AB15: 0 | AC15: Ground | AE15: 0.9 | AF15: Small | AG15: FALSE | AH15: FALSE | AI15: FALSE | AJ15: FALSE | AK15: FALSE | AL15: FALSE | AM15: FALSE | AN15: 25 | AO15: 0 | AP15: T1 | AR15: autocannon_25_flak | AS15: thap;xe | AT15: armored_car;guard_tower.nest | AU15: 2 | AV15: armored_car:0;guard_tower.nest:other | AW15: 0 | AX15: FALSE | AZ15: =IF(AND($AX$15,$AW$15>$AA$15/$Z$15),$AW$15,$AA$15/$Z$15) | BA15: 0.14285714 | BB15: 500 | BC15: 200 | BD15: ac | BE15: Wikipedia 'M242 Bushmaster': 200 or 500 rpm | BG15: giong | CR15: 8 | CS15: 0.1667 | CT15: 25 | DD15: 1.4667 | DE15: 17 | DF15: Kinetic | DJ15: autocannon | DS15: Small | EB15: 2 | EH15: Bullet | EP15: 30 | EQ15: M242 Bushmaster 25 mm | EV15: 22 | EX15: 25 | EZ15: 0.9 | FW15: Ground | GA15: m242_bushmaster_25_mm | GB15: cal_25 | GD15: Assets/MachineBrigade/Resources/Data/balance.json: weapons[25] | GE15: {"id":"autocannon_25","weaponFamilyId":"cal_25","weaponFamily":"m242_bushmaster_25_mm","burstInterval":0.1667,"burst":8,"real":"M242 Bushmaster 25 mm","family":"autocannon","size":25,"caliberMm":25,"pen":2,"damageType":"Kinetic","damage":17,"cooldown":1.4667,"range":30,"spread":0.9,"impactTier":"Small","projectile":"Bullet","targets":"Ground","roundWeight":22}
A16: autocannon_25_flak | B16: M242 Bushmaster 25 mm air-burst | C16: cal_25 | D16: flak | E16: m242_bushmaster_25_mm_air_burst | F16: autocannon | G16: 25 | K16: Fragmentation | L16: 1 | M16: Bullet | N16: 1 | O16: RIPPLE | P16: 8 | Q16: 0.1667 | R16: 1.4667 | S16: 0 | T16: 0 | U16: 0 | V16: 0 | W16: 17 | X16: 2 | Y16: 0 | Z16: 210 | AA16: 30 | AB16: 0 | AC16: Air | AE16: 0.9 | AF16: Small | AG16: FALSE | AH16: FALSE | AI16: FALSE | AJ16: FALSE | AK16: FALSE | AL16: FALSE | AM16: FALSE | AN16: 25 | AO16: 0 | AP16: T1 | AQ16: autocannon_25 | AU16: 0 | AW16: 0 | AX16: FALSE | AZ16: =IF(AND($AX$16,$AW$16>$AA$16/$Z$16),$AW$16,$AA$16/$Z$16) | BA16: 0.14285714 | BB16: 500 | BC16: 200 | BD16: ac | BE16: Wikipedia 'M242 Bushmaster': 200 or 500 rpm | BG16: giong | DE16: 17 | DF16: Fragmentation | DM16: air | DN16: Airburst | DT16: autocannon_25 | EB16: 1 | EE16: FALSE | EQ16: M242 Bushmaster 25 mm air-burst | ES16: flak | EU16: autocannon_25 | EY16: 2 | FW16: Air | GA16: m242_bushmaster_25_mm_air_burst | GC16: flak | GD16: Assets/MachineBrigade/Resources/Data/balance.json: secondRounds.rounds[1] | GE16: {"id":"autocannon_25_flak","roundOf":"autocannon_25","inherits":"autocannon_25","weaponVariantId":"flak","weaponFamily":"m242_bushmaster_25_mm_air_burst","round":"flak","for":["air"],"real":"M242 Bushmaster 25 mm air-burst","damageType":"Fragmentation","pen":1,"damage":17,"splash":2,"form":"Airburst","piercing":false,"targets":"Air"}
A17: autocannon_30 | B17: 2A42 30 mm | C17: cal_30 | E17: 2a42_30_mm | F17: autocannon | G17: 30 | K17: Kinetic | L17: 2 | M17: Bullet | N17: 1 | O17: RIPPLE | P17: 10 | Q17: 0.1111 | R17: 1.6111 | S17: 0 | T17: 0 | U17: 0 | V17: 0 | W17: 22 | X17: 0 | Y17: 0 | Z17: 200 | AA17: 30 | AB17: 0 | AC17: Ground | AE17: 0.8 | AF17: Small | AG17: FALSE | AH17: FALSE | AI17: FALSE | AJ17: FALSE | AK17: FALSE | AL17: FALSE | AM17: FALSE | AN17: 30 | AO17: 0 | AP17: T1 | AR17: autocannon_30_flak | AS17: boss_part;xe | AT17: elite_apc;elite_heavy_tank;gun_30;heavy_tank | AU17: 4 | AV17: elite_apc:0;elite_heavy_tank:1;gun_30:part;heavy_tank:1 | AW17: 0 | AX17: FALSE | AZ17: =IF(AND($AX$17,$AW$17>$AA$17/$Z$17),$AW$17,$AA$17/$Z$17) | BA17: 0.15 | BB17: 800 | BC17: 300 | BD17: ac | BE17: Wikipedia '2A42': 550-800 high, 200-300 low rpm | BG17: giong | CR17: 10 | CS17: 0.1111 | CT17: 30 | DD17: 1.6111 | DE17: 22 | DF17: Kinetic | DJ17: autocannon | DS17: Small | EB17: 2 | EH17: Bullet | EP17: 30 | EQ17: 2A42 30 mm | EX17: 30 | EZ17: 0.8 | FW17: Ground | GA17: 2a42_30_mm | GB17: cal_30 | GD17: Assets/MachineBrigade/Resources/Data/balance.json: weapons[8] | GE17: {"id":"autocannon_30","weaponFamilyId":"cal_30","weaponFamily":"2a42_30_mm","burstInterval":0.1111,"burst":10,"real":"2A42 30 mm","family":"autocannon","size":30,"caliberMm":30,"pen":2,"damageType":"Kinetic","damage":22,"cooldown":1.6111,"range":30,"spread":0.8,"impactTier":"Small","projectile":"Bullet","targets":"Ground"}
A18: autocannon_30_flak | B18: 2A42 30 mm air-burst | C18: cal_30 | D18: flak | E18: 2a42_30_mm_air_burst | F18: autocannon | G18: 30 | K18: Fragmentation | L18: 2 | M18: Bullet | N18: 1 | O18: RIPPLE | P18: 10 | Q18: 0.1111 | R18: 1.6111 | S18: 0 | T18: 0 | U18: 0 | V18: 0 | W18: 22 | X18: 2.5 | Y18: 0 | Z18: 200 | AA18: 30 | AB18: 0 | AC18: Air | AE18: 0.8 | AF18: Small | AG18: FALSE | AH18: FALSE | AI18: FALSE | AJ18: FALSE | AK18: FALSE | AL18: FALSE | AM18: FALSE | AN18: 30 | AO18: 0 | AP18: T1 | AQ18: autocannon_30 | AU18: 0 | AW18: 0 | AX18: FALSE | AZ18: =IF(AND($AX$18,$AW$18>$AA$18/$Z$18),$AW$18,$AA$18/$Z$18) | BA18: 0.15 | BB18: 800 | BC18: 300 | BD18: ac | BE18: Wikipedia '2A42': 550-800 high, 200-300 low rpm | BG18: giong | DE18: 22 | DF18: Fragmentation | DM18: air | DN18: Airburst | DT18: autocannon_30 | EB18: 2 | EE18: FALSE | EQ18: 2A42 30 mm air-burst | ES18: flak | EU18: autocannon_30 | EY18: 2.5 | FW18: Air | GA18: 2a42_30_mm_air_burst | GC18: flak | GD18: Assets/MachineBrigade/Resources/Data/balance.json: secondRounds.rounds[2] | GE18: {"id":"autocannon_30_flak","roundOf":"autocannon_30","inherits":"autocannon_30","weaponVariantId":"flak","weaponFamily":"2a42_30_mm_air_burst","round":"flak","for":["air"],"real":"2A42 30 mm air-burst","damageType":"Fragmentation","pen":2,"damage":22,"splash":2.5,"form":"Airburst","piercing":false,"targets":"Air"}
A19: autocannon_40 | B19: Bofors 40 mm | C19: cal_40 | F19: autocannon | G19: 40 | K19: Kinetic | L19: 2 | M19: Bullet | N19: 1 | O19: RIPPLE | P19: 1 | Q19: 0.1 | R19: 0.2 | S19: 10 | T19: 1.72 | U19: 0 | V19: 0 | W19: 30 | X19: 1 | Y19: 0 | Z19: 210 | AA19: 28 | AB19: 0 | AC19: All | AE19: 0.8 | AF19: Small | AG19: FALSE | AH19: FALSE | AI19: FALSE | AJ19: FALSE | AK19: FALSE | AL19: FALSE | AM19: FALSE | AN19: 40 | AO19: 0 | AP19: T1 | AR19: autocannon_40_flak | AS19: boss_part | AT19: gun_40 | AU19: 1 | AV19: gun_40:part | AW19: 0 | AX19: FALSE | AZ19: =IF(AND($AX$19,$AW$19>$AA$19/$Z$19),$AW$19,$AA$19/$Z$19) | BA19: 0.13333333 | BB19: 330 | BC19: 120 | BD19: aa | BE19: Wikipedia 'Bofors 40 mm L/70': 240-330 rpm | BF19: Gungnir's 40 mm guns: frozen (fix rule 8); their 1 m burst is Gungnir's own | BG19: giong | CT19: 40 | CW19: 10 | CX19: 1.72 | DD19: 0.2 | DE19: 30 | DF19: Kinetic | DJ19: autocannon | DS19: Small | EB19: 2 | EH19: Bullet | EK19: 210 | EP19: 28 | EQ19: Bofors 40 mm | EV19: 51 | EX19: 40 | EY19: 1 | EZ19: 0.8 | FW19: All | GB19: cal_40 | GD19: Assets/MachineBrigade/Resources/Data/balance.json: weapons[99] | GE19: {"id":"autocannon_40","weaponFamilyId":"cal_40","real":"Bofors 40 mm","family":"autocannon","size":40,"caliberMm":40,"pen":2,"damageType":"Kinetic","damage":30,"cooldown":0.2,"range":28,"projectileSpeed":210,"splash":1,"spread":0.8,"impactTier":"Small","projectile":"Bullet","targets":"All","clip":10,"clipReload":1.72,"roundWeight":51}
A20: autocannon_40_flak | B20: Bofors 40 mm air-burst | C20: cal_40 | D20: flak | F20: autocannon | G20: 40 | K20: Fragmentation | L20: 2 | M20: Bullet | N20: 1 | O20: RIPPLE | P20: 1 | Q20: 0.1 | R20: 0.2 | S20: 10 | T20: 1.72 | U20: 0 | V20: 0 | W20: 30 | X20: 3.5 | Y20: 0 | Z20: 210 | AA20: 28 | AB20: 0 | AC20: Air | AE20: 0.8 | AF20: Small | AG20: FALSE | AH20: FALSE | AI20: FALSE | AJ20: FALSE | AK20: FALSE | AL20: FALSE | AM20: FALSE | AN20: 40 | AO20: 0 | AP20: T1 | AQ20: autocannon_40 | AU20: 0 | AW20: 0 | AX20: FALSE | AZ20: =IF(AND($AX$20,$AW$20>$AA$20/$Z$20),$AW$20,$AA$20/$Z$20) | BA20: 0.13333333 | BB20: 330 | BC20: 120 | BD20: aa | BE20: Wikipedia 'Bofors 40 mm L/70': 240-330 rpm | BG20: giong | DE20: 30 | DF20: Fragmentation | DM20: air | DN20: Airburst | DT20: autocannon_40 | EB20: 2 | EE20: FALSE | EQ20: Bofors 40 mm air-burst | ES20: flak | EU20: autocannon_40 | EY20: 3.5 | FW20: Air | GC20: flak | GD20: Assets/MachineBrigade/Resources/Data/balance.json: secondRounds.rounds[3] | GE20: {"id":"autocannon_40_flak","roundOf":"autocannon_40","inherits":"autocannon_40","weaponVariantId":"flak","weaponFamily":"","round":"flak","for":["air"],"real":"Bofors 40 mm air-burst","damageType":"Fragmentation","pen":2,"damage":30,"splash":3.5,"form":"Airburst","piercing":false,"targets":"Air"}
A21: ballistic_missile | B21: 9M723 Iskander (700 kg) | C21: bal_9m723_iskander | F21: ballistic | H21: 480 | K21: HighExplosive | L21: 4 | M21: Rocket | N21: 1 | O21: RIPPLE | P21: 2 | Q21: 1.5 | R21: 22.71 | S21: 0 | T21: 0 | U21: 2 | V21: 0 | W21: 630 | X21: 10 | Y21: 0 | Z21: 200 | AA21: 180 | AB21: 40 | AC21: Ground | AE21: 5 | AF21: Ultimate | AG21: FALSE | AH21: FALSE | AI21: FALSE | AJ21: FALSE | AK21: FALSE | AL21: FALSE | AM21: FALSE | AN21: 700 | AO21: 0 | AP21: T4 | AS21: xe | AT21: ballistic_launcher | AU21: 1 | AV21: ballistic_launcher:0 | AW21: 2.7222222 | AX21: TRUE | AZ21: =IF(AND($AX$21,$AW$21>$AA$21/$Z$21),$AW$21,$AA$21/$Z$21) | BA21: 2.7222222 | BB21: 2 | BC21: 2 | BD21: missile | BE21: Wikipedia '9K720 Iskander': two missiles within a minute | BG21: doi | BR21: 50 | BS21: 200 | CN21: 2 | CR21: 2 | CS21: 1.5 | DD21: 22.71 | DE21: 630 | DF21: HighExplosive | DJ21: ballistic | DS21: Ultimate | DZ21: 40 | EB21: 4 | EH21: Rocket | EJ21: 0.85 | EK21: 200 | EP21: 180 | EQ21: 9M723 Iskander (700 kg) | EV21: 700 | EX21: 700 | EY21: 10 | EZ21: 5 | FZ21: 480 | GB21: bal_9m723_iskander | GD21: Assets/MachineBrigade/Resources/Data/balance.json: weapons[59] | GE21: {"id":"ballistic_missile","weaponFamilyId":"bal_9m723_iskander","real":"9M723 Iskander (700 kg)","family":"ballistic","size":700,"warheadKg":480,"pen":4,"projectileScale":0.85,"damageType":"HighExplosive","damage":630,"cooldown":22.71,"range":180,"minRange":40,"projectileSpeed":200,"splash":10,"spread":5,"impactTier":"Ultimate","projectile":"Rocket","burst":2,"burstInterval":1.5,"ammo":2,"roundWeight":700}
A22: bastion_gun | B22: 2A83 152 mm (twin) | C22: cal_152_155 | D22: ap | E22: 2a83_152_mm | F22: tank_gun | G22: 152 | K22: Kinetic | L22: 4 | M22: Shell | N22: 2 | O22: SIMULTANEOUS | P22: 1 | Q22: 0.05 | R22: 7.443 | S22: 0 | T22: 0 | U22: 0 | V22: 0 | W22: 457 | X22: 2.5 | Y22: 0 | Z22: 160 | AA22: 40 | AB22: 0 | AC22: Ground | AE22: 0.3 | AF22: Large | AG22: FALSE | AH22: FALSE | AI22: FALSE | AJ22: FALSE | AK22: FALSE | AL22: FALSE | AM22: FALSE | AN22: 152 | AO22: 0 | AP22: T3 | AR22: bastion_gun_he | AS22: cong_trinh;thap | AT22: headquarters;headquarters.fortress_air;headquarters.fortress_ground;headquarters.shield;spawn_bastion | AU22: 5 | AV22: headquarters:0;headquarters.fortress_air:0;headquarters.fortress_ground:0;headquarters.shield:0;spawn_bastion:0 | AW22: 0 | AX22: FALSE | AZ22: =IF(AND($AX$22,$AW$22>$AA$22/$Z$22),$AW$22,$AA$22/$Z$22) | BA22: 0.25 | BB22: 10 | BC22: 8 | BD22: gun | BE22: Object 195 / T-14 152 mm, est. ~10 rpm (the sheet) | BG22: doi | BH22: 320 | BI22: 457 | BJ22: 5.16 | BK22: 7.443 | BT22: 2 | BU22: 1 | BX22: 1 | BY22: 2 | BZ22: RIPPLE | CA22: SIMULTANEOUS | CO22: 2 | CR22: 1 | CS22: 0.05 | CT22: 152 | DD22: 7.443 | DE22: 457 | DF22: Kinetic | DJ22: tank_gun | DR22: 1.5 | DS22: Large | EB22: 4 | EE22: TRUE | EP22: 40 | EQ22: 2A83 152 mm (twin) | EW22: SIMULTANEOUS | EX22: 152 | EZ22: 0.3 | GA22: 2a83_152_mm | GB22: cal_152_155 | GC22: ap | GD22: Assets/MachineBrigade/Resources/Data/balance.json: weapons[91] | GE22: {"id":"bastion_gun","weaponFamilyId":"cal_152_155","weaponVariantId":"ap","salvoMode":"SIMULTANEOUS","barrels":2,"weaponFamily":"2a83_152_mm","real":"2A83 152 mm (twin)","family":"tank_gun","size":152,"caliberMm":152,"pen":4,"piercing":true,"damageType":"Kinetic","damage":457,"cooldown":7.443,"range":40,"spread":0.3,"impactTier":"Large","burst":1,"burstInterval":0.05,"impactScale":1.5}
A23: bastion_gun_he | B23: 2A83 152 mm HE-FRAG (twin) | C23: cal_152_155 | E23: 2a83_152_mm_he_frag | F23: tank_gun | G23: 152 | K23: HighExplosive | L23: 3 | M23: Shell | N23: 2 | O23: SIMULTANEOUS | P23: 1 | Q23: 0.05 | R23: 7.443 | S23: 0 | T23: 0 | U23: 0 | V23: 0 | W23: 457 | X23: 6.5 | Y23: 0 | Z23: 150 | AA23: 40 | AB23: 0 | AC23: Ground | AE23: 0.3 | AF23: Huge | AG23: FALSE | AH23: FALSE | AI23: FALSE | AJ23: FALSE | AK23: FALSE | AL23: FALSE | AM23: FALSE | AN23: 152 | AO23: 0 | AP23: T3 | AQ23: bastion_gun | AU23: 0 | AW23: 0 | AX23: FALSE | AZ23: =IF(AND($AX$23,$AW$23>$AA$23/$Z$23),$AW$23,$AA$23/$Z$23) | BA23: 0.26666667 | BB23: 10 | BC23: 8 | BD23: gun | BE23: Object 195 / T-14 152 mm, est. ~10 rpm (the sheet) | BG23: doi | BH23: 320 | BI23: 457 | BJ23: 5.16 | BK23: 7.443 | BT23: 2 | BU23: 1 | BX23: 1 | BY23: 2 | BZ23: RIPPLE | CA23: SIMULTANEOUS | DE23: 457 | DF23: HighExplosive | DM23: light;structure | DN23: HeShell | DS23: Huge | DT23: bastion_gun | EB23: 3 | EE23: FALSE | EK23: 150 | EQ23: 2A83 152 mm HE-FRAG (twin) | ES23: he | EU23: bastion_gun | EV23: 343 | EY23: 6.5 | FW23: Ground | GA23: 2a83_152_mm_he_frag | GD23: Assets/MachineBrigade/Resources/Data/balance.json: secondRounds.rounds[4] | GE23: {"id":"bastion_gun_he","roundOf":"bastion_gun","inherits":"bastion_gun","weaponVariantId":"","weaponFamily":"2a83_152_mm_he_frag","round":"he","for":["light","structure"],"real":"2A83 152 mm HE-FRAG (twin)","damageType":"HighExplosive","pen":3,"damage":457,"splash":6.5,"form":"HeShell","piercing":false,"targets":"Ground","projectileSpeed":150,"impactTier":"Huge","roundWeight":343}
A24: boat_rockets | B24: S-8 80 mm | C24: rkt_70_80 | E24: s_8_80_mm_boat | F24: rocket | G24: 80 | K24: HighExplosive | L24: 2 | M24: Rocket | N24: 1 | O24: RIPPLE | P24: 10 | Q24: 0.12 | R24: 7 | S24: 0 | T24: 0 | U24: 0 | V24: 0 | W24: 32 | X24: 3.5 | Y24: 7 | Z24: 180 | AA24: 55 | AB24: 0 | AC24: Ground | AE24: 4 | AF24: Medium | AG24: FALSE | AH24: FALSE | AI24: FALSE | AJ24: FALSE | AK24: FALSE | AL24: FALSE | AM24: FALSE | AN24: 80 | AO24: 0 | AP24: T2 | AS24: xe | AT24: missile_boat | AU24: 1 | AV24: missile_boat:0 | AW24: 0 | AX24: FALSE | AZ24: =IF(AND($AX$24,$AW$24>$AA$24/$Z$24),$AW$24,$AA$24/$Z$24) | BA24: 0.30555556 | BB24: 900 | BD24: rocket | BE24: rocket pods: ripples of 0.05-0.12 s (DECISIONS 19R) | BG24: doi | BN24: 3 | BO24: 3.5 | BP24: 0 | BQ24: 7 | BR24: 40 | BS24: 180 | CR24: 10 | CS24: 0.12 | CT24: 80 | DD24: 7 | DE24: 32 | DF24: HighExplosive | DG24: 7 | DJ24: rocket | DS24: Medium | EB24: 2 | EH24: Rocket | EJ24: 0.9 | EP24: 55 | EQ24: S-8 80 mm | EX24: 80 | EZ24: 4 | GA24: s_8_80_mm_boat | GB24: rkt_70_80 | GD24: Assets/MachineBrigade/Resources/Data/balance.json: weapons[255] | GE24: {"id":"boat_rockets","weaponFamilyId":"rkt_70_80","weaponFamily":"s_8_80_mm_boat","real":"S-8 80 mm","family":"rocket","size":80,"caliberMm":80,"pen":2,"projectileScale":0.9,"damageType":"HighExplosive","damage":32,"cooldown":7,"edge":7,"range":55,"spread":4,"impactTier":"Medium","projectile":"Rocket","burst":10,"burstInterval":0.12}
A25: bofors_l70 | B25: Bofors 40 mm L/70 | C25: cal_40 | D25: flak | E25: bofors_40_mm_l_70 | F25: autocannon | G25: 40 | K25: Fragmentation | L25: 2 | M25: Bullet | N25: 1 | O25: RIPPLE | P25: 1 | Q25: 0.1 | R25: 0.25 | S25: 20 | T25: 3 | U25: 0 | V25: 0 | W25: 30 | X25: 2.5 | Y25: 0 | Z25: 220 | AA25: 48 | AB25: 0 | AC25: All | AE25: 1.2 | AF25: Small | AG25: FALSE | AH25: FALSE | AI25: FALSE | AJ25: FALSE | AK25: FALSE | AL25: FALSE | AM25: FALSE | AN25: 40 | AO25: 0 | AP25: T1 | AS25: cong_trinh;thap;xe | AT25: aa_gun_tower;aa_gun_vehicle;headquarters.fortress_air | AU25: 3 | AV25: aa_gun_tower:0;aa_gun_vehicle:0;headquarters.fortress_air:4 | AW25: 0 | AX25: FALSE | AZ25: =IF(AND($AX$25,$AW$25>$AA$25/$Z$25),$AW$25,$AA$25/$Z$25) | BA25: 0.21818182 | BB25: 330 | BC25: 120 | BD25: aa | BE25: Wikipedia 'Bofors 40 mm L/70': 240-330 rpm | BG25: giong | CT25: 40 | CW25: 20 | CX25: 3 | DD25: 0.25 | DE25: 30 | DF25: Fragmentation | DJ25: autocannon | DS25: Small | EB25: 2 | EH25: Bullet | EP25: 48 | EQ25: Bofors 40 mm L/70 | EX25: 40 | EZ25: 1.2 | FW25: All | GA25: bofors_40_mm_l_70 | GB25: cal_40 | GC25: flak | GD25: Assets/MachineBrigade/Resources/Data/balance.json: weapons[279] | GE25: {"id":"bofors_l70","weaponFamilyId":"cal_40","weaponVariantId":"flak","weaponFamily":"bofors_40_mm_l_70","real":"Bofors 40 mm L/70","family":"autocannon","size":40,"caliberMm":40,"pen":2,"damageType":"Fragmentation","damage":30,"cooldown":0.25,"range":48,"spread":1.2,"impactTier":"Small","projectile":"Bullet","targets":"All","clip":20,"clipReload":3}
A26: bomber_payload | B26: FAB-500 (500 kg) | C26: bomb_fab_500 | F26: bomb | H26: 500 | K26: HighExplosive | L26: 3 | M26: Bomb | N26: 1 | O26: RIPPLE | P26: 7 | Q26: 0.2 | R26: 11.2 | S26: 0 | T26: 0 | U26: 0 | V26: 0 | W26: 420 | X26: 10 | Y26: 0 | Z26: 35 | AA26: 28 | AB26: 0 | AC26: Ground | AE26: 7 | AF26: Huge | AG26: FALSE | AH26: FALSE | AI26: FALSE | AJ26: FALSE | AK26: FALSE | AL26: FALSE | AM26: FALSE | AN26: 500 | AO26: 7 | AP26: T4 | AS26: xe | AT26: heavy_bomber | AU26: 1 | AV26: heavy_bomber:0 | AW26: 2.7222222 | AX26: TRUE | AZ26: =IF(AND($AX$26,$AW$26>$AA$26/$Z$26),$AW$26,$AA$26/$Z$26) | BA26: 0.8 | BB26: 600 | BD26: bomb | BE26: a stick's release, 0.1 s and up (est.) | BG26: giong | CR26: 7 | CS26: 0.2 | DD26: 11.2 | DE26: 420 | DF26: HighExplosive | DJ26: bomb | DS26: Huge | DW26: 7 | EB26: 3 | EH26: Bomb | EI26: bomb | EJ26: 0.7324 | EK26: 35 | EP26: 28 | EQ26: FAB-500 (500 kg) | ET26: 1.2 | EX26: 500 | EY26: 10 | EZ26: 7 | FA26: CENTER | FB26: 1.5 | FC26: 7 | FD26: OVERFLY | FE26: 40 | FF26: 1.449 | FG26: AXIS | FH26: 0.625 | FI26: 2.5 | FJ26: 1.65 | FK26: 25.5 | FL26: 66 | FM26: 3 | FN26: STICK | FO26: 0.909 | FP26: 17.6 | FQ26: 10 | FR26: 11 | FS26: 6.2 | FT26: STICK_RECT | FU26: 25 | FZ26: 500 | GB26: bomb_fab_500 | GD26: Assets/MachineBrigade/Resources/Data/balance.json: weapons[48] | GE26: {"id":"bomber_payload","weaponFamilyId":"bomb_fab_500","load":7,"real":"FAB-500 (500 kg)","family":"bomb","size":500,"warheadKg":500,"pen":3,"projectileModel":"bomb","projectileScale":0.7324,"roundLength":1.2,"damageType":"HighExplosive","damage":420,"cooldown":11.2,"range":28,"projectileSpeed":35,"splash":10,"spread":7,"impactTier":"Huge","projectile":"Bomb","burst":7,"burstInterval":0.2,"stick":{"mode":"STICK","bombs":7,"spacing":11,"length":66,"interval":0.625,"releaseSpeed":17.6,"fallTime":1.449,"lead":25.5,"heading":"AXIS","anchor":"CENTER","drop":"OVERFLY","jitterAcross":2.5,"jitterAlong":1.65,"overlap":0.909,"width":25,"minTargets":3,"safety":10,"straightTime":6.2,"exit":40,"bayOpen":1.5,"warnShape":"STICK_RECT"}}
A27: bomber_tail_guns | B27: M3 12.7 mm (quad tail) | C27: cal_12_7 | F27: mg | G27: 12.7 | K27: Kinetic | L27: 1 | M27: Bullet | N27: 1 | O27: RIPPLE | P27: 1 | Q27: 0.1 | R27: 0.0167 | S27: 26 | T27: 2.78 | U27: 0 | V27: 0 | W27: 9.5 | X27: 0 | Y27: 0 | Z27: 240 | AA27: 30 | AB27: 0 | AC27: Air | AE27: 1.5 | AF27: Small | AG27: FALSE | AH27: FALSE | AI27: FALSE | AJ27: FALSE | AK27: FALSE | AL27: FALSE | AM27: FALSE | AN27: 12.7 | AO27: 0 | AP27: T0 | AR27: bomber_tail_guns_api | AS27: xe | AT27: heavy_bomber | AU27: 1 | AV27: heavy_bomber:1 | AW27: 0 | AX27: FALSE | AZ27: =IF(AND($AX$27,$AW$27>$AA$27/$Z$27),$AW$27,$AA$27/$Z$27) | BA27: 0.125 | BB27: 1200 | BC27: 200 | BD27: mg | BE27: Wikipedia 'M3 Browning' (AN/M3): 1,100-1,250 rpm | BG27: giong | CT27: 12.7 | CW27: 26 | CX27: 2.78 | DD27: 0.0167 | DE27: 9.5 | DF27: Kinetic | DJ27: mg | DS27: Small | EB27: 1 | EH27: Bullet | EK27: 240 | EP27: 30 | EQ27: M3 12.7 mm (quad tail) | EV27: 19 | EX27: 12.7 | EZ27: 1.5 | FW27: Air | GB27: cal_12_7 | GD27: Assets/MachineBrigade/Resources/Data/balance.json: weapons[49] | GE27: {"id":"bomber_tail_guns","weaponFamilyId":"cal_12_7","real":"M3 12.7 mm (quad tail)","family":"mg","size":12.7,"caliberMm":12.7,"pen":1,"damageType":"Kinetic","damage":9.5,"cooldown":0.0167,"range":30,"projectileSpeed":240,"spread":1.5,"impactTier":"Small","projectile":"Bullet","targets":"Air","roundWeight":19,"clip":26,"clipReload":2.78}
A28: bomber_tail_guns_api | B28: M3 12.7 mm API (quad tail) | C28: cal_12_7 | F28: mg | G28: 12.7 | K28: Kinetic | L28: 2 | M28: Bullet | N28: 1 | O28: RIPPLE | P28: 1 | Q28: 0.1 | R28: 0.0167 | S28: 26 | T28: 2.78 | U28: 0 | V28: 0 | W28: 9.5 | X28: 0 | Y28: 0 | Z28: 240 | AA28: 30 | AB28: 0 | AC28: Air | AE28: 1.5 | AF28: Small | AG28: FALSE | AH28: FALSE | AI28: FALSE | AJ28: FALSE | AK28: FALSE | AL28: FALSE | AM28: FALSE | AN28: 12.7 | AO28: 0 | AP28: T0 | AQ28: bomber_tail_guns | AU28: 0 | AW28: 0 | AX28: FALSE | AZ28: =IF(AND($AX$28,$AW$28>$AA$28/$Z$28),$AW$28,$AA$28/$Z$28) | BA28: 0.125 | BB28: 1200 | BC28: 200 | BD28: mg | BE28: Wikipedia 'M3 Browning' (AN/M3): 1,100-1,250 rpm | BG28: giong | DE28: 9.5 | DF28: Kinetic | DH28: TRUE | DM28: any | DN28: BulletBig | DT28: bomber_tail_guns | EB28: 2 | EE28: TRUE | EQ28: M3 12.7 mm API (quad tail) | ES28: api | EU28: bomber_tail_guns | GD28: Assets/MachineBrigade/Resources/Data/balance.json: secondRounds.rounds[5] | GE28: {"id":"bomber_tail_guns_api","roundOf":"bomber_tail_guns","inherits":"bomber_tail_guns","weaponFamily":"","round":"api","for":["any"],"elite":true,"real":"M3 12.7 mm API (quad tail)","damageType":"Kinetic","pen":2,"damage":9.5,"form":"BulletBig","piercing":true}
A29: borer_cannon | B29: 2A70 100/76 mm | C29: cal_76 | F29: tank_gun | G29: 76 | K29: Kinetic | L29: 3 | M29: Shell | N29: 1 | O29: RIPPLE | P29: 1 | Q29: 0.1 | R29: 6 | S29: 0 | T29: 0 | U29: 0 | V29: 0 | W29: 120 | X29: 1.5 | Y29: 0 | Z29: 170 | AA29: 34 | AB29: 0 | AC29: Ground | AE29: 0.7 | AF29: Medium | AG29: FALSE | AH29: FALSE | AI29: FALSE | AJ29: FALSE | AK29: FALSE | AL29: FALSE | AM29: FALSE | AN29: 76 | AO29: 0 | AP29: T2 | AR29: borer_cannon_he | AS29: boss | AT29: earth_borer | AU29: 1 | AV29: earth_borer:1;earth_borer:2 | AW29: 0 | AX29: FALSE | AZ29: =IF(AND($AX$29,$AW$29>$AA$29/$Z$29),$AW$29,$AA$29/$Z$29) | BA29: 0.2 | BB29: 10 | BC29: 8 | BD29: gun | BE29: Wikipedia '2A70': 10 rpm (100 mm), BMP-3 | BF29: real 2A70 10 rpm (6 s); 2.08 s was too fast | BG29: doi | BJ29: 2.08 | BK29: 6 | CT29: 76 | DD29: 6 | DE29: 120 | DF29: Kinetic | DJ29: tank_gun | DO29: 16 | DS29: Medium | EB29: 3 | EE29: TRUE | EK29: 170 | EP29: 34 | EQ29: 2A70 100/76 mm | EV29: 150 | EX29: 76 | EY29: 1.5 | EZ29: 0.7 | GB29: cal_76 | GD29: Assets/MachineBrigade/Resources/Data/balance.json: weapons[244] | GE29: {"id":"borer_cannon","groundMinReach":16,"weaponFamilyId":"cal_76","real":"2A70 100/76 mm","family":"tank_gun","size":76,"caliberMm":76,"pen":3,"piercing":true,"damageType":"Kinetic","damage":120,"cooldown":6,"range":34,"projectileSpeed":170,"splash":1.5,"spread":0.7,"impactTier":"Medium","roundWeight":150}
A30: borer_cannon_he | B30: 2A70 100/76 mm HE | C30: cal_76 | F30: tank_gun | G30: 76 | K30: HighExplosive | L30: 2 | M30: Shell | N30: 1 | O30: RIPPLE | P30: 1 | Q30: 0.1 | R30: 6 | S30: 0 | T30: 0 | U30: 0 | V30: 0 | W30: 120 | X30: 3 | Y30: 0 | Z30: 170 | AA30: 34 | AB30: 0 | AC30: Ground | AE30: 0.7 | AF30: Large | AG30: FALSE | AH30: FALSE | AI30: FALSE | AJ30: FALSE | AK30: FALSE | AL30: FALSE | AM30: FALSE | AN30: 76 | AO30: 0 | AP30: T2 | AQ30: borer_cannon | AU30: 0 | AW30: 0 | AX30: FALSE | AZ30: =IF(AND($AX$30,$AW$30>$AA$30/$Z$30),$AW$30,$AA$30/$Z$30) | BA30: 0.2 | BB30: 10 | BC30: 8 | BD30: gun | BE30: Wikipedia '2A70': 10 rpm (100 mm), BMP-3 | BG30: doi | BJ30: 2.08 | BK30: 6 | DE30: 120 | DF30: HighExplosive | DM30: light;structure | DN30: HeShell | DS30: Large | DT30: borer_cannon | EB30: 2 | EE30: FALSE | EQ30: 2A70 100/76 mm HE | ES30: he | EU30: borer_cannon | EY30: 3 | FW30: Ground | GD30: Assets/MachineBrigade/Resources/Data/balance.json: secondRounds.rounds[7] | GE30: {"id":"borer_cannon_he","roundOf":"borer_cannon","inherits":"borer_cannon","weaponFamily":"","round":"he","for":["light","structure"],"real":"2A70 100/76 mm HE","damageType":"HighExplosive","pen":2,"damage":120,"splash":3,"form":"HeShell","piercing":false,"targets":"Ground","impactTier":"Large"}
A31: borer_drill | B31: drill head | C31: melee_drill_head | F31: melee | K31: Kinetic | L31: 4 | M31: Bullet | N31: 1 | O31: RIPPLE | P31: 1 | Q31: 0.1 | R31: 1.5 | S31: 0 | T31: 0 | U31: 0 | V31: 0 | W31: 260 | X31: 0 | Y31: 0 | Z31: 400 | AA31: 7 | AB31: 0 | AC31: Ground | AE31: 0 | AF31: Large | AG31: FALSE | AH31: FALSE | AI31: FALSE | AJ31: FALSE | AK31: FALSE | AL31: FALSE | AM31: FALSE | AN31: 2 | AO31: 0 | AP31: T0 | AS31: boss | AT31: earth_borer | AU31: 1 | AV31: earth_borer:0 | AW31: 0 | AX31: FALSE | AZ31: =IF(AND($AX$31,$AW$31>$AA$31/$Z$31),$AW$31,$AA$31/$Z$31) | BA31: 0.0175 | BB31: NEED_SOURCE | BC31: NEED_SOURCE | BE31: NEED_SOURCE | BG31: giong | DD31: 1.5 | DE31: 260 | DF31: Kinetic | DJ31: melee | DS31: Large | DY31: TRUE | EB31: 4 | EE31: TRUE | EH31: Bullet | EK31: 400 | EP31: 7 | EQ31: drill head | EX31: 2 | FW31: Ground | GB31: melee_drill_head | GD31: Assets/MachineBrigade/Resources/Data/balance.json: weapons[243] | GE31: {"id":"borer_drill","weaponFamilyId":"melee_drill_head","real":"drill head","family":"melee","size":2,"pen":4,"piercing":true,"melee":true,"damageType":"Kinetic","damage":260,"cooldown":1.5,"range":7,"projectileSpeed":400,"impactTier":"Large","projectile":"Bullet","targets":"Ground","bonuses":[{"armor":"Structure","mult":2}]}
A32: boss_flak | B32: Oerlikon 35 mm (twin) | C32: cal_35 | E32: oerlikon_35_mm | F32: autocannon | G32: 35 | K32: Fragmentation | L32: 2 | M32: Bullet | N32: 1 | O32: RIPPLE | P32: 1 | Q32: 0.1 | R32: 0.05 | S32: 41 | T32: 3.38 | U32: 0 | V32: 0 | W32: 25 | X32: 2.5 | Y32: 0 | Z32: 260 | AA32: 40 | AB32: 0 | AC32: All | AE32: 1.5 | AF32: Small | AG32: FALSE | AH32: FALSE | AI32: FALSE | AJ32: FALSE | AK32: FALSE | AL32: FALSE | AM32: FALSE | AN32: 35 | AO32: 0 | AP32: T1 | AR32: boss_flak_ap | AS32: boss;boss_part;xe | AT32: armored_train;flak_35;mara_behemoth | AU32: 3 | AV32: armored_train:3;armored_train:5;flak_35:part;mara_behemoth:2;mara_behemoth:3 | AW32: 0 | AX32: FALSE | AZ32: =IF(AND($AX$32,$AW$32>$AA$32/$Z$32),$AW$32,$AA$32/$Z$32) | BA32: 0.15384615 | BB32: 550 | BC32: 300 | BD32: aa | BE32: Wikipedia 'Oerlikon GDF': 550 rpm a gun (the twin: 1,100) | BG32: giong | CT32: 35 | CW32: 41 | CX32: 3.38 | DD32: 0.05 | DE32: 25 | DF32: Fragmentation | DJ32: autocannon | DS32: Small | EB32: 2 | EH32: Bullet | EP32: 40 | EQ32: Oerlikon 35 mm (twin) | EX32: 35 | EZ32: 1.5 | FW32: All | GA32: oerlikon_35_mm | GB32: cal_35 | GD32: Assets/MachineBrigade/Resources/Data/balance.json: weapons[232] | GE32: {"id":"boss_flak","weaponFamilyId":"cal_35","weaponFamily":"oerlikon_35_mm","real":"Oerlikon 35 mm (twin)","family":"autocannon","size":35,"caliberMm":35,"pen":2,"damageType":"Fragmentation","damage":25,"cooldown":0.05,"range":40,"spread":1.5,"impactTier":"Small","projectile":"Bullet","targets":"All","clip":41,"clipReload":3.38}
A33: boss_flak_ap | B33: Oerlikon 35 mm AP (twin) | C33: cal_35 | D33: ap | E33: oerlikon_35_mm_ap | F33: autocannon | G33: 35 | K33: Kinetic | L33: 2 | M33: Bullet | N33: 1 | O33: RIPPLE | P33: 1 | Q33: 0.1 | R33: 0.05 | S33: 41 | T33: 3.38 | U33: 0 | V33: 0 | W33: 25 | X33: 0 | Y33: 0 | Z33: 260 | AA33: 40 | AB33: 0 | AC33: Ground | AE33: 1.5 | AF33: Small | AG33: FALSE | AH33: FALSE | AI33: FALSE | AJ33: FALSE | AK33: FALSE | AL33: FALSE | AM33: FALSE | AN33: 35 | AO33: 0 | AP33: T1 | AQ33: boss_flak | AU33: 0 | AW33: 0 | AX33: FALSE | AZ33: =IF(AND($AX$33,$AW$33>$AA$33/$Z$33),$AW$33,$AA$33/$Z$33) | BA33: 0.15384615 | BB33: 550 | BC33: 300 | BD33: aa | BE33: Wikipedia 'Oerlikon GDF': 550 rpm a gun (the twin: 1,100) | BG33: giong | DE33: 25 | DF33: Kinetic | DM33: ground | DN33: BeltedAutocannon | DT33: boss_flak | EB33: 2 | EE33: TRUE | EQ33: Oerlikon 35 mm AP (twin) | ES33: ap | EU33: boss_flak | EY33: 0 | FW33: Ground | GA33: oerlikon_35_mm_ap | GC33: ap | GD33: Assets/MachineBrigade/Resources/Data/balance.json: secondRounds.rounds[8] | GE33: {"id":"boss_flak_ap","roundOf":"boss_flak","inherits":"boss_flak","weaponVariantId":"ap","weaponFamily":"oerlikon_35_mm_ap","round":"ap","for":["ground"],"real":"Oerlikon 35 mm AP (twin)","damageType":"Kinetic","pen":2,"damage":25,"splash":0,"form":"BeltedAutocannon","piercing":true,"targets":"Ground"}
A34: boss_flamer | B34: flamethrower (heavy) | C34: flame_flamethrower | F34: flame | K34: Fire | L34: 2 | M34: Flame | N34: 1 | O34: RIPPLE | P34: 1 | Q34: 0.1 | R34: 0.25 | S34: 0 | T34: 0 | U34: 0 | V34: 0 | W34: 30 | X34: 3.5 | Y34: 0 | Z34: 38 | AA34: 20 | AB34: 0 | AC34: Ground | AE34: 0.8 | AF34: Medium | AG34: FALSE | AH34: FALSE | AI34: FALSE | AJ34: FALSE | AK34: FALSE | AL34: FALSE | AM34: FALSE | AN34: 3 | AO34: 0 | AP34: T1 | AS34: boss | AT34: behemoth_inferno | AU34: 1 | AV34: behemoth_inferno:0;behemoth_inferno:2 | AW34: 0 | AX34: FALSE | AZ34: =IF(AND($AX$34,$AW$34>$AA$34/$Z$34),$AW$34,$AA$34/$Z$34) | BA34: 0.52631579 | BB34: NEED_SOURCE | BC34: NEED_SOURCE | BE34: NEED_SOURCE | BG34: giong | DD34: 0.25 | DE34: 30 | DF34: Fire | DJ34: flame | DS34: Medium | EB34: 2 | EH34: Flame | EK34: 38 | EP34: 20 | EQ34: flamethrower (heavy) | EX34: 3 | EY34: 3.5 | EZ34: 0.8 | GB34: flame_flamethrower | GD34: Assets/MachineBrigade/Resources/Data/balance.json: weapons[239] | GE34: {"id":"boss_flamer","weaponFamilyId":"flame_flamethrower","real":"flamethrower (heavy)","family":"flame","size":3,"pen":2,"damageType":"Fire","damage":30,"cooldown":0.25,"range":20,"projectileSpeed":38,"splash":3.5,"spread":0.8,"impactTier":"Medium","projectile":"Flame"}
A35: boss_heli_gun | B35: M230 30 mm | C35: cal_30 | F35: autocannon | G35: 30 | K35: Kinetic | L35: 2 | M35: Bullet | N35: 1 | O35: RIPPLE | P35: 1 | Q35: 0.1 | R35: 0.1667 | S35: 40 | T35: 3.167 | U35: 0 | V35: 0 | W35: 22 | X35: 0 | Y35: 0 | Z35: 200 | AA35: 26 | AB35: 0 | AC35: All | AE35: 1.3 | AF35: Small | AG35: FALSE | AH35: FALSE | AI35: FALSE | AJ35: FALSE | AK35: FALSE | AL35: FALSE | AM35: FALSE | AN35: 30 | AO35: 0 | AP35: T1 | AQ35: heli_gun | AR35: boss_heli_gun_flak | AS35: boss | AT35: mega_gunship | AU35: 1 | AV35: mega_gunship:1;mega_gunship:2 | AW35: 0 | AX35: FALSE | AZ35: =IF(AND($AX$35,$AW$35>$AA$35/$Z$35),$AW$35,$AA$35/$Z$35) | BA35: 0.13 | BB35: 625 | BC35: 300 | BD35: ac | BE35: Wikipedia 'M230 chain gun': 625 rpm | BG35: doi | BR35: 220 | BS35: 200 | CH35: 3.1667 | CI35: 3.167 | CT35: 30 | CW35: 40 | CX35: 3.167 | DD35: 0.1667 | DJ35: autocannon | DT35: heli_gun | EB35: 2 | EK35: 200 | EQ35: M230 30 mm | EX35: 30 | EY35: 0 | GD35: Assets/MachineBrigade/Resources/Data/balance.json: weapons[247] | GE35: {"id":"boss_heli_gun","weaponFamily":"","real":"M230 30 mm","family":"autocannon","size":30,"caliberMm":30,"pen":2,"inherits":"heli_gun","splash":0,"projectileSpeed":200,"cooldown":0.1667,"clip":40,"clipReload":3.167}
A36: boss_heli_gun_flak | B36: M230 30 mm air-burst | C36: cal_30 | D36: flak | E36: m230_30_mm_air_burst | F36: autocannon | G36: 30 | K36: Fragmentation | L36: 2 | M36: Bullet | N36: 1 | O36: RIPPLE | P36: 1 | Q36: 0.1 | R36: 0.1667 | S36: 40 | T36: 3.167 | U36: 0 | V36: 0 | W36: 22 | X36: 2.5 | Y36: 0 | Z36: 220 | AA36: 26 | AB36: 0 | AC36: Air | AE36: 1.3 | AF36: Small | AG36: FALSE | AH36: FALSE | AI36: FALSE | AJ36: FALSE | AK36: FALSE | AL36: FALSE | AM36: FALSE | AN36: 30 | AO36: 0 | AP36: T1 | AQ36: boss_heli_gun | AU36: 0 | AW36: 0 | AX36: FALSE | AZ36: =IF(AND($AX$36,$AW$36>$AA$36/$Z$36),$AW$36,$AA$36/$Z$36) | BA36: 0.11818182 | BB36: 625 | BC36: 300 | BD36: ac | BE36: Wikipedia 'M230 chain gun': 625 rpm | BG36: doi | CH36: 3.1667 | CI36: 3.167 | DE36: 22 | DF36: Fragmentation | DM36: air | DN36: Airburst | DT36: boss_heli_gun | EB36: 2 | EE36: FALSE | EQ36: M230 30 mm air-burst | ES36: flak | EU36: boss_heli_gun | EY36: 2.5 | FW36: Air | GA36: m230_30_mm_air_burst | GC36: flak | GD36: Assets/MachineBrigade/Resources/Data/balance.json: secondRounds.rounds[9] | GE36: {"id":"boss_heli_gun_flak","roundOf":"boss_heli_gun","inherits":"boss_heli_gun","weaponVariantId":"flak","weaponFamily":"m230_30_mm_air_burst","round":"flak","for":["air"],"real":"M230 30 mm air-burst","damageType":"Fragmentation","pen":2,"damage":22,"splash":2.5,"form":"Airburst","piercing":false,"targets":"Air"}
A37: boss_hmg | B37: NSV 12.7 mm | C37: cal_12_7 | E37: nsv_12_7_mm | F37: mg | G37: 12.7 | K37: Kinetic | L37: 1 | M37: Bullet | N37: 1 | O37: RIPPLE | P37: 1 | Q37: 0.1 | R37: 0.0833 | S37: 100 | T37: 5 | U37: 0 | V37: 0 | W37: 15 | X37: 0 | Y37: 0 | Z37: 240 | AA37: 30 | AB37: 0 | AC37: All | AE37: 1.3 | AF37: Small | AG37: FALSE | AH37: FALSE | AI37: FALSE | AJ37: FALSE | AK37: FALSE | AL37: FALSE | AM37: FALSE | AN37: 12.7 | AO37: 0 | AP37: T0 | AQ37: hmg_roof | AR37: boss_hmg_api | AS37: boss | AT37: armored_train;mega_gunship | AU37: 2 | AV37: armored_train:2;mega_gunship:5;mega_gunship:6 | AW37: 0 | AX37: FALSE | AZ37: =IF(AND($AX$37,$AW$37>$AA$37/$Z$37),$AW$37,$AA$37/$Z$37) | BA37: 0.125 | BB37: 800 | BC37: 100 | BD37: mg | BE37: Wikipedia 'NSV machine gun': 700-800 cyclic, 100 practical | BF37: wave 1 boss_hmg: 100 rounds at 720 rpm, changed in 5 s (NSV 700-800 rpm) | BG37: doi | BH37: 9.5 | BI37: 15 | CH37: 5.0833 | CI37: 5 | CT37: 12.7 | CW37: 100 | CX37: 5 | DD37: 0.0833 | DE37: 15 | DJ37: mg | DT37: hmg_roof | EB37: 1 | EQ37: NSV 12.7 mm | EX37: 12.7 | GA37: nsv_12_7_mm | GD37: Assets/MachineBrigade/Resources/Data/balance.json: weapons[249] | GE37: {"id":"boss_hmg","weaponFamily":"nsv_12_7_mm","real":"NSV 12.7 mm","family":"mg","size":12.7,"caliberMm":12.7,"pen":1,"inherits":"hmg_roof","damage":15,"cooldown":0.0833,"clip":100,"clipReload":5}
A38: boss_hmg_api | B38: NSV 12.7 mm API | C38: cal_12_7 | E38: nsv_12_7_mm_api | F38: mg | G38: 12.7 | K38: Kinetic | L38: 2 | M38: Bullet | N38: 1 | O38: RIPPLE | P38: 1 | Q38: 0.1 | R38: 0.0833 | S38: 100 | T38: 5 | U38: 0 | V38: 0 | W38: 15 | X38: 0 | Y38: 0 | Z38: 240 | AA38: 30 | AB38: 0 | AC38: All | AE38: 1.3 | AF38: Small | AG38: FALSE | AH38: FALSE | AI38: FALSE | AJ38: FALSE | AK38: FALSE | AL38: FALSE | AM38: FALSE | AN38: 12.7 | AO38: 0 | AP38: T0 | AQ38: boss_hmg | AU38: 0 | AW38: 0 | AX38: FALSE | AZ38: =IF(AND($AX$38,$AW$38>$AA$38/$Z$38),$AW$38,$AA$38/$Z$38) | BA38: 0.125 | BB38: 800 | BC38: 100 | BD38: mg | BE38: Wikipedia 'NSV machine gun': 700-800 cyclic, 100 practical | BG38: doi | BH38: 9.5 | BI38: 15 | CH38: 5.0833 | CI38: 5 | DE38: 15 | DF38: Kinetic | DH38: TRUE | DM38: any | DN38: BulletBig | DT38: boss_hmg | EB38: 2 | EE38: TRUE | EQ38: NSV 12.7 mm API | ES38: api | EU38: boss_hmg | GA38: nsv_12_7_mm_api | GD38: Assets/MachineBrigade/Resources/Data/balance.json: secondRounds.rounds[10] | GE38: {"id":"boss_hmg_api","roundOf":"boss_hmg","inherits":"boss_hmg","weaponFamily":"nsv_12_7_mm_api","round":"api","for":["any"],"elite":true,"real":"NSV 12.7 mm API","damageType":"Kinetic","pen":2,"damage":15,"form":"BulletBig","piercing":true}
A39: boss_howitzer | B39: 2A44 203 mm | C39: cal_203 | F39: howitzer | G39: 203 | K39: HighExplosive | L39: 4 | M39: Shell | N39: 1 | O39: RIPPLE | P39: 1 | Q39: 0.1 | R39: 9.44 | S39: 0 | T39: 0 | U39: 0 | V39: 0 | W39: 420 | X39: 8 | Y39: 0 | Z39: 100 | AA39: 60 | AB39: 0 | AC39: Ground | AE39: 3 | AF39: Huge | AG39: FALSE | AH39: FALSE | AI39: FALSE | AJ39: FALSE | AK39: FALSE | AL39: FALSE | AM39: FALSE | AN39: 203 | AO39: 0 | AP39: T4 | AR39: boss_howitzer_guided | AS39: boss_part | AT39: howitzer_203 | AU39: 1 | AV39: howitzer_203:part | AW39: 2.5 | AX39: TRUE | AZ39: =IF(AND($AX$39,$AW$39>$AA$39/$Z$39),$AW$39,$AA$39/$Z$39) | BA39: 2.5 | BB39: 2.5 | BC39: 1 | BD39: gun | BE39: Wikipedia '2S7 Pion': 1.5 rpm (2S7M Malka 2.5) | BG39: doi | BR39: 60 | BS39: 100 | CT39: 203 | DD39: 9.44 | DE39: 420 | DF39: HighExplosive | DJ39: howitzer | DS39: Huge | DX39: TRUE | EB39: 4 | EI39: shell_155 | EJ39: 0.9455 | EK39: 100 | EP39: 60 | EQ39: 2A44 203 mm | ET39: 1.04 | EX39: 203 | EY39: 8 | EZ39: 3 | GB39: cal_203 | GD39: Assets/MachineBrigade/Resources/Data/balance.json: weapons[137] | GE39: {"id":"boss_howitzer","lobs":true,"weaponFamilyId":"cal_203","real":"2A44 203 mm","family":"howitzer","size":203,"caliberMm":203,"pen":4,"projectileModel":"shell_155","projectileScale":0.9455,"roundLength":1.04,"damageType":"HighExplosive","damage":420,"cooldown":9.44,"range":60,"projectileSpeed":100,"splash":8,"spread":3,"impactTier":"Huge"}
A40: boss_howitzer_guided | B40: 2A44 203 mm guided | C40: cal_203 | F40: howitzer | G40: 203 | K40: HighExplosive | L40: 4 | M40: Shell | N40: 1 | O40: RIPPLE | P40: 1 | Q40: 0.1 | R40: 9.44 | S40: 0 | T40: 0 | U40: 0 | V40: 0 | W40: 420 | X40: 8 | Y40: 0 | Z40: 100 | AA40: 60 | AB40: 0 | AC40: Ground | AE40: 0 | AF40: Huge | AG40: FALSE | AH40: FALSE | AI40: FALSE | AJ40: FALSE | AK40: FALSE | AL40: FALSE | AM40: TRUE | AN40: 203 | AO40: 0 | AP40: T4 | AQ40: boss_howitzer | AU40: 0 | AW40: 2.5 | AX40: TRUE | AZ40: =IF(AND($AX$40,$AW$40>$AA$40/$Z$40),$AW$40,$AA$40/$Z$40) | BA40: 2.5 | BB40: 2.5 | BC40: 1 | BD40: gun | BE40: Wikipedia '2S7 Pion': 1.5 rpm (2S7M Malka 2.5) | BG40: doi | BR40: 60 | BS40: 100 | CR40: 1 | DE40: 420 | DF40: HighExplosive | DH40: TRUE | DM40: armour | DN40: HeShell | DP40: TRUE | DT40: boss_howitzer | EB40: 4 | EQ40: 2A44 203 mm guided | ES40: guided | EU40: boss_howitzer | EZ40: 0 | FW40: Ground | GD40: Assets/MachineBrigade/Resources/Data/balance.json: secondRounds.rounds[11] | GE40: {"id":"boss_howitzer_guided","roundOf":"boss_howitzer","inherits":"boss_howitzer","weaponFamily":"","round":"guided","for":["armour"],"elite":true,"real":"2A44 203 mm guided","damageType":"HighExplosive","pen":4,"damage":420,"spread":0,"burst":1,"guided":true,"form":"HeShell","targets":"Ground"}
A41: boss_minigun | B41: GShG 7.62 mm | C41: cal_7_62 | F41: mg | G41: 7.62 | K41: Kinetic | L41: 0 | M41: Bullet | N41: 1 | O41: RIPPLE | P41: 1 | Q41: 0.1 | R41: 0.0172 | S41: 40 | T41: 6.09 | U41: 0 | V41: 0 | W41: 5.5 | X41: 0 | Y41: 0 | Z41: 240 | AA41: 24 | AB41: 0 | AC41: All | AE41: 1.4 | AF41: Small | AG41: FALSE | AH41: FALSE | AI41: FALSE | AJ41: FALSE | AK41: FALSE | AL41: FALSE | AM41: FALSE | AN41: 7.62 | AO41: 0 | AP41: T0 | AQ41: minigun | AS41: boss | AT41: mega_gunship | AU41: 1 | AV41: mega_gunship:3 | AW41: 0 | AX41: FALSE | AZ41: =IF(AND($AX$41,$AW$41>$AA$41/$Z$41),$AW$41,$AA$41/$Z$41) | BA41: 0.1 | BB41: 6000 | BD41: mg | BE41: Wikipedia 'GShG-7.62': 3,500 / 6,000 rpm | BG41: giong | CT41: 7.62 | CW41: 40 | CX41: 6.09 | DD41: 0.0172 | DJ41: mg | DT41: minigun | EB41: 0 | EQ41: GShG 7.62 mm | EV41: 7 | EX41: 7.62 | GD41: Assets/MachineBrigade/Resources/Data/balance.json: weapons[248] | GE41: {"id":"boss_minigun","real":"GShG 7.62 mm","family":"mg","size":7.62,"caliberMm":7.62,"pen":0,"inherits":"minigun","cooldown":0.0172,"roundWeight":7,"clip":40,"clipReload":6.09}
A42: boss_missiles | B42: 9M133 Kornet | C42: atgm_kornet | E42: 9m133_kornet | F42: atgm | H42: 7 | K42: ShapedCharge | L42: 4 | M42: Missile | N42: 1 | O42: RIPPLE | P42: 1 | Q42: 0.1 | R42: 6.39 | S42: 0 | T42: 0 | U42: 0 | V42: 0 | W42: 230 | X42: 0 | Y42: 0 | Z42: 80 | AA42: 45 | AB42: 0 | AC42: Ground | AE42: 0 | AF42: Medium | AG42: FALSE | AH42: FALSE | AI42: FALSE | AJ42: FALSE | AK42: FALSE | AL42: FALSE | AM42: FALSE | AN42: 29 | AO42: 0 | AP42: T2 | AS42: xe | AT42: mara_behemoth | AU42: 1 | AV42: mara_behemoth:4;mara_behemoth:5 | AW42: 0 | AX42: FALSE | AZ42: =IF(AND($AX$42,$AW$42>$AA$42/$Z$42),$AW$42,$AA$42/$Z$42) | BA42: 0.5625 | BB42: 3 | BC42: 3 | BD42: atgm | BE42: Wikipedia '9M133 Kornet': 2-3 rpm | BG42: doi | BR42: 22 | BS42: 80 | DD42: 6.39 | DE42: 230 | DF42: ShapedCharge | DJ42: atgm | DS42: Medium | EB42: 4 | EE42: TRUE | EH42: Missile | EP42: 45 | EQ42: 9M133 Kornet | EX42: 29 | FW42: Ground | FZ42: 7 | GA42: 9m133_kornet | GB42: atgm_kornet | GD42: Assets/MachineBrigade/Resources/Data/balance.json: weapons[139] | GE42: {"id":"boss_missiles","weaponFamilyId":"atgm_kornet","weaponFamily":"9m133_kornet","real":"9M133 Kornet","family":"atgm","size":29,"warheadKg":7,"pen":4,"piercing":true,"damageType":"ShapedCharge","damage":230,"cooldown":6.39,"range":45,"impactTier":"Medium","projectile":"Missile","targets":"Ground"}
A43: boss_mortar | B43: 2B8 240 mm | C43: cal_240 | E43: 2b8_240_mm | F43: mortar | G43: 240 | K43: HighExplosive | L43: 4 | M43: Shell | N43: 1 | O43: RIPPLE | P43: 1 | Q43: 0.1 | R43: 9.78 | S43: 0 | T43: 0 | U43: 0 | V43: 0 | W43: 450 | X43: 9 | Y43: 0 | Z43: 60 | AA43: 80 | AB43: 12 | AC43: Ground | AE43: 3.5 | AF43: Huge | AG43: FALSE | AH43: FALSE | AI43: FALSE | AJ43: FALSE | AK43: FALSE | AL43: FALSE | AM43: FALSE | AN43: 240 | AO43: 0 | AP43: T4 | AU43: 0 | AW43: 2.5 | AX43: TRUE | AZ43: =IF(AND($AX$43,$AW$43>$AA$43/$Z$43),$AW$43,$AA$43/$Z$43) | BA43: 2.5 | BB43: 1 | BC43: 1 | BD43: gun | BE43: Wikipedia '2S4 Tyulpan': ~1 rpm | BG43: doi | BR43: 38 | BS43: 60 | CT43: 240 | DD43: 9.78 | DE43: 450 | DF43: HighExplosive | DJ43: mortar | DS43: Huge | DZ43: 12 | EB43: 4 | EH43: Shell | EP43: 80 | EQ43: 2B8 240 mm | EX43: 240 | EZ43: 3.5 | GA43: 2b8_240_mm | GB43: cal_240 | GD43: Assets/MachineBrigade/Resources/Data/balance.json: weapons[242] | GE43: {"id":"boss_mortar","weaponFamilyId":"cal_240","weaponFamily":"2b8_240_mm","real":"2B8 240 mm","family":"mortar","size":240,"caliberMm":240,"pen":4,"damageType":"HighExplosive","damage":450,"cooldown":9.78,"range":80,"minRange":12,"spread":3.5,"impactTier":"Huge","projectile":"Shell"}
A44: boss_railgun | B44: railgun (64 MJ) | C44: rail_railgun | F44: railgun | J44: 64 | K44: Kinetic | L44: 4 | M44: Bullet | N44: 1 | O44: RIPPLE | P44: 1 | Q44: 0.1 | R44: 8 | S44: 0 | T44: 0 | U44: 0 | V44: 0 | W44: 720 | X44: 0 | Y44: 0 | Z44: 700 | AA44: 80 | AB44: 0 | AC44: Ground | AE44: 0.4 | AF44: Large | AG44: FALSE | AH44: FALSE | AI44: FALSE | AJ44: FALSE | AK44: FALSE | AL44: FALSE | AM44: FALSE | AN44: 64 | AO44: 0 | AP44: T3 | AS44: boss | AT44: behemoth_tempest | AU44: 1 | AV44: behemoth_tempest:0 | AW44: 0 | AX44: FALSE | AZ44: =IF(AND($AX$44,$AW$44>$AA$44/$Z$44),$AW$44,$AA$44/$Z$44) | BA44: 0.11428571 | BB44: NEED_SOURCE | BC44: NEED_SOURCE | BE44: NEED_SOURCE | BG44: giong | CV44: 1 | DD44: 8 | DE44: 720 | DF44: Kinetic | DI44: 64 | DJ44: railgun | DO44: 33 | DR44: 1.6 | DS44: Large | EB44: 4 | EC44: TRUE | EE44: TRUE | EH44: Bullet | EI44: rail_slug | EK44: 700 | EP44: 80 | EQ44: railgun (64 MJ) | EX44: 64 | EZ44: 0.4 | GB44: rail_railgun | GD44: Assets/MachineBrigade/Resources/Data/balance.json: weapons[241] | GE44: {"id":"boss_railgun","groundMinReach":33,"weaponFamilyId":"rail_railgun","real":"railgun (64 MJ)","family":"railgun","size":64,"energyMj":64,"pen":4,"piercing":true,"charge":1.0,"projectileModel":"rail_slug","damageType":"Kinetic","damage":720,"cooldown":8,"range":80,"projectileSpeed":700,"spread":0.4,"impactTier":"Large","projectile":"Bullet","pierce":true,"impactScale":1.6}
A45: boss_rockets | B45: BM-21 Grad 122 mm | C45: rkt_grad_122 | F45: rocket | G45: 122 | K45: HighExplosive | L45: 2 | M45: Rocket | N45: 1 | O45: RIPPLE | P45: 13 | Q45: 0.5 | R45: 2.44 | S45: 0 | T45: 0 | U45: 0 | V45: 0 | W45: 200 | X45: 4.5 | Y45: 9 | Z45: 65 | AA45: 45 | AB45: 0 | AC45: Ground | AE45: 5 | AF45: Medium | AG45: FALSE | AH45: FALSE | AI45: FALSE | AJ45: FALSE | AK45: FALSE | AL45: FALSE | AM45: FALSE | AN45: 122 | AO45: 0 | AP45: T3 | AS45: boss_part | AT45: rocket_pod | AU45: 1 | AV45: rocket_pod:part | AW45: 0 | AX45: FALSE | AZ45: =IF(AND($AX$45,$AW$45>$AA$45/$Z$45),$AW$45,$AA$45/$Z$45) | BA45: 0.69230769 | BB45: 120 | BD45: rocket | BE45: Wikipedia 'BM-21 Grad': 40 rockets in 20 s | BF45: wave 1 boss_rockets: rockets 0.5 s apart (BM-21: 40 in 20 s), 2.44 s after the ripple; each pod keeps its rockets; made up: a full BM-21 pack of 40 tubes (8 before); made up: a full BM-21 pack of 40 tubes (13 before) | BG45: doi | BH45: 57 | BI45: 200 | BJ45: 2.94 | BK45: 2.44 | BP45: 0 | BQ45: 9 | BR45: 45 | BS45: 65 | CR45: 13 | CS45: 0.5 | CT45: 122 | DD45: 2.44 | DE45: 200 | DF45: HighExplosive | DG45: 9 | DJ45: rocket | DL45: Ballistic | DO45: 14 | DS45: Medium | EB45: 2 | EH45: Rocket | EI45: grad | EK45: 65 | EP45: 45 | EQ45: BM-21 Grad 122 mm | EX45: 122 | EY45: 4.5 | EZ45: 5 | GB45: rkt_grad_122 | GD45: Assets/MachineBrigade/Resources/Data/balance.json: weapons[138] | GE45: {"id":"boss_rockets","groundMinReach":14,"flightProfile":"Ballistic","weaponFamilyId":"rkt_grad_122","edge":9,"real":"BM-21 Grad 122 mm","family":"rocket","size":122,"caliberMm":122,"pen":2,"projectileModel":"grad","damageType":"HighExplosive","damage":200,"cooldown":2.44,"range":45,"projectileSpeed":65,"splash":4.5,"spread":5,"impactTier":"Medium","projectile":"Rocket","burst":13,"burstInterval":0.5}
A46: boss_thermo | B46: 2A46M 125 mm, 3VOF128 thermobaric | C46: cal_125_he | F46: tank_gun | G46: 125 | K46: HighExplosive | L46: 3 | M46: Shell | N46: 1 | O46: RIPPLE | P46: 1 | Q46: 0.1 | R46: 6.255 | S46: 0 | T46: 0 | U46: 0 | V46: 0 | W46: 291 | X46: 7 | Y46: 0 | Z46: 170 | AA46: 46 | AB46: 0 | AC46: Ground | AE46: 1 | AF46: Large | AG46: FALSE | AH46: FALSE | AI46: TRUE | AJ46: FALSE | AK46: FALSE | AL46: FALSE | AM46: FALSE | AN46: 125 | AO46: 0 | AP46: T3 | AS46: boss | AT46: behemoth_inferno | AU46: 1 | AV46: behemoth_inferno:1 | AW46: 0 | AX46: FALSE | AZ46: =IF(AND($AX$46,$AW$46>$AA$46/$Z$46),$AW$46,$AA$46/$Z$46) | BA46: 0.27058824 | BB46: 8 | BC46: 7 | BD46: gun | BE46: Wikipedia '2A46': 7-8 rpm with the autoloader | BG46: doi | BH46: 97 | BI46: 291 | BJ46: 12.51 | BK46: 6.255 | BR46: 35 | BS46: 170 | BT46: 6 | BU46: 1 | BV46: 0.3 | BW46: 0.1 | CJ46: Rocket | CK46: Shell | CT46: 125 | DD46: 6.255 | DE46: 291 | DF46: HighExplosive | DJ46: tank_gun | DO46: 21 | DS46: Large | EB46: 3 | EH46: Shell | EK46: 170 | EP46: 46 | EQ46: 2A46M 125 mm, 3VOF128 thermobaric | EX46: 125 | EY46: 7 | EZ46: 1 | FX46: TRUE | GB46: cal_125_he | GD46: Assets/MachineBrigade/Resources/Data/balance.json: weapons[240] | GE46: {"id":"boss_thermo","groundMinReach":21,"weaponFamilyId":"cal_125_he","real":"2A46M 125 mm, 3VOF128 thermobaric","family":"tank_gun","size":125,"caliberMm":125,"pen":3,"thermobaric":true,"damageType":"HighExplosive","damage":291,"cooldown":6.255,"range":46,"projectileSpeed":170,"splash":7,"spread":1,"impactTier":"Large","projectile":"Shell"}
A47: buk_launcher | B47: 9M317 Buk | C47: sam_9m317_buk | E47: 9m317_buk | F47: aa_missile | H47: 70 | K47: Fragmentation | L47: 3 | M47: Missile | N47: 1 | O47: RIPPLE | P47: 2 | Q47: 0.5 | R47: 2.8 | S47: 0 | T47: 0 | U47: 0 | V47: 0 | W47: 320 | X47: 2 | Y47: 0 | Z47: 250 | AA47: 55 | AB47: 0 | AC47: Air | AE47: 0 | AF47: Medium | AG47: FALSE | AH47: FALSE | AI47: FALSE | AJ47: FALSE | AK47: FALSE | AL47: FALSE | AM47: FALSE | AN47: 70 | AO47: 0 | AP47: T2 | AQ47: sam_long | AS47: xe | AT47: sam_launcher | AU47: 1 | AV47: sam_launcher:0 | AW47: 0 | AX47: FALSE | AZ47: =IF(AND($AX$47,$AW$47>$AA$47/$Z$47),$AW$47,$AA$47/$Z$47) | BA47: 0.22 | BB47: 15 | BC47: 15 | BD47: missile | BE47: Wikipedia 'Buk missile system': 4 s between launches | BG47: doi | BR47: 50 | BS47: 250 | DD47: 2.8 | DJ47: aa_missile | DT47: sam_long | EB47: 3 | EQ47: 9M317 Buk | EX47: 70 | FZ47: 70 | GA47: 9m317_buk | GD47: Assets/MachineBrigade/Resources/Data/balance.json: weapons[30] | GE47: {"id":"buk_launcher","weaponFamily":"9m317_buk","real":"9M317 Buk","family":"aa_missile","size":70,"warheadKg":70,"pen":3,"inherits":"sam_long","cooldown":2.8}
A48: bunker_flame | B48: flamethrower (bunker) | C48: flame_flamethrower | F48: flame | K48: Fire | L48: 1 | M48: Flame | N48: 1 | O48: RIPPLE | P48: 1 | Q48: 0.1 | R48: 0.195 | S48: 0 | T48: 0 | U48: 0 | V48: 0 | W48: 26 | X48: 4.5 | Y48: 0 | Z48: 36 | AA48: 16 | AB48: 0 | AC48: Ground | AE48: 1.2 | AF48: Small | AG48: FALSE | AH48: FALSE | AI48: FALSE | AJ48: FALSE | AK48: FALSE | AL48: FALSE | AM48: FALSE | AN48: 2 | AO48: 0 | AP48: T1 | AQ48: flamethrower | AS48: thap | AT48: mg_bunker.flame | AU48: 1 | AV48: mg_bunker.flame:0 | AW48: 0 | AX48: FALSE | AZ48: =IF(AND($AX$48,$AW$48>$AA$48/$Z$48),$AW$48,$AA$48/$Z$48) | BA48: 0.44444444 | BB48: NEED_SOURCE | BC48: NEED_SOURCE | BE48: NEED_SOURCE | BG48: giong | DD48: 0.195 | DE48: 26 | DJ48: flame | DT48: flamethrower | EB48: 1 | EP48: 16 | EQ48: flamethrower (bunker) | EX48: 2 | EY48: 4.5 | GD48: Assets/MachineBrigade/Resources/Data/balance.json: weapons[112] | GE48: {"id":"bunker_flame","splash":4.5,"cooldown":0.195,"real":"flamethrower (bunker)","family":"flame","size":2,"pen":1,"inherits":"flamethrower","range":16,"damage":26}
A49: bunker_hmg | B49: NSV 12.7 mm | C49: cal_12_7 | E49: nsv_12_7_mm | F49: mg | G49: 12.7 | K49: Kinetic | L49: 1 | M49: Bullet | N49: 1 | O49: RIPPLE | P49: 1 | Q49: 0.1 | R49: 0.062 | S49: 150 | T49: 4.062 | U49: 0 | V49: 0 | W49: 9.5 | X49: 0 | Y49: 0 | Z49: 240 | AA49: 32 | AB49: 0 | AC49: All | AE49: 1.4 | AF49: Small | AG49: FALSE | AH49: FALSE | AI49: FALSE | AJ49: FALSE | AK49: FALSE | AL49: FALSE | AM49: FALSE | AN49: 12.7 | AO49: 0 | AP49: T0 | AR49: bunker_hmg_api | AS49: thap | AT49: bulwark_post;mg_bunker | AU49: 2 | AV49: bulwark_post:0;mg_bunker:0 | AW49: 0 | AX49: FALSE | AZ49: =IF(AND($AX$49,$AW$49>$AA$49/$Z$49),$AW$49,$AA$49/$Z$49) | BA49: 0.13333333 | BB49: 800 | BC49: 100 | BD49: mg | BE49: Wikipedia 'NSV machine gun': 700-800 cyclic, 100 practical | BG49: giong | CT49: 12.7 | CW49: 150 | CX49: 4.062 | DD49: 0.062 | DE49: 9.5 | DF49: Kinetic | DJ49: mg | DS49: Small | EB49: 1 | EH49: Bullet | EP49: 32 | EQ49: NSV 12.7 mm | EX49: 12.7 | EZ49: 1.4 | FW49: All | GA49: nsv_12_7_mm | GB49: cal_12_7 | GD49: Assets/MachineBrigade/Resources/Data/balance.json: weapons[131] | GE49: {"id":"bunker_hmg","weaponFamilyId":"cal_12_7","weaponFamily":"nsv_12_7_mm","real":"NSV 12.7 mm","family":"mg","size":12.7,"caliberMm":12.7,"pen":1,"damageType":"Kinetic","damage":9.5,"cooldown":0.062,"range":32,"spread":1.4,"impactTier":"Small","projectile":"Bullet","targets":"All","clip":150,"clipReload":4.062}
A50: bunker_hmg_api | B50: NSV 12.7 mm API | C50: cal_12_7 | E50: nsv_12_7_mm_api | F50: mg | G50: 12.7 | K50: Kinetic | L50: 2 | M50: Bullet | N50: 1 | O50: RIPPLE | P50: 1 | Q50: 0.1 | R50: 0.062 | S50: 150 | T50: 4.062 | U50: 0 | V50: 0 | W50: 9.5 | X50: 0 | Y50: 0 | Z50: 240 | AA50: 32 | AB50: 0 | AC50: All | AE50: 1.4 | AF50: Small | AG50: FALSE | AH50: FALSE | AI50: FALSE | AJ50: FALSE | AK50: FALSE | AL50: FALSE | AM50: FALSE | AN50: 12.7 | AO50: 0 | AP50: T0 | AQ50: bunker_hmg | AU50: 0 | AW50: 0 | AX50: FALSE | AZ50: =IF(AND($AX$50,$AW$50>$AA$50/$Z$50),$AW$50,$AA$50/$Z$50) | BA50: 0.13333333 | BB50: 800 | BC50: 100 | BD50: mg | BE50: Wikipedia 'NSV machine gun': 700-800 cyclic, 100 practical | BG50: giong | DE50: 9.5 | DF50: Kinetic | DH50: TRUE | DM50: any | DN50: BulletBig | DT50: bunker_hmg | EB50: 2 | EE50: TRUE | EQ50: NSV 12.7 mm API | ES50: api | EU50: bunker_hmg | GA50: nsv_12_7_mm_api | GD50: Assets/MachineBrigade/Resources/Data/balance.json: secondRounds.rounds[12] | GE50: {"id":"bunker_hmg_api","roundOf":"bunker_hmg","inherits":"bunker_hmg","weaponFamily":"nsv_12_7_mm_api","round":"api","for":["any"],"elite":true,"real":"NSV 12.7 mm API","damageType":"Kinetic","pen":2,"damage":9.5,"form":"BulletBig","piercing":true}
A51: bunker_hmg_twin | B51: NSV 12.7 mm (twin) | C51: cal_12_7 | E51: nsv_12_7_mm | F51: mg | G51: 12.7 | K51: Kinetic | L51: 1 | M51: Bullet | N51: 1 | O51: RIPPLE | P51: 1 | Q51: 0.1 | R51: 0.05 | S51: 150 | T51: 4.05 | U51: 0 | V51: 0 | W51: 9.5 | X51: 0 | Y51: 0 | Z51: 240 | AA51: 28 | AB51: 0 | AC51: All | AE51: 1.4 | AF51: Small | AG51: FALSE | AH51: FALSE | AI51: FALSE | AJ51: FALSE | AK51: FALSE | AL51: FALSE | AM51: FALSE | AN51: 12.7 | AO51: 0 | AP51: T0 | AQ51: bunker_hmg | AR51: bunker_hmg_twin_api | AS51: thap | AT51: mg_bunker.twin | AU51: 1 | AV51: mg_bunker.twin:0 | AW51: 0 | AX51: FALSE | AZ51: =IF(AND($AX$51,$AW$51>$AA$51/$Z$51),$AW$51,$AA$51/$Z$51) | BA51: 0.11666667 | BB51: 800 | BC51: 100 | BD51: mg | BE51: Wikipedia 'NSV machine gun': 700-800 cyclic, 100 practical | BG51: giong | CT51: 12.7 | CW51: 150 | CX51: 4.05 | DD51: 0.05 | DJ51: mg | DT51: bunker_hmg | EB51: 1 | EP51: 28 | EQ51: NSV 12.7 mm (twin) | EX51: 12.7 | GA51: nsv_12_7_mm | GD51: Assets/MachineBrigade/Resources/Data/balance.json: weapons[110] | GE51: {"id":"bunker_hmg_twin","weaponFamily":"nsv_12_7_mm","real":"NSV 12.7 mm (twin)","family":"mg","size":12.7,"caliberMm":12.7,"pen":1,"inherits":"bunker_hmg","cooldown":0.05,"range":28,"clip":150,"clipReload":4.05}
A52: bunker_hmg_twin_api | B52: NSV 12.7 mm API (twin) | C52: cal_12_7 | E52: nsv_12_7_mm_api | F52: mg | G52: 12.7 | K52: Kinetic | L52: 2 | M52: Bullet | N52: 1 | O52: RIPPLE | P52: 1 | Q52: 0.1 | R52: 0.05 | S52: 150 | T52: 4.05 | U52: 0 | V52: 0 | W52: 9.5 | X52: 0 | Y52: 0 | Z52: 240 | AA52: 28 | AB52: 0 | AC52: All | AE52: 1.4 | AF52: Small | AG52: FALSE | AH52: FALSE | AI52: FALSE | AJ52: FALSE | AK52: FALSE | AL52: FALSE | AM52: FALSE | AN52: 12.7 | AO52: 0 | AP52: T0 | AQ52: bunker_hmg_twin | AU52: 0 | AW52: 0 | AX52: FALSE | AZ52: =IF(AND($AX$52,$AW$52>$AA$52/$Z$52),$AW$52,$AA$52/$Z$52) | BA52: 0.11666667 | BB52: 800 | BC52: 100 | BD52: mg | BE52: Wikipedia 'NSV machine gun': 700-800 cyclic, 100 practical | BG52: giong | DE52: 9.5 | DF52: Kinetic | DH52: TRUE | DM52: any | DN52: BulletBig | DT52: bunker_hmg_twin | EB52: 2 | EE52: TRUE | EQ52: NSV 12.7 mm API (twin) | ES52: api | EU52: bunker_hmg_twin | GA52: nsv_12_7_mm_api | GD52: Assets/MachineBrigade/Resources/Data/balance.json: secondRounds.rounds[13] | GE52: {"id":"bunker_hmg_twin_api","roundOf":"bunker_hmg_twin","inherits":"bunker_hmg_twin","weaponFamily":"nsv_12_7_mm_api","round":"api","for":["any"],"elite":true,"real":"NSV 12.7 mm API (twin)","damageType":"Kinetic","pen":2,"damage":9.5,"form":"BulletBig","piercing":true}
A53: bunker_pkm | B53: PKM 7.62 mm (bunker embrasure) | C53: cal_7_62 | E53: pkt_m240_7_62_mm | F53: mg | G53: 7.62 | K53: Kinetic | L53: 0 | M53: Bullet | N53: 1 | O53: RIPPLE | P53: 1 | Q53: 0.1 | R53: 0.092 | S53: 100 | T53: 6 | U53: 0 | V53: 0 | W53: 1.6 | X53: 0 | Y53: 0 | Z53: 240 | AA53: 28 | AB53: 0 | AC53: All | AE53: 1 | AF53: Small | AG53: FALSE | AH53: FALSE | AI53: FALSE | AJ53: FALSE | AK53: FALSE | AL53: FALSE | AM53: FALSE | AN53: 7.62 | AO53: 0 | AP53: T0 | AQ53: mg_coax | AS53: thap | AT53: mg_bunker;mg_bunker.twin | AU53: 2 | AV53: mg_bunker:1;mg_bunker:2;mg_bunker:3;mg_bunker:4;mg_bunker.twin:1;mg_bunker.twin:2;mg_bunker.twin:3;mg_bunker.twin:4 | AW53: 0 | AX53: FALSE | AZ53: =IF(AND($AX$53,$AW$53>$AA$53/$Z$53),$AW$53,$AA$53/$Z$53) | BA53: 0.11666667 | BB53: NEED_SOURCE | BC53: NEED_SOURCE | BE53: NEED_SOURCE | BG53: moi | CT53: 7.62 | CW53: 100 | CX53: 6 | DD53: 0.092 | DE53: 1.6 | DJ53: mg | DT53: mg_coax | EB53: 0 | EP53: 28 | EQ53: PKM 7.62 mm (bunker embrasure) | EX53: 7.62 | GA53: pkt_m240_7_62_mm | GD53: Assets/MachineBrigade/Resources/Data/balance.json: weapons[111] | GE53: {"id":"bunker_pkm","weaponFamily":"pkt_m240_7_62_mm","real":"PKM 7.62 mm (bunker embrasure)","family":"mg","size":7.62,"caliberMm":7.62,"pen":0,"inherits":"mg_coax","damage":1.6,"cooldown":0.092,"range":28,"clip":100,"clipReload":6.0}
A54: c_ram_gatling | B54: Phalanx M61 20 mm | C54: cal_20 | F54: autocannon | G54: 20 | K54: Fragmentation | L54: 1 | M54: Bullet | N54: 1 | O54: RIPPLE | P54: 1 | Q54: 0.1 | R54: 0.02 | S54: 200 | T54: 3.02 | U54: 0 | V54: 0 | W54: 2 | X54: 1.2 | Y54: 0 | Z54: 380 | AA54: 32 | AB54: 0 | AC54: Air | AE54: 1.2 | AF54: Small | AG54: FALSE | AH54: FALSE | AI54: FALSE | AJ54: TRUE | AK54: FALSE | AL54: FALSE | AM54: FALSE | AN54: 20 | AO54: 0 | AP54: T1 | AS54: thap | AT54: c_ram;c_ram.centurion | AU54: 2 | AV54: c_ram:0;c_ram.centurion:0 | AW54: 0 | AX54: FALSE | AZ54: =IF(AND($AX$54,$AW$54>$AA$54/$Z$54),$AW$54,$AA$54/$Z$54) | BA54: 0.084210526 | BB54: 4500 | BD54: aa | BE54: Wikipedia 'Phalanx CIWS': 4,500 rpm (C-RAM) | BG54: giong | CT54: 20 | CW54: 200 | CX54: 3.02 | DD54: 0.02 | DE54: 2 | DF54: Fragmentation | DJ54: autocannon | DS54: Small | DU54: TRUE | EB54: 1 | EH54: Bullet | EK54: 380 | EP54: 32 | EQ54: Phalanx M61 20 mm | EX54: 20 | EY54: 1.2 | EZ54: 1.2 | FW54: Air | GB54: cal_20 | GD54: Assets/MachineBrigade/Resources/Data/balance.json: weapons[107] | GE54: {"id":"c_ram_gatling","weaponFamilyId":"cal_20","real":"Phalanx M61 20 mm","family":"autocannon","size":20,"caliberMm":20,"pen":1,"damageType":"Fragmentation","damage":2,"cooldown":0.02,"range":32,"projectileSpeed":380,"splash":1.2,"spread":1.2,"impactTier":"Small","projectile":"Bullet","targets":"Air","interceptOnly":true,"clip":200,"clipReload":3.02}
A55: casemate_155 | B55: M284 155 mm (casemate) | C55: cal_152_155 | E55: m284_155_mm_casemate | F55: howitzer | G55: 155 | K55: HighExplosive | L55: 3 | M55: Shell | N55: 1 | O55: RIPPLE | P55: 1 | Q55: 0.1 | R55: 12.81 | S55: 0 | T55: 0 | U55: 0 | V55: 0 | W55: 620 | X55: 8 | Y55: 16 | Z55: 100 | AA55: 75 | AB55: 20 | AC55: Ground | AE55: 4.5 | AF55: Huge | AG55: FALSE | AH55: FALSE | AI55: FALSE | AJ55: FALSE | AK55: FALSE | AL55: FALSE | AM55: FALSE | AN55: 155 | AO55: 0 | AP55: T3 | AQ55: gun_155_sph | AR55: casemate_155_guided | AS55: boss_part | AT55: casemate_155 | AU55: 1 | AV55: casemate_155:part | AW55: 0 | AX55: FALSE | AZ55: =IF(AND($AX$55,$AW$55>$AA$55/$Z$55),$AW$55,$AA$55/$Z$55) | BA55: 0.75 | BB55: 4 | BC55: 1 | BD55: gun | BE55: US Army M109A7 fact file: 4 rpm for 3 min, 1 rpm sustained | BG55: doi | BH55: 320 | BI55: 620 | BN55: 7 | BO55: 8 | BP55: 0 | BQ55: 16 | BR55: 45 | BS55: 100 | CN55: 0 | CT55: 155 | DE55: 620 | DG55: 16 | DJ55: howitzer | DT55: gun_155_sph | DZ55: 20 | EB55: 3 | EP55: 75 | EQ55: M284 155 mm (casemate) | ER55: 0 | EX55: 155 | GA55: m284_155_mm_casemate | GD55: Assets/MachineBrigade/Resources/Data/balance.json: weapons[267] | GE55: {"id":"casemate_155","weaponFamily":"m284_155_mm_casemate","inherits":"gun_155_sph","real":"M284 155 mm (casemate)","family":"howitzer","size":155,"caliberMm":155,"pen":3,"damage":620,"edge":16,"range":75,"minRange":20,"ammo":0,"reload":0}
A56: casemate_155_guided | B56: M284 155 mm guided (casemate) | C56: cal_152_155 | D56: guided | E56: m284_155_mm_guided | F56: howitzer | G56: 155 | K56: HighExplosive | L56: 3 | M56: Shell | N56: 1 | O56: RIPPLE | P56: 1 | Q56: 0.1 | R56: 12.81 | S56: 0 | T56: 0 | U56: 0 | V56: 0 | W56: 620 | X56: 7 | Y56: 16 | Z56: 45 | AA56: 75 | AB56: 20 | AC56: Ground | AE56: 0 | AF56: Huge | AG56: FALSE | AH56: FALSE | AI56: FALSE | AJ56: FALSE | AK56: FALSE | AL56: FALSE | AM56: TRUE | AN56: 155 | AO56: 0 | AP56: T3 | AQ56: casemate_155 | AU56: 0 | AW56: 0 | AX56: FALSE | AZ56: =IF(AND($AX$56,$AW$56>$AA$56/$Z$56),$AW$56,$AA$56/$Z$56) | BA56: 1.6666667 | BB56: 4 | BC56: 1 | BD56: gun | BE56: US Army M109A7 fact file: 4 rpm for 3 min, 1 rpm sustained | BG56: doi | BH56: 320 | BI56: 620 | BP56: 0 | BQ56: 16 | CR56: 1 | DE56: 620 | DF56: HighExplosive | DH56: TRUE | DM56: armour | DN56: HeShell | DP56: TRUE | DT56: casemate_155 | EB56: 3 | EQ56: M284 155 mm guided (casemate) | ES56: guided | EU56: casemate_155 | EZ56: 0 | FW56: Ground | GA56: m284_155_mm_guided | GC56: guided | GD56: Assets/MachineBrigade/Resources/Data/balance.json: secondRounds.rounds[14] | GE56: {"id":"casemate_155_guided","roundOf":"casemate_155","inherits":"casemate_155","weaponVariantId":"guided","weaponFamily":"m284_155_mm_guided","round":"guided","for":["armour"],"elite":true,"real":"M284 155 mm guided (casemate)","damageType":"HighExplosive","pen":3,"damage":620,"spread":0,"burst":1,"guided":true,"form":"HeShell","targets":"Ground"}
A57: ciws_aa | B57: AK-630 30 mm | C57: cal_30 | D57: ciws | E57: ak_630_30_mm | F57: autocannon | G57: 30 | K57: Kinetic | L57: 2 | M57: Bullet | N57: 1 | O57: RIPPLE | P57: 1 | Q57: 0.1 | R57: 0.0167 | S57: 60 | T57: 5.0167 | U57: 0 | V57: 0 | W57: 12 | X57: 0 | Y57: 0 | Z57: 300 | AA57: 34 | AB57: 0 | AC57: Air | AE57: 1.3 | AF57: Small | AG57: FALSE | AH57: FALSE | AI57: FALSE | AJ57: FALSE | AK57: FALSE | AL57: FALSE | AM57: FALSE | AN57: 30 | AO57: 0 | AP57: T1 | AQ57: hover_ciws | AR57: ciws_aa_flak | AS57: boss | AT57: landing_hovercraft | AU57: 1 | AV57: landing_hovercraft:2 | AW57: 0 | AX57: FALSE | AZ57: =IF(AND($AX$57,$AW$57>$AA$57/$Z$57),$AW$57,$AA$57/$Z$57) | BA57: 0.11333333 | BB57: 5000 | BC57: 1000 | BD57: aa | BE57: Wikipedia 'AK-630': 4,000-5,000 rpm, 2,000-round belt | BG57: giong | CT57: 30 | DJ57: autocannon | DT57: hover_ciws | EB57: 2 | EQ57: AK-630 30 mm | EX57: 30 | FW57: Air | GA57: ak_630_30_mm | GD57: Assets/MachineBrigade/Resources/Data/balance.json: weapons[258] | GE57: {"id":"ciws_aa","weaponFamily":"ak_630_30_mm","real":"AK-630 30 mm","family":"autocannon","size":30,"caliberMm":30,"pen":2,"inherits":"hover_ciws","targets":"Air"}
A58: ciws_aa_flak | B58: AK-630 30 mm air-burst | C58: cal_30 | D58: flak | E58: ak_630_30_mm_air_burst | F58: autocannon | G58: 30 | K58: Fragmentation | L58: 2 | M58: Bullet | N58: 1 | O58: RIPPLE | P58: 1 | Q58: 0.1 | R58: 0.0167 | S58: 60 | T58: 5.0167 | U58: 0 | V58: 0 | W58: 12 | X58: 2.5 | Y58: 0 | Z58: 300 | AA58: 34 | AB58: 0 | AC58: Air | AE58: 1.3 | AF58: Small | AG58: FALSE | AH58: FALSE | AI58: FALSE | AJ58: FALSE | AK58: FALSE | AL58: FALSE | AM58: FALSE | AN58: 30 | AO58: 0 | AP58: T1 | AQ58: ciws_aa | AU58: 0 | AW58: 0 | AX58: FALSE | AZ58: =IF(AND($AX$58,$AW$58>$AA$58/$Z$58),$AW$58,$AA$58/$Z$58) | BA58: 0.11333333 | BB58: 5000 | BC58: 1000 | BD58: aa | BE58: Wikipedia 'AK-630': 4,000-5,000 rpm, 2,000-round belt | BG58: giong | DE58: 12 | DF58: Fragmentation | DM58: air | DN58: Airburst | DT58: ciws_aa | EB58: 2 | EE58: FALSE | EQ58: AK-630 30 mm air-burst | ES58: flak | EU58: ciws_aa | EY58: 2.5 | FW58: Air | GA58: ak_630_30_mm_air_burst | GC58: flak | GD58: Assets/MachineBrigade/Resources/Data/balance.json: secondRounds.rounds[15] | GE58: {"id":"ciws_aa_flak","roundOf":"ciws_aa","inherits":"ciws_aa","weaponVariantId":"flak","weaponFamily":"ak_630_30_mm_air_burst","round":"flak","for":["air"],"real":"AK-630 30 mm air-burst","damageType":"Fragmentation","pen":2,"damage":12,"splash":2.5,"form":"Airburst","piercing":false,"targets":"Air"}
A59: coilgun | B59: coilgun (10 MJ) | C59: rail_coilgun | F59: railgun | J59: 10 | K59: Kinetic | L59: 4 | M59: Bullet | N59: 1 | O59: RIPPLE | P59: 2 | Q59: 0.25 | R59: 4.54 | S59: 0 | T59: 0 | U59: 0 | V59: 0 | W59: 250 | X59: 0 | Y59: 0 | Z59: 420 | AA59: 55 | AB59: 0 | AC59: All | AE59: 0.6 | AF59: Large | AG59: FALSE | AH59: FALSE | AI59: FALSE | AJ59: FALSE | AK59: FALSE | AL59: FALSE | AM59: FALSE | AN59: 10 | AO59: 0 | AP59: T3 | AS59: boss | AT59: behemoth_tempest | AU59: 1 | AV59: behemoth_tempest:1;behemoth_tempest:2 | AW59: 0 | AX59: FALSE | AZ59: =IF(AND($AX$59,$AW$59>$AA$59/$Z$59),$AW$59,$AA$59/$Z$59) | BA59: 0.13095238 | BB59: NEED_SOURCE | BC59: NEED_SOURCE | BE59: NEED_SOURCE | BG59: giong | CR59: 2 | CS59: 0.25 | CV59: 0.5 | DD59: 4.54 | DE59: 250 | DF59: Kinetic | DI59: 10 | DJ59: railgun | DO59: 17 | DS59: Large | EB59: 4 | EE59: TRUE | EH59: Bullet | EK59: 420 | EP59: 55 | EQ59: coilgun (10 MJ) | EX59: 10 | EZ59: 0.6 | FW59: All | GB59: rail_coilgun | GD59: Assets/MachineBrigade/Resources/Data/balance.json: weapons[133] | GE59: {"id":"coilgun","groundMinReach":17,"weaponFamilyId":"rail_coilgun","real":"coilgun (10 MJ)","family":"railgun","size":10,"energyMj":10,"pen":4,"piercing":true,"charge":0.5,"damageType":"Kinetic","damage":250,"cooldown":4.54,"range":55,"projectileSpeed":420,"spread":0.6,"impactTier":"Large","projectile":"Bullet","targets":"All","burst":2,"burstInterval":0.25}
A60: cruise_missile_ground | B60: Typhon MRC (ground-launched Tomahawk) | C60: cruise_typhon_mrc | F60: cruise_missile | H60: 450 | K60: ShapedCharge | L60: 4 | M60: Missile | N60: 1 | O60: RIPPLE | P60: 1 | Q60: 0.1 | R60: 15 | S60: 2 | T60: 30 | U60: 0 | V60: 0 | W60: 450 | X60: 0 | Y60: 0 | Z60: 70 | AA60: 180 | AB60: 0 | AC60: All | AE60: 0 | AF60: Huge | AG60: FALSE | AH60: FALSE | AI60: FALSE | AJ60: FALSE | AK60: FALSE | AL60: FALSE | AM60: FALSE | AN60: 450 | AO60: 0 | AP60: T4 | AS60: xe | AT60: ground_cruise_missile_vehicle | AU60: 1 | AV60: ground_cruise_missile_vehicle:0 | AW60: 2.5 | AX60: FALSE | AZ60: =IF(AND($AX$60,$AW$60>$AA$60/$Z$60),$AW$60,$AA$60/$Z$60) | BA60: 2.5714286 | BB60: 20 | BC60: 6 | BD60: missile | BE60: cruise missiles: ~3 s between launches (est.) | BG60: doi | BR60: 22 | BS60: 70 | CW60: 2 | CX60: 30 | DD60: 15 | DE60: 450 | DF60: ShapedCharge | DJ60: cruise_missile | DL60: Loft | DS60: Huge | EB60: 4 | EH60: Missile | EK60: 70 | EP60: 180 | EQ60: Typhon MRC (ground-launched Tomahawk) | EX60: 450 | FW60: All | FZ60: 450 | GB60: cruise_typhon_mrc | GD60: Assets/MachineBrigade/Resources/Data/balance.json: weapons[287] | GE60: {"id":"cruise_missile_ground","flightProfile":"Loft","weaponFamilyId":"cruise_typhon_mrc","real":"Typhon MRC (ground-launched Tomahawk)","family":"cruise_missile","size":450,"warheadKg":450,"pen":4,"damageType":"ShapedCharge","damage":450,"cooldown":15,"range":180,"projectileSpeed":70,"impactTier":"Huge","projectile":"Missile","targets":"All","clip":2,"clipReload":30}
A61: cruiser_203 | B61: Mk 71 203 mm (twin) | C61: cal_203 | F61: howitzer | G61: 203 | K61: HighExplosive | L61: 4 | M61: Shell | N61: 2 | O61: SIMULTANEOUS | P61: 1 | Q61: 0.4 | R61: 16.857 | S61: 0 | T61: 0 | U61: 0 | V61: 0 | W61: 600 | X61: 8 | Y61: 0 | Z61: 110 | AA61: 105 | AB61: 0 | AC61: Ground | AE61: 2.6 | AF61: Huge | AG61: FALSE | AH61: FALSE | AI61: FALSE | AJ61: FALSE | AK61: FALSE | AL61: FALSE | AM61: FALSE | AN61: 203 | AO61: 0 | AP61: T4 | AQ61: naval_76 | AR61: cruiser_203_guided | AS61: xe | AT61: sea_cruiser | AU61: 1 | AV61: sea_cruiser:0;sea_cruiser:1 | AW61: 2.5 | AX61: TRUE | AZ61: =IF(AND($AX$61,$AW$61>$AA$61/$Z$61),$AW$61,$AA$61/$Z$61) | BA61: 2.5 | BB61: 12 | BC61: 12 | BD61: gun | BE61: Wikipedia '8"/55 caliber Mark 71': 12 rpm | BG61: doi | BH61: 420 | BI61: 600 | BJ61: 11.4 | BK61: 16.857 | BR61: 70 | BS61: 110 | BT61: 2 | BU61: 1 | BX61: 1 | BY61: 2 | BZ61: RIPPLE | CA61: SIMULTANEOUS | CO61: 2 | CR61: 1 | CS61: 0.4 | CT61: 203 | DD61: 16.857 | DE61: 600 | DJ61: howitzer | DS61: Huge | DT61: naval_76 | EB61: 4 | EI61: shell_155 | EJ61: 0.9455 | EK61: 110 | EP61: 105 | EQ61: Mk 71 203 mm (twin) | ET61: 1.04 | EW61: SIMULTANEOUS | EX61: 203 | EY61: 8 | EZ61: 2.6 | GB61: cal_203 | GD61: Assets/MachineBrigade/Resources/Data/balance.json: weapons[252] | GE61: {"id":"cruiser_203","inherits":"naval_76","weaponFamilyId":"cal_203","salvoMode":"SIMULTANEOUS","barrels":2,"real":"Mk 71 203 mm (twin)","family":"howitzer","size":203,"caliberMm":203,"pen":4,"projectileModel":"shell_155","roundLength":1.04,"projectileScale":0.9455,"damage":600,"cooldown":16.857,"range":105,"projectileSpeed":110,"splash":8,"spread":2.6,"impactTier":"Huge","burst":1,"burstInterval":0.4}
A62: cruiser_203_guided | B62: Mk 71 203 mm guided (twin) | C62: cal_203 | F62: howitzer | G62: 203 | K62: HighExplosive | L62: 4 | M62: Shell | N62: 1 | O62: RIPPLE | P62: 1 | Q62: 0.4 | R62: 16.857 | S62: 0 | T62: 0 | U62: 0 | V62: 0 | W62: 600 | X62: 8 | Y62: 0 | Z62: 110 | AA62: 105 | AB62: 0 | AC62: Ground | AE62: 0 | AF62: Huge | AG62: FALSE | AH62: FALSE | AI62: FALSE | AJ62: FALSE | AK62: FALSE | AL62: FALSE | AM62: TRUE | AN62: 203 | AO62: 0 | AP62: T4 | AQ62: cruiser_203 | AU62: 0 | AW62: 2.5 | AX62: TRUE | AZ62: =IF(AND($AX$62,$AW$62>$AA$62/$Z$62),$AW$62,$AA$62/$Z$62) | BA62: 2.5 | BB62: 12 | BC62: 12 | BD62: gun | BE62: Wikipedia '8"/55 caliber Mark 71': 12 rpm | BG62: doi | BH62: 420 | BI62: 600 | BJ62: 11.4 | BK62: 16.857 | BR62: 70 | BS62: 110 | CO62: 1 | CR62: 1 | DE62: 600 | DF62: HighExplosive | DH62: TRUE | DM62: armour | DN62: HeShell | DP62: TRUE | DT62: cruiser_203 | EB62: 4 | EQ62: Mk 71 203 mm guided (twin) | ES62: guided | EU62: cruiser_203 | EW62: RIPPLE | EZ62: 0 | FW62: Ground | GD62: Assets/MachineBrigade/Resources/Data/balance.json: secondRounds.rounds[16] | GE62: {"id":"cruiser_203_guided","roundOf":"cruiser_203","inherits":"cruiser_203","salvoMode":"RIPPLE","barrels":1,"weaponFamily":"","round":"guided","for":["armour"],"elite":true,"real":"Mk 71 203 mm guided (twin)","damageType":"HighExplosive","pen":4,"damage":600,"spread":0,"burst":1,"guided":true,"form":"HeShell","targets":"Ground"}
A63: detonator | B63: car bomb (900 kg) | C63: bomb_car_bomb | F63: bomb | H63: 900 | K63: HighExplosive | L63: 4 | M63: Shell | N63: 1 | O63: RIPPLE | P63: 1 | Q63: 0.1 | R63: 1 | S63: 0 | T63: 0 | U63: 0 | V63: 0 | W63: 770 | X63: 10 | Y63: 0 | Z63: 100 | AA63: 3 | AB63: 0 | AC63: Ground | AE63: 0 | AF63: Ultimate | AG63: FALSE | AH63: FALSE | AI63: FALSE | AJ63: FALSE | AK63: FALSE | AL63: FALSE | AM63: FALSE | AN63: 900 | AO63: 0 | AP63: T4 | AS63: xe | AT63: vbied | AU63: 1 | AV63: vbied:0 | AW63: 2.7222222 | AX63: TRUE | AZ63: =IF(AND($AX$63,$AW$63>$AA$63/$Z$63),$AW$63,$AA$63/$Z$63) | BA63: 2.7222222 | BB63: 600 | BD63: bomb | BE63: a stick's release, 0.1 s and up (est.) | BG63: giong | DD63: 1 | DE63: 770 | DF63: HighExplosive | DJ63: bomb | DN63: CarBomb | DS63: Ultimate | EB63: 4 | EK63: 100 | EP63: 3 | EQ63: car bomb (900 kg) | EX63: 900 | EY63: 10 | FZ63: 900 | GB63: bomb_car_bomb | GD63: Assets/MachineBrigade/Resources/Data/balance.json: weapons[72] | GE63: {"id":"detonator","weaponFamilyId":"bomb_car_bomb","real":"car bomb (900 kg)","family":"bomb","size":900,"warheadKg":900,"pen":4,"form":"CarBomb","damageType":"HighExplosive","damage":770,"cooldown":1,"range":3,"projectileSpeed":100,"splash":10,"impactTier":"Ultimate","bonuses":[{"armor":"Structure","mult":0.5}]}
A64: dozer_blade | B64: dozer blade | C64: melee_dozer_blade | F64: melee | K64: Kinetic | L64: 3 | M64: Bullet | N64: 1 | O64: RIPPLE | P64: 1 | Q64: 0.1 | R64: 1.6 | S64: 0 | T64: 0 | U64: 0 | V64: 0 | W64: 110 | X64: 0 | Y64: 0 | Z64: 400 | AA64: 4 | AB64: 0 | AC64: Ground | AE64: 0 | AF64: Medium | AG64: FALSE | AH64: FALSE | AI64: FALSE | AJ64: FALSE | AK64: FALSE | AL64: FALSE | AM64: FALSE | AN64: 1 | AO64: 0 | AP64: T0 | AS64: xe | AT64: armored_bulldozer | AU64: 1 | AV64: armored_bulldozer:0 | AW64: 0 | AX64: FALSE | AZ64: =IF(AND($AX$64,$AW$64>$AA$64/$Z$64),$AW$64,$AA$64/$Z$64) | BA64: 0.01 | BB64: NEED_SOURCE | BC64: NEED_SOURCE | BE64: NEED_SOURCE | BG64: giong | DD64: 1.6 | DE64: 110 | DF64: Kinetic | DJ64: melee | DS64: Medium | DY64: TRUE | EB64: 3 | EE64: TRUE | EH64: Bullet | EK64: 400 | EP64: 4 | EQ64: dozer blade | EX64: 1 | FW64: Ground | GB64: melee_dozer_blade | GD64: Assets/MachineBrigade/Resources/Data/balance.json: weapons[104] | GE64: {"id":"dozer_blade","weaponFamilyId":"melee_dozer_blade","real":"dozer blade","family":"melee","size":1,"pen":3,"piercing":true,"melee":true,"damageType":"Kinetic","damage":110,"cooldown":1.6,"range":4,"projectileSpeed":400,"impactTier":"Medium","projectile":"Bullet","targets":"Ground","bonuses":[{"armor":"Structure","mult":3},{"armor":"Heavy","mult":0.4},{"armor":"Light","mult":0.55}]}
A65: drone_gun | B65: M3P 12.7 mm | C65: cal_12_7 | F65: mg | G65: 12.7 | K65: Kinetic | L65: 1 | M65: Bullet | N65: 1 | O65: RIPPLE | P65: 1 | Q65: 0.1 | R65: 0.158 | S65: 0 | T65: 0 | U65: 0 | V65: 0 | W65: 9.5 | X65: 0 | Y65: 0 | Z65: 220 | AA65: 26 | AB65: 0 | AC65: Ground | AE65: 1.4 | AF65: Small | AG65: FALSE | AH65: FALSE | AI65: FALSE | AJ65: FALSE | AK65: FALSE | AL65: FALSE | AM65: FALSE | AN65: 12.7 | AO65: 0 | AP65: T0 | AU65: 0 | AW65: 0 | AX65: FALSE | AZ65: =IF(AND($AX$65,$AW$65>$AA$65/$Z$65),$AW$65,$AA$65/$Z$65) | BA65: 0.11818182 | BB65: 1200 | BC65: 200 | BD65: mg | BE65: Wikipedia 'M3 Browning' (AN/M3): 1,100-1,250 rpm | BG65: giong | CT65: 12.7 | DD65: 0.158 | DE65: 9.5 | DF65: Kinetic | DJ65: mg | DS65: Small | EB65: 1 | EH65: Bullet | EK65: 220 | EP65: 26 | EQ65: M3P 12.7 mm | EV65: 12 | EX65: 12.7 | EZ65: 1.4 | GB65: cal_12_7 | GD65: Assets/MachineBrigade/Resources/Data/balance.json: weapons[238] | GE65: {"id":"drone_gun","weaponFamilyId":"cal_12_7","real":"M3P 12.7 mm","family":"mg","size":12.7,"caliberMm":12.7,"pen":1,"damageType":"Kinetic","damage":9.5,"cooldown":0.158,"range":26,"projectileSpeed":220,"spread":1.4,"impactTier":"Small","projectile":"Bullet","roundWeight":12}
A66: drone_missile | B66: AGM-114 Hellfire | C66: atgm_agm_114_hellfire | E66: agm_114_hellfire | F66: atgm | H66: 9 | K66: ShapedCharge | L66: 4 | M66: Missile | N66: 1 | O66: RIPPLE | P66: 1 | Q66: 0.1 | R66: 3.58 | S66: 0 | T66: 0 | U66: 0 | V66: 0 | W66: 260 | X66: 0 | Y66: 0 | Z66: 110 | AA66: 48 | AB66: 0 | AC66: Ground | AE66: 0 | AF66: Medium | AG66: FALSE | AH66: FALSE | AI66: FALSE | AJ66: FALSE | AK66: FALSE | AL66: FALSE | AM66: FALSE | AN66: 49 | AO66: 3 | AP66: T2 | AS66: xe | AT66: strike_drone | AU66: 1 | AV66: strike_drone:0 | AW66: 0 | AX66: FALSE | AZ66: =IF(AND($AX$66,$AW$66>$AA$66/$Z$66),$AW$66,$AA$66/$Z$66) | BA66: 0.43636364 | BB66: 60 | BC66: 10 | BD66: atgm | BE66: air-launched: ripples ~1 s apart, est. 6 s an aimed shot | BG66: doi | BR66: 26 | BS66: 110 | DD66: 3.58 | DE66: 260 | DF66: ShapedCharge | DJ66: atgm | DS66: Medium | DW66: 3 | EB66: 4 | EE66: TRUE | EH66: Missile | EJ66: 0.65 | EP66: 48 | EQ66: AGM-114 Hellfire | EX66: 49 | FZ66: 9 | GA66: agm_114_hellfire | GB66: atgm_agm_114_hellfire | GD66: Assets/MachineBrigade/Resources/Data/balance.json: weapons[41] | GE66: {"id":"drone_missile","weaponFamilyId":"atgm_agm_114_hellfire","weaponFamily":"agm_114_hellfire","load":3,"real":"AGM-114 Hellfire","family":"atgm","size":49,"warheadKg":9,"pen":4,"piercing":true,"projectileScale":0.65,"damageType":"ShapedCharge","damage":260,"cooldown":3.58,"range":48,"impactTier":"Medium","projectile":"Missile","bonuses":[{"armor":"Structure","mult":1.5}]}
A67: fighter_cannon | B67: GAU-22/A 25 mm | C67: cal_25 | D67: flak | F67: autocannon | G67: 25 | K67: Fragmentation | L67: 2 | M67: Bullet | N67: 1 | O67: RIPPLE | P67: 1 | Q67: 0.1 | R67: 0.1151 | S67: 44 | T67: 1 | U67: 0 | V67: 0 | W67: 18 | X67: 0 | Y67: 0 | Z67: 320 | AA67: 30 | AB67: 0 | AC67: All | AE67: 1.5 | AF67: Small | AG67: FALSE | AH67: FALSE | AI67: FALSE | AJ67: FALSE | AK67: FALSE | AL67: FALSE | AM67: FALSE | AN67: 25 | AO67: 0 | AP67: T1 | AR67: fighter_cannon_ap | AS67: xe | AT67: fighter_jet;stealth_fighter | AU67: 2 | AV67: fighter_jet:2;stealth_fighter:2 | AW67: 0 | AX67: FALSE | AZ67: =IF(AND($AX$67,$AW$67>$AA$67/$Z$67),$AW$67,$AA$67/$Z$67) | BA67: 0.09375 | BB67: 3300 | BD67: ac | BE67: Wikipedia 'GAU-22/A': 3,300 rpm | BG67: giong | CT67: 25 | CW67: 44 | CX67: 1 | DD67: 0.1151 | DE67: 18 | DF67: Fragmentation | DJ67: autocannon | DN67: BeltedAutocannon | DS67: Small | EB67: 2 | EH67: Bullet | EK67: 320 | EP67: 30 | EQ67: GAU-22/A 25 mm | EV67: 30 | EX67: 25 | EZ67: 1.5 | FW67: All | GB67: cal_25 | GC67: flak | GD67: Assets/MachineBrigade/Resources/Data/balance.json: weapons[80] | GE67: {"id":"fighter_cannon","weaponFamilyId":"cal_25","weaponVariantId":"flak","real":"GAU-22/A 25 mm","family":"autocannon","size":25,"caliberMm":25,"pen":2,"form":"BeltedAutocannon","damageType":"Fragmentation","damage":18,"cooldown":0.1151,"range":30,"projectileSpeed":320,"spread":1.5,"impactTier":"Small","projectile":"Bullet","targets":"All","clip":44,"clipReload":1,"roundWeight":30}
A68: fighter_cannon_ap | B68: GAU-22/A 25 mm AP | C68: cal_25 | F68: autocannon | G68: 25 | K68: Kinetic | L68: 2 | M68: Bullet | N68: 1 | O68: RIPPLE | P68: 1 | Q68: 0.1 | R68: 0.1151 | S68: 44 | T68: 1 | U68: 0 | V68: 0 | W68: 18 | X68: 0 | Y68: 0 | Z68: 320 | AA68: 30 | AB68: 0 | AC68: Ground | AE68: 1.5 | AF68: Small | AG68: FALSE | AH68: FALSE | AI68: FALSE | AJ68: FALSE | AK68: FALSE | AL68: FALSE | AM68: FALSE | AN68: 25 | AO68: 0 | AP68: T1 | AQ68: fighter_cannon | AU68: 0 | AW68: 0 | AX68: FALSE | AZ68: =IF(AND($AX$68,$AW$68>$AA$68/$Z$68),$AW$68,$AA$68/$Z$68) | BA68: 0.09375 | BB68: 3300 | BD68: ac | BE68: Wikipedia 'GAU-22/A': 3,300 rpm | BG68: giong | DE68: 18 | DF68: Kinetic | DM68: ground | DN68: BeltedAutocannon | DT68: fighter_cannon | EB68: 2 | EE68: TRUE | EQ68: GAU-22/A 25 mm AP | ES68: ap | EU68: fighter_cannon | EY68: 0 | FW68: Ground | GD68: Assets/MachineBrigade/Resources/Data/balance.json: secondRounds.rounds[17] | GE68: {"id":"fighter_cannon_ap","roundOf":"fighter_cannon","inherits":"fighter_cannon","weaponVariantId":"","weaponFamily":"","round":"ap","for":["ground"],"real":"GAU-22/A 25 mm AP","damageType":"Kinetic","pen":2,"damage":18,"splash":0,"form":"BeltedAutocannon","piercing":true,"targets":"Ground"}
A69: flak_35 | B69: Oerlikon KDA 35 mm (Gepard) | C69: cal_35 | E69: oerlikon_35_mm | F69: autocannon | G69: 35 | K69: Fragmentation | L69: 2 | M69: Bullet | N69: 1 | O69: RIPPLE | P69: 1 | Q69: 0.1 | R69: 0.25 | S69: 22 | T69: 1.25 | U69: 0 | V69: 0 | W69: 26 | X69: 2.5 | Y69: 0 | Z69: 260 | AA69: 36 | AB69: 0 | AC69: All | AE69: 1.5 | AF69: Small | AG69: FALSE | AH69: FALSE | AI69: FALSE | AJ69: FALSE | AK69: FALSE | AL69: FALSE | AM69: FALSE | AN69: 35 | AO69: 0 | AP69: T1 | AR69: flak_35_ap | AS69: xe | AT69: aa_vehicle | AU69: 1 | AV69: aa_vehicle:0 | AW69: 0 | AX69: FALSE | AZ69: =IF(AND($AX$69,$AW$69>$AA$69/$Z$69),$AW$69,$AA$69/$Z$69) | BA69: 0.13846154 | BB69: 550 | BC69: 300 | BD69: aa | BE69: Wikipedia 'Oerlikon GDF' / 'Gepard': 2 x 550 rpm | BG69: giong | CT69: 35 | CW69: 22 | CX69: 1.25 | DD69: 0.25 | DE69: 26 | DF69: Fragmentation | DJ69: autocannon | DS69: Small | EB69: 2 | EH69: Bullet | EP69: 36 | EQ69: Oerlikon KDA 35 mm (Gepard) | EX69: 35 | EZ69: 1.5 | FW69: All | GA69: oerlikon_35_mm | GB69: cal_35 | GD69: Assets/MachineBrigade/Resources/Data/balance.json: weapons[19] | GE69: {"id":"flak_35","weaponFamilyId":"cal_35","weaponFamily":"oerlikon_35_mm","real":"Oerlikon KDA 35 mm (Gepard)","family":"autocannon","size":35,"caliberMm":35,"pen":2,"damageType":"Fragmentation","damage":26,"cooldown":0.25,"range":36,"spread":1.5,"impactTier":"Small","projectile":"Bullet","targets":"All","clip":22,"clipReload":1.25,"bonuses":[{"class":"Plane","mult":1.5}]}
A70: flak_35_ap | B70: Oerlikon 35 mm AP (Gepard) | C70: cal_35 | D70: ap | E70: oerlikon_35_mm_ap | F70: autocannon | G70: 35 | K70: Kinetic | L70: 2 | M70: Bullet | N70: 1 | O70: RIPPLE | P70: 1 | Q70: 0.1 | R70: 0.25 | S70: 22 | T70: 1.25 | U70: 0 | V70: 0 | W70: 26 | X70: 0 | Y70: 0 | Z70: 260 | AA70: 36 | AB70: 0 | AC70: Ground | AE70: 1.5 | AF70: Small | AG70: FALSE | AH70: FALSE | AI70: FALSE | AJ70: FALSE | AK70: FALSE | AL70: FALSE | AM70: FALSE | AN70: 35 | AO70: 0 | AP70: T1 | AQ70: flak_35 | AU70: 0 | AW70: 0 | AX70: FALSE | AZ70: =IF(AND($AX$70,$AW$70>$AA$70/$Z$70),$AW$70,$AA$70/$Z$70) | BA70: 0.13846154 | BB70: 550 | BC70: 300 | BD70: aa | BE70: Wikipedia 'Oerlikon GDF': 550 rpm a gun (the twin: 1,100) | BG70: giong | DE70: 26 | DF70: Kinetic | DM70: ground | DN70: BeltedAutocannon | DT70: flak_35 | EB70: 2 | EE70: TRUE | EQ70: Oerlikon 35 mm AP (Gepard) | ES70: ap | EU70: flak_35 | EY70: 0 | FW70: Ground | GA70: oerlikon_35_mm_ap | GC70: ap | GD70: Assets/MachineBrigade/Resources/Data/balance.json: secondRounds.rounds[18] | GE70: {"id":"flak_35_ap","roundOf":"flak_35","inherits":"flak_35","weaponVariantId":"ap","weaponFamily":"oerlikon_35_mm_ap","round":"ap","for":["ground"],"real":"Oerlikon 35 mm AP (Gepard)","damageType":"Kinetic","pen":2,"damage":26,"splash":0,"form":"BeltedAutocannon","piercing":true,"targets":"Ground","bonuses":[]}
A71: flak_quad | B71: ZSU-23-4 23 mm (quad) | C71: cal_23 | F71: autocannon | G71: 23 | K71: Fragmentation | L71: 1 | M71: Bullet | N71: 1 | O71: RIPPLE | P71: 1 | Q71: 0.1 | R71: 0.0324 | S71: 54 | T71: 1.5 | U71: 0 | V71: 0 | W71: 14 | X71: 3.5 | Y71: 0 | Z71: 300 | AA71: 46 | AB71: 0 | AC71: All | AE71: 1.6 | AF71: Medium | AG71: FALSE | AH71: FALSE | AI71: FALSE | AJ71: FALSE | AK71: FALSE | AL71: FALSE | AM71: FALSE | AN71: 23 | AO71: 0 | AP71: T1 | AR71: flak_quad_ap | AS71: thap | AT71: aa_turret.flak | AU71: 1 | AV71: aa_turret.flak:0 | AW71: 0 | AX71: FALSE | AZ71: =IF(AND($AX$71,$AW$71>$AA$71/$Z$71),$AW$71,$AA$71/$Z$71) | BA71: 0.15333333 | BB71: 1000 | BC71: 400 | BD71: aa | BE71: Wikipedia 'ZSU-23-4 Shilka': 4 x 850-1,000 rpm | BG71: giong | CT71: 23 | CW71: 54 | CX71: 1.5 | DD71: 0.0324 | DE71: 14 | DF71: Fragmentation | DJ71: autocannon | DS71: Medium | EB71: 1 | EH71: Bullet | EK71: 300 | EP71: 46 | EQ71: ZSU-23-4 23 mm (quad) | EV71: 22 | EX71: 23 | EY71: 3.5 | EZ71: 1.6 | FW71: All | GB71: cal_23 | GD71: Assets/MachineBrigade/Resources/Data/balance.json: weapons[86] | GE71: {"id":"flak_quad","weaponFamilyId":"cal_23","real":"ZSU-23-4 23 mm (quad)","family":"autocannon","size":23,"caliberMm":23,"pen":1,"damageType":"Fragmentation","damage":14,"cooldown":0.0324,"range":46,"projectileSpeed":300,"splash":3.5,"spread":1.6,"impactTier":"Medium","projectile":"Bullet","targets":"All","clip":54,"clipReload":1.5,"roundWeight":22}
A72: flak_quad_ap | B72: ZSU-23-4 23 mm AP (quad) | C72: cal_23 | F72: autocannon | G72: 23 | K72: Kinetic | L72: 2 | M72: Bullet | N72: 1 | O72: RIPPLE | P72: 1 | Q72: 0.1 | R72: 0.0324 | S72: 54 | T72: 1.5 | U72: 0 | V72: 0 | W72: 14 | X72: 0 | Y72: 0 | Z72: 300 | AA72: 46 | AB72: 0 | AC72: Ground | AE72: 1.6 | AF72: Medium | AG72: FALSE | AH72: FALSE | AI72: FALSE | AJ72: FALSE | AK72: FALSE | AL72: FALSE | AM72: FALSE | AN72: 23 | AO72: 0 | AP72: T1 | AQ72: flak_quad | AU72: 0 | AW72: 0 | AX72: FALSE | AZ72: =IF(AND($AX$72,$AW$72>$AA$72/$Z$72),$AW$72,$AA$72/$Z$72) | BA72: 0.15333333 | BB72: 1000 | BC72: 400 | BD72: aa | BE72: Wikipedia 'ZSU-23-4 Shilka': 4 x 850-1,000 rpm | BG72: giong | DE72: 14 | DF72: Kinetic | DM72: ground | DN72: BeltedAutocannon | DT72: flak_quad | EB72: 2 | EE72: TRUE | EQ72: ZSU-23-4 23 mm AP (quad) | ES72: ap | EU72: flak_quad | EY72: 0 | FW72: Ground | GD72: Assets/MachineBrigade/Resources/Data/balance.json: secondRounds.rounds[19] | GE72: {"id":"flak_quad_ap","roundOf":"flak_quad","inherits":"flak_quad","weaponFamily":"","round":"ap","for":["ground"],"real":"ZSU-23-4 23 mm AP (quad)","damageType":"Kinetic","pen":2,"damage":14,"splash":0,"form":"BeltedAutocannon","piercing":true,"targets":"Ground"}
A73: flamethrower | B73: flamethrower | C73: flame_flamethrower | F73: flame | K73: Fire | L73: 1 | M73: Flame | N73: 1 | O73: RIPPLE | P73: 1 | Q73: 0.1 | R73: 0.25 | S73: 0 | T73: 0 | U73: 0 | V73: 0 | W73: 21 | X73: 2.5 | Y73: 0 | Z73: 36 | AA73: 13 | AB73: 0 | AC73: Ground | AE73: 1.2 | AF73: Small | AG73: FALSE | AH73: FALSE | AI73: FALSE | AJ73: FALSE | AK73: FALSE | AL73: FALSE | AM73: FALSE | AN73: 1 | AO73: 0 | AP73: T1 | AS73: xe | AT73: flame_tank | AU73: 1 | AV73: flame_tank:0 | AW73: 0 | AX73: FALSE | AZ73: =IF(AND($AX$73,$AW$73>$AA$73/$Z$73),$AW$73,$AA$73/$Z$73) | BA73: 0.36111111 | BB73: NEED_SOURCE | BC73: NEED_SOURCE | BE73: NEED_SOURCE | BG73: giong | DD73: 0.25 | DE73: 21 | DF73: Fire | DJ73: flame | DS73: Small | EB73: 1 | EH73: Flame | EK73: 36 | EP73: 13 | EQ73: flamethrower | EX73: 1 | EY73: 2.5 | EZ73: 1.2 | GB73: flame_flamethrower | GD73: Assets/MachineBrigade/Resources/Data/balance.json: weapons[15] | GE73: {"id":"flamethrower","weaponFamilyId":"flame_flamethrower","real":"flamethrower","family":"flame","size":1,"pen":1,"damageType":"Fire","damage":21,"cooldown":0.25,"range":13,"projectileSpeed":36,"splash":2.5,"spread":1.2,"impactTier":"Small","projectile":"Flame"}
A74: focus_laser | B74: focused laser (300 kW) | C74: laser_focused_laser | F74: laser | I74: 300 | K74: Energy | L74: 4 | M74: Bullet | N74: 1 | O74: RIPPLE | P74: 1 | Q74: 0.1 | R74: 0.1 | S74: 80 | T74: 1.5 | U74: 0 | V74: 0 | W74: 12.5 | X74: 0 | Y74: 0 | Z74: 3000 | AA74: 40 | AB74: 0 | AC74: Ground | AE74: 0 | AF74: Small | AG74: FALSE | AH74: FALSE | AI74: FALSE | AJ74: FALSE | AK74: FALSE | AL74: TRUE | AM74: FALSE | AN74: 300 | AO74: 0 | AP74: T1 | AS74: xe | AT74: laser_tank | AU74: 1 | AV74: laser_tank:0 | AW74: 0 | AX74: FALSE | AZ74: =IF(AND($AX$74,$AW$74>$AA$74/$Z$74),$AW$74,$AA$74/$Z$74) | BA74: 0.013333333 | BB74: NEED_SOURCE | BC74: NEED_SOURCE | BE74: NEED_SOURCE | BG74: giong | CP74: TRUE | CW74: 80 | CX74: 1.5 | DD74: 0.1 | DE74: 12.5 | DF74: Energy | DJ74: laser | DS74: Small | EB74: 4 | EF74: 300 | EH74: Bullet | EK74: 3000 | EL74: 0.3 | EM74: 2 | EN74: 4 | EO74: 2 | EP74: 40 | EQ74: focused laser (300 kW) | EX74: 300 | GB74: laser_focused_laser | GD74: Assets/MachineBrigade/Resources/Data/balance.json: weapons[261] | GE74: {"id":"focus_laser","weaponFamilyId":"laser_focused_laser","real":"focused laser (300 kW)","family":"laser","size":300,"powerKw":300,"pen":4,"damageType":"Energy","damage":12.5,"cooldown":0.1,"range":40,"projectileSpeed":3000,"impactTier":"Small","projectile":"Bullet","beam":true,"clip":80,"clipReload":1.5,"ramp":{"from":0.3,"to":2.0,"seconds":4,"grace":2.0}}
A75: fpv_hangar | B75: FPV drone (1.5 kg) | C75: drone_fpv_drone | E75: fpv_drone | F75: drone | H75: 1.5 | K75: ShapedCharge | L75: 3 | M75: Drone | N75: 1 | O75: RIPPLE | P75: 4 | Q75: 1 | R75: 7.5 | S75: 0 | T75: 0 | U75: 0 | V75: 9 | W75: 140 | X75: 2.5 | Y75: 0 | Z75: 26 | AA75: 70 | AB75: 8 | AC75: Ground | AE75: 0 | AF75: Medium | AG75: TRUE | AH75: FALSE | AI75: FALSE | AJ75: FALSE | AK75: FALSE | AL75: FALSE | AM75: FALSE | AN75: 1.5 | AO75: 0 | AP75: T2 | AQ75: fpv_swarm | AS75: thap | AT75: drone_hangar | AU75: 1 | AV75: drone_hangar:0 | AW75: 0 | AX75: FALSE | AZ75: =IF(AND($AX$75,$AW$75>$AA$75/$Z$75),$AW$75,$AA$75/$Z$75) | BA75: 2.6923077 | BB75: NEED_SOURCE | BC75: NEED_SOURCE | BE75: NEED_SOURCE | BG75: giong | CN75: 0 | CR75: 4 | CS75: 1 | DD75: 7.5 | DJ75: drone | DT75: fpv_swarm | DZ75: 8 | EB75: 3 | EP75: 70 | EQ75: FPV drone (1.5 kg) | EX75: 1.5 | FY75: TRUE | FZ75: 1.5 | GA75: fpv_drone | GD75: Assets/MachineBrigade/Resources/Data/balance.json: weapons[109] | GE75: {"id":"fpv_hangar","weaponFamily":"fpv_drone","real":"FPV drone (1.5 kg)","family":"drone","size":1.5,"warheadKg":1.5,"pen":3,"topAttack":true,"inherits":"fpv_swarm","cooldown":7.5,"range":70,"minRange":8,"burst":4,"burstInterval":1.0,"ammo":0}
A76: fpv_hangar_swarm | B76: FPV drone (1.5 kg) | C76: drone_fpv_drone | E76: fpv_drone | F76: drone | H76: 1.5 | K76: ShapedCharge | L76: 3 | M76: Drone | N76: 1 | O76: RIPPLE | P76: 4 | Q76: 0.6 | R76: 6.1 | S76: 0 | T76: 0 | U76: 0 | V76: 9 | W76: 140 | X76: 2.5 | Y76: 0 | Z76: 26 | AA76: 70 | AB76: 8 | AC76: Ground | AE76: 0 | AF76: Medium | AG76: TRUE | AH76: FALSE | AI76: FALSE | AJ76: FALSE | AK76: FALSE | AL76: FALSE | AM76: FALSE | AN76: 1.5 | AO76: 0 | AP76: T2 | AQ76: fpv_hangar | AS76: thap | AT76: drone_hangar.swarm | AU76: 1 | AV76: drone_hangar.swarm:0 | AW76: 0 | AX76: FALSE | AZ76: =IF(AND($AX$76,$AW$76>$AA$76/$Z$76),$AW$76,$AA$76/$Z$76) | BA76: 2.6923077 | BB76: NEED_SOURCE | BC76: NEED_SOURCE | BE76: NEED_SOURCE | BG76: giong | CR76: 4 | CS76: 0.6 | DD76: 6.1 | DJ76: drone | DT76: fpv_hangar | EB76: 3 | EQ76: FPV drone (1.5 kg) | EX76: 1.5 | FY76: TRUE | FZ76: 1.5 | GA76: fpv_drone | GD76: Assets/MachineBrigade/Resources/Data/balance.json: weapons[128] | GE76: {"id":"fpv_hangar_swarm","weaponFamily":"fpv_drone","real":"FPV drone (1.5 kg)","family":"drone","size":1.5,"warheadKg":1.5,"pen":3,"topAttack":true,"inherits":"fpv_hangar","cooldown":6.1,"burst":4,"burstInterval":0.6}
A77: fpv_swarm | B77: FPV drone (1.5 kg) | C77: drone_fpv_drone | E77: fpv_drone | F77: drone | H77: 1.5 | K77: ShapedCharge | L77: 3 | M77: Drone | N77: 1 | O77: RIPPLE | P77: 1 | Q77: 0.1 | R77: 2.8 | S77: 0 | T77: 0 | U77: 16 | V77: 9 | W77: 140 | X77: 2.5 | Y77: 0 | Z77: 26 | AA77: 75 | AB77: 12 | AC77: Ground | AE77: 0 | AF77: Medium | AG77: TRUE | AH77: FALSE | AI77: FALSE | AJ77: FALSE | AK77: FALSE | AL77: FALSE | AM77: FALSE | AN77: 1.5 | AO77: 0 | AP77: T2 | AS77: xe | AT77: elite_fpv_carrier;fpv_carrier | AU77: 2 | AV77: elite_fpv_carrier:0;fpv_carrier:0 | AW77: 0 | AX77: FALSE | AZ77: =IF(AND($AX$77,$AW$77>$AA$77/$Z$77),$AW$77,$AA$77/$Z$77) | BA77: 2.8846154 | BB77: NEED_SOURCE | BC77: NEED_SOURCE | BE77: NEED_SOURCE | BG77: giong | CN77: 16 | DD77: 2.8 | DE77: 140 | DF77: ShapedCharge | DJ77: drone | DS77: Medium | DZ77: 12 | EB77: 3 | EE77: TRUE | EH77: Drone | EP77: 75 | EQ77: FPV drone (1.5 kg) | ER77: 9 | EX77: 1.5 | FY77: TRUE | FZ77: 1.5 | GA77: fpv_drone | GB77: drone_fpv_drone | GD77: Assets/MachineBrigade/Resources/Data/balance.json: weapons[61] | GE77: {"id":"fpv_swarm","weaponFamilyId":"drone_fpv_drone","weaponFamily":"fpv_drone","real":"FPV drone (1.5 kg)","family":"drone","size":1.5,"warheadKg":1.5,"pen":3,"topAttack":true,"piercing":true,"damageType":"ShapedCharge","damage":140,"cooldown":2.8,"range":75,"minRange":12,"impactTier":"Medium","projectile":"Drone","ammo":16,"reload":9,"bonuses":[{"armor":"Structure","mult":1.5}]}
A78: gau_gatling | B78: GAU-8 Avenger 30 mm | C78: cal_30 | F78: autocannon | G78: 30 | K78: Kinetic | L78: 3 | M78: Bullet | N78: 1 | O78: RIPPLE | P78: 1 | Q78: 0.1 | R78: 0.0167 | S78: 113 | T78: 2.79 | U78: 0 | V78: 0 | W78: 22 | X78: 0 | Y78: 0 | Z78: 320 | AA78: 32 | AB78: 0 | AC78: Ground | AE78: 2.2 | AF78: Small | AG78: FALSE | AH78: FALSE | AI78: FALSE | AJ78: FALSE | AK78: FALSE | AL78: FALSE | AM78: FALSE | AN78: 30 | AO78: 0 | AP78: T1 | AU78: 0 | AW78: 0 | AX78: FALSE | AZ78: =IF(AND($AX$78,$AW$78>$AA$78/$Z$78),$AW$78,$AA$78/$Z$78) | BA78: 0.1 | BB78: 3900 | BD78: ac | BE78: Wikipedia 'GAU-8 Avenger': 3,900 rpm | BG78: giong | CT78: 30 | CW78: 113 | CX78: 2.79 | DD78: 0.0167 | DE78: 22 | DF78: Kinetic | DJ78: autocannon | DS78: Small | EB78: 3 | EE78: TRUE | EH78: Bullet | EK78: 320 | EP78: 32 | EQ78: GAU-8 Avenger 30 mm | EV78: 27 | EX78: 30 | EZ78: 2.2 | GB78: cal_30 | GD78: Assets/MachineBrigade/Resources/Data/balance.json: weapons[81] | GE78: {"id":"gau_gatling","weaponFamilyId":"cal_30","real":"GAU-8 Avenger 30 mm","family":"autocannon","size":30,"caliberMm":30,"pen":3,"piercing":true,"damageType":"Kinetic","damage":22,"cooldown":0.0167,"range":32,"projectileSpeed":320,"spread":2.2,"impactTier":"Small","projectile":"Bullet","clip":113,"clipReload":2.79,"roundWeight":27}
A79: grad_cluster | B79: BM-21 Grad 122 mm (cluster) | C79: rkt_grad_122 | D79: cluster | E79: bm_21_grad_122_mm_2 | F79: rocket | G79: 122 | K79: HighExplosive | L79: 2 | M79: Rocket | N79: 1 | O79: RIPPLE | P79: 11 | Q79: 0.5 | R79: 8 | S79: 0 | T79: 0 | U79: 3 | V79: 13.67 | W79: 57 | X79: 4 | Y79: 0 | Z79: 130 | AA79: 78 | AB79: 18 | AC79: Ground | AE79: 8 | AF79: Medium | AG79: FALSE | AH79: FALSE | AI79: FALSE | AJ79: FALSE | AK79: FALSE | AL79: FALSE | AM79: FALSE | AN79: 122 | AO79: 0 | AP79: T3 | AS79: xe | AT79: elite_grad | AU79: 1 | AV79: elite_grad:0 | AW79: 0 | AX79: FALSE | AZ79: =IF(AND($AX$79,$AW$79>$AA$79/$Z$79),$AW$79,$AA$79/$Z$79) | BA79: 0.6 | BB79: 120 | BD79: rocket | BE79: Wikipedia 'BM-21 Grad': 40 rockets in 20 s | BG79: doi | BR79: 45 | BS79: 130 | CN79: 3 | CR79: 11 | CS79: 0.5 | CT79: 122 | CY79: 4 | CZ79: 15 | DA79: 5 | DB79: 2.2 | DC79: Small | DD79: 8 | DE79: 57 | DF79: HighExplosive | DJ79: rocket | DS79: Medium | DZ79: 18 | EB79: 2 | EH79: Rocket | EP79: 78 | EQ79: BM-21 Grad 122 mm (cluster) | ER79: 13.67 | EX79: 122 | EZ79: 8 | GA79: bm_21_grad_122_mm_2 | GB79: rkt_grad_122 | GC79: cluster | GD79: Assets/MachineBrigade/Resources/Data/balance.json: weapons[96] | GE79: {"id":"grad_cluster","weaponFamilyId":"rkt_grad_122","weaponVariantId":"cluster","weaponFamily":"bm_21_grad_122_mm_2","real":"BM-21 Grad 122 mm (cluster)","family":"rocket","size":122,"caliberMm":122,"pen":2,"reload":13.67,"damageType":"HighExplosive","damage":57,"cooldown":8,"range":78,"minRange":18,"spread":8,"impactTier":"Medium","projectile":"Rocket","burst":11,"burstInterval":0.5,"ammo":3,"cluster":{"count":4,"radius":5,"damage":15,"splash":2.2,"tier":"Small"}}
A80: grad_rockets | B80: BM-21 Grad 122 mm | C80: rkt_grad_122 | E80: bm_21_grad_122_mm | F80: rocket | G80: 122 | K80: HighExplosive | L80: 2 | M80: Rocket | N80: 1 | O80: RIPPLE | P80: 9 | Q80: 0.5 | R80: 11.31 | S80: 0 | T80: 0 | U80: 3 | V80: 16.6 | W80: 57 | X80: 4.5 | Y80: 0 | Z80: 130 | AA80: 55 | AB80: 18 | AC80: Ground | AE80: 7 | AF80: Medium | AG80: FALSE | AH80: FALSE | AI80: FALSE | AJ80: FALSE | AK80: FALSE | AL80: FALSE | AM80: FALSE | AN80: 122 | AO80: 0 | AP80: T3 | AU80: 0 | AW80: 0 | AX80: FALSE | AZ80: =IF(AND($AX$80,$AW$80>$AA$80/$Z$80),$AW$80,$AA$80/$Z$80) | BA80: 0.42307692 | BB80: 120 | BD80: rocket | BE80: Wikipedia 'BM-21 Grad': 40 rockets in 20 s | BG80: doi | BR80: 45 | BS80: 130 | CN80: 3 | CR80: 9 | CS80: 0.5 | CT80: 122 | DD80: 11.31 | DE80: 57 | DF80: HighExplosive | DJ80: rocket | DS80: Medium | DZ80: 18 | EB80: 2 | EH80: Rocket | EP80: 55 | EQ80: BM-21 Grad 122 mm | ER80: 16.6 | EX80: 122 | EZ80: 7 | GA80: bm_21_grad_122_mm | GB80: rkt_grad_122 | GD80: Assets/MachineBrigade/Resources/Data/balance.json: weapons[33] | GE80: {"id":"grad_rockets","weaponFamilyId":"rkt_grad_122","weaponFamily":"bm_21_grad_122_mm","real":"BM-21 Grad 122 mm","family":"rocket","size":122,"caliberMm":122,"pen":2,"damageType":"HighExplosive","damage":57,"cooldown":11.31,"range":55,"minRange":18,"spread":7,"impactTier":"Medium","projectile":"Rocket","burst":9,"burstInterval":0.5,"ammo":3,"reload":16.6}
A81: gsh_23v | B81: GSh-23V 23 mm | C81: cal_23 | F81: autocannon | G81: 23 | K81: Kinetic | L81: 2 | M81: Bullet | N81: 1 | O81: RIPPLE | P81: 1 | Q81: 0.1 | R81: 0.0182 | S81: 44 | T81: 5.6 | U81: 0 | V81: 0 | W81: 14 | X81: 0 | Y81: 0 | Z81: 240 | AA81: 26 | AB81: 0 | AC81: All | AE81: 1.3 | AF81: Small | AG81: FALSE | AH81: FALSE | AI81: FALSE | AJ81: FALSE | AK81: FALSE | AL81: FALSE | AM81: FALSE | AN81: 23 | AO81: 0 | AP81: T1 | AU81: 0 | AW81: 0 | AX81: FALSE | AZ81: =IF(AND($AX$81,$AW$81>$AA$81/$Z$81),$AW$81,$AA$81/$Z$81) | BA81: 0.10833333 | BB81: 3400 | BD81: ac | BE81: Wikipedia 'Gryazev-Shipunov GSh-23': 3,000-3,400 rpm (GSh-23V) | BG81: giong | CT81: 23 | CW81: 44 | CX81: 5.6 | DD81: 0.0182 | DE81: 14 | DF81: Kinetic | DJ81: autocannon | DS81: Small | EB81: 2 | EH81: Bullet | EK81: 240 | EP81: 26 | EQ81: GSh-23V 23 mm | EX81: 23 | EZ81: 1.3 | FW81: All | GB81: cal_23 | GD81: Assets/MachineBrigade/Resources/Data/balance.json: weapons[71] | GE81: {"id":"gsh_23v","weaponFamilyId":"cal_23","real":"GSh-23V 23 mm","family":"autocannon","size":23,"caliberMm":23,"pen":2,"damageType":"Kinetic","damage":14,"cooldown":0.0182,"range":26,"projectileSpeed":240,"spread":1.3,"impactTier":"Small","projectile":"Bullet","targets":"All","clip":44,"clipReload":5.6}
A82: guided_bomb | B82: GBU-39 SDB (110 kg) | C82: bomb_gbu_39_sdb | F82: bomb | H82: 110 | K82: HighExplosive | L82: 3 | M82: Bomb | N82: 1 | O82: RIPPLE | P82: 1 | Q82: 0.1 | R82: 6.651 | S82: 0 | T82: 0 | U82: 0 | V82: 0 | W82: 210 | X82: 4 | Y82: 0 | Z82: 40 | AA82: 30 | AB82: 0 | AC82: Ground | AE82: 1 | AF82: Large | AG82: FALSE | AH82: FALSE | AI82: FALSE | AJ82: FALSE | AK82: FALSE | AL82: FALSE | AM82: FALSE | AN82: 110 | AO82: 2 | AP82: T2 | AS82: xe | AT82: stealth_fighter;strike_drone | AU82: 2 | AV82: stealth_fighter:1;strike_drone:1 | AW82: 0 | AX82: FALSE | AZ82: =IF(AND($AX$82,$AW$82>$AA$82/$Z$82),$AW$82,$AA$82/$Z$82) | BA82: 0.75 | BB82: 600 | BD82: bomb | BE82: a stick's release, 0.1 s and up (est.) | BG82: giong | DD82: 6.651 | DE82: 210 | DF82: HighExplosive | DJ82: bomb | DN82: GuidedBomb | DS82: Large | DW82: 2 | EB82: 3 | EH82: Bomb | EI82: gbu39 | EJ82: 0.4091 | EK82: 40 | EP82: 30 | EQ82: GBU-39 SDB (110 kg) | ET82: 0.9 | EV82: 297 | EX82: 110 | EY82: 4 | EZ82: 1 | FA82: CENTER | FB82: 0.5 | FC82: 1 | FD82: OVERFLY | FE82: 0 | FF82: 0 | FG82: APPROACH | FH82: 0.1 | FI82: 0 | FJ82: 0 | FK82: 0 | FL82: 0 | FM82: 0 | FN82: POINT | FO82: 0 | FP82: 0 | FQ82: 8 | FR82: 0 | FS82: 0 | FT82: NONE | FU82: 8 | FZ82: 110 | GB82: bomb_gbu_39_sdb | GD82: Assets/MachineBrigade/Resources/Data/balance.json: weapons[236] | GE82: {"id":"guided_bomb","weaponFamilyId":"bomb_gbu_39_sdb","load":2,"real":"GBU-39 SDB (110 kg)","family":"bomb","size":110,"warheadKg":110,"pen":3,"form":"GuidedBomb","projectileModel":"gbu39","projectileScale":0.4091,"roundLength":0.9,"damageType":"HighExplosive","damage":210,"cooldown":6.651,"range":30,"projectileSpeed":40,"splash":4,"spread":1,"impactTier":"Large","projectile":"Bomb","roundWeight":297,"stick":{"mode":"POINT","bombs":1,"spacing":0,"length":0,"interval":0.1,"releaseSpeed":0,"fallTime":0,"lead":0,"heading":"APPROACH","anchor":"CENTER","drop":"OVERFLY","jitterAcross":0,"jitterAlong":0,"overlap":0,"width":8,"minTargets":0,"safety":8,"straightTime":0,"exit":0,"bayOpen":0.5,"warnShape":"NONE"}}
A83: gun_57_air | B83: AU-220 57 mm (air burst) | C83: cal_57 | D83: flak | F83: autocannon | G83: 57 | K83: Fragmentation | L83: 2 | M83: Bullet | N83: 1 | O83: RIPPLE | P83: 1 | Q83: 0.1 | R83: 0.5 | S83: 6 | T83: 2.4 | U83: 0 | V83: 0 | W83: 70 | X83: 3 | Y83: 0 | Z83: 260 | AA83: 40 | AB83: 0 | AC83: Air | AE83: 1.2 | AF83: Medium | AG83: FALSE | AH83: FALSE | AI83: FALSE | AJ83: FALSE | AK83: FALSE | AL83: FALSE | AM83: FALSE | AN83: 57 | AO83: 0 | AP83: T2 | AU83: 0 | AW83: 0 | AX83: FALSE | AZ83: =IF(AND($AX$83,$AW$83>$AA$83/$Z$83),$AW$83,$AA$83/$Z$83) | BA83: 0.15384615 | BB83: 120 | BC83: 80 | BD83: ac | BE83: Wikipedia 'AU-220M': 80-120 rpm | BG83: giong | CT83: 57 | CW83: 6 | CX83: 2.4 | DD83: 0.5 | DE83: 70 | DF83: Fragmentation | DJ83: autocannon | DS83: Medium | EB83: 2 | EH83: Bullet | EK83: 260 | EP83: 40 | EQ83: AU-220 57 mm (air burst) | EV83: 70 | EX83: 57 | EY83: 3 | EZ83: 1.2 | FW83: Air | GB83: cal_57 | GC83: flak | GD83: Assets/MachineBrigade/Resources/Data/balance.json: weapons[116] | GE83: {"id":"gun_57_air","weaponFamilyId":"cal_57","weaponVariantId":"flak","real":"AU-220 57 mm (air burst)","family":"autocannon","size":57,"caliberMm":57,"pen":2,"damageType":"Fragmentation","damage":70,"cooldown":0.5,"clip":6,"clipReload":2.4,"range":40,"projectileSpeed":260,"splash":3,"spread":1.2,"impactTier":"Medium","projectile":"Bullet","targets":"Air","roundWeight":70}
A84: gun_57_auto | B84: AU-220 57 mm (tower, twin) | C84: cal_57 | D84: ap | F84: autocannon | G84: 57 | K84: Kinetic | L84: 2 | M84: Bullet | N84: 2 | O84: RIPPLE | P84: 1 | Q84: 0.1 | R84: 0.25 | S84: 12 | T84: 2.65 | U84: 0 | V84: 0 | W84: 35 | X84: 1.5 | Y84: 0 | Z84: 260 | AA84: 40 | AB84: 0 | AC84: Ground | AE84: 0.9 | AF84: Medium | AG84: FALSE | AH84: FALSE | AI84: FALSE | AJ84: FALSE | AK84: FALSE | AL84: FALSE | AM84: FALSE | AN84: 57 | AO84: 0 | AP84: T2 | AS84: thap | AT84: gun_turret.auto | AU84: 1 | AV84: gun_turret.auto:0 | AW84: 0 | AX84: FALSE | AY84: KHONG_AP_DUNG | AZ84: =IF(AND($AX$84,$AW$84>$AA$84/$Z$84),$AW$84,$AA$84/$Z$84) | BA84: 0.15384615 | BB84: 120 | BC84: 80 | BD84: ac | BE84: Wikipedia 'AU-220M': 80-120 rpm | BG84: doi | BH84: 70 | BI84: 35 | BJ84: 0.5 | BK84: 0.25 | BX84: 1 | BY84: 2 | CF84: 6 | CG84: 12 | CH84: 2.9 | CI84: 2.65 | CL84: All | CM84: Ground | CO84: 2 | CT84: 57 | CW84: 12 | CX84: 2.65 | DD84: 0.25 | DE84: 35 | DF84: Kinetic | DJ84: autocannon | DS84: Medium | EB84: 2 | EG84: Light | EH84: Bullet | EK84: 260 | EP84: 40 | EQ84: AU-220 57 mm (tower, twin) | EV84: 70 | EX84: 57 | EY84: 1.5 | EZ84: 0.9 | FW84: Ground | GB84: cal_57 | GC84: ap | GD84: Assets/MachineBrigade/Resources/Data/balance.json: weapons[115] | GE84: {"id":"gun_57_auto","weaponFamilyId":"cal_57","weaponVariantId":"ap","prey":"Light","real":"AU-220 57 mm (tower, twin)","family":"autocannon","size":57,"caliberMm":57,"barrels":2,"pen":2,"damageType":"Kinetic","damage":35,"cooldown":0.25,"clip":12,"clipReload":2.65,"range":40,"projectileSpeed":260,"splash":1.5,"spread":0.9,"impactTier":"Medium","projectile":"Bullet","targets":"Ground","roundWeight":70}
A85: gun_57mm | B85: S-60 57 mm (2A91) | C85: cal_57 | D85: ap | F85: tank_gun | G85: 57 | K85: Kinetic | L85: 2 | M85: Shell | N85: 1 | O85: RIPPLE | P85: 2 | Q85: 0.5 | R85: 5.929 | S85: 0 | T85: 0 | U85: 0 | V85: 0 | W85: 110 | X85: 0 | Y85: 0 | Z85: 150 | AA85: 28 | AB85: 0 | AC85: Ground | AE85: 0.8 | AF85: Medium | AG85: FALSE | AH85: FALSE | AI85: FALSE | AJ85: FALSE | AK85: FALSE | AL85: FALSE | AM85: FALSE | AN85: 57 | AO85: 0 | AP85: T2 | AR85: gun_57mm_he | AS85: xe | AT85: light_tank | AU85: 1 | AV85: light_tank:0 | AW85: 0 | AX85: FALSE | AZ85: =IF(AND($AX$85,$AW$85>$AA$85/$Z$85),$AW$85,$AA$85/$Z$85) | BA85: 0.18666667 | BB85: 120 | BC85: 80 | BD85: ac | BE85: Wikipedia 'AU-220M': 80-120 rpm | BG85: doi | BH85: 77 | BI85: 110 | BJ85: 4 | BK85: 5.929 | CR85: 2 | CS85: 0.5 | CT85: 57 | DD85: 5.929 | DE85: 110 | DF85: Kinetic | DJ85: tank_gun | DS85: Medium | EB85: 2 | EE85: TRUE | EK85: 150 | EP85: 28 | EQ85: S-60 57 mm (2A91) | EV85: 79 | EX85: 57 | EZ85: 0.8 | GB85: cal_57 | GC85: ap | GD85: Assets/MachineBrigade/Resources/Data/balance.json: weapons[10] | GE85: {"id":"gun_57mm","weaponFamilyId":"cal_57","weaponVariantId":"ap","burstInterval":0.5,"burst":2,"real":"S-60 57 mm (2A91)","family":"tank_gun","size":57,"caliberMm":57,"pen":2,"piercing":true,"damageType":"Kinetic","damage":110,"cooldown":5.929,"range":28,"projectileSpeed":150,"spread":0.8,"impactTier":"Medium","roundWeight":79}
A86: gun_57mm_he | B86: S-60 57 mm HE (2A91) | C86: cal_57 | F86: tank_gun | G86: 57 | K86: HighExplosive | L86: 2 | M86: Shell | N86: 1 | O86: RIPPLE | P86: 2 | Q86: 0.5 | R86: 5.929 | S86: 0 | T86: 0 | U86: 0 | V86: 0 | W86: 110 | X86: 3 | Y86: 0 | Z86: 150 | AA86: 28 | AB86: 0 | AC86: Ground | AE86: 0.8 | AF86: Large | AG86: FALSE | AH86: FALSE | AI86: FALSE | AJ86: FALSE | AK86: FALSE | AL86: FALSE | AM86: FALSE | AN86: 57 | AO86: 0 | AP86: T2 | AQ86: gun_57mm | AU86: 0 | AW86: 0 | AX86: FALSE | AZ86: =IF(AND($AX$86,$AW$86>$AA$86/$Z$86),$AW$86,$AA$86/$Z$86) | BA86: 0.18666667 | BB86: 120 | BC86: 80 | BD86: ac | BE86: Wikipedia 'AU-220M': 80-120 rpm | BG86: doi | BH86: 77 | BI86: 110 | BJ86: 4 | BK86: 5.929 | DE86: 110 | DF86: HighExplosive | DM86: light;structure | DN86: HeShell | DS86: Large | DT86: gun_57mm | EB86: 2 | EE86: FALSE | EQ86: S-60 57 mm HE (2A91) | ES86: he | EU86: gun_57mm | EY86: 3 | FW86: Ground | GD86: Assets/MachineBrigade/Resources/Data/balance.json: secondRounds.rounds[32] | GE86: {"id":"gun_57mm_he","roundOf":"gun_57mm","inherits":"gun_57mm","weaponVariantId":"","weaponFamily":"","round":"he","for":["light","structure"],"real":"S-60 57 mm HE (2A91)","damageType":"HighExplosive","pen":2,"damage":110,"splash":3,"form":"HeShell","piercing":false,"targets":"Ground","impactTier":"Large"}
A87: gun_100_river | B87: A-190 100 mm (Buyan-class river gunboat) | C87: cal_100_105_he | F87: naval_gun | G87: 100 | K87: HighExplosive | L87: 2 | M87: Shell | N87: 1 | O87: RIPPLE | P87: 1 | Q87: 0.1 | R87: 4.286 | S87: 0 | T87: 0 | U87: 0 | V87: 0 | W87: 229 | X87: 4 | Y87: 0 | Z87: 170 | AA87: 70 | AB87: 0 | AC87: Ground | AE87: 0 | AF87: Large | AG87: FALSE | AH87: FALSE | AI87: FALSE | AJ87: FALSE | AK87: FALSE | AL87: FALSE | AM87: FALSE | AN87: 100 | AO87: 0 | AP87: T2 | AS87: xe | AT87: river_gunboat | AU87: 1 | AV87: river_gunboat:0 | AW87: 0 | AX87: FALSE | AZ87: =IF(AND($AX$87,$AW$87>$AA$87/$Z$87),$AW$87,$AA$87/$Z$87) | BA87: 0.41176471 | BB87: 80 | BC87: 40 | BD87: gun | BE87: Wikipedia 'A-190': 80 rpm | BG87: doi | BH87: 160 | BI87: 229 | BJ87: 3 | BK87: 4.286 | CL87: All | CM87: Ground | CT87: 100 | DD87: 4.286 | DE87: 229 | DF87: HighExplosive | DJ87: naval_gun | DS87: Large | EB87: 2 | EH87: Shell | EK87: 170 | EP87: 70 | EQ87: A-190 100 mm (Buyan-class river gunboat) | EX87: 100 | EY87: 4 | FW87: Ground | GB87: cal_100_105_he | GD87: Assets/MachineBrigade/Resources/Data/balance.json: weapons[285] | GE87: {"id":"gun_100_river","weaponFamilyId":"cal_100_105_he","real":"A-190 100 mm (Buyan-class river gunboat)","family":"naval_gun","size":100,"caliberMm":100,"pen":2,"damageType":"HighExplosive","damage":229,"cooldown":4.286,"range":70,"projectileSpeed":170,"splash":4,"impactTier":"Large","projectile":"Shell","targets":"Ground"}
A88: gun_105_apfsds | B88: 2A75 125 mm APFSDS | C88: cal_125_ap | F88: tank_gun | G88: 125 | K88: Kinetic | L88: 4 | M88: Shell | N88: 1 | O88: RIPPLE | P88: 1 | Q88: 0.1 | R88: 5.583 | S88: 0 | T88: 0 | U88: 0 | V88: 0 | W88: 371 | X88: 0 | Y88: 0 | Z88: 260 | AA88: 46 | AB88: 0 | AC88: Ground | AE88: 0.3 | AF88: Medium | AG88: FALSE | AH88: FALSE | AI88: FALSE | AJ88: FALSE | AK88: FALSE | AL88: FALSE | AM88: FALSE | AN88: 125 | AO88: 0 | AP88: T3 | AR88: gun_105_apfsds_he | AS88: xe | AT88: elite_tank_destroyer | AU88: 1 | AV88: elite_tank_destroyer:0 | AW88: 0 | AX88: FALSE | AZ88: =IF(AND($AX$88,$AW$88>$AA$88/$Z$88),$AW$88,$AA$88/$Z$88) | BA88: 0.17692308 | BB88: 7 | BC88: 7 | BD88: gun | BE88: Wikipedia '2S25 Sprut-SD': ~7 rpm | BG88: doi | BH88: 260 | BI88: 371 | BJ88: 3.908 | BK88: 5.583 | CT88: 125 | DD88: 5.583 | DE88: 371 | DF88: Kinetic | DJ88: tank_gun | DS88: Medium | EB88: 4 | EE88: TRUE | EK88: 260 | EP88: 46 | EQ88: 2A75 125 mm APFSDS | EV88: 345 | EX88: 125 | EZ88: 0.3 | GB88: cal_125_ap | GD88: Assets/MachineBrigade/Resources/Data/balance.json: weapons[93] | GE88: {"id":"gun_105_apfsds","weaponFamilyId":"cal_125_ap","real":"2A75 125 mm APFSDS","family":"tank_gun","size":125,"caliberMm":125,"pen":4,"piercing":true,"damageType":"Kinetic","damage":371,"cooldown":5.583,"range":46,"projectileSpeed":260,"spread":0.3,"impactTier":"Medium","roundWeight":345}
A89: gun_105_apfsds_he | B89: 2A75 125 mm HE | C89: cal_125_he | E89: 2a75_125_mm_he | F89: tank_gun | G89: 125 | K89: HighExplosive | L89: 2 | M89: Shell | N89: 1 | O89: RIPPLE | P89: 1 | Q89: 0.1 | R89: 5.583 | S89: 0 | T89: 0 | U89: 0 | V89: 0 | W89: 371 | X89: 3 | Y89: 0 | Z89: 260 | AA89: 46 | AB89: 0 | AC89: Ground | AE89: 0.3 | AF89: Large | AG89: FALSE | AH89: FALSE | AI89: FALSE | AJ89: FALSE | AK89: FALSE | AL89: FALSE | AM89: FALSE | AN89: 125 | AO89: 0 | AP89: T3 | AQ89: gun_105_apfsds | AU89: 0 | AW89: 0 | AX89: FALSE | AZ89: =IF(AND($AX$89,$AW$89>$AA$89/$Z$89),$AW$89,$AA$89/$Z$89) | BA89: 0.17692308 | BB89: 7 | BC89: 7 | BD89: gun | BE89: Wikipedia '2S25 Sprut-SD': ~7 rpm | BG89: doi | BH89: 260 | BI89: 371 | BJ89: 3.908 | BK89: 5.583 | DE89: 371 | DF89: HighExplosive | DM89: light;structure | DN89: HeShell | DS89: Large | DT89: gun_105_apfsds | EB89: 2 | EE89: FALSE | EQ89: 2A75 125 mm HE | ES89: he | EU89: gun_105_apfsds | EY89: 3 | FW89: Ground | GA89: 2a75_125_mm_he | GB89: cal_125_he | GD89: Assets/MachineBrigade/Resources/Data/balance.json: secondRounds.rounds[20] | GE89: {"id":"gun_105_apfsds_he","roundOf":"gun_105_apfsds","inherits":"gun_105_apfsds","weaponFamilyId":"cal_125_he","weaponFamily":"2a75_125_mm_he","round":"he","for":["light","structure"],"real":"2A75 125 mm HE","damageType":"HighExplosive","pen":2,"damage":371,"splash":3,"form":"HeShell","piercing":false,"targets":"Ground","impactTier":"Large"}
A90: gun_105_bunker | B90: L7 105 mm | C90: cal_100_105_ap | E90: l7_105_mm | F90: tank_gun | G90: 105 | K90: Kinetic | L90: 3 | M90: Shell | N90: 1 | O90: RIPPLE | P90: 1 | Q90: 0.1 | R90: 4.536 | S90: 0 | T90: 0 | U90: 0 | V90: 0 | W90: 250 | X90: 1.5 | Y90: 0 | Z90: 190 | AA90: 34 | AB90: 0 | AC90: Ground | AE90: 0.6 | AF90: Medium | AG90: FALSE | AH90: FALSE | AI90: FALSE | AJ90: FALSE | AK90: FALSE | AL90: FALSE | AM90: FALSE | AN90: 105 | AO90: 0 | AP90: T2 | AR90: gun_105_bunker_he | AU90: 0 | AW90: 0 | AX90: FALSE | AZ90: =IF(AND($AX$90,$AW$90>$AA$90/$Z$90),$AW$90,$AA$90/$Z$90) | BA90: 0.17894737 | BB90: 10 | BC90: 6 | BD90: gun | BE90: Wikipedia 'Royal Ordnance L7': 6-10 rpm | BG90: doi | BH90: 212 | BI90: 250 | CT90: 105 | DD90: 4.536 | DE90: 250 | DF90: Kinetic | DJ90: tank_gun | DS90: Medium | EB90: 3 | EE90: TRUE | EP90: 34 | EQ90: L7 105 mm | EX90: 105 | EZ90: 0.6 | GA90: l7_105_mm | GB90: cal_100_105_ap | GD90: Assets/MachineBrigade/Resources/Data/balance.json: weapons[263] | GE90: {"id":"gun_105_bunker","weaponFamilyId":"cal_100_105_ap","weaponFamily":"l7_105_mm","real":"L7 105 mm","family":"tank_gun","size":105,"caliberMm":105,"pen":3,"piercing":true,"damageType":"Kinetic","damage":250,"cooldown":4.536,"range":34,"spread":0.6,"impactTier":"Medium"}
A91: gun_105_bunker_he | B91: L7 105 mm HE | C91: cal_100_105_he | E91: l7_105_mm_he_bunker | F91: tank_gun | G91: 105 | K91: HighExplosive | L91: 2 | M91: Shell | N91: 1 | O91: RIPPLE | P91: 1 | Q91: 0.1 | R91: 4.536 | S91: 0 | T91: 0 | U91: 0 | V91: 0 | W91: 300 | X91: 5.5 | Y91: 11 | Z91: 190 | AA91: 34 | AB91: 0 | AC91: Ground | AE91: 0.6 | AF91: Large | AG91: FALSE | AH91: FALSE | AI91: FALSE | AJ91: FALSE | AK91: FALSE | AL91: FALSE | AM91: FALSE | AN91: 105 | AO91: 0 | AP91: T2 | AQ91: gun_105_bunker | AU91: 0 | AW91: 0 | AX91: FALSE | AZ91: =IF(AND($AX$91,$AW$91>$AA$91/$Z$91),$AW$91,$AA$91/$Z$91) | BA91: 0.17894737 | BB91: 10 | BC91: 6 | BD91: gun | BE91: Wikipedia 'Royal Ordnance L7': 6-10 rpm | BG91: doi | BH91: 212 | BI91: 300 | BN91: 3 | BO91: 5.5 | BP91: 0 | BQ91: 11 | DE91: 300 | DF91: HighExplosive | DG91: 11 | DM91: light;structure | DN91: HeShell | DS91: Large | DT91: gun_105_bunker | EB91: 2 | EE91: FALSE | EQ91: L7 105 mm HE | ES91: he | EU91: gun_105_bunker | EY91: 3 | FW91: Ground | GA91: l7_105_mm_he_bunker | GB91: cal_100_105_he | GD91: Assets/MachineBrigade/Resources/Data/balance.json: secondRounds.rounds[21] | GE91: {"id":"gun_105_bunker_he","roundOf":"gun_105_bunker","inherits":"gun_105_bunker","weaponFamilyId":"cal_100_105_he","weaponFamily":"l7_105_mm_he_bunker","round":"he","for":["light","structure"],"real":"L7 105 mm HE","damageType":"HighExplosive","pen":2,"damage":300,"splash":3,"edge":11,"form":"HeShell","piercing":false,"targets":"Ground","impactTier":"Large"}
A92: gun_105_long | B92: 2A75 125 mm (2S25 Sprut) | C92: cal_125_ap | F92: tank_gun | G92: 125 | K92: Kinetic | L92: 4 | M92: Shell | N92: 1 | O92: RIPPLE | P92: 1 | Q92: 0.1 | R92: 4.762 | S92: 0 | T92: 0 | U92: 0 | V92: 0 | W92: 371 | X92: 0 | Y92: 0 | Z92: 220 | AA92: 46 | AB92: 0 | AC92: Ground | AE92: 0.4 | AF92: Medium | AG92: FALSE | AH92: FALSE | AI92: FALSE | AJ92: FALSE | AK92: FALSE | AL92: FALSE | AM92: FALSE | AN92: 125 | AO92: 0 | AP92: T3 | AR92: gun_105_long_he | AS92: xe | AT92: tank_destroyer | AU92: 1 | AV92: tank_destroyer:0 | AW92: 0 | AX92: FALSE | AZ92: =IF(AND($AX$92,$AW$92>$AA$92/$Z$92),$AW$92,$AA$92/$Z$92) | BA92: 0.20909091 | BB92: 7 | BC92: 7 | BD92: gun | BE92: Wikipedia '2S25 Sprut-SD': ~7 rpm | BG92: doi | BH92: 260 | BI92: 371 | BJ92: 3.3333 | BK92: 4.762 | CT92: 125 | DD92: 4.762 | DE92: 371 | DF92: Kinetic | DJ92: tank_gun | DS92: Medium | EB92: 4 | EE92: TRUE | EK92: 220 | EP92: 46 | EQ92: 2A75 125 mm (2S25 Sprut) | EV92: 357 | EX92: 125 | EZ92: 0.4 | GB92: cal_125_ap | GD92: Assets/MachineBrigade/Resources/Data/balance.json: weapons[27] | GE92: {"id":"gun_105_long","weaponFamilyId":"cal_125_ap","real":"2A75 125 mm (2S25 Sprut)","family":"tank_gun","size":125,"caliberMm":125,"pen":4,"piercing":true,"damageType":"Kinetic","damage":371,"cooldown":4.762,"range":46,"projectileSpeed":220,"spread":0.4,"impactTier":"Medium","roundWeight":357}
A93: gun_105_long_he | B93: 2A75 125 mm HE (2S25 Sprut) | C93: cal_125_he | E93: 2a75_125_mm_he | F93: tank_gun | G93: 125 | K93: HighExplosive | L93: 2 | M93: Shell | N93: 1 | O93: RIPPLE | P93: 1 | Q93: 0.1 | R93: 4.762 | S93: 0 | T93: 0 | U93: 0 | V93: 0 | W93: 371 | X93: 3 | Y93: 0 | Z93: 260 | AA93: 46 | AB93: 0 | AC93: Ground | AE93: 0.4 | AF93: Large | AG93: FALSE | AH93: FALSE | AI93: FALSE | AJ93: FALSE | AK93: FALSE | AL93: FALSE | AM93: FALSE | AN93: 125 | AO93: 0 | AP93: T3 | AQ93: gun_105_long | AU93: 0 | AW93: 0 | AX93: FALSE | AZ93: =IF(AND($AX$93,$AW$93>$AA$93/$Z$93),$AW$93,$AA$93/$Z$93) | BA93: 0.17692308 | BB93: 7 | BC93: 7 | BD93: gun | BE93: Wikipedia '2S25 Sprut-SD': ~7 rpm | BG93: doi | BH93: 260 | BI93: 371 | BJ93: 3.3333 | BK93: 4.762 | DE93: 371 | DF93: HighExplosive | DM93: light;structure | DN93: HeShell | DS93: Large | DT93: gun_105_long | EB93: 2 | EE93: FALSE | EQ93: 2A75 125 mm HE (2S25 Sprut) | ES93: he | EU93: gun_105_long | EY93: 3 | FW93: Ground | GA93: 2a75_125_mm_he | GB93: cal_125_he | GD93: Assets/MachineBrigade/Resources/Data/balance.json: secondRounds.rounds[22] | GE93: {"id":"gun_105_long_he","roundOf":"gun_105_long","inherits":"gun_105_long","weaponFamilyId":"cal_125_he","weaponFamily":"2a75_125_mm_he","round":"he","for":["light","structure"],"real":"2A75 125 mm HE (2S25 Sprut)","damageType":"HighExplosive","pen":2,"damage":371,"splash":3,"form":"HeShell","piercing":false,"targets":"Ground","impactTier":"Large"}
A94: gun_105_twin | B94: L7 105 mm (twin) | C94: cal_100_105_ap | E94: l7_105_mm | F94: tank_gun | G94: 105 | K94: Kinetic | L94: 3 | M94: Shell | N94: 1 | O94: RIPPLE | P94: 2 | Q94: 0.05 | R94: 5.69 | S94: 0 | T94: 0 | U94: 0 | V94: 0 | W94: 212 | X94: 1.5 | Y94: 0 | Z94: 190 | AA94: 34 | AB94: 0 | AC94: Ground | AE94: 0.6 | AF94: Medium | AG94: FALSE | AH94: FALSE | AI94: FALSE | AJ94: FALSE | AK94: FALSE | AL94: FALSE | AM94: FALSE | AN94: 105 | AO94: 0 | AP94: T2 | AU94: 0 | AW94: 0 | AX94: FALSE | AZ94: =IF(AND($AX$94,$AW$94>$AA$94/$Z$94),$AW$94,$AA$94/$Z$94) | BA94: 0.17894737 | BB94: 10 | BC94: 6 | BD94: gun | BE94: Wikipedia 'Royal Ordnance L7': 6-10 rpm | BG94: giong | CR94: 2 | CS94: 0.05 | CT94: 105 | DD94: 5.69 | DE94: 212 | DF94: Kinetic | DJ94: tank_gun | DS94: Medium | EB94: 3 | EE94: TRUE | EP94: 34 | EQ94: L7 105 mm (twin) | EX94: 105 | EZ94: 0.6 | GA94: l7_105_mm | GB94: cal_100_105_ap | GD94: Assets/MachineBrigade/Resources/Data/balance.json: weapons[54] | GE94: {"id":"gun_105_twin","weaponFamilyId":"cal_100_105_ap","weaponFamily":"l7_105_mm","real":"L7 105 mm (twin)","family":"tank_gun","size":105,"caliberMm":105,"pen":3,"piercing":true,"damageType":"Kinetic","damage":212,"cooldown":5.69,"range":34,"spread":0.6,"impactTier":"Medium","burst":2,"burstInterval":0.05}
A95: gun_105_wheeled | B95: Centauro II 120 mm | C95: cal_120_ap | F95: tank_gun | G95: 120 | K95: Kinetic | L95: 4 | M95: Shell | N95: 1 | O95: RIPPLE | P95: 1 | Q95: 0.1 | R95: 5.291 | S95: 0 | T95: 0 | U95: 0 | V95: 0 | W95: 369 | X95: 0 | Y95: 0 | Z95: 230 | AA95: 38 | AB95: 0 | AC95: Ground | AE95: 0.4 | AF95: Medium | AG95: FALSE | AH95: FALSE | AI95: FALSE | AJ95: FALSE | AK95: FALSE | AL95: FALSE | AM95: FALSE | AN95: 120 | AO95: 0 | AP95: T3 | AR95: gun_105_wheeled_he | AS95: xe | AT95: wheeled_gun | AU95: 1 | AV95: wheeled_gun:0 | AW95: 0 | AX95: FALSE | AZ95: =IF(AND($AX$95,$AW$95>$AA$95/$Z$95),$AW$95,$AA$95/$Z$95) | BA95: 0.16521739 | BB95: 8 | BC95: 6 | BD95: gun | BE95: Centauro II 120 mm, manual: 6-8 rpm (the sheet) | BG95: doi | BH95: 258 | BI95: 369 | BJ95: 3.7037 | BK95: 5.291 | CT95: 120 | DD95: 5.291 | DE95: 369 | DF95: Kinetic | DJ95: tank_gun | DS95: Medium | EB95: 4 | EE95: TRUE | EK95: 230 | EP95: 38 | EQ95: Centauro II 120 mm | EV95: 300 | EX95: 120 | EZ95: 0.4 | GB95: cal_120_ap | GD95: Assets/MachineBrigade/Resources/Data/balance.json: weapons[100] | GE95: {"id":"gun_105_wheeled","weaponFamilyId":"cal_120_ap","real":"Centauro II 120 mm","family":"tank_gun","size":120,"caliberMm":120,"pen":4,"piercing":true,"roundWeight":300,"damageType":"Kinetic","damage":369,"cooldown":5.291,"range":38,"projectileSpeed":230,"spread":0.4,"impactTier":"Medium","bonuses":[{"flank":true,"mult":1.25}]}
A96: gun_105_wheeled_he | B96: Centauro II 120 mm HE | C96: cal_120_he | F96: tank_gun | G96: 120 | K96: HighExplosive | L96: 2 | M96: Shell | N96: 1 | O96: RIPPLE | P96: 1 | Q96: 0.1 | R96: 5.291 | S96: 0 | T96: 0 | U96: 0 | V96: 0 | W96: 369 | X96: 3 | Y96: 0 | Z96: 230 | AA96: 38 | AB96: 0 | AC96: Ground | AE96: 0.4 | AF96: Large | AG96: FALSE | AH96: FALSE | AI96: FALSE | AJ96: FALSE | AK96: FALSE | AL96: FALSE | AM96: FALSE | AN96: 120 | AO96: 0 | AP96: T3 | AQ96: gun_105_wheeled | AU96: 0 | AW96: 0 | AX96: FALSE | AZ96: =IF(AND($AX$96,$AW$96>$AA$96/$Z$96),$AW$96,$AA$96/$Z$96) | BA96: 0.16521739 | BB96: 8 | BC96: 6 | BD96: gun | BE96: Centauro II 120 mm, manual: 6-8 rpm (the sheet) | BG96: doi | BH96: 258 | BI96: 369 | BJ96: 3.7037 | BK96: 5.291 | DE96: 369 | DF96: HighExplosive | DM96: light;structure | DN96: HeShell | DS96: Large | DT96: gun_105_wheeled | EB96: 2 | EE96: FALSE | EQ96: Centauro II 120 mm HE | ES96: he | EU96: gun_105_wheeled | EY96: 3 | FW96: Ground | GB96: cal_120_he | GD96: Assets/MachineBrigade/Resources/Data/balance.json: secondRounds.rounds[23] | GE96: {"id":"gun_105_wheeled_he","roundOf":"gun_105_wheeled","inherits":"gun_105_wheeled","weaponFamilyId":"cal_120_he","weaponFamily":"","round":"he","for":["light","structure"],"real":"Centauro II 120 mm HE","damageType":"HighExplosive","pen":2,"damage":369,"splash":3,"form":"HeShell","piercing":false,"targets":"Ground","impactTier":"Large","bonuses":[]}
A97: gun_120_twin | B97: Rh-120 L/44 120 mm (twin) | C97: cal_120_ap | E97: rh_120_l_44_120_mm | F97: tank_gun | G97: 120 | K97: Kinetic | L97: 4 | M97: Shell | N97: 1 | O97: RIPPLE | P97: 2 | Q97: 0.05 | R97: 7.326 | S97: 0 | T97: 0 | U97: 0 | V97: 0 | W97: 343 | X97: 1.5 | Y97: 0 | Z97: 170 | AA97: 34 | AB97: 0 | AC97: Ground | AE97: 0.5 | AF97: Medium | AG97: FALSE | AH97: FALSE | AI97: FALSE | AJ97: FALSE | AK97: FALSE | AL97: FALSE | AM97: FALSE | AN97: 120 | AO97: 0 | AP97: T3 | AR97: gun_120_twin_he | AS97: xe | AT97: twin_tank | AU97: 1 | AV97: twin_tank:0 | AW97: 0 | AX97: FALSE | AZ97: =IF(AND($AX$97,$AW$97>$AA$97/$Z$97),$AW$97,$AA$97/$Z$97) | BA97: 0.2 | BB97: 8 | BC97: 6 | BD97: gun | BE97: the sheet's 'Ngoài đời': Rh-120 6-8 rpm with a loader (Wikipedia 'Rheinmetall 120 mm gun') | BG97: doi | BH97: 240 | BI97: 343 | BJ97: 5.113 | BK97: 7.326 | CR97: 2 | CS97: 0.05 | CT97: 120 | DD97: 7.326 | DE97: 343 | DF97: Kinetic | DJ97: tank_gun | DS97: Medium | EB97: 4 | EE97: TRUE | EP97: 34 | EQ97: Rh-120 L/44 120 mm (twin) | EX97: 120 | EZ97: 0.5 | GA97: rh_120_l_44_120_mm | GB97: cal_120_ap | GD97: Assets/MachineBrigade/Resources/Data/balance.json: weapons[265] | GE97: {"id":"gun_120_twin","weaponFamilyId":"cal_120_ap","weaponFamily":"rh_120_l_44_120_mm","real":"Rh-120 L/44 120 mm (twin)","family":"tank_gun","size":120,"caliberMm":120,"pen":4,"piercing":true,"damageType":"Kinetic","damage":343,"cooldown":7.326,"range":34,"spread":0.5,"impactTier":"Medium","burst":2,"burstInterval":0.05}
A98: gun_120_twin_he | B98: Rh-120 L/44 120 mm HE (twin) | C98: cal_120_he | E98: rh_120_l_44_120_mm_he | F98: tank_gun | G98: 120 | K98: HighExplosive | L98: 2 | M98: Shell | N98: 1 | O98: RIPPLE | P98: 2 | Q98: 0.05 | R98: 7.326 | S98: 0 | T98: 0 | U98: 0 | V98: 0 | W98: 343 | X98: 3 | Y98: 0 | Z98: 170 | AA98: 34 | AB98: 0 | AC98: Ground | AE98: 0.5 | AF98: Large | AG98: FALSE | AH98: FALSE | AI98: FALSE | AJ98: FALSE | AK98: FALSE | AL98: FALSE | AM98: FALSE | AN98: 120 | AO98: 0 | AP98: T3 | AQ98: gun_120_twin | AU98: 0 | AW98: 0 | AX98: FALSE | AZ98: =IF(AND($AX$98,$AW$98>$AA$98/$Z$98),$AW$98,$AA$98/$Z$98) | BA98: 0.2 | BB98: 8 | BC98: 6 | BD98: gun | BE98: the sheet's 'Ngoài đời': Rh-120 6-8 rpm with a loader (Wikipedia 'Rheinmetall 120 mm gun') | BG98: doi | BH98: 240 | BI98: 343 | BJ98: 5.113 | BK98: 7.326 | DE98: 343 | DF98: HighExplosive | DM98: light;structure | DN98: HeShell | DS98: Large | DT98: gun_120_twin | EB98: 2 | EE98: FALSE | EQ98: Rh-120 L/44 120 mm HE (twin) | ES98: he | EU98: gun_120_twin | EY98: 3 | FW98: Ground | GA98: rh_120_l_44_120_mm_he | GB98: cal_120_he | GD98: Assets/MachineBrigade/Resources/Data/balance.json: secondRounds.rounds[24] | GE98: {"id":"gun_120_twin_he","roundOf":"gun_120_twin","inherits":"gun_120_twin","weaponFamilyId":"cal_120_he","weaponFamily":"rh_120_l_44_120_mm_he","round":"he","for":["light","structure"],"real":"Rh-120 L/44 120 mm HE (twin)","damageType":"HighExplosive","pen":2,"damage":343,"splash":3,"form":"HeShell","piercing":false,"targets":"Ground","impactTier":"Large"}
A99: gun_120mm | B99: Rh-120 L/44 120 mm | C99: cal_120_ap | E99: rh_120_l_44_120_mm | F99: tank_gun | G99: 120 | K99: Kinetic | L99: 4 | M99: Shell | N99: 1 | O99: RIPPLE | P99: 1 | Q99: 0.1 | R99: 7.283 | S99: 0 | T99: 0 | U99: 0 | V99: 0 | W99: 343 | X99: 1.5 | Y99: 0 | Z99: 170 | AA99: 32 | AB99: 0 | AC99: Ground | AE99: 0.6 | AF99: Medium | AG99: FALSE | AH99: FALSE | AI99: FALSE | AJ99: FALSE | AK99: FALSE | AL99: FALSE | AM99: FALSE | AN99: 120 | AO99: 0 | AP99: T3 | AR99: gun_120mm_he | AS99: boss_part;xe | AT99: main_battle_tank;mara_behemoth;side_gun_120;turret_120 | AU99: 4 | AV99: main_battle_tank:0;mara_behemoth:1;side_gun_120:part;turret_120:part | AW99: 0 | AX99: FALSE | AZ99: =IF(AND($AX$99,$AW$99>$AA$99/$Z$99),$AW$99,$AA$99/$Z$99) | BA99: 0.18823529 | BB99: 8 | BC99: 6 | BD99: gun | BE99: the sheet's 'Ngoài đời': Rh-120 6-8 rpm with a loader (Wikipedia 'Rheinmetall 120 mm gun') | BG99: doi | BH99: 240 | BI99: 343 | BJ99: 5.098 | BK99: 7.283 | CT99: 120 | DD99: 7.283 | DE99: 343 | DF99: Kinetic | DJ99: tank_gun | DS99: Medium | EB99: 4 | EE99: TRUE | EP99: 32 | EQ99: Rh-120 L/44 120 mm | EX99: 120 | EZ99: 0.6 | GA99: rh_120_l_44_120_mm | GB99: cal_120_ap | GD99: Assets/MachineBrigade/Resources/Data/balance.json: weapons[11] | GE99: {"id":"gun_120mm","weaponFamilyId":"cal_120_ap","weaponFamily":"rh_120_l_44_120_mm","real":"Rh-120 L/44 120 mm","family":"tank_gun","size":120,"caliberMm":120,"pen":4,"piercing":true,"damageType":"Kinetic","damage":343,"cooldown":7.283,"range":32,"spread":0.6,"impactTier":"Medium"}
A100: gun_120mm_he | B100: Rh-120 L/44 120 mm HE | C100: cal_120_he | E100: rh_120_l_44_120_mm_he | F100: tank_gun | G100: 120 | K100: HighExplosive | L100: 2 | M100: Shell | N100: 1 | O100: RIPPLE | P100: 1 | Q100: 0.1 | R100: 7.283 | S100: 0 | T100: 0 | U100: 0 | V100: 0 | W100: 343 | X100: 3 | Y100: 0 | Z100: 170 | AA100: 32 | AB100: 0 | AC100: Ground | AE100: 0.6 | AF100: Large | AG100: FALSE | AH100: FALSE | AI100: FALSE | AJ100: FALSE | AK100: FALSE | AL100: FALSE | AM100: FALSE | AN100: 120 | AO100: 0 | AP100: T3 | AQ100: gun_120mm | AU100: 0 | AW100: 0 | AX100: FALSE | AZ100: =IF(AND($AX$100,$AW$100>$AA$100/$Z$100),$AW$100,$AA$100/$Z$100) | BA100: 0.18823529 | BB100: 8 | BC100: 6 | BD100: gun | BE100: the sheet's 'Ngoài đời': Rh-120 6-8 rpm with a loader (Wikipedia 'Rheinmetall 120 mm gun') | BG100: doi | BH100: 240 | BI100: 343 | BJ100: 5.098 | BK100: 7.283 | DE100: 343 | DF100: HighExplosive | DM100: light;structure | DN100: HeShell | DS100: Large | DT100: gun_120mm | EB100: 2 | EE100: FALSE | EQ100: Rh-120 L/44 120 mm HE | ES100: he | EU100: gun_120mm | EY100: 3 | FW100: Ground | GA100: rh_120_l_44_120_mm_he | GB100: cal_120_he | GD100: Assets/MachineBrigade/Resources/Data/balance.json: secondRounds.rounds[25] | GE100: {"id":"gun_120mm_he","roundOf":"gun_120mm","inherits":"gun_120mm","weaponFamilyId":"cal_120_he","weaponFamily":"rh_120_l_44_120_mm_he","round":"he","for":["light","structure"],"real":"Rh-120 L/44 120 mm HE","damageType":"HighExplosive","pen":2,"damage":343,"splash":3,"form":"HeShell","piercing":false,"targets":"Ground","impactTier":"Large"}
...

Sheet Vu_khi_he_so_thuong
A1: id | B1: vu_khi_id | C1: thu_tu | D1: armor | E1: class | F1: flank | G1: mult | H1: still | I1: nguon | J1: raw_json
A2: borer_drill/0 | B2: borer_drill | C2: 0 | D2: Structure | G2: 2 | I2: Assets/MachineBrigade/Resources/Data/balance.json: weapons[243].bonuses[0] | J2: {"armor":"Structure","mult":2}
A3: detonator/0 | B3: detonator | C3: 0 | D3: Structure | G3: 0.5 | I3: Assets/MachineBrigade/Resources/Data/balance.json: weapons[72].bonuses[0] | J3: {"armor":"Structure","mult":0.5}
A4: dozer_blade/0 | B4: dozer_blade | C4: 0 | D4: Structure | G4: 3 | I4: Assets/MachineBrigade/Resources/Data/balance.json: weapons[104].bonuses[0] | J4: {"armor":"Structure","mult":3}
A5: dozer_blade/1 | B5: dozer_blade | C5: 1 | D5: Heavy | G5: 0.4 | I5: Assets/MachineBrigade/Resources/Data/balance.json: weapons[104].bonuses[1] | J5: {"armor":"Heavy","mult":0.4}
A6: dozer_blade/2 | B6: dozer_blade | C6: 2 | D6: Light | G6: 0.55 | I6: Assets/MachineBrigade/Resources/Data/balance.json: weapons[104].bonuses[2] | J6: {"armor":"Light","mult":0.55}
A7: drone_missile/0 | B7: drone_missile | C7: 0 | D7: Structure | G7: 1.5 | I7: Assets/MachineBrigade/Resources/Data/balance.json: weapons[41].bonuses[0] | J7: {"armor":"Structure","mult":1.5}
A8: flak_35/0 | B8: flak_35 | C8: 0 | E8: Plane | G8: 1.5 | I8: Assets/MachineBrigade/Resources/Data/balance.json: weapons[19].bonuses[0] | J8: {"class":"Plane","mult":1.5}
A9: fpv_swarm/0 | B9: fpv_swarm | C9: 0 | D9: Structure | G9: 1.5 | I9: Assets/MachineBrigade/Resources/Data/balance.json: weapons[61].bonuses[0] | J9: {"armor":"Structure","mult":1.5}
A10: gun_105_wheeled/0 | B10: gun_105_wheeled | C10: 0 | F10: TRUE | G10: 1.25 | I10: Assets/MachineBrigade/Resources/Data/balance.json: weapons[100].bonuses[0] | J10: {"flank":true,"mult":1.25}
A11: gun_203_siege/0 | B11: gun_203_siege | C11: 0 | D11: Structure | G11: 2.4 | I11: Assets/MachineBrigade/Resources/Data/balance.json: weapons[55].bonuses[0] | J11: {"armor":"Structure","mult":2.4}
A12: kornet_multi/0 | B12: kornet_multi | C12: 0 | D12: Light | G12: 0.6 | I12: Assets/MachineBrigade/Resources/Data/balance.json: weapons[118].bonuses[0] | J12: {"armor":"Light","mult":0.6}
A13: kornet_multi/1 | B13: kornet_multi | C13: 1 | D13: Heavy | G13: 0.85 | I13: Assets/MachineBrigade/Resources/Data/balance.json: weapons[118].bonuses[1] | J13: {"armor":"Heavy","mult":0.85}
A14: lancet/0 | B14: lancet | C14: 0 | E14: Artillery | G14: 2 | I14: Assets/MachineBrigade/Resources/Data/balance.json: weapons[74].bonuses[0] | J14: {"class":"Artillery","mult":2}
A15: lancet/1 | B15: lancet | C15: 1 | G15: 2 | H15: 3 | I15: Assets/MachineBrigade/Resources/Data/balance.json: weapons[74].bonuses[1] | J15: {"still":3,"mult":2}
A16: lancet/2 | B16: lancet | C16: 2 | D16: Structure | G16: 1.5 | I16: Assets/MachineBrigade/Resources/Data/balance.json: weapons[74].bonuses[2] | J16: {"armor":"Structure","mult":1.5}
A17: siege_mortar_240/0 | B17: siege_mortar_240 | C17: 0 | D17: Structure | G17: 2 | I17: Assets/MachineBrigade/Resources/Data/balance.json: weapons[57].bonuses[0] | J17: {"armor":"Structure","mult":2}
A18: swarm_drones/0 | B18: swarm_drones | C18: 0 | D18: Structure | G18: 1.5 | I18: Assets/MachineBrigade/Resources/Data/balance.json: weapons[262].bonuses[0] | J18: {"armor":"Structure","mult":1.5}
A19: technical_rockets/0 | B19: technical_rockets | C19: 0 | D19: Structure | G19: 0.6 | I19: Assets/MachineBrigade/Resources/Data/balance.json: weapons[32].bonuses[0] | J19: {"armor":"Structure","mult":0.6}
A20: tower_flak_30/0 | B20: tower_flak_30 | C20: 0 | D20: Light | G20: 0.48 | I20: Assets/MachineBrigade/Resources/Data/balance.json: weapons[45].bonuses[0] | J20: {"armor":"Light","mult":0.48}
A21: tower_flak_30/1 | B21: tower_flak_30 | C21: 1 | D21: Heavy | G21: 0.4 | I21: Assets/MachineBrigade/Resources/Data/balance.json: weapons[45].bonuses[1] | J21: {"armor":"Heavy","mult":0.4}
A22: tower_kornet/0 | B22: tower_kornet | C22: 0 | D22: Light | G22: 0.4 | I22: Assets/MachineBrigade/Resources/Data/balance.json: weapons[103].bonuses[0] | J22: {"armor":"Light","mult":0.4}
A23: turret_gmlrs/0 | B23: turret_gmlrs | C23: 0 | E23: Artillery | G23: 1.5 | I23: Assets/MachineBrigade/Resources/Data/balance.json: weapons[121].bonuses[0] | J23: {"class":"Artillery","mult":1.5}
A24: turret_gmlrs/1 | B24: turret_gmlrs | C24: 1 | D24: Structure | G24: 1.5 | I24: Assets/MachineBrigade/Resources/Data/balance.json: weapons[121].bonuses[1] | J24: {"armor":"Structure","mult":1.5}
A25: turret_gun_120/0 | B25: turret_gun_120 | C25: 0 | D25: Light | G25: 0.65 | I25: Assets/MachineBrigade/Resources/Data/balance.json: weapons[12].bonuses[0] | J25: {"armor":"Light","mult":0.65}
A26: turret_rockets/0 | B26: turret_rockets | C26: 0 | D26: Heavy | G26: 0.46 | I26: Assets/MachineBrigade/Resources/Data/balance.json: weapons[130].bonuses[0] | J26: {"armor":"Heavy","mult":0.46}
A27: twin_30_flak/0 | B27: twin_30_flak | C27: 0 | E27: Plane | G27: 1.25 | I27: Assets/MachineBrigade/Resources/Data/balance.json: weapons[44].bonuses[0] | J27: {"class":"Plane","mult":1.25}
A28: twin_35_ahead/0 | B28: twin_35_ahead | C28: 0 | E28: Plane | G28: 1.5 | I28: Assets/MachineBrigade/Resources/Data/balance.json: weapons[95].bonuses[0] | J28: {"class":"Plane","mult":1.5}

Sheet Ho_vu_khi
A1: id | B1: ten | C1: bac | D1: boss_sat_thuong | E1: boss_loi_m | F1: boss_ria_m | G1: bien_the | H1: so_vu_khi | I1: vu_khi | J1: nguon | K1: raw_json
A2: atgm_9k121_vikhr | B2: atgm_9k121_vikhr | C2: 2 | H2: 1 | I2: vikhr | J2: Assets/MachineBrigade/Resources/Data/balance.json: weaponFamilyTable[37] | K2: {"id":"atgm_9k121_vikhr","name":"atgm_9k121_vikhr","tier":2}
A3: atgm_9m113_konkurs | B3: atgm_9m113_konkurs | C3: 2 | H3: 1 | I3: atgm_post | J3: Assets/MachineBrigade/Resources/Data/balance.json: weaponFamilyTable[38] | K3: {"id":"atgm_9m113_konkurs","name":"atgm_9m113_konkurs","tier":2}
A4: atgm_9m120_ataka | B4: atgm_9m120_ataka | C4: 2 | H4: 0 | J4: Assets/MachineBrigade/Resources/Data/balance.json: weaponFamilyTable[39] | K4: {"id":"atgm_9m120_ataka","name":"atgm_9m120_ataka","tier":2}
A5: atgm_9m123_khrizantema | B5: atgm_9m123_khrizantema | C5: 2 | H5: 0 | J5: Assets/MachineBrigade/Resources/Data/balance.json: weaponFamilyTable[40] | K5: {"id":"atgm_9m123_khrizantema","name":"atgm_9m123_khrizantema","tier":2}
A6: atgm_agm_65_maverick | B6: atgm_agm_65_maverick | C6: 3 | H6: 1 | I6: maverick | J6: Assets/MachineBrigade/Resources/Data/balance.json: weaponFamilyTable[44] | K6: {"id":"atgm_agm_65_maverick","name":"atgm_agm_65_maverick","tier":3}
A7: atgm_agm_114_hellfire | B7: atgm_agm_114_hellfire | C7: 2 | H7: 2 | I7: drone_missile;pt14_th_jagm | J7: Assets/MachineBrigade/Resources/Data/balance.json: weaponFamilyTable[41] | K7: {"id":"atgm_agm_114_hellfire","name":"atgm_agm_114_hellfire","tier":2}
A8: atgm_agm_114l_hellfire_longbow | B8: atgm_agm_114l_hellfire_longbow | C8: 2 | H8: 2 | I8: hellfire_standoff;hellfire_volley | J8: Assets/MachineBrigade/Resources/Data/balance.json: weaponFamilyTable[42] | K8: {"id":"atgm_agm_114l_hellfire_longbow","name":"atgm_agm_114l_hellfire_longbow","tier":2}
A9: atgm_agm_176_griffin | B9: atgm_agm_176_griffin | C9: 2 | H9: 0 | J9: Assets/MachineBrigade/Resources/Data/balance.json: weaponFamilyTable[43] | K9: {"id":"atgm_agm_176_griffin","name":"atgm_agm_176_griffin","tier":2}
A10: atgm_bgm_71_tow_2 | B10: atgm_bgm_71_tow_2 | C10: 2 | H10: 1 | I10: atgm | J10: Assets/MachineBrigade/Resources/Data/balance.json: weaponFamilyTable[45] | K10: {"id":"atgm_bgm_71_tow_2","name":"atgm_bgm_71_tow_2","tier":2}
A11: atgm_gun_launched_atgm | B11: atgm_gun_launched_atgm | C11: 2 | H11: 1 | I11: gun_launched_atgm | J11: Assets/MachineBrigade/Resources/Data/balance.json: weaponFamilyTable[46] | K11: {"id":"atgm_gun_launched_atgm","name":"atgm_gun_launched_atgm","tier":2}
A12: atgm_kh_29l | B12: atgm_kh_29l | C12: 4 | H12: 1 | I12: kh29 | J12: Assets/MachineBrigade/Resources/Data/balance.json: weaponFamilyTable[47] | K12: {"id":"atgm_kh_29l","name":"atgm_kh_29l","tier":4}
A13: atgm_kornet | B13: 9M133 Kornet | C13: 2 | D13: 230 | E13: 0 | F13: 0 | H13: 14 | I13: atgm_heavy;boss_missiles;kornet_multi;kornet_top;kornet_twin;one_shot_kornet;p26_bastion_tiny_kornet_twin;p26_behemoth_tiny_boss_missiles;p26_matriarch_direct_ma_atgm;p26_matriarch_ma_atgm;p26_roc_direct_roc_atgm;p26_roc_roc_atgm;pt14_ixion_kornet;tower_kornet | J13: Assets/MachineBrigade/Resources/Data/balance.json: weaponFamilyTable[35] | K13: {"id":"atgm_kornet","name":"9M133 Kornet","tier":2,"boss":{"damage":230,"core":0,"edge":0}}
A14: atgm_mam_l | B14: atgm_mam_l | C14: 2 | H14: 1 | I14: recon_missile | J14: Assets/MachineBrigade/Resources/Data/balance.json: weaponFamilyTable[48] | K14: {"id":"atgm_mam_l","name":"atgm_mam_l","tier":2}
A15: atgm_spike_nlos | B15: atgm_spike_nlos | C15: 2 | H15: 1 | I15: pt14_co_spike | J15: Assets/MachineBrigade/Resources/Data/balance.json: weaponFamilyTable[49] | K15: {"id":"atgm_spike_nlos","name":"atgm_spike_nlos","tier":2}
A16: bal_9m723_iskander | B16: bal_9m723_iskander | C16: 4 | H16: 1 | I16: ballistic_missile | J16: Assets/MachineBrigade/Resources/Data/balance.json: weaponFamilyTable[50] | K16: {"id":"bal_9m723_iskander","name":"bal_9m723_iskander","tier":4}
A17: bomb_400 | B17: 400 kg bomb | C17: 4 | D17: 700 | E17: 10 | F17: 20 | H17: 2 | I17: p26_roc_main_roc_bombs;p26_roc_roc_bombs | J17: Assets/MachineBrigade/Resources/Data/balance.json: weaponFamilyTable[34] | K17: {"id":"bomb_400","name":"400 kg bomb","tier":4,"boss":{"damage":700,"core":10,"edge":20}}
A18: bomb_car_bomb | B18: bomb_car_bomb | C18: 4 | H18: 1 | I18: detonator | J18: Assets/MachineBrigade/Resources/Data/balance.json: weaponFamilyTable[51] | K18: {"id":"bomb_car_bomb","name":"bomb_car_bomb","tier":4}
A19: bomb_cbu_97_sensor_fuzed_weapon | B19: bomb_cbu_97_sensor_fuzed_weapon | C19: 4 | H19: 0 | J19: Assets/MachineBrigade/Resources/Data/balance.json: weaponFamilyTable[52] | K19: {"id":"bomb_cbu_97_sensor_fuzed_weapon","name":"bomb_cbu_97_sensor_fuzed_weapon","tier":4}
A20: bomb_fab_250 | B20: bomb_fab_250 | C20: 3 | H20: 1 | I20: jet_bombs | J20: Assets/MachineBrigade/Resources/Data/balance.json: weaponFamilyTable[53] | K20: {"id":"bomb_fab_250","name":"bomb_fab_250","tier":3}
A21: bomb_fab_500 | B21: bomb_fab_500 | C21: 4 | H21: 1 | I21: bomber_payload | J21: Assets/MachineBrigade/Resources/Data/balance.json: weaponFamilyTable[54] | K21: {"id":"bomb_fab_500","name":"bomb_fab_500","tier":4}
A22: bomb_fab_500_m_62_with_umpk_glide_kit | B22: bomb_fab_500_m_62_with_umpk_glide_kit | C22: 4 | H22: 0 | J22: Assets/MachineBrigade/Resources/Data/balance.json: weaponFamilyTable[55] | K22: {"id":"bomb_fab_500_m_62_with_umpk_glide_kit","name":"bomb_fab_500_m_62_with_umpk_glide_kit","tier":4}
A23: bomb_gbu_28 | B23: bomb_gbu_28 | C23: 4 | H23: 0 | J23: Assets/MachineBrigade/Resources/Data/balance.json: weaponFamilyTable[56] | K23: {"id":"bomb_gbu_28","name":"bomb_gbu_28","tier":4}
A24: bomb_gbu_31_jdam | B24: bomb_gbu_31_jdam | C24: 4 | H24: 1 | I24: stealth_payload | J24: Assets/MachineBrigade/Resources/Data/balance.json: weaponFamilyTable[57] | K24: {"id":"bomb_gbu_31_jdam","name":"bomb_gbu_31_jdam","tier":4}
A25: bomb_gbu_39_sdb | B25: bomb_gbu_39_sdb | C25: 2 | H25: 1 | I25: guided_bomb | J25: Assets/MachineBrigade/Resources/Data/balance.json: weaponFamilyTable[58] | K25: {"id":"bomb_gbu_39_sdb","name":"bomb_gbu_39_sdb","tier":2}
A26: bomb_odab_500 | B26: bomb_odab_500 | C26: 4 | H26: 0 | J26: Assets/MachineBrigade/Resources/Data/balance.json: weaponFamilyTable[59] | K26: {"id":"bomb_odab_500","name":"bomb_odab_500","tier":4}
A27: cal_7_62 | B27: 7.62 mm machine gun | C27: 0 | H27: 5 | I27: boss_minigun;bunker_pkm;mg_coax;mg_coax_long;minigun | J27: Assets/MachineBrigade/Resources/Data/balance.json: weaponFamilyTable[0] | K27: {"id":"cal_7_62","name":"7.62 mm machine gun","tier":0}
A28: cal_12_7 | B28: 12.7 mm heavy machine gun | C28: 0 | D28: 15 | E28: 0 | F28: 0 | H28: 25 | I28: bomber_tail_guns;bomber_tail_guns_api;boss_hmg;boss_hmg_api;bunker_hmg;bunker_hmg_api;bunker_hmg_twin;bunker_hmg_twin_api;drone_gun;hmg_roof;hmg_roof_api;hmg_selfdef_15;hmg_selfdef_15_api;hmg_selfdef_18;hmg_selfdef_18_api;hmg_selfdef_21;hmg_selfdef_21_api;mg_jeep;mg_jeep_api;mg_jeep_selfdef;mg_jeep_selfdef_api;p26_bastion_close_boss_hmg;p26_ixion_mg;tower_hmg;tower_hmg_api | J28: Assets/MachineBrigade/Resources/Data/balance.json: weaponFamilyTable[1] | K28: {"id":"cal_12_7","name":"12.7 mm heavy machine gun","tier":0,"boss":{"damage":15,"core":0,"edge":0}}
A29: cal_14_5 | B29: 14.5 mm heavy machine gun | C29: 0 | H29: 1 | I29: scylla_2m7 | J29: Assets/MachineBrigade/Resources/Data/balance.json: weaponFamilyTable[2] | K29: {"id":"cal_14_5","name":"14.5 mm heavy machine gun","tier":0}
A30: cal_20 | B30: 20 mm | C30: 1 | H30: 1 | I30: c_ram_gatling | J30: Assets/MachineBrigade/Resources/Data/balance.json: weaponFamilyTable[3] | K30: {"id":"cal_20","name":"20 mm","tier":1}
A31: cal_23 | B31: 23 mm | C31: 1 | D31: 3.5 | E31: 0 | F31: 0 | H31: 7 | I31: flak_quad;flak_quad_ap;gsh_23v;p26_bastion_tiny_zu23;p26_moloch_tiny_zu23;zu23;zu23_ap | J31: Assets/MachineBrigade/Resources/Data/balance.json: weaponFamilyTable[4] | K31: {"id":"cal_23","name":"23 mm","tier":1,"boss":{"damage":3.5,"core":0,"edge":0}}
A32: cal_25 | B32: 25 mm | C32: 1 | G32: flak | H32: 11 | I32: aa_25_triple;aa_25_triple_ap;autocannon_25;autocannon_25_flak;fighter_cannon;fighter_cannon_ap;gunship_25mm;gunship_25mm_flak;pt14_dd_v25;tower_ac25;tower_ac25_flak | J32: Assets/MachineBrigade/Resources/Data/balance.json: weaponFamilyTable[5] | K32: {"id":"cal_25","name":"25 mm","tier":1,"variants":{"flak":"air-burst rounds against aircraft, the family's others are plain belted rounds"}}
A33: cal_30 | B33: 30 mm | C33: 1 | D33: 22 | E33: 0 | F33: 0 | G33: ciws;flak | H33: 29 | I33: autocannon_30;autocannon_30_flak;boss_heli_gun;boss_heli_gun_flak;ciws_aa;ciws_aa_flak;gau_gatling;heli_gun;heli_gun_flak;hover_ciws;hover_ciws_flak;hq_flak;hq_flak_ap;ifv_30;ifv_30_flak;jet_cannon;jet_cannon_flak;p26_jotunn_tiny_twin_30_flak;p26_matriarch_sec_autocannon_30;p26_roc_close_twin_30_bmpt;pt14_ixion_30;pt14_sb_v30;scylla_ak230;tower_flak_30;tower_flak_30_ap;twin_30_bmpt;twin_30_bmpt_flak;twin_30_flak;twin_30_flak_ap | J33: Assets/MachineBrigade/Resources/Data/balance.json: weaponFamilyTable[6] | K33: {"id":"cal_30","name":"30 mm","tier":1,"boss":{"damage":22,"core":0,"edge":0},"variants":{"flak":"the 2A38 / AK-630 air-burst (fragmentation, a 2.5 m burst) against aircraft; the family's round is a plain AP / HE belt","ciws":"the AK-630 close-in weapon of the ships and hovercraft: a six-barrel 5,000 rpm belt of light rounds (12 a round at 300 m/s) against the 22 of the 2A42 / M230 class"}}
A34: cal_35 | B34: 35 mm Oerlikon | C34: 1 | D34: 25 | E34: 2.5 | F34: 0 | G34: ap | H34: 13 | I34: boss_flak;boss_flak_ap;flak_35;flak_35_ap;nyx_millennium;p26_behemoth_close_boss_flak;p26_jotunn_close_boss_flak;p26_matriarch_close_boss_flak;p26_moloch_close_boss_flak;p26_nemesis_close_boss_flak;pt14_th_v35;twin_35_ahead;twin_35_ahead_ap | J34: Assets/MachineBrigade/Resources/Data/balance.json: weaponFamilyTable[7] | K34: {"id":"cal_35","name":"35 mm Oerlikon","tier":1,"boss":{"damage":25,"core":2.5,"edge":0},"variants":{"ap":"AP rounds (no burst) loaded against ground targets instead of the air-burst"}}
A35: cal_40 | B35: 40 mm Bofors | C35: 1 | D35: 30 | E35: 0 | F35: 0 | G35: flak;he | H35: 9 | I35: autocannon_40;autocannon_40_flak;bofors_l70;gunship_40mm;gunship_40mm_ap;gunship_40mm_flak;p26_bastion_tiny_autocannon_40;p26_icarus_close_autocannon_40;pt14_mk0_v40 | J35: Assets/MachineBrigade/Resources/Data/balance.json: weaponFamilyTable[8] | K35: {"id":"cal_40","name":"40 mm Bofors","tier":1,"boss":{"damage":30,"core":0,"edge":0},"variants":{"flak":"proximity air-burst (3.5 m) against aircraft","he":"the AC-130's 40 mm HE against the ground (a 3 m burst), not the plain round"}}
A36: cal_57 | B36: 57 mm | C36: 2 | D36: 120 | E36: 3 | F36: 6 | G36: ap;flak | H36: 12 | I36: airship_flak;gun_57_air;gun_57_auto;gun_57mm;gun_57mm_he;mothership_cannon;p26_daedalus_dae57;p26_daedalus_sec_dae57;p26_matriarch_tiny_mothership_cannon;p26_typhon_sec_ty57;p26_typhon_ty57;pt14_dd_v57 | J36: Assets/MachineBrigade/Resources/Data/balance.json: weaponFamilyTable[10] | K36: {"id":"cal_57","name":"57 mm","tier":2,"boss":{"damage":120,"core":3,"edge":6},"variants":{"ap":"AP rounds (kinetic, no burst) instead of HE","flak":"air-burst against aircraft"}}
A37: cal_76 | B37: 76 mm | C37: 2 | H37: 5 | I37: borer_cannon;borer_cannon_he;naval_76;naval_76_guided;pt14_co_v76 | J37: Assets/MachineBrigade/Resources/Data/balance.json: weaponFamilyTable[12] | K37: {"id":"cal_76","name":"76 mm","tier":2}
A38: cal_100_105_ap | B38: 100-105 mm AP | C38: 2 | G38: he | H38: 5 | I38: gun_105_bunker;gun_105_twin;p26_bastion_b100;p26_bastion_direct_b100;siege_gun_105 | J38: Assets/MachineBrigade/Resources/Data/balance.json: weaponFamilyTable[14] | K38: {"id":"cal_100_105_ap","name":"100-105 mm AP","tier":2,"variants":{"he":"a high-explosive second round of an AP gun"}}
A39: cal_100_105_he | B39: 100-105 mm HE | C39: 2 | D39: 300 | E39: 5 | F39: 10 | G39: flak | H39: 11 | I39: gun_100_river;gun_105_bunker_he;gunship_105;gunship_105_guided;naval_100;naval_100_guided;p26_roc_roc105;p26_typhon_direct_ty100;p26_typhon_ty100;pt14_sb_v105;siege_gun_105_he | J39: Assets/MachineBrigade/Resources/Data/balance.json: weaponFamilyTable[13] | K39: {"id":"cal_100_105_he","name":"100-105 mm HE","tier":2,"boss":{"damage":300,"core":5,"edge":10},"variants":{"flak":"the KS-19's time-fused flak against aircraft"}}
A40: cal_120_ap | B40: 120 mm AP | C40: 3 | D40: 260 | E40: 0 | F40: 0 | H40: 13 | I40: gun_105_wheeled;gun_120_twin;gun_120mm;gun_pit_105;p26_behemoth_be120;p26_behemoth_direct_be120;p26_behemoth_tiny_be120;p26_behemoth_tiny_kornet_twin;p26_moloch_direct_mo120ap;p26_moloch_mo120ap;turret_gun_120;turret_gun_120_auto;turret_gun_120_long | J40: Assets/MachineBrigade/Resources/Data/balance.json: weaponFamilyTable[17] | K40: {"id":"cal_120_ap","name":"120 mm AP","tier":3,"boss":{"damage":260,"core":0,"edge":0}}
A41: cal_120_he | B41: 120 mm HE | C41: 3 | D41: 340 | E41: 5 | F41: 10 | G41: mortar | H41: 10 | I41: amos_120;gun_105_wheeled_he;gun_120_twin_he;gun_120mm_he;mortar_120;p26_moloch_main_mo120;p26_moloch_mo120;train_mortar;turret_gun_120_he;turret_gun_120_long_he | J41: Assets/MachineBrigade/Resources/Data/balance.json: weaponFamilyTable[16] | K41: {"id":"cal_120_he","name":"120 mm HE","tier":3,"boss":{"damage":340,"core":5,"edge":10},"variants":{"mortar":"a lobbed mortar bomb (slow, high arc), not a gun's HE shell"}}
A42: cal_125_ap | B42: 125 mm AP | C42: 3 | D42: 400 | E42: 0 | F42: 0 | H42: 9 | I42: gun_105_apfsds;gun_105_long;gun_125_armata_ke;gun_125_elite;p26_ixion_125;p26_jotunn_direct_jo125;p26_jotunn_jo125;p26_nemesis_direct_ne125;p26_nemesis_ne125 | J42: Assets/MachineBrigade/Resources/Data/balance.json: weaponFamilyTable[18] | K42: {"id":"cal_125_ap","name":"125 mm AP","tier":3,"boss":{"damage":400,"core":0,"edge":0}}
A43: cal_125_he | B43: 125 mm HE | C43: 3 | H43: 5 | I43: boss_thermo;gun_105_apfsds_he;gun_105_long_he;gun_125_elite_he;p26_ixion_125_he | J43: Assets/MachineBrigade/Resources/Data/balance.json: weaponFamilyTable[19] | K43: {"id":"cal_125_he","name":"125 mm HE","tier":3}
A44: cal_127_130 | B44: 127-130 mm | C44: 3 | D44: 380 | E44: 5 | F44: 10 | G44: ap | H44: 5 | I44: naval_127;naval_130_twin;p26_leviathan_direct_lev127;p26_leviathan_lev127;pt14_hp_v127 | J44: Assets/MachineBrigade/Resources/Data/balance.json: weaponFamilyTable[20] | K44: {"id":"cal_127_130","name":"127-130 mm","tier":3,"boss":{"damage":380,"core":5,"edge":10},"variants":{"ap":"an armour-piercing round fired direct (Leviathan's AK-127 in its direct-fire role), not the HE shell"}}
A45: cal_140 | B45: 140 mm | C45: 3 | H45: 2 | I45: gun_140_twin;gun_140_twin_he | J45: Assets/MachineBrigade/Resources/Data/balance.json: weaponFamilyTable[21] | K45: {"id":"cal_140","name":"140 mm","tier":3}
A46: cal_152_155 | B46: 152-155 mm | C46: 3 | D46: 600 | E46: 7 | F46: 14 | G46: ap;guided;heat;smart | H46: 39 | I46: bastion_gun;bastion_gun_he;casemate_155;casemate_155_guided;gun_152;gun_152_he;gun_152_heat;gun_152_heat_he;gun_155_coastal;gun_155_coastal_guided;gun_155_sph;gun_155_twin;gun_155_twin_ap;gun_155_twin_coastlr;gun_155_twin_coastlr_guided;gun_155_twin_fort;gun_155_twin_fort_guided;gun_155_twin_long;gun_behemoth;gun_behemoth_guided;howitzer;howitzer_ext;howitzer_fixed;howitzer_fixed_guided;howitzer_guided;naval_155_triple;naval_155_triple_guided;nyx_ags_155;p26_bastion_b155;p26_bastion_main_b155;p26_behemoth_be152;p26_behemoth_main_be152;p26_leviathan_lev155;p26_leviathan_sec_lev155;p26_nemesis_main_ne152;p26_nemesis_ne152;pt14_hp_155;train_gun;train_gun_he | J46: Assets/MachineBrigade/Resources/Data/balance.json: weaponFamilyTable[22] | K46: {"id":"cal_152_155","name":"152-155 mm","tier":3,"boss":{"damage":600,"core":7,"edge":14},"variants":{"ap":"an armour-piercing round fired direct (a tank gun's or a naval gun's AP), not the HE shell","heat":"a shaped-charge (HEAT) round","smart":"a sensor-fuzed or guided shell with submunitions","guided":"a guided shell (one at a time)"}}
A47: cal_203 | B47: 203 mm | C47: 4 | D47: 900 | E47: 8.5 | F47: 17 | H47: 7 | I47: boss_howitzer;boss_howitzer_guided;cruiser_203;cruiser_203_guided;gun_203_siege;p26_jotunn_jo203;pt14_co_203 | J47: Assets/MachineBrigade/Resources/Data/balance.json: weaponFamilyTable[23] | K47: {"id":"cal_203","name":"203 mm","tier":4,"boss":{"damage":900,"core":8.5,"edge":17}}
A48: cal_240 | B48: 240 mm | C48: 4 | D48: 1100 | E48: 10 | F48: 20 | H48: 5 | I48: boss_mortar;mortar_240;p26_bastion_b240;p26_bastion_sec_b240;siege_mortar_240 | J48: Assets/MachineBrigade/Resources/Data/balance.json: weaponFamilyTable[24] | K48: {"id":"cal_240","name":"240 mm","tier":4,"boss":{"damage":1100,"core":10,"edge":20}}
A49: cal_406 | B49: 406 mm | C49: 5 | D49: 2400 | E49: 14 | F49: 24 | H49: 3 | I49: leviathan_460;leviathan_460_guided;p26_leviathan_lev406 | J49: Assets/MachineBrigade/Resources/Data/balance.json: weaponFamilyTable[25] | K49: {"id":"cal_406","name":"406 mm","tier":5,"boss":{"damage":2400,"core":14,"edge":24}}
A50: cal_800 | B50: 800 mm super-gun | C50: 5 | H50: 0 | J50: Assets/MachineBrigade/Resources/Data/balance.json: weaponFamilyTable[26] | K50: {"id":"cal_800","name":"800 mm super-gun","tier":5}
A51: cruise_3m_54_kalibr | B51: cruise_3m_54_kalibr | C51: 4 | H51: 2 | I51: hydra_club_s;leviathan_cruise | J51: Assets/MachineBrigade/Resources/Data/balance.json: weaponFamilyTable[60] | K51: {"id":"cruise_3m_54_kalibr","name":"cruise_3m_54_kalibr","tier":4}
A52: cruise_agm_158_jassm | B52: cruise_agm_158_jassm | C52: 4 | H52: 1 | I52: jassm | J52: Assets/MachineBrigade/Resources/Data/balance.json: weaponFamilyTable[61] | K52: {"id":"cruise_agm_158_jassm","name":"cruise_agm_158_jassm","tier":4}
A53: cruise_kh_101 | B53: cruise_kh_101 | C53: 4 | H53: 1 | I53: air_cruise_missile | J53: Assets/MachineBrigade/Resources/Data/balance.json: weaponFamilyTable[62] | K53: {"id":"cruise_kh_101","name":"cruise_kh_101","tier":4}
A54: cruise_nsm_coastal_defence | B54: cruise_nsm_coastal_defence | C54: 4 | H54: 0 | J54: Assets/MachineBrigade/Resources/Data/balance.json: weaponFamilyTable[63] | K54: {"id":"cruise_nsm_coastal_defence","name":"cruise_nsm_coastal_defence","tier":4}
A55: cruise_typhon_mrc | B55: cruise_typhon_mrc | C55: 4 | H55: 2 | I55: cruise_missile_ground;nyx_tomahawk | J55: Assets/MachineBrigade/Resources/Data/balance.json: weaponFamilyTable[64] | K55: {"id":"cruise_typhon_mrc","name":"cruise_typhon_mrc","tier":4}
A56: drone_coyote_block_2 | B56: drone_coyote_block_2 | C56: 2 | H56: 0 | J56: Assets/MachineBrigade/Resources/Data/balance.json: weaponFamilyTable[65] | K56: {"id":"drone_coyote_block_2","name":"drone_coyote_block_2","tier":2}
A57: drone_fibre_optic_fpv_drone | B57: drone_fibre_optic_fpv_drone | C57: 2 | H57: 0 | J57: Assets/MachineBrigade/Resources/Data/balance.json: weaponFamilyTable[66] | K57: {"id":"drone_fibre_optic_fpv_drone","name":"drone_fibre_optic_fpv_drone","tier":2}
A58: drone_fpv_drone | B58: drone_fpv_drone | C58: 2 | H58: 5 | I58: airship_drones;fpv_hangar;fpv_hangar_swarm;fpv_swarm;swarm_drones | J58: Assets/MachineBrigade/Resources/Data/balance.json: weaponFamilyTable[67] | K58: {"id":"drone_fpv_drone","name":"drone_fpv_drone","tier":2}
A59: drone_interceptor_drone | B59: drone_interceptor_drone | C59: 2 | H59: 0 | J59: Assets/MachineBrigade/Resources/Data/balance.json: weaponFamilyTable[68] | K59: {"id":"drone_interceptor_drone","name":"drone_interceptor_drone","tier":2}
A60: drone_shahed_136 | B60: drone_shahed_136 | C60: 3 | H60: 1 | I60: shahed | J60: Assets/MachineBrigade/Resources/Data/balance.json: weaponFamilyTable[69] | K60: {"id":"drone_shahed_136","name":"drone_shahed_136","tier":3}
A61: drone_switchblade_300 | B61: drone_switchblade_300 | C61: 2 | H61: 0 | J61: Assets/MachineBrigade/Resources/Data/balance.json: weaponFamilyTable[70] | K61: {"id":"drone_switchblade_300","name":"drone_switchblade_300","tier":2}
A62: drone_zala_lancet_3 | B62: drone_zala_lancet_3 | C62: 2 | H62: 3 | I62: lancet;lancet_hangar;mothership_drones | J62: Assets/MachineBrigade/Resources/Data/balance.json: weaponFamilyTable[71] | K62: {"id":"drone_zala_lancet_3","name":"drone_zala_lancet_3","tier":2}
A63: drone_zala_lancet_3_swarm | B63: drone_zala_lancet_3_swarm | C63: 2 | H63: 2 | I63: locust_drones;p26_matriarch_ma_drones | J63: Assets/MachineBrigade/Resources/Data/balance.json: weaponFamilyTable[72] | K63: {"id":"drone_zala_lancet_3_swarm","name":"drone_zala_lancet_3_swarm","tier":2}
A64: flame_flamethrower | B64: flame_flamethrower | C64: 1 | H64: 3 | I64: boss_flamer;bunker_flame;flamethrower | J64: Assets/MachineBrigade/Resources/Data/balance.json: weaponFamilyTable[73] | K64: {"id":"flame_flamethrower","name":"flame_flamethrower","tier":1}
A65: gl_40 | B65: 40 mm grenade launcher | C65: 1 | H65: 2 | I65: agl_40;tower_agl | J65: Assets/MachineBrigade/Resources/Data/balance.json: weaponFamilyTable[9] | K65: {"id":"gl_40","name":"40 mm grenade launcher","tier":1}
A66: gungnir_emrg | B66: EMRG electromagnetic railgun (Gungnir) | C66: 5 | H66: 0 | J66: Assets/MachineBrigade/Resources/Data/balance.json: weaponFamilyTable[36] | K66: {"id":"gungnir_emrg","name":"EMRG electromagnetic railgun (Gungnir)","tier":5}
A67: laser_50_kw_laser | B67: laser_50_kw_laser | C67: 1 | H67: 2 | I67: laser_50kw;pt14_th_pd | J67: Assets/MachineBrigade/Resources/Data/balance.json: weaponFamilyTable[74] | K67: {"id":"laser_50_kw_laser","name":"laser_50_kw_laser","tier":1}
A68: laser_focused_laser | B68: laser_focused_laser | C68: 1 | H68: 1 | I68: focus_laser | J68: Assets/MachineBrigade/Resources/Data/balance.json: weaponFamilyTable[75] | K68: {"id":"laser_focused_laser","name":"laser_focused_laser","tier":1}
A69: laser_iron_beam_laser | B69: laser_iron_beam_laser | C69: 1 | H69: 1 | I69: hel_beam | J69: Assets/MachineBrigade/Resources/Data/balance.json: weaponFamilyTable[76] | K69: {"id":"laser_iron_beam_laser","name":"laser_iron_beam_laser","tier":1}
A70: laser_laser | B70: laser_laser | C70: 1 | H70: 2 | I70: orbital_laser;p26_icarus_sec_orbital_laser | J70: Assets/MachineBrigade/Resources/Data/balance.json: weaponFamilyTable[77] | K70: {"id":"laser_laser","name":"laser_laser","tier":1}
A71: laser_targeting_laser | B71: laser_targeting_laser | C71: 1 | H71: 2 | I71: p26_daedalus_dae_laser;p26_daedalus_direct_dae_laser | J71: Assets/MachineBrigade/Resources/Data/balance.json: weaponFamilyTable[78] | K71: {"id":"laser_targeting_laser","name":"laser_targeting_laser","tier":1}
A72: laser_tower | B72: laser_tower | C72: 1 | H72: 3 | I72: p26_icarus_direct_ic_laser;p26_icarus_ic_laser;pt14_hp_vlaser | J72: Assets/MachineBrigade/Resources/Data/balance.json: weaponFamilyTable[79] | K72: {"id":"laser_tower","name":"laser_tower","tier":1}
A73: melee_bucket_wheel | B73: melee_bucket_wheel | C73: 0 | H73: 0 | J73: Assets/MachineBrigade/Resources/Data/balance.json: weaponFamilyTable[80] | K73: {"id":"melee_bucket_wheel","name":"melee_bucket_wheel","tier":0}
A74: melee_dozer_blade | B74: melee_dozer_blade | C74: 0 | H74: 1 | I74: dozer_blade | J74: Assets/MachineBrigade/Resources/Data/balance.json: weaponFamilyTable[81] | K74: {"id":"melee_dozer_blade","name":"melee_dozer_blade","tier":0}
A75: melee_drill_head | B75: melee_drill_head | C75: 0 | H75: 1 | I75: borer_drill | J75: Assets/MachineBrigade/Resources/Data/balance.json: weaponFamilyTable[82] | K75: {"id":"melee_drill_head","name":"melee_drill_head","tier":0}
A76: msl_agm_88_harm | B76: msl_agm_88_harm | C76: 3 | H76: 0 | J76: Assets/MachineBrigade/Resources/Data/balance.json: weaponFamilyTable[83] | K76: {"id":"msl_agm_88_harm","name":"msl_agm_88_harm","tier":3}
A77: msl_nsm_p_800_oniks | B77: msl_nsm_p_800_oniks | C77: 4 | H77: 3 | I77: anti_ship_missile;pt14_hp_nsm;scylla_kh35 | J77: Assets/MachineBrigade/Resources/Data/balance.json: weaponFamilyTable[84] | K77: {"id":"msl_nsm_p_800_oniks","name":"msl_nsm_p_800_oniks","tier":4}
A78: rail_coilgun | B78: rail_coilgun | C78: 3 | H78: 2 | I78: coilgun;p26_icarus_ic_coil | J78: Assets/MachineBrigade/Resources/Data/balance.json: weaponFamilyTable[86] | K78: {"id":"rail_coilgun","name":"rail_coilgun","tier":3}
A79: rail_heavy_coilgun | B79: heavy coilgun (64 MJ) | C79: 3 | H79: 1 | I79: p26_icarus_main_ic_coil | J79: Assets/MachineBrigade/Resources/Data/balance.json: weaponFamilyTable[85] | K79: {"id":"rail_heavy_coilgun","name":"heavy coilgun (64 MJ)","tier":3}
A80: rail_railgun | B80: rail_railgun | C80: 3 | H80: 2 | I80: boss_railgun;railgun | J80: Assets/MachineBrigade/Resources/Data/balance.json: weaponFamilyTable[87] | K80: {"id":"rail_railgun","name":"rail_railgun","tier":3}
A81: rcl_73 | B81: 73 mm recoilless | C81: 2 | H81: 1 | I81: spg9_73mm | J81: Assets/MachineBrigade/Resources/Data/balance.json: weaponFamilyTable[11] | K81: {"id":"rcl_73","name":"73 mm recoilless","tier":2}
A82: rcl_106 | B82: 106 mm recoilless | C82: 2 | H82: 1 | I82: recoilless_106 | J82: Assets/MachineBrigade/Resources/Data/balance.json: weaponFamilyTable[15] | K82: {"id":"rcl_106","name":"106 mm recoilless","tier":2}
A83: rkt_70_80 | B83: 70-80 mm rockets | C83: 2 | G83: guided | H83: 8 | I83: apkws_rocket;boat_rockets;gunship_rockets;heli_rockets;hind_rockets;jet_rockets;s8_pods;scout_rockets | J83: Assets/MachineBrigade/Resources/Data/balance.json: weaponFamilyTable[27] | K83: {"id":"rkt_70_80","name":"70-80 mm rockets","tier":2,"variants":{"guided":"a laser-guided rocket (APKWS)"}}
A84: rkt_107 | B84: 107 mm rockets | C84: 2 | H84: 1 | I84: technical_rockets | J84: Assets/MachineBrigade/Resources/Data/balance.json: weaponFamilyTable[28] | K84: {"id":"rkt_107","name":"107 mm rockets","tier":2}
A85: rkt_140 | B85: 140 mm rockets | C85: 3 | H85: 1 | I85: hover_rockets | J85: Assets/MachineBrigade/Resources/Data/balance.json: weaponFamilyTable[30] | K85: {"id":"rkt_140","name":"140 mm rockets","tier":3}
A86: rkt_gmlrs_227 | B86: GMLRS 227 mm | C86: 4 | G86: cluster | H86: 3 | I86: mlrs_elite;mlrs_rockets;turret_gmlrs | J86: Assets/MachineBrigade/Resources/Data/balance.json: weaponFamilyTable[32] | K86: {"id":"rkt_gmlrs_227","name":"GMLRS 227 mm","tier":4,"variants":{"cluster":"the M30's cluster warhead"}}
A87: rkt_grad_122 | B87: Grad 122 mm rockets | C87: 3 | D87: 200 | E87: 4.5 | F87: 9 | G87: cluster;thermobaric | H87: 11 | I87: boss_rockets;grad_cluster;grad_rockets;p26_behemoth_be_rockets;p26_behemoth_sec_be_rockets;p26_nemesis_sec_boss_rockets;pt14_ixion_grad;pt14_train_grad;turret_rockets;turret_rockets_cluster;turret_thermobaric | J87: Assets/MachineBrigade/Resources/Data/balance.json: weaponFamilyTable[29] | K87: {"id":"rkt_grad_122","name":"Grad 122 mm rockets","tier":3,"boss":{"damage":200,"core":4.5,"edge":9},"variants":{"thermobaric":"a thermobaric warhead","cluster":"a cluster warhead (bomblets)"}}
A88: rkt_smerch_300 | B88: Smerch 300 mm rockets | C88: 4 | D88: 450 | E88: 8 | F88: 16 | H88: 3 | I88: p26_jotunn_jo_rockets;p26_jotunn_sec_jo_rockets;rockets_300mm | J88: Assets/MachineBrigade/Resources/Data/balance.json: weaponFamilyTable[33] | K88: {"id":"rkt_smerch_300","name":"Smerch 300 mm rockets","tier":4,"boss":{"damage":450,"core":8,"edge":16}}
A89: rkt_tos_220 | B89: TOS-1A 220 mm thermobaric | C89: 4 | H89: 1 | I89: thermobaric_rockets | J89: Assets/MachineBrigade/Resources/Data/balance.json: weaponFamilyTable[31] | K89: {"id":"rkt_tos_220","name":"TOS-1A 220 mm thermobaric","tier":4}
A90: sam_9k38_igla_v | B90: sam_9k38_igla_v | C90: 2 | H90: 1 | I90: igla_v | J90: Assets/MachineBrigade/Resources/Data/balance.json: weaponFamilyTable[89] | K90: {"id":"sam_9k38_igla_v","name":"sam_9k38_igla_v","tier":2}
A91: sam_9m317_buk | B91: sam_9m317_buk | C91: 2 | H91: 3 | I91: buk_launcher;sam_long;sam_post | J91: Assets/MachineBrigade/Resources/Data/balance.json: weaponFamilyTable[90] | K91: {"id":"sam_9m317_buk","name":"sam_9m317_buk","tier":2}
A92: sam_57e6 | B92: sam_57e6 | C92: 2 | H92: 1 | I92: missile_57e6 | J92: Assets/MachineBrigade/Resources/Data/balance.json: weaponFamilyTable[88] | K92: {"id":"sam_57e6","name":"sam_57e6","tier":2}
A93: sam_aim_9_sidewinder | B93: sam_aim_9_sidewinder | C93: 2 | H93: 0 | J93: Assets/MachineBrigade/Resources/Data/balance.json: weaponFamilyTable[92] | K93: {"id":"sam_aim_9_sidewinder","name":"sam_aim_9_sidewinder","tier":2}
A94: sam_aim_9x_sidewinder | B94: sam_aim_9x_sidewinder | C94: 2 | H94: 1 | I94: wvr_aam | J94: Assets/MachineBrigade/Resources/Data/balance.json: weaponFamilyTable[93] | K94: {"id":"sam_aim_9x_sidewinder","name":"sam_aim_9x_sidewinder","tier":2}
A95: sam_aim_120_amraam | B95: sam_aim_120_amraam | C95: 2 | H95: 1 | I95: air_to_air | J95: Assets/MachineBrigade/Resources/Data/balance.json: weaponFamilyTable[91] | K95: {"id":"sam_aim_120_amraam","name":"sam_aim_120_amraam","tier":2}
A96: sam_fim_92_stinger | B96: sam_fim_92_stinger | C96: 2 | H96: 2 | I96: stinger_atas;stinger_post | J96: Assets/MachineBrigade/Resources/Data/balance.json: weaponFamilyTable[94] | K96: {"id":"sam_fim_92_stinger","name":"sam_fim_92_stinger","tier":2}
A97: sam_mim_104_patriot_pac_2 | B97: sam_mim_104_patriot_pac_2 | C97: 2 | H97: 3 | I97: patriot;sam_battery;sam_battery_lrr | J97: Assets/MachineBrigade/Resources/Data/balance.json: weaponFamilyTable[95] | K97: {"id":"sam_mim_104_patriot_pac_2","name":"sam_mim_104_patriot_pac_2","tier":2}
A98: sam_patriot_pac_3_mse | B98: sam_patriot_pac_3_mse | C98: 2 | H98: 1 | I98: sam_pac3 | J98: Assets/MachineBrigade/Resources/Data/balance.json: weaponFamilyTable[96] | K98: {"id":"sam_patriot_pac_3_mse","name":"sam_patriot_pac_3_mse","tier":2}
A99: sam_r_37m | B99: sam_r_37m | C99: 2 | H99: 0 | J99: Assets/MachineBrigade/Resources/Data/balance.json: weaponFamilyTable[97] | K99: {"id":"sam_r_37m","name":"sam_r_37m","tier":2}
A100: sam_r_60 | B100: sam_r_60 | C100: 2 | H100: 1 | I100: r60 | J100: Assets/MachineBrigade/Resources/Data/balance.json: weaponFamilyTable[98] | K100: {"id":"sam_r_60","name":"sam_r_60","tier":2}
...

Sheet Ho_vu_khi_bien_the
A1: id | B1: ho_vu_khi_id | C1: thu_tu | D1: bien_the | E1: ly_do | F1: nguon | G1: raw_json
A2: cal_25/flak | B2: cal_25 | C2: 0 | D2: flak | E2: air-burst rounds against aircraft, the family's others are plain belted rounds | F2: Assets/MachineBrigade/Resources/Data/balance.json: weaponFamilyTable[5].variants.flak | G2: {"flak":"air-burst rounds against aircraft, the family's others are plain belted rounds"}
A3: cal_30/ciws | B3: cal_30 | C3: 0 | D3: ciws | E3: the AK-630 close-in weapon of the ships and hovercraft: a six-barrel 5,000 rpm belt of light rounds (12 a round at 300 m/s) against the 22 of the 2A42 / M230 class | F3: Assets/MachineBrigade/Resources/Data/balance.json: weaponFamilyTable[6].variants.ciws | G3: {"ciws":"the AK-630 close-in weapon of the ships and hovercraft: a six-barrel 5,000 rpm belt of light rounds (12 a round at 300 m/s) against the 22 of the 2A42 / M230 class"}
A4: cal_30/flak | B4: cal_30 | C4: 1 | D4: flak | E4: the 2A38 / AK-630 air-burst (fragmentation, a 2.5 m burst) against aircraft; the family's round is a plain AP / HE belt | F4: Assets/MachineBrigade/Resources/Data/balance.json: weaponFamilyTable[6].variants.flak | G4: {"flak":"the 2A38 / AK-630 air-burst (fragmentation, a 2.5 m burst) against aircraft; the family's round is a plain AP / HE belt"}
A5: cal_35/ap | B5: cal_35 | C5: 0 | D5: ap | E5: AP rounds (no burst) loaded against ground targets instead of the air-burst | F5: Assets/MachineBrigade/Resources/Data/balance.json: weaponFamilyTable[7].variants.ap | G5: {"ap":"AP rounds (no burst) loaded against ground targets instead of the air-burst"}
A6: cal_40/flak | B6: cal_40 | C6: 0 | D6: flak | E6: proximity air-burst (3.5 m) against aircraft | F6: Assets/MachineBrigade/Resources/Data/balance.json: weaponFamilyTable[8].variants.flak | G6: {"flak":"proximity air-burst (3.5 m) against aircraft"}
A7: cal_40/he | B7: cal_40 | C7: 1 | D7: he | E7: the AC-130's 40 mm HE against the ground (a 3 m burst), not the plain round | F7: Assets/MachineBrigade/Resources/Data/balance.json: weaponFamilyTable[8].variants.he | G7: {"he":"the AC-130's 40 mm HE against the ground (a 3 m burst), not the plain round"}
A8: cal_57/ap | B8: cal_57 | C8: 0 | D8: ap | E8: AP rounds (kinetic, no burst) instead of HE | F8: Assets/MachineBrigade/Resources/Data/balance.json: weaponFamilyTable[10].variants.ap | G8: {"ap":"AP rounds (kinetic, no burst) instead of HE"}
A9: cal_57/flak | B9: cal_57 | C9: 1 | D9: flak | E9: air-burst against aircraft | F9: Assets/MachineBrigade/Resources/Data/balance.json: weaponFamilyTable[10].variants.flak | G9: {"flak":"air-burst against aircraft"}
A10: cal_100_105_ap/he | B10: cal_100_105_ap | C10: 0 | D10: he | E10: a high-explosive second round of an AP gun | F10: Assets/MachineBrigade/Resources/Data/balance.json: weaponFamilyTable[14].variants.he | G10: {"he":"a high-explosive second round of an AP gun"}
A11: cal_100_105_he/flak | B11: cal_100_105_he | C11: 0 | D11: flak | E11: the KS-19's time-fused flak against aircraft | F11: Assets/MachineBrigade/Resources/Data/balance.json: weaponFamilyTable[13].variants.flak | G11: {"flak":"the KS-19's time-fused flak against aircraft"}
A12: cal_120_he/mortar | B12: cal_120_he | C12: 0 | D12: mortar | E12: a lobbed mortar bomb (slow, high arc), not a gun's HE shell | F12: Assets/MachineBrigade/Resources/Data/balance.json: weaponFamilyTable[16].variants.mortar | G12: {"mortar":"a lobbed mortar bomb (slow, high arc), not a gun's HE shell"}
A13: cal_127_130/ap | B13: cal_127_130 | C13: 0 | D13: ap | E13: an armour-piercing round fired direct (Leviathan's AK-127 in its direct-fire role), not the HE shell | F13: Assets/MachineBrigade/Resources/Data/balance.json: weaponFamilyTable[20].variants.ap | G13: {"ap":"an armour-piercing round fired direct (Leviathan's AK-127 in its direct-fire role), not the HE shell"}
... A21: rkt_grad_122/thermobaric | B21: rkt_grad_122 | C21: 1 | D21: thermobaric | E21: a thermobaric warhead | F21: Assets/MachineBrigade/Resources/Data/balance.json: weaponFamilyTable[29].variants.thermobaric | G21: {"thermobaric":"a thermobaric warhead"}

Sheet Dong_vu_khi
A1: id | B1: ten_that | C1: khoi_nguon | D1: so_vu_khi | E1: flight_profile | F1: projectile_model | G1: projectile_scale | H1: projectile_speed_m_s | I1: round_length | J1: round_weight | K1: splash_m | L1: nguon | M1: raw_json
A2: 2a38_30_mm | B2: 2A38 30 mm | C2: weaponFamilies | D2: 3 | H2: 280 | J2: 7.5 | K2: 2.5 | L2: Assets/MachineBrigade/Resources/Data/balance.json: weaponFamilies[0] | M2: {"id":"2a38_30_mm","real":"2A38 30 mm","projectileSpeed":280,"splash":2.5,"roundWeight":7.5}
A3: 2a38_30_mm_ap | B3: 2A38 30 mm AP | C3: secondRounds.families | D3: 3 | H3: 280 | J3: 7.5 | K3: 0 | L3: Assets/MachineBrigade/Resources/Data/balance.json: secondRounds.families[14] | M3: {"id":"2a38_30_mm_ap","real":"2A38 30 mm AP","projectileSpeed":280,"splash":0,"roundWeight":7.5}
A4: 2a42_30_mm | B4: 2A42 30 mm | C4: weaponFamilies | D4: 3 | H4: 200 | J4: 32 | K4: 0 | L4: Assets/MachineBrigade/Resources/Data/balance.json: weaponFamilies[1] | M4: {"id":"2a42_30_mm","real":"2A42 30 mm","projectileSpeed":200,"splash":0,"roundWeight":32}
A5: 2a42_30_mm_air_burst | B5: 2A42 30 mm air-burst | C5: secondRounds.families | D5: 3 | H5: 200 | J5: 32 | K5: 2.5 | L5: Assets/MachineBrigade/Resources/Data/balance.json: secondRounds.families[1] | M5: {"id":"2a42_30_mm_air_burst","real":"2A42 30 mm air-burst","projectileSpeed":200,"splash":2.5,"roundWeight":32}
A6: 2a75_125_mm_he | B6: 2A75 125 mm HE | C6: secondRounds.families | D6: 2 | H6: 260 | J6: 345 | K6: 3 | L6: Assets/MachineBrigade/Resources/Data/balance.json: secondRounds.families[8] | M6: {"id":"2a75_125_mm_he","real":"2A75 125 mm HE","projectileSpeed":260,"splash":3,"roundWeight":345}
A7: 2a83_152_mm | B7: 2A83 152 mm | C7: weaponFamilies | D7: 2 | H7: 160 | J7: 343 | K7: 2.5 | L7: Assets/MachineBrigade/Resources/Data/balance.json: weaponFamilies[2] | M7: {"id":"2a83_152_mm","real":"2A83 152 mm","projectileSpeed":160,"splash":2.5,"roundWeight":343}
A8: 2a83_152_mm_he_frag | B8: 2A83 152 mm HE-FRAG | C8: secondRounds.families | D8: 3 | H8: 150 | J8: 343 | K8: 6.5 | L8: Assets/MachineBrigade/Resources/Data/balance.json: secondRounds.families[2] | M8: {"id":"2a83_152_mm_he_frag","real":"2A83 152 mm HE-FRAG","projectileSpeed":150,"splash":6.5,"roundWeight":343}
A9: 2b8_240_mm | B9: 2B8 240 mm | C9: weaponFamilies | D9: 3 | F9: mortar_bomb | G9: 1.3333 | H9: 60 | I9: 1.2 | J9: 543 | K9: 9 | L9: Assets/MachineBrigade/Resources/Data/balance.json: weaponFamilies[4] | M9: {"id":"2b8_240_mm","real":"2B8 240 mm","projectileSpeed":60,"splash":9,"projectileModel":"mortar_bomb","roundWeight":543,"roundLength":1.2,"projectileScale":1.3333}
A10: 2b11_120_mm | B10: 2B11 120 mm | C10: weaponFamilies | D10: 2 | F10: mortar_bomb | H10: 60 | K10: 5 | L10: Assets/MachineBrigade/Resources/Data/balance.json: weaponFamilies[3] | M10: {"id":"2b11_120_mm","real":"2B11 120 mm","projectileSpeed":60,"splash":5,"projectileModel":"mortar_bomb"}
A11: 9m120_ataka | B11: 9M120 Ataka | C11: weaponFamilies | D11: 0 | F11: atgm_ataka | H11: 120 | K11: 0 | L11: Assets/MachineBrigade/Resources/Data/balance.json: weaponFamilies[5] | M11: {"id":"9m120_ataka","real":"9M120 Ataka","projectileSpeed":120,"splash":0,"projectileModel":"atgm_ataka"}
A12: 9m133_kornet | B12: 9M133 Kornet | C12: weaponFamilies | D12: 7 | F12: atgm_kornet | G12: 0.7385 | H12: 80 | I12: 0.96 | K12: 0 | L12: Assets/MachineBrigade/Resources/Data/balance.json: weaponFamilies[6] | M12: {"id":"9m133_kornet","real":"9M133 Kornet","projectileSpeed":80,"splash":0,"projectileModel":"atgm_kornet","roundLength":0.96,"projectileScale":0.7385}
A13: 9m317_buk | B13: 9M317 Buk | C13: weaponFamilies | D13: 2 | F13: buk | G13: 1.2333 | H13: 250 | I13: 4.44 | K13: 2 | L13: Assets/MachineBrigade/Resources/Data/balance.json: weaponFamilies[7] | M13: {"id":"9m317_buk","real":"9M317 Buk","projectileSpeed":250,"splash":2,"projectileModel":"buk","roundLength":4.44,"projectileScale":1.2333}
A14: agm_88_harm | B14: AGM-88 HARM | C14: weaponFamilies | D14: 0 | H14: 210 | I14: 2.09 | J14: 360 | K14: 4 | L14: Assets/MachineBrigade/Resources/Data/balance.json: weaponFamilies[36] | M14: {"id":"agm_88_harm","real":"AGM-88 HARM","projectileSpeed":210,"splash":4,"roundWeight":360,"roundLength":2.09}
A15: agm_114_hellfire | B15: AGM-114 Hellfire | C15: weaponFamilies | D15: 3 | F15: hellfire_longbow | H15: 110 | J15: 270 | K15: 0 | L15: Assets/MachineBrigade/Resources/Data/balance.json: weaponFamilies[8] | M15: {"id":"agm_114_hellfire","real":"AGM-114 Hellfire","projectileSpeed":110,"splash":0,"projectileModel":"hellfire_longbow","roundWeight":270}
A16: aim_9_sidewinder | B16: AIM-9 Sidewinder | C16: weaponFamilies | D16: 1 | F16: aim9 | H16: 210 | J16: 260 | K16: 1.5 | L16: Assets/MachineBrigade/Resources/Data/balance.json: weaponFamilies[9] | M16: {"id":"aim_9_sidewinder","real":"AIM-9 Sidewinder","projectileSpeed":210,"splash":1.5,"projectileModel":"aim9","roundWeight":260}
A17: ak_630_30_mm | B17: AK-630 30 mm | C17: weaponFamilies | D17: 2 | H17: 300 | K17: 0 | L17: Assets/MachineBrigade/Resources/Data/balance.json: weaponFamilies[10] | M17: {"id":"ak_630_30_mm","real":"AK-630 30 mm","projectileSpeed":300,"splash":0}
A18: ak_630_30_mm_air_burst | B18: AK-630 30 mm air-burst | C18: secondRounds.families | D18: 2 | H18: 300 | K18: 2.5 | L18: Assets/MachineBrigade/Resources/Data/balance.json: secondRounds.families[7] | M18: {"id":"ak_630_30_mm_air_burst","real":"AK-630 30 mm air-burst","projectileSpeed":300,"splash":2.5}
A19: apkws | B19: APKWS (laser-guided Hydra 70) | C19: weaponFamilies | D19: 1 | F19: apkws | H19: 180 | I19: 0.8 | J19: 15 | K19: 2 | L19: Assets/MachineBrigade/Resources/Data/balance.json: weaponFamilies[37] | M19: {"id":"apkws","real":"APKWS (laser-guided Hydra 70)","projectileSpeed":180,"splash":2,"projectileModel":"apkws","roundWeight":15,"roundLength":0.8}
A20: bm_21_grad_122_mm | B20: BM-21 Grad 122 mm | C20: weaponFamilies | D20: 2 | F20: grad | H20: 130 | J20: 66 | K20: 4.5 | L20: Assets/MachineBrigade/Resources/Data/balance.json: weaponFamilies[11] | M20: {"id":"bm_21_grad_122_mm","real":"BM-21 Grad 122 mm","projectileSpeed":130,"splash":4.5,"projectileModel":"grad","roundWeight":66}
A21: bm_21_grad_122_mm_2 | B21: BM-21 Grad 122 mm | C21: weaponFamilies | D21: 2 | F21: grad_cluster | H21: 130 | J21: 66 | K21: 4 | L21: Assets/MachineBrigade/Resources/Data/balance.json: weaponFamilies[12] | M21: {"id":"bm_21_grad_122_mm_2","real":"BM-21 Grad 122 mm","projectileSpeed":130,"splash":4,"projectileModel":"grad_cluster","roundWeight":66}
A22: bofors_40_mm_l_70 | B22: Bofors 40 mm L/70 | C22: weaponFamilies | D22: 1 | H22: 220 | J22: 51 | K22: 2.5 | L22: Assets/MachineBrigade/Resources/Data/balance.json: weaponFamilies[32] | M22: {"id":"bofors_40_mm_l_70","real":"Bofors 40 mm L/70","projectileSpeed":220,"splash":2.5,"roundWeight":51}
A23: cbu_97_sfw | B23: CBU-97 Sensor Fuzed Weapon | C23: weaponFamilies | D23: 0 | H23: 35 | I23: 1.17 | J23: 450 | K23: 3 | L23: Assets/MachineBrigade/Resources/Data/balance.json: weaponFamilies[33] | M23: {"id":"cbu_97_sfw","real":"CBU-97 Sensor Fuzed Weapon","projectileSpeed":35,"splash":3,"roundWeight":450,"roundLength":1.17}
A24: coyote_block_2 | B24: Coyote Block 2 | C24: weaponFamilies | D24: 0 | H24: 40 | I24: 0.8 | J24: 5 | K24: 2 | L24: Assets/MachineBrigade/Resources/Data/balance.json: weaponFamilies[38] | M24: {"id":"coyote_block_2","real":"Coyote Block 2","projectileSpeed":40,"splash":2,"roundWeight":5,"roundLength":0.8}
A25: fpv_drone | B25: FPV drone | C25: weaponFamilies | D25: 5 | F25: fpv_drone | G25: 1.4551 | H25: 26 | I25: 0.8 | K25: 2.5 | L25: Assets/MachineBrigade/Resources/Data/balance.json: weaponFamilies[13] | M25: {"id":"fpv_drone","real":"FPV drone","projectileSpeed":26,"splash":2.5,"projectileModel":"fpv_drone","roundLength":0.8,"projectileScale":1.4551}
A26: gbu_28 | B26: GBU-28 | C26: weaponFamilies | D26: 0 | H26: 35 | I26: 2.92 | J26: 2100 | K26: 6 | L26: Assets/MachineBrigade/Resources/Data/balance.json: weaponFamilies[34] | M26: {"id":"gbu_28","real":"GBU-28","projectileSpeed":35,"splash":6,"roundWeight":2100,"roundLength":2.92}
A27: hydra_70_mm | B27: Hydra 70 mm | C27: weaponFamilies | D27: 3 | F27: hydra | H27: 180 | J27: 61 | K27: 3 | L27: Assets/MachineBrigade/Resources/Data/balance.json: weaponFamilies[14] | M27: {"id":"hydra_70_mm","real":"Hydra 70 mm","projectileSpeed":180,"splash":3,"projectileModel":"hydra","roundWeight":61}
A28: l7_105_mm | B28: L7 105 mm | C28: weaponFamilies | D28: 3 | H28: 190 | K28: 1.5 | L28: Assets/MachineBrigade/Resources/Data/balance.json: weaponFamilies[15] | M28: {"id":"l7_105_mm","real":"L7 105 mm","projectileSpeed":190,"splash":1.5}
A29: l7_105_mm_he | B29: L7 105 mm HE | C29: secondRounds.families | D29: 1 | H29: 190 | K29: 3 | L29: Assets/MachineBrigade/Resources/Data/balance.json: secondRounds.families[9] | M29: {"id":"l7_105_mm_he","real":"L7 105 mm HE","projectileSpeed":190,"splash":3}
A30: l7_105_mm_he_bunker | B30: L7 105 mm HE | C30: secondRounds.families | D30: 1 | H30: 190 | K30: 5.5 | L30: Assets/MachineBrigade/Resources/Data/balance.json: secondRounds.families[10] | M30: {"id":"l7_105_mm_he_bunker","real":"L7 105 mm HE","projectileSpeed":190,"splash":5.5}
A31: m2_browning_12_7_mm | B31: M2 Browning 12.7 mm | C31: weaponFamilies | D31: 7 | H31: 230 | J31: 11 | K31: 0 | L31: Assets/MachineBrigade/Resources/Data/balance.json: weaponFamilies[16] | M31: {"id":"m2_browning_12_7_mm","real":"M2 Browning 12.7 mm","projectileSpeed":230,"splash":0,"roundWeight":11}
A32: m2_browning_12_7_mm_api | B32: M2 Browning 12.7 mm API | C32: secondRounds.families | D32: 7 | H32: 230 | J32: 11 | K32: 0 | L32: Assets/MachineBrigade/Resources/Data/balance.json: secondRounds.families[13] | M32: {"id":"m2_browning_12_7_mm_api","real":"M2 Browning 12.7 mm API","projectileSpeed":230,"splash":0,"roundWeight":11}
A33: m31_gmlrs_227_mm | B33: M31 GMLRS 227 mm | C33: weaponFamilies | D33: 2 | F33: gmlrs | H33: 140 | J33: 160 | K33: 4.5 | L33: Assets/MachineBrigade/Resources/Data/balance.json: weaponFamilies[22] | M33: {"id":"m31_gmlrs_227_mm","real":"M31 GMLRS 227 mm","projectileSpeed":140,"splash":4.5,"projectileModel":"gmlrs","roundWeight":160}
A34: m230_30_mm | B34: M230 30 mm | C34: weaponFamilies | D34: 1 | H34: 220 | K34: 0 | L34: Assets/MachineBrigade/Resources/Data/balance.json: weaponFamilies[17] | M34: {"id":"m230_30_mm","real":"M230 30 mm","projectileSpeed":220,"splash":0}
A35: m230_30_mm_air_burst | B35: M230 30 mm air-burst | C35: secondRounds.families | D35: 2 | H35: 220 | K35: 2.5 | L35: Assets/MachineBrigade/Resources/Data/balance.json: secondRounds.families[4] | M35: {"id":"m230_30_mm_air_burst","real":"M230 30 mm air-burst","projectileSpeed":220,"splash":2.5}
A36: m242_bushmaster_25_mm | B36: M242 Bushmaster 25 mm | C36: weaponFamilies | D36: 2 | H36: 210 | K36: 0 | L36: Assets/MachineBrigade/Resources/Data/balance.json: weaponFamilies[18] | M36: {"id":"m242_bushmaster_25_mm","real":"M242 Bushmaster 25 mm","projectileSpeed":210,"splash":0}
A37: m242_bushmaster_25_mm_air_burst | B37: M242 Bushmaster 25 mm air-burst | C37: secondRounds.families | D37: 2 | H37: 210 | J37: 22 | K37: 2 | L37: Assets/MachineBrigade/Resources/Data/balance.json: secondRounds.families[0] | M37: {"id":"m242_bushmaster_25_mm_air_burst","real":"M242 Bushmaster 25 mm air-burst","projectileSpeed":210,"splash":2,"roundWeight":22}
A38: m284_155_mm | B38: M284 155 mm | C38: weaponFamilies | D38: 5 | F38: shell_155 | G38: 0.7273 | H38: 150 | I38: 0.8 | K38: 7 | L38: Assets/MachineBrigade/Resources/Data/balance.json: weaponFamilies[19] | M38: {"id":"m284_155_mm","real":"M284 155 mm","projectileSpeed":150,"splash":7,"projectileModel":"shell_155","roundLength":0.8,"projectileScale":0.7273}
A39: m284_155_mm_2 | B39: M284 155 mm | C39: weaponFamilies | D39: 4 | F39: shell_155 | G39: 0.7273 | H39: 100 | I39: 0.8 | K39: 7 | L39: Assets/MachineBrigade/Resources/Data/balance.json: weaponFamilies[20] | M39: {"id":"m284_155_mm_2","real":"M284 155 mm","projectileSpeed":100,"splash":7,"projectileModel":"shell_155","roundLength":0.8,"projectileScale":0.7273}
A40: m284_155_mm_casemate | B40: M284 155 mm | C40: weaponFamilies | D40: 1 | F40: shell_155 | G40: 0.7273 | H40: 100 | I40: 0.8 | K40: 8 | L40: Assets/MachineBrigade/Resources/Data/balance.json: weaponFamilies[21] | M40: {"id":"m284_155_mm_casemate","real":"M284 155 mm","projectileSpeed":100,"splash":8,"projectileModel":"shell_155","roundLength":0.8,"projectileScale":0.7273}
A41: m284_155_mm_guided | B41: M284 155 mm guided | C41: secondRounds.families | D41: 3 | F41: shell_155 | H41: 45 | K41: 7 | L41: Assets/MachineBrigade/Resources/Data/balance.json: secondRounds.families[6] | M41: {"id":"m284_155_mm_guided","real":"M284 155 mm guided","projectileSpeed":45,"splash":7,"projectileModel":"shell_155"}
A42: m284_155_mm_guided_direct | B42: M284 155 mm guided | C42: secondRounds.families | D42: 3 | F42: shell_155 | H42: 150 | K42: 7 | L42: Assets/MachineBrigade/Resources/Data/balance.json: secondRounds.families[12] | M42: {"id":"m284_155_mm_guided_direct","real":"M284 155 mm guided","projectileSpeed":150,"splash":7,"projectileModel":"shell_155"}
A43: mim_104_patriot_pac_2 | B43: MIM-104 Patriot PAC-2 | C43: weaponFamilies | D43: 2 | E43: Loft | F43: patriot | G43: 1.2471 | H43: 300 | I43: 4.24 | K43: 2.5 | L43: Assets/MachineBrigade/Resources/Data/balance.json: weaponFamilies[23] | M43: {"id":"mim_104_patriot_pac_2","flightProfile":"Loft","real":"MIM-104 Patriot PAC-2","projectileSpeed":300,"splash":2.5,"projectileModel":"patriot","roundLength":4.24,"projectileScale":1.2471}
A44: mk_19_40_mm | B44: Mk 19 40 mm | C44: weaponFamilies | D44: 2 | H44: 70 | K44: 2 | L44: Assets/MachineBrigade/Resources/Data/balance.json: weaponFamilies[24] | M44: {"id":"mk_19_40_mm","real":"Mk 19 40 mm","projectileSpeed":70,"splash":2}
A45: nsm_oniks | B45: NSM / P-800 Oniks | C45: weaponFamilies | D45: 1 | E45: Loft | H45: 225 | I45: 3.17 | J45: 680 | K45: 7 | L45: Assets/MachineBrigade/Resources/Data/balance.json: weaponFamilies[41] | M45: {"id":"nsm_oniks","flightProfile":"Loft","real":"NSM / P-800 Oniks","projectileSpeed":225,"splash":7,"roundWeight":680,"roundLength":3.17}
A46: nsv_12_7_mm | B46: NSV 12.7 mm | C46: weaponFamilies | D46: 3 | H46: 240 | J46: 14 | K46: 0 | L46: Assets/MachineBrigade/Resources/Data/balance.json: weaponFamilies[25] | M46: {"id":"nsv_12_7_mm","real":"NSV 12.7 mm","projectileSpeed":240,"splash":0,"roundWeight":14}
A47: nsv_12_7_mm_api | B47: NSV 12.7 mm API | C47: secondRounds.families | D47: 3 | H47: 240 | J47: 14 | K47: 0 | L47: Assets/MachineBrigade/Resources/Data/balance.json: secondRounds.families[5] | M47: {"id":"nsv_12_7_mm_api","real":"NSV 12.7 mm API","projectileSpeed":240,"splash":0,"roundWeight":14}
A48: odab_500 | B48: ODAB-500 | C48: weaponFamilies | D48: 0 | H48: 35 | I48: 1.23 | J48: 500 | K48: 12 | L48: Assets/MachineBrigade/Resources/Data/balance.json: weaponFamilies[35] | M48: {"id":"odab_500","real":"ODAB-500","projectileSpeed":35,"splash":12,"roundWeight":500,"roundLength":1.23}
A49: oerlikon_35_mm | B49: Oerlikon 35 mm | C49: weaponFamilies | D49: 4 | H49: 260 | J49: 26 | K49: 2.5 | L49: Assets/MachineBrigade/Resources/Data/balance.json: weaponFamilies[26] | M49: {"id":"oerlikon_35_mm","real":"Oerlikon 35 mm","projectileSpeed":260,"splash":2.5,"roundWeight":26}
A50: oerlikon_35_mm_ap | B50: Oerlikon 35 mm AP | C50: secondRounds.families | D50: 2 | H50: 260 | J50: 26 | K50: 0 | L50: Assets/MachineBrigade/Resources/Data/balance.json: secondRounds.families[3] | M50: {"id":"oerlikon_35_mm_ap","real":"Oerlikon 35 mm AP","projectileSpeed":260,"splash":0,"roundWeight":26}
A51: pkt_m240_7_62_mm | B51: PKT / M240 7.62 mm | C51: weaponFamilies | D51: 3 | H51: 240 | K51: 0 | L51: Assets/MachineBrigade/Resources/Data/balance.json: weaponFamilies[27] | M51: {"id":"pkt_m240_7_62_mm","real":"PKT / M240 7.62 mm","projectileSpeed":240,"splash":0}
A52: rh_120_l_44_120_mm | B52: Rh-120 L/44 120 mm | C52: weaponFamilies | D52: 5 | H52: 170 | J52: 290 | K52: 1.5 | L52: Assets/MachineBrigade/Resources/Data/balance.json: weaponFamilies[28] | M52: {"id":"rh_120_l_44_120_mm","real":"Rh-120 L/44 120 mm","projectileSpeed":170,"splash":1.5,"roundWeight":290}
