Workbook

Sheet Thap
A1: id | B1: ten_en | C1: ten_vi | D1: ten_ngan_vi | E1: lop | F1: nhanh | G1: ke_thua_tu | H1: base_cp | I1: mau_hp | J1: mau_trong_tran_hp | K1: giap_truoc | L1: giap_hong | M1: giap_sau | N1: giap_noc | O1: cong_trinh | P1: toc_do_m_s | Q1: xoay_than_deg_s | R1: xoay_thap_deg_s | S1: tam_nhin_m | T1: ban_kinh_m | U1: dai_m | V1: rong_m | W1: bay | X1: do_cao_m | Y1: dung_yen | Z1: ban_khi_chay | AA1: toc_do_chiem | AB1: tha_du_s | AC1: he_so_sat_thuong_ra | AD1: vu_khi_chinh | AE1: vu_khi_phu | AF1: noi_tai | AG1: tu_ve | AH1: so_lan_tu_ve | AI1: hoi_tu_ve_s | AJ1: mo_hinh | AK1: so_voi_ban_goc | AL1: base_cp_truoc | AM1: base_cp_sau | AN1: mau_hp_truoc | AO1: mau_hp_sau | AP1: giap_truoc_truoc | AQ1: giap_truoc_sau | AR1: giap_hong_truoc | AS1: giap_hong_sau | AT1: giap_sau_truoc | AU1: giap_sau_sau | AV1: giap_noc_truoc | AW1: giap_noc_sau | AX1: toc_do_m_s_truoc | AY1: toc_do_m_s_sau | AZ1: tam_nhin_m_truoc | BA1: tam_nhin_m_sau | BB1: vu_khi_chinh_truoc | BC1: vu_khi_chinh_sau | BD1: vu_khi_phu_truoc | BE1: vu_khi_phu_sau | BF1: he_so_sat_thuong_ra_truoc | BG1: he_so_sat_thuong_ra_sau | BH1: the_goc | BI1: nhanh_ab | BJ1: co_o | BK1: vai_tro | BL1: trong_roster | BM1: base_rebuild_cp | BN1: runtime_rebuild_cp | BO1: xay_lai_cho_s | BP1: xay_lai_tha_s | BQ1: mo_khoa | BR1: the_cu_gop_vao | BS1: co_can_bang | BT1: armour | BU1: armour_front | BV1: armour_rear | BW1: armour_side | BX1: armour_top | BY1: art | BZ1: balloon_radius_m | CA1: balloon_scatter | CB1: blast_wall_cone | CC1: blast_wall_cut | CD1: blast_wall_radius_m | CE1: branch_of | CF1: branches | CG1: class | CH1: counter_battery_bonus | CI1: counter_battery_range_m | CJ1: counter_battery_seconds_s | CK1: cp | CL1: death_explosion_damage | CM1: death_explosion_delay_s | CN1: death_explosion_radius_m | CO1: death_explosion_tier | CP1: dome_hp | CQ1: dome_radius_m | CR1: dome_recharge_s | CS1: erect_seconds | CT1: fires_while_moving | CU1: fort_size | CV1: hangar_alive | CW1: hangar_budget | CX1: hangar_every_s | CY1: hangar_post | CZ1: hangar_units | DA1: hp | DB1: inherits | DC1: jammer | DD1: length_m | DE1: main_aim | DF1: main_slot | DG1: model | DH1: model_size_height_m | DI1: model_size_length_m | DJ1: model_size_width_m | DK1: naval_only | DL1: no_branch | DM1: outgoing_damage_mult | DN1: passable | DO1: radius_m | DP1: rebuild_cp | DQ1: relay_income | DR1: relay_quiet | DS1: relay_second | DT1: reveal_air | DU1: reveal_stealth | DV1: scale | DW1: secondary | DX1: shelter_cut | DY1: shelter_radius_m | DZ1: speed_m_s | EA1: static | EB1: tower_range_aura_radius_m | EC1: tower_range_aura_range_m | ED1: tower_role | EE1: turn_rate_deg_s | EF1: turret_turn_rate_deg_s | EG1: vision_m | EH1: wards_hp | EI1: wards_radius_m | EJ1: wards_recharge_s | EK1: weapon | EL1: width_m | EM1: nguon | EN1: raw_json
A2: aa_gun_tower | B2: 40 mm AA gun | C2: Pháo phòng không 40 mm | D2: Pháo PK 40 mm | H2: 0 | I2: 1273 | J2: 2800.6 | K2: 2 | L2: 2 | M2: 2 | N2: 2 | O2: TRUE | P2: 0 | Q2: 1 | R2: 120 | S2: 56 | T2: 2.4 | U2: 5 | V2: 5 | W2: FALSE | X2: 0 | Y2: TRUE | Z2: TRUE | AA2: 1 | AB2: 3.5 | AC2: 1 | AD2: bofors_l70 | AG2: none | AJ2: aa_gun_tower | AK2: giong | BJ2: Medium | BL2: FALSE | BM2: 4 | BN2: 4 | BO2: 40 | BP2: 3.5 | BQ2: Campaign | BR2: aa_gun_tower | BT2: 2 | CK2: 0 | CL2: 90 | CM2: 0.4 | CN2: 7 | CO2: Huge | CU2: Medium | DA2: 1273 | DD2: 5 | DH2: 3.2 | DI2: 5.5 | DJ2: 5.5 | DO2: 2.4 | DZ2: 0 | EA2: TRUE | EE2: 1 | EF2: 120 | EG2: 56 | EK2: bofors_l70 | EL2: 5 | EM2: Assets/MachineBrigade/Resources/Data/balance.json: vehicles[121] | EN2: {"id":"aa_gun_tower","modelSize":[5.5,5.5,3.2],"fort":{"size":"Medium"},"static":true,"armour":2,"hp":1273,"speed":0,"turnRate":1,"turretTurnRate":120,"radius":2.4,"length":5.0,"width":5.0,"cp":0,"vision":56,"weapon":"bofors_l70","secondary":[],"deathExplosion":{"damage":90,"radius":7,"delay":0.4,"tier":"Huge"}}
A3: aa_turret | B3: AA turret | C3: Tháp phòng không | D3: Tháp PK | H3: 0 | I3: 1100 | J3: 2420 | K3: 2 | L3: 2 | M3: 2 | N3: 2 | O3: TRUE | P3: 0 | Q3: 1 | R3: 200 | S3: 60 | T3: 2.3 | U3: 4.5 | V3: 4.5 | W3: FALSE | X3: 0 | Y3: TRUE | Z3: TRUE | AA3: 1 | AB3: 3.5 | AC3: 1 | AD3: tower_flak_30 | AE3: sam | AG3: none | AJ3: aa_turret | AK3: giong | BJ3: Small | BL3: TRUE | BM3: 6 | BN3: 6 | BO3: 25 | BP3: 2.5 | BQ3: Starter | BR3: aa_turret | BT3: 2 | CF3: aa_turret.flak;aa_turret.sam | CK3: 0 | CL3: 90 | CM3: 0.4 | CN3: 7 | CO3: Huge | CU3: Small | DA3: 1100 | DD3: 4.5 | DM3: 1 | DO3: 2.3 | DP3: 6 | DZ3: 0 | EA3: TRUE | EE3: 1 | EF3: 200 | EG3: 60 | EK3: tower_flak_30 | EL3: 4.5 | EM3: Assets/MachineBrigade/Resources/Data/balance.json: vehicles[70] | EN3: {"id":"aa_turret","outgoingDamageMult":1,"rebuildCp":6,"branches":["aa_turret.flak","aa_turret.sam"],"fort":{"size":"Small"},"static":true,"armour":2,"hp":1100,"speed":0,"turnRate":1,"turretTurnRate":200,"radius":2.3,"length":4.5,"width":4.5,"cp":0,"vision":60,"weapon":"tower_flak_30","secondary":[{"weapon":"sam","slot":"missile","aim":"Turret"}],"deathExplosion":{"damage":90,"radius":7,"delay":0.4,"tier":"Huge"}}
A4: aa_turret.flak | D4: Tháp cao xạ | G4: aa_turret | H4: 0 | I4: 1100 | J4: 2420 | K4: 2 | L4: 2 | M4: 2 | N4: 2 | O4: TRUE | P4: 0 | Q4: 1 | R4: 200 | S4: 60 | T4: 2.3 | U4: 4.5 | V4: 4.5 | W4: FALSE | X4: 0 | Y4: TRUE | Z4: TRUE | AA4: 1 | AB4: 3.5 | AC4: 0.7869 | AD4: flak_quad | AG4: none | AJ4: aa_turret | AK4: doi | BF4: 1 | BG4: 0.7869 | BH4: aa_turret | BI4: flak | BJ4: Small | BK4: aa_gun_23_drones_helis | BL4: FALSE | BM4: 6 | BN4: 6 | BO4: 25 | BP4: 2.5 | BQ4: Campaign | BR4: aa_turret | BS4: giam_dps_giu_mau | BY4: aa_turret_a | CE4: aa_turret | DB4: aa_turret | DM4: 0.7869 | DP4: 6 | ED4: aa_gun_23_drones_helis | EK4: flak_quad | EM4: Assets/MachineBrigade/Resources/Data/balance.json: vehicles[102] | EN4: {"id":"aa_turret.flak","outgoingDamageMult":0.7869,"rebuildCp":6,"towerRole":"aa_gun_23_drones_helis","art":"aa_turret_a","inherits":"aa_turret","branchOf":"aa_turret","weapon":"flak_quad","secondary":[]}
A5: aa_turret.sam | D5: Stinger | G5: aa_turret | H5: 0 | I5: 1100 | J5: 2420 | K5: 2 | L5: 2 | M5: 2 | N5: 2 | O5: TRUE | P5: 0 | Q5: 1 | R5: 200 | S5: 60 | T5: 2.3 | U5: 4.5 | V5: 4.5 | W5: FALSE | X5: 0 | Y5: TRUE | Z5: TRUE | AA5: 1 | AB5: 3.5 | AC5: 1 | AD5: stinger_post | AG5: none | AJ5: aa_turret | AK5: doi | AZ5: 64 | BA5: 60 | BB5: sam_post | BC5: stinger_post | BH5: aa_turret | BI5: sam | BJ5: Small | BK5: aa_manpads_aircraft | BL5: FALSE | BM5: 5 | BN5: 5 | BO5: 25 | BP5: 2.5 | BQ5: Campaign | BR5: aa_turret | BY5: aa_turret_b | CE5: aa_turret | DB5: aa_turret | DF5: missile | DM5: 1 | DP5: 5 | ED5: aa_manpads_aircraft | EG5: 60 | EK5: stinger_post | EM5: Assets/MachineBrigade/Resources/Data/balance.json: vehicles[103] | EN5: {"id":"aa_turret.sam","outgoingDamageMult":1,"rebuildCp":5,"towerRole":"aa_manpads_aircraft","art":"aa_turret_b","inherits":"aa_turret","branchOf":"aa_turret","weapon":"stinger_post","mainSlot":"missile","vision":60,"secondary":[]}
A6: aircraft_hangar | B6: Aircraft hangar | C6: Nhà chứa máy bay | D6: Nhà chứa máy bay | H6: 0 | I6: 1800 | J6: 3960 | K6: 2 | L6: 2 | M6: 2 | N6: 2 | O6: TRUE | P6: 0 | Q6: 1 | R6: 1 | S6: 50 | T6: 3.6 | U6: 8 | V6: 8 | W6: FALSE | X6: 0 | Y6: TRUE | Z6: TRUE | AA6: 1 | AB6: 3.5 | AC6: 1 | AD6: none | AG6: none | AJ6: aircraft_hangar | AK6: moi | BJ6: Medium | BL6: TRUE | BM6: 8 | BN6: 8 | BO6: 40 | BP6: 3.5 | BQ6: Campaign | BR6: aircraft_hangar | BT6: 2 | CK6: 0 | CL6: 120 | CM6: 0.4 | CN6: 8 | CO6: Huge | CU6: Medium | CV6: 2 | CW6: 12 | CX6: 60 | CY6: 30 | CZ6: scout_heli;recon_drone | DA6: 1800 | DD6: 8 | DG6: aircraft_hangar | DH6: 5.32 | DI6: 8 | DJ6: 7.72 | DO6: 3.6 | DP6: 8 | DZ6: 0 | EA6: TRUE | EE6: 1 | EF6: 1 | EG6: 50 | EK6: none | EL6: 8 | EM6: Assets/MachineBrigade/Resources/Data/balance.json: vehicles[75] | EN6: {"id":"aircraft_hangar","rebuildCp":8,"model":"aircraft_hangar","modelSize":[8.0,7.72,5.32],"fort":{"size":"Medium"},"static":true,"armour":2,"hp":1800,"speed":0,"turnRate":1,"turretTurnRate":1,"radius":3.6,"length":8,"width":8,"cp":0,"vision":50,"weapon":"none","hangar":{"units":["scout_heli","recon_drone"],"every":60,"alive":2,"budget":12,"post":30},"deathExplosion":{"damage":120,"radius":8,"delay":0.4,"tier":"Huge"}}
A7: atgm_tower | B7: ATGM tower | C7: Tháp tên lửa chống tăng | D7: Tháp ATGM | H7: 0 | I7: 900 | J7: 1980 | K7: 2 | L7: 2 | M7: 2 | N7: 2 | O7: TRUE | P7: 0 | Q7: 1 | R7: 90 | S7: 55 | T7: 2.3 | U7: 4.8 | V7: 4.8 | W7: FALSE | X7: 0 | Y7: TRUE | Z7: TRUE | AA7: 1 | AB7: 3.5 | AC7: 1 | AD7: tower_kornet | AG7: none | AJ7: atgm_tower | AK7: giong | BJ7: Medium | BL7: TRUE | BM7: 7 | BN7: 7 | BO7: 40 | BP7: 3.5 | BQ7: Campaign | BR7: atgm_tower | BT7: 2 | CF7: atgm_tower.top;atgm_tower.multi | CK7: 0 | CL7: 90 | CM7: 0.3 | CN7: 6 | CO7: Large | CU7: Medium | DA7: 900 | DD7: 4.8 | DF7: missile | DO7: 2.3 | DP7: 7 | DZ7: 0 | EA7: TRUE | EE7: 1 | EF7: 90 | EG7: 55 | EK7: tower_kornet | EL7: 4.8 | EM7: Assets/MachineBrigade/Resources/Data/balance.json: vehicles[68] | EN7: {"id":"atgm_tower","rebuildCp":7,"branches":["atgm_tower.top","atgm_tower.multi"],"fort":{"size":"Medium"},"static":true,"armour":2,"hp":900,"speed":0,"turnRate":1,"turretTurnRate":90,"radius":2.3,"length":4.8,"width":4.8,"cp":0,"vision":55,"weapon":"tower_kornet","mainSlot":"missile","deathExplosion":{"damage":90,"radius":6,"delay":0.3,"tier":"Large"}}
A8: atgm_tower.multi | D8: Đa năng | G8: atgm_tower | H8: 0 | I8: 900 | J8: 1980 | K8: 2 | L8: 2 | M8: 2 | N8: 2 | O8: TRUE | P8: 0 | Q8: 1 | R8: 90 | S8: 55 | T8: 2.3 | U8: 4.8 | V8: 4.8 | W8: FALSE | X8: 0 | Y8: TRUE | Z8: TRUE | AA8: 1 | AB8: 3.5 | AC8: 1 | AD8: kornet_multi | AG8: none | AJ8: atgm_tower | AK8: giong | BH8: atgm_tower | BI8: multi | BJ8: Medium | BK8: atgm_multi | BL8: FALSE | BM8: 6 | BN8: 6 | BO8: 40 | BP8: 3.5 | BQ8: Campaign | BR8: atgm_tower | BY8: atgm_tower_b | CE8: atgm_tower | DB8: atgm_tower | DP8: 6 | ED8: atgm_multi | EK8: kornet_multi | EM8: Assets/MachineBrigade/Resources/Data/balance.json: vehicles[88] | EN8: {"id":"atgm_tower.multi","rebuildCp":6,"towerRole":"atgm_multi","art":"atgm_tower_b","inherits":"atgm_tower","branchOf":"atgm_tower","weapon":"kornet_multi"}
A9: atgm_tower.top | D9: Đánh từ trên | G9: atgm_tower | H9: 0 | I9: 900 | J9: 1980 | K9: 2 | L9: 2 | M9: 2 | N9: 2 | O9: TRUE | P9: 0 | Q9: 1 | R9: 90 | S9: 55 | T9: 2.3 | U9: 4.8 | V9: 4.8 | W9: FALSE | X9: 0 | Y9: TRUE | Z9: TRUE | AA9: 1 | AB9: 3.5 | AC9: 1 | AD9: kornet_top | AG9: none | AJ9: atgm_tower | AK9: giong | BH9: atgm_tower | BI9: top | BJ9: Medium | BK9: atgm_top_attack | BL9: FALSE | BM9: 7 | BN9: 7 | BO9: 40 | BP9: 3.5 | BQ9: Campaign | BR9: atgm_tower | BY9: atgm_tower_a | CE9: atgm_tower | DB9: atgm_tower | DP9: 7 | ED9: atgm_top_attack | EK9: kornet_top | EM9: Assets/MachineBrigade/Resources/Data/balance.json: vehicles[87] | EN9: {"id":"atgm_tower.top","rebuildCp":7,"towerRole":"atgm_top_attack","art":"atgm_tower_a","inherits":"atgm_tower","branchOf":"atgm_tower","weapon":"kornet_top"}
A10: barrage_balloon | B10: Radar aerostat (JLENS) | C10: Khí cầu neo radar (JLENS) | D10: Khí cầu radar | H10: 0 | I10: 364 | J10: 800.8 | K10: 0 | L10: 0 | M10: 0 | N10: 0 | O10: TRUE | P10: 0 | Q10: 1 | R10: 1 | S10: 1 | T10: 2 | U10: 4 | V10: 4 | W10: FALSE | X10: 0 | Y10: TRUE | Z10: TRUE | AA10: 1 | AB10: 3.5 | AC10: 1 | AD10: none | AG10: none | AJ10: barrage_balloon | AK10: giong | BJ10: Small | BL10: FALSE | BM10: 2 | BN10: 2 | BO10: 25 | BP10: 2.5 | BQ10: Campaign | BR10: barrage_balloon | BT10: 0 | BZ10: 40 | CA10: 0.5 | CK10: 0 | CU10: Small | DA10: 364 | DD10: 4 | DH10: 16 | DI10: 9 | DJ10: 4 | DO10: 2 | DT10: 45 | DZ10: 0 | EA10: TRUE | EE10: 1 | EF10: 1 | EG10: 1 | EK10: none | EL10: 4 | EM10: Assets/MachineBrigade/Resources/Data/balance.json: vehicles[117] | EN10: {"id":"barrage_balloon","modelSize":[9.0,4.0,16.0],"fort":{"size":"Small"},"static":true,"armour":0,"hp":364,"speed":0,"turnRate":1,"turretTurnRate":1,"radius":2.0,"length":4.0,"width":4.0,"cp":0,"vision":1,"weapon":"none","balloon":{"radius":40,"scatter":0.5},"revealAir":45}
A11: blast_wall | B11: Gabion blast wall | C11: Tường chắn đạn | D11: Tường chắn đạn | H11: 0 | I11: 1364 | J11: 3000.8 | K11: 3 | L11: 3 | M11: 3 | N11: 3 | O11: TRUE | P11: 0 | Q11: 1 | R11: 1 | S11: 1 | T11: 2.2 | U11: 1.9 | V11: 4.8 | W11: FALSE | X11: 0 | Y11: TRUE | Z11: TRUE | AA11: 1 | AB11: 3.5 | AC11: 1 | AD11: none | AG11: none | AJ11: blast_wall | AK11: giong | BJ11: Small | BL11: FALSE | BM11: 2 | BN11: 2 | BO11: 25 | BP11: 2.5 | BQ11: Campaign | BR11: blast_wall | BT11: 3 | CB11: 50 | CC11: 0.3 | CD11: 10 | CK11: 0 | CU11: Small | DA11: 1364 | DD11: 1.9 | DH11: 2.4 | DI11: 1.9 | DJ11: 4.8 | DN11: TRUE | DO11: 2.2 | DZ11: 0 | EA11: TRUE | EE11: 1 | EF11: 1 | EG11: 1 | EK11: none | EL11: 4.8 | EM11: Assets/MachineBrigade/Resources/Data/balance.json: vehicles[115] | EN11: {"id":"blast_wall","modelSize":[1.9,4.8,2.4],"fort":{"size":"Small"},"static":true,"passable":true,"armour":3,"hp":1364,"speed":0,"turnRate":1,"turretTurnRate":1,"radius":2.2,"length":1.9,"width":4.8,"cp":0,"vision":1,"weapon":"none","blastWall":{"radius":10,"cut":0.3,"cone":50}}
A12: bulwark_post | B12: Field gun post | C12: Ụ súng dã chiến | D12: Ụ súng | E12: Defense | H12: 0 | I12: 500 | J12: 1100 | K12: 1 | L12: 1 | M12: 1 | N12: 1 | O12: TRUE | P12: 0 | Q12: 1 | R12: 160 | S12: 34 | T12: 1.6 | U12: 2.72 | V12: 2.72 | W12: FALSE | X12: 0 | Y12: TRUE | Z12: TRUE | AA12: 1 | AB12: 3.5 | AC12: 1 | AD12: bunker_hmg | AG12: none | AJ12: bulwark_post | AK12: giong | BL12: FALSE | BN12: 2 | BQ12: Campaign | BR12: bulwark_post | BT12: 1 | CG12: Defense | CK12: 0 | CL12: 40 | CM12: 0.2 | CN12: 4 | CO12: Large | DA12: 500 | DD12: 3.4 | DG12: bulwark_post | DO12: 1.6 | DV12: 0.8 | DZ12: 0 | EA12: TRUE | EE12: 1 | EF12: 160 | EG12: 34 | EK12: bunker_hmg | EL12: 3.4 | EM12: Assets/MachineBrigade/Resources/Data/balance.json: vehicles[106] | EN12: {"id":"bulwark_post","class":"Defense","static":true,"model":"bulwark_post","armour":1,"hp":500,"speed":0,"turnRate":1,"turretTurnRate":160,"radius":1.6,"length":3.4,"width":3.4,"scale":0.8,"cp":0,"vision":34,"weapon":"bunker_hmg","deathExplosion":{"damage":40,"radius":4,"delay":0.2,"tier":"Large"}}
A13: bunker_shelter_tower | B13: Bunker (medium slot) | C13: Hầm ngầm che quân | D13: Hầm ngầm | H13: 0 | I13: 1818 | J13: 3999.6 | K13: 3 | L13: 3 | M13: 3 | N13: 3 | O13: TRUE | P13: 0 | Q13: 1 | R13: 1 | S13: 30 | T13: 2.6 | U13: 6 | V13: 5 | W13: FALSE | X13: 0 | Y13: TRUE | Z13: TRUE | AA13: 1 | AB13: 3.5 | AC13: 1 | AD13: none | AG13: none | AJ13: bunker_shelter_tower | AK13: giong | BJ13: Medium | BL13: FALSE | BM13: 4 | BN13: 4 | BO13: 40 | BP13: 3.5 | BQ13: Campaign | BR13: bunker_shelter_tower | BT13: 3 | CK13: 0 | CU13: Medium | DA13: 1818 | DD13: 6 | DG13: bunker_shelter_tower | DH13: 2.2 | DI13: 6 | DJ13: 5 | DO13: 2.6 | DX13: 0.5 | DY13: 18 | DZ13: 0 | EA13: TRUE | EE13: 1 | EF13: 1 | EG13: 30 | EK13: none | EL13: 5 | EM13: Assets/MachineBrigade/Resources/Data/balance.json: vehicles[130] | EN13: {"id":"bunker_shelter_tower","model":"bunker_shelter_tower","modelSize":[6.0,5.0,2.2],"fort":{"size":"Medium"},"static":true,"armour":3,"hp":1818,"speed":0,"turnRate":1,"turretTurnRate":1,"radius":2.6,"length":6.0,"width":5.0,"cp":0,"vision":30,"weapon":"none","shelter":{"radius":18,"cut":0.5}}
A14: c_ram | B14: C-RAM interceptor | C14: Trạm đánh chặn C-RAM | D14: C-RAM | H14: 0 | I14: 1300 | J14: 2860 | K14: 1 | L14: 1 | M14: 1 | N14: 1 | O14: TRUE | P14: 0 | Q14: 1 | R14: 240 | S14: 60 | T14: 2.5 | U14: 5.5 | V14: 5.5 | W14: FALSE | X14: 0 | Y14: TRUE | Z14: TRUE | AA14: 1 | AB14: 3.5 | AC14: 1 | AD14: c_ram_gatling | AG14: aps | AH14: 4 | AI14: 0.6 | AJ14: c_ram | AK14: giong | BJ14: Medium | BL14: TRUE | BM14: 5 | BN14: 5 | BO14: 40 | BP14: 3.5 | BQ14: Campaign | BR14: c_ram | BT14: 1 | CF14: c_ram.centurion;c_ram.dome | CK14: 0 | CL14: 90 | CM14: 0.4 | CN14: 7 | CO14: Huge | CU14: Medium | DA14: 1300 | DD14: 5.5 | DO14: 2.5 | DP14: 5 | DZ14: 0 | EA14: TRUE | EE14: 1 | EF14: 240 | EG14: 60 | EK14: c_ram_gatling | EL14: 5.5 | EM14: Assets/MachineBrigade/Resources/Data/balance.json: vehicles[72] | EN14: {"id":"c_ram","rebuildCp":5,"branches":["c_ram.centurion","c_ram.dome"],"fort":{"size":"Medium"},"static":true,"armour":1,"hp":1300,"speed":0,"turnRate":1,"turretTurnRate":240,"radius":2.5,"length":5.5,"width":5.5,"cp":0,"vision":60,"weapon":"c_ram_gatling","aps":{"radius":35,"charges":4,"recharge":0.6,"rockets":true,"shells":0.3,"burst":0.5},"deathExplosion":{"damage":90,"radius":7,"delay":0.4,"tier":"Huge"}}
A15: c_ram.centurion | D15: Centurion | G15: c_ram | H15: 0 | I15: 1300 | J15: 2860 | K15: 1 | L15: 1 | M15: 1 | N15: 1 | O15: TRUE | P15: 0 | Q15: 1 | R15: 240 | S15: 60 | T15: 2.5 | U15: 5.5 | V15: 5.5 | W15: FALSE | X15: 0 | Y15: TRUE | Z15: TRUE | AA15: 1 | AB15: 3.5 | AC15: 1 | AD15: c_ram_gatling | AG15: aps | AH15: 5 | AI15: 0.35 | AJ15: c_ram | AK15: giong | BH15: c_ram | BI15: centurion | BJ15: Medium | BK15: intercept_close_fast | BL15: FALSE | BM15: 5 | BN15: 5 | BO15: 40 | BP15: 3.5 | BQ15: Campaign | BR15: c_ram | BY15: c_ram_a | CE15: c_ram | DB15: c_ram | DP15: 5 | ED15: intercept_close_fast | EM15: Assets/MachineBrigade/Resources/Data/balance.json: vehicles[91] | EN15: {"id":"c_ram.centurion","rebuildCp":5,"towerRole":"intercept_close_fast","art":"c_ram_a","inherits":"c_ram","branchOf":"c_ram","aps":{"radius":35,"charges":5,"recharge":0.35,"rockets":true,"shells":0.4,"burst":0.3}}
A16: c_ram.dome | D16: Vòm Sắt | G16: c_ram | H16: 0 | I16: 1300 | J16: 2860 | K16: 1 | L16: 1 | M16: 1 | N16: 1 | O16: TRUE | P16: 0 | Q16: 1 | R16: 240 | S16: 64 | T16: 2.5 | U16: 5.5 | V16: 5.5 | W16: FALSE | X16: 0 | Y16: TRUE | Z16: TRUE | AA16: 1 | AB16: 3.5 | AC16: 1 | AD16: tamir | AG16: aps | AH16: 6 | AJ16: c_ram | AK16: giong | BH16: c_ram | BI16: dome | BJ16: Medium | BK16: intercept_far_slow | BL16: FALSE | BM16: 5 | BN16: 5 | BO16: 40 | BP16: 3.5 | BQ16: Campaign | BR16: c_ram | BY16: c_ram_b | CE16: c_ram | DB16: c_ram | DP16: 5 | ED16: intercept_far_slow | EG16: 64 | EK16: tamir | EM16: Assets/MachineBrigade/Resources/Data/balance.json: vehicles[92] | EN16: {"id":"c_ram.dome","rebuildCp":5,"towerRole":"intercept_far_slow","art":"c_ram_b","inherits":"c_ram","branchOf":"c_ram","weapon":"tamir","vision":64,"aps":{"radius":60,"charges":6,"reload":12,"rockets":true,"shells":0.5,"direct":false,"missiles":true}}
A17: coastal_battery | B17: Coastal Battery | C17: Trận địa pháo bờ biển | D17: Pháo bờ biển | E17: Defense | H17: 0 | I17: 3000 | J17: 6600 | K17: 4 | L17: 3 | M17: 3 | N17: 3 | O17: TRUE | P17: 0 | Q17: 1 | R17: 18 | S17: 130 | T17: 3.8 | U17: 8 | V17: 8 | W17: FALSE | X17: 0 | Y17: TRUE | Z17: TRUE | AA17: 1 | AB17: 3.5 | AC17: 1 | AD17: gun_155_coastal | AG17: none | AJ17: coastal_battery | AK17: giong | BL17: FALSE | BN17: 2 | BQ17: Campaign | BR17: coastal_battery | BU17: 4 | BV17: 3 | BW17: 3 | BX17: 3 | CG17: Defense | CK17: 0 | CL17: 220 | CM17: 0.5 | CN17: 12 | CO17: Ultimate | DA17: 3000 | DD17: 8 | DG17: coastal_battery | DK17: TRUE | DO17: 3.8 | DZ17: 0 | EA17: TRUE | EE17: 1 | EF17: 18 | EG17: 130 | EK17: gun_155_coastal | EL17: 8 | EM17: Assets/MachineBrigade/Resources/Data/balance.json: vehicles[158] | EN17: {"id":"coastal_battery","class":"Defense","static":true,"model":"coastal_battery","armour":[4,3,3,3],"hp":3000,"speed":0,"turnRate":1,"turretTurnRate":18,"radius":3.8,"length":8,"width":8,"cp":0,"vision":130,"weapon":"gun_155_coastal","navalOnly":true,"deathExplosion":{"damage":220,"radius":12,"delay":0.5,"tier":"Ultimate"}}
A18: cp_relay | B18: CP relay | C18: Trạm tiếp tế CP | D18: Trạm CP | H18: 0 | I18: 600 | J18: 1320 | K18: 1 | L18: 1 | M18: 1 | N18: 1 | O18: TRUE | P18: 0 | Q18: 1 | R18: 1 | S18: 30 | T18: 1.8 | U18: 4 | V18: 4 | W18: FALSE | X18: 0 | Y18: TRUE | Z18: TRUE | AA18: 1 | AB18: 3.5 | AC18: 1 | AD18: none | AG18: none | AJ18: cp_relay | AK18: giong | BI18: noBranch | BJ18: Small | BK18: cp_income | BL18: TRUE | BM18: 6 | BN18: 6 | BO18: 25 | BP18: 2.5 | BQ18: Campaign | BR18: cp_relay | BT18: 1 | CK18: 0 | CL18: 50 | CM18: 0.3 | CN18: 5 | CO18: Large | CU18: Small | DA18: 600 | DD18: 4 | DL18: TRUE | DO18: 1.8 | DP18: 6 | DQ18: 0.1 | DR18: 5 | DS18: 0.06 | DZ18: 0 | EA18: TRUE | ED18: cp_income | EE18: 1 | EF18: 1 | EG18: 30 | EK18: none | EL18: 4 | EM18: Assets/MachineBrigade/Resources/Data/balance.json: vehicles[109] | EN18: {"id":"cp_relay","rebuildCp":6,"towerRole":"cp_income","noBranch":true,"fort":{"size":"Small"},"static":true,"armour":1,"hp":600,"speed":0,"turnRate":1,"turretTurnRate":1,"radius":1.8,"length":4,"width":4,"cp":0,"vision":30,"weapon":"none","relay":{"income":0.1,"second":0.06,"quiet":5},"deathExplosion":{"damage":50,"radius":5,"delay":0.3,"tier":"Large"}}
A19: drone_hangar | B19: Drone hangar | C19: Nhà chứa drone | D19: Nhà chứa drone | H19: 0 | I19: 2200 | J19: 4840 | K19: 2 | L19: 2 | M19: 2 | N19: 2 | O19: TRUE | P19: 0 | Q19: 1 | R19: 1 | S19: 60 | T19: 3.6 | U19: 8 | V19: 8 | W19: FALSE | X19: 0 | Y19: TRUE | Z19: TRUE | AA19: 1 | AB19: 3.5 | AC19: 1 | AD19: fpv_hangar | AG19: none | AJ19: drone_hangar | AK19: giong | BJ19: Large | BL19: TRUE | BM19: 12 | BN19: 12 | BO19: 60 | BP19: 5 | BQ19: Campaign | BR19: drone_hangar | BT19: 2 | CF19: drone_hangar.lancet;drone_hangar.swarm | CK19: 0 | CL19: 160 | CM19: 0.4 | CN19: 10 | CO19: Ultimate | CU19: Large | DA19: 2200 | DD19: 8 | DE19: Hull | DF19: door_l | DO19: 3.6 | DP19: 12 | DZ19: 0 | EA19: TRUE | EE19: 1 | EF19: 1 | EG19: 60 | EK19: fpv_hangar | EL19: 8 | EM19: Assets/MachineBrigade/Resources/Data/balance.json: vehicles[73] | EN19: {"id":"drone_hangar","rebuildCp":12,"branches":["drone_hangar.lancet","drone_hangar.swarm"],"fort":{"size":"Large"},"static":true,"armour":2,"hp":2200,"speed":0,"turnRate":1,"turretTurnRate":1,"radius":3.6,"length":8,"width":8,"cp":0,"vision":60,"weapon":"fpv_hangar","mainSlot":"door_l","mainAim":"Hull","deathExplosion":{"damage":160,"radius":10,"delay":0.4,"tier":"Ultimate"}}
A20: drone_hangar.lancet | D20: Lancet | G20: drone_hangar | H20: 0 | I20: 2200 | J20: 4840 | K20: 2 | L20: 2 | M20: 2 | N20: 2 | O20: TRUE | P20: 0 | Q20: 1 | R20: 1 | S20: 60 | T20: 3.6 | U20: 8 | V20: 8 | W20: FALSE | X20: 0 | Y20: TRUE | Z20: TRUE | AA20: 1 | AB20: 3.5 | AC20: 1 | AD20: lancet_hangar | AG20: none | AJ20: drone_hangar | AK20: giong | BH20: drone_hangar | BI20: lancet | BJ20: Large | BK20: drone_loitering | BL20: FALSE | BM20: 14 | BN20: 14 | BO20: 60 | BP20: 5 | BQ20: Campaign | BR20: drone_hangar | BY20: drone_hangar_a | CE20: drone_hangar | DB20: drone_hangar | DP20: 14 | ED20: drone_loitering | EK20: lancet_hangar | EM20: Assets/MachineBrigade/Resources/Data/balance.json: vehicles[95] | EN20: {"id":"drone_hangar.lancet","rebuildCp":14,"towerRole":"drone_loitering","art":"drone_hangar_a","inherits":"drone_hangar","branchOf":"drone_hangar","weapon":"lancet_hangar"}
A21: drone_hangar.swarm | D21: Bầy đàn | G21: drone_hangar | H21: 0 | I21: 2200 | J21: 4840 | K21: 2 | L21: 2 | M21: 2 | N21: 2 | O21: TRUE | P21: 0 | Q21: 1 | R21: 1 | S21: 60 | T21: 3.6 | U21: 8 | V21: 8 | W21: FALSE | X21: 0 | Y21: TRUE | Z21: TRUE | AA21: 1 | AB21: 3.5 | AC21: 1 | AD21: fpv_hangar_swarm | AG21: none | AJ21: drone_hangar | AK21: giong | BH21: drone_hangar | BI21: swarm | BJ21: Large | BK21: drone_fpv_swarm | BL21: FALSE | BM21: 14 | BN21: 14 | BO21: 60 | BP21: 5 | BQ21: Campaign | BR21: drone_hangar | BY21: drone_hangar_b | CE21: drone_hangar | DB21: drone_hangar | DP21: 14 | ED21: drone_fpv_swarm | EK21: fpv_hangar_swarm | EM21: Assets/MachineBrigade/Resources/Data/balance.json: vehicles[96] | EN21: {"id":"drone_hangar.swarm","rebuildCp":14,"towerRole":"drone_fpv_swarm","art":"drone_hangar_b","inherits":"drone_hangar","branchOf":"drone_hangar","weapon":"fpv_hangar_swarm"}
A22: drone_net_tower | B22: Drone net corridor | C22: Lưới chắn drone | D22: Lưới drone | H22: 0 | I22: 364 | J22: 800.8 | K22: 0 | L22: 0 | M22: 0 | N22: 0 | O22: TRUE | P22: 0 | Q22: 1 | R22: 1 | S22: 20 | T22: 1.6 | U22: 3 | V22: 8 | W22: FALSE | X22: 0 | Y22: TRUE | Z22: TRUE | AA22: 1 | AB22: 3.5 | AC22: 1 | AD22: net_zap | AG22: none | AJ22: drone_net_tower | AK22: giong | BJ22: Small | BL22: FALSE | BM22: 2 | BN22: 2 | BO22: 25 | BP22: 2.5 | BQ22: Campaign | BR22: drone_net_tower | BT22: 0 | CK22: 0 | CU22: Small | DA22: 364 | DD22: 3 | DG22: drone_net_tower | DH22: 4.6 | DI22: 6 | DJ22: 4 | DN22: TRUE | DO22: 1.6 | DZ22: 0 | EA22: TRUE | EE22: 1 | EF22: 1 | EG22: 20 | EK22: net_zap | EL22: 8 | EM22: Assets/MachineBrigade/Resources/Data/balance.json: vehicles[133] | EN22: {"id":"drone_net_tower","model":"drone_net_tower","modelSize":[6.0,4.0,4.6],"fort":{"size":"Small"},"static":true,"passable":true,"armour":0,"hp":364,"speed":0,"turnRate":1,"turretTurnRate":1,"radius":1.6,"length":3.0,"width":8.0,"cp":0,"vision":20,"weapon":"net_zap"}
A23: ew_tower | B23: EW tower | C23: Tháp gây nhiễu EW | D23: Tháp EW | H23: 0 | I23: 800 | J23: 1760 | K23: 1 | L23: 1 | M23: 1 | N23: 1 | O23: TRUE | P23: 0 | Q23: 1 | R23: 60 | S23: 50 | T23: 1.8 | U23: 4 | V23: 4 | W23: FALSE | X23: 0 | Y23: TRUE | Z23: TRUE | AA23: 1 | AB23: 3.5 | AC23: 1 | AD23: none | AG23: none | AJ23: ew_tower | AK23: giong | BJ23: Small | BL23: TRUE | BM23: 3 | BN23: 3 | BO23: 25 | BP23: 2.5 | BQ23: Campaign | BR23: ew_tower | BT23: 1 | CF23: ew_tower.drone;ew_tower.spoof | CK23: 0 | CL23: 60 | CM23: 0.3 | CN23: 5 | CO23: Large | CU23: Small | DA23: 800 | DC23: 30 | DD23: 4 | DO23: 1.8 | DP23: 3 | DZ23: 0 | EA23: TRUE | EE23: 1 | EF23: 60 | EG23: 50 | EK23: none | EL23: 4 | EM23: Assets/MachineBrigade/Resources/Data/balance.json: vehicles[71] | EN23: {"id":"ew_tower","rebuildCp":3,"branches":["ew_tower.drone","ew_tower.spoof"],"fort":{"size":"Small"},"static":true,"armour":1,"hp":800,"speed":0,"turnRate":1,"turretTurnRate":60,"radius":1.8,"length":4,"width":4,"cp":0,"vision":50,"weapon":"none","jammer":30,"deathExplosion":{"damage":60,"radius":5,"delay":0.3,"tier":"Large"}}
A24: ew_tower.drone | D24: Chống drone | G24: ew_tower | H24: 0 | I24: 800 | J24: 1760 | K24: 1 | L24: 1 | M24: 1 | N24: 1 | O24: TRUE | P24: 0 | Q24: 1 | R24: 60 | S24: 50 | T24: 1.8 | U24: 4 | V24: 4 | W24: FALSE | X24: 0 | Y24: TRUE | Z24: TRUE | AA24: 1 | AB24: 3.5 | AC24: 1 | AD24: none | AG24: none | AJ24: ew_tower | AK24: giong | BH24: ew_tower | BI24: drone | BJ24: Small | BK24: jam_drones_guided | BL24: FALSE | BM24: 3 | BN24: 3 | BO24: 25 | BP24: 2.5 | BQ24: Campaign | BR24: ew_tower | BY24: ew_tower_a | CE24: ew_tower | DB24: ew_tower | DC24: 45 | DP24: 3 | ED24: jam_drones_guided | EM24: Assets/MachineBrigade/Resources/Data/balance.json: vehicles[80] | EN24: {"id":"ew_tower.drone","rebuildCp":3,"towerRole":"jam_drones_guided","art":"ew_tower_a","inherits":"ew_tower","branchOf":"ew_tower","jammer":45}
A25: ew_tower.spoof | D25: Đánh lừa radar | G25: ew_tower | H25: 0 | I25: 800 | J25: 1760 | K25: 1 | L25: 1 | M25: 1 | N25: 1 | O25: TRUE | P25: 0 | Q25: 1 | R25: 60 | S25: 50 | T25: 1.8 | U25: 4 | V25: 4 | W25: FALSE | X25: 0 | Y25: TRUE | Z25: TRUE | AA25: 1 | AB25: 3.5 | AC25: 1 | AD25: none | AG25: none | AJ25: ew_tower | AK25: giong | BH25: ew_tower | BI25: spoof | BJ25: Small | BK25: radar_spoof_counterbattery | BL25: FALSE | BM25: 3 | BN25: 3 | BO25: 25 | BP25: 2.5 | BQ25: Campaign | BR25: ew_tower | BY25: ew_tower_b | CE25: ew_tower | CH25: 0 | CI25: 80 | CJ25: 6 | DB25: ew_tower | DP25: 3 | ED25: radar_spoof_counterbattery | EM25: Assets/MachineBrigade/Resources/Data/balance.json: vehicles[81] | EN25: {"id":"ew_tower.spoof","rebuildCp":3,"towerRole":"radar_spoof_counterbattery","art":"ew_tower_b","inherits":"ew_tower","branchOf":"ew_tower","counterBattery":{"range":80,"seconds":6,"bonus":0}}
A26: flare_searchlight_tower | B26: Flare tower (small slot) | C26: Tháp pháo sáng (ô nhỏ) | D26: Tháp pháo sáng | H26: 0 | I26: 455 | J26: 1001 | K26: 1 | L26: 1 | M26: 1 | N26: 1 | O26: TRUE | P26: 0 | Q26: 1 | R26: 90 | S26: 55 | T26: 1.8 | U26: 3.6 | V26: 3.6 | W26: FALSE | X26: 0 | Y26: TRUE | Z26: TRUE | AA26: 1 | AB26: 3.5 | AC26: 1 | AD26: illum_flare | AG26: flare | AH26: 0 | AI26: 0 | AJ26: flare_searchlight_tower | AK26: giong | BJ26: Small | BL26: FALSE | BM26: 2 | BN26: 2 | BO26: 25 | BP26: 2.5 | BQ26: Campaign | BR26: flare_searchlight_tower | BT26: 1 | CK26: 0 | CL26: 25 | CM26: 0.2 | CN26: 4 | CO26: Large | CU26: Small | DA26: 455 | DD26: 3.6 | DG26: flare_searchlight_tower | DH26: 5 | DI26: 3.6 | DJ26: 3.6 | DO26: 1.8 | DZ26: 0 | EA26: TRUE | EE26: 1 | EF26: 90 | EG26: 55 | EK26: illum_flare | EL26: 3.6 | EM26: Assets/MachineBrigade/Resources/Data/balance.json: vehicles[128] | EN26: {"id":"flare_searchlight_tower","model":"flare_searchlight_tower","modelSize":[3.6,3.6,5.0],"fort":{"size":"Small"},"static":true,"armour":1,"hp":455,"speed":0,"turnRate":1,"turretTurnRate":90,"radius":1.8,"length":3.6,"width":3.6,"cp":0,"vision":55,"weapon":"illum_flare","flares":{"every":15,"range":40,"radius":25,"seconds":15},"deathExplosion":{"damage":25,"radius":4,"delay":0.2,"tier":"Large"}}
A27: flare_tower | B27: Flare tower | C27: Tháp pháo sáng | D27: Tháp pháo sáng | H27: 0 | I27: 455 | J27: 1001 | K27: 1 | L27: 1 | M27: 1 | N27: 1 | O27: TRUE | P27: 0 | Q27: 1 | R27: 90 | S27: 60 | T27: 1.8 | U27: 3.6 | V27: 3.6 | W27: FALSE | X27: 0 | Y27: TRUE | Z27: TRUE | AA27: 1 | AB27: 3.5 | AC27: 1 | AD27: illum_flare | AG27: flare | AH27: 0 | AI27: 0 | AJ27: flare_tower | AK27: giong | BJ27: Small | BL27: FALSE | BM27: 2 | BN27: 2 | BO27: 25 | BP27: 2.5 | BQ27: Campaign | BR27: flare_tower | BT27: 1 | CK27: 0 | CL27: 30 | CM27: 0.2 | CN27: 4 | CO27: Large | CU27: Small | DA27: 455 | DD27: 3.6 | DH27: 5 | DI27: 3.6 | DJ27: 3.6 | DO27: 1.8 | DZ27: 0 | EA27: TRUE | EE27: 1 | EF27: 90 | EG27: 60 | EK27: illum_flare | EL27: 3.6 | EM27: Assets/MachineBrigade/Resources/Data/balance.json: vehicles[118] | EN27: {"id":"flare_tower","modelSize":[3.6,3.6,5.0],"fort":{"size":"Small"},"static":true,"armour":1,"hp":455,"speed":0,"turnRate":1,"turretTurnRate":90,"radius":1.8,"length":3.6,"width":3.6,"cp":0,"vision":60,"weapon":"illum_flare","flares":{"every":15,"range":40,"radius":30,"seconds":15},"deathExplosion":{"damage":30,"radius":4,"delay":0.2,"tier":"Large"}}
A28: guard_tower | B28: Guard tower | C28: Tháp canh | D28: Tháp canh | H28: 0 | I28: 700 | J28: 1540 | K28: 1 | L28: 1 | M28: 1 | N28: 1 | O28: TRUE | P28: 0 | Q28: 1 | R28: 200 | S28: 60 | T28: 1.8 | U28: 3.5 | V28: 3.5 | W28: FALSE | X28: 0 | Y28: TRUE | Z28: TRUE | AA28: 1 | AB28: 3.5 | AC28: 1 | AD28: tower_hmg | AG28: none | AJ28: guard_tower | AK28: giong | BJ28: Small | BL28: TRUE | BM28: 5 | BN28: 5 | BO28: 25 | BP28: 2.5 | BQ28: Starter | BR28: guard_tower | BT28: 1 | CF28: guard_tower.watch;guard_tower.nest | CK28: 0 | CL28: 60 | CM28: 0.3 | CN28: 5 | CO28: Large | CU28: Small | DA28: 700 | DD28: 3.5 | DO28: 1.8 | DP28: 5 | DU28: TRUE | DZ28: 0 | EA28: TRUE | EB28: 25 | EC28: 0.1 | EE28: 1 | EF28: 200 | EG28: 60 | EK28: tower_hmg | EL28: 3.5 | EM28: Assets/MachineBrigade/Resources/Data/balance.json: vehicles[107] | EN28: {"id":"guard_tower","rebuildCp":5,"branches":["guard_tower.watch","guard_tower.nest"],"fort":{"size":"Small"},"static":true,"armour":1,"hp":700,"speed":0,"turnRate":1,"turretTurnRate":200,"radius":1.8,"length":3.5,"width":3.5,"cp":0,"vision":60,"revealStealth":true,"towerRangeAura":{"radius":25,"range":0.1},"weapon":"tower_hmg","secondary":[],"deathExplosion":{"damage":60,"radius":5,"delay":0.3,"tier":"Large"}}
A29: guard_tower.nest | D29: Ổ súng | G29: guard_tower | H29: 0 | I29: 700 | J29: 1540 | K29: 1 | L29: 1 | M29: 1 | N29: 1 | O29: TRUE | P29: 0 | Q29: 1 | R29: 200 | S29: 48 | T29: 1.8 | U29: 3.5 | V29: 3.5 | W29: FALSE | X29: 0 | Y29: TRUE | Z29: TRUE | AA29: 1 | AB29: 3.5 | AC29: 1 | AD29: tower_ac25 | AG29: none | AJ29: guard_tower | AK29: giong | BH29: guard_tower | BI29: nest | BJ29: Small | BK29: autocannon_25 | BL29: FALSE | BM29: 5 | BN29: 5 | BO29: 25 | BP29: 2.5 | BQ29: Campaign | BR29: guard_tower | BY29: guard_tower_b | CE29: guard_tower | DB29: guard_tower | DP29: 5 | ED29: autocannon_25 | EG29: 48 | EK29: tower_ac25 | EM29: Assets/MachineBrigade/Resources/Data/balance.json: vehicles[77] | EN29: {"id":"guard_tower.nest","rebuildCp":5,"towerRole":"autocannon_25","art":"guard_tower_b","inherits":"guard_tower","branchOf":"guard_tower","weapon":"tower_ac25","vision":48}
A30: guard_tower.watch | D30: Tháp quan sát | G30: guard_tower | H30: 0 | I30: 700 | J30: 1540 | K30: 1 | L30: 1 | M30: 1 | N30: 1 | O30: TRUE | P30: 0 | Q30: 1 | R30: 200 | S30: 78 | T30: 1.8 | U30: 3.5 | V30: 3.5 | W30: FALSE | X30: 0 | Y30: TRUE | Z30: TRUE | AA30: 1 | AB30: 3.5 | AC30: 1 | AD30: tower_hmg | AG30: none | AJ30: guard_tower | AK30: giong | BH30: guard_tower | BI30: watch | BJ30: Small | BK30: observation_reach | BL30: FALSE | BM30: 5 | BN30: 5 | BO30: 25 | BP30: 2.5 | BQ30: Campaign | BR30: guard_tower | BY30: guard_tower_a | CE30: guard_tower | DB30: guard_tower | DP30: 5 | EB30: 35 | EC30: 0.15 | ED30: observation_reach | EG30: 78 | EM30: Assets/MachineBrigade/Resources/Data/balance.json: vehicles[76] | EN30: {"id":"guard_tower.watch","rebuildCp":5,"towerRole":"observation_reach","art":"guard_tower_a","inherits":"guard_tower","branchOf":"guard_tower","vision":78,"towerRangeAura":{"radius":35,"range":0.15}}
A31: gun_turret | B31: Gun turret | C31: Tháp pháo | D31: Tháp pháo | H31: 0 | I31: 1800 | J31: 3960 | K31: 3 | L31: 3 | M31: 3 | N31: 3 | O31: TRUE | P31: 0 | Q31: 1 | R31: 28 | S31: 42 | T31: 2.5 | U31: 5 | V31: 5 | W31: FALSE | X31: 0 | Y31: TRUE | Z31: TRUE | AA31: 1 | AB31: 3.5 | AC31: 1 | AD31: turret_gun_120 | AG31: none | AJ31: gun_turret | AK31: giong | BJ31: Medium | BL31: TRUE | BM31: 11 | BN31: 11 | BO31: 40 | BP31: 3.5 | BQ31: Starter | BR31: gun_turret | BT31: 3 | CF31: gun_turret.long;gun_turret.auto | CK31: 0 | CL31: 120 | CM31: 0.4 | CN31: 8 | CO31: Huge | CU31: Medium | DA31: 1800 | DD31: 5 | DO31: 2.5 | DP31: 11 | DZ31: 0 | EA31: TRUE | EE31: 1 | EF31: 28 | EG31: 42 | EK31: turret_gun_120 | EL31: 5 | EM31: Assets/MachineBrigade/Resources/Data/balance.json: vehicles[69] | EN31: {"id":"gun_turret","rebuildCp":11,"branches":["gun_turret.long","gun_turret.auto"],"fort":{"size":"Medium"},"static":true,"armour":3,"hp":1800,"speed":0,"turnRate":1,"turretTurnRate":28,"radius":2.5,"length":5,"width":5,"cp":0,"vision":42,"weapon":"turret_gun_120","secondary":[],"deathExplosion":{"damage":120,"radius":8,"delay":0.4,"tier":"Huge"}}
A32: gun_turret.auto | D32: Pháo 57 mm | G32: gun_turret | H32: 0 | I32: 1800 | J32: 3960 | K32: 3 | L32: 3 | M32: 3 | N32: 3 | O32: TRUE | P32: 0 | Q32: 1 | R32: 28 | S32: 42 | T32: 2.5 | U32: 5 | V32: 5 | W32: FALSE | X32: 0 | Y32: TRUE | Z32: TRUE | AA32: 1 | AB32: 3.5 | AC32: 1 | AD32: gun_57_auto | AG32: none | AJ32: gun_turret | AK32: giong | BH32: gun_turret | BI32: auto | BJ32: Medium | BK32: gun_57_light | BL32: FALSE | BM32: 11 | BN32: 11 | BO32: 40 | BP32: 3.5 | BQ32: Campaign | BR32: gun_turret | BY32: gun_turret_b | CE32: gun_turret | DB32: gun_turret | DP32: 11 | ED32: gun_57_light | EK32: gun_57_auto | EM32: Assets/MachineBrigade/Resources/Data/balance.json: vehicles[86] | EN32: {"id":"gun_turret.auto","rebuildCp":11,"towerRole":"gun_57_light","art":"gun_turret_b","inherits":"gun_turret","branchOf":"gun_turret","weapon":"gun_57_auto"}
A33: gun_turret.long | D33: Pháo bắn tỉa | G33: gun_turret | H33: 0 | I33: 1800 | J33: 3960 | K33: 3 | L33: 3 | M33: 3 | N33: 3 | O33: TRUE | P33: 0 | Q33: 1 | R33: 28 | S33: 42 | T33: 2.5 | U33: 5 | V33: 5 | W33: FALSE | X33: 0 | Y33: TRUE | Z33: TRUE | AA33: 1 | AB33: 3.5 | AC33: 1 | AD33: turret_gun_120_long | AG33: none | AJ33: gun_turret | AK33: giong | BH33: gun_turret | BI33: long | BJ33: Medium | BK33: gun_sniper_120 | BL33: FALSE | BM33: 11 | BN33: 11 | BO33: 40 | BP33: 3.5 | BQ33: Campaign | BR33: gun_turret | BY33: gun_turret_a | CE33: gun_turret | DB33: gun_turret | DP33: 11 | ED33: gun_sniper_120 | EK33: turret_gun_120_long | EM33: Assets/MachineBrigade/Resources/Data/balance.json: vehicles[85] | EN33: {"id":"gun_turret.long","rebuildCp":11,"towerRole":"gun_sniper_120","art":"gun_turret_a","inherits":"gun_turret","branchOf":"gun_turret","weapon":"turret_gun_120_long"}
A34: heavy_turret | B34: Heavy gun turret | C34: Tháp pháo hạng nặng | D34: Pháo hạng nặng | H34: 0 | I34: 2800 | J34: 6160 | K34: 4 | L34: 3 | M34: 3 | N34: 3 | O34: TRUE | P34: 0 | Q34: 1 | R34: 20 | S34: 60 | T34: 3.8 | U34: 8 | V34: 8 | W34: FALSE | X34: 0 | Y34: TRUE | Z34: TRUE | AA34: 1 | AB34: 3.5 | AC34: 1 | AD34: gun_155_twin_ap | AG34: none | AJ34: heavy_turret | AK34: giong | BJ34: Large | BL34: TRUE | BM34: 18 | BN34: 18 | BO34: 60 | BP34: 5 | BQ34: Campaign | BR34: heavy_turret | BU34: 4 | BV34: 3 | BW34: 3 | BX34: 3 | CF34: heavy_turret.coastal;heavy_turret.bastion | CK34: 0 | CL34: 220 | CM34: 0.5 | CN34: 12 | CO34: Ultimate | CU34: Large | DA34: 2800 | DD34: 8 | DO34: 3.8 | DP34: 18 | DZ34: 0 | EA34: TRUE | EE34: 1 | EF34: 20 | EG34: 60 | EK34: gun_155_twin_ap | EL34: 8 | EM34: Assets/MachineBrigade/Resources/Data/balance.json: vehicles[66] | EN34: {"id":"heavy_turret","rebuildCp":18,"branches":["heavy_turret.coastal","heavy_turret.bastion"],"fort":{"size":"Large"},"static":true,"armour":[4,3,3,3],"hp":2800,"speed":0,"turnRate":1,"turretTurnRate":20,"radius":3.8,"length":8,"width":8,"cp":0,"vision":60,"weapon":"gun_155_twin_ap","secondary":[],"deathExplosion":{"damage":220,"radius":12,"delay":0.5,"tier":"Ultimate"}}
A35: heavy_turret.bastion | D35: Pháo đài thép | G35: heavy_turret | H35: 0 | I35: 4340 | J35: 9548 | K35: 4 | L35: 3 | M35: 3 | N35: 3 | O35: TRUE | P35: 0 | Q35: 1 | R35: 20 | S35: 60 | T35: 3.8 | U35: 8 | V35: 8 | W35: FALSE | X35: 0 | Y35: TRUE | Z35: TRUE | AA35: 1 | AB35: 3.5 | AC35: 1 | AD35: gun_155_twin_ap | AE35: hmg_roof;hmg_roof | AG35: none | AJ35: heavy_turret | AK35: giong | BH35: heavy_turret | BI35: bastion | BJ35: Large | BK35: fortress_close_defence | BL35: FALSE | BM35: 18 | BN35: 18 | BO35: 60 | BP35: 5 | BQ35: Campaign | BR35: heavy_turret | BY35: heavy_turret_b | CE35: heavy_turret | DA35: 4340 | DB35: heavy_turret | DP35: 18 | ED35: fortress_close_defence | EM35: Assets/MachineBrigade/Resources/Data/balance.json: vehicles[98] | EN35: {"id":"heavy_turret.bastion","rebuildCp":18,"towerRole":"fortress_close_defence","art":"heavy_turret_b","secondary":[{"weapon":"hmg_roof","slot":"gun","aim":"Free"},{"weapon":"hmg_roof","slot":"gun","aim":"Free"}],"inherits":"heavy_turret","branchOf":"heavy_turret","hp":4340}
A36: heavy_turret.coastal | D36: Pháo bờ biển | G36: heavy_turret | H36: 0 | I36: 2800 | J36: 6160 | K36: 4 | L36: 3 | M36: 3 | N36: 3 | O36: TRUE | P36: 0 | Q36: 1 | R36: 20 | S36: 60 | T36: 3.8 | U36: 8 | V36: 8 | W36: FALSE | X36: 0 | Y36: TRUE | Z36: TRUE | AA36: 1 | AB36: 3.5 | AC36: 1 | AD36: gun_155_twin_coastlr | AG36: none | AJ36: heavy_turret | AK36: giong | BH36: heavy_turret | BI36: coastal | BJ36: Large | BK36: gun_coastal_long | BL36: FALSE | BM36: 18 | BN36: 18 | BO36: 60 | BP36: 5 | BQ36: Campaign | BR36: heavy_turret | BY36: heavy_turret_a | CE36: heavy_turret | DB36: heavy_turret | DP36: 18 | ED36: gun_coastal_long | EK36: gun_155_twin_coastlr | EM36: Assets/MachineBrigade/Resources/Data/balance.json: vehicles[97] | EN36: {"id":"heavy_turret.coastal","rebuildCp":18,"towerRole":"gun_coastal_long","art":"heavy_turret_a","inherits":"heavy_turret","branchOf":"heavy_turret","weapon":"gun_155_twin_coastlr"}
A37: laser_ad_station | B37: Laser Defence Tower | C37: Tháp la-de phòng thủ | D37: Tháp la-de | H37: 0 | I37: 1136 | J37: 2499.2 | K37: 1 | L37: 1 | M37: 1 | N37: 1 | O37: TRUE | P37: 0 | Q37: 1 | R37: 180 | S37: 56 | T37: 2.5 | U37: 5.5 | V37: 4 | W37: FALSE | X37: 0 | Y37: TRUE | Z37: TRUE | AA37: 1 | AB37: 3.5 | AC37: 1 | AD37: laser_50kw | AG37: aps | AH37: 1 | AI37: 0.8 | AJ37: laser_ad_station | AK37: giong | BJ37: Medium | BL37: TRUE | BM37: 5 | BN37: 5 | BO37: 40 | BP37: 3.5 | BQ37: Premium | BR37: laser_ad_station | BT37: 1 | CF37: laser_ad_station.laser | CK37: 0 | CL37: 80 | CM37: 0.4 | CN37: 7 | CO37: Huge | CU37: Medium | DA37: 1136 | DD37: 5.5 | DH37: 6.6 | DI37: 6 | DJ37: 3.85 | DO37: 2.5 | DP37: 5 | DZ37: 0 | EA37: TRUE | EE37: 1 | EF37: 180 | EG37: 56 | EK37: laser_50kw | EL37: 4 | EM37: Assets/MachineBrigade/Resources/Data/balance.json: vehicles[119] | EN37: {"id":"laser_ad_station","rebuildCp":5,"branches":["laser_ad_station.laser"],"modelSize":[6.0,3.85,6.6],"fort":{"size":"Medium"},"static":true,"armour":1,"hp":1136,"speed":0,"turnRate":1,"turretTurnRate":180,"radius":2.5,"length":5.5,"width":4.0,"cp":0,"vision":56,"weapon":"laser_50kw","aps":{"radius":40,"shells":0,"charges":1,"recharge":0.8,"rockets":true,"laser":true},"deathExplosion":{"damage":80,"radius":7,"delay":0.4,"tier":"Huge"}}
A38: laser_ad_station.laser | D38: La-de | G38: laser_ad_station | H38: 0 | I38: 1136 | J38: 2499.2 | K38: 1 | L38: 1 | M38: 1 | N38: 1 | O38: TRUE | P38: 0 | Q38: 1 | R38: 180 | S38: 56 | T38: 2.5 | U38: 5.5 | V38: 4 | W38: FALSE | X38: 0 | Y38: TRUE | Z38: TRUE | AA38: 1 | AB38: 3.5 | AC38: 1 | AD38: laser_50kw | AG38: aps | AH38: 1 | AI38: 0.8 | AJ38: laser_ad_station | AK38: moi | BH38: laser_ad_station | BI38: laser | BJ38: Medium | BK38: antidrone_laser | BL38: FALSE | BM38: 5 | BN38: 5 | BO38: 40 | BP38: 3.5 | BQ38: Campaign | BR38: laser_ad_station | CE38: laser_ad_station | DB38: laser_ad_station | DP38: 5 | ED38: antidrone_laser | EM38: Assets/MachineBrigade/Resources/Data/balance.json: vehicles[120] | EN38: {"id":"laser_ad_station.laser","rebuildCp":5,"inherits":"laser_ad_station","branchOf":"laser_ad_station","towerRole":"antidrone_laser"}
A39: manpads_tower | B39: MANPADS post | C39: Tổ tên lửa vác vai | D39: Tổ vác vai | H39: 0 | I39: 545 | J39: 1199 | K39: 1 | L39: 1 | M39: 1 | N39: 1 | O39: TRUE | P39: 0 | Q39: 1 | R39: 120 | S39: 40 | T39: 1.7 | U39: 3 | V39: 3 | W39: FALSE | X39: 0 | Y39: TRUE | Z39: TRUE | AA39: 1 | AB39: 3.5 | AC39: 1 | AD39: sam | AG39: none | AJ39: manpads_tower | AK39: giong | BJ39: Small | BL39: FALSE | BM39: 2 | BN39: 2 | BO39: 25 | BP39: 2.5 | BQ39: Campaign | BR39: manpads_tower | BT39: 1 | CK39: 0 | CU39: Small | DA39: 545 | DD39: 3 | DG39: manpads_tower | DH39: 2.4 | DI39: 3.2 | DJ39: 3.2 | DO39: 1.7 | DZ39: 0 | EA39: TRUE | EE39: 1 | EF39: 120 | EG39: 40 | EK39: sam | EL39: 3 | EM39: Assets/MachineBrigade/Resources/Data/balance.json: vehicles[135] | EN39: {"id":"manpads_tower","model":"manpads_tower","modelSize":[3.2,3.2,2.4],"fort":{"size":"Small"},"static":true,"armour":1,"hp":545,"speed":0,"turnRate":1,"turretTurnRate":120,"radius":1.7,"length":3.0,"width":3.0,"cp":0,"vision":40,"weapon":"sam"}
A40: mg_bunker | B40: MG bunker | C40: Lô cốt súng máy | D40: Lô cốt | H40: 0 | I40: 1500 | J40: 3300 | K40: 3 | L40: 2 | M40: 2 | N40: 2 | O40: TRUE | P40: 0 | Q40: 1 | R40: 120 | S40: 36 | T40: 2 | U40: 4 | V40: 4 | W40: FALSE | X40: 0 | Y40: TRUE | Z40: TRUE | AA40: 1 | AB40: 3.5 | AC40: 0.6086 | AD40: bunker_hmg | AE40: bunker_pkm;bunker_pkm;bunker_pkm;bunker_pkm | AG40: none | AJ40: mg_bunker | AK40: doi | BE40: bunker_pkm;bunker_pkm;bunker_pkm;bunker_pkm | BF40: 1 | BG40: 0.6086 | BJ40: Small | BL40: TRUE | BM40: 6 | BN40: 6 | BO40: 25 | BP40: 2.5 | BQ40: Starter | BR40: mg_bunker | BS40: giam_dps_giu_mau | BU40: 3 | BV40: 2 | BW40: 2 | BX40: 2 | CF40: mg_bunker.twin;mg_bunker.flame | CK40: 0 | CL40: 70 | CM40: 0.3 | CN40: 6 | CO40: Large | CU40: Small | DA40: 1500 | DD40: 4 | DM40: 0.6086 | DO40: 2 | DP40: 6 | DZ40: 0 | EA40: TRUE | EE40: 1 | EF40: 120 | EG40: 36 | EK40: bunker_hmg | EL40: 4 | EM40: Assets/MachineBrigade/Resources/Data/balance.json: vehicles[105] | EN40: {"id":"mg_bunker","outgoingDamageMult":0.6086,"rebuildCp":6,"branches":["mg_bunker.twin","mg_bunker.flame"],"fort":{"size":"Small"},"static":true,"armour":[3,2,2,2],"hp":1500,"speed":0,"turnRate":1,"turretTurnRate":120,"radius":2.0,"length":4,"width":4,"cp":0,"vision":36,"weapon":"bunker_hmg","deathExplosion":{"damage":70,"radius":6,"delay":0.3,"tier":"Large"},"secondary":[{"weapon":"bunker_pkm","slot":"mg","aim":"Free","arc":[-30,40]},{"weapon":"bunker_pkm","slot":"mg","aim":"Free","arc":[30,40]},{"weapon":"bunker_pkm","slot":"mg","aim":"Free","arc":[-90,40]},{"weapon":"bunker_pkm","slot":"mg","aim":"Free","arc":[90,40]}]}
A41: mg_bunker.flame | D41: Lô cốt lửa | G41: mg_bunker | H41: 0 | I41: 1500 | J41: 3300 | K41: 3 | L41: 2 | M41: 2 | N41: 2 | O41: TRUE | P41: 0 | Q41: 1 | R41: 120 | S41: 36 | T41: 2 | U41: 4 | V41: 4 | W41: FALSE | X41: 0 | Y41: TRUE | Z41: TRUE | AA41: 1 | AB41: 3.5 | AC41: 0.3248 | AD41: bunker_flame | AG41: none | AJ41: mg_bunker | AK41: doi | BF41: 1 | BG41: 0.3248 | BH41: mg_bunker | BI41: flame | BJ41: Small | BK41: flame_close | BL41: FALSE | BM41: 6 | BN41: 6 | BO41: 25 | BP41: 2.5 | BQ41: Campaign | BR41: mg_bunker | BS41: giam_dps_giu_mau | BY41: mg_bunker_b | CE41: mg_bunker | DB41: mg_bunker | DM41: 0.3248 | DP41: 6 | ED41: flame_close | EK41: bunker_flame | EM41: Assets/MachineBrigade/Resources/Data/balance.json: vehicles[79] | EN41: {"id":"mg_bunker.flame","outgoingDamageMult":0.3248,"rebuildCp":6,"towerRole":"flame_close","art":"mg_bunker_b","inherits":"mg_bunker","branchOf":"mg_bunker","weapon":"bunker_flame","secondary":[]}
A42: mg_bunker.twin | D42: Súng máy đôi | G42: mg_bunker | H42: 0 | I42: 1500 | J42: 3300 | K42: 3 | L42: 2 | M42: 2 | N42: 2 | O42: TRUE | P42: 0 | Q42: 1 | R42: 120 | S42: 36 | T42: 2 | U42: 4 | V42: 4 | W42: FALSE | X42: 0 | Y42: TRUE | Z42: TRUE | AA42: 1 | AB42: 3.5 | AC42: 0.5036 | AD42: bunker_hmg_twin | AE42: bunker_pkm;bunker_pkm;bunker_pkm;bunker_pkm | AG42: none | AJ42: mg_bunker | AK42: doi | BE42: bunker_pkm;bunker_pkm;bunker_pkm;bunker_pkm | BF42: 1 | BG42: 0.5036 | BH42: mg_bunker | BI42: twin | BJ42: Small | BK42: mg_twin | BL42: FALSE | BM42: 6 | BN42: 6 | BO42: 25 | BP42: 2.5 | BQ42: Campaign | BR42: mg_bunker | BS42: giam_dps_giu_mau | BY42: mg_bunker_a | CE42: mg_bunker | DB42: mg_bunker | DM42: 0.5036 | DP42: 6 | ED42: mg_twin | EK42: bunker_hmg_twin | EM42: Assets/MachineBrigade/Resources/Data/balance.json: vehicles[78] | EN42: {"id":"mg_bunker.twin","outgoingDamageMult":0.5036,"rebuildCp":6,"towerRole":"mg_twin","art":"mg_bunker_a","inherits":"mg_bunker","branchOf":"mg_bunker","weapon":"bunker_hmg_twin"}
A43: missile_battery | B43: Long-range SAM site | C43: Trạm tên lửa phòng không tầm xa | D43: Trạm PK tầm xa | H43: 0 | I43: 1900 | J43: 4180 | K43: 1 | L43: 1 | M43: 1 | N43: 1 | O43: TRUE | P43: 0 | Q43: 1 | R43: 70 | S43: 95 | T43: 3.8 | U43: 7 | V43: 9 | W43: FALSE | X43: 0 | Y43: TRUE | Z43: TRUE | AA43: 1 | AB43: 3.5 | AC43: 1 | AD43: patriot | AG43: none | AJ43: missile_battery | AK43: giong | BJ43: Large | BL43: TRUE | BM43: 13 | BN43: 13 | BO43: 60 | BP43: 5 | BQ43: Campaign | BR43: missile_battery | BT43: 1 | CF43: missile_battery.pac3;missile_battery.lrr | CK43: 0 | CL43: 200 | CM43: 0.4 | CN43: 12 | CO43: Ultimate | CS43: 1.2 | CU43: Large | DA43: 1900 | DD43: 7 | DO43: 3.8 | DP43: 13 | DZ43: 0 | EA43: TRUE | EE43: 1 | EF43: 70 | EG43: 95 | EK43: patriot | EL43: 9 | EM43: Assets/MachineBrigade/Resources/Data/balance.json: vehicles[67] | EN43: {"id":"missile_battery","erectSeconds":1.2,"rebuildCp":13,"branches":["missile_battery.pac3","missile_battery.lrr"],"fort":{"size":"Large"},"static":true,"armour":1,"hp":1900,"speed":0,"turnRate":1,"turretTurnRate":70,"radius":3.8,"length":7,"width":9,"cp":0,"vision":95,"weapon":"patriot","secondary":[],"deathExplosion":{"damage":200,"radius":12,"delay":0.4,"tier":"Ultimate"}}
A44: missile_battery.lrr | D44: Radar tầm xa | G44: missile_battery | H44: 0 | I44: 1900 | J44: 4180 | K44: 1 | L44: 1 | M44: 1 | N44: 1 | O44: TRUE | P44: 0 | Q44: 1 | R44: 70 | S44: 110 | T44: 3.8 | U44: 7 | V44: 9 | W44: FALSE | X44: 0 | Y44: TRUE | Z44: TRUE | AA44: 1 | AB44: 3.5 | AC44: 1 | AD44: sam_battery_lrr | AG44: none | AJ44: missile_battery | AK44: giong | BH44: missile_battery | BI44: lrr | BJ44: Large | BK44: sam_long_radar | BL44: FALSE | BM44: 12 | BN44: 12 | BO44: 60 | BP44: 5 | BQ44: Campaign | BR44: missile_battery | BY44: missile_battery_b | CE44: missile_battery | DB44: missile_battery | DP44: 12 | DT44: 140 | ED44: sam_long_radar | EG44: 110 | EK44: sam_battery_lrr | EM44: Assets/MachineBrigade/Resources/Data/balance.json: vehicles[94] | EN44: {"id":"missile_battery.lrr","rebuildCp":12,"towerRole":"sam_long_radar","art":"missile_battery_b","revealAir":140,"inherits":"missile_battery","branchOf":"missile_battery","weapon":"sam_battery_lrr","vision":110}
A45: missile_battery.pac3 | D45: PAC-3 | G45: missile_battery | H45: 0 | I45: 1900 | J45: 4180 | K45: 1 | L45: 1 | M45: 1 | N45: 1 | O45: TRUE | P45: 0 | Q45: 1 | R45: 70 | S45: 95 | T45: 3.8 | U45: 7 | V45: 9 | W45: FALSE | X45: 0 | Y45: TRUE | Z45: TRUE | AA45: 1 | AB45: 3.5 | AC45: 1 | AD45: sam_pac3 | AG45: aps | AH45: 4 | AJ45: missile_battery | AK45: giong | BH45: missile_battery | BI45: pac3 | BJ45: Large | BK45: intercept_heavy_missiles | BL45: FALSE | BM45: 9 | BN45: 9 | BO45: 60 | BP45: 5 | BQ45: Campaign | BR45: missile_battery | BY45: missile_battery_a | CE45: missile_battery | DB45: missile_battery | DP45: 9 | ED45: intercept_heavy_missiles | EK45: sam_pac3 | EM45: Assets/MachineBrigade/Resources/Data/balance.json: vehicles[93] | EN45: {"id":"missile_battery.pac3","rebuildCp":9,"towerRole":"intercept_heavy_missiles","art":"missile_battery_a","aps":{"radius":72,"charges":4,"reload":16,"heavy":true,"direct":false,"missiles":true},"inherits":"missile_battery","branchOf":"missile_battery","weapon":"sam_pac3"}
A46: one_shot_atgm_tower | B46: One-shot ATGM battery | C46: Bệ tên lửa phòng thủ một lần | D46: TL một lần | H46: 0 | I46: 909 | J46: 1999.8 | K46: 2 | L46: 2 | M46: 2 | N46: 2 | O46: TRUE | P46: 0 | Q46: 1 | R46: 90 | S46: 40 | T46: 2.3 | U46: 4.8 | V46: 4.8 | W46: FALSE | X46: 0 | Y46: TRUE | Z46: TRUE | AA46: 1 | AB46: 3.5 | AC46: 1 | AD46: one_shot_kornet | AG46: none | AJ46: one_shot_atgm_tower | AK46: giong | BJ46: Medium | BL46: FALSE | BM46: 4 | BN46: 4 | BO46: 40 | BP46: 3.5 | BQ46: Campaign | BR46: one_shot_atgm_tower | BT46: 2 | CK46: 0 | CL46: 80 | CM46: 0.4 | CN46: 7 | CO46: Huge | CU46: Medium | DA46: 909 | DD46: 4.8 | DG46: one_shot_atgm_tower | DH46: 3.6 | DI46: 4.8 | DJ46: 4.8 | DO46: 2.3 | DZ46: 0 | EA46: TRUE | EE46: 1 | EF46: 90 | EG46: 40 | EK46: one_shot_kornet | EL46: 4.8 | EM46: Assets/MachineBrigade/Resources/Data/balance.json: vehicles[134] | EN46: {"id":"one_shot_atgm_tower","model":"one_shot_atgm_tower","modelSize":[4.8,4.8,3.6],"fort":{"size":"Medium"},"static":true,"armour":2,"hp":909,"speed":0,"turnRate":1,"turretTurnRate":90,"radius":2.3,"length":4.8,"width":4.8,"cp":0,"vision":40,"weapon":"one_shot_kornet","deathExplosion":{"damage":80,"radius":7,"delay":0.4,"tier":"Huge"}}
A47: recoilless_gun_tower | B47: Recoilless gun post | C47: Ụ súng không giật | D47: Súng không giật | H47: 0 | I47: 545 | J47: 1199 | K47: 1 | L47: 1 | M47: 1 | N47: 1 | O47: TRUE | P47: 0 | Q47: 1 | R47: 120 | S47: 32 | T47: 1.8 | U47: 3.5 | V47: 3.5 | W47: FALSE | X47: 0 | Y47: TRUE | Z47: TRUE | AA47: 1 | AB47: 3.5 | AC47: 1 | AD47: spg9_73mm | AG47: none | AJ47: recoilless_gun_tower | AK47: giong | BJ47: Small | BL47: FALSE | BM47: 2 | BN47: 2 | BO47: 25 | BP47: 2.5 | BQ47: Campaign | BR47: recoilless_gun_tower | BT47: 1 | CK47: 0 | CL47: 40 | CM47: 0.25 | CN47: 5 | CO47: Large | CU47: Small | DA47: 545 | DD47: 3.5 | DG47: recoilless_gun_tower | DH47: 3 | DI47: 4.2 | DJ47: 4.2 | DO47: 1.8 | DZ47: 0 | EA47: TRUE | EE47: 1 | EF47: 120 | EG47: 32 | EK47: spg9_73mm | EL47: 3.5 | EM47: Assets/MachineBrigade/Resources/Data/balance.json: vehicles[129] | EN47: {"id":"recoilless_gun_tower","model":"recoilless_gun_tower","modelSize":[4.2,4.2,3.0],"fort":{"size":"Small"},"static":true,"armour":1,"hp":545,"speed":0,"turnRate":1,"turretTurnRate":120,"radius":1.8,"length":3.5,"width":3.5,"cp":0,"vision":32,"weapon":"spg9_73mm","deathExplosion":{"damage":40,"radius":5,"delay":0.25,"tier":"Large"}}
A48: rocket_turret | B48: Rocket battery | C48: Dàn rốc-két | D48: Dàn rốc-két | H48: 0 | I48: 1100 | J48: 2420 | K48: 1 | L48: 1 | M48: 1 | N48: 1 | O48: TRUE | P48: 0 | Q48: 1 | R48: 90 | S48: 55 | T48: 2.3 | U48: 4.5 | V48: 4.5 | W48: FALSE | X48: 0 | Y48: TRUE | Z48: TRUE | AA48: 1 | AB48: 3.5 | AC48: 1 | AD48: turret_rockets | AG48: none | AJ48: rocket_turret | AK48: giong | BJ48: Medium | BL48: TRUE | BM48: 11 | BN48: 11 | BO48: 40 | BP48: 3.5 | BQ48: Campaign | BR48: rocket_turret | BT48: 1 | CF48: rocket_turret.cluster;rocket_turret.guided | CK48: 0 | CL48: 140 | CM48: 0.4 | CN48: 9 | CO48: Huge | CU48: Medium | DA48: 1100 | DD48: 4.5 | DO48: 2.3 | DP48: 11 | DZ48: 0 | EA48: TRUE | EE48: 1 | EF48: 90 | EG48: 55 | EK48: turret_rockets | EL48: 4.5 | EM48: Assets/MachineBrigade/Resources/Data/balance.json: vehicles[104] | EN48: {"id":"rocket_turret","rebuildCp":11,"branches":["rocket_turret.cluster","rocket_turret.guided"],"fort":{"size":"Medium"},"static":true,"armour":1,"hp":1100,"speed":0,"turnRate":1,"turretTurnRate":90,"radius":2.3,"length":4.5,"width":4.5,"cp":0,"vision":55,"weapon":"turret_rockets","secondary":[],"deathExplosion":{"damage":140,"radius":9,"delay":0.4,"tier":"Huge"}}
A49: rocket_turret.cluster | D49: Rốc-két chùm | G49: rocket_turret | H49: 0 | I49: 1100 | J49: 2420 | K49: 1 | L49: 1 | M49: 1 | N49: 1 | O49: TRUE | P49: 0 | Q49: 1 | R49: 90 | S49: 55 | T49: 2.3 | U49: 4.5 | V49: 4.5 | W49: FALSE | X49: 0 | Y49: TRUE | Z49: TRUE | AA49: 1 | AB49: 3.5 | AC49: 1 | AD49: turret_rockets_cluster | AG49: none | AJ49: rocket_turret | AK49: giong | BH49: rocket_turret | BI49: cluster | BJ49: Medium | BK49: rockets_cluster | BL49: FALSE | BM49: 10 | BN49: 10 | BO49: 40 | BP49: 3.5 | BQ49: Campaign | BR49: rocket_turret | BY49: rocket_turret_a | CE49: rocket_turret | DB49: rocket_turret | DP49: 10 | ED49: rockets_cluster | EK49: turret_rockets_cluster | EM49: Assets/MachineBrigade/Resources/Data/balance.json: vehicles[89] | EN49: {"id":"rocket_turret.cluster","rebuildCp":10,"towerRole":"rockets_cluster","art":"rocket_turret_a","inherits":"rocket_turret","branchOf":"rocket_turret","weapon":"turret_rockets_cluster"}
A50: rocket_turret.guided | D50: Dẫn đường | G50: rocket_turret | H50: 0 | I50: 1100 | J50: 2420 | K50: 1 | L50: 1 | M50: 1 | N50: 1 | O50: TRUE | P50: 0 | Q50: 1 | R50: 90 | S50: 95 | T50: 2.3 | U50: 4.5 | V50: 4.5 | W50: FALSE | X50: 0 | Y50: TRUE | Z50: TRUE | AA50: 1 | AB50: 3.5 | AC50: 1 | AD50: turret_gmlrs | AG50: none | AJ50: rocket_turret | AK50: giong | BH50: rocket_turret | BI50: guided | BJ50: Medium | BK50: rockets_guided | BL50: FALSE | BM50: 9 | BN50: 9 | BO50: 40 | BP50: 3.5 | BQ50: Campaign | BR50: rocket_turret | BY50: rocket_turret_b | CE50: rocket_turret | DB50: rocket_turret | DP50: 9 | ED50: rockets_guided | EG50: 95 | EK50: turret_gmlrs | EM50: Assets/MachineBrigade/Resources/Data/balance.json: vehicles[90] | EN50: {"id":"rocket_turret.guided","rebuildCp":9,"towerRole":"rockets_guided","art":"rocket_turret_b","vision":95,"inherits":"rocket_turret","branchOf":"rocket_turret","weapon":"turret_gmlrs"}
A51: shield_tower | B51: Shield generator | C51: Máy phát khiên | D51: Máy phát khiên | H51: 0 | I51: 2000 | J51: 4400 | K51: 2 | L51: 2 | M51: 2 | N51: 2 | O51: TRUE | P51: 0 | Q51: 1 | R51: 1 | S51: 40 | T51: 3.2 | U51: 7 | V51: 7 | W51: FALSE | X51: 0 | Y51: TRUE | Z51: TRUE | AA51: 1 | AB51: 3.5 | AC51: 1 | AD51: none | AG51: none | AJ51: shield_tower | AK51: giong | BJ51: Large | BL51: TRUE | BM51: 10 | BN51: 10 | BO51: 60 | BP51: 5 | BQ51: Campaign | BR51: shield_tower | BT51: 2 | CF51: shield_tower.bulwark;shield_tower.ward | CK51: 0 | CL51: 160 | CM51: 0.4 | CN51: 9 | CO51: Huge | CP51: 3000 | CQ51: 25 | CR51: 30 | CU51: Large | DA51: 2000 | DD51: 7 | DO51: 3.2 | DP51: 10 | DZ51: 0 | EA51: TRUE | EE51: 1 | EF51: 1 | EG51: 40 | EK51: none | EL51: 7 | EM51: Assets/MachineBrigade/Resources/Data/balance.json: vehicles[108] | EN51: {"id":"shield_tower","rebuildCp":10,"branches":["shield_tower.bulwark","shield_tower.ward"],"fort":{"size":"Large"},"static":true,"armour":2,"hp":2000,"speed":0,"turnRate":1,"turretTurnRate":1,"radius":3.2,"length":7,"width":7,"cp":0,"vision":40,"weapon":"none","dome":{"radius":25,"hp":3000,"recharge":30},"deathExplosion":{"damage":160,"radius":9,"delay":0.4,"tier":"Huge"}}
A52: shield_tower.bulwark | D52: Vòm khiên | G52: shield_tower | H52: 0 | I52: 2000 | J52: 4400 | K52: 2 | L52: 2 | M52: 2 | N52: 2 | O52: TRUE | P52: 0 | Q52: 1 | R52: 1 | S52: 40 | T52: 3.2 | U52: 7 | V52: 7 | W52: FALSE | X52: 0 | Y52: TRUE | Z52: TRUE | AA52: 1 | AB52: 3.5 | AC52: 1 | AD52: none | AG52: none | AJ52: shield_tower | AK52: giong | BH52: shield_tower | BI52: bulwark | BJ52: Large | BK52: shield_dome | BL52: FALSE | BM52: 10 | BN52: 10 | BO52: 60 | BP52: 5 | BQ52: Campaign | BR52: shield_tower | BY52: shield_tower_a | CE52: shield_tower | CP52: 4200 | CQ52: 25 | CR52: 28 | DB52: shield_tower | DP52: 10 | ED52: shield_dome | EM52: Assets/MachineBrigade/Resources/Data/balance.json: vehicles[110] | EN52: {"id":"shield_tower.bulwark","rebuildCp":10,"towerRole":"shield_dome","art":"shield_tower_a","inherits":"shield_tower","branchOf":"shield_tower","dome":{"radius":25,"hp":4200,"recharge":28}}
A53: shield_tower.ward | D53: Lá chắn tháp | H53: 0 | I53: 2000 | J53: 4400 | K53: 2 | L53: 2 | M53: 2 | N53: 2 | O53: TRUE | P53: 0 | Q53: 1 | R53: 1 | S53: 40 | T53: 3.2 | U53: 7 | V53: 7 | W53: FALSE | X53: 0 | Y53: TRUE | Z53: TRUE | AA53: 1 | AB53: 3.5 | AC53: 1 | AD53: none | AG53: none | AJ53: shield_tower | AK53: giong | BH53: shield_tower | BI53: ward | BJ53: Large | BK53: tower_shields | BL53: FALSE | BM53: 10 | BN53: 10 | BO53: 60 | BP53: 5 | BQ53: Campaign | BR53: shield_tower | BT53: 2 | BY53: shield_tower_b | CE53: shield_tower | CK53: 0 | CL53: 160 | CM53: 0.4 | CN53: 9 | CO53: Huge | CU53: Large | DA53: 2000 | DD53: 7 | DG53: shield_tower | DO53: 3.2 | DP53: 10 | DZ53: 0 | EA53: TRUE | ED53: tower_shields | EE53: 1 | EF53: 1 | EG53: 40 | EH53: 1200 | EI53: 28 | EJ53: 6 | EK53: none | EL53: 7 | EM53: Assets/MachineBrigade/Resources/Data/balance.json: vehicles[111] | EN53: {"id":"shield_tower.ward","rebuildCp":10,"towerRole":"tower_shields","art":"shield_tower_b","branchOf":"shield_tower","model":"shield_tower","fort":{"size":"Large"},"static":true,"armour":2,"hp":2000,"speed":0,"turnRate":1,"turretTurnRate":1,"radius":3.2,"length":7,"width":7,"cp":0,"vision":40,"weapon":"none","wards":{"radius":28,"hp":1200,"recharge":6},"deathExplosion":{"damage":160,"radius":9,"delay":0.4,"tier":"Huge"}}
A54: spawn_bastion | B54: Camp bastion | C54: Tháp căn cứ | D54: Tháp căn cứ | E54: Defense | H54: 0 | I54: 5000 | J54: 11000 | K54: 4 | L54: 3 | M54: 3 | N54: 3 | O54: TRUE | P54: 0 | Q54: 1 | R54: 90 | S54: 44 | T54: 3.8 | U54: 8 | V54: 8 | W54: FALSE | X54: 0 | Y54: TRUE | Z54: TRUE | AA54: 1 | AB54: 3.5 | AC54: 1 | AD54: bastion_gun | AG54: none | AJ54: heavy_turret | AK54: giong | BL54: FALSE | BN54: 2 | BQ54: Campaign | BR54: spawn_bastion | BU54: 4 | BV54: 3 | BW54: 3 | BX54: 3 | CG54: Defense | CK54: 0 | CT54: TRUE | DA54: 5000 | DD54: 8 | DG54: heavy_turret | DO54: 3.8 | DZ54: 0 | EA54: TRUE | EE54: 1 | EF54: 90 | EG54: 44 | EK54: bastion_gun | EL54: 8 | EM54: Assets/MachineBrigade/Resources/Data/balance.json: vehicles[65] | EN54: {"id":"spawn_bastion","class":"Defense","static":true,"model":"heavy_turret","armour":[4,3,3,3],"hp":5000,"speed":0,"turnRate":1,"turretTurnRate":90,"radius":3.8,"length":8,"width":8,"cp":0,"vision":44,"firesWhileMoving":true,"weapon":"bastion_gun","secondary":[]}
A55: super_gun | B55: Super-gun | C55: Siêu pháo | D55: Siêu pháo | E55: Defense | H55: 0 | I55: 5200 | J55: 11440 | K55: 3 | L55: 3 | M55: 3 | N55: 3 | O55: TRUE | P55: 0 | Q55: 1 | R55: 12 | S55: 40 | T55: 7 | U55: 14.4 | V55: 14.4 | W55: FALSE | X55: 0 | Y55: TRUE | Z55: TRUE | AA55: 1 | AB55: 3.5 | AC55: 1 | AD55: none | AG55: none | AJ55: super_gun | AK55: giong | BL55: FALSE | BN55: 2 | BQ55: Campaign | BR55: super_gun | BT55: 3 | CG55: Defense | CK55: 0 | CL55: 380 | CM55: 0.6 | CN55: 18 | CO55: Ultimate | DA55: 5200 | DD55: 8 | DG55: super_gun | DO55: 7 | DV55: 1.8 | DZ55: 0 | EA55: TRUE | EE55: 1 | EF55: 12 | EG55: 40 | EK55: none | EL55: 8 | EM55: Assets/MachineBrigade/Resources/Data/balance.json: vehicles[64] | EN55: {"id":"super_gun","class":"Defense","static":true,"model":"super_gun","scale":1.8,"armour":3,"hp":5200,"speed":0,"turnRate":1,"turretTurnRate":12,"radius":7,"length":8,"width":8,"cp":0,"vision":40,"weapon":"none","deathExplosion":{"damage":380,"radius":18,"delay":0.6,"tier":"Ultimate"}}
A56: targeting_station | B56: Fire-control post | C56: Trạm chỉ thị mục tiêu | D56: Trạm chỉ thị | E56: Defense | H56: 0 | I56: 700 | J56: 1540 | K56: 1 | L56: 1 | M56: 1 | N56: 1 | O56: TRUE | P56: 0 | Q56: 1 | R56: 1 | S56: 110 | T56: 3.4 | U56: 8 | V56: 6.5 | W56: FALSE | X56: 0 | Y56: TRUE | Z56: TRUE | AA56: 1 | AB56: 3.5 | AC56: 1 | AD56: none | AG56: none | AJ56: targeting_station | AK56: giong | BL56: FALSE | BN56: 2 | BQ56: Campaign | BR56: targeting_station | BT56: 1 | CG56: Defense | CK56: 0 | CL56: 80 | CM56: 0.3 | CN56: 6 | CO56: Huge | DA56: 700 | DD56: 8 | DO56: 3.4 | DZ56: 0 | EA56: TRUE | EE56: 1 | EF56: 1 | EG56: 110 | EK56: none | EL56: 6.5 | EM56: Assets/MachineBrigade/Resources/Data/balance.json: vehicles[149] | EN56: {"id":"targeting_station","class":"Defense","static":true,"armour":1,"hp":700,"speed":0,"turnRate":1,"turretTurnRate":1,"radius":3.4,"length":8,"width":6.5,"cp":0,"vision":110,"weapon":"none","deathExplosion":{"damage":80,"radius":6,"delay":0.3,"tier":"Huge"}}
A57: vehicle_hangar | B57: Vehicle hangar | C57: Nhà chứa xe | D57: Nhà chứa xe | H57: 0 | I57: 1800 | J57: 3960 | K57: 2 | L57: 2 | M57: 2 | N57: 2 | O57: TRUE | P57: 0 | Q57: 1 | R57: 1 | S57: 50 | T57: 3.6 | U57: 8 | V57: 8 | W57: FALSE | X57: 0 | Y57: TRUE | Z57: TRUE | AA57: 1 | AB57: 3.5 | AC57: 1 | AD57: none | AG57: none | AJ57: vehicle_hangar_base | AK57: moi | BJ57: Medium | BL57: TRUE | BM57: 8 | BN57: 8 | BO57: 40 | BP57: 3.5 | BQ57: Campaign | BR57: vehicle_hangar | BT57: 2 | CK57: 0 | CL57: 120 | CM57: 0.4 | CN57: 8 | CO57: Huge | CU57: Medium | CV57: 2 | CW57: 5 | CX57: 60 | CY57: 20 | CZ57: scout_jeep;armored_car;light_tank | DA57: 1800 | DD57: 8 | DG57: vehicle_hangar_base | DH57: 4.93 | DI57: 8 | DJ57: 7.5 | DO57: 3.6 | DP57: 8 | DZ57: 0 | EA57: TRUE | EE57: 1 | EF57: 1 | EG57: 50 | EK57: none | EL57: 8 | EM57: Assets/MachineBrigade/Resources/Data/balance.json: vehicles[74] | EN57: {"id":"vehicle_hangar","rebuildCp":8,"model":"vehicle_hangar_base","modelSize":[8.0,7.5,4.93],"fort":{"size":"Medium"},"static":true,"armour":2,"hp":1800,"speed":0,"turnRate":1,"turretTurnRate":1,"radius":3.6,"length":8,"width":8,"cp":0,"vision":50,"weapon":"none","hangar":{"units":["scout_jeep","armored_car","light_tank"],"every":60,"alive":2,"budget":5,"post":20},"deathExplosion":{"damage":120,"radius":8,"delay":0.4,"tier":"Huge"}}

Sheet Thap_vu_khi
A1: id | B1: thap_id | C1: thu_tu | D1: weapon | E1: aim | F1: arc_deg_center_deg | G1: arc_deg_half_deg | H1: slot | I1: nguon | J1: raw_json
A2: aa_turret/0 | B2: aa_turret | C2: 0 | D2: sam | E2: Turret | H2: missile | I2: Assets/MachineBrigade/Resources/Data/balance.json: vehicles[70].secondary[0] | J2: {"weapon":"sam","slot":"missile","aim":"Turret"}
A3: heavy_turret.bastion/0 | B3: heavy_turret.bastion | C3: 0 | D3: hmg_roof | E3: Free | H3: gun | I3: Assets/MachineBrigade/Resources/Data/balance.json: vehicles[98].secondary[0] | J3: {"weapon":"hmg_roof","slot":"gun","aim":"Free"}
A4: heavy_turret.bastion/1 | B4: heavy_turret.bastion | C4: 1 | D4: hmg_roof | E4: Free | H4: gun | I4: Assets/MachineBrigade/Resources/Data/balance.json: vehicles[98].secondary[1] | J4: {"weapon":"hmg_roof","slot":"gun","aim":"Free"}
A5: mg_bunker/0 | B5: mg_bunker | C5: 0 | D5: bunker_pkm | E5: Free | F5: -30 | G5: 40 | H5: mg | I5: Assets/MachineBrigade/Resources/Data/balance.json: vehicles[105].secondary[0] | J5: {"weapon":"bunker_pkm","slot":"mg","aim":"Free","arc":[-30,40]}
A6: mg_bunker/1 | B6: mg_bunker | C6: 1 | D6: bunker_pkm | E6: Free | F6: 30 | G6: 40 | H6: mg | I6: Assets/MachineBrigade/Resources/Data/balance.json: vehicles[105].secondary[1] | J6: {"weapon":"bunker_pkm","slot":"mg","aim":"Free","arc":[30,40]}
A7: mg_bunker/2 | B7: mg_bunker | C7: 2 | D7: bunker_pkm | E7: Free | F7: -90 | G7: 40 | H7: mg | I7: Assets/MachineBrigade/Resources/Data/balance.json: vehicles[105].secondary[2] | J7: {"weapon":"bunker_pkm","slot":"mg","aim":"Free","arc":[-90,40]}
A8: mg_bunker/3 | B8: mg_bunker | C8: 3 | D8: bunker_pkm | E8: Free | F8: 90 | G8: 40 | H8: mg | I8: Assets/MachineBrigade/Resources/Data/balance.json: vehicles[105].secondary[3] | J8: {"weapon":"bunker_pkm","slot":"mg","aim":"Free","arc":[90,40]}

Sheet Tuong
A1: id | B1: ten_en | C1: ten_vi | D1: ten_ngan_vi | E1: lop | F1: nhanh | G1: ke_thua_tu | H1: base_cp | I1: mau_hp | J1: mau_trong_tran_hp | K1: giap_truoc | L1: giap_hong | M1: giap_sau | N1: giap_noc | O1: cong_trinh | P1: toc_do_m_s | Q1: xoay_than_deg_s | R1: xoay_thap_deg_s | S1: tam_nhin_m | T1: ban_kinh_m | U1: dai_m | V1: rong_m | W1: bay | X1: do_cao_m | Y1: dung_yen | Z1: ban_khi_chay | AA1: toc_do_chiem | AB1: tha_du_s | AC1: he_so_sat_thuong_ra | AD1: vu_khi_chinh | AE1: vu_khi_phu | AF1: noi_tai | AG1: tu_ve | AH1: so_lan_tu_ve | AI1: hoi_tu_ve_s | AJ1: mo_hinh | AK1: so_voi_ban_goc | AL1: base_cp_truoc | AM1: base_cp_sau | AN1: mau_hp_truoc | AO1: mau_hp_sau | AP1: giap_truoc_truoc | AQ1: giap_truoc_sau | AR1: giap_hong_truoc | AS1: giap_hong_sau | AT1: giap_sau_truoc | AU1: giap_sau_sau | AV1: giap_noc_truoc | AW1: giap_noc_sau | AX1: toc_do_m_s_truoc | AY1: toc_do_m_s_sau | AZ1: tam_nhin_m_truoc | BA1: tam_nhin_m_sau | BB1: vu_khi_chinh_truoc | BC1: vu_khi_chinh_sau | BD1: vu_khi_phu_truoc | BE1: vu_khi_phu_sau | BF1: he_so_sat_thuong_ra_truoc | BG1: he_so_sat_thuong_ra_sau | BH1: loai | BI1: do_ben_tuong_doi | BJ1: tuong_them | BK1: co_sung | BL1: trang_thai_navmesh | BM1: armour | BN1: card | BO1: cp | BP1: hp | BQ1: length_m | BR1: obstacle | BS1: radius_m | BT1: speed_m_s | BU1: static | BV1: turn_rate_deg_s | BW1: turret_turn_rate_deg_s | BX1: vision_m | BY1: wall | BZ1: weapon | CA1: width_m | CB1: nguon | CC1: raw_json
A2: wall_gun | B2: Gun wall | C2: Tường gắn súng | D2: Tường súng | H2: 0 | I2: 2880 | J2: 6336 | K2: 3 | L2: 3 | M2: 3 | N2: 3 | O2: TRUE | P2: 0 | Q2: 1 | R2: 1 | S2: 1 | T2: 1.5 | U2: 2 | V2: 12 | W2: FALSE | X2: 0 | Y2: TRUE | Z2: TRUE | AA2: 1 | AB2: 3.5 | AC2: 1 | AD2: none | AG2: none | AJ2: wall_gun | AK2: moi | BH2: gun_wall | BI2: 1.2 | BK2: TRUE | BL2: obstacle | BM2: 3 | BN2: FALSE | BO2: 0 | BP2: 2880 | BQ2: 2 | BR2: TRUE | BS2: 1.5 | BT2: 0 | BU2: TRUE | BV2: 1 | BW2: 1 | BX2: 1 | BY2: TRUE | BZ2: none | CA2: 12 | CB2: Assets/MachineBrigade/Resources/Data/balance.json: vehicles[84] | CC2: {"id":"wall_gun","card":false,"wall":true,"static":true,"obstacle":true,"armour":3,"hp":2880,"speed":0,"turnRate":1,"turretTurnRate":1,"radius":1.5,"length":2,"width":12,"cp":0,"vision":1,"weapon":"none"}
A3: wall_hesco | B3: HESCO wall | C3: Tường HESCO | D3: HESCO | H3: 0 | I3: 2400 | J3: 5280 | K3: 3 | L3: 3 | M3: 3 | N3: 3 | O3: TRUE | P3: 0 | Q3: 1 | R3: 1 | S3: 1 | T3: 1.5 | U3: 2 | V3: 12 | W3: FALSE | X3: 0 | Y3: TRUE | Z3: TRUE | AA3: 1 | AB3: 3.5 | AC3: 1 | AD3: none | AG3: none | AJ3: wall_hesco | AK3: moi | BH3: hesco | BI3: 1 | BL3: obstacle | BM3: 3 | BN3: FALSE | BO3: 0 | BP3: 2400 | BQ3: 2 | BR3: TRUE | BS3: 1.5 | BT3: 0 | BU3: TRUE | BV3: 1 | BW3: 1 | BX3: 1 | BY3: TRUE | BZ3: none | CA3: 12 | CB3: Assets/MachineBrigade/Resources/Data/balance.json: vehicles[82] | CC3: {"id":"wall_hesco","card":false,"wall":true,"static":true,"obstacle":true,"armour":3,"hp":2400,"speed":0,"turnRate":1,"turretTurnRate":1,"radius":1.5,"length":2,"width":12,"cp":0,"vision":1,"weapon":"none"}
A4: wall_t | B4: T-wall | C4: Tường chữ T | D4: Tường T | H4: 0 | I4: 3840 | J4: 8448 | K4: 4 | L4: 4 | M4: 4 | N4: 4 | O4: TRUE | P4: 0 | Q4: 1 | R4: 1 | S4: 1 | T4: 1.5 | U4: 2 | V4: 12 | W4: FALSE | X4: 0 | Y4: TRUE | Z4: TRUE | AA4: 1 | AB4: 3.5 | AC4: 1 | AD4: none | AG4: none | AJ4: wall_t | AK4: moi | BH4: t_wall | BI4: 1.6 | BJ4: TRUE | BL4: obstacle | BM4: 4 | BN4: FALSE | BO4: 0 | BP4: 3840 | BQ4: 2 | BR4: TRUE | BS4: 1.5 | BT4: 0 | BU4: TRUE | BV4: 1 | BW4: 1 | BX4: 1 | BY4: TRUE | BZ4: none | CA4: 12 | CB4: Assets/MachineBrigade/Resources/Data/balance.json: vehicles[83] | CC4: {"id":"wall_t","card":false,"wall":true,"static":true,"obstacle":true,"armour":4,"hp":3840,"speed":0,"turnRate":1,"turretTurnRate":1,"radius":1.5,"length":2,"width":12,"cp":0,"vision":1,"weapon":"none"}

Sheet Tuong_luat
A1: id | B1: nhom | C1: khoa | D1: gia_tri_so | E1: gia_tri_chu | F1: don_vi | G1: nguon | H1: raw_json
A2: ai.brandt | B2: base.walls | C2: brandt | E2: t_wall | G2: Assets/MachineBrigade/Resources/Data/balance.json: base.walls.ai.brandt | H2: "t_wall"
A3: ai.default | B3: base.walls | C3: default | E3: hesco | G3: Assets/MachineBrigade/Resources/Data/balance.json: base.walls.ai.default | H3: "hesco"
A4: ai.kessler | B4: base.walls | C4: kessler | E4: t_wall | G4: Assets/MachineBrigade/Resources/Data/balance.json: base.walls.ai.kessler | H4: "t_wall"
A5: ai.varga | B5: base.walls | C5: varga | E5: gun_wall | G5: Assets/MachineBrigade/Resources/Data/balance.json: base.walls.ai.varga | H5: "gun_wall"
A6: breakerMultiplier | B6: base.walls | C6: breakerMultiplier | D6: 1.5 | G6: Assets/MachineBrigade/Resources/Data/balance.json: base.walls.breakerMultiplier | H6: 1.5
A7: breakers | B7: base.walls | C7: breakers | E7: armored_bulldozer;engineer_vehicle;demolition_line_vehicle | G7: Assets/MachineBrigade/Resources/Data/balance.json: base.walls.breakers | H7: ["armored_bulldozer","engineer_vehicle","demolition_line_vehicle"]
A8: campLines | B8: base.walls | C8: campLines | D8: 2 | G8: Assets/MachineBrigade/Resources/Data/balance.json: base.walls.campLines | H8: 2
A9: default | B9: base.walls | C9: default | E9: hesco | G9: Assets/MachineBrigade/Resources/Data/balance.json: base.walls.default | H9: "hesco"
A10: fortressLines | B10: base.walls | C10: fortressLines | D10: 3 | G10: Assets/MachineBrigade/Resources/Data/balance.json: base.walls.fortressLines | H10: 3
A11: rubbleSlow | B11: base.walls | C11: rubbleSlow | D11: 0.2 | G11: Assets/MachineBrigade/Resources/Data/balance.json: base.walls.rubbleSlow | H11: 0.2
A12: segmentHp | B12: base.walls | C12: segmentHp | D12: 2400 | G12: Assets/MachineBrigade/Resources/Data/balance.json: base.walls.segmentHp | H12: 2400

Sheet Nha_chinh
A1: id | B1: ten_en | C1: ten_vi | D1: ten_ngan_vi | E1: lop | F1: nhanh | G1: ke_thua_tu | H1: base_cp | I1: mau_hp | J1: mau_trong_tran_hp | K1: giap_truoc | L1: giap_hong | M1: giap_sau | N1: giap_noc | O1: cong_trinh | P1: toc_do_m_s | Q1: xoay_than_deg_s | R1: xoay_thap_deg_s | S1: tam_nhin_m | T1: ban_kinh_m | U1: dai_m | V1: rong_m | W1: bay | X1: do_cao_m | Y1: dung_yen | Z1: ban_khi_chay | AA1: toc_do_chiem | AB1: tha_du_s | AC1: he_so_sat_thuong_ra | AD1: vu_khi_chinh | AE1: vu_khi_phu | AF1: noi_tai | AG1: tu_ve | AH1: so_lan_tu_ve | AI1: hoi_tu_ve_s | AJ1: mo_hinh | AK1: so_voi_ban_goc | AL1: base_cp_truoc | AM1: base_cp_sau | AN1: mau_hp_truoc | AO1: mau_hp_sau | AP1: giap_truoc_truoc | AQ1: giap_truoc_sau | AR1: giap_hong_truoc | AS1: giap_hong_sau | AT1: giap_sau_truoc | AU1: giap_sau_sau | AV1: giap_noc_truoc | AW1: giap_noc_sau | AX1: toc_do_m_s_truoc | AY1: toc_do_m_s_sau | AZ1: tam_nhin_m_truoc | BA1: tam_nhin_m_sau | BB1: vu_khi_chinh_truoc | BC1: vu_khi_chinh_sau | BD1: vu_khi_phu_truoc | BE1: vu_khi_phu_sau | BF1: he_so_sat_thuong_ra_truoc | BG1: he_so_sat_thuong_ra_sau | BH1: armour | BI1: class | BJ1: cp | BK1: death_explosion_damage | BL1: death_explosion_delay_s | BM1: death_explosion_radius_m | BN1: death_explosion_tier | BO1: fires_while_moving | BP1: fort_kind | BQ1: fort_points | BR1: hp | BS1: inherits | BT1: length_m | BU1: model | BV1: radius_m | BW1: scale | BX1: speed_m_s | BY1: static | BZ1: turn_rate_deg_s | CA1: turret_turn_rate_deg_s | CB1: vision_m | CC1: weapon | CD1: width_m | CE1: nguon | CF1: raw_json
A2: headquarters | B2: Headquarters | C2: Sở chỉ huy | D2: Sở chỉ huy | E2: Defense | H2: 0 | I2: 9000 | J2: 19800 | K2: 4 | L2: 4 | M2: 4 | N2: 4 | O2: TRUE | P2: 0 | Q2: 1 | R2: 90 | S2: 50 | T2: 6.8 | U2: 12 | V2: 14 | W2: FALSE | X2: 0 | Y2: TRUE | Z2: TRUE | AA2: 1 | AB2: 3.5 | AC2: 1 | AD2: bastion_gun | AE2: hq_flak;hq_flak;mg_coax | AG2: none | AJ2: headquarters | AK2: giong | BH2: 4 | BI2: Defense | BJ2: 0 | BK2: 260 | BL2: 0.8 | BM2: 14 | BN2: Ultimate | BO2: TRUE | BP2: Hq | BQ2: 0 | BR2: 9000 | BT2: 12 | BU2: headquarters | BV2: 6.8 | BW2: 1 | BX2: 0 | BY2: TRUE | BZ2: 1 | CA2: 90 | CB2: 50 | CC2: bastion_gun | CD2: 14 | CE2: Assets/MachineBrigade/Resources/Data/balance.json: vehicles[60] | CF2: {"id":"headquarters","class":"Defense","static":true,"model":"headquarters","armour":4,"hp":9000,"speed":0,"turnRate":1,"turretTurnRate":90,"radius":6.8,"length":12,"width":14,"scale":1.0,"cp":0,"vision":50,"firesWhileMoving":true,"weapon":"bastion_gun","fort":{"points":0,"kind":"Hq"},"secondary":[{"weapon":"hq_flak","slot":"mg","aim":"Free"},{"weapon":"hq_flak","slot":"mg","aim":"Free"},{"weapon":"mg_coax","slot":"coax","aim":"Turret"}],"deathExplosion":{"damage":260,"radius":14,"delay":0.8,"tier":"Ultimate"}}
A3: headquarters.fortress_air | B3: Headquarters · AA Fortress | C3: Sở chỉ huy · Pháo đài phòng không | D3: Pháo đài PK | E3: Defense | G3: headquarters | H3: 0 | I3: 9000 | J3: 19800 | K3: 4 | L3: 4 | M3: 4 | N3: 4 | O3: TRUE | P3: 0 | Q3: 1 | R3: 90 | S3: 50 | T3: 6.8 | U3: 12 | V3: 14 | W3: FALSE | X3: 0 | Y3: TRUE | Z3: TRUE | AA3: 1 | AB3: 3.5 | AC3: 1 | AD3: bastion_gun | AE3: hq_flak;hq_flak;mg_coax;bofors_l70 | AG3: none | AJ3: headquarters | AK3: moi | BS3: headquarters | CE3: Assets/MachineBrigade/Resources/Data/balance.json: vehicles[62] | CF3: {"id":"headquarters.fortress_air","inherits":"headquarters","secondary":[{"weapon":"hq_flak","slot":"mg","aim":"Free"},{"weapon":"hq_flak","slot":"mg","aim":"Free"},{"weapon":"mg_coax","slot":"coax","aim":"Turret"},{"weapon":"bofors_l70","slot":"gun","aim":"Free"}]}
A4: headquarters.fortress_ground | B4: Headquarters · Fortress | C4: Sở chỉ huy · Pháo đài | D4: SCH Pháo đài | E4: Defense | G4: headquarters | H4: 0 | I4: 9000 | J4: 19800 | K4: 4 | L4: 4 | M4: 4 | N4: 4 | O4: TRUE | P4: 0 | Q4: 1 | R4: 90 | S4: 50 | T4: 6.8 | U4: 12 | V4: 14 | W4: FALSE | X4: 0 | Y4: TRUE | Z4: TRUE | AA4: 1 | AB4: 3.5 | AC4: 1 | AD4: bastion_gun | AE4: hq_flak;hq_flak;mg_coax;turret_gun_120_long | AG4: none | AJ4: headquarters | AK4: moi | BS4: headquarters | CE4: Assets/MachineBrigade/Resources/Data/balance.json: vehicles[61] | CF4: {"id":"headquarters.fortress_ground","inherits":"headquarters","secondary":[{"weapon":"hq_flak","slot":"mg","aim":"Free"},{"weapon":"hq_flak","slot":"mg","aim":"Free"},{"weapon":"mg_coax","slot":"coax","aim":"Turret"},{"weapon":"turret_gun_120_long","slot":"gun","aim":"Free"}]}
A5: headquarters.shield | B5: Headquarters · Shield | C5: Sở chỉ huy · Lá chắn | D5: SCH Lá chắn | E5: Defense | G5: headquarters | H5: 0 | I5: 9000 | J5: 19800 | K5: 4 | L5: 4 | M5: 4 | N5: 4 | O5: TRUE | P5: 0 | Q5: 1 | R5: 90 | S5: 50 | T5: 6.8 | U5: 12 | V5: 14 | W5: FALSE | X5: 0 | Y5: TRUE | Z5: TRUE | AA5: 1 | AB5: 3.5 | AC5: 1 | AD5: bastion_gun | AE5: hq_flak;hq_flak;mg_coax | AG5: aps | AH5: 6 | AI5: 0.6 | AJ5: headquarters | AK5: moi | BS5: headquarters | CE5: Assets/MachineBrigade/Resources/Data/balance.json: vehicles[63] | CF5: {"id":"headquarters.shield","inherits":"headquarters","aps":{"radius":45,"charges":6,"recharge":0.6,"rockets":true,"shells":0.3,"burst":0.5}}

Sheet Nha_chinh_vu_khi
A1: id | B1: nha_chinh_id | C1: thu_tu | D1: weapon | E1: aim | F1: slot | G1: nguon | H1: raw_json
A2: headquarters.fortress_air/0 | B2: headquarters.fortress_air | C2: 0 | D2: hq_flak | E2: Free | F2: mg | G2: Assets/MachineBrigade/Resources/Data/balance.json: vehicles[62].secondary[0] | H2: {"weapon":"hq_flak","slot":"mg","aim":"Free"}
A3: headquarters.fortress_air/1 | B3: headquarters.fortress_air | C3: 1 | D3: hq_flak | E3: Free | F3: mg | G3: Assets/MachineBrigade/Resources/Data/balance.json: vehicles[62].secondary[1] | H3: {"weapon":"hq_flak","slot":"mg","aim":"Free"}
A4: headquarters.fortress_air/2 | B4: headquarters.fortress_air | C4: 2 | D4: mg_coax | E4: Turret | F4: coax | G4: Assets/MachineBrigade/Resources/Data/balance.json: vehicles[62].secondary[2] | H4: {"weapon":"mg_coax","slot":"coax","aim":"Turret"}
A5: headquarters.fortress_air/3 | B5: headquarters.fortress_air | C5: 3 | D5: bofors_l70 | E5: Free | F5: gun | G5: Assets/MachineBrigade/Resources/Data/balance.json: vehicles[62].secondary[3] | H5: {"weapon":"bofors_l70","slot":"gun","aim":"Free"}
A6: headquarters.fortress_ground/0 | B6: headquarters.fortress_ground | C6: 0 | D6: hq_flak | E6: Free | F6: mg | G6: Assets/MachineBrigade/Resources/Data/balance.json: vehicles[61].secondary[0] | H6: {"weapon":"hq_flak","slot":"mg","aim":"Free"}
A7: headquarters.fortress_ground/1 | B7: headquarters.fortress_ground | C7: 1 | D7: hq_flak | E7: Free | F7: mg | G7: Assets/MachineBrigade/Resources/Data/balance.json: vehicles[61].secondary[1] | H7: {"weapon":"hq_flak","slot":"mg","aim":"Free"}
A8: headquarters.fortress_ground/2 | B8: headquarters.fortress_ground | C8: 2 | D8: mg_coax | E8: Turret | F8: coax | G8: Assets/MachineBrigade/Resources/Data/balance.json: vehicles[61].secondary[2] | H8: {"weapon":"mg_coax","slot":"coax","aim":"Turret"}
A9: headquarters.fortress_ground/3 | B9: headquarters.fortress_ground | C9: 3 | D9: turret_gun_120_long | E9: Free | F9: gun | G9: Assets/MachineBrigade/Resources/Data/balance.json: vehicles[61].secondary[3] | H9: {"weapon":"turret_gun_120_long","slot":"gun","aim":"Free"}
A10: headquarters/0 | B10: headquarters | C10: 0 | D10: hq_flak | E10: Free | F10: mg | G10: Assets/MachineBrigade/Resources/Data/balance.json: vehicles[60].secondary[0] | H10: {"weapon":"hq_flak","slot":"mg","aim":"Free"}
A11: headquarters/1 | B11: headquarters | C11: 1 | D11: hq_flak | E11: Free | F11: mg | G11: Assets/MachineBrigade/Resources/Data/balance.json: vehicles[60].secondary[1] | H11: {"weapon":"hq_flak","slot":"mg","aim":"Free"}
A12: headquarters/2 | B12: headquarters | C12: 2 | D12: mg_coax | E12: Turret | F12: coax | G12: Assets/MachineBrigade/Resources/Data/balance.json: vehicles[60].secondary[2] | H12: {"weapon":"mg_coax","slot":"coax","aim":"Turret"}

Sheet Nha_chinh_kieu
A1: id | B1: nha_chinh | C1: ai_air_share | D1: air | E1: barrage | F1: callable | G1: charges | H1: clear | I1: dome_seconds_s | J1: ground | K1: hq | L1: regen_delay_s | M1: stock | N1: nguon | O1: raw_json
A2: fortress | B2: headquarters.fortress_ground;headquarters.fortress_air | C2: 0.3 | D2: headquarters.fortress_air | E2: hq_barrage | J2: headquarters.fortress_ground | N2: Assets/MachineBrigade/Resources/Data/balance.json: base.hqTypes.fortress | O2: {"ground":"headquarters.fortress_ground","air":"headquarters.fortress_air","barrage":"hq_barrage","scale":[0.29,0.36,0.42,0.49,0.55],"airScale":[0.16,0.2,0.23,0.27,0.31],"aiAirShare":0.3}
A3: garrison | F3: scout_jeep;armored_car;light_tank | H3: 30 | M3: 2 | N3: Assets/MachineBrigade/Resources/Data/balance.json: base.hqTypes.garrison | O3: {"every":[120.0,100.0,100.0,130.0,170.0],"stock":2,"clear":30,"caps":[6,8,10,12,15],"squads":[{"units":["light_tank"]},{"units":["armored_car","scout_jeep"]},{"units":["light_tank","armored_car"]},{"units":["main_battle_tank"]},{"units":["main_battle_tank","scout_jeep"]}],"callable":["scout_jeep","armored_car","light_tank"]}
A4: shield | B4: headquarters.shield | G4: 4 | I4: 10 | K4: headquarters.shield | L4: 5 | N4: Assets/MachineBrigade/Resources/Data/balance.json: base.hqTypes.shield | O4: {"hq":"headquarters.shield","scale":[0.15,0.19,0.24,0.26,0.29],"charges":4,"regenDelay":5,"regen":[0.00059,0.00073,0.0009,0.00092,0.00096],"dome":[0.024,0.029,0.036,0.04,0.043],"domeSeconds":10}

Sheet Nha_chinh_kieu_cap
A1: id | B1: kieu | C1: cap_hq | D1: scale | E1: airScale | F1: every | G1: caps | H1: regen | I1: dome | J1: squads_units | K1: nguon | L1: raw_json
A2: fortress/1 | B2: fortress | C2: 1 | D2: 0.29 | E2: 0.16 | K2: Assets/MachineBrigade/Resources/Data/balance.json: base.hqTypes.fortress [cấp 1]
A3: fortress/2 | B3: fortress | C3: 2 | D3: 0.36 | E3: 0.2 | K3: Assets/MachineBrigade/Resources/Data/balance.json: base.hqTypes.fortress [cấp 2]
A4: fortress/3 | B4: fortress | C4: 3 | D4: 0.42 | E4: 0.23 | K4: Assets/MachineBrigade/Resources/Data/balance.json: base.hqTypes.fortress [cấp 3]
A5: fortress/4 | B5: fortress | C5: 4 | D5: 0.49 | E5: 0.27 | K5: Assets/MachineBrigade/Resources/Data/balance.json: base.hqTypes.fortress [cấp 4]
A6: fortress/5 | B6: fortress | C6: 5 | D6: 0.55 | E6: 0.31 | K6: Assets/MachineBrigade/Resources/Data/balance.json: base.hqTypes.fortress [cấp 5]
A7: garrison/1 | B7: garrison | C7: 1 | F7: 120 | G7: 6 | J7: light_tank | K7: Assets/MachineBrigade/Resources/Data/balance.json: base.hqTypes.garrison [cấp 1]
A8: garrison/2 | B8: garrison | C8: 2 | F8: 100 | G8: 8 | J8: armored_car;scout_jeep | K8: Assets/MachineBrigade/Resources/Data/balance.json: base.hqTypes.garrison [cấp 2]
A9: garrison/3 | B9: garrison | C9: 3 | F9: 100 | G9: 10 | J9: light_tank;armored_car | K9: Assets/MachineBrigade/Resources/Data/balance.json: base.hqTypes.garrison [cấp 3]
A10: garrison/4 | B10: garrison | C10: 4 | F10: 130 | G10: 12 | J10: main_battle_tank | K10: Assets/MachineBrigade/Resources/Data/balance.json: base.hqTypes.garrison [cấp 4]
A11: garrison/5 | B11: garrison | C11: 5 | F11: 170 | G11: 15 | J11: main_battle_tank;scout_jeep | K11: Assets/MachineBrigade/Resources/Data/balance.json: base.hqTypes.garrison [cấp 5]
A12: shield/1 | B12: shield | C12: 1 | D12: 0.15 | H12: 0.00059 | I12: 0.024 | K12: Assets/MachineBrigade/Resources/Data/balance.json: base.hqTypes.shield [cấp 1]
A13: shield/2 | B13: shield | C13: 2 | D13: 0.19 | H13: 0.00073 | I13: 0.029 | K13: Assets/MachineBrigade/Resources/Data/balance.json: base.hqTypes.shield [cấp 2]
A14: shield/3 | B14: shield | C14: 3 | D14: 0.24 | H14: 0.0009 | I14: 0.036 | K14: Assets/MachineBrigade/Resources/Data/balance.json: base.hqTypes.shield [cấp 3]
A15: shield/4 | B15: shield | C15: 4 | D15: 0.26 | H15: 0.00092 | I15: 0.04 | K15: Assets/MachineBrigade/Resources/Data/balance.json: base.hqTypes.shield [cấp 4]
A16: shield/5 | B16: shield | C16: 5 | D16: 0.29 | H16: 0.00096 | I16: 0.043 | K16: Assets/MachineBrigade/Resources/Data/balance.json: base.hqTypes.shield [cấp 5]

Sheet Nha_chinh_luat
A1: id | B1: nhom | C1: khoa | D1: gia_tri_so | E1: gia_tri_chu | F1: don_vi | G1: nguon | H1: raw_json
A2: hq | B2: base | C2: hq | E2: headquarters | G2: Assets/MachineBrigade/Resources/Data/balance.json: base.hq | H2: "headquarters"
A3: hqTypes.ai.Easy | B3: base.hqTypes | C3: Easy | E3: garrison | G3: Assets/MachineBrigade/Resources/Data/balance.json: base.hqTypes.ai.Easy | H3: "garrison"
A4: hqTypes.ai.Hard | B4: base.hqTypes | C4: Hard | E4: shield | G4: Assets/MachineBrigade/Resources/Data/balance.json: base.hqTypes.ai.Hard | H4: "shield"
A5: hqTypes.ai.Normal | B5: base.hqTypes | C5: Normal | E5: fortress | G5: Assets/MachineBrigade/Resources/Data/balance.json: base.hqTypes.ai.Normal | H5: "fortress"
A6: hqTypes.ai.VeryHard | B6: base.hqTypes | C6: VeryHard | E6: fortress | G6: Assets/MachineBrigade/Resources/Data/balance.json: base.hqTypes.ai.VeryHard | H6: "fortress"
A7: hqTypes.ai.aurel | B7: base.hqTypes | C7: aurel | E7: shield | G7: Assets/MachineBrigade/Resources/Data/balance.json: base.hqTypes.ai.aurel | H7: "shield"
A8: hqTypes.ai.brandt | B8: base.hqTypes | C8: brandt | E8: fortress | G8: Assets/MachineBrigade/Resources/Data/balance.json: base.hqTypes.ai.brandt | H8: "fortress"
A9: hqTypes.ai.kessler | B9: base.hqTypes | C9: kessler | E9: fortress | G9: Assets/MachineBrigade/Resources/Data/balance.json: base.hqTypes.ai.kessler | H9: "fortress"
A10: hqTypes.ai.orlov | B10: base.hqTypes | C10: orlov | E10: shield | G10: Assets/MachineBrigade/Resources/Data/balance.json: base.hqTypes.ai.orlov | H10: "shield"
A11: hqTypes.ai.varga | B11: base.hqTypes | C11: varga | E11: garrison | G11: Assets/MachineBrigade/Resources/Data/balance.json: base.hqTypes.ai.varga | H11: "garrison"
A12: hqTypes.default | B12: base.hqTypes | C12: default | E12: fortress | G12: Assets/MachineBrigade/Resources/Data/balance.json: base.hqTypes.default | H12: "fortress"
A13: hqTypes.radius | B13: base.hqTypes | C13: radius | D13: 45 | F13: m | G13: Assets/MachineBrigade/Resources/Data/balance.json: base.hqTypes.radius | H13: 45
A14: hqTypes.skillCooldown | B14: base.hqTypes | C14: skillCooldown | D14: 120 | F14: s | G14: Assets/MachineBrigade/Resources/Data/balance.json: base.hqTypes.skillCooldown | H14: 120

Sheet Mo_dun_tien_ich
A1: id | B1: ten_en | C1: ten_vi | D1: ten_ngan_vi | E1: lop | F1: nhanh | G1: ke_thua_tu | H1: base_cp | I1: mau_hp | J1: mau_trong_tran_hp | K1: giap_truoc | L1: giap_hong | M1: giap_sau | N1: giap_noc | O1: cong_trinh | P1: toc_do_m_s | Q1: xoay_than_deg_s | R1: xoay_thap_deg_s | S1: tam_nhin_m | T1: ban_kinh_m | U1: dai_m | V1: rong_m | W1: bay | X1: do_cao_m | Y1: dung_yen | Z1: ban_khi_chay | AA1: toc_do_chiem | AB1: tha_du_s | AC1: he_so_sat_thuong_ra | AD1: vu_khi_chinh | AE1: vu_khi_phu | AF1: noi_tai | AG1: tu_ve | AH1: so_lan_tu_ve | AI1: hoi_tu_ve_s | AJ1: mo_hinh | AK1: so_voi_ban_goc | AL1: base_cp_truoc | AM1: base_cp_sau | AN1: mau_hp_truoc | AO1: mau_hp_sau | AP1: giap_truoc_truoc | AQ1: giap_truoc_sau | AR1: giap_hong_truoc | AS1: giap_hong_sau | AT1: giap_sau_truoc | AU1: giap_sau_sau | AV1: giap_noc_truoc | AW1: giap_noc_sau | AX1: toc_do_m_s_truoc | AY1: toc_do_m_s_sau | AZ1: tam_nhin_m_truoc | BA1: tam_nhin_m_sau | BB1: vu_khi_chinh_truoc | BC1: vu_khi_chinh_sau | BD1: vu_khi_phu_truoc | BE1: vu_khi_phu_sau | BF1: he_so_sat_thuong_ra_truoc | BG1: he_so_sat_thuong_ra_sau | BH1: armour | BI1: aura_damage | BJ1: aura_hp | BK1: aura_range_m | BL1: aura_reach_m | BM1: aura_speed_m_s | BN1: cp | BO1: death_explosion_damage | BP1: death_explosion_delay_s | BQ1: death_explosion_radius_m | BR1: death_explosion_tier | BS1: fort_kind | BT1: fort_size | BU1: hp | BV1: length_m | BW1: model | BX1: model_size_height_m | BY1: model_size_length_m | BZ1: model_size_width_m | CA1: passable | CB1: radius_m | CC1: speed_m_s | CD1: static | CE1: turn_rate_deg_s | CF1: turret_turn_rate_deg_s | CG1: utility_supply | CH1: vision_m | CI1: weapon | CJ1: width_m | CK1: nguon | CL1: raw_json
A2: airfield | B2: Airfield | C2: Sân bay dã chiến | D2: Sân bay | H2: 0 | I2: 1600 | J2: 3520 | K2: 1 | L2: 1 | M2: 1 | N2: 1 | O2: TRUE | P2: 0 | Q2: 1 | R2: 1 | S2: 30 | T2: 3 | U2: 6 | V2: 6 | W2: FALSE | X2: 0 | Y2: TRUE | Z2: TRUE | AA2: 1 | AB2: 3.5 | AC2: 1 | AD2: none | AG2: none | AJ2: helipad | AK2: giong | BH2: 1 | BI2: 0.1 | BL2: Aircraft | BM2: 0.1 | BN2: 0 | BS2: Utility | BT2: Medium | BU2: 1600 | BV2: 6 | BW2: helipad | CA2: TRUE | CB2: 3 | CC2: 0 | CD2: TRUE | CE2: 1 | CF2: 1 | CH2: 30 | CI2: none | CJ2: 6 | CK2: Assets/MachineBrigade/Resources/Data/balance.json: vehicles[100] | CL2: {"id":"airfield","fort":{"size":"Medium","kind":"Utility"},"model":"helipad","static":true,"passable":true,"armour":1,"hp":1600,"speed":0,"turnRate":1,"turretTurnRate":1,"radius":3,"length":6,"width":6,"cp":0,"vision":30,"weapon":"none","aura":{"reach":"Aircraft","damage":0.1,"speed":0.1}}
A3: fire_control_centre | B3: Defence Command Centre | C3: Trung tâm chỉ huy phòng thủ | D3: TT phòng thủ | H3: 0 | I3: 1136 | J3: 2499.2 | K3: 1 | L3: 1 | M3: 1 | N3: 1 | O3: TRUE | P3: 0 | Q3: 1 | R3: 1 | S3: 40 | T3: 3 | U3: 6 | V3: 6 | W3: FALSE | X3: 0 | Y3: TRUE | Z3: TRUE | AA3: 1 | AB3: 3.5 | AC3: 1 | AD3: none | AG3: none | AJ3: fire_control_centre | AK3: giong | BH3: 1 | BJ3: 0.1 | BK3: 0.15 | BL3: Structures | BN3: 0 | BO3: 90 | BP3: 0.4 | BQ3: 7 | BR3: Huge | BS3: Utility | BT3: Medium | BU3: 1136 | BV3: 6 | BX3: 5.5 | BY3: 6 | BZ3: 6 | CB3: 3 | CC3: 0 | CD3: TRUE | CE3: 1 | CF3: 1 | CH3: 40 | CI3: none | CJ3: 6 | CK3: Assets/MachineBrigade/Resources/Data/balance.json: vehicles[116] | CL3: {"id":"fire_control_centre","modelSize":[6.0,6.0,5.5],"fort":{"size":"Medium","kind":"Utility"},"static":true,"armour":1,"hp":1136,"speed":0,"turnRate":1,"turretTurnRate":1,"radius":3,"length":6,"width":6,"cp":0,"vision":40,"weapon":"none","aura":{"reach":"Structures","range":0.15,"hp":0.1},"deathExplosion":{"damage":90,"radius":7,"delay":0.4,"tier":"Huge"}}
A4: logistics_station | B4: Logistics station | C4: Trạm hậu cần | D4: Trạm hậu cần | H4: 0 | I4: 1400 | J4: 3080 | K4: 1 | L4: 1 | M4: 1 | N4: 1 | O4: TRUE | P4: 0 | Q4: 1 | R4: 1 | S4: 30 | T4: 3 | U4: 6 | V4: 6 | W4: FALSE | X4: 0 | Y4: TRUE | Z4: TRUE | AA4: 1 | AB4: 3.5 | AC4: 1 | AD4: none | AG4: none | AJ4: logistics_station | AK4: giong | BH4: 1 | BN4: 0 | BO4: 160 | BP4: 0.4 | BQ4: 9 | BR4: Huge | BS4: Utility | BT4: Medium | BU4: 1400 | BV4: 6 | CB4: 3 | CC4: 0 | CD4: TRUE | CE4: 1 | CF4: 1 | CG4: 8 | CH4: 30 | CI4: none | CJ4: 6 | CK4: Assets/MachineBrigade/Resources/Data/balance.json: vehicles[101] | CL4: {"id":"logistics_station","fort":{"size":"Medium","kind":"Utility"},"static":true,"armour":1,"hp":1400,"speed":0,"turnRate":1,"turretTurnRate":1,"radius":3,"length":6,"width":6,"cp":0,"vision":30,"weapon":"none","utility":{"supply":8},"deathExplosion":{"damage":160,"radius":9,"delay":0.4,"tier":"Huge"}}
A5: repair_bay | B5: Repair bay | C5: Xưởng sửa chữa | D5: Xưởng sửa chữa | H5: 0 | I5: 1600 | J5: 3520 | K5: 2 | L5: 2 | M5: 2 | N5: 2 | O5: TRUE | P5: 0 | Q5: 1 | R5: 1 | S5: 30 | T5: 3 | U5: 6 | V5: 6 | W5: FALSE | X5: 0 | Y5: TRUE | Z5: TRUE | AA5: 1 | AB5: 3.5 | AC5: 1 | AD5: none | AG5: none | AJ5: repair_bay | AK5: giong | BH5: 2 | BI5: 0.1 | BJ5: 0.1 | BL5: Ground | BN5: 0 | BS5: Utility | BT5: Medium | BU5: 1600 | BV5: 6 | CB5: 3 | CC5: 0 | CD5: TRUE | CE5: 1 | CF5: 1 | CH5: 30 | CI5: none | CJ5: 6 | CK5: Assets/MachineBrigade/Resources/Data/balance.json: vehicles[99] | CL5: {"id":"repair_bay","fort":{"size":"Medium","kind":"Utility"},"static":true,"armour":2,"hp":1600,"speed":0,"turnRate":1,"turretTurnRate":1,"radius":3,"length":6,"width":6,"cp":0,"vision":30,"weapon":"none","aura":{"reach":"Ground","damage":0.1,"hp":0.1}}

Sheet Loadout_can_cu
A1: id | B1: bang | C1: cap_hq | D1: large | E1: medium | F1: small | G1: utility | H1: nguon | I1: raw_json
A2: levels/1 | B2: levels | C2: 1 | D2: 0 | E2: 1 | F2: 3 | G2: 1 | H2: Assets/MachineBrigade/Resources/Data/balance.json: base.levels[0] | I2: {"small":3,"medium":1,"large":0,"utility":1}
A3: levels/2 | B3: levels | C3: 2 | D3: 0 | E3: 2 | F3: 4 | G3: 1 | H3: Assets/MachineBrigade/Resources/Data/balance.json: base.levels[1] | I3: {"small":4,"medium":2,"large":0,"utility":1}
A4: levels/3 | B4: levels | C4: 3 | D4: 1 | E4: 2 | F4: 4 | G4: 2 | H4: Assets/MachineBrigade/Resources/Data/balance.json: base.levels[2] | I4: {"small":4,"medium":2,"large":1,"utility":2}
A5: levels/4 | B5: levels | C5: 4 | D5: 1 | E5: 3 | F5: 5 | G5: 2 | H5: Assets/MachineBrigade/Resources/Data/balance.json: base.levels[3] | I5: {"small":5,"medium":3,"large":1,"utility":2}
A6: levels/5 | B6: levels | C6: 5 | D6: 2 | E6: 3 | F6: 6 | G6: 3 | H6: Assets/MachineBrigade/Resources/Data/balance.json: base.levels[4] | I6: {"small":6,"medium":3,"large":2,"utility":3}
A7: longLevels/1 | B7: longLevels | C7: 1 | D7: 0 | E7: 1 | F7: 4 | G7: 1 | H7: Assets/MachineBrigade/Resources/Data/balance.json: base.longLevels[0] | I7: {"small":4,"medium":1,"large":0,"utility":1}
A8: longLevels/2 | B8: longLevels | C8: 2 | D8: 1 | E8: 2 | F8: 5 | G8: 1 | H8: Assets/MachineBrigade/Resources/Data/balance.json: base.longLevels[1] | I8: {"small":5,"medium":2,"large":1,"utility":1}
A9: longLevels/3 | B9: longLevels | C9: 3 | D9: 1 | E9: 3 | F9: 6 | G9: 2 | H9: Assets/MachineBrigade/Resources/Data/balance.json: base.longLevels[2] | I9: {"small":6,"medium":3,"large":1,"utility":2}
A10: longLevels/4 | B10: longLevels | C10: 4 | D10: 2 | E10: 4 | F10: 7 | G10: 3 | H10: Assets/MachineBrigade/Resources/Data/balance.json: base.longLevels[3] | I10: {"small":7,"medium":4,"large":2,"utility":3}
A11: longLevels/5 | B11: longLevels | C11: 5 | D11: 3 | E11: 5 | F11: 8 | G11: 4 | H11: Assets/MachineBrigade/Resources/Data/balance.json: base.longLevels[4] | I11: {"small":8,"medium":5,"large":3,"utility":4}

Sheet Xay_lai
A1: id | B1: cooldown_s | C1: cp | D1: drop | E1: nguon | F1: raw_json
A2: large | B2: 60 | C2: 7 | D2: 5 | E2: Assets/MachineBrigade/Resources/Data/balance.json: base.rebuild.large | F2: {"cp":7,"cooldown":60,"drop":5}
A3: medium | B3: 40 | C3: 4 | D3: 3.5 | E3: Assets/MachineBrigade/Resources/Data/balance.json: base.rebuild.medium | F3: {"cp":4,"cooldown":40,"drop":3.5}
A4: small | B4: 25 | C4: 2 | D4: 2.5 | E4: Assets/MachineBrigade/Resources/Data/balance.json: base.rebuild.small | F4: {"cp":2,"cooldown":25,"drop":2.5}

Sheet Can_cu_luat
A1: id | B1: nhom | C1: khoa | D1: gia_tri_so | E1: gia_tri_chu | F1: don_vi | G1: nguon | H1: raw_json
A2: base.roster | B2: base.roster | E2: guard_tower;mg_bunker;aa_turret;ew_tower;cp_relay;atgm_tower;gun_turret;c_ram;rocket_turret;laser_ad_station;heavy_turret;missile_battery;drone_hangar;shield_tower;vehicle_hangar;aircraft_hangar | G2: Assets/MachineBrigade/Resources/Data/balance.json: base.roster | H2: ["guard_tower","mg_bunker","aa_turret","ew_tower","cp_relay","atgm_tower","gun_turret","c_ram","rocket_turret","laser_ad_station","heavy_turret","missile_battery","drone_hangar","shield_tower","vehicle_hangar","aircraft_hangar"]
A3: longForward.medium | B3: base.longForward | C3: medium | D3: 2 | G3: Assets/MachineBrigade/Resources/Data/balance.json: base.longForward.medium | H3: 2
A4: longForward.small | B4: base.longForward | C4: small | D4: 6 | G4: Assets/MachineBrigade/Resources/Data/balance.json: base.longForward.small | H4: 6
A5: outpost.cp | B5: base.outpost | C5: cp | D5: 6 | F5: CP | G5: Assets/MachineBrigade/Resources/Data/balance.json: base.outpost.cp | H5: 6
A6: outpost.slots | B6: base.outpost | C6: slots | D6: 2 | G6: Assets/MachineBrigade/Resources/Data/balance.json: base.outpost.slots | H6: 2
A7: rebuild.delay | B7: base.rebuild | C7: delay | D7: 4 | F7: s | G7: Assets/MachineBrigade/Resources/Data/balance.json: base.rebuild.delay | H7: 4
A8: rebuild.enemyRadius | B8: base.rebuild | C8: enemyRadius | D8: 20 | F8: m | G8: Assets/MachineBrigade/Resources/Data/balance.json: base.rebuild.enemyRadius | H8: 20
A9: rebuild.hqRescue | B9: base.rebuild | C9: hqRescue | D9: 0.25 | G9: Assets/MachineBrigade/Resources/Data/balance.json: base.rebuild.hqRescue | H9: 0.25
A10: rebuild.showdownCutoff | B10: base.rebuild | C10: showdownCutoff | D10: 600 | F10: s | G10: Assets/MachineBrigade/Resources/Data/balance.json: base.rebuild.showdownCutoff | H10: 600
A11: roles.Assault | B11: base.roles | C11: Assault | E11: Target | G11: Assets/MachineBrigade/Resources/Data/balance.json: base.roles.Assault | H11: "Target"
A12: roles.BossRush | B12: base.roles | C12: BossRush | E12: None | G12: Assets/MachineBrigade/Resources/Data/balance.json: base.roles.BossRush | H12: "None"
A13: roles.Campaign | B13: base.roles | C13: Campaign | E13: None | G13: Assets/MachineBrigade/Resources/Data/balance.json: base.roles.Campaign | H13: "None"
A14: roles.Conquest | B14: base.roles | C14: Conquest | E14: Anchor | G14: Assets/MachineBrigade/Resources/Data/balance.json: base.roles.Conquest | H14: "Anchor"
A15: roles.Deathmatch | B15: base.roles | C15: Deathmatch | E15: Anchor | G15: Assets/MachineBrigade/Resources/Data/balance.json: base.roles.Deathmatch | H15: "Anchor"
A16: roles.Defend | B16: base.roles | C16: Defend | E16: Defend | G16: Assets/MachineBrigade/Resources/Data/balance.json: base.roles.Defend | H16: "Defend"
A17: roles.Endless | B17: base.roles | C17: Endless | E17: Defend | G17: Assets/MachineBrigade/Resources/Data/balance.json: base.roles.Endless | H17: "Defend"
A18: roles.KingOfTheHill | B18: base.roles | C18: KingOfTheHill | E18: Anchor | G18: Assets/MachineBrigade/Resources/Data/balance.json: base.roles.KingOfTheHill | H18: "Anchor"
A19: roles.Showdown | B19: base.roles | C19: Showdown | E19: Target | G19: Assets/MachineBrigade/Resources/Data/balance.json: base.roles.Showdown | H19: "Target"
A20: roles.Siege | B20: base.roles | C20: Siege | E20: Target | G20: Assets/MachineBrigade/Resources/Data/balance.json: base.roles.Siege | H20: "Target"
A21: roles.Survival | B21: base.roles | C21: Survival | E21: None | G21: Assets/MachineBrigade/Resources/Data/balance.json: base.roles.Survival | H21: "None"
A22: roles.Weekly | B22: base.roles | C22: Weekly | E22: Target | G22: Assets/MachineBrigade/Resources/Data/balance.json: base.roles.Weekly | H22: "Target"

Sheet Dot_phong_thu
A1: id | B1: small | C1: medium | D1: large | E1: utilities | F1: he_so_do_kho | G1: duong_cong_dot | H1: cap_hq | I1: nguon | J1: raw_json
A2: hq1 | B2: guard_tower;mg_bunker;aa_turret | C2: gun_turret | E2: repair_bay | F2: 0.75 | G2: 2;4;5;6;8;9;10;12;13;14 | H2: 1 | I2: Assets/MachineBrigade/Resources/Data/balance.json: base.reference[0] | J2: {"level":1,"small":["guard_tower","mg_bunker","aa_turret"],"medium":["gun_turret"],"utilities":["repair_bay"]}
A3: hq2 | B3: guard_tower;mg_bunker;aa_turret;mg_bunker | C3: gun_turret;atgm_tower | E3: repair_bay | F3: 0.8722 | G3: 3;4;6;7;9;10;12;14;15;17 | H3: 2 | I3: Assets/MachineBrigade/Resources/Data/balance.json: base.reference[1] | J3: {"level":2,"small":["guard_tower","mg_bunker","aa_turret","mg_bunker"],"medium":["gun_turret","atgm_tower"],"utilities":["repair_bay"]}
A4: hq3 | B4: guard_tower;mg_bunker;aa_turret;mg_bunker | C4: gun_turret;rocket_turret | D4: heavy_turret | E4: repair_bay;logistics_station | F4: 1.0414 | G4: 3;5;7;9;11;12;14;16;18;20 | H4: 3 | I4: Assets/MachineBrigade/Resources/Data/balance.json: base.reference[2] | J4: {"level":3,"small":["guard_tower","mg_bunker","aa_turret","mg_bunker"],"medium":["gun_turret","rocket_turret"],"large":["heavy_turret"],"utilities":["repair_bay","logistics_station"]}
A5: hq4 | B5: guard_tower;mg_bunker;aa_turret;mg_bunker;guard_tower | C5: gun_turret;atgm_tower;rocket_turret | D5: heavy_turret | E5: repair_bay;logistics_station | F5: 1.1887 | G5: 4;6;8;10;12;14;16;19;21;23 | H5: 4 | I5: Assets/MachineBrigade/Resources/Data/balance.json: base.reference[3] | J5: {"level":4,"small":["guard_tower","mg_bunker","aa_turret","mg_bunker","guard_tower"],"medium":["gun_turret","atgm_tower","rocket_turret"],"large":["heavy_turret"],"utilities":["repair_bay","logistics_station"]}
A6: hq5 | B6: guard_tower;mg_bunker;aa_turret;mg_bunker;guard_tower;ew_tower | C6: gun_turret;atgm_tower;c_ram | D6: heavy_turret;missile_battery | E6: repair_bay;logistics_station;airfield | F6: 1.3554 | G6: 4;7;9;11;14;16;19;21;24;26 | H6: 5 | I6: Assets/MachineBrigade/Resources/Data/balance.json: base.reference[4] | J6: {"level":5,"small":["guard_tower","mg_bunker","aa_turret","mg_bunker","guard_tower","ew_tower"],"medium":["gun_turret","atgm_tower","c_ram"],"large":["heavy_turret","missile_battery"],"utilities":["repair_bay","logistics_station","airfield"]}

Sheet Can_cu_AI_kieu
A1: id | B1: kieu | C1: thap | D1: trong_so | E1: nguon | F1: raw_json
A2: air/aa_turret | B2: air | C2: aa_turret | D2: 2 | E2: Assets/MachineBrigade/Resources/Data/balance.json: base.ai.styles.air.aa_turret | F2: 2.0
A3: air/c_ram | B3: air | C3: c_ram | D3: 1.2 | E3: Assets/MachineBrigade/Resources/Data/balance.json: base.ai.styles.air.c_ram | F3: 1.2
A4: air/fire_control_centre | B4: air | C4: fire_control_centre | D4: 1 | E4: Assets/MachineBrigade/Resources/Data/balance.json: base.ai.styles.air.fire_control_centre | F4: 1.0
A5: air/guard_tower | B5: air | C5: guard_tower | D5: 0.8 | E5: Assets/MachineBrigade/Resources/Data/balance.json: base.ai.styles.air.guard_tower | F5: 0.8
A6: air/laser_ad_station | B6: air | C6: laser_ad_station | D6: 1 | E6: Assets/MachineBrigade/Resources/Data/balance.json: base.ai.styles.air.laser_ad_station | F6: 1.0
A7: air/missile_battery | B7: air | C7: missile_battery | D7: 1.6 | E7: Assets/MachineBrigade/Resources/Data/balance.json: base.ai.styles.air.missile_battery | F7: 1.6
A8: armour/aa_turret | B8: armour | C8: aa_turret | D8: 0.8 | E8: Assets/MachineBrigade/Resources/Data/balance.json: base.ai.styles.armour.aa_turret | F8: 0.8
A9: armour/fire_control_centre | B9: armour | C9: fire_control_centre | D9: 1 | E9: Assets/MachineBrigade/Resources/Data/balance.json: base.ai.styles.armour.fire_control_centre | F9: 1.0
A10: armour/guard_tower | B10: armour | C10: guard_tower | D10: 0.6 | E10: Assets/MachineBrigade/Resources/Data/balance.json: base.ai.styles.armour.guard_tower | F10: 0.6
A11: armour/gun_turret | B11: armour | C11: gun_turret | D11: 2 | E11: Assets/MachineBrigade/Resources/Data/balance.json: base.ai.styles.armour.gun_turret | F11: 2.0
A12: armour/heavy_turret | B12: armour | C12: heavy_turret | D12: 1.4 | E12: Assets/MachineBrigade/Resources/Data/balance.json: base.ai.styles.armour.heavy_turret | F12: 1.4
A13: armour/mg_bunker | B13: armour | C13: mg_bunker | D13: 1 | E13: Assets/MachineBrigade/Resources/Data/balance.json: base.ai.styles.armour.mg_bunker | F13: 1.0
... A18: artillery/rocket_turret | B18: artillery | C18: rocket_turret | D18: 1.6 | E18: Assets/MachineBrigade/Resources/Data/balance.json: base.ai.styles.artillery.rocket_turret | F18: 1.6
A19: aurel/* | B19: aurel | D19: 0.8 | E19: Assets/MachineBrigade/Resources/Data/balance.json: base.ai.styles.aurel["*"] | F19: 0.8
A20: aurel/atgm_tower | B20: aurel | C20: atgm_tower | D20: 1.2 | E20: Assets/MachineBrigade/Resources/Data/balance.json: base.ai.styles.aurel.atgm_tower | F20: 1.2
A21: aurel/c_ram | B21: aurel | C21: c_ram | D21: 1.2 | E21: Assets/MachineBrigade/Resources/Data/balance.json: base.ai.styles.aurel.c_ram | F21: 1.2
A22: aurel/fire_control_centre | B22: aurel | C22: fire_control_centre | D22: 1.2 | E22: Assets/MachineBrigade/Resources/Data/balance.json: base.ai.styles.aurel.fire_control_centre | F22: 1.2
A23: aurel/heavy_turret | B23: aurel | C23: heavy_turret | D23: 1.6 | E23: Assets/MachineBrigade/Resources/Data/balance.json: base.ai.styles.aurel.heavy_turret | F23: 1.6
A24: aurel/heavy_turret.bastion | B24: aurel | C24: heavy_turret.bastion | D24: 1.2 | E24: Assets/MachineBrigade/Resources/Data/balance.json: base.ai.styles.aurel["heavy_turret.bastion"] | F24: 1.2
A25: aurel/missile_battery | B25: aurel | C25: missile_battery | D25: 1.4 | E25: Assets/MachineBrigade/Resources/Data/balance.json: base.ai.styles.aurel.missile_battery | F25: 1.4
A26: aurel/missile_battery.pac3 | B26: aurel | C26: missile_battery.pac3 | D26: 1.3 | E26: Assets/MachineBrigade/Resources/Data/balance.json: base.ai.styles.aurel["missile_battery.pac3"] | F26: 1.3
A27: aurel/shield_tower.bulwark | B27: aurel | C27: shield_tower.bulwark | D27: 1.2 | E27: Assets/MachineBrigade/Resources/Data/balance.json: base.ai.styles.aurel["shield_tower.bulwark"] | F27: 1.2
A28: default/aa_gun_tower | B28: default | C28: aa_gun_tower | D28: 0.8 | E28: Assets/MachineBrigade/Resources/Data/balance.json: base.ai.styles.default.aa_gun_tower | F28: 0.8
A29: default/aa_turret | B29: default | C29: aa_turret | D29: 1.2 | E29: Assets/MachineBrigade/Resources/Data/balance.json: base.ai.styles.default.aa_turret | F29: 1.2
A30: default/aircraft_hangar | B30: default | C30: aircraft_hangar | D30: 0.3 | E30: Assets/MachineBrigade/Resources/Data/balance.json: base.ai.styles.default.aircraft_hangar | F30: 0.3
A31: default/atgm_tower | B31: default | C31: atgm_tower | D31: 1 | E31: Assets/MachineBrigade/Resources/Data/balance.json: base.ai.styles.default.atgm_tower | F31: 1.0
... A54: default/vehicle_hangar | B54: default | C54: vehicle_hangar | D54: 0.5 | E54: Assets/MachineBrigade/Resources/Data/balance.json: base.ai.styles.default.vehicle_hangar | F54: 0.5
A55: kessler/* | B55: kessler | D55: 1 | E55: Assets/MachineBrigade/Resources/Data/balance.json: base.ai.styles.kessler["*"] | F55: 1.0
A56: orlov/aa_turret | B56: orlov | C56: aa_turret | D56: 0.8 | E56: Assets/MachineBrigade/Resources/Data/balance.json: base.ai.styles.orlov.aa_turret | F56: 0.8
A57: orlov/fire_control_centre | B57: orlov | C57: fire_control_centre | D57: 1.2 | E57: Assets/MachineBrigade/Resources/Data/balance.json: base.ai.styles.orlov.fire_control_centre | F57: 1.2
A58: orlov/guard_tower | B58: orlov | C58: guard_tower | D58: 1.2 | E58: Assets/MachineBrigade/Resources/Data/balance.json: base.ai.styles.orlov.guard_tower | F58: 1.2
A59: orlov/gun_turret | B59: orlov | C59: gun_turret | D59: 0.8 | E59: Assets/MachineBrigade/Resources/Data/balance.json: base.ai.styles.orlov.gun_turret | F59: 0.8
A60: orlov/rocket_turret | B60: orlov | C60: rocket_turret | D60: 1.8 | E60: Assets/MachineBrigade/Resources/Data/balance.json: base.ai.styles.orlov.rocket_turret | F60: 1.8
A61: orlov/rocket_turret.guided | B61: orlov | C61: rocket_turret.guided | D61: 1.3 | E61: Assets/MachineBrigade/Resources/Data/balance.json: base.ai.styles.orlov["rocket_turret.guided"] | F61: 1.3
A62: quaden/aa_turret | B62: quaden | C62: aa_turret | D62: 2.4 | E62: Assets/MachineBrigade/Resources/Data/balance.json: base.ai.styles.quaden.aa_turret | F62: 2.4
A63: quaden/aa_turret.sam | B63: quaden | C63: aa_turret.sam | D63: 1.3 | E63: Assets/MachineBrigade/Resources/Data/balance.json: base.ai.styles.quaden["aa_turret.sam"] | F63: 1.3
A64: quaden/c_ram | B64: quaden | C64: c_ram | D64: 1.4 | E64: Assets/MachineBrigade/Resources/Data/balance.json: base.ai.styles.quaden.c_ram | F64: 1.4
A65: quaden/c_ram.dome | B65: quaden | C65: c_ram.dome | D65: 1.2 | E65: Assets/MachineBrigade/Resources/Data/balance.json: base.ai.styles.quaden["c_ram.dome"] | F65: 1.2
A66: quaden/guard_tower | B66: quaden | C66: guard_tower | D66: 1 | E66: Assets/MachineBrigade/Resources/Data/balance.json: base.ai.styles.quaden.guard_tower | F66: 1.0
A67: quaden/gun_turret | B67: quaden | C67: gun_turret | D67: 0.6 | E67: Assets/MachineBrigade/Resources/Data/balance.json: base.ai.styles.quaden.gun_turret | F67: 0.6
... A88: varga/mg_bunker | B88: varga | C88: mg_bunker | D88: 1 | E88: Assets/MachineBrigade/Resources/Data/balance.json: base.ai.styles.varga.mg_bunker | F88: 1.0

Sheet cc_input_vu_khi
A1: id | B1: sat_thuong_moi_phat | C1: xuyen | D1: nguon | E1: raw_json
A2: gun_105_wheeled | B2: 369 | C2: 4 | D2: 01_chien_dau/Vu_khi (id gun_105_wheeled)
A3: gun_105_wheeled_he | B3: 369 | C3: 2 | D3: 01_chien_dau/Vu_khi (id gun_105_wheeled_he)
A4: gun_120_twin_he | B4: 343 | C4: 2 | D4: 01_chien_dau/Vu_khi (id gun_120_twin_he)
A5: gun_120mm_he | B5: 343 | C5: 2 | D5: 01_chien_dau/Vu_khi (id gun_120mm_he)
A6: gun_152 | B6: 457 | C6: 4 | D6: 01_chien_dau/Vu_khi (id gun_152)
A7: ifv_30 | B7: 22 | C7: 2 | D7: 01_chien_dau/Vu_khi (id ifv_30)
A8: mlrs_rockets | B8: 100 | C8: 3 | D8: 01_chien_dau/Vu_khi (id mlrs_rockets)
A9: recoilless_106 | B9: 314 | C9: 3 | D9: 01_chien_dau/Vu_khi (id recoilless_106)
A10: technical_rockets | B10: 49.5 | C10: 2 | D10: 01_chien_dau/Vu_khi (id technical_rockets)
A11: thermobaric_rockets | B11: 97 | C11: 3 | D11: 01_chien_dau/Vu_khi (id thermobaric_rockets)

Sheet cc_input_vu_khi_suy_ra
A1: id | B1: danh_tu_tren | C1: ban_mat_dat | D1: he_so_cong_trinh | E1: nguon | F1: raw_json
A2: gun_105_wheeled | B2: FALSE | C2: TRUE | D2: 0.6 | E2: 01_chien_dau/Vu_khi_suy_ra (id gun_105_wheeled)
A3: gun_105_wheeled_he | B3: FALSE | C3: TRUE | D3: 1.5 | E3: 01_chien_dau/Vu_khi_suy_ra (id gun_105_wheeled_he)
A4: gun_120_twin_he | B4: FALSE | C4: TRUE | D4: 1.5 | E4: 01_chien_dau/Vu_khi_suy_ra (id gun_120_twin_he)
A5: gun_120mm_he | B5: FALSE | C5: TRUE | D5: 1.5 | E5: 01_chien_dau/Vu_khi_suy_ra (id gun_120mm_he)
A6: gun_152 | B6: FALSE | C6: TRUE | D6: 0.6 | E6: 01_chien_dau/Vu_khi_suy_ra (id gun_152)
A7: ifv_30 | B7: FALSE | C7: TRUE | D7: 0.6 | E7: 01_chien_dau/Vu_khi_suy_ra (id ifv_30)
A8: mlrs_rockets | B8: TRUE | C8: TRUE | D8: 1.5 | E8: 01_chien_dau/Vu_khi_suy_ra (id mlrs_rockets)
A9: recoilless_106 | B9: FALSE | C9: TRUE | D9: 0.6 | E9: 01_chien_dau/Vu_khi_suy_ra (id recoilless_106)
A10: technical_rockets | B10: TRUE | C10: TRUE | D10: 1.5 | E10: 01_chien_dau/Vu_khi_suy_ra (id technical_rockets)
A11: thermobaric_rockets | B11: TRUE | C11: TRUE | D11: 2 | E11: 01_chien_dau/Vu_khi_suy_ra (id thermobaric_rockets)

Sheet cc_input_bang_xuyen_giap
A1: id | B1: he_so | C1: nguon | D1: raw_json
A2: buoc_0 | B2: 1.2 | C2: 01_chien_dau/Bang_xuyen_giap (id buoc_0)
A3: buoc_1 | B3: 1 | C3: 01_chien_dau/Bang_xuyen_giap (id buoc_1)
A4: buoc_2 | B4: 0.85 | C4: 01_chien_dau/Bang_xuyen_giap (id buoc_2)
A5: buoc_3 | B5: 0.5 | C5: 01_chien_dau/Bang_xuyen_giap (id buoc_3)
A6: buoc_4 | B6: 0.25 | C6: 01_chien_dau/Bang_xuyen_giap (id buoc_4)
A7: buoc_5 | B7: 0.1 | C7: 01_chien_dau/Bang_xuyen_giap (id buoc_5)

Sheet Thap_gia_cong_thuc
A1: id | B1: co_o | C1: vai_tro_gia | D1: cach_tinh | E1: he_so_trung_vi_doa | F1: role_dps | G1: mau_tren_cp_nhom | H1: dps_tren_cp_nhom | I1: so_xe_nhom | J1: he_so_dung_yen | K1: gia_tri_tien_ich | L1: gia_tri_moc | M1: gia_moc_cp | N1: can_duoi_cp | O1: can_tren_cp | P1: effective_hp | Q1: equivalent_cp | R1: gia_tho | S1: gia_cong_thuc_cp | T1: lech_voi_game | U1: nguon | V1: raw_json
A2: aa_turret | B2: Small | C2: air | D2: chien_dau | E2: 0.9375 | F2: 219.41673 | G2: 173.8 | H2: 36.018667 | I2: 7 | J2: 0.625 | N2: 3 | O2: 6 | P2: =IF($D$2="chien_dau",Thap!$J$3/MAX(0.000001,$E$2),"") | Q2: =IF($D$2="chien_dau",SQRT(MAX(0,($P$2/$G$2)*($F$2/$H$2))),"") | R2: =IF($D$2="chien_dau",$Q$2*$J$2*1.25,IF($D$2="san",$N$2,IF($D$2="relay",$K$2,IF($L$2>0,$M$2*SQRT($K$2/$L$2),$N$2)))) | S2: =MAX($N$2,MIN($O$2,ROUND($R$2,0))) | T2: =$S$2-Thap!$BN$3 | U2: Tools/balance/p32_tower_prices.py Model.price('aa_turret')
A3: aa_turret.flak | B3: Small | C3: air | D3: chien_dau | E3: 0.9375 | F3: 240.3846 | G3: 173.8 | H3: 36.018667 | I3: 7 | J3: 0.625 | N3: 3 | O3: 6 | P3: =IF($D$3="chien_dau",Thap!$J$4/MAX(0.000001,$E$3),"") | Q3: =IF($D$3="chien_dau",SQRT(MAX(0,($P$3/$G$3)*($F$3/$H$3))),"") | R3: =IF($D$3="chien_dau",$Q$3*$J$3*1.25,IF($D$3="san",$N$3,IF($D$3="relay",$K$3,IF($L$3>0,$M$3*SQRT($K$3/$L$3),$N$3)))) | S3: =MAX($N$3,MIN($O$3,ROUND($R$3,0))) | T3: =$S$3-Thap!$BN$4 | U3: Tools/balance/p32_tower_prices.py Model.price('aa_turret.flak')
A4: aa_turret.sam | B4: Small | C4: air | D4: chien_dau | E4: 0.9375 | F4: 49.640611 | G4: 173.8 | H4: 36.018667 | I4: 7 | J4: 0.725 | N4: 3 | O4: 6 | P4: =IF($D$4="chien_dau",Thap!$J$5/MAX(0.000001,$E$4),"") | Q4: =IF($D$4="chien_dau",SQRT(MAX(0,($P$4/$G$4)*($F$4/$H$4))),"") | R4: =IF($D$4="chien_dau",$Q$4*$J$4*1.25,IF($D$4="san",$N$4,IF($D$4="relay",$K$4,IF($L$4>0,$M$4*SQRT($K$4/$L$4),$N$4)))) | S4: =MAX($N$4,MIN($O$4,ROUND($R$4,0))) | T4: =$S$4-Thap!$BN$5 | U4: Tools/balance/p32_tower_prices.py Model.price('aa_turret.sam')
A5: aircraft_hangar | B5: Medium | C5: multi | D5: chien_dau | E5: 1.275 | F5: 0 | G5: 172.87897 | H5: 9.8043496 | I5: 46 | J5: 0.575 | N5: 5 | O5: 11 | P5: =IF($D$5="chien_dau",Thap!$J$6/MAX(0.000001,$E$5),"") | Q5: =IF($D$5="chien_dau",SQRT(MAX(0,($P$5/$G$5)*($F$5/$H$5))),"") | R5: =IF($D$5="chien_dau",$Q$5*$J$5*1.25,IF($D$5="san",$N$5,IF($D$5="relay",$K$5,IF($L$5>0,$M$5*SQRT($K$5/$L$5),$N$5)))) | S5: =MAX($N$5,MIN($O$5,ROUND($R$5,0))) | T5: =$S$5-Thap!$BN$6 | U5: Tools/balance/p32_tower_prices.py Model.price('aircraft_hangar')
A6: atgm_tower | B6: Medium | C6: at | D6: chien_dau | E6: 1.275 | F6: 76.666667 | G6: 328.4902 | H6: 7.6732421 | I6: 14 | J6: 0.625 | N6: 5 | O6: 11 | P6: =IF($D$6="chien_dau",Thap!$J$7/MAX(0.000001,$E$6),"") | Q6: =IF($D$6="chien_dau",SQRT(MAX(0,($P$6/$G$6)*($F$6/$H$6))),"") | R6: =IF($D$6="chien_dau",$Q$6*$J$6*1.25,IF($D$6="san",$N$6,IF($D$6="relay",$K$6,IF($L$6>0,$M$6*SQRT($K$6/$L$6),$N$6)))) | S6: =MAX($N$6,MIN($O$6,ROUND($R$6,0))) | T6: =$S$6-Thap!$BN$7 | U6: Tools/balance/p32_tower_prices.py Model.price('atgm_tower')
A7: atgm_tower.multi | B7: Medium | C7: at | D7: chien_dau | E7: 1.275 | F7: 65.166667 | G7: 328.4902 | H7: 7.6732421 | I7: 14 | J7: 0.625 | N7: 5 | O7: 11 | P7: =IF($D$7="chien_dau",Thap!$J$8/MAX(0.000001,$E$7),"") | Q7: =IF($D$7="chien_dau",SQRT(MAX(0,($P$7/$G$7)*($F$7/$H$7))),"") | R7: =IF($D$7="chien_dau",$Q$7*$J$7*1.25,IF($D$7="san",$N$7,IF($D$7="relay",$K$7,IF($L$7>0,$M$7*SQRT($K$7/$L$7),$N$7)))) | S7: =MAX($N$7,MIN($O$7,ROUND($R$7,0))) | T7: =$S$7-Thap!$BN$8 | U7: Tools/balance/p32_tower_prices.py Model.price('atgm_tower.multi')
A8: atgm_tower.top | B8: Medium | C8: at | D8: chien_dau | E8: 1.275 | F8: 81.826923 | G8: 328.4902 | H8: 7.6732421 | I8: 14 | J8: 0.625 | N8: 5 | O8: 11 | P8: =IF($D$8="chien_dau",Thap!$J$9/MAX(0.000001,$E$8),"") | Q8: =IF($D$8="chien_dau",SQRT(MAX(0,($P$8/$G$8)*($F$8/$H$8))),"") | R8: =IF($D$8="chien_dau",$Q$8*$J$8*1.25,IF($D$8="san",$N$8,IF($D$8="relay",$K$8,IF($L$8>0,$M$8*SQRT($K$8/$L$8),$N$8)))) | S8: =MAX($N$8,MIN($O$8,ROUND($R$8,0))) | T8: =$S$8-Thap!$BN$9 | U8: Tools/balance/p32_tower_prices.py Model.price('atgm_tower.top')
A9: c_ram | B9: Medium | C9: util:intercept | D9: intercept | K9: 100 | L9: 100 | M9: 5 | N9: 5 | O9: 11 | P9: =IF($D$9="chien_dau",Thap!$J$14/MAX(0.000001,$E$9),"") | Q9: =IF($D$9="chien_dau",SQRT(MAX(0,($P$9/$G$9)*($F$9/$H$9))),"") | R9: =IF($D$9="chien_dau",$Q$9*$J$9*1.25,IF($D$9="san",$N$9,IF($D$9="relay",$K$9,IF($L$9>0,$M$9*SQRT($K$9/$L$9),$N$9)))) | S9: =MAX($N$9,MIN($O$9,ROUND($R$9,0))) | T9: =$S$9-Thap!$BN$14 | U9: Tools/balance/p32_tower_prices.py Model.price('c_ram')
A10: c_ram.centurion | B10: Medium | C10: util:intercept | D10: intercept | K10: 120 | L10: 100 | M10: 5 | N10: 5 | O10: 11 | P10: =IF($D$10="chien_dau",Thap!$J$15/MAX(0.000001,$E$10),"") | Q10: =IF($D$10="chien_dau",SQRT(MAX(0,($P$10/$G$10)*($F$10/$H$10))),"") | R10: =IF($D$10="chien_dau",$Q$10*$J$10*1.25,IF($D$10="san",$N$10,IF($D$10="relay",$K$10,IF($L$10>0,$M$10*SQRT($K$10/$L$10),$N$10)))) | S10: =MAX($N$10,MIN($O$10,ROUND($R$10,0))) | T10: =$S$10-Thap!$BN$15 | U10: Tools/balance/p32_tower_prices.py Model.price('c_ram.centurion')
A11: c_ram.dome | B11: Medium | C11: util:intercept | D11: intercept | K11: 88.163265 | L11: 100 | M11: 5 | N11: 5 | O11: 11 | P11: =IF($D$11="chien_dau",Thap!$J$16/MAX(0.000001,$E$11),"") | Q11: =IF($D$11="chien_dau",SQRT(MAX(0,($P$11/$G$11)*($F$11/$H$11))),"") | R11: =IF($D$11="chien_dau",$Q$11*$J$11*1.25,IF($D$11="san",$N$11,IF($D$11="relay",$K$11,IF($L$11>0,$M$11*SQRT($K$11/$L$11),$N$11)))) | S11: =MAX($N$11,MIN($O$11,ROUND($R$11,0))) | T11: =$S$11-Thap!$BN$16 | U11: Tools/balance/p32_tower_prices.py Model.price('c_ram.dome')
A12: cp_relay | B12: Small | C12: util:relay | D12: relay | K12: 10.8 | N12: 3 | O12: 6 | P12: =IF($D$12="chien_dau",Thap!$J$18/MAX(0.000001,$E$12),"") | Q12: =IF($D$12="chien_dau",SQRT(MAX(0,($P$12/$G$12)*($F$12/$H$12))),"") | R12: =IF($D$12="chien_dau",$Q$12*$J$12*1.25,IF($D$12="san",$N$12,IF($D$12="relay",$K$12,IF($L$12>0,$M$12*SQRT($K$12/$L$12),$N$12)))) | S12: =MAX($N$12,MIN($O$12,ROUND($R$12,0))) | T12: =$S$12-Thap!$BN$18 | U12: Tools/balance/p32_tower_prices.py Model.price('cp_relay')
A13: drone_hangar | B13: Large | C13: multi | D13: chien_dau | E13: 1.275 | F13: 44.666667 | G13: 172.87897 | H13: 9.8043496 | I13: 46 | J13: 0.725 | N13: 9 | O13: 18 | P13: =IF($D$13="chien_dau",Thap!$J$19/MAX(0.000001,$E$13),"") | Q13: =IF($D$13="chien_dau",SQRT(MAX(0,($P$13/$G$13)*($F$13/$H$13))),"") | R13: =IF($D$13="chien_dau",$Q$13*$J$13*1.25,IF($D$13="san",$N$13,IF($D$13="relay",$K$13,IF($L$13>0,$M$13*SQRT($K$13/$L$13),$N$13)))) | S13: =MAX($N$13,MIN($O$13,ROUND($R$13,0))) | T13: =$S$13-Thap!$BN$19 | U13: Tools/balance/p32_tower_prices.py Model.price('drone_hangar')
A14: drone_hangar.lancet | B14: Large | C14: multi | D14: chien_dau | E14: 1.275 | F14: 64.166667 | G14: 172.87897 | H14: 9.8043496 | I14: 46 | J14: 0.725 | N14: 9 | O14: 18 | P14: =IF($D$14="chien_dau",Thap!$J$20/MAX(0.000001,$E$14),"") | Q14: =IF($D$14="chien_dau",SQRT(MAX(0,($P$14/$G$14)*($F$14/$H$14))),"") | R14: =IF($D$14="chien_dau",$Q$14*$J$14*1.25,IF($D$14="san",$N$14,IF($D$14="relay",$K$14,IF($L$14>0,$M$14*SQRT($K$14/$L$14),$N$14)))) | S14: =MAX($N$14,MIN($O$14,ROUND($R$14,0))) | T14: =$S$14-Thap!$BN$20 | U14: Tools/balance/p32_tower_prices.py Model.price('drone_hangar.lancet')
A15: drone_hangar.swarm | B15: Large | C15: multi | D15: chien_dau | E15: 1.275 | F15: 59.367089 | G15: 172.87897 | H15: 9.8043496 | I15: 46 | J15: 0.725 | N15: 9 | O15: 18 | P15: =IF($D$15="chien_dau",Thap!$J$21/MAX(0.000001,$E$15),"") | Q15: =IF($D$15="chien_dau",SQRT(MAX(0,($P$15/$G$15)*($F$15/$H$15))),"") | R15: =IF($D$15="chien_dau",$Q$15*$J$15*1.25,IF($D$15="san",$N$15,IF($D$15="relay",$K$15,IF($L$15>0,$M$15*SQRT($K$15/$L$15),$N$15)))) | S15: =MAX($N$15,MIN($O$15,ROUND($R$15,0))) | T15: =$S$15-Thap!$BN$21 | U15: Tools/balance/p32_tower_prices.py Model.price('drone_hangar.swarm')
A16: ew_tower | B16: Small | C16: util:floor | D16: san | N16: 3 | O16: 6 | P16: =IF($D$16="chien_dau",Thap!$J$23/MAX(0.000001,$E$16),"") | Q16: =IF($D$16="chien_dau",SQRT(MAX(0,($P$16/$G$16)*($F$16/$H$16))),"") | R16: =IF($D$16="chien_dau",$Q$16*$J$16*1.25,IF($D$16="san",$N$16,IF($D$16="relay",$K$16,IF($L$16>0,$M$16*SQRT($K$16/$L$16),$N$16)))) | S16: =MAX($N$16,MIN($O$16,ROUND($R$16,0))) | T16: =$S$16-Thap!$BN$23 | U16: Tools/balance/p32_tower_prices.py Model.price('ew_tower')
A17: ew_tower.drone | B17: Small | C17: util:floor | D17: san | N17: 3 | O17: 6 | P17: =IF($D$17="chien_dau",Thap!$J$24/MAX(0.000001,$E$17),"") | Q17: =IF($D$17="chien_dau",SQRT(MAX(0,($P$17/$G$17)*($F$17/$H$17))),"") | R17: =IF($D$17="chien_dau",$Q$17*$J$17*1.25,IF($D$17="san",$N$17,IF($D$17="relay",$K$17,IF($L$17>0,$M$17*SQRT($K$17/$L$17),$N$17)))) | S17: =MAX($N$17,MIN($O$17,ROUND($R$17,0))) | T17: =$S$17-Thap!$BN$24 | U17: Tools/balance/p32_tower_prices.py Model.price('ew_tower.drone')
A18: ew_tower.spoof | B18: Small | C18: util:floor | D18: san | N18: 3 | O18: 6 | P18: =IF($D$18="chien_dau",Thap!$J$25/MAX(0.000001,$E$18),"") | Q18: =IF($D$18="chien_dau",SQRT(MAX(0,($P$18/$G$18)*($F$18/$H$18))),"") | R18: =IF($D$18="chien_dau",$Q$18*$J$18*1.25,IF($D$18="san",$N$18,IF($D$18="relay",$K$18,IF($L$18>0,$M$18*SQRT($K$18/$L$18),$N$18)))) | S18: =MAX($N$18,MIN($O$18,ROUND($R$18,0))) | T18: =$S$18-Thap!$BN$25 | U18: Tools/balance/p32_tower_prices.py Model.price('ew_tower.spoof')
A19: guard_tower | B19: Small | C19: light | D19: chien_dau | E19: 1.11 | F19: 64.6 | G19: 220 | H19: 20.842881 | I19: 7 | J19: 0.575 | N19: 3 | O19: 6 | P19: =IF($D$19="chien_dau",Thap!$J$28/MAX(0.000001,$E$19),"") | Q19: =IF($D$19="chien_dau",SQRT(MAX(0,($P$19/$G$19)*($F$19/$H$19))),"") | R19: =IF($D$19="chien_dau",$Q$19*$J$19*1.25,IF($D$19="san",$N$19,IF($D$19="relay",$K$19,IF($L$19>0,$M$19*SQRT($K$19/$L$19),$N$19)))) | S19: =MAX($N$19,MIN($O$19,ROUND($R$19,0))) | T19: =$S$19-Thap!$BN$28 | U19: Tools/balance/p32_tower_prices.py Model.price('guard_tower')
A20: guard_tower.nest | B20: Small | C20: light | D20: chien_dau | E20: 1.11 | F20: 66.666667 | G20: 220 | H20: 20.842881 | I20: 7 | J20: 0.575 | N20: 3 | O20: 6 | P20: =IF($D$20="chien_dau",Thap!$J$29/MAX(0.000001,$E$20),"") | Q20: =IF($D$20="chien_dau",SQRT(MAX(0,($P$20/$G$20)*($F$20/$H$20))),"") | R20: =IF($D$20="chien_dau",$Q$20*$J$20*1.25,IF($D$20="san",$N$20,IF($D$20="relay",$K$20,IF($L$20>0,$M$20*SQRT($K$20/$L$20),$N$20)))) | S20: =MAX($N$20,MIN($O$20,ROUND($R$20,0))) | T20: =$S$20-Thap!$BN$29 | U20: Tools/balance/p32_tower_prices.py Model.price('guard_tower.nest')
A21: guard_tower.watch | B21: Small | C21: light | D21: chien_dau | E21: 1.11 | F21: 66.891595 | G21: 220 | H21: 20.842881 | I21: 7 | J21: 0.575 | N21: 3 | O21: 6 | P21: =IF($D$21="chien_dau",Thap!$J$30/MAX(0.000001,$E$21),"") | Q21: =IF($D$21="chien_dau",SQRT(MAX(0,($P$21/$G$21)*($F$21/$H$21))),"") | R21: =IF($D$21="chien_dau",$Q$21*$J$21*1.25,IF($D$21="san",$N$21,IF($D$21="relay",$K$21,IF($L$21>0,$M$21*SQRT($K$21/$L$21),$N$21)))) | S21: =MAX($N$21,MIN($O$21,ROUND($R$21,0))) | T21: =$S$21-Thap!$BN$30 | U21: Tools/balance/p32_tower_prices.py Model.price('guard_tower.watch')
A22: gun_turret | B22: Medium | C22: at | D22: chien_dau | E22: 0.75 | F22: 77.120807 | G22: 328.4902 | H22: 7.6732421 | I22: 14 | J22: 0.625 | N22: 5 | O22: 11 | P22: =IF($D$22="chien_dau",Thap!$J$31/MAX(0.000001,$E$22),"") | Q22: =IF($D$22="chien_dau",SQRT(MAX(0,($P$22/$G$22)*($F$22/$H$22))),"") | R22: =IF($D$22="chien_dau",$Q$22*$J$22*1.25,IF($D$22="san",$N$22,IF($D$22="relay",$K$22,IF($L$22>0,$M$22*SQRT($K$22/$L$22),$N$22)))) | S22: =MAX($N$22,MIN($O$22,ROUND($R$22,0))) | T22: =$S$22-Thap!$BN$31 | U22: Tools/balance/p32_tower_prices.py Model.price('gun_turret')
A23: gun_turret.auto | B23: Medium | C23: light | D23: chien_dau | E23: 0.75 | F23: 77.777778 | G23: 183.33333 | H23: 20.842881 | I23: 7 | J23: 0.625 | N23: 5 | O23: 11 | P23: =IF($D$23="chien_dau",Thap!$J$32/MAX(0.000001,$E$23),"") | Q23: =IF($D$23="chien_dau",SQRT(MAX(0,($P$23/$G$23)*($F$23/$H$23))),"") | R23: =IF($D$23="chien_dau",$Q$23*$J$23*1.25,IF($D$23="san",$N$23,IF($D$23="relay",$K$23,IF($L$23>0,$M$23*SQRT($K$23/$L$23),$N$23)))) | S23: =MAX($N$23,MIN($O$23,ROUND($R$23,0))) | T23: =$S$23-Thap!$BN$32 | U23: Tools/balance/p32_tower_prices.py Model.price('gun_turret.auto')
A24: gun_turret.long | B24: Medium | C24: at | D24: chien_dau | E24: 0.75 | F24: 67.725722 | G24: 328.4902 | H24: 7.6732421 | I24: 14 | J24: 0.625 | N24: 5 | O24: 11 | P24: =IF($D$24="chien_dau",Thap!$J$33/MAX(0.000001,$E$24),"") | Q24: =IF($D$24="chien_dau",SQRT(MAX(0,($P$24/$G$24)*($F$24/$H$24))),"") | R24: =IF($D$24="chien_dau",$Q$24*$J$24*1.25,IF($D$24="san",$N$24,IF($D$24="relay",$K$24,IF($L$24>0,$M$24*SQRT($K$24/$L$24),$N$24)))) | S24: =MAX($N$24,MIN($O$24,ROUND($R$24,0))) | T24: =$S$24-Thap!$BN$33 | U24: Tools/balance/p32_tower_prices.py Model.price('gun_turret.long')
A25: heavy_turret | B25: Large | C25: at | D25: chien_dau | E25: 0.51 | F25: 50.047295 | G25: 328.4902 | H25: 7.6732421 | I25: 14 | J25: 0.625 | N25: 9 | O25: 18 | P25: =IF($D$25="chien_dau",Thap!$J$34/MAX(0.000001,$E$25),"") | Q25: =IF($D$25="chien_dau",SQRT(MAX(0,($P$25/$G$25)*($F$25/$H$25))),"") | R25: =IF($D$25="chien_dau",$Q$25*$J$25*1.25,IF($D$25="san",$N$25,IF($D$25="relay",$K$25,IF($L$25>0,$M$25*SQRT($K$25/$L$25),$N$25)))) | S25: =MAX($N$25,MIN($O$25,ROUND($R$25,0))) | T25: =$S$25-Thap!$BN$34 | U25: Tools/balance/p32_tower_prices.py Model.price('heavy_turret')
A26: heavy_turret.bastion | B26: Large | C26: at | D26: chien_dau | E26: 0.51 | F26: 87.83636 | G26: 328.4902 | H26: 7.6732421 | I26: 14 | J26: 0.625 | N26: 9 | O26: 18 | P26: =IF($D$26="chien_dau",Thap!$J$35/MAX(0.000001,$E$26),"") | Q26: =IF($D$26="chien_dau",SQRT(MAX(0,($P$26/$G$26)*($F$26/$H$26))),"") | R26: =IF($D$26="chien_dau",$Q$26*$J$26*1.25,IF($D$26="san",$N$26,IF($D$26="relay",$K$26,IF($L$26>0,$M$26*SQRT($K$26/$L$26),$N$26)))) | S26: =MAX($N$26,MIN($O$26,ROUND($R$26,0))) | T26: =$S$26-Thap!$BN$35 | U26: Tools/balance/p32_tower_prices.py Model.price('heavy_turret.bastion')
A27: heavy_turret.coastal | B27: Large | C27: ground | D27: chien_dau | E27: 0.51 | F27: 49.967762 | G27: 126.69206 | H27: 8.9217841 | I27: 10 | J27: 0.725 | N27: 9 | O27: 18 | P27: =IF($D$27="chien_dau",Thap!$J$36/MAX(0.000001,$E$27),"") | Q27: =IF($D$27="chien_dau",SQRT(MAX(0,($P$27/$G$27)*($F$27/$H$27))),"") | R27: =IF($D$27="chien_dau",$Q$27*$J$27*1.25,IF($D$27="san",$N$27,IF($D$27="relay",$K$27,IF($L$27>0,$M$27*SQRT($K$27/$L$27),$N$27)))) | S27: =MAX($N$27,MIN($O$27,ROUND($R$27,0))) | T27: =$S$27-Thap!$BN$36 | U27: Tools/balance/p32_tower_prices.py Model.price('heavy_turret.coastal')
A28: laser_ad_station | B28: Medium | C28: util:intercept | D28: intercept | K28: 97.959184 | L28: 100 | M28: 5 | N28: 5 | O28: 11 | P28: =IF($D$28="chien_dau",Thap!$J$37/MAX(0.000001,$E$28),"") | Q28: =IF($D$28="chien_dau",SQRT(MAX(0,($P$28/$G$28)*($F$28/$H$28))),"") | R28: =IF($D$28="chien_dau",$Q$28*$J$28*1.25,IF($D$28="san",$N$28,IF($D$28="relay",$K$28,IF($L$28>0,$M$28*SQRT($K$28/$L$28),$N$28)))) | S28: =MAX($N$28,MIN($O$28,ROUND($R$28,0))) | T28: =$S$28-Thap!$BN$37 | U28: Tools/balance/p32_tower_prices.py Model.price('laser_ad_station')
A29: laser_ad_station.laser | B29: Medium | C29: util:intercept | D29: intercept | K29: 97.959184 | L29: 100 | M29: 5 | N29: 5 | O29: 11 | P29: =IF($D$29="chien_dau",Thap!$J$38/MAX(0.000001,$E$29),"") | Q29: =IF($D$29="chien_dau",SQRT(MAX(0,($P$29/$G$29)*($F$29/$H$29))),"") | R29: =IF($D$29="chien_dau",$Q$29*$J$29*1.25,IF($D$29="san",$N$29,IF($D$29="relay",$K$29,IF($L$29>0,$M$29*SQRT($K$29/$L$29),$N$29)))) | S29: =MAX($N$29,MIN($O$29,ROUND($R$29,0))) | T29: =$S$29-Thap!$BN$38 | U29: Tools/balance/p32_tower_prices.py Model.price('laser_ad_station.laser')
A30: mg_bunker | B30: Small | C30: light | D30: chien_dau | E30: 0.63 | F30: 68.316725 | G30: 220 | H30: 20.842881 | I30: 7 | J30: 0.625 | N30: 3 | O30: 6 | P30: =IF($D$30="chien_dau",Thap!$J$40/MAX(0.000001,$E$30),"") | Q30: =IF($D$30="chien_dau",SQRT(MAX(0,($P$30/$G$30)*($F$30/$H$30))),"") | R30: =IF($D$30="chien_dau",$Q$30*$J$30*1.25,IF($D$30="san",$N$30,IF($D$30="relay",$K$30,IF($L$30>0,$M$30*SQRT($K$30/$L$30),$N$30)))) | S30: =MAX($N$30,MIN($O$30,ROUND($R$30,0))) | T30: =$S$30-Thap!$BN$40 | U30: Tools/balance/p32_tower_prices.py Model.price('mg_bunker')
A31: mg_bunker.flame | B31: Small | C31: light | D31: chien_dau | E31: 0.63 | F31: 55.216 | G31: 220 | H31: 20.842881 | I31: 7 | J31: 0.575 | N31: 3 | O31: 6 | P31: =IF($D$31="chien_dau",Thap!$J$41/MAX(0.000001,$E$31),"") | Q31: =IF($D$31="chien_dau",SQRT(MAX(0,($P$31/$G$31)*($F$31/$H$31))),"") | R31: =IF($D$31="chien_dau",$Q$31*$J$31*1.25,IF($D$31="san",$N$31,IF($D$31="relay",$K$31,IF($L$31>0,$M$31*SQRT($K$31/$L$31),$N$31)))) | S31: =MAX($N$31,MIN($O$31,ROUND($R$31,0))) | T31: =$S$31-Thap!$BN$41 | U31: Tools/balance/p32_tower_prices.py Model.price('mg_bunker.flame')
A32: mg_bunker.twin | B32: Small | C32: light | D32: chien_dau | E32: 0.63 | F32: 65.646939 | G32: 220 | H32: 20.842881 | I32: 7 | J32: 0.575 | N32: 3 | O32: 6 | P32: =IF($D$32="chien_dau",Thap!$J$42/MAX(0.000001,$E$32),"") | Q32: =IF($D$32="chien_dau",SQRT(MAX(0,($P$32/$G$32)*($F$32/$H$32))),"") | R32: =IF($D$32="chien_dau",$Q$32*$J$32*1.25,IF($D$32="san",$N$32,IF($D$32="relay",$K$32,IF($L$32>0,$M$32*SQRT($K$32/$L$32),$N$32)))) | S32: =MAX($N$32,MIN($O$32,ROUND($R$32,0))) | T32: =$S$32-Thap!$BN$42 | U32: Tools/balance/p32_tower_prices.py Model.price('mg_bunker.twin')
A33: missile_battery | B33: Large | C33: air | D33: chien_dau | E33: 1.5 | F33: 276.25 | G33: 144.83333 | H33: 36.018667 | I33: 7 | J33: 0.725 | N33: 9 | O33: 18 | P33: =IF($D$33="chien_dau",Thap!$J$43/MAX(0.000001,$E$33),"") | Q33: =IF($D$33="chien_dau",SQRT(MAX(0,($P$33/$G$33)*($F$33/$H$33))),"") | R33: =IF($D$33="chien_dau",$Q$33*$J$33*1.25,IF($D$33="san",$N$33,IF($D$33="relay",$K$33,IF($L$33>0,$M$33*SQRT($K$33/$L$33),$N$33)))) | S33: =MAX($N$33,MIN($O$33,ROUND($R$33,0))) | T33: =$S$33-Thap!$BN$43 | U33: Tools/balance/p32_tower_prices.py Model.price('missile_battery')
A34: missile_battery.lrr | B34: Large | C34: air | D34: chien_dau | E34: 1.5 | F34: 226.66667 | G34: 144.83333 | H34: 36.018667 | I34: 7 | J34: 0.725 | N34: 9 | O34: 18 | P34: =IF($D$34="chien_dau",Thap!$J$44/MAX(0.000001,$E$34),"") | Q34: =IF($D$34="chien_dau",SQRT(MAX(0,($P$34/$G$34)*($F$34/$H$34))),"") | R34: =IF($D$34="chien_dau",$Q$34*$J$34*1.25,IF($D$34="san",$N$34,IF($D$34="relay",$K$34,IF($L$34>0,$M$34*SQRT($K$34/$L$34),$N$34)))) | S34: =MAX($N$34,MIN($O$34,ROUND($R$34,0))) | T34: =$S$34-Thap!$BN$44 | U34: Tools/balance/p32_tower_prices.py Model.price('missile_battery.lrr')
A35: missile_battery.pac3 | B35: Large | C35: air | D35: chien_dau | E35: 1.5 | F35: 139.70149 | G35: 144.83333 | H35: 36.018667 | I35: 7 | J35: 0.725 | N35: 9 | O35: 18 | P35: =IF($D$35="chien_dau",Thap!$J$45/MAX(0.000001,$E$35),"") | Q35: =IF($D$35="chien_dau",SQRT(MAX(0,($P$35/$G$35)*($F$35/$H$35))),"") | R35: =IF($D$35="chien_dau",$Q$35*$J$35*1.25,IF($D$35="san",$N$35,IF($D$35="relay",$K$35,IF($L$35>0,$M$35*SQRT($K$35/$L$35),$N$35)))) | S35: =MAX($N$35,MIN($O$35,ROUND($R$35,0))) | T35: =$S$35-Thap!$BN$45 | U35: Tools/balance/p32_tower_prices.py Model.price('missile_battery.pac3')
A36: rocket_turret | B36: Medium | C36: ground | D36: chien_dau | E36: 1.5 | F36: 57.040541 | G36: 126.69206 | H36: 8.9217841 | I36: 10 | J36: 0.725 | N36: 5 | O36: 11 | P36: =IF($D$36="chien_dau",Thap!$J$48/MAX(0.000001,$E$36),"") | Q36: =IF($D$36="chien_dau",SQRT(MAX(0,($P$36/$G$36)*($F$36/$H$36))),"") | R36: =IF($D$36="chien_dau",$Q$36*$J$36*1.25,IF($D$36="san",$N$36,IF($D$36="relay",$K$36,IF($L$36>0,$M$36*SQRT($K$36/$L$36),$N$36)))) | S36: =MAX($N$36,MIN($O$36,ROUND($R$36,0))) | T36: =$S$36-Thap!$BN$48 | U36: Tools/balance/p32_tower_prices.py Model.price('rocket_turret')
A37: rocket_turret.cluster | B37: Medium | C37: ground | D37: chien_dau | E37: 1.5 | F37: 51.147321 | G37: 126.69206 | H37: 8.9217841 | I37: 10 | J37: 0.725 | N37: 5 | O37: 11 | P37: =IF($D$37="chien_dau",Thap!$J$49/MAX(0.000001,$E$37),"") | Q37: =IF($D$37="chien_dau",SQRT(MAX(0,($P$37/$G$37)*($F$37/$H$37))),"") | R37: =IF($D$37="chien_dau",$Q$37*$J$37*1.25,IF($D$37="san",$N$37,IF($D$37="relay",$K$37,IF($L$37>0,$M$37*SQRT($K$37/$L$37),$N$37)))) | S37: =MAX($N$37,MIN($O$37,ROUND($R$37,0))) | T37: =$S$37-Thap!$BN$49 | U37: Tools/balance/p32_tower_prices.py Model.price('rocket_turret.cluster')
A38: rocket_turret.guided | B38: Medium | C38: ground | D38: chien_dau | E38: 1.5 | F38: 37.5 | G38: 126.69206 | H38: 8.9217841 | I38: 10 | J38: 0.725 | N38: 5 | O38: 11 | P38: =IF($D$38="chien_dau",Thap!$J$50/MAX(0.000001,$E$38),"") | Q38: =IF($D$38="chien_dau",SQRT(MAX(0,($P$38/$G$38)*($F$38/$H$38))),"") | R38: =IF($D$38="chien_dau",$Q$38*$J$38*1.25,IF($D$38="san",$N$38,IF($D$38="relay",$K$38,IF($L$38>0,$M$38*SQRT($K$38/$L$38),$N$38)))) | S38: =MAX($N$38,MIN($O$38,ROUND($R$38,0))) | T38: =$S$38-Thap!$BN$50 | U38: Tools/balance/p32_tower_prices.py Model.price('rocket_turret.guided')
A39: shield_tower | B39: Large | C39: util:protect | D39: protect | K39: 3600 | L39: 3600 | M39: 9 | N39: 9 | O39: 18 | P39: =IF($D$39="chien_dau",Thap!$J$51/MAX(0.000001,$E$39),"") | Q39: =IF($D$39="chien_dau",SQRT(MAX(0,($P$39/$G$39)*($F$39/$H$39))),"") | R39: =IF($D$39="chien_dau",$Q$39*$J$39*1.25,IF($D$39="san",$N$39,IF($D$39="relay",$K$39,IF($L$39>0,$M$39*SQRT($K$39/$L$39),$N$39)))) | S39: =MAX($N$39,MIN($O$39,ROUND($R$39,0))) | T39: =$S$39-Thap!$BN$51 | U39: Tools/balance/p32_tower_prices.py Model.price('shield_tower')
A40: shield_tower.bulwark | B40: Large | C40: util:protect | D40: protect | K40: 3600 | L40: 3600 | M40: 9 | N40: 9 | O40: 18 | P40: =IF($D$40="chien_dau",Thap!$J$52/MAX(0.000001,$E$40),"") | Q40: =IF($D$40="chien_dau",SQRT(MAX(0,($P$40/$G$40)*($F$40/$H$40))),"") | R40: =IF($D$40="chien_dau",$Q$40*$J$40*1.25,IF($D$40="san",$N$40,IF($D$40="relay",$K$40,IF($L$40>0,$M$40*SQRT($K$40/$L$40),$N$40)))) | S40: =MAX($N$40,MIN($O$40,ROUND($R$40,0))) | T40: =$S$40-Thap!$BN$52 | U40: Tools/balance/p32_tower_prices.py Model.price('shield_tower.bulwark')
A41: shield_tower.ward | B41: Large | C41: util:protect | D41: protect | K41: 3600 | L41: 3600 | M41: 9 | N41: 9 | O41: 18 | P41: =IF($D$41="chien_dau",Thap!$J$53/MAX(0.000001,$E$41),"") | Q41: =IF($D$41="chien_dau",SQRT(MAX(0,($P$41/$G$41)*($F$41/$H$41))),"") | R41: =IF($D$41="chien_dau",$Q$41*$J$41*1.25,IF($D$41="san",$N$41,IF($D$41="relay",$K$41,IF($L$41>0,$M$41*SQRT($K$41/$L$41),$N$41)))) | S41: =MAX($N$41,MIN($O$41,ROUND($R$41,0))) | T41: =$S$41-Thap!$BN$53 | U41: Tools/balance/p32_tower_prices.py Model.price('shield_tower.ward')
A42: vehicle_hangar | B42: Medium | C42: multi | D42: chien_dau | E42: 1.275 | F42: 0 | G42: 172.87897 | H42: 9.8043496 | I42: 46 | J42: 0.575 | N42: 5 | O42: 11 | P42: =IF($D$42="chien_dau",Thap!$J$57/MAX(0.000001,$E$42),"") | Q42: =IF($D$42="chien_dau",SQRT(MAX(0,($P$42/$G$42)*($F$42/$H$42))),"") | R42: =IF($D$42="chien_dau",$Q$42*$J$42*1.25,IF($D$42="san",$N$42,IF($D$42="relay",$K$42,IF($L$42>0,$M$42*SQRT($K$42/$L$42),$N$42)))) | S42: =MAX($N$42,MIN($O$42,ROUND($R$42,0))) | T42: =$S$42-Thap!$BN$57 | U42: Tools/balance/p32_tower_prices.py Model.price('vehicle_hangar')

Sheet Tuong_duong_xe_cong_trinh
A1: id | B1: gia_tri_tuong_duong_xe_cp | C1: ty_le_so_voi_gia | D1: doa_kinetic | E1: so_phat_kinetic | F1: doa_he | G1: so_phat_he | H1: doa_shaped | I1: so_phat_shaped | J1: doa_artillery | K1: so_phat_artillery | L1: nguon | M1: raw_json
A2: aa_turret | B2: =Thap_gia_cong_thuc!$Q$2 | C2: =IF(ISNUMBER($B$2),$B$2/Thap!$BN$3,"") | D2: ifv_30 | E2: =IF($D$2="","",IF(INDEX(cc_input_vu_khi!$B$2:$B$11,MATCH($D$2,cc_input_vu_khi!$A$2:$A$11,0))*INDEX(cc_input_bang_xuyen_giap!$B$2:$B$7,MIN(6,MAX(1,IF(INDEX(cc_input_vu_khi_suy_ra!$B$2:$B$11,MATCH($D$2,cc_input_vu_khi_suy_ra!$A$2:$A$11,0)),MAX(1,2-(INDEX(cc_input_vu_khi!$C$2:$C$11,MATCH($D$2,cc_input_vu_khi!$A$2:$A$11,0))-Thap!$K$3)),2-(INDEX(cc_input_vu_khi!$C$2:$C$11,MATCH($D$2,cc_input_vu_khi!$A$2:$A$11,0))-Thap!$K$3))+1)))*INDEX(cc_input_vu_khi_suy_ra!$D$2:$D$11,MATCH($D$2,cc_input_vu_khi_suy_ra!$A$2:$A$11,0))>0,CEILING(Thap!$J$3/(INDEX(cc_input_vu_khi!$B$2:$B$11,MATCH($D$2,cc_input_vu_khi!$A$2:$A$11,0))*INDEX(cc_input_bang_xuyen_giap!$B$2:$B$7,MIN(6,MAX(1,IF(INDEX(cc_input_vu_khi_suy_ra!$B$2:$B$11,MATCH($D$2,cc_input_vu_khi_suy_ra!$A$2:$A$11,0)),MAX(1,2-(INDEX(cc_input_vu_khi!$C$2:$C$11,MATCH($D$2,cc_input_vu_khi!$A$2:$A$11,0))-Thap!$K$3)),2-(INDEX(cc_input_vu_khi!$C$2:$C$11,MATCH($D$2,cc_input_vu_khi!$A$2:$A$11,0))-Thap!$K$3))+1)))*INDEX(cc_input_vu_khi_suy_ra!$D$2:$D$11,MATCH($D$2,cc_input_vu_khi_suy_ra!$A$2:$A$11,0))),1),"")) | F2: gun_120mm_he | G2: =IF($F$2="","",IF(INDEX(cc_input_vu_khi!$B$2:$B$11,MATCH($F$2,cc_input_vu_khi!$A$2:$A$11,0))*INDEX(cc_input_bang_xuyen_giap!$B$2:$B$7,MIN(6,MAX(1,IF(INDEX(cc_input_vu_khi_suy_ra!$B$2:$B$11,MATCH($F$2,cc_input_vu_khi_suy_ra!$A$2:$A$11,0)),MAX(1,2-(INDEX(cc_input_vu_khi!$C$2:$C$11,MATCH($F$2,cc_input_vu_khi!$A$2:$A$11,0))-Thap!$K$3)),2-(INDEX(cc_input_vu_khi!$C$2:$C$11,MATCH($F$2,cc_input_vu_khi!$A$2:$A$11,0))-Thap!$K$3))+1)))*INDEX(cc_input_vu_khi_suy_ra!$D$2:$D$11,MATCH($F$2,cc_input_vu_khi_suy_ra!$A$2:$A$11,0))>0,CEILING(Thap!$J$3/(INDEX(cc_input_vu_khi!$B$2:$B$11,MATCH($F$2,cc_input_vu_khi!$A$2:$A$11,0))*INDEX(cc_input_bang_xuyen_giap!$B$2:$B$7,MIN(6,MAX(1,IF(INDEX(cc_input_vu_khi_suy_ra!$B$2:$B$11,MATCH($F$2,cc_input_vu_khi_suy_ra!$A$2:$A$11,0)),MAX(1,2-(INDEX(cc_input_vu_khi!$C$2:$C$11,MATCH($F$2,cc_input_vu_khi!$A$2:$A$11,0))-Thap!$K$3)),2-(INDEX(cc_input_vu_khi!$C$2:$C$11,MATCH($F$2,cc_input_vu_khi!$A$2:$A$11,0))-Thap!$K$3))+1)))*INDEX(cc_input_vu_khi_suy_ra!$D$2:$D$11,MATCH($F$2,cc_input_vu_khi_suy_ra!$A$2:$A$11,0))),1),"")) | H2: recoilless_106 | I2: =IF($H$2="","",IF(INDEX(cc_input_vu_khi!$B$2:$B$11,MATCH($H$2,cc_input_vu_khi!$A$2:$A$11,0))*INDEX(cc_input_bang_xuyen_giap!$B$2:$B$7,MIN(6,MAX(1,IF(INDEX(cc_input_vu_khi_suy_ra!$B$2:$B$11,MATCH($H$2,cc_input_vu_khi_suy_ra!$A$2:$A$11,0)),MAX(1,2-(INDEX(cc_input_vu_khi!$C$2:$C$11,MATCH($H$2,cc_input_vu_khi!$A$2:$A$11,0))-Thap!$K$3)),2-(INDEX(cc_input_vu_khi!$C$2:$C$11,MATCH($H$2,cc_input_vu_khi!$A$2:$A$11,0))-Thap!$K$3))+1)))*INDEX(cc_input_vu_khi_suy_ra!$D$2:$D$11,MATCH($H$2,cc_input_vu_khi_suy_ra!$A$2:$A$11,0))>0,CEILING(Thap!$J$3/(INDEX(cc_input_vu_khi!$B$2:$B$11,MATCH($H$2,cc_input_vu_khi!$A$2:$A$11,0))*INDEX(cc_input_bang_xuyen_giap!$B$2:$B$7,MIN(6,MAX(1,IF(INDEX(cc_input_vu_khi_suy_ra!$B$2:$B$11,MATCH($H$2,cc_input_vu_khi_suy_ra!$A$2:$A$11,0)),MAX(1,2-(INDEX(cc_input_vu_khi!$C$2:$C$11,MATCH($H$2,cc_input_vu_khi!$A$2:$A$11,0))-Thap!$K$3)),2-(INDEX(cc_input_vu_khi!$C$2:$C$11,MATCH($H$2,cc_input_vu_khi!$A$2:$A$11,0))-Thap!$K$3))+1)))*INDEX(cc_input_vu_khi_suy_ra!$D$2:$D$11,MATCH($H$2,cc_input_vu_khi_suy_ra!$A$2:$A$11,0))),1),"")) | J2: technical_rockets | K2: =IF($J$2="","",IF(INDEX(cc_input_vu_khi!$B$2:$B$11,MATCH($J$2,cc_input_vu_khi!$A$2:$A$11,0))*INDEX(cc_input_bang_xuyen_giap!$B$2:$B$7,MIN(6,MAX(1,IF(INDEX(cc_input_vu_khi_suy_ra!$B$2:$B$11,MATCH($J$2,cc_input_vu_khi_suy_ra!$A$2:$A$11,0)),MAX(1,2-(INDEX(cc_input_vu_khi!$C$2:$C$11,MATCH($J$2,cc_input_vu_khi!$A$2:$A$11,0))-Thap!$K$3)),2-(INDEX(cc_input_vu_khi!$C$2:$C$11,MATCH($J$2,cc_input_vu_khi!$A$2:$A$11,0))-Thap!$K$3))+1)))*INDEX(cc_input_vu_khi_suy_ra!$D$2:$D$11,MATCH($J$2,cc_input_vu_khi_suy_ra!$A$2:$A$11,0))>0,CEILING(Thap!$J$3/(INDEX(cc_input_vu_khi!$B$2:$B$11,MATCH($J$2,cc_input_vu_khi!$A$2:$A$11,0))*INDEX(cc_input_bang_xuyen_giap!$B$2:$B$7,MIN(6,MAX(1,IF(INDEX(cc_input_vu_khi_suy_ra!$B$2:$B$11,MATCH($J$2,cc_input_vu_khi_suy_ra!$A$2:$A$11,0)),MAX(1,2-(INDEX(cc_input_vu_khi!$C$2:$C$11,MATCH($J$2,cc_input_vu_khi!$A$2:$A$11,0))-Thap!$K$3)),2-(INDEX(cc_input_vu_khi!$C$2:$C$11,MATCH($J$2,cc_input_vu_khi!$A$2:$A$11,0))-Thap!$K$3))+1)))*INDEX(cc_input_vu_khi_suy_ra!$D$2:$D$11,MATCH($J$2,cc_input_vu_khi_suy_ra!$A$2:$A$11,0))),1),"")) | L2: Tools/balance/p32_tower_prices.py Model.price('aa_turret') + threats('Small')
A3: aa_turret.flak | B3: =Thap_gia_cong_thuc!$Q$3 | C3: =IF(ISNUMBER($B$3),$B$3/Thap!$BN$4,"") | D3: ifv_30 | E3: =IF($D$3="","",IF(INDEX(cc_input_vu_khi!$B$2:$B$11,MATCH($D$3,cc_input_vu_khi!$A$2:$A$11,0))*INDEX(cc_input_bang_xuyen_giap!$B$2:$B$7,MIN(6,MAX(1,IF(INDEX(cc_input_vu_khi_suy_ra!$B$2:$B$11,MATCH($D$3,cc_input_vu_khi_suy_ra!$A$2:$A$11,0)),MAX(1,2-(INDEX(cc_input_vu_khi!$C$2:$C$11,MATCH($D$3,cc_input_vu_khi!$A$2:$A$11,0))-Thap!$K$4)),2-(INDEX(cc_input_vu_khi!$C$2:$C$11,MATCH($D$3,cc_input_vu_khi!$A$2:$A$11,0))-Thap!$K$4))+1)))*INDEX(cc_input_vu_khi_suy_ra!$D$2:$D$11,MATCH($D$3,cc_input_vu_khi_suy_ra!$A$2:$A$11,0))>0,CEILING(Thap!$J$4/(INDEX(cc_input_vu_khi!$B$2:$B$11,MATCH($D$3,cc_input_vu_khi!$A$2:$A$11,0))*INDEX(cc_input_bang_xuyen_giap!$B$2:$B$7,MIN(6,MAX(1,IF(INDEX(cc_input_vu_khi_suy_ra!$B$2:$B$11,MATCH($D$3,cc_input_vu_khi_suy_ra!$A$2:$A$11,0)),MAX(1,2-(INDEX(cc_input_vu_khi!$C$2:$C$11,MATCH($D$3,cc_input_vu_khi!$A$2:$A$11,0))-Thap!$K$4)),2-(INDEX(cc_input_vu_khi!$C$2:$C$11,MATCH($D$3,cc_input_vu_khi!$A$2:$A$11,0))-Thap!$K$4))+1)))*INDEX(cc_input_vu_khi_suy_ra!$D$2:$D$11,MATCH($D$3,cc_input_vu_khi_suy_ra!$A$2:$A$11,0))),1),"")) | F3: gun_120mm_he | G3: =IF($F$3="","",IF(INDEX(cc_input_vu_khi!$B$2:$B$11,MATCH($F$3,cc_input_vu_khi!$A$2:$A$11,0))*INDEX(cc_input_bang_xuyen_giap!$B$2:$B$7,MIN(6,MAX(1,IF(INDEX(cc_input_vu_khi_suy_ra!$B$2:$B$11,MATCH($F$3,cc_input_vu_khi_suy_ra!$A$2:$A$11,0)),MAX(1,2-(INDEX(cc_input_vu_khi!$C$2:$C$11,MATCH($F$3,cc_input_vu_khi!$A$2:$A$11,0))-Thap!$K$4)),2-(INDEX(cc_input_vu_khi!$C$2:$C$11,MATCH($F$3,cc_input_vu_khi!$A$2:$A$11,0))-Thap!$K$4))+1)))*INDEX(cc_input_vu_khi_suy_ra!$D$2:$D$11,MATCH($F$3,cc_input_vu_khi_suy_ra!$A$2:$A$11,0))>0,CEILING(Thap!$J$4/(INDEX(cc_input_vu_khi!$B$2:$B$11,MATCH($F$3,cc_input_vu_khi!$A$2:$A$11,0))*INDEX(cc_input_bang_xuyen_giap!$B$2:$B$7,MIN(6,MAX(1,IF(INDEX(cc_input_vu_khi_suy_ra!$B$2:$B$11,MATCH($F$3,cc_input_vu_khi_suy_ra!$A$2:$A$11,0)),MAX(1,2-(INDEX(cc_input_vu_khi!$C$2:$C$11,MATCH($F$3,cc_input_vu_khi!$A$2:$A$11,0))-Thap!$K$4)),2-(INDEX(cc_input_vu_khi!$C$2:$C$11,MATCH($F$3,cc_input_vu_khi!$A$2:$A$11,0))-Thap!$K$4))+1)))*INDEX(cc_input_vu_khi_suy_ra!$D$2:$D$11,MATCH($F$3,cc_input_vu_khi_suy_ra!$A$2:$A$11,0))),1),"")) | H3: recoilless_106 | I3: =IF($H$3="","",IF(INDEX(cc_input_vu_khi!$B$2:$B$11,MATCH($H$3,cc_input_vu_khi!$A$2:$A$11,0))*INDEX(cc_input_bang_xuyen_giap!$B$2:$B$7,MIN(6,MAX(1,IF(INDEX(cc_input_vu_khi_suy_ra!$B$2:$B$11,MATCH($H$3,cc_input_vu_khi_suy_ra!$A$2:$A$11,0)),MAX(1,2-(INDEX(cc_input_vu_khi!$C$2:$C$11,MATCH($H$3,cc_input_vu_khi!$A$2:$A$11,0))-Thap!$K$4)),2-(INDEX(cc_input_vu_khi!$C$2:$C$11,MATCH($H$3,cc_input_vu_khi!$A$2:$A$11,0))-Thap!$K$4))+1)))*INDEX(cc_input_vu_khi_suy_ra!$D$2:$D$11,MATCH($H$3,cc_input_vu_khi_suy_ra!$A$2:$A$11,0))>0,CEILING(Thap!$J$4/(INDEX(cc_input_vu_khi!$B$2:$B$11,MATCH($H$3,cc_input_vu_khi!$A$2:$A$11,0))*INDEX(cc_input_bang_xuyen_giap!$B$2:$B$7,MIN(6,MAX(1,IF(INDEX(cc_input_vu_khi_suy_ra!$B$2:$B$11,MATCH($H$3,cc_input_vu_khi_suy_ra!$A$2:$A$11,0)),MAX(1,2-(INDEX(cc_input_vu_khi!$C$2:$C$11,MATCH($H$3,cc_input_vu_khi!$A$2:$A$11,0))-Thap!$K$4)),2-(INDEX(cc_input_vu_khi!$C$2:$C$11,MATCH($H$3,cc_input_vu_khi!$A$2:$A$11,0))-Thap!$K$4))+1)))*INDEX(cc_input_vu_khi_suy_ra!$D$2:$D$11,MATCH($H$3,cc_input_vu_khi_suy_ra!$A$2:$A$11,0))),1),"")) | J3: technical_rockets | K3: =IF($J$3="","",IF(INDEX(cc_input_vu_khi!$B$2:$B$11,MATCH($J$3,cc_input_vu_khi!$A$2:$A$11,0))*INDEX(cc_input_bang_xuyen_giap!$B$2:$B$7,MIN(6,MAX(1,IF(INDEX(cc_input_vu_khi_suy_ra!$B$2:$B$11,MATCH($J$3,cc_input_vu_khi_suy_ra!$A$2:$A$11,0)),MAX(1,2-(INDEX(cc_input_vu_khi!$C$2:$C$11,MATCH($J$3,cc_input_vu_khi!$A$2:$A$11,0))-Thap!$K$4)),2-(INDEX(cc_input_vu_khi!$C$2:$C$11,MATCH($J$3,cc_input_vu_khi!$A$2:$A$11,0))-Thap!$K$4))+1)))*INDEX(cc_input_vu_khi_suy_ra!$D$2:$D$11,MATCH($J$3,cc_input_vu_khi_suy_ra!$A$2:$A$11,0))>0,CEILING(Thap!$J$4/(INDEX(cc_input_vu_khi!$B$2:$B$11,MATCH($J$3,cc_input_vu_khi!$A$2:$A$11,0))*INDEX(cc_input_bang_xuyen_giap!$B$2:$B$7,MIN(6,MAX(1,IF(INDEX(cc_input_vu_khi_suy_ra!$B$2:$B$11,MATCH($J$3,cc_input_vu_khi_suy_ra!$A$2:$A$11,0)),MAX(1,2-(INDEX(cc_input_vu_khi!$C$2:$C$11,MATCH($J$3,cc_input_vu_khi!$A$2:$A$11,0))-Thap!$K$4)),2-(INDEX(cc_input_vu_khi!$C$2:$C$11,MATCH($J$3,cc_input_vu_khi!$A$2:$A$11,0))-Thap!$K$4))+1)))*INDEX(cc_input_vu_khi_suy_ra!$D$2:$D$11,MATCH($J$3,cc_input_vu_khi_suy_ra!$A$2:$A$11,0))),1),"")) | L3: Tools/balance/p32_tower_prices.py Model.price('aa_turret.flak') + threats('Small')
A4: aa_turret.sam | B4: =Thap_gia_cong_thuc!$Q$4 | C4: =IF(ISNUMBER($B$4),$B$4/Thap!$BN$5,"") | D4: ifv_30 | E4: =IF($D$4="","",IF(INDEX(cc_input_vu_khi!$B$2:$B$11,MATCH($D$4,cc_input_vu_khi!$A$2:$A$11,0))*INDEX(cc_input_bang_xuyen_giap!$B$2:$B$7,MIN(6,MAX(1,IF(INDEX(cc_input_vu_khi_suy_ra!$B$2:$B$11,MATCH($D$4,cc_input_vu_khi_suy_ra!$A$2:$A$11,0)),MAX(1,2-(INDEX(cc_input_vu_khi!$C$2:$C$11,MATCH($D$4,cc_input_vu_khi!$A$2:$A$11,0))-Thap!$K$5)),2-(INDEX(cc_input_vu_khi!$C$2:$C$11,MATCH($D$4,cc_input_vu_khi!$A$2:$A$11,0))-Thap!$K$5))+1)))*INDEX(cc_input_vu_khi_suy_ra!$D$2:$D$11,MATCH($D$4,cc_input_vu_khi_suy_ra!$A$2:$A$11,0))>0,CEILING(Thap!$J$5/(INDEX(cc_input_vu_khi!$B$2:$B$11,MATCH($D$4,cc_input_vu_khi!$A$2:$A$11,0))*INDEX(cc_input_bang_xuyen_giap!$B$2:$B$7,MIN(6,MAX(1,IF(INDEX(cc_input_vu_khi_suy_ra!$B$2:$B$11,MATCH($D$4,cc_input_vu_khi_suy_ra!$A$2:$A$11,0)),MAX(1,2-(INDEX(cc_input_vu_khi!$C$2:$C$11,MATCH($D$4,cc_input_vu_khi!$A$2:$A$11,0))-Thap!$K$5)),2-(INDEX(cc_input_vu_khi!$C$2:$C$11,MATCH($D$4,cc_input_vu_khi!$A$2:$A$11,0))-Thap!$K$5))+1)))*INDEX(cc_input_vu_khi_suy_ra!$D$2:$D$11,MATCH($D$4,cc_input_vu_khi_suy_ra!$A$2:$A$11,0))),1),"")) | F4: gun_120mm_he | G4: =IF($F$4="","",IF(INDEX(cc_input_vu_khi!$B$2:$B$11,MATCH($F$4,cc_input_vu_khi!$A$2:$A$11,0))*INDEX(cc_input_bang_xuyen_giap!$B$2:$B$7,MIN(6,MAX(1,IF(INDEX(cc_input_vu_khi_suy_ra!$B$2:$B$11,MATCH($F$4,cc_input_vu_khi_suy_ra!$A$2:$A$11,0)),MAX(1,2-(INDEX(cc_input_vu_khi!$C$2:$C$11,MATCH($F$4,cc_input_vu_khi!$A$2:$A$11,0))-Thap!$K$5)),2-(INDEX(cc_input_vu_khi!$C$2:$C$11,MATCH($F$4,cc_input_vu_khi!$A$2:$A$11,0))-Thap!$K$5))+1)))*INDEX(cc_input_vu_khi_suy_ra!$D$2:$D$11,MATCH($F$4,cc_input_vu_khi_suy_ra!$A$2:$A$11,0))>0,CEILING(Thap!$J$5/(INDEX(cc_input_vu_khi!$B$2:$B$11,MATCH($F$4,cc_input_vu_khi!$A$2:$A$11,0))*INDEX(cc_input_bang_xuyen_giap!$B$2:$B$7,MIN(6,MAX(1,IF(INDEX(cc_input_vu_khi_suy_ra!$B$2:$B$11,MATCH($F$4,cc_input_vu_khi_suy_ra!$A$2:$A$11,0)),MAX(1,2-(INDEX(cc_input_vu_khi!$C$2:$C$11,MATCH($F$4,cc_input_vu_khi!$A$2:$A$11,0))-Thap!$K$5)),2-(INDEX(cc_input_vu_khi!$C$2:$C$11,MATCH($F$4,cc_input_vu_khi!$A$2:$A$11,0))-Thap!$K$5))+1)))*INDEX(cc_input_vu_khi_suy_ra!$D$2:$D$11,MATCH($F$4,cc_input_vu_khi_suy_ra!$A$2:$A$11,0))),1),"")) | H4: recoilless_106 | I4: =IF($H$4="","",IF(INDEX(cc_input_vu_khi!$B$2:$B$11,MATCH($H$4,cc_input_vu_khi!$A$2:$A$11,0))*INDEX(cc_input_bang_xuyen_giap!$B$2:$B$7,MIN(6,MAX(1,IF(INDEX(cc_input_vu_khi_suy_ra!$B$2:$B$11,MATCH($H$4,cc_input_vu_khi_suy_ra!$A$2:$A$11,0)),MAX(1,2-(INDEX(cc_input_vu_khi!$C$2:$C$11,MATCH($H$4,cc_input_vu_khi!$A$2:$A$11,0))-Thap!$K$5)),2-(INDEX(cc_input_vu_khi!$C$2:$C$11,MATCH($H$4,cc_input_vu_khi!$A$2:$A$11,0))-Thap!$K$5))+1)))*INDEX(cc_input_vu_khi_suy_ra!$D$2:$D$11,MATCH($H$4,cc_input_vu_khi_suy_ra!$A$2:$A$11,0))>0,CEILING(Thap!$J$5/(INDEX(cc_input_vu_khi!$B$2:$B$11,MATCH($H$4,cc_input_vu_khi!$A$2:$A$11,0))*INDEX(cc_input_bang_xuyen_giap!$B$2:$B$7,MIN(6,MAX(1,IF(INDEX(cc_input_vu_khi_suy_ra!$B$2:$B$11,MATCH($H$4,cc_input_vu_khi_suy_ra!$A$2:$A$11,0)),MAX(1,2-(INDEX(cc_input_vu_khi!$C$2:$C$11,MATCH($H$4,cc_input_vu_khi!$A$2:$A$11,0))-Thap!$K$5)),2-(INDEX(cc_input_vu_khi!$C$2:$C$11,MATCH($H$4,cc_input_vu_khi!$A$2:$A$11,0))-Thap!$K$5))+1)))*INDEX(cc_input_vu_khi_suy_ra!$D$2:$D$11,MATCH($H$4,cc_input_vu_khi_suy_ra!$A$2:$A$11,0))),1),"")) | J4: technical_rockets | K4: =IF($J$4="","",IF(INDEX(cc_input_vu_khi!$B$2:$B$11,MATCH($J$4,cc_input_vu_khi!$A$2:$A$11,0))*INDEX(cc_input_bang_xuyen_giap!$B$2:$B$7,MIN(6,MAX(1,IF(INDEX(cc_input_vu_khi_suy_ra!$B$2:$B$11,MATCH($J$4,cc_input_vu_khi_suy_ra!$A$2:$A$11,0)),MAX(1,2-(INDEX(cc_input_vu_khi!$C$2:$C$11,MATCH($J$4,cc_input_vu_khi!$A$2:$A$11,0))-Thap!$K$5)),2-(INDEX(cc_input_vu_khi!$C$2:$C$11,MATCH($J$4,cc_input_vu_khi!$A$2:$A$11,0))-Thap!$K$5))+1)))*INDEX(cc_input_vu_khi_suy_ra!$D$2:$D$11,MATCH($J$4,cc_input_vu_khi_suy_ra!$A$2:$A$11,0))>0,CEILING(Thap!$J$5/(INDEX(cc_input_vu_khi!$B$2:$B$11,MATCH($J$4,cc_input_vu_khi!$A$2:$A$11,0))*INDEX(cc_input_bang_xuyen_giap!$B$2:$B$7,MIN(6,MAX(1,IF(INDEX(cc_input_vu_khi_suy_ra!$B$2:$B$11,MATCH($J$4,cc_input_vu_khi_suy_ra!$A$2:$A$11,0)),MAX(1,2-(INDEX(cc_input_vu_khi!$C$2:$C$11,MATCH($J$4,cc_input_vu_khi!$A$2:$A$11,0))-Thap!$K$5)),2-(INDEX(cc_input_vu_khi!$C$2:$C$11,MATCH($J$4,cc_input_vu_khi!$A$2:$A$11,0))-Thap!$K$5))+1)))*INDEX(cc_input_vu_khi_suy_ra!$D$2:$D$11,MATCH($J$4,cc_input_vu_khi_suy_ra!$A$2:$A$11,0))),1),"")) | L4: Tools/balance/p32_tower_prices.py Model.price('aa_turret.sam') + threats('Small')
A5: aircraft_hangar | B5: =Thap_gia_cong_thuc!$Q$5 | C5: =IF(ISNUMBER($B$5),$B$5/Thap!$BN$6,"") | D5: gun_105_wheeled | E5: =IF($D$5="","",IF(INDEX(cc_input_vu_khi!$B$2:$B$11,MATCH($D$5,cc_input_vu_khi!$A$2:$A$11,0))*INDEX(cc_input_bang_xuyen_giap!$B$2:$B$7,MIN(6,MAX(1,IF(INDEX(cc_input_vu_khi_suy_ra!$B$2:$B$11,MATCH($D$5,cc_input_vu_khi_suy_ra!$A$2:$A$11,0)),MAX(1,2-(INDEX(cc_input_vu_khi!$C$2:$C$11,MATCH($D$5,cc_input_vu_khi!$A$2:$A$11,0))-Thap!$K$6)),2-(INDEX(cc_input_vu_khi!$C$2:$C$11,MATCH($D$5,cc_input_vu_khi!$A$2:$A$11,0))-Thap!$K$6))+1)))*INDEX(cc_input_vu_khi_suy_ra!$D$2:$D$11,MATCH($D$5,cc_input_vu_khi_suy_ra!$A$2:$A$11,0))>0,CEILING(Thap!$J$6/(INDEX(cc_input_vu_khi!$B$2:$B$11,MATCH($D$5,cc_input_vu_khi!$A$2:$A$11,0))*INDEX(cc_input_bang_xuyen_giap!$B$2:$B$7,MIN(6,MAX(1,IF(INDEX(cc_input_vu_khi_suy_ra!$B$2:$B$11,MATCH($D$5,cc_input_vu_khi_suy_ra!$A$2:$A$11,0)),MAX(1,2-(INDEX(cc_input_vu_khi!$C$2:$C$11,MATCH($D$5,cc_input_vu_khi!$A$2:$A$11,0))-Thap!$K$6)),2-(INDEX(cc_input_vu_khi!$C$2:$C$11,MATCH($D$5,cc_input_vu_khi!$A$2:$A$11,0))-Thap!$K$6))+1)))*INDEX(cc_input_vu_khi_suy_ra!$D$2:$D$11,MATCH($D$5,cc_input_vu_khi_suy_ra!$A$2:$A$11,0))),1),"")) | F5: gun_105_wheeled_he | G5: =IF($F$5="","",IF(INDEX(cc_input_vu_khi!$B$2:$B$11,MATCH($F$5,cc_input_vu_khi!$A$2:$A$11,0))*INDEX(cc_input_bang_xuyen_giap!$B$2:$B$7,MIN(6,MAX(1,IF(INDEX(cc_input_vu_khi_suy_ra!$B$2:$B$11,MATCH($F$5,cc_input_vu_khi_suy_ra!$A$2:$A$11,0)),MAX(1,2-(INDEX(cc_input_vu_khi!$C$2:$C$11,MATCH($F$5,cc_input_vu_khi!$A$2:$A$11,0))-Thap!$K$6)),2-(INDEX(cc_input_vu_khi!$C$2:$C$11,MATCH($F$5,cc_input_vu_khi!$A$2:$A$11,0))-Thap!$K$6))+1)))*INDEX(cc_input_vu_khi_suy_ra!$D$2:$D$11,MATCH($F$5,cc_input_vu_khi_suy_ra!$A$2:$A$11,0))>0,CEILING(Thap!$J$6/(INDEX(cc_input_vu_khi!$B$2:$B$11,MATCH($F$5,cc_input_vu_khi!$A$2:$A$11,0))*INDEX(cc_input_bang_xuyen_giap!$B$2:$B$7,MIN(6,MAX(1,IF(INDEX(cc_input_vu_khi_suy_ra!$B$2:$B$11,MATCH($F$5,cc_input_vu_khi_suy_ra!$A$2:$A$11,0)),MAX(1,2-(INDEX(cc_input_vu_khi!$C$2:$C$11,MATCH($F$5,cc_input_vu_khi!$A$2:$A$11,0))-Thap!$K$6)),2-(INDEX(cc_input_vu_khi!$C$2:$C$11,MATCH($F$5,cc_input_vu_khi!$A$2:$A$11,0))-Thap!$K$6))+1)))*INDEX(cc_input_vu_khi_suy_ra!$D$2:$D$11,MATCH($F$5,cc_input_vu_khi_suy_ra!$A$2:$A$11,0))),1),"")) | I5: =IF($H$5="","",IF(INDEX(cc_input_vu_khi!$B$2:$B$11,MATCH($H$5,cc_input_vu_khi!$A$2:$A$11,0))*INDEX(cc_input_bang_xuyen_giap!$B$2:$B$7,MIN(6,MAX(1,IF(INDEX(cc_input_vu_khi_suy_ra!$B$2:$B$11,MATCH($H$5,cc_input_vu_khi_suy_ra!$A$2:$A$11,0)),MAX(1,2-(INDEX(cc_input_vu_khi!$C$2:$C$11,MATCH($H$5,cc_input_vu_khi!$A$2:$A$11,0))-Thap!$K$6)),2-(INDEX(cc_input_vu_khi!$C$2:$C$11,MATCH($H$5,cc_input_vu_khi!$A$2:$A$11,0))-Thap!$K$6))+1)))*INDEX(cc_input_vu_khi_suy_ra!$D$2:$D$11,MATCH($H$5,cc_input_vu_khi_suy_ra!$A$2:$A$11,0))>0,CEILING(Thap!$J$6/(INDEX(cc_input_vu_khi!$B$2:$B$11,MATCH($H$5,cc_input_vu_khi!$A$2:$A$11,0))*INDEX(cc_input_bang_xuyen_giap!$B$2:$B$7,MIN(6,MAX(1,IF(INDEX(cc_input_vu_khi_suy_ra!$B$2:$B$11,MATCH($H$5,cc_input_vu_khi_suy_ra!$A$2:$A$11,0)),MAX(1,2-(INDEX(cc_input_vu_khi!$C$2:$C$11,MATCH($H$5,cc_input_vu_khi!$A$2:$A$11,0))-Thap!$K$6)),2-(INDEX(cc_input_vu_khi!$C$2:$C$11,MATCH($H$5,cc_input_vu_khi!$A$2:$A$11,0))-Thap!$K$6))+1)))*INDEX(cc_input_vu_khi_suy_ra!$D$2:$D$11,MATCH($H$5,cc_input_vu_khi_suy_ra!$A$2:$A$11,0))),1),"")) | J5: mlrs_rockets | K5: =IF($J$5="","",IF(INDEX(cc_input_vu_khi!$B$2:$B$11,MATCH($J$5,cc_input_vu_khi!$A$2:$A$11,0))*INDEX(cc_input_bang_xuyen_giap!$B$2:$B$7,MIN(6,MAX(1,IF(INDEX(cc_input_vu_khi_suy_ra!$B$2:$B$11,MATCH($J$5,cc_input_vu_khi_suy_ra!$A$2:$A$11,0)),MAX(1,2-(INDEX(cc_input_vu_khi!$C$2:$C$11,MATCH($J$5,cc_input_vu_khi!$A$2:$A$11,0))-Thap!$K$6)),2-(INDEX(cc_input_vu_khi!$C$2:$C$11,MATCH($J$5,cc_input_vu_khi!$A$2:$A$11,0))-Thap!$K$6))+1)))*INDEX(cc_input_vu_khi_suy_ra!$D$2:$D$11,MATCH($J$5,cc_input_vu_khi_suy_ra!$A$2:$A$11,0))>0,CEILING(Thap!$J$6/(INDEX(cc_input_vu_khi!$B$2:$B$11,MATCH($J$5,cc_input_vu_khi!$A$2:$A$11,0))*INDEX(cc_input_bang_xuyen_giap!$B$2:$B$7,MIN(6,MAX(1,IF(INDEX(cc_input_vu_khi_suy_ra!$B$2:$B$11,MATCH($J$5,cc_input_vu_khi_suy_ra!$A$2:$A$11,0)),MAX(1,2-(INDEX(cc_input_vu_khi!$C$2:$C$11,MATCH($J$5,cc_input_vu_khi!$A$2:$A$11,0))-Thap!$K$6)),2-(INDEX(cc_input_vu_khi!$C$2:$C$11,MATCH($J$5,cc_input_vu_khi!$A$2:$A$11,0))-Thap!$K$6))+1)))*INDEX(cc_input_vu_khi_suy_ra!$D$2:$D$11,MATCH($J$5,cc_input_vu_khi_suy_ra!$A$2:$A$11,0))),1),"")) | L5: Tools/balance/p32_tower_prices.py Model.price('aircraft_hangar') + threats('Medium')
A6: atgm_tower | B6: =Thap_gia_cong_thuc!$Q$6 | C6: =IF(ISNUMBER($B$6),$B$6/Thap!$BN$7,"") | D6: gun_105_wheeled | E6: =IF($D$6="","",IF(INDEX(cc_input_vu_khi!$B$2:$B$11,MATCH($D$6,cc_input_vu_khi!$A$2:$A$11,0))*INDEX(cc_input_bang_xuyen_giap!$B$2:$B$7,MIN(6,MAX(1,IF(INDEX(cc_input_vu_khi_suy_ra!$B$2:$B$11,MATCH($D$6,cc_input_vu_khi_suy_ra!$A$2:$A$11,0)),MAX(1,2-(INDEX(cc_input_vu_khi!$C$2:$C$11,MATCH($D$6,cc_input_vu_khi!$A$2:$A$11,0))-Thap!$K$7)),2-(INDEX(cc_input_vu_khi!$C$2:$C$11,MATCH($D$6,cc_input_vu_khi!$A$2:$A$11,0))-Thap!$K$7))+1)))*INDEX(cc_input_vu_khi_suy_ra!$D$2:$D$11,MATCH($D$6,cc_input_vu_khi_suy_ra!$A$2:$A$11,0))>0,CEILING(Thap!$J$7/(INDEX(cc_input_vu_khi!$B$2:$B$11,MATCH($D$6,cc_input_vu_khi!$A$2:$A$11,0))*INDEX(cc_input_bang_xuyen_giap!$B$2:$B$7,MIN(6,MAX(1,IF(INDEX(cc_input_vu_khi_suy_ra!$B$2:$B$11,MATCH($D$6,cc_input_vu_khi_suy_ra!$A$2:$A$11,0)),MAX(1,2-(INDEX(cc_input_vu_khi!$C$2:$C$11,MATCH($D$6,cc_input_vu_khi!$A$2:$A$11,0))-Thap!$K$7)),2-(INDEX(cc_input_vu_khi!$C$2:$C$11,MATCH($D$6,cc_input_vu_khi!$A$2:$A$11,0))-Thap!$K$7))+1)))*INDEX(cc_input_vu_khi_suy_ra!$D$2:$D$11,MATCH($D$6,cc_input_vu_khi_suy_ra!$A$2:$A$11,0))),1),"")) | F6: gun_105_wheeled_he | G6: =IF($F$6="","",IF(INDEX(cc_input_vu_khi!$B$2:$B$11,MATCH($F$6,cc_input_vu_khi!$A$2:$A$11,0))*INDEX(cc_input_bang_xuyen_giap!$B$2:$B$7,MIN(6,MAX(1,IF(INDEX(cc_input_vu_khi_suy_ra!$B$2:$B$11,MATCH($F$6,cc_input_vu_khi_suy_ra!$A$2:$A$11,0)),MAX(1,2-(INDEX(cc_input_vu_khi!$C$2:$C$11,MATCH($F$6,cc_input_vu_khi!$A$2:$A$11,0))-Thap!$K$7)),2-(INDEX(cc_input_vu_khi!$C$2:$C$11,MATCH($F$6,cc_input_vu_khi!$A$2:$A$11,0))-Thap!$K$7))+1)))*INDEX(cc_input_vu_khi_suy_ra!$D$2:$D$11,MATCH($F$6,cc_input_vu_khi_suy_ra!$A$2:$A$11,0))>0,CEILING(Thap!$J$7/(INDEX(cc_input_vu_khi!$B$2:$B$11,MATCH($F$6,cc_input_vu_khi!$A$2:$A$11,0))*INDEX(cc_input_bang_xuyen_giap!$B$2:$B$7,MIN(6,MAX(1,IF(INDEX(cc_input_vu_khi_suy_ra!$B$2:$B$11,MATCH($F$6,cc_input_vu_khi_suy_ra!$A$2:$A$11,0)),MAX(1,2-(INDEX(cc_input_vu_khi!$C$2:$C$11,MATCH($F$6,cc_input_vu_khi!$A$2:$A$11,0))-Thap!$K$7)),2-(INDEX(cc_input_vu_khi!$C$2:$C$11,MATCH($F$6,cc_input_vu_khi!$A$2:$A$11,0))-Thap!$K$7))+1)))*INDEX(cc_input_vu_khi_suy_ra!$D$2:$D$11,MATCH($F$6,cc_input_vu_khi_suy_ra!$A$2:$A$11,0))),1),"")) | I6: =IF($H$6="","",IF(INDEX(cc_input_vu_khi!$B$2:$B$11,MATCH($H$6,cc_input_vu_khi!$A$2:$A$11,0))*INDEX(cc_input_bang_xuyen_giap!$B$2:$B$7,MIN(6,MAX(1,IF(INDEX(cc_input_vu_khi_suy_ra!$B$2:$B$11,MATCH($H$6,cc_input_vu_khi_suy_ra!$A$2:$A$11,0)),MAX(1,2-(INDEX(cc_input_vu_khi!$C$2:$C$11,MATCH($H$6,cc_input_vu_khi!$A$2:$A$11,0))-Thap!$K$7)),2-(INDEX(cc_input_vu_khi!$C$2:$C$11,MATCH($H$6,cc_input_vu_khi!$A$2:$A$11,0))-Thap!$K$7))+1)))*INDEX(cc_input_vu_khi_suy_ra!$D$2:$D$11,MATCH($H$6,cc_input_vu_khi_suy_ra!$A$2:$A$11,0))>0,CEILING(Thap!$J$7/(INDEX(cc_input_vu_khi!$B$2:$B$11,MATCH($H$6,cc_input_vu_khi!$A$2:$A$11,0))*INDEX(cc_input_bang_xuyen_giap!$B$2:$B$7,MIN(6,MAX(1,IF(INDEX(cc_input_vu_khi_suy_ra!$B$2:$B$11,MATCH($H$6,cc_input_vu_khi_suy_ra!$A$2:$A$11,0)),MAX(1,2-(INDEX(cc_input_vu_khi!$C$2:$C$11,MATCH($H$6,cc_input_vu_khi!$A$2:$A$11,0))-Thap!$K$7)),2-(INDEX(cc_input_vu_khi!$C$2:$C$11,MATCH($H$6,cc_input_vu_khi!$A$2:$A$11,0))-Thap!$K$7))+1)))*INDEX(cc_input_vu_khi_suy_ra!$D$2:$D$11,MATCH($H$6,cc_input_vu_khi_suy_ra!$A$2:$A$11,0))),1),"")) | J6: mlrs_rockets | K6: =IF($J$6="","",IF(INDEX(cc_input_vu_khi!$B$2:$B$11,MATCH($J$6,cc_input_vu_khi!$A$2:$A$11,0))*INDEX(cc_input_bang_xuyen_giap!$B$2:$B$7,MIN(6,MAX(1,IF(INDEX(cc_input_vu_khi_suy_ra!$B$2:$B$11,MATCH($J$6,cc_input_vu_khi_suy_ra!$A$2:$A$11,0)),MAX(1,2-(INDEX(cc_input_vu_khi!$C$2:$C$11,MATCH($J$6,cc_input_vu_khi!$A$2:$A$11,0))-Thap!$K$7)),2-(INDEX(cc_input_vu_khi!$C$2:$C$11,MATCH($J$6,cc_input_vu_khi!$A$2:$A$11,0))-Thap!$K$7))+1)))*INDEX(cc_input_vu_khi_suy_ra!$D$2:$D$11,MATCH($J$6,cc_input_vu_khi_suy_ra!$A$2:$A$11,0))>0,CEILING(Thap!$J$7/(INDEX(cc_input_vu_khi!$B$2:$B$11,MATCH($J$6,cc_input_vu_khi!$A$2:$A$11,0))*INDEX(cc_input_bang_xuyen_giap!$B$2:$B$7,MIN(6,MAX(1,IF(INDEX(cc_input_vu_khi_suy_ra!$B$2:$B$11,MATCH($J$6,cc_input_vu_khi_suy_ra!$A$2:$A$11,0)),MAX(1,2-(INDEX(cc_input_vu_khi!$C$2:$C$11,MATCH($J$6,cc_input_vu_khi!$A$2:$A$11,0))-Thap!$K$7)),2-(INDEX(cc_input_vu_khi!$C$2:$C$11,MATCH($J$6,cc_input_vu_khi!$A$2:$A$11,0))-Thap!$K$7))+1)))*INDEX(cc_input_vu_khi_suy_ra!$D$2:$D$11,MATCH($J$6,cc_input_vu_khi_suy_ra!$A$2:$A$11,0))),1),"")) | L6: Tools/balance/p32_tower_prices.py Model.price('atgm_tower') + threats('Medium')
A7: atgm_tower.multi | B7: =Thap_gia_cong_thuc!$Q$7 | C7: =IF(ISNUMBER($B$7),$B$7/Thap!$BN$8,"") | D7: gun_105_wheeled | E7: =IF($D$7="","",IF(INDEX(cc_input_vu_khi!$B$2:$B$11,MATCH($D$7,cc_input_vu_khi!$A$2:$A$11,0))*INDEX(cc_input_bang_xuyen_giap!$B$2:$B$7,MIN(6,MAX(1,IF(INDEX(cc_input_vu_khi_suy_ra!$B$2:$B$11,MATCH($D$7,cc_input_vu_khi_suy_ra!$A$2:$A$11,0)),MAX(1,2-(INDEX(cc_input_vu_khi!$C$2:$C$11,MATCH($D$7,cc_input_vu_khi!$A$2:$A$11,0))-Thap!$K$8)),2-(INDEX(cc_input_vu_khi!$C$2:$C$11,MATCH($D$7,cc_input_vu_khi!$A$2:$A$11,0))-Thap!$K$8))+1)))*INDEX(cc_input_vu_khi_suy_ra!$D$2:$D$11,MATCH($D$7,cc_input_vu_khi_suy_ra!$A$2:$A$11,0))>0,CEILING(Thap!$J$8/(INDEX(cc_input_vu_khi!$B$2:$B$11,MATCH($D$7,cc_input_vu_khi!$A$2:$A$11,0))*INDEX(cc_input_bang_xuyen_giap!$B$2:$B$7,MIN(6,MAX(1,IF(INDEX(cc_input_vu_khi_suy_ra!$B$2:$B$11,MATCH($D$7,cc_input_vu_khi_suy_ra!$A$2:$A$11,0)),MAX(1,2-(INDEX(cc_input_vu_khi!$C$2:$C$11,MATCH($D$7,cc_input_vu_khi!$A$2:$A$11,0))-Thap!$K$8)),2-(INDEX(cc_input_vu_khi!$C$2:$C$11,MATCH($D$7,cc_input_vu_khi!$A$2:$A$11,0))-Thap!$K$8))+1)))*INDEX(cc_input_vu_khi_suy_ra!$D$2:$D$11,MATCH($D$7,cc_input_vu_khi_suy_ra!$A$2:$A$11,0))),1),"")) | F7: gun_105_wheeled_he | G7: =IF($F$7="","",IF(INDEX(cc_input_vu_khi!$B$2:$B$11,MATCH($F$7,cc_input_vu_khi!$A$2:$A$11,0))*INDEX(cc_input_bang_xuyen_giap!$B$2:$B$7,MIN(6,MAX(1,IF(INDEX(cc_input_vu_khi_suy_ra!$B$2:$B$11,MATCH($F$7,cc_input_vu_khi_suy_ra!$A$2:$A$11,0)),MAX(1,2-(INDEX(cc_input_vu_khi!$C$2:$C$11,MATCH($F$7,cc_input_vu_khi!$A$2:$A$11,0))-Thap!$K$8)),2-(INDEX(cc_input_vu_khi!$C$2:$C$11,MATCH($F$7,cc_input_vu_khi!$A$2:$A$11,0))-Thap!$K$8))+1)))*INDEX(cc_input_vu_khi_suy_ra!$D$2:$D$11,MATCH($F$7,cc_input_vu_khi_suy_ra!$A$2:$A$11,0))>0,CEILING(Thap!$J$8/(INDEX(cc_input_vu_khi!$B$2:$B$11,MATCH($F$7,cc_input_vu_khi!$A$2:$A$11,0))*INDEX(cc_input_bang_xuyen_giap!$B$2:$B$7,MIN(6,MAX(1,IF(INDEX(cc_input_vu_khi_suy_ra!$B$2:$B$11,MATCH($F$7,cc_input_vu_khi_suy_ra!$A$2:$A$11,0)),MAX(1,2-(INDEX(cc_input_vu_khi!$C$2:$C$11,MATCH($F$7,cc_input_vu_khi!$A$2:$A$11,0))-Thap!$K$8)),2-(INDEX(cc_input_vu_khi!$C$2:$C$11,MATCH($F$7,cc_input_vu_khi!$A$2:$A$11,0))-Thap!$K$8))+1)))*INDEX(cc_input_vu_khi_suy_ra!$D$2:$D$11,MATCH($F$7,cc_input_vu_khi_suy_ra!$A$2:$A$11,0))),1),"")) | I7: =IF($H$7="","",IF(INDEX(cc_input_vu_khi!$B$2:$B$11,MATCH($H$7,cc_input_vu_khi!$A$2:$A$11,0))*INDEX(cc_input_bang_xuyen_giap!$B$2:$B$7,MIN(6,MAX(1,IF(INDEX(cc_input_vu_khi_suy_ra!$B$2:$B$11,MATCH($H$7,cc_input_vu_khi_suy_ra!$A$2:$A$11,0)),MAX(1,2-(INDEX(cc_input_vu_khi!$C$2:$C$11,MATCH($H$7,cc_input_vu_khi!$A$2:$A$11,0))-Thap!$K$8)),2-(INDEX(cc_input_vu_khi!$C$2:$C$11,MATCH($H$7,cc_input_vu_khi!$A$2:$A$11,0))-Thap!$K$8))+1)))*INDEX(cc_input_vu_khi_suy_ra!$D$2:$D$11,MATCH($H$7,cc_input_vu_khi_suy_ra!$A$2:$A$11,0))>0,CEILING(Thap!$J$8/(INDEX(cc_input_vu_khi!$B$2:$B$11,MATCH($H$7,cc_input_vu_khi!$A$2:$A$11,0))*INDEX(cc_input_bang_xuyen_giap!$B$2:$B$7,MIN(6,MAX(1,IF(INDEX(cc_input_vu_khi_suy_ra!$B$2:$B$11,MATCH($H$7,cc_input_vu_khi_suy_ra!$A$2:$A$11,0)),MAX(1,2-(INDEX(cc_input_vu_khi!$C$2:$C$11,MATCH($H$7,cc_input_vu_khi!$A$2:$A$11,0))-Thap!$K$8)),2-(INDEX(cc_input_vu_khi!$C$2:$C$11,MATCH($H$7,cc_input_vu_khi!$A$2:$A$11,0))-Thap!$K$8))+1)))*INDEX(cc_input_vu_khi_suy_ra!$D$2:$D$11,MATCH($H$7,cc_input_vu_khi_suy_ra!$A$2:$A$11,0))),1),"")) | J7: mlrs_rockets | K7: =IF($J$7="","",IF(INDEX(cc_input_vu_khi!$B$2:$B$11,MATCH($J$7,cc_input_vu_khi!$A$2:$A$11,0))*INDEX(cc_input_bang_xuyen_giap!$B$2:$B$7,MIN(6,MAX(1,IF(INDEX(cc_input_vu_khi_suy_ra!$B$2:$B$11,MATCH($J$7,cc_input_vu_khi_suy_ra!$A$2:$A$11,0)),MAX(1,2-(INDEX(cc_input_vu_khi!$C$2:$C$11,MATCH($J$7,cc_input_vu_khi!$A$2:$A$11,0))-Thap!$K$8)),2-(INDEX(cc_input_vu_khi!$C$2:$C$11,MATCH($J$7,cc_input_vu_khi!$A$2:$A$11,0))-Thap!$K$8))+1)))*INDEX(cc_input_vu_khi_suy_ra!$D$2:$D$11,MATCH($J$7,cc_input_vu_khi_suy_ra!$A$2:$A$11,0))>0,CEILING(Thap!$J$8/(INDEX(cc_input_vu_khi!$B$2:$B$11,MATCH($J$7,cc_input_vu_khi!$A$2:$A$11,0))*INDEX(cc_input_bang_xuyen_giap!$B$2:$B$7,MIN(6,MAX(1,IF(INDEX(cc_input_vu_khi_suy_ra!$B$2:$B$11,MATCH($J$7,cc_input_vu_khi_suy_ra!$A$2:$A$11,0)),MAX(1,2-(INDEX(cc_input_vu_khi!$C$2:$C$11,MATCH($J$7,cc_input_vu_khi!$A$2:$A$11,0))-Thap!$K$8)),2-(INDEX(cc_input_vu_khi!$C$2:$C$11,MATCH($J$7,cc_input_vu_khi!$A$2:$A$11,0))-Thap!$K$8))+1)))*INDEX(cc_input_vu_khi_suy_ra!$D$2:$D$11,MATCH($J$7,cc_input_vu_khi_suy_ra!$A$2:$A$11,0))),1),"")) | L7: Tools/balance/p32_tower_prices.py Model.price('atgm_tower.multi') + threats('Medium')
A8: atgm_tower.top | B8: =Thap_gia_cong_thuc!$Q$8 | C8: =IF(ISNUMBER($B$8),$B$8/Thap!$BN$9,"") | D8: gun_105_wheeled | E8: =IF($D$8="","",IF(INDEX(cc_input_vu_khi!$B$2:$B$11,MATCH($D$8,cc_input_vu_khi!$A$2:$A$11,0))*INDEX(cc_input_bang_xuyen_giap!$B$2:$B$7,MIN(6,MAX(1,IF(INDEX(cc_input_vu_khi_suy_ra!$B$2:$B$11,MATCH($D$8,cc_input_vu_khi_suy_ra!$A$2:$A$11,0)),MAX(1,2-(INDEX(cc_input_vu_khi!$C$2:$C$11,MATCH($D$8,cc_input_vu_khi!$A$2:$A$11,0))-Thap!$K$9)),2-(INDEX(cc_input_vu_khi!$C$2:$C$11,MATCH($D$8,cc_input_vu_khi!$A$2:$A$11,0))-Thap!$K$9))+1)))*INDEX(cc_input_vu_khi_suy_ra!$D$2:$D$11,MATCH($D$8,cc_input_vu_khi_suy_ra!$A$2:$A$11,0))>0,CEILING(Thap!$J$9/(INDEX(cc_input_vu_khi!$B$2:$B$11,MATCH($D$8,cc_input_vu_khi!$A$2:$A$11,0))*INDEX(cc_input_bang_xuyen_giap!$B$2:$B$7,MIN(6,MAX(1,IF(INDEX(cc_input_vu_khi_suy_ra!$B$2:$B$11,MATCH($D$8,cc_input_vu_khi_suy_ra!$A$2:$A$11,0)),MAX(1,2-(INDEX(cc_input_vu_khi!$C$2:$C$11,MATCH($D$8,cc_input_vu_khi!$A$2:$A$11,0))-Thap!$K$9)),2-(INDEX(cc_input_vu_khi!$C$2:$C$11,MATCH($D$8,cc_input_vu_khi!$A$2:$A$11,0))-Thap!$K$9))+1)))*INDEX(cc_input_vu_khi_suy_ra!$D$2:$D$11,MATCH($D$8,cc_input_vu_khi_suy_ra!$A$2:$A$11,0))),1),"")) | F8: gun_105_wheeled_he | G8: =IF($F$8="","",IF(INDEX(cc_input_vu_khi!$B$2:$B$11,MATCH($F$8,cc_input_vu_khi!$A$2:$A$11,0))*INDEX(cc_input_bang_xuyen_giap!$B$2:$B$7,MIN(6,MAX(1,IF(INDEX(cc_input_vu_khi_suy_ra!$B$2:$B$11,MATCH($F$8,cc_input_vu_khi_suy_ra!$A$2:$A$11,0)),MAX(1,2-(INDEX(cc_input_vu_khi!$C$2:$C$11,MATCH($F$8,cc_input_vu_khi!$A$2:$A$11,0))-Thap!$K$9)),2-(INDEX(cc_input_vu_khi!$C$2:$C$11,MATCH($F$8,cc_input_vu_khi!$A$2:$A$11,0))-Thap!$K$9))+1)))*INDEX(cc_input_vu_khi_suy_ra!$D$2:$D$11,MATCH($F$8,cc_input_vu_khi_suy_ra!$A$2:$A$11,0))>0,CEILING(Thap!$J$9/(INDEX(cc_input_vu_khi!$B$2:$B$11,MATCH($F$8,cc_input_vu_khi!$A$2:$A$11,0))*INDEX(cc_input_bang_xuyen_giap!$B$2:$B$7,MIN(6,MAX(1,IF(INDEX(cc_input_vu_khi_suy_ra!$B$2:$B$11,MATCH($F$8,cc_input_vu_khi_suy_ra!$A$2:$A$11,0)),MAX(1,2-(INDEX(cc_input_vu_khi!$C$2:$C$11,MATCH($F$8,cc_input_vu_khi!$A$2:$A$11,0))-Thap!$K$9)),2-(INDEX(cc_input_vu_khi!$C$2:$C$11,MATCH($F$8,cc_input_vu_khi!$A$2:$A$11,0))-Thap!$K$9))+1)))*INDEX(cc_input_vu_khi_suy_ra!$D$2:$D$11,MATCH($F$8,cc_input_vu_khi_suy_ra!$A$2:$A$11,0))),1),"")) | I8: =IF($H$8="","",IF(INDEX(cc_input_vu_khi!$B$2:$B$11,MATCH($H$8,cc_input_vu_khi!$A$2:$A$11,0))*INDEX(cc_input_bang_xuyen_giap!$B$2:$B$7,MIN(6,MAX(1,IF(INDEX(cc_input_vu_khi_suy_ra!$B$2:$B$11,MATCH($H$8,cc_input_vu_khi_suy_ra!$A$2:$A$11,0)),MAX(1,2-(INDEX(cc_input_vu_khi!$C$2:$C$11,MATCH($H$8,cc_input_vu_khi!$A$2:$A$11,0))-Thap!$K$9)),2-(INDEX(cc_input_vu_khi!$C$2:$C$11,MATCH($H$8,cc_input_vu_khi!$A$2:$A$11,0))-Thap!$K$9))+1)))*INDEX(cc_input_vu_khi_suy_ra!$D$2:$D$11,MATCH($H$8,cc_input_vu_khi_suy_ra!$A$2:$A$11,0))>0,CEILING(Thap!$J$9/(INDEX(cc_input_vu_khi!$B$2:$B$11,MATCH($H$8,cc_input_vu_khi!$A$2:$A$11,0))*INDEX(cc_input_bang_xuyen_giap!$B$2:$B$7,MIN(6,MAX(1,IF(INDEX(cc_input_vu_khi_suy_ra!$B$2:$B$11,MATCH($H$8,cc_input_vu_khi_suy_ra!$A$2:$A$11,0)),MAX(1,2-(INDEX(cc_input_vu_khi!$C$2:$C$11,MATCH($H$8,cc_input_vu_khi!$A$2:$A$11,0))-Thap!$K$9)),2-(INDEX(cc_input_vu_khi!$C$2:$C$11,MATCH($H$8,cc_input_vu_khi!$A$2:$A$11,0))-Thap!$K$9))+1)))*INDEX(cc_input_vu_khi_suy_ra!$D$2:$D$11,MATCH($H$8,cc_input_vu_khi_suy_ra!$A$2:$A$11,0))),1),"")) | J8: mlrs_rockets | K8: =IF($J$8="","",IF(INDEX(cc_input_vu_khi!$B$2:$B$11,MATCH($J$8,cc_input_vu_khi!$A$2:$A$11,0))*INDEX(cc_input_bang_xuyen_giap!$B$2:$B$7,MIN(6,MAX(1,IF(INDEX(cc_input_vu_khi_suy_ra!$B$2:$B$11,MATCH($J$8,cc_input_vu_khi_suy_ra!$A$2:$A$11,0)),MAX(1,2-(INDEX(cc_input_vu_khi!$C$2:$C$11,MATCH($J$8,cc_input_vu_khi!$A$2:$A$11,0))-Thap!$K$9)),2-(INDEX(cc_input_vu_khi!$C$2:$C$11,MATCH($J$8,cc_input_vu_khi!$A$2:$A$11,0))-Thap!$K$9))+1)))*INDEX(cc_input_vu_khi_suy_ra!$D$2:$D$11,MATCH($J$8,cc_input_vu_khi_suy_ra!$A$2:$A$11,0))>0,CEILING(Thap!$J$9/(INDEX(cc_input_vu_khi!$B$2:$B$11,MATCH($J$8,cc_input_vu_khi!$A$2:$A$11,0))*INDEX(cc_input_bang_xuyen_giap!$B$2:$B$7,MIN(6,MAX(1,IF(INDEX(cc_input_vu_khi_suy_ra!$B$2:$B$11,MATCH($J$8,cc_input_vu_khi_suy_ra!$A$2:$A$11,0)),MAX(1,2-(INDEX(cc_input_vu_khi!$C$2:$C$11,MATCH($J$8,cc_input_vu_khi!$A$2:$A$11,0))-Thap!$K$9)),2-(INDEX(cc_input_vu_khi!$C$2:$C$11,MATCH($J$8,cc_input_vu_khi!$A$2:$A$11,0))-Thap!$K$9))+1)))*INDEX(cc_input_vu_khi_suy_ra!$D$2:$D$11,MATCH($J$8,cc_input_vu_khi_suy_ra!$A$2:$A$11,0))),1),"")) | L8: Tools/balance/p32_tower_prices.py Model.price('atgm_tower.top') + threats('Medium')
A9: c_ram | B9: =Thap_gia_cong_thuc!$Q$9 | C9: =IF(ISNUMBER($B$9),$B$9/Thap!$BN$14,"") | D9: gun_105_wheeled | E9: =IF($D$9="","",IF(INDEX(cc_input_vu_khi!$B$2:$B$11,MATCH($D$9,cc_input_vu_khi!$A$2:$A$11,0))*INDEX(cc_input_bang_xuyen_giap!$B$2:$B$7,MIN(6,MAX(1,IF(INDEX(cc_input_vu_khi_suy_ra!$B$2:$B$11,MATCH($D$9,cc_input_vu_khi_suy_ra!$A$2:$A$11,0)),MAX(1,2-(INDEX(cc_input_vu_khi!$C$2:$C$11,MATCH($D$9,cc_input_vu_khi!$A$2:$A$11,0))-Thap!$K$14)),2-(INDEX(cc_input_vu_khi!$C$2:$C$11,MATCH($D$9,cc_input_vu_khi!$A$2:$A$11,0))-Thap!$K$14))+1)))*INDEX(cc_input_vu_khi_suy_ra!$D$2:$D$11,MATCH($D$9,cc_input_vu_khi_suy_ra!$A$2:$A$11,0))>0,CEILING(Thap!$J$14/(INDEX(cc_input_vu_khi!$B$2:$B$11,MATCH($D$9,cc_input_vu_khi!$A$2:$A$11,0))*INDEX(cc_input_bang_xuyen_giap!$B$2:$B$7,MIN(6,MAX(1,IF(INDEX(cc_input_vu_khi_suy_ra!$B$2:$B$11,MATCH($D$9,cc_input_vu_khi_suy_ra!$A$2:$A$11,0)),MAX(1,2-(INDEX(cc_input_vu_khi!$C$2:$C$11,MATCH($D$9,cc_input_vu_khi!$A$2:$A$11,0))-Thap!$K$14)),2-(INDEX(cc_input_vu_khi!$C$2:$C$11,MATCH($D$9,cc_input_vu_khi!$A$2:$A$11,0))-Thap!$K$14))+1)))*INDEX(cc_input_vu_khi_suy_ra!$D$2:$D$11,MATCH($D$9,cc_input_vu_khi_suy_ra!$A$2:$A$11,0))),1),"")) | F9: gun_105_wheeled_he | G9: =IF($F$9="","",IF(INDEX(cc_input_vu_khi!$B$2:$B$11,MATCH($F$9,cc_input_vu_khi!$A$2:$A$11,0))*INDEX(cc_input_bang_xuyen_giap!$B$2:$B$7,MIN(6,MAX(1,IF(INDEX(cc_input_vu_khi_suy_ra!$B$2:$B$11,MATCH($F$9,cc_input_vu_khi_suy_ra!$A$2:$A$11,0)),MAX(1,2-(INDEX(cc_input_vu_khi!$C$2:$C$11,MATCH($F$9,cc_input_vu_khi!$A$2:$A$11,0))-Thap!$K$14)),2-(INDEX(cc_input_vu_khi!$C$2:$C$11,MATCH($F$9,cc_input_vu_khi!$A$2:$A$11,0))-Thap!$K$14))+1)))*INDEX(cc_input_vu_khi_suy_ra!$D$2:$D$11,MATCH($F$9,cc_input_vu_khi_suy_ra!$A$2:$A$11,0))>0,CEILING(Thap!$J$14/(INDEX(cc_input_vu_khi!$B$2:$B$11,MATCH($F$9,cc_input_vu_khi!$A$2:$A$11,0))*INDEX(cc_input_bang_xuyen_giap!$B$2:$B$7,MIN(6,MAX(1,IF(INDEX(cc_input_vu_khi_suy_ra!$B$2:$B$11,MATCH($F$9,cc_input_vu_khi_suy_ra!$A$2:$A$11,0)),MAX(1,2-(INDEX(cc_input_vu_khi!$C$2:$C$11,MATCH($F$9,cc_input_vu_khi!$A$2:$A$11,0))-Thap!$K$14)),2-(INDEX(cc_input_vu_khi!$C$2:$C$11,MATCH($F$9,cc_input_vu_khi!$A$2:$A$11,0))-Thap!$K$14))+1)))*INDEX(cc_input_vu_khi_suy_ra!$D$2:$D$11,MATCH($F$9,cc_input_vu_khi_suy_ra!$A$2:$A$11,0))),1),"")) | I9: =IF($H$9="","",IF(INDEX(cc_input_vu_khi!$B$2:$B$11,MATCH($H$9,cc_input_vu_khi!$A$2:$A$11,0))*INDEX(cc_input_bang_xuyen_giap!$B$2:$B$7,MIN(6,MAX(1,IF(INDEX(cc_input_vu_khi_suy_ra!$B$2:$B$11,MATCH($H$9,cc_input_vu_khi_suy_ra!$A$2:$A$11,0)),MAX(1,2-(INDEX(cc_input_vu_khi!$C$2:$C$11,MATCH($H$9,cc_input_vu_khi!$A$2:$A$11,0))-Thap!$K$14)),2-(INDEX(cc_input_vu_khi!$C$2:$C$11,MATCH($H$9,cc_input_vu_khi!$A$2:$A$11,0))-Thap!$K$14))+1)))*INDEX(cc_input_vu_khi_suy_ra!$D$2:$D$11,MATCH($H$9,cc_input_vu_khi_suy_ra!$A$2:$A$11,0))>0,CEILING(Thap!$J$14/(INDEX(cc_input_vu_khi!$B$2:$B$11,MATCH($H$9,cc_input_vu_khi!$A$2:$A$11,0))*INDEX(cc_input_bang_xuyen_giap!$B$2:$B$7,MIN(6,MAX(1,IF(INDEX(cc_input_vu_khi_suy_ra!$B$2:$B$11,MATCH($H$9,cc_input_vu_khi_suy_ra!$A$2:$A$11,0)),MAX(1,2-(INDEX(cc_input_vu_khi!$C$2:$C$11,MATCH($H$9,cc_input_vu_khi!$A$2:$A$11,0))-Thap!$K$14)),2-(INDEX(cc_input_vu_khi!$C$2:$C$11,MATCH($H$9,cc_input_vu_khi!$A$2:$A$11,0))-Thap!$K$14))+1)))*INDEX(cc_input_vu_khi_suy_ra!$D$2:$D$11,MATCH($H$9,cc_input_vu_khi_suy_ra!$A$2:$A$11,0))),1),"")) | J9: mlrs_rockets | K9: =IF($J$9="","",IF(INDEX(cc_input_vu_khi!$B$2:$B$11,MATCH($J$9,cc_input_vu_khi!$A$2:$A$11,0))*INDEX(cc_input_bang_xuyen_giap!$B$2:$B$7,MIN(6,MAX(1,IF(INDEX(cc_input_vu_khi_suy_ra!$B$2:$B$11,MATCH($J$9,cc_input_vu_khi_suy_ra!$A$2:$A$11,0)),MAX(1,2-(INDEX(cc_input_vu_khi!$C$2:$C$11,MATCH($J$9,cc_input_vu_khi!$A$2:$A$11,0))-Thap!$K$14)),2-(INDEX(cc_input_vu_khi!$C$2:$C$11,MATCH($J$9,cc_input_vu_khi!$A$2:$A$11,0))-Thap!$K$14))+1)))*INDEX(cc_input_vu_khi_suy_ra!$D$2:$D$11,MATCH($J$9,cc_input_vu_khi_suy_ra!$A$2:$A$11,0))>0,CEILING(Thap!$J$14/(INDEX(cc_input_vu_khi!$B$2:$B$11,MATCH($J$9,cc_input_vu_khi!$A$2:$A$11,0))*INDEX(cc_input_bang_xuyen_giap!$B$2:$B$7,MIN(6,MAX(1,IF(INDEX(cc_input_vu_khi_suy_ra!$B$2:$B$11,MATCH($J$9,cc_input_vu_khi_suy_ra!$A$2:$A$11,0)),MAX(1,2-(INDEX(cc_input_vu_khi!$C$2:$C$11,MATCH($J$9,cc_input_vu_khi!$A$2:$A$11,0))-Thap!$K$14)),2-(INDEX(cc_input_vu_khi!$C$2:$C$11,MATCH($J$9,cc_input_vu_khi!$A$2:$A$11,0))-Thap!$K$14))+1)))*INDEX(cc_input_vu_khi_suy_ra!$D$2:$D$11,MATCH($J$9,cc_input_vu_khi_suy_ra!$A$2:$A$11,0))),1),"")) | L9: Tools/balance/p32_tower_prices.py Model.price('c_ram') + threats('Medium')
A10: c_ram.centurion | B10: =Thap_gia_cong_thuc!$Q$10 | C10: =IF(ISNUMBER($B$10),$B$10/Thap!$BN$15,"") | D10: gun_105_wheeled | E10: =IF($D$10="","",IF(INDEX(cc_input_vu_khi!$B$2:$B$11,MATCH($D$10,cc_input_vu_khi!$A$2:$A$11,0))*INDEX(cc_input_bang_xuyen_giap!$B$2:$B$7,MIN(6,MAX(1,IF(INDEX(cc_input_vu_khi_suy_ra!$B$2:$B$11,MATCH($D$10,cc_input_vu_khi_suy_ra!$A$2:$A$11,0)),MAX(1,2-(INDEX(cc_input_vu_khi!$C$2:$C$11,MATCH($D$10,cc_input_vu_khi!$A$2:$A$11,0))-Thap!$K$15)),2-(INDEX(cc_input_vu_khi!$C$2:$C$11,MATCH($D$10,cc_input_vu_khi!$A$2:$A$11,0))-Thap!$K$15))+1)))*INDEX(cc_input_vu_khi_suy_ra!$D$2:$D$11,MATCH($D$10,cc_input_vu_khi_suy_ra!$A$2:$A$11,0))>0,CEILING(Thap!$J$15/(INDEX(cc_input_vu_khi!$B$2:$B$11,MATCH($D$10,cc_input_vu_khi!$A$2:$A$11,0))*INDEX(cc_input_bang_xuyen_giap!$B$2:$B$7,MIN(6,MAX(1,IF(INDEX(cc_input_vu_khi_suy_ra!$B$2:$B$11,MATCH($D$10,cc_input_vu_khi_suy_ra!$A$2:$A$11,0)),MAX(1,2-(INDEX(cc_input_vu_khi!$C$2:$C$11,MATCH($D$10,cc_input_vu_khi!$A$2:$A$11,0))-Thap!$K$15)),2-(INDEX(cc_input_vu_khi!$C$2:$C$11,MATCH($D$10,cc_input_vu_khi!$A$2:$A$11,0))-Thap!$K$15))+1)))*INDEX(cc_input_vu_khi_suy_ra!$D$2:$D$11,MATCH($D$10,cc_input_vu_khi_suy_ra!$A$2:$A$11,0))),1),"")) | F10: gun_105_wheeled_he | G10: =IF($F$10="","",IF(INDEX(cc_input_vu_khi!$B$2:$B$11,MATCH($F$10,cc_input_vu_khi!$A$2:$A$11,0))*INDEX(cc_input_bang_xuyen_giap!$B$2:$B$7,MIN(6,MAX(1,IF(INDEX(cc_input_vu_khi_suy_ra!$B$2:$B$11,MATCH($F$10,cc_input_vu_khi_suy_ra!$A$2:$A$11,0)),MAX(1,2-(INDEX(cc_input_vu_khi!$C$2:$C$11,MATCH($F$10,cc_input_vu_khi!$A$2:$A$11,0))-Thap!$K$15)),2-(INDEX(cc_input_vu_khi!$C$2:$C$11,MATCH($F$10,cc_input_vu_khi!$A$2:$A$11,0))-Thap!$K$15))+1)))*INDEX(cc_input_vu_khi_suy_ra!$D$2:$D$11,MATCH($F$10,cc_input_vu_khi_suy_ra!$A$2:$A$11,0))>0,CEILING(Thap!$J$15/(INDEX(cc_input_vu_khi!$B$2:$B$11,MATCH($F$10,cc_input_vu_khi!$A$2:$A$11,0))*INDEX(cc_input_bang_xuyen_giap!$B$2:$B$7,MIN(6,MAX(1,IF(INDEX(cc_input_vu_khi_suy_ra!$B$2:$B$11,MATCH($F$10,cc_input_vu_khi_suy_ra!$A$2:$A$11,0)),MAX(1,2-(INDEX(cc_input_vu_khi!$C$2:$C$11,MATCH($F$10,cc_input_vu_khi!$A$2:$A$11,0))-Thap!$K$15)),2-(INDEX(cc_input_vu_khi!$C$2:$C$11,MATCH($F$10,cc_input_vu_khi!$A$2:$A$11,0))-Thap!$K$15))+1)))*INDEX(cc_input_vu_khi_suy_ra!$D$2:$D$11,MATCH($F$10,cc_input_vu_khi_suy_ra!$A$2:$A$11,0))),1),"")) | I10: =IF($H$10="","",IF(INDEX(cc_input_vu_khi!$B$2:$B$11,MATCH($H$10,cc_input_vu_khi!$A$2:$A$11,0))*INDEX(cc_input_bang_xuyen_giap!$B$2:$B$7,MIN(6,MAX(1,IF(INDEX(cc_input_vu_khi_suy_ra!$B$2:$B$11,MATCH($H$10,cc_input_vu_khi_suy_ra!$A$2:$A$11,0)),MAX(1,2-(INDEX(cc_input_vu_khi!$C$2:$C$11,MATCH($H$10,cc_input_vu_khi!$A$2:$A$11,0))-Thap!$K$15)),2-(INDEX(cc_input_vu_khi!$C$2:$C$11,MATCH($H$10,cc_input_vu_khi!$A$2:$A$11,0))-Thap!$K$15))+1)))*INDEX(cc_input_vu_khi_suy_ra!$D$2:$D$11,MATCH($H$10,cc_input_vu_khi_suy_ra!$A$2:$A$11,0))>0,CEILING(Thap!$J$15/(INDEX(cc_input_vu_khi!$B$2:$B$11,MATCH($H$10,cc_input_vu_khi!$A$2:$A$11,0))*INDEX(cc_input_bang_xuyen_giap!$B$2:$B$7,MIN(6,MAX(1,IF(INDEX(cc_input_vu_khi_suy_ra!$B$2:$B$11,MATCH($H$10,cc_input_vu_khi_suy_ra!$A$2:$A$11,0)),MAX(1,2-(INDEX(cc_input_vu_khi!$C$2:$C$11,MATCH($H$10,cc_input_vu_khi!$A$2:$A$11,0))-Thap!$K$15)),2-(INDEX(cc_input_vu_khi!$C$2:$C$11,MATCH($H$10,cc_input_vu_khi!$A$2:$A$11,0))-Thap!$K$15))+1)))*INDEX(cc_input_vu_khi_suy_ra!$D$2:$D$11,MATCH($H$10,cc_input_vu_khi_suy_ra!$A$2:$A$11,0))),1),"")) | J10: mlrs_rockets | K10: =IF($J$10="","",IF(INDEX(cc_input_vu_khi!$B$2:$B$11,MATCH($J$10,cc_input_vu_khi!$A$2:$A$11,0))*INDEX(cc_input_bang_xuyen_giap!$B$2:$B$7,MIN(6,MAX(1,IF(INDEX(cc_input_vu_khi_suy_ra!$B$2:$B$11,MATCH($J$10,cc_input_vu_khi_suy_ra!$A$2:$A$11,0)),MAX(1,2-(INDEX(cc_input_vu_khi!$C$2:$C$11,MATCH($J$10,cc_input_vu_khi!$A$2:$A$11,0))-Thap!$K$15)),2-(INDEX(cc_input_vu_khi!$C$2:$C$11,MATCH($J$10,cc_input_vu_khi!$A$2:$A$11,0))-Thap!$K$15))+1)))*INDEX(cc_input_vu_khi_suy_ra!$D$2:$D$11,MATCH($J$10,cc_input_vu_khi_suy_ra!$A$2:$A$11,0))>0,CEILING(Thap!$J$15/(INDEX(cc_input_vu_khi!$B$2:$B$11,MATCH($J$10,cc_input_vu_khi!$A$2:$A$11,0))*INDEX(cc_input_bang_xuyen_giap!$B$2:$B$7,MIN(6,MAX(1,IF(INDEX(cc_input_vu_khi_suy_ra!$B$2:$B$11,MATCH($J$10,cc_input_vu_khi_suy_ra!$A$2:$A$11,0)),MAX(1,2-(INDEX(cc_input_vu_khi!$C$2:$C$11,MATCH($J$10,cc_input_vu_khi!$A$2:$A$11,0))-Thap!$K$15)),2-(INDEX(cc_input_vu_khi!$C$2:$C$11,MATCH($J$10,cc_input_vu_khi!$A$2:$A$11,0))-Thap!$K$15))+1)))*INDEX(cc_input_vu_khi_suy_ra!$D$2:$D$11,MATCH($J$10,cc_input_vu_khi_suy_ra!$A$2:$A$11,0))),1),"")) | L10: Tools/balance/p32_tower_prices.py Model.price('c_ram.centurion') + threats('Medium')
A11: c_ram.dome | B11: =Thap_gia_cong_thuc!$Q$11 | C11: =IF(ISNUMBER($B$11),$B$11/Thap!$BN$16,"") | D11: gun_105_wheeled | E11: =IF($D$11="","",IF(INDEX(cc_input_vu_khi!$B$2:$B$11,MATCH($D$11,cc_input_vu_khi!$A$2:$A$11,0))*INDEX(cc_input_bang_xuyen_giap!$B$2:$B$7,MIN(6,MAX(1,IF(INDEX(cc_input_vu_khi_suy_ra!$B$2:$B$11,MATCH($D$11,cc_input_vu_khi_suy_ra!$A$2:$A$11,0)),MAX(1,2-(INDEX(cc_input_vu_khi!$C$2:$C$11,MATCH($D$11,cc_input_vu_khi!$A$2:$A$11,0))-Thap!$K$16)),2-(INDEX(cc_input_vu_khi!$C$2:$C$11,MATCH($D$11,cc_input_vu_khi!$A$2:$A$11,0))-Thap!$K$16))+1)))*INDEX(cc_input_vu_khi_suy_ra!$D$2:$D$11,MATCH($D$11,cc_input_vu_khi_suy_ra!$A$2:$A$11,0))>0,CEILING(Thap!$J$16/(INDEX(cc_input_vu_khi!$B$2:$B$11,MATCH($D$11,cc_input_vu_khi!$A$2:$A$11,0))*INDEX(cc_input_bang_xuyen_giap!$B$2:$B$7,MIN(6,MAX(1,IF(INDEX(cc_input_vu_khi_suy_ra!$B$2:$B$11,MATCH($D$11,cc_input_vu_khi_suy_ra!$A$2:$A$11,0)),MAX(1,2-(INDEX(cc_input_vu_khi!$C$2:$C$11,MATCH($D$11,cc_input_vu_khi!$A$2:$A$11,0))-Thap!$K$16)),2-(INDEX(cc_input_vu_khi!$C$2:$C$11,MATCH($D$11,cc_input_vu_khi!$A$2:$A$11,0))-Thap!$K$16))+1)))*INDEX(cc_input_vu_khi_suy_ra!$D$2:$D$11,MATCH($D$11,cc_input_vu_khi_suy_ra!$A$2:$A$11,0))),1),"")) | F11: gun_105_wheeled_he | G11: =IF($F$11="","",IF(INDEX(cc_input_vu_khi!$B$2:$B$11,MATCH($F$11,cc_input_vu_khi!$A$2:$A$11,0))*INDEX(cc_input_bang_xuyen_giap!$B$2:$B$7,MIN(6,MAX(1,IF(INDEX(cc_input_vu_khi_suy_ra!$B$2:$B$11,MATCH($F$11,cc_input_vu_khi_suy_ra!$A$2:$A$11,0)),MAX(1,2-(INDEX(cc_input_vu_khi!$C$2:$C$11,MATCH($F$11,cc_input_vu_khi!$A$2:$A$11,0))-Thap!$K$16)),2-(INDEX(cc_input_vu_khi!$C$2:$C$11,MATCH($F$11,cc_input_vu_khi!$A$2:$A$11,0))-Thap!$K$16))+1)))*INDEX(cc_input_vu_khi_suy_ra!$D$2:$D$11,MATCH($F$11,cc_input_vu_khi_suy_ra!$A$2:$A$11,0))>0,CEILING(Thap!$J$16/(INDEX(cc_input_vu_khi!$B$2:$B$11,MATCH($F$11,cc_input_vu_khi!$A$2:$A$11,0))*INDEX(cc_input_bang_xuyen_giap!$B$2:$B$7,MIN(6,MAX(1,IF(INDEX(cc_input_vu_khi_suy_ra!$B$2:$B$11,MATCH($F$11,cc_input_vu_khi_suy_ra!$A$2:$A$11,0)),MAX(1,2-(INDEX(cc_input_vu_khi!$C$2:$C$11,MATCH($F$11,cc_input_vu_khi!$A$2:$A$11,0))-Thap!$K$16)),2-(INDEX(cc_input_vu_khi!$C$2:$C$11,MATCH($F$11,cc_input_vu_khi!$A$2:$A$11,0))-Thap!$K$16))+1)))*INDEX(cc_input_vu_khi_suy_ra!$D$2:$D$11,MATCH($F$11,cc_input_vu_khi_suy_ra!$A$2:$A$11,0))),1),"")) | I11: =IF($H$11="","",IF(INDEX(cc_input_vu_khi!$B$2:$B$11,MATCH($H$11,cc_input_vu_khi!$A$2:$A$11,0))*INDEX(cc_input_bang_xuyen_giap!$B$2:$B$7,MIN(6,MAX(1,IF(INDEX(cc_input_vu_khi_suy_ra!$B$2:$B$11,MATCH($H$11,cc_input_vu_khi_suy_ra!$A$2:$A$11,0)),MAX(1,2-(INDEX(cc_input_vu_khi!$C$2:$C$11,MATCH($H$11,cc_input_vu_khi!$A$2:$A$11,0))-Thap!$K$16)),2-(INDEX(cc_input_vu_khi!$C$2:$C$11,MATCH($H$11,cc_input_vu_khi!$A$2:$A$11,0))-Thap!$K$16))+1)))*INDEX(cc_input_vu_khi_suy_ra!$D$2:$D$11,MATCH($H$11,cc_input_vu_khi_suy_ra!$A$2:$A$11,0))>0,CEILING(Thap!$J$16/(INDEX(cc_input_vu_khi!$B$2:$B$11,MATCH($H$11,cc_input_vu_khi!$A$2:$A$11,0))*INDEX(cc_input_bang_xuyen_giap!$B$2:$B$7,MIN(6,MAX(1,IF(INDEX(cc_input_vu_khi_suy_ra!$B$2:$B$11,MATCH($H$11,cc_input_vu_khi_suy_ra!$A$2:$A$11,0)),MAX(1,2-(INDEX(cc_input_vu_khi!$C$2:$C$11,MATCH($H$11,cc_input_vu_khi!$A$2:$A$11,0))-Thap!$K$16)),2-(INDEX(cc_input_vu_khi!$C$2:$C$11,MATCH($H$11,cc_input_vu_khi!$A$2:$A$11,0))-Thap!$K$16))+1)))*INDEX(cc_input_vu_khi_suy_ra!$D$2:$D$11,MATCH($H$11,cc_input_vu_khi_suy_ra!$A$2:$A$11,0))),1),"")) | J11: mlrs_rockets | K11: =IF($J$11="","",IF(INDEX(cc_input_vu_khi!$B$2:$B$11,MATCH($J$11,cc_input_vu_khi!$A$2:$A$11,0))*INDEX(cc_input_bang_xuyen_giap!$B$2:$B$7,MIN(6,MAX(1,IF(INDEX(cc_input_vu_khi_suy_ra!$B$2:$B$11,MATCH($J$11,cc_input_vu_khi_suy_ra!$A$2:$A$11,0)),MAX(1,2-(INDEX(cc_input_vu_khi!$C$2:$C$11,MATCH($J$11,cc_input_vu_khi!$A$2:$A$11,0))-Thap!$K$16)),2-(INDEX(cc_input_vu_khi!$C$2:$C$11,MATCH($J$11,cc_input_vu_khi!$A$2:$A$11,0))-Thap!$K$16))+1)))*INDEX(cc_input_vu_khi_suy_ra!$D$2:$D$11,MATCH($J$11,cc_input_vu_khi_suy_ra!$A$2:$A$11,0))>0,CEILING(Thap!$J$16/(INDEX(cc_input_vu_khi!$B$2:$B$11,MATCH($J$11,cc_input_vu_khi!$A$2:$A$11,0))*INDEX(cc_input_bang_xuyen_giap!$B$2:$B$7,MIN(6,MAX(1,IF(INDEX(cc_input_vu_khi_suy_ra!$B$2:$B$11,MATCH($J$11,cc_input_vu_khi_suy_ra!$A$2:$A$11,0)),MAX(1,2-(INDEX(cc_input_vu_khi!$C$2:$C$11,MATCH($J$11,cc_input_vu_khi!$A$2:$A$11,0))-Thap!$K$16)),2-(INDEX(cc_input_vu_khi!$C$2:$C$11,MATCH($J$11,cc_input_vu_khi!$A$2:$A$11,0))-Thap!$K$16))+1)))*INDEX(cc_input_vu_khi_suy_ra!$D$2:$D$11,MATCH($J$11,cc_input_vu_khi_suy_ra!$A$2:$A$11,0))),1),"")) | L11: Tools/balance/p32_tower_prices.py Model.price('c_ram.dome') + threats('Medium')
A12: cp_relay | B12: =Thap_gia_cong_thuc!$Q$12 | C12: =IF(ISNUMBER($B$12),$B$12/Thap!$BN$18,"") | D12: ifv_30 | E12: =IF($D$12="","",IF(INDEX(cc_input_vu_khi!$B$2:$B$11,MATCH($D$12,cc_input_vu_khi!$A$2:$A$11,0))*INDEX(cc_input_bang_xuyen_giap!$B$2:$B$7,MIN(6,MAX(1,IF(INDEX(cc_input_vu_khi_suy_ra!$B$2:$B$11,MATCH($D$12,cc_input_vu_khi_suy_ra!$A$2:$A$11,0)),MAX(1,2-(INDEX(cc_input_vu_khi!$C$2:$C$11,MATCH($D$12,cc_input_vu_khi!$A$2:$A$11,0))-Thap!$K$18)),2-(INDEX(cc_input_vu_khi!$C$2:$C$11,MATCH($D$12,cc_input_vu_khi!$A$2:$A$11,0))-Thap!$K$18))+1)))*INDEX(cc_input_vu_khi_suy_ra!$D$2:$D$11,MATCH($D$12,cc_input_vu_khi_suy_ra!$A$2:$A$11,0))>0,CEILING(Thap!$J$18/(INDEX(cc_input_vu_khi!$B$2:$B$11,MATCH($D$12,cc_input_vu_khi!$A$2:$A$11,0))*INDEX(cc_input_bang_xuyen_giap!$B$2:$B$7,MIN(6,MAX(1,IF(INDEX(cc_input_vu_khi_suy_ra!$B$2:$B$11,MATCH($D$12,cc_input_vu_khi_suy_ra!$A$2:$A$11,0)),MAX(1,2-(INDEX(cc_input_vu_khi!$C$2:$C$11,MATCH($D$12,cc_input_vu_khi!$A$2:$A$11,0))-Thap!$K$18)),2-(INDEX(cc_input_vu_khi!$C$2:$C$11,MATCH($D$12,cc_input_vu_khi!$A$2:$A$11,0))-Thap!$K$18))+1)))*INDEX(cc_input_vu_khi_suy_ra!$D$2:$D$11,MATCH($D$12,cc_input_vu_khi_suy_ra!$A$2:$A$11,0))),1),"")) | F12: gun_120mm_he | G12: =IF($F$12="","",IF(INDEX(cc_input_vu_khi!$B$2:$B$11,MATCH($F$12,cc_input_vu_khi!$A$2:$A$11,0))*INDEX(cc_input_bang_xuyen_giap!$B$2:$B$7,MIN(6,MAX(1,IF(INDEX(cc_input_vu_khi_suy_ra!$B$2:$B$11,MATCH($F$12,cc_input_vu_khi_suy_ra!$A$2:$A$11,0)),MAX(1,2-(INDEX(cc_input_vu_khi!$C$2:$C$11,MATCH($F$12,cc_input_vu_khi!$A$2:$A$11,0))-Thap!$K$18)),2-(INDEX(cc_input_vu_khi!$C$2:$C$11,MATCH($F$12,cc_input_vu_khi!$A$2:$A$11,0))-Thap!$K$18))+1)))*INDEX(cc_input_vu_khi_suy_ra!$D$2:$D$11,MATCH($F$12,cc_input_vu_khi_suy_ra!$A$2:$A$11,0))>0,CEILING(Thap!$J$18/(INDEX(cc_input_vu_khi!$B$2:$B$11,MATCH($F$12,cc_input_vu_khi!$A$2:$A$11,0))*INDEX(cc_input_bang_xuyen_giap!$B$2:$B$7,MIN(6,MAX(1,IF(INDEX(cc_input_vu_khi_suy_ra!$B$2:$B$11,MATCH($F$12,cc_input_vu_khi_suy_ra!$A$2:$A$11,0)),MAX(1,2-(INDEX(cc_input_vu_khi!$C$2:$C$11,MATCH($F$12,cc_input_vu_khi!$A$2:$A$11,0))-Thap!$K$18)),2-(INDEX(cc_input_vu_khi!$C$2:$C$11,MATCH($F$12,cc_input_vu_khi!$A$2:$A$11,0))-Thap!$K$18))+1)))*INDEX(cc_input_vu_khi_suy_ra!$D$2:$D$11,MATCH($F$12,cc_input_vu_khi_suy_ra!$A$2:$A$11,0))),1),"")) | H12: recoilless_106 | I12: =IF($H$12="","",IF(INDEX(cc_input_vu_khi!$B$2:$B$11,MATCH($H$12,cc_input_vu_khi!$A$2:$A$11,0))*INDEX(cc_input_bang_xuyen_giap!$B$2:$B$7,MIN(6,MAX(1,IF(INDEX(cc_input_vu_khi_suy_ra!$B$2:$B$11,MATCH($H$12,cc_input_vu_khi_suy_ra!$A$2:$A$11,0)),MAX(1,2-(INDEX(cc_input_vu_khi!$C$2:$C$11,MATCH($H$12,cc_input_vu_khi!$A$2:$A$11,0))-Thap!$K$18)),2-(INDEX(cc_input_vu_khi!$C$2:$C$11,MATCH($H$12,cc_input_vu_khi!$A$2:$A$11,0))-Thap!$K$18))+1)))*INDEX(cc_input_vu_khi_suy_ra!$D$2:$D$11,MATCH($H$12,cc_input_vu_khi_suy_ra!$A$2:$A$11,0))>0,CEILING(Thap!$J$18/(INDEX(cc_input_vu_khi!$B$2:$B$11,MATCH($H$12,cc_input_vu_khi!$A$2:$A$11,0))*INDEX(cc_input_bang_xuyen_giap!$B$2:$B$7,MIN(6,MAX(1,IF(INDEX(cc_input_vu_khi_suy_ra!$B$2:$B$11,MATCH($H$12,cc_input_vu_khi_suy_ra!$A$2:$A$11,0)),MAX(1,2-(INDEX(cc_input_vu_khi!$C$2:$C$11,MATCH($H$12,cc_input_vu_khi!$A$2:$A$11,0))-Thap!$K$18)),2-(INDEX(cc_input_vu_khi!$C$2:$C$11,MATCH($H$12,cc_input_vu_khi!$A$2:$A$11,0))-Thap!$K$18))+1)))*INDEX(cc_input_vu_khi_suy_ra!$D$2:$D$11,MATCH($H$12,cc_input_vu_khi_suy_ra!$A$2:$A$11,0))),1),"")) | J12: technical_rockets | K12: =IF($J$12="","",IF(INDEX(cc_input_vu_khi!$B$2:$B$11,MATCH($J$12,cc_input_vu_khi!$A$2:$A$11,0))*INDEX(cc_input_bang_xuyen_giap!$B$2:$B$7,MIN(6,MAX(1,IF(INDEX(cc_input_vu_khi_suy_ra!$B$2:$B$11,MATCH($J$12,cc_input_vu_khi_suy_ra!$A$2:$A$11,0)),MAX(1,2-(INDEX(cc_input_vu_khi!$C$2:$C$11,MATCH($J$12,cc_input_vu_khi!$A$2:$A$11,0))-Thap!$K$18)),2-(INDEX(cc_input_vu_khi!$C$2:$C$11,MATCH($J$12,cc_input_vu_khi!$A$2:$A$11,0))-Thap!$K$18))+1)))*INDEX(cc_input_vu_khi_suy_ra!$D$2:$D$11,MATCH($J$12,cc_input_vu_khi_suy_ra!$A$2:$A$11,0))>0,CEILING(Thap!$J$18/(INDEX(cc_input_vu_khi!$B$2:$B$11,MATCH($J$12,cc_input_vu_khi!$A$2:$A$11,0))*INDEX(cc_input_bang_xuyen_giap!$B$2:$B$7,MIN(6,MAX(1,IF(INDEX(cc_input_vu_khi_suy_ra!$B$2:$B$11,MATCH($J$12,cc_input_vu_khi_suy_ra!$A$2:$A$11,0)),MAX(1,2-(INDEX(cc_input_vu_khi!$C$2:$C$11,MATCH($J$12,cc_input_vu_khi!$A$2:$A$11,0))-Thap!$K$18)),2-(INDEX(cc_input_vu_khi!$C$2:$C$11,MATCH($J$12,cc_input_vu_khi!$A$2:$A$11,0))-Thap!$K$18))+1)))*INDEX(cc_input_vu_khi_suy_ra!$D$2:$D$11,MATCH($J$12,cc_input_vu_khi_suy_ra!$A$2:$A$11,0))),1),"")) | L12: Tools/balance/p32_tower_prices.py Model.price('cp_relay') + threats('Small')
A13: drone_hangar | B13: =Thap_gia_cong_thuc!$Q$13 | C13: =IF(ISNUMBER($B$13),$B$13/Thap!$BN$19,"") | D13: gun_152 | E13: =IF($D$13="","",IF(INDEX(cc_input_vu_khi!$B$2:$B$11,MATCH($D$13,cc_input_vu_khi!$A$2:$A$11,0))*INDEX(cc_input_bang_xuyen_giap!$B$2:$B$7,MIN(6,MAX(1,IF(INDEX(cc_input_vu_khi_suy_ra!$B$2:$B$11,MATCH($D$13,cc_input_vu_khi_suy_ra!$A$2:$A$11,0)),MAX(1,2-(INDEX(cc_input_vu_khi!$C$2:$C$11,MATCH($D$13,cc_input_vu_khi!$A$2:$A$11,0))-Thap!$K$19)),2-(INDEX(cc_input_vu_khi!$C$2:$C$11,MATCH($D$13,cc_input_vu_khi!$A$2:$A$11,0))-Thap!$K$19))+1)))*INDEX(cc_input_vu_khi_suy_ra!$D$2:$D$11,MATCH($D$13,cc_input_vu_khi_suy_ra!$A$2:$A$11,0))>0,CEILING(Thap!$J$19/(INDEX(cc_input_vu_khi!$B$2:$B$11,MATCH($D$13,cc_input_vu_khi!$A$2:$A$11,0))*INDEX(cc_input_bang_xuyen_giap!$B$2:$B$7,MIN(6,MAX(1,IF(INDEX(cc_input_vu_khi_suy_ra!$B$2:$B$11,MATCH($D$13,cc_input_vu_khi_suy_ra!$A$2:$A$11,0)),MAX(1,2-(INDEX(cc_input_vu_khi!$C$2:$C$11,MATCH($D$13,cc_input_vu_khi!$A$2:$A$11,0))-Thap!$K$19)),2-(INDEX(cc_input_vu_khi!$C$2:$C$11,MATCH($D$13,cc_input_vu_khi!$A$2:$A$11,0))-Thap!$K$19))+1)))*INDEX(cc_input_vu_khi_suy_ra!$D$2:$D$11,MATCH($D$13,cc_input_vu_khi_suy_ra!$A$2:$A$11,0))),1),"")) | F13: gun_120_twin_he | G13: =IF($F$13="","",IF(INDEX(cc_input_vu_khi!$B$2:$B$11,MATCH($F$13,cc_input_vu_khi!$A$2:$A$11,0))*INDEX(cc_input_bang_xuyen_giap!$B$2:$B$7,MIN(6,MAX(1,IF(INDEX(cc_input_vu_khi_suy_ra!$B$2:$B$11,MATCH($F$13,cc_input_vu_khi_suy_ra!$A$2:$A$11,0)),MAX(1,2-(INDEX(cc_input_vu_khi!$C$2:$C$11,MATCH($F$13,cc_input_vu_khi!$A$2:$A$11,0))-Thap!$K$19)),2-(INDEX(cc_input_vu_khi!$C$2:$C$11,MATCH($F$13,cc_input_vu_khi!$A$2:$A$11,0))-Thap!$K$19))+1)))*INDEX(cc_input_vu_khi_suy_ra!$D$2:$D$11,MATCH($F$13,cc_input_vu_khi_suy_ra!$A$2:$A$11,0))>0,CEILING(Thap!$J$19/(INDEX(cc_input_vu_khi!$B$2:$B$11,MATCH($F$13,cc_input_vu_khi!$A$2:$A$11,0))*INDEX(cc_input_bang_xuyen_giap!$B$2:$B$7,MIN(6,MAX(1,IF(INDEX(cc_input_vu_khi_suy_ra!$B$2:$B$11,MATCH($F$13,cc_input_vu_khi_suy_ra!$A$2:$A$11,0)),MAX(1,2-(INDEX(cc_input_vu_khi!$C$2:$C$11,MATCH($F$13,cc_input_vu_khi!$A$2:$A$11,0))-Thap!$K$19)),2-(INDEX(cc_input_vu_khi!$C$2:$C$11,MATCH($F$13,cc_input_vu_khi!$A$2:$A$11,0))-Thap!$K$19))+1)))*INDEX(cc_input_vu_khi_suy_ra!$D$2:$D$11,MATCH($F$13,cc_input_vu_khi_suy_ra!$A$2:$A$11,0))),1),"")) | I13: =IF($H$13="","",IF(INDEX(cc_input_vu_khi!$B$2:$B$11,MATCH($H$13,cc_input_vu_khi!$A$2:$A$11,0))*INDEX(cc_input_bang_xuyen_giap!$B$2:$B$7,MIN(6,MAX(1,IF(INDEX(cc_input_vu_khi_suy_ra!$B$2:$B$11,MATCH($H$13,cc_input_vu_khi_suy_ra!$A$2:$A$11,0)),MAX(1,2-(INDEX(cc_input_vu_khi!$C$2:$C$11,MATCH($H$13,cc_input_vu_khi!$A$2:$A$11,0))-Thap!$K$19)),2-(INDEX(cc_input_vu_khi!$C$2:$C$11,MATCH($H$13,cc_input_vu_khi!$A$2:$A$11,0))-Thap!$K$19))+1)))*INDEX(cc_input_vu_khi_suy_ra!$D$2:$D$11,MATCH($H$13,cc_input_vu_khi_suy_ra!$A$2:$A$11,0))>0,CEILING(Thap!$J$19/(INDEX(cc_input_vu_khi!$B$2:$B$11,MATCH($H$13,cc_input_vu_khi!$A$2:$A$11,0))*INDEX(cc_input_bang_xuyen_giap!$B$2:$B$7,MIN(6,MAX(1,IF(INDEX(cc_input_vu_khi_suy_ra!$B$2:$B$11,MATCH($H$13,cc_input_vu_khi_suy_ra!$A$2:$A$11,0)),MAX(1,2-(INDEX(cc_input_vu_khi!$C$2:$C$11,MATCH($H$13,cc_input_vu_khi!$A$2:$A$11,0))-Thap!$K$19)),2-(INDEX(cc_input_vu_khi!$C$2:$C$11,MATCH($H$13,cc_input_vu_khi!$A$2:$A$11,0))-Thap!$K$19))+1)))*INDEX(cc_input_vu_khi_suy_ra!$D$2:$D$11,MATCH($H$13,cc_input_vu_khi_suy_ra!$A$2:$A$11,0))),1),"")) | J13: thermobaric_rockets | K13: =IF($J$13="","",IF(INDEX(cc_input_vu_khi!$B$2:$B$11,MATCH($J$13,cc_input_vu_khi!$A$2:$A$11,0))*INDEX(cc_input_bang_xuyen_giap!$B$2:$B$7,MIN(6,MAX(1,IF(INDEX(cc_input_vu_khi_suy_ra!$B$2:$B$11,MATCH($J$13,cc_input_vu_khi_suy_ra!$A$2:$A$11,0)),MAX(1,2-(INDEX(cc_input_vu_khi!$C$2:$C$11,MATCH($J$13,cc_input_vu_khi!$A$2:$A$11,0))-Thap!$K$19)),2-(INDEX(cc_input_vu_khi!$C$2:$C$11,MATCH($J$13,cc_input_vu_khi!$A$2:$A$11,0))-Thap!$K$19))+1)))*INDEX(cc_input_vu_khi_suy_ra!$D$2:$D$11,MATCH($J$13,cc_input_vu_khi_suy_ra!$A$2:$A$11,0))>0,CEILING(Thap!$J$19/(INDEX(cc_input_vu_khi!$B$2:$B$11,MATCH($J$13,cc_input_vu_khi!$A$2:$A$11,0))*INDEX(cc_input_bang_xuyen_giap!$B$2:$B$7,MIN(6,MAX(1,IF(INDEX(cc_input_vu_khi_suy_ra!$B$2:$B$11,MATCH($J$13,cc_input_vu_khi_suy_ra!$A$2:$A$11,0)),MAX(1,2-(INDEX(cc_input_vu_khi!$C$2:$C$11,MATCH($J$13,cc_input_vu_khi!$A$2:$A$11,0))-Thap!$K$19)),2-(INDEX(cc_input_vu_khi!$C$2:$C$11,MATCH($J$13,cc_input_vu_khi!$A$2:$A$11,0))-Thap!$K$19))+1)))*INDEX(cc_input_vu_khi_suy_ra!$D$2:$D$11,MATCH($J$13,cc_input_vu_khi_suy_ra!$A$2:$A$11,0))),1),"")) | L13: Tools/balance/p32_tower_prices.py Model.price('drone_hangar') + threats('Large')
A14: drone_hangar.lancet | B14: =Thap_gia_cong_thuc!$Q$14 | C14: =IF(ISNUMBER($B$14),$B$14/Thap!$BN$20,"") | D14: gun_152 | E14: =IF($D$14="","",IF(INDEX(cc_input_vu_khi!$B$2:$B$11,MATCH($D$14,cc_input_vu_khi!$A$2:$A$11,0))*INDEX(cc_input_bang_xuyen_giap!$B$2:$B$7,MIN(6,MAX(1,IF(INDEX(cc_input_vu_khi_suy_ra!$B$2:$B$11,MATCH($D$14,cc_input_vu_khi_suy_ra!$A$2:$A$11,0)),MAX(1,2-(INDEX(cc_input_vu_khi!$C$2:$C$11,MATCH($D$14,cc_input_vu_khi!$A$2:$A$11,0))-Thap!$K$20)),2-(INDEX(cc_input_vu_khi!$C$2:$C$11,MATCH($D$14,cc_input_vu_khi!$A$2:$A$11,0))-Thap!$K$20))+1)))*INDEX(cc_input_vu_khi_suy_ra!$D$2:$D$11,MATCH($D$14,cc_input_vu_khi_suy_ra!$A$2:$A$11,0))>0,CEILING(Thap!$J$20/(INDEX(cc_input_vu_khi!$B$2:$B$11,MATCH($D$14,cc_input_vu_khi!$A$2:$A$11,0))*INDEX(cc_input_bang_xuyen_giap!$B$2:$B$7,MIN(6,MAX(1,IF(INDEX(cc_input_vu_khi_suy_ra!$B$2:$B$11,MATCH($D$14,cc_input_vu_khi_suy_ra!$A$2:$A$11,0)),MAX(1,2-(INDEX(cc_input_vu_khi!$C$2:$C$11,MATCH($D$14,cc_input_vu_khi!$A$2:$A$11,0))-Thap!$K$20)),2-(INDEX(cc_input_vu_khi!$C$2:$C$11,MATCH($D$14,cc_input_vu_khi!$A$2:$A$11,0))-Thap!$K$20))+1)))*INDEX(cc_input_vu_khi_suy_ra!$D$2:$D$11,MATCH($D$14,cc_input_vu_khi_suy_ra!$A$2:$A$11,0))),1),"")) | F14: gun_120_twin_he | G14: =IF($F$14="","",IF(INDEX(cc_input_vu_khi!$B$2:$B$11,MATCH($F$14,cc_input_vu_khi!$A$2:$A$11,0))*INDEX(cc_input_bang_xuyen_giap!$B$2:$B$7,MIN(6,MAX(1,IF(INDEX(cc_input_vu_khi_suy_ra!$B$2:$B$11,MATCH($F$14,cc_input_vu_khi_suy_ra!$A$2:$A$11,0)),MAX(1,2-(INDEX(cc_input_vu_khi!$C$2:$C$11,MATCH($F$14,cc_input_vu_khi!$A$2:$A$11,0))-Thap!$K$20)),2-(INDEX(cc_input_vu_khi!$C$2:$C$11,MATCH($F$14,cc_input_vu_khi!$A$2:$A$11,0))-Thap!$K$20))+1)))*INDEX(cc_input_vu_khi_suy_ra!$D$2:$D$11,MATCH($F$14,cc_input_vu_khi_suy_ra!$A$2:$A$11,0))>0,CEILING(Thap!$J$20/(INDEX(cc_input_vu_khi!$B$2:$B$11,MATCH($F$14,cc_input_vu_khi!$A$2:$A$11,0))*INDEX(cc_input_bang_xuyen_giap!$B$2:$B$7,MIN(6,MAX(1,IF(INDEX(cc_input_vu_khi_suy_ra!$B$2:$B$11,MATCH($F$14,cc_input_vu_khi_suy_ra!$A$2:$A$11,0)),MAX(1,2-(INDEX(cc_input_vu_khi!$C$2:$C$11,MATCH($F$14,cc_input_vu_khi!$A$2:$A$11,0))-Thap!$K$20)),2-(INDEX(cc_input_vu_khi!$C$2:$C$11,MATCH($F$14,cc_input_vu_khi!$A$2:$A$11,0))-Thap!$K$20))+1)))*INDEX(cc_input_vu_khi_suy_ra!$D$2:$D$11,MATCH($F$14,cc_input_vu_khi_suy_ra!$A$2:$A$11,0))),1),"")) | I14: =IF($H$14="","",IF(INDEX(cc_input_vu_khi!$B$2:$B$11,MATCH($H$14,cc_input_vu_khi!$A$2:$A$11,0))*INDEX(cc_input_bang_xuyen_giap!$B$2:$B$7,MIN(6,MAX(1,IF(INDEX(cc_input_vu_khi_suy_ra!$B$2:$B$11,MATCH($H$14,cc_input_vu_khi_suy_ra!$A$2:$A$11,0)),MAX(1,2-(INDEX(cc_input_vu_khi!$C$2:$C$11,MATCH($H$14,cc_input_vu_khi!$A$2:$A$11,0))-Thap!$K$20)),2-(INDEX(cc_input_vu_khi!$C$2:$C$11,MATCH($H$14,cc_input_vu_khi!$A$2:$A$11,0))-Thap!$K$20))+1)))*INDEX(cc_input_vu_khi_suy_ra!$D$2:$D$11,MATCH($H$14,cc_input_vu_khi_suy_ra!$A$2:$A$11,0))>0,CEILING(Thap!$J$20/(INDEX(cc_input_vu_khi!$B$2:$B$11,MATCH($H$14,cc_input_vu_khi!$A$2:$A$11,0))*INDEX(cc_input_bang_xuyen_giap!$B$2:$B$7,MIN(6,MAX(1,IF(INDEX(cc_input_vu_khi_suy_ra!$B$2:$B$11,MATCH($H$14,cc_input_vu_khi_suy_ra!$A$2:$A$11,0)),MAX(1,2-(INDEX(cc_input_vu_khi!$C$2:$C$11,MATCH($H$14,cc_input_vu_khi!$A$2:$A$11,0))-Thap!$K$20)),2-(INDEX(cc_input_vu_khi!$C$2:$C$11,MATCH($H$14,cc_input_vu_khi!$A$2:$A$11,0))-Thap!$K$20))+1)))*INDEX(cc_input_vu_khi_suy_ra!$D$2:$D$11,MATCH($H$14,cc_input_vu_khi_suy_ra!$A$2:$A$11,0))),1),"")) | J14: thermobaric_rockets | K14: =IF($J$14="","",IF(INDEX(cc_input_vu_khi!$B$2:$B$11,MATCH($J$14,cc_input_vu_khi!$A$2:$A$11,0))*INDEX(cc_input_bang_xuyen_giap!$B$2:$B$7,MIN(6,MAX(1,IF(INDEX(cc_input_vu_khi_suy_ra!$B$2:$B$11,MATCH($J$14,cc_input_vu_khi_suy_ra!$A$2:$A$11,0)),MAX(1,2-(INDEX(cc_input_vu_khi!$C$2:$C$11,MATCH($J$14,cc_input_vu_khi!$A$2:$A$11,0))-Thap!$K$20)),2-(INDEX(cc_input_vu_khi!$C$2:$C$11,MATCH($J$14,cc_input_vu_khi!$A$2:$A$11,0))-Thap!$K$20))+1)))*INDEX(cc_input_vu_khi_suy_ra!$D$2:$D$11,MATCH($J$14,cc_input_vu_khi_suy_ra!$A$2:$A$11,0))>0,CEILING(Thap!$J$20/(INDEX(cc_input_vu_khi!$B$2:$B$11,MATCH($J$14,cc_input_vu_khi!$A$2:$A$11,0))*INDEX(cc_input_bang_xuyen_giap!$B$2:$B$7,MIN(6,MAX(1,IF(INDEX(cc_input_vu_khi_suy_ra!$B$2:$B$11,MATCH($J$14,cc_input_vu_khi_suy_ra!$A$2:$A$11,0)),MAX(1,2-(INDEX(cc_input_vu_khi!$C$2:$C$11,MATCH($J$14,cc_input_vu_khi!$A$2:$A$11,0))-Thap!$K$20)),2-(INDEX(cc_input_vu_khi!$C$2:$C$11,MATCH($J$14,cc_input_vu_khi!$A$2:$A$11,0))-Thap!$K$20))+1)))*INDEX(cc_input_vu_khi_suy_ra!$D$2:$D$11,MATCH($J$14,cc_input_vu_khi_suy_ra!$A$2:$A$11,0))),1),"")) | L14: Tools/balance/p32_tower_prices.py Model.price('drone_hangar.lancet') + threats('Large')
A15: drone_hangar.swarm | B15: =Thap_gia_cong_thuc!$Q$15 | C15: =IF(ISNUMBER($B$15),$B$15/Thap!$BN$21,"") | D15: gun_152 | E15: =IF($D$15="","",IF(INDEX(cc_input_vu_khi!$B$2:$B$11,MATCH($D$15,cc_input_vu_khi!$A$2:$A$11,0))*INDEX(cc_input_bang_xuyen_giap!$B$2:$B$7,MIN(6,MAX(1,IF(INDEX(cc_input_vu_khi_suy_ra!$B$2:$B$11,MATCH($D$15,cc_input_vu_khi_suy_ra!$A$2:$A$11,0)),MAX(1,2-(INDEX(cc_input_vu_khi!$C$2:$C$11,MATCH($D$15,cc_input_vu_khi!$A$2:$A$11,0))-Thap!$K$21)),2-(INDEX(cc_input_vu_khi!$C$2:$C$11,MATCH($D$15,cc_input_vu_khi!$A$2:$A$11,0))-Thap!$K$21))+1)))*INDEX(cc_input_vu_khi_suy_ra!$D$2:$D$11,MATCH($D$15,cc_input_vu_khi_suy_ra!$A$2:$A$11,0))>0,CEILING(Thap!$J$21/(INDEX(cc_input_vu_khi!$B$2:$B$11,MATCH($D$15,cc_input_vu_khi!$A$2:$A$11,0))*INDEX(cc_input_bang_xuyen_giap!$B$2:$B$7,MIN(6,MAX(1,IF(INDEX(cc_input_vu_khi_suy_ra!$B$2:$B$11,MATCH($D$15,cc_input_vu_khi_suy_ra!$A$2:$A$11,0)),MAX(1,2-(INDEX(cc_input_vu_khi!$C$2:$C$11,MATCH($D$15,cc_input_vu_khi!$A$2:$A$11,0))-Thap!$K$21)),2-(INDEX(cc_input_vu_khi!$C$2:$C$11,MATCH($D$15,cc_input_vu_khi!$A$2:$A$11,0))-Thap!$K$21))+1)))*INDEX(cc_input_vu_khi_suy_ra!$D$2:$D$11,MATCH($D$15,cc_input_vu_khi_suy_ra!$A$2:$A$11,0))),1),"")) | F15: gun_120_twin_he | G15: =IF($F$15="","",IF(INDEX(cc_input_vu_khi!$B$2:$B$11,MATCH($F$15,cc_input_vu_khi!$A$2:$A$11,0))*INDEX(cc_input_bang_xuyen_giap!$B$2:$B$7,MIN(6,MAX(1,IF(INDEX(cc_input_vu_khi_suy_ra!$B$2:$B$11,MATCH($F$15,cc_input_vu_khi_suy_ra!$A$2:$A$11,0)),MAX(1,2-(INDEX(cc_input_vu_khi!$C$2:$C$11,MATCH($F$15,cc_input_vu_khi!$A$2:$A$11,0))-Thap!$K$21)),2-(INDEX(cc_input_vu_khi!$C$2:$C$11,MATCH($F$15,cc_input_vu_khi!$A$2:$A$11,0))-Thap!$K$21))+1)))*INDEX(cc_input_vu_khi_suy_ra!$D$2:$D$11,MATCH($F$15,cc_input_vu_khi_suy_ra!$A$2:$A$11,0))>0,CEILING(Thap!$J$21/(INDEX(cc_input_vu_khi!$B$2:$B$11,MATCH($F$15,cc_input_vu_khi!$A$2:$A$11,0))*INDEX(cc_input_bang_xuyen_giap!$B$2:$B$7,MIN(6,MAX(1,IF(INDEX(cc_input_vu_khi_suy_ra!$B$2:$B$11,MATCH($F$15,cc_input_vu_khi_suy_ra!$A$2:$A$11,0)),MAX(1,2-(INDEX(cc_input_vu_khi!$C$2:$C$11,MATCH($F$15,cc_input_vu_khi!$A$2:$A$11,0))-Thap!$K$21)),2-(INDEX(cc_input_vu_khi!$C$2:$C$11,MATCH($F$15,cc_input_vu_khi!$A$2:$A$11,0))-Thap!$K$21))+1)))*INDEX(cc_input_vu_khi_suy_ra!$D$2:$D$11,MATCH($F$15,cc_input_vu_khi_suy_ra!$A$2:$A$11,0))),1),"")) | I15: =IF($H$15="","",IF(INDEX(cc_input_vu_khi!$B$2:$B$11,MATCH($H$15,cc_input_vu_khi!$A$2:$A$11,0))*INDEX(cc_input_bang_xuyen_giap!$B$2:$B$7,MIN(6,MAX(1,IF(INDEX(cc_input_vu_khi_suy_ra!$B$2:$B$11,MATCH($H$15,cc_input_vu_khi_suy_ra!$A$2:$A$11,0)),MAX(1,2-(INDEX(cc_input_vu_khi!$C$2:$C$11,MATCH($H$15,cc_input_vu_khi!$A$2:$A$11,0))-Thap!$K$21)),2-(INDEX(cc_input_vu_khi!$C$2:$C$11,MATCH($H$15,cc_input_vu_khi!$A$2:$A$11,0))-Thap!$K$21))+1)))*INDEX(cc_input_vu_khi_suy_ra!$D$2:$D$11,MATCH($H$15,cc_input_vu_khi_suy_ra!$A$2:$A$11,0))>0,CEILING(Thap!$J$21/(INDEX(cc_input_vu_khi!$B$2:$B$11,MATCH($H$15,cc_input_vu_khi!$A$2:$A$11,0))*INDEX(cc_input_bang_xuyen_giap!$B$2:$B$7,MIN(6,MAX(1,IF(INDEX(cc_input_vu_khi_suy_ra!$B$2:$B$11,MATCH($H$15,cc_input_vu_khi_suy_ra!$A$2:$A$11,0)),MAX(1,2-(INDEX(cc_input_vu_khi!$C$2:$C$11,MATCH($H$15,cc_input_vu_khi!$A$2:$A$11,0))-Thap!$K$21)),2-(INDEX(cc_input_vu_khi!$C$2:$C$11,MATCH($H$15,cc_input_vu_khi!$A$2:$A$11,0))-Thap!$K$21))+1)))*INDEX(cc_input_vu_khi_suy_ra!$D$2:$D$11,MATCH($H$15,cc_input_vu_khi_suy_ra!$A$2:$A$11,0))),1),"")) | J15: thermobaric_rockets | K15: =IF($J$15="","",IF(INDEX(cc_input_vu_khi!$B$2:$B$11,MATCH($J$15,cc_input_vu_khi!$A$2:$A$11,0))*INDEX(cc_input_bang_xuyen_giap!$B$2:$B$7,MIN(6,MAX(1,IF(INDEX(cc_input_vu_khi_suy_ra!$B$2:$B$11,MATCH($J$15,cc_input_vu_khi_suy_ra!$A$2:$A$11,0)),MAX(1,2-(INDEX(cc_input_vu_khi!$C$2:$C$11,MATCH($J$15,cc_input_vu_khi!$A$2:$A$11,0))-Thap!$K$21)),2-(INDEX(cc_input_vu_khi!$C$2:$C$11,MATCH($J$15,cc_input_vu_khi!$A$2:$A$11,0))-Thap!$K$21))+1)))*INDEX(cc_input_vu_khi_suy_ra!$D$2:$D$11,MATCH($J$15,cc_input_vu_khi_suy_ra!$A$2:$A$11,0))>0,CEILING(Thap!$J$21/(INDEX(cc_input_vu_khi!$B$2:$B$11,MATCH($J$15,cc_input_vu_khi!$A$2:$A$11,0))*INDEX(cc_input_bang_xuyen_giap!$B$2:$B$7,MIN(6,MAX(1,IF(INDEX(cc_input_vu_khi_suy_ra!$B$2:$B$11,MATCH($J$15,cc_input_vu_khi_suy_ra!$A$2:$A$11,0)),MAX(1,2-(INDEX(cc_input_vu_khi!$C$2:$C$11,MATCH($J$15,cc_input_vu_khi!$A$2:$A$11,0))-Thap!$K$21)),2-(INDEX(cc_input_vu_khi!$C$2:$C$11,MATCH($J$15,cc_input_vu_khi!$A$2:$A$11,0))-Thap!$K$21))+1)))*INDEX(cc_input_vu_khi_suy_ra!$D$2:$D$11,MATCH($J$15,cc_input_vu_khi_suy_ra!$A$2:$A$11,0))),1),"")) | L15: Tools/balance/p32_tower_prices.py Model.price('drone_hangar.swarm') + threats('Large')
