Workbook

Sheet Che_do
A1: id | B1: ten_che_do | C1: kho_cp | D1: cp_khoi_dau_nhan_he_so | E1: ho_so_ai | F1: trung_lap | G1: lists_maps | H1: numbers | I1: numbers_anti_snipe_range | J1: numbers_anti_snipe_share | K1: numbers_base_radius | L1: numbers_bleed | M1: numbers_boss_wave | N1: numbers_bosses | O1: numbers_catch_up_max | P1: numbers_escalation_at | Q1: numbers_escalation_income | R1: numbers_final_phase | S1: numbers_final_scale | T1: numbers_kill_cap | U1: numbers_kill_ticket_factor | V1: numbers_losses | W1: numbers_losses_at_zero_cp | X1: numbers_max_bank | Y1: numbers_mini_boss_wave | Z1: numbers_neutrals_max | AA1: numbers_overtime | AB1: numbers_overtime_lead | AC1: numbers_per_second | AD1: numbers_points | AE1: numbers_rebuild_cutoff | AF1: numbers_sector_bonus | AG1: numbers_start | AH1: numbers_sudden_death | AI1: numbers_sudden_death_income | AJ1: numbers_target | AK1: numbers_time_limit_s | AL1: numbers_waves | AM1: text_anti_snipe_rule | AN1: text_breach_rule | AO1: text_catch_up_policy | AP1: text_draw_rule | AQ1: text_escalation | AR1: text_lose_condition | AS1: text_map_eligibility | AT1: text_overtime_rule | AU1: text_score_rule | AV1: text_time_limit | AW1: text_win_condition | AX1: nguon | AY1: raw_json
A2: assault | B2: Assault | C2: 30;45 | D2: TRUE | E2: assault | F2: ammo_depot | O2: 0.25 | X2: 300 | AA2: 60 | AF2: 150 | AG2: 240 | AO2: Như hiện có | AP2: Không có hòa | AR2: Hết quỹ thời gian | AT2: Hết giờ khi đang chiếm dở: kéo dài tới khi chiếm xong hoặc bị đẩy ra, tối đa 60 s | AU2: Không tính điểm; sao (nếu là màn chiến dịch) theo số khu | AV2: Bắt đầu 4:00; chiếm A +2:30; chiếm B +2:30; quỹ tối đa 5:00 | AW2: Chiếm A, B, C | AX2: Assets/MachineBrigade/Resources/Data/balance.json: matchRules.modes.assault | AY2: {"text":{"winCondition":"Chiếm A, B, C","loseCondition":"Hết quỹ thời gian","timeLimit":"Bắt đầu 4:00; chiếm A +2:30; chiếm B +2:30; quỹ tối đa 5:00","overtimeRule":"Hết giờ khi đang chiếm dở: kéo dài tới khi chiếm xong hoặc bị đẩy ra, tối đa 60 s","drawRule":"Không có hòa","scoreRule":"Không tính điểm; sao (nếu là màn chiến dịch) theo số khu","catchUpPolicy":"Như hiện có"},"numbers":{"start":240,"sectorBonus":150,"maxBank":300,"overtime":60,"catchUpMax":0.25}}
A3: bossrush | B3: BossRush | C3: 45;60 | D3: TRUE | E3: bossrush | N3: 10 | AK3: 1800 | AO3: Không áp | AP3: Không | AR3: Mất toàn bộ quân hoặc hết 30 phút | AT3: Không | AU3: Xếp hạng: số boss hạ (giảm dần) → thời gian hoàn thành (tăng dần) → số bộ phận phá (giảm dần). Thưởng CP mỗi bộ phận giữ nguyên | AV3: 30 phút | AW3: Hạ đủ 10 boss | AX3: Assets/MachineBrigade/Resources/Data/balance.json: matchRules.modes.bossrush | AY3: {"text":{"winCondition":"Hạ đủ 10 boss","loseCondition":"Mất toàn bộ quân hoặc hết 30 phút","timeLimit":"30 phút","overtimeRule":"Không","drawRule":"Không","scoreRule":"Xếp hạng: số boss hạ (giảm dần) → thời gian hoàn thành (tăng dần) → số bộ phận phá (giảm dần). Thưởng CP mỗi bộ phận giữ nguyên","catchUpPolicy":"Không áp"},"numbers":{"bosses":10,"timeLimit":1800}}
A4: conquest | B4: Conquest | C4: 30;45 | D4: TRUE | E4: conquest | F4: radar;workshop | L4: 0.8 | O4: 0.25 | R4: 120 | S4: 2 | U4: 0 | AA4: 60 | AD4: 500 | AK4: 600 | AO4: Giảm (tối đa +25%) | AP4: Hòa nếu hết hiệp phụ | AR4: Về 0 điểm, hoặc ít điểm hơn khi hết giờ | AT4: Bằng điểm khi hết giờ: tối đa 60 s, bên chiếm thêm cứ điểm trước thắng | AU4: 500 điểm mỗi bên; bên giữ ít cứ điểm hơn mất 0,8 × (chênh lệch số cứ điểm) điểm/s; 2 phút cuối ×2; giữ cả 3 không cộng thêm | AV4: 10 phút | AW4: Đối phương về 0 điểm, hoặc nhiều điểm hơn khi hết giờ | AX4: Assets/MachineBrigade/Resources/Data/balance.json: matchRules.modes.conquest | AY4: {"text":{"winCondition":"Đối phương về 0 điểm, hoặc nhiều điểm hơn khi hết giờ","loseCondition":"Về 0 điểm, hoặc ít điểm hơn khi hết giờ","timeLimit":"10 phút","overtimeRule":"Bằng điểm khi hết giờ: tối đa 60 s, bên chiếm thêm cứ điểm trước thắng","drawRule":"Hòa nếu hết hiệp phụ","scoreRule":"500 điểm mỗi bên; bên giữ ít cứ điểm hơn mất 0,8 × (chênh lệch số cứ điểm) điểm/s; 2 phút cuối ×2; giữ cả 3 không cộng thêm","catchUpPolicy":"Giảm (tối đa +25%)"},"numbers":{"points":500,"bleed":0.8,"killTicketFactor":0,"timeLimit":600,"finalPhase":120,"finalScale":2,"overtime":60,"catchUpMax":0.25}}
A5: deathmatch | B5: Deathmatch | C5: 30;45 | D5: TRUE | E5: deathmatch | F5: ammo_depot;aa_site | O5: 0.25 | T5: 18 | AA5: 60 | AJ5: 480 | AK5: 540 | AO5: Giảm (tối đa +25%) | AP5: Hòa nếu hết hiệp phụ | AR5: Đối phương đạt 480 trước, hoặc ít điểm hơn khi hết giờ | AT5: Bằng điểm: tối đa 60 s, xe bị hạ đầu tiên quyết định | AU5: Mỗi xe địch bị hạ: min(baseCP, 18) điểm. Dùng baseCP, không dùng giá sau giảm | AV5: 9 phút | AW5: Đạt 480 điểm, hoặc nhiều điểm hơn khi hết giờ | AX5: Assets/MachineBrigade/Resources/Data/balance.json: matchRules.modes.deathmatch | AY5: {"text":{"winCondition":"Đạt 480 điểm, hoặc nhiều điểm hơn khi hết giờ","loseCondition":"Đối phương đạt 480 trước, hoặc ít điểm hơn khi hết giờ","timeLimit":"9 phút","overtimeRule":"Bằng điểm: tối đa 60 s, xe bị hạ đầu tiên quyết định","drawRule":"Hòa nếu hết hiệp phụ","scoreRule":"Mỗi xe địch bị hạ: min(baseCP, 18) điểm. Dùng baseCP, không dùng giá sau giảm","catchUpPolicy":"Giảm (tối đa +25%)"},"numbers":{"target":480,"killCap":18,"timeLimit":540,"overtime":60,"catchUpMax":0.25}}
A6: defend | B6: Defend | C6: 30;45 | D6: TRUE | E6: defend | AK6: 720 | AO6: Không áp (đợt theo Sức mạnh căn cứ) | AP6: Không | AR6: Mất sở chỉ huy | AT6: Không | AU6: Không tính điểm; sao (nếu là màn chiến dịch) theo máu sở chỉ huy và số tuyến còn giữ; mất tuyến ngoài KHÔNG là thất bại | AV6: 12 phút | AW6: Sở chỉ huy còn đứng khi hết giờ | AX6: Assets/MachineBrigade/Resources/Data/balance.json: matchRules.modes.defend | AY6: {"text":{"winCondition":"Sở chỉ huy còn đứng khi hết giờ","loseCondition":"Mất sở chỉ huy","timeLimit":"12 phút","overtimeRule":"Không","drawRule":"Không","scoreRule":"Không tính điểm; sao (nếu là màn chiến dịch) theo máu sở chỉ huy và số tuyến còn giữ; mất tuyến ngoài KHÔNG là thất bại","catchUpPolicy":"Không áp (đợt theo Sức mạnh căn cứ)"},"numbers":{"timeLimit":720}}
A7: endless | B7: Endless | C7: 30;45 | D7: TRUE | E7: defend | AO7: Không áp | AP7: Không | AR7: Mất sở chỉ huy | AT7: Không | AU7: Xếp hạng theo thứ tự: đợt hoàn thành (giảm dần) → baseCP xe địch đã hạ (giảm dần) → thời gian sống (giảm dần) | AV7: Không giới hạn | AW7: Không có trạng thái thắng | AX7: Assets/MachineBrigade/Resources/Data/balance.json: matchRules.modes.endless | AY7: {"text":{"winCondition":"Không có trạng thái thắng","loseCondition":"Mất sở chỉ huy","timeLimit":"Không giới hạn","overtimeRule":"Không","drawRule":"Không","scoreRule":"Xếp hạng theo thứ tự: đợt hoàn thành (giảm dần) → baseCP xe địch đã hạ (giảm dần) → thời gian sống (giảm dần)","catchUpPolicy":"Không áp"},"numbers":{}}
A8: hill | B8: KingOfTheHill | C8: 30;45 | D8: TRUE | E8: hill | F8: workshop | O8: 0.25 | AA8: 60 | AC8: 1 | AJ8: 170 | AK8: 540 | AO8: Như hiện có | AP8: Hòa nếu hết hiệp phụ | AR8: Ngược lại | AT8: Bằng điểm hoặc đồi đang tranh khi hết giờ: tối đa 60 s; còn tranh thì kéo dài, một bên giữ riêng thì phân định | AU8: Một mình giữ đồi: +1 điểm/s; tranh chấp hoặc trống: 0 | AV8: 9 phút | AW8: Đạt 170 điểm, hoặc dẫn khi hết giờ | AX8: Assets/MachineBrigade/Resources/Data/balance.json: matchRules.modes.hill | AY8: {"text":{"winCondition":"Đạt 170 điểm, hoặc dẫn khi hết giờ","loseCondition":"Ngược lại","timeLimit":"9 phút","overtimeRule":"Bằng điểm hoặc đồi đang tranh khi hết giờ: tối đa 60 s; còn tranh thì kéo dài, một bên giữ riêng thì phân định","drawRule":"Hòa nếu hết hiệp phụ","scoreRule":"Một mình giữ đồi: +1 điểm/s; tranh chấp hoặc trống: 0","catchUpPolicy":"Như hiện có"},"numbers":{"target":170,"perSecond":1,"timeLimit":540,"overtime":60,"catchUpMax":0.25}}
A9: operations | B9: Operation | D9: FALSE | E9: operation | V9: 2000 | W9: 150 | AO9: Như màn gốc | AP9: Như màn gốc | AR9: Như màn gốc | AT9: Như màn gốc | AU9: Giữ công thức hiện có (5.000 + thời gian + tổn thất + máu sở chỉ huy, × hệ số cấp). Phần tổn thất đổi từ số xe sang baseCP đã mất: 2.000 khi mất 0, về 0 khi mất 150 baseCP | AV9: Như màn gốc | AW9: Như màn gốc | AX9: Assets/MachineBrigade/Resources/Data/balance.json: matchRules.modes.operations | AY9: {"text":{"winCondition":"Như màn gốc","loseCondition":"Như màn gốc","timeLimit":"Như màn gốc","overtimeRule":"Như màn gốc","drawRule":"Như màn gốc","scoreRule":"Giữ công thức hiện có (5.000 + thời gian + tổn thất + máu sở chỉ huy, × hệ số cấp). Phần tổn thất đổi từ số xe sang baseCP đã mất: 2.000 khi mất 0, về 0 khi mất 150 baseCP","catchUpPolicy":"Như màn gốc"},"numbers":{"losses":2000,"lossesAtZeroCp":150}}
A10: showdown | B10: Showdown | D10: TRUE | E10: showdown | F10: ammo_depot | G10: ashfield;capital;coralisles;dunebreak;foundry;frostpeak;greenvale;ironport;junglepass;landingbeach;launchsite;lighthousebay;metrocity;openpit;orbitalgate;redrock;rustyard;saltflat;skyhold;swamp;veyra_old_quarter;whiteout | I10: 60 | J10: 0.25 | K10: 46 | O10: 0.25 | P10: 360 | Q10: 1.5 | Z10: 2 | AB10: 0.05 | AE10: 600 | AH10: 90 | AI10: 2 | AK10: 720 | AM10: Nhà chính chỉ nhận 25% sát thương từ pháo binh, tên lửa và máy bay bắn từ ngoài 60 m, cho tới khi outerDefenseBreached | AN10: outerDefenseBreached khi quân mặt đất địch vào qua cổng chính (cổng trại là lối mở), hoặc một đoạn tường ngoài thành RUBBLE và mở được đường từ phía công vào trong căn cứ (kiểm bằng trạng thái NavGrid) | AO10: Chỉ bắt kịp thu nhập, trần +25%; không tiếp viện miễn phí | AP10: Bằng nhau sau đột tử → hòa | AQ10: Phút 6: thu nhập ×1,5 cho cả hai phe, trạm CP ngừng tạo CP; phút 10: tháp bị phá không xây lại (lần đã trừ CP thì hoàn tất) | AR10: Mất nhà chính | AS10: Chỉ bản đồ 300×300 đạt ngưỡng đối xứng của docs/checks/map_audit.md (không dùng 300×480) | AT10: Hết 12 phút: bên có nhà chính còn nhiều % máu hơn từ 5 điểm phần trăm trở lên thắng ngay; chênh dưới 5 điểm → đột tử 90 s (tắt chống bắn tỉa, không xây lại tháp, thu nhập ×2, không đặt lại hồi chiêu kỹ năng nhà chính): phá nhà chính thì thắng, hết 90 s thì bên gây nhiều sát thương lên nhà chính đối phương trong đột tử hơn thắng | AU10: Không có điểm phụ | AV10: 12 phút | AW10: Phá nhà chính đối phương | AX10: Assets/MachineBrigade/Resources/Data/balance.json: matchRules.modes.showdown | AY10: {"text":{"winCondition":"Phá nhà chính đối phương","loseCondition":"Mất nhà chính","timeLimit":"12 phút","overtimeRule":"Hết 12 phút: bên có nhà chính còn nhiều % máu hơn từ 5 điểm phần trăm trở lên thắng ngay; chênh dưới 5 điểm → đột tử 90 s (tắt chống bắn tỉa, không xây lại tháp, thu nhập ×2, không đặt lại hồi chiêu kỹ năng nhà chính): phá nhà chính thì thắng, hết 90 s thì bên gây nhiều sát thương lên nhà chính đối phương trong đột tử hơn thắng","drawRule":"Bằng nhau sau đột tử → hòa","scoreRule":"Không có điểm phụ","catchUpPolicy":"Chỉ bắt kịp thu nhập, trần +25%; không tiếp viện miễn phí","antiSnipeRule":"Nhà chính chỉ nhận 25% sát thương từ pháo binh, tên lửa và máy bay bắn từ ngoài 60 m, cho tới khi outerDefenseBreached","breachRule":"outerDefenseBreached khi quân mặt đất địch vào qua cổng chính (cổng trại là lối mở), hoặc một đoạn tường ngoài thành RUBBLE và mở được đường từ phía công vào trong căn cứ (kiểm bằng trạng thái NavGrid)","escalation":"Phút 6: thu nhập ×1,5 cho cả hai phe, trạm CP ngừng tạo CP; phút 10: tháp bị phá không xây lại (lần đã trừ CP thì hoàn tất)","mapEligibility":"Chỉ bản đồ 300×300 đạt ngưỡng đối xứng của docs/checks/map_audit.md (không dùng 300×480)"},"numbers":{"timeLimit":720,"antiSnipeShare":0.25,"antiSnipeRange":60,"escalationAt":360,"escalationIncome":1.5,"rebuildCutoff":600,"overtimeLead":0.05,"suddenDeath":90,"suddenDeathIncome":2,"catchUpMax":0.25,"baseRadius":46,"neutralsMax":2},"lists":{"maps":["ashfield","capital","coralisles","dunebreak","foundry","frostpeak","greenvale","ironport","junglepass","landingbeach","launchsite","lighthousebay","metrocity","openpit","orbitalgate","redrock","rustyard","saltflat","skyhold","swamp","veyra_old_quarter","whiteout"]}}
A11: siege | B11: Siege | C11: 40;55 | D11: TRUE | E11: siege | F11: aa_site | AA11: 60 | AK11: 1080 | AO11: Như hiện có | AP11: Không có hòa | AR11: Hết giờ | AT11: Mục tiêu cuối đang bị tấn công khi hết giờ: tối đa 60 s | AU11: Không tính điểm | AV11: 18 phút mặc định; màn chiến dịch dùng giới hạn thời gian riêng | AW11: Hạ sở chỉ huy pháo đài | AX11: Assets/MachineBrigade/Resources/Data/balance.json: matchRules.modes.siege | AY11: {"text":{"winCondition":"Hạ sở chỉ huy pháo đài","loseCondition":"Hết giờ","timeLimit":"18 phút mặc định; màn chiến dịch dùng giới hạn thời gian riêng","overtimeRule":"Mục tiêu cuối đang bị tấn công khi hết giờ: tối đa 60 s","drawRule":"Không có hòa","scoreRule":"Không tính điểm","catchUpPolicy":"Như hiện có"},"numbers":{"timeLimit":1080,"overtime":60}}
A12: survival | B12: Survival | C12: 30;40 | D12: TRUE | E12: survival | F12: workshop | M12: 10 | Y12: 5 | AL12: 10 | AO12: Không áp | AP12: Không | AR12: Mất toàn bộ quân hoặc địch chiếm bãi thả | AT12: Không | AU12: Số đợt đã qua | AV12: 10 đợt; nhịp mục tiêu khoảng 60 giây/đợt, tổng khoảng 10 phút | AW12: Qua hết đợt 10 (đợt 5 có mini boss, đợt 10 có boss chủ lực) | AX12: Assets/MachineBrigade/Resources/Data/balance.json: matchRules.modes.survival | AY12: {"text":{"winCondition":"Qua hết đợt 10 (đợt 5 có mini boss, đợt 10 có boss chủ lực)","loseCondition":"Mất toàn bộ quân hoặc địch chiếm bãi thả","timeLimit":"10 đợt; nhịp mục tiêu khoảng 60 giây/đợt, tổng khoảng 10 phút","overtimeRule":"Không","drawRule":"Không","scoreRule":"Số đợt đã qua","catchUpPolicy":"Không áp"},"numbers":{"waves":10,"miniBossWave":5,"bossWave":10}}
A13: weekly | B13: Weekly | D13: TRUE | E13: siege | F13: ammo_depot | AA13: 60 | AO13: Như Công thành | AP13: Không | AR13: Mỗi lần đánh có thể dừng giữa chừng; lớp đã phá được giữ | AT13: Như Công thành | AU13: Xếp hạng: đã phá xong? → số lần đánh (tăng dần) → tổng thời gian giao chiến (tăng dần) | AV13: Theo lần đánh (như Công thành) + chu kỳ tuần | AW13: Hạ sở chỉ huy trước khi tuần kết thúc | AX13: Assets/MachineBrigade/Resources/Data/balance.json: matchRules.modes.weekly | AY13: {"text":{"winCondition":"Hạ sở chỉ huy trước khi tuần kết thúc","loseCondition":"Mỗi lần đánh có thể dừng giữa chừng; lớp đã phá được giữ","timeLimit":"Theo lần đánh (như Công thành) + chu kỳ tuần","overtimeRule":"Như Công thành","drawRule":"Không","scoreRule":"Xếp hạng: đã phá xong? → số lần đánh (tăng dần) → tổng thời gian giao chiến (tăng dần)","catchUpPolicy":"Như Công thành"},"numbers":{"overtime":60}}

Sheet Sao_chien_dich
A1: id | B1: sao2_kind | C1: sao2_value | D1: sao3_kind | E1: sao3_value | F1: nguon | G1: raw_json
A2: Boss | B2: BossParts | C2: 2 | D2: NoAircraft | F2: Assets/MachineBrigade/Resources/Data/balance.json: matchRules.starMastery.Boss
A3: Capture | B3: LossShare | C3: 0.4 | D3: Kills | E3: 10 | F3: Assets/MachineBrigade/Resources/Data/balance.json: matchRules.starMastery.Capture
A4: Destroy | B4: LossShare | C4: 0.4 | D4: NoStrikes | F4: Assets/MachineBrigade/Resources/Data/balance.json: matchRules.starMastery.Destroy
A5: Duel | B5: HqShare | C5: 0.5 | D5: Kills | E5: 15 | F5: Assets/MachineBrigade/Resources/Data/balance.json: matchRules.starMastery.Duel
A6: Escort | B6: ConvoyShare | C6: 0.8 | D6: Kills | E6: 10 | F6: Assets/MachineBrigade/Resources/Data/balance.json: matchRules.starMastery.Escort
A7: Evacuate | B7: ConvoyShare | C7: 0.8 | D7: Kills | E7: 10 | F7: Assets/MachineBrigade/Resources/Data/balance.json: matchRules.starMastery.Evacuate
A8: Hold | B8: HoldShare | C8: 0.8 | D8: Kills | E8: 15 | F8: Assets/MachineBrigade/Resources/Data/balance.json: matchRules.starMastery.Hold
A9: Hunt | B9: LossShare | C9: 0.4 | D9: Kills | E9: 10 | F9: Assets/MachineBrigade/Resources/Data/balance.json: matchRules.starMastery.Hunt
A10: Intercept | B10: LossShare | C10: 0.4 | D10: NoStrikes | F10: Assets/MachineBrigade/Resources/Data/balance.json: matchRules.starMastery.Intercept
A11: Outpost | B11: HoldShare | C11: 0.8 | D11: Kills | E11: 12 | F11: Assets/MachineBrigade/Resources/Data/balance.json: matchRules.starMastery.Outpost
A12: Protect | B12: ProtectShare | C12: 0.75 | D12: Kills | E12: 15 | F12: Assets/MachineBrigade/Resources/Data/balance.json: matchRules.starMastery.Protect
A13: Recon | B13: ReconQuiet | C13: 0.67 | D13: NoStrikes | F13: Assets/MachineBrigade/Resources/Data/balance.json: matchRules.starMastery.Recon
A14: Relieve | B14: LossShare | C14: 0.4 | D14: Kills | E14: 12 | F14: Assets/MachineBrigade/Resources/Data/balance.json: matchRules.starMastery.Relieve
A15: ShootDown | B15: LossShare | C15: 0.4 | D15: Kills | E15: 12 | F15: Assets/MachineBrigade/Resources/Data/balance.json: matchRules.starMastery.ShootDown
A16: Survive | B16: HqShare | C16: 0.5 | D16: Kills | E16: 20 | F16: Assets/MachineBrigade/Resources/Data/balance.json: matchRules.starMastery.Survive

Sheet Vo_han
A1: id | B1: thu_tu_xep_hang | C1: he_so_tang_thuong | D1: nguon | E1: raw_json
A2: bossrush | B2: -bosses;+seconds;-parts | C2: 0.9 | D2: Assets/MachineBrigade/Resources/Data/balance.json: matchRules.leaderboards.bossrush | E2: ["-bosses","+seconds","-parts"]
A3: bossrushEndless | B3: -bosses;+seconds;-parts | C3: 0.9 | D3: Assets/MachineBrigade/Resources/Data/balance.json: matchRules.leaderboards.bossrushEndless | E3: ["-bosses","+seconds","-parts"]
A4: defendEndless | B4: -waves;-killedBaseCp;-seconds | C4: 0.9 | D4: Assets/MachineBrigade/Resources/Data/balance.json: matchRules.leaderboards.defendEndless | E4: ["-waves","-killedBaseCp","-seconds"]
A5: endless | B5: -waves;-killedBaseCp;-seconds | C5: 0.9 | D5: Assets/MachineBrigade/Resources/Data/balance.json: matchRules.leaderboards.endless | E5: ["-waves","-killedBaseCp","-seconds"]
A6: survivalEndless | B6: -waves;-killedBaseCp;-seconds | C6: 0.9 | D6: Assets/MachineBrigade/Resources/Data/balance.json: matchRules.leaderboards.survivalEndless | E6: ["-waves","-killedBaseCp","-seconds"]
A7: weekly | B7: -cleared;+attempts;+seconds | C7: 0.9 | D7: Assets/MachineBrigade/Resources/Data/balance.json: matchRules.leaderboards.weekly | E7: ["-cleared","+attempts","+seconds"]

Sheet Kinh_te
A1: id | B1: nhom | C1: khoa | D1: gia_tri_so | E1: gia_tri_chu | F1: don_vi | G1: nguon | H1: raw_json
A2: campaign.economy.payScale["2"] | B2: economy | C2: 2 | D2: 1.66 | G2: Assets/MachineBrigade/Resources/Data/campaign.json: economy.payScale["2"] | H2: 1.66
A3: campaign.economy.payScale["3"] | B3: economy | C3: 3 | D3: 1 | G3: Assets/MachineBrigade/Resources/Data/campaign.json: economy.payScale["3"] | H3: 1.0
A4: economy.armyCap.Campaign | B4: economy | C4: Campaign | D4: 24 | G4: Assets/MachineBrigade/Resources/Data/balance.json: economy.armyCap.Campaign | H4: 24
A5: economy.armyCap.Survival | B5: economy | C5: Survival | D5: 30 | G5: Assets/MachineBrigade/Resources/Data/balance.json: economy.armyCap.Survival | H5: 30
A6: economy.armyCap.default | B6: economy | C6: default | D6: 40 | G6: Assets/MachineBrigade/Resources/Data/balance.json: economy.armyCap.default | H6: 40
A7: economy.enemyScaling | B7: economy | C7: enemyScaling | D7: 0.55 | G7: Assets/MachineBrigade/Resources/Data/balance.json: economy.enemyScaling | H7: 0.55
A8: economy.enemyScalingModes.Weekly | B8: economy | C8: Weekly | D8: 0.5 | G8: Assets/MachineBrigade/Resources/Data/balance.json: economy.enemyScalingModes.Weekly | H8: 0.5
A9: economy.income | B9: economy | C9: income | D9: 0.9 | G9: Assets/MachineBrigade/Resources/Data/balance.json: economy.income | H9: 0.9
A10: economy.startCp.modes | B10: economy | C10: modes | E10: Conquest;Deathmatch;KingOfTheHill;Assault;Siege;Weekly;Defend;Endless;Survival;BossRush;Campaign;Showdown | G10: Assets/MachineBrigade/Resources/Data/balance.json: economy.startCp.modes | H10: ["Conquest","Deathmatch","KingOfTheHill","Assault","Siege","Weekly","Defend","Endless","Survival","BossRush","Campaign","Showdown"]
A11: economy.startCp.scale | B11: economy | C11: scale | D11: 1.16 | G11: Assets/MachineBrigade/Resources/Data/balance.json: economy.startCp.scale | H11: 1.16
A12: economy.supply | B12: economy | C12: supply | D12: 1.05 | G12: Assets/MachineBrigade/Resources/Data/balance.json: economy.supply | H12: 1.05
A13: economy.vehicleCap.Defend | B13: economy | C13: Defend | D13: 48 | G13: Assets/MachineBrigade/Resources/Data/balance.json: economy.vehicleCap.Defend | H13: 48
A14: economy.vehicleCap.Endless | B14: economy | C14: Endless | D14: 48 | G14: Assets/MachineBrigade/Resources/Data/balance.json: economy.vehicleCap.Endless | H14: 48
A15: economy.vehicleCap.Operation | B15: economy | C15: Operation | D15: 48 | G15: Assets/MachineBrigade/Resources/Data/balance.json: economy.vehicleCap.Operation | H15: 48
A16: economy.vehicleCap.Siege | B16: economy | C16: Siege | D16: 48 | G16: Assets/MachineBrigade/Resources/Data/balance.json: economy.vehicleCap.Siege | H16: 48
A17: economy.vehicleCap.default | B17: economy | C17: default | D17: 32 | G17: Assets/MachineBrigade/Resources/Data/balance.json: economy.vehicleCap.default | H17: 32
A18: ma.hoan_cp_khi_ha | B18: ma | C18: hoàn CP khi hạ, bắt kịp, thưởng rút lui, thưởng bộ phận boss, thứ tự áp | E18: kill_share 0.25; tran_hoan_khi_ha 0.45; tran_hoan_khi_mat 0.15; duong_bat_kip (ban/doi_thu:tang_thu_nhap) 1:1;0.75:1;0.6:1.1364;0.5:1.2273;0.4:1.3182;0.3:1.4091;0.2:1.5;0.1:1.5; duong_phat_tiep_te (quan/tiep_te:thu_nhap_giu) 1:1;1.25:0.875;1.5:0.75;2:0.5;2.5:0.25;3:0.25 | G18: Assets/MachineBrigade/Scripts/Sim (mã kinh tế)
A19: ma.tiep_te_cong_thuc | B19: ma | C19: tiếp tế: công thức, ngưỡng, đường phạt, tối đa -75 % | E19: armyCap = round((economy.armyCap[mode] x supplyPriceScale + bonus) x economy.supply x commander); supply = floor(armyCap x supplyPerArmyCap); income kept = max(upkeepFloor, 1 - upkeepSlope x (army - supply) / supply) above the supply | G19: Assets/MachineBrigade/Scripts/Sim (mã kinh tế)

Sheet Do_kho
A1: id | B1: he_so_dich_tran_nhanh | C1: thu_tu | D1: bien_co_ally | E1: bien_co_ally_waves | F1: bien_co_directions | G1: bien_co_elites | H1: bien_co_escorts | I1: bien_co_step | J1: bien_co_warning | K1: bien_co_wave_scale | L1: nguon | M1: raw_json
A2: Easy | B2: 0.4 | C2: 0 | D2: 0.7 | E2: -1 | F2: 1;2 | G2: FALSE | H2: 2 | I2: 0 | J2: 15 | K2: 0.7 | L2: Assets/MachineBrigade/Resources/Data/balance.json: economy.enemyScalingQuick.Easy
A3: Hard | B3: 0.85 | C3: 2 | D3: 0.3 | E3: -1 | F3: 2;3 | G3: FALSE | H3: 4 | I3: 2 | J3: 8 | K3: 1.15 | L3: Assets/MachineBrigade/Resources/Data/balance.json: economy.enemyScalingQuick.Hard
A4: Normal | B4: 0.75 | C4: 1 | D4: 0.5 | E4: -1 | F4: 2;2 | G4: FALSE | H4: 3 | I4: 1 | J4: 10 | K4: 1 | L4: Assets/MachineBrigade/Resources/Data/balance.json: economy.enemyScalingQuick.Normal
A5: VeryHard | B5: 1.08 | C5: 3 | D5: 0.15 | E5: 1 | F5: 3;4 | G5: TRUE | H5: 5 | I5: 3 | J5: 6 | K5: 1.3 | L5: Assets/MachineBrigade/Resources/Data/balance.json: economy.enemyScalingQuick.VeryHard

Sheet Diem_tac_chien
A1: id | B1: nhom | C1: khoa | D1: gia_tri_so | E1: gia_tri_chu | F1: don_vi | G1: nguon | H1: raw_json
A2: score.hq | C2: hq | D2: 2000 | G2: Assets/MachineBrigade/Resources/Data/operations.json: score.hq | H2: 2000
A3: score.losses | C3: losses | D3: 2000 | G3: Assets/MachineBrigade/Resources/Data/operations.json: score.losses | H3: 2000
A4: score.lossesAtZeroCp | C4: lossesAtZeroCp | D4: 150 | G4: Assets/MachineBrigade/Resources/Data/operations.json: score.lossesAtZeroCp | H4: 150
A5: score.par | C5: par | D5: 1500 | G5: Assets/MachineBrigade/Resources/Data/operations.json: score.par | H5: 1500
A6: score.time | C6: time | D6: 3000 | G6: Assets/MachineBrigade/Resources/Data/operations.json: score.time | H6: 3000
A7: score.win | C7: win | D7: 5000 | G7: Assets/MachineBrigade/Resources/Data/operations.json: score.win | H7: 5000
A8: weekly.fortress | C8: fortress | D8: 600 | G8: Assets/MachineBrigade/Resources/Data/operations.json: weekly.fortress | H8: 600
A9: weekly.operation | C9: operation | D9: 800 | G9: Assets/MachineBrigade/Resources/Data/operations.json: weekly.operation | H9: 800

Sheet Tac_chien_bac
A1: id | B1: enemy | C1: player_income | D1: score | E1: supports | F1: nguon | G1: raw_json
A2: heroic | B2: 1.3 | C2: 1 | D2: 1.3 | E2: TRUE | F2: Assets/MachineBrigade/Resources/Data/operations.json: tiers[1] | G2: {"id":"heroic","enemy":1.3,"playerIncome":1.0,"supports":true,"score":1.3}
A3: iron | B3: 1.3 | C3: 0.8 | D3: 1.6 | E3: FALSE | F3: Assets/MachineBrigade/Resources/Data/operations.json: tiers[2] | G3: {"id":"iron","enemy":1.3,"playerIncome":0.8,"supports":false,"score":1.6}
A4: legend | B4: 1.6 | C4: 0.75 | D4: 2 | E4: FALSE | F4: Assets/MachineBrigade/Resources/Data/operations.json: tiers[3] | G4: {"id":"legend","enemy":1.6,"playerIncome":0.75,"supports":false,"score":2.0}
A5: normal | B5: 1 | C5: 1 | D5: 1 | E5: TRUE | F5: Assets/MachineBrigade/Resources/Data/operations.json: tiers[0] | G5: {"id":"normal","enemy":1.0,"playerIncome":1.0,"supports":true,"score":1.0}

Sheet Mutator
A1: id | B1: excludes | C1: class | D1: both_damage | E1: both_hp | F1: empty_base | G1: enemy_air | H1: enemy_cp | I1: enemy_hp | J1: enemy_income | K1: extra_boss | L1: extra_escorts | M1: extra_raiders | N1: no_air | O1: no_repair | P1: no_supports | Q1: player_heavy | R1: player_income | S1: player_max_cp | T1: raids | U1: score | V1: sea_sight | W1: swarm | X1: time_scale | Y1: tower_damage | Z1: tower_hp | AA1: weather | AB1: nguon | AC1: raw_json
A2: armour_only | B2: light_deck;enemy_air | C2: rule | Q2: TRUE | U2: 0.15 | AB2: Assets/MachineBrigade/Resources/Data/operations.json: mutators[8] | AC2: {"id":"armour_only","class":"rule","score":0.15,"playerHeavy":true,"excludes":["light_deck","enemy_air"]}
A3: empty_base | B3: towers_x2 | C3: pressure | F3: TRUE | U3: 0.25 | AB3: Assets/MachineBrigade/Resources/Data/operations.json: mutators[16] | AC3: {"id":"empty_base","class":"pressure","score":0.25,"emptyBase":true,"excludes":["towers_x2"]}
A4: enemy_air | B4: no_air;armour_only;light_deck | C4: pressure | G4: TRUE | U4: 0.25 | AB4: Assets/MachineBrigade/Resources/Data/operations.json: mutators[1] | AC4: {"id":"enemy_air","class":"pressure","score":0.25,"enemyAir":true,"excludes":["no_air","armour_only","light_deck"]}
A5: fleet | C5: pressure | J5: 1.1 | L5: 1 | M5: 2 | U5: 0.2 | AB5: Assets/MachineBrigade/Resources/Data/operations.json: mutators[19] | AC5: {"id":"fleet","class":"pressure","score":0.2,"extraEscorts":1,"extraRaiders":2,"enemyIncome":1.1}
A6: general_boost | B6: veterans | C6: pressure | H6: 1.5 | J6: 1.3 | U6: 0.25 | AB6: Assets/MachineBrigade/Resources/Data/operations.json: mutators[6] | AC6: {"id":"general_boost","class":"pressure","score":0.25,"enemyCp":1.5,"enemyIncome":1.3,"excludes":["veterans"]}
A7: glass_cannon | C7: rule | D7: 1.5 | E7: 0.75 | U7: 0.1 | AB7: Assets/MachineBrigade/Resources/Data/operations.json: mutators[10] | AC7: {"id":"glass_cannon","class":"rule","score":0.1,"bothDamage":1.5,"bothHp":0.75}
A8: iron_rain | C8: rule | T8: TRUE | U8: 0.1 | AB8: Assets/MachineBrigade/Resources/Data/operations.json: mutators[14] | AC8: {"id":"iron_rain","class":"rule","score":0.1,"raids":true}
A9: lean_logistics | C9: pressure | R9: 0.75 | U9: 0.2 | AB9: Assets/MachineBrigade/Resources/Data/operations.json: mutators[13] | AC9: {"id":"lean_logistics","class":"pressure","score":0.2,"playerIncome":0.75}
A10: light_deck | B10: armour_only | C10: rule | S10: 8 | U10: 0.2 | AB10: Assets/MachineBrigade/Resources/Data/operations.json: mutators[7] | AC10: {"id":"light_deck","class":"rule","score":0.2,"playerMaxCp":8,"excludes":["armour_only"]}
A11: night_ops | B11: storm | C11: rule | U11: 0.05 | AA11: Night | AB11: Assets/MachineBrigade/Resources/Data/operations.json: mutators[17] | AC11: {"id":"night_ops","class":"rule","score":0.05,"weather":"Night","excludes":["storm"]}
A12: no_air | B12: enemy_air | C12: rule | N12: TRUE | U12: 0.1 | AB12: Assets/MachineBrigade/Resources/Data/operations.json: mutators[9] | AC12: {"id":"no_air","class":"rule","score":0.1,"noAir":true,"excludes":["enemy_air"]}
A13: no_repair | C13: rule | O13: TRUE | U13: 0.15 | AB13: Assets/MachineBrigade/Resources/Data/operations.json: mutators[5] | AC13: {"id":"no_repair","class":"rule","score":0.15,"noRepair":true}
A14: no_support | C14: rule | P14: TRUE | U14: 0.2 | AB14: Assets/MachineBrigade/Resources/Data/operations.json: mutators[2] | AC14: {"id":"no_support","class":"rule","score":0.2,"noSupports":true}
A15: sea_storm | B15: storm | C15: rule | U15: 0.15 | V15: 0.55 | AA15: Storm | AB15: Assets/MachineBrigade/Resources/Data/operations.json: mutators[18] | AC15: {"id":"sea_storm","class":"rule","score":0.15,"weather":"Storm","seaSight":0.55,"excludes":["storm"]}
A16: storm | C16: rule | U16: 0.05 | AA16: Storm | AB16: Assets/MachineBrigade/Resources/Data/operations.json: mutators[0] | AC16: {"id":"storm","class":"rule","score":0.05,"weather":"Storm"}
A17: swarm | C17: pressure | U17: 0.2 | W17: TRUE | AB17: Assets/MachineBrigade/Resources/Data/operations.json: mutators[15] | AC17: {"id":"swarm","class":"pressure","score":0.2,"swarm":true}
A18: time_attack | B18: two_bosses | C18: pressure | U18: 0.2 | X18: 0.7 | AB18: Assets/MachineBrigade/Resources/Data/operations.json: mutators[12] | AC18: {"id":"time_attack","class":"pressure","score":0.2,"timeScale":0.7,"excludes":["two_bosses"]}
A19: towers_x2 | C19: pressure | U19: 0.2 | Y19: 1.5 | Z19: 2 | AB19: Assets/MachineBrigade/Resources/Data/operations.json: mutators[4] | AC19: {"id":"towers_x2","class":"pressure","score":0.2,"towerHp":2.0,"towerDamage":1.5}
A20: two_bosses | B20: time_attack | C20: pressure | K20: TRUE | U20: 0.3 | AB20: Assets/MachineBrigade/Resources/Data/operations.json: mutators[3] | AC20: {"id":"two_bosses","class":"pressure","score":0.3,"extraBoss":true,"excludes":["time_attack"]}
A21: veterans | B21: general_boost | C21: pressure | I21: 1.25 | U21: 0.2 | AB21: Assets/MachineBrigade/Resources/Data/operations.json: mutators[11] | AC21: {"id":"veterans","class":"pressure","score":0.2,"enemyHp":1.25,"excludes":["general_boost"]}

Sheet Che_do_thoi_luong
A1: id | B1: doc_gio_du_lieu | C1: gio_bat_dau_ma_s | D1: thuong_giai_doan_s | E1: tran_quy_ma_s | F1: dot_dau_s | G1: cach_dot_s | H1: nguon_ma | I1: gio_du_lieu_s | J1: hiep_phu_s | K1: gio_vao_tran_s | L1: quy_cong_them_s | M1: thoi_luong_toi_da_s | N1: thang_som_nhat_s | O1: so_ha_toi_thieu | P1: dot_cuoi_bat_dau_s | Q1: thoi_luong_tham_chieu_s | R1: lech_gio_du_lieu_s | S1: nguon | T1: raw_json
A2: assault | B2: FALSE | C2: 300 | H2: Game/Match/ModeSessions.cs:602 | I2: =IF(ISNUMBER(Che_do!$AK$2),Che_do!$AK$2,"") | J2: =IF(ISNUMBER(Che_do!$AA$2),Che_do!$AA$2,0)+IF(ISNUMBER(Che_do!$AH$2),Che_do!$AH$2,0) | K2: =IF(AND($B$2,ISNUMBER($I$2)),$I$2,IF(ISNUMBER(Che_do!$AG$2),Che_do!$AG$2*$C$2/300,IF(ISNUMBER($C$2),$C$2,""))) | L2: =IF(ISNUMBER(Che_do!$AF$2),2*MIN(Che_do!$AF$2,Che_do!$X$2),IF(ISNUMBER($D$2),MIN($D$2,2*$E$2),0)) | M2: =IF(ISNUMBER($K$2),$K$2+$L$2+$J$2,"") | N2: =IF(ISNUMBER(Che_do!$L$2),IF(Che_do!$AD$2/(Che_do!$L$2*3)<=Che_do!$AK$2-Che_do!$R$2,Che_do!$AD$2/(Che_do!$L$2*3),Che_do!$AK$2-Che_do!$R$2+(Che_do!$AD$2-Che_do!$L$2*3*(Che_do!$AK$2-Che_do!$R$2))/(Che_do!$L$2*3*Che_do!$S$2)),IF(ISNUMBER(Che_do!$AC$2),Che_do!$AJ$2/Che_do!$AC$2,"")) | O2: =IF(ISNUMBER(Che_do!$T$2),CEILING(Che_do!$AJ$2/Che_do!$T$2,1),"") | P2: =IF(ISNUMBER($F$2),$F$2+(Che_do!$AL$2-1)*$G$2,"") | Q2: =IF(ISNUMBER($M$2),$M$2,IF(ISNUMBER($P$2),$P$2,"")) | R2: =IF(AND(ISNUMBER($I$2),ISNUMBER($C$2),NOT($B$2)),$I$2-($C$2+$L$2),"") | S2: 04_che_do_kinh_te_ai/Che_do (assault) + C# của chế độ
A3: bossrush | B3: FALSE | C3: 1800 | H3: tunables.json: bosses.bossHunts.weeklyMinutes.value | I3: =IF(ISNUMBER(Che_do!$AK$3),Che_do!$AK$3,"") | J3: =IF(ISNUMBER(Che_do!$AA$3),Che_do!$AA$3,0)+IF(ISNUMBER(Che_do!$AH$3),Che_do!$AH$3,0) | K3: =IF(AND($B$3,ISNUMBER($I$3)),$I$3,IF(ISNUMBER(Che_do!$AG$3),Che_do!$AG$3*$C$3/300,IF(ISNUMBER($C$3),$C$3,""))) | L3: =IF(ISNUMBER(Che_do!$AF$3),2*MIN(Che_do!$AF$3,Che_do!$X$3),IF(ISNUMBER($D$3),MIN($D$3,2*$E$3),0)) | M3: =IF(ISNUMBER($K$3),$K$3+$L$3+$J$3,"") | N3: =IF(ISNUMBER(Che_do!$L$3),IF(Che_do!$AD$3/(Che_do!$L$3*3)<=Che_do!$AK$3-Che_do!$R$3,Che_do!$AD$3/(Che_do!$L$3*3),Che_do!$AK$3-Che_do!$R$3+(Che_do!$AD$3-Che_do!$L$3*3*(Che_do!$AK$3-Che_do!$R$3))/(Che_do!$L$3*3*Che_do!$S$3)),IF(ISNUMBER(Che_do!$AC$3),Che_do!$AJ$3/Che_do!$AC$3,"")) | O3: =IF(ISNUMBER(Che_do!$T$3),CEILING(Che_do!$AJ$3/Che_do!$T$3,1),"") | P3: =IF(ISNUMBER($F$3),$F$3+(Che_do!$AL$3-1)*$G$3,"") | Q3: =IF(ISNUMBER($M$3),$M$3,IF(ISNUMBER($P$3),$P$3,"")) | R3: =IF(AND(ISNUMBER($I$3),ISNUMBER($C$3),NOT($B$3)),$I$3-($C$3+$L$3),"") | S3: 04_che_do_kinh_te_ai/Che_do (bossrush) + C# của chế độ
A4: conquest | B4: TRUE | I4: =IF(ISNUMBER(Che_do!$AK$4),Che_do!$AK$4,"") | J4: =IF(ISNUMBER(Che_do!$AA$4),Che_do!$AA$4,0)+IF(ISNUMBER(Che_do!$AH$4),Che_do!$AH$4,0) | K4: =IF(AND($B$4,ISNUMBER($I$4)),$I$4,IF(ISNUMBER(Che_do!$AG$4),Che_do!$AG$4*$C$4/300,IF(ISNUMBER($C$4),$C$4,""))) | L4: =IF(ISNUMBER(Che_do!$AF$4),2*MIN(Che_do!$AF$4,Che_do!$X$4),IF(ISNUMBER($D$4),MIN($D$4,2*$E$4),0)) | M4: =IF(ISNUMBER($K$4),$K$4+$L$4+$J$4,"") | N4: =IF(ISNUMBER(Che_do!$L$4),IF(Che_do!$AD$4/(Che_do!$L$4*3)<=Che_do!$AK$4-Che_do!$R$4,Che_do!$AD$4/(Che_do!$L$4*3),Che_do!$AK$4-Che_do!$R$4+(Che_do!$AD$4-Che_do!$L$4*3*(Che_do!$AK$4-Che_do!$R$4))/(Che_do!$L$4*3*Che_do!$S$4)),IF(ISNUMBER(Che_do!$AC$4),Che_do!$AJ$4/Che_do!$AC$4,"")) | O4: =IF(ISNUMBER(Che_do!$T$4),CEILING(Che_do!$AJ$4/Che_do!$T$4,1),"") | P4: =IF(ISNUMBER($F$4),$F$4+(Che_do!$AL$4-1)*$G$4,"") | Q4: =IF(ISNUMBER($M$4),$M$4,IF(ISNUMBER($P$4),$P$4,"")) | R4: =IF(AND(ISNUMBER($I$4),ISNUMBER($C$4),NOT($B$4)),$I$4-($C$4+$L$4),"") | S4: 04_che_do_kinh_te_ai/Che_do (conquest) + C# của chế độ
A5: deathmatch | B5: TRUE | I5: =IF(ISNUMBER(Che_do!$AK$5),Che_do!$AK$5,"") | J5: =IF(ISNUMBER(Che_do!$AA$5),Che_do!$AA$5,0)+IF(ISNUMBER(Che_do!$AH$5),Che_do!$AH$5,0) | K5: =IF(AND($B$5,ISNUMBER($I$5)),$I$5,IF(ISNUMBER(Che_do!$AG$5),Che_do!$AG$5*$C$5/300,IF(ISNUMBER($C$5),$C$5,""))) | L5: =IF(ISNUMBER(Che_do!$AF$5),2*MIN(Che_do!$AF$5,Che_do!$X$5),IF(ISNUMBER($D$5),MIN($D$5,2*$E$5),0)) | M5: =IF(ISNUMBER($K$5),$K$5+$L$5+$J$5,"") | N5: =IF(ISNUMBER(Che_do!$L$5),IF(Che_do!$AD$5/(Che_do!$L$5*3)<=Che_do!$AK$5-Che_do!$R$5,Che_do!$AD$5/(Che_do!$L$5*3),Che_do!$AK$5-Che_do!$R$5+(Che_do!$AD$5-Che_do!$L$5*3*(Che_do!$AK$5-Che_do!$R$5))/(Che_do!$L$5*3*Che_do!$S$5)),IF(ISNUMBER(Che_do!$AC$5),Che_do!$AJ$5/Che_do!$AC$5,"")) | O5: =IF(ISNUMBER(Che_do!$T$5),CEILING(Che_do!$AJ$5/Che_do!$T$5,1),"") | P5: =IF(ISNUMBER($F$5),$F$5+(Che_do!$AL$5-1)*$G$5,"") | Q5: =IF(ISNUMBER($M$5),$M$5,IF(ISNUMBER($P$5),$P$5,"")) | R5: =IF(AND(ISNUMBER($I$5),ISNUMBER($C$5),NOT($B$5)),$I$5-($C$5+$L$5),"") | S5: 04_che_do_kinh_te_ai/Che_do (deathmatch) + C# của chế độ
A6: defend | B6: TRUE | C6: 480 | D6: 150 | E6: 900 | H6: Game/Match/ModeSessions.cs:691 | I6: =IF(ISNUMBER(Che_do!$AK$6),Che_do!$AK$6,"") | J6: =IF(ISNUMBER(Che_do!$AA$6),Che_do!$AA$6,0)+IF(ISNUMBER(Che_do!$AH$6),Che_do!$AH$6,0) | K6: =IF(AND($B$6,ISNUMBER($I$6)),$I$6,IF(ISNUMBER(Che_do!$AG$6),Che_do!$AG$6*$C$6/300,IF(ISNUMBER($C$6),$C$6,""))) | L6: =IF(ISNUMBER(Che_do!$AF$6),2*MIN(Che_do!$AF$6,Che_do!$X$6),IF(ISNUMBER($D$6),MIN($D$6,2*$E$6),0)) | M6: =IF(ISNUMBER($K$6),$K$6+$L$6+$J$6,"") | N6: =IF(ISNUMBER(Che_do!$L$6),IF(Che_do!$AD$6/(Che_do!$L$6*3)<=Che_do!$AK$6-Che_do!$R$6,Che_do!$AD$6/(Che_do!$L$6*3),Che_do!$AK$6-Che_do!$R$6+(Che_do!$AD$6-Che_do!$L$6*3*(Che_do!$AK$6-Che_do!$R$6))/(Che_do!$L$6*3*Che_do!$S$6)),IF(ISNUMBER(Che_do!$AC$6),Che_do!$AJ$6/Che_do!$AC$6,"")) | O6: =IF(ISNUMBER(Che_do!$T$6),CEILING(Che_do!$AJ$6/Che_do!$T$6,1),"") | P6: =IF(ISNUMBER($F$6),$F$6+(Che_do!$AL$6-1)*$G$6,"") | Q6: =IF(ISNUMBER($M$6),$M$6,IF(ISNUMBER($P$6),$P$6,"")) | R6: =IF(AND(ISNUMBER($I$6),ISNUMBER($C$6),NOT($B$6)),$I$6-($C$6+$L$6),"") | S6: 04_che_do_kinh_te_ai/Che_do (defend) + C# của chế độ
A7: endless | B7: FALSE | I7: =IF(ISNUMBER(Che_do!$AK$7),Che_do!$AK$7,"") | J7: =IF(ISNUMBER(Che_do!$AA$7),Che_do!$AA$7,0)+IF(ISNUMBER(Che_do!$AH$7),Che_do!$AH$7,0) | K7: =IF(AND($B$7,ISNUMBER($I$7)),$I$7,IF(ISNUMBER(Che_do!$AG$7),Che_do!$AG$7*$C$7/300,IF(ISNUMBER($C$7),$C$7,""))) | L7: =IF(ISNUMBER(Che_do!$AF$7),2*MIN(Che_do!$AF$7,Che_do!$X$7),IF(ISNUMBER($D$7),MIN($D$7,2*$E$7),0)) | M7: =IF(ISNUMBER($K$7),$K$7+$L$7+$J$7,"") | N7: =IF(ISNUMBER(Che_do!$L$7),IF(Che_do!$AD$7/(Che_do!$L$7*3)<=Che_do!$AK$7-Che_do!$R$7,Che_do!$AD$7/(Che_do!$L$7*3),Che_do!$AK$7-Che_do!$R$7+(Che_do!$AD$7-Che_do!$L$7*3*(Che_do!$AK$7-Che_do!$R$7))/(Che_do!$L$7*3*Che_do!$S$7)),IF(ISNUMBER(Che_do!$AC$7),Che_do!$AJ$7/Che_do!$AC$7,"")) | O7: =IF(ISNUMBER(Che_do!$T$7),CEILING(Che_do!$AJ$7/Che_do!$T$7,1),"") | P7: =IF(ISNUMBER($F$7),$F$7+(Che_do!$AL$7-1)*$G$7,"") | Q7: =IF(ISNUMBER($M$7),$M$7,IF(ISNUMBER($P$7),$P$7,"")) | R7: =IF(AND(ISNUMBER($I$7),ISNUMBER($C$7),NOT($B$7)),$I$7-($C$7+$L$7),"") | S7: 04_che_do_kinh_te_ai/Che_do (endless) + C# của chế độ
A8: hill | B8: TRUE | I8: =IF(ISNUMBER(Che_do!$AK$8),Che_do!$AK$8,"") | J8: =IF(ISNUMBER(Che_do!$AA$8),Che_do!$AA$8,0)+IF(ISNUMBER(Che_do!$AH$8),Che_do!$AH$8,0) | K8: =IF(AND($B$8,ISNUMBER($I$8)),$I$8,IF(ISNUMBER(Che_do!$AG$8),Che_do!$AG$8*$C$8/300,IF(ISNUMBER($C$8),$C$8,""))) | L8: =IF(ISNUMBER(Che_do!$AF$8),2*MIN(Che_do!$AF$8,Che_do!$X$8),IF(ISNUMBER($D$8),MIN($D$8,2*$E$8),0)) | M8: =IF(ISNUMBER($K$8),$K$8+$L$8+$J$8,"") | N8: =IF(ISNUMBER(Che_do!$L$8),IF(Che_do!$AD$8/(Che_do!$L$8*3)<=Che_do!$AK$8-Che_do!$R$8,Che_do!$AD$8/(Che_do!$L$8*3),Che_do!$AK$8-Che_do!$R$8+(Che_do!$AD$8-Che_do!$L$8*3*(Che_do!$AK$8-Che_do!$R$8))/(Che_do!$L$8*3*Che_do!$S$8)),IF(ISNUMBER(Che_do!$AC$8),Che_do!$AJ$8/Che_do!$AC$8,"")) | O8: =IF(ISNUMBER(Che_do!$T$8),CEILING(Che_do!$AJ$8/Che_do!$T$8,1),"") | P8: =IF(ISNUMBER($F$8),$F$8+(Che_do!$AL$8-1)*$G$8,"") | Q8: =IF(ISNUMBER($M$8),$M$8,IF(ISNUMBER($P$8),$P$8,"")) | R8: =IF(AND(ISNUMBER($I$8),ISNUMBER($C$8),NOT($B$8)),$I$8-($C$8+$L$8),"") | S8: 04_che_do_kinh_te_ai/Che_do (hill) + C# của chế độ
A9: operations | B9: FALSE | I9: =IF(ISNUMBER(Che_do!$AK$9),Che_do!$AK$9,"") | J9: =IF(ISNUMBER(Che_do!$AA$9),Che_do!$AA$9,0)+IF(ISNUMBER(Che_do!$AH$9),Che_do!$AH$9,0) | K9: =IF(AND($B$9,ISNUMBER($I$9)),$I$9,IF(ISNUMBER(Che_do!$AG$9),Che_do!$AG$9*$C$9/300,IF(ISNUMBER($C$9),$C$9,""))) | L9: =IF(ISNUMBER(Che_do!$AF$9),2*MIN(Che_do!$AF$9,Che_do!$X$9),IF(ISNUMBER($D$9),MIN($D$9,2*$E$9),0)) | M9: =IF(ISNUMBER($K$9),$K$9+$L$9+$J$9,"") | N9: =IF(ISNUMBER(Che_do!$L$9),IF(Che_do!$AD$9/(Che_do!$L$9*3)<=Che_do!$AK$9-Che_do!$R$9,Che_do!$AD$9/(Che_do!$L$9*3),Che_do!$AK$9-Che_do!$R$9+(Che_do!$AD$9-Che_do!$L$9*3*(Che_do!$AK$9-Che_do!$R$9))/(Che_do!$L$9*3*Che_do!$S$9)),IF(ISNUMBER(Che_do!$AC$9),Che_do!$AJ$9/Che_do!$AC$9,"")) | O9: =IF(ISNUMBER(Che_do!$T$9),CEILING(Che_do!$AJ$9/Che_do!$T$9,1),"") | P9: =IF(ISNUMBER($F$9),$F$9+(Che_do!$AL$9-1)*$G$9,"") | Q9: =IF(ISNUMBER($M$9),$M$9,IF(ISNUMBER($P$9),$P$9,"")) | R9: =IF(AND(ISNUMBER($I$9),ISNUMBER($C$9),NOT($B$9)),$I$9-($C$9+$L$9),"") | S9: 04_che_do_kinh_te_ai/Che_do (operations) + C# của chế độ
A10: showdown | B10: TRUE | I10: =IF(ISNUMBER(Che_do!$AK$10),Che_do!$AK$10,"") | J10: =IF(ISNUMBER(Che_do!$AA$10),Che_do!$AA$10,0)+IF(ISNUMBER(Che_do!$AH$10),Che_do!$AH$10,0) | K10: =IF(AND($B$10,ISNUMBER($I$10)),$I$10,IF(ISNUMBER(Che_do!$AG$10),Che_do!$AG$10*$C$10/300,IF(ISNUMBER($C$10),$C$10,""))) | L10: =IF(ISNUMBER(Che_do!$AF$10),2*MIN(Che_do!$AF$10,Che_do!$X$10),IF(ISNUMBER($D$10),MIN($D$10,2*$E$10),0)) | M10: =IF(ISNUMBER($K$10),$K$10+$L$10+$J$10,"") | N10: =IF(ISNUMBER(Che_do!$L$10),IF(Che_do!$AD$10/(Che_do!$L$10*3)<=Che_do!$AK$10-Che_do!$R$10,Che_do!$AD$10/(Che_do!$L$10*3),Che_do!$AK$10-Che_do!$R$10+(Che_do!$AD$10-Che_do!$L$10*3*(Che_do!$AK$10-Che_do!$R$10))/(Che_do!$L$10*3*Che_do!$S$10)),IF(ISNUMBER(Che_do!$AC$10),Che_do!$AJ$10/Che_do!$AC$10,"")) | O10: =IF(ISNUMBER(Che_do!$T$10),CEILING(Che_do!$AJ$10/Che_do!$T$10,1),"") | P10: =IF(ISNUMBER($F$10),$F$10+(Che_do!$AL$10-1)*$G$10,"") | Q10: =IF(ISNUMBER($M$10),$M$10,IF(ISNUMBER($P$10),$P$10,"")) | R10: =IF(AND(ISNUMBER($I$10),ISNUMBER($C$10),NOT($B$10)),$I$10-($C$10+$L$10),"") | S10: 04_che_do_kinh_te_ai/Che_do (showdown) + C# của chế độ
A11: siege | B11: TRUE | C11: 480 | D11: 600 | E11: 900 | H11: Game/Match/ModeSessions.cs:874, 879 | I11: =IF(ISNUMBER(Che_do!$AK$11),Che_do!$AK$11,"") | J11: =IF(ISNUMBER(Che_do!$AA$11),Che_do!$AA$11,0)+IF(ISNUMBER(Che_do!$AH$11),Che_do!$AH$11,0) | K11: =IF(AND($B$11,ISNUMBER($I$11)),$I$11,IF(ISNUMBER(Che_do!$AG$11),Che_do!$AG$11*$C$11/300,IF(ISNUMBER($C$11),$C$11,""))) | L11: =IF(ISNUMBER(Che_do!$AF$11),2*MIN(Che_do!$AF$11,Che_do!$X$11),IF(ISNUMBER($D$11),MIN($D$11,2*$E$11),0)) | M11: =IF(ISNUMBER($K$11),$K$11+$L$11+$J$11,"") | N11: =IF(ISNUMBER(Che_do!$L$11),IF(Che_do!$AD$11/(Che_do!$L$11*3)<=Che_do!$AK$11-Che_do!$R$11,Che_do!$AD$11/(Che_do!$L$11*3),Che_do!$AK$11-Che_do!$R$11+(Che_do!$AD$11-Che_do!$L$11*3*(Che_do!$AK$11-Che_do!$R$11))/(Che_do!$L$11*3*Che_do!$S$11)),IF(ISNUMBER(Che_do!$AC$11),Che_do!$AJ$11/Che_do!$AC$11,"")) | O11: =IF(ISNUMBER(Che_do!$T$11),CEILING(Che_do!$AJ$11/Che_do!$T$11,1),"") | P11: =IF(ISNUMBER($F$11),$F$11+(Che_do!$AL$11-1)*$G$11,"") | Q11: =IF(ISNUMBER($M$11),$M$11,IF(ISNUMBER($P$11),$P$11,"")) | R11: =IF(AND(ISNUMBER($I$11),ISNUMBER($C$11),NOT($B$11)),$I$11-($C$11+$L$11),"") | S11: 04_che_do_kinh_te_ai/Che_do (siege) + C# của chế độ
A12: survival | B12: FALSE | F12: 20 | G12: 30 | H12: tunables.json: modes.sandboxMode.firstWaveDelay.value, tunables.json: modes.sandboxMode.waveInterval.value | I12: =IF(ISNUMBER(Che_do!$AK$12),Che_do!$AK$12,"") | J12: =IF(ISNUMBER(Che_do!$AA$12),Che_do!$AA$12,0)+IF(ISNUMBER(Che_do!$AH$12),Che_do!$AH$12,0) | K12: =IF(AND($B$12,ISNUMBER($I$12)),$I$12,IF(ISNUMBER(Che_do!$AG$12),Che_do!$AG$12*$C$12/300,IF(ISNUMBER($C$12),$C$12,""))) | L12: =IF(ISNUMBER(Che_do!$AF$12),2*MIN(Che_do!$AF$12,Che_do!$X$12),IF(ISNUMBER($D$12),MIN($D$12,2*$E$12),0)) | M12: =IF(ISNUMBER($K$12),$K$12+$L$12+$J$12,"") | N12: =IF(ISNUMBER(Che_do!$L$12),IF(Che_do!$AD$12/(Che_do!$L$12*3)<=Che_do!$AK$12-Che_do!$R$12,Che_do!$AD$12/(Che_do!$L$12*3),Che_do!$AK$12-Che_do!$R$12+(Che_do!$AD$12-Che_do!$L$12*3*(Che_do!$AK$12-Che_do!$R$12))/(Che_do!$L$12*3*Che_do!$S$12)),IF(ISNUMBER(Che_do!$AC$12),Che_do!$AJ$12/Che_do!$AC$12,"")) | O12: =IF(ISNUMBER(Che_do!$T$12),CEILING(Che_do!$AJ$12/Che_do!$T$12,1),"") | P12: =IF(ISNUMBER($F$12),$F$12+(Che_do!$AL$12-1)*$G$12,"") | Q12: =IF(ISNUMBER($M$12),$M$12,IF(ISNUMBER($P$12),$P$12,"")) | R12: =IF(AND(ISNUMBER($I$12),ISNUMBER($C$12),NOT($B$12)),$I$12-($C$12+$L$12),"") | S12: 04_che_do_kinh_te_ai/Che_do (survival) + C# của chế độ
A13: weekly | B13: TRUE | C13: 300 | D13: 540 | E13: 600 | H13: Game/Match/ModeSessions.cs:797, Sim/Modes/SiegeModes.cs:56 | I13: =IF(ISNUMBER(Che_do!$AK$13),Che_do!$AK$13,"") | J13: =IF(ISNUMBER(Che_do!$AA$13),Che_do!$AA$13,0)+IF(ISNUMBER(Che_do!$AH$13),Che_do!$AH$13,0) | K13: =IF(AND($B$13,ISNUMBER($I$13)),$I$13,IF(ISNUMBER(Che_do!$AG$13),Che_do!$AG$13*$C$13/300,IF(ISNUMBER($C$13),$C$13,""))) | L13: =IF(ISNUMBER(Che_do!$AF$13),2*MIN(Che_do!$AF$13,Che_do!$X$13),IF(ISNUMBER($D$13),MIN($D$13,2*$E$13),0)) | M13: =IF(ISNUMBER($K$13),$K$13+$L$13+$J$13,"") | N13: =IF(ISNUMBER(Che_do!$L$13),IF(Che_do!$AD$13/(Che_do!$L$13*3)<=Che_do!$AK$13-Che_do!$R$13,Che_do!$AD$13/(Che_do!$L$13*3),Che_do!$AK$13-Che_do!$R$13+(Che_do!$AD$13-Che_do!$L$13*3*(Che_do!$AK$13-Che_do!$R$13))/(Che_do!$L$13*3*Che_do!$S$13)),IF(ISNUMBER(Che_do!$AC$13),Che_do!$AJ$13/Che_do!$AC$13,"")) | O13: =IF(ISNUMBER(Che_do!$T$13),CEILING(Che_do!$AJ$13/Che_do!$T$13,1),"") | P13: =IF(ISNUMBER($F$13),$F$13+(Che_do!$AL$13-1)*$G$13,"") | Q13: =IF(ISNUMBER($M$13),$M$13,IF(ISNUMBER($P$13),$P$13,"")) | R13: =IF(AND(ISNUMBER($I$13),ISNUMBER($C$13),NOT($B$13)),$I$13-($C$13+$L$13),"") | S13: 04_che_do_kinh_te_ai/Che_do (weekly) + C# của chế độ

Sheet Kinh_te_suy_ra
A1: id | B1: che_do | C1: do_kho | D1: cp_khoi_dau_nguoi_choi_ma | E1: thu_nhap_nguoi_choi_ma_cp_s | F1: cp_khoi_dau_dich_ma | G1: thu_nhap_dich_ma_cp_s | H1: he_so_dich_che_do | I1: he_so_dich_do_kho | J1: thuong_muc_tieu_cp_s | K1: ghi_chu | L1: nguon_ma | M1: cp_khoi_dau_nguoi_choi | N1: cp_khoi_dau_nguoi_choi_game | O1: cp_khoi_dau_dich | P1: cp_khoi_dau_dich_game | Q1: thu_nhap_nguoi_choi_cp_s | R1: thu_nhap_nguoi_choi_cp_s_game | S1: thu_nhap_dich_cp_s | T1: thu_nhap_dich_cp_s_game | U1: thoi_luong_tham_chieu_s | V1: cp_nguoi_choi_25 | W1: cp_nguoi_choi_50 | X1: cp_nguoi_choi_75 | Y1: cp_nguoi_choi_100 | Z1: cp_dich_25 | AA1: cp_dich_50 | AB1: cp_dich_75 | AC1: cp_dich_100 | AD1: ty_le_dich_nguoi_choi_100 | AE1: nguon | AF1: raw_json
A2: assault/Easy | B2: assault | C2: Easy | D2: 20 | E2: 1.45 | F2: 32 | G2: 1.3 | H2: 1 | I2: 0.8 | J2: 0 | K2: thưởng khu (8 CP, +0,25 CP/s mỗi khu) không tính | L2: Game/Match/ModeSessions.cs:606; Sim/AI/ConquestAi.cs:65 | M2: =IF(ISNUMBER($D$2),IF(AND(ISNUMBER(FIND(";"&Che_do!$B$2&";",";"&Kinh_te!$E$10&";")),$D$2>0,Kinh_te!$D$11<>1),ROUND($D$2*Kinh_te!$D$11,0),$D$2),"") | N2: 23 | O2: =IF(ISNUMBER($F$2),IF(AND(ISNUMBER(FIND(";"&Che_do!$B$2&";",";"&Kinh_te!$E$10&";")),$F$2>0,Kinh_te!$D$11<>1),ROUND($F$2*Kinh_te!$D$11,0),$F$2),"") | P2: 37 | Q2: =($E$2+$J$2)*Kinh_te!$D$9 | R2: 1.305 | S2: =IF(ISNUMBER($G$2),($G$2+$J$2)*Kinh_te!$D$9*$H$2*$I$2,"") | T2: 0.936 | U2: =Che_do_thoi_luong!$Q$2 | V2: =IF(AND(ISNUMBER($U$2),ISNUMBER($M$2)),$M$2+$Q$2*0.25*$U$2,"") | W2: =IF(AND(ISNUMBER($U$2),ISNUMBER($M$2)),$M$2+$Q$2*0.5*$U$2,"") | X2: =IF(AND(ISNUMBER($U$2),ISNUMBER($M$2)),$M$2+$Q$2*0.75*$U$2,"") | Y2: =IF(AND(ISNUMBER($U$2),ISNUMBER($M$2)),$M$2+$Q$2*1.0*$U$2,"") | Z2: =IF(AND(ISNUMBER($U$2),ISNUMBER($O$2)),$O$2+$S$2*0.25*$U$2,"") | AA2: =IF(AND(ISNUMBER($U$2),ISNUMBER($O$2)),$O$2+$S$2*0.5*$U$2,"") | AB2: =IF(AND(ISNUMBER($U$2),ISNUMBER($O$2)),$O$2+$S$2*0.75*$U$2,"") | AC2: =IF(AND(ISNUMBER($U$2),ISNUMBER($O$2)),$O$2+$S$2*1.0*$U$2,"") | AD2: =IF(AND(ISNUMBER($AC$2),ISNUMBER($Y$2)),$AC$2/$Y$2,"") | AE2: C#: Game/Match/ModeSessions.cs:606; Sim/AI/ConquestAi.cs:65
A3: assault/Hard | B3: assault | C3: Hard | D3: 20 | E3: 1.45 | F3: 32 | G3: 1.3 | H3: 1 | I3: 1.2 | J3: 0 | K3: thưởng khu (8 CP, +0,25 CP/s mỗi khu) không tính | L3: Game/Match/ModeSessions.cs:606; Sim/AI/ConquestAi.cs:68 | M3: =IF(ISNUMBER($D$3),IF(AND(ISNUMBER(FIND(";"&Che_do!$B$2&";",";"&Kinh_te!$E$10&";")),$D$3>0,Kinh_te!$D$11<>1),ROUND($D$3*Kinh_te!$D$11,0),$D$3),"") | N3: 23 | O3: =IF(ISNUMBER($F$3),IF(AND(ISNUMBER(FIND(";"&Che_do!$B$2&";",";"&Kinh_te!$E$10&";")),$F$3>0,Kinh_te!$D$11<>1),ROUND($F$3*Kinh_te!$D$11,0),$F$3),"") | P3: 37 | Q3: =($E$3+$J$3)*Kinh_te!$D$9 | R3: 1.305 | S3: =IF(ISNUMBER($G$3),($G$3+$J$3)*Kinh_te!$D$9*$H$3*$I$3,"") | T3: 1.404 | U3: =Che_do_thoi_luong!$Q$2 | V3: =IF(AND(ISNUMBER($U$3),ISNUMBER($M$3)),$M$3+$Q$3*0.25*$U$3,"") | W3: =IF(AND(ISNUMBER($U$3),ISNUMBER($M$3)),$M$3+$Q$3*0.5*$U$3,"") | X3: =IF(AND(ISNUMBER($U$3),ISNUMBER($M$3)),$M$3+$Q$3*0.75*$U$3,"") | Y3: =IF(AND(ISNUMBER($U$3),ISNUMBER($M$3)),$M$3+$Q$3*1.0*$U$3,"") | Z3: =IF(AND(ISNUMBER($U$3),ISNUMBER($O$3)),$O$3+$S$3*0.25*$U$3,"") | AA3: =IF(AND(ISNUMBER($U$3),ISNUMBER($O$3)),$O$3+$S$3*0.5*$U$3,"") | AB3: =IF(AND(ISNUMBER($U$3),ISNUMBER($O$3)),$O$3+$S$3*0.75*$U$3,"") | AC3: =IF(AND(ISNUMBER($U$3),ISNUMBER($O$3)),$O$3+$S$3*1.0*$U$3,"") | AD3: =IF(AND(ISNUMBER($AC$3),ISNUMBER($Y$3)),$AC$3/$Y$3,"") | AE3: C#: Game/Match/ModeSessions.cs:606; Sim/AI/ConquestAi.cs:68
A4: assault/Normal | B4: assault | C4: Normal | D4: 20 | E4: 1.45 | F4: 32 | G4: 1.3 | H4: 1 | I4: 0.7 | J4: 0 | K4: thưởng khu (8 CP, +0,25 CP/s mỗi khu) không tính | L4: Game/Match/ModeSessions.cs:606; Sim/AI/ConquestAi.cs:67 | M4: =IF(ISNUMBER($D$4),IF(AND(ISNUMBER(FIND(";"&Che_do!$B$2&";",";"&Kinh_te!$E$10&";")),$D$4>0,Kinh_te!$D$11<>1),ROUND($D$4*Kinh_te!$D$11,0),$D$4),"") | N4: 23 | O4: =IF(ISNUMBER($F$4),IF(AND(ISNUMBER(FIND(";"&Che_do!$B$2&";",";"&Kinh_te!$E$10&";")),$F$4>0,Kinh_te!$D$11<>1),ROUND($F$4*Kinh_te!$D$11,0),$F$4),"") | P4: 37 | Q4: =($E$4+$J$4)*Kinh_te!$D$9 | R4: 1.305 | S4: =IF(ISNUMBER($G$4),($G$4+$J$4)*Kinh_te!$D$9*$H$4*$I$4,"") | T4: 0.819 | U4: =Che_do_thoi_luong!$Q$2 | V4: =IF(AND(ISNUMBER($U$4),ISNUMBER($M$4)),$M$4+$Q$4*0.25*$U$4,"") | W4: =IF(AND(ISNUMBER($U$4),ISNUMBER($M$4)),$M$4+$Q$4*0.5*$U$4,"") | X4: =IF(AND(ISNUMBER($U$4),ISNUMBER($M$4)),$M$4+$Q$4*0.75*$U$4,"") | Y4: =IF(AND(ISNUMBER($U$4),ISNUMBER($M$4)),$M$4+$Q$4*1.0*$U$4,"") | Z4: =IF(AND(ISNUMBER($U$4),ISNUMBER($O$4)),$O$4+$S$4*0.25*$U$4,"") | AA4: =IF(AND(ISNUMBER($U$4),ISNUMBER($O$4)),$O$4+$S$4*0.5*$U$4,"") | AB4: =IF(AND(ISNUMBER($U$4),ISNUMBER($O$4)),$O$4+$S$4*0.75*$U$4,"") | AC4: =IF(AND(ISNUMBER($U$4),ISNUMBER($O$4)),$O$4+$S$4*1.0*$U$4,"") | AD4: =IF(AND(ISNUMBER($AC$4),ISNUMBER($Y$4)),$AC$4/$Y$4,"") | AE4: C#: Game/Match/ModeSessions.cs:606; Sim/AI/ConquestAi.cs:67
A5: assault/VeryHard | B5: assault | C5: VeryHard | D5: 20 | E5: 1.45 | F5: 32 | G5: 1.3 | H5: 1 | I5: 1.4 | J5: 0 | K5: thưởng khu (8 CP, +0,25 CP/s mỗi khu) không tính | L5: Game/Match/ModeSessions.cs:606; Sim/AI/ConquestAi.cs:69 | M5: =IF(ISNUMBER($D$5),IF(AND(ISNUMBER(FIND(";"&Che_do!$B$2&";",";"&Kinh_te!$E$10&";")),$D$5>0,Kinh_te!$D$11<>1),ROUND($D$5*Kinh_te!$D$11,0),$D$5),"") | N5: 23 | O5: =IF(ISNUMBER($F$5),IF(AND(ISNUMBER(FIND(";"&Che_do!$B$2&";",";"&Kinh_te!$E$10&";")),$F$5>0,Kinh_te!$D$11<>1),ROUND($F$5*Kinh_te!$D$11,0),$F$5),"") | P5: 37 | Q5: =($E$5+$J$5)*Kinh_te!$D$9 | R5: 1.305 | S5: =IF(ISNUMBER($G$5),($G$5+$J$5)*Kinh_te!$D$9*$H$5*$I$5,"") | T5: 1.638 | U5: =Che_do_thoi_luong!$Q$2 | V5: =IF(AND(ISNUMBER($U$5),ISNUMBER($M$5)),$M$5+$Q$5*0.25*$U$5,"") | W5: =IF(AND(ISNUMBER($U$5),ISNUMBER($M$5)),$M$5+$Q$5*0.5*$U$5,"") | X5: =IF(AND(ISNUMBER($U$5),ISNUMBER($M$5)),$M$5+$Q$5*0.75*$U$5,"") | Y5: =IF(AND(ISNUMBER($U$5),ISNUMBER($M$5)),$M$5+$Q$5*1.0*$U$5,"") | Z5: =IF(AND(ISNUMBER($U$5),ISNUMBER($O$5)),$O$5+$S$5*0.25*$U$5,"") | AA5: =IF(AND(ISNUMBER($U$5),ISNUMBER($O$5)),$O$5+$S$5*0.5*$U$5,"") | AB5: =IF(AND(ISNUMBER($U$5),ISNUMBER($O$5)),$O$5+$S$5*0.75*$U$5,"") | AC5: =IF(AND(ISNUMBER($U$5),ISNUMBER($O$5)),$O$5+$S$5*1.0*$U$5,"") | AD5: =IF(AND(ISNUMBER($AC$5),ISNUMBER($Y$5)),$AC$5/$Y$5,"") | AE5: C#: Game/Match/ModeSessions.cs:606; Sim/AI/ConquestAi.cs:69
A6: bossrush/Easy | B6: bossrush | C6: Easy | D6: 40 | E6: 1.8 | J6: 0 | K6: thưởng boss (8 CP mỗi 25 % máu, 12 khi hạ) không tính | L6: Game/Match/ModeSessions.cs:979 | M6: =IF(ISNUMBER($D$6),IF(AND(ISNUMBER(FIND(";"&Che_do!$B$3&";",";"&Kinh_te!$E$10&";")),$D$6>0,Kinh_te!$D$11<>1),ROUND($D$6*Kinh_te!$D$11,0),$D$6),"") | N6: 46 | O6: =IF(ISNUMBER($F$6),IF(AND(ISNUMBER(FIND(";"&Che_do!$B$3&";",";"&Kinh_te!$E$10&";")),$F$6>0,Kinh_te!$D$11<>1),ROUND($F$6*Kinh_te!$D$11,0),$F$6),"") | Q6: =($E$6+$J$6)*Kinh_te!$D$9 | R6: 1.62 | S6: =IF(ISNUMBER($G$6),($G$6+$J$6)*Kinh_te!$D$9*$H$6*$I$6,"") | U6: =Che_do_thoi_luong!$Q$3 | V6: =IF(AND(ISNUMBER($U$6),ISNUMBER($M$6)),$M$6+$Q$6*0.25*$U$6,"") | W6: =IF(AND(ISNUMBER($U$6),ISNUMBER($M$6)),$M$6+$Q$6*0.5*$U$6,"") | X6: =IF(AND(ISNUMBER($U$6),ISNUMBER($M$6)),$M$6+$Q$6*0.75*$U$6,"") | Y6: =IF(AND(ISNUMBER($U$6),ISNUMBER($M$6)),$M$6+$Q$6*1.0*$U$6,"") | Z6: =IF(AND(ISNUMBER($U$6),ISNUMBER($O$6)),$O$6+$S$6*0.25*$U$6,"") | AA6: =IF(AND(ISNUMBER($U$6),ISNUMBER($O$6)),$O$6+$S$6*0.5*$U$6,"") | AB6: =IF(AND(ISNUMBER($U$6),ISNUMBER($O$6)),$O$6+$S$6*0.75*$U$6,"") | AC6: =IF(AND(ISNUMBER($U$6),ISNUMBER($O$6)),$O$6+$S$6*1.0*$U$6,"") | AD6: =IF(AND(ISNUMBER($AC$6),ISNUMBER($Y$6)),$AC$6/$Y$6,"") | AE6: C#: Game/Match/ModeSessions.cs:979; Sim/AI/ConquestAi.cs:65
A7: bossrush/Hard | B7: bossrush | C7: Hard | D7: 40 | E7: 1.6 | J7: 0 | K7: thưởng boss (8 CP mỗi 25 % máu, 12 khi hạ) không tính | L7: Game/Match/ModeSessions.cs:979 | M7: =IF(ISNUMBER($D$7),IF(AND(ISNUMBER(FIND(";"&Che_do!$B$3&";",";"&Kinh_te!$E$10&";")),$D$7>0,Kinh_te!$D$11<>1),ROUND($D$7*Kinh_te!$D$11,0),$D$7),"") | N7: 46 | O7: =IF(ISNUMBER($F$7),IF(AND(ISNUMBER(FIND(";"&Che_do!$B$3&";",";"&Kinh_te!$E$10&";")),$F$7>0,Kinh_te!$D$11<>1),ROUND($F$7*Kinh_te!$D$11,0),$F$7),"") | Q7: =($E$7+$J$7)*Kinh_te!$D$9 | R7: 1.44 | S7: =IF(ISNUMBER($G$7),($G$7+$J$7)*Kinh_te!$D$9*$H$7*$I$7,"") | U7: =Che_do_thoi_luong!$Q$3 | V7: =IF(AND(ISNUMBER($U$7),ISNUMBER($M$7)),$M$7+$Q$7*0.25*$U$7,"") | W7: =IF(AND(ISNUMBER($U$7),ISNUMBER($M$7)),$M$7+$Q$7*0.5*$U$7,"") | X7: =IF(AND(ISNUMBER($U$7),ISNUMBER($M$7)),$M$7+$Q$7*0.75*$U$7,"") | Y7: =IF(AND(ISNUMBER($U$7),ISNUMBER($M$7)),$M$7+$Q$7*1.0*$U$7,"") | Z7: =IF(AND(ISNUMBER($U$7),ISNUMBER($O$7)),$O$7+$S$7*0.25*$U$7,"") | AA7: =IF(AND(ISNUMBER($U$7),ISNUMBER($O$7)),$O$7+$S$7*0.5*$U$7,"") | AB7: =IF(AND(ISNUMBER($U$7),ISNUMBER($O$7)),$O$7+$S$7*0.75*$U$7,"") | AC7: =IF(AND(ISNUMBER($U$7),ISNUMBER($O$7)),$O$7+$S$7*1.0*$U$7,"") | AD7: =IF(AND(ISNUMBER($AC$7),ISNUMBER($Y$7)),$AC$7/$Y$7,"") | AE7: C#: Game/Match/ModeSessions.cs:979; Sim/AI/ConquestAi.cs:68
A8: bossrush/Normal | B8: bossrush | C8: Normal | D8: 40 | E8: 1.8 | J8: 0 | K8: thưởng boss (8 CP mỗi 25 % máu, 12 khi hạ) không tính | L8: Game/Match/ModeSessions.cs:979 | M8: =IF(ISNUMBER($D$8),IF(AND(ISNUMBER(FIND(";"&Che_do!$B$3&";",";"&Kinh_te!$E$10&";")),$D$8>0,Kinh_te!$D$11<>1),ROUND($D$8*Kinh_te!$D$11,0),$D$8),"") | N8: 46 | O8: =IF(ISNUMBER($F$8),IF(AND(ISNUMBER(FIND(";"&Che_do!$B$3&";",";"&Kinh_te!$E$10&";")),$F$8>0,Kinh_te!$D$11<>1),ROUND($F$8*Kinh_te!$D$11,0),$F$8),"") | Q8: =($E$8+$J$8)*Kinh_te!$D$9 | R8: 1.62 | S8: =IF(ISNUMBER($G$8),($G$8+$J$8)*Kinh_te!$D$9*$H$8*$I$8,"") | U8: =Che_do_thoi_luong!$Q$3 | V8: =IF(AND(ISNUMBER($U$8),ISNUMBER($M$8)),$M$8+$Q$8*0.25*$U$8,"") | W8: =IF(AND(ISNUMBER($U$8),ISNUMBER($M$8)),$M$8+$Q$8*0.5*$U$8,"") | X8: =IF(AND(ISNUMBER($U$8),ISNUMBER($M$8)),$M$8+$Q$8*0.75*$U$8,"") | Y8: =IF(AND(ISNUMBER($U$8),ISNUMBER($M$8)),$M$8+$Q$8*1.0*$U$8,"") | Z8: =IF(AND(ISNUMBER($U$8),ISNUMBER($O$8)),$O$8+$S$8*0.25*$U$8,"") | AA8: =IF(AND(ISNUMBER($U$8),ISNUMBER($O$8)),$O$8+$S$8*0.5*$U$8,"") | AB8: =IF(AND(ISNUMBER($U$8),ISNUMBER($O$8)),$O$8+$S$8*0.75*$U$8,"") | AC8: =IF(AND(ISNUMBER($U$8),ISNUMBER($O$8)),$O$8+$S$8*1.0*$U$8,"") | AD8: =IF(AND(ISNUMBER($AC$8),ISNUMBER($Y$8)),$AC$8/$Y$8,"") | AE8: C#: Game/Match/ModeSessions.cs:979; Sim/AI/ConquestAi.cs:67
A9: bossrush/VeryHard | B9: bossrush | C9: VeryHard | D9: 40 | E9: 1.45 | J9: 0 | K9: thưởng boss (8 CP mỗi 25 % máu, 12 khi hạ) không tính | L9: Game/Match/ModeSessions.cs:979 | M9: =IF(ISNUMBER($D$9),IF(AND(ISNUMBER(FIND(";"&Che_do!$B$3&";",";"&Kinh_te!$E$10&";")),$D$9>0,Kinh_te!$D$11<>1),ROUND($D$9*Kinh_te!$D$11,0),$D$9),"") | N9: 46 | O9: =IF(ISNUMBER($F$9),IF(AND(ISNUMBER(FIND(";"&Che_do!$B$3&";",";"&Kinh_te!$E$10&";")),$F$9>0,Kinh_te!$D$11<>1),ROUND($F$9*Kinh_te!$D$11,0),$F$9),"") | Q9: =($E$9+$J$9)*Kinh_te!$D$9 | R9: 1.305 | S9: =IF(ISNUMBER($G$9),($G$9+$J$9)*Kinh_te!$D$9*$H$9*$I$9,"") | U9: =Che_do_thoi_luong!$Q$3 | V9: =IF(AND(ISNUMBER($U$9),ISNUMBER($M$9)),$M$9+$Q$9*0.25*$U$9,"") | W9: =IF(AND(ISNUMBER($U$9),ISNUMBER($M$9)),$M$9+$Q$9*0.5*$U$9,"") | X9: =IF(AND(ISNUMBER($U$9),ISNUMBER($M$9)),$M$9+$Q$9*0.75*$U$9,"") | Y9: =IF(AND(ISNUMBER($U$9),ISNUMBER($M$9)),$M$9+$Q$9*1.0*$U$9,"") | Z9: =IF(AND(ISNUMBER($U$9),ISNUMBER($O$9)),$O$9+$S$9*0.25*$U$9,"") | AA9: =IF(AND(ISNUMBER($U$9),ISNUMBER($O$9)),$O$9+$S$9*0.5*$U$9,"") | AB9: =IF(AND(ISNUMBER($U$9),ISNUMBER($O$9)),$O$9+$S$9*0.75*$U$9,"") | AC9: =IF(AND(ISNUMBER($U$9),ISNUMBER($O$9)),$O$9+$S$9*1.0*$U$9,"") | AD9: =IF(AND(ISNUMBER($AC$9),ISNUMBER($Y$9)),$AC$9/$Y$9,"") | AE9: C#: Game/Match/ModeSessions.cs:979; Sim/AI/ConquestAi.cs:69
A10: conquest/Easy | B10: conquest | C10: Easy | D10: 14 | E10: 1 | F10: 14 | G10: 1 | H10: 1.18 | I10: 0.8 | J10: 0.225 | K10: PointIncome x 1,5 cứ điểm (chia đều 3 cứ điểm) | L10: Sim/Modes/ConquestMode.cs:64; Sim/Economy/EconomySystem.cs:27; Game/Match/ModeSessions.cs:480; Game/Match/ModeSessions.cs:473; Sim/AI/ConquestAi.cs:65 | M10: =IF(ISNUMBER($D$10),IF(AND(ISNUMBER(FIND(";"&Che_do!$B$4&";",";"&Kinh_te!$E$10&";")),$D$10>0,Kinh_te!$D$11<>1),ROUND($D$10*Kinh_te!$D$11,0),$D$10),"") | N10: 16 | O10: =IF(ISNUMBER($F$10),IF(AND(ISNUMBER(FIND(";"&Che_do!$B$4&";",";"&Kinh_te!$E$10&";")),$F$10>0,Kinh_te!$D$11<>1),ROUND($F$10*Kinh_te!$D$11,0),$F$10),"") | P10: 16 | Q10: =($E$10+$J$10)*Kinh_te!$D$9 | R10: 1.1025 | S10: =IF(ISNUMBER($G$10),($G$10+$J$10)*Kinh_te!$D$9*$H$10*$I$10,"") | T10: 1.04076 | U10: =Che_do_thoi_luong!$Q$4 | V10: =IF(AND(ISNUMBER($U$10),ISNUMBER($M$10)),$M$10+$Q$10*0.25*$U$10,"") | W10: =IF(AND(ISNUMBER($U$10),ISNUMBER($M$10)),$M$10+$Q$10*0.5*$U$10,"") | X10: =IF(AND(ISNUMBER($U$10),ISNUMBER($M$10)),$M$10+$Q$10*0.75*$U$10,"") | Y10: =IF(AND(ISNUMBER($U$10),ISNUMBER($M$10)),$M$10+$Q$10*1.0*$U$10,"") | Z10: =IF(AND(ISNUMBER($U$10),ISNUMBER($O$10)),$O$10+$S$10*0.25*$U$10,"") | AA10: =IF(AND(ISNUMBER($U$10),ISNUMBER($O$10)),$O$10+$S$10*0.5*$U$10,"") | AB10: =IF(AND(ISNUMBER($U$10),ISNUMBER($O$10)),$O$10+$S$10*0.75*$U$10,"") | AC10: =IF(AND(ISNUMBER($U$10),ISNUMBER($O$10)),$O$10+$S$10*1.0*$U$10,"") | AD10: =IF(AND(ISNUMBER($AC$10),ISNUMBER($Y$10)),$AC$10/$Y$10,"") | AE10: C#: Sim/Modes/ConquestMode.cs:64; Sim/Economy/EconomySystem.cs:27; Game/Match/ModeSessions.cs:480; Game/Match/ModeSessions.cs:473; Sim/AI/ConquestAi.cs:65
A11: conquest/Hard | B11: conquest | C11: Hard | D11: 14 | E11: 1 | F11: 14 | G11: 1 | H11: 1.18 | I11: 1.2 | J11: 0.225 | K11: PointIncome x 1,5 cứ điểm (chia đều 3 cứ điểm) | L11: Sim/Modes/ConquestMode.cs:64; Sim/Economy/EconomySystem.cs:27; Game/Match/ModeSessions.cs:480; Game/Match/ModeSessions.cs:473; Sim/AI/ConquestAi.cs:68 | M11: =IF(ISNUMBER($D$11),IF(AND(ISNUMBER(FIND(";"&Che_do!$B$4&";",";"&Kinh_te!$E$10&";")),$D$11>0,Kinh_te!$D$11<>1),ROUND($D$11*Kinh_te!$D$11,0),$D$11),"") | N11: 16 | O11: =IF(ISNUMBER($F$11),IF(AND(ISNUMBER(FIND(";"&Che_do!$B$4&";",";"&Kinh_te!$E$10&";")),$F$11>0,Kinh_te!$D$11<>1),ROUND($F$11*Kinh_te!$D$11,0),$F$11),"") | P11: 16 | Q11: =($E$11+$J$11)*Kinh_te!$D$9 | R11: 1.1025 | S11: =IF(ISNUMBER($G$11),($G$11+$J$11)*Kinh_te!$D$9*$H$11*$I$11,"") | T11: 1.56114 | U11: =Che_do_thoi_luong!$Q$4 | V11: =IF(AND(ISNUMBER($U$11),ISNUMBER($M$11)),$M$11+$Q$11*0.25*$U$11,"") | W11: =IF(AND(ISNUMBER($U$11),ISNUMBER($M$11)),$M$11+$Q$11*0.5*$U$11,"") | X11: =IF(AND(ISNUMBER($U$11),ISNUMBER($M$11)),$M$11+$Q$11*0.75*$U$11,"") | Y11: =IF(AND(ISNUMBER($U$11),ISNUMBER($M$11)),$M$11+$Q$11*1.0*$U$11,"") | Z11: =IF(AND(ISNUMBER($U$11),ISNUMBER($O$11)),$O$11+$S$11*0.25*$U$11,"") | AA11: =IF(AND(ISNUMBER($U$11),ISNUMBER($O$11)),$O$11+$S$11*0.5*$U$11,"") | AB11: =IF(AND(ISNUMBER($U$11),ISNUMBER($O$11)),$O$11+$S$11*0.75*$U$11,"") | AC11: =IF(AND(ISNUMBER($U$11),ISNUMBER($O$11)),$O$11+$S$11*1.0*$U$11,"") | AD11: =IF(AND(ISNUMBER($AC$11),ISNUMBER($Y$11)),$AC$11/$Y$11,"") | AE11: C#: Sim/Modes/ConquestMode.cs:64; Sim/Economy/EconomySystem.cs:27; Game/Match/ModeSessions.cs:480; Game/Match/ModeSessions.cs:473; Sim/AI/ConquestAi.cs:68
A12: conquest/Normal | B12: conquest | C12: Normal | D12: 14 | E12: 1 | F12: 14 | G12: 1 | H12: 1.18 | I12: 0.7 | J12: 0.225 | K12: PointIncome x 1,5 cứ điểm (chia đều 3 cứ điểm) | L12: Sim/Modes/ConquestMode.cs:64; Sim/Economy/EconomySystem.cs:27; Game/Match/ModeSessions.cs:480; Game/Match/ModeSessions.cs:473; Sim/AI/ConquestAi.cs:67 | M12: =IF(ISNUMBER($D$12),IF(AND(ISNUMBER(FIND(";"&Che_do!$B$4&";",";"&Kinh_te!$E$10&";")),$D$12>0,Kinh_te!$D$11<>1),ROUND($D$12*Kinh_te!$D$11,0),$D$12),"") | N12: 16 | O12: =IF(ISNUMBER($F$12),IF(AND(ISNUMBER(FIND(";"&Che_do!$B$4&";",";"&Kinh_te!$E$10&";")),$F$12>0,Kinh_te!$D$11<>1),ROUND($F$12*Kinh_te!$D$11,0),$F$12),"") | P12: 16 | Q12: =($E$12+$J$12)*Kinh_te!$D$9 | R12: 1.1025 | S12: =IF(ISNUMBER($G$12),($G$12+$J$12)*Kinh_te!$D$9*$H$12*$I$12,"") | T12: 0.910665 | U12: =Che_do_thoi_luong!$Q$4 | V12: =IF(AND(ISNUMBER($U$12),ISNUMBER($M$12)),$M$12+$Q$12*0.25*$U$12,"") | W12: =IF(AND(ISNUMBER($U$12),ISNUMBER($M$12)),$M$12+$Q$12*0.5*$U$12,"") | X12: =IF(AND(ISNUMBER($U$12),ISNUMBER($M$12)),$M$12+$Q$12*0.75*$U$12,"") | Y12: =IF(AND(ISNUMBER($U$12),ISNUMBER($M$12)),$M$12+$Q$12*1.0*$U$12,"") | Z12: =IF(AND(ISNUMBER($U$12),ISNUMBER($O$12)),$O$12+$S$12*0.25*$U$12,"") | AA12: =IF(AND(ISNUMBER($U$12),ISNUMBER($O$12)),$O$12+$S$12*0.5*$U$12,"") | AB12: =IF(AND(ISNUMBER($U$12),ISNUMBER($O$12)),$O$12+$S$12*0.75*$U$12,"") | AC12: =IF(AND(ISNUMBER($U$12),ISNUMBER($O$12)),$O$12+$S$12*1.0*$U$12,"") | AD12: =IF(AND(ISNUMBER($AC$12),ISNUMBER($Y$12)),$AC$12/$Y$12,"") | AE12: C#: Sim/Modes/ConquestMode.cs:64; Sim/Economy/EconomySystem.cs:27; Game/Match/ModeSessions.cs:480; Game/Match/ModeSessions.cs:473; Sim/AI/ConquestAi.cs:67
A13: conquest/VeryHard | B13: conquest | C13: VeryHard | D13: 14 | E13: 1 | F13: 14 | G13: 1 | H13: 1.18 | I13: 1.4 | J13: 0.225 | K13: PointIncome x 1,5 cứ điểm (chia đều 3 cứ điểm) | L13: Sim/Modes/ConquestMode.cs:64; Sim/Economy/EconomySystem.cs:27; Game/Match/ModeSessions.cs:480; Game/Match/ModeSessions.cs:473; Sim/AI/ConquestAi.cs:69 | M13: =IF(ISNUMBER($D$13),IF(AND(ISNUMBER(FIND(";"&Che_do!$B$4&";",";"&Kinh_te!$E$10&";")),$D$13>0,Kinh_te!$D$11<>1),ROUND($D$13*Kinh_te!$D$11,0),$D$13),"") | N13: 16 | O13: =IF(ISNUMBER($F$13),IF(AND(ISNUMBER(FIND(";"&Che_do!$B$4&";",";"&Kinh_te!$E$10&";")),$F$13>0,Kinh_te!$D$11<>1),ROUND($F$13*Kinh_te!$D$11,0),$F$13),"") | P13: 16 | Q13: =($E$13+$J$13)*Kinh_te!$D$9 | R13: 1.1025 | S13: =IF(ISNUMBER($G$13),($G$13+$J$13)*Kinh_te!$D$9*$H$13*$I$13,"") | T13: 1.82133 | U13: =Che_do_thoi_luong!$Q$4 | V13: =IF(AND(ISNUMBER($U$13),ISNUMBER($M$13)),$M$13+$Q$13*0.25*$U$13,"") | W13: =IF(AND(ISNUMBER($U$13),ISNUMBER($M$13)),$M$13+$Q$13*0.5*$U$13,"") | X13: =IF(AND(ISNUMBER($U$13),ISNUMBER($M$13)),$M$13+$Q$13*0.75*$U$13,"") | Y13: =IF(AND(ISNUMBER($U$13),ISNUMBER($M$13)),$M$13+$Q$13*1.0*$U$13,"") | Z13: =IF(AND(ISNUMBER($U$13),ISNUMBER($O$13)),$O$13+$S$13*0.25*$U$13,"") | AA13: =IF(AND(ISNUMBER($U$13),ISNUMBER($O$13)),$O$13+$S$13*0.5*$U$13,"") | AB13: =IF(AND(ISNUMBER($U$13),ISNUMBER($O$13)),$O$13+$S$13*0.75*$U$13,"") | AC13: =IF(AND(ISNUMBER($U$13),ISNUMBER($O$13)),$O$13+$S$13*1.0*$U$13,"") | AD13: =IF(AND(ISNUMBER($AC$13),ISNUMBER($Y$13)),$AC$13/$Y$13,"") | AE13: C#: Sim/Modes/ConquestMode.cs:64; Sim/Economy/EconomySystem.cs:27; Game/Match/ModeSessions.cs:480; Game/Match/ModeSessions.cs:473; Sim/AI/ConquestAi.cs:69
A14: deathmatch/Easy | B14: deathmatch | C14: Easy | D14: 18 | E14: 1.35 | F14: 18 | G14: 1.2 | H14: 1 | I14: 0.8 | J14: 0 | L14: Game/Match/ModeSessions.cs:517; Sim/AI/ConquestAi.cs:65 | M14: =IF(ISNUMBER($D$14),IF(AND(ISNUMBER(FIND(";"&Che_do!$B$5&";",";"&Kinh_te!$E$10&";")),$D$14>0,Kinh_te!$D$11<>1),ROUND($D$14*Kinh_te!$D$11,0),$D$14),"") | N14: 21 | O14: =IF(ISNUMBER($F$14),IF(AND(ISNUMBER(FIND(";"&Che_do!$B$5&";",";"&Kinh_te!$E$10&";")),$F$14>0,Kinh_te!$D$11<>1),ROUND($F$14*Kinh_te!$D$11,0),$F$14),"") | P14: 21 | Q14: =($E$14+$J$14)*Kinh_te!$D$9 | R14: 1.215 | S14: =IF(ISNUMBER($G$14),($G$14+$J$14)*Kinh_te!$D$9*$H$14*$I$14,"") | T14: 0.864 | U14: =Che_do_thoi_luong!$Q$5 | V14: =IF(AND(ISNUMBER($U$14),ISNUMBER($M$14)),$M$14+$Q$14*0.25*$U$14,"") | W14: =IF(AND(ISNUMBER($U$14),ISNUMBER($M$14)),$M$14+$Q$14*0.5*$U$14,"") | X14: =IF(AND(ISNUMBER($U$14),ISNUMBER($M$14)),$M$14+$Q$14*0.75*$U$14,"") | Y14: =IF(AND(ISNUMBER($U$14),ISNUMBER($M$14)),$M$14+$Q$14*1.0*$U$14,"") | Z14: =IF(AND(ISNUMBER($U$14),ISNUMBER($O$14)),$O$14+$S$14*0.25*$U$14,"") | AA14: =IF(AND(ISNUMBER($U$14),ISNUMBER($O$14)),$O$14+$S$14*0.5*$U$14,"") | AB14: =IF(AND(ISNUMBER($U$14),ISNUMBER($O$14)),$O$14+$S$14*0.75*$U$14,"") | AC14: =IF(AND(ISNUMBER($U$14),ISNUMBER($O$14)),$O$14+$S$14*1.0*$U$14,"") | AD14: =IF(AND(ISNUMBER($AC$14),ISNUMBER($Y$14)),$AC$14/$Y$14,"") | AE14: C#: Game/Match/ModeSessions.cs:517; Sim/AI/ConquestAi.cs:65
A15: deathmatch/Hard | B15: deathmatch | C15: Hard | D15: 18 | E15: 1.35 | F15: 18 | G15: 1.2 | H15: 1 | I15: 1.2 | J15: 0 | L15: Game/Match/ModeSessions.cs:517; Sim/AI/ConquestAi.cs:68 | M15: =IF(ISNUMBER($D$15),IF(AND(ISNUMBER(FIND(";"&Che_do!$B$5&";",";"&Kinh_te!$E$10&";")),$D$15>0,Kinh_te!$D$11<>1),ROUND($D$15*Kinh_te!$D$11,0),$D$15),"") | N15: 21 | O15: =IF(ISNUMBER($F$15),IF(AND(ISNUMBER(FIND(";"&Che_do!$B$5&";",";"&Kinh_te!$E$10&";")),$F$15>0,Kinh_te!$D$11<>1),ROUND($F$15*Kinh_te!$D$11,0),$F$15),"") | P15: 21 | Q15: =($E$15+$J$15)*Kinh_te!$D$9 | R15: 1.215 | S15: =IF(ISNUMBER($G$15),($G$15+$J$15)*Kinh_te!$D$9*$H$15*$I$15,"") | T15: 1.296 | U15: =Che_do_thoi_luong!$Q$5 | V15: =IF(AND(ISNUMBER($U$15),ISNUMBER($M$15)),$M$15+$Q$15*0.25*$U$15,"") | W15: =IF(AND(ISNUMBER($U$15),ISNUMBER($M$15)),$M$15+$Q$15*0.5*$U$15,"") | X15: =IF(AND(ISNUMBER($U$15),ISNUMBER($M$15)),$M$15+$Q$15*0.75*$U$15,"") | Y15: =IF(AND(ISNUMBER($U$15),ISNUMBER($M$15)),$M$15+$Q$15*1.0*$U$15,"") | Z15: =IF(AND(ISNUMBER($U$15),ISNUMBER($O$15)),$O$15+$S$15*0.25*$U$15,"") | AA15: =IF(AND(ISNUMBER($U$15),ISNUMBER($O$15)),$O$15+$S$15*0.5*$U$15,"") | AB15: =IF(AND(ISNUMBER($U$15),ISNUMBER($O$15)),$O$15+$S$15*0.75*$U$15,"") | AC15: =IF(AND(ISNUMBER($U$15),ISNUMBER($O$15)),$O$15+$S$15*1.0*$U$15,"") | AD15: =IF(AND(ISNUMBER($AC$15),ISNUMBER($Y$15)),$AC$15/$Y$15,"") | AE15: C#: Game/Match/ModeSessions.cs:517; Sim/AI/ConquestAi.cs:68
A16: deathmatch/Normal | B16: deathmatch | C16: Normal | D16: 18 | E16: 1.35 | F16: 18 | G16: 1.2 | H16: 1 | I16: 0.7 | J16: 0 | L16: Game/Match/ModeSessions.cs:517; Sim/AI/ConquestAi.cs:67 | M16: =IF(ISNUMBER($D$16),IF(AND(ISNUMBER(FIND(";"&Che_do!$B$5&";",";"&Kinh_te!$E$10&";")),$D$16>0,Kinh_te!$D$11<>1),ROUND($D$16*Kinh_te!$D$11,0),$D$16),"") | N16: 21 | O16: =IF(ISNUMBER($F$16),IF(AND(ISNUMBER(FIND(";"&Che_do!$B$5&";",";"&Kinh_te!$E$10&";")),$F$16>0,Kinh_te!$D$11<>1),ROUND($F$16*Kinh_te!$D$11,0),$F$16),"") | P16: 21 | Q16: =($E$16+$J$16)*Kinh_te!$D$9 | R16: 1.215 | S16: =IF(ISNUMBER($G$16),($G$16+$J$16)*Kinh_te!$D$9*$H$16*$I$16,"") | T16: 0.756 | U16: =Che_do_thoi_luong!$Q$5 | V16: =IF(AND(ISNUMBER($U$16),ISNUMBER($M$16)),$M$16+$Q$16*0.25*$U$16,"") | W16: =IF(AND(ISNUMBER($U$16),ISNUMBER($M$16)),$M$16+$Q$16*0.5*$U$16,"") | X16: =IF(AND(ISNUMBER($U$16),ISNUMBER($M$16)),$M$16+$Q$16*0.75*$U$16,"") | Y16: =IF(AND(ISNUMBER($U$16),ISNUMBER($M$16)),$M$16+$Q$16*1.0*$U$16,"") | Z16: =IF(AND(ISNUMBER($U$16),ISNUMBER($O$16)),$O$16+$S$16*0.25*$U$16,"") | AA16: =IF(AND(ISNUMBER($U$16),ISNUMBER($O$16)),$O$16+$S$16*0.5*$U$16,"") | AB16: =IF(AND(ISNUMBER($U$16),ISNUMBER($O$16)),$O$16+$S$16*0.75*$U$16,"") | AC16: =IF(AND(ISNUMBER($U$16),ISNUMBER($O$16)),$O$16+$S$16*1.0*$U$16,"") | AD16: =IF(AND(ISNUMBER($AC$16),ISNUMBER($Y$16)),$AC$16/$Y$16,"") | AE16: C#: Game/Match/ModeSessions.cs:517; Sim/AI/ConquestAi.cs:67
A17: deathmatch/VeryHard | B17: deathmatch | C17: VeryHard | D17: 18 | E17: 1.35 | F17: 18 | G17: 1.2 | H17: 1 | I17: 1.4 | J17: 0 | L17: Game/Match/ModeSessions.cs:517; Sim/AI/ConquestAi.cs:69 | M17: =IF(ISNUMBER($D$17),IF(AND(ISNUMBER(FIND(";"&Che_do!$B$5&";",";"&Kinh_te!$E$10&";")),$D$17>0,Kinh_te!$D$11<>1),ROUND($D$17*Kinh_te!$D$11,0),$D$17),"") | N17: 21 | O17: =IF(ISNUMBER($F$17),IF(AND(ISNUMBER(FIND(";"&Che_do!$B$5&";",";"&Kinh_te!$E$10&";")),$F$17>0,Kinh_te!$D$11<>1),ROUND($F$17*Kinh_te!$D$11,0),$F$17),"") | P17: 21 | Q17: =($E$17+$J$17)*Kinh_te!$D$9 | R17: 1.215 | S17: =IF(ISNUMBER($G$17),($G$17+$J$17)*Kinh_te!$D$9*$H$17*$I$17,"") | T17: 1.512 | U17: =Che_do_thoi_luong!$Q$5 | V17: =IF(AND(ISNUMBER($U$17),ISNUMBER($M$17)),$M$17+$Q$17*0.25*$U$17,"") | W17: =IF(AND(ISNUMBER($U$17),ISNUMBER($M$17)),$M$17+$Q$17*0.5*$U$17,"") | X17: =IF(AND(ISNUMBER($U$17),ISNUMBER($M$17)),$M$17+$Q$17*0.75*$U$17,"") | Y17: =IF(AND(ISNUMBER($U$17),ISNUMBER($M$17)),$M$17+$Q$17*1.0*$U$17,"") | Z17: =IF(AND(ISNUMBER($U$17),ISNUMBER($O$17)),$O$17+$S$17*0.25*$U$17,"") | AA17: =IF(AND(ISNUMBER($U$17),ISNUMBER($O$17)),$O$17+$S$17*0.5*$U$17,"") | AB17: =IF(AND(ISNUMBER($U$17),ISNUMBER($O$17)),$O$17+$S$17*0.75*$U$17,"") | AC17: =IF(AND(ISNUMBER($U$17),ISNUMBER($O$17)),$O$17+$S$17*1.0*$U$17,"") | AD17: =IF(AND(ISNUMBER($AC$17),ISNUMBER($Y$17)),$AC$17/$Y$17,"") | AE17: C#: Game/Match/ModeSessions.cs:517; Sim/AI/ConquestAi.cs:69
A18: defend/Easy | B18: defend | C18: Easy | D18: 30 | E18: 1.35 | F18: 22 | G18: 1.1 | H18: 1 | I18: 0.8 | J18: 0 | L18: Game/Match/ModeSessions.cs:682; Game/Match/ModeSessions.cs:685; Sim/AI/ConquestAi.cs:65 | M18: =IF(ISNUMBER($D$18),IF(AND(ISNUMBER(FIND(";"&Che_do!$B$6&";",";"&Kinh_te!$E$10&";")),$D$18>0,Kinh_te!$D$11<>1),ROUND($D$18*Kinh_te!$D$11,0),$D$18),"") | N18: 35 | O18: =IF(ISNUMBER($F$18),IF(AND(ISNUMBER(FIND(";"&Che_do!$B$6&";",";"&Kinh_te!$E$10&";")),$F$18>0,Kinh_te!$D$11<>1),ROUND($F$18*Kinh_te!$D$11,0),$F$18),"") | P18: 26 | Q18: =($E$18+$J$18)*Kinh_te!$D$9 | R18: 1.215 | S18: =IF(ISNUMBER($G$18),($G$18+$J$18)*Kinh_te!$D$9*$H$18*$I$18,"") | T18: 0.792 | U18: =Che_do_thoi_luong!$Q$6 | V18: =IF(AND(ISNUMBER($U$18),ISNUMBER($M$18)),$M$18+$Q$18*0.25*$U$18,"") | W18: =IF(AND(ISNUMBER($U$18),ISNUMBER($M$18)),$M$18+$Q$18*0.5*$U$18,"") | X18: =IF(AND(ISNUMBER($U$18),ISNUMBER($M$18)),$M$18+$Q$18*0.75*$U$18,"") | Y18: =IF(AND(ISNUMBER($U$18),ISNUMBER($M$18)),$M$18+$Q$18*1.0*$U$18,"") | Z18: =IF(AND(ISNUMBER($U$18),ISNUMBER($O$18)),$O$18+$S$18*0.25*$U$18,"") | AA18: =IF(AND(ISNUMBER($U$18),ISNUMBER($O$18)),$O$18+$S$18*0.5*$U$18,"") | AB18: =IF(AND(ISNUMBER($U$18),ISNUMBER($O$18)),$O$18+$S$18*0.75*$U$18,"") | AC18: =IF(AND(ISNUMBER($U$18),ISNUMBER($O$18)),$O$18+$S$18*1.0*$U$18,"") | AD18: =IF(AND(ISNUMBER($AC$18),ISNUMBER($Y$18)),$AC$18/$Y$18,"") | AE18: C#: Game/Match/ModeSessions.cs:682; Game/Match/ModeSessions.cs:685; Sim/AI/ConquestAi.cs:65
A19: defend/Hard | B19: defend | C19: Hard | D19: 30 | E19: 1.35 | F19: 22 | G19: 1.1 | H19: 1 | I19: 1.2 | J19: 0 | L19: Game/Match/ModeSessions.cs:682; Game/Match/ModeSessions.cs:685; Sim/AI/ConquestAi.cs:68 | M19: =IF(ISNUMBER($D$19),IF(AND(ISNUMBER(FIND(";"&Che_do!$B$6&";",";"&Kinh_te!$E$10&";")),$D$19>0,Kinh_te!$D$11<>1),ROUND($D$19*Kinh_te!$D$11,0),$D$19),"") | N19: 35 | O19: =IF(ISNUMBER($F$19),IF(AND(ISNUMBER(FIND(";"&Che_do!$B$6&";",";"&Kinh_te!$E$10&";")),$F$19>0,Kinh_te!$D$11<>1),ROUND($F$19*Kinh_te!$D$11,0),$F$19),"") | P19: 26 | Q19: =($E$19+$J$19)*Kinh_te!$D$9 | R19: 1.215 | S19: =IF(ISNUMBER($G$19),($G$19+$J$19)*Kinh_te!$D$9*$H$19*$I$19,"") | T19: 1.188 | U19: =Che_do_thoi_luong!$Q$6 | V19: =IF(AND(ISNUMBER($U$19),ISNUMBER($M$19)),$M$19+$Q$19*0.25*$U$19,"") | W19: =IF(AND(ISNUMBER($U$19),ISNUMBER($M$19)),$M$19+$Q$19*0.5*$U$19,"") | X19: =IF(AND(ISNUMBER($U$19),ISNUMBER($M$19)),$M$19+$Q$19*0.75*$U$19,"") | Y19: =IF(AND(ISNUMBER($U$19),ISNUMBER($M$19)),$M$19+$Q$19*1.0*$U$19,"") | Z19: =IF(AND(ISNUMBER($U$19),ISNUMBER($O$19)),$O$19+$S$19*0.25*$U$19,"") | AA19: =IF(AND(ISNUMBER($U$19),ISNUMBER($O$19)),$O$19+$S$19*0.5*$U$19,"") | AB19: =IF(AND(ISNUMBER($U$19),ISNUMBER($O$19)),$O$19+$S$19*0.75*$U$19,"") | AC19: =IF(AND(ISNUMBER($U$19),ISNUMBER($O$19)),$O$19+$S$19*1.0*$U$19,"") | AD19: =IF(AND(ISNUMBER($AC$19),ISNUMBER($Y$19)),$AC$19/$Y$19,"") | AE19: C#: Game/Match/ModeSessions.cs:682; Game/Match/ModeSessions.cs:685; Sim/AI/ConquestAi.cs:68
A20: defend/Normal | B20: defend | C20: Normal | D20: 30 | E20: 1.35 | F20: 22 | G20: 1.1 | H20: 1 | I20: 0.7 | J20: 0 | L20: Game/Match/ModeSessions.cs:682; Game/Match/ModeSessions.cs:685; Sim/AI/ConquestAi.cs:67 | M20: =IF(ISNUMBER($D$20),IF(AND(ISNUMBER(FIND(";"&Che_do!$B$6&";",";"&Kinh_te!$E$10&";")),$D$20>0,Kinh_te!$D$11<>1),ROUND($D$20*Kinh_te!$D$11,0),$D$20),"") | N20: 35 | O20: =IF(ISNUMBER($F$20),IF(AND(ISNUMBER(FIND(";"&Che_do!$B$6&";",";"&Kinh_te!$E$10&";")),$F$20>0,Kinh_te!$D$11<>1),ROUND($F$20*Kinh_te!$D$11,0),$F$20),"") | P20: 26 | Q20: =($E$20+$J$20)*Kinh_te!$D$9 | R20: 1.215 | S20: =IF(ISNUMBER($G$20),($G$20+$J$20)*Kinh_te!$D$9*$H$20*$I$20,"") | T20: 0.693 | U20: =Che_do_thoi_luong!$Q$6 | V20: =IF(AND(ISNUMBER($U$20),ISNUMBER($M$20)),$M$20+$Q$20*0.25*$U$20,"") | W20: =IF(AND(ISNUMBER($U$20),ISNUMBER($M$20)),$M$20+$Q$20*0.5*$U$20,"") | X20: =IF(AND(ISNUMBER($U$20),ISNUMBER($M$20)),$M$20+$Q$20*0.75*$U$20,"") | Y20: =IF(AND(ISNUMBER($U$20),ISNUMBER($M$20)),$M$20+$Q$20*1.0*$U$20,"") | Z20: =IF(AND(ISNUMBER($U$20),ISNUMBER($O$20)),$O$20+$S$20*0.25*$U$20,"") | AA20: =IF(AND(ISNUMBER($U$20),ISNUMBER($O$20)),$O$20+$S$20*0.5*$U$20,"") | AB20: =IF(AND(ISNUMBER($U$20),ISNUMBER($O$20)),$O$20+$S$20*0.75*$U$20,"") | AC20: =IF(AND(ISNUMBER($U$20),ISNUMBER($O$20)),$O$20+$S$20*1.0*$U$20,"") | AD20: =IF(AND(ISNUMBER($AC$20),ISNUMBER($Y$20)),$AC$20/$Y$20,"") | AE20: C#: Game/Match/ModeSessions.cs:682; Game/Match/ModeSessions.cs:685; Sim/AI/ConquestAi.cs:67
A21: defend/VeryHard | B21: defend | C21: VeryHard | D21: 30 | E21: 1.35 | F21: 22 | G21: 1.1 | H21: 1 | I21: 1.4 | J21: 0 | L21: Game/Match/ModeSessions.cs:682; Game/Match/ModeSessions.cs:685; Sim/AI/ConquestAi.cs:69 | M21: =IF(ISNUMBER($D$21),IF(AND(ISNUMBER(FIND(";"&Che_do!$B$6&";",";"&Kinh_te!$E$10&";")),$D$21>0,Kinh_te!$D$11<>1),ROUND($D$21*Kinh_te!$D$11,0),$D$21),"") | N21: 35 | O21: =IF(ISNUMBER($F$21),IF(AND(ISNUMBER(FIND(";"&Che_do!$B$6&";",";"&Kinh_te!$E$10&";")),$F$21>0,Kinh_te!$D$11<>1),ROUND($F$21*Kinh_te!$D$11,0),$F$21),"") | P21: 26 | Q21: =($E$21+$J$21)*Kinh_te!$D$9 | R21: 1.215 | S21: =IF(ISNUMBER($G$21),($G$21+$J$21)*Kinh_te!$D$9*$H$21*$I$21,"") | T21: 1.386 | U21: =Che_do_thoi_luong!$Q$6 | V21: =IF(AND(ISNUMBER($U$21),ISNUMBER($M$21)),$M$21+$Q$21*0.25*$U$21,"") | W21: =IF(AND(ISNUMBER($U$21),ISNUMBER($M$21)),$M$21+$Q$21*0.5*$U$21,"") | X21: =IF(AND(ISNUMBER($U$21),ISNUMBER($M$21)),$M$21+$Q$21*0.75*$U$21,"") | Y21: =IF(AND(ISNUMBER($U$21),ISNUMBER($M$21)),$M$21+$Q$21*1.0*$U$21,"") | Z21: =IF(AND(ISNUMBER($U$21),ISNUMBER($O$21)),$O$21+$S$21*0.25*$U$21,"") | AA21: =IF(AND(ISNUMBER($U$21),ISNUMBER($O$21)),$O$21+$S$21*0.5*$U$21,"") | AB21: =IF(AND(ISNUMBER($U$21),ISNUMBER($O$21)),$O$21+$S$21*0.75*$U$21,"") | AC21: =IF(AND(ISNUMBER($U$21),ISNUMBER($O$21)),$O$21+$S$21*1.0*$U$21,"") | AD21: =IF(AND(ISNUMBER($AC$21),ISNUMBER($Y$21)),$AC$21/$Y$21,"") | AE21: C#: Game/Match/ModeSessions.cs:682; Game/Match/ModeSessions.cs:685; Sim/AI/ConquestAi.cs:69
A22: endless/Easy | B22: endless | C22: Easy | D22: 30 | E22: 1.35 | F22: 22 | G22: 1.1 | H22: 1 | I22: 0.8 | J22: 0 | L22: Game/Match/ModeSessions.cs:682; Game/Match/ModeSessions.cs:685; Sim/AI/ConquestAi.cs:65 | M22: =IF(ISNUMBER($D$22),IF(AND(ISNUMBER(FIND(";"&Che_do!$B$7&";",";"&Kinh_te!$E$10&";")),$D$22>0,Kinh_te!$D$11<>1),ROUND($D$22*Kinh_te!$D$11,0),$D$22),"") | N22: 35 | O22: =IF(ISNUMBER($F$22),IF(AND(ISNUMBER(FIND(";"&Che_do!$B$7&";",";"&Kinh_te!$E$10&";")),$F$22>0,Kinh_te!$D$11<>1),ROUND($F$22*Kinh_te!$D$11,0),$F$22),"") | P22: 26 | Q22: =($E$22+$J$22)*Kinh_te!$D$9 | R22: 1.215 | S22: =IF(ISNUMBER($G$22),($G$22+$J$22)*Kinh_te!$D$9*$H$22*$I$22,"") | T22: 0.792 | U22: =Che_do_thoi_luong!$Q$7 | V22: =IF(AND(ISNUMBER($U$22),ISNUMBER($M$22)),$M$22+$Q$22*0.25*$U$22,"") | W22: =IF(AND(ISNUMBER($U$22),ISNUMBER($M$22)),$M$22+$Q$22*0.5*$U$22,"") | X22: =IF(AND(ISNUMBER($U$22),ISNUMBER($M$22)),$M$22+$Q$22*0.75*$U$22,"") | Y22: =IF(AND(ISNUMBER($U$22),ISNUMBER($M$22)),$M$22+$Q$22*1.0*$U$22,"") | Z22: =IF(AND(ISNUMBER($U$22),ISNUMBER($O$22)),$O$22+$S$22*0.25*$U$22,"") | AA22: =IF(AND(ISNUMBER($U$22),ISNUMBER($O$22)),$O$22+$S$22*0.5*$U$22,"") | AB22: =IF(AND(ISNUMBER($U$22),ISNUMBER($O$22)),$O$22+$S$22*0.75*$U$22,"") | AC22: =IF(AND(ISNUMBER($U$22),ISNUMBER($O$22)),$O$22+$S$22*1.0*$U$22,"") | AD22: =IF(AND(ISNUMBER($AC$22),ISNUMBER($Y$22)),$AC$22/$Y$22,"") | AE22: C#: Game/Match/ModeSessions.cs:682; Game/Match/ModeSessions.cs:685; Sim/AI/ConquestAi.cs:65
A23: endless/Hard | B23: endless | C23: Hard | D23: 30 | E23: 1.35 | F23: 22 | G23: 1.1 | H23: 1 | I23: 1.2 | J23: 0 | L23: Game/Match/ModeSessions.cs:682; Game/Match/ModeSessions.cs:685; Sim/AI/ConquestAi.cs:68 | M23: =IF(ISNUMBER($D$23),IF(AND(ISNUMBER(FIND(";"&Che_do!$B$7&";",";"&Kinh_te!$E$10&";")),$D$23>0,Kinh_te!$D$11<>1),ROUND($D$23*Kinh_te!$D$11,0),$D$23),"") | N23: 35 | O23: =IF(ISNUMBER($F$23),IF(AND(ISNUMBER(FIND(";"&Che_do!$B$7&";",";"&Kinh_te!$E$10&";")),$F$23>0,Kinh_te!$D$11<>1),ROUND($F$23*Kinh_te!$D$11,0),$F$23),"") | P23: 26 | Q23: =($E$23+$J$23)*Kinh_te!$D$9 | R23: 1.215 | S23: =IF(ISNUMBER($G$23),($G$23+$J$23)*Kinh_te!$D$9*$H$23*$I$23,"") | T23: 1.188 | U23: =Che_do_thoi_luong!$Q$7 | V23: =IF(AND(ISNUMBER($U$23),ISNUMBER($M$23)),$M$23+$Q$23*0.25*$U$23,"") | W23: =IF(AND(ISNUMBER($U$23),ISNUMBER($M$23)),$M$23+$Q$23*0.5*$U$23,"") | X23: =IF(AND(ISNUMBER($U$23),ISNUMBER($M$23)),$M$23+$Q$23*0.75*$U$23,"") | Y23: =IF(AND(ISNUMBER($U$23),ISNUMBER($M$23)),$M$23+$Q$23*1.0*$U$23,"") | Z23: =IF(AND(ISNUMBER($U$23),ISNUMBER($O$23)),$O$23+$S$23*0.25*$U$23,"") | AA23: =IF(AND(ISNUMBER($U$23),ISNUMBER($O$23)),$O$23+$S$23*0.5*$U$23,"") | AB23: =IF(AND(ISNUMBER($U$23),ISNUMBER($O$23)),$O$23+$S$23*0.75*$U$23,"") | AC23: =IF(AND(ISNUMBER($U$23),ISNUMBER($O$23)),$O$23+$S$23*1.0*$U$23,"") | AD23: =IF(AND(ISNUMBER($AC$23),ISNUMBER($Y$23)),$AC$23/$Y$23,"") | AE23: C#: Game/Match/ModeSessions.cs:682; Game/Match/ModeSessions.cs:685; Sim/AI/ConquestAi.cs:68
A24: endless/Normal | B24: endless | C24: Normal | D24: 30 | E24: 1.35 | F24: 22 | G24: 1.1 | H24: 1 | I24: 0.7 | J24: 0 | L24: Game/Match/ModeSessions.cs:682; Game/Match/ModeSessions.cs:685; Sim/AI/ConquestAi.cs:67 | M24: =IF(ISNUMBER($D$24),IF(AND(ISNUMBER(FIND(";"&Che_do!$B$7&";",";"&Kinh_te!$E$10&";")),$D$24>0,Kinh_te!$D$11<>1),ROUND($D$24*Kinh_te!$D$11,0),$D$24),"") | N24: 35 | O24: =IF(ISNUMBER($F$24),IF(AND(ISNUMBER(FIND(";"&Che_do!$B$7&";",";"&Kinh_te!$E$10&";")),$F$24>0,Kinh_te!$D$11<>1),ROUND($F$24*Kinh_te!$D$11,0),$F$24),"") | P24: 26 | Q24: =($E$24+$J$24)*Kinh_te!$D$9 | R24: 1.215 | S24: =IF(ISNUMBER($G$24),($G$24+$J$24)*Kinh_te!$D$9*$H$24*$I$24,"") | T24: 0.693 | U24: =Che_do_thoi_luong!$Q$7 | V24: =IF(AND(ISNUMBER($U$24),ISNUMBER($M$24)),$M$24+$Q$24*0.25*$U$24,"") | W24: =IF(AND(ISNUMBER($U$24),ISNUMBER($M$24)),$M$24+$Q$24*0.5*$U$24,"") | X24: =IF(AND(ISNUMBER($U$24),ISNUMBER($M$24)),$M$24+$Q$24*0.75*$U$24,"") | Y24: =IF(AND(ISNUMBER($U$24),ISNUMBER($M$24)),$M$24+$Q$24*1.0*$U$24,"") | Z24: =IF(AND(ISNUMBER($U$24),ISNUMBER($O$24)),$O$24+$S$24*0.25*$U$24,"") | AA24: =IF(AND(ISNUMBER($U$24),ISNUMBER($O$24)),$O$24+$S$24*0.5*$U$24,"") | AB24: =IF(AND(ISNUMBER($U$24),ISNUMBER($O$24)),$O$24+$S$24*0.75*$U$24,"") | AC24: =IF(AND(ISNUMBER($U$24),ISNUMBER($O$24)),$O$24+$S$24*1.0*$U$24,"") | AD24: =IF(AND(ISNUMBER($AC$24),ISNUMBER($Y$24)),$AC$24/$Y$24,"") | AE24: C#: Game/Match/ModeSessions.cs:682; Game/Match/ModeSessions.cs:685; Sim/AI/ConquestAi.cs:67
A25: endless/VeryHard | B25: endless | C25: VeryHard | D25: 30 | E25: 1.35 | F25: 22 | G25: 1.1 | H25: 1 | I25: 1.4 | J25: 0 | L25: Game/Match/ModeSessions.cs:682; Game/Match/ModeSessions.cs:685; Sim/AI/ConquestAi.cs:69 | M25: =IF(ISNUMBER($D$25),IF(AND(ISNUMBER(FIND(";"&Che_do!$B$7&";",";"&Kinh_te!$E$10&";")),$D$25>0,Kinh_te!$D$11<>1),ROUND($D$25*Kinh_te!$D$11,0),$D$25),"") | N25: 35 | O25: =IF(ISNUMBER($F$25),IF(AND(ISNUMBER(FIND(";"&Che_do!$B$7&";",";"&Kinh_te!$E$10&";")),$F$25>0,Kinh_te!$D$11<>1),ROUND($F$25*Kinh_te!$D$11,0),$F$25),"") | P25: 26 | Q25: =($E$25+$J$25)*Kinh_te!$D$9 | R25: 1.215 | S25: =IF(ISNUMBER($G$25),($G$25+$J$25)*Kinh_te!$D$9*$H$25*$I$25,"") | T25: 1.386 | U25: =Che_do_thoi_luong!$Q$7 | V25: =IF(AND(ISNUMBER($U$25),ISNUMBER($M$25)),$M$25+$Q$25*0.25*$U$25,"") | W25: =IF(AND(ISNUMBER($U$25),ISNUMBER($M$25)),$M$25+$Q$25*0.5*$U$25,"") | X25: =IF(AND(ISNUMBER($U$25),ISNUMBER($M$25)),$M$25+$Q$25*0.75*$U$25,"") | Y25: =IF(AND(ISNUMBER($U$25),ISNUMBER($M$25)),$M$25+$Q$25*1.0*$U$25,"") | Z25: =IF(AND(ISNUMBER($U$25),ISNUMBER($O$25)),$O$25+$S$25*0.25*$U$25,"") | AA25: =IF(AND(ISNUMBER($U$25),ISNUMBER($O$25)),$O$25+$S$25*0.5*$U$25,"") | AB25: =IF(AND(ISNUMBER($U$25),ISNUMBER($O$25)),$O$25+$S$25*0.75*$U$25,"") | AC25: =IF(AND(ISNUMBER($U$25),ISNUMBER($O$25)),$O$25+$S$25*1.0*$U$25,"") | AD25: =IF(AND(ISNUMBER($AC$25),ISNUMBER($Y$25)),$AC$25/$Y$25,"") | AE25: C#: Game/Match/ModeSessions.cs:682; Game/Match/ModeSessions.cs:685; Sim/AI/ConquestAi.cs:69
A26: hill/Easy | B26: hill | C26: Easy | D26: 16 | E26: 1.2 | F26: 16 | G26: 1.1 | H26: 1 | I26: 0.8 | J26: 0.175 | K26: bên giữ đồi +0,35 CP/s, mỗi bên giữ một nửa thời gian | L26: Game/Match/ModeSessions.cs:560; Sim/Modes/QuickModes.cs:251; Sim/AI/ConquestAi.cs:65 | M26: =IF(ISNUMBER($D$26),IF(AND(ISNUMBER(FIND(";"&Che_do!$B$8&";",";"&Kinh_te!$E$10&";")),$D$26>0,Kinh_te!$D$11<>1),ROUND($D$26*Kinh_te!$D$11,0),$D$26),"") | N26: 19 | O26: =IF(ISNUMBER($F$26),IF(AND(ISNUMBER(FIND(";"&Che_do!$B$8&";",";"&Kinh_te!$E$10&";")),$F$26>0,Kinh_te!$D$11<>1),ROUND($F$26*Kinh_te!$D$11,0),$F$26),"") | P26: 19 | Q26: =($E$26+$J$26)*Kinh_te!$D$9 | R26: 1.2375 | S26: =IF(ISNUMBER($G$26),($G$26+$J$26)*Kinh_te!$D$9*$H$26*$I$26,"") | T26: 0.918 | U26: =Che_do_thoi_luong!$Q$8 | V26: =IF(AND(ISNUMBER($U$26),ISNUMBER($M$26)),$M$26+$Q$26*0.25*$U$26,"") | W26: =IF(AND(ISNUMBER($U$26),ISNUMBER($M$26)),$M$26+$Q$26*0.5*$U$26,"") | X26: =IF(AND(ISNUMBER($U$26),ISNUMBER($M$26)),$M$26+$Q$26*0.75*$U$26,"") | Y26: =IF(AND(ISNUMBER($U$26),ISNUMBER($M$26)),$M$26+$Q$26*1.0*$U$26,"") | Z26: =IF(AND(ISNUMBER($U$26),ISNUMBER($O$26)),$O$26+$S$26*0.25*$U$26,"") | AA26: =IF(AND(ISNUMBER($U$26),ISNUMBER($O$26)),$O$26+$S$26*0.5*$U$26,"") | AB26: =IF(AND(ISNUMBER($U$26),ISNUMBER($O$26)),$O$26+$S$26*0.75*$U$26,"") | AC26: =IF(AND(ISNUMBER($U$26),ISNUMBER($O$26)),$O$26+$S$26*1.0*$U$26,"") | AD26: =IF(AND(ISNUMBER($AC$26),ISNUMBER($Y$26)),$AC$26/$Y$26,"") | AE26: C#: Game/Match/ModeSessions.cs:560; Sim/Modes/QuickModes.cs:251; Sim/AI/ConquestAi.cs:65
A27: hill/Hard | B27: hill | C27: Hard | D27: 16 | E27: 1.2 | F27: 16 | G27: 1.1 | H27: 1 | I27: 1.2 | J27: 0.175 | K27: bên giữ đồi +0,35 CP/s, mỗi bên giữ một nửa thời gian | L27: Game/Match/ModeSessions.cs:560; Sim/Modes/QuickModes.cs:251; Sim/AI/ConquestAi.cs:68 | M27: =IF(ISNUMBER($D$27),IF(AND(ISNUMBER(FIND(";"&Che_do!$B$8&";",";"&Kinh_te!$E$10&";")),$D$27>0,Kinh_te!$D$11<>1),ROUND($D$27*Kinh_te!$D$11,0),$D$27),"") | N27: 19 | O27: =IF(ISNUMBER($F$27),IF(AND(ISNUMBER(FIND(";"&Che_do!$B$8&";",";"&Kinh_te!$E$10&";")),$F$27>0,Kinh_te!$D$11<>1),ROUND($F$27*Kinh_te!$D$11,0),$F$27),"") | P27: 19 | Q27: =($E$27+$J$27)*Kinh_te!$D$9 | R27: 1.2375 | S27: =IF(ISNUMBER($G$27),($G$27+$J$27)*Kinh_te!$D$9*$H$27*$I$27,"") | T27: 1.377 | U27: =Che_do_thoi_luong!$Q$8 | V27: =IF(AND(ISNUMBER($U$27),ISNUMBER($M$27)),$M$27+$Q$27*0.25*$U$27,"") | W27: =IF(AND(ISNUMBER($U$27),ISNUMBER($M$27)),$M$27+$Q$27*0.5*$U$27,"") | X27: =IF(AND(ISNUMBER($U$27),ISNUMBER($M$27)),$M$27+$Q$27*0.75*$U$27,"") | Y27: =IF(AND(ISNUMBER($U$27),ISNUMBER($M$27)),$M$27+$Q$27*1.0*$U$27,"") | Z27: =IF(AND(ISNUMBER($U$27),ISNUMBER($O$27)),$O$27+$S$27*0.25*$U$27,"") | AA27: =IF(AND(ISNUMBER($U$27),ISNUMBER($O$27)),$O$27+$S$27*0.5*$U$27,"") | AB27: =IF(AND(ISNUMBER($U$27),ISNUMBER($O$27)),$O$27+$S$27*0.75*$U$27,"") | AC27: =IF(AND(ISNUMBER($U$27),ISNUMBER($O$27)),$O$27+$S$27*1.0*$U$27,"") | AD27: =IF(AND(ISNUMBER($AC$27),ISNUMBER($Y$27)),$AC$27/$Y$27,"") | AE27: C#: Game/Match/ModeSessions.cs:560; Sim/Modes/QuickModes.cs:251; Sim/AI/ConquestAi.cs:68
A28: hill/Normal | B28: hill | C28: Normal | D28: 16 | E28: 1.2 | F28: 16 | G28: 1.1 | H28: 1 | I28: 0.7 | J28: 0.175 | K28: bên giữ đồi +0,35 CP/s, mỗi bên giữ một nửa thời gian | L28: Game/Match/ModeSessions.cs:560; Sim/Modes/QuickModes.cs:251; Sim/AI/ConquestAi.cs:67 | M28: =IF(ISNUMBER($D$28),IF(AND(ISNUMBER(FIND(";"&Che_do!$B$8&";",";"&Kinh_te!$E$10&";")),$D$28>0,Kinh_te!$D$11<>1),ROUND($D$28*Kinh_te!$D$11,0),$D$28),"") | N28: 19 | O28: =IF(ISNUMBER($F$28),IF(AND(ISNUMBER(FIND(";"&Che_do!$B$8&";",";"&Kinh_te!$E$10&";")),$F$28>0,Kinh_te!$D$11<>1),ROUND($F$28*Kinh_te!$D$11,0),$F$28),"") | P28: 19 | Q28: =($E$28+$J$28)*Kinh_te!$D$9 | R28: 1.2375 | S28: =IF(ISNUMBER($G$28),($G$28+$J$28)*Kinh_te!$D$9*$H$28*$I$28,"") | T28: 0.80325 | U28: =Che_do_thoi_luong!$Q$8 | V28: =IF(AND(ISNUMBER($U$28),ISNUMBER($M$28)),$M$28+$Q$28*0.25*$U$28,"") | W28: =IF(AND(ISNUMBER($U$28),ISNUMBER($M$28)),$M$28+$Q$28*0.5*$U$28,"") | X28: =IF(AND(ISNUMBER($U$28),ISNUMBER($M$28)),$M$28+$Q$28*0.75*$U$28,"") | Y28: =IF(AND(ISNUMBER($U$28),ISNUMBER($M$28)),$M$28+$Q$28*1.0*$U$28,"") | Z28: =IF(AND(ISNUMBER($U$28),ISNUMBER($O$28)),$O$28+$S$28*0.25*$U$28,"") | AA28: =IF(AND(ISNUMBER($U$28),ISNUMBER($O$28)),$O$28+$S$28*0.5*$U$28,"") | AB28: =IF(AND(ISNUMBER($U$28),ISNUMBER($O$28)),$O$28+$S$28*0.75*$U$28,"") | AC28: =IF(AND(ISNUMBER($U$28),ISNUMBER($O$28)),$O$28+$S$28*1.0*$U$28,"") | AD28: =IF(AND(ISNUMBER($AC$28),ISNUMBER($Y$28)),$AC$28/$Y$28,"") | AE28: C#: Game/Match/ModeSessions.cs:560; Sim/Modes/QuickModes.cs:251; Sim/AI/ConquestAi.cs:67
A29: hill/VeryHard | B29: hill | C29: VeryHard | D29: 16 | E29: 1.2 | F29: 16 | G29: 1.1 | H29: 1 | I29: 1.4 | J29: 0.175 | K29: bên giữ đồi +0,35 CP/s, mỗi bên giữ một nửa thời gian | L29: Game/Match/ModeSessions.cs:560; Sim/Modes/QuickModes.cs:251; Sim/AI/ConquestAi.cs:69 | M29: =IF(ISNUMBER($D$29),IF(AND(ISNUMBER(FIND(";"&Che_do!$B$8&";",";"&Kinh_te!$E$10&";")),$D$29>0,Kinh_te!$D$11<>1),ROUND($D$29*Kinh_te!$D$11,0),$D$29),"") | N29: 19 | O29: =IF(ISNUMBER($F$29),IF(AND(ISNUMBER(FIND(";"&Che_do!$B$8&";",";"&Kinh_te!$E$10&";")),$F$29>0,Kinh_te!$D$11<>1),ROUND($F$29*Kinh_te!$D$11,0),$F$29),"") | P29: 19 | Q29: =($E$29+$J$29)*Kinh_te!$D$9 | R29: 1.2375 | S29: =IF(ISNUMBER($G$29),($G$29+$J$29)*Kinh_te!$D$9*$H$29*$I$29,"") | T29: 1.6065 | U29: =Che_do_thoi_luong!$Q$8 | V29: =IF(AND(ISNUMBER($U$29),ISNUMBER($M$29)),$M$29+$Q$29*0.25*$U$29,"") | W29: =IF(AND(ISNUMBER($U$29),ISNUMBER($M$29)),$M$29+$Q$29*0.5*$U$29,"") | X29: =IF(AND(ISNUMBER($U$29),ISNUMBER($M$29)),$M$29+$Q$29*0.75*$U$29,"") | Y29: =IF(AND(ISNUMBER($U$29),ISNUMBER($M$29)),$M$29+$Q$29*1.0*$U$29,"") | Z29: =IF(AND(ISNUMBER($U$29),ISNUMBER($O$29)),$O$29+$S$29*0.25*$U$29,"") | AA29: =IF(AND(ISNUMBER($U$29),ISNUMBER($O$29)),$O$29+$S$29*0.5*$U$29,"") | AB29: =IF(AND(ISNUMBER($U$29),ISNUMBER($O$29)),$O$29+$S$29*0.75*$U$29,"") | AC29: =IF(AND(ISNUMBER($U$29),ISNUMBER($O$29)),$O$29+$S$29*1.0*$U$29,"") | AD29: =IF(AND(ISNUMBER($AC$29),ISNUMBER($Y$29)),$AC$29/$Y$29,"") | AE29: C#: Game/Match/ModeSessions.cs:560; Sim/Modes/QuickModes.cs:251; Sim/AI/ConquestAi.cs:69
A30: showdown/Easy | B30: showdown | C30: Easy | D30: 18 | E30: 1.35 | F30: 18 | G30: 1.35 | H30: 1 | I30: 0.8 | J30: 0 | L30: Game/Match/ShowdownSession.cs:48; Sim/AI/ConquestAi.cs:65 | M30: =IF(ISNUMBER($D$30),IF(AND(ISNUMBER(FIND(";"&Che_do!$B$10&";",";"&Kinh_te!$E$10&";")),$D$30>0,Kinh_te!$D$11<>1),ROUND($D$30*Kinh_te!$D$11,0),$D$30),"") | N30: 21 | O30: =IF(ISNUMBER($F$30),IF(AND(ISNUMBER(FIND(";"&Che_do!$B$10&";",";"&Kinh_te!$E$10&";")),$F$30>0,Kinh_te!$D$11<>1),ROUND($F$30*Kinh_te!$D$11,0),$F$30),"") | P30: 21 | Q30: =($E$30+$J$30)*Kinh_te!$D$9 | R30: 1.215 | S30: =IF(ISNUMBER($G$30),($G$30+$J$30)*Kinh_te!$D$9*$H$30*$I$30,"") | T30: 0.972 | U30: =Che_do_thoi_luong!$Q$10 | V30: =IF(AND(ISNUMBER($U$30),ISNUMBER($M$30)),$M$30+$Q$30*0.25*$U$30,"") | W30: =IF(AND(ISNUMBER($U$30),ISNUMBER($M$30)),$M$30+$Q$30*0.5*$U$30,"") | X30: =IF(AND(ISNUMBER($U$30),ISNUMBER($M$30)),$M$30+$Q$30*0.75*$U$30,"") | Y30: =IF(AND(ISNUMBER($U$30),ISNUMBER($M$30)),$M$30+$Q$30*1.0*$U$30,"") | Z30: =IF(AND(ISNUMBER($U$30),ISNUMBER($O$30)),$O$30+$S$30*0.25*$U$30,"") | AA30: =IF(AND(ISNUMBER($U$30),ISNUMBER($O$30)),$O$30+$S$30*0.5*$U$30,"") | AB30: =IF(AND(ISNUMBER($U$30),ISNUMBER($O$30)),$O$30+$S$30*0.75*$U$30,"") | AC30: =IF(AND(ISNUMBER($U$30),ISNUMBER($O$30)),$O$30+$S$30*1.0*$U$30,"") | AD30: =IF(AND(ISNUMBER($AC$30),ISNUMBER($Y$30)),$AC$30/$Y$30,"") | AE30: C#: Game/Match/ShowdownSession.cs:48; Sim/AI/ConquestAi.cs:65
A31: showdown/Hard | B31: showdown | C31: Hard | D31: 18 | E31: 1.35 | F31: 18 | G31: 1.35 | H31: 1 | I31: 1.2 | J31: 0 | L31: Game/Match/ShowdownSession.cs:48; Sim/AI/ConquestAi.cs:68 | M31: =IF(ISNUMBER($D$31),IF(AND(ISNUMBER(FIND(";"&Che_do!$B$10&";",";"&Kinh_te!$E$10&";")),$D$31>0,Kinh_te!$D$11<>1),ROUND($D$31*Kinh_te!$D$11,0),$D$31),"") | N31: 21 | O31: =IF(ISNUMBER($F$31),IF(AND(ISNUMBER(FIND(";"&Che_do!$B$10&";",";"&Kinh_te!$E$10&";")),$F$31>0,Kinh_te!$D$11<>1),ROUND($F$31*Kinh_te!$D$11,0),$F$31),"") | P31: 21 | Q31: =($E$31+$J$31)*Kinh_te!$D$9 | R31: 1.215 | S31: =IF(ISNUMBER($G$31),($G$31+$J$31)*Kinh_te!$D$9*$H$31*$I$31,"") | T31: 1.458 | U31: =Che_do_thoi_luong!$Q$10 | V31: =IF(AND(ISNUMBER($U$31),ISNUMBER($M$31)),$M$31+$Q$31*0.25*$U$31,"") | W31: =IF(AND(ISNUMBER($U$31),ISNUMBER($M$31)),$M$31+$Q$31*0.5*$U$31,"") | X31: =IF(AND(ISNUMBER($U$31),ISNUMBER($M$31)),$M$31+$Q$31*0.75*$U$31,"") | Y31: =IF(AND(ISNUMBER($U$31),ISNUMBER($M$31)),$M$31+$Q$31*1.0*$U$31,"") | Z31: =IF(AND(ISNUMBER($U$31),ISNUMBER($O$31)),$O$31+$S$31*0.25*$U$31,"") | AA31: =IF(AND(ISNUMBER($U$31),ISNUMBER($O$31)),$O$31+$S$31*0.5*$U$31,"") | AB31: =IF(AND(ISNUMBER($U$31),ISNUMBER($O$31)),$O$31+$S$31*0.75*$U$31,"") | AC31: =IF(AND(ISNUMBER($U$31),ISNUMBER($O$31)),$O$31+$S$31*1.0*$U$31,"") | AD31: =IF(AND(ISNUMBER($AC$31),ISNUMBER($Y$31)),$AC$31/$Y$31,"") | AE31: C#: Game/Match/ShowdownSession.cs:48; Sim/AI/ConquestAi.cs:68
A32: showdown/Normal | B32: showdown | C32: Normal | D32: 18 | E32: 1.35 | F32: 18 | G32: 1.35 | H32: 1 | I32: 0.7 | J32: 0 | L32: Game/Match/ShowdownSession.cs:48; Sim/AI/ConquestAi.cs:67 | M32: =IF(ISNUMBER($D$32),IF(AND(ISNUMBER(FIND(";"&Che_do!$B$10&";",";"&Kinh_te!$E$10&";")),$D$32>0,Kinh_te!$D$11<>1),ROUND($D$32*Kinh_te!$D$11,0),$D$32),"") | N32: 21 | O32: =IF(ISNUMBER($F$32),IF(AND(ISNUMBER(FIND(";"&Che_do!$B$10&";",";"&Kinh_te!$E$10&";")),$F$32>0,Kinh_te!$D$11<>1),ROUND($F$32*Kinh_te!$D$11,0),$F$32),"") | P32: 21 | Q32: =($E$32+$J$32)*Kinh_te!$D$9 | R32: 1.215 | S32: =IF(ISNUMBER($G$32),($G$32+$J$32)*Kinh_te!$D$9*$H$32*$I$32,"") | T32: 0.8505 | U32: =Che_do_thoi_luong!$Q$10 | V32: =IF(AND(ISNUMBER($U$32),ISNUMBER($M$32)),$M$32+$Q$32*0.25*$U$32,"") | W32: =IF(AND(ISNUMBER($U$32),ISNUMBER($M$32)),$M$32+$Q$32*0.5*$U$32,"") | X32: =IF(AND(ISNUMBER($U$32),ISNUMBER($M$32)),$M$32+$Q$32*0.75*$U$32,"") | Y32: =IF(AND(ISNUMBER($U$32),ISNUMBER($M$32)),$M$32+$Q$32*1.0*$U$32,"") | Z32: =IF(AND(ISNUMBER($U$32),ISNUMBER($O$32)),$O$32+$S$32*0.25*$U$32,"") | AA32: =IF(AND(ISNUMBER($U$32),ISNUMBER($O$32)),$O$32+$S$32*0.5*$U$32,"") | AB32: =IF(AND(ISNUMBER($U$32),ISNUMBER($O$32)),$O$32+$S$32*0.75*$U$32,"") | AC32: =IF(AND(ISNUMBER($U$32),ISNUMBER($O$32)),$O$32+$S$32*1.0*$U$32,"") | AD32: =IF(AND(ISNUMBER($AC$32),ISNUMBER($Y$32)),$AC$32/$Y$32,"") | AE32: C#: Game/Match/ShowdownSession.cs:48; Sim/AI/ConquestAi.cs:67
A33: showdown/VeryHard | B33: showdown | C33: VeryHard | D33: 18 | E33: 1.35 | F33: 18 | G33: 1.35 | H33: 1 | I33: 1.4 | J33: 0 | L33: Game/Match/ShowdownSession.cs:48; Sim/AI/ConquestAi.cs:69 | M33: =IF(ISNUMBER($D$33),IF(AND(ISNUMBER(FIND(";"&Che_do!$B$10&";",";"&Kinh_te!$E$10&";")),$D$33>0,Kinh_te!$D$11<>1),ROUND($D$33*Kinh_te!$D$11,0),$D$33),"") | N33: 21 | O33: =IF(ISNUMBER($F$33),IF(AND(ISNUMBER(FIND(";"&Che_do!$B$10&";",";"&Kinh_te!$E$10&";")),$F$33>0,Kinh_te!$D$11<>1),ROUND($F$33*Kinh_te!$D$11,0),$F$33),"") | P33: 21 | Q33: =($E$33+$J$33)*Kinh_te!$D$9 | R33: 1.215 | S33: =IF(ISNUMBER($G$33),($G$33+$J$33)*Kinh_te!$D$9*$H$33*$I$33,"") | T33: 1.701 | U33: =Che_do_thoi_luong!$Q$10 | V33: =IF(AND(ISNUMBER($U$33),ISNUMBER($M$33)),$M$33+$Q$33*0.25*$U$33,"") | W33: =IF(AND(ISNUMBER($U$33),ISNUMBER($M$33)),$M$33+$Q$33*0.5*$U$33,"") | X33: =IF(AND(ISNUMBER($U$33),ISNUMBER($M$33)),$M$33+$Q$33*0.75*$U$33,"") | Y33: =IF(AND(ISNUMBER($U$33),ISNUMBER($M$33)),$M$33+$Q$33*1.0*$U$33,"") | Z33: =IF(AND(ISNUMBER($U$33),ISNUMBER($O$33)),$O$33+$S$33*0.25*$U$33,"") | AA33: =IF(AND(ISNUMBER($U$33),ISNUMBER($O$33)),$O$33+$S$33*0.5*$U$33,"") | AB33: =IF(AND(ISNUMBER($U$33),ISNUMBER($O$33)),$O$33+$S$33*0.75*$U$33,"") | AC33: =IF(AND(ISNUMBER($U$33),ISNUMBER($O$33)),$O$33+$S$33*1.0*$U$33,"") | AD33: =IF(AND(ISNUMBER($AC$33),ISNUMBER($Y$33)),$AC$33/$Y$33,"") | AE33: C#: Game/Match/ShowdownSession.cs:48; Sim/AI/ConquestAi.cs:69
A34: siege/Easy | B34: siege | C34: Easy | D34: 38 | E34: 2.4 | F34: 20 | G34: 0.8 | H34: 1 | I34: 0.8 | J34: 0 | L34: Game/Match/ModeSessions.cs:863; Game/Match/ModeSessions.cs:871; Sim/AI/ConquestAi.cs:65 | M34: =IF(ISNUMBER($D$34),IF(AND(ISNUMBER(FIND(";"&Che_do!$B$11&";",";"&Kinh_te!$E$10&";")),$D$34>0,Kinh_te!$D$11<>1),ROUND($D$34*Kinh_te!$D$11,0),$D$34),"") | N34: 44 | O34: =IF(ISNUMBER($F$34),IF(AND(ISNUMBER(FIND(";"&Che_do!$B$11&";",";"&Kinh_te!$E$10&";")),$F$34>0,Kinh_te!$D$11<>1),ROUND($F$34*Kinh_te!$D$11,0),$F$34),"") | P34: 23 | Q34: =($E$34+$J$34)*Kinh_te!$D$9 | R34: 2.16 | S34: =IF(ISNUMBER($G$34),($G$34+$J$34)*Kinh_te!$D$9*$H$34*$I$34,"") | T34: 0.576 | U34: =Che_do_thoi_luong!$Q$11 | V34: =IF(AND(ISNUMBER($U$34),ISNUMBER($M$34)),$M$34+$Q$34*0.25*$U$34,"") | W34: =IF(AND(ISNUMBER($U$34),ISNUMBER($M$34)),$M$34+$Q$34*0.5*$U$34,"") | X34: =IF(AND(ISNUMBER($U$34),ISNUMBER($M$34)),$M$34+$Q$34*0.75*$U$34,"") | Y34: =IF(AND(ISNUMBER($U$34),ISNUMBER($M$34)),$M$34+$Q$34*1.0*$U$34,"") | Z34: =IF(AND(ISNUMBER($U$34),ISNUMBER($O$34)),$O$34+$S$34*0.25*$U$34,"") | AA34: =IF(AND(ISNUMBER($U$34),ISNUMBER($O$34)),$O$34+$S$34*0.5*$U$34,"") | AB34: =IF(AND(ISNUMBER($U$34),ISNUMBER($O$34)),$O$34+$S$34*0.75*$U$34,"") | AC34: =IF(AND(ISNUMBER($U$34),ISNUMBER($O$34)),$O$34+$S$34*1.0*$U$34,"") | AD34: =IF(AND(ISNUMBER($AC$34),ISNUMBER($Y$34)),$AC$34/$Y$34,"") | AE34: C#: Game/Match/ModeSessions.cs:863; Game/Match/ModeSessions.cs:871; Sim/AI/ConquestAi.cs:65
A35: siege/Hard | B35: siege | C35: Hard | D35: 38 | E35: 2.4 | F35: 24 | G35: 0.8 | H35: 1 | I35: 1.2 | J35: 0 | L35: Game/Match/ModeSessions.cs:863; Game/Match/ModeSessions.cs:871; Sim/AI/ConquestAi.cs:68 | M35: =IF(ISNUMBER($D$35),IF(AND(ISNUMBER(FIND(";"&Che_do!$B$11&";",";"&Kinh_te!$E$10&";")),$D$35>0,Kinh_te!$D$11<>1),ROUND($D$35*Kinh_te!$D$11,0),$D$35),"") | N35: 44 | O35: =IF(ISNUMBER($F$35),IF(AND(ISNUMBER(FIND(";"&Che_do!$B$11&";",";"&Kinh_te!$E$10&";")),$F$35>0,Kinh_te!$D$11<>1),ROUND($F$35*Kinh_te!$D$11,0),$F$35),"") | P35: 28 | Q35: =($E$35+$J$35)*Kinh_te!$D$9 | R35: 2.16 | S35: =IF(ISNUMBER($G$35),($G$35+$J$35)*Kinh_te!$D$9*$H$35*$I$35,"") | T35: 0.864 | U35: =Che_do_thoi_luong!$Q$11 | V35: =IF(AND(ISNUMBER($U$35),ISNUMBER($M$35)),$M$35+$Q$35*0.25*$U$35,"") | W35: =IF(AND(ISNUMBER($U$35),ISNUMBER($M$35)),$M$35+$Q$35*0.5*$U$35,"") | X35: =IF(AND(ISNUMBER($U$35),ISNUMBER($M$35)),$M$35+$Q$35*0.75*$U$35,"") | Y35: =IF(AND(ISNUMBER($U$35),ISNUMBER($M$35)),$M$35+$Q$35*1.0*$U$35,"") | Z35: =IF(AND(ISNUMBER($U$35),ISNUMBER($O$35)),$O$35+$S$35*0.25*$U$35,"") | AA35: =IF(AND(ISNUMBER($U$35),ISNUMBER($O$35)),$O$35+$S$35*0.5*$U$35,"") | AB35: =IF(AND(ISNUMBER($U$35),ISNUMBER($O$35)),$O$35+$S$35*0.75*$U$35,"") | AC35: =IF(AND(ISNUMBER($U$35),ISNUMBER($O$35)),$O$35+$S$35*1.0*$U$35,"") | AD35: =IF(AND(ISNUMBER($AC$35),ISNUMBER($Y$35)),$AC$35/$Y$35,"") | AE35: C#: Game/Match/ModeSessions.cs:863; Game/Match/ModeSessions.cs:871; Sim/AI/ConquestAi.cs:68
A36: siege/Normal | B36: siege | C36: Normal | D36: 38 | E36: 2.4 | F36: 20 | G36: 0.8 | H36: 1 | I36: 0.7 | J36: 0 | L36: Game/Match/ModeSessions.cs:863; Game/Match/ModeSessions.cs:871; Sim/AI/ConquestAi.cs:67 | M36: =IF(ISNUMBER($D$36),IF(AND(ISNUMBER(FIND(";"&Che_do!$B$11&";",";"&Kinh_te!$E$10&";")),$D$36>0,Kinh_te!$D$11<>1),ROUND($D$36*Kinh_te!$D$11,0),$D$36),"") | N36: 44 | O36: =IF(ISNUMBER($F$36),IF(AND(ISNUMBER(FIND(";"&Che_do!$B$11&";",";"&Kinh_te!$E$10&";")),$F$36>0,Kinh_te!$D$11<>1),ROUND($F$36*Kinh_te!$D$11,0),$F$36),"") | P36: 23 | Q36: =($E$36+$J$36)*Kinh_te!$D$9 | R36: 2.16 | S36: =IF(ISNUMBER($G$36),($G$36+$J$36)*Kinh_te!$D$9*$H$36*$I$36,"") | T36: 0.504 | U36: =Che_do_thoi_luong!$Q$11 | V36: =IF(AND(ISNUMBER($U$36),ISNUMBER($M$36)),$M$36+$Q$36*0.25*$U$36,"") | W36: =IF(AND(ISNUMBER($U$36),ISNUMBER($M$36)),$M$36+$Q$36*0.5*$U$36,"") | X36: =IF(AND(ISNUMBER($U$36),ISNUMBER($M$36)),$M$36+$Q$36*0.75*$U$36,"") | Y36: =IF(AND(ISNUMBER($U$36),ISNUMBER($M$36)),$M$36+$Q$36*1.0*$U$36,"") | Z36: =IF(AND(ISNUMBER($U$36),ISNUMBER($O$36)),$O$36+$S$36*0.25*$U$36,"") | AA36: =IF(AND(ISNUMBER($U$36),ISNUMBER($O$36)),$O$36+$S$36*0.5*$U$36,"") | AB36: =IF(AND(ISNUMBER($U$36),ISNUMBER($O$36)),$O$36+$S$36*0.75*$U$36,"") | AC36: =IF(AND(ISNUMBER($U$36),ISNUMBER($O$36)),$O$36+$S$36*1.0*$U$36,"") | AD36: =IF(AND(ISNUMBER($AC$36),ISNUMBER($Y$36)),$AC$36/$Y$36,"") | AE36: C#: Game/Match/ModeSessions.cs:863; Game/Match/ModeSessions.cs:871; Sim/AI/ConquestAi.cs:67
A37: siege/VeryHard | B37: siege | C37: VeryHard | D37: 38 | E37: 2.4 | F37: 24 | G37: 0.8 | H37: 1 | I37: 1.4 | J37: 0 | L37: Game/Match/ModeSessions.cs:863; Game/Match/ModeSessions.cs:871; Sim/AI/ConquestAi.cs:69 | M37: =IF(ISNUMBER($D$37),IF(AND(ISNUMBER(FIND(";"&Che_do!$B$11&";",";"&Kinh_te!$E$10&";")),$D$37>0,Kinh_te!$D$11<>1),ROUND($D$37*Kinh_te!$D$11,0),$D$37),"") | N37: 44 | O37: =IF(ISNUMBER($F$37),IF(AND(ISNUMBER(FIND(";"&Che_do!$B$11&";",";"&Kinh_te!$E$10&";")),$F$37>0,Kinh_te!$D$11<>1),ROUND($F$37*Kinh_te!$D$11,0),$F$37),"") | P37: 28 | Q37: =($E$37+$J$37)*Kinh_te!$D$9 | R37: 2.16 | S37: =IF(ISNUMBER($G$37),($G$37+$J$37)*Kinh_te!$D$9*$H$37*$I$37,"") | T37: 1.008 | U37: =Che_do_thoi_luong!$Q$11 | V37: =IF(AND(ISNUMBER($U$37),ISNUMBER($M$37)),$M$37+$Q$37*0.25*$U$37,"") | W37: =IF(AND(ISNUMBER($U$37),ISNUMBER($M$37)),$M$37+$Q$37*0.5*$U$37,"") | X37: =IF(AND(ISNUMBER($U$37),ISNUMBER($M$37)),$M$37+$Q$37*0.75*$U$37,"") | Y37: =IF(AND(ISNUMBER($U$37),ISNUMBER($M$37)),$M$37+$Q$37*1.0*$U$37,"") | Z37: =IF(AND(ISNUMBER($U$37),ISNUMBER($O$37)),$O$37+$S$37*0.25*$U$37,"") | AA37: =IF(AND(ISNUMBER($U$37),ISNUMBER($O$37)),$O$37+$S$37*0.5*$U$37,"") | AB37: =IF(AND(ISNUMBER($U$37),ISNUMBER($O$37)),$O$37+$S$37*0.75*$U$37,"") | AC37: =IF(AND(ISNUMBER($U$37),ISNUMBER($O$37)),$O$37+$S$37*1.0*$U$37,"") | AD37: =IF(AND(ISNUMBER($AC$37),ISNUMBER($Y$37)),$AC$37/$Y$37,"") | AE37: C#: Game/Match/ModeSessions.cs:863; Game/Match/ModeSessions.cs:871; Sim/AI/ConquestAi.cs:69
A38: survival/Easy | B38: survival | C38: Easy | D38: 16 | E38: 0.9 | J38: 0 | L38: Game/Match/ModeSessions.cs:1202 | M38: =IF(ISNUMBER($D$38),IF(AND(ISNUMBER(FIND(";"&Che_do!$B$12&";",";"&Kinh_te!$E$10&";")),$D$38>0,Kinh_te!$D$11<>1),ROUND($D$38*Kinh_te!$D$11,0),$D$38),"") | N38: 19 | O38: =IF(ISNUMBER($F$38),IF(AND(ISNUMBER(FIND(";"&Che_do!$B$12&";",";"&Kinh_te!$E$10&";")),$F$38>0,Kinh_te!$D$11<>1),ROUND($F$38*Kinh_te!$D$11,0),$F$38),"") | Q38: =($E$38+$J$38)*Kinh_te!$D$9 | R38: 0.81 | S38: =IF(ISNUMBER($G$38),($G$38+$J$38)*Kinh_te!$D$9*$H$38*$I$38,"") | U38: =Che_do_thoi_luong!$Q$12 | V38: =IF(AND(ISNUMBER($U$38),ISNUMBER($M$38)),$M$38+$Q$38*0.25*$U$38,"") | W38: =IF(AND(ISNUMBER($U$38),ISNUMBER($M$38)),$M$38+$Q$38*0.5*$U$38,"") | X38: =IF(AND(ISNUMBER($U$38),ISNUMBER($M$38)),$M$38+$Q$38*0.75*$U$38,"") | Y38: =IF(AND(ISNUMBER($U$38),ISNUMBER($M$38)),$M$38+$Q$38*1.0*$U$38,"") | Z38: =IF(AND(ISNUMBER($U$38),ISNUMBER($O$38)),$O$38+$S$38*0.25*$U$38,"") | AA38: =IF(AND(ISNUMBER($U$38),ISNUMBER($O$38)),$O$38+$S$38*0.5*$U$38,"") | AB38: =IF(AND(ISNUMBER($U$38),ISNUMBER($O$38)),$O$38+$S$38*0.75*$U$38,"") | AC38: =IF(AND(ISNUMBER($U$38),ISNUMBER($O$38)),$O$38+$S$38*1.0*$U$38,"") | AD38: =IF(AND(ISNUMBER($AC$38),ISNUMBER($Y$38)),$AC$38/$Y$38,"") | AE38: C#: Game/Match/ModeSessions.cs:1202; Sim/AI/ConquestAi.cs:65
A39: survival/Hard | B39: survival | C39: Hard | D39: 16 | E39: 0.9 | J39: 0 | L39: Game/Match/ModeSessions.cs:1202 | M39: =IF(ISNUMBER($D$39),IF(AND(ISNUMBER(FIND(";"&Che_do!$B$12&";",";"&Kinh_te!$E$10&";")),$D$39>0,Kinh_te!$D$11<>1),ROUND($D$39*Kinh_te!$D$11,0),$D$39),"") | N39: 19 | O39: =IF(ISNUMBER($F$39),IF(AND(ISNUMBER(FIND(";"&Che_do!$B$12&";",";"&Kinh_te!$E$10&";")),$F$39>0,Kinh_te!$D$11<>1),ROUND($F$39*Kinh_te!$D$11,0),$F$39),"") | Q39: =($E$39+$J$39)*Kinh_te!$D$9 | R39: 0.81 | S39: =IF(ISNUMBER($G$39),($G$39+$J$39)*Kinh_te!$D$9*$H$39*$I$39,"") | U39: =Che_do_thoi_luong!$Q$12 | V39: =IF(AND(ISNUMBER($U$39),ISNUMBER($M$39)),$M$39+$Q$39*0.25*$U$39,"") | W39: =IF(AND(ISNUMBER($U$39),ISNUMBER($M$39)),$M$39+$Q$39*0.5*$U$39,"") | X39: =IF(AND(ISNUMBER($U$39),ISNUMBER($M$39)),$M$39+$Q$39*0.75*$U$39,"") | Y39: =IF(AND(ISNUMBER($U$39),ISNUMBER($M$39)),$M$39+$Q$39*1.0*$U$39,"") | Z39: =IF(AND(ISNUMBER($U$39),ISNUMBER($O$39)),$O$39+$S$39*0.25*$U$39,"") | AA39: =IF(AND(ISNUMBER($U$39),ISNUMBER($O$39)),$O$39+$S$39*0.5*$U$39,"") | AB39: =IF(AND(ISNUMBER($U$39),ISNUMBER($O$39)),$O$39+$S$39*0.75*$U$39,"") | AC39: =IF(AND(ISNUMBER($U$39),ISNUMBER($O$39)),$O$39+$S$39*1.0*$U$39,"") | AD39: =IF(AND(ISNUMBER($AC$39),ISNUMBER($Y$39)),$AC$39/$Y$39,"") | AE39: C#: Game/Match/ModeSessions.cs:1202; Sim/AI/ConquestAi.cs:68
A40: survival/Normal | B40: survival | C40: Normal | D40: 16 | E40: 0.9 | J40: 0 | L40: Game/Match/ModeSessions.cs:1202 | M40: =IF(ISNUMBER($D$40),IF(AND(ISNUMBER(FIND(";"&Che_do!$B$12&";",";"&Kinh_te!$E$10&";")),$D$40>0,Kinh_te!$D$11<>1),ROUND($D$40*Kinh_te!$D$11,0),$D$40),"") | N40: 19 | O40: =IF(ISNUMBER($F$40),IF(AND(ISNUMBER(FIND(";"&Che_do!$B$12&";",";"&Kinh_te!$E$10&";")),$F$40>0,Kinh_te!$D$11<>1),ROUND($F$40*Kinh_te!$D$11,0),$F$40),"") | Q40: =($E$40+$J$40)*Kinh_te!$D$9 | R40: 0.81 | S40: =IF(ISNUMBER($G$40),($G$40+$J$40)*Kinh_te!$D$9*$H$40*$I$40,"") | U40: =Che_do_thoi_luong!$Q$12 | V40: =IF(AND(ISNUMBER($U$40),ISNUMBER($M$40)),$M$40+$Q$40*0.25*$U$40,"") | W40: =IF(AND(ISNUMBER($U$40),ISNUMBER($M$40)),$M$40+$Q$40*0.5*$U$40,"") | X40: =IF(AND(ISNUMBER($U$40),ISNUMBER($M$40)),$M$40+$Q$40*0.75*$U$40,"") | Y40: =IF(AND(ISNUMBER($U$40),ISNUMBER($M$40)),$M$40+$Q$40*1.0*$U$40,"") | Z40: =IF(AND(ISNUMBER($U$40),ISNUMBER($O$40)),$O$40+$S$40*0.25*$U$40,"") | AA40: =IF(AND(ISNUMBER($U$40),ISNUMBER($O$40)),$O$40+$S$40*0.5*$U$40,"") | AB40: =IF(AND(ISNUMBER($U$40),ISNUMBER($O$40)),$O$40+$S$40*0.75*$U$40,"") | AC40: =IF(AND(ISNUMBER($U$40),ISNUMBER($O$40)),$O$40+$S$40*1.0*$U$40,"") | AD40: =IF(AND(ISNUMBER($AC$40),ISNUMBER($Y$40)),$AC$40/$Y$40,"") | AE40: C#: Game/Match/ModeSessions.cs:1202; Sim/AI/ConquestAi.cs:67
A41: survival/VeryHard | B41: survival | C41: VeryHard | D41: 16 | E41: 0.9 | J41: 0 | L41: Game/Match/ModeSessions.cs:1202 | M41: =IF(ISNUMBER($D$41),IF(AND(ISNUMBER(FIND(";"&Che_do!$B$12&";",";"&Kinh_te!$E$10&";")),$D$41>0,Kinh_te!$D$11<>1),ROUND($D$41*Kinh_te!$D$11,0),$D$41),"") | N41: 19 | O41: =IF(ISNUMBER($F$41),IF(AND(ISNUMBER(FIND(";"&Che_do!$B$12&";",";"&Kinh_te!$E$10&";")),$F$41>0,Kinh_te!$D$11<>1),ROUND($F$41*Kinh_te!$D$11,0),$F$41),"") | Q41: =($E$41+$J$41)*Kinh_te!$D$9 | R41: 0.81 | S41: =IF(ISNUMBER($G$41),($G$41+$J$41)*Kinh_te!$D$9*$H$41*$I$41,"") | U41: =Che_do_thoi_luong!$Q$12 | V41: =IF(AND(ISNUMBER($U$41),ISNUMBER($M$41)),$M$41+$Q$41*0.25*$U$41,"") | W41: =IF(AND(ISNUMBER($U$41),ISNUMBER($M$41)),$M$41+$Q$41*0.5*$U$41,"") | X41: =IF(AND(ISNUMBER($U$41),ISNUMBER($M$41)),$M$41+$Q$41*0.75*$U$41,"") | Y41: =IF(AND(ISNUMBER($U$41),ISNUMBER($M$41)),$M$41+$Q$41*1.0*$U$41,"") | Z41: =IF(AND(ISNUMBER($U$41),ISNUMBER($O$41)),$O$41+$S$41*0.25*$U$41,"") | AA41: =IF(AND(ISNUMBER($U$41),ISNUMBER($O$41)),$O$41+$S$41*0.5*$U$41,"") | AB41: =IF(AND(ISNUMBER($U$41),ISNUMBER($O$41)),$O$41+$S$41*0.75*$U$41,"") | AC41: =IF(AND(ISNUMBER($U$41),ISNUMBER($O$41)),$O$41+$S$41*1.0*$U$41,"") | AD41: =IF(AND(ISNUMBER($AC$41),ISNUMBER($Y$41)),$AC$41/$Y$41,"") | AE41: C#: Game/Match/ModeSessions.cs:1202; Sim/AI/ConquestAi.cs:69
A42: weekly/Easy | B42: weekly | C42: Easy | D42: 26 | E42: 1.5 | F42: 22 | G42: 1.15 | H42: 1 | I42: 0.8 | J42: 0 | L42: Game/Match/ModeSessions.cs:793; Game/Match/ModeSessions.cs:798; Sim/AI/ConquestAi.cs:65 | M42: =IF(ISNUMBER($D$42),IF(AND(ISNUMBER(FIND(";"&Che_do!$B$13&";",";"&Kinh_te!$E$10&";")),$D$42>0,Kinh_te!$D$11<>1),ROUND($D$42*Kinh_te!$D$11,0),$D$42),"") | N42: 30 | O42: =IF(ISNUMBER($F$42),IF(AND(ISNUMBER(FIND(";"&Che_do!$B$13&";",";"&Kinh_te!$E$10&";")),$F$42>0,Kinh_te!$D$11<>1),ROUND($F$42*Kinh_te!$D$11,0),$F$42),"") | P42: 26 | Q42: =($E$42+$J$42)*Kinh_te!$D$9 | R42: 1.35 | S42: =IF(ISNUMBER($G$42),($G$42+$J$42)*Kinh_te!$D$9*$H$42*$I$42,"") | T42: 0.828 | U42: =Che_do_thoi_luong!$Q$13 | V42: =IF(AND(ISNUMBER($U$42),ISNUMBER($M$42)),$M$42+$Q$42*0.25*$U$42,"") | W42: =IF(AND(ISNUMBER($U$42),ISNUMBER($M$42)),$M$42+$Q$42*0.5*$U$42,"") | X42: =IF(AND(ISNUMBER($U$42),ISNUMBER($M$42)),$M$42+$Q$42*0.75*$U$42,"") | Y42: =IF(AND(ISNUMBER($U$42),ISNUMBER($M$42)),$M$42+$Q$42*1.0*$U$42,"") | Z42: =IF(AND(ISNUMBER($U$42),ISNUMBER($O$42)),$O$42+$S$42*0.25*$U$42,"") | AA42: =IF(AND(ISNUMBER($U$42),ISNUMBER($O$42)),$O$42+$S$42*0.5*$U$42,"") | AB42: =IF(AND(ISNUMBER($U$42),ISNUMBER($O$42)),$O$42+$S$42*0.75*$U$42,"") | AC42: =IF(AND(ISNUMBER($U$42),ISNUMBER($O$42)),$O$42+$S$42*1.0*$U$42,"") | AD42: =IF(AND(ISNUMBER($AC$42),ISNUMBER($Y$42)),$AC$42/$Y$42,"") | AE42: C#: Game/Match/ModeSessions.cs:793; Game/Match/ModeSessions.cs:798; Sim/AI/ConquestAi.cs:65
A43: weekly/Hard | B43: weekly | C43: Hard | D43: 26 | E43: 1.5 | F43: 22 | G43: 1.15 | H43: 1 | I43: 1.2 | J43: 0 | L43: Game/Match/ModeSessions.cs:793; Game/Match/ModeSessions.cs:798; Sim/AI/ConquestAi.cs:68 | M43: =IF(ISNUMBER($D$43),IF(AND(ISNUMBER(FIND(";"&Che_do!$B$13&";",";"&Kinh_te!$E$10&";")),$D$43>0,Kinh_te!$D$11<>1),ROUND($D$43*Kinh_te!$D$11,0),$D$43),"") | N43: 30 | O43: =IF(ISNUMBER($F$43),IF(AND(ISNUMBER(FIND(";"&Che_do!$B$13&";",";"&Kinh_te!$E$10&";")),$F$43>0,Kinh_te!$D$11<>1),ROUND($F$43*Kinh_te!$D$11,0),$F$43),"") | P43: 26 | Q43: =($E$43+$J$43)*Kinh_te!$D$9 | R43: 1.35 | S43: =IF(ISNUMBER($G$43),($G$43+$J$43)*Kinh_te!$D$9*$H$43*$I$43,"") | T43: 1.242 | U43: =Che_do_thoi_luong!$Q$13 | V43: =IF(AND(ISNUMBER($U$43),ISNUMBER($M$43)),$M$43+$Q$43*0.25*$U$43,"") | W43: =IF(AND(ISNUMBER($U$43),ISNUMBER($M$43)),$M$43+$Q$43*0.5*$U$43,"") | X43: =IF(AND(ISNUMBER($U$43),ISNUMBER($M$43)),$M$43+$Q$43*0.75*$U$43,"") | Y43: =IF(AND(ISNUMBER($U$43),ISNUMBER($M$43)),$M$43+$Q$43*1.0*$U$43,"") | Z43: =IF(AND(ISNUMBER($U$43),ISNUMBER($O$43)),$O$43+$S$43*0.25*$U$43,"") | AA43: =IF(AND(ISNUMBER($U$43),ISNUMBER($O$43)),$O$43+$S$43*0.5*$U$43,"") | AB43: =IF(AND(ISNUMBER($U$43),ISNUMBER($O$43)),$O$43+$S$43*0.75*$U$43,"") | AC43: =IF(AND(ISNUMBER($U$43),ISNUMBER($O$43)),$O$43+$S$43*1.0*$U$43,"") | AD43: =IF(AND(ISNUMBER($AC$43),ISNUMBER($Y$43)),$AC$43/$Y$43,"") | AE43: C#: Game/Match/ModeSessions.cs:793; Game/Match/ModeSessions.cs:798; Sim/AI/ConquestAi.cs:68
A44: weekly/Normal | B44: weekly | C44: Normal | D44: 26 | E44: 1.5 | F44: 22 | G44: 1.15 | H44: 1 | I44: 0.7 | J44: 0 | L44: Game/Match/ModeSessions.cs:793; Game/Match/ModeSessions.cs:798; Sim/AI/ConquestAi.cs:67 | M44: =IF(ISNUMBER($D$44),IF(AND(ISNUMBER(FIND(";"&Che_do!$B$13&";",";"&Kinh_te!$E$10&";")),$D$44>0,Kinh_te!$D$11<>1),ROUND($D$44*Kinh_te!$D$11,0),$D$44),"") | N44: 30 | O44: =IF(ISNUMBER($F$44),IF(AND(ISNUMBER(FIND(";"&Che_do!$B$13&";",";"&Kinh_te!$E$10&";")),$F$44>0,Kinh_te!$D$11<>1),ROUND($F$44*Kinh_te!$D$11,0),$F$44),"") | P44: 26 | Q44: =($E$44+$J$44)*Kinh_te!$D$9 | R44: 1.35 | S44: =IF(ISNUMBER($G$44),($G$44+$J$44)*Kinh_te!$D$9*$H$44*$I$44,"") | T44: 0.7245 | U44: =Che_do_thoi_luong!$Q$13 | V44: =IF(AND(ISNUMBER($U$44),ISNUMBER($M$44)),$M$44+$Q$44*0.25*$U$44,"") | W44: =IF(AND(ISNUMBER($U$44),ISNUMBER($M$44)),$M$44+$Q$44*0.5*$U$44,"") | X44: =IF(AND(ISNUMBER($U$44),ISNUMBER($M$44)),$M$44+$Q$44*0.75*$U$44,"") | Y44: =IF(AND(ISNUMBER($U$44),ISNUMBER($M$44)),$M$44+$Q$44*1.0*$U$44,"") | Z44: =IF(AND(ISNUMBER($U$44),ISNUMBER($O$44)),$O$44+$S$44*0.25*$U$44,"") | AA44: =IF(AND(ISNUMBER($U$44),ISNUMBER($O$44)),$O$44+$S$44*0.5*$U$44,"") | AB44: =IF(AND(ISNUMBER($U$44),ISNUMBER($O$44)),$O$44+$S$44*0.75*$U$44,"") | AC44: =IF(AND(ISNUMBER($U$44),ISNUMBER($O$44)),$O$44+$S$44*1.0*$U$44,"") | AD44: =IF(AND(ISNUMBER($AC$44),ISNUMBER($Y$44)),$AC$44/$Y$44,"") | AE44: C#: Game/Match/ModeSessions.cs:793; Game/Match/ModeSessions.cs:798; Sim/AI/ConquestAi.cs:67
A45: weekly/VeryHard | B45: weekly | C45: VeryHard | D45: 26 | E45: 1.5 | F45: 22 | G45: 1.15 | H45: 1 | I45: 1.4 | J45: 0 | L45: Game/Match/ModeSessions.cs:793; Game/Match/ModeSessions.cs:798; Sim/AI/ConquestAi.cs:69 | M45: =IF(ISNUMBER($D$45),IF(AND(ISNUMBER(FIND(";"&Che_do!$B$13&";",";"&Kinh_te!$E$10&";")),$D$45>0,Kinh_te!$D$11<>1),ROUND($D$45*Kinh_te!$D$11,0),$D$45),"") | N45: 30 | O45: =IF(ISNUMBER($F$45),IF(AND(ISNUMBER(FIND(";"&Che_do!$B$13&";",";"&Kinh_te!$E$10&";")),$F$45>0,Kinh_te!$D$11<>1),ROUND($F$45*Kinh_te!$D$11,0),$F$45),"") | P45: 26 | Q45: =($E$45+$J$45)*Kinh_te!$D$9 | R45: 1.35 | S45: =IF(ISNUMBER($G$45),($G$45+$J$45)*Kinh_te!$D$9*$H$45*$I$45,"") | T45: 1.449 | U45: =Che_do_thoi_luong!$Q$13 | V45: =IF(AND(ISNUMBER($U$45),ISNUMBER($M$45)),$M$45+$Q$45*0.25*$U$45,"") | W45: =IF(AND(ISNUMBER($U$45),ISNUMBER($M$45)),$M$45+$Q$45*0.5*$U$45,"") | X45: =IF(AND(ISNUMBER($U$45),ISNUMBER($M$45)),$M$45+$Q$45*0.75*$U$45,"") | Y45: =IF(AND(ISNUMBER($U$45),ISNUMBER($M$45)),$M$45+$Q$45*1.0*$U$45,"") | Z45: =IF(AND(ISNUMBER($U$45),ISNUMBER($O$45)),$O$45+$S$45*0.25*$U$45,"") | AA45: =IF(AND(ISNUMBER($U$45),ISNUMBER($O$45)),$O$45+$S$45*0.5*$U$45,"") | AB45: =IF(AND(ISNUMBER($U$45),ISNUMBER($O$45)),$O$45+$S$45*0.75*$U$45,"") | AC45: =IF(AND(ISNUMBER($U$45),ISNUMBER($O$45)),$O$45+$S$45*1.0*$U$45,"") | AD45: =IF(AND(ISNUMBER($AC$45),ISNUMBER($Y$45)),$AC$45/$Y$45,"") | AE45: C#: Game/Match/ModeSessions.cs:793; Game/Match/ModeSessions.cs:798; Sim/AI/ConquestAi.cs:69

Sheet Kiem_tinh_che_do
A1: id | B1: che_do | C1: phan_tram | D1: doi_xung | E1: thoi_luong_muc_tieu_s | F1: mien_phi_nguoi_choi_cp | G1: mien_phi_dich_cp | H1: tinh_nguoi_choi_cp | I1: tinh_dich_cp | J1: nhip_nguoi_choi_s | K1: nhip_dich_s | L1: t_s | M1: kinh_te_nguoi_choi_cp | N1: kinh_te_dich_cp | O1: tong_nguoi_choi_cp | P1: tong_dich_cp | Q1: dai_suc_manh | R1: lech_pct | S1: trang_thai | T1: nguon | U1: raw_json
A2: assault/25 | B2: assault | C2: 25 | D2: FALSE | E2: 600 | F2: 0 | G2: 0 | H2: 0 | I2: 0 | J2: 26.092308 | K2: 25.907692 | L2: =$C$2/100*$E$2 | M2: =Kinh_te_suy_ra!$M$4+Kinh_te_suy_ra!$Q$4*$L$2 | N2: =IF(ISNUMBER(Kinh_te_suy_ra!$O$4),Kinh_te_suy_ra!$O$4+Kinh_te_suy_ra!$S$4*$L$2,0) | O2: =$M$2+$F$2+$H$2 | P2: =$N$2+$G$2+$I$2 | Q2: =$P$2/MAX(0.000001,$O$2) | R2: =($Q$2-1)*100 | S2: =IF($D$2,IF(ABS($R$2)>30,"RED",IF(ABS($R$2)>20,"YELLOW","GREEN")),"THEO_VAI") | T2: Tools/audit/mode_static_audit.py MODES['Assault'] + 04_che_do_kinh_te_ai/Kinh_te_suy_ra (assault/Normal)
A3: assault/50 | B3: assault | C3: 50 | D3: FALSE | E3: 600 | F3: 0 | G3: 0 | H3: 0 | I3: 0 | J3: 26.092308 | K3: 25.907692 | L3: =$C$3/100*$E$3 | M3: =Kinh_te_suy_ra!$M$4+Kinh_te_suy_ra!$Q$4*$L$3 | N3: =IF(ISNUMBER(Kinh_te_suy_ra!$O$4),Kinh_te_suy_ra!$O$4+Kinh_te_suy_ra!$S$4*$L$3,0) | O3: =$M$3+$F$3+$H$3 | P3: =$N$3+$G$3+$I$3 | Q3: =$P$3/MAX(0.000001,$O$3) | R3: =($Q$3-1)*100 | S3: =IF($D$3,IF(ABS($R$3)>30,"RED",IF(ABS($R$3)>20,"YELLOW","GREEN")),"THEO_VAI") | T3: Tools/audit/mode_static_audit.py MODES['Assault'] + 04_che_do_kinh_te_ai/Kinh_te_suy_ra (assault/Normal)
A4: assault/75 | B4: assault | C4: 75 | D4: FALSE | E4: 600 | F4: 0 | G4: 0 | H4: 0 | I4: 0 | J4: 26.092308 | K4: 25.907692 | L4: =$C$4/100*$E$4 | M4: =Kinh_te_suy_ra!$M$4+Kinh_te_suy_ra!$Q$4*$L$4 | N4: =IF(ISNUMBER(Kinh_te_suy_ra!$O$4),Kinh_te_suy_ra!$O$4+Kinh_te_suy_ra!$S$4*$L$4,0) | O4: =$M$4+$F$4+$H$4 | P4: =$N$4+$G$4+$I$4 | Q4: =$P$4/MAX(0.000001,$O$4) | R4: =($Q$4-1)*100 | S4: =IF($D$4,IF(ABS($R$4)>30,"RED",IF(ABS($R$4)>20,"YELLOW","GREEN")),"THEO_VAI") | T4: Tools/audit/mode_static_audit.py MODES['Assault'] + 04_che_do_kinh_te_ai/Kinh_te_suy_ra (assault/Normal)
A5: assault/100 | B5: assault | C5: 100 | D5: FALSE | E5: 600 | F5: 0 | G5: 0 | H5: 0 | I5: 0 | J5: 26.092308 | K5: 25.907692 | L5: =$C$5/100*$E$5 | M5: =Kinh_te_suy_ra!$M$4+Kinh_te_suy_ra!$Q$4*$L$5 | N5: =IF(ISNUMBER(Kinh_te_suy_ra!$O$4),Kinh_te_suy_ra!$O$4+Kinh_te_suy_ra!$S$4*$L$5,0) | O5: =$M$5+$F$5+$H$5 | P5: =$N$5+$G$5+$I$5 | Q5: =$P$5/MAX(0.000001,$O$5) | R5: =($Q$5-1)*100 | S5: =IF($D$5,IF(ABS($R$5)>30,"RED",IF(ABS($R$5)>20,"YELLOW","GREEN")),"THEO_VAI") | T5: Tools/audit/mode_static_audit.py MODES['Assault'] + 04_che_do_kinh_te_ai/Kinh_te_suy_ra (assault/Normal)
A6: bossrush/25 | B6: bossrush | C6: 25 | D6: FALSE | E6: 1200 | F6: 0 | G6: 799.04739 | H6: 0 | I6: 0 | J6: 26.092308 | K6: 25.907692 | L6: =$C$6/100*$E$6 | M6: =Kinh_te_suy_ra!$M$8+Kinh_te_suy_ra!$Q$8*$L$6 | N6: =IF(ISNUMBER(Kinh_te_suy_ra!$O$8),Kinh_te_suy_ra!$O$8+Kinh_te_suy_ra!$S$8*$L$6,0) | O6: =$M$6+$F$6+$H$6 | P6: =$N$6+$G$6+$I$6 | Q6: =$P$6/MAX(0.000001,$O$6) | R6: =($Q$6-1)*100 | S6: =IF($D$6,IF(ABS($R$6)>30,"RED",IF(ABS($R$6)>20,"YELLOW","GREEN")),"THEO_VAI") | T6: Tools/audit/mode_static_audit.py MODES['BossRush'] + 04_che_do_kinh_te_ai/Kinh_te_suy_ra (bossrush/Normal)
A7: bossrush/50 | B7: bossrush | C7: 50 | D7: FALSE | E7: 1200 | F7: 0 | G7: 1598.0948 | H7: 0 | I7: 0 | J7: 26.092308 | K7: 25.907692 | L7: =$C$7/100*$E$7 | M7: =Kinh_te_suy_ra!$M$8+Kinh_te_suy_ra!$Q$8*$L$7 | N7: =IF(ISNUMBER(Kinh_te_suy_ra!$O$8),Kinh_te_suy_ra!$O$8+Kinh_te_suy_ra!$S$8*$L$7,0) | O7: =$M$7+$F$7+$H$7 | P7: =$N$7+$G$7+$I$7 | Q7: =$P$7/MAX(0.000001,$O$7) | R7: =($Q$7-1)*100 | S7: =IF($D$7,IF(ABS($R$7)>30,"RED",IF(ABS($R$7)>20,"YELLOW","GREEN")),"THEO_VAI") | T7: Tools/audit/mode_static_audit.py MODES['BossRush'] + 04_che_do_kinh_te_ai/Kinh_te_suy_ra (bossrush/Normal)
A8: bossrush/75 | B8: bossrush | C8: 75 | D8: FALSE | E8: 1200 | F8: 0 | G8: 2397.1422 | H8: 0 | I8: 0 | J8: 26.092308 | K8: 25.907692 | L8: =$C$8/100*$E$8 | M8: =Kinh_te_suy_ra!$M$8+Kinh_te_suy_ra!$Q$8*$L$8 | N8: =IF(ISNUMBER(Kinh_te_suy_ra!$O$8),Kinh_te_suy_ra!$O$8+Kinh_te_suy_ra!$S$8*$L$8,0) | O8: =$M$8+$F$8+$H$8 | P8: =$N$8+$G$8+$I$8 | Q8: =$P$8/MAX(0.000001,$O$8) | R8: =($Q$8-1)*100 | S8: =IF($D$8,IF(ABS($R$8)>30,"RED",IF(ABS($R$8)>20,"YELLOW","GREEN")),"THEO_VAI") | T8: Tools/audit/mode_static_audit.py MODES['BossRush'] + 04_che_do_kinh_te_ai/Kinh_te_suy_ra (bossrush/Normal)
A9: bossrush/100 | B9: bossrush | C9: 100 | D9: FALSE | E9: 1200 | F9: 0 | G9: 3196.1895 | H9: 0 | I9: 0 | J9: 26.092308 | K9: 25.907692 | L9: =$C$9/100*$E$9 | M9: =Kinh_te_suy_ra!$M$8+Kinh_te_suy_ra!$Q$8*$L$9 | N9: =IF(ISNUMBER(Kinh_te_suy_ra!$O$8),Kinh_te_suy_ra!$O$8+Kinh_te_suy_ra!$S$8*$L$9,0) | O9: =$M$9+$F$9+$H$9 | P9: =$N$9+$G$9+$I$9 | Q9: =$P$9/MAX(0.000001,$O$9) | R9: =($Q$9-1)*100 | S9: =IF($D$9,IF(ABS($R$9)>30,"RED",IF(ABS($R$9)>20,"YELLOW","GREEN")),"THEO_VAI") | T9: Tools/audit/mode_static_audit.py MODES['BossRush'] + 04_che_do_kinh_te_ai/Kinh_te_suy_ra (bossrush/Normal)
A10: conquest/25 | B10: conquest | C10: 25 | D10: TRUE | E10: 480 | F10: 0 | G10: 0 | H10: 0 | I10: 0 | J10: 26.092308 | K10: 25.907692 | L10: =$C$10/100*$E$10 | M10: =Kinh_te_suy_ra!$M$12+Kinh_te_suy_ra!$Q$12*$L$10 | N10: =IF(ISNUMBER(Kinh_te_suy_ra!$O$12),Kinh_te_suy_ra!$O$12+Kinh_te_suy_ra!$S$12*$L$10,0) | O10: =$M$10+$F$10+$H$10 | P10: =$N$10+$G$10+$I$10 | Q10: =$P$10/MAX(0.000001,$O$10) | R10: =($Q$10-1)*100 | S10: =IF($D$10,IF(ABS($R$10)>30,"RED",IF(ABS($R$10)>20,"YELLOW","GREEN")),"THEO_VAI") | T10: Tools/audit/mode_static_audit.py MODES['Conquest'] + 04_che_do_kinh_te_ai/Kinh_te_suy_ra (conquest/Normal)
A11: conquest/50 | B11: conquest | C11: 50 | D11: TRUE | E11: 480 | F11: 0 | G11: 0 | H11: 0 | I11: 0 | J11: 26.092308 | K11: 25.907692 | L11: =$C$11/100*$E$11 | M11: =Kinh_te_suy_ra!$M$12+Kinh_te_suy_ra!$Q$12*$L$11 | N11: =IF(ISNUMBER(Kinh_te_suy_ra!$O$12),Kinh_te_suy_ra!$O$12+Kinh_te_suy_ra!$S$12*$L$11,0) | O11: =$M$11+$F$11+$H$11 | P11: =$N$11+$G$11+$I$11 | Q11: =$P$11/MAX(0.000001,$O$11) | R11: =($Q$11-1)*100 | S11: =IF($D$11,IF(ABS($R$11)>30,"RED",IF(ABS($R$11)>20,"YELLOW","GREEN")),"THEO_VAI") | T11: Tools/audit/mode_static_audit.py MODES['Conquest'] + 04_che_do_kinh_te_ai/Kinh_te_suy_ra (conquest/Normal)
A12: conquest/75 | B12: conquest | C12: 75 | D12: TRUE | E12: 480 | F12: 0 | G12: 0 | H12: 0 | I12: 0 | J12: 26.092308 | K12: 25.907692 | L12: =$C$12/100*$E$12 | M12: =Kinh_te_suy_ra!$M$12+Kinh_te_suy_ra!$Q$12*$L$12 | N12: =IF(ISNUMBER(Kinh_te_suy_ra!$O$12),Kinh_te_suy_ra!$O$12+Kinh_te_suy_ra!$S$12*$L$12,0) | O12: =$M$12+$F$12+$H$12 | P12: =$N$12+$G$12+$I$12 | Q12: =$P$12/MAX(0.000001,$O$12) | R12: =($Q$12-1)*100 | S12: =IF($D$12,IF(ABS($R$12)>30,"RED",IF(ABS($R$12)>20,"YELLOW","GREEN")),"THEO_VAI") | T12: Tools/audit/mode_static_audit.py MODES['Conquest'] + 04_che_do_kinh_te_ai/Kinh_te_suy_ra (conquest/Normal)
A13: conquest/100 | B13: conquest | C13: 100 | D13: TRUE | E13: 480 | F13: 0 | G13: 0 | H13: 0 | I13: 0 | J13: 26.092308 | K13: 25.907692 | L13: =$C$13/100*$E$13 | M13: =Kinh_te_suy_ra!$M$12+Kinh_te_suy_ra!$Q$12*$L$13 | N13: =IF(ISNUMBER(Kinh_te_suy_ra!$O$12),Kinh_te_suy_ra!$O$12+Kinh_te_suy_ra!$S$12*$L$13,0) | O13: =$M$13+$F$13+$H$13 | P13: =$N$13+$G$13+$I$13 | Q13: =$P$13/MAX(0.000001,$O$13) | R13: =($Q$13-1)*100 | S13: =IF($D$13,IF(ABS($R$13)>30,"RED",IF(ABS($R$13)>20,"YELLOW","GREEN")),"THEO_VAI") | T13: Tools/audit/mode_static_audit.py MODES['Conquest'] + 04_che_do_kinh_te_ai/Kinh_te_suy_ra (conquest/Normal)
A14: deathmatch/25 | B14: deathmatch | C14: 25 | D14: TRUE | E14: 450 | F14: 0 | G14: 0 | H14: 0 | I14: 0 | J14: 26.092308 | K14: 25.907692 | L14: =$C$14/100*$E$14 | M14: =Kinh_te_suy_ra!$M$16+Kinh_te_suy_ra!$Q$16*$L$14 | N14: =IF(ISNUMBER(Kinh_te_suy_ra!$O$16),Kinh_te_suy_ra!$O$16+Kinh_te_suy_ra!$S$16*$L$14,0) | O14: =$M$14+$F$14+$H$14 | P14: =$N$14+$G$14+$I$14 | Q14: =$P$14/MAX(0.000001,$O$14) | R14: =($Q$14-1)*100 | S14: =IF($D$14,IF(ABS($R$14)>30,"RED",IF(ABS($R$14)>20,"YELLOW","GREEN")),"THEO_VAI") | T14: Tools/audit/mode_static_audit.py MODES['Deathmatch'] + 04_che_do_kinh_te_ai/Kinh_te_suy_ra (deathmatch/Normal)
A15: deathmatch/50 | B15: deathmatch | C15: 50 | D15: TRUE | E15: 450 | F15: 0 | G15: 0 | H15: 0 | I15: 0 | J15: 26.092308 | K15: 25.907692 | L15: =$C$15/100*$E$15 | M15: =Kinh_te_suy_ra!$M$16+Kinh_te_suy_ra!$Q$16*$L$15 | N15: =IF(ISNUMBER(Kinh_te_suy_ra!$O$16),Kinh_te_suy_ra!$O$16+Kinh_te_suy_ra!$S$16*$L$15,0) | O15: =$M$15+$F$15+$H$15 | P15: =$N$15+$G$15+$I$15 | Q15: =$P$15/MAX(0.000001,$O$15) | R15: =($Q$15-1)*100 | S15: =IF($D$15,IF(ABS($R$15)>30,"RED",IF(ABS($R$15)>20,"YELLOW","GREEN")),"THEO_VAI") | T15: Tools/audit/mode_static_audit.py MODES['Deathmatch'] + 04_che_do_kinh_te_ai/Kinh_te_suy_ra (deathmatch/Normal)
A16: deathmatch/75 | B16: deathmatch | C16: 75 | D16: TRUE | E16: 450 | F16: 0 | G16: 0 | H16: 0 | I16: 0 | J16: 26.092308 | K16: 25.907692 | L16: =$C$16/100*$E$16 | M16: =Kinh_te_suy_ra!$M$16+Kinh_te_suy_ra!$Q$16*$L$16 | N16: =IF(ISNUMBER(Kinh_te_suy_ra!$O$16),Kinh_te_suy_ra!$O$16+Kinh_te_suy_ra!$S$16*$L$16,0) | O16: =$M$16+$F$16+$H$16 | P16: =$N$16+$G$16+$I$16 | Q16: =$P$16/MAX(0.000001,$O$16) | R16: =($Q$16-1)*100 | S16: =IF($D$16,IF(ABS($R$16)>30,"RED",IF(ABS($R$16)>20,"YELLOW","GREEN")),"THEO_VAI") | T16: Tools/audit/mode_static_audit.py MODES['Deathmatch'] + 04_che_do_kinh_te_ai/Kinh_te_suy_ra (deathmatch/Normal)
A17: deathmatch/100 | B17: deathmatch | C17: 100 | D17: TRUE | E17: 450 | F17: 0 | G17: 0 | H17: 0 | I17: 0 | J17: 26.092308 | K17: 25.907692 | L17: =$C$17/100*$E$17 | M17: =Kinh_te_suy_ra!$M$16+Kinh_te_suy_ra!$Q$16*$L$17 | N17: =IF(ISNUMBER(Kinh_te_suy_ra!$O$16),Kinh_te_suy_ra!$O$16+Kinh_te_suy_ra!$S$16*$L$17,0) | O17: =$M$17+$F$17+$H$17 | P17: =$N$17+$G$17+$I$17 | Q17: =$P$17/MAX(0.000001,$O$17) | R17: =($Q$17-1)*100 | S17: =IF($D$17,IF(ABS($R$17)>30,"RED",IF(ABS($R$17)>20,"YELLOW","GREEN")),"THEO_VAI") | T17: Tools/audit/mode_static_audit.py MODES['Deathmatch'] + 04_che_do_kinh_te_ai/Kinh_te_suy_ra (deathmatch/Normal)
A18: defend/25 | B18: defend | C18: 25 | D18: FALSE | E18: 720 | F18: 0 | G18: 59.9625 | H18: 133.00115 | I18: 0 | J18: 27.907692 | K18: 52.569231 | L18: =$C$18/100*$E$18 | M18: =Kinh_te_suy_ra!$M$20+Kinh_te_suy_ra!$Q$20*$L$18 | N18: =IF(ISNUMBER(Kinh_te_suy_ra!$O$20),Kinh_te_suy_ra!$O$20+Kinh_te_suy_ra!$S$20*$L$18,0) | O18: =$M$18+$F$18+$H$18 | P18: =$N$18+$G$18+$I$18 | Q18: =$P$18/MAX(0.000001,$O$18) | R18: =($Q$18-1)*100 | S18: =IF($D$18,IF(ABS($R$18)>30,"RED",IF(ABS($R$18)>20,"YELLOW","GREEN")),"THEO_VAI") | T18: Tools/audit/mode_static_audit.py MODES['Defend'] + 04_che_do_kinh_te_ai/Kinh_te_suy_ra (defend/Normal)
A19: defend/50 | B19: defend | C19: 50 | D19: FALSE | E19: 720 | F19: 0 | G19: 253.6875 | H19: 133.00115 | I19: 0 | J19: 27.907692 | K19: 52.569231 | L19: =$C$19/100*$E$19 | M19: =Kinh_te_suy_ra!$M$20+Kinh_te_suy_ra!$Q$20*$L$19 | N19: =IF(ISNUMBER(Kinh_te_suy_ra!$O$20),Kinh_te_suy_ra!$O$20+Kinh_te_suy_ra!$S$20*$L$19,0) | O19: =$M$19+$F$19+$H$19 | P19: =$N$19+$G$19+$I$19 | Q19: =$P$19/MAX(0.000001,$O$19) | R19: =($Q$19-1)*100 | S19: =IF($D$19,IF(ABS($R$19)>30,"RED",IF(ABS($R$19)>20,"YELLOW","GREEN")),"THEO_VAI") | T19: Tools/audit/mode_static_audit.py MODES['Defend'] + 04_che_do_kinh_te_ai/Kinh_te_suy_ra (defend/Normal)
A20: defend/75 | B20: defend | C20: 75 | D20: FALSE | E20: 720 | F20: 0 | G20: 452.025 | H20: 133.00115 | I20: 0 | J20: 27.907692 | K20: 52.569231 | L20: =$C$20/100*$E$20 | M20: =Kinh_te_suy_ra!$M$20+Kinh_te_suy_ra!$Q$20*$L$20 | N20: =IF(ISNUMBER(Kinh_te_suy_ra!$O$20),Kinh_te_suy_ra!$O$20+Kinh_te_suy_ra!$S$20*$L$20,0) | O20: =$M$20+$F$20+$H$20 | P20: =$N$20+$G$20+$I$20 | Q20: =$P$20/MAX(0.000001,$O$20) | R20: =($Q$20-1)*100 | S20: =IF($D$20,IF(ABS($R$20)>30,"RED",IF(ABS($R$20)>20,"YELLOW","GREEN")),"THEO_VAI") | T20: Tools/audit/mode_static_audit.py MODES['Defend'] + 04_che_do_kinh_te_ai/Kinh_te_suy_ra (defend/Normal)
A21: defend/100 | B21: defend | C21: 100 | D21: FALSE | E21: 720 | F21: 0 | G21: 853.3125 | H21: 133.00115 | I21: 0 | J21: 27.907692 | K21: 52.569231 | L21: =$C$21/100*$E$21 | M21: =Kinh_te_suy_ra!$M$20+Kinh_te_suy_ra!$Q$20*$L$21 | N21: =IF(ISNUMBER(Kinh_te_suy_ra!$O$20),Kinh_te_suy_ra!$O$20+Kinh_te_suy_ra!$S$20*$L$21,0) | O21: =$M$21+$F$21+$H$21 | P21: =$N$21+$G$21+$I$21 | Q21: =$P$21/MAX(0.000001,$O$21) | R21: =($Q$21-1)*100 | S21: =IF($D$21,IF(ABS($R$21)>30,"RED",IF(ABS($R$21)>20,"YELLOW","GREEN")),"THEO_VAI") | T21: Tools/audit/mode_static_audit.py MODES['Defend'] + 04_che_do_kinh_te_ai/Kinh_te_suy_ra (defend/Normal)
A22: hill/25 | B22: hill | C22: 25 | D22: TRUE | E22: 450 | F22: 0 | G22: 0 | H22: 0 | I22: 0 | J22: 26.092308 | K22: 25.907692 | L22: =$C$22/100*$E$22 | M22: =Kinh_te_suy_ra!$M$28+Kinh_te_suy_ra!$Q$28*$L$22 | N22: =IF(ISNUMBER(Kinh_te_suy_ra!$O$28),Kinh_te_suy_ra!$O$28+Kinh_te_suy_ra!$S$28*$L$22,0) | O22: =$M$22+$F$22+$H$22 | P22: =$N$22+$G$22+$I$22 | Q22: =$P$22/MAX(0.000001,$O$22) | R22: =($Q$22-1)*100 | S22: =IF($D$22,IF(ABS($R$22)>30,"RED",IF(ABS($R$22)>20,"YELLOW","GREEN")),"THEO_VAI") | T22: Tools/audit/mode_static_audit.py MODES['KingOfTheHill'] + 04_che_do_kinh_te_ai/Kinh_te_suy_ra (hill/Normal)
A23: hill/50 | B23: hill | C23: 50 | D23: TRUE | E23: 450 | F23: 0 | G23: 0 | H23: 0 | I23: 0 | J23: 26.092308 | K23: 25.907692 | L23: =$C$23/100*$E$23 | M23: =Kinh_te_suy_ra!$M$28+Kinh_te_suy_ra!$Q$28*$L$23 | N23: =IF(ISNUMBER(Kinh_te_suy_ra!$O$28),Kinh_te_suy_ra!$O$28+Kinh_te_suy_ra!$S$28*$L$23,0) | O23: =$M$23+$F$23+$H$23 | P23: =$N$23+$G$23+$I$23 | Q23: =$P$23/MAX(0.000001,$O$23) | R23: =($Q$23-1)*100 | S23: =IF($D$23,IF(ABS($R$23)>30,"RED",IF(ABS($R$23)>20,"YELLOW","GREEN")),"THEO_VAI") | T23: Tools/audit/mode_static_audit.py MODES['KingOfTheHill'] + 04_che_do_kinh_te_ai/Kinh_te_suy_ra (hill/Normal)
A24: hill/75 | B24: hill | C24: 75 | D24: TRUE | E24: 450 | F24: 0 | G24: 0 | H24: 0 | I24: 0 | J24: 26.092308 | K24: 25.907692 | L24: =$C$24/100*$E$24 | M24: =Kinh_te_suy_ra!$M$28+Kinh_te_suy_ra!$Q$28*$L$24 | N24: =IF(ISNUMBER(Kinh_te_suy_ra!$O$28),Kinh_te_suy_ra!$O$28+Kinh_te_suy_ra!$S$28*$L$24,0) | O24: =$M$24+$F$24+$H$24 | P24: =$N$24+$G$24+$I$24 | Q24: =$P$24/MAX(0.000001,$O$24) | R24: =($Q$24-1)*100 | S24: =IF($D$24,IF(ABS($R$24)>30,"RED",IF(ABS($R$24)>20,"YELLOW","GREEN")),"THEO_VAI") | T24: Tools/audit/mode_static_audit.py MODES['KingOfTheHill'] + 04_che_do_kinh_te_ai/Kinh_te_suy_ra (hill/Normal)
A25: hill/100 | B25: hill | C25: 100 | D25: TRUE | E25: 450 | F25: 0 | G25: 0 | H25: 0 | I25: 0 | J25: 26.092308 | K25: 25.907692 | L25: =$C$25/100*$E$25 | M25: =Kinh_te_suy_ra!$M$28+Kinh_te_suy_ra!$Q$28*$L$25 | N25: =IF(ISNUMBER(Kinh_te_suy_ra!$O$28),Kinh_te_suy_ra!$O$28+Kinh_te_suy_ra!$S$28*$L$25,0) | O25: =$M$25+$F$25+$H$25 | P25: =$N$25+$G$25+$I$25 | Q25: =$P$25/MAX(0.000001,$O$25) | R25: =($Q$25-1)*100 | S25: =IF($D$25,IF(ABS($R$25)>30,"RED",IF(ABS($R$25)>20,"YELLOW","GREEN")),"THEO_VAI") | T25: Tools/audit/mode_static_audit.py MODES['KingOfTheHill'] + 04_che_do_kinh_te_ai/Kinh_te_suy_ra (hill/Normal)
A26: siege/25 | B26: siege | C26: 25 | D26: FALSE | E26: 750 | F26: 0 | G26: 0 | H26: 0 | I26: 589.00508 | J26: 53.953846 | K26: 2.8461538 | L26: =$C$26/100*$E$26 | M26: =Kinh_te_suy_ra!$M$36+Kinh_te_suy_ra!$Q$36*$L$26 | N26: =IF(ISNUMBER(Kinh_te_suy_ra!$O$36),Kinh_te_suy_ra!$O$36+Kinh_te_suy_ra!$S$36*$L$26,0) | O26: =$M$26+$F$26+$H$26 | P26: =$N$26+$G$26+$I$26 | Q26: =$P$26/MAX(0.000001,$O$26) | R26: =($Q$26-1)*100 | S26: =IF($D$26,IF(ABS($R$26)>30,"RED",IF(ABS($R$26)>20,"YELLOW","GREEN")),"THEO_VAI") | T26: Tools/audit/mode_static_audit.py MODES['Siege'] + 04_che_do_kinh_te_ai/Kinh_te_suy_ra (siege/Normal)
A27: siege/50 | B27: siege | C27: 50 | D27: FALSE | E27: 750 | F27: 0 | G27: 0 | H27: 0 | I27: 589.00508 | J27: 53.953846 | K27: 2.8461538 | L27: =$C$27/100*$E$27 | M27: =Kinh_te_suy_ra!$M$36+Kinh_te_suy_ra!$Q$36*$L$27 | N27: =IF(ISNUMBER(Kinh_te_suy_ra!$O$36),Kinh_te_suy_ra!$O$36+Kinh_te_suy_ra!$S$36*$L$27,0) | O27: =$M$27+$F$27+$H$27 | P27: =$N$27+$G$27+$I$27 | Q27: =$P$27/MAX(0.000001,$O$27) | R27: =($Q$27-1)*100 | S27: =IF($D$27,IF(ABS($R$27)>30,"RED",IF(ABS($R$27)>20,"YELLOW","GREEN")),"THEO_VAI") | T27: Tools/audit/mode_static_audit.py MODES['Siege'] + 04_che_do_kinh_te_ai/Kinh_te_suy_ra (siege/Normal)
A28: siege/75 | B28: siege | C28: 75 | D28: FALSE | E28: 750 | F28: 0 | G28: 0 | H28: 0 | I28: 589.00508 | J28: 53.953846 | K28: 2.8461538 | L28: =$C$28/100*$E$28 | M28: =Kinh_te_suy_ra!$M$36+Kinh_te_suy_ra!$Q$36*$L$28 | N28: =IF(ISNUMBER(Kinh_te_suy_ra!$O$36),Kinh_te_suy_ra!$O$36+Kinh_te_suy_ra!$S$36*$L$28,0) | O28: =$M$28+$F$28+$H$28 | P28: =$N$28+$G$28+$I$28 | Q28: =$P$28/MAX(0.000001,$O$28) | R28: =($Q$28-1)*100 | S28: =IF($D$28,IF(ABS($R$28)>30,"RED",IF(ABS($R$28)>20,"YELLOW","GREEN")),"THEO_VAI") | T28: Tools/audit/mode_static_audit.py MODES['Siege'] + 04_che_do_kinh_te_ai/Kinh_te_suy_ra (siege/Normal)
A29: siege/100 | B29: siege | C29: 100 | D29: FALSE | E29: 750 | F29: 0 | G29: 0 | H29: 0 | I29: 589.00508 | J29: 53.953846 | K29: 2.8461538 | L29: =$C$29/100*$E$29 | M29: =Kinh_te_suy_ra!$M$36+Kinh_te_suy_ra!$Q$36*$L$29 | N29: =IF(ISNUMBER(Kinh_te_suy_ra!$O$36),Kinh_te_suy_ra!$O$36+Kinh_te_suy_ra!$S$36*$L$29,0) | O29: =$M$29+$F$29+$H$29 | P29: =$N$29+$G$29+$I$29 | Q29: =$P$29/MAX(0.000001,$O$29) | R29: =($Q$29-1)*100 | S29: =IF($D$29,IF(ABS($R$29)>30,"RED",IF(ABS($R$29)>20,"YELLOW","GREEN")),"THEO_VAI") | T29: Tools/audit/mode_static_audit.py MODES['Siege'] + 04_che_do_kinh_te_ai/Kinh_te_suy_ra (siege/Normal)
A30: survival/25 | B30: survival | C30: 25 | D30: FALSE | E30: 600 | F30: 0 | G30: 404.00828 | H30: 0 | I30: 0 | J30: 26.092308 | K30: 25.907692 | L30: =$C$30/100*$E$30 | M30: =Kinh_te_suy_ra!$M$40+Kinh_te_suy_ra!$Q$40*$L$30 | N30: =IF(ISNUMBER(Kinh_te_suy_ra!$O$40),Kinh_te_suy_ra!$O$40+Kinh_te_suy_ra!$S$40*$L$30,0) | O30: =$M$30+$F$30+$H$30 | P30: =$N$30+$G$30+$I$30 | Q30: =$P$30/MAX(0.000001,$O$30) | R30: =($Q$30-1)*100 | S30: =IF($D$30,IF(ABS($R$30)>30,"RED",IF(ABS($R$30)>20,"YELLOW","GREEN")),"THEO_VAI") | T30: Tools/audit/mode_static_audit.py MODES['Survival'] + 04_che_do_kinh_te_ai/Kinh_te_suy_ra (survival/Normal)
A31: survival/50 | B31: survival | C31: 50 | D31: FALSE | E31: 600 | F31: 0 | G31: 1181.2067 | H31: 0 | I31: 0 | J31: 26.092308 | K31: 25.907692 | L31: =$C$31/100*$E$31 | M31: =Kinh_te_suy_ra!$M$40+Kinh_te_suy_ra!$Q$40*$L$31 | N31: =IF(ISNUMBER(Kinh_te_suy_ra!$O$40),Kinh_te_suy_ra!$O$40+Kinh_te_suy_ra!$S$40*$L$31,0) | O31: =$M$31+$F$31+$H$31 | P31: =$N$31+$G$31+$I$31 | Q31: =$P$31/MAX(0.000001,$O$31) | R31: =($Q$31-1)*100 | S31: =IF($D$31,IF(ABS($R$31)>30,"RED",IF(ABS($R$31)>20,"YELLOW","GREEN")),"THEO_VAI") | T31: Tools/audit/mode_static_audit.py MODES['Survival'] + 04_che_do_kinh_te_ai/Kinh_te_suy_ra (survival/Normal)
A32: survival/75 | B32: survival | C32: 75 | D32: FALSE | E32: 600 | F32: 0 | G32: 1181.2067 | H32: 0 | I32: 0 | J32: 26.092308 | K32: 25.907692 | L32: =$C$32/100*$E$32 | M32: =Kinh_te_suy_ra!$M$40+Kinh_te_suy_ra!$Q$40*$L$32 | N32: =IF(ISNUMBER(Kinh_te_suy_ra!$O$40),Kinh_te_suy_ra!$O$40+Kinh_te_suy_ra!$S$40*$L$32,0) | O32: =$M$32+$F$32+$H$32 | P32: =$N$32+$G$32+$I$32 | Q32: =$P$32/MAX(0.000001,$O$32) | R32: =($Q$32-1)*100 | S32: =IF($D$32,IF(ABS($R$32)>30,"RED",IF(ABS($R$32)>20,"YELLOW","GREEN")),"THEO_VAI") | T32: Tools/audit/mode_static_audit.py MODES['Survival'] + 04_che_do_kinh_te_ai/Kinh_te_suy_ra (survival/Normal)
A33: survival/100 | B33: survival | C33: 100 | D33: FALSE | E33: 600 | F33: 0 | G33: 1181.2067 | H33: 0 | I33: 0 | J33: 26.092308 | K33: 25.907692 | L33: =$C$33/100*$E$33 | M33: =Kinh_te_suy_ra!$M$40+Kinh_te_suy_ra!$Q$40*$L$33 | N33: =IF(ISNUMBER(Kinh_te_suy_ra!$O$40),Kinh_te_suy_ra!$O$40+Kinh_te_suy_ra!$S$40*$L$33,0) | O33: =$M$33+$F$33+$H$33 | P33: =$N$33+$G$33+$I$33 | Q33: =$P$33/MAX(0.000001,$O$33) | R33: =($Q$33-1)*100 | S33: =IF($D$33,IF(ABS($R$33)>30,"RED",IF(ABS($R$33)>20,"YELLOW","GREEN")),"THEO_VAI") | T33: Tools/audit/mode_static_audit.py MODES['Survival'] + 04_che_do_kinh_te_ai/Kinh_te_suy_ra (survival/Normal)
A34: weekly/25 | B34: weekly | C34: 25 | D34: FALSE | E34: 750 | F34: 0 | G34: 0 | H34: 0 | I34: 589.00508 | J34: 53.953846 | K34: 2.8461538 | L34: =$C$34/100*$E$34 | M34: =Kinh_te_suy_ra!$M$44+Kinh_te_suy_ra!$Q$44*$L$34 | N34: =IF(ISNUMBER(Kinh_te_suy_ra!$O$44),Kinh_te_suy_ra!$O$44+Kinh_te_suy_ra!$S$44*$L$34,0) | O34: =$M$34+$F$34+$H$34 | P34: =$N$34+$G$34+$I$34 | Q34: =$P$34/MAX(0.000001,$O$34) | R34: =($Q$34-1)*100 | S34: =IF($D$34,IF(ABS($R$34)>30,"RED",IF(ABS($R$34)>20,"YELLOW","GREEN")),"THEO_VAI") | T34: Tools/audit/mode_static_audit.py MODES['Weekly'] + 04_che_do_kinh_te_ai/Kinh_te_suy_ra (weekly/Normal)
A35: weekly/50 | B35: weekly | C35: 50 | D35: FALSE | E35: 750 | F35: 0 | G35: 0 | H35: 0 | I35: 589.00508 | J35: 53.953846 | K35: 2.8461538 | L35: =$C$35/100*$E$35 | M35: =Kinh_te_suy_ra!$M$44+Kinh_te_suy_ra!$Q$44*$L$35 | N35: =IF(ISNUMBER(Kinh_te_suy_ra!$O$44),Kinh_te_suy_ra!$O$44+Kinh_te_suy_ra!$S$44*$L$35,0) | O35: =$M$35+$F$35+$H$35 | P35: =$N$35+$G$35+$I$35 | Q35: =$P$35/MAX(0.000001,$O$35) | R35: =($Q$35-1)*100 | S35: =IF($D$35,IF(ABS($R$35)>30,"RED",IF(ABS($R$35)>20,"YELLOW","GREEN")),"THEO_VAI") | T35: Tools/audit/mode_static_audit.py MODES['Weekly'] + 04_che_do_kinh_te_ai/Kinh_te_suy_ra (weekly/Normal)
A36: weekly/75 | B36: weekly | C36: 75 | D36: FALSE | E36: 750 | F36: 0 | G36: 0 | H36: 0 | I36: 589.00508 | J36: 53.953846 | K36: 2.8461538 | L36: =$C$36/100*$E$36 | M36: =Kinh_te_suy_ra!$M$44+Kinh_te_suy_ra!$Q$44*$L$36 | N36: =IF(ISNUMBER(Kinh_te_suy_ra!$O$44),Kinh_te_suy_ra!$O$44+Kinh_te_suy_ra!$S$44*$L$36,0) | O36: =$M$36+$F$36+$H$36 | P36: =$N$36+$G$36+$I$36 | Q36: =$P$36/MAX(0.000001,$O$36) | R36: =($Q$36-1)*100 | S36: =IF($D$36,IF(ABS($R$36)>30,"RED",IF(ABS($R$36)>20,"YELLOW","GREEN")),"THEO_VAI") | T36: Tools/audit/mode_static_audit.py MODES['Weekly'] + 04_che_do_kinh_te_ai/Kinh_te_suy_ra (weekly/Normal)
A37: weekly/100 | B37: weekly | C37: 100 | D37: FALSE | E37: 750 | F37: 0 | G37: 0 | H37: 0 | I37: 589.00508 | J37: 53.953846 | K37: 2.8461538 | L37: =$C$37/100*$E$37 | M37: =Kinh_te_suy_ra!$M$44+Kinh_te_suy_ra!$Q$44*$L$37 | N37: =IF(ISNUMBER(Kinh_te_suy_ra!$O$44),Kinh_te_suy_ra!$O$44+Kinh_te_suy_ra!$S$44*$L$37,0) | O37: =$M$37+$F$37+$H$37 | P37: =$N$37+$G$37+$I$37 | Q37: =$P$37/MAX(0.000001,$O$37) | R37: =($Q$37-1)*100 | S37: =IF($D$37,IF(ABS($R$37)>30,"RED",IF(ABS($R$37)>20,"YELLOW","GREEN")),"THEO_VAI") | T37: Tools/audit/mode_static_audit.py MODES['Weekly'] + 04_che_do_kinh_te_ai/Kinh_te_suy_ra (weekly/Normal)

Sheet Che_do_hoc_thuyet_AI
A1: id | B1: ke_thua | C1: che_do | D1: muc_tieu | E1: AirFirst | F1: ArtilleryWeight | G1: BandBias | H1: BossWeight | I1: Escalating | J1: EscortWeight | K1: FastReserve | L1: FireSupport | M1: Frontline | N1: MissionTarget | O1: Phased | P1: Pursuit | Q1: QuietStrikes | R1: ReserveAllowed | S1: ReserveEmergencyOnly | T1: Rotate | U1: ShootAndScoot | V1: StructureWeight | W1: TowerWeight | X1: Triggers | Y1: nguon | Z1: raw_json
A2: assault | B2: balanced_objective | C2: Assault | E2: false | F2: 1 | G2: 0.5 | H2: 1 | I2: false | J2: 1 | K2: false | L2: FrontLogical | M2: Advance | N2: false | O2: false | P2: Normal | Q2: false | R2: true | S2: false | T2: false | U2: false | V2: 1 | W2: 1.4 | X2: Utilization|FrontMoved|RangeBandLost|CounterBattery|RouteChanged|PhaseChange|TerrainChange | Y2: Assets/MachineBrigade/Scripts/Sim/AI/P2/ModeCombatDoctrine.cs:239
A3: balanced_objective | E3: false | F3: 1 | G3: 0.5 | H3: 1 | I3: false | J3: 1 | K3: false | L3: FrontLogical | M3: Advance | N3: false | O3: false | P3: Normal | Q3: false | R3: true | S3: false | T3: false | U3: false | V3: 1 | W3: 1 | X3: All | Y3: Assets/MachineBrigade/Scripts/Sim/AI/P2/ModeCombatDoctrine.cs:227
A4: bossrush | B4: balanced_objective | C4: BossRush | E4: false | F4: 1 | G4: 0.5 | H4: 1.3 | I4: false | J4: 1.1 | K4: false | L4: BossPredict | M4: BossFocus | N4: false | O4: false | P4: Normal | Q4: false | R4: false | S4: false | T4: false | U4: false | V4: 1 | W4: 1 | X4: All | Y4: Assets/MachineBrigade/Scripts/Sim/AI/P2/ModeCombatDoctrine.cs:324
A5: bossrush_goal | B5: bossrush | D5: Boss | E5: false | F5: 1 | G5: 0.5 | H5: 1.3 | I5: false | J5: 1.1 | K5: false | L5: BossPredict | M5: BossFocus | N5: false | O5: false | P5: Normal | Q5: false | R5: false | S5: false | T5: false | U5: false | V5: 1 | W5: 1 | X5: All | Y5: Assets/MachineBrigade/Scripts/Sim/AI/P2/ModeCombatDoctrine.cs:332
A6: capture | B6: conquest | D6: Capture | E6: false | F6: 1 | G6: 0.5 | H6: 1 | I6: false | J6: 1 | K6: true | L6: ObjectiveCover | M6: ObjectiveBody | N6: false | O6: false | P6: Normal | Q6: false | R6: true | S6: false | T6: false | U6: false | V6: 1 | W6: 1 | X6: ObjectiveUncovered|Utilization|CounterBattery|PhaseChange|TerrainChange | Y6: Assets/MachineBrigade/Scripts/Sim/AI/P2/ModeCombatDoctrine.cs:287
A7: conquest | B7: balanced_objective | C7: Conquest;Sandbox | E7: false | F7: 1 | G7: 0.5 | H7: 1 | I7: false | J7: 1 | K7: true | L7: ObjectiveCover | M7: ObjectiveBody | N7: false | O7: false | P7: Normal | Q7: false | R7: true | S7: false | T7: false | U7: false | V7: 1 | W7: 1 | X7: ObjectiveUncovered|Utilization|CounterBattery|PhaseChange|TerrainChange | Y7: Assets/MachineBrigade/Scripts/Sim/AI/P2/ModeCombatDoctrine.cs:279
A8: deathmatch | B8: balanced_objective | C8: Deathmatch | E8: false | F8: 1 | G8: 0.5 | H8: 1 | I8: false | J8: 1 | K8: false | L8: FrontLogical | M8: Mobile | N8: false | O8: false | P8: Normal | Q8: false | R8: true | S8: false | T8: false | U8: false | V8: 1 | W8: 1 | X8: Utilization|FrontMoved|RangeBandLost|PocketCompromised|CounterBattery|TerrainChange | Y8: Assets/MachineBrigade/Scripts/Sim/AI/P2/ModeCombatDoctrine.cs:334
A9: defend | B9: balanced_objective | C9: Defend | E9: false | F9: 1 | G9: 0.8 | H9: 1 | I9: false | J9: 1 | K9: false | L9: DefenceLine | M9: HoldLine | N9: false | O9: false | P9: NoChase | Q9: false | R9: true | S9: false | T9: false | U9: false | V9: 1 | W9: 1 | X9: Utilization|RangeBandLost|CounterBattery|PhaseChange|TerrainChange | Y9: Assets/MachineBrigade/Scripts/Sim/AI/P2/ModeCombatDoctrine.cs:250
A10: destroy | B10: assault | D10: Destroy | E10: false | F10: 1 | G10: 0.5 | H10: 1 | I10: false | J10: 1 | K10: false | L10: FrontLogical | M10: Advance | N10: true | O10: false | P10: Normal | Q10: false | R10: true | S10: false | T10: false | U10: false | V10: 1.3 | W10: 1.4 | X10: Utilization|FrontMoved|RangeBandLost|CounterBattery|RouteChanged|PhaseChange|TerrainChange | Y10: Assets/MachineBrigade/Scripts/Sim/AI/P2/ModeCombatDoctrine.cs:248
A11: duel | B11: deathmatch | D11: Duel | E11: false | F11: 1 | G11: 0.5 | H11: 1 | I11: false | J11: 1 | K11: false | L11: FrontLogical | M11: Mobile | N11: false | O11: false | P11: Normal | Q11: false | R11: false) | S11: false | T11: false | U11: false | V11: 1 | W11: 1 | X11: Utilization|FrontMoved|RangeBandLost|PocketCompromised|CounterBattery|TerrainChange | Y11: Assets/MachineBrigade/Scripts/Sim/AI/P2/ModeCombatDoctrine.cs:341
A12: endless | B12: defend | C12: Endless | E12: false | F12: 1 | G12: 0.8 | H12: 1 | I12: false | J12: 1 | K12: false | L12: PreparedPockets | M12: HoldLine | N12: false | O12: false | P12: NoChase | Q12: false | R12: true | S12: true | T12: true | U12: false | V12: 1 | W12: 1 | X12: Utilization|RangeBandLost|CounterBattery|PhaseChange|TerrainChange|Rotation|WaveDirection | Y12: Assets/MachineBrigade/Scripts/Sim/AI/P2/ModeCombatDoctrine.cs:271
A13: escort | B13: balanced_objective | D13: Escort | E13: false | F13: 1 | G13: 0.5 | H13: 1 | I13: false | J13: 1 | K13: false | L13: ConvoyLeapfrog | M13: ConvoyScreen | N13: false | O13: false | P13: Leash | Q13: false | R13: true | S13: false | T13: false | U13: false | V13: 1 | W13: 1 | X13: RangeBandLost|RouteChanged|CounterBattery|PhaseChange|TerrainChange | Y13: Assets/MachineBrigade/Scripts/Sim/AI/P2/ModeCombatDoctrine.cs:290
A14: evacuate | B14: escort | D14: Evacuate | E14: false | F14: 1 | G14: 0.5 | H14: 1 | I14: false | J14: 1 | K14: false | L14: ConvoyLeapfrog | M14: ConvoyScreen | N14: false | O14: false | P14: NoChase) | Q14: false | R14: true | S14: false | T14: false | U14: false | V14: 1 | W14: 1 | X14: RangeBandLost|RouteChanged|CounterBattery|PhaseChange|TerrainChange | Y14: Assets/MachineBrigade/Scripts/Sim/AI/P2/ModeCombatDoctrine.cs:299
A15: fixed_deck | B15: balanced_objective | C15: FixedDeck | E15: false | F15: 1 | G15: 0.5 | H15: 1 | I15: false | J15: 1 | K15: false | L15: FrontLogical | M15: Advance | N15: false | O15: false | P15: Normal | Q15: false | R15: true | S15: false | T15: false | U15: false | V15: 1 | W15: 1 | X15: All | Y15: Assets/MachineBrigade/Scripts/Sim/AI/P2/ModeCombatDoctrine.cs:377
A16: hill | B16: conquest | C16: KingOfTheHill | E16: false | F16: 1 | G16: 0.5 | H16: 1 | I16: false | J16: 1 | K16: true | L16: ObjectiveCover | M16: ObjectiveBody | N16: false | O16: false | P16: Normal | Q16: false | R16: true | S16: false | T16: false | U16: false | V16: 1 | W16: 1 | X16: ObjectiveUncovered|Utilization|CounterBattery|PhaseChange|TerrainChange | Y16: Assets/MachineBrigade/Scripts/Sim/AI/P2/ModeCombatDoctrine.cs:288
A17: hold | B17: defend | D17: Hold | E17: false | F17: 1 | G17: 0.8 | H17: 1 | I17: false | J17: 1 | K17: false | L17: DefenceLine | M17: ObjectiveBody) | N17: false | O17: false | P17: NoChase | Q17: false | R17: true | S17: false | T17: false | U17: false | V17: 1 | W17: 1 | X17: Utilization|RangeBandLost|CounterBattery|PhaseChange|TerrainChange | Y17: Assets/MachineBrigade/Scripts/Sim/AI/P2/ModeCombatDoctrine.cs:260
A18: hunt | B18: balanced_objective | D18: Hunt | E18: false | F18: 1 | G18: 0.5 | H18: 1 | I18: false | J18: 1 | K18: false | L18: InterceptPredict | M18: Mobile | N18: false | O18: false | P18: Leash | Q18: false | R18: true | S18: false | T18: false | U18: false | V18: 1 | W18: 1 | X18: All | Y18: Assets/MachineBrigade/Scripts/Sim/AI/P2/ModeCombatDoctrine.cs:343
A19: intercept | B19: hunt | D19: Intercept | E19: false | F19: 1 | G19: 0.5 | H19: 1 | I19: false | J19: 1 | K19: false | L19: InterceptPredict | M19: Mobile | N19: false | O19: false | P19: Leash | Q19: false | R19: false) | S19: false | T19: false | U19: false | V19: 1 | W19: 1 | X19: All | Y19: Assets/MachineBrigade/Scripts/Sim/AI/P2/ModeCombatDoctrine.cs:349
A20: operation | B20: assault | C20: Operation | E20: false | F20: 1 | G20: 0.5 | H20: 1 | I20: false | J20: 1 | K20: false | L20: FrontLogical | M20: Advance | N20: false | O20: true) | P20: Normal | Q20: false | R20: true | S20: false | T20: false | U20: false | V20: 1 | W20: 1.4 | X20: Utilization|FrontMoved|RangeBandLost|CounterBattery|RouteChanged|PhaseChange|TerrainChange | Y20: Assets/MachineBrigade/Scripts/Sim/AI/P2/ModeCombatDoctrine.cs:360
A21: outpost | B21: defend | D21: Outpost | E21: false | F21: 1 | G21: 0.7) | H21: 1 | I21: false | J21: 1 | K21: false | L21: DefenceLine | M21: HoldLine | N21: false | O21: false | P21: NoChase | Q21: false | R21: true | S21: false | T21: false | U21: false | V21: 1 | W21: 1 | X21: Utilization|RangeBandLost|CounterBattery|PhaseChange|TerrainChange | Y21: Assets/MachineBrigade/Scripts/Sim/AI/P2/ModeCombatDoctrine.cs:262
A22: protect | B22: defend | D22: Protect | E22: false | F22: 1 | G22: 0.8 | H22: 1 | I22: false | J22: 1 | K22: false | L22: DefenceLine | M22: HoldLine | N22: false | O22: false | P22: NoChase) | Q22: false | R22: true | S22: false | T22: false | U22: false | V22: 1 | W22: 1 | X22: Utilization|RangeBandLost|CounterBattery|PhaseChange|TerrainChange | Y22: Assets/MachineBrigade/Scripts/Sim/AI/P2/ModeCombatDoctrine.cs:261
A23: recon | B23: balanced_objective | D23: Recon | E23: false | F23: 1 | G23: 1 | H23: 1 | I23: false | J23: 1 | K23: false | L23: Quiet | M23: Mobile | N23: false | O23: false | P23: NoChase | Q23: true | R23: true | S23: false | T23: false | U23: false | V23: 1 | W23: 1 | X23: All | Y23: Assets/MachineBrigade/Scripts/Sim/AI/P2/ModeCombatDoctrine.cs:351
A24: relieve | B24: defend | D24: Relieve | E24: false | F24: 1 | G24: 0.6 | H24: 1 | I24: false | J24: 1 | K24: false | L24: FrontLogical | M24: Advance | N24: false | O24: false | P24: Leash | Q24: false | R24: true | S24: false | T24: false | U24: false | V24: 1 | W24: 1 | X24: Utilization|RangeBandLost|CounterBattery|PhaseChange|TerrainChange | Y24: Assets/MachineBrigade/Scripts/Sim/AI/P2/ModeCombatDoctrine.cs:263
A25: shootdown | B25: balanced_objective | D25: ShootDown | E25: true | F25: 1 | G25: 0.5 | H25: 1 | I25: false | J25: 1 | K25: false | L25: DefenceLine | M25: HoldLine | N25: false | O25: false | P25: NoChase | Q25: false | R25: true | S25: false | T25: false | U25: false | V25: 1 | W25: 1 | X25: All | Y25: Assets/MachineBrigade/Scripts/Sim/AI/P2/ModeCombatDoctrine.cs:369
A26: showdown | B26: balanced_objective | C26: Showdown | E26: false | F26: 1 | G26: 0.5 | H26: 1 | I26: true | J26: 1 | K26: false | L26: FrontLogical | M26: Advance | N26: false | O26: false | P26: Normal | Q26: false | R26: true | S26: false | T26: false | U26: false | V26: 1 | W26: 1.2 | X26: All | Y26: Assets/MachineBrigade/Scripts/Sim/AI/P2/ModeCombatDoctrine.cs:362
A27: siege | B27: balanced_objective | C27: Siege | E27: false | F27: 1.3 | G27: 0.5 | H27: 1 | I27: false | J27: 1 | K27: false | L27: SiegeLayers | M27: Advance | N27: false | O27: false | P27: Normal | Q27: false | R27: false | S27: false | T27: false | U27: true | V27: 1 | W27: 1.5 | X27: All | Y27: Assets/MachineBrigade/Scripts/Sim/AI/P2/ModeCombatDoctrine.cs:301
A28: survival | B28: balanced_objective | C28: Survival | D28: Survive | E28: false | F28: 1 | G28: 0.5 | H28: 1 | I28: false | J28: 1 | K28: false | L28: PreparedPockets | M28: Survival | N28: false | O28: false | P28: NoChase | Q28: false | R28: false | S28: false | T28: true | U28: false | V28: 1 | W28: 1 | X28: WaveDirection|Rotation|CounterBattery|RangeBandLost|TerrainChange | Y28: Assets/MachineBrigade/Scripts/Sim/AI/P2/ModeCombatDoctrine.cs:313
A29: weekly | B29: siege | C29: Weekly | E29: false | F29: 1.3 | G29: 0.5 | H29: 1 | I29: false | J29: 1 | K29: false | L29: SiegeLayers | M29: Advance | N29: true) | O29: false | P29: Normal | Q29: false | R29: false | S29: false | T29: false | U29: true | V29: 1 | W29: 1.5 | X29: All | Y29: Assets/MachineBrigade/Scripts/Sim/AI/P2/ModeCombatDoctrine.cs:311

Sheet Che_do_tham_chieu
A1: id | B1: entity_id | C1: ten_hien_thi | D1: loai_tham_chieu | E1: ten_mau_that | F1: quoc_gia | G1: nam_dua_vao_su_dung | H1: ten_game | I1: co_che_game | J1: ten_phim_truyen | K1: diem_giong | L1: diem_khac_co_chu_dich | M1: ly_do_khac | N1: cam_giac_khac_khi_choi | O1: do_tin_cay | P1: nguon_id | Q1: ly_do | R1: ghi_chu_ban_quyen | S1: co_che_giu_nguyen | T1: co_che_doi | U1: nguon | V1: raw_json
A2: assault | B2: assault | C2: Assault | D2: NEED_SOURCE | H2: NEED_SOURCE | O2: NEED_SOURCE | Q2: repo không có tham chiếu cho mục này | R2: chỉ ở mức ý tưởng và thông số (sự kiện); không dùng tên, logo, văn bản, ảnh hay mô hình có bản quyền; tên và phù hiệu quốc gia thật không hiện cho người chơi | U2: spec 12.2 (05)
A3: bossrush | B3: bossrush | C3: BossRush | D3: NEED_SOURCE | H3: NEED_SOURCE | O3: NEED_SOURCE | Q3: repo không có tham chiếu cho mục này | R3: chỉ ở mức ý tưởng và thông số (sự kiện); không dùng tên, logo, văn bản, ảnh hay mô hình có bản quyền; tên và phù hiệu quốc gia thật không hiện cho người chơi | U3: spec 12.2 (05)
A4: conquest | B4: conquest | C4: Conquest | D4: game | H4: Company of Heroes | I4: Bleed: bên giữ ít cứ điểm hơn bị trừ dần | K4: DECISIONS mục '28 5 (cloud, 2026-10-02)': Conquest đã trừ dần bên giữ ít điểm hơn | O4: ban_dau_doan | P4: R_decisions | R4: chỉ ở mức ý tưởng và thông số (sự kiện); không dùng tên, logo, văn bản, ảnh hay mô hình có bản quyền; tên và phù hiệu quốc gia thật không hiện cho người chơi | S4: trừ dần bên giữ ít cứ điểm hơn | T4: NEED_SOURCE | U4: Docs/DECISIONS.md: 28 5 (cloud, 2026-10-02)
A5: deathmatch | B5: deathmatch | C5: Deathmatch | D5: NEED_SOURCE | H5: NEED_SOURCE | O5: NEED_SOURCE | Q5: repo không có tham chiếu cho mục này | R5: chỉ ở mức ý tưởng và thông số (sự kiện); không dùng tên, logo, văn bản, ảnh hay mô hình có bản quyền; tên và phù hiệu quốc gia thật không hiện cho người chơi | U5: spec 12.2 (05)
A6: defend | B6: defend | C6: Defend | D6: NEED_SOURCE | H6: NEED_SOURCE | O6: NEED_SOURCE | Q6: repo không có tham chiếu cho mục này | R6: chỉ ở mức ý tưởng và thông số (sự kiện); không dùng tên, logo, văn bản, ảnh hay mô hình có bản quyền; tên và phù hiệu quốc gia thật không hiện cho người chơi | U6: spec 12.2 (05)
A7: endless | B7: endless | C7: Endless | D7: NEED_SOURCE | H7: NEED_SOURCE | O7: NEED_SOURCE | Q7: repo không có tham chiếu cho mục này | R7: chỉ ở mức ý tưởng và thông số (sự kiện); không dùng tên, logo, văn bản, ảnh hay mô hình có bản quyền; tên và phù hiệu quốc gia thật không hiện cho người chơi | U7: spec 12.2 (05)
A8: hill | B8: hill | C8: KingOfTheHill | D8: NEED_SOURCE | H8: NEED_SOURCE | O8: NEED_SOURCE | Q8: repo không có tham chiếu cho mục này | R8: chỉ ở mức ý tưởng và thông số (sự kiện); không dùng tên, logo, văn bản, ảnh hay mô hình có bản quyền; tên và phù hiệu quốc gia thật không hiện cho người chơi | U8: spec 12.2 (05)
A9: operations | B9: operations | C9: Operation | D9: NEED_SOURCE | H9: NEED_SOURCE | O9: NEED_SOURCE | Q9: repo không có tham chiếu cho mục này | R9: chỉ ở mức ý tưởng và thông số (sự kiện); không dùng tên, logo, văn bản, ảnh hay mô hình có bản quyền; tên và phù hiệu quốc gia thật không hiện cho người chơi | U9: spec 12.2 (05)
A10: showdown | B10: showdown | C10: Showdown | D10: NEED_SOURCE | H10: NEED_SOURCE | O10: NEED_SOURCE | Q10: repo không có tham chiếu cho mục này | R10: chỉ ở mức ý tưởng và thông số (sự kiện); không dùng tên, logo, văn bản, ảnh hay mô hình có bản quyền; tên và phù hiệu quốc gia thật không hiện cho người chơi | U10: spec 12.2 (05)
A11: siege | B11: siege | C11: Siege | D11: NEED_SOURCE | H11: NEED_SOURCE | O11: NEED_SOURCE | Q11: repo không có tham chiếu cho mục này | R11: chỉ ở mức ý tưởng và thông số (sự kiện); không dùng tên, logo, văn bản, ảnh hay mô hình có bản quyền; tên và phù hiệu quốc gia thật không hiện cho người chơi | U11: spec 12.2 (05)
A12: survival | B12: survival | C12: Survival | D12: NEED_SOURCE | H12: NEED_SOURCE | O12: NEED_SOURCE | Q12: repo không có tham chiếu cho mục này | R12: chỉ ở mức ý tưởng và thông số (sự kiện); không dùng tên, logo, văn bản, ảnh hay mô hình có bản quyền; tên và phù hiệu quốc gia thật không hiện cho người chơi | U12: spec 12.2 (05)
A13: weekly | B13: weekly | C13: Weekly | D13: NEED_SOURCE | H13: NEED_SOURCE | O13: NEED_SOURCE | Q13: repo không có tham chiếu cho mục này | R13: chỉ ở mức ý tưởng và thông số (sự kiện); không dùng tên, logo, văn bản, ảnh hay mô hình có bản quyền; tên và phù hiệu quốc gia thật không hiện cho người chơi | U13: spec 12.2 (05)

Sheet Nang_hang
A1: id | B1: hang | C1: xu | D1: ban_thiet_ke | E1: nguon | F1: raw_json
A2: 1 | B2: 1 | C2: 0 | D2: 0 | E2: Assets/MachineBrigade/Scripts/Game/Match/Arsenal.cs:128 (Coins)
A3: 2 | B3: 2 | C3: 50 | D3: 2 | E3: Assets/MachineBrigade/Scripts/Game/Match/Arsenal.cs:128 (Coins)
A4: 3 | B4: 3 | C4: 100 | D4: 4 | E4: Assets/MachineBrigade/Scripts/Game/Match/Arsenal.cs:128 (Coins)
A5: 4 | B5: 4 | C5: 200 | D5: 8 | E5: Assets/MachineBrigade/Scripts/Game/Match/Arsenal.cs:128 (Coins)
A6: 5 | B6: 5 | C6: 400 | D6: 12 | E6: Assets/MachineBrigade/Scripts/Game/Match/Arsenal.cs:128 (Coins)
A7: 6 | B7: 6 | C7: 700 | D7: 20 | E7: Assets/MachineBrigade/Scripts/Game/Match/Arsenal.cs:128 (Coins)
A8: 7 | B8: 7 | C8: 1200 | D8: 30 | E8: Assets/MachineBrigade/Scripts/Game/Match/Arsenal.cs:128 (Coins)
A9: 8 | B9: 8 | C9: 2000 | D9: 45 | E9: Assets/MachineBrigade/Scripts/Game/Match/Arsenal.cs:128 (Coins)
A10: 9 | B10: 9 | C10: 3200 | D10: 65 | E10: Assets/MachineBrigade/Scripts/Game/Match/Arsenal.cs:128 (Coins)
A11: 10 | B11: 10 | C11: 5000 | D11: 90 | E11: Assets/MachineBrigade/Scripts/Game/Match/Arsenal.cs:128 (Coins)

Sheet Hom_do
A1: id | B1: bac_hom | C1: ty_le_0 | D1: ty_le_1 | E1: ty_le_2 | F1: ty_le_3 | G1: ty_le_4 | H1: rolls | I1: coins_low | J1: coins_high | K1: print_count | L1: print_cards | M1: coin_price | N1: epic_pity | O1: legendary_pity | P1: tower_share | Q1: nguon | R1: raw_json
A2: 0 | B2: 0 | C2: 0.7 | D2: 0.25 | E2: 0.045 | F2: 0.005 | G2: 0 | H2: 1 | I2: 60 | J2: 120 | K2: 6 | L2: 1 | M2: 0 | N2: 0 | O2: 0 | P2: 0.2 | Q2: Assets/MachineBrigade/Scripts/Game/Match/Arsenal.cs:479 (Rolls)
A3: 1 | B3: 1 | C3: 0.5 | D3: 0.35 | E3: 0.12 | F3: 0.028 | G3: 0.002 | H3: 2 | I3: 250 | J3: 350 | K3: 15 | L3: 2 | M3: 900 | N3: 0 | O3: 0 | P3: 0.2 | Q3: Assets/MachineBrigade/Scripts/Game/Match/Arsenal.cs:479 (Rolls)
A4: 2 | B4: 2 | C4: 0.2 | D4: 0.42 | E4: 0.28 | F4: 0.085 | G4: 0.015 | H4: 4 | I4: 800 | J4: 1000 | K4: 45 | L4: 3 | M4: 3000 | N4: 5 | O4: 25 | P4: 0.2 | Q4: Assets/MachineBrigade/Scripts/Game/Match/Arsenal.cs:479 (Rolls)
A5: 3 | B5: 3 | C5: 0 | D5: 0.25 | E5: 0.45 | F5: 0.24 | G5: 0.06 | H5: 6 | I5: 2000 | J5: 2500 | K5: 120 | L5: 4 | M5: 8000 | N5: 0 | O5: 4 | P5: 0.2 | Q5: Assets/MachineBrigade/Scripts/Game/Match/Arsenal.cs:479 (Rolls)

Sheet Cua_hang
A1: id | B1: id_goi | C1: xu | D1: gia_hien_thi | E1: nguon | F1: raw_json
A2: coins_1200 | B2: coins_1200 | C2: 1200 | D2: $0.99 | E2: Assets/MachineBrigade/Scripts/Game/Match/Arsenal.cs:641 (Packs[0]) | F2: ["coins_1200",1200,"$0.99"]
A3: coins_7000 | B3: coins_7000 | C3: 7000 | D3: $4.99 | E3: Assets/MachineBrigade/Scripts/Game/Match/Arsenal.cs:641 (Packs[1]) | F3: ["coins_7000",7000,"$4.99"]
A4: coins_15000 | B4: coins_15000 | C4: 15000 | D4: $9.99 | E4: Assets/MachineBrigade/Scripts/Game/Match/Arsenal.cs:641 (Packs[2]) | F4: ["coins_15000",15000,"$9.99"]
A5: coins_32000 | B5: coins_32000 | C5: 32000 | D5: $19.99 | E5: Assets/MachineBrigade/Scripts/Game/Match/Arsenal.cs:642 (Packs[3]) | F5: ["coins_32000",32000,"$19.99"]
A6: coins_85000 | B6: coins_85000 | C6: 85000 | D6: $49.99 | E6: Assets/MachineBrigade/Scripts/Game/Match/Arsenal.cs:642 (Packs[4]) | F6: ["coins_85000",85000,"$49.99"]
A7: coins_180000 | B7: coins_180000 | C7: 180000 | D7: $99.99 | E7: Assets/MachineBrigade/Scripts/Game/Match/Arsenal.cs:642 (Packs[5]) | F7: ["coins_180000",180000,"$99.99"]

Sheet Nhiem_vu_ngay
A1: id | B1: loai | C1: muc_tieu | D1: thuong_xu | E1: nguon | F1: raw_json
A2: bosses | B2: bosses | C2: 1;1;2 | D2: 250 | E2: Assets/MachineBrigade/Scripts/Game/Match/DailyMissions.cs:36 (Pool[5]) | F2: ["bosses",[1,1,2],250]
A3: buildings | B3: buildings | C3: 12;20;30 | D3: 120 | E3: Assets/MachineBrigade/Scripts/Game/Match/DailyMissions.cs:34 (Pool[3]) | F3: ["buildings",[12,20,30],120]
A4: captures | B4: captures | C4: 4;8;12 | D4: 130 | E4: Assets/MachineBrigade/Scripts/Game/Match/DailyMissions.cs:35 (Pool[4]) | F4: ["captures",[4,8,12],130]
A5: elites | B5: elites | C5: 3;5;8 | D5: 160 | E5: Assets/MachineBrigade/Scripts/Game/Match/DailyMissions.cs:37 (Pool[6]) | F5: ["elites",[3,5,8],160]
A6: items | B6: items | C6: 1;2;3 | D6: 100 | E6: Assets/MachineBrigade/Scripts/Game/Match/DailyMissions.cs:38 (Pool[7]) | F6: ["items",[1,2,3],100]
A7: kills | B7: kills | C7: 40;60;90 | D7: 150 | E7: Assets/MachineBrigade/Scripts/Game/Match/DailyMissions.cs:31 (Pool[0]) | F7: ["kills",[40,60,90],150]
A8: strikes | B8: strikes | C8: 6;10;15 | D8: 120 | E8: Assets/MachineBrigade/Scripts/Game/Match/DailyMissions.cs:33 (Pool[2]) | F8: ["strikes",[6,10,15],120]
A9: wins | B9: wins | C9: 1;2;3 | D9: 180 | E9: Assets/MachineBrigade/Scripts/Game/Match/DailyMissions.cs:32 (Pool[1]) | F9: ["wins",[1,2,3],180]

Sheet Skin
A1: id | B1: base_hex | C1: metallic | D1: pattern | E1: price | F1: roughness | G1: scale | H1: second_hex | I1: third_hex | J1: nguon | K1: raw_json
A2: arctic | B2: #e4e9ec | D2: Blotches | E2: 900 | G2: 0.34 | H2: #b4bec5 | I2: #7b8790 | J2: Assets/MachineBrigade/Scripts/Game/Match/Skins.cs:57 (All[3]) | K2: {"id":"arctic","price":900,"baseHex":"#e4e9ec","secondHex":"#b4bec5","thirdHex":"#7b8790","pattern":"Blotches","scale":0.34}
A3: desert | B3: #c7a46a | D3: Blotches | E3: 500 | G3: 0.32 | H3: #9a7646 | I3: #6f5535 | J3: Assets/MachineBrigade/Scripts/Game/Match/Skins.cs:55 (All[1]) | K3: {"id":"desert","price":500,"baseHex":"#c7a46a","secondHex":"#9a7646","thirdHex":"#6f5535","pattern":"Blotches","scale":0.32}
A4: gold | B4: #d5a63c | C4: 0.92 | D4: Plain | E4: 6000 | F4: 0.26 | G4: 0.35 | H4: #b8872a | I4: #f0cd6c | J4: Assets/MachineBrigade/Scripts/Game/Match/Skins.cs:63 (All[9]) | K4: {"id":"gold","price":6000,"baseHex":"#d5a63c","secondHex":"#b8872a","thirdHex":"#f0cd6c","pattern":"Plain","scale":0.35,"metallic":0.92,"roughness":0.26}
A5: midnight | B5: #272b31 | C5: 0.35 | D5: Digital | E5: 3000 | F5: 0.35 | G5: 0.6 | H5: #3b4550 | I5: #4fd7ff | J5: Assets/MachineBrigade/Scripts/Game/Match/Skins.cs:61 (All[7]) | K5: {"id":"midnight","price":3000,"baseHex":"#272b31","secondHex":"#3b4550","thirdHex":"#4fd7ff","pattern":"Digital","scale":0.6,"metallic":0.35,"roughness":0.35}
A6: ocean | B6: #4b6b8c | D6: Digital | E6: 1500 | G6: 0.55 | H6: #2c435e | I6: #8aa7c4 | J6: Assets/MachineBrigade/Scripts/Game/Match/Skins.cs:59 (All[5]) | K6: {"id":"ocean","price":1500,"baseHex":"#4b6b8c","secondHex":"#2c435e","thirdHex":"#8aa7c4","pattern":"Digital","scale":0.55}
A7: olive | B7: #7a9654 | D7: Plain | E7: 0 | H7: #7a9654 | I7: #7a9654 | J7: Assets/MachineBrigade/Scripts/Game/Match/Skins.cs:54 (All[0]) | K7: {"id":"olive","price":0,"baseHex":"#7a9654","secondHex":"#7a9654","thirdHex":"#7a9654","pattern":"Plain"}
A8: steel | B8: #b3bcc3 | C8: 0.9 | D8: Plain | E8: 4500 | F8: 0.24 | G8: 0.35 | H8: #8c969e | I8: #d7dde2 | J8: Assets/MachineBrigade/Scripts/Game/Match/Skins.cs:62 (All[8]) | K8: {"id":"steel","price":4500,"baseHex":"#b3bcc3","secondHex":"#8c969e","thirdHex":"#d7dde2","pattern":"Plain","scale":0.35,"metallic":0.9,"roughness":0.24}
A9: tiger | B9: #d9832c | D9: Stripes | E9: 2500 | G9: 0.5 | H9: #1e1b18 | I9: #d9832c | J9: Assets/MachineBrigade/Scripts/Game/Match/Skins.cs:60 (All[6]) | K9: {"id":"tiger","price":2500,"baseHex":"#d9832c","secondHex":"#1e1b18","thirdHex":"#d9832c","pattern":"Stripes","scale":0.5}
A10: urban | B10: #8b9197 | D10: Digital | E10: 1200 | G10: 0.55 | H10: #5a6066 | I10: #b9bdc1 | J10: Assets/MachineBrigade/Scripts/Game/Match/Skins.cs:58 (All[4]) | K10: {"id":"urban","price":1200,"baseHex":"#8b9197","secondHex":"#5a6066","thirdHex":"#b9bdc1","pattern":"Digital","scale":0.55}
A11: woodland | B11: #617540 | D11: Blotches | E11: 800 | G11: 0.36 | H11: #3c4a29 | I11: #6d5436 | J11: Assets/MachineBrigade/Scripts/Game/Match/Skins.cs:56 (All[2]) | K11: {"id":"woodland","price":800,"baseHex":"#617540","secondHex":"#3c4a29","thirdHex":"#6d5436","pattern":"Blotches","scale":0.36}

Sheet Ban_do_menu
A1: id | B1: icon | C1: theme | D1: weathers | E1: nguon | F1: raw_json
A2: ashfield | B2: pine | C2: temperate | D2: Clear;Clear;Overcast;Rain;Storm;Fog;Night | E2: Assets/MachineBrigade/Scripts/Game/Match/MatchSettings.cs:203 (AllMaps[0]) | F2: {"id":"ashfield","theme":"temperate","icon":"pine","weathers":["Clear","Clear","Overcast","Rain","Storm","Fog","Night"]}
A3: borderbridge | B3: flag | C3: temperate | D3: Clear;Overcast;Rain;Fog;Storm;Night | E3: Assets/MachineBrigade/Scripts/Game/Match/MatchSettings.cs:243 (AllMaps[17]) | F3: {"id":"borderbridge","theme":"temperate","icon":"flag","weathers":["Clear","Overcast","Rain","Fog","Storm","Night"]}
A4: capital | B4: crown | C4: urban | D4: Clear;Night;Overcast;Rain;Fog;Storm | E4: Assets/MachineBrigade/Scripts/Game/Match/MatchSettings.cs:235 (AllMaps[14]) | F4: {"id":"capital","theme":"urban","icon":"crown","weathers":["Clear","Night","Overcast","Rain","Fog","Storm"]}
A5: coralisles | B5: sun | C5: desert | D5: Clear;Clear;Storm;Overcast;Night | E5: Assets/MachineBrigade/Scripts/Game/Match/MatchSettings.cs:247 (AllMaps[19]) | F5: {"id":"coralisles","theme":"desert","icon":"sun","weathers":["Clear","Clear","Storm","Overcast","Night"]}
A6: dunebreak | B6: dune | C6: desert | D6: Clear;Clear;Sandstorm;Overcast;Night | E6: Assets/MachineBrigade/Scripts/Game/Match/MatchSettings.cs:205 (AllMaps[1]) | F6: {"id":"dunebreak","theme":"desert","icon":"dune","weathers":["Clear","Clear","Sandstorm","Overcast","Night"]}
A7: emberridge | B7: flame | C7: volcanic | D7: Night;Night;Clear;Overcast;Fog;Storm | E7: Assets/MachineBrigade/Scripts/Game/Match/MatchSettings.cs:220 (AllMaps[8]) | F7: {"id":"emberridge","theme":"volcanic","icon":"flame","weathers":["Night","Night","Clear","Overcast","Fog","Storm"]}
A8: foundry | B8: gear | C8: urban | D8: Overcast;Clear;Rain;Fog;Night;Night | E8: Assets/MachineBrigade/Scripts/Game/Match/MatchSettings.cs:260 (AllMaps[23]) | F8: {"id":"foundry","theme":"urban","icon":"gear","weathers":["Overcast","Clear","Rain","Fog","Night","Night"]}
A9: frostpeak | B9: snow | C9: snow | D9: Snow;Clear;Overcast;Fog;Night | E9: Assets/MachineBrigade/Scripts/Game/Match/MatchSettings.cs:207 (AllMaps[2]) | F9: {"id":"frostpeak","theme":"snow","icon":"snow","weathers":["Snow","Clear","Overcast","Fog","Night"]}
A10: greenvale | B10: pine | C10: temperate | D10: Clear;Overcast;Rain;Storm;Fog;Night | E10: Assets/MachineBrigade/Scripts/Game/Match/MatchSettings.cs:215 (AllMaps[6]) | F10: {"id":"greenvale","theme":"temperate","icon":"pine","weathers":["Clear","Overcast","Rain","Storm","Fog","Night"]}
A11: hydrodam | B11: bolt | C11: temperate | D11: Clear;Overcast;Rain;Fog;Storm;Night | E11: Assets/MachineBrigade/Scripts/Game/Match/MatchSettings.cs:233 (AllMaps[13]) | F11: {"id":"hydrodam","theme":"temperate","icon":"bolt","weathers":["Clear","Overcast","Rain","Fog","Storm","Night"]}
A12: ironport | B12: anchor | C12: harbor | D12: Clear;Overcast;Rain;Storm;Fog;Night | E12: Assets/MachineBrigade/Scripts/Game/Match/MatchSettings.cs:209 (AllMaps[3]) | F12: {"id":"ironport","theme":"harbor","icon":"anchor","weathers":["Clear","Overcast","Rain","Storm","Fog","Night"]}
... A26: whiteout | B26: snow | C26: snow | D26: Snow;Snow;Fog;Clear;Night | E26: Assets/MachineBrigade/Scripts/Game/Match/MatchSettings.cs:213 (AllMaps[5]) | F26: {"id":"whiteout","theme":"snow","icon":"snow","weathers":["Snow","Snow","Fog","Clear","Night"]}

Sheet Meta_bang_hang
A1: id | B1: bang | C1: chi_so | D1: gia_tri | E1: nguon | F1: raw_json
A2: GraphicsOptions#AntiAliasingLevels/0 | B2: GraphicsOptions#AntiAliasingLevels | C2: 0 | D2: 1 | E2: Assets/MachineBrigade/Scripts/Game/Match/GraphicsOptions.cs:45 (AntiAliasingLevels[0]) | F2: 1
A3: GraphicsOptions#AntiAliasingLevels/1 | B3: GraphicsOptions#AntiAliasingLevels | C3: 1 | D3: 2 | E3: Assets/MachineBrigade/Scripts/Game/Match/GraphicsOptions.cs:45 (AntiAliasingLevels[1]) | F3: 2
A4: GraphicsOptions#AntiAliasingLevels/2 | B4: GraphicsOptions#AntiAliasingLevels | C4: 2 | D4: 4 | E4: Assets/MachineBrigade/Scripts/Game/Match/GraphicsOptions.cs:45 (AntiAliasingLevels[2]) | F4: 4
A5: GraphicsOptions#FrameRates/0 | B5: GraphicsOptions#FrameRates | C5: 0 | D5: 30 | E5: Assets/MachineBrigade/Scripts/Game/Match/GraphicsOptions.cs:46 (FrameRates[0]) | F5: 30
A6: GraphicsOptions#FrameRates/1 | B6: GraphicsOptions#FrameRates | C6: 1 | D6: 60 | E6: Assets/MachineBrigade/Scripts/Game/Match/GraphicsOptions.cs:46 (FrameRates[1]) | F6: 60
A7: GraphicsOptions#FrameRates/2 | B7: GraphicsOptions#FrameRates | C7: 2 | D7: 90 | E7: Assets/MachineBrigade/Scripts/Game/Match/GraphicsOptions.cs:46 (FrameRates[2]) | F7: 90
A8: GraphicsOptions#FrameRates/3 | B8: GraphicsOptions#FrameRates | C8: 3 | D8: 120 | E8: Assets/MachineBrigade/Scripts/Game/Match/GraphicsOptions.cs:46 (FrameRates[3]) | F8: 120
A9: GraphicsOptions#RenderScales/0 | B9: GraphicsOptions#RenderScales | C9: 0 | D9: 70 | E9: Assets/MachineBrigade/Scripts/Game/Match/GraphicsOptions.cs:44 (RenderScales[0]) | F9: 70
A10: GraphicsOptions#RenderScales/1 | B10: GraphicsOptions#RenderScales | C10: 1 | D10: 85 | E10: Assets/MachineBrigade/Scripts/Game/Match/GraphicsOptions.cs:44 (RenderScales[1]) | F10: 85
A11: GraphicsOptions#RenderScales/2 | B11: GraphicsOptions#RenderScales | C11: 2 | D11: 100 | E11: Assets/MachineBrigade/Scripts/Game/Match/GraphicsOptions.cs:44 (RenderScales[2]) | F11: 100
A12: MatchSettings#AllSupports/0 | B12: MatchSettings#AllSupports | C12: 0 | D12: artillery_barrage | E12: Assets/MachineBrigade/Scripts/Game/Match/MatchSettings.cs:153 (AllSupports[0]) | F12: "artillery_barrage"
A13: MatchSettings#AllSupports/1 | B13: MatchSettings#AllSupports | C13: 1 | D13: airstrike | E13: Assets/MachineBrigade/Scripts/Game/Match/MatchSettings.cs:153 (AllSupports[1]) | F13: "airstrike"
A14: MatchSettings#AllSupports/2 | B14: MatchSettings#AllSupports | C14: 2 | D14: cruise_missile | E14: Assets/MachineBrigade/Scripts/Game/Match/MatchSettings.cs:153 (AllSupports[2]) | F14: "cruise_missile"
A15: MatchSettings#AllSupports/3 | B15: MatchSettings#AllSupports | C15: 3 | D15: repair_drop | E15: Assets/MachineBrigade/Scripts/Game/Match/MatchSettings.cs:153 (AllSupports[3]) | F15: "repair_drop"
A16: MatchSettings#AllSupports/4 | B16: MatchSettings#AllSupports | C16: 4 | D16: napalm_strike | E16: Assets/MachineBrigade/Scripts/Game/Match/MatchSettings.cs:153 (AllSupports[4]) | F16: "napalm_strike"
A17: MatchSettings#AllSupports/5 | B17: MatchSettings#AllSupports | C17: 5 | D17: remote_mines | E17: Assets/MachineBrigade/Scripts/Game/Match/MatchSettings.cs:154 (AllSupports[5]) | F17: "remote_mines"
A18: MatchSettings#AllSupports/6 | B18: MatchSettings#AllSupports | C18: 6 | D18: field_tower | E18: Assets/MachineBrigade/Scripts/Game/Match/MatchSettings.cs:154 (AllSupports[6]) | F18: "field_tower"
A19: MatchSettings#AllSupports/7 | B19: MatchSettings#AllSupports | C19: 7 | D19: glide_bomb_strike | E19: Assets/MachineBrigade/Scripts/Game/Match/MatchSettings.cs:156 (AllSupports[7]) | F19: "glide_bomb_strike"
A20: MatchSettings#AllVehicles/0 | B20: MatchSettings#AllVehicles | C20: 0 | D20: scout_jeep | E20: Assets/MachineBrigade/Scripts/Game/Match/MatchSettings.cs:118 (AllVehicles[0]) | F20: "scout_jeep"
A21: MatchSettings#AllVehicles/1 | B21: MatchSettings#AllVehicles | C21: 1 | D21: armored_car | E21: Assets/MachineBrigade/Scripts/Game/Match/MatchSettings.cs:118 (AllVehicles[1]) | F21: "armored_car"
A22: MatchSettings#AllVehicles/2 | B22: MatchSettings#AllVehicles | C22: 2 | D22: rocket_technical | E22: Assets/MachineBrigade/Scripts/Game/Match/MatchSettings.cs:118 (AllVehicles[2]) | F22: "rocket_technical"
A23: MatchSettings#AllVehicles/3 | B23: MatchSettings#AllVehicles | C23: 3 | D23: light_tank | E23: Assets/MachineBrigade/Scripts/Game/Match/MatchSettings.cs:118 (AllVehicles[3]) | F23: "light_tank"
... A113: Progression#StarterVehicles/3 | B113: Progression#StarterVehicles | C113: 3 | D113: main_battle_tank | E113: Assets/MachineBrigade/Scripts/Game/Match/Progression.cs:35 (StarterVehicles[3]) | F113: "main_battle_tank"

Sheet Mo_khoa
A1: id | B1: the | C1: chuong | D1: early | E1: notCards | F1: nguon | G1: raw_json
A2: chapters.aa_vehicle | B2: aa_vehicle | C2: 2 | F2: Tools/campaign/unlocks_sheet.json: chapters.aa_vehicle | G2: 2
A3: chapters.ammo_carrier | B3: ammo_carrier | C3: 2 | F3: Tools/campaign/unlocks_sheet.json: chapters.ammo_carrier | G3: 2
A4: chapters.armored_bulldozer | B4: armored_bulldozer | C4: 4 | F4: Tools/campaign/unlocks_sheet.json: chapters.armored_bulldozer | G4: 4
A5: chapters.artillery | B5: artillery | C5: 2 | F5: Tools/campaign/unlocks_sheet.json: chapters.artillery | G5: 2
A6: chapters.attack_helicopter | B6: attack_helicopter | C6: 3 | F6: Tools/campaign/unlocks_sheet.json: chapters.attack_helicopter | G6: 3
A7: chapters.attack_jet | B7: attack_jet | C7: 7 | F7: Tools/campaign/unlocks_sheet.json: chapters.attack_jet | G7: 7
A8: chapters.ballistic_launcher | B8: ballistic_launcher | C8: 8 | F8: Tools/campaign/unlocks_sheet.json: chapters.ballistic_launcher | G8: 8
A9: chapters.command_vehicle | B9: command_vehicle | C9: 4 | F9: Tools/campaign/unlocks_sheet.json: chapters.command_vehicle | G9: 4
A10: chapters.engineer_vehicle | B10: engineer_vehicle | C10: 1 | F10: Tools/campaign/unlocks_sheet.json: chapters.engineer_vehicle | G10: 1
A11: chapters.ew_jammer | B11: ew_jammer | C11: 5 | F11: Tools/campaign/unlocks_sheet.json: chapters.ew_jammer | G11: 5
A12: chapters.fighter_jet | B12: fighter_jet | C12: 3 | F12: Tools/campaign/unlocks_sheet.json: chapters.fighter_jet | G12: 3
A13: chapters.flame_tank | B13: flame_tank | C13: 2 | F13: Tools/campaign/unlocks_sheet.json: chapters.flame_tank | G13: 2
... A45: chapters.zu23_technical | B45: zu23_technical | C45: 1 | F45: Tools/campaign/unlocks_sheet.json: chapters.zu23_technical | G45: 1
A46: early.aa_vehicle | B46: aa_vehicle | D46: 300 | F46: Tools/campaign/unlocks_sheet.json: early.aa_vehicle | G46: 300
A47: early.ammo_carrier | B47: ammo_carrier | D47: 300 | F47: Tools/campaign/unlocks_sheet.json: early.ammo_carrier | G47: 300
A48: early.armored_bulldozer | B48: armored_bulldozer | D48: 800 | F48: Tools/campaign/unlocks_sheet.json: early.armored_bulldozer | G48: 800
A49: early.artillery | B49: artillery | D49: 300 | F49: Tools/campaign/unlocks_sheet.json: early.artillery | G49: 300
A50: early.attack_helicopter | B50: attack_helicopter | D50: 300 | F50: Tools/campaign/unlocks_sheet.json: early.attack_helicopter | G50: 300
A51: early.attack_jet | B51: attack_jet | D51: 1500 | F51: Tools/campaign/unlocks_sheet.json: early.attack_jet | G51: 1500
A52: early.ballistic_launcher | B52: ballistic_launcher | D52: 1500 | F52: Tools/campaign/unlocks_sheet.json: early.ballistic_launcher | G52: 1500
A53: early.command_vehicle | B53: command_vehicle | D53: 800 | F53: Tools/campaign/unlocks_sheet.json: early.command_vehicle | G53: 800
A54: early.engineer_vehicle | B54: engineer_vehicle | D54: 300 | F54: Tools/campaign/unlocks_sheet.json: early.engineer_vehicle | G54: 300
A55: early.ew_jammer | B55: ew_jammer | D55: 800 | F55: Tools/campaign/unlocks_sheet.json: early.ew_jammer | G55: 800
A56: early.fighter_jet | B56: fighter_jet | D56: 300 | F56: Tools/campaign/unlocks_sheet.json: early.fighter_jet | G56: 300
A57: early.flame_tank | B57: flame_tank | D57: 300 | F57: Tools/campaign/unlocks_sheet.json: early.flame_tank | G57: 300
... A87: early.zu23_technical | B87: zu23_technical | D87: 300 | F87: Tools/campaign/unlocks_sheet.json: early.zu23_technical | G87: 300
A88: notCards.hover_gunboat | B88: hover_gunboat | E88: Không mở (hộ tống boss) | F88: Tools/campaign/unlocks_sheet.json: notCards.hover_gunboat | G88: "Không mở (hộ tống boss)"
A89: notCards.supply_truck | B89: supply_truck | E89: Nhiệm vụ (không vào bộ bài) | F89: Tools/campaign/unlocks_sheet.json: notCards.supply_truck | G89: "Nhiệm vụ (không vào bộ bài)"

Sheet Mo_khoa_chung
A1: id | B1: nhom | C1: khoa | D1: gia_tri_so | E1: gia_tri_chu | F1: don_vi | G1: nguon | H1: raw_json
A2: _about | C2: _about | E2: Generated by Tools/balance/import_unlocks.py from the sheet "Phương tiện" of Docs/balance/Machine_Brigade_Can_bang.xlsx: edit the sheet and run the script. chapters: 1-12, 13-15 the interludes. Read by Tools/campaign/act11.py. | G2: Tools/campaign/unlocks_sheet.json: _about | H2: "Generated by Tools/balance/import_unlocks.py from the sheet \"Phương tiện\" of Docs/balance/Machine_Brigade_Can_bang.xlsx: edit the sheet and run the script. chapters: 1-12, 13-15 the interludes. Read by Tools/campaign/act11.py."
A3: loot | C3: loot | E3: swarm_carrier;railgun_truck | G3: Tools/campaign/unlocks_sheet.json: loot | H3: ["swarm_carrier","railgun_truck"]
A4: starters | C4: starters | E4: scout_jeep;armored_car;ifv;main_battle_tank | G4: Tools/campaign/unlocks_sheet.json: starters | H4: ["scout_jeep","armored_car","ifv","main_battle_tank"]

Sheet Meta_kinh_te_nguon
A1: id | B1: loai | C1: don_vi_tinh | D1: xu | E1: tran | F1: ghi_chu | G1: nguon_ma | H1: nguon | I1: raw_json
A2: bac_anh_hung | B2: nguon | C2: he_so | D2: 1.5 | F2: Rewards.TierPay: Anh hùng | G2: Game/Match/Rewards.cs:144 | H2: C#: Game/Match/Rewards.cs:144
A3: bac_sat | B3: nguon | C3: he_so | D3: 2 | F3: Rewards.TierPay: Sắt | G3: Game/Match/Rewards.cs:144 | H3: C#: Game/Match/Rewards.cs:144
A4: cua_hang_goi_lon_nhat | B4: nguon | C4: goi | D4: =MAX(Cua_hang!$C$2:$C$7) | F4: gói xu lớn nhất (Cua_hang) | G4: Cua_hang | H4: C#: Cua_hang
A5: hom_gia_cao_nhat | B5: tieu | C5: hom | D5: =MAX(Hom_do!$M$2:$M$5) | F5: giá xu của hòm đắt nhất (Hom_do.coin_price) | G5: Hom_do | H5: C#: Hom_do
A6: hom_quang_cao_ngay | B6: nguon | C6: hom | E6: 3 | F6: DailyCrates.AdCrates: hòm xem quảng cáo mỗi ngày | G6: Game/Match/Arsenal.cs:621 | H6: C#: Game/Match/Arsenal.cs:621
A7: hom_thang_ngay | B7: nguon | C7: hom | E7: 5 | F7: DailyCrates.WinCrates: hòm cho các trận thắng đầu mỗi ngày | G7: Game/Match/Arsenal.cs:620 | H7: C#: Game/Match/Arsenal.cs:620
A8: nang_hang_tong | B8: tieu | C8: the | D8: =SUM(Nang_hang!$C$2:$C$11) | E8: 10 | F8: xu nâng một thẻ hạng 1 -> tối đa (Nang_hang); trần: hạng tối đa | G8: Game/Match/Arsenal.cs:126 | H8: C#: Game/Match/Arsenal.cs:126
A9: nhiem_vu_choi_lai | B9: nguon | C9: he_so | D9: 0.35 | F9: Rewards.Mission: phần RewardCoins khi chơi lại | G9: Game/Match/Rewards.cs:159 | H9: C#: Game/Match/Rewards.cs:159
A10: nhiem_vu_lan_dau | B10: nguon | C10: he_so | D10: 1 | F10: Rewards.Mission: phần RewardCoins lần thắng đầu | G10: Game/Match/Rewards.cs:159 | H10: C#: Game/Match/Rewards.cs:159
A11: nhiem_vu_ngay | B11: nguon | C11: ngay | D11: =AVERAGE(Nhiem_vu_ngay!$D$2:$D$9) | E11: 3 | F11: DailyMissions: số nhiệm vụ mỗi ngày (trần); xu: trung bình thưởng của Pool | G11: Game/Match/DailyMissions.cs:51 | H11: C#: Game/Match/DailyMissions.cs:51
A12: nhiem_vu_sao | B12: nguon | C12: sao | D12: 50 | E12: 3 | F12: Rewards.Mission: mỗi sao (x TierPay), tối đa 3 sao | G12: Game/Match/Rewards.cs:160 | H12: C#: Game/Match/Rewards.cs:160
A13: nhiem_vu_thua | B13: nguon | C13: tran | D13: 30 | F13: Rewards.Mission: thua | G13: Game/Match/Rewards.cs:155 | H13: C#: Game/Match/Rewards.cs:155
A14: skin_tong | B14: tieu | C14: skin | D14: =SUM(Skin!$E$2:$E$11) | F14: tổng giá mọi skin (Skin.price) | G14: Skin | H14: C#: Skin
A15: song_sot_co_ban | B15: nguon | C15: tran | D15: 30 | F15: Rewards.Survival: cơ bản | G15: Game/Match/Rewards.cs:104 | H15: C#: Game/Match/Rewards.cs:104
A16: song_sot_dot | B16: nguon | C16: dot | D16: 18 | F16: Rewards.Survival: mỗi đợt | G16: Game/Match/Rewards.cs:104 | H16: C#: Game/Match/Rewards.cs:104
A17: song_sot_ha_xe | B17: nguon | C17: ha_xe | D17: 1.5 | E17: 150 | F17: Rewards.Survival: mỗi xe hạ, tối đa | G17: Game/Match/Rewards.cs:104 | H17: C#: Game/Match/Rewards.cs:104
A18: tran_nhanh_ha_xe | B18: nguon | C18: ha_xe | D18: 1.5 | E18: 120 | F18: Rewards.Quick: mỗi xe hạ, tối đa | G18: Game/Match/Rewards.cs:95 | H18: C#: Game/Match/Rewards.cs:95
A19: tran_nhanh_hoa | B19: nguon | C19: tran | D19: 70 | F19: Rewards.Quick: hòa | G19: Game/Match/Rewards.cs:94 | H19: C#: Game/Match/Rewards.cs:94
A20: tran_nhanh_phut | B20: nguon | C20: phut | D20: 4 | E20: 15 | F20: Rewards.Quick: mỗi phút, tối đa (phút) | G20: Game/Match/Rewards.cs:97 | H20: C#: Game/Match/Rewards.cs:97
A21: tran_nhanh_thang | B21: nguon | C21: tran | D21: 120 | F21: Rewards.Quick: thắng | G21: Game/Match/Rewards.cs:94 | H21: C#: Game/Match/Rewards.cs:94
A22: tran_nhanh_thua | B22: nguon | C22: tran | D22: 40 | F22: Rewards.Quick: thua | G22: Game/Match/Rewards.cs:94 | H22: C#: Game/Match/Rewards.cs:94
A23: vo_tan_boss | B23: nguon | C23: boss | D23: 18 | E23: 18 | F23: Endless: mỗi boss; trần xu mỗi ngày | G23: tunables.json: modes.endlessRules.waveCoins.value | H23: C#: tunables.json: modes.endlessRules.waveCoins.value
A24: vo_tan_dot | B24: nguon | C24: dot | D24: 18 | E24: 18 | F24: Endless: mỗi đợt; trần xu mỗi ngày | G24: tunables.json: modes.endlessRules.waveCoins.value | H24: C#: tunables.json: modes.endlessRules.waveCoins.value

Sheet Meta_kinh_te_tran
A1: id | B1: do_kho | C1: ket_qua | D1: he_so_do_kho | E1: so_xe_ha | F1: so_phut | G1: xu | H1: xu_game | I1: nguon | J1: raw_json
A2: Easy/hoa | B2: Easy | C2: hoa | D2: 0.7 | E2: 20 | F2: 9 | G2: =ROUND((Meta_kinh_te_nguon!$D$19+MIN($E$2,Meta_kinh_te_nguon!$E$18)*Meta_kinh_te_nguon!$D$18+MIN(MAX($F$2,0),Meta_kinh_te_nguon!$E$20)*Meta_kinh_te_nguon!$D$20)*$D$2,0) | H2: 95 | I2: Game/Match/Rewards.cs Quick (Game/Match/Rewards.cs:85)
A3: Easy/thang | B3: Easy | C3: thang | D3: 0.7 | E3: 20 | F3: 9 | G3: =ROUND((Meta_kinh_te_nguon!$D$21+MIN($E$3,Meta_kinh_te_nguon!$E$18)*Meta_kinh_te_nguon!$D$18+MIN(MAX($F$3,0),Meta_kinh_te_nguon!$E$20)*Meta_kinh_te_nguon!$D$20)*$D$3,0) | H3: 130 | I3: Game/Match/Rewards.cs Quick (Game/Match/Rewards.cs:85)
A4: Easy/thua | B4: Easy | C4: thua | D4: 0.7 | E4: 20 | F4: 9 | G4: =ROUND((Meta_kinh_te_nguon!$D$22+MIN($E$4,Meta_kinh_te_nguon!$E$18)*Meta_kinh_te_nguon!$D$18+MIN(MAX($F$4,0),Meta_kinh_te_nguon!$E$20)*Meta_kinh_te_nguon!$D$20)*$D$4,0) | H4: 74 | I4: Game/Match/Rewards.cs Quick (Game/Match/Rewards.cs:85)
A5: Hard/hoa | B5: Hard | C5: hoa | D5: 1.45 | E5: 20 | F5: 9 | G5: =ROUND((Meta_kinh_te_nguon!$D$19+MIN($E$5,Meta_kinh_te_nguon!$E$18)*Meta_kinh_te_nguon!$D$18+MIN(MAX($F$5,0),Meta_kinh_te_nguon!$E$20)*Meta_kinh_te_nguon!$D$20)*$D$5,0) | H5: 197 | I5: Game/Match/Rewards.cs Quick (Game/Match/Rewards.cs:86)
A6: Hard/thang | B6: Hard | C6: thang | D6: 1.45 | E6: 20 | F6: 9 | G6: =ROUND((Meta_kinh_te_nguon!$D$21+MIN($E$6,Meta_kinh_te_nguon!$E$18)*Meta_kinh_te_nguon!$D$18+MIN(MAX($F$6,0),Meta_kinh_te_nguon!$E$20)*Meta_kinh_te_nguon!$D$20)*$D$6,0) | H6: 270 | I6: Game/Match/Rewards.cs Quick (Game/Match/Rewards.cs:86)
A7: Hard/thua | B7: Hard | C7: thua | D7: 1.45 | E7: 20 | F7: 9 | G7: =ROUND((Meta_kinh_te_nguon!$D$22+MIN($E$7,Meta_kinh_te_nguon!$E$18)*Meta_kinh_te_nguon!$D$18+MIN(MAX($F$7,0),Meta_kinh_te_nguon!$E$20)*Meta_kinh_te_nguon!$D$20)*$D$7,0) | H7: 154 | I7: Game/Match/Rewards.cs Quick (Game/Match/Rewards.cs:86)
A8: Normal/hoa | B8: Normal | C8: hoa | D8: 1 | E8: 20 | F8: 9 | G8: =ROUND((Meta_kinh_te_nguon!$D$19+MIN($E$8,Meta_kinh_te_nguon!$E$18)*Meta_kinh_te_nguon!$D$18+MIN(MAX($F$8,0),Meta_kinh_te_nguon!$E$20)*Meta_kinh_te_nguon!$D$20)*$D$8,0) | H8: 136 | I8: Game/Match/Rewards.cs Quick (Game/Match/Rewards.cs:88)
A9: Normal/thang | B9: Normal | C9: thang | D9: 1 | E9: 20 | F9: 9 | G9: =ROUND((Meta_kinh_te_nguon!$D$21+MIN($E$9,Meta_kinh_te_nguon!$E$18)*Meta_kinh_te_nguon!$D$18+MIN(MAX($F$9,0),Meta_kinh_te_nguon!$E$20)*Meta_kinh_te_nguon!$D$20)*$D$9,0) | H9: 186 | I9: Game/Match/Rewards.cs Quick (Game/Match/Rewards.cs:88)
A10: Normal/thua | B10: Normal | C10: thua | D10: 1 | E10: 20 | F10: 9 | G10: =ROUND((Meta_kinh_te_nguon!$D$22+MIN($E$10,Meta_kinh_te_nguon!$E$18)*Meta_kinh_te_nguon!$D$18+MIN(MAX($F$10,0),Meta_kinh_te_nguon!$E$20)*Meta_kinh_te_nguon!$D$20)*$D$10,0) | H10: 106 | I10: Game/Match/Rewards.cs Quick (Game/Match/Rewards.cs:88)
A11: VeryHard/hoa | B11: VeryHard | C11: hoa | D11: 1.8 | E11: 20 | F11: 9 | G11: =ROUND((Meta_kinh_te_nguon!$D$19+MIN($E$11,Meta_kinh_te_nguon!$E$18)*Meta_kinh_te_nguon!$D$18+MIN(MAX($F$11,0),Meta_kinh_te_nguon!$E$20)*Meta_kinh_te_nguon!$D$20)*$D$11,0) | H11: 245 | I11: Game/Match/Rewards.cs Quick (Game/Match/Rewards.cs:87)
A12: VeryHard/thang | B12: VeryHard | C12: thang | D12: 1.8 | E12: 20 | F12: 9 | G12: =ROUND((Meta_kinh_te_nguon!$D$21+MIN($E$12,Meta_kinh_te_nguon!$E$18)*Meta_kinh_te_nguon!$D$18+MIN(MAX($F$12,0),Meta_kinh_te_nguon!$E$20)*Meta_kinh_te_nguon!$D$20)*$D$12,0) | H12: 335 | I12: Game/Match/Rewards.cs Quick (Game/Match/Rewards.cs:87)
A13: VeryHard/thua | B13: VeryHard | C13: thua | D13: 1.8 | E13: 20 | F13: 9 | G13: =ROUND((Meta_kinh_te_nguon!$D$22+MIN($E$13,Meta_kinh_te_nguon!$E$18)*Meta_kinh_te_nguon!$D$18+MIN(MAX($F$13,0),Meta_kinh_te_nguon!$E$20)*Meta_kinh_te_nguon!$D$20)*$D$13,0) | H13: 191 | I13: Game/Match/Rewards.cs Quick (Game/Match/Rewards.cs:87)

Sheet Meta_kinh_te
A1: id | B1: xu_len_hang | C1: xu_tich_luy | D1: xu_tich_luy_game | E1: ban_thiet_ke_tich_luy | F1: ban_thiet_ke_tich_luy_game | G1: so_tran_thang | H1: gio_choi | I1: trong_tran | J1: nguon | K1: raw_json
A2: 1 | B2: =Nang_hang!$C$2 | C2: =SUMIFS(Nang_hang!$C$2:$C$11,Nang_hang!$B$2:$B$11,"<="&Nang_hang!$B$2) | D2: 0 | E2: =SUMIFS(Nang_hang!$D$2:$D$11,Nang_hang!$B$2:$B$11,"<="&Nang_hang!$B$2) | F2: 0 | G2: =CEILING($C$2/Meta_kinh_te_tran!$G$9,1) | H2: =$G$2*Meta_kinh_te_tran!$F$9/60 | I2: =Nang_hang!$B$2<=Meta_kinh_te_nguon!$E$8 | J2: 04_che_do_kinh_te_ai/Nang_hang (1); Game/Match/Arsenal.cs CardRanks
A3: 2 | B3: =Nang_hang!$C$3 | C3: =SUMIFS(Nang_hang!$C$2:$C$11,Nang_hang!$B$2:$B$11,"<="&Nang_hang!$B$3) | D3: 50 | E3: =SUMIFS(Nang_hang!$D$2:$D$11,Nang_hang!$B$2:$B$11,"<="&Nang_hang!$B$3) | F3: 2 | G3: =CEILING($C$3/Meta_kinh_te_tran!$G$9,1) | H3: =$G$3*Meta_kinh_te_tran!$F$9/60 | I3: =Nang_hang!$B$3<=Meta_kinh_te_nguon!$E$8 | J3: 04_che_do_kinh_te_ai/Nang_hang (2); Game/Match/Arsenal.cs CardRanks
A4: 3 | B4: =Nang_hang!$C$4 | C4: =SUMIFS(Nang_hang!$C$2:$C$11,Nang_hang!$B$2:$B$11,"<="&Nang_hang!$B$4) | D4: 150 | E4: =SUMIFS(Nang_hang!$D$2:$D$11,Nang_hang!$B$2:$B$11,"<="&Nang_hang!$B$4) | F4: 6 | G4: =CEILING($C$4/Meta_kinh_te_tran!$G$9,1) | H4: =$G$4*Meta_kinh_te_tran!$F$9/60 | I4: =Nang_hang!$B$4<=Meta_kinh_te_nguon!$E$8 | J4: 04_che_do_kinh_te_ai/Nang_hang (3); Game/Match/Arsenal.cs CardRanks
A5: 4 | B5: =Nang_hang!$C$5 | C5: =SUMIFS(Nang_hang!$C$2:$C$11,Nang_hang!$B$2:$B$11,"<="&Nang_hang!$B$5) | D5: 350 | E5: =SUMIFS(Nang_hang!$D$2:$D$11,Nang_hang!$B$2:$B$11,"<="&Nang_hang!$B$5) | F5: 14 | G5: =CEILING($C$5/Meta_kinh_te_tran!$G$9,1) | H5: =$G$5*Meta_kinh_te_tran!$F$9/60 | I5: =Nang_hang!$B$5<=Meta_kinh_te_nguon!$E$8 | J5: 04_che_do_kinh_te_ai/Nang_hang (4); Game/Match/Arsenal.cs CardRanks
A6: 5 | B6: =Nang_hang!$C$6 | C6: =SUMIFS(Nang_hang!$C$2:$C$11,Nang_hang!$B$2:$B$11,"<="&Nang_hang!$B$6) | D6: 750 | E6: =SUMIFS(Nang_hang!$D$2:$D$11,Nang_hang!$B$2:$B$11,"<="&Nang_hang!$B$6) | F6: 26 | G6: =CEILING($C$6/Meta_kinh_te_tran!$G$9,1) | H6: =$G$6*Meta_kinh_te_tran!$F$9/60 | I6: =Nang_hang!$B$6<=Meta_kinh_te_nguon!$E$8 | J6: 04_che_do_kinh_te_ai/Nang_hang (5); Game/Match/Arsenal.cs CardRanks
A7: 6 | B7: =Nang_hang!$C$7 | C7: =SUMIFS(Nang_hang!$C$2:$C$11,Nang_hang!$B$2:$B$11,"<="&Nang_hang!$B$7) | D7: 1450 | E7: =SUMIFS(Nang_hang!$D$2:$D$11,Nang_hang!$B$2:$B$11,"<="&Nang_hang!$B$7) | F7: 46 | G7: =CEILING($C$7/Meta_kinh_te_tran!$G$9,1) | H7: =$G$7*Meta_kinh_te_tran!$F$9/60 | I7: =Nang_hang!$B$7<=Meta_kinh_te_nguon!$E$8 | J7: 04_che_do_kinh_te_ai/Nang_hang (6); Game/Match/Arsenal.cs CardRanks
A8: 7 | B8: =Nang_hang!$C$8 | C8: =SUMIFS(Nang_hang!$C$2:$C$11,Nang_hang!$B$2:$B$11,"<="&Nang_hang!$B$8) | D8: 2650 | E8: =SUMIFS(Nang_hang!$D$2:$D$11,Nang_hang!$B$2:$B$11,"<="&Nang_hang!$B$8) | F8: 76 | G8: =CEILING($C$8/Meta_kinh_te_tran!$G$9,1) | H8: =$G$8*Meta_kinh_te_tran!$F$9/60 | I8: =Nang_hang!$B$8<=Meta_kinh_te_nguon!$E$8 | J8: 04_che_do_kinh_te_ai/Nang_hang (7); Game/Match/Arsenal.cs CardRanks
A9: 8 | B9: =Nang_hang!$C$9 | C9: =SUMIFS(Nang_hang!$C$2:$C$11,Nang_hang!$B$2:$B$11,"<="&Nang_hang!$B$9) | D9: 4650 | E9: =SUMIFS(Nang_hang!$D$2:$D$11,Nang_hang!$B$2:$B$11,"<="&Nang_hang!$B$9) | F9: 121 | G9: =CEILING($C$9/Meta_kinh_te_tran!$G$9,1) | H9: =$G$9*Meta_kinh_te_tran!$F$9/60 | I9: =Nang_hang!$B$9<=Meta_kinh_te_nguon!$E$8 | J9: 04_che_do_kinh_te_ai/Nang_hang (8); Game/Match/Arsenal.cs CardRanks
A10: 9 | B10: =Nang_hang!$C$10 | C10: =SUMIFS(Nang_hang!$C$2:$C$11,Nang_hang!$B$2:$B$11,"<="&Nang_hang!$B$10) | D10: 7850 | E10: =SUMIFS(Nang_hang!$D$2:$D$11,Nang_hang!$B$2:$B$11,"<="&Nang_hang!$B$10) | F10: 186 | G10: =CEILING($C$10/Meta_kinh_te_tran!$G$9,1) | H10: =$G$10*Meta_kinh_te_tran!$F$9/60 | I10: =Nang_hang!$B$10<=Meta_kinh_te_nguon!$E$8 | J10: 04_che_do_kinh_te_ai/Nang_hang (9); Game/Match/Arsenal.cs CardRanks
A11: 10 | B11: =Nang_hang!$C$11 | C11: =SUMIFS(Nang_hang!$C$2:$C$11,Nang_hang!$B$2:$B$11,"<="&Nang_hang!$B$11) | D11: 12850 | E11: =SUMIFS(Nang_hang!$D$2:$D$11,Nang_hang!$B$2:$B$11,"<="&Nang_hang!$B$11) | F11: 276 | G11: =CEILING($C$11/Meta_kinh_te_tran!$G$9,1) | H11: =$G$11*Meta_kinh_te_tran!$F$9/60 | I11: =Nang_hang!$B$11<=Meta_kinh_te_nguon!$E$8 | J11: 04_che_do_kinh_te_ai/Nang_hang (10); Game/Match/Arsenal.cs CardRanks

Sheet Cai_dat_mac_dinh
A1: id | B1: gia_tri | C1: kieu | D1: nguon | E1: raw_json
A2: aiHints | B2: TRUE | C2: bool | D2: game.json balancePack.defaultSettings
A3: autoDeploy | B3: TRUE | C3: bool | D3: game.json balancePack.defaultSettings
A4: autoStrike | B4: TRUE | C4: bool | D4: game.json balancePack.defaultSettings
A5: batterySaver | B5: 2 | C5: int | D5: game.json balancePack.defaultSettings
A6: brightness | B6: 100 | C6: int | D6: game.json balancePack.defaultSettings
A7: cameraSpeed | B7: 1 | C7: int | D7: game.json balancePack.defaultSettings
A8: cinematicMoments | B8: TRUE | C8: bool | D8: game.json balancePack.defaultSettings
A9: colorBlind | B9: FALSE | C9: bool | D9: game.json balancePack.defaultSettings
A10: compactHud | B10: TRUE | C10: bool | D10: game.json balancePack.defaultSettings
A11: dialogue | B11: Full | C11: text | D11: game.json balancePack.defaultSettings
A12: dialogueVolume | B12: 1 | C12: int | D12: game.json balancePack.defaultSettings
A13: effectsVolume | B13: 1 | C13: int | D13: game.json balancePack.defaultSettings
A14: graphics | B14: Auto | C14: text | D14: game.json balancePack.defaultSettings
A15: haptics | B15: TRUE | C15: bool | D15: game.json balancePack.defaultSettings
A16: language | B16: Auto | C16: text | D16: game.json balancePack.defaultSettings
A17: musicVolume | B17: 0.7 | C17: float | D17: game.json balancePack.defaultSettings
A18: screenShake | B18: 2 | C18: int | D18: game.json balancePack.defaultSettings
A19: showCombatNumbers | B19: FALSE | C19: bool | D19: game.json balancePack.defaultSettings
A20: showFps | B20: FALSE | C20: bool | D20: game.json balancePack.defaultSettings
A21: textSize | B21: Normal | C21: text | D21: game.json balancePack.defaultSettings
A22: uiSize | B22: 1 | C22: int | D22: game.json balancePack.defaultSettings
A23: volume | B23: 0.8 | C23: float | D23: game.json balancePack.defaultSettings

Sheet Mutator_tuan
A1: id | B1: trang_thai | C1: ghi_chu | D1: nguon | E1: raw_json
A2: can_doc_ma | B2: XEM_05 | C2: dữ liệu ở 04_che_do_kinh_te_ai/Mutator (operations.json, cột class: pressure / rule); luật chọn theo tuần (MB_FINAL F3, OperationsData.Weekly): seed = năm x 100 + tuần ISO; 2 mutator khác nhau không vi phạm excludes, một mutator tăng áp lực + một mutator đổi luật, mỗi nhóm theo thứ tự id ổn định; nhóm không đủ thì lấy cặp hợp lệ đầu tiên theo thứ tự id; cùng tuần + cùng phiên bản dữ liệu -> cùng cặp | D2: Assets/MachineBrigade/Resources/Data/operations.json

Sheet Thu_hang
A1: id | B1: trang_thai | C1: ghi_chu | D1: nguon | E1: raw_json
A2: can_doc_ma | B2: XEM_05 | C2: thứ tự xếp hạng ở 04_che_do_kinh_te_ai/Vo_han (matchRules.leaderboards); không có bảng xếp hạng trực tuyến | D2: Assets/MachineBrigade/Resources/Data/balance.json: matchRules.leaderboards

Sheet Thuong
A1: id | B1: trang_thai | C1: ghi_chu | D1: nguon | E1: raw_json
A2: can_doc_ma | B2: XEM_Meta_kinh_te_nguon | C2: xu / XP / bản thiết kế mỗi nhiệm vụ: 05_chien_dich/Nhiem_vu (coins, xp, prints, rarePrints); công thức thưởng trận nhanh / Sinh tồn / nhiệm vụ của Rewards.cs: Meta_kinh_te_nguon, Meta_kinh_te_tran (lớp B,) | D2: Assets/MachineBrigade/Scripts/Game/Match/Rewards.cs

Sheet Meta_tham_chieu
A1: id | B1: entity_id | C1: ten_hien_thi | D1: loai_tham_chieu | E1: ten_mau_that | F1: quoc_gia | G1: nam_dua_vao_su_dung | H1: ten_game | I1: co_che_game | J1: ten_phim_truyen | K1: diem_giong | L1: diem_khac_co_chu_dich | M1: ly_do_khac | N1: cam_giac_khac_khi_choi | O1: do_tin_cay | P1: nguon_id | Q1: ly_do | R1: ghi_chu_ban_quyen | S1: sheet_lien_quan | T1: nguon | U1: raw_json
A2: Cai_dat_mac_dinh | B2: Cai_dat_mac_dinh | C2: Cài đặt mặc định | D2: NEED_SOURCE | H2: NEED_SOURCE | O2: NEED_SOURCE | Q2: repo không ghi game tham khảo cho cơ chế này | R2: chỉ ở mức ý tưởng và thông số (sự kiện); không dùng tên, logo, văn bản, ảnh hay mô hình có bản quyền; tên và phù hiệu quốc gia thật không hiện cho người chơi | S2: Cai_dat_mac_dinh | T2: spec 12.2 (11): Cai_dat_mac_dinh
A3: Cua_hang | B3: Cua_hang | C3: Cửa hàng | D3: NEED_SOURCE | H3: NEED_SOURCE | O3: NEED_SOURCE | Q3: repo không ghi game tham khảo cho cơ chế này | R3: chỉ ở mức ý tưởng và thông số (sự kiện); không dùng tên, logo, văn bản, ảnh hay mô hình có bản quyền; tên và phù hiệu quốc gia thật không hiện cho người chơi | S3: Cua_hang | T3: spec 12.2 (11): Cua_hang
A4: Hom_do | B4: Hom_do | C4: Hòm đồ và tỷ lệ rơi | D4: NEED_SOURCE | H4: NEED_SOURCE | O4: NEED_SOURCE | Q4: repo không ghi game tham khảo cho cơ chế này | R4: chỉ ở mức ý tưởng và thông số (sự kiện); không dùng tên, logo, văn bản, ảnh hay mô hình có bản quyền; tên và phù hiệu quốc gia thật không hiện cho người chơi | S4: Hom_do | T4: spec 12.2 (11): Hom_do
A5: Huong_dan | B5: Huong_dan | C5: Hướng dẫn người chơi | D5: NEED_SOURCE | H5: NEED_SOURCE | O5: NEED_SOURCE | Q5: repo không ghi game tham khảo cho cơ chế này | R5: chỉ ở mức ý tưởng và thông số (sự kiện); không dùng tên, logo, văn bản, ảnh hay mô hình có bản quyền; tên và phù hiệu quốc gia thật không hiện cho người chơi | S5: Huong_dan | T5: spec 12.2 (11): Huong_dan
A6: Mo_khoa | B6: Mo_khoa | C6: Mở khóa | D6: NEED_SOURCE | H6: NEED_SOURCE | O6: NEED_SOURCE | Q6: repo không ghi game tham khảo cho cơ chế này | R6: chỉ ở mức ý tưởng và thông số (sự kiện); không dùng tên, logo, văn bản, ảnh hay mô hình có bản quyền; tên và phù hiệu quốc gia thật không hiện cho người chơi | S6: Mo_khoa | T6: spec 12.2 (11): Mo_khoa
A7: Mutator_tuan | B7: Mutator_tuan | C7: Mutator tuần | D7: NEED_SOURCE | H7: NEED_SOURCE | O7: NEED_SOURCE | Q7: repo không ghi game tham khảo cho cơ chế này | R7: chỉ ở mức ý tưởng và thông số (sự kiện); không dùng tên, logo, văn bản, ảnh hay mô hình có bản quyền; tên và phù hiệu quốc gia thật không hiện cho người chơi | S7: Mutator_tuan | T7: spec 12.2 (11): Mutator_tuan
A8: Nang_hang | B8: Nang_hang | C8: Giá nâng hạng | D8: NEED_SOURCE | H8: NEED_SOURCE | O8: NEED_SOURCE | Q8: repo không ghi game tham khảo cho cơ chế này | R8: chỉ ở mức ý tưởng và thông số (sự kiện); không dùng tên, logo, văn bản, ảnh hay mô hình có bản quyền; tên và phù hiệu quốc gia thật không hiện cho người chơi | S8: Nang_hang | T8: spec 12.2 (11): Nang_hang
A9: Nhiem_vu_ngay | B9: Nhiem_vu_ngay | C9: Nhiệm vụ ngày | D9: NEED_SOURCE | H9: NEED_SOURCE | O9: NEED_SOURCE | Q9: repo không ghi game tham khảo cho cơ chế này | R9: chỉ ở mức ý tưởng và thông số (sự kiện); không dùng tên, logo, văn bản, ảnh hay mô hình có bản quyền; tên và phù hiệu quốc gia thật không hiện cho người chơi | S9: Nhiem_vu_ngay | T9: spec 12.2 (11): Nhiem_vu_ngay
A10: Skin | B10: Skin | C10: Skin | D10: NEED_SOURCE | H10: NEED_SOURCE | O10: NEED_SOURCE | Q10: repo không ghi game tham khảo cho cơ chế này | R10: chỉ ở mức ý tưởng và thông số (sự kiện); không dùng tên, logo, văn bản, ảnh hay mô hình có bản quyền; tên và phù hiệu quốc gia thật không hiện cho người chơi | S10: Skin | T10: spec 12.2 (11): Skin
A11: Thanh_tuu | B11: Thanh_tuu | C11: Thành tựu | D11: NEED_SOURCE | H11: NEED_SOURCE | O11: NEED_SOURCE | Q11: repo không ghi game tham khảo cho cơ chế này | R11: chỉ ở mức ý tưởng và thông số (sự kiện); không dùng tên, logo, văn bản, ảnh hay mô hình có bản quyền; tên và phù hiệu quốc gia thật không hiện cho người chơi | S11: Thanh_tuu | T11: spec 12.2 (11): Thanh_tuu
A12: Thu_hang | B12: Thu_hang | C12: Thứ hạng | D12: NEED_SOURCE | H12: NEED_SOURCE | O12: NEED_SOURCE | Q12: repo không ghi game tham khảo cho cơ chế này | R12: chỉ ở mức ý tưởng và thông số (sự kiện); không dùng tên, logo, văn bản, ảnh hay mô hình có bản quyền; tên và phù hiệu quốc gia thật không hiện cho người chơi | S12: Thu_hang | T12: spec 12.2 (11): Thu_hang
A13: Thuong | B13: Thuong | C13: Thưởng | D13: NEED_SOURCE | H13: NEED_SOURCE | O13: NEED_SOURCE | Q13: repo không ghi game tham khảo cho cơ chế này | R13: chỉ ở mức ý tưởng và thông số (sự kiện); không dùng tên, logo, văn bản, ảnh hay mô hình có bản quyền; tên và phù hiệu quốc gia thật không hiện cho người chơi | S13: Thuong | T13: spec 12.2 (11): Thuong
A14: Trang_bi_hang | B14: Trang_bi_hang | C14: Trang bị theo độ hiếm | D14: NEED_SOURCE | H14: NEED_SOURCE | O14: NEED_SOURCE | Q14: repo không ghi game tham khảo cho cơ chế này | R14: chỉ ở mức ý tưởng và thông số (sự kiện); không dùng tên, logo, văn bản, ảnh hay mô hình có bản quyền; tên và phù hiệu quốc gia thật không hiện cho người chơi | S14: Trang_bi_hang | T14: spec 12.2 (11): Trang_bi_hang

Sheet Hang_so_che_do
A1: id | B1: nhom | C1: khoa | D1: gia_tri_so | E1: gia_tri_chu | F1: don_vi | G1: nhom_quet | H1: linh_vuc_ma_cu | I1: ma_nguon | J1: nguon | K1: raw_json
A2: modes.baseStrengthRules.waveScaleExponent | B2: baseStrengthRules | C2: waveScaleExponent | D2: 0.75 | F2: x | G2: khac | H2: 04 | I2: BaseStrength.WaveScale | J2: Assets/MachineBrigade/Resources/Data/tunables.json: modes.baseStrengthRules.waveScaleExponent | K2: {"value":0.75,"unit":"x","kind":"khac","linh_vuc":"04","code":"BaseStrength.WaveScale"}
A3: modes.baseStrengthRules.waveScaleMax | B3: baseStrengthRules | C3: waveScaleMax | D3: 2.5 | F3: x | G3: tran | H3: 04 | I3: BaseStrength.WaveScale | J3: Assets/MachineBrigade/Resources/Data/tunables.json: modes.baseStrengthRules.waveScaleMax | K3: {"value":2.5,"unit":"x","kind":"tran","linh_vuc":"04","code":"BaseStrength.WaveScale"}
A4: modes.baseStrengthRules.waveScaleMin | B4: baseStrengthRules | C4: waveScaleMin | D4: 0.75 | F4: x | G4: tran | H4: 04 | I4: BaseStrength.WaveScale | J4: Assets/MachineBrigade/Resources/Data/tunables.json: modes.baseStrengthRules.waveScaleMin | K4: {"value":0.75,"unit":"x","kind":"tran","linh_vuc":"04","code":"BaseStrength.WaveScale"}
A5: modes.battleEvents.claimReach | B5: battleEvents | C5: claimReach | D5: 6 | F5: m | G5: ban_kinh | H5: 05 | I5: BattleEvents.ClaimReach | J5: Assets/MachineBrigade/Resources/Data/tunables.json: modes.battleEvents.claimReach | K5: {"value":6.0,"unit":"m","kind":"ban_kinh","linh_vuc":"05","code":"BattleEvents.ClaimReach"}
A6: modes.battleEvents.claimSeconds | B6: battleEvents | C6: claimSeconds | D6: 2 | F6: s | G6: thoi_gian | H6: 05 | I6: BattleEvents.ClaimSeconds | J6: Assets/MachineBrigade/Resources/Data/tunables.json: modes.battleEvents.claimSeconds | K6: {"value":2.0,"unit":"s","kind":"thoi_gian","linh_vuc":"05","code":"BattleEvents.ClaimSeconds"}
A7: modes.battleEvents.crateCp | B7: battleEvents | C7: crateCp | D7: 10 | F7: CP | G7: thuong | H7: 05 | I7: BattleEvents.CrateCp | J7: Assets/MachineBrigade/Resources/Data/tunables.json: modes.battleEvents.crateCp | K7: {"value":10.0,"unit":"CP","kind":"thuong","linh_vuc":"05","code":"BattleEvents.CrateCp"}
A8: modes.battleEvents.crateFall | B8: battleEvents | C8: crateFall | D8: 15 | F8: s | G8: thoi_gian | H8: 05 | I8: BattleEvents.CrateFall | J8: Assets/MachineBrigade/Resources/Data/tunables.json: modes.battleEvents.crateFall | K8: {"value":15.0,"unit":"s","kind":"thoi_gian","linh_vuc":"05","code":"BattleEvents.CrateFall"}
A9: modes.battleEvents.crateLife | B9: battleEvents | C9: crateLife | D9: 50 | F9: s | G9: thoi_gian | H9: 05 | I9: BattleEvents.CrateLife | J9: Assets/MachineBrigade/Resources/Data/tunables.json: modes.battleEvents.crateLife | K9: {"value":50.0,"unit":"s","kind":"thoi_gian","linh_vuc":"05","code":"BattleEvents.CrateLife"}
A10: modes.battleEvents.crateRepair | B10: battleEvents | C10: crateRepair | D10: 0.3 | F10: share | G10: thuong | H10: 05 | I10: BattleEvents.CrateRepair | J10: Assets/MachineBrigade/Resources/Data/tunables.json: modes.battleEvents.crateRepair | K10: {"value":0.3,"unit":"share","kind":"thuong","linh_vuc":"05","code":"BattleEvents.CrateRepair"}
A11: modes.defendWaves.endlessCompound | B11: defendWaves | C11: endlessCompound | D11: 0.06 | F11: share/wave | G11: tan_suat | H11: 05 | I11: SiegeMode.DefendWaveCompound | J11: Assets/MachineBrigade/Resources/Data/tunables.json: modes.defendWaves.endlessCompound | K11: {"value":0.06,"unit":"share/wave","kind":"tan_suat","linh_vuc":"05","code":"SiegeMode.DefendWaveCompound"}
A12: modes.defendWaves.endlessGrowth | B12: defendWaves | C12: endlessGrowth | D12: 1.2 | F12: count/wave | G12: tan_suat | H12: 05 | I12: SiegeMode.DefendWaveGrowth | J12: Assets/MachineBrigade/Resources/Data/tunables.json: modes.defendWaves.endlessGrowth | K12: {"value":1.2,"unit":"count/wave","kind":"tan_suat","linh_vuc":"05","code":"SiegeMode.DefendWaveGrowth"}
A13: modes.defendWaves.endlessStartEasy | B13: defendWaves | C13: endlessStartEasy | D13: 4 | F13: count | G13: gioi_han_thuc_the | H13: 05 | I13: SiegeMode.DefendWaveStart | J13: Assets/MachineBrigade/Resources/Data/tunables.json: modes.defendWaves.endlessStartEasy | K13: {"value":4,"unit":"count","kind":"gioi_han_thuc_the","linh_vuc":"05","code":"SiegeMode.DefendWaveStart"}
... A38: modes.economySystem.rollIn | B38: economySystem | C38: rollIn | D38: 12 | F38: m | G38: khac | H38: 05 | I38: EconomySystem.RollIn | J38: Assets/MachineBrigade/Resources/Data/tunables.json: modes.economySystem.rollIn | K38: {"value":12.0,"unit":"m","kind":"khac","linh_vuc":"05","code":"EconomySystem.RollIn"}
A39: modes.endlessRules.bossBadges | B39: endlessRules | C39: bossBadges | E39: 5;10 | F39: bosses | G39: gioi_han_thuc_the | H39: 05 | I39: EndlessRules.BossBadges | J39: Assets/MachineBrigade/Resources/Data/tunables.json: modes.endlessRules.bossBadges | K39: {"value":[5,10],"unit":"bosses","kind":"gioi_han_thuc_the","linh_vuc":"05","code":"EndlessRules.BossBadges"}
A40: modes.endlessRules.bossCoins | B40: endlessRules | C40: bossCoins | D40: 60 | F40: coins | G40: thuong | H40: 05 | I40: EndlessRules.BossCoins | J40: Assets/MachineBrigade/Resources/Data/tunables.json: modes.endlessRules.bossCoins | K40: {"value":60,"unit":"coins","kind":"thuong","linh_vuc":"05","code":"EndlessRules.BossCoins"}
A41: modes.endlessRules.bossEvery | B41: endlessRules | C41: bossEvery | D41: 10 | F41: waves | G41: thoi_gian | H41: 05 | I41: EndlessRules.BossEvery | J41: Assets/MachineBrigade/Resources/Data/tunables.json: modes.endlessRules.bossEvery | K41: {"value":10,"unit":"waves","kind":"thoi_gian","linh_vuc":"05","code":"EndlessRules.BossEvery"}
A42: modes.endlessRules.coinDecay | B42: endlessRules | C42: coinDecay | D42: 0.9 | F42: x | G42: thuong | H42: 05 | I42: EndlessRules.CoinDecay | J42: Assets/MachineBrigade/Resources/Data/tunables.json: modes.endlessRules.coinDecay | K42: {"value":0.9,"unit":"x","kind":"thuong","linh_vuc":"05","code":"EndlessRules.CoinDecay"}
A43: modes.endlessRules.dailyCap | B43: endlessRules | C43: dailyCap | D43: 600 | F43: coins | G43: tran | H43: 05 | I43: EndlessRules.DailyCap | J43: Assets/MachineBrigade/Resources/Data/tunables.json: modes.endlessRules.dailyCap | K43: {"value":600,"unit":"coins","kind":"tran","linh_vuc":"05","code":"EndlessRules.DailyCap"}
A44: modes.endlessRules.defendFiniteWaves | B44: endlessRules | C44: defendFiniteWaves | D44: 10 | F44: waves | G44: gioi_han_thuc_the | H44: 05 | I44: EndlessRules.DefendFiniteWaves | J44: Assets/MachineBrigade/Resources/Data/tunables.json: modes.endlessRules.defendFiniteWaves | K44: {"value":10,"unit":"waves","kind":"gioi_han_thuc_the","linh_vuc":"05","code":"EndlessRules.DefendFiniteWaves"}
A45: modes.endlessRules.enemyPerBoss | B45: endlessRules | C45: enemyPerBoss | D45: 0.08 | F45: share/step | G45: khac | H45: 05 | I45: EndlessRules.EnemyPerBoss | J45: Assets/MachineBrigade/Resources/Data/tunables.json: modes.endlessRules.enemyPerBoss | K45: {"value":0.08,"unit":"share/step","kind":"khac","linh_vuc":"05","code":"EndlessRules.EnemyPerBoss"}
A46: modes.endlessRules.enemyPerWave | B46: endlessRules | C46: enemyPerWave | D46: 0.04 | F46: share/wave | G46: khac | H46: 05 | I46: EndlessRules.EnemyPerWave | J46: Assets/MachineBrigade/Resources/Data/tunables.json: modes.endlessRules.enemyPerWave | K46: {"value":0.04,"unit":"share/wave","kind":"khac","linh_vuc":"05","code":"EndlessRules.EnemyPerWave"}
A47: modes.endlessRules.miniBossEvery | B47: endlessRules | C47: miniBossEvery | D47: 5 | F47: waves | G47: thoi_gian | H47: 05 | I47: EndlessRules.MiniBossEvery | J47: Assets/MachineBrigade/Resources/Data/tunables.json: modes.endlessRules.miniBossEvery | K47: {"value":5,"unit":"waves","kind":"thoi_gian","linh_vuc":"05","code":"EndlessRules.MiniBossEvery"}
A48: modes.endlessRules.playerMax | B48: endlessRules | C48: playerMax | D48: 0.3 | F48: share | G48: tran | H48: 05 | I48: EndlessRules.PlayerMax | J48: Assets/MachineBrigade/Resources/Data/tunables.json: modes.endlessRules.playerMax | K48: {"value":0.3,"unit":"share","kind":"tran","linh_vuc":"05","code":"EndlessRules.PlayerMax"}
A49: modes.endlessRules.playerPerWave | B49: endlessRules | C49: playerPerWave | D49: 0.02 | F49: share/wave | G49: khac | H49: 05 | I49: EndlessRules.PlayerPerWave | J49: Assets/MachineBrigade/Resources/Data/tunables.json: modes.endlessRules.playerPerWave | K49: {"value":0.02,"unit":"share/wave","kind":"khac","linh_vuc":"05","code":"EndlessRules.PlayerPerWave"}
A50: modes.endlessRules.survivalWaves | B50: endlessRules | C50: survivalWaves | D50: 10 | F50: waves | G50: gioi_han_thuc_the | H50: 05 | I50: EndlessRules.SurvivalWaves | J50: Assets/MachineBrigade/Resources/Data/tunables.json: modes.endlessRules.survivalWaves | K50: {"value":10,"unit":"waves","kind":"gioi_han_thuc_the","linh_vuc":"05","code":"EndlessRules.SurvivalWaves"}
A51: modes.endlessRules.waveBadges | B51: endlessRules | C51: waveBadges | E51: 10;20;30 | F51: waves | G51: gioi_han_thuc_the | H51: 05 | I51: EndlessRules.WaveBadges | J51: Assets/MachineBrigade/Resources/Data/tunables.json: modes.endlessRules.waveBadges | K51: {"value":[10,20,30],"unit":"waves","kind":"gioi_han_thuc_the","linh_vuc":"05","code":"EndlessRules.WaveBadges"}
A52: modes.endlessRules.waveCoins | B52: endlessRules | C52: waveCoins | D52: 18 | F52: coins | G52: thuong | H52: 05 | I52: EndlessRules.WaveCoins | J52: Assets/MachineBrigade/Resources/Data/tunables.json: modes.endlessRules.waveCoins | K52: {"value":18,"unit":"coins","kind":"thuong","linh_vuc":"05","code":"EndlessRules.WaveCoins"}
A53: modes.holdFlags.laterEventsQuickModes | B53: holdFlags | C53: laterEventsQuickModes | D53: FALSE | F53: flag | G53: khac | H53: 07 | I53: off (no code path when true) | J53: Assets/MachineBrigade/Resources/Data/tunables.json: modes.holdFlags.laterEventsQuickModes | K53: {"value":false,"unit":"flag","kind":"khac","linh_vuc":"07","code":"off (no code path when true)"}
A54: modes.holdFlags.laterNeutrals | B54: holdFlags | C54: laterNeutrals | D54: FALSE | F54: flag | G54: khac | H54: 05 | I54: off (no code path when true) | J54: Assets/MachineBrigade/Resources/Data/tunables.json: modes.holdFlags.laterNeutrals | K54: {"value":false,"unit":"flag","kind":"khac","linh_vuc":"05","code":"off (no code path when true)"}
A55: modes.holdFlags.outpostForwardDropsQuickModes | B55: holdFlags | C55: outpostForwardDropsQuickModes | D55: FALSE | F55: flag | G55: khac | H55: 04 | I55: off (no code path when true) | J55: Assets/MachineBrigade/Resources/Data/tunables.json: modes.holdFlags.outpostForwardDropsQuickModes | K55: {"value":false,"unit":"flag","kind":"khac","linh_vuc":"04","code":"off (no code path when true)"}
A56: modes.neutralSystem.interval | B56: neutralSystem | C56: interval | D56: 0.5 | F56: s | G56: thoi_gian | H56: 05 | I56: NeutralSystem.Interval | J56: Assets/MachineBrigade/Resources/Data/tunables.json: modes.neutralSystem.interval | K56: {"value":0.5,"unit":"s","kind":"thoi_gian","linh_vuc":"05","code":"NeutralSystem.Interval"}
