Workbook

Sheet Chuong
A1: id | B1: maps | C1: main | D1: minis | E1: general | F1: tep_thoai_chuong | G1: tep_thoai | H1: so_cau_thoai | I1: act | J1: comic | K1: interlude | L1: number | M1: nguon | N1: raw_json
A2: 1 | B2: landingbeach;greenvale;ashfield | C2: fortress_bastion | D2: bastion_mk0 | E2: brandt | F2: 1 | G2: ch01.json | H2: 82 | I2: 1 | J2: comic.1 | L2: 1 | M2: Assets/MachineBrigade/Resources/Data/campaign.json: chapters[0] | N2: {"number":1,"act":1,"maps":["landingbeach","greenvale","ashfield"],"general":"brandt","main":"fortress_bastion","minis":["bastion_mk0"],"comic":"comic.1"}
A3: 2 | B3: dunebreak;redrock | C3: behemoth | D3: behemoth_inferno | E3: varga | F3: 2 | G3: ch02.json | H3: 108 | I3: 1 | J3: comic.2 | L3: 2 | M3: Assets/MachineBrigade/Resources/Data/campaign.json: chapters[1] | N3: {"number":2,"act":1,"maps":["dunebreak","redrock"],"general":"varga","main":"behemoth","minis":["behemoth_inferno"],"comic":"comic.2"}
A4: 3 | B4: whiteout;frostpeak | C4: mobile_fortress | D4: mega_gunship;fenrir | E4: orlov | F4: 3 | G4: ch03.json | H4: 111 | I4: 1 | J4: comic.3 | L4: 3 | M4: Assets/MachineBrigade/Resources/Data/campaign.json: chapters[2] | N4: {"number":3,"act":1,"maps":["whiteout","frostpeak"],"general":"orlov","main":"mobile_fortress","minis":["mega_gunship","fenrir"],"comic":"comic.3"}
A5: 4 | B5: rustyard;ironport;lighthousebay | C5: leviathan | D5: behemoth_tempest;armored_train;scylla | E5: kessler | F5: 4 | G5: ch04.json | H5: 164 | I5: 2 | J5: comic.4 | L5: 4 | M5: Assets/MachineBrigade/Resources/Data/campaign.json: chapters[4] | N5: {"number":4,"act":2,"maps":["rustyard","ironport","lighthousebay"],"general":"kessler","main":"leviathan","minis":["behemoth_tempest","armored_train","scylla"],"comic":"comic.4"}
A6: 5 | B6: junglepass;emberridge | C6: drone_mothership | D6: locust | E6: sen | F6: 5 | G6: ch05.json | H6: 121 | I6: 2 | J6: comic.5 | L6: 5 | M6: Assets/MachineBrigade/Resources/Data/campaign.json: chapters[5] | N6: {"number":5,"act":2,"maps":["junglepass","emberridge"],"general":"sen","main":"drone_mothership","minis":["locust"],"comic":"comic.5"}
A7: 6 | B7: ashfield;whiteout;greenvale;landingbeach;hydrodam | C7: moloch | D7: landing_hovercraft;behemoth_mk2 | E7: varga | F7: 6 | G7: ch06.json | H7: 153 | I7: 2 | J7: comic.6 | L7: 6 | M7: Assets/MachineBrigade/Resources/Data/campaign.json: chapters[6] | N7: {"number":6,"act":2,"maps":["ashfield","whiteout","greenvale","landingbeach","hydrodam"],"general":"varga","main":"moloch","minis":["landing_hovercraft","behemoth_mk2"],"comic":"comic.6"}
A8: 7 | B8: metrocity;veyra_old_quarter;capital | C8: nuke_train | D8: behemoth_mk2;behemoth_inferno;armored_train | E8: hung | F8: 7 | G8: ch07.json | H8: 149 | I8: 3 | J8: comic.7 | L8: 7 | M8: Assets/MachineBrigade/Resources/Data/campaign.json: chapters[8] | N8: {"number":7,"act":3,"maps":["metrocity","veyra_old_quarter","capital"],"general":"hung","main":"nuke_train","minis":["behemoth_mk2","behemoth_inferno","armored_train"],"comic":"comic.7"}
A9: 8 | B9: redrock;openpit;hydrodam;dunebreak | C9: moloch | D9: ixion;earth_borer | E9: hung | F9: 8 | G9: ch08.json | H9: 129 | I9: 3 | J9: comic.8 | L9: 8 | M9: Assets/MachineBrigade/Resources/Data/campaign.json: chapters[9] | N9: {"number":8,"act":3,"maps":["redrock","openpit","hydrodam","dunebreak"],"general":"hung","main":"moloch","minis":["ixion","earth_borer"],"comic":"comic.8"}
A10: 9 | B10: ironport;landingbeach;lighthousebay;coralisles | C10: typhon | D10: landing_hovercraft;scylla | E10: hung | F10: 9 | G10: ch09.json | H10: 131 | I10: 3 | J10: comic.9 | L10: 9 | M10: Assets/MachineBrigade/Resources/Data/campaign.json: chapters[10] | N10: {"number":9,"act":3,"maps":["ironport","landingbeach","lighthousebay","coralisles"],"general":"hung","main":"typhon","minis":["landing_hovercraft","scylla"],"comic":"comic.9"}
A11: 10 | B11: frostpeak;skyhold;whiteout | C11: command_airship | D11: icarus_mk0;argus;mega_gunship | E11: quaden | F11: 10 | G11: ch10.json | H11: 134 | I11: 4 | J11: comic.10 | L11: 10 | M11: Assets/MachineBrigade/Resources/Data/campaign.json: chapters[12] | N11: {"number":10,"act":4,"maps":["frostpeak","skyhold","whiteout"],"general":"quaden","main":"command_airship","minis":["icarus_mk0","argus","mega_gunship"],"comic":"comic.10"}
A12: 11 | B12: rustyard;skyhold;frostpeak;orbitalgate | C12: daedalus | D12: monster;locust | E12: aurel | F12: 11 | G12: ch11.json | H12: 120 | I12: 4 | J12: comic.11 | L12: 11 | M12: Assets/MachineBrigade/Resources/Data/campaign.json: chapters[13] | N12: {"number":11,"act":4,"maps":["rustyard","skyhold","frostpeak","orbitalgate"],"general":"aurel","main":"daedalus","minis":["monster","locust"],"comic":"comic.11"}
A13: 12 | B13: launchsite;saltflat;dunebreak;lighthousebay | C13: silver_bug | D13: behemoth_mk2;scylla;locust | E13: aurel | F13: 12 | G13: ch12.json | H13: 93 | I13: 4 | J13: comic.12 | L13: 12 | M13: Assets/MachineBrigade/Resources/Data/campaign.json: chapters[14] | N13: {"number":12,"act":4,"maps":["launchsite","saltflat","dunebreak","lighthousebay"],"general":"aurel","main":"silver_bug","minis":["behemoth_mk2","scylla","locust"],"comic":"comic.12"}
A14: 13 | B14: foundry | D14: behemoth_mk0 | E14: varga | F14: 13 | G14: ch13.json | H14: 35 | I14: 1 | J14: comic.13 | K14: 1 | L14: 13 | M14: Assets/MachineBrigade/Resources/Data/campaign.json: chapters[3] | N14: {"number":13,"act":1,"interlude":1,"maps":["foundry"],"general":"varga","minis":["behemoth_mk0"],"comic":"comic.13"}
A15: 14 | B15: swamp;borderbridge | D15: locust | F15: 14 | G15: ch14.json | H15: 44 | I15: 2 | J15: comic.14 | K15: 2 | L15: 14 | M15: Assets/MachineBrigade/Resources/Data/campaign.json: chapters[7] | N15: {"number":14,"act":2,"interlude":2,"maps":["swamp","borderbridge"],"minis":["locust"],"comic":"comic.14"}
A16: 15 | B16: frostpeak;junglepass | D16: mega_gunship | E16: quaden | F16: 15 | G16: ch15.json | H16: 40 | I16: 3 | J16: comic.15 | K16: 3 | L16: 15 | M16: Assets/MachineBrigade/Resources/Data/campaign.json: chapters[11] | N16: {"number":15,"act":3,"interlude":3,"maps":["frostpeak","junglepass"],"general":"quaden","minis":["mega_gunship"],"comic":"comic.15"}

Sheet Nhiem_vu
A1: id | B1: chapter | C1: map | D1: general | E1: enemy_deck | F1: unlocks | G1: after | H1: boss_def | I1: nguoi_noi_chinh | J1: bo_bai_game | K1: so_cau_thoai | L1: trang_thai_kich_ban | M1: ally_heading_deg | N1: ally_hq | O1: ally_x_m | P1: ally_z_m | Q1: awaits | R1: boss_fallback | S1: boss_fallback_health | T1: boss_flee_at | U1: boss_heading_deg | V1: boss_health | W1: boss_name | X1: boss_route | Y1: boss_x_m | Z1: boss_z_m | AA1: branch | AB1: challenge_kind | AC1: challenge_value | AD1: coins | AE1: commander | AF1: convoy_count | AG1: convoy_def | AH1: convoy_heading_deg | AI1: convoy_health | AJ1: convoy_interval_s | AK1: convoy_needed | AL1: convoy_route | AM1: convoy_x_m | AN1: convoy_z_m | AO1: difficulty | AP1: enemy_ai | AQ1: enemy_base | AR1: enemy_cp | AS1: enemy_hq | AT1: enemy_income | AU1: enemy_owns | AV1: enemy_stance | AW1: goal | AX1: hold_seconds_s | AY1: hq_level | AZ1: kills_needed | BA1: launch_seconds_s | BB1: legacy | BC1: operation | BD1: option | BE1: outposts | BF1: play_area_max_x | BG1: play_area_max_z | BH1: play_area_min_x | BI1: play_area_min_z | BJ1: player_base | BK1: player_cap | BL1: player_cp | BM1: player_income | BN1: points | BO1: prints | BP1: protect_needed | BQ1: rare_prints | BR1: reinforcements | BS1: replay | BT1: reversed | BU1: set_piece | BV1: side | BW1: speaker | BX1: star_losses | BY1: star_time_s | BZ1: story_choice | CA1: survive_seconds_s | CB1: target_health | CC1: target_radius | CD1: target_x | CE1: target_z | CF1: targets | CG1: time_limit_s | CH1: tower_gear | CI1: variant | CJ1: waves_first | CK1: waves_grow | CL1: waves_interval_s | CM1: waves_max_alive | CN1: waves_max_size | CO1: waves_roster | CP1: waves_size | CQ1: waves_spawns | CR1: weather | CS1: xp | CT1: nguon | CU1: raw_json
A2: c1m01 | B2: 1 | C2: landingbeach | E2: scout_jeep;armored_car | F2: rocket_technical | I2: khai | J2: TRUE | K2: 8 | L2: co_kich_ban | AB2: Kills | AC2: 8 | AD2: 100 | AO2: Easy | AP2: commander | AR2: 8 | AT2: 0.45 | AV2: Defend | AW2: Capture | BL2: 22 | BM2: 1.3 | BN2: east;town | BO2: 1 | BR2: 0 | BU2: TRUE | BX2: 4 | BY2: 300 | CR2: Clear | CS2: 80 | CT2: Assets/MachineBrigade/Resources/Data/campaign.json: missions[0] | CU2: {"id":"c1m01","chapter":1,"map":"landingbeach","weather":"Clear","goal":"Capture","points":["east","town"],"reinforcements":0,"enemyAi":"commander","enemyStance":"Defend","difficulty":"Easy","enemyCp":8,"enemyIncome":0.45,"enemyDeck":["scout_jeep","armored_car"],"playerCp":22,"playerIncome":1.3,"tips":[{"at":2,"key":"tip.auto"},{"at":9,"key":"tip.deploy"},{"at":16,"key":"tip.points"},{"at":24,"key":"tip.strike"},{"at":33,"key":"tip.select"},{"at":43,"key":"tip.counters"},{"at":54,"key":"tip.items"}],"starTime":300,"starLosses":4,"challenge":{"kind":"Kills","value":8},"radio":[{"key":"radio.khai.c1m01.1","on":"Start"},{"key":"radio.dieuhau.c1m01.2","on":"Capture","arg":"east"},{"key":"radio.khai.c1m01.3","on":"Win"}],"unlocks":["rocket_technical"],"setPiece":true,"missionEvents":[{"id":"landing_assault","params":{"size":4}},"accord_landing",{"id":"enemy_barrage","trigger":{"at":90,"every":80,"times":4},"params":{"salvos":2,"radius":16}},"tide_turn"],"fixedDeck":{"vehicleIds":["recoilless_jeep","light_tank","armored_car","rocket_technical","mortar_carrier","ifv","main_battle_tank","scout_jeep"],"supportIds":["repair_drop","artillery_barrage"],"placedAllies":[],"loanedCards":["recoilless_jeep","light_tank","rocket_technical","mortar_carrier"],"specialRules":["noBaseStart","beachLanding","coastalGuns"],"status":"MAKE_FIRST"},"navStates":[{"id":"shoal","initial":"low","states":[{"name":"low"},{"name":"high","blocks":[{"x":66,"z":-130,"w":152,"d":12}]}]}],"coins":100,"xp":80,"prints":1}
A3: c1m02 | B3: 1 | C3: landingbeach | E3: scout_jeep;armored_car;light_tank;rocket_technical;ifv | F3: mortar_carrier | I3: linh | J3: FALSE | K3: 7 | L3: co_kich_ban | AB3: NoStrikes | AD3: 105 | AO3: Easy | AP3: commander | AR3: 10 | AT3: 0.7 | AV3: Defend | AW3: Destroy | BL3: 20 | BM3: 1.3 | BO3: 1 | BR3: 1 | BY3: 420 | CB3: 3 | CF3: radar_station_prop | CG3: 900 | CR3: Overcast | CS3: 85 | CT3: Assets/MachineBrigade/Resources/Data/campaign.json: missions[1] | CU3: {"id":"c1m02","chapter":1,"map":"landingbeach","weather":"Overcast","goal":"Destroy","targets":["radar_station_prop"],"targetHealth":3,"timeLimit":900,"reinforcements":1,"enemyAi":"commander","enemyStance":"Defend","difficulty":"Easy","enemyCp":10,"enemyIncome":0.7,"enemyDeck":["scout_jeep","armored_car","light_tank","rocket_technical","ifv"],"playerCp":20,"playerIncome":1.3,"starTime":420,"challenge":{"kind":"NoStrikes"},"radio":[{"key":"radio.linh.c1m02.1","on":"Start"},{"key":"radio.khai.c1m02.2","on":"Win"}],"unlocks":["mortar_carrier"],"missionEvents":["landing_assault","nadia_intel","rain_sets_in"],"coins":105,"xp":85,"prints":1}
A4: c1m03 | B4: 1 | C4: greenvale | E4: scout_jeep;armored_car;light_tank | F4: light_tank | I4: linh | J4: FALSE | K4: 7 | L4: co_kich_ban | AD4: 105 | AO4: Easy | AP4: commander | AR4: 9 | AT4: 0.55 | AV4: Defend | AW4: Capture | BB4: m00 | BL4: 22 | BM4: 1.3 | BN4: west;town;east | BO4: 1 | BR4: 0 | BX4: 5 | BY4: 360 | CR4: Clear | CS4: 85 | CT4: Assets/MachineBrigade/Resources/Data/campaign.json: missions[2] | CU4: {"id":"c1m03","chapter":1,"map":"greenvale","weather":"Clear","goal":"Capture","legacy":"m00","points":["west","town","east"],"reinforcements":0,"enemyAi":"commander","enemyStance":"Defend","difficulty":"Easy","enemyCp":9,"enemyIncome":0.55,"enemyDeck":["scout_jeep","armored_car","light_tank"],"playerCp":22,"playerIncome":1.3,"starTime":360,"starLosses":5,"radio":[{"key":"radio.khai.c1m03.1","on":"Start"},{"key":"radio.linh.c1m03.2","on":"Capture","arg":"town"},{"key":"radio.khai.c1m03.q1","on":"Win"}],"unlocks":["light_tank"],"missionEvents":["enemy_wave","loot_drop","accord_wave"],"coins":105,"xp":85,"prints":1}
A5: c1m04 | B5: 1 | C5: greenvale | E5: scout_jeep;armored_car;light_tank;rocket_technical;ifv | F5: rocket_turret;repair_bay | I5: mai | J5: FALSE | K5: 7 | L5: co_kich_ban | AD5: 110 | AO5: Easy | AP5: both | AR5: 8 | AT5: 0.6 | AV5: Attack | AW5: Outpost | AX5: 150 | AY5: 1 | BL5: 24 | BM5: 1.4 | BN5: town | BO5: 1 | BR5: 1 | BW5: mai | BX5: 6 | BY5: 480 | CG5: 1000 | CJ5: 60 | CK5: 0.3 | CL5: 55 | CM5: 10 | CN5: 4 | CO5: armored_car;light_tank;rocket_technical | CP5: 2 | CQ5: 90;60;60;95;100;20 | CR5: Overcast | CS5: 90 | CT5: Assets/MachineBrigade/Resources/Data/campaign.json: missions[3] | CU5: {"id":"c1m04","chapter":1,"map":"greenvale","weather":"Overcast","goal":"Outpost","points":["town"],"holdSeconds":150,"speaker":"mai","reinforcements":1,"timeLimit":1000,"enemyAi":"both","enemyStance":"Attack","difficulty":"Easy","enemyCp":8,"enemyIncome":0.6,"enemyDeck":["scout_jeep","armored_car","light_tank","rocket_technical","ifv"],"playerCp":24,"playerIncome":1.4,"waves":{"first":60,"interval":55,"size":2,"grow":0.3,"maxSize":4,"maxAlive":10,"roster":["armored_car","light_tank","rocket_technical"],"spawns":[90,60,60,95,100,20]},"starTime":480,"starLosses":6,"radio":[{"key":"radio.mai.c1m04.1","on":"Start"},{"key":"radio.mai.c1m04.2","on":"Capture","arg":"town"},{"key":"radio.mai.c1m04.3","on":"Win"}],"unlocks":["rocket_turret","repair_bay"],"hqLevel":1,"missionEvents":["enemy_wave_late","supply_drop","rain_sets_in"],"coins":110,"xp":90,"prints":1}
A6: c1m05 | B6: 1 | C6: greenvale | E6: armored_car;light_tank;ifv;main_battle_tank;mortar_carrier;rocket_technical | F6: engineer_vehicle | H6: bastion_mk0 | I6: mai | J6: FALSE | K6: 13 | L6: co_kich_ban | R6: fortress_bastion | S6: 0.55 | U6: 225 | W6: bastion_mk0 | X6: 55;55;20;25;-15;-5 | Y6: 84 | Z6: 84 | AD6: 170 | AO6: Normal | AP6: commander | AR6: 10 | AT6: 0.8 | AV6: Attack | AW6: Boss | BJ6: Anchor | BL6: 24 | BM6: 1.4 | BO6: 1 | BR6: 2 | BX6: 8 | BY6: 600 | CG6: 1140 | CR6: Night | CS6: 135 | CT6: Assets/MachineBrigade/Resources/Data/campaign.json: missions[4] | CU6: {"id":"c1m05","chapter":1,"map":"greenvale","weather":"Night","goal":"Boss","timeLimit":1140,"reinforcements":2,"boss":{"def":"bastion_mk0","x":84,"z":84,"heading":225,"route":[55,55,20,25,-15,-5],"fallback":"fortress_bastion","fallbackHealth":0.55,"name":"bastion_mk0"},"enemyAi":"commander","enemyStance":"Attack","difficulty":"Normal","enemyCp":10,"enemyIncome":0.8,"enemyDeck":["armored_car","light_tank","ifv","main_battle_tank","mortar_carrier","rocket_technical"],"playerCp":24,"playerIncome":1.4,"playerBase":"Anchor","starTime":600,"starLosses":8,"radio":[{"key":"radio.linh.c1m05.1","on":"Start"},{"key":"radio.khai.c1m05.2","on":"Win"}],"missionEvents":["accord_artillery","loot_repair"],"unlocks":["engineer_vehicle"],"coins":170,"xp":135,"prints":1}
A7: c1m06 | B7: 1 | C7: greenvale | F7: zu23_technical | I7: khai | J7: FALSE | K7: 7 | L7: co_kich_ban | AB7: Kills | AC7: 15 | AD7: 115 | AF7: 5 | AG7: supply_truck | AH7: 45 | AK7: 3 | AL7: -78.75;-78.75;-78.75;0;0;0;0;86.25;-60;86.25 | AM7: -100 | AN7: -100 | AO7: Easy | AP7: waves | AW7: Escort | BJ7: Anchor | BO7: 1 | BR7: 1 | BX7: 5 | BY7: 300 | CG7: 1000 | CJ7: 15 | CK7: 0.4 | CL7: 28 | CM7: 11 | CN7: 5 | CO7: armored_car;rocket_technical;light_tank;ifv | CP7: 2 | CQ7: 20;110;95;40;60;90;-10;60 | CR7: Rain | CS7: 95 | CT7: Assets/MachineBrigade/Resources/Data/campaign.json: missions[5] | CU7: {"id":"c1m06","chapter":1,"map":"greenvale","weather":"Rain","goal":"Escort","convoyCount":5,"convoyNeeded":3,"reinforcements":1,"timeLimit":1000,"convoy":{"def":"supply_truck","x":-100,"z":-100,"heading":45,"route":[-78.75,-78.75,-78.75,0,0,0,0,86.25,-60,86.25]},"units":[{"def":"light_tank","team":0,"x":-85.0,"z":-88.0,"heading":45},{"def":"ifv","team":0,"x":-92.5,"z":-83.67,"heading":45},{"def":"main_battle_tank","team":0,"x":-92.5,"z":-92.33,"heading":45}],"enemyAi":"waves","difficulty":"Easy","waves":{"first":15,"interval":28,"size":2,"grow":0.4,"maxSize":5,"maxAlive":11,"roster":["armored_car","rocket_technical","light_tank","ifv"],"spawns":[20,110,95,40,60,90,-10,60]},"playerBase":"Anchor","starTime":300,"starLosses":5,"challenge":{"kind":"Kills","value":15},"radio":[{"key":"radio.khai.c1m06.1","on":"Start"},{"key":"radio.linh.c1m06.2","at":60}],"unlocks":["zu23_technical"],"missionEvents":["enemy_barrage","accord_relief","skies_clear"],"coins":115,"xp":95,"prints":1}
A8: c1m08 | B8: 1 | C8: ashfield | E8: armored_car;light_tank;ifv;main_battle_tank;mortar_carrier;rocket_technical | I8: linh | J8: FALSE | K8: 7 | L8: co_kich_ban | AB8: NoStrikes | AD8: 120 | AO8: Normal | AP8: commander | AR8: 11 | AT8: 0.8 | AV8: Attack | AW8: Capture | BB8: m01 | BJ8: Anchor | BL8: 22 | BM8: 1.3 | BN8: west;town;east | BO8: 1 | BR8: 1 | BX8: 6 | BY8: 480 | CR8: Clear | CS8: 95 | CT8: Assets/MachineBrigade/Resources/Data/campaign.json: missions[6] | CU8: {"id":"c1m08","chapter":1,"map":"ashfield","weather":"Clear","goal":"Capture","legacy":"m01","points":["west","town","east"],"reinforcements":1,"enemyAi":"commander","enemyStance":"Attack","difficulty":"Normal","enemyCp":11,"enemyIncome":0.8,"enemyDeck":["armored_car","light_tank","ifv","main_battle_tank","mortar_carrier","rocket_technical"],"playerCp":22,"playerIncome":1.3,"playerBase":"Anchor","starTime":480,"starLosses":6,"challenge":{"kind":"NoStrikes"},"radio":[{"key":"radio.khai.c1m08.1","on":"Start"},{"key":"radio.linh.c1m08.2","on":"Lost"}],"missionEvents":[{"id":"general_field","params":{"general":"brandt"}},{"id":"intercept_files","reward":{"intel":"c1.inspection"}},"enemy_wave"],"coins":120,"xp":95,"prints":1}
A9: c1m09 | B9: 1 | C9: ashfield | I9: khai | J9: FALSE | K9: 7 | L9: co_kich_ban | AB9: Kills | AC9: 18 | AD9: 125 | AF9: 5 | AG9: supply_truck | AH9: 45 | AK9: 3 | AL9: -78.75;-78.75;0;-78.75;78.75;-78.75;78.75;0;31.8;0;7.5;0 | AM9: -105 | AN9: -105 | AO9: Normal | AP9: waves | AW9: Escort | BB9: m02 | BJ9: Anchor | BO9: 1 | BR9: 1 | BX9: 5 | BY9: 300 | CG9: 1000 | CJ9: 12 | CK9: 0.45 | CL9: 26 | CM9: 11 | CN9: 5 | CO9: scout_jeep;armored_car;rocket_technical;light_tank;mortar_carrier | CP9: 2 | CQ9: 15;-108;93;-45;93;30;45;45;-45;21 | CR9: Overcast | CS9: 100 | CT9: Assets/MachineBrigade/Resources/Data/campaign.json: missions[7] | CU9: {"id":"c1m09","chapter":1,"map":"ashfield","weather":"Overcast","goal":"Escort","legacy":"m02","convoyCount":5,"convoyNeeded":3,"reinforcements":1,"timeLimit":1000,"convoy":{"def":"supply_truck","x":-105,"z":-105,"heading":45,"route":[-78.75,-78.75,0,-78.75,78.75,-78.75,78.75,0,31.8,0,7.5,0]},"units":[{"def":"light_tank","team":0,"x":-84.0,"z":-90.0,"heading":45},{"def":"light_tank","team":0,"x":-93.0,"z":-84.8,"heading":45},{"def":"ifv","team":0,"x":-93.0,"z":-95.2,"heading":45}],"enemyAi":"waves","difficulty":"Normal","waves":{"first":12,"interval":26,"size":2,"grow":0.45,"maxSize":5,"maxAlive":11,"roster":["scout_jeep","armored_car","rocket_technical","light_tank","mortar_carrier"],"spawns":[15,-108,93,-45,93,30,45,45,-45,21]},"playerBase":"Anchor","starTime":300,"starLosses":5,"challenge":{"kind":"Kills","value":18},"radio":[{"key":"radio.khai.c1m09.1","on":"Start"}],"missionEvents":["enemy_air_raid","accord_wave","sea_fog"],"coins":125,"xp":100,"prints":1}
A10: c1m10 | B10: 1 | C10: ashfield | E10: armored_car;light_tank;ifv;main_battle_tank;mortar_carrier;rocket_technical | I10: khai | J10: FALSE | K10: 14 | L10: co_kich_ban | AD10: 305 | AO10: Normal | AP10: both | AR10: 12 | AS10: 2 | AT10: 0.85 | AV10: Defend | AW10: Destroy | BC10: TRUE | BJ10: Anchor | BK10: 42 | BL10: 30 | BM10: 2 | BO10: 2 | BR10: 2 | BX10: 16 | BY10: 1320 | CI10: siege | CJ10: 70 | CK10: 0.3 | CL10: 60 | CM10: 12 | CN10: 5 | CO10: light_tank;main_battle_tank;ifv;mortar_carrier;rocket_technical | CP10: 2 | CQ10: 100;60;60;100;80;80 | CR10: Fog | CS10: 245 | CT10: Assets/MachineBrigade/Resources/Data/campaign.json: missions[8] | CU10: {"id":"c1m10","chapter":1,"map":"ashfield","variant":"siege","weather":"Fog","goal":"Destroy","operation":true,"reinforcements":2,"enemyAi":"both","enemyStance":"Defend","difficulty":"Normal","enemyCp":12,"enemyIncome":0.85,"enemyDeck":["armored_car","light_tank","ifv","main_battle_tank","mortar_carrier","rocket_technical"],"playerCp":30,"playerIncome":2.0,"playerCap":42,"playerBase":"Anchor","enemyHq":2,"stages":[{"stage":"depot","goal":"Destroy","targets":["fuel_tank"],"targetX":56.25,"targetZ":-97,"targetRadius":25,"targetHealth":2,"cp":8,"events":[{"at":"start","kind":"Radio","key":"radio.khai.c1m10.s1"}],"choices":[{"key":"dump","next":"dump"},{"key":"radar","next":"radar"}],"missionEvents":["enemy_wave"]},{"stage":"dump","goal":"Destroy","targets":["ammo_dump"],"targetHealth":2,"cp":6,"next":"bastion","events":[{"at":"end","kind":"Income","team":1,"amount":0.7},{"at":"end","kind":"Radio","key":"radio.enemyWeakened"}]},{"stage":"radar","goal":"Destroy","targets":["radar_station_prop"],"targetHealth":2,"cp":6,"next":"bastion","events":[{"at":"end","kind":"Strike","team":0,"support":"airstrike","every":55},{"at":"end","kind":"Radio","key":"radio.alliedStrikes"}]},{"stage":"bastion","goal":"Boss","boss":{"def":"fortress_bastion","x":92,"z":92,"heading":225,"health":0.55},"cp":10,"events":[{"at":"start","kind":"Radio","key":"radio.mai.c1m10.s3"}],"missionEvents":["accord_artillery"]},{"stage":"counter","goal":"Survive","surviveSeconds":240,"cp":8,"events":[{"at":"start","kind":"Radio","key":"radio.khai.c1m10.s4"},{"at":"30","kind":"Reinforce","team":1,"units":["main_battle_tank","ifv","mortar_carrier","light_tank"]},{"at":"140","kind":"Reinforce","team":1,"units":["main_battle_tank","rocket_technical","ifv"]}],"missionEvents":["enemy_counterattack","accord_landing"]},{"stage":"hq","goal":"Destroy","targets":["command_hq"],"targetHealth":0.8,"events":[{"at":"start","kind":"Reinforce","team":1,"units":["main_battle_tank","ifv","mortar_carrier"]}]}],"waves":{"first":70,"interval":60,"size":2,"grow":0.3,"maxSize":5,"maxAlive":12,"roster":["light_tank","main_battle_tank","ifv","mortar_carrier","rocket_technical"],"spawns":[100,60,60,100,80,80]},"starTime":1320,"starLosses":16,"radio":[{"key":"radio.khai.c1m10.1","on":"Start"},{"key":"radio.khai.c1m10.2","on":"Win"},{"key":"radio.brandt.c1m10.q1","on":"Win"},{"key":"radio.linh.c1m10.q2","on":"Win"}],"missionEvents":["hawk_strike","supply_drop"],"coins":305,"xp":245,"prints":2}
A11: c1s1 | B11: 1 | C11: greenvale | E11: scout_jeep;armored_car;light_tank;rocket_technical;ifv | G11: c1m03 | I11: linh | J11: FALSE | K11: 5 | L11: co_kich_ban | AD11: 350 | AO11: Easy | AP11: commander | AR11: 10 | AT11: 0.7 | AV11: Defend | AW11: Recon | BL11: 22 | BM11: 1.3 | BN11: west;town;east | BO11: 1 | BQ11: 18 | BR11: 1 | BV11: TRUE | BW11: linh | BX11: 5 | BY11: 360 | CG11: 840 | CR11: Fog | CS11: 280 | CT11: Assets/MachineBrigade/Resources/Data/campaign.json: missions[9] | CU11: {"id":"c1s1","chapter":1,"side":true,"after":"c1m03","map":"greenvale","weather":"Fog","goal":"Recon","speaker":"linh","points":["west","town","east"],"timeLimit":840,"reinforcements":1,"enemyAi":"commander","enemyStance":"Defend","difficulty":"Easy","enemyCp":10,"enemyIncome":0.7,"enemyDeck":["scout_jeep","armored_car","light_tank","rocket_technical","ifv"],"playerCp":22,"playerIncome":1.3,"rarePrints":18,"starTime":360,"starLosses":5,"radio":[{"key":"radio.linh.c1s1.1","on":"Start"}],"missionEvents":["nadia_intel","skies_clear"],"coins":350,"xp":280,"prints":1}
A12: c2m01 | B12: 2 | C12: dunebreak | D12: varga | F12: aa_vehicle | I12: khai | J12: FALSE | K12: 8 | L12: co_kich_ban | AB12: NoAircraft | AD12: 130 | AO12: Normal | AP12: waves | AW12: Survive | BB12: m04 | BJ12: Anchor | BL12: 20 | BM12: 1.3 | BN12: east | BO12: 1 | BX12: 8 | BY12: 0 | CA12: 300 | CJ12: 18 | CK12: 0.6 | CL12: 30 | CM12: 16 | CN12: 8 | CO12: rocket_technical;armored_car;light_tank;mortar_carrier;ifv | CP12: 3 | CQ12: 93;-15;75;33;27;-114 | CR12: Clear | CS12: 105 | CT12: Assets/MachineBrigade/Resources/Data/campaign.json: missions[10] | CU12: {"id":"c2m01","chapter":2,"map":"dunebreak","weather":"Clear","goal":"Survive","legacy":"m04","surviveSeconds":300,"points":["east"],"general":"varga","enemyAi":"waves","difficulty":"Normal","playerCp":20,"playerIncome":1.3,"waves":{"first":18,"interval":30,"size":3,"grow":0.6,"maxSize":8,"maxAlive":16,"roster":["rocket_technical","armored_car","light_tank","mortar_carrier","ifv"],"spawns":[93,-15,75,33,27,-114]},"playerBase":"Anchor","starTime":0,"starLosses":8,"challenge":{"kind":"NoAircraft"},"radio":[{"key":"radio.khai.c2m01.1","on":"Start"},{"key":"radio.varga.c2m01.q1","at":15}],"missionEvents":["oil_convoy","enemy_wave","sandstorm"],"unlocks":["aa_vehicle"],"coins":130,"xp":105,"prints":1}
A13: c2m02 | B13: 2 | C13: redrock | D13: varga | E13: armored_car;light_tank;main_battle_tank;ifv;tank_destroyer;mortar_carrier | F13: artillery | I13: linh | J13: FALSE | K13: 7 | L13: co_kich_ban | AD13: 135 | AO13: Normal | AP13: commander | AR13: 13 | AT13: 0.85 | AU13: town | AV13: Defend | AW13: Capture | BJ13: Anchor | BL13: 24 | BM13: 1.4 | BN13: west;town;east | BO13: 1 | BR13: 2 | BX13: 8 | BY13: 540 | CR13: Clear | CS13: 105 | CT13: Assets/MachineBrigade/Resources/Data/campaign.json: missions[11] | CU13: {"id":"c2m02","chapter":2,"map":"redrock","weather":"Clear","goal":"Capture","points":["west","town","east"],"enemyOwns":["town"],"general":"varga","reinforcements":2,"enemyAi":"commander","enemyStance":"Defend","difficulty":"Normal","enemyCp":13,"enemyIncome":0.85,"enemyDeck":["armored_car","light_tank","main_battle_tank","ifv","tank_destroyer","mortar_carrier"],"playerCp":24,"playerIncome":1.4,"playerBase":"Anchor","starTime":540,"starLosses":8,"radio":[{"key":"radio.linh.c2m02.1","on":"Start"},{"key":"radio.varga.c2m02.2","on":"Capture","arg":"town"}],"missionEvents":["enemy_wave_late","loot_drop","accord_wave"],"unlocks":["artillery"],"coins":135,"xp":105,"prints":1}
A14: c2m03 | B14: 2 | C14: redrock | F14: flame_tank | I14: khai | J14: FALSE | K14: 7 | L14: co_kich_ban | AB14: Kills | AC14: 18 | AD14: 135 | AF14: 5 | AG14: supply_truck | AH14: 45 | AK14: 3 | AL14: -78;-65;-34;-45;-20;-20;0;0;-30;40;-56.25;86.25 | AM14: -100 | AN14: -100 | AO14: Normal | AP14: waves | AW14: Escort | BO14: 1 | BR14: 1 | BX14: 6 | BY14: 360 | CG14: 1000 | CJ14: 20 | CK14: 0.5 | CL14: 28 | CM14: 13 | CN14: 6 | CO14: armored_car;rocket_technical;light_tank;tank_destroyer;mortar_carrier | CP14: 2 | CQ14: 60;80;90;20;20;110;-60;110 | CR14: Night | CS14: 110 | CT14: Assets/MachineBrigade/Resources/Data/campaign.json: missions[12] | CU14: {"id":"c2m03","chapter":2,"map":"redrock","weather":"Night","goal":"Escort","convoyCount":5,"convoyNeeded":3,"reinforcements":1,"timeLimit":1000,"convoy":{"def":"supply_truck","x":-100,"z":-100,"heading":45,"route":[-78,-65,-34,-45,-20,-20,0,0,-30,40,-56.25,86.25]},"units":[{"def":"main_battle_tank","team":0,"x":-82.0,"z":-92.0,"heading":45},{"def":"ifv","team":0,"x":-91.0,"z":-86.8,"heading":45},{"def":"aa_vehicle","team":0,"x":-91.0,"z":-97.2,"heading":45}],"enemyAi":"waves","difficulty":"Normal","waves":{"first":20,"interval":28,"size":2,"grow":0.5,"maxSize":6,"maxAlive":13,"roster":["armored_car","rocket_technical","light_tank","tank_destroyer","mortar_carrier"],"spawns":[60,80,90,20,20,110,-60,110]},"starTime":360,"starLosses":6,"challenge":{"kind":"Kills","value":18},"radio":[{"key":"radio.khai.c2m03.1","on":"Start"}],"unlocks":["flame_tank"],"missionEvents":["neutral_convoy","enemy_barrage"],"coins":135,"xp":110,"prints":1}
A15: c2m04 | B15: 2 | C15: dunebreak | D15: varga | E15: armored_car;light_tank;main_battle_tank;ifv;tank_destroyer;mortar_carrier | F15: airstrike | I15: khai | J15: TRUE | K15: 8 | L15: co_kich_ban | AB15: NoStrikes | AD15: 140 | AO15: Normal | AP15: commander | AR15: 14 | AT15: 0.85 | AV15: Defend | AW15: Destroy | BL15: 24 | BM15: 1.4 | BO15: 1 | BR15: 2 | BX15: 8 | BY15: 480 | CB15: 2.5 | CF15: pipeline | CG15: 900 | CR15: Overcast | CS15: 110 | CT15: Assets/MachineBrigade/Resources/Data/campaign.json: missions[13] | CU15: {"id":"c2m04","chapter":2,"map":"dunebreak","weather":"Overcast","goal":"Destroy","targets":["pipeline"],"targetHealth":2.5,"timeLimit":900,"general":"varga","reinforcements":2,"units":[{"def":"main_battle_tank","team":1,"x":6.0,"z":30.0,"heading":225},{"def":"tank_destroyer","team":1,"x":-6.0,"z":30.0,"heading":225},{"def":"light_tank","team":1,"x":106.0,"z":-50.0,"heading":225},{"def":"ifv","team":1,"x":94.0,"z":-50.0,"heading":225}],"enemyAi":"commander","enemyStance":"Defend","difficulty":"Normal","enemyCp":14,"enemyIncome":0.85,"enemyDeck":["armored_car","light_tank","main_battle_tank","ifv","tank_destroyer","mortar_carrier"],"playerCp":24,"playerIncome":1.4,"starTime":480,"starLosses":8,"challenge":{"kind":"NoStrikes"},"radio":[{"key":"radio.khai.c2m04.1","on":"Start"},{"key":"radio.varga.c2m04.2","at":150}],"unlocks":["airstrike"],"missionEvents":["general_field",{"id":"intercept_files","reward":{"intel":"c2.order"}},"oil_convoy"],"fixedDeck":{"vehicleIds":["armored_car","scout_jeep","vbied","rocket_technical","ifv","light_tank","zu23_technical","demolition_line_vehicle"],"supportIds":["artillery_barrage","repair_drop"],"placedAllies":[],"loanedCards":["vbied","demolition_line_vehicle"],"specialRules":["raidNoBase"],"status":"MAKE_FIRST"},"coins":140,"xp":110,"prints":1}
A16: c2m05 | B16: 2 | C16: dunebreak | D16: varga | E16: armored_car;light_tank;main_battle_tank;ifv;tank_destroyer;mortar_carrier | F16: ammo_carrier | H16: behemoth_inferno | I16: mai | J16: FALSE | K16: 13 | L16: co_kich_ban | T16: 0.5 | U16: 225 | V16: 1.6 | W16: behemoth_inferno | Y16: 75 | Z16: 75 | AD16: 215 | AO16: Normal | AP16: commander | AR16: 11 | AT16: 0.85 | AV16: Attack | AW16: Boss | BB16: m06 | BJ16: Anchor | BK16: 36 | BL16: 26 | BM16: 1.45 | BO16: 2 | BR16: 3 | BX16: 10 | BY16: 720 | CG16: 1200 | CR16: Sandstorm | CS16: 170 | CT16: Assets/MachineBrigade/Resources/Data/campaign.json: missions[14] | CU16: {"id":"c2m05","chapter":2,"map":"dunebreak","weather":"Sandstorm","goal":"Boss","legacy":"m06","timeLimit":1200,"general":"varga","reinforcements":3,"boss":{"def":"behemoth_inferno","x":75,"z":75,"heading":225,"health":1.6,"name":"behemoth_inferno","fleeAt":0.5},"enemyAi":"commander","enemyStance":"Attack","difficulty":"Normal","enemyCp":11,"enemyIncome":0.85,"enemyDeck":["armored_car","light_tank","main_battle_tank","ifv","tank_destroyer","mortar_carrier"],"playerCp":26,"playerIncome":1.45,"playerCap":36,"playerBase":"Anchor","starTime":720,"starLosses":10,"radio":[{"key":"radio.varga.c2m05.q1","on":"Start"},{"key":"radio.mai.c2m05.q2","on":"Boss"},{"key":"radio.khai.c2m05.q3","on":"Win"}],"missionEvents":["hawk_strike","skies_clear"],"unlocks":["ammo_carrier"],"coins":215,"xp":170,"prints":2}
A17: c2m06 | B17: 2 | C17: redrock | D17: varga | E17: main_battle_tank;aa_vehicle;tank_destroyer;ifv;heavy_tank;mortar_carrier | F17: atgm_tower | I17: linh | J17: FALSE | K17: 7 | L17: co_kich_ban | AB17: Kills | AC17: 25 | AD17: 145 | AO17: Normal | AP17: commander | AR17: 14 | AT17: 0.85 | AV17: Defend | AW17: Hunt | BB17: m17 | BJ17: Anchor | BK17: 36 | BL17: 26 | BM17: 1.4 | BO17: 1 | BR17: 2 | BX17: 12 | BY17: 660 | CB17: 2.5 | CG17: 1100 | CR17: Sandstorm | CS17: 115 | CT17: Assets/MachineBrigade/Resources/Data/campaign.json: missions[15] | CU17: {"id":"c2m06","chapter":2,"map":"redrock","weather":"Sandstorm","goal":"Hunt","legacy":"m17","timeLimit":1100,"targetHealth":2.5,"general":"varga","reinforcements":2,"hunt":[{"def":"elite_mlrs","x":90,"z":45,"heading":225,"route":[60,82.5,22.5,60,52.5,22.5,90,45]},{"def":"elite_grad","x":-15,"z":105,"heading":180,"route":[-60,120,-37.5,75,-15,105]},{"def":"sam_launcher","x":105,"z":0,"heading":225,"route":[82.5,-37.5,120,-45,105,0]}],"units":[{"def":"tank_destroyer","team":1,"x":75,"z":52.5,"heading":225},{"def":"aa_vehicle","team":1,"x":82.5,"z":63,"heading":225},{"def":"main_battle_tank","team":1,"x":-7.5,"z":90,"heading":200},{"def":"tank_destroyer","team":1,"x":-27,"z":99,"heading":200},{"def":"heavy_tank","team":1,"x":93,"z":-12,"heading":225},{"def":"main_battle_tank","team":1,"x":108,"z":-21,"heading":225}],"enemyAi":"commander","enemyStance":"Defend","difficulty":"Normal","enemyCp":14,"enemyIncome":0.85,"enemyDeck":["main_battle_tank","aa_vehicle","tank_destroyer","ifv","heavy_tank","mortar_carrier"],"playerCp":26,"playerIncome":1.4,"playerCap":36,"playerBase":"Anchor","starTime":660,"starLosses":12,"challenge":{"kind":"Kills","value":25},"radio":[{"key":"radio.linh.c2m06.1","on":"Start"}],"unlocks":["atgm_tower"],"missionEvents":["thorne_support","enemy_wave","nadia_intel",{"id":"sandstorm_turn","params":{"sight":0.65,"clear":1.25}}],"coins":145,"xp":115,"prints":1}
A18: c2m07 | B18: 2 | C18: redrock | E18: armored_car;light_tank;main_battle_tank;ifv;tank_destroyer;mortar_carrier | F18: vbied | I18: khai | J18: FALSE | K18: 7 | L18: co_kich_ban | N18: headquarters | O18: 0 | P18: 0 | AD18: 150 | AO18: Normal | AP18: both | AR18: 10 | AT18: 0.75 | AV18: Attack | AW18: Relieve | BJ18: Anchor | BK18: 36 | BL18: 26 | BM18: 1.45 | BO18: 1 | BR18: 2 | BX18: 8 | BY18: 480 | CB18: 3 | CG18: 1000 | CJ18: 70 | CK18: 0.3 | CL18: 60 | CM18: 12 | CN18: 4 | CO18: light_tank;ifv;mortar_carrier;tank_destroyer | CP18: 2 | CQ18: 60;80;80;30 | CR18: Night | CS18: 120 | CT18: Assets/MachineBrigade/Resources/Data/campaign.json: missions[16] | CU18: {"id":"c2m07","chapter":2,"map":"redrock","weather":"Night","goal":"Relieve","targetHealth":3.0,"reinforcements":2,"timeLimit":1000,"ally":{"x":0,"z":0,"hq":"headquarters","structures":[{"def":"mg_bunker","team":0,"x":14.0,"z":0.0,"heading":45},{"def":"gun_turret","team":0,"x":-7.0,"z":12.12,"heading":45},{"def":"guard_tower","team":0,"x":-7.0,"z":-12.12,"heading":45}],"units":[{"def":"ifv","team":0,"x":-2.0,"z":-6.0,"heading":45},{"def":"light_tank","team":0,"x":-10.0,"z":-6.0,"heading":45}]},"hunt":[{"def":"main_battle_tank","x":36.3,"z":11.23,"heading":225},{"def":"tank_destroyer","x":8.43,"z":37.05,"heading":225},{"def":"light_tank","x":-27.88,"z":25.82,"heading":225},{"def":"mortar_carrier","x":-36.3,"z":-11.23,"heading":225},{"def":"ifv","x":-8.43,"z":-37.05,"heading":225},{"def":"main_battle_tank","x":27.88,"z":-25.82,"heading":225}],"enemyAi":"both","enemyStance":"Attack","difficulty":"Normal","enemyCp":10,"enemyIncome":0.75,"enemyDeck":["armored_car","light_tank","main_battle_tank","ifv","tank_destroyer","mortar_carrier"],"playerCp":26,"playerIncome":1.45,"playerCap":36,"playerBase":"Anchor","waves":{"first":70,"interval":60,"size":2,"grow":0.3,"maxSize":4,"maxAlive":12,"roster":["light_tank","ifv","mortar_carrier","tank_destroyer"],"spawns":[60,80,80,30]},"starTime":480,"starLosses":8,"radio":[{"key":"radio.khai.c2m07.1","on":"Start"},{"key":"radio.linh.c2m07.2","at":120}],"missionEvents":["enemy_counterattack","supply_drop"],"unlocks":["vbied"],"coins":150,"xp":120,"prints":1}
A19: c2m08 | B19: 2 | C19: dunebreak | D19: varga | E19: light_tank;main_battle_tank;ifv;tank_destroyer;flame_tank;heavy_tank | I19: khai | J19: FALSE | K19: 7 | L19: co_kich_ban | AD19: 155 | AO19: Normal | AP19: both | AR19: 10 | AT19: 0.8 | AV19: Attack | AW19: Hold | AX19: 240 | BJ19: Anchor | BK19: 40 | BL19: 24 | BM19: 1.3 | BN19: town | BO19: 1 | BR19: 2 | BX19: 10 | BY19: 0 | CJ19: 40 | CK19: 0.35 | CL19: 48 | CM19: 12 | CN19: 5 | CO19: light_tank;main_battle_tank;ifv;mortar_carrier;flame_tank | CP19: 2 | CR19: Night | CS19: 125 | CT19: Assets/MachineBrigade/Resources/Data/campaign.json: missions[17] | CU19: {"id":"c2m08","chapter":2,"map":"dunebreak","weather":"Night","goal":"Hold","points":["town"],"holdSeconds":240,"general":"varga","reinforcements":2,"units":[{"def":"main_battle_tank","team":0,"x":0.0,"z":-8.0,"heading":45},{"def":"main_battle_tank","team":0,"x":-5.53,"z":-0.39,"heading":45},{"def":"ifv","team":0,"x":-14.47,"z":-3.3,"heading":45},{"def":"aa_vehicle","team":0,"x":-14.47,"z":-12.7,"heading":45},{"def":"tank_destroyer","team":0,"x":-5.53,"z":-15.61,"heading":45}],"enemyAi":"both","enemyStance":"Attack","difficulty":"Normal","enemyCp":10,"enemyIncome":0.8,"enemyDeck":["light_tank","main_battle_tank","ifv","tank_destroyer","flame_tank","heavy_tank"],"playerCp":24,"playerIncome":1.3,"playerCap":40,"playerBase":"Anchor","waves":{"first":40,"interval":48,"size":2,"grow":0.35,"maxSize":5,"maxAlive":12,"roster":["light_tank","main_battle_tank","ifv","mortar_carrier","flame_tank"]},"starTime":0,"starLosses":10,"radio":[{"key":"radio.khai.c2m08.1","on":"Start"},{"key":"radio.varga.c2m08.2","at":100}],"missionEvents":["enemy_wave","thorne_support","supply_raid"],"coins":155,"xp":125,"prints":1}
A20: c2m09 | B20: 2 | C20: redrock | D20: varga | I20: khai | J20: FALSE | K20: 9 | L20: co_kich_ban | AD20: 155 | AO20: Normal | AP20: commander | AQ20: Target | AR20: 10 | AS20: 3 | AT20: 0.54 | AV20: Defend | AW20: Duel | BJ20: Anchor | BK20: 38 | BL20: 26 | BM20: 1.9 | BO20: 1 | BR20: 3 | BS20: TRUE | BX20: 12 | BY20: 780 | CB20: 0.4 | CG20: 1500 | CR20: Sandstorm | CS20: 125 | CT20: Assets/MachineBrigade/Resources/Data/campaign.json: missions[18] | CU20: {"id":"c2m09","chapter":2,"map":"redrock","weather":"Sandstorm","goal":"Duel","targetHealth":0.4,"general":"varga","enemyBase":"Target","enemyHq":3,"replay":true,"reinforcements":3,"timeLimit":1500,"enemyAi":"commander","enemyStance":"Defend","difficulty":"Normal","enemyCp":10,"enemyIncome":0.54,"playerCp":26,"playerIncome":1.9,"playerCap":38,"playerBase":"Anchor","starTime":780,"starLosses":12,"radio":[{"key":"radio.varga.c2m09.1","on":"Start"},{"key":"radio.khai.c2m09.2","on":"Start"},{"key":"radio.varga.c2m09.3","on":"Win"}],"missionEvents":["enemy_barrage","accord_artillery","loot_drop"],"coins":155,"xp":125,"prints":1}
A21: c2m10 | B21: 2 | C21: dunebreak | D21: varga | E21: light_tank;main_battle_tank;ifv;tank_destroyer;flame_tank;heavy_tank | I21: khai | J21: FALSE | K21: 7 | L21: co_kich_ban | AD21: 290 | AO21: Normal | AP21: both | AR21: 14 | AT21: 0.9 | AV21: Defend | AW21: Capture | BB21: m05 | BJ21: Anchor | BK21: 40 | BL21: 28 | BM21: 1.6 | BO21: 2 | BR21: 3 | BS21: TRUE | BU21: TRUE | BX21: 16 | BY21: 1320 | CJ21: 80 | CK21: 0.3 | CL21: 60 | CM21: 12 | CN21: 5 | CO21: light_tank;main_battle_tank;ifv;flame_tank;tank_destroyer | CP21: 2 | CR21: Overcast | CS21: 230 | CT21: Assets/MachineBrigade/Resources/Data/campaign.json: missions[19] | CU21: {"id":"c2m10","chapter":2,"map":"dunebreak","weather":"Overcast","goal":"Capture","legacy":"m05","general":"varga","reinforcements":3,"enemyAi":"both","enemyStance":"Defend","difficulty":"Normal","enemyCp":14,"enemyIncome":0.9,"enemyDeck":["light_tank","main_battle_tank","ifv","tank_destroyer","flame_tank","heavy_tank"],"playerCp":28,"playerIncome":1.6,"playerCap":40,"playerBase":"Anchor","waves":{"first":80,"interval":60,"size":2,"grow":0.3,"maxSize":5,"maxAlive":12,"roster":["light_tank","main_battle_tank","ifv","flame_tank","tank_destroyer"]},"stages":[{"stage":"fields","goal":"Capture","points":["east","west"],"enemyOwns":["east","west"],"cp":8,"events":[{"at":"start","kind":"Radio","key":"radio.khai.c2m10.s1"}],"choices":[{"key":"tanks","next":"tanks"},{"key":"oasis","next":"oasis"}],"missionEvents":["oil_convoy"]},{"stage":"tanks","goal":"Destroy","targets":["fuel_tank"],"targetX":65,"targetZ":29,"targetRadius":20,"targetHealth":2,"cp":6,"next":"wells","events":[{"at":"end","kind":"Income","team":1,"amount":0.7},{"at":"end","kind":"Radio","key":"radio.enemyWeakened"}]},{"stage":"oasis","goal":"Survive","points":["west"],"surviveSeconds":90,"cp":6,"next":"wells","events":[{"at":"end","kind":"Strike","team":0,"support":"airstrike","every":55},{"at":"end","kind":"Radio","key":"radio.alliedStrikes"}]},{"stage":"wells","goal":"Destroy","targets":["oil_pump"],"targetX":56,"targetZ":-86,"targetRadius":40,"targetHealth":2,"cp":6},{"stage":"refinery","goal":"Destroy","targets":["refinery_tower","storage_tank"],"targetX":0,"targetZ":0,"targetRadius":40,"targetHealth":2,"cp":10,"events":[{"at":"start","kind":"Reinforce","team":1,"units":["main_battle_tank","tank_destroyer","flame_tank"]}]},{"stage":"yard","goal":"Survive","points":["town"],"surviveSeconds":240,"cp":8,"events":[{"at":"30","kind":"Reinforce","team":1,"units":["main_battle_tank","ifv","flame_tank"]}]},{"stage":"inferno","goal":"Boss","boss":{"def":"behemoth_inferno","x":30,"z":30,"heading":225,"health":1.2,"name":"behemoth_inferno"},"cp":8,"events":[{"at":"start","kind":"Radio","key":"radio.varga.c2m10.s5"}]},{"stage":"counter","goal":"Survive","surviveSeconds":480,"events":[{"at":"start","kind":"Radio","key":"radio.varga.c2m10.s6"},{"at":"40","kind":"Reinforce","team":1,"units":["heavy_tank","tank_destroyer","ifv","mlrs"]},{"at":"200","kind":"Reinforce","team":1,"units":["main_battle_tank","flame_tank","heavy_tank"]}],"missionEvents":["accord_wave"]}],"towerGear":null,"starTime":1320,"starLosses":16,"radio":[{"key":"radio.khai.c2m10.1","on":"Start"},{"key":"radio.khai.c2m10.2","on":"Win"}],"replay":true,"setPiece":true,"missionEvents":["sandstorm"],"coins":290,"xp":230,"prints":2}
A22: c2m11 | B22: 2 | C22: redrock | D22: varga | E22: light_tank;main_battle_tank;ifv;tank_destroyer;flame_tank;heavy_tank | I22: mai | J22: FALSE | K22: 16 | L22: co_kich_ban | M22: 45 | O22: -96 | P22: -80 | AD22: 390 | AO22: Normal | AP22: both | AR22: 14 | AT22: 0.9 | AV22: Defend | AW22: Capture | BC22: TRUE | BF22: 146 | BG22: 146 | BH22: -146 | BI22: -146 | BJ22: Anchor | BK22: 40 | BL22: 28 | BM22: 1.6 | BO22: 3 | BR22: 3 | BS22: TRUE | BX22: 16 | BY22: 1320 | CJ22: 80 | CK22: 0.3 | CL22: 60 | CM22: 12 | CN22: 5 | CO22: light_tank;main_battle_tank;ifv;flame_tank;tank_destroyer | CP22: 2 | CR22: Sandstorm | CS22: 315 | CT22: Assets/MachineBrigade/Resources/Data/campaign.json: missions[20] | CU22: {"id":"c2m11","chapter":2,"map":"redrock","weather":"Sandstorm","goal":"Capture","general":"varga","reinforcements":3,"enemyAi":"both","enemyStance":"Defend","difficulty":"Normal","enemyCp":14,"enemyIncome":0.9,"enemyDeck":["light_tank","main_battle_tank","ifv","tank_destroyer","flame_tank","heavy_tank"],"playerCp":28,"playerIncome":1.6,"playerCap":40,"playerBase":"Anchor","waves":{"first":80,"interval":60,"size":2,"grow":0.3,"maxSize":5,"maxAlive":12,"roster":["light_tank","main_battle_tank","ifv","flame_tank","tank_destroyer"]},"stages":[{"stage":"wells","goal":"Capture","points":["west"],"enemyOwns":["west","town","east"],"cp":8,"choices":[{"key":"pumps","next":"pumps"},{"key":"guns","next":"guns"}],"events":[{"at":"start","kind":"Radio","key":"radio.khai.c2m11.s1"}],"missionEvents":["oil_convoy"]},{"stage":"pumps","goal":"Destroy","targets":["oil_pump"],"targetX":-56,"targetZ":92,"targetRadius":30,"targetHealth":2,"cp":6,"next":"oasis","events":[{"at":"end","kind":"Income","team":1,"amount":0.7},{"at":"end","kind":"Radio","key":"radio.enemyWeakened"}]},{"stage":"guns","goal":"Survive","points":["west"],"surviveSeconds":150,"cp":6,"next":"oasis","events":[{"at":"end","kind":"Strike","team":0,"support":"artillery_barrage","every":55},{"at":"end","kind":"Radio","key":"radio.hung.c2m11.s2"}]},{"stage":"oasis","goal":"Capture","points":["town"],"enemyOwns":["town"],"cp":8,"events":[{"at":"start","kind":"Reinforce","team":1,"units":["heavy_tank","tank_destroyer","ifv"]}],"missionEvents":["enemy_wave"]},{"stage":"caravan","goal":"Survive","points":["town"],"surviveSeconds":180,"cp":6,"events":[{"at":"30","kind":"Reinforce","team":1,"units":["main_battle_tank","flame_tank","ifv"]}],"missionEvents":["enemy_barrage"]},{"stage":"behemoth","goal":"Boss","boss":{"def":"behemoth","name":"behemoth","x":84,"z":84,"heading":225,"health":1.8},"cp":0,"events":[{"at":"start","kind":"Radio","key":"radio.varga.c2m11.s5"}],"missionEvents":["skies_clear"]}],"starTime":1320,"starLosses":16,"operation":true,"replay":true,"playArea":{"minX":-146,"minZ":-146,"maxX":146,"maxZ":146},"ally":{"x":-96,"z":-80,"heading":45,"units":[{"def":"main_battle_tank","team":0,"x":-89.0,"z":-80.0,"heading":45},{"def":"main_battle_tank","team":0,"x":-93.84,"z":-73.34,"heading":45},{"def":"ifv","team":0,"x":-101.66,"z":-75.89,"heading":45},{"def":"aa_vehicle","team":0,"x":-101.66,"z":-84.11,"heading":45},{"def":"mlrs","team":0,"x":-93.84,"z":-86.66,"heading":45}],"reinforcements":[{"at":240,"units":["heavy_tank","ifv","tank_destroyer"]}]},"radio":[{"key":"radio.khai.c2m11.1","on":"Start"},{"key":"radio.hung.c2m11.2","at":12},{"key":"radio.mai.c2m11.3","on":"Win"}],"missionEvents":["thorne_support","hawk_strike"],"coins":390,"xp":315,"prints":3}
A23: c2s1 | B23: 2 | C23: dunebreak | E23: armored_car;light_tank;main_battle_tank;ifv;tank_destroyer;mortar_carrier | G23: c2m03 | I23: linh | J23: FALSE | K23: 5 | L23: co_kich_ban | AB23: NoAircraft | AD23: 450 | AO23: Normal | AP23: commander | AR23: 12 | AT23: 0.8 | AV23: Defend | AW23: Recon | BL23: 24 | BM23: 1.4 | BN23: west;town;east | BO23: 2 | BQ23: 22 | BR23: 1 | BV23: TRUE | BW23: linh | BX23: 6 | BY23: 420 | CG23: 840 | CR23: Night | CS23: 360 | CT23: Assets/MachineBrigade/Resources/Data/campaign.json: missions[21] | CU23: {"id":"c2s1","chapter":2,"side":true,"after":"c2m03","map":"dunebreak","weather":"Night","goal":"Recon","speaker":"linh","points":["west","town","east"],"timeLimit":840,"reinforcements":1,"enemyAi":"commander","enemyStance":"Defend","difficulty":"Normal","enemyCp":12,"enemyIncome":0.8,"enemyDeck":["armored_car","light_tank","main_battle_tank","ifv","tank_destroyer","mortar_carrier"],"playerCp":24,"playerIncome":1.4,"rarePrints":22,"starTime":420,"starLosses":6,"challenge":{"kind":"NoAircraft"},"radio":[{"key":"radio.linh.c2s1.1","on":"Start"}],"missionEvents":["nadia_intel","loot_drop"],"coins":450,"xp":360,"prints":2}
A24: c2s2 | B24: 2 | C24: redrock | G24: c2m07 | I24: dieuhau | J24: TRUE | K24: 7 | L24: co_kich_ban | AD24: 450 | AO24: Normal | AP24: waves | AW24: ShootDown | AZ24: 10 | BK24: 34 | BL24: 24 | BM24: 1.4 | BO24: 2 | BV24: TRUE | BW24: dieuhau | BX24: 8 | BY24: 540 | CG24: 1100 | CH24: Rare | CJ24: 30 | CK24: 0.35 | CL24: 40 | CM24: 12 | CN24: 5 | CO24: attack_helicopter;attack_helicopter;scout_heli;armored_car;light_tank | CP24: 2 | CR24: Clear | CS24: 360 | CT24: Assets/MachineBrigade/Resources/Data/campaign.json: missions[22] | CU24: {"id":"c2s2","chapter":2,"side":true,"after":"c2m07","map":"redrock","weather":"Clear","goal":"ShootDown","speaker":"dieuhau","killsNeeded":10,"timeLimit":1100,"enemyAi":"waves","difficulty":"Normal","playerCp":24,"playerIncome":1.4,"playerCap":34,"waves":{"first":30,"interval":40,"size":2,"grow":0.35,"maxSize":5,"maxAlive":12,"roster":["attack_helicopter","attack_helicopter","scout_heli","armored_car","light_tank"]},"towerGear":"Rare","starTime":540,"starLosses":8,"radio":[{"key":"radio.dieuhau.c2s2.1","on":"Start"}],"missionEvents":["air_wave","loot_repair"],"fixedDeck":{"vehicleIds":["zu23_technical","aa_vehicle","heavy_aa","aa_gun_vehicle","armored_car","ifv","engineer_vehicle","ammo_carrier"],"supportIds":["artillery_barrage","repair_drop"],"placedAllies":[],"loanedCards":["heavy_aa","aa_gun_vehicle"],"specialRules":["warnedAirWaves"],"status":"MAKE_FIRST"},"coins":450,"xp":360,"prints":2}
A25: c3m01 | B25: 3 | C25: whiteout | D25: orlov | E25: main_battle_tank;ifv;mlrs;artillery;mortar_carrier;sam_launcher;aa_vehicle;attack_helicopter | F25: sam_launcher | I25: khai | J25: FALSE | K25: 7 | L25: co_kich_ban | AD25: 165 | AO25: Normal | AP25: commander | AR25: 14 | AT25: 0.85 | AV25: Defend | AW25: Capture | BJ25: Anchor | BL25: 24 | BM25: 1.4 | BN25: west;town;east | BO25: 1 | BR25: 2 | BX25: 8 | BY25: 540 | CR25: Snow | CS25: 135 | CT25: Assets/MachineBrigade/Resources/Data/campaign.json: missions[23] | CU25: {"id":"c3m01","chapter":3,"map":"whiteout","weather":"Snow","goal":"Capture","points":["west","town","east"],"general":"orlov","reinforcements":2,"enemyAi":"commander","enemyStance":"Defend","difficulty":"Normal","enemyCp":14,"enemyIncome":0.85,"enemyDeck":["main_battle_tank","ifv","mlrs","artillery","mortar_carrier","sam_launcher","aa_vehicle","attack_helicopter"],"playerCp":24,"playerIncome":1.4,"playerBase":"Anchor","starTime":540,"starLosses":8,"radio":[{"key":"radio.orlov.c3m01.1","on":"Start"},{"key":"radio.khai.c3m01.2","on":"Start"}],"missionEvents":["orlov_barrage","accord_wave"],"unlocks":["sam_launcher"],"coins":165,"xp":135,"prints":1}
A26: c3m02 | B26: 3 | C26: frostpeak | D26: orlov | E26: main_battle_tank;ifv;mlrs;artillery;mortar_carrier;sam_launcher;aa_vehicle;attack_helicopter | F26: attack_helicopter | I26: linh | J26: FALSE | K26: 7 | L26: co_kich_ban | AB26: NoStrikes | AD26: 170 | AO26: Normal | AP26: both | AR26: 15 | AT26: 0.9 | AV26: Defend | AW26: Destroy | BB26: m07 | BJ26: Anchor | BL26: 24 | BM26: 1.4 | BO26: 1 | BR26: 2 | BX26: 8 | BY26: 480 | CB26: 5 | CF26: radar_station_prop | CG26: 840 | CJ26: 60 | CK26: 0.4 | CL26: 55 | CM26: 16 | CN26: 5 | CO26: scout_heli;attack_helicopter;armored_car | CP26: 2 | CR26: Snow | CS26: 135 | CT26: Assets/MachineBrigade/Resources/Data/campaign.json: missions[24] | CU26: {"id":"c3m02","chapter":3,"map":"frostpeak","weather":"Snow","goal":"Destroy","legacy":"m07","targets":["radar_station_prop"],"timeLimit":840,"targetHealth":5,"general":"orlov","reinforcements":2,"units":[{"def":"heavy_tank","team":1,"x":-56.25,"z":93.75,"heading":225},{"def":"sam_launcher","team":1,"x":-75,"z":116.25,"heading":225},{"def":"aa_vehicle","team":1,"x":-37.5,"z":112.5,"heading":225},{"def":"main_battle_tank","team":1,"x":-41.25,"z":97.5,"heading":225},{"def":"mortar_carrier","team":1,"x":-60,"z":128,"heading":225}],"enemyAi":"both","enemyStance":"Defend","difficulty":"Normal","enemyCp":15,"enemyIncome":0.9,"enemyDeck":["main_battle_tank","ifv","mlrs","artillery","mortar_carrier","sam_launcher","aa_vehicle","attack_helicopter"],"waves":{"first":60,"interval":55,"size":2,"grow":0.4,"maxSize":5,"maxAlive":16,"roster":["scout_heli","attack_helicopter","armored_car"]},"playerCp":24,"playerIncome":1.4,"playerBase":"Anchor","starTime":480,"starLosses":8,"challenge":{"kind":"NoStrikes"},"radio":[{"key":"radio.linh.c3m02.1","on":"Start"}],"unlocks":["attack_helicopter"],"missionEvents":["counter_battery","enemy_wave","nadia_intel"],"coins":170,"xp":135,"prints":1}
A27: c3m03 | B27: 3 | C27: frostpeak | D27: orlov | E27: light_tank;ifv;main_battle_tank;heavy_tank;mortar_carrier;flame_tank;attack_helicopter | F27: scout_heli | I27: khai | J27: FALSE | K27: 7 | L27: co_kich_ban | AD27: 175 | AO27: Normal | AP27: both | AR27: 9 | AT27: 0.85 | AV27: Attack | AW27: Hold | AX27: 210 | BB27: m08 | BJ27: Anchor | BK27: 40 | BL27: 24 | BM27: 1.2 | BN27: town | BO27: 2 | BR27: 2 | BX27: 10 | BY27: 0 | CJ27: 45 | CK27: 0.3 | CL27: 50 | CM27: 10 | CN27: 4 | CO27: light_tank;main_battle_tank;ifv;mortar_carrier;attack_helicopter;flame_tank | CP27: 2 | CR27: Fog | CS27: 140 | CT27: Assets/MachineBrigade/Resources/Data/campaign.json: missions[26] | CU27: {"id":"c3m03","chapter":3,"map":"frostpeak","weather":"Fog","goal":"Hold","legacy":"m08","points":["town"],"holdSeconds":210,"general":"orlov","reinforcements":2,"units":[{"def":"main_battle_tank","team":0,"x":12.0,"z":0.0,"heading":45},{"def":"main_battle_tank","team":0,"x":7.48,"z":9.38,"heading":45},{"def":"aa_vehicle","team":0,"x":-2.67,"z":11.7,"heading":45},{"def":"light_tank","team":0,"x":-10.81,"z":5.21,"heading":45},{"def":"tank_destroyer","team":0,"x":-10.81,"z":-5.21,"heading":45},{"def":"heavy_tank","team":0,"x":-2.67,"z":-11.7,"heading":45},{"def":"mlrs","team":0,"x":7.48,"z":-9.38,"heading":45}],"enemyAi":"both","enemyStance":"Attack","difficulty":"Normal","enemyCp":9,"enemyIncome":0.85,"enemyDeck":["light_tank","ifv","main_battle_tank","heavy_tank","mortar_carrier","flame_tank","attack_helicopter"],"playerCp":24,"playerIncome":1.2,"playerCap":40,"playerBase":"Anchor","waves":{"first":45,"interval":50,"size":2,"grow":0.3,"maxSize":4,"maxAlive":10,"roster":["light_tank","main_battle_tank","ifv","mortar_carrier","attack_helicopter","flame_tank"]},"starTime":0,"starLosses":10,"tips":[{"at":20,"key":"tip.ammoIcons"}],"radio":[{"key":"radio.khai.c3m03.1","on":"Start"}],"missionEvents":["snowstorm","enemy_wave_late","supply_drop"],"unlocks":["scout_heli"],"coins":175,"xp":140,"prints":2}
A28: c3m04 | B28: 3 | C28: whiteout | D28: orlov | E28: main_battle_tank;ifv;mlrs;artillery;mortar_carrier;sam_launcher;aa_vehicle;attack_helicopter | F28: vehicle_hangar | I28: mai | J28: FALSE | K28: 7 | L28: co_kich_ban | AD28: 180 | AO28: Normal | AP28: both | AR28: 12 | AT28: 0.85 | AV28: Attack | AW28: Outpost | AX28: 180 | BJ28: Anchor | BK28: 36 | BL28: 26 | BM28: 1.45 | BN28: town | BO28: 2 | BR28: 2 | BW28: mai | BX28: 8 | BY28: 600 | CG28: 1100 | CJ28: 70 | CK28: 0.3 | CL28: 55 | CM28: 12 | CN28: 4 | CO28: light_tank;ifv;mortar_carrier;main_battle_tank | CP28: 2 | CR28: Night | CS28: 145 | CT28: Assets/MachineBrigade/Resources/Data/campaign.json: missions[27] | CU28: {"id":"c3m04","chapter":3,"map":"whiteout","weather":"Night","goal":"Outpost","points":["town"],"holdSeconds":180,"speaker":"mai","general":"orlov","reinforcements":2,"timeLimit":1100,"enemyAi":"both","enemyStance":"Attack","difficulty":"Normal","enemyCp":12,"enemyIncome":0.85,"enemyDeck":["main_battle_tank","ifv","mlrs","artillery","mortar_carrier","sam_launcher","aa_vehicle","attack_helicopter"],"playerCp":26,"playerIncome":1.45,"playerCap":36,"playerBase":"Anchor","waves":{"first":70,"interval":55,"size":2,"grow":0.3,"maxSize":4,"maxAlive":12,"roster":["light_tank","ifv","mortar_carrier","main_battle_tank"]},"starTime":600,"starLosses":8,"radio":[{"key":"radio.mai.c3m04.1","on":"Start"},{"key":"radio.orlov.c3m04.2","at":120}],"unlocks":["vehicle_hangar"],"missionEvents":["orlov_barrage","accord_relief","snowstorm","ice_crack"],"coins":180,"xp":145,"prints":2}
A29: c3m05 | B29: 3 | C29: whiteout | D29: orlov | E29: light_tank;main_battle_tank;ifv;mortar_carrier;aa_vehicle;attack_helicopter | F29: recon_drone | H29: mega_gunship | I29: dieuhau | J29: FALSE | K29: 14 | L29: co_kich_ban | U29: 225 | V29: 1.6 | X29: 60;60;-20;60;-40;-10;30;-30 | Y29: 84 | Z29: 84 | AB29: NoStrikes | AD29: 275 | AO29: Normal | AP29: commander | AR29: 12 | AT29: 0.85 | AV29: Attack | AW29: Boss | AY29: 2 | BB29: m03 | BJ29: Anchor | BK29: 36 | BL29: 26 | BM29: 1.45 | BO29: 2 | BR29: 2 | BU29: TRUE | BX29: 10 | BY29: 660 | CG29: 1140 | CR29: Clear | CS29: 220 | CT29: Assets/MachineBrigade/Resources/Data/campaign.json: missions[28] | CU29: {"id":"c3m05","chapter":3,"map":"whiteout","weather":"Clear","goal":"Boss","legacy":"m03","general":"orlov","timeLimit":1140,"reinforcements":2,"boss":{"def":"mega_gunship","x":84,"z":84,"heading":225,"route":[60,60,-20,60,-40,-10,30,-30],"health":1.6},"enemyAi":"commander","enemyStance":"Attack","difficulty":"Normal","enemyCp":12,"enemyIncome":0.85,"enemyDeck":["light_tank","main_battle_tank","ifv","mortar_carrier","aa_vehicle","attack_helicopter"],"playerCp":26,"playerIncome":1.45,"playerCap":36,"playerBase":"Anchor","starTime":660,"starLosses":10,"challenge":{"kind":"NoStrikes"},"radio":[{"key":"radio.dieuhau.c3m05.1","on":"Start"},{"key":"radio.orlov.c3m05.2","on":"Boss"},{"key":"radio.dieuhau.c3m05.3","on":"Win"},{"key":"radio.quaden.c3m05.q1","on":"Boss"},{"key":"radio.dieuhau.c3m05.q2","on":"Boss"}],"unlocks":["recon_drone"],"hqLevel":2,"setPiece":true,"missionEvents":["snowstorm","hawk_strike"],"coins":275,"xp":220,"prints":2}
A30: c3m06 | B30: 3 | C30: frostpeak | D30: orlov | E30: main_battle_tank;ifv;mlrs;artillery;mortar_carrier;sam_launcher;aa_vehicle;attack_helicopter | F30: mine_layer | I30: linh | J30: TRUE | K30: 8 | L30: co_kich_ban | AB30: Kills | AC30: 25 | AD30: 185 | AO30: Normal | AP30: commander | AR30: 14 | AT30: 0.9 | AV30: Defend | AW30: Hunt | BJ30: Anchor | BK30: 36 | BL30: 26 | BM30: 1.45 | BO30: 2 | BR30: 2 | BX30: 10 | BY30: 660 | CB30: 2.5 | CG30: 1100 | CR30: Night | CS30: 150 | CT30: Assets/MachineBrigade/Resources/Data/campaign.json: missions[29] | CU30: {"id":"c3m06","chapter":3,"map":"frostpeak","weather":"Night","goal":"Hunt","general":"orlov","timeLimit":1100,"targetHealth":2.5,"reinforcements":2,"hunt":[{"def":"mlrs","x":60,"z":70,"heading":225,"route":[80,90,40,60,70,40]},{"def":"artillery","x":-20,"z":100,"heading":225,"route":[-40,120,0,90,-30,80]},{"def":"mlrs","x":100,"z":20,"heading":225,"route":[110,-10,90,40,120,30]}],"units":[{"def":"main_battle_tank","team":1,"x":67.0,"z":70.0,"heading":225},{"def":"aa_vehicle","team":1,"x":56.5,"z":76.06,"heading":225},{"def":"tank_destroyer","team":1,"x":56.5,"z":63.94,"heading":225},{"def":"ifv","team":1,"x":-14.0,"z":100.0,"heading":225},{"def":"sam_launcher","team":1,"x":-26.0,"z":100.0,"heading":225},{"def":"heavy_tank","team":1,"x":106.0,"z":20.0,"heading":225},{"def":"mortar_carrier","team":1,"x":94.0,"z":20.0,"heading":225}],"enemyAi":"commander","enemyStance":"Defend","difficulty":"Normal","enemyCp":14,"enemyIncome":0.9,"enemyDeck":["main_battle_tank","ifv","mlrs","artillery","mortar_carrier","sam_launcher","aa_vehicle","attack_helicopter"],"playerCp":26,"playerIncome":1.45,"playerCap":36,"playerBase":"Anchor","starTime":660,"starLosses":10,"challenge":{"kind":"Kills","value":25},"radio":[{"key":"radio.linh.c3m06.1","on":"Start"},{"key":"radio.orlov.c3m06.2","at":150}],"missionEvents":["counter_battery",{"id":"intercept_files","reward":{"intel":"c3.tables"}},"enemy_wave"],"unlocks":["mine_layer"],"fixedDeck":{"vehicleIds":["scout_jeep","rocket_technical","command_vehicle","mortar_carrier","artillery","attack_helicopter","recon_drone","armored_car"],"supportIds":["artillery_barrage","airstrike"],"placedAllies":[],"loanedCards":["command_vehicle"],"specialRules":["nightGuns"],"status":"MAKE_FIRST"},"coins":185,"xp":150,"prints":2}
A31: c3m07 | B31: 3 | C31: whiteout | D31: orlov | E31: main_battle_tank;ifv;mlrs;artillery;mortar_carrier;sam_launcher;aa_vehicle;attack_helicopter | I31: khai | J31: FALSE | K31: 8 | L31: co_kich_ban | AB31: NoAircraft | AD31: 195 | AO31: Normal | AP31: both | AR31: 10 | AT31: 0.8 | AV31: Attack | AW31: Protect | BJ31: Anchor | BK31: 36 | BL31: 26 | BM31: 1.4 | BO31: 2 | BP31: 1 | BR31: 2 | BX31: 10 | BY31: 0 | CA31: 390 | CB31: 22 | CF31: log_cabin;barn | CJ31: 90 | CK31: 0.3 | CL31: 65 | CM31: 10 | CN31: 4 | CO31: light_tank;ifv;mortar_carrier;main_battle_tank;attack_helicopter | CP31: 2 | CR31: Fog | CS31: 155 | CT31: Assets/MachineBrigade/Resources/Data/campaign.json: missions[31] | CU31: {"id":"c3m07","chapter":3,"map":"whiteout","weather":"Fog","goal":"Protect","targets":["log_cabin","barn"],"protectNeeded":1,"targetHealth":22,"surviveSeconds":390,"general":"orlov","reinforcements":2,"enemyAi":"both","enemyStance":"Attack","difficulty":"Normal","enemyCp":10,"enemyIncome":0.8,"enemyDeck":["main_battle_tank","ifv","mlrs","artillery","mortar_carrier","sam_launcher","aa_vehicle","attack_helicopter"],"playerCp":26,"playerIncome":1.4,"playerCap":36,"playerBase":"Anchor","waves":{"first":90,"interval":65,"size":2,"grow":0.3,"maxSize":4,"maxAlive":10,"roster":["light_tank","ifv","mortar_carrier","main_battle_tank","attack_helicopter"]},"starTime":0,"starLosses":10,"challenge":{"kind":"NoAircraft"},"radio":[{"key":"radio.khai.c3m07.1","on":"Start"}],"missionEvents":["orlov_barrage","protect_civilians","snowstorm"],"coins":195,"xp":155,"prints":2}
A32: c3m08 | B32: 3 | C32: whiteout | I32: linh | J32: FALSE | K32: 7 | L32: co_kich_ban | AB32: Kills | AC32: 18 | AD32: 195 | AF32: 5 | AG32: supply_truck | AH32: 45 | AK32: 3 | AL32: -84.8;-74.2;-53;-53;-33;-33;0;0;-40;40;-71.25;71.25 | AM32: -100 | AN32: -100 | AO32: Normal | AP32: waves | AW32: Escort | BO32: 2 | BR32: 1 | BW32: linh | BX32: 6 | BY32: 360 | CG32: 1000 | CJ32: 20 | CK32: 0.45 | CL32: 30 | CM32: 13 | CN32: 6 | CO32: light_tank;ifv;mortar_carrier;attack_helicopter;main_battle_tank | CP32: 2 | CQ32: 80;60;40;100;100;10 | CR32: Night | CS32: 155 | CT32: Assets/MachineBrigade/Resources/Data/campaign.json: missions[32] | CU32: {"id":"c3m08","chapter":3,"map":"whiteout","weather":"Night","goal":"Escort","speaker":"linh","convoyCount":5,"convoyNeeded":3,"reinforcements":1,"timeLimit":1000,"convoy":{"def":"supply_truck","x":-100,"z":-100,"heading":45,"route":[-84.8,-74.2,-53,-53,-33,-33,0,0,-40,40,-71.25,71.25]},"units":[{"def":"main_battle_tank","team":0,"x":-84.0,"z":-90.0,"heading":45},{"def":"heavy_aa","team":0,"x":-93.0,"z":-84.8,"heading":45},{"def":"ifv","team":0,"x":-93.0,"z":-95.2,"heading":45}],"enemyAi":"waves","difficulty":"Normal","waves":{"first":20,"interval":30,"size":2,"grow":0.45,"maxSize":6,"maxAlive":13,"roster":["light_tank","ifv","mortar_carrier","attack_helicopter","main_battle_tank"],"spawns":[80,60,40,100,100,10]},"starTime":360,"starLosses":6,"challenge":{"kind":"Kills","value":18},"radio":[{"key":"radio.linh.c3m08.1","on":"Start"}],"missionEvents":["enemy_air_raid","snowstorm"],"coins":195,"xp":155,"prints":2}
A33: c3m09 | B33: 3 | C33: frostpeak | D33: orlov | I33: khai | J33: FALSE | K33: 8 | L33: co_kich_ban | AD33: 200 | AO33: Normal | AP33: commander | AQ33: Target | AR33: 10 | AS33: 2 | AT33: 0.34 | AV33: Defend | AW33: Duel | BJ33: Anchor | BK33: 38 | BL33: 28 | BM33: 2.25 | BO33: 2 | BR33: 1 | BS33: TRUE | BX33: 12 | BY33: 840 | CB33: 0.3 | CG33: 1800 | CR33: Clear | CS33: 160 | CT33: Assets/MachineBrigade/Resources/Data/campaign.json: missions[33] | CU33: {"id":"c3m09","chapter":3,"map":"frostpeak","weather":"Clear","goal":"Duel","targetHealth":0.3,"general":"orlov","enemyBase":"Target","enemyHq":2,"replay":true,"reinforcements":1,"timeLimit":1800,"units":[{"def":"artillery","team":0,"x":-80.0,"z":-86.0,"heading":45},{"def":"artillery","team":0,"x":-89.0,"z":-80.8,"heading":45},{"def":"mlrs","team":0,"x":-89.0,"z":-91.2,"heading":45}],"enemyAi":"commander","enemyStance":"Defend","difficulty":"Normal","enemyCp":10,"enemyIncome":0.34,"playerCp":28,"playerIncome":2.25,"playerCap":38,"playerBase":"Anchor","starTime":840,"starLosses":12,"radio":[{"key":"radio.orlov.c3m09.1","on":"Start"},{"key":"radio.orlov.c3m09.2","on":"Win"}],"missionEvents":["general_field","orlov_barrage","counter_battery"],"coins":200,"xp":160,"prints":2}
A34: c3m10 | B34: 3 | C34: frostpeak | D34: orlov | E34: main_battle_tank;ifv;mlrs;artillery;mortar_carrier;sam_launcher;aa_vehicle;attack_helicopter | I34: khai | J34: FALSE | K34: 14 | L34: co_kich_ban | AD34: 490 | AO34: Normal | AP34: both | AR34: 15 | AS34: 3 | AT34: 0.95 | AV34: Defend | AW34: Destroy | BB34: m09 | BC34: TRUE | BJ34: Anchor | BK34: 42 | BL34: 30 | BM34: 2 | BO34: 4 | BR34: 3 | BX34: 16 | BY34: 1380 | CI34: siege | CJ34: 80 | CK34: 0.3 | CL34: 60 | CM34: 12 | CN34: 5 | CO34: main_battle_tank;ifv;mlrs;attack_helicopter;heavy_tank | CP34: 2 | CQ34: 100;60;60;100 | CR34: Overcast | CS34: 390 | CT34: Assets/MachineBrigade/Resources/Data/campaign.json: missions[34] | CU34: {"id":"c3m10","chapter":3,"map":"frostpeak","variant":"siege","weather":"Overcast","goal":"Destroy","legacy":"m09","operation":true,"general":"orlov","reinforcements":3,"enemyAi":"both","enemyStance":"Defend","difficulty":"Normal","enemyCp":15,"enemyIncome":0.95,"enemyDeck":["main_battle_tank","ifv","mlrs","artillery","mortar_carrier","sam_launcher","aa_vehicle","attack_helicopter"],"playerCp":30,"playerIncome":2.0,"playerCap":42,"playerBase":"Anchor","enemyHq":3,"waves":{"first":80,"interval":60,"size":2,"grow":0.3,"maxSize":5,"maxAlive":12,"roster":["main_battle_tank","ifv","mlrs","attack_helicopter","heavy_tank"],"spawns":[100,60,60,100]},"stages":[{"stage":"radar","goal":"Destroy","targets":["radar_station_prop"],"targetX":-56.25,"targetZ":116,"targetRadius":20,"targetHealth":3,"cp":8,"events":[{"at":"start","kind":"Radio","key":"radio.khai.c3m10.s1"}],"choices":[{"key":"depots","next":"depots"},{"key":"radars","next":"radars"}],"missionEvents":["counter_battery"]},{"stage":"depots","goal":"Destroy","targets":["fuel_depot"],"targetHealth":2,"cp":6,"next":"fortress","events":[{"at":"end","kind":"Income","team":1,"amount":0.7},{"at":"end","kind":"Radio","key":"radio.enemyWeakened"}]},{"stage":"radars","goal":"Destroy","targets":["radar_station_prop"],"targetX":79,"targetZ":79,"targetRadius":46,"targetHealth":2,"cp":6,"next":"fortress","events":[{"at":"end","kind":"Strike","team":0,"support":"airstrike","every":50},{"at":"end","kind":"Radio","key":"radio.alliedStrikes"}]},{"stage":"fortress","goal":"Boss","boss":{"def":"mobile_fortress","x":90,"z":90,"heading":225,"health":1.3},"cp":10,"events":[{"at":"start","kind":"Radio","key":"radio.orlov.c3m10.s4"}],"missionEvents":["hawk_strike"]},{"stage":"gate","goal":"Survive","surviveSeconds":300,"events":[{"at":"start","kind":"Radio","key":"radio.orlov.c3m10.s5"},{"at":"30","kind":"Reinforce","team":1,"units":["heavy_tank","mlrs","sam_launcher","main_battle_tank"]},{"at":"190","kind":"Reinforce","team":1,"units":["main_battle_tank","artillery","ifv"]}],"missionEvents":["enemy_counterattack","accord_wave"]}],"starTime":1380,"starLosses":16,"radio":[{"key":"radio.khai.c3m10.1","on":"Start"},{"key":"radio.khai.c3m10.2","on":"Win"},{"key":"radio.orlov.c3m10.q1","on":"Win"}],"missionEvents":["orlov_barrage","snowstorm"],"coins":490,"xp":390,"prints":4}
A35: c3m11 | B35: 3 | C35: frostpeak | D35: orlov | E35: main_battle_tank;ifv;mlrs;artillery;mortar_carrier;sam_launcher;aa_vehicle;attack_helicopter | F35: fighter_jet | I35: linh | J35: FALSE | K35: 7 | L35: co_kich_ban | AD35: 175 | AO35: Normal | AP35: commander | AR35: 14 | AT35: 0.85 | AV35: Defend | AW35: Capture | BJ35: None | BK35: 36 | BL35: 26 | BM35: 1.45 | BN35: west;town;east | BO35: 2 | BR35: 2 | BX35: 8 | BY35: 540 | CR35: Snow | CS35: 140 | CT35: Assets/MachineBrigade/Resources/Data/campaign.json: missions[25] | CU35: {"id":"c3m11","chapter":3,"map":"frostpeak","weather":"Snow","goal":"Capture","points":["west","town","east"],"general":"orlov","reinforcements":2,"enemyAi":"commander","enemyStance":"Defend","difficulty":"Normal","enemyCp":14,"enemyIncome":0.85,"enemyDeck":["main_battle_tank","ifv","mlrs","artillery","mortar_carrier","sam_launcher","aa_vehicle","attack_helicopter"],"playerCp":26,"playerIncome":1.45,"playerBase":"None","starTime":540,"starLosses":8,"playerCap":36,"radio":[{"key":"radio.linh.c3m11.1","on":"Start"},{"key":"radio.orlov.c3m11.2","on":"Win"}],"missionEvents":["orlov_barrage","loot_drop","skies_clear"],"unlocks":["fighter_jet"],"coins":175,"xp":140,"prints":2}
A36: c3m12 | B36: 3 | C36: frostpeak | D36: orlov | E36: main_battle_tank;ifv;mlrs;artillery;mortar_carrier;sam_launcher;aa_vehicle;attack_helicopter | I36: khai | J36: FALSE | K36: 7 | L36: co_kich_ban | AD36: 190 | AO36: Normal | AP36: waves | AW36: Survive | BJ36: None | BK36: 36 | BL36: 26 | BM36: 1.45 | BN36: east | BO36: 2 | BX36: 8 | BY36: 0 | CA36: 300 | CJ36: 18 | CK36: 0.6 | CL36: 30 | CM36: 16 | CN36: 8 | CO36: mortar_carrier;mlrs;ifv;main_battle_tank;artillery | CP36: 3 | CR36: Overcast | CS36: 150 | CT36: Assets/MachineBrigade/Resources/Data/campaign.json: missions[30] | CU36: {"id":"c3m12","chapter":3,"map":"frostpeak","weather":"Overcast","goal":"Survive","surviveSeconds":300,"points":["east"],"general":"orlov","enemyAi":"waves","difficulty":"Normal","playerCp":26,"playerIncome":1.45,"waves":{"first":18,"interval":30,"size":3,"grow":0.6,"maxSize":8,"maxAlive":16,"roster":["mortar_carrier","mlrs","ifv","main_battle_tank","artillery"]},"playerBase":"None","starTime":0,"starLosses":8,"enemyDeck":["main_battle_tank","ifv","mlrs","artillery","mortar_carrier","sam_launcher","aa_vehicle","attack_helicopter"],"playerCap":36,"radio":[{"key":"radio.khai.c3m12.1","on":"Start"},{"key":"radio.orlov.c3m12.2","at":70}],"missionEvents":["enemy_wave","snowstorm","supply_drop"],"coins":190,"xp":150,"prints":2}
A37: c3s1 | B37: 3 | C37: frostpeak | E37: main_battle_tank;ifv;mlrs;artillery;mortar_carrier;sam_launcher;aa_vehicle;attack_helicopter | G37: c3m03 | I37: linh | J37: FALSE | K37: 5 | L37: co_kich_ban | AD37: 560 | AO37: Normal | AP37: commander | AR37: 13 | AT37: 0.85 | AV37: Defend | AW37: Recon | BL37: 24 | BM37: 1.4 | BN37: west;town;east | BO37: 3 | BQ37: 26 | BR37: 1 | BV37: TRUE | BW37: linh | BX37: 6 | BY37: 420 | CG37: 840 | CR37: Fog | CS37: 450 | CT37: Assets/MachineBrigade/Resources/Data/campaign.json: missions[35] | CU37: {"id":"c3s1","chapter":3,"side":true,"after":"c3m03","map":"frostpeak","weather":"Fog","goal":"Recon","speaker":"linh","points":["west","town","east"],"timeLimit":840,"reinforcements":1,"enemyAi":"commander","enemyStance":"Defend","difficulty":"Normal","enemyCp":13,"enemyIncome":0.85,"enemyDeck":["main_battle_tank","ifv","mlrs","artillery","mortar_carrier","sam_launcher","aa_vehicle","attack_helicopter"],"playerCp":24,"playerIncome":1.4,"rarePrints":26,"starTime":420,"starLosses":6,"radio":[{"key":"radio.linh.c3s1.1","on":"Start"}],"missionEvents":["nadia_intel","snowstorm"],"coins":560,"xp":450,"prints":3}
A38: c3s2 | B38: 3 | C38: whiteout | D38: orlov | E38: main_battle_tank;ifv;mlrs;artillery;mortar_carrier;sam_launcher;aa_vehicle;attack_helicopter | G38: c3m07 | H38: fenrir | I38: linh | J38: FALSE | K38: 5 | L38: co_kich_ban | R38: behemoth | S38: 1.2 | U38: 45 | W38: fenrir | X38: -55;-60;-15;-30;20;-10 | Y38: -84 | Z38: -84 | AD38: 560 | AO38: Normal | AP38: commander | AR38: 12 | AT38: 0.85 | AV38: Defend | AW38: Boss | BK38: 36 | BL38: 26 | BM38: 1.45 | BO38: 3 | BR38: 2 | BT38: TRUE | BV38: TRUE | BX38: 10 | BY38: 660 | CG38: 1080 | CH38: Rare | CR38: Snow | CS38: 450 | CT38: Assets/MachineBrigade/Resources/Data/campaign.json: missions[36] | CU38: {"id":"c3s2","chapter":3,"side":true,"after":"c3m07","map":"whiteout","reversed":true,"weather":"Snow","goal":"Boss","general":"orlov","timeLimit":1080,"reinforcements":2,"boss":{"def":"fenrir","x":-84,"z":-84,"heading":45,"route":[-55,-60,-15,-30,20,-10],"fallback":"behemoth","fallbackHealth":1.2,"name":"fenrir"},"enemyAi":"commander","enemyStance":"Defend","difficulty":"Normal","enemyCp":12,"enemyIncome":0.85,"enemyDeck":["main_battle_tank","ifv","mlrs","artillery","mortar_carrier","sam_launcher","aa_vehicle","attack_helicopter"],"playerCp":26,"playerIncome":1.45,"playerCap":36,"starTime":660,"starLosses":10,"towerGear":"Rare","radio":[{"key":"radio.linh.c3s2.1","on":"Start"}],"missionEvents":["accord_artillery","loot_repair"],"coins":560,"xp":450,"prints":3}
A39: c4m01 | B39: 4 | C39: rustyard | D39: kessler | E39: wheeled_gun;ifv;main_battle_tank;heavy_tank;sam_launcher;fpv_carrier;mine_layer;mlrs | F39: command_vehicle | I39: khai | J39: FALSE | K39: 8 | L39: co_kich_ban | AD39: 220 | AO39: Normal | AP39: commander | AR39: 15 | AT39: 0.9 | AU39: town | AV39: Defend | AW39: Capture | BJ39: Anchor | BK39: 36 | BL39: 26 | BM39: 1.45 | BN39: west;town;east | BO39: 2 | BR39: 2 | BX39: 10 | BY39: 600 | CR39: Overcast | CS39: 175 | CT39: Assets/MachineBrigade/Resources/Data/campaign.json: missions[41] | CU39: {"id":"c4m01","chapter":4,"map":"rustyard","weather":"Overcast","goal":"Capture","points":["west","town","east"],"enemyOwns":["town"],"general":"kessler","reinforcements":2,"enemyAi":"commander","enemyStance":"Defend","difficulty":"Normal","enemyCp":15,"enemyIncome":0.9,"enemyDeck":["wheeled_gun","ifv","main_battle_tank","heavy_tank","sam_launcher","fpv_carrier","mine_layer","mlrs"],"playerCp":26,"playerIncome":1.45,"playerCap":36,"playerBase":"Anchor","starTime":600,"starLosses":10,"radio":[{"key":"radio.kessler.c4m01.1","on":"Start"},{"key":"radio.khai.c4m01.2","on":"Start"}],"unlocks":["command_vehicle"],"missionEvents":["rail_reinforcements","accord_wave","rain_sets_in"],"coins":220,"xp":175,"prints":2}
A40: c4m02 | B40: 4 | C40: ironport | D40: kessler | E40: main_battle_tank;heavy_tank;tank_destroyer;aa_vehicle;sam_launcher;mlrs;attack_helicopter;artillery | F40: tank_destroyer | I40: linh | J40: FALSE | K40: 7 | L40: co_kich_ban | AD40: 225 | AO40: Hard | AP40: commander | AR40: 15 | AT40: 0.7 | AU40: west;town;east | AV40: Defend | AW40: Capture | BB40: m10 | BE40: town | BK40: 36 | BL40: 26 | BM40: 1.85 | BN40: west;town;east | BO40: 2 | BR40: 3 | BX40: 12 | BY40: 600 | CG40: 1000 | CR40: Rain | CS40: 180 | CT40: Assets/MachineBrigade/Resources/Data/campaign.json: missions[42] | CU40: {"id":"c4m02","chapter":4,"map":"ironport","weather":"Rain","goal":"Capture","legacy":"m10","points":["west","town","east"],"outposts":["town"],"enemyOwns":["west","town","east"],"timeLimit":1000,"general":"kessler","reinforcements":3,"enemyAi":"commander","enemyStance":"Defend","difficulty":"Hard","enemyCp":15,"enemyIncome":0.7,"enemyDeck":["main_battle_tank","heavy_tank","tank_destroyer","aa_vehicle","sam_launcher","mlrs","attack_helicopter","artillery"],"playerCp":26,"playerIncome":1.85,"playerCap":36,"starTime":600,"starLosses":12,"radio":[{"key":"radio.linh.c4m02.1","on":"Start"}],"missionEvents":["landing_assault","nadia_intel","crane_fall"],"unlocks":["tank_destroyer"],"navStates":[{"id":"crane","initial":"standing","states":[{"name":"standing"},{"name":"fallen","blocks":[{"x":17,"z":131,"w":30,"d":5}]}]}],"coins":225,"xp":180,"prints":2}
A41: c4m03 | B41: 4 | C41: ironport | F41: wheeled_gun | I41: khai | J41: FALSE | K41: 7 | L41: co_kich_ban | AB41: Kills | AC41: 25 | AD41: 225 | AF41: 5 | AG41: supply_truck | AH41: 45 | AK41: 3 | AL41: -33.75;-33.75;-33.75;33.75;0;33.75;0;106.8;-56.25;106.8 | AM41: -105 | AN41: -105 | AO41: Normal | AP41: waves | AW41: Escort | BB41: m11 | BO41: 2 | BR41: 2 | BX41: 8 | BY41: 300 | CG41: 1100 | CJ41: 20 | CK41: 0.6 | CL41: 26 | CM41: 18 | CN41: 7 | CO41: armored_car;rocket_technical;light_tank;attack_helicopter;flame_tank | CP41: 3 | CQ41: 60;93;93;15;-96;60 | CR41: Fog | CS41: 180 | CT41: Assets/MachineBrigade/Resources/Data/campaign.json: missions[43] | CU41: {"id":"c4m03","chapter":4,"map":"ironport","weather":"Fog","goal":"Escort","legacy":"m11","convoyCount":5,"convoyNeeded":3,"timeLimit":1100,"reinforcements":2,"convoy":{"def":"supply_truck","x":-105,"z":-105,"heading":45,"route":[-33.75,-33.75,-33.75,33.75,0,33.75,0,106.8,-56.25,106.8]},"units":[{"def":"main_battle_tank","team":0,"x":-81.0,"z":-92.0,"heading":45},{"def":"main_battle_tank","team":0,"x":-88.0,"z":-85.0,"heading":45},{"def":"aa_vehicle","team":0,"x":-95.0,"z":-92.0,"heading":45},{"def":"armored_car","team":0,"x":-88.0,"z":-99.0,"heading":45}],"enemyAi":"waves","difficulty":"Normal","waves":{"first":20,"interval":26,"size":3,"grow":0.6,"maxSize":7,"maxAlive":18,"roster":["armored_car","rocket_technical","light_tank","attack_helicopter","flame_tank"],"spawns":[60,93,93,15,-96,60]},"starTime":300,"starLosses":8,"challenge":{"kind":"Kills","value":25},"radio":[{"key":"radio.khai.c4m03.1","on":"Start"}],"unlocks":["wheeled_gun"],"missionEvents":["landing_assault","hawk_strike","skies_clear"],"coins":225,"xp":180,"prints":2}
A42: c4m04 | B42: 4 | C42: rustyard | D42: kessler | E42: light_tank;ifv;main_battle_tank;aa_vehicle;tank_destroyer;mortar_carrier | F42: logistics_station | I42: linh | J42: FALSE | K42: 6 | L42: co_kich_ban | AB42: NoAircraft | AD42: 230 | AO42: Normal | AP42: commander | AR42: 16 | AT42: 0.9 | AV42: Defend | AW42: Recon | BB42: m19 | BK42: 36 | BL42: 24 | BM42: 1.35 | BN42: west;town;east | BO42: 2 | BR42: 2 | BW42: linh | BX42: 10 | BY42: 420 | CG42: 900 | CR42: Fog | CS42: 185 | CT42: Assets/MachineBrigade/Resources/Data/campaign.json: missions[44] | CU42: {"id":"c4m04","chapter":4,"map":"rustyard","weather":"Fog","goal":"Recon","legacy":"m19","points":["west","town","east"],"timeLimit":900,"speaker":"linh","general":"kessler","reinforcements":2,"enemyAi":"commander","enemyStance":"Defend","difficulty":"Normal","enemyCp":16,"enemyIncome":0.9,"enemyDeck":["light_tank","ifv","main_battle_tank","aa_vehicle","tank_destroyer","mortar_carrier"],"playerCp":24,"playerIncome":1.35,"playerCap":36,"starTime":420,"starLosses":10,"challenge":{"kind":"NoAircraft"},"radio":[{"key":"radio.linh.c4m04.1","on":"Start"}],"unlocks":["logistics_station"],"missionEvents":["nadia_intel","rail_reinforcements"],"coins":230,"xp":185,"prints":2}
A43: c4m05 | B43: 4 | C43: ironport | D43: kessler | E43: main_battle_tank;heavy_tank;aa_vehicle;sam_launcher;attack_helicopter;attack_jet | F43: field_tower | H43: armored_train | I43: khai | J43: TRUE | K43: 15 | L43: co_kich_ban | U43: 270 | V43: 1.6 | X43: 75;106.8;0;106.8;-75;106.8;-138.75;106.8 | Y43: 128 | Z43: 106.8 | AB43: NoStrikes | AD43: 350 | AO43: Normal | AP43: commander | AR43: 10 | AT43: 0.85 | AV43: Attack | AW43: Intercept | BB43: m12 | BK43: 36 | BL43: 28 | BM43: 1.4 | BO43: 3 | BR43: 3 | BX43: 8 | BY43: 480 | CG43: 1200 | CR43: Night | CS43: 280 | CT43: Assets/MachineBrigade/Resources/Data/campaign.json: missions[45] | CU43: {"id":"c4m05","chapter":4,"map":"ironport","weather":"Night","goal":"Intercept","legacy":"m12","timeLimit":1200,"general":"kessler","reinforcements":3,"boss":{"def":"armored_train","x":128,"z":106.8,"heading":270,"route":[75,106.8,0,106.8,-75,106.8,-138.75,106.8],"health":1.6},"units":[{"def":"main_battle_tank","team":0,"x":-93.75,"z":56.25,"heading":45},{"def":"light_tank","team":0,"x":-82.5,"z":63.75,"heading":45},{"def":"tank_destroyer","team":0,"x":-101.25,"z":71.25,"heading":45},{"def":"tank_destroyer","team":0,"x":-71.25,"z":82.5,"heading":45},{"def":"mlrs","team":0,"x":-112.5,"z":41.25,"heading":45},{"def":"heavy_tank","team":0,"x":-56.25,"z":86.25,"heading":90},{"def":"heavy_tank","team":0,"x":-45,"z":93.75,"heading":90}],"enemyAi":"commander","enemyStance":"Attack","difficulty":"Normal","enemyCp":10,"enemyIncome":0.85,"enemyDeck":["main_battle_tank","heavy_tank","aa_vehicle","sam_launcher","attack_helicopter","attack_jet"],"playerCp":28,"playerIncome":1.4,"playerCap":36,"starTime":480,"starLosses":8,"challenge":{"kind":"NoStrikes"},"radio":[{"key":"radio.kessler.c4m05.1","on":"Start"},{"key":"radio.khai.c4m05.2","on":"Boss"},{"key":"radio.kessler.c4m05.3","on":"Win"}],"unlocks":["field_tower"],"missionEvents":["landing_assault","accord_artillery","crane_fall"],"fixedDeck":{"vehicleIds":["engineer_vehicle","vbied","mine_layer","tank_destroyer","artillery","wheeled_gun","recoilless_jeep","scout_jeep"],"supportIds":["remote_mines","artillery_barrage"],"placedAllies":[],"loanedCards":["recoilless_jeep","remote_mines"],"specialRules":["trainPrep"],"status":"MAKE_FIRST","prepSeconds":60},"navStates":[{"id":"crane","initial":"standing","states":[{"name":"standing"},{"name":"fallen","blocks":[{"x":17,"z":131,"w":30,"d":5}]}]}],"coins":350,"xp":280,"prints":3}
A44: c4m06 | B44: 4 | C44: lighthousebay | D44: kessler | E44: wheeled_gun;ifv;main_battle_tank;heavy_tank;sam_launcher;fpv_carrier;mine_layer;mlrs | H44: scylla | I44: khai | J44: TRUE | K44: 15 | L44: co_kich_ban | R44: leviathan | S44: 0.5 | U44: 45 | W44: scylla | Y44: 42.4 | Z44: -127.3 | AD44: 395 | AO44: Normal | AP44: commander | AR44: 12 | AT44: 0.85 | AV44: Defend | AW44: Boss | BJ44: None | BK44: 38 | BL44: 28 | BM44: 1.5 | BO44: 4 | BR44: 3 | BX44: 12 | BY44: 720 | CG44: 1500 | CR44: Fog | CS44: 315 | CT44: Assets/MachineBrigade/Resources/Data/campaign.json: missions[56] | CU44: {"id":"c4m06","chapter":4,"map":"lighthousebay","weather":"Fog","goal":"Boss","timeLimit":1500,"general":"kessler","reinforcements":3,"boss":{"def":"scylla","x":42.4,"z":-127.3,"heading":45,"name":"scylla","fallback":"leviathan","fallbackHealth":0.5},"units":[{"def":"artillery","team":0,"x":-79.0,"z":-86.0,"heading":45},{"def":"mlrs","team":0,"x":-82.5,"z":-79.94,"heading":45},{"def":"main_battle_tank","team":0,"x":-89.5,"z":-79.94,"heading":45},{"def":"aa_vehicle","team":0,"x":-93.0,"z":-86.0,"heading":45},{"def":"tank_destroyer","team":0,"x":-89.5,"z":-92.06,"heading":45},{"def":"ifv","team":0,"x":-82.5,"z":-92.06,"heading":45}],"enemyAi":"commander","enemyStance":"Defend","difficulty":"Normal","enemyCp":12,"enemyIncome":0.85,"enemyDeck":["wheeled_gun","ifv","main_battle_tank","heavy_tank","sam_launcher","fpv_carrier","mine_layer","mlrs"],"playerCp":28,"playerIncome":1.5,"playerCap":38,"playerBase":"None","starTime":720,"starLosses":12,"radio":[{"key":"radio.kessler.c4m06.1","on":"Start"}],"missionEvents":["landing_assault","skies_clear"],"fixedDeck":{"vehicleIds":["river_patrol_boat","river_gunboat","ifv","railgun_truck","light_tank","attack_helicopter","scout_heli","aa_vehicle"],"supportIds":["artillery_barrage","repair_drop"],"placedAllies":[],"loanedCards":["river_patrol_boat","river_gunboat"],"specialRules":["seaFogLighthouse"],"status":"MAKE_FIRST"},"coins":395,"xp":315,"prints":4}
A45: c4m07 | B45: 4 | C45: ironport | D45: kessler | E45: wheeled_gun;ifv;main_battle_tank;heavy_tank;sam_launcher;fpv_carrier;mine_layer;mlrs | F45: heavy_aa | I45: khai | J45: FALSE | K45: 7 | L45: co_kich_ban | AB45: NoAircraft | AD45: 240 | AO45: Normal | AP45: both | AR45: 11 | AT45: 0.85 | AV45: Attack | AW45: Protect | BJ45: Anchor | BK45: 36 | BL45: 28 | BM45: 1.45 | BO45: 2 | BP45: 1 | BR45: 2 | BT45: TRUE | BX45: 10 | BY45: 0 | CA45: 420 | CB45: 14 | CF45: factory;office_block | CJ45: 90 | CK45: 0.3 | CL45: 65 | CM45: 10 | CN45: 4 | CO45: ifv;main_battle_tank;mine_layer;wheeled_gun;attack_helicopter | CP45: 2 | CR45: Overcast | CS45: 190 | CT45: Assets/MachineBrigade/Resources/Data/campaign.json: missions[47] | CU45: {"id":"c4m07","chapter":4,"map":"ironport","reversed":true,"weather":"Overcast","goal":"Protect","targets":["factory","office_block"],"protectNeeded":1,"targetHealth":14,"surviveSeconds":420,"general":"kessler","reinforcements":2,"enemyAi":"both","enemyStance":"Attack","difficulty":"Normal","enemyCp":11,"enemyIncome":0.85,"enemyDeck":["wheeled_gun","ifv","main_battle_tank","heavy_tank","sam_launcher","fpv_carrier","mine_layer","mlrs"],"playerCp":28,"playerIncome":1.45,"playerCap":36,"playerBase":"Anchor","waves":{"first":90,"interval":65,"size":2,"grow":0.3,"maxSize":4,"maxAlive":10,"roster":["ifv","main_battle_tank","mine_layer","wheeled_gun","attack_helicopter"]},"starTime":0,"starLosses":10,"challenge":{"kind":"NoAircraft"},"radio":[{"key":"radio.khai.c4m07.1","on":"Start"}],"missionEvents":["landing_assault","supply_raid","accord_relief"],"unlocks":["heavy_aa"],"coins":240,"xp":190,"prints":2}
A46: c4m08 | B46: 4 | C46: rustyard | D46: kessler | E46: wheeled_gun;ifv;main_battle_tank;heavy_tank;sam_launcher;fpv_carrier;mine_layer;mlrs | F46: reinforcements | I46: linh | J46: FALSE | K46: 7 | L46: co_kich_ban | AB46: Kills | AC46: 25 | AD46: 245 | AO46: Normal | AP46: commander | AR46: 15 | AT46: 0.9 | AV46: Defend | AW46: Hunt | BJ46: Anchor | BK46: 36 | BL46: 28 | BM46: 1.45 | BO46: 2 | BR46: 2 | BX46: 10 | BY46: 660 | CB46: 1.5 | CG46: 1500 | CR46: Night | CS46: 195 | CT46: Assets/MachineBrigade/Resources/Data/campaign.json: missions[49] | CU46: {"id":"c4m08","chapter":4,"map":"rustyard","weather":"Night","goal":"Hunt","general":"kessler","timeLimit":1500,"targetHealth":1.5,"reinforcements":2,"hunt":[{"def":"mine_layer","x":60,"z":70,"heading":225,"route":[90,60,40,80,60,40]},{"def":"mine_layer","x":-20,"z":90,"heading":225,"route":[-50,100,0,70,-30,60]},{"def":"mine_layer","x":80,"z":-10,"heading":225,"route":[90,-30,60,10,90,25]}],"units":[{"def":"main_battle_tank","team":1,"x":67.0,"z":70.0,"heading":225},{"def":"sam_launcher","team":1,"x":53.0,"z":70.0,"heading":225},{"def":"wheeled_gun","team":1,"x":-14.0,"z":90.0,"heading":225},{"def":"ifv","team":1,"x":-26.0,"z":90.0,"heading":225},{"def":"heavy_tank","team":1,"x":86.0,"z":-10.0,"heading":225},{"def":"aa_vehicle","team":1,"x":74.0,"z":-10.0,"heading":225}],"enemyAi":"commander","enemyStance":"Defend","difficulty":"Normal","enemyCp":15,"enemyIncome":0.9,"enemyDeck":["wheeled_gun","ifv","main_battle_tank","heavy_tank","sam_launcher","fpv_carrier","mine_layer","mlrs"],"playerCp":28,"playerIncome":1.45,"playerCap":36,"playerBase":"Anchor","starTime":660,"starLosses":10,"challenge":{"kind":"Kills","value":25},"radio":[{"key":"radio.linh.c4m08.1","on":"Start"},{"key":"radio.linh.c4m08.d1","on":"Win"}],"missionEvents":["rail_reinforcements","enemy_barrage"],"unlocks":["reinforcements"],"coins":245,"xp":195,"prints":2}
A47: c4m09 | B47: 4 | C47: ironport | D47: kessler | I47: khai | J47: FALSE | K47: 8 | L47: co_kich_ban | AD47: 255 | AO47: Normal | AP47: commander | AQ47: Target | AR47: 11 | AS47: 2 | AT47: 0.34 | AV47: Defend | AW47: Duel | BJ47: Anchor | BK47: 40 | BL47: 30 | BM47: 2.3 | BO47: 2 | BR47: 1 | BS47: TRUE | BX47: 14 | BY47: 900 | CB47: 0.3 | CG47: 1800 | CR47: Storm | CS47: 205 | CT47: Assets/MachineBrigade/Resources/Data/campaign.json: missions[51] | CU47: {"id":"c4m09","chapter":4,"map":"ironport","weather":"Storm","goal":"Duel","targetHealth":0.3,"general":"kessler","enemyBase":"Target","enemyHq":2,"replay":true,"reinforcements":1,"timeLimit":1800,"units":[{"def":"artillery","team":0,"x":-80.0,"z":-86.0,"heading":45},{"def":"artillery","team":0,"x":-89.0,"z":-80.8,"heading":45},{"def":"mlrs","team":0,"x":-89.0,"z":-91.2,"heading":45}],"enemyAi":"commander","enemyStance":"Defend","difficulty":"Normal","enemyCp":11,"enemyIncome":0.34,"playerCp":30,"playerIncome":2.3,"playerCap":40,"playerBase":"Anchor","starTime":900,"starLosses":14,"radio":[{"key":"radio.kessler.c4m09.1","on":"Start"},{"key":"radio.kessler.c4m09.2","on":"Win"}],"missionEvents":["general_field","landing_assault","hawk_strike"],"coins":255,"xp":205,"prints":2}
A48: c4m10 | B48: 4 | C48: ironport | D48: kessler | E48: wheeled_gun;ifv;main_battle_tank;heavy_tank;sam_launcher;fpv_carrier;mine_layer;mlrs | F48: railgun_truck | I48: khai | J48: FALSE | K48: 8 | L48: co_kich_ban | AD48: 460 | AO48: Normal | AP48: both | AR48: 16 | AT48: 0.95 | AV48: Defend | AW48: Capture | BF48: 146 | BG48: 146 | BH48: -146 | BI48: -146 | BJ48: Anchor | BK48: 42 | BL48: 30 | BM48: 1.7 | BO48: 4 | BR48: 3 | BS48: TRUE | BU48: TRUE | BX48: 18 | BY48: 1380 | CJ48: 90 | CK48: 0.3 | CL48: 65 | CM48: 12 | CN48: 5 | CO48: ifv;main_battle_tank;wheeled_gun;attack_helicopter;heavy_tank | CP48: 2 | CR48: Clear | CS48: 370 | CT48: Assets/MachineBrigade/Resources/Data/campaign.json: missions[52] | CU48: {"id":"c4m10","chapter":4,"map":"ironport","weather":"Clear","goal":"Capture","general":"kessler","reinforcements":3,"playArea":{"minX":-146,"minZ":-146,"maxX":146,"maxZ":146},"enemyAi":"both","enemyStance":"Defend","difficulty":"Normal","enemyCp":16,"enemyIncome":0.95,"enemyDeck":["wheeled_gun","ifv","main_battle_tank","heavy_tank","sam_launcher","fpv_carrier","mine_layer","mlrs"],"playerCp":30,"playerIncome":1.7,"playerCap":42,"playerBase":"Anchor","waves":{"first":90,"interval":65,"size":2,"grow":0.3,"maxSize":5,"maxAlive":12,"roster":["ifv","main_battle_tank","wheeled_gun","attack_helicopter","heavy_tank"]},"stages":[{"stage":"yard","goal":"Capture","points":["east"],"enemyOwns":["west","town","east"],"cp":8,"events":[{"at":"start","kind":"Radio","key":"radio.khai.c4m10.s1"}],"choices":[{"key":"crane","next":"crane"},{"key":"signal","next":"signal"}],"missionEvents":["landing_assault"]},{"stage":"crane","goal":"Destroy","targets":["fuel_tank","rail_tanker"],"targetX":45,"targetZ":-85,"targetRadius":30,"targetHealth":2,"cp":6,"next":"factories","events":[{"at":"end","kind":"Income","team":1,"amount":0.7},{"at":"end","kind":"Radio","key":"radio.enemyWeakened"}]},{"stage":"signal","goal":"Survive","points":["east"],"surviveSeconds":150,"cp":6,"next":"factories","events":[{"at":"end","kind":"Strike","team":0,"support":"airstrike","every":55},{"at":"end","kind":"Radio","key":"radio.alliedStrikes"}]},{"stage":"factories","goal":"Capture","points":["town","west"],"enemyOwns":["town","west"],"cp":10,"events":[{"at":"start","kind":"Reinforce","team":1,"units":["heavy_tank","wheeled_gun","sam_launcher"]}]},{"stage":"works","goal":"Survive","points":["town"],"surviveSeconds":240,"cp":8,"events":[{"at":"30","kind":"Reinforce","team":1,"units":["main_battle_tank","ifv","mine_layer"]}]},{"stage":"tempest","goal":"Boss","boss":{"def":"behemoth_tempest","x":-56,"z":100,"heading":180,"health":1.8},"cp":8,"events":[{"at":"start","kind":"Radio","key":"radio.kessler.c4m10.s4"}]},{"stage":"quay","goal":"Survive","points":["west"],"surviveSeconds":540,"events":[{"at":"20","kind":"Reinforce","team":1,"units":["main_battle_tank","ifv","fpv_carrier","mlrs"]},{"at":"200","kind":"Reinforce","team":1,"units":["heavy_tank","wheeled_gun","sam_launcher"]}],"missionEvents":["accord_wave"]}],"starTime":1380,"starLosses":18,"radio":[{"key":"radio.khai.c4m10.1","on":"Start"},{"key":"radio.khai.c4m10.2","on":"Win"}],"unlocks":["railgun_truck"],"replay":true,"setPiece":true,"missionEvents":["rail_reinforcements"],"coins":460,"xp":370,"prints":4}
A49: c4m11 | B49: 4 | C49: lighthousebay | D49: kessler | E49: wheeled_gun;ifv;main_battle_tank;heavy_tank;sam_launcher;fpv_carrier;mine_layer;mlrs | F49: heavy_turret.coastal | I49: khai | J49: FALSE | K49: 16 | L49: co_kich_ban | AB49: Kills | AC49: 20 | AD49: 650 | AO49: Normal | AP49: commander | AR49: 10 | AT49: 0.7 | AV49: Defend | AW49: Capture | BC49: TRUE | BJ49: Anchor | BK49: 38 | BL49: 30 | BM49: 1.6 | BO49: 6 | BR49: 3 | BX49: 12 | BY49: 960 | CR49: Overcast | CS49: 520 | CT49: Assets/MachineBrigade/Resources/Data/campaign.json: missions[58] | CU49: {"id":"c4m11","chapter":4,"map":"lighthousebay","weather":"Overcast","goal":"Capture","general":"kessler","reinforcements":3,"units":[{"def":"artillery","team":0,"x":-79.0,"z":-86.0,"heading":45},{"def":"mlrs","team":0,"x":-82.5,"z":-79.94,"heading":45},{"def":"main_battle_tank","team":0,"x":-89.5,"z":-79.94,"heading":45},{"def":"aa_vehicle","team":0,"x":-93.0,"z":-86.0,"heading":45},{"def":"tank_destroyer","team":0,"x":-89.5,"z":-92.06,"heading":45},{"def":"ifv","team":0,"x":-82.5,"z":-92.06,"heading":45}],"enemyAi":"commander","enemyStance":"Defend","difficulty":"Normal","enemyCp":10,"enemyIncome":0.7,"enemyDeck":["wheeled_gun","ifv","main_battle_tank","heavy_tank","sam_launcher","fpv_carrier","mine_layer","mlrs"],"playerCp":30,"playerIncome":1.6,"playerCap":38,"playerBase":"Anchor","starTime":960,"starLosses":12,"challenge":{"kind":"Kills","value":20},"radio":[{"key":"radio.linh.c4m11.1","on":"Start"},{"key":"radio.mai.c4m11.2","at":20},{"key":"radio.khai.c4m11.3","on":"BossHalf"},{"key":"radio.khai.c4m11.4","on":"Win"},{"key":"radio.kessler.c4m11.q1","on":"Win"}],"unlocks":["heavy_turret.coastal"],"operation":true,"stages":[{"stage":"lighthouse","goal":"Capture","points":["east"],"enemyOwns":["west","town","east"],"cp":8,"choices":[{"key":"battery","next":"battery"},{"key":"strikes","next":"strikes"}],"events":[{"at":"start","kind":"Radio","key":"radio.khai.c4m11.s1"}],"missionEvents":["sea_fog"]},{"stage":"battery","goal":"Capture","points":["west"],"enemyOwns":["west"],"cp":8,"next":"village","events":[{"at":"end","kind":"Strike","team":0,"support":"artillery_barrage","every":50},{"at":"end","kind":"Radio","key":"radio.mai.c4m11.s2"}]},{"stage":"strikes","goal":"Survive","points":["east"],"surviveSeconds":150,"cp":8,"next":"village","events":[{"at":"end","kind":"Strike","team":0,"support":"airstrike","every":55},{"at":"end","kind":"Radio","key":"radio.alliedStrikes"}]},{"stage":"village","goal":"Capture","points":["town"],"enemyOwns":["town"],"cp":8,"events":[{"at":"start","kind":"Reinforce","team":1,"units":["main_battle_tank","ifv","wheeled_gun"]}],"missionEvents":["accord_wave"]},{"stage":"leviathan","goal":"Boss","boss":{"def":"leviathan","x":42.4,"z":-127.3,"heading":45,"name":"leviathan"},"cp":0,"events":[{"at":"start","kind":"Radio","key":"radio.kessler.c4m11.s4"}],"missionEvents":["accord_artillery"]}],"missionEvents":["landing_assault","hawk_strike","supply_drop"],"coins":650,"xp":520,"prints":6}
A50: c4m12 | B50: 4 | C50: ironport | D50: kessler | E50: wheeled_gun;ifv;main_battle_tank;heavy_tank;sam_launcher;fpv_carrier;mine_layer;mlrs | F50: mlrs | I50: adler | J50: FALSE | K50: 7 | L50: co_kich_ban | AD50: 235 | AO50: Hard | AP50: commander | AR50: 15 | AT50: 0.85 | AU50: west;town;east | AV50: Defend | AW50: Capture | BE50: town | BJ50: Anchor | BK50: 38 | BL50: 28 | BM50: 1.85 | BN50: west;town;east | BO50: 2 | BR50: 3 | BT50: TRUE | BW50: adler | BX50: 12 | BY50: 600 | CG50: 1000 | CR50: Rain | CS50: 190 | CT50: Assets/MachineBrigade/Resources/Data/campaign.json: missions[46] | CU50: {"id":"c4m12","chapter":4,"map":"ironport","reversed":true,"weather":"Rain","goal":"Capture","points":["west","town","east"],"outposts":["town"],"enemyOwns":["west","town","east"],"timeLimit":1000,"general":"kessler","reinforcements":3,"enemyAi":"commander","enemyStance":"Defend","difficulty":"Hard","enemyCp":15,"enemyIncome":0.85,"enemyDeck":["wheeled_gun","ifv","main_battle_tank","heavy_tank","sam_launcher","fpv_carrier","mine_layer","mlrs"],"playerCp":28,"playerIncome":1.85,"playerCap":38,"starTime":600,"starLosses":12,"playerBase":"Anchor","speaker":"adler","radio":[{"key":"radio.adler.c4m12.1","on":"Start"},{"key":"radio.adler.c4m12.2","on":"Win"}],"missionEvents":[{"id":"intercept_files","reward":{"intel":"c4.balance"}},"rail_reinforcements","sea_fog"],"unlocks":["mlrs"],"coins":235,"xp":190,"prints":2}
A51: c4m13 | B51: 4 | C51: rustyard | D51: kessler | E51: wheeled_gun;ifv;main_battle_tank;heavy_tank;sam_launcher;fpv_carrier;mine_layer;mlrs | I51: linh | J51: FALSE | K51: 8 | L51: co_kich_ban | AD51: 250 | AO51: Normal | AP51: both | AR51: 12 | AT51: 0.85 | AV51: Attack | AW51: Hold | AX51: 210 | BJ51: Anchor | BK51: 40 | BL51: 28 | BM51: 1.5 | BN51: town | BO51: 2 | BR51: 2 | BX51: 10 | BY51: 0 | CJ51: 45 | CK51: 0.3 | CL51: 50 | CM51: 10 | CN51: 4 | CO51: light_tank;main_battle_tank;ifv;mortar_carrier;attack_helicopter;flame_tank | CP51: 2 | CR51: Rain | CS51: 200 | CT51: Assets/MachineBrigade/Resources/Data/campaign.json: missions[50] | CU51: {"id":"c4m13","chapter":4,"map":"rustyard","weather":"Rain","goal":"Hold","points":["town"],"holdSeconds":210,"general":"kessler","reinforcements":2,"units":[{"def":"main_battle_tank","team":0,"x":12.0,"z":0.0,"heading":45},{"def":"main_battle_tank","team":0,"x":7.48,"z":9.38,"heading":45},{"def":"aa_vehicle","team":0,"x":-2.67,"z":11.7,"heading":45},{"def":"light_tank","team":0,"x":-10.81,"z":5.21,"heading":45},{"def":"tank_destroyer","team":0,"x":-10.81,"z":-5.21,"heading":45},{"def":"heavy_tank","team":0,"x":-2.67,"z":-11.7,"heading":45},{"def":"mlrs","team":0,"x":7.48,"z":-9.38,"heading":45}],"enemyAi":"both","enemyStance":"Attack","difficulty":"Normal","enemyCp":12,"enemyIncome":0.85,"enemyDeck":["wheeled_gun","ifv","main_battle_tank","heavy_tank","sam_launcher","fpv_carrier","mine_layer","mlrs"],"playerCp":28,"playerIncome":1.5,"playerCap":40,"playerBase":"Anchor","waves":{"first":45,"interval":50,"size":2,"grow":0.3,"maxSize":4,"maxAlive":10,"roster":["light_tank","main_battle_tank","ifv","mortar_carrier","attack_helicopter","flame_tank"]},"starTime":0,"starLosses":10,"radio":[{"key":"radio.linh.c4m13.1","on":"Start"},{"key":"radio.linh.c4m13.2","on":"Win"}],"missionEvents":["enemy_wave_late","supply_drop","skies_clear"],"coins":250,"xp":200,"prints":2}
A52: c4m14 | B52: 4 | C52: rustyard | D52: kessler | E52: wheeled_gun;ifv;main_battle_tank;heavy_tank;sam_launcher;fpv_carrier;mine_layer;mlrs | I52: khai | J52: FALSE | K52: 7 | L52: co_kich_ban | AD52: 260 | AO52: Normal | AP52: waves | AW52: Survive | BJ52: None | BK52: 38 | BL52: 28 | BM52: 1.5 | BN52: east | BO52: 2 | BX52: 8 | BY52: 0 | BZ52: c4.pursuit | CA52: 300 | CJ52: 18 | CK52: 0.6 | CL52: 30 | CM52: 16 | CN52: 8 | CO52: wheeled_gun;ifv;main_battle_tank;mine_layer;mlrs | CP52: 3 | CR52: Clear | CS52: 210 | CT52: Assets/MachineBrigade/Resources/Data/campaign.json: missions[53] | CU52: {"id":"c4m14","chapter":4,"map":"rustyard","weather":"Clear","goal":"Survive","surviveSeconds":300,"points":["east"],"general":"kessler","enemyAi":"waves","difficulty":"Normal","playerCp":28,"playerIncome":1.5,"waves":{"first":18,"interval":30,"size":3,"grow":0.6,"maxSize":8,"maxAlive":16,"roster":["wheeled_gun","ifv","main_battle_tank","mine_layer","mlrs"]},"playerBase":"None","starTime":0,"starLosses":8,"enemyDeck":["wheeled_gun","ifv","main_battle_tank","heavy_tank","sam_launcher","fpv_carrier","mine_layer","mlrs"],"playerCap":38,"radio":[{"key":"radio.kessler.c4m14.1","on":"Start"},{"key":"radio.khai.c4m14.2","on":"Win"}],"storyChoice":"c4.pursuit","missionEvents":["rail_reinforcements","enemy_air_raid",{"id":"plan_change","trigger":{"progress":0.6},"plan":{"goal":"Capture","points":["town"]},"lines":{"start":"radio.khai.ev.planChange.kessler.start"}}],"coins":260,"xp":210,"prints":2}
A53: c4m15 | B53: 4 | C53: lighthousebay | D53: kessler | E53: wheeled_gun;ifv;main_battle_tank;heavy_tank;sam_launcher;fpv_carrier;mine_layer;mlrs | I53: khai | J53: FALSE | K53: 7 | L53: co_kich_ban | AD53: 265 | AO53: Normal | AP53: both | AR53: 12 | AT53: 0.85 | AV53: Attack | AW53: Hold | AX53: 210 | BJ53: None | BK53: 40 | BL53: 28 | BM53: 1.5 | BN53: town | BO53: 2 | BR53: 2 | BX53: 10 | BY53: 0 | CJ53: 45 | CK53: 0.3 | CL53: 50 | CM53: 10 | CN53: 4 | CO53: light_tank;main_battle_tank;ifv;mortar_carrier;attack_helicopter;flame_tank | CP53: 2 | CR53: Night | CS53: 215 | CT53: Assets/MachineBrigade/Resources/Data/campaign.json: missions[57] | CU53: {"id":"c4m15","chapter":4,"map":"lighthousebay","weather":"Night","goal":"Hold","points":["town"],"holdSeconds":210,"general":"kessler","reinforcements":2,"units":[{"def":"main_battle_tank","team":0,"x":12.0,"z":0.0,"heading":45},{"def":"main_battle_tank","team":0,"x":7.48,"z":9.38,"heading":45},{"def":"aa_vehicle","team":0,"x":-2.67,"z":11.7,"heading":45},{"def":"light_tank","team":0,"x":-10.81,"z":5.21,"heading":45},{"def":"tank_destroyer","team":0,"x":-10.81,"z":-5.21,"heading":45},{"def":"heavy_tank","team":0,"x":-2.67,"z":-11.7,"heading":45},{"def":"mlrs","team":0,"x":7.48,"z":-9.38,"heading":45}],"enemyAi":"both","enemyStance":"Attack","difficulty":"Normal","enemyCp":12,"enemyIncome":0.85,"enemyDeck":["wheeled_gun","ifv","main_battle_tank","heavy_tank","sam_launcher","fpv_carrier","mine_layer","mlrs"],"playerCp":28,"playerIncome":1.5,"playerCap":40,"playerBase":"None","waves":{"first":45,"interval":50,"size":2,"grow":0.3,"maxSize":4,"maxAlive":10,"roster":["light_tank","main_battle_tank","ifv","mortar_carrier","attack_helicopter","flame_tank"]},"starTime":0,"starLosses":10,"radio":[{"key":"radio.khai.c4m15.1","on":"Start"},{"key":"radio.mai.c4m15.2","on":"Win"}],"missionEvents":["landing_assault","accord_wave","sea_fog"],"coins":265,"xp":215,"prints":2}
A54: c4m16 | B54: 4 | C54: ironport | D54: kessler | E54: wheeled_gun;ifv;main_battle_tank;heavy_tank;sam_launcher;fpv_carrier;mine_layer;mlrs | F54: armored_bulldozer | I54: linh | J54: FALSE | K54: 7 | L54: co_kich_ban | AD54: 245 | AO54: Normal | AP54: commander | AR54: 14 | AT54: 0.85 | AV54: Defend | AW54: Hunt | BJ54: None | BK54: 38 | BL54: 28 | BM54: 1.5 | BO54: 2 | BR54: 1 | BW54: linh | BX54: 8 | BY54: 480 | CB54: 1.8 | CG54: 1300 | CR54: Overcast | CS54: 195 | CT54: Assets/MachineBrigade/Resources/Data/campaign.json: missions[48] | CU54: {"id":"c4m16","chapter":4,"map":"ironport","weather":"Overcast","goal":"Hunt","timeLimit":1300,"targetHealth":1.8,"reinforcements":1,"hunt":[{"def":"command_vehicle","x":60,"z":60,"heading":225,"route":[80,40,40,80,70,90]},{"def":"command_vehicle","x":-30,"z":90,"heading":225,"route":[-60,100,0,80,-20,60]}],"units":[{"def":"main_battle_tank","team":1,"x":67.0,"z":60.0,"heading":225},{"def":"aa_vehicle","team":1,"x":56.5,"z":66.06,"heading":225},{"def":"ifv","team":1,"x":56.5,"z":53.94,"heading":225},{"def":"wheeled_gun","team":1,"x":-24.0,"z":90.0,"heading":225},{"def":"sam_launcher","team":1,"x":-36.0,"z":90.0,"heading":225}],"enemyAi":"commander","enemyStance":"Defend","difficulty":"Normal","enemyCp":14,"enemyIncome":0.85,"enemyDeck":["wheeled_gun","ifv","main_battle_tank","heavy_tank","sam_launcher","fpv_carrier","mine_layer","mlrs"],"playerCp":28,"playerIncome":1.5,"playerCap":38,"playerBase":"None","starTime":480,"starLosses":8,"general":"kessler","speaker":"linh","radio":[{"key":"radio.linh.c4m16.1","on":"Start"},{"key":"radio.linh.c4m16.2","on":"Win"}],"missionEvents":["rail_reinforcements","nadia_intel","rain_sets_in"],"unlocks":["armored_bulldozer"],"coins":245,"xp":195,"prints":2}
A55: c4m17 | B55: 4 | C55: ironport | D55: kessler | E55: wheeled_gun;ifv;main_battle_tank;heavy_tank;sam_launcher;fpv_carrier;mine_layer;mlrs | I55: khai | J55: FALSE | K55: 7 | L55: co_kich_ban | AA55: c4.pursuit | AD55: 415 | AO55: Normal | AP55: commander | AR55: 14 | AT55: 0.85 | AV55: Defend | AW55: Hunt | BD55: sea | BJ55: None | BK55: 38 | BL55: 28 | BM55: 1.5 | BO55: 2 | BR55: 1 | BT55: TRUE | BW55: khai | BX55: 8 | BY55: 480 | CB55: 1.8 | CG55: 1300 | CR55: Fog | CS55: 335 | CT55: Assets/MachineBrigade/Resources/Data/campaign.json: missions[54] | CU55: {"id":"c4m17","chapter":4,"map":"ironport","reversed":true,"weather":"Fog","goal":"Hunt","timeLimit":1300,"targetHealth":1.8,"reinforcements":1,"hunt":[{"def":"command_vehicle","x":-60,"z":-60,"heading":45,"route":[-80,-40,-40,-80,-70,-90]},{"def":"command_vehicle","x":30,"z":-90,"heading":45,"route":[60,-100,0,-80,20,-60]}],"units":[{"def":"main_battle_tank","team":1,"x":-67.0,"z":-60.0,"heading":45},{"def":"aa_vehicle","team":1,"x":-56.5,"z":-66.06,"heading":45},{"def":"ifv","team":1,"x":-56.5,"z":-53.94,"heading":45},{"def":"wheeled_gun","team":1,"x":24.0,"z":-90.0,"heading":45},{"def":"sam_launcher","team":1,"x":36.0,"z":-90.0,"heading":45}],"enemyAi":"commander","enemyStance":"Defend","difficulty":"Normal","enemyCp":14,"enemyIncome":0.85,"enemyDeck":["wheeled_gun","ifv","main_battle_tank","heavy_tank","sam_launcher","fpv_carrier","mine_layer","mlrs"],"playerCp":28,"playerIncome":1.5,"playerCap":38,"playerBase":"None","starTime":480,"starLosses":8,"general":"kessler","speaker":"khai","branch":"c4.pursuit","option":"sea","radio":[{"key":"radio.kessler.c4m17.1","on":"Start"},{"key":"radio.khai.c4m17.2","on":"Win"}],"missionEvents":["general_field","landing_assault"],"coins":415,"xp":335,"prints":2}
A56: c4m18 | B56: 4 | C56: ironport | D56: kessler | E56: wheeled_gun;ifv;main_battle_tank;heavy_tank;sam_launcher;fpv_carrier;mine_layer;mlrs | I56: linh | J56: FALSE | K56: 7 | L56: co_kich_ban | AA56: c4.pursuit | AD56: 260 | AO56: Normal | AP56: both | AR56: 12 | AT56: 0.85 | AV56: Attack | AW56: Hold | AX56: 300 | BD56: harbour | BJ56: Anchor | BK56: 38 | BL56: 28 | BM56: 1.5 | BN56: town | BO56: 2 | BQ56: 3 | BR56: 2 | BT56: TRUE | BW56: linh | BX56: 10 | BY56: 0 | CJ56: 90 | CK56: 0.3 | CL56: 65 | CM56: 10 | CN56: 4 | CO56: ifv;main_battle_tank;mine_layer;wheeled_gun;attack_helicopter | CP56: 2 | CR56: Fog | CS56: 210 | CT56: Assets/MachineBrigade/Resources/Data/campaign.json: missions[55] | CU56: {"id":"c4m18","chapter":4,"map":"ironport","reversed":true,"weather":"Fog","goal":"Hold","general":"kessler","reinforcements":2,"enemyAi":"both","enemyStance":"Attack","difficulty":"Normal","enemyCp":12,"enemyIncome":0.85,"enemyDeck":["wheeled_gun","ifv","main_battle_tank","heavy_tank","sam_launcher","fpv_carrier","mine_layer","mlrs"],"playerCp":28,"playerIncome":1.5,"playerCap":38,"playerBase":"Anchor","waves":{"first":90,"interval":65,"size":2,"grow":0.3,"maxSize":4,"maxAlive":10,"roster":["ifv","main_battle_tank","mine_layer","wheeled_gun","attack_helicopter"]},"starTime":0,"starLosses":10,"speaker":"linh","branch":"c4.pursuit","option":"harbour","rarePrints":3,"points":["town"],"holdSeconds":300,"radio":[{"key":"radio.linh.c4m18.1","on":"Start"},{"key":"radio.khai.c4m18.2","on":"Win"}],"missionEvents":["ferries","enemy_barrage","accord_relief"],"coins":260,"xp":210,"prints":2}
A57: c4s1 | B57: 4 | C57: rustyard | G57: c4m03 | I57: linh | J57: FALSE | K57: 5 | L57: co_kich_ban | AD57: 745 | AF57: 4 | AG57: supply_truck | AH57: 45 | AK57: 3 | AL57: -82.5;-82.5;-82.5;-60;-40;-33.75;20;-33.75;63.75;-60;63.75;-86.25 | AM57: -100 | AN57: -100 | AO57: Normal | AP57: waves | AW57: Escort | BO57: 4 | BQ57: 30 | BR57: 1 | BV57: TRUE | BW57: linh | BX57: 6 | BY57: 360 | CG57: 1000 | CJ57: 20 | CK57: 0.45 | CL57: 30 | CM57: 13 | CN57: 6 | CO57: ifv;wheeled_gun;light_tank;attack_helicopter | CP57: 2 | CQ57: 80;60;100;0;20;100 | CR57: Rain | CS57: 595 | CT57: Assets/MachineBrigade/Resources/Data/campaign.json: missions[59] | CU57: {"id":"c4s1","chapter":4,"side":true,"after":"c4m03","map":"rustyard","weather":"Rain","goal":"Escort","speaker":"linh","convoyCount":4,"convoyNeeded":3,"timeLimit":1000,"reinforcements":1,"convoy":{"def":"supply_truck","x":-100,"z":-100,"heading":45,"route":[-82.5,-82.5,-82.5,-60,-40,-33.75,20,-33.75,63.75,-60,63.75,-86.25]},"units":[{"def":"main_battle_tank","team":0,"x":-84.0,"z":-88.0,"heading":45},{"def":"heavy_aa","team":0,"x":-93.0,"z":-82.8,"heading":45},{"def":"wheeled_gun","team":0,"x":-93.0,"z":-93.2,"heading":45}],"enemyAi":"waves","difficulty":"Normal","waves":{"first":20,"interval":30,"size":2,"grow":0.45,"maxSize":6,"maxAlive":13,"roster":["ifv","wheeled_gun","light_tank","attack_helicopter"],"spawns":[80,60,100,0,20,100]},"rarePrints":30,"starTime":360,"starLosses":6,"radio":[{"key":"radio.linh.c4s1.1","on":"Start"}],"missionEvents":["rail_reinforcements","loot_drop"],"coins":745,"xp":595,"prints":4}
A58: c4s2 | B58: 4 | C58: ironport | E58: wheeled_gun;ifv;main_battle_tank;heavy_tank;sam_launcher;fpv_carrier;mine_layer;mlrs | G58: c4m07 | I58: linh | J58: FALSE | K58: 5 | L58: co_kich_ban | AD58: 745 | AO58: Normal | AP58: commander | AR58: 14 | AT58: 0.85 | AV58: Defend | AW58: Hunt | BJ58: Anchor | BK58: 36 | BL58: 26 | BM58: 1.4 | BO58: 4 | BR58: 1 | BT58: TRUE | BV58: TRUE | BW58: linh | BX58: 8 | BY58: 480 | CB58: 1.8 | CG58: 1300 | CH58: Epic | CR58: Clear | CS58: 595 | CT58: Assets/MachineBrigade/Resources/Data/campaign.json: missions[60] | CU58: {"id":"c4s2","chapter":4,"side":true,"after":"c4m07","map":"ironport","reversed":true,"weather":"Clear","goal":"Hunt","speaker":"linh","timeLimit":1300,"targetHealth":1.8,"reinforcements":1,"hunt":[{"def":"command_vehicle","x":-60,"z":-60,"heading":45,"route":[-80,-40,-40,-80,-70,-90]},{"def":"command_vehicle","x":30,"z":-90,"heading":45,"route":[60,-100,0,-80,20,-60]}],"units":[{"def":"main_battle_tank","team":1,"x":-67.0,"z":-60.0,"heading":45},{"def":"aa_vehicle","team":1,"x":-56.5,"z":-66.06,"heading":45},{"def":"ifv","team":1,"x":-56.5,"z":-53.94,"heading":45},{"def":"wheeled_gun","team":1,"x":24.0,"z":-90.0,"heading":45},{"def":"sam_launcher","team":1,"x":36.0,"z":-90.0,"heading":45}],"enemyAi":"commander","enemyStance":"Defend","difficulty":"Normal","enemyCp":14,"enemyIncome":0.85,"enemyDeck":["wheeled_gun","ifv","main_battle_tank","heavy_tank","sam_launcher","fpv_carrier","mine_layer","mlrs"],"playerCp":26,"playerIncome":1.4,"playerCap":36,"playerBase":"Anchor","towerGear":"Epic","starTime":480,"starLosses":8,"radio":[{"key":"radio.linh.c4s2.1","on":"Start"}],"missionEvents":["loot_drop","cloud_over"],"coins":745,"xp":595,"prints":4}
A59: c5m01 | B59: 5 | C59: junglepass | D59: sen | E59: light_tank;ifv;main_battle_tank;flame_tank;attack_helicopter;tank_destroyer;strike_drone | F59: strike_drone | I59: linh | J59: FALSE | K59: 7 | L59: co_kich_ban | AB59: NoAircraft | AD59: 275 | AO59: Normal | AP59: both | AR59: 14 | AT59: 0.9 | AU59: town;east | AV59: Defend | AW59: Capture | BB59: m14 | BE59: west | BK59: 36 | BL59: 24 | BM59: 1.35 | BN59: west;town;east | BO59: 3 | BR59: 3 | BX59: 14 | BY59: 600 | CG59: 1100 | CJ59: 80 | CK59: 0.3 | CL59: 70 | CM59: 10 | CN59: 4 | CO59: ifv;main_battle_tank;elite_mbt;attack_helicopter | CP59: 2 | CR59: Rain | CS59: 220 | CT59: Assets/MachineBrigade/Resources/Data/campaign.json: missions[61] | CU59: {"id":"c5m01","chapter":5,"map":"junglepass","weather":"Rain","goal":"Capture","legacy":"m14","points":["west","town","east"],"outposts":["west"],"enemyOwns":["town","east"],"timeLimit":1100,"general":"sen","reinforcements":3,"enemyAi":"both","enemyStance":"Defend","difficulty":"Normal","enemyCp":14,"enemyIncome":0.9,"enemyDeck":["light_tank","ifv","main_battle_tank","flame_tank","attack_helicopter","tank_destroyer","strike_drone"],"waves":{"first":80,"interval":70,"size":2,"grow":0.3,"maxSize":4,"maxAlive":10,"roster":["ifv","main_battle_tank","elite_mbt","attack_helicopter"]},"playerCp":24,"playerIncome":1.35,"playerCap":36,"starTime":600,"starLosses":14,"challenge":{"kind":"NoAircraft"},"radio":[{"key":"radio.sen.c5m01.1","on":"Start"},{"key":"radio.linh.c5m01.2","on":"Start"}],"unlocks":["strike_drone"],"missionEvents":["drone_swarm","accord_wave"],"coins":275,"xp":220,"prints":3}
A60: c5m02 | B60: 5 | C60: emberridge | D60: sen | E60: strike_drone;fpv_carrier;recon_drone;ew_jammer;ifv;main_battle_tank;aa_vehicle | F60: fpv_carrier | I60: linh | J60: FALSE | K60: 7 | L60: co_kich_ban | AB60: Kills | AC60: 25 | AD60: 275 | AO60: Normal | AP60: commander | AR60: 14 | AT60: 0.9 | AV60: Defend | AW60: Hunt | BJ60: Anchor | BK60: 36 | BL60: 26 | BM60: 1.45 | BO60: 3 | BR60: 2 | BX60: 10 | BY60: 660 | CB60: 2.5 | CG60: 1100 | CR60: Night | CS60: 220 | CT60: Assets/MachineBrigade/Resources/Data/campaign.json: missions[62] | CU60: {"id":"c5m02","chapter":5,"map":"emberridge","weather":"Night","goal":"Hunt","general":"sen","timeLimit":1100,"targetHealth":2.5,"reinforcements":2,"hunt":[{"def":"fpv_carrier","x":60,"z":60,"heading":225,"route":[80,80,40,50,70,30]},{"def":"fpv_carrier","x":-20,"z":90,"heading":225,"route":[-50,90,0,70,-30,60]},{"def":"fpv_carrier","x":90,"z":-10,"heading":225,"route":[110,-40,80,10,110,20]}],"units":[{"def":"main_battle_tank","team":1,"x":66.0,"z":60.0,"heading":225},{"def":"aa_vehicle","team":1,"x":54.0,"z":60.0,"heading":225},{"def":"ifv","team":1,"x":-14.0,"z":90.0,"heading":225},{"def":"ew_jammer","team":1,"x":-26.0,"z":90.0,"heading":225},{"def":"main_battle_tank","team":1,"x":96.0,"z":-10.0,"heading":225},{"def":"aa_vehicle","team":1,"x":84.0,"z":-10.0,"heading":225}],"enemyAi":"commander","enemyStance":"Defend","difficulty":"Normal","enemyCp":14,"enemyIncome":0.9,"enemyDeck":["strike_drone","fpv_carrier","recon_drone","ew_jammer","ifv","main_battle_tank","aa_vehicle"],"playerCp":26,"playerIncome":1.45,"playerCap":36,"playerBase":"Anchor","starTime":660,"starLosses":10,"challenge":{"kind":"Kills","value":25},"radio":[{"key":"radio.linh.c5m02.1","on":"Start"}],"unlocks":["fpv_carrier"],"missionEvents":["ew_blackout","drone_swarm","nadia_intel"],"coins":275,"xp":220,"prints":3}
A61: c5m03 | B61: 5 | C61: junglepass | F61: shahed_truck | I61: khai | J61: TRUE | K61: 8 | L61: co_kich_ban | AB61: Kills | AC61: 22 | AD61: 280 | AF61: 5 | AG61: supply_truck | AH61: 45 | AK61: 3 | AL61: -82.2;-71.6;-50.4;-50.4;-77;-13;-82;34;-75;63 | AM61: -100 | AN61: -100 | AO61: Normal | AP61: waves | AW61: Escort | BO61: 3 | BR61: 2 | BX61: 8 | BY61: 360 | CG61: 1100 | CJ61: 35 | CK61: 0.35 | CL61: 32 | CM61: 12 | CN61: 5 | CO61: ifv;light_tank;strike_drone;armored_car;fpv_carrier | CP61: 2 | CQ61: 60;80;95;20;20;110 | CR61: Fog | CS61: 225 | CT61: Assets/MachineBrigade/Resources/Data/campaign.json: missions[63] | CU61: {"id":"c5m03","chapter":5,"map":"junglepass","weather":"Fog","goal":"Escort","convoyCount":5,"convoyNeeded":3,"timeLimit":1100,"reinforcements":2,"convoy":{"def":"supply_truck","x":-100,"z":-100,"heading":45,"route":[-82.2,-71.6,-50.4,-50.4,-77,-13,-82,34,-75,63]},"units":[{"def":"main_battle_tank","team":0,"x":-82.0,"z":-90.0,"heading":45},{"def":"heavy_aa","team":0,"x":-88.0,"z":-84.0,"heading":45},{"def":"ifv","team":0,"x":-94.0,"z":-90.0,"heading":45},{"def":"heavy_tank","team":0,"x":-88.0,"z":-96.0,"heading":45}],"enemyAi":"waves","difficulty":"Normal","waves":{"first":35,"interval":32,"size":2,"grow":0.35,"maxSize":5,"maxAlive":12,"roster":["ifv","light_tank","strike_drone","armored_car","fpv_carrier"],"spawns":[60,80,95,20,20,110]},"starTime":360,"starLosses":8,"challenge":{"kind":"Kills","value":22},"radio":[{"key":"radio.khai.c5m03.1","on":"Start"}],"missionEvents":["drone_swarm","rain_sets_in"],"unlocks":["shahed_truck"],"fixedDeck":{"vehicleIds":["iron_beam","aa_gun_vehicle","aa_vehicle","zu23_technical","engineer_vehicle","ammo_carrier","armored_car","ifv"],"supportIds":["airstrike","repair_drop"],"placedAllies":[],"loanedCards":["iron_beam","aa_gun_vehicle"],"specialRules":["droneCanopy"],"status":"READY"},"coins":280,"xp":225,"prints":3}
A62: c5m04 | B62: 5 | C62: emberridge | D62: sen | E62: strike_drone;fpv_carrier;recon_drone;ew_jammer;ifv;main_battle_tank;aa_vehicle | F62: airfield | I62: mai | J62: FALSE | K62: 7 | L62: co_kich_ban | AD62: 285 | AO62: Normal | AP62: both | AR62: 13 | AT62: 0.85 | AV62: Attack | AW62: Outpost | AX62: 180 | BJ62: Anchor | BK62: 38 | BL62: 28 | BM62: 1.5 | BN62: town | BO62: 3 | BR62: 2 | BW62: mai | BX62: 10 | BY62: 600 | CG62: 1100 | CJ62: 70 | CK62: 0.3 | CL62: 55 | CM62: 12 | CN62: 4 | CO62: strike_drone;ifv;main_battle_tank;fpv_carrier | CP62: 2 | CR62: Clear | CS62: 225 | CT62: Assets/MachineBrigade/Resources/Data/campaign.json: missions[64] | CU62: {"id":"c5m04","chapter":5,"map":"emberridge","weather":"Clear","goal":"Outpost","points":["town"],"holdSeconds":180,"speaker":"mai","general":"sen","reinforcements":2,"timeLimit":1100,"enemyAi":"both","enemyStance":"Attack","difficulty":"Normal","enemyCp":13,"enemyIncome":0.85,"enemyDeck":["strike_drone","fpv_carrier","recon_drone","ew_jammer","ifv","main_battle_tank","aa_vehicle"],"playerCp":28,"playerIncome":1.5,"playerCap":38,"playerBase":"Anchor","waves":{"first":70,"interval":55,"size":2,"grow":0.3,"maxSize":4,"maxAlive":12,"roster":["strike_drone","ifv","main_battle_tank","fpv_carrier"]},"starTime":600,"starLosses":10,"radio":[{"key":"radio.mai.c5m04.1","on":"Start"},{"key":"radio.sen.c5m04.2","at":120}],"unlocks":["airfield"],"missionEvents":["drone_swarm","supply_drop","cloud_over"],"coins":285,"xp":225,"prints":3}
A63: c5m05 | B63: 5 | C63: junglepass | D63: sen | E63: strike_drone;fpv_carrier;recon_drone;ew_jammer;ifv;main_battle_tank;aa_vehicle | H63: drone_mothership | I63: mai | J63: FALSE | K63: 13 | L63: co_kich_ban | T63: 0.5 | U63: 225 | V63: 0.9 | X63: 60;60;20;30;-20;10;30;-20 | Y63: 84 | Z63: 84 | AB63: NoAircraft | AD63: 440 | AO63: Normal | AP63: commander | AR63: 13 | AT63: 0.85 | AV63: Attack | AW63: Boss | BJ63: Anchor | BK63: 38 | BL63: 28 | BM63: 1.5 | BO63: 4 | BR63: 3 | BX63: 12 | BY63: 780 | CG63: 1200 | CR63: Storm | CS63: 350 | CT63: Assets/MachineBrigade/Resources/Data/campaign.json: missions[67] | CU63: {"id":"c5m05","chapter":5,"map":"junglepass","weather":"Storm","goal":"Boss","general":"sen","timeLimit":1200,"reinforcements":3,"boss":{"def":"drone_mothership","x":84,"z":84,"heading":225,"route":[60,60,20,30,-20,10,30,-20],"health":0.9,"fleeAt":0.5},"enemyAi":"commander","enemyStance":"Attack","difficulty":"Normal","enemyCp":13,"enemyIncome":0.85,"enemyDeck":["strike_drone","fpv_carrier","recon_drone","ew_jammer","ifv","main_battle_tank","aa_vehicle"],"playerCp":28,"playerIncome":1.5,"playerCap":38,"playerBase":"Anchor","starTime":780,"starLosses":12,"challenge":{"kind":"NoAircraft"},"radio":[{"key":"radio.sen.c5m05.1","on":"Start"},{"key":"radio.khai.c5m05.2","on":"Boss"},{"key":"radio.sen.c5m05.3","on":"Win"}],"missionEvents":["ew_blackout","hawk_strike"],"coins":440,"xp":350,"prints":4}
A64: c5m06 | B64: 5 | C64: emberridge | D64: sen | E64: main_battle_tank;heavy_tank;aa_vehicle;mortar_carrier;tank_destroyer;strike_drone | I64: khai | J64: FALSE | K64: 7 | L64: co_kich_ban | AD64: 295 | AO64: Easy | AP64: commander | AR64: 10 | AT64: 0.9 | AV64: Defend | AW64: Destroy | BB64: m13 | BK64: 48 | BL64: 32 | BM64: 2.8 | BO64: 3 | BR64: 3 | BS64: TRUE | BU64: TRUE | BX64: 16 | BY64: 780 | CB64: 0.8 | CF64: command_hq | CG64: 1500 | CI64: siege | CJ64: 90 | CK64: 0.3 | CL64: 75 | CM64: 10 | CN64: 3 | CO64: main_battle_tank;ifv;attack_helicopter;elite_mbt | CP64: 2 | CR64: Night | CS64: 235 | CT64: Assets/MachineBrigade/Resources/Data/campaign.json: missions[68] | CU64: {"id":"c5m06","chapter":5,"map":"emberridge","variant":"siege","weather":"Night","goal":"Destroy","legacy":"m13","targets":["command_hq"],"targetHealth":0.8,"timeLimit":1500,"replay":true,"general":"sen","reinforcements":3,"enemyAi":"commander","enemyStance":"Defend","difficulty":"Easy","enemyCp":10,"enemyIncome":0.9,"enemyDeck":["main_battle_tank","heavy_tank","aa_vehicle","mortar_carrier","tank_destroyer","strike_drone"],"waves":{"first":90,"interval":75,"size":2,"grow":0.3,"maxSize":3,"maxAlive":10,"roster":["main_battle_tank","ifv","attack_helicopter","elite_mbt"]},"playerCp":32,"playerIncome":2.8,"playerCap":48,"starTime":780,"starLosses":16,"radio":[{"key":"radio.khai.c5m06.1","on":"Start"}],"setPiece":true,"missionEvents":["drone_swarm","accord_artillery","enemy_air_raid"],"coins":295,"xp":235,"prints":3}
A65: c5m07 | B65: 5 | C65: junglepass | D65: sen | I65: dieuhau | J65: TRUE | K65: 9 | L65: co_kich_ban | AD65: 305 | AO65: Normal | AP65: waves | AW65: ShootDown | AZ65: 14 | BJ65: Anchor | BK65: 36 | BL65: 28 | BM65: 1.45 | BO65: 3 | BX65: 10 | BY65: 600 | CG65: 1200 | CJ65: 30 | CK65: 0.4 | CL65: 42 | CM65: 14 | CN65: 7 | CO65: strike_drone;strike_drone;attack_helicopter;recon_drone;ifv;main_battle_tank | CP65: 3 | CR65: Clear | CS65: 245 | CT65: Assets/MachineBrigade/Resources/Data/campaign.json: missions[70] | CU65: {"id":"c5m07","chapter":5,"map":"junglepass","weather":"Clear","goal":"ShootDown","killsNeeded":14,"timeLimit":1200,"general":"sen","enemyAi":"waves","difficulty":"Normal","playerCp":28,"playerIncome":1.45,"playerCap":36,"playerBase":"Anchor","waves":{"first":30,"interval":42,"size":3,"grow":0.4,"maxSize":7,"maxAlive":14,"roster":["strike_drone","strike_drone","attack_helicopter","recon_drone","ifv","main_battle_tank"]},"starTime":600,"starLosses":10,"radio":[{"key":"radio.dieuhau.c5m07.1","on":"Start"},{"key":"radio.linh.c5m07.d1","on":"Win"}],"missionEvents":["air_wave","drone_swarm","supply_drop"],"fixedDeck":{"vehicleIds":["fighter_jet","scout_heli","attack_helicopter","strike_drone","sam_launcher","ew_jammer","iron_beam","aa_vehicle"],"supportIds":["airstrike","artillery_barrage"],"placedAllies":[],"loanedCards":["iron_beam"],"specialRules":["airCap6"],"status":"MAKE_FIRST"},"coins":305,"xp":245,"prints":3}
A66: c5m08 | B66: 5 | C66: emberridge | D66: sen | E66: strike_drone;fpv_carrier;recon_drone;ew_jammer;ifv;main_battle_tank;aa_vehicle | F66: ew_jammer | H66: locust | I66: linh | J66: FALSE | K66: 11 | L66: co_kich_ban | R66: drone_mothership | S66: 0.4 | U66: 45 | W66: locust | X66: -60;-60;-20;-30;10;-10 | Y66: -84 | Z66: -84 | AB66: NoAircraft | AD66: 285 | AO66: Normal | AP66: both | AR66: 11 | AT66: 0.85 | AV66: Attack | AW66: Protect | BJ66: Anchor | BK66: 36 | BL66: 28 | BM66: 1.45 | BO66: 3 | BP66: 1 | BR66: 2 | BT66: TRUE | BX66: 10 | BY66: 0 | CA66: 420 | CB66: 14 | CF66: storage_tank | CJ66: 90 | CK66: 0.3 | CL66: 65 | CM66: 10 | CN66: 4 | CO66: strike_drone;fpv_carrier;ifv;main_battle_tank | CP66: 2 | CR66: Overcast | CS66: 230 | CT66: Assets/MachineBrigade/Resources/Data/campaign.json: missions[65] | CU66: {"id":"c5m08","chapter":5,"map":"emberridge","reversed":true,"weather":"Overcast","goal":"Protect","targets":["storage_tank"],"protectNeeded":1,"targetHealth":14,"surviveSeconds":420,"general":"sen","reinforcements":2,"enemyAi":"both","enemyStance":"Attack","difficulty":"Normal","enemyCp":11,"enemyIncome":0.85,"enemyDeck":["strike_drone","fpv_carrier","recon_drone","ew_jammer","ifv","main_battle_tank","aa_vehicle"],"playerCp":28,"playerIncome":1.45,"playerCap":36,"playerBase":"Anchor","waves":{"first":90,"interval":65,"size":2,"grow":0.3,"maxSize":4,"maxAlive":10,"roster":["strike_drone","fpv_carrier","ifv","main_battle_tank"]},"starTime":0,"starLosses":10,"challenge":{"kind":"NoAircraft"},"radio":[{"key":"radio.linh.c5m08.1","on":"Start"},{"key":"radio.linh.c5m08.p1","on":"Boss"}],"boss":{"def":"locust","name":"locust","fallback":"drone_mothership","fallbackHealth":0.4,"x":-84,"z":-84,"heading":45,"route":[-60,-60,-20,-30,10,-10]},"missionEvents":["ew_blackout","protect_civilians","accord_relief"],"unlocks":["ew_jammer"],"coins":285,"xp":230,"prints":3}
A67: c5m09 | B67: 5 | C67: junglepass | D67: sen | I67: khai | J67: FALSE | K67: 8 | L67: co_kich_ban | AD67: 310 | AO67: Normal | AP67: commander | AQ67: Target | AR67: 11 | AS67: 2 | AT67: 0.56 | AV67: Defend | AW67: Duel | BJ67: Anchor | BK67: 40 | BL67: 30 | BM67: 2.3 | BO67: 3 | BR67: 3 | BS67: TRUE | BX67: 14 | BY67: 900 | CB67: 0.4 | CG67: 1500 | CR67: Night | CS67: 250 | CT67: Assets/MachineBrigade/Resources/Data/campaign.json: missions[72] | CU67: {"id":"c5m09","chapter":5,"map":"junglepass","weather":"Night","goal":"Duel","targetHealth":0.4,"general":"sen","enemyBase":"Target","enemyHq":2,"replay":true,"reinforcements":3,"timeLimit":1500,"enemyAi":"commander","enemyStance":"Defend","difficulty":"Normal","enemyCp":11,"enemyIncome":0.56,"playerCp":30,"playerIncome":2.3,"playerCap":40,"playerBase":"Anchor","starTime":900,"starLosses":14,"radio":[{"key":"radio.sen.c5m09.1","on":"Start"},{"key":"radio.sen.c5m09.2","on":"Win"},{"key":"radio.linh.c5m09.q1","on":"Win"}],"missionEvents":["general_field","drone_swarm","hawk_strike"],"coins":310,"xp":250,"prints":3}
A68: c5m10 | B68: 5 | C68: emberridge | D68: sen | E68: strike_drone;fpv_carrier;recon_drone;ew_jammer;ifv;main_battle_tank;aa_vehicle | F68: swarm_carrier | I68: khai | J68: FALSE | K68: 13 | L68: co_kich_ban | AD68: 750 | AO68: Normal | AP68: both | AR68: 15 | AT68: 0.95 | AV68: Defend | AW68: Capture | BB68: m15 | BC68: TRUE | BF68: 146 | BG68: 146 | BH68: -146 | BI68: -146 | BJ68: Anchor | BK68: 42 | BL68: 30 | BM68: 1.7 | BO68: 7 | BR68: 3 | BX68: 18 | BY68: 1380 | CJ68: 90 | CK68: 0.3 | CL68: 65 | CM68: 12 | CN68: 5 | CO68: strike_drone;fpv_carrier;ifv;main_battle_tank;attack_helicopter | CP68: 2 | CR68: Storm | CS68: 600 | CT68: Assets/MachineBrigade/Resources/Data/campaign.json: missions[73] | CU68: {"id":"c5m10","chapter":5,"map":"emberridge","weather":"Storm","goal":"Capture","legacy":"m15","operation":true,"general":"sen","reinforcements":3,"playArea":{"minX":-146,"minZ":-146,"maxX":146,"maxZ":146},"enemyAi":"both","enemyStance":"Defend","difficulty":"Normal","enemyCp":15,"enemyIncome":0.95,"enemyDeck":["strike_drone","fpv_carrier","recon_drone","ew_jammer","ifv","main_battle_tank","aa_vehicle"],"playerCp":30,"playerIncome":1.7,"playerCap":42,"playerBase":"Anchor","waves":{"first":90,"interval":65,"size":2,"grow":0.3,"maxSize":5,"maxAlive":12,"roster":["strike_drone","fpv_carrier","ifv","main_battle_tank","attack_helicopter"]},"stages":[{"stage":"causeways","goal":"Capture","points":["west","east"],"enemyOwns":["west","town","east"],"cp":8,"events":[{"at":"start","kind":"Radio","key":"radio.khai.c5m10.s1"}],"choices":[{"key":"fuel","next":"fuel"},{"key":"relay","next":"relay"}],"missionEvents":["nadia_intel"]},{"stage":"fuel","goal":"Destroy","targets":["storage_tank"],"targetX":36,"targetZ":20,"targetRadius":36,"targetHealth":2,"cp":6,"next":"plant","events":[{"at":"end","kind":"Income","team":1,"amount":0.7},{"at":"end","kind":"Radio","key":"radio.enemyWeakened"}]},{"stage":"relay","goal":"Survive","points":["town"],"enemyOwns":[],"surviveSeconds":120,"cp":6,"next":"plant","events":[{"at":"end","kind":"Strike","team":0,"support":"airstrike","every":55},{"at":"end","kind":"Radio","key":"radio.alliedStrikes"}]},{"stage":"plant","goal":"Survive","points":["town"],"surviveSeconds":300,"cp":8,"events":[{"at":"40","kind":"Reinforce","team":1,"units":["ifv","main_battle_tank","fpv_carrier"]}],"missionEvents":["accord_artillery"]},{"stage":"swarm","goal":"Survive","surviveSeconds":480,"cp":8,"events":[{"at":"start","kind":"Radio","key":"radio.sen.c5m10.s3"},{"at":"30","kind":"Reinforce","team":1,"units":["strike_drone","strike_drone","fpv_carrier","ifv"]},{"at":"110","kind":"Reinforce","team":1,"units":["strike_drone","fpv_carrier","main_battle_tank","ew_jammer"]},{"at":"3","kind":"Radio","key":"radio.khai.c5m10.s3b"}],"missionEvents":[{"id":"drone_swarm","params":{"size":10,"directions":4},"trigger":{"at":60}}]},{"stage":"mothership","goal":"Boss","boss":{"def":"drone_mothership","x":84,"z":84,"heading":225,"health":1.6},"events":[{"at":"end","kind":"Radio","key":"radio.sen.c5m10.end"}],"missionEvents":["hawk_strike"]}],"starTime":1380,"starLosses":18,"radio":[{"key":"radio.khai.c5m10.1","on":"Start"},{"key":"radio.khai.c5m10.2","on":"Win"}],"unlocks":["swarm_carrier"],"missionEvents":["drone_swarm","ew_blackout","lava_flow"],"navStates":[{"id":"lava","initial":"clear","states":[{"name":"clear"},{"name":"cut","blocks":[{"x":-50,"z":78,"w":24,"d":8}]}]}],"coins":750,"xp":600,"prints":7}
A69: c5m11 | B69: 5 | C69: emberridge | D69: sen | E69: strike_drone;fpv_carrier;recon_drone;ew_jammer;ifv;main_battle_tank;aa_vehicle | I69: linh | J69: FALSE | K69: 7 | L69: co_kich_ban | AD69: 300 | AO69: Normal | AP69: commander | AR69: 14 | AT69: 0.9 | AV69: Defend | AW69: Recon | BK69: 38 | BL69: 28 | BM69: 1.5 | BN69: west;town;east | BO69: 3 | BR69: 1 | BW69: linh | BX69: 8 | BY69: 420 | CG69: 900 | CR69: Fog | CS69: 240 | CT69: Assets/MachineBrigade/Resources/Data/campaign.json: missions[69] | CU69: {"id":"c5m11","chapter":5,"map":"emberridge","weather":"Fog","goal":"Recon","points":["west","town","east"],"timeLimit":900,"reinforcements":1,"enemyAi":"commander","enemyStance":"Defend","difficulty":"Normal","enemyCp":14,"enemyIncome":0.9,"enemyDeck":["strike_drone","fpv_carrier","recon_drone","ew_jammer","ifv","main_battle_tank","aa_vehicle"],"playerCp":28,"playerIncome":1.5,"playerCap":38,"starTime":420,"starLosses":8,"general":"sen","speaker":"linh","radio":[{"key":"radio.linh.c5m11.1","on":"Start"},{"key":"radio.sen.c5m11.2","at":45},{"key":"radio.linh.c5m11.3","on":"Win"}],"missionEvents":[{"id":"intercept_files","reward":{"intel":"c5.notebook"}},"ew_blackout"],"coins":300,"xp":240,"prints":3}
A70: c5m12 | B70: 5 | C70: junglepass | D70: sen | E70: strike_drone;fpv_carrier;recon_drone;ew_jammer;ifv;main_battle_tank;aa_vehicle | I70: khai | J70: FALSE | K70: 7 | L70: co_kich_ban | AD70: 290 | AO70: Normal | AP70: both | AR70: 14 | AT70: 0.9 | AU70: town;east | AV70: Defend | AW70: Capture | BE70: west | BJ70: Anchor | BK70: 38 | BL70: 28 | BM70: 1.5 | BN70: west;town;east | BO70: 3 | BR70: 3 | BT70: TRUE | BX70: 14 | BY70: 600 | CG70: 1100 | CJ70: 80 | CK70: 0.3 | CL70: 70 | CM70: 10 | CN70: 4 | CO70: ifv;main_battle_tank;elite_mbt;attack_helicopter | CP70: 2 | CR70: Rain | CS70: 230 | CT70: Assets/MachineBrigade/Resources/Data/campaign.json: missions[66] | CU70: {"id":"c5m12","chapter":5,"map":"junglepass","reversed":true,"weather":"Rain","goal":"Capture","points":["west","town","east"],"outposts":["west"],"enemyOwns":["town","east"],"timeLimit":1100,"general":"sen","reinforcements":3,"enemyAi":"both","enemyStance":"Defend","difficulty":"Normal","enemyCp":14,"enemyIncome":0.9,"enemyDeck":["strike_drone","fpv_carrier","recon_drone","ew_jammer","ifv","main_battle_tank","aa_vehicle"],"waves":{"first":80,"interval":70,"size":2,"grow":0.3,"maxSize":4,"maxAlive":10,"roster":["ifv","main_battle_tank","elite_mbt","attack_helicopter"]},"playerCp":28,"playerIncome":1.5,"playerCap":38,"starTime":600,"starLosses":14,"playerBase":"Anchor","radio":[{"key":"radio.khai.c5m12.1","on":"Start"},{"key":"radio.linh.c5m12.2","on":"Win"}],"missionEvents":["drone_swarm","loot_drop","storm_front"],"coins":290,"xp":230,"prints":3}
A71: c5m13 | B71: 5 | C71: junglepass | D71: sen | E71: strike_drone;fpv_carrier;recon_drone;ew_jammer;ifv;main_battle_tank;aa_vehicle | I71: khai | J71: FALSE | K71: 7 | L71: co_kich_ban | AD71: 305 | AO71: Normal | AP71: both | AR71: 13 | AT71: 0.9 | AV71: Attack | AW71: Hold | AX71: 210 | BJ71: None | BK71: 40 | BL71: 28 | BM71: 1.5 | BN71: town | BO71: 3 | BR71: 2 | BX71: 10 | BY71: 0 | CJ71: 45 | CK71: 0.3 | CL71: 50 | CM71: 10 | CN71: 4 | CO71: light_tank;main_battle_tank;ifv;mortar_carrier;attack_helicopter;flame_tank | CP71: 2 | CR71: Night | CS71: 245 | CT71: Assets/MachineBrigade/Resources/Data/campaign.json: missions[71] | CU71: {"id":"c5m13","chapter":5,"map":"junglepass","weather":"Night","goal":"Hold","points":["town"],"holdSeconds":210,"general":"sen","reinforcements":2,"units":[{"def":"main_battle_tank","team":0,"x":12.0,"z":0.0,"heading":45},{"def":"main_battle_tank","team":0,"x":7.48,"z":9.38,"heading":45},{"def":"aa_vehicle","team":0,"x":-2.67,"z":11.7,"heading":45},{"def":"light_tank","team":0,"x":-10.81,"z":5.21,"heading":45},{"def":"tank_destroyer","team":0,"x":-10.81,"z":-5.21,"heading":45},{"def":"heavy_tank","team":0,"x":-2.67,"z":-11.7,"heading":45},{"def":"mlrs","team":0,"x":7.48,"z":-9.38,"heading":45}],"enemyAi":"both","enemyStance":"Attack","difficulty":"Normal","enemyCp":13,"enemyIncome":0.9,"enemyDeck":["strike_drone","fpv_carrier","recon_drone","ew_jammer","ifv","main_battle_tank","aa_vehicle"],"playerCp":28,"playerIncome":1.5,"playerCap":40,"playerBase":"None","waves":{"first":45,"interval":50,"size":2,"grow":0.3,"maxSize":4,"maxAlive":10,"roster":["light_tank","main_battle_tank","ifv","mortar_carrier","attack_helicopter","flame_tank"]},"starTime":0,"starLosses":10,"radio":[{"key":"radio.khai.c5m13.1","on":"Start"},{"key":"radio.mai.c5m13.2","on":"Win"}],"missionEvents":["drone_swarm","ew_blackout","accord_wave","forest_fire"],"navStates":[{"id":"fire","initial":"none","states":[{"name":"none"},{"name":"front1","blocks":[{"x":-60,"z":-40,"w":50,"d":12}]},{"name":"front2","blocks":[{"x":-60,"z":-28,"w":50,"d":12}]},{"name":"front3","blocks":[{"x":-60,"z":-16,"w":50,"d":12}]},{"name":"front4","blocks":[{"x":-60,"z":-4,"w":50,"d":12}]},{"name":"out"}]}],"coins":305,"xp":245,"prints":3}
A72: c5s1 | B72: 5 | C72: junglepass | E72: strike_drone;fpv_carrier;recon_drone;ew_jammer;ifv;main_battle_tank;aa_vehicle | G72: c5m03 | I72: linh | J72: FALSE | K72: 5 | L72: co_kich_ban | AD72: 865 | AO72: Normal | AP72: commander | AR72: 14 | AT72: 0.85 | AV72: Defend | AW72: Recon | BK72: 36 | BL72: 26 | BM72: 1.4 | BN72: west;town;east | BO72: 4 | BQ72: 34 | BR72: 1 | BV72: TRUE | BW72: linh | BX72: 8 | BY72: 420 | CG72: 900 | CR72: Overcast | CS72: 690 | CT72: Assets/MachineBrigade/Resources/Data/campaign.json: missions[74] | CU72: {"id":"c5s1","chapter":5,"side":true,"after":"c5m03","map":"junglepass","weather":"Overcast","goal":"Recon","speaker":"linh","points":["west","town","east"],"timeLimit":900,"reinforcements":1,"enemyAi":"commander","enemyStance":"Defend","difficulty":"Normal","enemyCp":14,"enemyIncome":0.85,"enemyDeck":["strike_drone","fpv_carrier","recon_drone","ew_jammer","ifv","main_battle_tank","aa_vehicle"],"playerCp":26,"playerIncome":1.4,"playerCap":36,"rarePrints":34,"starTime":420,"starLosses":8,"radio":[{"key":"radio.linh.c5s1.1","on":"Start"}],"missionEvents":["nadia_intel","storm_front"],"coins":865,"xp":690,"prints":4}
A73: c5s2 | B73: 5 | C73: emberridge | E73: strike_drone;fpv_carrier;recon_drone;ew_jammer;ifv;main_battle_tank;aa_vehicle | G73: c5m07 | I73: linh | J73: FALSE | K73: 5 | L73: co_kich_ban | N73: headquarters | O73: -60 | P73: -20 | AD73: 865 | AO73: Normal | AP73: both | AR73: 10 | AT73: 0.75 | AV73: Attack | AW73: Relieve | BJ73: Anchor | BK73: 36 | BL73: 28 | BM73: 1.5 | BO73: 4 | BR73: 2 | BV73: TRUE | BW73: linh | BX73: 8 | BY73: 480 | CB73: 3 | CG73: 1000 | CH73: Epic | CJ73: 70 | CK73: 0.3 | CL73: 60 | CM73: 12 | CN73: 4 | CO73: strike_drone;ifv;fpv_carrier | CP73: 2 | CQ73: 40;60;80;20 | CR73: Fog | CS73: 690 | CT73: Assets/MachineBrigade/Resources/Data/campaign.json: missions[75] | CU73: {"id":"c5s2","chapter":5,"side":true,"after":"c5m07","map":"emberridge","weather":"Fog","goal":"Relieve","targetHealth":3.0,"speaker":"linh","reinforcements":2,"timeLimit":1000,"ally":{"x":-60,"z":-20,"hq":"headquarters","structures":[{"def":"mg_bunker","team":0,"x":-46.0,"z":-20.0,"heading":45},{"def":"gun_turret","team":0,"x":-67.0,"z":-7.88,"heading":45},{"def":"aa_turret","team":0,"x":-67.0,"z":-32.12,"heading":45}],"units":[{"def":"ifv","team":0,"x":-62.0,"z":-26.0,"heading":45},{"def":"light_tank","team":0,"x":-70.0,"z":-26.0,"heading":45}]},"hunt":[{"def":"main_battle_tank","x":-23.16,"z":-4.42,"heading":225},{"def":"fpv_carrier","x":-55.07,"z":19.69,"heading":225},{"def":"ifv","x":-91.91,"z":4.12,"heading":225},{"def":"strike_drone","x":-96.84,"z":-35.58,"heading":225},{"def":"mortar_carrier","x":-64.93,"z":-59.69,"heading":225},{"def":"main_battle_tank","x":-28.09,"z":-44.12,"heading":225}],"enemyAi":"both","enemyStance":"Attack","difficulty":"Normal","enemyCp":10,"enemyIncome":0.75,"enemyDeck":["strike_drone","fpv_carrier","recon_drone","ew_jammer","ifv","main_battle_tank","aa_vehicle"],"playerCp":28,"playerIncome":1.5,"playerCap":36,"playerBase":"Anchor","waves":{"first":70,"interval":60,"size":2,"grow":0.3,"maxSize":4,"maxAlive":12,"roster":["strike_drone","ifv","fpv_carrier"],"spawns":[40,60,80,20]},"towerGear":"Epic","starTime":480,"starLosses":8,"radio":[{"key":"radio.linh.c5s2.1","on":"Start"}],"missionEvents":["drone_swarm","supply_raid"],"coins":865,"xp":690,"prints":4}
A74: c6m01 | B74: 6 | C74: ashfield | D74: varga | E74: main_battle_tank;heavy_tank;twin_tank;tank_destroyer;fpv_carrier;flame_tank;ifv;mlrs | F74: heavy_tank | I74: khai | J74: FALSE | K74: 8 | L74: co_kich_ban | AD74: 315 | AO74: Normal | AP74: both | AR74: 14 | AT74: 1 | AV74: Attack | AW74: Protect | BK74: 40 | BL74: 28 | BM74: 1.5 | BO74: 3 | BP74: 1 | BR74: 3 | BS74: TRUE | BT74: TRUE | BX74: 16 | BY74: 0 | CA74: 480 | CB74: 2.5 | CF74: command_hq | CI74: siege | CJ74: 60 | CK74: 0.4 | CL74: 55 | CM74: 16 | CN74: 6 | CO74: main_battle_tank;heavy_tank;ifv;mlrs;flame_tank | CP74: 3 | CQ74: -20;-60;-60;-20;-40;-40 | CR74: Storm | CS74: 255 | CT74: Assets/MachineBrigade/Resources/Data/campaign.json: missions[76] | CU74: {"id":"c6m01","chapter":6,"map":"ashfield","variant":"siege","reversed":true,"weather":"Storm","goal":"Protect","targets":["command_hq"],"protectNeeded":1,"targetHealth":2.5,"surviveSeconds":480,"general":"varga","replay":true,"reinforcements":3,"enemyAi":"both","enemyStance":"Attack","difficulty":"Normal","enemyCp":14,"enemyIncome":1.0,"enemyDeck":["main_battle_tank","heavy_tank","twin_tank","tank_destroyer","fpv_carrier","flame_tank","ifv","mlrs"],"playerCp":28,"playerIncome":1.5,"playerCap":40,"waves":{"first":60,"interval":55,"size":3,"grow":0.4,"maxSize":6,"maxAlive":16,"roster":["main_battle_tank","heavy_tank","ifv","mlrs","flame_tank"],"spawns":[-20,-60,-60,-20,-40,-40]},"starTime":0,"starLosses":16,"radio":[{"key":"radio.varga.c6m01.1","on":"Start"},{"key":"radio.khai.c6m01.2","on":"Start"}],"missionEvents":[{"id":"enemy_all_directions","params":{"size":9}},"brandt_line","supply_drop"],"unlocks":["heavy_tank"],"coins":315,"xp":255,"prints":3}
A75: c6m02 | B75: 6 | C75: whiteout | D75: varga | E75: main_battle_tank;heavy_tank;twin_tank;tank_destroyer;fpv_carrier;flame_tank;ifv;mlrs | F75: c_ram | I75: khai | J75: FALSE | K75: 7 | L75: co_kich_ban | AD75: 325 | AF75: 8 | AG75: supply_truck | AH75: 45 | AJ75: 18 | AK75: 5 | AL75: 33;33;53;53;84.8;74.2;108;100 | AM75: 0 | AN75: 0 | AO75: Normal | AP75: both | AR75: 12 | AT75: 0.9 | AV75: Attack | AW75: Evacuate | BJ75: Anchor | BK75: 38 | BL75: 28 | BM75: 1.5 | BO75: 3 | BR75: 2 | BT75: TRUE | BX75: 10 | BY75: 600 | CG75: 900 | CJ75: 50 | CK75: 0.35 | CL75: 50 | CM75: 12 | CN75: 5 | CO75: main_battle_tank;ifv;flame_tank;mortar_carrier | CP75: 2 | CQ75: -80;-60;-40;-100;-100;-10 | CR75: Snow | CS75: 260 | CT75: Assets/MachineBrigade/Resources/Data/campaign.json: missions[78] | CU75: {"id":"c6m02","chapter":6,"map":"whiteout","reversed":true,"weather":"Snow","goal":"Evacuate","convoyCount":8,"convoyNeeded":5,"convoyInterval":18,"timeLimit":900,"general":"varga","reinforcements":2,"convoy":{"def":"supply_truck","x":0,"z":0,"heading":45,"route":[33,33,53,53,84.8,74.2,108,100]},"units":[{"def":"main_battle_tank","team":0,"x":-2.0,"z":6.0,"heading":225},{"def":"heavy_aa","team":0,"x":6.0,"z":-2.0,"heading":225},{"def":"tank_destroyer","team":0,"x":14.0,"z":6.0,"heading":225},{"def":"ifv","team":0,"x":6.0,"z":14.0,"heading":225}],"enemyAi":"both","enemyStance":"Attack","difficulty":"Normal","enemyCp":12,"enemyIncome":0.9,"enemyDeck":["main_battle_tank","heavy_tank","twin_tank","tank_destroyer","fpv_carrier","flame_tank","ifv","mlrs"],"playerCp":28,"playerIncome":1.5,"playerCap":38,"playerBase":"Anchor","waves":{"first":50,"interval":50,"size":2,"grow":0.35,"maxSize":5,"maxAlive":12,"roster":["main_battle_tank","ifv","flame_tank","mortar_carrier"],"spawns":[-80,-60,-40,-100,-100,-10]},"starTime":600,"starLosses":10,"radio":[{"key":"radio.khai.c6m02.1","on":"Start"},{"key":"radio.linh.c6m02.2","at":80}],"unlocks":["c_ram"],"missionEvents":["enemy_wave","brandt_line","sea_fog"],"coins":325,"xp":260,"prints":3}
A76: c6m03 | B76: 6 | C76: ashfield | D76: varga | E76: main_battle_tank;heavy_tank;twin_tank;tank_destroyer;fpv_carrier;flame_tank;ifv;mlrs | F76: ew_tower | I76: mai | J76: TRUE | K76: 8 | L76: co_kich_ban | AB76: Kills | AC76: 25 | AD76: 335 | AF76: 1 | AG76: behemoth | AH76: 225 | AI76: 4 | AK76: 1 | AL76: 78.75;78.75;31.9;31.9;0;0;-31.9;-31.9;-78.75;-78.75 | AM76: 100 | AN76: 100 | AO76: Normal | AP76: both | AR76: 12 | AT76: 0.9 | AV76: Attack | AW76: Escort | BJ76: Anchor | BK76: 38 | BL76: 28 | BM76: 1.5 | BO76: 3 | BR76: 3 | BT76: TRUE | BU76: TRUE | BW76: mai | BX76: 10 | BY76: 660 | CG76: 1100 | CJ76: 40 | CK76: 0.35 | CL76: 45 | CM76: 12 | CN76: 5 | CO76: tank_destroyer;fpv_carrier;main_battle_tank;attack_helicopter | CP76: 2 | CQ76: -60;-90;-90;-60;-100;-100 | CR76: Clear | CS76: 265 | CT76: Assets/MachineBrigade/Resources/Data/campaign.json: missions[81] | CU76: {"id":"c6m03","chapter":6,"map":"ashfield","reversed":true,"weather":"Clear","goal":"Escort","convoyCount":1,"convoyNeeded":1,"timeLimit":1100,"speaker":"mai","general":"varga","reinforcements":3,"convoy":{"def":"behemoth","x":100,"z":100,"heading":225,"route":[78.75,78.75,31.9,31.9,0,0,-31.9,-31.9,-78.75,-78.75],"health":4.0},"units":[{"def":"main_battle_tank","team":0,"x":81.0,"z":80.0,"heading":225},{"def":"tank_destroyer","team":0,"x":88.0,"z":73.0,"heading":225},{"def":"heavy_aa","team":0,"x":95.0,"z":80.0,"heading":225},{"def":"ifv","team":0,"x":88.0,"z":87.0,"heading":225}],"enemyAi":"both","enemyStance":"Attack","difficulty":"Normal","enemyCp":12,"enemyIncome":0.9,"enemyDeck":["main_battle_tank","heavy_tank","twin_tank","tank_destroyer","fpv_carrier","flame_tank","ifv","mlrs"],"playerCp":28,"playerIncome":1.5,"playerCap":38,"playerBase":"Anchor","waves":{"first":40,"interval":45,"size":2,"grow":0.35,"maxSize":5,"maxAlive":12,"roster":["tank_destroyer","fpv_carrier","main_battle_tank","attack_helicopter"],"spawns":[-60,-90,-90,-60,-100,-100]},"starTime":660,"starLosses":10,"challenge":{"kind":"Kills","value":25},"radio":[{"key":"radio.mai.c6m03.1","on":"Start"},{"key":"radio.varga.c6m03.2","on":"Start"},{"key":"radio.mai.c6m03.3","on":"Win"}],"unlocks":["ew_tower"],"setPiece":true,"missionEvents":["enemy_barrage","brandt_line","hawk_strike"],"fixedDeck":{"vehicleIds":["command_vehicle","ammo_carrier","engineer_vehicle","aa_vehicle","ifv","ew_jammer","tank_destroyer","scout_jeep"],"supportIds":["repair_drop","artillery_barrage"],"placedAllies":[{"def":"behemoth","x":100,"z":100,"heading":225,"name":"behemoth_mara","convoy":true,"lossIfDestroyed":true}],"loanedCards":[],"specialRules":["behemothOurs"],"status":"READY"},"coins":335,"xp":265,"prints":3}
A77: c6m04 | B77: 6 | C77: hydrodam | D77: varga | E77: main_battle_tank;heavy_tank;twin_tank;tank_destroyer;fpv_carrier;flame_tank;ifv;mlrs | I77: linh | J77: FALSE | K77: 7 | L77: co_kich_ban | AD77: 350 | AO77: Normal | AP77: commander | AR77: 15 | AT77: 0.95 | AU77: west | AV77: Attack | AW77: Capture | AY77: 3 | BJ77: Anchor | BK77: 38 | BL77: 28 | BM77: 1.55 | BN77: west;town;east | BO77: 3 | BR77: 3 | BX77: 12 | BY77: 660 | CR77: Rain | CS77: 280 | CT77: Assets/MachineBrigade/Resources/Data/campaign.json: missions[86] | CU77: {"id":"c6m04","chapter":6,"map":"hydrodam","weather":"Rain","goal":"Capture","points":["west","town","east"],"enemyOwns":["west"],"general":"varga","reinforcements":3,"enemyAi":"commander","enemyStance":"Attack","difficulty":"Normal","enemyCp":15,"enemyIncome":0.95,"enemyDeck":["main_battle_tank","heavy_tank","twin_tank","tank_destroyer","fpv_carrier","flame_tank","ifv","mlrs"],"playerCp":28,"playerIncome":1.55,"playerCap":38,"playerBase":"Anchor","starTime":660,"starLosses":12,"radio":[{"key":"radio.linh.c6m04.1","on":"Start"}],"hqLevel":3,"missionEvents":["enemy_wave","accord_wave","sea_fog"],"coins":350,"xp":280,"prints":3}
A78: c6m05 | B78: 6 | C78: whiteout | D78: varga | E78: main_battle_tank;heavy_tank;aa_vehicle;tank_destroyer;mlrs;ifv | H78: behemoth_mk2 | I78: mai | J78: FALSE | K78: 14 | L78: co_kich_ban | R78: behemoth | S78: 2.2 | U78: 225 | W78: behemoth_mk2 | Y78: 84 | Z78: 84 | AB78: NoStrikes | AD78: 505 | AO78: Normal | AP78: commander | AR78: 13 | AT78: 0.85 | AV78: Attack | AW78: Boss | BB78: m18 | BK78: 36 | BL78: 26 | BM78: 1.45 | BO78: 5 | BR78: 3 | BX78: 12 | BY78: 780 | CG78: 1200 | CR78: Fog | CS78: 405 | CT78: Assets/MachineBrigade/Resources/Data/campaign.json: missions[82] | CU78: {"id":"c6m05","chapter":6,"map":"whiteout","weather":"Fog","goal":"Boss","legacy":"m18","general":"varga","timeLimit":1200,"reinforcements":3,"boss":{"def":"behemoth_mk2","x":84,"z":84,"heading":225,"name":"behemoth_mk2","fallback":"behemoth","fallbackHealth":2.2},"enemyAi":"commander","enemyStance":"Attack","difficulty":"Normal","enemyCp":13,"enemyIncome":0.85,"enemyDeck":["main_battle_tank","heavy_tank","aa_vehicle","tank_destroyer","mlrs","ifv"],"playerCp":26,"playerIncome":1.45,"playerCap":36,"starTime":780,"starLosses":12,"challenge":{"kind":"NoStrikes"},"radio":[{"key":"radio.mai.c6m05.1","on":"Start"},{"key":"radio.varga.c6m05.2","on":"Boss"}],"missionEvents":["accord_artillery","snowstorm"],"coins":505,"xp":405,"prints":5}
A79: c6m06 | B79: 6 | C79: hydrodam | D79: varga | E79: main_battle_tank;heavy_tank;twin_tank;tank_destroyer;fpv_carrier;flame_tank;ifv;mlrs | I79: khai | J79: FALSE | K79: 7 | L79: co_kich_ban | AD79: 355 | AO79: Normal | AP79: both | AR79: 11 | AT79: 0.9 | AV79: Attack | AW79: Hold | AX79: 240 | BJ79: Anchor | BK79: 42 | BL79: 28 | BM79: 1.4 | BN79: town | BO79: 3 | BR79: 3 | BX79: 12 | BY79: 0 | CJ79: 40 | CK79: 0.35 | CL79: 45 | CM79: 12 | CN79: 5 | CO79: main_battle_tank;ifv;flame_tank;mortar_carrier;twin_tank | CP79: 2 | CR79: Fog | CS79: 285 | CT79: Assets/MachineBrigade/Resources/Data/campaign.json: missions[87] | CU79: {"id":"c6m06","chapter":6,"map":"hydrodam","weather":"Fog","goal":"Hold","points":["town"],"holdSeconds":240,"general":"varga","reinforcements":3,"units":[{"def":"main_battle_tank","team":0,"x":2.0,"z":-8.0,"heading":45},{"def":"heavy_tank","team":0,"x":-3.53,"z":-0.39,"heading":45},{"def":"tank_destroyer","team":0,"x":-12.47,"z":-3.3,"heading":45},{"def":"heavy_aa","team":0,"x":-12.47,"z":-12.7,"heading":45},{"def":"mlrs","team":0,"x":-3.53,"z":-15.61,"heading":45}],"enemyAi":"both","enemyStance":"Attack","difficulty":"Normal","enemyCp":11,"enemyIncome":0.9,"enemyDeck":["main_battle_tank","heavy_tank","twin_tank","tank_destroyer","fpv_carrier","flame_tank","ifv","mlrs"],"playerCp":28,"playerIncome":1.4,"playerCap":42,"playerBase":"Anchor","waves":{"first":40,"interval":45,"size":2,"grow":0.35,"maxSize":5,"maxAlive":12,"roster":["main_battle_tank","ifv","flame_tank","mortar_carrier","twin_tank"]},"starTime":0,"starLosses":12,"radio":[{"key":"radio.khai.c6m06.1","on":"Start"}],"unlocks":[],"missionEvents":["general_field","supply_raid","supply_drop"],"coins":355,"xp":285,"prints":3}
A80: c6m07 | B80: 6 | C80: ashfield | D80: varga | E80: main_battle_tank;heavy_tank;twin_tank;tank_destroyer;fpv_carrier;flame_tank;ifv;mlrs | I80: khai | J80: FALSE | K80: 7 | L80: co_kich_ban | N80: headquarters | O80: 0 | P80: 0 | AD80: 345 | AO80: Normal | AP80: both | AR80: 11 | AT80: 0.85 | AV80: Attack | AW80: Relieve | BJ80: Anchor | BK80: 38 | BL80: 28 | BM80: 1.5 | BO80: 3 | BR80: 3 | BT80: TRUE | BX80: 10 | BY80: 540 | CB80: 3 | CG80: 1000 | CJ80: 70 | CK80: 0.3 | CL80: 60 | CM80: 12 | CN80: 4 | CO80: main_battle_tank;ifv;mortar_carrier;tank_destroyer | CP80: 2 | CQ80: -60;-80;-80;-30 | CR80: Overcast | CS80: 275 | CT80: Assets/MachineBrigade/Resources/Data/campaign.json: missions[85] | CU80: {"id":"c6m07","chapter":6,"map":"ashfield","reversed":true,"weather":"Overcast","goal":"Relieve","targetHealth":3.0,"reinforcements":3,"timeLimit":1000,"general":"varga","ally":{"x":0,"z":0,"hq":"headquarters","structures":[{"def":"mg_bunker","team":0,"x":-15.0,"z":-0.0,"heading":225},{"def":"gun_turret","team":0,"x":-0.0,"z":-15.0,"heading":225},{"def":"aa_turret","team":0,"x":15.0,"z":-0.0,"heading":225},{"def":"guard_tower","team":0,"x":0.0,"z":15.0,"heading":225}],"units":[{"def":"ifv","team":0,"x":2.0,"z":6.0,"heading":225},{"def":"main_battle_tank","team":0,"x":10.0,"z":6.0,"heading":225}]},"hunt":[{"def":"heavy_tank","x":-39.2,"z":-7.95,"heading":45},{"def":"tank_destroyer","x":-18.23,"z":-35.6,"heading":45},{"def":"main_battle_tank","x":16.47,"z":-36.45,"heading":45},{"def":"mlrs","x":38.77,"z":-9.85,"heading":45},{"def":"ifv","x":31.87,"z":24.17,"heading":45},{"def":"flame_tank","x":0.98,"z":39.99,"heading":45},{"def":"main_battle_tank","x":-30.66,"z":25.7,"heading":45}],"enemyAi":"both","enemyStance":"Attack","difficulty":"Normal","enemyCp":11,"enemyIncome":0.85,"enemyDeck":["main_battle_tank","heavy_tank","twin_tank","tank_destroyer","fpv_carrier","flame_tank","ifv","mlrs"],"playerCp":28,"playerIncome":1.5,"playerCap":38,"playerBase":"Anchor","waves":{"first":70,"interval":60,"size":2,"grow":0.3,"maxSize":4,"maxAlive":12,"roster":["main_battle_tank","ifv","mortar_carrier","tank_destroyer"],"spawns":[-60,-80,-80,-30]},"starTime":540,"starLosses":10,"radio":[{"key":"radio.khai.c6m07.1","on":"Start"}],"missionEvents":["enemy_counterattack","brandt_line"],"coins":345,"xp":275,"prints":3}
A81: c6m08 | B81: 6 | C81: landingbeach | E81: armored_car;light_tank;ifv;main_battle_tank;mortar_carrier;rocket_technical | H81: landing_hovercraft | I81: linh | J81: FALSE | K81: 13 | L81: co_kich_ban | R81: mobile_fortress | S81: 0.5 | U81: 315 | W81: landing_hovercraft | X81: 58.0;-92.0;20;-45;0;0;45;-30 | Y81: 58 | Z81: -92 | AD81: 515 | AO81: Normal | AP81: commander | AR81: 13 | AT81: 0.9 | AV81: Attack | AW81: Boss | BJ81: Anchor | BK81: 40 | BL81: 30 | BM81: 1.55 | BO81: 5 | BR81: 2 | BX81: 8 | BY81: 600 | CG81: 1140 | CR81: Night | CS81: 410 | CT81: Assets/MachineBrigade/Resources/Data/campaign.json: missions[84] | CU81: {"id":"c6m08","chapter":6,"map":"landingbeach","weather":"Night","goal":"Boss","timeLimit":1140,"reinforcements":2,"boss":{"def":"landing_hovercraft","x":58.0,"z":-92.0,"heading":315,"route":[58.0,-92.0,20,-45,0,0,45,-30],"fallback":"mobile_fortress","fallbackHealth":0.5,"name":"landing_hovercraft"},"enemyAi":"commander","enemyStance":"Attack","difficulty":"Normal","enemyCp":13,"enemyIncome":0.9,"enemyDeck":["armored_car","light_tank","ifv","main_battle_tank","mortar_carrier","rocket_technical"],"playerCp":30,"playerIncome":1.55,"playerBase":"Anchor","starTime":600,"starLosses":8,"radio":[{"key":"radio.linh.c6m08.p1","on":"Start"},{"key":"radio.khai.c6m08.p2","on":"Win"}],"playerCap":40,"missionEvents":["accord_landing","loot_drop"],"coins":515,"xp":410,"prints":5}
A82: c6m09 | B82: 6 | C82: whiteout | D82: varga | I82: khai | J82: FALSE | K82: 8 | L82: co_kich_ban | AD82: 355 | AO82: Normal | AP82: commander | AQ82: Target | AR82: 11 | AS82: 2 | AT82: 0.35 | AV82: Defend | AW82: Duel | BJ82: Anchor | BK82: 40 | BL82: 30 | BM82: 2.35 | BO82: 3 | BR82: 1 | BS82: TRUE | BT82: TRUE | BX82: 14 | BY82: 900 | CB82: 0.3 | CG82: 1800 | CR82: Fog | CS82: 285 | CT82: Assets/MachineBrigade/Resources/Data/campaign.json: missions[88] | CU82: {"id":"c6m09","chapter":6,"map":"whiteout","reversed":true,"weather":"Fog","goal":"Duel","targetHealth":0.3,"general":"varga","enemyBase":"Target","enemyHq":2,"replay":true,"reinforcements":1,"timeLimit":1800,"units":[{"def":"artillery","team":0,"x":80.0,"z":86.0,"heading":225},{"def":"artillery","team":0,"x":89.0,"z":80.8,"heading":225},{"def":"mlrs","team":0,"x":89.0,"z":91.2,"heading":225}],"enemyAi":"commander","enemyStance":"Defend","difficulty":"Normal","enemyCp":11,"enemyIncome":0.35,"playerCp":30,"playerIncome":2.35,"playerCap":40,"playerBase":"Anchor","starTime":900,"starLosses":14,"radio":[{"key":"radio.varga.c6m09.1","on":"Start"},{"key":"radio.varga.c6m09.2","on":"Win"},{"key":"radio.linh.c6m09.d1","on":"Win"}],"missionEvents":["enemy_barrage","brandt_line","snowstorm"],"coins":355,"xp":285,"prints":3}
A83: c6m10 | B83: 6 | C83: hydrodam | D83: varga | E83: main_battle_tank;heavy_tank;twin_tank;tank_destroyer;fpv_carrier;flame_tank;ifv;mlrs | I83: khai | J83: FALSE | K83: 15 | L83: co_kich_ban | M83: 45 | O83: -100 | P83: -60 | AD83: 880 | AO83: Normal | AP83: both | AR83: 15 | AT83: 1 | AV83: Attack | AW83: Hold | BC83: TRUE | BF83: 146 | BG83: 146 | BH83: -146 | BI83: -146 | BJ83: Defend | BK83: 44 | BL83: 30 | BM83: 1.7 | BO83: 8 | BR83: 3 | BS83: TRUE | BX83: 20 | BY83: 1440 | CH83: Epic | CJ83: 60 | CK83: 0.4 | CL83: 55 | CM83: 16 | CN83: 6 | CO83: main_battle_tank;heavy_tank;ifv;twin_tank;mlrs;flame_tank | CP83: 3 | CR83: Storm | CS83: 705 | CT83: Assets/MachineBrigade/Resources/Data/campaign.json: missions[91] | CU83: {"id":"c6m10","chapter":6,"map":"hydrodam","weather":"Storm","goal":"Hold","operation":true,"replay":true,"general":"varga","reinforcements":3,"playArea":{"minX":-146,"minZ":-146,"maxX":146,"maxZ":146},"enemyAi":"both","enemyStance":"Attack","difficulty":"Normal","enemyCp":15,"enemyIncome":1.0,"enemyDeck":["main_battle_tank","heavy_tank","twin_tank","tank_destroyer","fpv_carrier","flame_tank","ifv","mlrs"],"playerCp":30,"playerIncome":1.7,"playerCap":44,"playerBase":"Defend","towerGear":"Epic","waves":{"first":60,"interval":55,"size":3,"grow":0.4,"maxSize":6,"maxAlive":16,"roster":["main_battle_tank","heavy_tank","ifv","twin_tank","mlrs","flame_tank"]},"ally":{"x":-100,"z":-60,"heading":45},"stages":[{"stage":"crest","goal":"Survive","points":["town"],"surviveSeconds":240,"cp":8,"events":[{"at":"start","kind":"Radio","key":"radio.khai.c6m10.s1"}],"choices":[{"key":"spillway","next":"spillway"},{"key":"station","next":"station"}],"missionEvents":["accord_artillery"]},{"stage":"spillway","goal":"Destroy","targets":["fuel_bladder","barn","cottage"],"targetX":60,"targetZ":-100,"targetRadius":45,"targetHealth":2,"cp":6,"next":"monster","events":[{"at":"end","kind":"Income","team":1,"amount":0.7},{"at":"end","kind":"Radio","key":"radio.enemyWeakened"}]},{"stage":"station","goal":"Survive","points":["west"],"surviveSeconds":150,"cp":6,"next":"monster","events":[{"at":"end","kind":"Strike","team":0,"support":"airstrike","every":55},{"at":"end","kind":"Radio","key":"radio.alliedStrikes"}]},{"stage":"monster","goal":"Boss","boss":{"def":"moloch","x":90,"z":90,"heading":225,"route":[50,40,10,10,-20,-20],"name":"moloch","fallback":"mobile_fortress","fallbackHealth":1.8},"cp":10,"events":[{"at":"start","kind":"Radio","key":"radio.varga.c6m10.s3"}],"missionEvents":["hawk_strike"]},{"stage":"relief","goal":"Survive","surviveSeconds":360,"events":[{"at":"start","kind":"Radio","key":"radio.hung.c6m10.s4"},{"at":"40","kind":"AllyReinforce","units":["main_battle_tank","main_battle_tank","ifv","aa_vehicle"]},{"at":"60","kind":"Reinforce","team":1,"units":["heavy_tank","twin_tank","mlrs","flame_tank"]},{"at":"120","kind":"AllyReinforce","units":["heavy_tank","tank_destroyer","mlrs","heavy_aa"]}],"missionEvents":["enemy_counterattack","supply_drop"]}],"starTime":1440,"starLosses":20,"radio":[{"key":"radio.khai.c6m10.1","on":"Start"},{"key":"radio.khai.c6m10.2","on":"Win"},{"key":"radio.linh.c6m10.q1","on":"Win"}],"missionEvents":["enemy_all_directions","brandt_line","dam_breach"],"navStates":[{"id":"flood","initial":"dry","states":[{"name":"dry"},{"name":"rising","blocks":[{"x":4,"z":-100,"w":28,"d":10}]},{"name":"high","blocks":[{"x":4,"z":-100,"w":28,"d":28}]},{"name":"flood","blocks":[{"x":4,"z":-100,"w":28,"d":28},{"x":-18,"z":-52,"w":6,"d":64},{"x":14,"z":-52,"w":6,"d":64}]}]}],"coins":880,"xp":705,"prints":8}
A84: c6m11 | B84: 6 | C84: greenvale | D84: varga | E84: main_battle_tank;heavy_tank;twin_tank;tank_destroyer;fpv_carrier;flame_tank;ifv;mlrs | I84: khai | J84: FALSE | K84: 7 | L84: co_kich_ban | AD84: 330 | AO84: Normal | AP84: both | AR84: 13 | AT84: 0.9 | AV84: Attack | AW84: Protect | BB84: m22 | BJ84: Anchor | BK84: 40 | BL84: 30 | BM84: 1.55 | BO84: 3 | BP84: 1 | BX84: 10 | BY84: 0 | CA84: 420 | CB84: 8 | CF84: silo;water_tower | CJ84: 100 | CK84: 0.3 | CL84: 70 | CM84: 10 | CN84: 4 | CO84: main_battle_tank;ifv;flame_tank;tank_destroyer | CP84: 2 | CR84: Storm | CS84: 265 | CT84: Assets/MachineBrigade/Resources/Data/campaign.json: missions[80] | CU84: {"id":"c6m11","chapter":6,"map":"greenvale","weather":"Storm","goal":"Protect","targets":["silo","water_tower"],"protectNeeded":1,"targetHealth":8,"surviveSeconds":420,"enemyAi":"both","enemyStance":"Attack","difficulty":"Normal","enemyCp":13,"enemyIncome":0.9,"enemyDeck":["main_battle_tank","heavy_tank","twin_tank","tank_destroyer","fpv_carrier","flame_tank","ifv","mlrs"],"playerCp":30,"playerIncome":1.55,"playerCap":40,"waves":{"first":100,"interval":70,"size":2,"grow":0.3,"maxSize":4,"maxAlive":10,"roster":["main_battle_tank","ifv","flame_tank","tank_destroyer"]},"playerBase":"Anchor","starTime":0,"starLosses":10,"general":"varga","legacy":"m22","radio":[{"key":"radio.khai.c6m11.1","on":"Start"},{"key":"radio.varga.c6m11.2","at":60}],"missionEvents":[{"id":"enemy_all_directions","params":{"size":9}},"accord_relief"],"coins":330,"xp":265,"prints":3}
A85: c6m12 | B85: 6 | C85: landingbeach | D85: varga | E85: main_battle_tank;heavy_tank;twin_tank;tank_destroyer;fpv_carrier;flame_tank;ifv;mlrs | I85: linh | J85: FALSE | K85: 7 | L85: co_kich_ban | AD85: 340 | AO85: Normal | AP85: commander | AR85: 13 | AT85: 0.9 | AV85: Defend | AW85: Hunt | BJ85: Anchor | BK85: 40 | BL85: 30 | BM85: 1.55 | BO85: 3 | BW85: linh | BX85: 6 | BY85: 480 | CB85: 2 | CG85: 900 | CR85: Rain | CS85: 270 | CT85: Assets/MachineBrigade/Resources/Data/campaign.json: missions[83] | CU85: {"id":"c6m12","chapter":6,"map":"landingbeach","weather":"Rain","goal":"Hunt","timeLimit":900,"targetHealth":2,"hunt":[{"def":"mortar_carrier","x":-40,"z":70,"heading":225,"route":[-60,90,-30,60,-50,50]},{"def":"mortar_carrier","x":20,"z":50,"heading":225,"route":[10,70,40,40,20,30]},{"def":"mlrs","x":60,"z":20,"heading":225,"route":[80,40,50,0,70,-10]}],"units":[{"def":"light_tank","team":1,"x":-28.0,"z":65.0,"heading":225},{"def":"ifv","team":1,"x":-38.5,"z":71.06,"heading":225},{"def":"armored_car","team":1,"x":-38.5,"z":58.94,"heading":225},{"def":"light_tank","team":1,"x":61.0,"z":25.0,"heading":225},{"def":"rocket_technical","team":1,"x":49.0,"z":25.0,"heading":225}],"enemyAi":"commander","enemyStance":"Defend","difficulty":"Normal","enemyCp":13,"enemyIncome":0.9,"enemyDeck":["main_battle_tank","heavy_tank","twin_tank","tank_destroyer","fpv_carrier","flame_tank","ifv","mlrs"],"playerCp":30,"playerIncome":1.55,"playerBase":"Anchor","starTime":480,"starLosses":6,"general":"varga","speaker":"linh","playerCap":40,"radio":[{"key":"radio.linh.c6m12.1","on":"Start"},{"key":"radio.brandt.c6m12.2","at":25}],"missionEvents":["landing_assault","nadia_intel","storm_front"],"coins":340,"xp":270,"prints":3}
A86: c6m13 | B86: 6 | C86: ashfield | D86: varga | E86: main_battle_tank;heavy_tank;twin_tank;tank_destroyer;fpv_carrier;flame_tank;ifv;mlrs | F86: twin_tank | I86: brandt | J86: FALSE | K86: 9 | L86: co_kich_ban | AD86: 320 | AO86: Easy | AP86: both | AR86: 13 | AT86: 0.9 | AV86: Attack | AW86: Outpost | AX86: 150 | BJ86: Anchor | BK86: 40 | BL86: 30 | BM86: 1.55 | BN86: town | BO86: 3 | BR86: 1 | BW86: brandt | BX86: 6 | BY86: 480 | CG86: 1000 | CJ86: 60 | CK86: 0.3 | CL86: 55 | CM86: 10 | CN86: 4 | CO86: main_battle_tank;ifv;tank_destroyer;flame_tank | CP86: 2 | CQ86: 90;60;60;95;100;20 | CR86: Rain | CS86: 255 | CT86: Assets/MachineBrigade/Resources/Data/campaign.json: missions[77] | CU86: {"id":"c6m13","chapter":6,"map":"ashfield","weather":"Rain","goal":"Outpost","points":["town"],"holdSeconds":150,"reinforcements":1,"timeLimit":1000,"enemyAi":"both","enemyStance":"Attack","difficulty":"Easy","enemyCp":13,"enemyIncome":0.9,"enemyDeck":["main_battle_tank","heavy_tank","twin_tank","tank_destroyer","fpv_carrier","flame_tank","ifv","mlrs"],"playerCp":30,"playerIncome":1.55,"waves":{"first":60,"interval":55,"size":2,"grow":0.3,"maxSize":4,"maxAlive":10,"roster":["main_battle_tank","ifv","tank_destroyer","flame_tank"],"spawns":[90,60,60,95,100,20]},"starTime":480,"starLosses":6,"playerBase":"Anchor","general":"varga","speaker":"brandt","playerCap":40,"radio":[{"key":"radio.brandt.c6m13.1","on":"Start"},{"key":"radio.khai.c6m13.2","on":"Win"},{"key":"radio.brandt.c6m13.3","on":"Win"}],"missionEvents":["enemy_counterattack","accord_wave","skies_clear"],"unlocks":["twin_tank"],"coins":320,"xp":255,"prints":3}
A87: c6m14 | B87: 6 | C87: hydrodam | D87: varga | E87: strike_drone;fpv_carrier;recon_drone;ew_jammer;ifv;main_battle_tank;aa_vehicle | I87: khai | J87: TRUE | K87: 10 | L87: co_kich_ban | AD87: 365 | AF87: 6 | AG87: supply_truck | AH87: 225 | AJ87: 14 | AK87: 4 | AL87: -30;0;-52;-12;-80;-60;-108;-104 | AM87: 0 | AN87: 0 | AO87: Normal | AP87: waves | AR87: 13 | AT87: 0.9 | AV87: Attack | AW87: Evacuate | BJ87: Anchor | BK87: 40 | BL87: 30 | BM87: 1.55 | BO87: 3 | BR87: 2 | BU87: TRUE | BW87: khai | BX87: 10 | BY87: 600 | CG87: 900 | CJ87: 50 | CK87: 0.35 | CL87: 50 | CM87: 12 | CN87: 5 | CO87: strike_drone;fpv_carrier;recon_drone | CP87: 2 | CR87: Clear | CS87: 290 | CT87: Assets/MachineBrigade/Resources/Data/campaign.json: missions[90] | CU87: {"id":"c6m14","chapter":6,"map":"hydrodam","weather":"Clear","goal":"Evacuate","convoyCount":6,"convoyNeeded":4,"convoyInterval":14,"timeLimit":900,"general":"varga","reinforcements":2,"convoy":{"def":"supply_truck","x":0,"z":0,"heading":225,"route":[-30,0,-52,-12,-80,-60,-108,-104]},"units":[{"def":"heavy_tank","team":0,"x":2.0,"z":-6.0,"heading":45},{"def":"heavy_aa","team":0,"x":-6.0,"z":2.0,"heading":45},{"def":"tank_destroyer","team":0,"x":-14.0,"z":-6.0,"heading":45},{"def":"ifv","team":0,"x":-6.0,"z":-14.0,"heading":45}],"enemyAi":"waves","enemyStance":"Attack","difficulty":"Normal","enemyCp":13,"enemyIncome":0.9,"enemyDeck":["strike_drone","fpv_carrier","recon_drone","ew_jammer","ifv","main_battle_tank","aa_vehicle"],"playerCp":30,"playerIncome":1.55,"playerCap":40,"playerBase":"Anchor","waves":{"first":50,"interval":50,"size":2,"grow":0.35,"maxSize":5,"maxAlive":12,"roster":["strike_drone","fpv_carrier","recon_drone"]},"starTime":600,"starLosses":10,"speaker":"khai","setPiece":true,"radio":[{"key":"radio.varga.c6m14.1","on":"Start"},{"key":"radio.khai.c6m14.2","at":2},{"key":"radio.linh.c6m14.3","at":45},{"key":"radio.varga.c6m14.4","on":"Win"}],"missionEvents":[{"id":"ceasefire","params":{"seconds":900,"faction":true}},"supply_drop","cloud_over",{"id":"dam_breach","trigger":{"at":240,"every":150,"times":3}}],"fixedDeck":{"vehicleIds":["heavy_aa","iron_beam","aa_gun_vehicle","zu23_technical","aa_vehicle","engineer_vehicle","armored_bulldozer","ammo_carrier"],"supportIds":["airstrike","repair_drop"],"placedAllies":[],"loanedCards":["aa_gun_vehicle"],"specialRules":["ceasefireFaction"],"status":"READY"},"navStates":[{"id":"flood","initial":"dry","states":[{"name":"dry"},{"name":"rising","blocks":[{"x":4,"z":-100,"w":28,"d":10}]},{"name":"high","blocks":[{"x":4,"z":-100,"w":28,"d":28}]},{"name":"flood","blocks":[{"x":4,"z":-100,"w":28,"d":28},{"x":-18,"z":-52,"w":6,"d":64},{"x":14,"z":-52,"w":6,"d":64}]}]}],"coins":365,"xp":290,"prints":3}
A88: c6m15 | B88: 6 | C88: hydrodam | D88: varga | E88: main_battle_tank;heavy_tank;twin_tank;tank_destroyer;fpv_carrier;flame_tank;ifv;mlrs | I88: linh | J88: FALSE | K88: 8 | L88: co_kich_ban | AD88: 360 | AO88: Normal | AP88: commander | AR88: 15 | AT88: 0.95 | AU88: west | AV88: Attack | AW88: Capture | BJ88: None | BK88: 40 | BL88: 30 | BM88: 1.55 | BN88: west;town;east | BO88: 3 | BR88: 3 | BW88: linh | BX88: 12 | BY88: 660 | CR88: Overcast | CS88: 290 | CT88: Assets/MachineBrigade/Resources/Data/campaign.json: missions[89] | CU88: {"id":"c6m15","chapter":6,"map":"hydrodam","weather":"Overcast","goal":"Capture","points":["west","town","east"],"enemyOwns":["west"],"general":"varga","reinforcements":3,"enemyAi":"commander","enemyStance":"Attack","difficulty":"Normal","enemyCp":15,"enemyIncome":0.95,"enemyDeck":["main_battle_tank","heavy_tank","twin_tank","tank_destroyer","fpv_carrier","flame_tank","ifv","mlrs"],"playerCp":30,"playerIncome":1.55,"playerCap":40,"playerBase":"None","starTime":660,"starLosses":12,"speaker":"linh","radio":[{"key":"radio.linh.c6m15.1","on":"Start"},{"key":"radio.linh.c6m15.2","on":"Win"}],"missionEvents":[{"id":"enemy_all_directions","params":{"size":9}},"nadia_intel"],"coins":360,"xp":290,"prints":3}
A89: c6m16 | B89: 6 | C89: greenvale | D89: varga | E89: main_battle_tank;heavy_tank;twin_tank;tank_destroyer;fpv_carrier;flame_tank;ifv;mlrs | F89: iron_beam | I89: khai | J89: FALSE | K89: 8 | L89: co_kich_ban | AD89: 325 | AO89: Normal | AP89: commander | AR89: 13 | AT89: 0.9 | AV89: Defend | AW89: Capture | BJ89: Anchor | BK89: 40 | BL89: 30 | BM89: 1.55 | BN89: west;town;east | BO89: 3 | BR89: 0 | BT89: TRUE | BX89: 5 | BY89: 360 | CR89: Fog | CS89: 260 | CT89: Assets/MachineBrigade/Resources/Data/campaign.json: missions[79] | CU89: {"id":"c6m16","chapter":6,"map":"greenvale","reversed":true,"weather":"Fog","goal":"Capture","points":["west","town","east"],"reinforcements":0,"enemyAi":"commander","enemyStance":"Defend","difficulty":"Normal","enemyCp":13,"enemyIncome":0.9,"enemyDeck":["main_battle_tank","heavy_tank","twin_tank","tank_destroyer","fpv_carrier","flame_tank","ifv","mlrs"],"playerCp":30,"playerIncome":1.55,"starTime":360,"starLosses":5,"playerBase":"Anchor","general":"varga","playerCap":40,"radio":[{"key":"radio.khai.c6m16.1","on":"Start"},{"key":"radio.varga.c6m16.2","on":"Win"}],"missionEvents":[{"id":"intercept_files","reward":{"intel":"c6.board"}},"enemy_wave_late","skies_clear"],"unlocks":["iron_beam"],"coins":325,"xp":260,"prints":3}
A90: c6s1 | B90: 6 | C90: ashfield | G90: c6m03 | I90: dieuhau | J90: FALSE | K90: 5 | L90: co_kich_ban | AD90: 1010 | AO90: Normal | AP90: waves | AW90: ShootDown | AZ90: 14 | BJ90: Anchor | BK90: 36 | BL90: 28 | BM90: 1.45 | BO90: 5 | BQ90: 40 | BT90: TRUE | BV90: TRUE | BW90: dieuhau | BX90: 10 | BY90: 600 | CG90: 1200 | CJ90: 30 | CK90: 0.4 | CL90: 42 | CM90: 14 | CN90: 6 | CO90: attack_helicopter;attack_jet;strike_drone;main_battle_tank | CP90: 3 | CR90: Night | CS90: 810 | CT90: Assets/MachineBrigade/Resources/Data/campaign.json: missions[92] | CU90: {"id":"c6s1","chapter":6,"side":true,"after":"c6m03","map":"ashfield","reversed":true,"weather":"Night","goal":"ShootDown","speaker":"dieuhau","killsNeeded":14,"timeLimit":1200,"enemyAi":"waves","difficulty":"Normal","playerCp":28,"playerIncome":1.45,"playerCap":36,"playerBase":"Anchor","waves":{"first":30,"interval":42,"size":3,"grow":0.4,"maxSize":6,"maxAlive":14,"roster":["attack_helicopter","attack_jet","strike_drone","main_battle_tank"]},"rarePrints":40,"starTime":600,"starLosses":10,"radio":[{"key":"radio.dieuhau.c6s1.1","on":"Start"}],"missionEvents":["air_wave","loot_repair"],"coins":1010,"xp":810,"prints":5}
A91: c6s2 | B91: 6 | C91: hydrodam | E91: main_battle_tank;heavy_tank;twin_tank;tank_destroyer;fpv_carrier;flame_tank;ifv;mlrs | G91: c6m06 | I91: linh | J91: FALSE | K91: 5 | L91: co_kich_ban | AB91: NoAircraft | AD91: 1010 | AO91: Normal | AP91: commander | AR91: 15 | AT91: 0.9 | AV91: Defend | AW91: Recon | BK91: 36 | BL91: 28 | BM91: 1.45 | BN91: west;town;east | BO91: 5 | BR91: 1 | BV91: TRUE | BW91: linh | BX91: 8 | BY91: 420 | CG91: 900 | CH91: Epic | CR91: Clear | CS91: 810 | CT91: Assets/MachineBrigade/Resources/Data/campaign.json: missions[93] | CU91: {"id":"c6s2","chapter":6,"side":true,"after":"c6m06","map":"hydrodam","weather":"Clear","goal":"Recon","speaker":"linh","points":["west","town","east"],"timeLimit":900,"reinforcements":1,"enemyAi":"commander","enemyStance":"Defend","difficulty":"Normal","enemyCp":15,"enemyIncome":0.9,"enemyDeck":["main_battle_tank","heavy_tank","twin_tank","tank_destroyer","fpv_carrier","flame_tank","ifv","mlrs"],"playerCp":28,"playerIncome":1.45,"playerCap":36,"towerGear":"Epic","starTime":420,"starLosses":8,"challenge":{"kind":"NoAircraft"},"radio":[{"key":"radio.linh.c6s2.1","on":"Start"}],"missionEvents":["nadia_intel","rain_sets_in"],"coins":1010,"xp":810,"prints":5}
A92: c7m01 | B92: 7 | C92: metrocity | D92: aurel | E92: main_battle_tank;heavy_tank;ifv;aa_vehicle;sam_launcher;attack_helicopter;mlrs | F92: attack_jet | I92: khai | J92: FALSE | K92: 7 | L92: co_kich_ban | AD92: 385 | AO92: Normal | AP92: commander | AR92: 16 | AT92: 0.95 | AU92: town | AV92: Defend | AW92: Capture | BJ92: Anchor | BK92: 40 | BL92: 30 | BM92: 1.6 | BN92: west;town;east | BO92: 4 | BR92: 3 | BX92: 12 | BY92: 660 | CR92: Fog | CS92: 305 | CT92: Assets/MachineBrigade/Resources/Data/campaign.json: missions[98] | CU92: {"id":"c7m01","chapter":7,"map":"metrocity","weather":"Fog","goal":"Capture","points":["west","town","east"],"enemyOwns":["town"],"general":"aurel","reinforcements":3,"enemyAi":"commander","enemyStance":"Defend","difficulty":"Normal","enemyCp":16,"enemyIncome":0.95,"enemyDeck":["main_battle_tank","heavy_tank","ifv","aa_vehicle","sam_launcher","attack_helicopter","mlrs"],"playerCp":30,"playerIncome":1.6,"playerCap":40,"playerBase":"Anchor","starTime":660,"starLosses":12,"radio":[{"key":"radio.khai.c7m01.2","on":"Start"},{"key":"radio.linh.c7m01.q1","on":"Start"}],"missionEvents":["militia","enemy_wave"],"unlocks":["attack_jet"],"coins":385,"xp":305,"prints":4}
A93: c7m02 | B93: 7 | C93: capital | D93: aurel | E93: main_battle_tank;heavy_tank;ifv;aa_vehicle;sam_launcher;attack_helicopter;mlrs | F93: aircraft_hangar | I93: linh | J93: FALSE | K93: 6 | L93: co_kich_ban | AB93: NoAircraft | AD93: 415 | AO93: Normal | AP93: commander | AR93: 16 | AT93: 0.95 | AV93: Defend | AW93: Recon | BK93: 40 | BL93: 30 | BM93: 1.55 | BN93: west;town;east | BO93: 4 | BR93: 2 | BW93: linh | BX93: 10 | BY93: 420 | CG93: 900 | CR93: Overcast | CS93: 335 | CT93: Assets/MachineBrigade/Resources/Data/campaign.json: missions[108] | CU93: {"id":"c7m02","chapter":7,"map":"capital","weather":"Overcast","goal":"Recon","points":["west","town","east"],"timeLimit":900,"speaker":"linh","general":"aurel","reinforcements":2,"enemyAi":"commander","enemyStance":"Defend","difficulty":"Normal","enemyCp":16,"enemyIncome":0.95,"enemyDeck":["main_battle_tank","heavy_tank","ifv","aa_vehicle","sam_launcher","attack_helicopter","mlrs"],"playerCp":30,"playerIncome":1.55,"playerCap":40,"starTime":420,"starLosses":10,"challenge":{"kind":"NoAircraft"},"radio":[{"key":"radio.linh.c7m02.1","on":"Start"}],"unlocks":["aircraft_hangar"],"missionEvents":[{"id":"intercept_files","reward":{"intel":"c7.letters"}},"ew_blackout"],"coins":415,"xp":335,"prints":4}
A94: c7m03 | B94: 7 | C94: metrocity | D94: aurel | E94: main_battle_tank;heavy_tank;ifv;aa_vehicle;sam_launcher;attack_helicopter;mlrs | F94: thermobaric_launcher | I94: khai | J94: FALSE | K94: 7 | L94: co_kich_ban | N94: headquarters | O94: 0 | P94: 0 | AD94: 385 | AO94: Normal | AP94: both | AR94: 12 | AT94: 0.9 | AV94: Attack | AW94: Relieve | BJ94: Anchor | BK94: 40 | BL94: 30 | BM94: 1.6 | BO94: 4 | BR94: 3 | BX94: 12 | BY94: 540 | CB94: 2.2 | CG94: 1000 | CJ94: 70 | CK94: 0.3 | CL94: 60 | CM94: 12 | CN94: 4 | CO94: main_battle_tank;ifv;attack_helicopter | CP94: 2 | CQ94: 60;80;80;30 | CR94: Rain | CS94: 310 | CT94: Assets/MachineBrigade/Resources/Data/campaign.json: missions[99] | CU94: {"id":"c7m03","chapter":7,"map":"metrocity","weather":"Rain","goal":"Relieve","targetHealth":2.2,"reinforcements":3,"timeLimit":1000,"general":"aurel","ally":{"x":0,"z":0,"hq":"headquarters","structures":[{"def":"mg_bunker","team":0,"x":15.0,"z":0.0,"heading":45},{"def":"gun_turret","team":0,"x":0.0,"z":15.0,"heading":45},{"def":"aa_turret","team":0,"x":-15.0,"z":0.0,"heading":45},{"def":"atgm_tower","team":0,"x":-0.0,"z":-15.0,"heading":45}],"units":[{"def":"ifv","team":0,"x":-2.0,"z":-6.0,"heading":45},{"def":"main_battle_tank","team":0,"x":-10.0,"z":-6.0,"heading":45}]},"hunt":[{"def":"heavy_tank","x":39.8,"z":3.99,"heading":225},{"def":"ifv","x":21.69,"z":33.61,"heading":225},{"def":"main_battle_tank","x":-12.75,"z":37.91,"heading":225},{"def":"mlrs","x":-37.59,"z":13.67,"heading":225},{"def":"ifv","x":-34.13,"z":-20.87,"heading":225},{"def":"sam_launcher","x":-4.96,"z":-39.69,"heading":225},{"def":"main_battle_tank","x":27.94,"z":-28.63,"heading":225}],"enemyAi":"both","enemyStance":"Attack","difficulty":"Normal","enemyCp":12,"enemyIncome":0.9,"enemyDeck":["main_battle_tank","heavy_tank","ifv","aa_vehicle","sam_launcher","attack_helicopter","mlrs"],"playerCp":30,"playerIncome":1.6,"playerCap":40,"playerBase":"Anchor","waves":{"first":70,"interval":60,"size":2,"grow":0.3,"maxSize":4,"maxAlive":12,"roster":["main_battle_tank","ifv","attack_helicopter"],"spawns":[60,80,80,30]},"starTime":540,"starLosses":12,"radio":[{"key":"radio.khai.c7m03.1","on":"Start"}],"unlocks":["thermobaric_launcher"],"missionEvents":["militia","enemy_barrage","skies_clear"],"coins":385,"xp":310,"prints":4}
A95: c7m04 | B95: 7 | C95: metrocity | D95: aurel | E95: main_battle_tank;heavy_tank;ifv;aa_vehicle;sam_launcher;attack_helicopter;mlrs | F95: siege_tank | I95: khai | J95: FALSE | K95: 7 | L95: co_kich_ban | AB95: NoAircraft | AD95: 395 | AO95: Normal | AP95: both | AR95: 12 | AT95: 0.9 | AV95: Attack | AW95: Protect | BJ95: Anchor | BK95: 40 | BL95: 30 | BM95: 1.55 | BO95: 4 | BP95: 1 | BR95: 2 | BT95: TRUE | BX95: 12 | BY95: 0 | CA95: 360 | CB95: 14 | CF95: skyscraper;highrise_b;office_block | CJ95: 90 | CK95: 0.3 | CL95: 65 | CM95: 10 | CN95: 4 | CO95: main_battle_tank;ifv;heavy_rocket_artillery;attack_helicopter | CP95: 2 | CR95: Clear | CS95: 315 | CT95: Assets/MachineBrigade/Resources/Data/campaign.json: missions[101] | CU95: {"id":"c7m04","chapter":7,"map":"metrocity","reversed":true,"weather":"Clear","goal":"Protect","targets":["skyscraper","highrise_b","office_block"],"protectNeeded":1,"targetHealth":14,"surviveSeconds":360,"general":"aurel","reinforcements":2,"enemyAi":"both","enemyStance":"Attack","difficulty":"Normal","enemyCp":12,"enemyIncome":0.9,"enemyDeck":["main_battle_tank","heavy_tank","ifv","aa_vehicle","sam_launcher","attack_helicopter","mlrs"],"playerCp":30,"playerIncome":1.55,"playerCap":40,"playerBase":"Anchor","waves":{"first":90,"interval":65,"size":2,"grow":0.3,"maxSize":4,"maxAlive":10,"roster":["main_battle_tank","ifv","heavy_rocket_artillery","attack_helicopter"]},"starTime":0,"starLosses":12,"challenge":{"kind":"NoAircraft"},"radio":[{"key":"radio.khai.c7m04.1","on":"Start"}],"unlocks":["siege_tank"],"missionEvents":["protect_civilians","militia","ew_blackout"],"coins":395,"xp":315,"prints":4}
A96: c7m05 | B96: 7 | C96: metrocity | D96: aurel | E96: main_battle_tank;heavy_tank;aa_vehicle;sam_launcher;attack_helicopter;attack_jet | H96: armored_train | I96: khai | J96: FALSE | K96: 12 | L96: co_kich_ban | U96: 270 | W96: armored_train | X96: 75;101.25;0;101.25;-67.5;101.25;-101.25;101.25;-101.25;33.75 | Y96: 128 | Z96: 101.25 | AD96: 595 | AO96: Normal | AP96: commander | AR96: 12 | AT96: 0.9 | AV96: Attack | AW96: Intercept | BA96: 60 | BB96: m16 | BK96: 40 | BL96: 30 | BM96: 1.6 | BO96: 6 | BR96: 3 | BX96: 12 | BY96: 480 | CG96: 1200 | CR96: Night | CS96: 475 | CT96: Assets/MachineBrigade/Resources/Data/campaign.json: missions[102] | CU96: {"id":"c7m05","chapter":7,"map":"metrocity","weather":"Night","goal":"Intercept","legacy":"m16","launchSeconds":60,"timeLimit":1200,"general":"aurel","reinforcements":3,"boss":{"def":"armored_train","x":128,"z":101.25,"heading":270,"route":[75,101.25,0,101.25,-67.5,101.25,-101.25,101.25,-101.25,33.75],"name":"armored_train"},"units":[{"def":"main_battle_tank","team":0,"x":-75,"z":-18.75,"heading":0},{"def":"tank_destroyer","team":0,"x":-82.5,"z":-11.25,"heading":0},{"def":"heavy_tank","team":0,"x":-67.5,"z":-7.5,"heading":0},{"def":"mlrs","team":0,"x":-93.75,"z":-37.5,"heading":0}],"enemyAi":"commander","enemyStance":"Attack","difficulty":"Normal","enemyCp":12,"enemyIncome":0.9,"enemyDeck":["main_battle_tank","heavy_tank","aa_vehicle","sam_launcher","attack_helicopter","attack_jet"],"playerCp":30,"playerIncome":1.6,"playerCap":40,"starTime":480,"starLosses":12,"radio":[{"key":"radio.linh.c7m05.q1","on":"Start"},{"key":"radio.khai.c7m05.q2","on":"Boss"},{"key":"radio.khai.c7m05.q3","on":"Win"}],"missionEvents":["militia","accord_artillery"],"coins":595,"xp":475,"prints":6}
A97: c7m06 | B97: 7 | C97: capital | D97: aurel | E97: main_battle_tank;heavy_tank;ifv;aa_vehicle;sam_launcher;attack_helicopter;mlrs | I97: khai | J97: FALSE | K97: 7 | L97: co_kich_ban | AD97: 425 | AO97: Normal | AP97: both | AR97: 12 | AT97: 0.9 | AV97: Attack | AW97: Hold | AX97: 240 | BJ97: Anchor | BK97: 44 | BL97: 30 | BM97: 1.5 | BN97: town | BO97: 4 | BR97: 3 | BX97: 14 | BY97: 0 | CJ97: 40 | CK97: 0.35 | CL97: 45 | CM97: 12 | CN97: 5 | CO97: main_battle_tank;ifv;heavy_tank;attack_helicopter | CP97: 2 | CR97: Fog | CS97: 340 | CT97: Assets/MachineBrigade/Resources/Data/campaign.json: missions[110] | CU97: {"id":"c7m06","chapter":7,"map":"capital","weather":"Fog","goal":"Hold","points":["town"],"holdSeconds":240,"general":"aurel","reinforcements":3,"units":[{"def":"heavy_tank","team":0,"x":3.0,"z":-8.0,"heading":45},{"def":"main_battle_tank","team":0,"x":-1.5,"z":-0.21,"heading":45},{"def":"tank_destroyer","team":0,"x":-10.5,"z":-0.21,"heading":45},{"def":"heavy_aa","team":0,"x":-15.0,"z":-8.0,"heading":45},{"def":"mlrs","team":0,"x":-10.5,"z":-15.79,"heading":45},{"def":"ifv","team":0,"x":-1.5,"z":-15.79,"heading":45}],"enemyAi":"both","enemyStance":"Attack","difficulty":"Normal","enemyCp":12,"enemyIncome":0.9,"enemyDeck":["main_battle_tank","heavy_tank","ifv","aa_vehicle","sam_launcher","attack_helicopter","mlrs"],"playerCp":30,"playerIncome":1.5,"playerCap":44,"playerBase":"Anchor","waves":{"first":40,"interval":45,"size":2,"grow":0.35,"maxSize":5,"maxAlive":12,"roster":["main_battle_tank","ifv","heavy_tank","attack_helicopter"]},"starTime":0,"starLosses":14,"radio":[{"key":"radio.khai.c7m06.1","on":"Start"}],"missionEvents":["drop_pods","militia","supply_drop"],"coins":425,"xp":340,"prints":4}
A98: c7m07 | B98: 7 | C98: metrocity | D98: aurel | E98: main_battle_tank;heavy_tank;ifv;aa_vehicle;sam_launcher;attack_helicopter;mlrs | I98: linh | J98: FALSE | K98: 7 | L98: co_kich_ban | AB98: Kills | AC98: 28 | AD98: 400 | AO98: Normal | AP98: commander | AR98: 16 | AT98: 0.95 | AV98: Defend | AW98: Hunt | BJ98: Anchor | BK98: 40 | BL98: 32 | BM98: 1.6 | BO98: 4 | BR98: 3 | BX98: 12 | BY98: 660 | CB98: 2.5 | CG98: 1100 | CR98: Storm | CS98: 320 | CT98: Assets/MachineBrigade/Resources/Data/campaign.json: missions[103] | CU98: {"id":"c7m07","chapter":7,"map":"metrocity","weather":"Storm","goal":"Hunt","general":"aurel","timeLimit":1100,"targetHealth":2.5,"reinforcements":3,"hunt":[{"def":"command_vehicle","x":60,"z":60,"heading":225,"route":[80,40,40,80,60,100]},{"def":"command_vehicle","x":-30,"z":90,"heading":225,"route":[-60,100,0,80,-20,60]},{"def":"command_vehicle","x":90,"z":-20,"heading":225,"route":[110,-40,80,10,110,20]}],"units":[{"def":"heavy_tank","team":1,"x":67.0,"z":60.0,"heading":225},{"def":"aa_vehicle","team":1,"x":53.0,"z":60.0,"heading":225},{"def":"ifv","team":1,"x":-24.0,"z":90.0,"heading":225},{"def":"sam_launcher","team":1,"x":-36.0,"z":90.0,"heading":225},{"def":"main_battle_tank","team":1,"x":96.0,"z":-20.0,"heading":225},{"def":"ifv","team":1,"x":84.0,"z":-20.0,"heading":225}],"enemyAi":"commander","enemyStance":"Defend","difficulty":"Normal","enemyCp":16,"enemyIncome":0.95,"enemyDeck":["main_battle_tank","heavy_tank","ifv","aa_vehicle","sam_launcher","attack_helicopter","mlrs"],"playerCp":32,"playerIncome":1.6,"playerCap":40,"playerBase":"Anchor","starTime":660,"starLosses":12,"challenge":{"kind":"Kills","value":28},"radio":[{"key":"radio.linh.c7m07.1","on":"Start"}],"missionEvents":["enemy_wave","nadia_intel","rain_sets_in"],"coins":400,"xp":320,"prints":4}
A99: c7m08 | B99: 7 | C99: capital | D99: aurel | E99: main_battle_tank;heavy_tank;ifv;aa_vehicle;sam_launcher;attack_helicopter;mlrs | I99: khai | J99: FALSE | K99: 7 | L99: co_kich_ban | AD99: 435 | AF99: 6 | AG99: supply_truck | AH99: 270 | AJ99: 14 | AK99: 4 | AL99: -40;0;-80;0;-110;-40;-108;-100 | AM99: 0 | AN99: 0 | AO99: Normal | AP99: both | AR99: 12 | AT99: 0.9 | AV99: Attack | AW99: Evacuate | BJ99: Anchor | BK99: 40 | BL99: 30 | BM99: 1.55 | BO99: 4 | BR99: 2 | BU99: TRUE | BX99: 10 | BY99: 600 | CG99: 900 | CJ99: 50 | CK99: 0.35 | CL99: 50 | CM99: 12 | CN99: 5 | CO99: main_battle_tank;ifv;attack_helicopter | CP99: 2 | CQ99: 80;60;40;100;100;10 | CR99: Night | CS99: 350 | CT99: Assets/MachineBrigade/Resources/Data/campaign.json: missions[114] | CU99: {"id":"c7m08","chapter":7,"map":"capital","weather":"Night","goal":"Evacuate","convoyCount":6,"convoyNeeded":4,"convoyInterval":14,"timeLimit":900,"general":"aurel","reinforcements":2,"convoy":{"def":"supply_truck","x":0,"z":0,"heading":270,"route":[-40,0,-80,0,-110,-40,-108,-100]},"units":[{"def":"heavy_tank","team":0,"x":2.0,"z":-6.0,"heading":45},{"def":"heavy_aa","team":0,"x":-6.0,"z":2.0,"heading":45},{"def":"tank_destroyer","team":0,"x":-14.0,"z":-6.0,"heading":45},{"def":"ifv","team":0,"x":-6.0,"z":-14.0,"heading":45}],"enemyAi":"both","enemyStance":"Attack","difficulty":"Normal","enemyCp":12,"enemyIncome":0.9,"enemyDeck":["main_battle_tank","heavy_tank","ifv","aa_vehicle","sam_launcher","attack_helicopter","mlrs"],"playerCp":30,"playerIncome":1.55,"playerCap":40,"playerBase":"Anchor","waves":{"first":50,"interval":50,"size":2,"grow":0.35,"maxSize":5,"maxAlive":12,"roster":["main_battle_tank","ifv","attack_helicopter"],"spawns":[80,60,40,100,100,10]},"starTime":600,"starLosses":10,"radio":[{"key":"radio.khai.c7m08.1","on":"Start"}],"setPiece":true,"missionEvents":["militia","enemy_air_raid","rain_sets_in"],"coins":435,"xp":350,"prints":4}
A100: c7m09 | B100: 7 | C100: capital | D100: aurel | E100: main_battle_tank;heavy_tank;ifv;aa_vehicle;sam_launcher;attack_helicopter;mlrs | I100: linh | J100: FALSE | K100: 7 | L100: co_kich_ban | AB100: NoStrikes | AD100: 430 | AO100: Normal | AP100: commander | AR100: 16 | AT100: 0.95 | AV100: Defend | AW100: Destroy | BJ100: Anchor | BK100: 40 | BL100: 32 | BM100: 1.6 | BO100: 4 | BR100: 3 | BX100: 12 | BY100: 540 | CB100: 4 | CF100: radar_dome | CG100: 900 | CR100: Clear | CS100: 345 | CT100: Assets/MachineBrigade/Resources/Data/campaign.json: missions[112] | CU100: {"id":"c7m09","chapter":7,"map":"capital","weather":"Clear","goal":"Destroy","targets":["radar_dome"],"targetHealth":4,"timeLimit":900,"general":"aurel","reinforcements":3,"units":[{"def":"heavy_tank","team":1,"x":22.0,"z":-20.0,"heading":225},{"def":"long_sam","team":1,"x":10.0,"z":-8.0,"heading":225},{"def":"ifv","team":1,"x":-2.0,"z":-20.0,"heading":225},{"def":"aa_vehicle","team":1,"x":10.0,"z":-32.0,"heading":225}],"enemyAi":"commander","enemyStance":"Defend","difficulty":"Normal","enemyCp":16,"enemyIncome":0.95,"enemyDeck":["main_battle_tank","heavy_tank","ifv","aa_vehicle","sam_launcher","attack_helicopter","mlrs"],"playerCp":32,"playerIncome":1.6,"playerCap":40,"playerBase":"Anchor","starTime":540,"starLosses":12,"challenge":{"kind":"NoStrikes"},"radio":[{"key":"radio.linh.c7m09.q1","on":"Start"}],"missionEvents":["enemy_wave","accord_artillery","cloud_over"],"coins":430,"xp":345,"prints":4}
...

Sheet Nhiem_vu_quan
A1: id | B1: nhiem_vu_id | C1: thu_tu | D1: def | E1: heading_deg | F1: team | G1: x_m | H1: z_m | I1: nguon | J1: raw_json
A2: c1m06/0 | B2: c1m06 | C2: 0 | D2: light_tank | E2: 45 | F2: 0 | G2: -85 | H2: -88 | I2: Assets/MachineBrigade/Resources/Data/campaign.json: missions[5].units[0] | J2: {"def":"light_tank","team":0,"x":-85.0,"z":-88.0,"heading":45}
A3: c1m06/1 | B3: c1m06 | C3: 1 | D3: ifv | E3: 45 | F3: 0 | G3: -92.5 | H3: -83.67 | I3: Assets/MachineBrigade/Resources/Data/campaign.json: missions[5].units[1] | J3: {"def":"ifv","team":0,"x":-92.5,"z":-83.67,"heading":45}
A4: c1m06/2 | B4: c1m06 | C4: 2 | D4: main_battle_tank | E4: 45 | F4: 0 | G4: -92.5 | H4: -92.33 | I4: Assets/MachineBrigade/Resources/Data/campaign.json: missions[5].units[2] | J4: {"def":"main_battle_tank","team":0,"x":-92.5,"z":-92.33,"heading":45}
A5: c1m09/0 | B5: c1m09 | C5: 0 | D5: light_tank | E5: 45 | F5: 0 | G5: -84 | H5: -90 | I5: Assets/MachineBrigade/Resources/Data/campaign.json: missions[7].units[0] | J5: {"def":"light_tank","team":0,"x":-84.0,"z":-90.0,"heading":45}
A6: c1m09/1 | B6: c1m09 | C6: 1 | D6: light_tank | E6: 45 | F6: 0 | G6: -93 | H6: -84.8 | I6: Assets/MachineBrigade/Resources/Data/campaign.json: missions[7].units[1] | J6: {"def":"light_tank","team":0,"x":-93.0,"z":-84.8,"heading":45}
A7: c1m09/2 | B7: c1m09 | C7: 2 | D7: ifv | E7: 45 | F7: 0 | G7: -93 | H7: -95.2 | I7: Assets/MachineBrigade/Resources/Data/campaign.json: missions[7].units[2] | J7: {"def":"ifv","team":0,"x":-93.0,"z":-95.2,"heading":45}
A8: c2m03/0 | B8: c2m03 | C8: 0 | D8: main_battle_tank | E8: 45 | F8: 0 | G8: -82 | H8: -92 | I8: Assets/MachineBrigade/Resources/Data/campaign.json: missions[12].units[0] | J8: {"def":"main_battle_tank","team":0,"x":-82.0,"z":-92.0,"heading":45}
A9: c2m03/1 | B9: c2m03 | C9: 1 | D9: ifv | E9: 45 | F9: 0 | G9: -91 | H9: -86.8 | I9: Assets/MachineBrigade/Resources/Data/campaign.json: missions[12].units[1] | J9: {"def":"ifv","team":0,"x":-91.0,"z":-86.8,"heading":45}
A10: c2m03/2 | B10: c2m03 | C10: 2 | D10: aa_vehicle | E10: 45 | F10: 0 | G10: -91 | H10: -97.2 | I10: Assets/MachineBrigade/Resources/Data/campaign.json: missions[12].units[2] | J10: {"def":"aa_vehicle","team":0,"x":-91.0,"z":-97.2,"heading":45}
A11: c2m04/0 | B11: c2m04 | C11: 0 | D11: main_battle_tank | E11: 225 | F11: 1 | G11: 6 | H11: 30 | I11: Assets/MachineBrigade/Resources/Data/campaign.json: missions[13].units[0] | J11: {"def":"main_battle_tank","team":1,"x":6.0,"z":30.0,"heading":225}
A12: c2m04/1 | B12: c2m04 | C12: 1 | D12: tank_destroyer | E12: 225 | F12: 1 | G12: -6 | H12: 30 | I12: Assets/MachineBrigade/Resources/Data/campaign.json: missions[13].units[1] | J12: {"def":"tank_destroyer","team":1,"x":-6.0,"z":30.0,"heading":225}
A13: c2m04/2 | B13: c2m04 | C13: 2 | D13: light_tank | E13: 225 | F13: 1 | G13: 106 | H13: -50 | I13: Assets/MachineBrigade/Resources/Data/campaign.json: missions[13].units[2] | J13: {"def":"light_tank","team":1,"x":106.0,"z":-50.0,"heading":225}
... A333: i2m03/6 | B333: i2m03 | C333: 6 | D333: mlrs | E333: 45 | F333: 0 | G333: 7.48 | H333: -9.38 | I333: Assets/MachineBrigade/Resources/Data/campaign.json: missions[96].units[6] | J333: {"def":"mlrs","team":0,"x":7.48,"z":-9.38,"heading":45}

Sheet Nhiem_vu_san
A1: id | B1: nhiem_vu_id | C1: thu_tu | D1: def | E1: heading_deg | F1: route | G1: x_m | H1: z_m | I1: nguon | J1: raw_json
A2: c2m06/0 | B2: c2m06 | C2: 0 | D2: elite_mlrs | E2: 225 | F2: 60;82.5;22.5;60;52.5;22.5;90;45 | G2: 90 | H2: 45 | I2: Assets/MachineBrigade/Resources/Data/campaign.json: missions[15].hunt[0] | J2: {"def":"elite_mlrs","x":90,"z":45,"heading":225,"route":[60,82.5,22.5,60,52.5,22.5,90,45]}
A3: c2m06/1 | B3: c2m06 | C3: 1 | D3: elite_grad | E3: 180 | F3: -60;120;-37.5;75;-15;105 | G3: -15 | H3: 105 | I3: Assets/MachineBrigade/Resources/Data/campaign.json: missions[15].hunt[1] | J3: {"def":"elite_grad","x":-15,"z":105,"heading":180,"route":[-60,120,-37.5,75,-15,105]}
A4: c2m06/2 | B4: c2m06 | C4: 2 | D4: sam_launcher | E4: 225 | F4: 82.5;-37.5;120;-45;105;0 | G4: 105 | H4: 0 | I4: Assets/MachineBrigade/Resources/Data/campaign.json: missions[15].hunt[2] | J4: {"def":"sam_launcher","x":105,"z":0,"heading":225,"route":[82.5,-37.5,120,-45,105,0]}
A5: c2m07/0 | B5: c2m07 | C5: 0 | D5: main_battle_tank | E5: 225 | G5: 36.3 | H5: 11.23 | I5: Assets/MachineBrigade/Resources/Data/campaign.json: missions[16].hunt[0] | J5: {"def":"main_battle_tank","x":36.3,"z":11.23,"heading":225}
A6: c2m07/1 | B6: c2m07 | C6: 1 | D6: tank_destroyer | E6: 225 | G6: 8.43 | H6: 37.05 | I6: Assets/MachineBrigade/Resources/Data/campaign.json: missions[16].hunt[1] | J6: {"def":"tank_destroyer","x":8.43,"z":37.05,"heading":225}
A7: c2m07/2 | B7: c2m07 | C7: 2 | D7: light_tank | E7: 225 | G7: -27.88 | H7: 25.82 | I7: Assets/MachineBrigade/Resources/Data/campaign.json: missions[16].hunt[2] | J7: {"def":"light_tank","x":-27.88,"z":25.82,"heading":225}
A8: c2m07/3 | B8: c2m07 | C8: 3 | D8: mortar_carrier | E8: 225 | G8: -36.3 | H8: -11.23 | I8: Assets/MachineBrigade/Resources/Data/campaign.json: missions[16].hunt[3] | J8: {"def":"mortar_carrier","x":-36.3,"z":-11.23,"heading":225}
A9: c2m07/4 | B9: c2m07 | C9: 4 | D9: ifv | E9: 225 | G9: -8.43 | H9: -37.05 | I9: Assets/MachineBrigade/Resources/Data/campaign.json: missions[16].hunt[4] | J9: {"def":"ifv","x":-8.43,"z":-37.05,"heading":225}
A10: c2m07/5 | B10: c2m07 | C10: 5 | D10: main_battle_tank | E10: 225 | G10: 27.88 | H10: -25.82 | I10: Assets/MachineBrigade/Resources/Data/campaign.json: missions[16].hunt[5] | J10: {"def":"main_battle_tank","x":27.88,"z":-25.82,"heading":225}
A11: c3m06/0 | B11: c3m06 | C11: 0 | D11: mlrs | E11: 225 | F11: 80;90;40;60;70;40 | G11: 60 | H11: 70 | I11: Assets/MachineBrigade/Resources/Data/campaign.json: missions[29].hunt[0] | J11: {"def":"mlrs","x":60,"z":70,"heading":225,"route":[80,90,40,60,70,40]}
A12: c3m06/1 | B12: c3m06 | C12: 1 | D12: artillery | E12: 225 | F12: -40;120;0;90;-30;80 | G12: -20 | H12: 100 | I12: Assets/MachineBrigade/Resources/Data/campaign.json: missions[29].hunt[1] | J12: {"def":"artillery","x":-20,"z":100,"heading":225,"route":[-40,120,0,90,-30,80]}
A13: c3m06/2 | B13: c3m06 | C13: 2 | D13: mlrs | E13: 225 | F13: 110;-10;90;40;120;30 | G13: 100 | H13: 20 | I13: Assets/MachineBrigade/Resources/Data/campaign.json: missions[29].hunt[2] | J13: {"def":"mlrs","x":100,"z":20,"heading":225,"route":[110,-10,90,40,120,30]}
A14: c4m08/0 | B14: c4m08 | C14: 0 | D14: mine_layer | E14: 225 | F14: 90;60;40;80;60;40 | G14: 60 | H14: 70 | I14: Assets/MachineBrigade/Resources/Data/campaign.json: missions[49].hunt[0] | J14: {"def":"mine_layer","x":60,"z":70,"heading":225,"route":[90,60,40,80,60,40]}
A15: c4m08/1 | B15: c4m08 | C15: 1 | D15: mine_layer | E15: 225 | F15: -50;100;0;70;-30;60 | G15: -20 | H15: 90 | I15: Assets/MachineBrigade/Resources/Data/campaign.json: missions[49].hunt[1] | J15: {"def":"mine_layer","x":-20,"z":90,"heading":225,"route":[-50,100,0,70,-30,60]}
A16: c4m08/2 | B16: c4m08 | C16: 2 | D16: mine_layer | E16: 225 | F16: 90;-30;60;10;90;25 | G16: 80 | H16: -10 | I16: Assets/MachineBrigade/Resources/Data/campaign.json: missions[49].hunt[2] | J16: {"def":"mine_layer","x":80,"z":-10,"heading":225,"route":[90,-30,60,10,90,25]}
A17: c4m16/0 | B17: c4m16 | C17: 0 | D17: command_vehicle | E17: 225 | F17: 80;40;40;80;70;90 | G17: 60 | H17: 60 | I17: Assets/MachineBrigade/Resources/Data/campaign.json: missions[48].hunt[0] | J17: {"def":"command_vehicle","x":60,"z":60,"heading":225,"route":[80,40,40,80,70,90]}
A18: c4m16/1 | B18: c4m16 | C18: 1 | D18: command_vehicle | E18: 225 | F18: -60;100;0;80;-20;60 | G18: -30 | H18: 90 | I18: Assets/MachineBrigade/Resources/Data/campaign.json: missions[48].hunt[1] | J18: {"def":"command_vehicle","x":-30,"z":90,"heading":225,"route":[-60,100,0,80,-20,60]}
A19: c4m17/0 | B19: c4m17 | C19: 0 | D19: command_vehicle | E19: 45 | F19: -80;-40;-40;-80;-70;-90 | G19: -60 | H19: -60 | I19: Assets/MachineBrigade/Resources/Data/campaign.json: missions[54].hunt[0] | J19: {"def":"command_vehicle","x":-60,"z":-60,"heading":45,"route":[-80,-40,-40,-80,-70,-90]}
A20: c4m17/1 | B20: c4m17 | C20: 1 | D20: command_vehicle | E20: 45 | F20: 60;-100;0;-80;20;-60 | G20: 30 | H20: -90 | I20: Assets/MachineBrigade/Resources/Data/campaign.json: missions[54].hunt[1] | J20: {"def":"command_vehicle","x":30,"z":-90,"heading":45,"route":[60,-100,0,-80,20,-60]}
A21: c4s2/0 | B21: c4s2 | C21: 0 | D21: command_vehicle | E21: 45 | F21: -80;-40;-40;-80;-70;-90 | G21: -60 | H21: -60 | I21: Assets/MachineBrigade/Resources/Data/campaign.json: missions[60].hunt[0] | J21: {"def":"command_vehicle","x":-60,"z":-60,"heading":45,"route":[-80,-40,-40,-80,-70,-90]}
A22: c4s2/1 | B22: c4s2 | C22: 1 | D22: command_vehicle | E22: 45 | F22: 60;-100;0;-80;20;-60 | G22: 30 | H22: -90 | I22: Assets/MachineBrigade/Resources/Data/campaign.json: missions[60].hunt[1] | J22: {"def":"command_vehicle","x":30,"z":-90,"heading":45,"route":[60,-100,0,-80,20,-60]}
... A25: c5m02/2 | B25: c5m02 | C25: 2 | D25: fpv_carrier | E25: 225 | F25: 110;-40;80;10;110;20 | G25: 90 | H25: -10 | I25: Assets/MachineBrigade/Resources/Data/campaign.json: missions[62].hunt[2] | J25: {"def":"fpv_carrier","x":90,"z":-10,"heading":225,"route":[110,-40,80,10,110,20]}
A26: c5s2/0 | B26: c5s2 | C26: 0 | D26: main_battle_tank | E26: 225 | G26: -23.16 | H26: -4.42 | I26: Assets/MachineBrigade/Resources/Data/campaign.json: missions[75].hunt[0] | J26: {"def":"main_battle_tank","x":-23.16,"z":-4.42,"heading":225}
A27: c5s2/1 | B27: c5s2 | C27: 1 | D27: fpv_carrier | E27: 225 | G27: -55.07 | H27: 19.69 | I27: Assets/MachineBrigade/Resources/Data/campaign.json: missions[75].hunt[1] | J27: {"def":"fpv_carrier","x":-55.07,"z":19.69,"heading":225}
A28: c5s2/2 | B28: c5s2 | C28: 2 | D28: ifv | E28: 225 | G28: -91.91 | H28: 4.12 | I28: Assets/MachineBrigade/Resources/Data/campaign.json: missions[75].hunt[2] | J28: {"def":"ifv","x":-91.91,"z":4.12,"heading":225}
A29: c5s2/3 | B29: c5s2 | C29: 3 | D29: strike_drone | E29: 225 | G29: -96.84 | H29: -35.58 | I29: Assets/MachineBrigade/Resources/Data/campaign.json: missions[75].hunt[3] | J29: {"def":"strike_drone","x":-96.84,"z":-35.58,"heading":225}
A30: c5s2/4 | B30: c5s2 | C30: 4 | D30: mortar_carrier | E30: 225 | G30: -64.93 | H30: -59.69 | I30: Assets/MachineBrigade/Resources/Data/campaign.json: missions[75].hunt[4] | J30: {"def":"mortar_carrier","x":-64.93,"z":-59.69,"heading":225}
A31: c5s2/5 | B31: c5s2 | C31: 5 | D31: main_battle_tank | E31: 225 | G31: -28.09 | H31: -44.12 | I31: Assets/MachineBrigade/Resources/Data/campaign.json: missions[75].hunt[5] | J31: {"def":"main_battle_tank","x":-28.09,"z":-44.12,"heading":225}
A32: c6m07/0 | B32: c6m07 | C32: 0 | D32: heavy_tank | E32: 45 | G32: -39.2 | H32: -7.95 | I32: Assets/MachineBrigade/Resources/Data/campaign.json: missions[85].hunt[0] | J32: {"def":"heavy_tank","x":-39.2,"z":-7.95,"heading":45}
A33: c6m07/1 | B33: c6m07 | C33: 1 | D33: tank_destroyer | E33: 45 | G33: -18.23 | H33: -35.6 | I33: Assets/MachineBrigade/Resources/Data/campaign.json: missions[85].hunt[1] | J33: {"def":"tank_destroyer","x":-18.23,"z":-35.6,"heading":45}
A34: c6m07/2 | B34: c6m07 | C34: 2 | D34: main_battle_tank | E34: 45 | G34: 16.47 | H34: -36.45 | I34: Assets/MachineBrigade/Resources/Data/campaign.json: missions[85].hunt[2] | J34: {"def":"main_battle_tank","x":16.47,"z":-36.45,"heading":45}
A35: c6m07/3 | B35: c6m07 | C35: 3 | D35: mlrs | E35: 45 | G35: 38.77 | H35: -9.85 | I35: Assets/MachineBrigade/Resources/Data/campaign.json: missions[85].hunt[3] | J35: {"def":"mlrs","x":38.77,"z":-9.85,"heading":45}
A36: c6m07/4 | B36: c6m07 | C36: 4 | D36: ifv | E36: 45 | G36: 31.87 | H36: 24.17 | I36: Assets/MachineBrigade/Resources/Data/campaign.json: missions[85].hunt[4] | J36: {"def":"ifv","x":31.87,"z":24.17,"heading":45}
A37: c6m07/5 | B37: c6m07 | C37: 5 | D37: flame_tank | E37: 45 | G37: 0.98 | H37: 39.99 | I37: Assets/MachineBrigade/Resources/Data/campaign.json: missions[85].hunt[5] | J37: {"def":"flame_tank","x":0.98,"z":39.99,"heading":45}
A38: c6m07/6 | B38: c6m07 | C38: 6 | D38: main_battle_tank | E38: 45 | G38: -30.66 | H38: 25.7 | I38: Assets/MachineBrigade/Resources/Data/campaign.json: missions[85].hunt[6] | J38: {"def":"main_battle_tank","x":-30.66,"z":25.7,"heading":45}
A39: c6m12/0 | B39: c6m12 | C39: 0 | D39: mortar_carrier | E39: 225 | F39: -60;90;-30;60;-50;50 | G39: -40 | H39: 70 | I39: Assets/MachineBrigade/Resources/Data/campaign.json: missions[83].hunt[0] | J39: {"def":"mortar_carrier","x":-40,"z":70,"heading":225,"route":[-60,90,-30,60,-50,50]}
A40: c6m12/1 | B40: c6m12 | C40: 1 | D40: mortar_carrier | E40: 225 | F40: 10;70;40;40;20;30 | G40: 20 | H40: 50 | I40: Assets/MachineBrigade/Resources/Data/campaign.json: missions[83].hunt[1] | J40: {"def":"mortar_carrier","x":20,"z":50,"heading":225,"route":[10,70,40,40,20,30]}
A41: c6m12/2 | B41: c6m12 | C41: 2 | D41: mlrs | E41: 225 | F41: 80;40;50;0;70;-10 | G41: 60 | H41: 20 | I41: Assets/MachineBrigade/Resources/Data/campaign.json: missions[83].hunt[2] | J41: {"def":"mlrs","x":60,"z":20,"heading":225,"route":[80,40,50,0,70,-10]}
A42: c7m03/0 | B42: c7m03 | C42: 0 | D42: heavy_tank | E42: 225 | G42: 39.8 | H42: 3.99 | I42: Assets/MachineBrigade/Resources/Data/campaign.json: missions[99].hunt[0] | J42: {"def":"heavy_tank","x":39.8,"z":3.99,"heading":225}
A43: c7m03/1 | B43: c7m03 | C43: 1 | D43: ifv | E43: 225 | G43: 21.69 | H43: 33.61 | I43: Assets/MachineBrigade/Resources/Data/campaign.json: missions[99].hunt[1] | J43: {"def":"ifv","x":21.69,"z":33.61,"heading":225}
A44: c7m03/2 | B44: c7m03 | C44: 2 | D44: main_battle_tank | E44: 225 | G44: -12.75 | H44: 37.91 | I44: Assets/MachineBrigade/Resources/Data/campaign.json: missions[99].hunt[2] | J44: {"def":"main_battle_tank","x":-12.75,"z":37.91,"heading":225}
A45: c7m03/3 | B45: c7m03 | C45: 3 | D45: mlrs | E45: 225 | G45: -37.59 | H45: 13.67 | I45: Assets/MachineBrigade/Resources/Data/campaign.json: missions[99].hunt[3] | J45: {"def":"mlrs","x":-37.59,"z":13.67,"heading":225}
A46: c7m03/4 | B46: c7m03 | C46: 4 | D46: ifv | E46: 225 | G46: -34.13 | H46: -20.87 | I46: Assets/MachineBrigade/Resources/Data/campaign.json: missions[99].hunt[4] | J46: {"def":"ifv","x":-34.13,"z":-20.87,"heading":225}
A47: c7m03/5 | B47: c7m03 | C47: 5 | D47: sam_launcher | E47: 225 | G47: -4.96 | H47: -39.69 | I47: Assets/MachineBrigade/Resources/Data/campaign.json: missions[99].hunt[5] | J47: {"def":"sam_launcher","x":-4.96,"z":-39.69,"heading":225}
A48: c7m03/6 | B48: c7m03 | C48: 6 | D48: main_battle_tank | E48: 225 | G48: 27.94 | H48: -28.63 | I48: Assets/MachineBrigade/Resources/Data/campaign.json: missions[99].hunt[6] | J48: {"def":"main_battle_tank","x":27.94,"z":-28.63,"heading":225}
A49: c7m07/0 | B49: c7m07 | C49: 0 | D49: command_vehicle | E49: 225 | F49: 80;40;40;80;60;100 | G49: 60 | H49: 60 | I49: Assets/MachineBrigade/Resources/Data/campaign.json: missions[103].hunt[0] | J49: {"def":"command_vehicle","x":60,"z":60,"heading":225,"route":[80,40,40,80,60,100]}
A50: c7m07/1 | B50: c7m07 | C50: 1 | D50: command_vehicle | E50: 225 | F50: -60;100;0;80;-20;60 | G50: -30 | H50: 90 | I50: Assets/MachineBrigade/Resources/Data/campaign.json: missions[103].hunt[1] | J50: {"def":"command_vehicle","x":-30,"z":90,"heading":225,"route":[-60,100,0,80,-20,60]}
A51: c7m07/2 | B51: c7m07 | C51: 2 | D51: command_vehicle | E51: 225 | F51: 110;-40;80;10;110;20 | G51: 90 | H51: -20 | I51: Assets/MachineBrigade/Resources/Data/campaign.json: missions[103].hunt[2] | J51: {"def":"command_vehicle","x":90,"z":-20,"heading":225,"route":[110,-40,80,10,110,20]}
A52: c8m03/0 | B52: c8m03 | C52: 0 | D52: elite_mlrs | E52: 45 | F52: -60;-82.5;-22.5;-60;-52.5;-22.5;-90;-45 | G52: -90 | H52: -45 | I52: Assets/MachineBrigade/Resources/Data/campaign.json: missions[119].hunt[0] | J52: {"def":"elite_mlrs","x":-90,"z":-45,"heading":45,"route":[-60,-82.5,-22.5,-60,-52.5,-22.5,-90,-45]}
A53: c8m03/1 | B53: c8m03 | C53: 1 | D53: elite_grad | E53: 0 | F53: 60;-120;37.5;-75;15;-105 | G53: 15 | H53: -105 | I53: Assets/MachineBrigade/Resources/Data/campaign.json: missions[119].hunt[1] | J53: {"def":"elite_grad","x":15,"z":-105,"heading":0,"route":[60,-120,37.5,-75,15,-105]}
A54: c8m03/2 | B54: c8m03 | C54: 2 | D54: sam_launcher | E54: 45 | F54: -82.5;37.5;-120;45;-105;0 | G54: -105 | H54: 0 | I54: Assets/MachineBrigade/Resources/Data/campaign.json: missions[119].hunt[2] | J54: {"def":"sam_launcher","x":-105,"z":0,"heading":45,"route":[-82.5,37.5,-120,45,-105,0]}
A55: c8m04/0 | B55: c8m04 | C55: 0 | D55: main_battle_tank | E55: 45 | G55: -36.3 | H55: -11.23 | I55: Assets/MachineBrigade/Resources/Data/campaign.json: missions[121].hunt[0] | J55: {"def":"main_battle_tank","x":-36.3,"z":-11.23,"heading":45}
A56: c8m04/1 | B56: c8m04 | C56: 1 | D56: tank_destroyer | E56: 45 | G56: -8.43 | H56: -37.05 | I56: Assets/MachineBrigade/Resources/Data/campaign.json: missions[121].hunt[1] | J56: {"def":"tank_destroyer","x":-8.43,"z":-37.05,"heading":45}
A57: c8m04/2 | B57: c8m04 | C57: 2 | D57: light_tank | E57: 45 | G57: 27.88 | H57: -25.82 | I57: Assets/MachineBrigade/Resources/Data/campaign.json: missions[121].hunt[2] | J57: {"def":"light_tank","x":27.88,"z":-25.82,"heading":45}
A58: c8m04/3 | B58: c8m04 | C58: 3 | D58: mortar_carrier | E58: 45 | G58: 36.3 | H58: 11.23 | I58: Assets/MachineBrigade/Resources/Data/campaign.json: missions[121].hunt[3] | J58: {"def":"mortar_carrier","x":36.3,"z":11.23,"heading":45}
A59: c8m04/4 | B59: c8m04 | C59: 4 | D59: ifv | E59: 45 | G59: 8.43 | H59: 37.05 | I59: Assets/MachineBrigade/Resources/Data/campaign.json: missions[121].hunt[4] | J59: {"def":"ifv","x":8.43,"z":37.05,"heading":45}
A60: c8m04/5 | B60: c8m04 | C60: 5 | D60: main_battle_tank | E60: 45 | G60: -27.88 | H60: 25.82 | I60: Assets/MachineBrigade/Resources/Data/campaign.json: missions[121].hunt[5] | J60: {"def":"main_battle_tank","x":-27.88,"z":25.82,"heading":45}
A61: c9m09/0 | B61: c9m09 | C61: 0 | D61: mortar_carrier | E61: 45 | F61: 60;-90;30;-60;50;-50 | G61: 40 | H61: -70 | I61: Assets/MachineBrigade/Resources/Data/campaign.json: missions[145].hunt[0] | J61: {"def":"mortar_carrier","x":40,"z":-70,"heading":45,"route":[60,-90,30,-60,50,-50]}
A62: c9m09/1 | B62: c9m09 | C62: 1 | D62: mortar_carrier | E62: 45 | F62: -10;-70;-40;-40;-20;-30 | G62: -20 | H62: -50 | I62: Assets/MachineBrigade/Resources/Data/campaign.json: missions[145].hunt[1] | J62: {"def":"mortar_carrier","x":-20,"z":-50,"heading":45,"route":[-10,-70,-40,-40,-20,-30]}
A63: c9m09/2 | B63: c9m09 | C63: 2 | D63: mlrs | E63: 45 | F63: -80;-40;-50;0;-70;10 | G63: -60 | H63: -20 | I63: Assets/MachineBrigade/Resources/Data/campaign.json: missions[145].hunt[2] | J63: {"def":"mlrs","x":-60,"z":-20,"heading":45,"route":[-80,-40,-50,0,-70,10]}
A64: c9s1/0 | B64: c9s1 | C64: 0 | D64: command_vehicle | E64: 225 | F64: 80;40;40;80;70;90 | G64: 60 | H64: 60 | I64: Assets/MachineBrigade/Resources/Data/campaign.json: missions[147].hunt[0] | J64: {"def":"command_vehicle","x":60,"z":60,"heading":225,"route":[80,40,40,80,70,90]}
A65: c9s1/1 | B65: c9s1 | C65: 1 | D65: command_vehicle | E65: 225 | F65: -60;100;0;80;-20;60 | G65: -30 | H65: 90 | I65: Assets/MachineBrigade/Resources/Data/campaign.json: missions[147].hunt[1] | J65: {"def":"command_vehicle","x":-30,"z":90,"heading":225,"route":[-60,100,0,80,-20,60]}
A66: c10m06/0 | B66: c10m06 | C66: 0 | D66: long_sam | E66: 45 | F66: -80;-90;-40;-60;-70;-40 | G66: -60 | H66: -70 | I66: Assets/MachineBrigade/Resources/Data/campaign.json: missions[159].hunt[0] | J66: {"def":"long_sam","x":-60,"z":-70,"heading":45,"route":[-80,-90,-40,-60,-70,-40]}
