Workbook

Sheet Am_thanh
A1: id | B1: bank | C1: nhom | D1: bac_co | E1: duong_dan | F1: do_dai_s | G1: kenh | H1: tan_so_mau_hz | I1: nen | J1: tac_gia | K1: nguon_goc | L1: giay_phep | M1: nguon | N1: raw_json
A2: Music/battle_1 | C2: Music | E2: Assets/MachineBrigade/Resources/Audio/Music/battle_1.ogg | F2: 135 | G2: 2 | H2: 44100 | I2: ogg | J2: Armored Advance | K2: Assets/MachineBrigade/Resources/Audio/Music/MUSIC_CREDITS.md | M2: Assets/MachineBrigade/Resources/Audio/Music/battle_1.ogg
A3: Music/battle_2 | C3: Music | E3: Assets/MachineBrigade/Resources/Audio/Music/battle_2.ogg | F3: 132.414 | G3: 2 | H3: 44100 | I3: ogg | J3: Iron Rain | K3: Assets/MachineBrigade/Resources/Audio/Music/MUSIC_CREDITS.md | M3: Assets/MachineBrigade/Resources/Audio/Music/battle_2.ogg
A4: Music/battle_3 | C4: Music | E4: Assets/MachineBrigade/Resources/Audio/Music/battle_3.ogg | F4: 139.13 | G4: 2 | H4: 44100 | I4: ogg | J4: Air Superiority | K4: Assets/MachineBrigade/Resources/Audio/Music/MUSIC_CREDITS.md | M4: Assets/MachineBrigade/Resources/Audio/Music/battle_3.ogg
A5: Music/boss | C5: Music | E5: Assets/MachineBrigade/Resources/Audio/Music/boss.ogg | F5: 125.217 | G5: 2 | H5: 44100 | I5: ogg | J5: Colossus | K5: Assets/MachineBrigade/Resources/Audio/Music/MUSIC_CREDITS.md | M5: Assets/MachineBrigade/Resources/Audio/Music/boss.ogg
A6: Music/defeat | C6: Music | E6: Assets/MachineBrigade/Resources/Audio/Music/defeat.ogg | F6: 9.5 | G6: 2 | H6: 44100 | I6: ogg | J6: Defeat (stinger) | K6: Assets/MachineBrigade/Resources/Audio/Music/MUSIC_CREDITS.md | M6: Assets/MachineBrigade/Resources/Audio/Music/defeat.ogg
A7: Music/menu | C7: Music | E7: Assets/MachineBrigade/Resources/Audio/Music/menu.ogg | F7: 108 | G7: 2 | H7: 44100 | I7: ogg | J7: Command Briefing | K7: Assets/MachineBrigade/Resources/Audio/Music/MUSIC_CREDITS.md | M7: Assets/MachineBrigade/Resources/Audio/Music/menu.ogg
A8: Music/siege | C8: Music | E8: Assets/MachineBrigade/Resources/Audio/Music/siege.ogg | F8: 115.556 | G8: 2 | H8: 44100 | I8: ogg | J8: Hold the Line | K8: Assets/MachineBrigade/Resources/Audio/Music/MUSIC_CREDITS.md | M8: Assets/MachineBrigade/Resources/Audio/Music/siege.ogg
A9: Music/victory | C9: Music | E9: Assets/MachineBrigade/Resources/Audio/Music/victory.ogg | F9: 8.621 | G9: 2 | H9: 44100 | I9: ogg | J9: Victory (stinger) | K9: Assets/MachineBrigade/Resources/Audio/Music/MUSIC_CREDITS.md | M9: Assets/MachineBrigade/Resources/Audio/Music/victory.ogg
A10: autocannon/autocannon_1 | B10: autocannon | C10: shot | E10: Assets/MachineBrigade/Resources/Audio/autocannon/autocannon_1.ogg | F10: 0.695 | G10: 1 | H10: 44100 | I10: ogg | J10: Fascinated Sound | K10: The Gun Locker SFX Pack: "Automatic Cannon - MK44 - 03 - Single Shot with Report 03.wav" | L10: Sonniss GDC licence (no attribution) | M10: Assets/MachineBrigade/Resources/Audio/autocannon/autocannon_1.ogg
A11: autocannon/autocannon_2 | B11: autocannon | C11: shot | E11: Assets/MachineBrigade/Resources/Audio/autocannon/autocannon_2.ogg | F11: 0.695 | G11: 1 | H11: 44100 | I11: ogg | J11: Fascinated Sound | K11: The Gun Locker SFX Pack: "Automatic Cannon - MK44 - 03 - Single Shot with Report 03.wav" | L11: Sonniss GDC licence (no attribution) | M11: Assets/MachineBrigade/Resources/Audio/autocannon/autocannon_2.ogg
A12: autocannon/autocannon_3 | B12: autocannon | C12: shot | E12: Assets/MachineBrigade/Resources/Audio/autocannon/autocannon_3.ogg | F12: 0.682 | G12: 1 | H12: 44100 | I12: ogg | J12: Fascinated Sound | K12: The Gun Locker SFX Pack: "Automatic Cannon - MK44 - 03 - Single Shot with Report 03.wav" | L12: Sonniss GDC licence (no attribution) | M12: Assets/MachineBrigade/Resources/Audio/autocannon/autocannon_3.ogg
A13: cannon/cannon_1 | B13: cannon | C13: shot | E13: Assets/MachineBrigade/Resources/Audio/cannon/cannon_1.ogg | F13: 1.5 | G13: 1 | H13: 44100 | I13: ogg | J13: Bluezone Corporation | K13: Tank - Explosion Sound Effects: "Bluezone_BC0271_tank_artillery_cannon_shot_012.wav" | L13: Sonniss GDC licence (no attribution) | M13: Assets/MachineBrigade/Resources/Audio/cannon/cannon_1.ogg
A14: cannon/cannon_2 | B14: cannon | C14: shot | E14: Assets/MachineBrigade/Resources/Audio/cannon/cannon_2.ogg | F14: 1.5 | G14: 1 | H14: 44100 | I14: ogg | J14: Pole Position Production | K14: The Warfare Library: "warfare_t1b_cannon_firing_forest_distant_MKH8060_2.wav" | L14: Sonniss GDC licence (no attribution) | M14: Assets/MachineBrigade/Resources/Audio/cannon/cannon_2.ogg
A15: cannon/cannon_3 | B15: cannon | C15: shot | E15: Assets/MachineBrigade/Resources/Audio/cannon/cannon_3.ogg | F15: 1.384 | G15: 1 | H15: 44100 | I15: ogg | J15: Pole Position Production | K15: The Warfare Library: "warfare_t1b_cannon_firing_forest_distant_MKH8060_2.wav" | L15: Sonniss GDC licence (no attribution) | M15: Assets/MachineBrigade/Resources/Audio/cannon/cannon_3.ogg
A16: click/click_1 | C16: click | E16: Assets/MachineBrigade/Resources/Audio/click/click_1.ogg | F16: 0.092 | G16: 1 | H16: 44100 | I16: ogg | J16: Kenney (www.kenney.nl) | K16: UI Audio pack ("click1.ogg") | L16: CC0 1.0 | M16: Assets/MachineBrigade/Resources/Audio/click/click_1.ogg
A17: click/click_2 | C17: click | E17: Assets/MachineBrigade/Resources/Audio/click/click_2.ogg | F17: 0.065 | G17: 1 | H17: 44100 | I17: ogg | J17: Kenney (www.kenney.nl) | K17: UI Audio pack ("click3.ogg") | L17: CC0 1.0 | M17: Assets/MachineBrigade/Resources/Audio/click/click_2.ogg
A18: collapse/collapse_1 | B18: collapse | C18: wreck | E18: Assets/MachineBrigade/Resources/Audio/collapse/collapse_1.ogg | F18: 3.697 | G18: 1 | H18: 44100 | I18: ogg | J18: Alexander Kopeikin | K18: Rocks: "rocks stream down heavy 02.wav" | L18: Sonniss GDC licence (no attribution) | M18: Assets/MachineBrigade/Resources/Audio/collapse/collapse_1.ogg
A19: collapse/collapse_2 | B19: collapse | C19: wreck | E19: Assets/MachineBrigade/Resources/Audio/collapse/collapse_2.ogg | F19: 3.853 | G19: 1 | H19: 44100 | I19: ogg | J19: Alexander Kopeikin | K19: Rocks: "rock tumble down debris long 06.wav" | L19: Sonniss GDC licence (no attribution) | M19: Assets/MachineBrigade/Resources/Audio/collapse/collapse_2.ogg
A20: debris/debris_1 | B20: debris | C20: wreck | E20: Assets/MachineBrigade/Resources/Audio/debris/debris_1.ogg | F20: 0.805 | G20: 1 | H20: 44100 | I20: ogg | J20: Mechanical Wave | K20: Undoing-Computer: "Drop Fall Metal Rattle Scrap Debris_UC 10.wav" | L20: Sonniss GDC licence (no attribution) | M20: Assets/MachineBrigade/Resources/Audio/debris/debris_1.ogg
A21: debris/debris_2 | B21: debris | C21: wreck | E21: Assets/MachineBrigade/Resources/Audio/debris/debris_2.ogg | F21: 0.853 | G21: 1 | H21: 44100 | I21: ogg | J21: Mechanical Wave | K21: Undoing-Computer: "Hit Impact Metal Scrap Debris_UC 06.wav" | L21: Sonniss GDC licence (no attribution) | M21: Assets/MachineBrigade/Resources/Audio/debris/debris_2.ogg
A22: debris/debris_3 | B22: debris | C22: wreck | E22: Assets/MachineBrigade/Resources/Audio/debris/debris_3.ogg | F22: 0.954 | G22: 1 | H22: 44100 | I22: ogg | J22: Mechanical Wave | K22: Rock Brick and Dirt: "Hit Rock Debris_RBD 02.wav" | L22: Sonniss GDC licence (no attribution) | M22: Assets/MachineBrigade/Resources/Audio/debris/debris_3.ogg
A23: drums_loop/drums_loop_1 | C23: drums_loop | E23: Assets/MachineBrigade/Resources/Audio/drums_loop/drums_loop_1.ogg | F23: 7.385 | G23: 1 | H23: 44100 | I23: ogg | J23: William Hector | K23: Horde War Drums loop (OpenGameArt) ("horde_war_drums_by_william_hector.wav") | L23: CC0 1.0 | M23: Assets/MachineBrigade/Resources/Audio/drums_loop/drums_loop_1.ogg
A24: explosion_huge/explosion_huge_1 | B24: explosion_huge | C24: blast | E24: Assets/MachineBrigade/Resources/Audio/explosion_huge/explosion_huge_1.ogg | F24: 5 | G24: 1 | H24: 44100 | I24: ogg | J24: Stefano Cremona | K24: Explosions: "BigExplosion02.wav" | L24: Sonniss GDC licence (no attribution) | M24: Assets/MachineBrigade/Resources/Audio/explosion_huge/explosion_huge_1.ogg
A25: explosion_huge/explosion_huge_2 | B25: explosion_huge | C25: blast | E25: Assets/MachineBrigade/Resources/Audio/explosion_huge/explosion_huge_2.ogg | F25: 4.975 | G25: 1 | H25: 44100 | I25: ogg | J25: David Dumais Audio | K25: Explosion SFX Pack: "EXPLDsgn_Nuclear Explosion 07_DDUMAIS_NONE.wav" | L25: Sonniss GDC licence (no attribution) | M25: Assets/MachineBrigade/Resources/Audio/explosion_huge/explosion_huge_2.ogg
A26: explosion_huge/explosion_huge_3 | B26: explosion_huge | C26: blast | E26: Assets/MachineBrigade/Resources/Audio/explosion_huge/explosion_huge_3.ogg | F26: 4.964 | G26: 1 | H26: 44100 | I26: ogg | J26: MatiasMacSD | K26: Eradication - Small Pack: "Planet_Explosion_High-12.wav" | L26: Sonniss GDC licence (no attribution) | M26: Assets/MachineBrigade/Resources/Audio/explosion_huge/explosion_huge_3.ogg
A27: explosion_large/explosion_large_1 | B27: explosion_large | C27: blast | E27: Assets/MachineBrigade/Resources/Audio/explosion_large/explosion_large_1.ogg | F27: 3 | G27: 1 | H27: 44100 | I27: ogg | J27: Bluezone Corporation | K27: Tank - Explosion Sound Effects: "Bluezone_BC0271_explosion_outdoors_large_005.wav" | L27: Sonniss GDC licence (no attribution) | M27: Assets/MachineBrigade/Resources/Audio/explosion_large/explosion_large_1.ogg
A28: explosion_large/explosion_large_2 | B28: explosion_large | C28: blast | E28: Assets/MachineBrigade/Resources/Audio/explosion_large/explosion_large_2.ogg | F28: 2.511 | G28: 1 | H28: 44100 | I28: ogg | J28: Gamemaster Audio | K28: Guns, Bullets and Explosions: "explosion_large_07.wav" | L28: Sonniss GDC licence (no attribution) | M28: Assets/MachineBrigade/Resources/Audio/explosion_large/explosion_large_2.ogg
A29: explosion_large/explosion_large_3 | B29: explosion_large | C29: blast | E29: Assets/MachineBrigade/Resources/Audio/explosion_large/explosion_large_3.ogg | F29: 3 | G29: 1 | H29: 44100 | I29: ogg | J29: Gamemaster Audio | K29: Explosion Sound Pack: "explosion_large_08.wav" | L29: Sonniss GDC licence (no attribution) | M29: Assets/MachineBrigade/Resources/Audio/explosion_large/explosion_large_3.ogg
A30: explosion_large/explosion_large_4 | B30: explosion_large | C30: blast | E30: Assets/MachineBrigade/Resources/Audio/explosion_large/explosion_large_4.ogg | F30: 2.688 | G30: 1 | H30: 44100 | I30: ogg | J30: Bluezone Corporation | K30: Combat Drone: "Bluezone_BC0288_combat_drone_weapon_explosion_004.wav" | L30: Sonniss GDC licence (no attribution) | M30: Assets/MachineBrigade/Resources/Audio/explosion_large/explosion_large_4.ogg
A31: explosion_medium/explosion_medium_1 | B31: explosion_medium | C31: blast | E31: Assets/MachineBrigade/Resources/Audio/explosion_medium/explosion_medium_1.ogg | F31: 2 | G31: 1 | H31: 44100 | I31: ogg | J31: Gamemaster Audio | K31: Explosion Sound Pack: "explosion_med_long_tail_01.wav" | L31: Sonniss GDC licence (no attribution) | M31: Assets/MachineBrigade/Resources/Audio/explosion_medium/explosion_medium_1.ogg
A32: explosion_medium/explosion_medium_2 | B32: explosion_medium | C32: blast | E32: Assets/MachineBrigade/Resources/Audio/explosion_medium/explosion_medium_2.ogg | F32: 1.989 | G32: 1 | H32: 44100 | I32: ogg | J32: David Dumais Audio | K32: Explosion SFX Pack: "EXPLReal_Medium Realistic Explosion 15_DDUMAIS_NONE.wav" | L32: Sonniss GDC licence (no attribution) | M32: Assets/MachineBrigade/Resources/Audio/explosion_medium/explosion_medium_2.ogg
A33: explosion_medium/explosion_medium_3 | B33: explosion_medium | C33: blast | E33: Assets/MachineBrigade/Resources/Audio/explosion_medium/explosion_medium_3.ogg | F33: 2 | G33: 1 | H33: 44100 | I33: ogg | J33: Bluezone Corporation | K33: Detonation - Explosion: "Bluezone_BC0277_explosion_urban_004_02.wav" | L33: Sonniss GDC licence (no attribution) | M33: Assets/MachineBrigade/Resources/Audio/explosion_medium/explosion_medium_3.ogg
A34: explosion_medium/explosion_medium_4 | B34: explosion_medium | C34: blast | E34: Assets/MachineBrigade/Resources/Audio/explosion_medium/explosion_medium_4.ogg | F34: 1.998 | G34: 1 | H34: 44100 | I34: ogg | J34: Stefano Cremona | K34: Explosions: "DeepExplosion02.wav" | L34: Sonniss GDC licence (no attribution) | M34: Assets/MachineBrigade/Resources/Audio/explosion_medium/explosion_medium_4.ogg
A35: explosion_small/explosion_small_1 | B35: explosion_small | C35: blast | E35: Assets/MachineBrigade/Resources/Audio/explosion_small/explosion_small_1.ogg | F35: 0.95 | G35: 1 | H35: 44100 | I35: ogg | J35: Bluezone Corporation | K35: Detonation - Explosion: "Bluezone_BC0277_explosion_mortar_002_01.wav" | L35: Sonniss GDC licence (no attribution) | M35: Assets/MachineBrigade/Resources/Audio/explosion_small/explosion_small_1.ogg
... A47: heavy_cannon/heavy_cannon_3 | B47: heavy_cannon | C47: shot | E47: Assets/MachineBrigade/Resources/Audio/heavy_cannon/heavy_cannon_3.ogg | F47: 1.981 | G47: 1 | H47: 44100 | I47: ogg | J47: Airborne Sound | K47: Battlefield Howitzers: "Howitzer,M101,C3,105 mm,Medium Distant,Right Side,Shot,Firm,Heavy,EQ Version,Soft Attack.wav" | L47: Sonniss GDC licence (no attribution) | M47: Assets/MachineBrigade/Resources/Audio/heavy_cannon/heavy_cannon_3.ogg
A48: impact_metal/impact_metal_1 | C48: impact_metal | E48: Assets/MachineBrigade/Resources/Audio/impact_metal/impact_metal_1.ogg | F48: 0.453 | G48: 1 | H48: 44100 | I48: ogg | J48: Mechanical Wave | K48: Undoing-Computer: "Hit Impact Hard Metal Scrap Debris_UC 01.wav" | L48: Sonniss GDC licence (no attribution) | M48: Assets/MachineBrigade/Resources/Audio/impact_metal/impact_metal_1.ogg
A49: impact_metal/impact_metal_2 | C49: impact_metal | E49: Assets/MachineBrigade/Resources/Audio/impact_metal/impact_metal_2.ogg | F49: 0.468 | G49: 1 | H49: 44100 | I49: ogg | J49: Mechanical Wave | K49: Undoing-Computer: "Hit Impact Hard Metal Scrap Debris_UC 01.wav" | L49: Sonniss GDC licence (no attribution) | M49: Assets/MachineBrigade/Resources/Audio/impact_metal/impact_metal_2.ogg
A50: impact_metal/impact_metal_3 | C50: impact_metal | E50: Assets/MachineBrigade/Resources/Audio/impact_metal/impact_metal_3.ogg | F50: 0.442 | G50: 1 | H50: 44100 | I50: ogg | J50: Gamemaster Audio | K50: Bullet Impact Sounds: "bullet_impact_metal_heavy_08.wav" | L50: Sonniss GDC licence (no attribution) | M50: Assets/MachineBrigade/Resources/Audio/impact_metal/impact_metal_3.ogg
A51: jet_loop/jet_loop_1 | B51: jet_loop | C51: aircraft | E51: Assets/MachineBrigade/Resources/Audio/jet_loop/jet_loop_1.ogg | F51: 5 | G51: 1 | H51: 44100 | I51: ogg | J51: Airborne Sound | K51: Attack Aircraft Maneuvers: "Jet,Fighter,FA-18C,Hornet,Medium Distant,Climb,Right to High,Crest and Hold,Kill Engine,191.wav" | L51: Sonniss GDC licence (no attribution) | M51: Assets/MachineBrigade/Resources/Audio/jet_loop/jet_loop_1.ogg
A52: jet_pass/jet_pass_1 | B52: jet_pass | C52: aircraft | E52: Assets/MachineBrigade/Resources/Audio/jet_pass/jet_pass_1.ogg | F52: 3.657 | G52: 1 | H52: 44100 | I52: ogg | J52: Bert Foley | K52: MiG-15 UTI: "MiG15UTI_Ext_Flyby_100m_XY.wav" | L52: Sonniss GDC licence (no attribution) | M52: Assets/MachineBrigade/Resources/Audio/jet_pass/jet_pass_1.ogg
A53: jet_pass/jet_pass_2 | B53: jet_pass | C53: aircraft | E53: Assets/MachineBrigade/Resources/Audio/jet_pass/jet_pass_2.ogg | F53: 3.762 | G53: 1 | H53: 44100 | I53: ogg | J53: Sound Ex Machina | K53: F16 Maneuvers: "F-16 Jet Fighter passing by overhead and vanishing into the horizon 03.wav" | L53: Sonniss GDC licence (no attribution) | M53: Assets/MachineBrigade/Resources/Audio/jet_pass/jet_pass_2.ogg
A54: jet_pass/jet_pass_3 | B54: jet_pass | C54: aircraft | E54: Assets/MachineBrigade/Resources/Audio/jet_pass/jet_pass_3.ogg | F54: 3.668 | G54: 1 | H54: 44100 | I54: ogg | J54: Airborne Sound | K54: Jet Fighter Maneuvers: "Jet,Fighter,F-16,Fighting Falcon,Medium Distant,By,Whip,Buffet.wav" | L54: Sonniss GDC licence (no attribution) | M54: Assets/MachineBrigade/Resources/Audio/jet_pass/jet_pass_3.ogg
A55: mg/mg_1 | B55: mg | C55: shot | E55: Assets/MachineBrigade/Resources/Audio/mg/mg_1.ogg | F55: 0.791 | G55: 1 | H55: 44100 | I55: ogg | J55: Super Thump | K55: Weapons of World War II - Designed: "STDSGN_WoWW2_Wep_MG_M1919_Machinegun_Auto-Burst_Shot_X6.wav" | L55: Sonniss GDC licence (no attribution) | M55: Assets/MachineBrigade/Resources/Audio/mg/mg_1.ogg
A56: mg/mg_2 | B56: mg | C56: shot | E56: Assets/MachineBrigade/Resources/Audio/mg/mg_2.ogg | F56: 0.752 | G56: 1 | H56: 44100 | I56: ogg | J56: Super Thump | K56: Weapons of World War II - Designed: "STDSGN_WoWW2_Wep_MG_M1919_Machinegun_Auto-Burst_Shot_X6.wav" | L56: Sonniss GDC licence (no attribution) | M56: Assets/MachineBrigade/Resources/Audio/mg/mg_2.ogg
A57: mg/mg_3 | B57: mg | C57: shot | E57: Assets/MachineBrigade/Resources/Audio/mg/mg_3.ogg | F57: 0.751 | G57: 1 | H57: 44100 | I57: ogg | J57: Super Thump | K57: Weapons of World War II - Designed: "STDSGN_WoWW2_Wep_MG_M1919_Machinegun_Auto-Burst_Shot_X6.wav" | L57: Sonniss GDC licence (no attribution) | M57: Assets/MachineBrigade/Resources/Audio/mg/mg_3.ogg
A58: missile_launch/missile_launch_1 | B58: missile_launch | C58: launch | E58: Assets/MachineBrigade/Resources/Audio/missile_launch/missile_launch_1.ogg | F58: 1.474 | G58: 1 | H58: 44100 | I58: ogg | J58: David Dumais Audio | K58: Sci-fi Flyby Sfx Pack: "Vehicle5_BlastOff1.wav" | L58: Sonniss GDC licence (no attribution) | M58: Assets/MachineBrigade/Resources/Audio/missile_launch/missile_launch_1.ogg
A59: missile_launch/missile_launch_2 | B59: missile_launch | C59: launch | E59: Assets/MachineBrigade/Resources/Audio/missile_launch/missile_launch_2.ogg | F59: 1.5 | G59: 1 | H59: 44100 | I59: ogg | J59: Bluezone Corporation | K59: Combat Drone: "Bluezone_BC0288_combat_drone_jet_texture_sonic_boom_002.wav" | L59: Sonniss GDC licence (no attribution) | M59: Assets/MachineBrigade/Resources/Audio/missile_launch/missile_launch_2.ogg
A60: rain_loop/rain_loop_1 | B60: rain_loop | C60: ambience | E60: Assets/MachineBrigade/Resources/Audio/rain_loop/rain_loop_1.ogg | F60: 8 | G60: 1 | H60: 44100 | I60: ogg | J60: Double Trouble Audio | K60: Rain and Thunder: "RATH - Rain Hard Loop 08.wav" | L60: Sonniss GDC licence (no attribution) | M60: Assets/MachineBrigade/Resources/Audio/rain_loop/rain_loop_1.ogg
A61: rocket_launch/rocket_launch_1 | B61: rocket_launch | C61: launch | E61: Assets/MachineBrigade/Resources/Audio/rocket_launch/rocket_launch_1.ogg | F61: 1.139 | G61: 1 | H61: 44100 | I61: ogg | J61: Pole Position Production | K61: The Warfare 2 Library: "RPG - FIRING AND IMPACT - Through Car Roof Hit Metal - XY - MKH8040.wav" | L61: Sonniss GDC licence (no attribution) | M61: Assets/MachineBrigade/Resources/Audio/rocket_launch/rocket_launch_1.ogg
A62: rocket_launch/rocket_launch_2 | B62: rocket_launch | C62: launch | E62: Assets/MachineBrigade/Resources/Audio/rocket_launch/rocket_launch_2.ogg | F62: 1.15 | G62: 1 | H62: 44100 | I62: ogg | J62: Bluezone Corporation | K62: Detonation - Explosion: "Bluezone_BC0277_weapon_smoke_grenade_launcher_003.wav" | L62: Sonniss GDC licence (no attribution) | M62: Assets/MachineBrigade/Resources/Audio/rocket_launch/rocket_launch_2.ogg
... A65: rotor_loop/rotor_loop_1 | B65: rotor_loop | C65: helicopter | E65: Assets/MachineBrigade/Resources/Audio/rotor_loop/rotor_loop_1.ogg | F65: 2.464 | G65: 1 | H65: 44100 | I65: ogg | J65: InspectorJ | K65: 96 General Library: "AEROHeli_InsJ_Helicopter_Flyby_Close_03_Chinook.wav" | L65: Sonniss GDC licence (no attribution) | M65: Assets/MachineBrigade/Resources/Audio/rotor_loop/rotor_loop_1.ogg
A66: sfx/blast_air_s1/blast_air_s1_1 | B66: blast_air_s1 | C66: blast_air | D66: s1 | E66: Assets/MachineBrigade/Resources/Audio/sfx/blast_air_s1/blast_air_s1_1.ogg | F66: 1.18 | G66: 1 | H66: 44100 | I66: ogg | K66: tổng hợp / trộn bởi Tools/sfx/build_sfx.py (Audio/CREDITS.md) | L66: của dự án; lớp ghi âm theo Sonniss GDC (Audio/CREDITS.md) | M66: Assets/MachineBrigade/Resources/Audio/sfx/blast_air_s1/blast_air_s1_1.ogg
A67: sfx/blast_air_s1/blast_air_s1_2 | B67: blast_air_s1 | C67: blast_air | D67: s1 | E67: Assets/MachineBrigade/Resources/Audio/sfx/blast_air_s1/blast_air_s1_2.ogg | F67: 1.25 | G67: 1 | H67: 44100 | I67: ogg | K67: tổng hợp / trộn bởi Tools/sfx/build_sfx.py (Audio/CREDITS.md) | L67: của dự án; lớp ghi âm theo Sonniss GDC (Audio/CREDITS.md) | M67: Assets/MachineBrigade/Resources/Audio/sfx/blast_air_s1/blast_air_s1_2.ogg
A68: sfx/blast_air_s2/blast_air_s2_1 | B68: blast_air_s2 | C68: blast_air | D68: s2 | E68: Assets/MachineBrigade/Resources/Audio/sfx/blast_air_s2/blast_air_s2_1.ogg | F68: 1.78 | G68: 1 | H68: 44100 | I68: ogg | K68: tổng hợp / trộn bởi Tools/sfx/build_sfx.py (Audio/CREDITS.md) | L68: của dự án; lớp ghi âm theo Sonniss GDC (Audio/CREDITS.md) | M68: Assets/MachineBrigade/Resources/Audio/sfx/blast_air_s2/blast_air_s2_1.ogg
A69: sfx/blast_air_s2/blast_air_s2_2 | B69: blast_air_s2 | C69: blast_air | D69: s2 | E69: Assets/MachineBrigade/Resources/Audio/sfx/blast_air_s2/blast_air_s2_2.ogg | F69: 1.88 | G69: 1 | H69: 44100 | I69: ogg | K69: tổng hợp / trộn bởi Tools/sfx/build_sfx.py (Audio/CREDITS.md) | L69: của dự án; lớp ghi âm theo Sonniss GDC (Audio/CREDITS.md) | M69: Assets/MachineBrigade/Resources/Audio/sfx/blast_air_s2/blast_air_s2_2.ogg
A70: sfx/blast_air_s3/blast_air_s3_1 | B70: blast_air_s3 | C70: blast_air | D70: s3 | E70: Assets/MachineBrigade/Resources/Audio/sfx/blast_air_s3/blast_air_s3_1.ogg | F70: 2.61 | G70: 1 | H70: 44100 | I70: ogg | K70: tổng hợp / trộn bởi Tools/sfx/build_sfx.py (Audio/CREDITS.md) | L70: của dự án; lớp ghi âm theo Sonniss GDC (Audio/CREDITS.md) | M70: Assets/MachineBrigade/Resources/Audio/sfx/blast_air_s3/blast_air_s3_1.ogg
A71: sfx/blast_air_s3/blast_air_s3_2 | B71: blast_air_s3 | C71: blast_air | D71: s3 | E71: Assets/MachineBrigade/Resources/Audio/sfx/blast_air_s3/blast_air_s3_2.ogg | F71: 2.66 | G71: 1 | H71: 44100 | I71: ogg | K71: tổng hợp / trộn bởi Tools/sfx/build_sfx.py (Audio/CREDITS.md) | L71: của dự án; lớp ghi âm theo Sonniss GDC (Audio/CREDITS.md) | M71: Assets/MachineBrigade/Resources/Audio/sfx/blast_air_s3/blast_air_s3_2.ogg
A72: sfx/blast_bomb/blast_bomb_1 | B72: blast_bomb | C72: blast | D72: bomb | E72: Assets/MachineBrigade/Resources/Audio/sfx/blast_bomb/blast_bomb_1.ogg | F72: 5.925 | G72: 1 | H72: 44100 | I72: ogg | K72: tổng hợp / trộn bởi Tools/sfx/build_sfx.py (Audio/CREDITS.md) | L72: của dự án; lớp ghi âm theo Sonniss GDC (Audio/CREDITS.md) | M72: Assets/MachineBrigade/Resources/Audio/sfx/blast_bomb/blast_bomb_1.ogg
A73: sfx/blast_bomb/blast_bomb_2 | B73: blast_bomb | C73: blast | D73: bomb | E73: Assets/MachineBrigade/Resources/Audio/sfx/blast_bomb/blast_bomb_2.ogg | F73: 5.925 | G73: 1 | H73: 44100 | I73: ogg | K73: tổng hợp / trộn bởi Tools/sfx/build_sfx.py (Audio/CREDITS.md) | L73: của dự án; lớp ghi âm theo Sonniss GDC (Audio/CREDITS.md) | M73: Assets/MachineBrigade/Resources/Audio/sfx/blast_bomb/blast_bomb_2.ogg
A74: sfx/blast_bomb/blast_bomb_3 | B74: blast_bomb | C74: blast | D74: bomb | E74: Assets/MachineBrigade/Resources/Audio/sfx/blast_bomb/blast_bomb_3.ogg | F74: 5.88 | G74: 1 | H74: 44100 | I74: ogg | K74: tổng hợp / trộn bởi Tools/sfx/build_sfx.py (Audio/CREDITS.md) | L74: của dự án; lớp ghi âm theo Sonniss GDC (Audio/CREDITS.md) | M74: Assets/MachineBrigade/Resources/Audio/sfx/blast_bomb/blast_bomb_3.ogg
A75: sfx/blast_he_s1/blast_he_s1_1 | B75: blast_he_s1 | C75: blast | D75: s1 | E75: Assets/MachineBrigade/Resources/Audio/sfx/blast_he_s1/blast_he_s1_1.ogg | F75: 1.17 | G75: 1 | H75: 44100 | I75: ogg | K75: tổng hợp / trộn bởi Tools/sfx/build_sfx.py (Audio/CREDITS.md) | L75: của dự án; lớp ghi âm theo Sonniss GDC (Audio/CREDITS.md) | M75: Assets/MachineBrigade/Resources/Audio/sfx/blast_he_s1/blast_he_s1_1.ogg
A76: sfx/blast_he_s1/blast_he_s1_2 | B76: blast_he_s1 | C76: blast | D76: s1 | E76: Assets/MachineBrigade/Resources/Audio/sfx/blast_he_s1/blast_he_s1_2.ogg | F76: 1.19 | G76: 1 | H76: 44100 | I76: ogg | K76: tổng hợp / trộn bởi Tools/sfx/build_sfx.py (Audio/CREDITS.md) | L76: của dự án; lớp ghi âm theo Sonniss GDC (Audio/CREDITS.md) | M76: Assets/MachineBrigade/Resources/Audio/sfx/blast_he_s1/blast_he_s1_2.ogg
A77: sfx/blast_he_s1/blast_he_s1_3 | B77: blast_he_s1 | C77: blast | D77: s1 | E77: Assets/MachineBrigade/Resources/Audio/sfx/blast_he_s1/blast_he_s1_3.ogg | F77: 1.1 | G77: 1 | H77: 44100 | I77: ogg | K77: tổng hợp / trộn bởi Tools/sfx/build_sfx.py (Audio/CREDITS.md) | L77: của dự án; lớp ghi âm theo Sonniss GDC (Audio/CREDITS.md) | M77: Assets/MachineBrigade/Resources/Audio/sfx/blast_he_s1/blast_he_s1_3.ogg
... A119: sfx/burst_s1_55/burst_s1_55_3 | B119: burst_s1_55 | C119: shot | D119: s1 | E119: Assets/MachineBrigade/Resources/Audio/sfx/burst_s1_55/burst_s1_55_3.ogg | F119: 0.92 | G119: 1 | H119: 44100 | I119: ogg | K119: tổng hợp / trộn bởi Tools/sfx/build_sfx.py (Audio/CREDITS.md) | L119: của dự án; lớp ghi âm theo Sonniss GDC (Audio/CREDITS.md) | M119: Assets/MachineBrigade/Resources/Audio/sfx/burst_s1_55/burst_s1_55_3.ogg
A120: sfx/crash_fall/crash_fall_1 | B120: crash_fall | C120: aircraft | E120: Assets/MachineBrigade/Resources/Audio/sfx/crash_fall/crash_fall_1.ogg | F120: 2.8 | G120: 1 | H120: 44100 | I120: ogg | K120: tổng hợp / trộn bởi Tools/sfx/build_sfx.py (Audio/CREDITS.md) | L120: của dự án; lớp ghi âm theo Sonniss GDC (Audio/CREDITS.md) | M120: Assets/MachineBrigade/Resources/Audio/sfx/crash_fall/crash_fall_1.ogg
A121: sfx/crash_fall/crash_fall_2 | B121: crash_fall | C121: aircraft | E121: Assets/MachineBrigade/Resources/Audio/sfx/crash_fall/crash_fall_2.ogg | F121: 2.8 | G121: 1 | H121: 44100 | I121: ogg | K121: tổng hợp / trộn bởi Tools/sfx/build_sfx.py (Audio/CREDITS.md) | L121: của dự án; lớp ghi âm theo Sonniss GDC (Audio/CREDITS.md) | M121: Assets/MachineBrigade/Resources/Audio/sfx/crash_fall/crash_fall_2.ogg
A122: sfx/crash_impact/crash_impact_1 | B122: crash_impact | C122: aircraft | E122: Assets/MachineBrigade/Resources/Audio/sfx/crash_impact/crash_impact_1.ogg | F122: 4 | G122: 1 | H122: 44100 | I122: ogg | K122: tổng hợp / trộn bởi Tools/sfx/build_sfx.py (Audio/CREDITS.md) | L122: của dự án; lớp ghi âm theo Sonniss GDC (Audio/CREDITS.md) | M122: Assets/MachineBrigade/Resources/Audio/sfx/crash_impact/crash_impact_1.ogg
A123: sfx/crash_impact/crash_impact_2 | B123: crash_impact | C123: aircraft | E123: Assets/MachineBrigade/Resources/Audio/sfx/crash_impact/crash_impact_2.ogg | F123: 4 | G123: 1 | H123: 44100 | I123: ogg | K123: tổng hợp / trộn bởi Tools/sfx/build_sfx.py (Audio/CREDITS.md) | L123: của dự án; lớp ghi âm theo Sonniss GDC (Audio/CREDITS.md) | M123: Assets/MachineBrigade/Resources/Audio/sfx/crash_impact/crash_impact_2.ogg
A124: sfx/engine_heavy/engine_heavy_1 | B124: engine_heavy | C124: engine | E124: Assets/MachineBrigade/Resources/Audio/sfx/engine_heavy/engine_heavy_1.ogg | F124: 4 | G124: 1 | H124: 44100 | I124: ogg | K124: tổng hợp / trộn bởi Tools/sfx/build_sfx.py (Audio/CREDITS.md) | L124: của dự án; lớp ghi âm theo Sonniss GDC (Audio/CREDITS.md) | M124: Assets/MachineBrigade/Resources/Audio/sfx/engine_heavy/engine_heavy_1.ogg
A125: sfx/engine_tracked/engine_tracked_1 | B125: engine_tracked | C125: engine | E125: Assets/MachineBrigade/Resources/Audio/sfx/engine_tracked/engine_tracked_1.ogg | F125: 4 | G125: 1 | H125: 44100 | I125: ogg | K125: tổng hợp / trộn bởi Tools/sfx/build_sfx.py (Audio/CREDITS.md) | L125: của dự án; lớp ghi âm theo Sonniss GDC (Audio/CREDITS.md) | M125: Assets/MachineBrigade/Resources/Audio/sfx/engine_tracked/engine_tracked_1.ogg
A126: sfx/engine_wheeled/engine_wheeled_1 | B126: engine_wheeled | C126: engine | E126: Assets/MachineBrigade/Resources/Audio/sfx/engine_wheeled/engine_wheeled_1.ogg | F126: 4 | G126: 1 | H126: 44100 | I126: ogg | K126: tổng hợp / trộn bởi Tools/sfx/build_sfx.py (Audio/CREDITS.md) | L126: của dự án; lớp ghi âm theo Sonniss GDC (Audio/CREDITS.md) | M126: Assets/MachineBrigade/Resources/Audio/sfx/engine_wheeled/engine_wheeled_1.ogg
A127: sfx/flare_pop/flare_pop_1 | B127: flare_pop | C127: flare | E127: Assets/MachineBrigade/Resources/Audio/sfx/flare_pop/flare_pop_1.ogg | F127: 1.41 | G127: 1 | H127: 44100 | I127: ogg | K127: tổng hợp / trộn bởi Tools/sfx/build_sfx.py (Audio/CREDITS.md) | L127: của dự án; lớp ghi âm theo Sonniss GDC (Audio/CREDITS.md) | M127: Assets/MachineBrigade/Resources/Audio/sfx/flare_pop/flare_pop_1.ogg
A128: sfx/flare_pop/flare_pop_2 | B128: flare_pop | C128: flare | E128: Assets/MachineBrigade/Resources/Audio/sfx/flare_pop/flare_pop_2.ogg | F128: 1.43 | G128: 1 | H128: 44100 | I128: ogg | K128: tổng hợp / trộn bởi Tools/sfx/build_sfx.py (Audio/CREDITS.md) | L128: của dự án; lớp ghi âm theo Sonniss GDC (Audio/CREDITS.md) | M128: Assets/MachineBrigade/Resources/Audio/sfx/flare_pop/flare_pop_2.ogg
A129: sfx/hit_armour_glance/hit_armour_glance_1 | B129: hit_armour_glance | C129: hit_armour | D129: s2 | E129: Assets/MachineBrigade/Resources/Audio/sfx/hit_armour_glance/hit_armour_glance_1.ogg | F129: 0.41 | G129: 1 | H129: 44100 | I129: ogg | K129: tổng hợp / trộn bởi Tools/sfx/build_sfx.py (Audio/CREDITS.md) | L129: của dự án; lớp ghi âm theo Sonniss GDC (Audio/CREDITS.md) | M129: Assets/MachineBrigade/Resources/Audio/sfx/hit_armour_glance/hit_armour_glance_1.ogg
A130: sfx/hit_armour_glance/hit_armour_glance_2 | B130: hit_armour_glance | C130: hit_armour | D130: s2 | E130: Assets/MachineBrigade/Resources/Audio/sfx/hit_armour_glance/hit_armour_glance_2.ogg | F130: 0.41 | G130: 1 | H130: 44100 | I130: ogg | K130: tổng hợp / trộn bởi Tools/sfx/build_sfx.py (Audio/CREDITS.md) | L130: của dự án; lớp ghi âm theo Sonniss GDC (Audio/CREDITS.md) | M130: Assets/MachineBrigade/Resources/Audio/sfx/hit_armour_glance/hit_armour_glance_2.ogg
A131: sfx/hit_armour_glance/hit_armour_glance_3 | B131: hit_armour_glance | C131: hit_armour | D131: s2 | E131: Assets/MachineBrigade/Resources/Audio/sfx/hit_armour_glance/hit_armour_glance_3.ogg | F131: 0.41 | G131: 1 | H131: 44100 | I131: ogg | K131: tổng hợp / trộn bởi Tools/sfx/build_sfx.py (Audio/CREDITS.md) | L131: của dự án; lớp ghi âm theo Sonniss GDC (Audio/CREDITS.md) | M131: Assets/MachineBrigade/Resources/Audio/sfx/hit_armour_glance/hit_armour_glance_3.ogg
A132: sfx/hit_armour_heavy/hit_armour_heavy_1 | B132: hit_armour_heavy | C132: hit_armour | D132: s3 | E132: Assets/MachineBrigade/Resources/Audio/sfx/hit_armour_heavy/hit_armour_heavy_1.ogg | F132: 0.56 | G132: 1 | H132: 44100 | I132: ogg | K132: tổng hợp / trộn bởi Tools/sfx/build_sfx.py (Audio/CREDITS.md) | L132: của dự án; lớp ghi âm theo Sonniss GDC (Audio/CREDITS.md) | M132: Assets/MachineBrigade/Resources/Audio/sfx/hit_armour_heavy/hit_armour_heavy_1.ogg
A133: sfx/hit_armour_heavy/hit_armour_heavy_2 | B133: hit_armour_heavy | C133: hit_armour | D133: s3 | E133: Assets/MachineBrigade/Resources/Audio/sfx/hit_armour_heavy/hit_armour_heavy_2.ogg | F133: 0.56 | G133: 1 | H133: 44100 | I133: ogg | K133: tổng hợp / trộn bởi Tools/sfx/build_sfx.py (Audio/CREDITS.md) | L133: của dự án; lớp ghi âm theo Sonniss GDC (Audio/CREDITS.md) | M133: Assets/MachineBrigade/Resources/Audio/sfx/hit_armour_heavy/hit_armour_heavy_2.ogg
A134: sfx/hit_armour_heavy/hit_armour_heavy_3 | B134: hit_armour_heavy | C134: hit_armour | D134: s3 | E134: Assets/MachineBrigade/Resources/Audio/sfx/hit_armour_heavy/hit_armour_heavy_3.ogg | F134: 0.56 | G134: 1 | H134: 44100 | I134: ogg | K134: tổng hợp / trộn bởi Tools/sfx/build_sfx.py (Audio/CREDITS.md) | L134: của dự án; lớp ghi âm theo Sonniss GDC (Audio/CREDITS.md) | M134: Assets/MachineBrigade/Resources/Audio/sfx/hit_armour_heavy/hit_armour_heavy_3.ogg
A135: sfx/hit_armour_light/hit_armour_light_1 | B135: hit_armour_light | C135: hit_armour | D135: s1 | E135: Assets/MachineBrigade/Resources/Audio/sfx/hit_armour_light/hit_armour_light_1.ogg | F135: 0.26 | G135: 1 | H135: 44100 | I135: ogg | K135: tổng hợp / trộn bởi Tools/sfx/build_sfx.py (Audio/CREDITS.md) | L135: của dự án; lớp ghi âm theo Sonniss GDC (Audio/CREDITS.md) | M135: Assets/MachineBrigade/Resources/Audio/sfx/hit_armour_light/hit_armour_light_1.ogg
A136: sfx/hit_armour_light/hit_armour_light_2 | B136: hit_armour_light | C136: hit_armour | D136: s1 | E136: Assets/MachineBrigade/Resources/Audio/sfx/hit_armour_light/hit_armour_light_2.ogg | F136: 0.26 | G136: 1 | H136: 44100 | I136: ogg | K136: tổng hợp / trộn bởi Tools/sfx/build_sfx.py (Audio/CREDITS.md) | L136: của dự án; lớp ghi âm theo Sonniss GDC (Audio/CREDITS.md) | M136: Assets/MachineBrigade/Resources/Audio/sfx/hit_armour_light/hit_armour_light_2.ogg
A137: sfx/hit_armour_light/hit_armour_light_3 | B137: hit_armour_light | C137: hit_armour | D137: s1 | E137: Assets/MachineBrigade/Resources/Audio/sfx/hit_armour_light/hit_armour_light_3.ogg | F137: 0.26 | G137: 1 | H137: 44100 | I137: ogg | K137: tổng hợp / trộn bởi Tools/sfx/build_sfx.py (Audio/CREDITS.md) | L137: của dự án; lớp ghi âm theo Sonniss GDC (Audio/CREDITS.md) | M137: Assets/MachineBrigade/Resources/Audio/sfx/hit_armour_light/hit_armour_light_3.ogg
A138: sfx/hit_armour_light/hit_armour_light_4 | B138: hit_armour_light | C138: hit_armour | D138: s1 | E138: Assets/MachineBrigade/Resources/Audio/sfx/hit_armour_light/hit_armour_light_4.ogg | F138: 0.26 | G138: 1 | H138: 44100 | I138: ogg | K138: tổng hợp / trộn bởi Tools/sfx/build_sfx.py (Audio/CREDITS.md) | L138: của dự án; lớp ghi âm theo Sonniss GDC (Audio/CREDITS.md) | M138: Assets/MachineBrigade/Resources/Audio/sfx/hit_armour_light/hit_armour_light_4.ogg
A139: sfx/hit_concrete_heavy/hit_concrete_heavy_1 | B139: hit_concrete_heavy | C139: hit_concrete | D139: s2 | E139: Assets/MachineBrigade/Resources/Audio/sfx/hit_concrete_heavy/hit_concrete_heavy_1.ogg | F139: 0.85 | G139: 1 | H139: 44100 | I139: ogg | K139: tổng hợp / trộn bởi Tools/sfx/build_sfx.py (Audio/CREDITS.md) | L139: của dự án; lớp ghi âm theo Sonniss GDC (Audio/CREDITS.md) | M139: Assets/MachineBrigade/Resources/Audio/sfx/hit_concrete_heavy/hit_concrete_heavy_1.ogg
A140: sfx/hit_concrete_heavy/hit_concrete_heavy_2 | B140: hit_concrete_heavy | C140: hit_concrete | D140: s2 | E140: Assets/MachineBrigade/Resources/Audio/sfx/hit_concrete_heavy/hit_concrete_heavy_2.ogg | F140: 0.86 | G140: 1 | H140: 44100 | I140: ogg | K140: tổng hợp / trộn bởi Tools/sfx/build_sfx.py (Audio/CREDITS.md) | L140: của dự án; lớp ghi âm theo Sonniss GDC (Audio/CREDITS.md) | M140: Assets/MachineBrigade/Resources/Audio/sfx/hit_concrete_heavy/hit_concrete_heavy_2.ogg
... A180: sfx/launch_sam/launch_sam_3 | B180: launch_sam | C180: launch | D180: s2 | E180: Assets/MachineBrigade/Resources/Audio/sfx/launch_sam/launch_sam_3.ogg | F180: 2.02 | G180: 1 | H180: 44100 | I180: ogg | K180: tổng hợp / trộn bởi Tools/sfx/build_sfx.py (Audio/CREDITS.md) | L180: của dự án; lớp ghi âm theo Sonniss GDC (Audio/CREDITS.md) | M180: Assets/MachineBrigade/Resources/Audio/sfx/launch_sam/launch_sam_3.ogg
A181: sfx/missile_hiss/missile_hiss_1 | B181: missile_hiss | C181: launch | E181: Assets/MachineBrigade/Resources/Audio/sfx/missile_hiss/missile_hiss_1.ogg | F181: 0.5 | G181: 1 | H181: 44100 | I181: ogg | K181: tổng hợp / trộn bởi Tools/sfx/build_sfx.py (Audio/CREDITS.md) | L181: của dự án; lớp ghi âm theo Sonniss GDC (Audio/CREDITS.md) | M181: Assets/MachineBrigade/Resources/Audio/sfx/missile_hiss/missile_hiss_1.ogg
A182: sfx/missile_hiss/missile_hiss_2 | B182: missile_hiss | C182: launch | E182: Assets/MachineBrigade/Resources/Audio/sfx/missile_hiss/missile_hiss_2.ogg | F182: 0.55 | G182: 1 | H182: 44100 | I182: ogg | K182: tổng hợp / trộn bởi Tools/sfx/build_sfx.py (Audio/CREDITS.md) | L182: của dự án; lớp ghi âm theo Sonniss GDC (Audio/CREDITS.md) | M182: Assets/MachineBrigade/Resources/Audio/sfx/missile_hiss/missile_hiss_2.ogg
A183: sfx/ship_engine/ship_engine_1 | B183: ship_engine | C183: ship | E183: Assets/MachineBrigade/Resources/Audio/sfx/ship_engine/ship_engine_1.ogg | F183: 4 | G183: 1 | H183: 44100 | I183: ogg | K183: tổng hợp / trộn bởi Tools/sfx/build_sfx.py (Audio/CREDITS.md) | L183: của dự án; lớp ghi âm theo Sonniss GDC (Audio/CREDITS.md) | M183: Assets/MachineBrigade/Resources/Audio/sfx/ship_engine/ship_engine_1.ogg
A184: sfx/ship_horn/ship_horn_1 | B184: ship_horn | C184: ship | E184: Assets/MachineBrigade/Resources/Audio/sfx/ship_horn/ship_horn_1.ogg | F184: 3.8 | G184: 1 | H184: 44100 | I184: ogg | K184: tổng hợp / trộn bởi Tools/sfx/build_sfx.py (Audio/CREDITS.md) | L184: của dự án; lớp ghi âm theo Sonniss GDC (Audio/CREDITS.md) | M184: Assets/MachineBrigade/Resources/Audio/sfx/ship_horn/ship_horn_1.ogg
A185: sfx/shot_ac57/shot_ac57_1 | B185: shot_ac57 | C185: shot | D185: s2 | E185: Assets/MachineBrigade/Resources/Audio/sfx/shot_ac57/shot_ac57_1.ogg | F185: 0.714 | G185: 1 | H185: 44100 | I185: ogg | K185: tổng hợp / trộn bởi Tools/sfx/build_sfx.py (Audio/CREDITS.md) | L185: của dự án; lớp ghi âm theo Sonniss GDC (Audio/CREDITS.md) | M185: Assets/MachineBrigade/Resources/Audio/sfx/shot_ac57/shot_ac57_1.ogg
A186: sfx/shot_ac57/shot_ac57_2 | B186: shot_ac57 | C186: shot | D186: s2 | E186: Assets/MachineBrigade/Resources/Audio/sfx/shot_ac57/shot_ac57_2.ogg | F186: 0.714 | G186: 1 | H186: 44100 | I186: ogg | K186: tổng hợp / trộn bởi Tools/sfx/build_sfx.py (Audio/CREDITS.md) | L186: của dự án; lớp ghi âm theo Sonniss GDC (Audio/CREDITS.md) | M186: Assets/MachineBrigade/Resources/Audio/sfx/shot_ac57/shot_ac57_2.ogg
A187: sfx/shot_ac57/shot_ac57_3 | B187: shot_ac57 | C187: shot | D187: s2 | E187: Assets/MachineBrigade/Resources/Audio/sfx/shot_ac57/shot_ac57_3.ogg | F187: 0.714 | G187: 1 | H187: 44100 | I187: ogg | K187: tổng hợp / trộn bởi Tools/sfx/build_sfx.py (Audio/CREDITS.md) | L187: của dự án; lớp ghi âm theo Sonniss GDC (Audio/CREDITS.md) | M187: Assets/MachineBrigade/Resources/Audio/sfx/shot_ac57/shot_ac57_3.ogg
A188: sfx/shot_s0/shot_s0_1 | B188: shot_s0 | C188: shot | D188: s0 | E188: Assets/MachineBrigade/Resources/Audio/sfx/shot_s0/shot_s0_1.ogg | F188: 0.35 | G188: 1 | H188: 44100 | I188: ogg | K188: tổng hợp / trộn bởi Tools/sfx/build_sfx.py (Audio/CREDITS.md) | L188: của dự án; lớp ghi âm theo Sonniss GDC (Audio/CREDITS.md) | M188: Assets/MachineBrigade/Resources/Audio/sfx/shot_s0/shot_s0_1.ogg
A189: sfx/shot_s0/shot_s0_2 | B189: shot_s0 | C189: shot | D189: s0 | E189: Assets/MachineBrigade/Resources/Audio/sfx/shot_s0/shot_s0_2.ogg | F189: 0.35 | G189: 1 | H189: 44100 | I189: ogg | K189: tổng hợp / trộn bởi Tools/sfx/build_sfx.py (Audio/CREDITS.md) | L189: của dự án; lớp ghi âm theo Sonniss GDC (Audio/CREDITS.md) | M189: Assets/MachineBrigade/Resources/Audio/sfx/shot_s0/shot_s0_2.ogg
A190: sfx/shot_s0/shot_s0_3 | B190: shot_s0 | C190: shot | D190: s0 | E190: Assets/MachineBrigade/Resources/Audio/sfx/shot_s0/shot_s0_3.ogg | F190: 0.35 | G190: 1 | H190: 44100 | I190: ogg | K190: tổng hợp / trộn bởi Tools/sfx/build_sfx.py (Audio/CREDITS.md) | L190: của dự án; lớp ghi âm theo Sonniss GDC (Audio/CREDITS.md) | M190: Assets/MachineBrigade/Resources/Audio/sfx/shot_s0/shot_s0_3.ogg
A191: sfx/shot_s0/shot_s0_4 | B191: shot_s0 | C191: shot | D191: s0 | E191: Assets/MachineBrigade/Resources/Audio/sfx/shot_s0/shot_s0_4.ogg | F191: 0.35 | G191: 1 | H191: 44100 | I191: ogg | K191: tổng hợp / trộn bởi Tools/sfx/build_sfx.py (Audio/CREDITS.md) | L191: của dự án; lớp ghi âm theo Sonniss GDC (Audio/CREDITS.md) | M191: Assets/MachineBrigade/Resources/Audio/sfx/shot_s0/shot_s0_4.ogg
A192: sfx/shot_s1/shot_s1_1 | B192: shot_s1 | C192: shot | D192: s1 | E192: Assets/MachineBrigade/Resources/Audio/sfx/shot_s1/shot_s1_1.ogg | F192: 0.6 | G192: 1 | H192: 44100 | I192: ogg | K192: tổng hợp / trộn bởi Tools/sfx/build_sfx.py (Audio/CREDITS.md) | L192: của dự án; lớp ghi âm theo Sonniss GDC (Audio/CREDITS.md) | M192: Assets/MachineBrigade/Resources/Audio/sfx/shot_s1/shot_s1_1.ogg
A193: sfx/shot_s1/shot_s1_2 | B193: shot_s1 | C193: shot | D193: s1 | E193: Assets/MachineBrigade/Resources/Audio/sfx/shot_s1/shot_s1_2.ogg | F193: 0.6 | G193: 1 | H193: 44100 | I193: ogg | K193: tổng hợp / trộn bởi Tools/sfx/build_sfx.py (Audio/CREDITS.md) | L193: của dự án; lớp ghi âm theo Sonniss GDC (Audio/CREDITS.md) | M193: Assets/MachineBrigade/Resources/Audio/sfx/shot_s1/shot_s1_2.ogg
...

Sheet Am_thanh_bank
A1: id | B1: so_clip | C1: group | D1: kept | E1: row | F1: size | G1: variants | H1: nguon | I1: raw_json
A2: autocannon | B2: 3 | C2: shot | D2: TRUE | H2: Tools/sfx/library.json: banks.autocannon | I2: {"group":"shot","size":null,"row":null,"kept":true}
A3: blast_air_s1 | B3: 2 | C3: blast_air | F3: s1 | G3: 2 | H3: Tools/sfx/library.json: banks.blast_air_s1 | I3: {"group":"blast_air","size":"s1","row":null,"variants":2}
A4: blast_air_s2 | B4: 2 | C4: blast_air | F4: s2 | G4: 2 | H4: Tools/sfx/library.json: banks.blast_air_s2 | I4: {"group":"blast_air","size":"s2","row":null,"variants":2}
A5: blast_air_s3 | B5: 2 | C5: blast_air | F5: s3 | G5: 2 | H5: Tools/sfx/library.json: banks.blast_air_s3 | I5: {"group":"blast_air","size":"s3","row":null,"variants":2}
A6: blast_bomb | B6: 3 | C6: blast | E6: blast | F6: bomb | G6: 3 | H6: Tools/sfx/library.json: banks.blast_bomb | I6: {"group":"blast","size":"bomb","row":"blast","variants":3}
A7: blast_he_s1 | B7: 3 | C7: blast | E7: blast | F7: s1 | G7: 3 | H7: Tools/sfx/library.json: banks.blast_he_s1 | I7: {"group":"blast","size":"s1","row":"blast","variants":3}
A8: blast_he_s2 | B8: 3 | C8: blast | E8: blast | F8: s2 | G8: 3 | H8: Tools/sfx/library.json: banks.blast_he_s2 | I8: {"group":"blast","size":"s2","row":"blast","variants":3}
A9: blast_he_s3 | B9: 3 | C9: blast | E9: blast | F9: s3 | G9: 3 | H9: Tools/sfx/library.json: banks.blast_he_s3 | I9: {"group":"blast","size":"s3","row":"blast","variants":3}
A10: blast_he_s4 | B10: 3 | C10: blast | E10: blast | F10: s4 | G10: 3 | H10: Tools/sfx/library.json: banks.blast_he_s4 | I10: {"group":"blast","size":"s4","row":"blast","variants":3}
A11: blast_he_s406 | B11: 2 | C11: blast | E11: blast | F11: s406 | G11: 2 | H11: Tools/sfx/library.json: banks.blast_he_s406 | I11: {"group":"blast","size":"s406","row":"blast","variants":2}
A12: blast_heat_s2 | B12: 2 | C12: blast_heat | F12: s2 | G12: 2 | H12: Tools/sfx/library.json: banks.blast_heat_s2 | I12: {"group":"blast_heat","size":"s2","row":null,"variants":2}
A13: blast_heat_s3 | B13: 2 | C13: blast_heat | F13: s3 | G13: 2 | H13: Tools/sfx/library.json: banks.blast_heat_s3 | I13: {"group":"blast_heat","size":"s3","row":null,"variants":2}
A14: blast_super | B14: 2 | C14: blast | E14: blast | F14: super | G14: 2 | H14: Tools/sfx/library.json: banks.blast_super | I14: {"group":"blast","size":"super","row":"blast","variants":2}
A15: blast_thermo_s3 | B15: 2 | C15: blast_thermo | F15: s3 | G15: 2 | H15: Tools/sfx/library.json: banks.blast_thermo_s3 | I15: {"group":"blast_thermo","size":"s3","row":null,"variants":2}
A16: blast_thermo_s4 | B16: 2 | C16: blast_thermo | F16: s4 | G16: 2 | H16: Tools/sfx/library.json: banks.blast_thermo_s4 | I16: {"group":"blast_thermo","size":"s4","row":null,"variants":2}
A17: burst_s0_10 | B17: 3 | C17: shot | F17: s0 | G17: 3 | H17: Tools/sfx/library.json: banks.burst_s0_10 | I17: {"group":"shot","size":"s0","row":null,"variants":3}
A18: burst_s0_16 | B18: 3 | C18: shot | F18: s0 | G18: 3 | H18: Tools/sfx/library.json: banks.burst_s0_16 | I18: {"group":"shot","size":"s0","row":null,"variants":3}
A19: burst_s0_55 | B19: 3 | C19: shot | F19: s0 | G19: 3 | H19: Tools/sfx/library.json: banks.burst_s0_55 | I19: {"group":"shot","size":"s0","row":null,"variants":3}
A20: burst_s1_10 | B20: 3 | C20: shot | F20: s1 | G20: 3 | H20: Tools/sfx/library.json: banks.burst_s1_10 | I20: {"group":"shot","size":"s1","row":null,"variants":3}
A21: burst_s1_22 | B21: 3 | C21: shot | F21: s1 | G21: 3 | H21: Tools/sfx/library.json: banks.burst_s1_22 | I21: {"group":"shot","size":"s1","row":null,"variants":3}
A22: burst_s1_35 | B22: 3 | C22: shot | F22: s1 | G22: 3 | H22: Tools/sfx/library.json: banks.burst_s1_35 | I22: {"group":"shot","size":"s1","row":null,"variants":3}
A23: burst_s1_55 | B23: 3 | C23: shot | F23: s1 | G23: 3 | H23: Tools/sfx/library.json: banks.burst_s1_55 | I23: {"group":"shot","size":"s1","row":null,"variants":3}
A24: cannon | B24: 3 | C24: shot | D24: TRUE | H24: Tools/sfx/library.json: banks.cannon | I24: {"group":"shot","size":null,"row":null,"kept":true}
A25: collapse | B25: 2 | C25: wreck | D25: TRUE | H25: Tools/sfx/library.json: banks.collapse | I25: {"group":"wreck","size":null,"row":null,"kept":true}
A26: crash_fall | B26: 2 | C26: aircraft | G26: 2 | H26: Tools/sfx/library.json: banks.crash_fall | I26: {"group":"aircraft","size":null,"row":null,"variants":2}
A27: crash_impact | B27: 2 | C27: aircraft | G27: 2 | H27: Tools/sfx/library.json: banks.crash_impact | I27: {"group":"aircraft","size":null,"row":null,"variants":2}
A28: debris | B28: 3 | C28: wreck | D28: TRUE | H28: Tools/sfx/library.json: banks.debris | I28: {"group":"wreck","size":null,"row":null,"kept":true}
A29: engine_heavy | B29: 1 | C29: engine | G29: 1 | H29: Tools/sfx/library.json: banks.engine_heavy | I29: {"group":"engine","size":null,"row":null,"variants":1}
A30: engine_tracked | B30: 1 | C30: engine | G30: 1 | H30: Tools/sfx/library.json: banks.engine_tracked | I30: {"group":"engine","size":null,"row":null,"variants":1}
A31: engine_wheeled | B31: 1 | C31: engine | G31: 1 | H31: Tools/sfx/library.json: banks.engine_wheeled | I31: {"group":"engine","size":null,"row":null,"variants":1}
A32: explosion_huge | B32: 3 | C32: blast | D32: TRUE | H32: Tools/sfx/library.json: banks.explosion_huge | I32: {"group":"blast","size":null,"row":null,"kept":true}
A33: explosion_large | B33: 4 | C33: blast | D33: TRUE | H33: Tools/sfx/library.json: banks.explosion_large | I33: {"group":"blast","size":null,"row":null,"kept":true}
A34: explosion_medium | B34: 4 | C34: blast | D34: TRUE | H34: Tools/sfx/library.json: banks.explosion_medium | I34: {"group":"blast","size":null,"row":null,"kept":true}
A35: explosion_small | B35: 4 | C35: blast | D35: TRUE | H35: Tools/sfx/library.json: banks.explosion_small | I35: {"group":"blast","size":null,"row":null,"kept":true}
A36: fire_loop | B36: 1 | C36: ambience | D36: TRUE | H36: Tools/sfx/library.json: banks.fire_loop | I36: {"group":"ambience","size":null,"row":null,"kept":true}
A37: flak | B37: 3 | C37: blast_air | D37: TRUE | H37: Tools/sfx/library.json: banks.flak | I37: {"group":"blast_air","size":null,"row":null,"kept":true}
A38: flame | B38: 2 | C38: shot | D38: TRUE | H38: Tools/sfx/library.json: banks.flame | I38: {"group":"shot","size":null,"row":null,"kept":true}
A39: flare_pop | B39: 2 | C39: flare | G39: 2 | H39: Tools/sfx/library.json: banks.flare_pop | I39: {"group":"flare","size":null,"row":null,"variants":2}
A40: heavy_cannon | B40: 3 | C40: shot | D40: TRUE | H40: Tools/sfx/library.json: banks.heavy_cannon | I40: {"group":"shot","size":null,"row":null,"kept":true}
A41: hit_armour_glance | B41: 3 | C41: hit_armour | F41: s2 | G41: 3 | H41: Tools/sfx/library.json: banks.hit_armour_glance | I41: {"group":"hit_armour","size":"s2","row":null,"variants":3}
A42: hit_armour_heavy | B42: 3 | C42: hit_armour | F42: s3 | G42: 3 | H42: Tools/sfx/library.json: banks.hit_armour_heavy | I42: {"group":"hit_armour","size":"s3","row":null,"variants":3}
A43: hit_armour_light | B43: 4 | C43: hit_armour | F43: s1 | G43: 4 | H43: Tools/sfx/library.json: banks.hit_armour_light | I43: {"group":"hit_armour","size":"s1","row":null,"variants":4}
A44: hit_concrete_heavy | B44: 3 | C44: hit_concrete | F44: s2 | G44: 3 | H44: Tools/sfx/library.json: banks.hit_concrete_heavy | I44: {"group":"hit_concrete","size":"s2","row":null,"variants":3}
A45: hit_concrete_light | B45: 3 | C45: hit_concrete | F45: s0 | G45: 3 | H45: Tools/sfx/library.json: banks.hit_concrete_light | I45: {"group":"hit_concrete","size":"s0","row":null,"variants":3}
A46: hit_ground_heavy | B46: 3 | C46: hit_ground | F46: s2 | G46: 3 | H46: Tools/sfx/library.json: banks.hit_ground_heavy | I46: {"group":"hit_ground","size":"s2","row":null,"variants":3}
A47: hit_ground_light | B47: 3 | C47: hit_ground | E47: blast | F47: s0 | G47: 3 | H47: Tools/sfx/library.json: banks.hit_ground_light | I47: {"group":"hit_ground","size":"s0","row":"blast","variants":3}
A48: hit_metal_heavy | B48: 3 | C48: armour_metal | F48: s3 | G48: 3 | H48: Tools/sfx/library.json: banks.hit_metal_heavy | I48: {"group":"armour_metal","size":"s3","row":null,"variants":3}
A49: hit_metal_light | B49: 3 | C49: armour_metal | F49: s1 | G49: 3 | H49: Tools/sfx/library.json: banks.hit_metal_light | I49: {"group":"armour_metal","size":"s1","row":null,"variants":3}
A50: hit_pen_heavy | B50: 3 | C50: hit_pen | F50: s3 | G50: 3 | H50: Tools/sfx/library.json: banks.hit_pen_heavy | I50: {"group":"hit_pen","size":"s3","row":null,"variants":3}
A51: hit_pen_light | B51: 3 | C51: hit_pen | F51: s1 | G51: 3 | H51: Tools/sfx/library.json: banks.hit_pen_light | I51: {"group":"hit_pen","size":"s1","row":null,"variants":3}
A52: jet_loop | B52: 1 | C52: aircraft | D52: TRUE | H52: Tools/sfx/library.json: banks.jet_loop | I52: {"group":"aircraft","size":null,"row":null,"kept":true}
A53: jet_pass | B53: 3 | C53: aircraft | D53: TRUE | H53: Tools/sfx/library.json: banks.jet_pass | I53: {"group":"aircraft","size":null,"row":null,"kept":true}
A54: launch_atgm | B54: 3 | C54: launch | F54: s2 | G54: 3 | H54: Tools/sfx/library.json: banks.launch_atgm | I54: {"group":"launch","size":"s2","row":null,"variants":3}
A55: launch_big | B55: 3 | C55: launch | F55: s406 | G55: 3 | H55: Tools/sfx/library.json: banks.launch_big | I55: {"group":"launch","size":"s406","row":null,"variants":3}
A56: launch_cruise | B56: 3 | C56: launch | F56: s406 | G56: 3 | H56: Tools/sfx/library.json: banks.launch_cruise | I56: {"group":"launch","size":"s406","row":null,"variants":3}
A57: launch_s2 | B57: 3 | C57: launch | F57: s2 | G57: 3 | H57: Tools/sfx/library.json: banks.launch_s2 | I57: {"group":"launch","size":"s2","row":null,"variants":3}
A58: launch_s3 | B58: 3 | C58: launch | F58: s3 | G58: 3 | H58: Tools/sfx/library.json: banks.launch_s3 | I58: {"group":"launch","size":"s3","row":null,"variants":3}
A59: launch_sam | B59: 3 | C59: launch | F59: s2 | G59: 3 | H59: Tools/sfx/library.json: banks.launch_sam | I59: {"group":"launch","size":"s2","row":null,"variants":3}
A60: mg | B60: 3 | C60: shot | D60: TRUE | H60: Tools/sfx/library.json: banks.mg | I60: {"group":"shot","size":null,"row":null,"kept":true}
A61: missile_hiss | B61: 2 | C61: launch | G61: 2 | H61: Tools/sfx/library.json: banks.missile_hiss | I61: {"group":"launch","size":null,"row":null,"variants":2}
A62: missile_launch | B62: 2 | C62: launch | D62: TRUE | H62: Tools/sfx/library.json: banks.missile_launch | I62: {"group":"launch","size":null,"row":null,"kept":true}
A63: rain_loop | B63: 1 | C63: ambience | D63: TRUE | H63: Tools/sfx/library.json: banks.rain_loop | I63: {"group":"ambience","size":null,"row":null,"kept":true}
A64: rocket_launch | B64: 4 | C64: launch | D64: TRUE | H64: Tools/sfx/library.json: banks.rocket_launch | I64: {"group":"launch","size":null,"row":null,"kept":true}
A65: rotor_loop | B65: 1 | C65: helicopter | D65: TRUE | H65: Tools/sfx/library.json: banks.rotor_loop | I65: {"group":"helicopter","size":null,"row":null,"kept":true}
A66: ship_engine | B66: 1 | C66: ship | G66: 1 | H66: Tools/sfx/library.json: banks.ship_engine | I66: {"group":"ship","size":null,"row":null,"variants":1}
A67: ship_horn | B67: 1 | C67: ship | G67: 1 | H67: Tools/sfx/library.json: banks.ship_horn | I67: {"group":"ship","size":null,"row":null,"variants":1}
A68: shot_ac57 | B68: 3 | C68: shot | F68: s2 | G68: 3 | H68: Tools/sfx/library.json: banks.shot_ac57 | I68: {"group":"shot","size":"s2","row":null,"variants":3}
A69: shot_s0 | B69: 4 | C69: shot | E69: shot | F69: s0 | G69: 4 | H69: Tools/sfx/library.json: banks.shot_s0 | I69: {"group":"shot","size":"s0","row":"shot","variants":4}
A70: shot_s1 | B70: 4 | C70: shot | E70: shot | F70: s1 | G70: 4 | H70: Tools/sfx/library.json: banks.shot_s1 | I70: {"group":"shot","size":"s1","row":"shot","variants":4}
A71: shot_s2 | B71: 3 | C71: shot | E71: shot | F71: s2 | G71: 3 | H71: Tools/sfx/library.json: banks.shot_s2 | I71: {"group":"shot","size":"s2","row":"shot","variants":3}
A72: shot_s3 | B72: 3 | C72: shot | E72: shot | F72: s3 | G72: 3 | H72: Tools/sfx/library.json: banks.shot_s3 | I72: {"group":"shot","size":"s3","row":"shot","variants":3}
A73: shot_s4 | B73: 3 | C73: shot | E73: shot | F73: s4 | G73: 3 | H73: Tools/sfx/library.json: banks.shot_s4 | I73: {"group":"shot","size":"s4","row":"shot","variants":3}
A74: shot_s406 | B74: 2 | C74: shot | E74: shot | F74: s406 | G74: 2 | H74: Tools/sfx/library.json: banks.shot_s406 | I74: {"group":"shot","size":"s406","row":"shot","variants":2}
A75: shot_super | B75: 2 | C75: shot | E75: shot | F75: super | G75: 2 | H75: Tools/sfx/library.json: banks.shot_super | I75: {"group":"shot","size":"super","row":"shot","variants":2}
A76: siren | B76: 1 | C76: warning | D76: TRUE | H76: Tools/sfx/library.json: banks.siren | I76: {"group":"warning","size":null,"row":null,"kept":true}
A77: smallarms_cluster | B77: 3 | C77: shot | F77: s0 | G77: 3 | H77: Tools/sfx/library.json: banks.smallarms_cluster | I77: {"group":"shot","size":"s0","row":null,"variants":3}
A78: thunder | B78: 3 | C78: ambience | D78: TRUE | H78: Tools/sfx/library.json: banks.thunder | I78: {"group":"ambience","size":null,"row":null,"kept":true}
A79: train_horn | B79: 2 | C79: train | G79: 2 | H79: Tools/sfx/library.json: banks.train_horn | I79: {"group":"train","size":null,"row":null,"variants":2}
A80: train_rails | B80: 1 | C80: train | G80: 1 | H80: Tools/sfx/library.json: banks.train_rails | I80: {"group":"train","size":null,"row":null,"variants":1}
A81: warn_whistle | B81: 3 | C81: warning | G81: 3 | H81: Tools/sfx/library.json: banks.warn_whistle | I81: {"group":"warning","size":null,"row":null,"variants":3}
A82: warn_whistle_big | B82: 2 | C82: warning | G82: 2 | H82: Tools/sfx/library.json: banks.warn_whistle_big | I82: {"group":"warning","size":null,"row":null,"variants":2}
A83: wind_loop | B83: 1 | C83: ambience | D83: TRUE | H83: Tools/sfx/library.json: banks.wind_loop | I83: {"group":"ambience","size":null,"row":null,"kept":true}
A84: wreck_aircraft | B84: 2 | C84: wreck | G84: 2 | H84: Tools/sfx/library.json: banks.wreck_aircraft | I84: {"group":"wreck","size":null,"row":null,"variants":2}
A85: wreck_artillery | B85: 2 | C85: wreck | G85: 2 | H85: Tools/sfx/library.json: banks.wreck_artillery | I85: {"group":"wreck","size":null,"row":null,"variants":2}
A86: wreck_drone | B86: 2 | C86: wreck | G86: 2 | H86: Tools/sfx/library.json: banks.wreck_drone | I86: {"group":"wreck","size":null,"row":null,"variants":2}
A87: wreck_heli | B87: 2 | C87: wreck | G87: 2 | H87: Tools/sfx/library.json: banks.wreck_heli | I87: {"group":"wreck","size":null,"row":null,"variants":2}
A88: wreck_ship | B88: 2 | C88: wreck | G88: 2 | H88: Tools/sfx/library.json: banks.wreck_ship | I88: {"group":"wreck","size":null,"row":null,"variants":2}
A89: wreck_tank | B89: 2 | C89: wreck | G89: 2 | H89: Tools/sfx/library.json: banks.wreck_tank | I89: {"group":"wreck","size":null,"row":null,"variants":2}
A90: wreck_truck | B90: 2 | C90: wreck | G90: 2 | H90: Tools/sfx/library.json: banks.wreck_truck | I90: {"group":"wreck","size":null,"row":null,"variants":2}
A91: wreck_wheeled | B91: 2 | C91: wreck | G91: 2 | H91: Tools/sfx/library.json: banks.wreck_wheeled | I91: {"group":"wreck","size":null,"row":null,"variants":2}

Sheet Am_thanh_thu_vien
A1: id | B1: nhom | C1: khoa | D1: gia_tri_so | E1: gia_tri_chu | F1: don_vi | G1: nguon | H1: raw_json
A2: note | C2: note | E2: Fix pass L7: the sound library (Tools/sfx/build_sfx.py); sizes s0 = <= 14.5 mm, s1 = 20-40 mm, s2 = 57-105 mm, s3 = 120-155 mm, s4 = 203-240 mm, bomb = bombs, s406 = big rockets / >= 406 mm, super = super weapons | G2: Tools/sfx/library.json: note | H2: "Fix pass L7: the sound library (Tools/sfx/build_sfx.py); sizes s0 = <= 14.5 mm, s1 = 20-40 mm, s2 = 57-105 mm, s3 = 120-155 mm, s4 = 203-240 mm, bomb = bombs, s406 = big rockets / >= 406 mm, super = super weapons"

Sheet Am_thanh_loat
A1: id | B1: bank | C1: co | D1: nhip_phat_s | E1: so_phat | F1: nguon | G1: raw_json
A2: burst_s0_10 | B2: burst_s0_10 | C2: S0 | D2: 10 | E2: 3 | F2: Assets/MachineBrigade/Scripts/Game/Audio/SoundLibrary.cs:164 (Bursts[0]) | G2: ["burst_s0_10","S0",10,3]
A3: burst_s0_16 | B3: burst_s0_16 | C3: S0 | D3: 16 | E3: 5 | F3: Assets/MachineBrigade/Scripts/Game/Audio/SoundLibrary.cs:164 (Bursts[1]) | G3: ["burst_s0_16","S0",16,5]
A4: burst_s0_55 | B4: burst_s0_55 | C4: S0 | D4: 55 | E4: 18 | F4: Assets/MachineBrigade/Scripts/Game/Audio/SoundLibrary.cs:164 (Bursts[2]) | G4: ["burst_s0_55","S0",55,18]
A5: burst_s1_10 | B5: burst_s1_10 | C5: S1 | D5: 10 | E5: 3 | F5: Assets/MachineBrigade/Scripts/Game/Audio/SoundLibrary.cs:165 (Bursts[3]) | G5: ["burst_s1_10","S1",10,3]
A6: burst_s1_22 | B6: burst_s1_22 | C6: S1 | D6: 22 | E6: 7 | F6: Assets/MachineBrigade/Scripts/Game/Audio/SoundLibrary.cs:165 (Bursts[4]) | G6: ["burst_s1_22","S1",22,7]
A7: burst_s1_35 | B7: burst_s1_35 | C7: S1 | D7: 35 | E7: 12 | F7: Assets/MachineBrigade/Scripts/Game/Audio/SoundLibrary.cs:165 (Bursts[5]) | G7: ["burst_s1_35","S1",35,12]
A8: burst_s1_55 | B8: burst_s1_55 | C8: S1 | D8: 55 | E8: 18 | F8: Assets/MachineBrigade/Scripts/Game/Audio/SoundLibrary.cs:166 (Bursts[6]) | G8: ["burst_s1_55","S1",55,18]

Sheet VFX_bac
A1: id | B1: bac | C1: rung_camera_dong_thoi | D1: ban_dust_ring | E1: ban_flash | F1: ban_flash_life | G1: ban_light | H1: ban_pressure | I1: ban_puff_life | J1: ban_puff_life_arg0 | K1: ban_puff_life_arg1 | L1: ban_puff_size | M1: ban_puffs | N1: ban_squat | O1: ban_water | P1: doi_crater | Q1: doi_fireball | R1: doi_smoke_max | S1: doi_smoke_min | T1: nguon | U1: raw_json
A2: T0 | B2: 0 | C2: XEM_VFX_ngan_sach | D2: 0 | E2: 0 | F2: 0 | G2: 0 | H2: 0 | I2: zero | L2: 0 | M2: 0 | N2: 0 | O2: 0 | P2: 0 | Q2: 0.2 | R2: 0.5 | S2: 0.5 | T2: Assets/MachineBrigade/Scripts/Game/Effects/TierFx.cs (Fire), Assets/MachineBrigade/Scripts/Game/Effects/EffectLife.cs (Bands)
A3: T1 | B3: 1 | C3: XEM_VFX_ngan_sach | D3: 0 | E3: 0 | F3: 0 | G3: 0 | H3: 0 | J3: 1.2 | K3: 1.8 | L3: 0.6 | M3: 2 | N3: 0 | O3: 0 | P3: 10 | Q3: 0.3 | R3: 1 | S3: 0.5 | T3: Assets/MachineBrigade/Scripts/Game/Effects/TierFx.cs (Fire), Assets/MachineBrigade/Scripts/Game/Effects/EffectLife.cs (Bands)
A4: T2 | B4: 2 | C4: XEM_VFX_ngan_sach | D4: 0 | E4: 1.2 | F4: 0.1 | G4: 0 | H4: 0 | J4: 1.8 | K4: 2.6 | L4: 1.1 | M4: 4 | N4: 0 | O4: 0 | P4: 20 | Q4: 0.5 | R4: 2.5 | S4: 1.5 | T4: Assets/MachineBrigade/Scripts/Game/Effects/TierFx.cs (Fire), Assets/MachineBrigade/Scripts/Game/Effects/EffectLife.cs (Bands)
A5: T3 | B5: 3 | C5: XEM_VFX_ngan_sach | D5: 8 | E5: 2.4 | F5: 0.16 | G5: 9 | H5: 0 | J5: 3.5 | K5: 5 | L5: 1.7 | M5: 10 | N5: 1.6 | O5: 0 | P5: 30 | Q5: 0.8 | R5: 5 | S5: 3 | T5: Assets/MachineBrigade/Scripts/Game/Effects/TierFx.cs (Fire), Assets/MachineBrigade/Scripts/Game/Effects/EffectLife.cs (Bands)
A6: T4 | B6: 4 | C6: XEM_VFX_ngan_sach | D6: 16 | E6: 3.6 | F6: 0.24 | G6: 16 | H6: 7 | J6: 5 | K6: 7 | L6: 2.4 | M6: 16 | N6: 2.4 | O6: 12 | P6: 45 | Q6: 1.2 | R6: 10 | S6: 6 | T6: Assets/MachineBrigade/Scripts/Game/Effects/TierFx.cs (Fire), Assets/MachineBrigade/Scripts/Game/Effects/EffectLife.cs (Bands)
A7: T5 | B7: 5 | C7: XEM_VFX_ngan_sach | D7: 26 | E7: 5 | F7: 0.34 | G7: 28 | H7: 12 | J7: 7 | K7: 10 | L7: 3.2 | M7: 24 | N7: 3.2 | O7: 22 | P7: 60 | Q7: 1.8 | R7: 15 | S7: 10 | T7: Assets/MachineBrigade/Scripts/Game/Effects/TierFx.cs (Fire), Assets/MachineBrigade/Scripts/Game/Effects/EffectLife.cs (Bands)

Sheet VFX_chay_than_xe
A1: id | B1: bodies | C1: embers | D1: low_tongues | E1: power | F1: reach_m | G1: size | H1: smoke_alpha | I1: smoke_shade | J1: smoke_size | K1: sparks | L1: tongues | M1: nguon | N1: raw_json
A2: 0 | B2: 1 | C2: 0.5 | D2: 1 | E2: 2.8 | F2: 4.5 | G2: 1 | H2: 0.6 | I2: 0.34 | J2: 1 | K2: 0.25 | L2: 1 | M2: Assets/MachineBrigade/Scripts/Game/Effects/HullFire.cs:63 (Looks[0]) | N2: {"bodies":1,"tongues":1,"lowTongues":1,"size":1,"smokeShade":0.34,"smokeAlpha":0.6,"smokeSize":1,"embers":0.5,"sparks":0.25,"reach":4.5,"power":2.8}
A3: 1 | B3: 1 | C3: 1.1 | D3: 1 | E3: 4 | F3: 6 | G3: 1.2 | H3: 0.74 | I3: 0.16 | J3: 1.15 | K3: 0.7 | L3: 2 | M3: Assets/MachineBrigade/Scripts/Game/Effects/HullFire.cs:66 (Looks[1]) | N3: {"bodies":1,"tongues":2,"lowTongues":1,"size":1.2,"smokeShade":0.16,"smokeAlpha":0.74,"smokeSize":1.15,"embers":1.1,"sparks":0.7,"reach":6,"power":4}
A4: 2 | B4: 2 | C4: 1.8 | D4: 2 | E4: 5.2 | F4: 7.5 | G4: 1.45 | H4: 0.8 | I4: 0.06 | J4: 1.35 | K4: 1.2 | L4: 2 | M4: Assets/MachineBrigade/Scripts/Game/Effects/HullFire.cs:69 (Looks[2]) | N4: {"bodies":2,"tongues":2,"lowTongues":2,"size":1.45,"smokeShade":0.06,"smokeAlpha":0.8,"smokeSize":1.35,"embers":1.8,"sparks":1.2,"reach":7.5,"power":5.2}

Sheet Hau_ky_hinh_anh
A1: id | B1: hieu_ung | C1: thiet_lap | D1: ghi_de | E1: gia_tri | F1: dimension | G1: nguon | H1: raw_json
A2: BattlefieldProfile.m_Enabled | B2: BattlefieldProfile | C2: m_Enabled | E2: 1 | G2: Assets/MachineBrigade/Settings/BattlefieldProfile.asset: docs[3].MonoBehaviour.m_Enabled | H2: "1"
A3: BattlefieldProfile.m_Name | B3: BattlefieldProfile | C3: m_Name | E3: BattlefieldProfile | G3: Assets/MachineBrigade/Settings/BattlefieldProfile.asset: docs[3].MonoBehaviour.m_Name | H3: "BattlefieldProfile"
A4: Bloom.active | B4: Bloom | C4: active | E4: 1 | G4: Assets/MachineBrigade/Settings/BattlefieldProfile.asset: docs[0].MonoBehaviour.active | H4: "1"
A5: Bloom.clamp | B5: Bloom | C5: clamp | D5: 1 | E5: 6 | G5: Assets/MachineBrigade/Settings/BattlefieldProfile.asset: docs[0].MonoBehaviour.clamp | H5: {"m_OverrideState":"1","m_Value":"6"}
A6: Bloom.dirtIntensity | B6: Bloom | C6: dirtIntensity | D6: 0 | E6: 0 | G6: Assets/MachineBrigade/Settings/BattlefieldProfile.asset: docs[0].MonoBehaviour.dirtIntensity | H6: {"m_OverrideState":"0","m_Value":"0"}
A7: Bloom.dirtTexture | B7: Bloom | C7: dirtTexture | D7: 0 | E7: {fileID: 0} | F7: 1 | G7: Assets/MachineBrigade/Settings/BattlefieldProfile.asset: docs[0].MonoBehaviour.dirtTexture | H7: {"m_OverrideState":"0","m_Value":"{fileID: 0}","dimension":"1"}
A8: Bloom.downscale | B8: Bloom | C8: downscale | D8: 0 | E8: 0 | G8: Assets/MachineBrigade/Settings/BattlefieldProfile.asset: docs[0].MonoBehaviour.downscale | H8: {"m_OverrideState":"0","m_Value":"0"}
A9: Bloom.filter | B9: Bloom | C9: filter | D9: 0 | E9: 0 | G9: Assets/MachineBrigade/Settings/BattlefieldProfile.asset: docs[0].MonoBehaviour.filter | H9: {"m_OverrideState":"0","m_Value":"0"}
A10: Bloom.highQualityFiltering | B10: Bloom | C10: highQualityFiltering | D10: 1 | E10: 1 | G10: Assets/MachineBrigade/Settings/BattlefieldProfile.asset: docs[0].MonoBehaviour.highQualityFiltering | H10: {"m_OverrideState":"1","m_Value":"1"}
A11: Bloom.intensity | B11: Bloom | C11: intensity | D11: 1 | E11: 0.45 | G11: Assets/MachineBrigade/Settings/BattlefieldProfile.asset: docs[0].MonoBehaviour.intensity | H11: {"m_OverrideState":"1","m_Value":"0.45"}
A12: Bloom.m_Enabled | B12: Bloom | C12: m_Enabled | E12: 1 | G12: Assets/MachineBrigade/Settings/BattlefieldProfile.asset: docs[0].MonoBehaviour.m_Enabled | H12: "1"
A13: Bloom.m_Name | B13: Bloom | C13: m_Name | E13: Bloom | G13: Assets/MachineBrigade/Settings/BattlefieldProfile.asset: docs[0].MonoBehaviour.m_Name | H13: "Bloom"
A14: Bloom.maxIterations | B14: Bloom | C14: maxIterations | D14: 0 | E14: 6 | G14: Assets/MachineBrigade/Settings/BattlefieldProfile.asset: docs[0].MonoBehaviour.maxIterations | H14: {"m_OverrideState":"0","m_Value":"6"}
A15: Bloom.scatter | B15: Bloom | C15: scatter | D15: 1 | E15: 0.6 | G15: Assets/MachineBrigade/Settings/BattlefieldProfile.asset: docs[0].MonoBehaviour.scatter | H15: {"m_OverrideState":"1","m_Value":"0.6"}
A16: Bloom.skipIterations | B16: Bloom | C16: skipIterations | D16: 1 | E16: 0 | G16: Assets/MachineBrigade/Settings/BattlefieldProfile.asset: docs[0].MonoBehaviour.skipIterations | H16: {"m_OverrideState":"1","m_Value":"0"}
A17: Bloom.threshold | B17: Bloom | C17: threshold | D17: 1 | E17: 1 | G17: Assets/MachineBrigade/Settings/BattlefieldProfile.asset: docs[0].MonoBehaviour.threshold | H17: {"m_OverrideState":"1","m_Value":"1"}
A18: Bloom.tint | B18: Bloom | C18: tint | D18: 0 | E18: {r: 1, g: 1, b: 1, a: 1} | G18: Assets/MachineBrigade/Settings/BattlefieldProfile.asset: docs[0].MonoBehaviour.tint | H18: {"m_OverrideState":"0","m_Value":"{r: 1, g: 1, b: 1, a: 1}"}
A19: ColorAdjustments.active | B19: ColorAdjustments | C19: active | E19: 1 | G19: Assets/MachineBrigade/Settings/BattlefieldProfile.asset: docs[1].MonoBehaviour.active | H19: "1"
A20: ColorAdjustments.colorFilter | B20: ColorAdjustments | C20: colorFilter | D20: 1 | E20: {r: 1, g: 1, b: 1, a: 1} | G20: Assets/MachineBrigade/Settings/BattlefieldProfile.asset: docs[1].MonoBehaviour.colorFilter | H20: {"m_OverrideState":"1","m_Value":"{r: 1, g: 1, b: 1, a: 1}"}
A21: ColorAdjustments.contrast | B21: ColorAdjustments | C21: contrast | D21: 1 | E21: 10 | G21: Assets/MachineBrigade/Settings/BattlefieldProfile.asset: docs[1].MonoBehaviour.contrast | H21: {"m_OverrideState":"1","m_Value":"10"}
A22: ColorAdjustments.hueShift | B22: ColorAdjustments | C22: hueShift | D22: 1 | E22: 0 | G22: Assets/MachineBrigade/Settings/BattlefieldProfile.asset: docs[1].MonoBehaviour.hueShift | H22: {"m_OverrideState":"1","m_Value":"0"}
A23: ColorAdjustments.m_Enabled | B23: ColorAdjustments | C23: m_Enabled | E23: 1 | G23: Assets/MachineBrigade/Settings/BattlefieldProfile.asset: docs[1].MonoBehaviour.m_Enabled | H23: "1"
A24: ColorAdjustments.m_Name | B24: ColorAdjustments | C24: m_Name | E24: ColorAdjustments | G24: Assets/MachineBrigade/Settings/BattlefieldProfile.asset: docs[1].MonoBehaviour.m_Name | H24: "ColorAdjustments"
A25: ColorAdjustments.postExposure | B25: ColorAdjustments | C25: postExposure | D25: 1 | E25: 0.35 | G25: Assets/MachineBrigade/Settings/BattlefieldProfile.asset: docs[1].MonoBehaviour.postExposure | H25: {"m_OverrideState":"1","m_Value":"0.35"}
A26: ColorAdjustments.saturation | B26: ColorAdjustments | C26: saturation | D26: 1 | E26: 0 | G26: Assets/MachineBrigade/Settings/BattlefieldProfile.asset: docs[1].MonoBehaviour.saturation | H26: {"m_OverrideState":"1","m_Value":"0"}
A27: MotionBlur.active | B27: MotionBlur | C27: active | E27: 0 | G27: Assets/MachineBrigade/Settings/BattlefieldProfile.asset: docs[5].MonoBehaviour.active | H27: "0"
A28: MotionBlur.clamp | B28: MotionBlur | C28: clamp | D28: 0 | E28: 0.05 | G28: Assets/MachineBrigade/Settings/BattlefieldProfile.asset: docs[5].MonoBehaviour.clamp | H28: {"m_OverrideState":"0","m_Value":"0.05"}
A29: MotionBlur.intensity | B29: MotionBlur | C29: intensity | D29: 1 | E29: 0.6 | G29: Assets/MachineBrigade/Settings/BattlefieldProfile.asset: docs[5].MonoBehaviour.intensity | H29: {"m_OverrideState":"1","m_Value":"0.6"}
A30: MotionBlur.m_Enabled | B30: MotionBlur | C30: m_Enabled | E30: 1 | G30: Assets/MachineBrigade/Settings/BattlefieldProfile.asset: docs[5].MonoBehaviour.m_Enabled | H30: "1"
A31: MotionBlur.m_Name | B31: MotionBlur | C31: m_Name | E31: MotionBlur | G31: Assets/MachineBrigade/Settings/BattlefieldProfile.asset: docs[5].MonoBehaviour.m_Name | H31: "MotionBlur"
A32: MotionBlur.mode | B32: MotionBlur | C32: mode | D32: 0 | E32: 0 | G32: Assets/MachineBrigade/Settings/BattlefieldProfile.asset: docs[5].MonoBehaviour.mode | H32: {"m_OverrideState":"0","m_Value":"0"}
A33: MotionBlur.quality | B33: MotionBlur | C33: quality | D33: 1 | E33: 2 | G33: Assets/MachineBrigade/Settings/BattlefieldProfile.asset: docs[5].MonoBehaviour.quality | H33: {"m_OverrideState":"1","m_Value":"2"}
A34: Tonemapping.acesPreset | B34: Tonemapping | C34: acesPreset | D34: 0 | E34: 3 | G34: Assets/MachineBrigade/Settings/BattlefieldProfile.asset: docs[4].MonoBehaviour.acesPreset | H34: {"m_OverrideState":"0","m_Value":"3"}
A35: Tonemapping.active | B35: Tonemapping | C35: active | E35: 1 | G35: Assets/MachineBrigade/Settings/BattlefieldProfile.asset: docs[4].MonoBehaviour.active | H35: "1"
A36: Tonemapping.detectBrightnessLimits | B36: Tonemapping | C36: detectBrightnessLimits | D36: 1 | E36: 1 | G36: Assets/MachineBrigade/Settings/BattlefieldProfile.asset: docs[4].MonoBehaviour.detectBrightnessLimits | H36: {"m_OverrideState":"1","m_Value":"1"}
A37: Tonemapping.detectPaperWhite | B37: Tonemapping | C37: detectPaperWhite | D37: 1 | E37: 0 | G37: Assets/MachineBrigade/Settings/BattlefieldProfile.asset: docs[4].MonoBehaviour.detectPaperWhite | H37: {"m_OverrideState":"1","m_Value":"0"}
A38: Tonemapping.hueShiftAmount | B38: Tonemapping | C38: hueShiftAmount | D38: 0 | E38: 0 | G38: Assets/MachineBrigade/Settings/BattlefieldProfile.asset: docs[4].MonoBehaviour.hueShiftAmount | H38: {"m_OverrideState":"0","m_Value":"0"}
A39: Tonemapping.m_Enabled | B39: Tonemapping | C39: m_Enabled | E39: 1 | G39: Assets/MachineBrigade/Settings/BattlefieldProfile.asset: docs[4].MonoBehaviour.m_Enabled | H39: "1"
A40: Tonemapping.m_Name | B40: Tonemapping | C40: m_Name | E40: Tonemapping | G40: Assets/MachineBrigade/Settings/BattlefieldProfile.asset: docs[4].MonoBehaviour.m_Name | H40: "Tonemapping"
A41: Tonemapping.maxNits | B41: Tonemapping | C41: maxNits | D41: 1 | E41: 647 | G41: Assets/MachineBrigade/Settings/BattlefieldProfile.asset: docs[4].MonoBehaviour.maxNits | H41: {"m_OverrideState":"1","m_Value":"647"}
A42: Tonemapping.minNits | B42: Tonemapping | C42: minNits | D42: 1 | E42: 0.005 | G42: Assets/MachineBrigade/Settings/BattlefieldProfile.asset: docs[4].MonoBehaviour.minNits | H42: {"m_OverrideState":"1","m_Value":"0.005"}
A43: Tonemapping.mode | B43: Tonemapping | C43: mode | D43: 1 | E43: 2 | G43: Assets/MachineBrigade/Settings/BattlefieldProfile.asset: docs[4].MonoBehaviour.mode | H43: {"m_OverrideState":"1","m_Value":"2"}
A44: Tonemapping.neutralHDRRangeReductionMode | B44: Tonemapping | C44: neutralHDRRangeReductionMode | D44: 0 | E44: 2 | G44: Assets/MachineBrigade/Settings/BattlefieldProfile.asset: docs[4].MonoBehaviour.neutralHDRRangeReductionMode | H44: {"m_OverrideState":"0","m_Value":"2"}
A45: Tonemapping.paperWhite | B45: Tonemapping | C45: paperWhite | D45: 1 | E45: 234 | G45: Assets/MachineBrigade/Settings/BattlefieldProfile.asset: docs[4].MonoBehaviour.paperWhite | H45: {"m_OverrideState":"1","m_Value":"234"}
A46: Vignette.active | B46: Vignette | C46: active | E46: 1 | G46: Assets/MachineBrigade/Settings/BattlefieldProfile.asset: docs[2].MonoBehaviour.active | H46: "1"
A47: Vignette.center | B47: Vignette | C47: center | D47: 0 | E47: {x: 0.5, y: 0.5} | G47: Assets/MachineBrigade/Settings/BattlefieldProfile.asset: docs[2].MonoBehaviour.center | H47: {"m_OverrideState":"0","m_Value":"{x: 0.5, y: 0.5}"}
A48: Vignette.color | B48: Vignette | C48: color | D48: 0 | E48: {r: 0, g: 0, b: 0, a: 1} | G48: Assets/MachineBrigade/Settings/BattlefieldProfile.asset: docs[2].MonoBehaviour.color | H48: {"m_OverrideState":"0","m_Value":"{r: 0, g: 0, b: 0, a: 1}"}
A49: Vignette.intensity | B49: Vignette | C49: intensity | D49: 1 | E49: 0.18 | G49: Assets/MachineBrigade/Settings/BattlefieldProfile.asset: docs[2].MonoBehaviour.intensity | H49: {"m_OverrideState":"1","m_Value":"0.18"}
A50: Vignette.m_Enabled | B50: Vignette | C50: m_Enabled | E50: 1 | G50: Assets/MachineBrigade/Settings/BattlefieldProfile.asset: docs[2].MonoBehaviour.m_Enabled | H50: "1"
A51: Vignette.m_Name | B51: Vignette | C51: m_Name | E51: Vignette | G51: Assets/MachineBrigade/Settings/BattlefieldProfile.asset: docs[2].MonoBehaviour.m_Name | H51: "Vignette"
A52: Vignette.rounded | B52: Vignette | C52: rounded | D52: 0 | E52: 0 | G52: Assets/MachineBrigade/Settings/BattlefieldProfile.asset: docs[2].MonoBehaviour.rounded | H52: {"m_OverrideState":"0","m_Value":"0"}
A53: Vignette.smoothness | B53: Vignette | C53: smoothness | D53: 1 | E53: 0.45 | G53: Assets/MachineBrigade/Settings/BattlefieldProfile.asset: docs[2].MonoBehaviour.smoothness | H53: {"m_OverrideState":"1","m_Value":"0.45"}

Sheet Xac_vo
A1: id | B1: tran_day_du | C1: song_toi_thieu_s | D1: song_toi_da_s | E1: song_boss_s | F1: nguon | G1: raw_json
A2: High | B2: 12 | C2: 30 | D2: 45 | E2: 90 | F2: game.json balancePack.wrecks
A3: Low | B3: 6 | C3: 20.1 | D3: 30.15 | E3: 60.3 | F3: game.json balancePack.wrecks
A4: Medium | B4: 9 | C4: 30 | D4: 45 | E4: 90 | F4: game.json balancePack.wrecks

Sheet Am_thanh_mixer
A1: id | B1: loai | C1: gia_tri | D1: nguon | E1: raw_json
A2: am_luong.dialogue | B2: am_luong_mac_dinh | C2: 1 | D2: game.json balancePack.audio
A3: am_luong.effects | B3: am_luong_mac_dinh | C3: 1 | D3: game.json balancePack.audio
A4: am_luong.master | B4: am_luong_mac_dinh | C4: 0.8 | D4: game.json balancePack.audio
A5: am_luong.music | B5: am_luong_mac_dinh | C5: 0.7 | D5: game.json balancePack.audio
A6: nhom.Dialogue | B6: nhom_kenh | D6: game.json balancePack.audio
A7: nhom.Effects | B7: nhom_kenh | D7: game.json balancePack.audio
A8: nhom.Music | B8: nhom_kenh | D8: game.json balancePack.audio
A9: nhom.UI | B9: nhom_kenh | D9: game.json balancePack.audio

Sheet Am_thanh_mau
A1: id | B1: tep | C1: do_dai_s | D1: kenh | E1: tan_so_mau_hz | F1: lufs_mmax_tinh | G1: so_moc | H1: events | I1: played | J1: cooldown | K1: out_of_reach | L1: cut_for_priority | M1: dropped_no_voice | N1: clustered_shots | O1: metal_played | P1: metal_capped | Q1: max_busy | R1: bursts | S1: burst_events | T1: burst_dropped_at_cap | U1: limiter_min_gain_db | V1: compressor_min_gain_db | W1: do_dai_tron_s | X1: lufs | Y1: lufs_mmax | Z1: peak_db | AA1: sub150 | AB1: nguon | AC1: raw_json
A2: boss_battle | B2: Docs/audio/samples/boss_battle.ogg | C2: 48 | D2: 2 | E2: 44100 | F2: -13.9 | G2: 8 | H2: 1288 | I2: 972 | J2: 261 | K2: 0 | L2: 8 | M2: 1 | N2: 172 | O2: 24 | P2: 0 | Q2: 24 | R2: 298 | S2: 1003 | T2: 54 | U2: -0.5 | V2: -4.5 | W2: 48 | X2: -18.4 | Y2: -13.8 | Z2: -1 | AA2: 65.8 | AB2: Docs/audio/samples/boss_battle.ogg; Docs/audio/samples/mixes.json[boss_battle] | AC2: {"events":1288,"played":972,"cooldown":261,"out_of_reach":0,"cut_for_priority":8,"dropped_no_voice":1,"clustered_shots":172,"metal_played":24,"metal_capped":0,"max_busy":24,"bursts":298,"burst_events":1003,"burst_dropped_at_cap":54,"limiter_min_gain_db":-0.5,"compressor_min_gain_db":-4.5,"seconds":48.0,"lufs":-18.4,"lufs_mmax":-13.8,"peak_db":-1.0,"sub150":65.8}
A3: crowded_battle | B3: Docs/audio/samples/crowded_battle.ogg | C3: 43 | D3: 2 | E3: 44100 | F3: -15 | G3: 8 | H3: 5930 | I3: 1830 | J3: 2802 | K3: 0 | L3: 350 | M3: 228 | N3: 568 | O3: 97 | P3: 333 | Q3: 25 | R3: 1802 | S3: 6387 | T3: 1070 | U3: 0 | V3: -1 | W3: 43 | X3: -17.7 | Y3: -14.8 | Z3: -1 | AA3: 32.1 | AB3: Docs/audio/samples/crowded_battle.ogg; Docs/audio/samples/mixes.json[crowded_battle] | AC3: {"events":5930,"played":1830,"cooldown":2802,"out_of_reach":0,"cut_for_priority":350,"dropped_no_voice":228,"clustered_shots":568,"metal_played":97,"metal_capped":333,"max_busy":25,"bursts":1802,"burst_events":6387,"burst_dropped_at_cap":1070,"limiter_min_gain_db":-0.0,"compressor_min_gain_db":-1.0,"seconds":43.0,"lufs":-17.7,"lufs_mmax":-14.8,"peak_db":-1.0,"sub150":32.1}
A4: normal_battle | B4: Docs/audio/samples/normal_battle.ogg | C4: 43 | D4: 2 | E4: 44100 | F4: -15.6 | G4: 8 | H4: 1150 | I4: 739 | J4: 251 | K4: 0 | L4: 0 | M4: 0 | N4: 0 | O4: 28 | P4: 1 | Q4: 20 | R4: 349 | S4: 1065 | T4: 160 | U4: 0 | V4: -0.8 | W4: 43 | X4: -22 | Y4: -15.5 | Z4: -2.2 | AA4: 39 | AB4: Docs/audio/samples/normal_battle.ogg; Docs/audio/samples/mixes.json[normal_battle] | AC4: {"events":1150,"played":739,"cooldown":251,"out_of_reach":0,"cut_for_priority":0,"dropped_no_voice":0,"clustered_shots":0,"metal_played":28,"metal_capped":1,"max_busy":20,"bursts":349,"burst_events":1065,"burst_dropped_at_cap":160,"limiter_min_gain_db":0.0,"compressor_min_gain_db":-0.8,"seconds":43.0,"lufs":-22.0,"lufs_mmax":-15.5,"peak_db":-2.2,"sub150":39.0}

Sheet Am_thanh_mau_moc
A1: id | B1: am_thanh_mau_id | C1: thu_tu | D1: thoi_diem_s | E1: lufs_400ms | F1: duoi_to_nhat_lu | G1: dinh_dbfs | H1: hang | I1: nguon | J1: raw_json
A2: boss_battle/1 | B2: boss_battle | C2: 0 | D2: 9.7 | E2: -15.7 | F2: 1.8 | G2: -3.5 | H2: 5 | I2: Docs/audio/samples/boss_battle.ogg @ 9.7 s
A3: boss_battle/2 | B3: boss_battle | C3: 1 | D3: 13.2 | E3: -15.1 | F3: 1.2 | G3: -1.2 | H3: 2 | I3: Docs/audio/samples/boss_battle.ogg @ 13.2 s
A4: boss_battle/3 | B4: boss_battle | C4: 2 | D4: 21.4 | E4: -15.7 | F4: 1.8 | G4: -2.2 | H4: 6 | I4: Docs/audio/samples/boss_battle.ogg @ 21.4 s
A5: boss_battle/4 | B5: boss_battle | C5: 3 | D5: 29.4 | E5: -15.5 | F5: 1.6 | G5: -2.6 | H5: 4 | I5: Docs/audio/samples/boss_battle.ogg @ 29.4 s
A6: boss_battle/5 | B6: boss_battle | C6: 4 | D6: 31.7 | E6: -16.6 | F6: 2.7 | G6: -2.2 | H6: 8 | I6: Docs/audio/samples/boss_battle.ogg @ 31.7 s
A7: boss_battle/6 | B7: boss_battle | C7: 5 | D7: 33.7 | E7: -13.9 | F7: 0 | G7: -1 | H7: 1 | I7: Docs/audio/samples/boss_battle.ogg @ 33.7 s
A8: boss_battle/7 | B8: boss_battle | C8: 6 | D8: 36.2 | E8: -15.1 | F8: 1.2 | G8: -1.7 | H8: 3 | I8: Docs/audio/samples/boss_battle.ogg @ 36.2 s
A9: boss_battle/8 | B9: boss_battle | C9: 7 | D9: 43.1 | E9: -16 | F9: 2.1 | G9: -1.6 | H9: 7 | I9: Docs/audio/samples/boss_battle.ogg @ 43.1 s
A10: crowded_battle/1 | B10: crowded_battle | C10: 0 | D10: 1.9 | E10: -16.1 | F10: 1.1 | G10: -2.8 | H10: 4 | I10: Docs/audio/samples/crowded_battle.ogg @ 1.9 s
A11: crowded_battle/2 | B11: crowded_battle | C11: 1 | D11: 10.7 | E11: -15.3 | F11: 0.3 | G11: -1 | H11: 2 | I11: Docs/audio/samples/crowded_battle.ogg @ 10.7 s
A12: crowded_battle/3 | B12: crowded_battle | C12: 2 | D12: 15.3 | E12: -16.5 | F12: 1.5 | G12: -4.1 | H12: 6 | I12: Docs/audio/samples/crowded_battle.ogg @ 15.3 s
A13: crowded_battle/4 | B13: crowded_battle | C13: 3 | D13: 18.7 | E13: -15.8 | F13: 0.8 | G13: -3.2 | H13: 3 | I13: Docs/audio/samples/crowded_battle.ogg @ 18.7 s
... A25: normal_battle/8 | B25: normal_battle | C25: 7 | D25: 39.5 | E25: -18.2 | F25: 2.6 | G25: -5 | H25: 7 | I25: Docs/audio/samples/normal_battle.ogg @ 39.5 s

Sheet VFX_vu_khi
A1: id | B1: loai | C1: vu_khi | D1: bac | E1: co_mm | F1: so_nong | G1: loat | H1: don_vi_mang | I1: thu_muc | J1: so_anh | K1: so_anh_co | L1: trang_thai | M1: nguon | N1: raw_json
A2: amos_120 | B2: vu_khi | C2: amos_120 | D2: 3 | E2: 120 | F2: 1 | G2: FALSE | H2: sp_mortar | I2: Builds/effect_shots/amos_120/ | J2: 8 | K2: 0 | L2: pending | M2: EffectShots.FxJobs (01_chien_dau/Vu_khi); Builds/effect_shots/amos_120/
A3: bastion_gun | B3: vu_khi | C3: bastion_gun | D3: 3 | E3: 152 | F3: 2 | G3: TRUE | H3: headquarters;headquarters.fortress_air;headquarters.fortress_ground;headquarters.shield;spawn_bastion | I3: Builds/effect_shots/bastion_gun/ | J3: 10 | K3: 0 | L3: pending | M3: EffectShots.FxJobs (01_chien_dau/Vu_khi); Builds/effect_shots/bastion_gun/
A4: boss_howitzer | B4: vu_khi | C4: boss_howitzer | D4: 4 | E4: 203 | F4: 1 | G4: FALSE | H4: howitzer_203 | I4: Builds/effect_shots/boss_howitzer/ | J4: 8 | K4: 0 | L4: pending | M4: EffectShots.FxJobs (01_chien_dau/Vu_khi); Builds/effect_shots/boss_howitzer/
A5: boss_rockets | B5: vu_khi | C5: boss_rockets | D5: 3 | E5: 122 | F5: 1 | G5: FALSE | H5: rocket_pod | I5: Builds/effect_shots/boss_rockets/ | J5: 8 | K5: 0 | L5: pending | M5: EffectShots.FxJobs (01_chien_dau/Vu_khi); Builds/effect_shots/boss_rockets/
A6: boss_thermo | B6: vu_khi | C6: boss_thermo | D6: 3 | E6: 125 | F6: 1 | G6: FALSE | H6: behemoth_inferno | I6: Builds/effect_shots/boss_thermo/ | J6: 8 | K6: 0 | L6: pending | M6: EffectShots.FxJobs (01_chien_dau/Vu_khi); Builds/effect_shots/boss_thermo/
A7: casemate_155 | B7: vu_khi | C7: casemate_155 | D7: 3 | E7: 155 | F7: 1 | G7: FALSE | H7: casemate_155 | I7: Builds/effect_shots/casemate_155/ | J7: 8 | K7: 0 | L7: pending | M7: EffectShots.FxJobs (01_chien_dau/Vu_khi); Builds/effect_shots/casemate_155/
A8: cruiser_203 | B8: vu_khi | C8: cruiser_203 | D8: 4 | E8: 203 | F8: 2 | G8: TRUE | H8: sea_cruiser | I8: Builds/effect_shots/cruiser_203/ | J8: 10 | K8: 0 | L8: pending | M8: EffectShots.FxJobs (01_chien_dau/Vu_khi); Builds/effect_shots/cruiser_203/
A9: grad_cluster | B9: vu_khi | C9: grad_cluster | D9: 3 | E9: 122 | F9: 1 | G9: FALSE | H9: elite_grad | I9: Builds/effect_shots/grad_cluster/ | J9: 8 | K9: 0 | L9: pending | M9: EffectShots.FxJobs (01_chien_dau/Vu_khi); Builds/effect_shots/grad_cluster/
A10: gun_105_apfsds | B10: vu_khi | C10: gun_105_apfsds | D10: 3 | E10: 125 | F10: 1 | G10: FALSE | H10: elite_tank_destroyer | I10: Builds/effect_shots/gun_105_apfsds/ | J10: 8 | K10: 0 | L10: pending | M10: EffectShots.FxJobs (01_chien_dau/Vu_khi); Builds/effect_shots/gun_105_apfsds/
A11: gun_105_long | B11: vu_khi | C11: gun_105_long | D11: 3 | E11: 125 | F11: 1 | G11: FALSE | H11: tank_destroyer | I11: Builds/effect_shots/gun_105_long/ | J11: 8 | K11: 0 | L11: pending | M11: EffectShots.FxJobs (01_chien_dau/Vu_khi); Builds/effect_shots/gun_105_long/
A12: gun_105_wheeled | B12: vu_khi | C12: gun_105_wheeled | D12: 3 | E12: 120 | F12: 1 | G12: FALSE | H12: wheeled_gun | I12: Builds/effect_shots/gun_105_wheeled/ | J12: 8 | K12: 0 | L12: pending | M12: EffectShots.FxJobs (01_chien_dau/Vu_khi); Builds/effect_shots/gun_105_wheeled/
A13: gun_120_twin | B13: vu_khi | C13: gun_120_twin | D13: 3 | E13: 120 | F13: 1 | G13: FALSE | H13: twin_tank | I13: Builds/effect_shots/gun_120_twin/ | J13: 8 | K13: 0 | L13: pending | M13: EffectShots.FxJobs (01_chien_dau/Vu_khi); Builds/effect_shots/gun_120_twin/
... A59: thermobaric_rockets | B59: vu_khi | C59: thermobaric_rockets | D59: 4 | E59: 220 | F59: 1 | G59: FALSE | H59: thermobaric_launcher | I59: Builds/effect_shots/thermobaric_rockets/ | J59: 8 | K59: 0 | L59: pending | M59: EffectShots.FxJobs (01_chien_dau/Vu_khi); Builds/effect_shots/thermobaric_rockets/
A60: tier_T0 | B60: bac | D60: 0 | I60: Builds/effect_shots/tier_T0/ | J60: 8 | K60: 0 | L60: pending | M60: EffectShots.FxJobs (01_chien_dau/Vu_khi); Builds/effect_shots/tier_T0/
A61: tier_T1 | B61: bac | D61: 1 | I61: Builds/effect_shots/tier_T1/ | J61: 8 | K61: 0 | L61: pending | M61: EffectShots.FxJobs (01_chien_dau/Vu_khi); Builds/effect_shots/tier_T1/
A62: tier_T2 | B62: bac | D62: 2 | I62: Builds/effect_shots/tier_T2/ | J62: 8 | K62: 0 | L62: pending | M62: EffectShots.FxJobs (01_chien_dau/Vu_khi); Builds/effect_shots/tier_T2/
A63: tier_T3 | B63: bac | D63: 3 | I63: Builds/effect_shots/tier_T3/ | J63: 8 | K63: 0 | L63: pending | M63: EffectShots.FxJobs (01_chien_dau/Vu_khi); Builds/effect_shots/tier_T3/
A64: tier_T4 | B64: bac | D64: 4 | I64: Builds/effect_shots/tier_T4/ | J64: 8 | K64: 0 | L64: pending | M64: EffectShots.FxJobs (01_chien_dau/Vu_khi); Builds/effect_shots/tier_T4/
A65: tier_T5 | B65: bac | D65: 5 | I65: Builds/effect_shots/tier_T5/ | J65: 8 | K65: 0 | L65: pending | M65: EffectShots.FxJobs (01_chien_dau/Vu_khi); Builds/effect_shots/tier_T5/
A66: train_gun | B66: vu_khi | C66: train_gun | D66: 3 | E66: 152 | F66: 1 | G66: FALSE | H66: armored_train | I66: Builds/effect_shots/train_gun/ | J66: 8 | K66: 0 | L66: pending | M66: EffectShots.FxJobs (01_chien_dau/Vu_khi); Builds/effect_shots/train_gun/
A67: turret_gmlrs | B67: vu_khi | C67: turret_gmlrs | D67: 4 | E67: 227 | F67: 1 | G67: FALSE | H67: rocket_turret.guided | I67: Builds/effect_shots/turret_gmlrs/ | J67: 8 | K67: 0 | L67: pending | M67: EffectShots.FxJobs (01_chien_dau/Vu_khi); Builds/effect_shots/turret_gmlrs/
A68: turret_gun_120 | B68: vu_khi | C68: turret_gun_120 | D68: 3 | E68: 120 | F68: 1 | G68: FALSE | H68: gun_turret | I68: Builds/effect_shots/turret_gun_120/ | J68: 8 | K68: 0 | L68: pending | M68: EffectShots.FxJobs (01_chien_dau/Vu_khi); Builds/effect_shots/turret_gun_120/
A69: turret_gun_120_long | B69: vu_khi | C69: turret_gun_120_long | D69: 3 | E69: 120 | F69: 1 | G69: FALSE | H69: gun_turret.long;headquarters.fortress_ground | I69: Builds/effect_shots/turret_gun_120_long/ | J69: 8 | K69: 0 | L69: pending | M69: EffectShots.FxJobs (01_chien_dau/Vu_khi); Builds/effect_shots/turret_gun_120_long/
A70: turret_rockets | B70: vu_khi | C70: turret_rockets | D70: 3 | E70: 122 | F70: 1 | G70: FALSE | H70: rocket_turret | I70: Builds/effect_shots/turret_rockets/ | J70: 8 | K70: 0 | L70: pending | M70: EffectShots.FxJobs (01_chien_dau/Vu_khi); Builds/effect_shots/turret_rockets/
A71: turret_rockets_cluster | B71: vu_khi | C71: turret_rockets_cluster | D71: 3 | E71: 122 | F71: 1 | G71: FALSE | H71: rocket_turret.cluster | I71: Builds/effect_shots/turret_rockets_cluster/ | J71: 8 | K71: 0 | L71: pending | M71: EffectShots.FxJobs (01_chien_dau/Vu_khi); Builds/effect_shots/turret_rockets_cluster/

Sheet VFX_vu_khi_anh
A1: id | B1: vfx_vu_khi_id | C1: thu_tu | D1: khung | E1: thoi_diem_s | F1: duong_dan | G1: trang_thai | H1: nguon | I1: raw_json
A2: amos_120/fire_0.2s.png | B2: amos_120 | C2: 1 | D2: fire | E2: 0.2 | F2: Builds/effect_shots/amos_120/fire_0.2s.png | G2: pending | H2: Builds/effect_shots/amos_120/fire_0.2s.png
A3: amos_120/fire_0s.png | B3: amos_120 | C3: 0 | D3: fire | E3: 0 | F3: Builds/effect_shots/amos_120/fire_0s.png | G3: pending | H3: Builds/effect_shots/amos_120/fire_0s.png
A4: amos_120/fire_1s.png | B4: amos_120 | C4: 2 | D4: fire | E4: 1 | F4: Builds/effect_shots/amos_120/fire_1s.png | G4: pending | H4: Builds/effect_shots/amos_120/fire_1s.png
A5: amos_120/impact_0.5s.png | B5: amos_120 | C5: 4 | D5: impact | E5: 0.5 | F5: Builds/effect_shots/amos_120/impact_0.5s.png | G5: pending | H5: Builds/effect_shots/amos_120/impact_0.5s.png
A6: amos_120/impact_0s.png | B6: amos_120 | C6: 3 | D6: impact | E6: 0 | F6: Builds/effect_shots/amos_120/impact_0s.png | G6: pending | H6: Builds/effect_shots/amos_120/impact_0s.png
A7: amos_120/impact_2s.png | B7: amos_120 | C7: 5 | D7: impact | E7: 2 | F7: Builds/effect_shots/amos_120/impact_2s.png | G7: pending | H7: Builds/effect_shots/amos_120/impact_2s.png
A8: amos_120/impact_10s.png | B8: amos_120 | C8: 6 | D8: impact | E8: 10 | F8: Builds/effect_shots/amos_120/impact_10s.png | G8: pending | H8: Builds/effect_shots/amos_120/impact_10s.png
A9: amos_120/impact_30s.png | B9: amos_120 | C9: 7 | D9: impact | E9: 30 | F9: Builds/effect_shots/amos_120/impact_30s.png | G9: pending | H9: Builds/effect_shots/amos_120/impact_30s.png
A10: bastion_gun/fire_0.2s.png | B10: bastion_gun | C10: 1 | D10: fire | E10: 0.2 | F10: Builds/effect_shots/bastion_gun/fire_0.2s.png | G10: pending | H10: Builds/effect_shots/bastion_gun/fire_0.2s.png
A11: bastion_gun/fire_0s.png | B11: bastion_gun | C11: 0 | D11: fire | E11: 0 | F11: Builds/effect_shots/bastion_gun/fire_0s.png | G11: pending | H11: Builds/effect_shots/bastion_gun/fire_0s.png
A12: bastion_gun/fire_1s.png | B12: bastion_gun | C12: 2 | D12: fire | E12: 1 | F12: Builds/effect_shots/bastion_gun/fire_1s.png | G12: pending | H12: Builds/effect_shots/bastion_gun/fire_1s.png
A13: bastion_gun/impact_0.5s.png | B13: bastion_gun | C13: 4 | D13: impact | E13: 0.5 | F13: Builds/effect_shots/bastion_gun/impact_0.5s.png | G13: pending | H13: Builds/effect_shots/bastion_gun/impact_0.5s.png
... A17: bastion_gun/impact_30s.png | B17: bastion_gun | C17: 7 | D17: impact | E17: 30 | F17: Builds/effect_shots/bastion_gun/impact_30s.png | G17: pending | H17: Builds/effect_shots/bastion_gun/impact_30s.png
A18: bastion_gun/salvo.png | B18: bastion_gun | C18: 8 | D18: salvo | F18: Builds/effect_shots/bastion_gun/salvo.png | G18: pending | H18: Builds/effect_shots/bastion_gun/salvo.png
A19: bastion_gun/salvo_impact.png | B19: bastion_gun | C19: 9 | D19: salvo_impact | E19: 0.5 | F19: Builds/effect_shots/bastion_gun/salvo_impact.png | G19: pending | H19: Builds/effect_shots/bastion_gun/salvo_impact.png
A20: boss_howitzer/fire_0.2s.png | B20: boss_howitzer | C20: 1 | D20: fire | E20: 0.2 | F20: Builds/effect_shots/boss_howitzer/fire_0.2s.png | G20: pending | H20: Builds/effect_shots/boss_howitzer/fire_0.2s.png
A21: boss_howitzer/fire_0s.png | B21: boss_howitzer | C21: 0 | D21: fire | E21: 0 | F21: Builds/effect_shots/boss_howitzer/fire_0s.png | G21: pending | H21: Builds/effect_shots/boss_howitzer/fire_0s.png
A22: boss_howitzer/fire_1s.png | B22: boss_howitzer | C22: 2 | D22: fire | E22: 1 | F22: Builds/effect_shots/boss_howitzer/fire_1s.png | G22: pending | H22: Builds/effect_shots/boss_howitzer/fire_1s.png
A23: boss_howitzer/impact_0.5s.png | B23: boss_howitzer | C23: 4 | D23: impact | E23: 0.5 | F23: Builds/effect_shots/boss_howitzer/impact_0.5s.png | G23: pending | H23: Builds/effect_shots/boss_howitzer/impact_0.5s.png
A24: boss_howitzer/impact_0s.png | B24: boss_howitzer | C24: 3 | D24: impact | E24: 0 | F24: Builds/effect_shots/boss_howitzer/impact_0s.png | G24: pending | H24: Builds/effect_shots/boss_howitzer/impact_0s.png
A25: boss_howitzer/impact_2s.png | B25: boss_howitzer | C25: 5 | D25: impact | E25: 2 | F25: Builds/effect_shots/boss_howitzer/impact_2s.png | G25: pending | H25: Builds/effect_shots/boss_howitzer/impact_2s.png
A26: boss_howitzer/impact_10s.png | B26: boss_howitzer | C26: 6 | D26: impact | E26: 10 | F26: Builds/effect_shots/boss_howitzer/impact_10s.png | G26: pending | H26: Builds/effect_shots/boss_howitzer/impact_10s.png
A27: boss_howitzer/impact_30s.png | B27: boss_howitzer | C27: 7 | D27: impact | E27: 30 | F27: Builds/effect_shots/boss_howitzer/impact_30s.png | G27: pending | H27: Builds/effect_shots/boss_howitzer/impact_30s.png
A28: boss_rockets/fire_0.2s.png | B28: boss_rockets | C28: 1 | D28: fire | E28: 0.2 | F28: Builds/effect_shots/boss_rockets/fire_0.2s.png | G28: pending | H28: Builds/effect_shots/boss_rockets/fire_0.2s.png
A29: boss_rockets/fire_0s.png | B29: boss_rockets | C29: 0 | D29: fire | E29: 0 | F29: Builds/effect_shots/boss_rockets/fire_0s.png | G29: pending | H29: Builds/effect_shots/boss_rockets/fire_0s.png
A30: boss_rockets/fire_1s.png | B30: boss_rockets | C30: 2 | D30: fire | E30: 1 | F30: Builds/effect_shots/boss_rockets/fire_1s.png | G30: pending | H30: Builds/effect_shots/boss_rockets/fire_1s.png
... A59: cruiser_203/impact_30s.png | B59: cruiser_203 | C59: 7 | D59: impact | E59: 30 | F59: Builds/effect_shots/cruiser_203/impact_30s.png | G59: pending | H59: Builds/effect_shots/cruiser_203/impact_30s.png
A60: cruiser_203/salvo.png | B60: cruiser_203 | C60: 8 | D60: salvo | F60: Builds/effect_shots/cruiser_203/salvo.png | G60: pending | H60: Builds/effect_shots/cruiser_203/salvo.png
A61: cruiser_203/salvo_impact.png | B61: cruiser_203 | C61: 9 | D61: salvo_impact | E61: 0.5 | F61: Builds/effect_shots/cruiser_203/salvo_impact.png | G61: pending | H61: Builds/effect_shots/cruiser_203/salvo_impact.png
A62: grad_cluster/fire_0.2s.png | B62: grad_cluster | C62: 1 | D62: fire | E62: 0.2 | F62: Builds/effect_shots/grad_cluster/fire_0.2s.png | G62: pending | H62: Builds/effect_shots/grad_cluster/fire_0.2s.png
A63: grad_cluster/fire_0s.png | B63: grad_cluster | C63: 0 | D63: fire | E63: 0 | F63: Builds/effect_shots/grad_cluster/fire_0s.png | G63: pending | H63: Builds/effect_shots/grad_cluster/fire_0s.png
A64: grad_cluster/fire_1s.png | B64: grad_cluster | C64: 2 | D64: fire | E64: 1 | F64: Builds/effect_shots/grad_cluster/fire_1s.png | G64: pending | H64: Builds/effect_shots/grad_cluster/fire_1s.png
A65: grad_cluster/impact_0.5s.png | B65: grad_cluster | C65: 4 | D65: impact | E65: 0.5 | F65: Builds/effect_shots/grad_cluster/impact_0.5s.png | G65: pending | H65: Builds/effect_shots/grad_cluster/impact_0.5s.png
A66: grad_cluster/impact_0s.png | B66: grad_cluster | C66: 3 | D66: impact | E66: 0 | F66: Builds/effect_shots/grad_cluster/impact_0s.png | G66: pending | H66: Builds/effect_shots/grad_cluster/impact_0s.png
A67: grad_cluster/impact_2s.png | B67: grad_cluster | C67: 5 | D67: impact | E67: 2 | F67: Builds/effect_shots/grad_cluster/impact_2s.png | G67: pending | H67: Builds/effect_shots/grad_cluster/impact_2s.png
A68: grad_cluster/impact_10s.png | B68: grad_cluster | C68: 6 | D68: impact | E68: 10 | F68: Builds/effect_shots/grad_cluster/impact_10s.png | G68: pending | H68: Builds/effect_shots/grad_cluster/impact_10s.png
A69: grad_cluster/impact_30s.png | B69: grad_cluster | C69: 7 | D69: impact | E69: 30 | F69: Builds/effect_shots/grad_cluster/impact_30s.png | G69: pending | H69: Builds/effect_shots/grad_cluster/impact_30s.png
A70: gun_105_apfsds/fire_0.2s.png | B70: gun_105_apfsds | C70: 1 | D70: fire | E70: 0.2 | F70: Builds/effect_shots/gun_105_apfsds/fire_0.2s.png | G70: pending | H70: Builds/effect_shots/gun_105_apfsds/fire_0.2s.png
A71: gun_105_apfsds/fire_0s.png | B71: gun_105_apfsds | C71: 0 | D71: fire | E71: 0 | F71: Builds/effect_shots/gun_105_apfsds/fire_0s.png | G71: pending | H71: Builds/effect_shots/gun_105_apfsds/fire_0s.png
A72: gun_105_apfsds/fire_1s.png | B72: gun_105_apfsds | C72: 2 | D72: fire | E72: 1 | F72: Builds/effect_shots/gun_105_apfsds/fire_1s.png | G72: pending | H72: Builds/effect_shots/gun_105_apfsds/fire_1s.png
... A133: gun_140_twin/impact_30s.png | B133: gun_140_twin | C133: 7 | D133: impact | E133: 30 | F133: Builds/effect_shots/gun_140_twin/impact_30s.png | G133: pending | H133: Builds/effect_shots/gun_140_twin/impact_30s.png
A134: gun_140_twin/salvo.png | B134: gun_140_twin | C134: 8 | D134: salvo | F134: Builds/effect_shots/gun_140_twin/salvo.png | G134: pending | H134: Builds/effect_shots/gun_140_twin/salvo.png
A135: gun_140_twin/salvo_impact.png | B135: gun_140_twin | C135: 9 | D135: salvo_impact | E135: 0.5 | F135: Builds/effect_shots/gun_140_twin/salvo_impact.png | G135: pending | H135: Builds/effect_shots/gun_140_twin/salvo_impact.png
A136: gun_152/fire_0.2s.png | B136: gun_152 | C136: 1 | D136: fire | E136: 0.2 | F136: Builds/effect_shots/gun_152/fire_0.2s.png | G136: pending | H136: Builds/effect_shots/gun_152/fire_0.2s.png
A137: gun_152/fire_0s.png | B137: gun_152 | C137: 0 | D137: fire | E137: 0 | F137: Builds/effect_shots/gun_152/fire_0s.png | G137: pending | H137: Builds/effect_shots/gun_152/fire_0s.png
A138: gun_152/fire_1s.png | B138: gun_152 | C138: 2 | D138: fire | E138: 1 | F138: Builds/effect_shots/gun_152/fire_1s.png | G138: pending | H138: Builds/effect_shots/gun_152/fire_1s.png
A139: gun_152/impact_0.5s.png | B139: gun_152 | C139: 4 | D139: impact | E139: 0.5 | F139: Builds/effect_shots/gun_152/impact_0.5s.png | G139: pending | H139: Builds/effect_shots/gun_152/impact_0.5s.png
A140: gun_152/impact_0s.png | B140: gun_152 | C140: 3 | D140: impact | E140: 0 | F140: Builds/effect_shots/gun_152/impact_0s.png | G140: pending | H140: Builds/effect_shots/gun_152/impact_0s.png
A141: gun_152/impact_2s.png | B141: gun_152 | C141: 5 | D141: impact | E141: 2 | F141: Builds/effect_shots/gun_152/impact_2s.png | G141: pending | H141: Builds/effect_shots/gun_152/impact_2s.png
A142: gun_152/impact_10s.png | B142: gun_152 | C142: 6 | D142: impact | E142: 10 | F142: Builds/effect_shots/gun_152/impact_10s.png | G142: pending | H142: Builds/effect_shots/gun_152/impact_10s.png
A143: gun_152/impact_30s.png | B143: gun_152 | C143: 7 | D143: impact | E143: 30 | F143: Builds/effect_shots/gun_152/impact_30s.png | G143: pending | H143: Builds/effect_shots/gun_152/impact_30s.png
A144: gun_152_he/fire_0.2s.png | B144: gun_152_he | C144: 1 | D144: fire | E144: 0.2 | F144: Builds/effect_shots/gun_152_he/fire_0.2s.png | G144: pending | H144: Builds/effect_shots/gun_152_he/fire_0.2s.png
A145: gun_152_he/fire_0s.png | B145: gun_152_he | C145: 0 | D145: fire | E145: 0 | F145: Builds/effect_shots/gun_152_he/fire_0s.png | G145: pending | H145: Builds/effect_shots/gun_152_he/fire_0s.png
A146: gun_152_he/fire_1s.png | B146: gun_152_he | C146: 2 | D146: fire | E146: 1 | F146: Builds/effect_shots/gun_152_he/fire_1s.png | G146: pending | H146: Builds/effect_shots/gun_152_he/fire_1s.png
... A175: gun_155_twin_ap/impact_30s.png | B175: gun_155_twin_ap | C175: 7 | D175: impact | E175: 30 | F175: Builds/effect_shots/gun_155_twin_ap/impact_30s.png | G175: pending | H175: Builds/effect_shots/gun_155_twin_ap/impact_30s.png
A176: gun_155_twin_ap/salvo.png | B176: gun_155_twin_ap | C176: 8 | D176: salvo | F176: Builds/effect_shots/gun_155_twin_ap/salvo.png | G176: pending | H176: Builds/effect_shots/gun_155_twin_ap/salvo.png
A177: gun_155_twin_ap/salvo_impact.png | B177: gun_155_twin_ap | C177: 9 | D177: salvo_impact | E177: 0.5 | F177: Builds/effect_shots/gun_155_twin_ap/salvo_impact.png | G177: pending | H177: Builds/effect_shots/gun_155_twin_ap/salvo_impact.png
A178: gun_155_twin_coastlr/fire_0.2s.png | B178: gun_155_twin_coastlr | C178: 1 | D178: fire | E178: 0.2 | F178: Builds/effect_shots/gun_155_twin_coastlr/fire_0.2s.png | G178: pending | H178: Builds/effect_shots/gun_155_twin_coastlr/fire_0.2s.png
A179: gun_155_twin_coastlr/fire_0s.png | B179: gun_155_twin_coastlr | C179: 0 | D179: fire | E179: 0 | F179: Builds/effect_shots/gun_155_twin_coastlr/fire_0s.png | G179: pending | H179: Builds/effect_shots/gun_155_twin_coastlr/fire_0s.png
A180: gun_155_twin_coastlr/fire_1s.png | B180: gun_155_twin_coastlr | C180: 2 | D180: fire | E180: 1 | F180: Builds/effect_shots/gun_155_twin_coastlr/fire_1s.png | G180: pending | H180: Builds/effect_shots/gun_155_twin_coastlr/fire_1s.png
A181: gun_155_twin_coastlr/impact_0.5s.png | B181: gun_155_twin_coastlr | C181: 4 | D181: impact | E181: 0.5 | F181: Builds/effect_shots/gun_155_twin_coastlr/impact_0.5s.png | G181: pending | H181: Builds/effect_shots/gun_155_twin_coastlr/impact_0.5s.png
A182: gun_155_twin_coastlr/impact_0s.png | B182: gun_155_twin_coastlr | C182: 3 | D182: impact | E182: 0 | F182: Builds/effect_shots/gun_155_twin_coastlr/impact_0s.png | G182: pending | H182: Builds/effect_shots/gun_155_twin_coastlr/impact_0s.png
A183: gun_155_twin_coastlr/impact_2s.png | B183: gun_155_twin_coastlr | C183: 5 | D183: impact | E183: 2 | F183: Builds/effect_shots/gun_155_twin_coastlr/impact_2s.png | G183: pending | H183: Builds/effect_shots/gun_155_twin_coastlr/impact_2s.png
A184: gun_155_twin_coastlr/impact_10s.png | B184: gun_155_twin_coastlr | C184: 6 | D184: impact | E184: 10 | F184: Builds/effect_shots/gun_155_twin_coastlr/impact_10s.png | G184: pending | H184: Builds/effect_shots/gun_155_twin_coastlr/impact_10s.png
A185: gun_155_twin_coastlr/impact_30s.png | B185: gun_155_twin_coastlr | C185: 7 | D185: impact | E185: 30 | F185: Builds/effect_shots/gun_155_twin_coastlr/impact_30s.png | G185: pending | H185: Builds/effect_shots/gun_155_twin_coastlr/impact_30s.png
A186: gun_155_twin_coastlr/salvo.png | B186: gun_155_twin_coastlr | C186: 8 | D186: salvo | F186: Builds/effect_shots/gun_155_twin_coastlr/salvo.png | G186: pending | H186: Builds/effect_shots/gun_155_twin_coastlr/salvo.png
A187: gun_155_twin_coastlr/salvo_impact.png | B187: gun_155_twin_coastlr | C187: 9 | D187: salvo_impact | E187: 0.5 | F187: Builds/effect_shots/gun_155_twin_coastlr/salvo_impact.png | G187: pending | H187: Builds/effect_shots/gun_155_twin_coastlr/salvo_impact.png
A188: gun_behemoth/fire_0.2s.png | B188: gun_behemoth | C188: 1 | D188: fire | E188: 0.2 | F188: Builds/effect_shots/gun_behemoth/fire_0.2s.png | G188: pending | H188: Builds/effect_shots/gun_behemoth/fire_0.2s.png
A189: gun_behemoth/fire_0s.png | B189: gun_behemoth | C189: 0 | D189: fire | E189: 0 | F189: Builds/effect_shots/gun_behemoth/fire_0s.png | G189: pending | H189: Builds/effect_shots/gun_behemoth/fire_0s.png
A190: gun_behemoth/fire_1s.png | B190: gun_behemoth | C190: 2 | D190: fire | E190: 1 | F190: Builds/effect_shots/gun_behemoth/fire_1s.png | G190: pending | H190: Builds/effect_shots/gun_behemoth/fire_1s.png
A191: gun_behemoth/impact_0.5s.png | B191: gun_behemoth | C191: 4 | D191: impact | E191: 0.5 | F191: Builds/effect_shots/gun_behemoth/impact_0.5s.png | G191: pending | H191: Builds/effect_shots/gun_behemoth/impact_0.5s.png
A192: gun_behemoth/impact_0s.png | B192: gun_behemoth | C192: 3 | D192: impact | E192: 0 | F192: Builds/effect_shots/gun_behemoth/impact_0s.png | G192: pending | H192: Builds/effect_shots/gun_behemoth/impact_0s.png
A193: gun_behemoth/impact_2s.png | B193: gun_behemoth | C193: 5 | D193: impact | E193: 2 | F193: Builds/effect_shots/gun_behemoth/impact_2s.png | G193: pending | H193: Builds/effect_shots/gun_behemoth/impact_2s.png
A194: gun_behemoth/impact_10s.png | B194: gun_behemoth | C194: 6 | D194: impact | E194: 10 | F194: Builds/effect_shots/gun_behemoth/impact_10s.png | G194: pending | H194: Builds/effect_shots/gun_behemoth/impact_10s.png
A195: gun_behemoth/impact_30s.png | B195: gun_behemoth | C195: 7 | D195: impact | E195: 30 | F195: Builds/effect_shots/gun_behemoth/impact_30s.png | G195: pending | H195: Builds/effect_shots/gun_behemoth/impact_30s.png
A196: hover_rockets/fire_0.2s.png | B196: hover_rockets | C196: 1 | D196: fire | E196: 0.2 | F196: Builds/effect_shots/hover_rockets/fire_0.2s.png | G196: pending | H196: Builds/effect_shots/hover_rockets/fire_0.2s.png
A197: hover_rockets/fire_0s.png | B197: hover_rockets | C197: 0 | D197: fire | E197: 0 | F197: Builds/effect_shots/hover_rockets/fire_0s.png | G197: pending | H197: Builds/effect_shots/hover_rockets/fire_0s.png
A198: hover_rockets/fire_1s.png | B198: hover_rockets | C198: 2 | D198: fire | E198: 1 | F198: Builds/effect_shots/hover_rockets/fire_1s.png | G198: pending | H198: Builds/effect_shots/hover_rockets/fire_1s.png
... A251: naval_130_twin/impact_30s.png | B251: naval_130_twin | C251: 7 | D251: impact | E251: 30 | F251: Builds/effect_shots/naval_130_twin/impact_30s.png | G251: pending | H251: Builds/effect_shots/naval_130_twin/impact_30s.png
A252: naval_130_twin/salvo.png | B252: naval_130_twin | C252: 8 | D252: salvo | F252: Builds/effect_shots/naval_130_twin/salvo.png | G252: pending | H252: Builds/effect_shots/naval_130_twin/salvo.png
A253: naval_130_twin/salvo_impact.png | B253: naval_130_twin | C253: 9 | D253: salvo_impact | E253: 0.5 | F253: Builds/effect_shots/naval_130_twin/salvo_impact.png | G253: pending | H253: Builds/effect_shots/naval_130_twin/salvo_impact.png
A254: nyx_ags_155/fire_0.2s.png | B254: nyx_ags_155 | C254: 1 | D254: fire | E254: 0.2 | F254: Builds/effect_shots/nyx_ags_155/fire_0.2s.png | G254: pending | H254: Builds/effect_shots/nyx_ags_155/fire_0.2s.png
A255: nyx_ags_155/fire_0s.png | B255: nyx_ags_155 | C255: 0 | D255: fire | E255: 0 | F255: Builds/effect_shots/nyx_ags_155/fire_0s.png | G255: pending | H255: Builds/effect_shots/nyx_ags_155/fire_0s.png
A256: nyx_ags_155/fire_1s.png | B256: nyx_ags_155 | C256: 2 | D256: fire | E256: 1 | F256: Builds/effect_shots/nyx_ags_155/fire_1s.png | G256: pending | H256: Builds/effect_shots/nyx_ags_155/fire_1s.png
A257: nyx_ags_155/impact_0.5s.png | B257: nyx_ags_155 | C257: 4 | D257: impact | E257: 0.5 | F257: Builds/effect_shots/nyx_ags_155/impact_0.5s.png | G257: pending | H257: Builds/effect_shots/nyx_ags_155/impact_0.5s.png
A258: nyx_ags_155/impact_0s.png | B258: nyx_ags_155 | C258: 3 | D258: impact | E258: 0 | F258: Builds/effect_shots/nyx_ags_155/impact_0s.png | G258: pending | H258: Builds/effect_shots/nyx_ags_155/impact_0s.png
A259: nyx_ags_155/impact_2s.png | B259: nyx_ags_155 | C259: 5 | D259: impact | E259: 2 | F259: Builds/effect_shots/nyx_ags_155/impact_2s.png | G259: pending | H259: Builds/effect_shots/nyx_ags_155/impact_2s.png
A260: nyx_ags_155/impact_10s.png | B260: nyx_ags_155 | C260: 6 | D260: impact | E260: 10 | F260: Builds/effect_shots/nyx_ags_155/impact_10s.png | G260: pending | H260: Builds/effect_shots/nyx_ags_155/impact_10s.png
A261: nyx_ags_155/impact_30s.png | B261: nyx_ags_155 | C261: 7 | D261: impact | E261: 30 | F261: Builds/effect_shots/nyx_ags_155/impact_30s.png | G261: pending | H261: Builds/effect_shots/nyx_ags_155/impact_30s.png
A262: p26_bastion_main_b155/fire_0.2s.png | B262: p26_bastion_main_b155 | C262: 1 | D262: fire | E262: 0.2 | F262: Builds/effect_shots/p26_bastion_main_b155/fire_0.2s.png | G262: pending | H262: Builds/effect_shots/p26_bastion_main_b155/fire_0.2s.png
A263: p26_bastion_main_b155/fire_0s.png | B263: p26_bastion_main_b155 | C263: 0 | D263: fire | E263: 0 | F263: Builds/effect_shots/p26_bastion_main_b155/fire_0s.png | G263: pending | H263: Builds/effect_shots/p26_bastion_main_b155/fire_0s.png
A264: p26_bastion_main_b155/fire_1s.png | B264: p26_bastion_main_b155 | C264: 2 | D264: fire | E264: 1 | F264: Builds/effect_shots/p26_bastion_main_b155/fire_1s.png | G264: pending | H264: Builds/effect_shots/p26_bastion_main_b155/fire_1s.png
... A285: p26_behemoth_direct_be120/impact_30s.png | B285: p26_behemoth_direct_be120 | C285: 7 | D285: impact | E285: 30 | F285: Builds/effect_shots/p26_behemoth_direct_be120/impact_30s.png | G285: pending | H285: Builds/effect_shots/p26_behemoth_direct_be120/impact_30s.png
A286: p26_behemoth_direct_be120/salvo.png | B286: p26_behemoth_direct_be120 | C286: 8 | D286: salvo | F286: Builds/effect_shots/p26_behemoth_direct_be120/salvo.png | G286: pending | H286: Builds/effect_shots/p26_behemoth_direct_be120/salvo.png
A287: p26_behemoth_direct_be120/salvo_impact.png | B287: p26_behemoth_direct_be120 | C287: 9 | D287: salvo_impact | E287: 0.5 | F287: Builds/effect_shots/p26_behemoth_direct_be120/salvo_impact.png | G287: pending | H287: Builds/effect_shots/p26_behemoth_direct_be120/salvo_impact.png
A288: p26_behemoth_main_be152/fire_0.2s.png | B288: p26_behemoth_main_be152 | C288: 1 | D288: fire | E288: 0.2 | F288: Builds/effect_shots/p26_behemoth_main_be152/fire_0.2s.png | G288: pending | H288: Builds/effect_shots/p26_behemoth_main_be152/fire_0.2s.png
A289: p26_behemoth_main_be152/fire_0s.png | B289: p26_behemoth_main_be152 | C289: 0 | D289: fire | E289: 0 | F289: Builds/effect_shots/p26_behemoth_main_be152/fire_0s.png | G289: pending | H289: Builds/effect_shots/p26_behemoth_main_be152/fire_0s.png
A290: p26_behemoth_main_be152/fire_1s.png | B290: p26_behemoth_main_be152 | C290: 2 | D290: fire | E290: 1 | F290: Builds/effect_shots/p26_behemoth_main_be152/fire_1s.png | G290: pending | H290: Builds/effect_shots/p26_behemoth_main_be152/fire_1s.png
A291: p26_behemoth_main_be152/impact_0.5s.png | B291: p26_behemoth_main_be152 | C291: 4 | D291: impact | E291: 0.5 | F291: Builds/effect_shots/p26_behemoth_main_be152/impact_0.5s.png | G291: pending | H291: Builds/effect_shots/p26_behemoth_main_be152/impact_0.5s.png
...

Sheet Am_thanh_so_do
A1: id | B1: do_dai_s | C1: lufs | D1: lufs_mmax | E1: dinh_db | F1: dinh_that_db | G1: duoi_150hz_pct | H1: duoi_s | I1: keng_noi_db | J1: keng_tat_s | K1: keng_rong_hz | L1: keng_tan_so_hz | M1: keng_bao_cao | N1: bao_cao_cu | O1: keng | P1: keng_ngoai_giap | Q1: nguon | R1: raw_json
A2: autocannon/autocannon_1 | B2: 0.695 | C2: -21.5 | D2: -18.6 | E2: -0.9 | F2: -0.8 | G2: 44.3 | H2: 0.56 | I2: 4.2 | J2: 0.116 | K2: 517 | L2: 3854 | M2: FALSE | N2: FALSE | O2: =AND($I$2>=12.0,$J$2>=0.12,$K$2<160.0) | P2: =AND($O$2,Am_thanh!$C$10<>"armour_metal") | Q2: Docs/audio/metrics.json: clips["autocannon/autocannon_1.ogg"]
A3: autocannon/autocannon_2 | B3: 0.695 | C3: -15.5 | D3: -14 | E3: -0.9 | F3: -0.9 | G3: 43.9 | H3: 0.46 | I3: 3.9 | J3: 0.035 | K3: 409 | L3: 4328 | M3: FALSE | N3: FALSE | O3: =AND($I$3>=12.0,$J$3>=0.12,$K$3<160.0) | P3: =AND($O$3,Am_thanh!$C$11<>"armour_metal") | Q3: Docs/audio/metrics.json: clips["autocannon/autocannon_2.ogg"]
A4: autocannon/autocannon_3 | B4: 0.682 | C4: -17.1 | D4: -15.4 | E4: -1 | F4: -1 | G4: 49.6 | H4: 0.34 | I4: 4.9 | J4: 0.035 | K4: 280 | L4: 3962 | M4: FALSE | N4: FALSE | O4: =AND($I$4>=12.0,$J$4>=0.12,$K$4<160.0) | P4: =AND($O$4,Am_thanh!$C$12<>"armour_metal") | Q4: Docs/audio/metrics.json: clips["autocannon/autocannon_3.ogg"]
A5: cannon/cannon_1 | B5: 1.5 | C5: -16.7 | D5: -14.5 | E5: -1.6 | F5: -1.6 | G5: 70.3 | H5: 0.82 | I5: 3.4 | J5: 0.081 | K5: 2304 | L5: 2196 | M5: FALSE | N5: FALSE | O5: =AND($I$5>=12.0,$J$5>=0.12,$K$5<160.0) | P5: =AND($O$5,Am_thanh!$C$13<>"armour_metal") | Q5: Docs/audio/metrics.json: clips["cannon/cannon_1.ogg"]
A6: cannon/cannon_2 | B6: 1.5 | C6: -20.6 | D6: -15.6 | E6: -1 | F6: -1 | G6: 53.9 | H6: 1.1 | I6: 2.3 | J6: 0.139 | K6: 2304 | L6: 2046 | M6: FALSE | N6: FALSE | O6: =AND($I$6>=12.0,$J$6>=0.12,$K$6<160.0) | P6: =AND($O$6,Am_thanh!$C$14<>"armour_metal") | Q6: Docs/audio/metrics.json: clips["cannon/cannon_2.ogg"]
A7: cannon/cannon_3 | B7: 1.384 | C7: -22.5 | D7: -16.5 | E7: -0.9 | F7: -0.9 | G7: 45.5 | H7: 1.11 | I7: 0 | J7: 0 | K7: 0 | L7: 0 | M7: FALSE | N7: FALSE | O7: =AND($I$7>=12.0,$J$7>=0.12,$K$7<160.0) | P7: =AND($O$7,Am_thanh!$C$15<>"armour_metal") | Q7: Docs/audio/metrics.json: clips["cannon/cannon_3.ogg"]
A8: click/click_1 | B8: 0.092 | C8: -21 | D8: -21 | E8: -1.7 | F8: -1.3 | G8: 32.5 | H8: 0.03 | I8: 8.1 | J8: 0.035 | K8: 194 | L8: 3187 | M8: FALSE | N8: FALSE | O8: =AND($I$8>=12.0,$J$8>=0.12,$K$8<160.0) | P8: =AND($O$8,Am_thanh!$C$16<>"armour_metal") | Q8: Docs/audio/metrics.json: clips["click/click_1.ogg"]
A9: click/click_2 | B9: 0.065 | C9: -23.8 | D9: -23.8 | E9: -1 | F9: -1 | G9: 1.3 | H9: 0.04 | I9: 0 | J9: 0 | K9: 0 | L9: 0 | M9: FALSE | N9: FALSE | O9: =AND($I$9>=12.0,$J$9>=0.12,$K$9<160.0) | P9: =AND($O$9,Am_thanh!$C$17<>"armour_metal") | Q9: Docs/audio/metrics.json: clips["click/click_2.ogg"]
A10: collapse/collapse_1 | B10: 3.697 | C10: -19.2 | D10: -15.1 | E10: -1 | F10: -0.3 | G10: 89.4 | H10: 1.61 | I10: 4.4 | J10: 0.023 | K10: 345 | L10: 2455 | M10: FALSE | N10: FALSE | O10: =AND($I$10>=12.0,$J$10>=0.12,$K$10<160.0) | P10: =AND($O$10,Am_thanh!$C$18<>"armour_metal") | Q10: Docs/audio/metrics.json: clips["collapse/collapse_1.ogg"]
A11: collapse/collapse_2 | B11: 3.853 | C11: -20.1 | D11: -15.5 | E11: -1 | F11: -1 | G11: 57.5 | H11: 2.57 | I11: 0.4 | J11: 0.116 | K11: 3295 | L11: 2024 | M11: FALSE | N11: FALSE | O11: =AND($I$11>=12.0,$J$11>=0.12,$K$11<160.0) | P11: =AND($O$11,Am_thanh!$C$19<>"armour_metal") | Q11: Docs/audio/metrics.json: clips["collapse/collapse_2.ogg"]
A12: debris/debris_1 | B12: 0.805 | C12: -20.3 | D12: -17.8 | E12: -0.9 | F12: -0.8 | G12: 4.4 | H12: 0.55 | I12: 5.1 | J12: 0.058 | K12: 301 | L12: 3230 | M12: FALSE | N12: FALSE | O12: =AND($I$12>=12.0,$J$12>=0.12,$K$12<160.0) | P12: =AND($O$12,Am_thanh!$C$20<>"armour_metal") | Q12: Docs/audio/metrics.json: clips["debris/debris_1.ogg"]
A13: debris/debris_2 | B13: 0.853 | C13: -20.5 | D13: -16.5 | E13: -1.6 | F13: -1.5 | G13: 1.4 | H13: 0.71 | I13: 3.8 | J13: 0.07 | K13: 4630 | L13: 4565 | M13: FALSE | N13: FALSE | O13: =AND($I$13>=12.0,$J$13>=0.12,$K$13<160.0) | P13: =AND($O$13,Am_thanh!$C$21<>"armour_metal") | Q13: Docs/audio/metrics.json: clips["debris/debris_2.ogg"]
A14: debris/debris_3 | B14: 0.954 | C14: -22 | D14: -18.1 | E14: -1 | F14: -0.9 | G14: 2.5 | H14: 0.88 | I14: 4.5 | J14: 0.07 | K14: 668 | L14: 3252 | M14: FALSE | N14: FALSE | O14: =AND($I$14>=12.0,$J$14>=0.12,$K$14<160.0) | P14: =AND($O$14,Am_thanh!$C$22<>"armour_metal") | Q14: Docs/audio/metrics.json: clips["debris/debris_3.ogg"]
A15: drums_loop/drums_loop_1 | B15: 7.385 | C15: -15.7 | D15: -12.2 | E15: -1 | F15: -1 | G15: 97.9 | H15: 5.27 | I15: 0 | J15: 0 | K15: 0 | L15: 0 | M15: FALSE | N15: FALSE | O15: =AND($I$15>=12.0,$J$15>=0.12,$K$15<160.0) | P15: =AND($O$15,Am_thanh!$C$23<>"armour_metal") | Q15: Docs/audio/metrics.json: clips["drums_loop/drums_loop_1.ogg"]
A16: explosion_huge/explosion_huge_1 | B16: 5 | C16: -16.8 | D16: -13.4 | E16: -1 | F16: -1 | G16: 74.9 | H16: 4.16 | I16: 2.5 | J16: 0.139 | K16: 4608 | L16: 3919 | M16: FALSE | N16: FALSE | O16: =AND($I$16>=12.0,$J$16>=0.12,$K$16<160.0) | P16: =AND($O$16,Am_thanh!$C$24<>"armour_metal") | Q16: Docs/audio/metrics.json: clips["explosion_huge/explosion_huge_1.ogg"]
A17: explosion_huge/explosion_huge_2 | B17: 4.975 | C17: -14.9 | D17: -12.9 | E17: -1 | F17: -1 | G17: 92 | H17: 4.22 | I17: 0 | J17: 0 | K17: 0 | L17: 0 | M17: FALSE | N17: FALSE | O17: =AND($I$17>=12.0,$J$17>=0.12,$K$17<160.0) | P17: =AND($O$17,Am_thanh!$C$25<>"armour_metal") | Q17: Docs/audio/metrics.json: clips["explosion_huge/explosion_huge_2.ogg"]
A18: explosion_huge/explosion_huge_3 | B18: 4.964 | C18: -17.7 | D18: -12.5 | E18: -1.1 | F18: -1.1 | G18: 60.6 | H18: 3.81 | I18: 4.3 | J18: 0.255 | K18: 388 | L18: 3725 | M18: FALSE | N18: FALSE | O18: =AND($I$18>=12.0,$J$18>=0.12,$K$18<160.0) | P18: =AND($O$18,Am_thanh!$C$26<>"armour_metal") | Q18: Docs/audio/metrics.json: clips["explosion_huge/explosion_huge_3.ogg"]
A19: explosion_large/explosion_large_1 | B19: 3 | C19: -18 | D19: -12.5 | E19: -1 | F19: -1 | G19: 52.3 | H19: 2.57 | I19: 2.5 | J19: 0.418 | K19: 3682 | L19: 2885 | M19: FALSE | N19: FALSE | O19: =AND($I$19>=12.0,$J$19>=0.12,$K$19<160.0) | P19: =AND($O$19,Am_thanh!$C$27<>"armour_metal") | Q19: Docs/audio/metrics.json: clips["explosion_large/explosion_large_1.ogg"]
A20: explosion_large/explosion_large_2 | B20: 2.511 | C20: -17.4 | D20: -14 | E20: -1 | F20: -0.9 | G20: 66.3 | H20: 1.77 | I20: 2.7 | J20: 0.464 | K20: 2627 | L20: 2261 | M20: FALSE | N20: FALSE | O20: =AND($I$20>=12.0,$J$20>=0.12,$K$20<160.0) | P20: =AND($O$20,Am_thanh!$C$28<>"armour_metal") | Q20: Docs/audio/metrics.json: clips["explosion_large/explosion_large_2.ogg"]
A21: explosion_large/explosion_large_3 | B21: 3 | C21: -19 | D21: -13.6 | E21: -1 | F21: -0.9 | G21: 53 | H21: 2.3 | I21: 3.1 | J21: 0.116 | K21: 4522 | L21: 3876 | M21: FALSE | N21: FALSE | O21: =AND($I$21>=12.0,$J$21>=0.12,$K$21<160.0) | P21: =AND($O$21,Am_thanh!$C$29<>"armour_metal") | Q21: Docs/audio/metrics.json: clips["explosion_large/explosion_large_3.ogg"]
A22: explosion_large/explosion_large_4 | B22: 2.688 | C22: -17.6 | D22: -13.8 | E22: -1 | F22: -1 | G22: 73.5 | H22: 2.41 | I22: 4.7 | J22: 0.023 | K22: 947 | L22: 3790 | M22: FALSE | N22: FALSE | O22: =AND($I$22>=12.0,$J$22>=0.12,$K$22<160.0) | P22: =AND($O$22,Am_thanh!$C$30<>"armour_metal") | Q22: Docs/audio/metrics.json: clips["explosion_large/explosion_large_4.ogg"]
A23: explosion_medium/explosion_medium_1 | B23: 2 | C23: -18.5 | D23: -12.8 | E23: -0.9 | F23: -0.9 | G23: 33.1 | H23: 1.54 | I23: 1.4 | J23: 0.035 | K23: 2735 | L23: 2239 | M23: FALSE | N23: FALSE | O23: =AND($I$23>=12.0,$J$23>=0.12,$K$23<160.0) | P23: =AND($O$23,Am_thanh!$C$31<>"armour_metal") | Q23: Docs/audio/metrics.json: clips["explosion_medium/explosion_medium_1.ogg"]
A24: explosion_medium/explosion_medium_2 | B24: 1.989 | C24: -17.9 | D24: -13.6 | E24: -0.9 | F24: -0.9 | G24: 70.9 | H24: 1.61 | I24: 5.3 | J24: 0.023 | K24: 151 | L24: 4242 | M24: FALSE | N24: FALSE | O24: =AND($I$24>=12.0,$J$24>=0.12,$K$24<160.0) | P24: =AND($O$24,Am_thanh!$C$32<>"armour_metal") | Q24: Docs/audio/metrics.json: clips["explosion_medium/explosion_medium_2.ogg"]
A25: explosion_medium/explosion_medium_3 | B25: 2 | C25: -17.1 | D25: -11.8 | E25: -0.9 | F25: -0.8 | G25: 46.7 | H25: 1.67 | I25: 3.3 | J25: 0.29 | K25: 3682 | L25: 3273 | M25: FALSE | N25: FALSE | O25: =AND($I$25>=12.0,$J$25>=0.12,$K$25<160.0) | P25: =AND($O$25,Am_thanh!$C$33<>"armour_metal") | Q25: Docs/audio/metrics.json: clips["explosion_medium/explosion_medium_3.ogg"]
A26: explosion_medium/explosion_medium_4 | B26: 1.998 | C26: -15.1 | D26: -11.4 | E26: -1 | F26: -1 | G26: 78 | H26: 1.36 | I26: 3.9 | J26: 0.07 | K26: 323 | L26: 2153 | M26: FALSE | N26: FALSE | O26: =AND($I$26>=12.0,$J$26>=0.12,$K$26<160.0) | P26: =AND($O$26,Am_thanh!$C$34<>"armour_metal") | Q26: Docs/audio/metrics.json: clips["explosion_medium/explosion_medium_4.ogg"]
A27: explosion_small/explosion_small_1 | B27: 0.95 | C27: -17.6 | D27: -14.1 | E27: -1.7 | F27: -1.6 | G27: 51.9 | H27: 0.87 | I27: 4 | J27: 0.058 | K27: 2799 | L27: 2692 | M27: FALSE | N27: FALSE | O27: =AND($I$27>=12.0,$J$27>=0.12,$K$27<160.0) | P27: =AND($O$27,Am_thanh!$C$35<>"armour_metal") | Q27: Docs/audio/metrics.json: clips["explosion_small/explosion_small_1.ogg"]
A28: explosion_small/explosion_small_2 | B28: 0.999 | C28: -17.9 | D28: -15.2 | E28: -0.9 | F28: -0.9 | G28: 88.2 | H28: 0.72 | I28: 0 | J28: 0 | K28: 0 | L28: 0 | M28: FALSE | N28: FALSE | O28: =AND($I$28>=12.0,$J$28>=0.12,$K$28<160.0) | P28: =AND($O$28,Am_thanh!$C$36<>"armour_metal") | Q28: Docs/audio/metrics.json: clips["explosion_small/explosion_small_2.ogg"]
A29: explosion_small/explosion_small_3 | B29: 0.924 | C29: -22.2 | D29: -17.3 | E29: -1 | F29: -1 | G29: 72.8 | H29: 0.71 | I29: 3.4 | J29: 0.139 | K29: 5190 | L29: 4867 | M29: FALSE | N29: FALSE | O29: =AND($I$29>=12.0,$J$29>=0.12,$K$29<160.0) | P29: =AND($O$29,Am_thanh!$C$37<>"armour_metal") | Q29: Docs/audio/metrics.json: clips["explosion_small/explosion_small_3.ogg"]
A30: explosion_small/explosion_small_4 | B30: 0.956 | C30: -22.2 | D30: -17.5 | E30: -1 | F30: -1 | G30: 75.3 | H30: 0.73 | I30: 3.1 | J30: 0.163 | K30: 5168 | L30: 4393 | M30: FALSE | N30: FALSE | O30: =AND($I$30>=12.0,$J$30>=0.12,$K$30<160.0) | P30: =AND($O$30,Am_thanh!$C$38<>"armour_metal") | Q30: Docs/audio/metrics.json: clips["explosion_small/explosion_small_4.ogg"]
A31: fire_loop/fire_loop_1 | B31: 5.5 | C31: -20.9 | D31: -19.5 | E31: -0.9 | F31: -0.6 | G31: 46.7 | H31: 5.01 | I31: 2.6 | J31: 0.174 | K31: 1916 | L31: 3575 | M31: FALSE | N31: FALSE | O31: =AND($I$31>=12.0,$J$31>=0.12,$K$31<160.0) | P31: =AND($O$31,Am_thanh!$C$39<>"armour_metal") | Q31: Docs/audio/metrics.json: clips["fire_loop/fire_loop_1.ogg"]
A32: flak/flak_1 | B32: 0.596 | C32: -19.7 | D32: -19.7 | E32: -0.9 | F32: -0.9 | G32: 73.3 | H32: 0.5 | I32: 0 | J32: 0 | K32: 0 | L32: 0 | M32: FALSE | N32: FALSE | O32: =AND($I$32>=12.0,$J$32>=0.12,$K$32<160.0) | P32: =AND($O$32,Am_thanh!$C$40<>"armour_metal") | Q32: Docs/audio/metrics.json: clips["flak/flak_1.ogg"]
A33: flak/flak_2 | B33: 0.613 | C33: -19.5 | D33: -19.5 | E33: -0.9 | F33: -0.9 | G33: 79.8 | H33: 0.5 | I33: 3.5 | J33: 0.104 | K33: 258 | L33: 2562 | M33: FALSE | N33: FALSE | O33: =AND($I$33>=12.0,$J$33>=0.12,$K$33<160.0) | P33: =AND($O$33,Am_thanh!$C$41<>"armour_metal") | Q33: Docs/audio/metrics.json: clips["flak/flak_2.ogg"]
A34: flak/flak_3 | B34: 0.61 | C34: -25 | D34: -20.7 | E34: -0.9 | F34: -0.9 | G34: 77.6 | H34: 0.53 | I34: 0 | J34: 0 | K34: 0 | L34: 0 | M34: FALSE | N34: FALSE | O34: =AND($I$34>=12.0,$J$34>=0.12,$K$34<160.0) | P34: =AND($O$34,Am_thanh!$C$42<>"armour_metal") | Q34: Docs/audio/metrics.json: clips["flak/flak_3.ogg"]
A35: flame/flame_1 | B35: 1.5 | C35: -13.7 | D35: -12.9 | E35: -0.9 | F35: -0.9 | G35: 41.2 | H35: 1.15 | I35: 9.5 | J35: 0.104 | K35: 86 | L35: 2885 | M35: FALSE | N35: FALSE | O35: =AND($I$35>=12.0,$J$35>=0.12,$K$35<160.0) | P35: =AND($O$35,Am_thanh!$C$43<>"armour_metal") | Q35: Docs/audio/metrics.json: clips["flame/flame_1.ogg"]
A36: flame/flame_2 | B36: 1.377 | C36: -12.6 | D36: -12 | E36: -1 | F36: -1 | G36: 81.1 | H36: 0.71 | I36: 0 | J36: 0 | K36: 0 | L36: 0 | M36: FALSE | N36: FALSE | O36: =AND($I$36>=12.0,$J$36>=0.12,$K$36<160.0) | P36: =AND($O$36,Am_thanh!$C$44<>"armour_metal") | Q36: Docs/audio/metrics.json: clips["flame/flame_2.ogg"]
A37: heavy_cannon/heavy_cannon_1 | B37: 2 | C37: -19.6 | D37: -14.3 | E37: -1 | F37: -1 | G37: 76.5 | H37: 1.86 | I37: 3.2 | J37: 0.081 | K37: 2326 | L37: 2067 | M37: FALSE | N37: FALSE | O37: =AND($I$37>=12.0,$J$37>=0.12,$K$37<160.0) | P37: =AND($O$37,Am_thanh!$C$45<>"armour_metal") | Q37: Docs/audio/metrics.json: clips["heavy_cannon/heavy_cannon_1.ogg"]
A38: heavy_cannon/heavy_cannon_2 | B38: 1.842 | C38: -21.5 | D38: -15.5 | E38: -0.9 | F38: -0.9 | G38: 68 | H38: 1.52 | I38: 3.4 | J38: 0.197 | K38: 668 | L38: 4500 | M38: FALSE | N38: FALSE | O38: =AND($I$38>=12.0,$J$38>=0.12,$K$38<160.0) | P38: =AND($O$38,Am_thanh!$C$46<>"armour_metal") | Q38: Docs/audio/metrics.json: clips["heavy_cannon/heavy_cannon_2.ogg"]
A39: heavy_cannon/heavy_cannon_3 | B39: 1.981 | C39: -17.8 | D39: -13 | E39: -1 | F39: -1 | G39: 71.1 | H39: 1.53 | I39: 0 | J39: 0 | K39: 0 | L39: 0 | M39: FALSE | N39: FALSE | O39: =AND($I$39>=12.0,$J$39>=0.12,$K$39<160.0) | P39: =AND($O$39,Am_thanh!$C$47<>"armour_metal") | Q39: Docs/audio/metrics.json: clips["heavy_cannon/heavy_cannon_3.ogg"]
A40: impact_metal/impact_metal_1 | B40: 0.453 | C40: -17.1 | D40: -17.1 | E40: -0.7 | F40: -0.7 | G40: 8.5 | H40: 0.28 | I40: 7.7 | J40: 0.058 | K40: 108 | L40: 4221 | M40: FALSE | N40: FALSE | O40: =AND($I$40>=12.0,$J$40>=0.12,$K$40<160.0) | P40: =AND($O$40,Am_thanh!$C$48<>"armour_metal") | Q40: Docs/audio/metrics.json: clips["impact_metal/impact_metal_1.ogg"]
A41: impact_metal/impact_metal_2 | B41: 0.468 | C41: -17.8 | D41: -17.8 | E41: -1 | F41: -0.9 | G41: 5.4 | H41: 0.28 | I41: 5.9 | J41: 0.081 | K41: 129 | L41: 2541 | M41: FALSE | N41: FALSE | O41: =AND($I$41>=12.0,$J$41>=0.12,$K$41<160.0) | P41: =AND($O$41,Am_thanh!$C$49<>"armour_metal") | Q41: Docs/audio/metrics.json: clips["impact_metal/impact_metal_2.ogg"]
A42: impact_metal/impact_metal_3 | B42: 0.442 | C42: -15.7 | D42: -15.7 | E42: -1.9 | F42: -1.5 | G42: 14.6 | H42: 0.28 | I42: 8.1 | J42: 0.255 | K42: 65 | L42: 3445 | M42: FALSE | N42: FALSE | O42: =AND($I$42>=12.0,$J$42>=0.12,$K$42<160.0) | P42: =AND($O$42,Am_thanh!$C$50<>"armour_metal") | Q42: Docs/audio/metrics.json: clips["impact_metal/impact_metal_3.ogg"]
A43: jet_loop/jet_loop_1 | B43: 5 | C43: -17.6 | D43: -15.4 | E43: -1 | F43: -1 | G43: 28.6 | H43: 2.46 | I43: 0 | J43: 0 | K43: 0 | L43: 0 | M43: FALSE | N43: FALSE | O43: =AND($I$43>=12.0,$J$43>=0.12,$K$43<160.0) | P43: =AND($O$43,Am_thanh!$C$51<>"armour_metal") | Q43: Docs/audio/metrics.json: clips["jet_loop/jet_loop_1.ogg"]
A44: jet_pass/jet_pass_1 | B44: 3.657 | C44: -17 | D44: -13.4 | E44: -1 | F44: -1 | G44: 11.5 | H44: 1.63 | I44: 4 | J44: 0.302 | K44: 2799 | L44: 2390 | M44: FALSE | N44: FALSE | O44: =AND($I$44>=12.0,$J$44>=0.12,$K$44<160.0) | P44: =AND($O$44,Am_thanh!$C$52<>"armour_metal") | Q44: Docs/audio/metrics.json: clips["jet_pass/jet_pass_1.ogg"]
A45: jet_pass/jet_pass_2 | B45: 3.762 | C45: -16.4 | D45: -13.2 | E45: -1 | F45: -1 | G45: 5.1 | H45: 1.57 | I45: 3.6 | J45: 0.267 | K45: 883 | L45: 3531 | M45: FALSE | N45: FALSE | O45: =AND($I$45>=12.0,$J$45>=0.12,$K$45<160.0) | P45: =AND($O$45,Am_thanh!$C$53<>"armour_metal") | Q45: Docs/audio/metrics.json: clips["jet_pass/jet_pass_2.ogg"]
A46: jet_pass/jet_pass_3 | B46: 3.668 | C46: -19.7 | D46: -14.6 | E46: -1 | F46: -1 | G46: 24.7 | H46: 2.03 | I46: 3 | J46: 1.95 | K46: 2326 | L46: 2046 | M46: FALSE | N46: FALSE | O46: =AND($I$46>=12.0,$J$46>=0.12,$K$46<160.0) | P46: =AND($O$46,Am_thanh!$C$54<>"armour_metal") | Q46: Docs/audio/metrics.json: clips["jet_pass/jet_pass_3.ogg"]
A47: mg/mg_1 | B47: 0.791 | C47: -15.4 | D47: -13.3 | E47: -1 | F47: -1 | G47: 72.6 | H47: 0.66 | I47: 4.1 | J47: 0.023 | K47: 258 | L47: 2239 | M47: FALSE | N47: FALSE | O47: =AND($I$47>=12.0,$J$47>=0.12,$K$47<160.0) | P47: =AND($O$47,Am_thanh!$C$55<>"armour_metal") | Q47: Docs/audio/metrics.json: clips["mg/mg_1.ogg"]
A48: mg/mg_2 | B48: 0.752 | C48: -17.6 | D48: -14.8 | E48: -0.9 | F48: -0.9 | G48: 68.8 | H48: 0.59 | I48: 4.3 | J48: 0.035 | K48: 624 | L48: 5017 | M48: FALSE | N48: FALSE | O48: =AND($I$48>=12.0,$J$48>=0.12,$K$48<160.0) | P48: =AND($O$48,Am_thanh!$C$56<>"armour_metal") | Q48: Docs/audio/metrics.json: clips["mg/mg_2.ogg"]
A49: mg/mg_3 | B49: 0.751 | C49: -17.3 | D49: -14 | E49: -1 | F49: -1 | G49: 71.9 | H49: 0.61 | I49: 4.4 | J49: 0.035 | K49: 301 | L49: 5017 | M49: FALSE | N49: FALSE | O49: =AND($I$49>=12.0,$J$49>=0.12,$K$49<160.0) | P49: =AND($O$49,Am_thanh!$C$57<>"armour_metal") | Q49: Docs/audio/metrics.json: clips["mg/mg_3.ogg"]
A50: missile_launch/missile_launch_1 | B50: 1.474 | C50: -14.8 | D50: -12.5 | E50: -1 | F50: -1 | G50: 57.4 | H50: 1.06 | I50: 3.3 | J50: 0.476 | K50: 2907 | L50: 2369 | M50: FALSE | N50: FALSE | O50: =AND($I$50>=12.0,$J$50>=0.12,$K$50<160.0) | P50: =AND($O$50,Am_thanh!$C$58<>"armour_metal") | Q50: Docs/audio/metrics.json: clips["missile_launch/missile_launch_1.ogg"]
A51: missile_launch/missile_launch_2 | B51: 1.5 | C51: -13.4 | D51: -12.2 | E51: -0.9 | F51: -0.9 | G51: 22 | H51: 1.44 | I51: 2.6 | J51: 0.104 | K51: 4091 | L51: 3618 | M51: FALSE | N51: FALSE | O51: =AND($I$51>=12.0,$J$51>=0.12,$K$51<160.0) | P51: =AND($O$51,Am_thanh!$C$59<>"armour_metal") | Q51: Docs/audio/metrics.json: clips["missile_launch/missile_launch_2.ogg"]
A52: rain_loop/rain_loop_1 | B52: 8 | C52: -16.2 | D52: -15.7 | E52: -1 | F52: -1 | G52: 17.5 | H52: 2.99 | I52: 3.3 | J52: 0.639 | K52: 3811 | L52: 2929 | M52: FALSE | N52: FALSE | O52: =AND($I$52>=12.0,$J$52>=0.12,$K$52<160.0) | P52: =AND($O$52,Am_thanh!$C$60<>"armour_metal") | Q52: Docs/audio/metrics.json: clips["rain_loop/rain_loop_1.ogg"]
A53: rocket_launch/rocket_launch_1 | B53: 1.139 | C53: -19.8 | D53: -15.6 | E53: -0.9 | F53: -0.9 | G53: 73.2 | H53: 0.97 | I53: 2.6 | J53: 0.151 | K53: 5017 | L53: 4328 | M53: FALSE | N53: FALSE | O53: =AND($I$53>=12.0,$J$53>=0.12,$K$53<160.0) | P53: =AND($O$53,Am_thanh!$C$61<>"armour_metal") | Q53: Docs/audio/metrics.json: clips["rocket_launch/rocket_launch_1.ogg"]
A54: rocket_launch/rocket_launch_2 | B54: 1.15 | C54: -20.2 | D54: -15.5 | E54: -0.9 | F54: -0.9 | G54: 63.1 | H54: 0.94 | I54: 2.9 | J54: 0.046 | K54: 3833 | L54: 3596 | M54: FALSE | N54: FALSE | O54: =AND($I$54>=12.0,$J$54>=0.12,$K$54<160.0) | P54: =AND($O$54,Am_thanh!$C$62<>"armour_metal") | Q54: Docs/audio/metrics.json: clips["rocket_launch/rocket_launch_2.ogg"]
A55: rocket_launch/rocket_launch_3 | B55: 1.269 | C55: -16.1 | D55: -13.6 | E55: -1.7 | F55: -1.7 | G55: 0 | H55: 0.79 | I55: 3.6 | J55: 0.023 | K55: 1098 | L55: 4221 | M55: FALSE | N55: FALSE | O55: =AND($I$55>=12.0,$J$55>=0.12,$K$55<160.0) | P55: =AND($O$55,Am_thanh!$C$63<>"armour_metal") | Q55: Docs/audio/metrics.json: clips["rocket_launch/rocket_launch_3.ogg"]
A56: rocket_launch/rocket_launch_4 | B56: 1.003 | C56: -15.2 | D56: -13.5 | E56: -1.9 | F56: -1.8 | G56: 1.5 | H56: 0.55 | I56: 3.2 | J56: 0.337 | K56: 452 | L56: 2692 | M56: FALSE | N56: FALSE | O56: =AND($I$56>=12.0,$J$56>=0.12,$K$56<160.0) | P56: =AND($O$56,Am_thanh!$C$64<>"armour_metal") | Q56: Docs/audio/metrics.json: clips["rocket_launch/rocket_launch_4.ogg"]
A57: rotor_loop/rotor_loop_1 | B57: 2.464 | C57: -16.1 | D57: -15.8 | E57: -0.9 | F57: -0.9 | G57: 66.9 | H57: 0.26 | I57: 0 | J57: 0 | K57: 0 | L57: 0 | M57: FALSE | N57: FALSE | O57: =AND($I$57>=12.0,$J$57>=0.12,$K$57<160.0) | P57: =AND($O$57,Am_thanh!$C$65<>"armour_metal") | Q57: Docs/audio/metrics.json: clips["rotor_loop/rotor_loop_1.ogg"]
A58: sfx/blast_air_s1/blast_air_s1_1 | B58: 1.18 | C58: -23.9 | D58: -19.6 | E58: -0.7 | F58: -0.7 | G58: 20.5 | H58: 0.73 | I58: 3.9 | J58: 0.139 | K58: 5254 | L58: 4910 | M58: FALSE | N58: FALSE | O58: =AND($I$58>=12.0,$J$58>=0.12,$K$58<160.0) | P58: =AND($O$58,Am_thanh!$C$66<>"armour_metal") | Q58: Docs/audio/metrics.json: clips["sfx/blast_air_s1/blast_air_s1_1.ogg"]
A59: sfx/blast_air_s1/blast_air_s1_2 | B59: 1.25 | C59: -23.7 | D59: -19.6 | E59: -1.1 | F59: -1.1 | G59: 21.7 | H59: 0.8 | I59: 3.3 | J59: 0.163 | K59: 2972 | L59: 2649 | M59: FALSE | N59: FALSE | O59: =AND($I$59>=12.0,$J$59>=0.12,$K$59<160.0) | P59: =AND($O$59,Am_thanh!$C$67<>"armour_metal") | Q59: Docs/audio/metrics.json: clips["sfx/blast_air_s1/blast_air_s1_2.ogg"]
A60: sfx/blast_air_s2/blast_air_s2_1 | B60: 1.78 | C60: -21.1 | D60: -17.1 | E60: -3.8 | F60: -3.8 | G60: 33 | H60: 1.15 | I60: 4.2 | J60: 0.07 | K60: 2799 | L60: 2692 | M60: FALSE | N60: FALSE | O60: =AND($I$60>=12.0,$J$60>=0.12,$K$60<160.0) | P60: =AND($O$60,Am_thanh!$C$68<>"armour_metal") | Q60: Docs/audio/metrics.json: clips["sfx/blast_air_s2/blast_air_s2_1.ogg"]
A61: sfx/blast_air_s2/blast_air_s2_2 | B61: 1.88 | C61: -22.3 | D61: -17.1 | E61: -3.1 | F61: -3.1 | G61: 33.5 | H61: 1.19 | I61: 3 | J61: 0.046 | K61: 2972 | L61: 2347 | M61: FALSE | N61: FALSE | O61: =AND($I$61>=12.0,$J$61>=0.12,$K$61<160.0) | P61: =AND($O$61,Am_thanh!$C$69<>"armour_metal") | Q61: Docs/audio/metrics.json: clips["sfx/blast_air_s2/blast_air_s2_2.ogg"]
A62: sfx/blast_air_s3/blast_air_s3_1 | B62: 2.61 | C62: -19.7 | D62: -15.1 | E62: -3.3 | F62: -3.3 | G62: 42.2 | H62: 1.58 | I62: 4.1 | J62: 0.081 | K62: 2821 | L62: 2692 | M62: FALSE | N62: FALSE | O62: =AND($I$62>=12.0,$J$62>=0.12,$K$62<160.0) | P62: =AND($O$62,Am_thanh!$C$70<>"armour_metal") | Q62: Docs/audio/metrics.json: clips["sfx/blast_air_s3/blast_air_s3_1.ogg"]
A63: sfx/blast_air_s3/blast_air_s3_2 | B63: 2.66 | C63: -20.7 | D63: -15.1 | E63: -3.1 | F63: -3.1 | G63: 43.1 | H63: 1.68 | I63: 2.7 | J63: 0.058 | K63: 2972 | L63: 2347 | M63: FALSE | N63: FALSE | O63: =AND($I$63>=12.0,$J$63>=0.12,$K$63<160.0) | P63: =AND($O$63,Am_thanh!$C$71<>"armour_metal") | Q63: Docs/audio/metrics.json: clips["sfx/blast_air_s3/blast_air_s3_2.ogg"]
A64: sfx/blast_bomb/blast_bomb_1 | B64: 5.925 | C64: -15.6 | D64: -11.1 | E64: -1.9 | F64: -1.9 | G64: 65.4 | H64: 5.82 | I64: 0 | J64: 0 | K64: 0 | L64: 0 | M64: FALSE | N64: FALSE | O64: =AND($I$64>=12.0,$J$64>=0.12,$K$64<160.0) | P64: =AND($O$64,Am_thanh!$C$72<>"armour_metal") | Q64: Docs/audio/metrics.json: clips["sfx/blast_bomb/blast_bomb_1.ogg"]
A65: sfx/blast_bomb/blast_bomb_2 | B65: 5.925 | C65: -14.1 | D65: -11 | E65: -2.4 | F65: -2.4 | G65: 66.9 | H65: 5.84 | I65: 0 | J65: 0 | K65: 0 | L65: 0 | M65: FALSE | N65: FALSE | O65: =AND($I$65>=12.0,$J$65>=0.12,$K$65<160.0) | P65: =AND($O$65,Am_thanh!$C$73<>"armour_metal") | Q65: Docs/audio/metrics.json: clips["sfx/blast_bomb/blast_bomb_2.ogg"]
A66: sfx/blast_bomb/blast_bomb_3 | B66: 5.88 | C66: -16.3 | D66: -11 | E66: -2.2 | F66: -2.1 | G66: 66.3 | H66: 4.55 | I66: 0 | J66: 0 | K66: 0 | L66: 0 | M66: FALSE | N66: FALSE | O66: =AND($I$66>=12.0,$J$66>=0.12,$K$66<160.0) | P66: =AND($O$66,Am_thanh!$C$74<>"armour_metal") | Q66: Docs/audio/metrics.json: clips["sfx/blast_bomb/blast_bomb_3.ogg"]
A67: sfx/blast_he_s1/blast_he_s1_1 | B67: 1.17 | C67: -21.7 | D67: -18.1 | E67: -4.8 | F67: -4.8 | G67: 31 | H67: 1.01 | I67: 4.4 | J67: 0.058 | K67: 258 | L67: 2692 | M67: FALSE | N67: FALSE | O67: =AND($I$67>=12.0,$J$67>=0.12,$K$67<160.0) | P67: =AND($O$67,Am_thanh!$C$75<>"armour_metal") | Q67: Docs/audio/metrics.json: clips["sfx/blast_he_s1/blast_he_s1_1.ogg"]
A68: sfx/blast_he_s1/blast_he_s1_2 | B68: 1.19 | C68: -22.3 | D68: -18.1 | E68: -5.8 | F68: -5.8 | G68: 31.1 | H68: 1.03 | I68: 2.7 | J68: 0.186 | K68: 6331 | L68: 5491 | M68: FALSE | N68: FALSE | O68: =AND($I$68>=12.0,$J$68>=0.12,$K$68<160.0) | P68: =AND($O$68,Am_thanh!$C$76<>"armour_metal") | Q68: Docs/audio/metrics.json: clips["sfx/blast_he_s1/blast_he_s1_2.ogg"]
A69: sfx/blast_he_s1/blast_he_s1_3 | B69: 1.1 | C69: -23 | D69: -18.1 | E69: -3.6 | F69: -3.5 | G69: 31.1 | H69: 0.8 | I69: 3.5 | J69: 0.128 | K69: 969 | L69: 4177 | M69: FALSE | N69: FALSE | O69: =AND($I$69>=12.0,$J$69>=0.12,$K$69<160.0) | P69: =AND($O$69,Am_thanh!$C$77<>"armour_metal") | Q69: Docs/audio/metrics.json: clips["sfx/blast_he_s1/blast_he_s1_3.ogg"]
A70: sfx/blast_he_s2/blast_he_s2_1 | B70: 2.23 | C70: -21.7 | D70: -15.6 | E70: -3.2 | F70: -3.1 | G70: 45.5 | H70: 1.82 | I70: 0 | J70: 0 | K70: 0 | L70: 0 | M70: FALSE | N70: FALSE | O70: =AND($I$70>=12.0,$J$70>=0.12,$K$70<160.0) | P70: =AND($O$70,Am_thanh!$C$78<>"armour_metal") | Q70: Docs/audio/metrics.json: clips["sfx/blast_he_s2/blast_he_s2_1.ogg"]
A71: sfx/blast_he_s2/blast_he_s2_2 | B71: 2.18 | C71: -20.4 | D71: -15.6 | E71: -0.7 | F71: -0.4 | G71: 45.7 | H71: 1.61 | I71: 4.1 | J71: 0.023 | K71: 280 | L71: 4242 | M71: FALSE | N71: FALSE | O71: =AND($I$71>=12.0,$J$71>=0.12,$K$71<160.0) | P71: =AND($O$71,Am_thanh!$C$79<>"armour_metal") | Q71: Docs/audio/metrics.json: clips["sfx/blast_he_s2/blast_he_s2_2.ogg"]
A72: sfx/blast_he_s2/blast_he_s2_3 | B72: 2.15 | C72: -20.9 | D72: -15.6 | E72: -1.8 | F72: -1.8 | G72: 45.4 | H72: 1.74 | I72: 3.1 | J72: 0.023 | K72: 3811 | L72: 3273 | M72: FALSE | N72: FALSE | O72: =AND($I$72>=12.0,$J$72>=0.12,$K$72<160.0) | P72: =AND($O$72,Am_thanh!$C$80<>"armour_metal") | Q72: Docs/audio/metrics.json: clips["sfx/blast_he_s2/blast_he_s2_3.ogg"]
A73: sfx/blast_he_s3/blast_he_s3_1 | B73: 3.41 | C73: -19.9 | D73: -13.6 | E73: -0.9 | F73: -0.9 | G73: 55.8 | H73: 2.67 | I73: 2.9 | J73: 0.348 | K73: 2778 | L73: 2498 | M73: FALSE | N73: FALSE | O73: =AND($I$73>=12.0,$J$73>=0.12,$K$73<160.0) | P73: =AND($O$73,Am_thanh!$C$81<>"armour_metal") | Q73: Docs/audio/metrics.json: clips["sfx/blast_he_s3/blast_he_s3_1.ogg"]
A74: sfx/blast_he_s3/blast_he_s3_2 | B74: 2.87 | C74: -18.6 | D74: -13.5 | E74: -1 | F74: -1 | G74: 55.5 | H74: 2.33 | I74: 2.6 | J74: 0.43 | K74: 2950 | L74: 2261 | M74: FALSE | N74: FALSE | O74: =AND($I$74>=12.0,$J$74>=0.12,$K$74<160.0) | P74: =AND($O$74,Am_thanh!$C$82<>"armour_metal") | Q74: Docs/audio/metrics.json: clips["sfx/blast_he_s3/blast_he_s3_2.ogg"]
A75: sfx/blast_he_s3/blast_he_s3_3 | B75: 2.93 | C75: -19.7 | D75: -13.7 | E75: -0.9 | F75: -0.8 | G75: 55.6 | H75: 2.31 | I75: 3.1 | J75: 0.255 | K75: 2692 | L75: 2304 | M75: FALSE | N75: FALSE | O75: =AND($I$75>=12.0,$J$75>=0.12,$K$75<160.0) | P75: =AND($O$75,Am_thanh!$C$83<>"armour_metal") | Q75: Docs/audio/metrics.json: clips["sfx/blast_he_s3/blast_he_s3_3.ogg"]
A76: sfx/blast_he_s4/blast_he_s4_1 | B76: 4.38 | C76: -18.6 | D76: -12.1 | E76: -3 | F76: -3 | G76: 62.1 | H76: 4.15 | I76: 0 | J76: 0 | K76: 0 | L76: 0 | M76: FALSE | N76: FALSE | O76: =AND($I$76>=12.0,$J$76>=0.12,$K$76<160.0) | P76: =AND($O$76,Am_thanh!$C$84<>"armour_metal") | Q76: Docs/audio/metrics.json: clips["sfx/blast_he_s4/blast_he_s4_1.ogg"]
A77: sfx/blast_he_s4/blast_he_s4_2 | B77: 4.95 | C77: -20.6 | D77: -12.1 | E77: -3.2 | F77: -3.2 | G77: 63 | H77: 4.79 | I77: 2.1 | J77: 0.209 | K77: 2799 | L77: 2153 | M77: FALSE | N77: FALSE | O77: =AND($I$77>=12.0,$J$77>=0.12,$K$77<160.0) | P77: =AND($O$77,Am_thanh!$C$85<>"armour_metal") | Q77: Docs/audio/metrics.json: clips["sfx/blast_he_s4/blast_he_s4_2.ogg"]
A78: sfx/blast_he_s4/blast_he_s4_3 | B78: 4.47 | C78: -16.2 | D78: -12 | E78: -2.8 | F78: -2.7 | G78: 58.8 | H78: 3.67 | I78: 0 | J78: 0 | K78: 0 | L78: 0 | M78: FALSE | N78: FALSE | O78: =AND($I$78>=12.0,$J$78>=0.12,$K$78<160.0) | P78: =AND($O$78,Am_thanh!$C$86<>"armour_metal") | Q78: Docs/audio/metrics.json: clips["sfx/blast_he_s4/blast_he_s4_3.ogg"]
A79: sfx/blast_he_s406/blast_he_s406_1 | B79: 7.225 | C79: -14 | D79: -10.1 | E79: -0.8 | F79: -0.8 | G79: 70 | H79: 7.11 | I79: 0 | J79: 0 | K79: 0 | L79: 0 | M79: FALSE | N79: FALSE | O79: =AND($I$79>=12.0,$J$79>=0.12,$K$79<160.0) | P79: =AND($O$79,Am_thanh!$C$87<>"armour_metal") | Q79: Docs/audio/metrics.json: clips["sfx/blast_he_s406/blast_he_s406_1.ogg"]
A80: sfx/blast_he_s406/blast_he_s406_2 | B80: 7.225 | C80: -13.1 | D80: -10 | E80: -1.7 | F80: -1.7 | G80: 72 | H80: 7.13 | I80: 0 | J80: 0 | K80: 0 | L80: 0 | M80: FALSE | N80: FALSE | O80: =AND($I$80>=12.0,$J$80>=0.12,$K$80<160.0) | P80: =AND($O$80,Am_thanh!$C$88<>"armour_metal") | Q80: Docs/audio/metrics.json: clips["sfx/blast_he_s406/blast_he_s406_2.ogg"]
A81: sfx/blast_heat_s2/blast_heat_s2_1 | B81: 1.59 | C81: -20 | D81: -16.6 | E81: -4.7 | F81: -4.7 | G81: 33 | H81: 1.19 | I81: 4.2 | J81: 0.046 | K81: 2821 | L81: 2692 | M81: FALSE | N81: FALSE | O81: =AND($I$81>=12.0,$J$81>=0.12,$K$81<160.0) | P81: =AND($O$81,Am_thanh!$C$89<>"armour_metal") | Q81: Docs/audio/metrics.json: clips["sfx/blast_heat_s2/blast_heat_s2_1.ogg"]
A82: sfx/blast_heat_s2/blast_heat_s2_2 | B82: 1.75 | C82: -20.6 | D82: -16.6 | E82: -4.1 | F82: -4.1 | G82: 42.3 | H82: 1.11 | I82: 3 | J82: 0.151 | K82: 3618 | L82: 2412 | M82: FALSE | N82: FALSE | O82: =AND($I$82>=12.0,$J$82>=0.12,$K$82<160.0) | P82: =AND($O$82,Am_thanh!$C$90<>"armour_metal") | Q82: Docs/audio/metrics.json: clips["sfx/blast_heat_s2/blast_heat_s2_2.ogg"]
A83: sfx/blast_heat_s3/blast_heat_s3_1 | B83: 2.61 | C83: -20.6 | D83: -14.6 | E83: -3.6 | F83: -3.6 | G83: 46.4 | H83: 2.1 | I83: 0 | J83: 0 | K83: 0 | L83: 0 | M83: FALSE | N83: FALSE | O83: =AND($I$83>=12.0,$J$83>=0.12,$K$83<160.0) | P83: =AND($O$83,Am_thanh!$C$91<>"armour_metal") | Q83: Docs/audio/metrics.json: clips["sfx/blast_heat_s3/blast_heat_s3_1.ogg"]
A84: sfx/blast_heat_s3/blast_heat_s3_2 | B84: 2.66 | C84: -19.3 | D84: -14.6 | E84: -2.8 | F84: -2.8 | G84: 47.9 | H84: 1.82 | I84: 4.5 | J84: 0.023 | K84: 258 | L84: 4242 | M84: FALSE | N84: FALSE | O84: =AND($I$84>=12.0,$J$84>=0.12,$K$84<160.0) | P84: =AND($O$84,Am_thanh!$C$92<>"armour_metal") | Q84: Docs/audio/metrics.json: clips["sfx/blast_heat_s3/blast_heat_s3_2.ogg"]
A85: sfx/blast_super/blast_super_1 | B85: 11.45 | C85: -12.5 | D85: -9.2 | E85: 0 | F85: 0 | G85: 78 | H85: 10.27 | I85: 0 | J85: 0 | K85: 0 | L85: 0 | M85: FALSE | N85: FALSE | O85: =AND($I$85>=12.0,$J$85>=0.12,$K$85<160.0) | P85: =AND($O$85,Am_thanh!$C$93<>"armour_metal") | Q85: Docs/audio/metrics.json: clips["sfx/blast_super/blast_super_1.ogg"]
A86: sfx/blast_super/blast_super_2 | B86: 11.45 | C86: -11.9 | D86: -9 | E86: 0.1 | F86: 0.1 | G86: 78.7 | H86: 11.03 | I86: 0 | J86: 0 | K86: 0 | L86: 0 | M86: FALSE | N86: FALSE | O86: =AND($I$86>=12.0,$J$86>=0.12,$K$86<160.0) | P86: =AND($O$86,Am_thanh!$C$94<>"armour_metal") | Q86: Docs/audio/metrics.json: clips["sfx/blast_super/blast_super_2.ogg"]
A87: sfx/blast_thermo_s3/blast_thermo_s3_1 | B87: 3.49 | C87: -19 | D87: -13 | E87: -0.9 | F87: -0.9 | G87: 61.9 | H87: 2.78 | I87: 3 | J87: 0.244 | K87: 2778 | L87: 2476 | M87: FALSE | N87: FALSE | O87: =AND($I$87>=12.0,$J$87>=0.12,$K$87<160.0) | P87: =AND($O$87,Am_thanh!$C$95<>"armour_metal") | Q87: Docs/audio/metrics.json: clips["sfx/blast_thermo_s3/blast_thermo_s3_1.ogg"]
A88: sfx/blast_thermo_s3/blast_thermo_s3_2 | B88: 3.18 | C88: -17.4 | D88: -12.9 | E88: -0.7 | F88: -0.6 | G88: 61.6 | H88: 2.54 | I88: 0 | J88: 0 | K88: 0 | L88: 0 | M88: FALSE | N88: FALSE | O88: =AND($I$88>=12.0,$J$88>=0.12,$K$88<160.0) | P88: =AND($O$88,Am_thanh!$C$96<>"armour_metal") | Q88: Docs/audio/metrics.json: clips["sfx/blast_thermo_s3/blast_thermo_s3_2.ogg"]
A89: sfx/blast_thermo_s4/blast_thermo_s4_1 | B89: 4.72 | C89: -17.5 | D89: -11.4 | E89: -3.1 | F89: -3.1 | G89: 67.4 | H89: 4.36 | I89: 0 | J89: 0 | K89: 0 | L89: 0 | M89: FALSE | N89: FALSE | O89: =AND($I$89>=12.0,$J$89>=0.12,$K$89<160.0) | P89: =AND($O$89,Am_thanh!$C$97<>"armour_metal") | Q89: Docs/audio/metrics.json: clips["sfx/blast_thermo_s4/blast_thermo_s4_1.ogg"]
A90: sfx/blast_thermo_s4/blast_thermo_s4_2 | B90: 4.86 | C90: -19.4 | D90: -11.4 | E90: -1.1 | F90: -1 | G90: 68.9 | H90: 4.68 | I90: 0 | J90: 0 | K90: 0 | L90: 0 | M90: FALSE | N90: FALSE | O90: =AND($I$90>=12.0,$J$90>=0.12,$K$90<160.0) | P90: =AND($O$90,Am_thanh!$C$98<>"armour_metal") | Q90: Docs/audio/metrics.json: clips["sfx/blast_thermo_s4/blast_thermo_s4_2.ogg"]
A91: sfx/burst_s0_10/burst_s0_10_1 | B91: 0.57 | C91: -23.7 | D91: -23 | E91: -8.1 | F91: -7.7 | G91: 1.9 | H91: 0.51 | I91: 4.1 | J91: 0.058 | K91: 431 | L91: 5060 | M91: FALSE | N91: FALSE | O91: =AND($I$91>=12.0,$J$91>=0.12,$K$91<160.0) | P91: =AND($O$91,Am_thanh!$C$99<>"armour_metal") | Q91: Docs/audio/metrics.json: clips["sfx/burst_s0_10/burst_s0_10_1.ogg"]
A92: sfx/burst_s0_10/burst_s0_10_2 | B92: 0.57 | C92: -24.2 | D92: -23.3 | E92: -7.6 | F92: -7.4 | G92: 1.8 | H92: 0.51 | I92: 4.7 | J92: 0.035 | K92: 323 | L92: 5039 | M92: FALSE | N92: FALSE | O92: =AND($I$92>=12.0,$J$92>=0.12,$K$92<160.0) | P92: =AND($O$92,Am_thanh!$C$100<>"armour_metal") | Q92: Docs/audio/metrics.json: clips["sfx/burst_s0_10/burst_s0_10_2.ogg"]
A93: sfx/burst_s0_10/burst_s0_10_3 | B93: 0.57 | C93: -23.6 | D93: -23.1 | E93: -7.8 | F93: -7.6 | G93: 1.5 | H93: 0.31 | I93: 3.6 | J93: 0.163 | K93: 345 | L93: 2433 | M93: FALSE | N93: FALSE | O93: =AND($I$93>=12.0,$J$93>=0.12,$K$93<160.0) | P93: =AND($O$93,Am_thanh!$C$101<>"armour_metal") | Q93: Docs/audio/metrics.json: clips["sfx/burst_s0_10/burst_s0_10_3.ogg"]
A94: sfx/burst_s0_16/burst_s0_16_1 | B94: 0.62 | C94: -22.5 | D94: -20.6 | E94: -7.3 | F94: -6.6 | G94: 1.5 | H94: 0.5 | I94: 4.7 | J94: 0.221 | K94: 280 | L94: 2433 | M94: FALSE | N94: FALSE | O94: =AND($I$94>=12.0,$J$94>=0.12,$K$94<160.0) | P94: =AND($O$94,Am_thanh!$C$102<>"armour_metal") | Q94: Docs/audio/metrics.json: clips["sfx/burst_s0_16/burst_s0_16_1.ogg"]
A95: sfx/burst_s0_16/burst_s0_16_2 | B95: 0.62 | C95: -22.8 | D95: -21 | E95: -7.4 | F95: -6.6 | G95: 1.6 | H95: 0.56 | I95: 4.6 | J95: 0.023 | K95: 151 | L95: 2433 | M95: FALSE | N95: FALSE | O95: =AND($I$95>=12.0,$J$95>=0.12,$K$95<160.0) | P95: =AND($O$95,Am_thanh!$C$103<>"armour_metal") | Q95: Docs/audio/metrics.json: clips["sfx/burst_s0_16/burst_s0_16_2.ogg"]
A96: sfx/burst_s0_16/burst_s0_16_3 | B96: 0.62 | C96: -23.2 | D96: -21.5 | E96: -7.3 | F96: -7 | G96: 1.8 | H96: 0.56 | I96: 5.4 | J96: 0.116 | K96: 129 | L96: 2433 | M96: FALSE | N96: FALSE | O96: =AND($I$96>=12.0,$J$96>=0.12,$K$96<160.0) | P96: =AND($O$96,Am_thanh!$C$104<>"armour_metal") | Q96: Docs/audio/metrics.json: clips["sfx/burst_s0_16/burst_s0_16_3.ogg"]
A97: sfx/burst_s0_55/burst_s0_55_1 | B97: 0.7 | C97: -21.1 | D97: -18.8 | E97: -8 | F97: -8 | G97: 1.9 | H97: 0.43 | I97: 5.3 | J97: 0.232 | K97: 345 | L97: 2433 | M97: FALSE | N97: FALSE | O97: =AND($I$97>=12.0,$J$97>=0.12,$K$97<160.0) | P97: =AND($O$97,Am_thanh!$C$105<>"armour_metal") | Q97: Docs/audio/metrics.json: clips["sfx/burst_s0_55/burst_s0_55_1.ogg"]
A98: sfx/burst_s0_55/burst_s0_55_2 | B98: 0.72 | C98: -21.4 | D98: -19 | E98: -8.4 | F98: -8.4 | G98: 2.2 | H98: 0.41 | I98: 2.5 | J98: 0.116 | K98: 4350 | L98: 4134 | M98: FALSE | N98: FALSE | O98: =AND($I$98>=12.0,$J$98>=0.12,$K$98<160.0) | P98: =AND($O$98,Am_thanh!$C$106<>"armour_metal") | Q98: Docs/audio/metrics.json: clips["sfx/burst_s0_55/burst_s0_55_2.ogg"]
A99: sfx/burst_s0_55/burst_s0_55_3 | B99: 0.7 | C99: -21.5 | D99: -19.1 | E99: -7.7 | F99: -7.6 | G99: 1.7 | H99: 0.33 | I99: 3 | J99: 0.058 | K99: 2627 | L99: 2433 | M99: FALSE | N99: FALSE | O99: =AND($I$99>=12.0,$J$99>=0.12,$K$99<160.0) | P99: =AND($O$99,Am_thanh!$C$107<>"armour_metal") | Q99: Docs/audio/metrics.json: clips["sfx/burst_s0_55/burst_s0_55_3.ogg"]
A100: sfx/burst_s1_10/burst_s1_10_1 | B100: 0.8 | C100: -22.3 | D100: -19.5 | E100: -4.4 | F100: -4.4 | G100: 12 | H100: 0.6 | I100: 3 | J100: 0.232 | K100: 5642 | L100: 5146 | M100: FALSE | N100: FALSE | O100: =AND($I$100>=12.0,$J$100>=0.12,$K$100<160.0) | P100: =AND($O$100,Am_thanh!$C$108<>"armour_metal") | Q100: Docs/audio/metrics.json: clips["sfx/burst_s1_10/burst_s1_10_1.ogg"]
...

Sheet Am_thanh_so_do_bac
A1: id | B1: bac_co | C1: vai | D1: ten | E1: lufs_mmax | F1: lufs | G1: duoi_150hz_pct | H1: duoi_s | I1: bank | J1: bac_truoc | K1: tang_deu | L1: nguon | M1: raw_json
A2: blast/bomb | B2: bomb | C2: blast | D2: bombs | E2: -11.03 | F2: -15.33 | G2: 66.2 | H2: 5.4 | I2: blast_bomb | J2: blast/s4 | K2: =AND($E$2>$E$7,$G$2>$G$7,$H$2>$H$7) | L2: Docs/audio/metrics.json: sizes[5].blast
A3: blast/s0 | B3: s0 | C3: blast | D3: <= 14.5 mm | E3: -24.23 | F3: -24.23 | G3: 12.7 | H3: 0.22 | I3: hit_ground_light | K3: ="" | L3: Docs/audio/metrics.json: sizes[0].blast
A4: blast/s1 | B4: s1 | C4: blast | D4: 20-40 mm | E4: -18.1 | F4: -22.33 | G4: 31.07 | H4: 0.95 | I4: blast_he_s1 | J4: blast/s0 | K4: =AND($E$4>$E$3,$G$4>$G$3,$H$4>$H$3) | L4: Docs/audio/metrics.json: sizes[1].blast
A5: blast/s2 | B5: s2 | C5: blast | D5: 57-105 mm | E5: -15.6 | F5: -21 | G5: 45.53 | H5: 1.72 | I5: blast_he_s2 | J5: blast/s1 | K5: =AND($E$5>$E$4,$G$5>$G$4,$H$5>$H$4) | L5: Docs/audio/metrics.json: sizes[2].blast
A6: blast/s3 | B6: s3 | C6: blast | D6: 120-155 mm | E6: -13.6 | F6: -19.4 | G6: 55.63 | H6: 2.44 | I6: blast_he_s3 | J6: blast/s2 | K6: =AND($E$6>$E$5,$G$6>$G$5,$H$6>$H$5) | L6: Docs/audio/metrics.json: sizes[3].blast
A7: blast/s4 | B7: s4 | C7: blast | D7: 203-240 mm | E7: -12.07 | F7: -18.47 | G7: 61.3 | H7: 4.2 | I7: blast_he_s4 | J7: blast/s3 | K7: =AND($E$7>$E$6,$G$7>$G$6,$H$7>$H$6) | L7: Docs/audio/metrics.json: sizes[4].blast
A8: blast/s406 | B8: s406 | C8: blast | D8: big rockets / >= 406 mm | E8: -10.05 | F8: -13.55 | G8: 71 | H8: 7.12 | I8: blast_he_s406 | J8: blast/bomb | K8: =AND($E$8>$E$2,$G$8>$G$2,$H$8>$H$2) | L8: Docs/audio/metrics.json: sizes[6].blast
A9: blast/super | B9: super | C9: blast | D9: super weapons | E9: -9.1 | F9: -12.2 | G9: 78.35 | H9: 10.65 | I9: blast_super | J9: blast/s406 | K9: =AND($E$9>$E$8,$G$9>$G$8,$H$9>$H$8) | L9: Docs/audio/metrics.json: sizes[7].blast
A10: shot/s0 | B10: s0 | C10: shot | D10: <= 14.5 mm | E10: -28.05 | F10: -28.05 | G10: 1.75 | H10: 0.31 | I10: shot_s0 | K10: ="" | L10: Docs/audio/metrics.json: sizes[0].shot
A11: shot/s1 | B11: s1 | C11: shot | D11: 20-40 mm | E11: -23.77 | F11: -26.35 | G11: 12 | H11: 0.49 | I11: shot_s1 | J11: shot/s0 | K11: =AND($E$11>$E$10,$G$11>$G$10,$H$11>$H$10) | L11: Docs/audio/metrics.json: sizes[1].shot
A12: shot/s2 | B12: s2 | C12: shot | D12: 57-105 mm | E12: -16.6 | F12: -21.93 | G12: 39.13 | H12: 1.41 | I12: shot_s2 | J12: shot/s1 | K12: =AND($E$12>$E$11,$G$12>$G$11,$H$12>$H$11) | L12: Docs/audio/metrics.json: sizes[2].shot
A13: shot/s3 | B13: s3 | C13: shot | D13: 120-155 mm | E13: -14.57 | F13: -21.17 | G13: 53.63 | H13: 2.04 | I13: shot_s3 | J13: shot/s2 | K13: =AND($E$13>$E$12,$G$13>$G$12,$H$13>$H$12) | L13: Docs/audio/metrics.json: sizes[3].shot
A14: shot/s4 | B14: s4 | C14: shot | D14: 203-240 mm | E14: -13.1 | F14: -19.77 | G14: 61.27 | H14: 2.92 | I14: shot_s4 | J14: shot/s3 | K14: =AND($E$14>$E$13,$G$14>$G$13,$H$14>$H$13) | L14: Docs/audio/metrics.json: sizes[4].shot
A15: shot/s406 | B15: s406 | C15: shot | D15: big rockets / >= 406 mm | E15: -11.6 | F15: -18.05 | G15: 70.05 | H15: 4.67 | I15: shot_s406 | J15: shot/s4 | K15: =AND($E$15>$E$14,$G$15>$G$14,$H$15>$H$14) | L15: Docs/audio/metrics.json: sizes[6].shot
A16: shot/super | B16: super | C16: shot | D16: super weapons | E16: -10.6 | F16: -15.15 | G16: 75.3 | H16: 7.26 | I16: shot_super | J16: shot/s406 | K16: =AND($E$16>$E$15,$G$16>$G$15,$H$16>$H$15) | L16: Docs/audio/metrics.json: sizes[7].shot

Sheet VFX_ngan_sach
A1: id | B1: loai | C1: toan_chi_tiet_toi_da | D1: trong_so | E1: ban_s | F1: rung_tai_no | G1: tran_trong_so | H1: he_so_rung_khi_ban | I1: gioi_han_ma | J1: yeu_cau | K1: nguon_ma | L1: dong_thoi_theo_trong_so | M1: dong_thoi_toi_da | N1: rung_khi_ban | O1: dat | P1: nguon | Q1: raw_json
A2: T0 | B2: bac | D2: 0 | E2: 2.5 | F2: 0 | G2: 12 | H2: 0.5 | L2: =IF(AND(ISNUMBER($D$2),$D$2>0),FLOOR($G$2/$D$2,1),"") | M2: =IF(ISNUMBER($C$2),IF(ISNUMBER($L$2),MIN($C$2,$L$2),$C$2),"") | N2: =IF(ISNUMBER($F$2),$F$2*$H$2,"") | O2: =IF(AND(ISNUMBER($I$2),ISNUMBER($J$2)),$I$2<=$J$2,"") | P2: C#: Game/Effects/TierFx.cs:166; Game/Effects/TierFx.cs:172; Game/Effects/TierFx.cs:174; Game/Effects/TierFx.cs:177; Game/Effects/TierFx.cs:182; Game/Effects/TierFx.cs:185
A3: T1 | B3: bac | D3: 0 | E3: 2.5 | F3: 0 | G3: 12 | H3: 0.5 | L3: =IF(AND(ISNUMBER($D$3),$D$3>0),FLOOR($G$3/$D$3,1),"") | M3: =IF(ISNUMBER($C$3),IF(ISNUMBER($L$3),MIN($C$3,$L$3),$C$3),"") | N3: =IF(ISNUMBER($F$3),$F$3*$H$3,"") | O3: =IF(AND(ISNUMBER($I$3),ISNUMBER($J$3)),$I$3<=$J$3,"") | P3: C#: Game/Effects/TierFx.cs:166; Game/Effects/TierFx.cs:172; Game/Effects/TierFx.cs:174; Game/Effects/TierFx.cs:177; Game/Effects/TierFx.cs:182; Game/Effects/TierFx.cs:185
A4: T2 | B4: bac | D4: 0 | E4: 2.5 | F4: 0 | G4: 12 | H4: 0.5 | L4: =IF(AND(ISNUMBER($D$4),$D$4>0),FLOOR($G$4/$D$4,1),"") | M4: =IF(ISNUMBER($C$4),IF(ISNUMBER($L$4),MIN($C$4,$L$4),$C$4),"") | N4: =IF(ISNUMBER($F$4),$F$4*$H$4,"") | O4: =IF(AND(ISNUMBER($I$4),ISNUMBER($J$4)),$I$4<=$J$4,"") | P4: C#: Game/Effects/TierFx.cs:166; Game/Effects/TierFx.cs:172; Game/Effects/TierFx.cs:174; Game/Effects/TierFx.cs:177; Game/Effects/TierFx.cs:182; Game/Effects/TierFx.cs:185
A5: T3 | B5: bac | C5: 6 | D5: 1 | E5: 2.5 | F5: 0 | G5: 12 | H5: 0.5 | L5: =IF(AND(ISNUMBER($D$5),$D$5>0),FLOOR($G$5/$D$5,1),"") | M5: =IF(ISNUMBER($C$5),IF(ISNUMBER($L$5),MIN($C$5,$L$5),$C$5),"") | N5: =IF(ISNUMBER($F$5),$F$5*$H$5,"") | O5: =IF(AND(ISNUMBER($I$5),ISNUMBER($J$5)),$I$5<=$J$5,"") | P5: C#: Game/Effects/TierFx.cs:166; Game/Effects/TierFx.cs:172; Game/Effects/TierFx.cs:174; Game/Effects/TierFx.cs:177; Game/Effects/TierFx.cs:182; Game/Effects/TierFx.cs:185
A6: T4 | B6: bac | C6: 3 | D6: 3 | E6: 4 | F6: 0.22 | G6: 12 | H6: 0.5 | L6: =IF(AND(ISNUMBER($D$6),$D$6>0),FLOOR($G$6/$D$6,1),"") | M6: =IF(ISNUMBER($C$6),IF(ISNUMBER($L$6),MIN($C$6,$L$6),$C$6),"") | N6: =IF(ISNUMBER($F$6),$F$6*$H$6,"") | O6: =IF(AND(ISNUMBER($I$6),ISNUMBER($J$6)),$I$6<=$J$6,"") | P6: C#: Game/Effects/TierFx.cs:166; Game/Effects/TierFx.cs:172; Game/Effects/TierFx.cs:174; Game/Effects/TierFx.cs:177; Game/Effects/TierFx.cs:182; Game/Effects/TierFx.cs:185
A7: T5 | B7: bac | C7: 1 | D7: 6 | E7: 6 | F7: 0.6 | G7: 12 | H7: 0.5 | L7: =IF(AND(ISNUMBER($D$7),$D$7>0),FLOOR($G$7/$D$7,1),"") | M7: =IF(ISNUMBER($C$7),IF(ISNUMBER($L$7),MIN($C$7,$L$7),$C$7),"") | N7: =IF(ISNUMBER($F$7),$F$7*$H$7,"") | O7: =IF(AND(ISNUMBER($I$7),ISNUMBER($J$7)),$I$7<=$J$7,"") | P7: C#: Game/Effects/TierFx.cs:166; Game/Effects/TierFx.cs:172; Game/Effects/TierFx.cs:174; Game/Effects/TierFx.cs:177; Game/Effects/TierFx.cs:182; Game/Effects/TierFx.cs:185
A8: hat_tong | B8: hat_tong | I8: =SUM(VFX_ngan_sach_hat!$D$2:$D$10) | K8: VFX_ngan_sach_hat | L8: =IF(AND(ISNUMBER($D$8),$D$8>0),FLOOR($G$8/$D$8,1),"") | M8: =IF(ISNUMBER($C$8),IF(ISNUMBER($L$8),MIN($C$8,$L$8),$C$8),"") | N8: =IF(ISNUMBER($F$8),$F$8*$H$8,"") | O8: =IF(AND(ISNUMBER($I$8),ISNUMBER($J$8)),$I$8<=$J$8,"") | P8: VFX_ngan_sach_hat (tổng)
A9: khoi_lon | B9: khoi_lon | I9: 3 | J9: 3 | K9: Game/Effects/ImpactSmoke.cs:22 | L9: =IF(AND(ISNUMBER($D$9),$D$9>0),FLOOR($G$9/$D$9,1),"") | M9: =IF(ISNUMBER($C$9),IF(ISNUMBER($L$9),MIN($C$9,$L$9),$C$9),"") | N9: =IF(ISNUMBER($F$9),$F$9*$H$9,"") | O9: =IF(AND(ISNUMBER($I$9),ISNUMBER($J$9)),$I$9<=$J$9,"") | P9: C#: Game/Effects/ImpactSmoke.cs:22; spec 09 VFX_ngan_sach

Sheet VFX_ngan_sach_hat
A1: id | B1: tep | C1: dong | D1: hat_toi_da | E1: nguon | F1: raw_json
A2: Game/Effects/Emitters.cs:86 | B2: Game/Effects/Emitters.cs | C2: 86 | D2: 1500 | E2: Game/Effects/Emitters.cs:86
A3: Game/Effects/Emitters.cs:101 | B3: Game/Effects/Emitters.cs | C3: 101 | D3: 2400 | E3: Game/Effects/Emitters.cs:101
A4: Game/Effects/Emitters.cs:119 | B4: Game/Effects/Emitters.cs | C4: 119 | D4: 200 | E4: Game/Effects/Emitters.cs:119
A5: Game/Effects/ExplosionEffect.cs:282 | B5: Game/Effects/ExplosionEffect.cs | C5: 282 | D5: 3000 | E5: Game/Effects/ExplosionEffect.cs:282
A6: Game/Effects/NightLights.cs:47 | B6: Game/Effects/NightLights.cs | C6: 47 | D6: 300 | E6: Game/Effects/NightLights.cs:47
A7: Game/Effects/NightLights.cs:162 | B7: Game/Effects/NightLights.cs | C7: 162 | D7: 8 | E7: Game/Effects/NightLights.cs:162
A8: Game/Effects/ParticleBuilder.cs:56 | B8: Game/Effects/ParticleBuilder.cs | C8: 56 | D8: 128 | E8: Game/Effects/ParticleBuilder.cs:56
A9: Game/Effects/StrikeEffects.cs:547 | B9: Game/Effects/StrikeEffects.cs | C9: 547 | D9: 220 | E9: Game/Effects/StrikeEffects.cs:547
A10: Game/Effects/TrackMarks.cs:22 | B10: Game/Effects/TrackMarks.cs | C10: 22 | D10: 4000 | E10: Game/Effects/TrackMarks.cs:22

Sheet Hieu_ung_tham_chieu
A1: id | B1: entity_id | C1: ten_hien_thi | D1: loai_tham_chieu | E1: ten_mau_that | F1: quoc_gia | G1: nam_dua_vao_su_dung | H1: ten_game | I1: co_che_game | J1: ten_phim_truyen | K1: diem_giong | L1: diem_khac_co_chu_dich | M1: ly_do_khac | N1: cam_giac_khac_khi_choi | O1: do_tin_cay | P1: nguon_id | Q1: ly_do | R1: ghi_chu_ban_quyen | S1: clip_ids | T1: nguon_am_thanh | U1: giay_phep | V1: dac_diem_tieng_that | W1: nguon | X1: raw_json
A2: am_thanh/Music/- | B2: Music/battle_1 | C2: âm thanh Music - | D2: NEED_SOURCE | O2: NEED_SOURCE | P2: R_credits;R_asset_licenses | Q2: nguồn ghi âm / tổng hợp đã có; đặc điểm tiếng thật của hệ thống tương ứng chưa có nguồn | R2: chỉ ở mức ý tưởng và thông số (sự kiện); không dùng tên, logo, văn bản, ảnh hay mô hình có bản quyền; tên và phù hiệu quốc gia thật không hiện cho người chơi | S2: Music/battle_1;Music/battle_2;Music/battle_3;Music/boss;Music/defeat;Music/menu;Music/siege;Music/victory | T2: Assets/MachineBrigade/Resources/Audio/Music/MUSIC_CREDITS.md | V2: NEED_SOURCE | W2: 07_hinh_anh_am_thanh_model/Am_thanh (nguon_goc, giay_phep)
A3: am_thanh/aircraft/- | B3: jet_loop/jet_loop_1 | C3: âm thanh aircraft - | D3: NEED_SOURCE | O3: NEED_SOURCE | P3: R_credits;R_asset_licenses;D_attack_aircraft_maneuvers;D_mig_15_uti;D_f16_maneuvers;D_jet_fighter_maneuvers | Q3: nguồn ghi âm / tổng hợp đã có; đặc điểm tiếng thật của hệ thống tương ứng chưa có nguồn | R3: chỉ ở mức ý tưởng và thông số (sự kiện); không dùng tên, logo, văn bản, ảnh hay mô hình có bản quyền; tên và phù hiệu quốc gia thật không hiện cho người chơi | S3: jet_loop/jet_loop_1;jet_pass/jet_pass_1;jet_pass/jet_pass_2;jet_pass/jet_pass_3;sfx/crash_fall/crash_fall_1;sfx/crash_fall/crash_fall_2;sfx/crash_impact/crash_impact_1;sfx/crash_impact/crash_impact_2 | T3: Attack Aircraft Maneuvers;F16 Maneuvers;Jet Fighter Maneuvers;MiG-15 UTI;tổng hợp / trộn bởi Tools/sfx/build_sfx.py (Audio/CREDITS.md) | U3: Sonniss GDC licence (no attribution);của dự án; lớp ghi âm theo Sonniss GDC (Audio/CREDITS.md) | V3: NEED_SOURCE | W3: 07_hinh_anh_am_thanh_model/Am_thanh (nguon_goc, giay_phep)
A4: am_thanh/ambience/- | B4: fire_loop/fire_loop_1 | C4: âm thanh ambience - | D4: NEED_SOURCE | O4: NEED_SOURCE | P4: R_credits;R_asset_licenses;D_the_burning_house_library;D_rain_and_thunder;D_thunder;D_essentials_01_thunder;D_wind | Q4: nguồn ghi âm / tổng hợp đã có; đặc điểm tiếng thật của hệ thống tương ứng chưa có nguồn | R4: chỉ ở mức ý tưởng và thông số (sự kiện); không dùng tên, logo, văn bản, ảnh hay mô hình có bản quyền; tên và phù hiệu quốc gia thật không hiện cho người chơi | S4: fire_loop/fire_loop_1;rain_loop/rain_loop_1;thunder/thunder_1;thunder/thunder_2;thunder/thunder_3;wind_loop/wind_loop_1 | T4: Essentials 01 Thunder;Rain and Thunder;The Burning House Library;Thunder;Wind | U4: Sonniss GDC licence (no attribution) | V4: NEED_SOURCE | W4: 07_hinh_anh_am_thanh_model/Am_thanh (nguon_goc, giay_phep)
A5: am_thanh/armour_metal/s1 | B5: sfx/hit_metal_light/hit_metal_light_1 | C5: âm thanh armour_metal s1 | D5: NEED_SOURCE | O5: NEED_SOURCE | P5: R_credits;R_asset_licenses | Q5: nguồn ghi âm / tổng hợp đã có; đặc điểm tiếng thật của hệ thống tương ứng chưa có nguồn | R5: chỉ ở mức ý tưởng và thông số (sự kiện); không dùng tên, logo, văn bản, ảnh hay mô hình có bản quyền; tên và phù hiệu quốc gia thật không hiện cho người chơi | S5: sfx/hit_metal_light/hit_metal_light_1;sfx/hit_metal_light/hit_metal_light_2;sfx/hit_metal_light/hit_metal_light_3 | T5: tổng hợp / trộn bởi Tools/sfx/build_sfx.py (Audio/CREDITS.md) | U5: của dự án; lớp ghi âm theo Sonniss GDC (Audio/CREDITS.md) | V5: NEED_SOURCE | W5: 07_hinh_anh_am_thanh_model/Am_thanh (nguon_goc, giay_phep)
A6: am_thanh/armour_metal/s3 | B6: sfx/hit_metal_heavy/hit_metal_heavy_1 | C6: âm thanh armour_metal s3 | D6: NEED_SOURCE | O6: NEED_SOURCE | P6: R_credits;R_asset_licenses | Q6: nguồn ghi âm / tổng hợp đã có; đặc điểm tiếng thật của hệ thống tương ứng chưa có nguồn | R6: chỉ ở mức ý tưởng và thông số (sự kiện); không dùng tên, logo, văn bản, ảnh hay mô hình có bản quyền; tên và phù hiệu quốc gia thật không hiện cho người chơi | S6: sfx/hit_metal_heavy/hit_metal_heavy_1;sfx/hit_metal_heavy/hit_metal_heavy_2;sfx/hit_metal_heavy/hit_metal_heavy_3 | T6: tổng hợp / trộn bởi Tools/sfx/build_sfx.py (Audio/CREDITS.md) | U6: của dự án; lớp ghi âm theo Sonniss GDC (Audio/CREDITS.md) | V6: NEED_SOURCE | W6: 07_hinh_anh_am_thanh_model/Am_thanh (nguon_goc, giay_phep)
A7: am_thanh/blast/- | B7: explosion_huge/explosion_huge_1 | C7: âm thanh blast - | D7: NEED_SOURCE | O7: NEED_SOURCE | P7: R_credits;R_asset_licenses;D_explosions;D_explosion_sfx_pack;D_eradication_small_pack;D_tank_explosion_sound_effects;D_guns_bullets_and_explosions;D_explosion_sound_pack;D_combat_drone;D_detonation_explosion;D_naval_warfare;D_guns;D_the_warfare_2_library | Q7: nguồn ghi âm / tổng hợp đã có; đặc điểm tiếng thật của hệ thống tương ứng chưa có nguồn | R7: chỉ ở mức ý tưởng và thông số (sự kiện); không dùng tên, logo, văn bản, ảnh hay mô hình có bản quyền; tên và phù hiệu quốc gia thật không hiện cho người chơi | S7: explosion_huge/explosion_huge_1;explosion_huge/explosion_huge_2;explosion_huge/explosion_huge_3;explosion_large/explosion_large_1;explosion_large/explosion_large_2;explosion_large/explosion_large_3;explosion_large/explosion_large_4;explosion_medium/explosion_medium_1;explosion_medium/explosion_medium_2;explosion_medium/explosion_medium_3;explosion_medium/explosion_medium_4;explosion_small/explosion_small_1;explosion_small/explosion_small_2;explosion_small/explosion_small_3;explosion_small/explosion_small_4 | T7: Combat Drone;Detonation - Explosion;Eradication - Small Pack;Explosion SFX Pack;Explosion Sound Pack;Explosions;Guns;Guns, Bullets and Explosions;Naval Warfare;Tank - Explosion Sound Effects;The Warfare 2 Library | U7: Sonniss GDC licence (no attribution) | V7: NEED_SOURCE | W7: 07_hinh_anh_am_thanh_model/Am_thanh (nguon_goc, giay_phep)
A8: am_thanh/blast/bomb | B8: sfx/blast_bomb/blast_bomb_1 | C8: âm thanh blast bomb | D8: NEED_SOURCE | O8: NEED_SOURCE | P8: R_credits;R_asset_licenses | Q8: nguồn ghi âm / tổng hợp đã có; đặc điểm tiếng thật của hệ thống tương ứng chưa có nguồn | R8: chỉ ở mức ý tưởng và thông số (sự kiện); không dùng tên, logo, văn bản, ảnh hay mô hình có bản quyền; tên và phù hiệu quốc gia thật không hiện cho người chơi | S8: sfx/blast_bomb/blast_bomb_1;sfx/blast_bomb/blast_bomb_2;sfx/blast_bomb/blast_bomb_3 | T8: tổng hợp / trộn bởi Tools/sfx/build_sfx.py (Audio/CREDITS.md) | U8: của dự án; lớp ghi âm theo Sonniss GDC (Audio/CREDITS.md) | V8: NEED_SOURCE | W8: 07_hinh_anh_am_thanh_model/Am_thanh (nguon_goc, giay_phep)
A9: am_thanh/blast/s1 | B9: sfx/blast_he_s1/blast_he_s1_1 | C9: âm thanh blast s1 | D9: NEED_SOURCE | O9: NEED_SOURCE | P9: R_credits;R_asset_licenses | Q9: nguồn ghi âm / tổng hợp đã có; đặc điểm tiếng thật của hệ thống tương ứng chưa có nguồn | R9: chỉ ở mức ý tưởng và thông số (sự kiện); không dùng tên, logo, văn bản, ảnh hay mô hình có bản quyền; tên và phù hiệu quốc gia thật không hiện cho người chơi | S9: sfx/blast_he_s1/blast_he_s1_1;sfx/blast_he_s1/blast_he_s1_2;sfx/blast_he_s1/blast_he_s1_3 | T9: tổng hợp / trộn bởi Tools/sfx/build_sfx.py (Audio/CREDITS.md) | U9: của dự án; lớp ghi âm theo Sonniss GDC (Audio/CREDITS.md) | V9: NEED_SOURCE | W9: 07_hinh_anh_am_thanh_model/Am_thanh (nguon_goc, giay_phep)
A10: am_thanh/blast/s2 | B10: sfx/blast_he_s2/blast_he_s2_1 | C10: âm thanh blast s2 | D10: NEED_SOURCE | O10: NEED_SOURCE | P10: R_credits;R_asset_licenses | Q10: nguồn ghi âm / tổng hợp đã có; đặc điểm tiếng thật của hệ thống tương ứng chưa có nguồn | R10: chỉ ở mức ý tưởng và thông số (sự kiện); không dùng tên, logo, văn bản, ảnh hay mô hình có bản quyền; tên và phù hiệu quốc gia thật không hiện cho người chơi | S10: sfx/blast_he_s2/blast_he_s2_1;sfx/blast_he_s2/blast_he_s2_2;sfx/blast_he_s2/blast_he_s2_3 | T10: tổng hợp / trộn bởi Tools/sfx/build_sfx.py (Audio/CREDITS.md) | U10: của dự án; lớp ghi âm theo Sonniss GDC (Audio/CREDITS.md) | V10: NEED_SOURCE | W10: 07_hinh_anh_am_thanh_model/Am_thanh (nguon_goc, giay_phep)
A11: am_thanh/blast/s3 | B11: sfx/blast_he_s3/blast_he_s3_1 | C11: âm thanh blast s3 | D11: NEED_SOURCE | O11: NEED_SOURCE | P11: R_credits;R_asset_licenses | Q11: nguồn ghi âm / tổng hợp đã có; đặc điểm tiếng thật của hệ thống tương ứng chưa có nguồn | R11: chỉ ở mức ý tưởng và thông số (sự kiện); không dùng tên, logo, văn bản, ảnh hay mô hình có bản quyền; tên và phù hiệu quốc gia thật không hiện cho người chơi | S11: sfx/blast_he_s3/blast_he_s3_1;sfx/blast_he_s3/blast_he_s3_2;sfx/blast_he_s3/blast_he_s3_3 | T11: tổng hợp / trộn bởi Tools/sfx/build_sfx.py (Audio/CREDITS.md) | U11: của dự án; lớp ghi âm theo Sonniss GDC (Audio/CREDITS.md) | V11: NEED_SOURCE | W11: 07_hinh_anh_am_thanh_model/Am_thanh (nguon_goc, giay_phep)
A12: am_thanh/blast/s4 | B12: sfx/blast_he_s4/blast_he_s4_1 | C12: âm thanh blast s4 | D12: NEED_SOURCE | O12: NEED_SOURCE | P12: R_credits;R_asset_licenses | Q12: nguồn ghi âm / tổng hợp đã có; đặc điểm tiếng thật của hệ thống tương ứng chưa có nguồn | R12: chỉ ở mức ý tưởng và thông số (sự kiện); không dùng tên, logo, văn bản, ảnh hay mô hình có bản quyền; tên và phù hiệu quốc gia thật không hiện cho người chơi | S12: sfx/blast_he_s4/blast_he_s4_1;sfx/blast_he_s4/blast_he_s4_2;sfx/blast_he_s4/blast_he_s4_3 | T12: tổng hợp / trộn bởi Tools/sfx/build_sfx.py (Audio/CREDITS.md) | U12: của dự án; lớp ghi âm theo Sonniss GDC (Audio/CREDITS.md) | V12: NEED_SOURCE | W12: 07_hinh_anh_am_thanh_model/Am_thanh (nguon_goc, giay_phep)
A13: am_thanh/blast/s406 | B13: sfx/blast_he_s406/blast_he_s406_1 | C13: âm thanh blast s406 | D13: NEED_SOURCE | O13: NEED_SOURCE | P13: R_credits;R_asset_licenses | Q13: nguồn ghi âm / tổng hợp đã có; đặc điểm tiếng thật của hệ thống tương ứng chưa có nguồn | R13: chỉ ở mức ý tưởng và thông số (sự kiện); không dùng tên, logo, văn bản, ảnh hay mô hình có bản quyền; tên và phù hiệu quốc gia thật không hiện cho người chơi | S13: sfx/blast_he_s406/blast_he_s406_1;sfx/blast_he_s406/blast_he_s406_2 | T13: tổng hợp / trộn bởi Tools/sfx/build_sfx.py (Audio/CREDITS.md) | U13: của dự án; lớp ghi âm theo Sonniss GDC (Audio/CREDITS.md) | V13: NEED_SOURCE | W13: 07_hinh_anh_am_thanh_model/Am_thanh (nguon_goc, giay_phep)
A14: am_thanh/blast/super | B14: sfx/blast_super/blast_super_1 | C14: âm thanh blast super | D14: NEED_SOURCE | O14: NEED_SOURCE | P14: R_credits;R_asset_licenses | Q14: nguồn ghi âm / tổng hợp đã có; đặc điểm tiếng thật của hệ thống tương ứng chưa có nguồn | R14: chỉ ở mức ý tưởng và thông số (sự kiện); không dùng tên, logo, văn bản, ảnh hay mô hình có bản quyền; tên và phù hiệu quốc gia thật không hiện cho người chơi | S14: sfx/blast_super/blast_super_1;sfx/blast_super/blast_super_2 | T14: tổng hợp / trộn bởi Tools/sfx/build_sfx.py (Audio/CREDITS.md) | U14: của dự án; lớp ghi âm theo Sonniss GDC (Audio/CREDITS.md) | V14: NEED_SOURCE | W14: 07_hinh_anh_am_thanh_model/Am_thanh (nguon_goc, giay_phep)
... A53: am_thanh/wreck/- | B53: collapse/collapse_1 | C53: âm thanh wreck - | D53: NEED_SOURCE | O53: NEED_SOURCE | P53: R_credits;R_asset_licenses;D_rocks;D_undoing_computer;D_rock_brick_and_dirt | Q53: nguồn ghi âm / tổng hợp đã có; đặc điểm tiếng thật của hệ thống tương ứng chưa có nguồn | R53: chỉ ở mức ý tưởng và thông số (sự kiện); không dùng tên, logo, văn bản, ảnh hay mô hình có bản quyền; tên và phù hiệu quốc gia thật không hiện cho người chơi | S53: collapse/collapse_1;collapse/collapse_2;debris/debris_1;debris/debris_2;debris/debris_3;sfx/wreck_aircraft/wreck_aircraft_1;sfx/wreck_aircraft/wreck_aircraft_2;sfx/wreck_artillery/wreck_artillery_1;sfx/wreck_artillery/wreck_artillery_2;sfx/wreck_drone/wreck_drone_1;sfx/wreck_drone/wreck_drone_2;sfx/wreck_heli/wreck_heli_1;sfx/wreck_heli/wreck_heli_2;sfx/wreck_ship/wreck_ship_1;sfx/wreck_ship/wreck_ship_2;sfx/wreck_tank/wreck_tank_1;sfx/wreck_tank/wreck_tank_2;sfx/wreck_truck/wreck_truck_1;sfx/wreck_truck/wreck_truck_2;sfx/wreck_wheeled/wreck_wheeled_1;sfx/wreck_wheeled/wreck_wheeled_2 | T53: Rock Brick and Dirt;Rocks;Undoing-Computer;tổng hợp / trộn bởi Tools/sfx/build_sfx.py (Audio/CREDITS.md) | U53: Sonniss GDC licence (no attribution);của dự án; lớp ghi âm theo Sonniss GDC (Audio/CREDITS.md) | V53: NEED_SOURCE | W53: 07_hinh_anh_am_thanh_model/Am_thanh (nguon_goc, giay_phep)
A54: vfx/T0 | B54: T0 | C54: VFX bậc T0 | D54: NEED_SOURCE | E54: NEED_SOURCE | O54: NEED_SOURCE | Q54: repo không ghi nguồn hình ảnh / video thật cho bậc này | R54: chỉ ở mức ý tưởng và thông số (sự kiện); không dùng tên, logo, văn bản, ảnh hay mô hình có bản quyền; tên và phù hiệu quốc gia thật không hiện cho người chơi | W54: spec 12.2 (09): VFX theo bậc
A55: vfx/T1 | B55: T1 | C55: VFX bậc T1 | D55: NEED_SOURCE | E55: NEED_SOURCE | O55: NEED_SOURCE | Q55: repo không ghi nguồn hình ảnh / video thật cho bậc này | R55: chỉ ở mức ý tưởng và thông số (sự kiện); không dùng tên, logo, văn bản, ảnh hay mô hình có bản quyền; tên và phù hiệu quốc gia thật không hiện cho người chơi | W55: spec 12.2 (09): VFX theo bậc
A56: vfx/T2 | B56: T2 | C56: VFX bậc T2 | D56: NEED_SOURCE | E56: NEED_SOURCE | O56: NEED_SOURCE | Q56: repo không ghi nguồn hình ảnh / video thật cho bậc này | R56: chỉ ở mức ý tưởng và thông số (sự kiện); không dùng tên, logo, văn bản, ảnh hay mô hình có bản quyền; tên và phù hiệu quốc gia thật không hiện cho người chơi | W56: spec 12.2 (09): VFX theo bậc
A57: vfx/T3 | B57: T3 | C57: VFX bậc T3 | D57: NEED_SOURCE | E57: NEED_SOURCE | O57: NEED_SOURCE | Q57: repo không ghi nguồn hình ảnh / video thật cho bậc này | R57: chỉ ở mức ý tưởng và thông số (sự kiện); không dùng tên, logo, văn bản, ảnh hay mô hình có bản quyền; tên và phù hiệu quốc gia thật không hiện cho người chơi | W57: spec 12.2 (09): VFX theo bậc
A58: vfx/T4 | B58: T4 | C58: VFX bậc T4 | D58: NEED_SOURCE | E58: NEED_SOURCE | O58: NEED_SOURCE | Q58: repo không ghi nguồn hình ảnh / video thật cho bậc này | R58: chỉ ở mức ý tưởng và thông số (sự kiện); không dùng tên, logo, văn bản, ảnh hay mô hình có bản quyền; tên và phù hiệu quốc gia thật không hiện cho người chơi | W58: spec 12.2 (09): VFX theo bậc
A59: vfx/T5 | B59: T5 | C59: VFX bậc T5 | D59: NEED_SOURCE | E59: NEED_SOURCE | O59: NEED_SOURCE | Q59: repo không ghi nguồn hình ảnh / video thật cho bậc này | R59: chỉ ở mức ý tưởng và thông số (sự kiện); không dùng tên, logo, văn bản, ảnh hay mô hình có bản quyền; tên và phù hiệu quốc gia thật không hiện cho người chơi | W59: spec 12.2 (09): VFX theo bậc

Sheet Model
A1: id | B1: loai | C1: lop_ngan_sach | D1: tam_giac | E1: so_nut | F1: so_part | G1: so_mount | H1: so_muzzle | I1: co_mount_flare | J1: co_mount_aps | K1: vat_lieu | L1: mesh | M1: glb_x_m | N1: glb_y_m | O1: glb_z_m | P1: duong_dan | Q1: tam_giac_lod | R1: anh_3_goc | S1: anh_3_goc_trang_thai | T1: nguon | U1: raw_json
A2: aa_gun_tower | B2: structure | C2: tower | D2: 5924 | E2: 48 | F2: 0 | G2: 0 | H2: 2 | I2: FALSE | J2: FALSE | K2: Hazard;Steel;Armor;Undercarriage;Glass;Team;Canvas;Dirt;Wood;Sandbag;BarrelRed;Crate | L2: Clip_rounds;Clips;Cradle;Elevation_arc;Loader;Main_cannon;Muzzle_brake;Glass;Handwheels;Kit_handles;Kit_rivets;Mount;Pedals;Seat_posts;Seats;Shield;Shield_struts;Sights;Base;Base_timbers;Sandbags;Pad;Turntable;Jacks;Race;Kit_bolts;Radar_post;Radar_box;Radar_dish;Radar_feed;Kit_cables;Clip_racks;Clip_rounds.001;Clip_tips;Extinguishers;Toolbox;Kit_latches;Crates;Kit_straps;Spent_cases;Stakes;Field_phone;Antennas;Tarp;Kit_straps.001 | M2: 5.127 | N2: 5.412 | O2: 3.183 | P2: Assets/MachineBrigade/Resources/Models/aa_gun_tower.glb | Q2: KHONG_AP_DUNG | R2: Docs/models/rebuild/aa_gun_tower/unity_scan.png | S2: present | T2: Assets/MachineBrigade/Resources/Models/aa_gun_tower.glb | U2: {"triangles":5924}
A3: aa_gun_vehicle | B3: ground | C3: ground | D3: 8256 | E3: 51 | F3: 0 | G3: 0 | H3: 2 | I3: FALSE | J3: FALSE | K3: Steel;Glass;Armor;Undercarriage;Team;Rubber;Lamp;LavaGlow | L3: Antennas;Glass.001;Hatches.001;Kit_latches.001;Kit_steel.001;Main_cannon;Main_cannon_holes;Mantlet;MG_coax;Muzzle_brake;Radar_face;Radar_panel;Radar_mast;Sight.001;Smoke_brackets;Smoke_launchers;Stowage.001;Team_band.001;Turret_body;Turret_roof;Hull;Skirts;Skirt_flaps;Team_band;Hatches;Kit_steel;Sight;Glass;Grille_frames;Grilles;Lamp_rims;Lamps;Lamp_guards;Exhaust;Tail_lamps;Stowage;Kit_latches;Tracks;Track_links;Tyres;Wheels;Hubs;Sprockets;Idlers;Rollers;Turret_ring | M3: 6.111 | N3: 2.637 | O3: 2.777 | P3: Assets/MachineBrigade/Resources/Models/aa_gun_vehicle.glb | Q3: KHONG_AP_DUNG | R3: Docs/models/rebuild/aa_gun_vehicle/unity_scan.png | S3: present | T3: Assets/MachineBrigade/Resources/Models/aa_gun_vehicle.glb | U3: {"triangles":8256}
A4: aa_turret | B4: structure | C4: tower | D4: 5202 | E4: 55 | F4: 0 | G4: 0 | H4: 4 | I4: FALSE | J4: FALSE | K4: Alloy;Armor;Undercarriage;Steel;Glass;Canvas;Team;Concrete;Dirt;Sandbag;Grass;Wood;Crate;BarrelRed;FoliageDark | L4: Beacon;Beacon_base;Beacons;Gun_casing_chutes;Gun_cradle;Gun_sleeves;Main_cannon;Main_cannon_2;Muzzle_brake;Muzzle_brake_2;Glass;Hatches;Kit_steel;Launcher_arm;Launcher_caps;Launcher_grips;Launcher_tubes;Radar_dish;Radar_feed;Radar_mast;Sight;Turret_armor;Turret_body;Turret_steel;Base;Base_ties;Plinth;Race;Team_band;Berm;Sandbags;Berm_turf;Duckboards;Pallets;Ammo_boxes;Kit_handles;Tarp;Kit_straps;Masts;Phone_box;Kit_cables;Antennas;Extinguisher;Tools_wood;Tools_steel;Helmets;Casings;Net_poles;Camo_net;Camo_net_garnish | M4: 5.456 | N4: 4.748 | O4: 3.107 | P4: Assets/MachineBrigade/Resources/Models/aa_turret.glb | Q4: KHONG_AP_DUNG | R4: Docs/models/rebuild/aa_turret/unity_scan.png | S4: present | T4: Assets/MachineBrigade/Resources/Models/aa_turret.glb | U4: {"triangles":5202}
A5: aa_turret_a | B5: structure | C5: tower | D5: 5952 | E5: 58 | F5: 0 | G5: 0 | H5: 6 | I5: FALSE | J5: FALSE | K5: Alloy;Armor;Steel;Undercarriage;Glass;Canvas;Team;Concrete;Dirt;Sandbag;Grass;Wood;Crate;BarrelRed;FoliageDark | L5: Beacon;Beacon_base;Beacons;Cupola;Barrel_jackets;Gun_sleeves;Main_cannon;Main_cannon_2;Main_cannon_3;Main_cannon_4;Mantlet;Muzzle_brake;Muzzle_brake_2;Muzzle_brake_3;Muzzle_brake_4;Glass;Hatch_fittings;Hatches;Kit_steel;Radar_dish;Radar_feed;Radar_mast;Sight;Stowage;Turret_armor;Turret_body;Turret_steel;Base;Base_ties;Plinth;Race;Team_band;Berm;Sandbags;Berm_turf;Duckboards;Pallets;Ammo_boxes;Kit_handles;Tarp;Kit_straps;Masts;Phone_box;Kit_cables;Antennas;Extinguisher;Tools_wood;Tools_steel;Helmets;Casings;Net_poles;Camo_net;Camo_net_garnish | M5: 5.484 | N5: 4.748 | O5: 3.107 | P5: Assets/MachineBrigade/Resources/Models/aa_turret_a.glb | Q5: KHONG_AP_DUNG | R5: Docs/models/rebuild/aa_turret_a/unity_scan.png | S5: present | T5: Assets/MachineBrigade/Resources/Models/aa_turret_a.glb | U5: {"triangles":5952}
A6: aa_turret_b | B6: structure | C6: tower | D6: 2852 | E6: 50 | F6: 0 | G6: 0 | H6: 5 | I6: FALSE | J6: FALSE | K6: Fuel;Team;Undercarriage;Glass;Steel;Armor;Canvas;Dirt;Sandbag;Charred;Grass;Crate;Rock;Sandstone;SandstoneDark;FoliageDark;FoliageLight;Wood;Foliage;PlasterWhite | L6: Battery_boxes;Launcher_frame;Round_1;Round_2;Round_3;Round_4;Tube_bodies;Tube_bores;Glass;Kit_handles;Radar_array;Radar_face;Seats;Sight;Turret_socket;Turret_steel;Base;Sandbags;Sandbags_new;Stains;Turf;Ammo_boxes;Kit_latches;Stones;Ground_sandstone;Ground_rock;Ground_sandstonedark;Ground_foliagedark;Ground_foliagelight;Duckboards;Race;Rocket_rack;Missile_cases;Radio_box;Antennas;Kit_cables;Jerrycans;Net_poles;Camo_net;Camo_garnish;Signs;Sign_posts | M6: 4.704 | N6: 4.767 | O6: 2.887 | P6: Assets/MachineBrigade/Resources/Models/aa_turret_b.glb | Q6: KHONG_AP_DUNG | R6: Docs/models/rebuild/aa_turret_b/unity_scan.png | S6: present | T6: Assets/MachineBrigade/Resources/Models/aa_turret_b.glb | U6: {"triangles":2852}
A7: aa_vehicle | B7: ground | C7: ground | D7: 11760 | E7: 78 | F7: 0 | G7: 1 | H7: 6 | I7: FALSE | J7: FALSE | K7: Steel;Armor;Team;Undercarriage;Glass;Lamp;Rubber;LavaGlow | L7: Antennas;Cradle;Gun_feeds;Gun_housing;Gun_housing_lids;Kit_hinges;Kit_rivets.001;Main_cannon;Main_cannon_2;Muzzle_brake;Muzzle_brake_2;Trunnions;Glass.001;Hatches.001;Iff_antenna;Kit_latches.001;Kit_rivets;Kit_steel.001;Lamp_rims.001;Lamps.001;Launcher_box;Launcher_covers;Launcher_post;Radar_dish;Radar_drive;Radar_feed;Radar_mast;Radar_tracker;Radar_tracker_face;Radar_tracker_feed;Sight.001;Sight.002;Smoke_brackets;Smoke_launchers;Stowage.001;Team_band.001;Turret_armor;Turret_body;Turret_roof;Hull;Hull_lower;Fenders;Skirts;Skirt_flaps;Team_band;Hatches;Kit_steel;Sight;Glass;Lamp_rims;Lamps;Lamp_guards;Grille_frames;Grilles;Deck_plates;Tail_lamps;Stowage;Kit_latches;Tow_cable;Tracks;Track_links;Tyres;Wheels;Hubs;Sprockets;Idlers;Rollers;Turret_ring | M7: 6.41 | N7: 2.805 | O7: 2.732 | P7: Assets/MachineBrigade/Resources/Models/aa_vehicle.glb | Q7: KHONG_AP_DUNG | R7: Docs/models/rebuild/aa_vehicle/unity_scan.png | S7: present | T7: Assets/MachineBrigade/Resources/Models/aa_vehicle.glb | U7: {"triangles":11760}
A8: aa_vehicle_hd | B8: ground | C8: ground | D8: 11940 | E8: 78 | F8: 0 | G8: 1 | H8: 6 | I8: FALSE | J8: FALSE | K8: Steel;Armor;Team;Undercarriage;Glass;Lamp;Rubber;LavaGlow | L8: Antennas;Cradle;Gun_feeds;Gun_housing;Gun_housing_lids;Kit_hinges;Kit_rivets.001;Main_cannon;Main_cannon_2;Muzzle_brake;Muzzle_brake_2;Trunnions;Glass.001;Hatches.001;Iff_antenna;Kit_latches.001;Kit_rivets;Kit_steel.001;Lamp_rims.001;Lamps.001;Launcher_box;Launcher_covers;Launcher_post;Radar_dish;Radar_drive;Radar_feed;Radar_mast;Radar_tracker;Radar_tracker_face;Radar_tracker_feed;Sight.001;Sight.002;Smoke_brackets;Smoke_launchers;Stowage.001;Team_band.001;Turret_armor;Turret_body;Turret_roof;Hull;Hull_lower;Fenders;Skirts;Skirt_flaps;Team_band;Hatches;Kit_steel;Sight;Glass;Lamp_rims;Lamps;Lamp_guards;Grille_frames;Grilles;Deck_plates;Tail_lamps;Stowage;Kit_latches;Tow_cable;Tracks;Track_links;Tyres;Wheels;Hubs;Sprockets;Idlers;Rollers;Turret_ring | M8: 6.41 | N8: 2.805 | O8: 2.732 | P8: Assets/MachineBrigade/Resources/Models/aa_vehicle_hd.glb | Q8: KHONG_AP_DUNG | R8: Builds/scan/aa_vehicle_hd.png | S8: pending | T8: Assets/MachineBrigade/Resources/Models/aa_vehicle_hd.glb | U8: {"triangles":11940}
A9: adobe_house | B9: prop | C9: prop | D9: 1660 | E9: 19 | F9: 0 | G9: 0 | H9: 0 | I9: FALSE | J9: FALSE | K9: AdobeTrim;Adobe;Wood;Armor;Glass;Lamp;Steel;PlasterBlue;Brick | L9: Plinth;Stair;Walls;Parapet;Roof_deck;Vigas;Reveals;Door;Straps;Lintels;Windows;Lit_windows;Canales;Tank_stand;Water_tank;Tank_lid;Chimney;Jars;Bench | M9: 7.234 | N9: 7.27 | O9: 5.04 | P9: Assets/MachineBrigade/Resources/Models/adobe_house.glb | Q9: KHONG_AP_DUNG | R9: Builds/scan/adobe_house.png | S9: pending | T9: Assets/MachineBrigade/Resources/Models/adobe_house.glb | U9: {"triangles":1660}
A10: adobe_large | B10: prop | C10: prop | D10: 3946 | E10: 28 | F10: 0 | G10: 0 | H10: 0 | I10: FALSE | J10: FALSE | K10: AdobeTrim;Adobe;Wood;Charred;Armor;PlasterWhite;Glass;Lamp;Canvas;Steel;Fuel;Brick;Hazard | L10: Plinth;Stair;Walls;Parapet;Roof_deck;Vigas;Portal;Portal_recess;Door;Straps;Moulding;Reveals;Windows;Lintels;Lit_windows;Oriel;Oriel_screen;Awning;Poles;Ladder;Canales;Tank_stand;Water_tank;Tank_lid;Chimney;Jars;Crates;Produce | M10: 9.325 | N10: 11.77 | O10: 9.76 | P10: Assets/MachineBrigade/Resources/Models/adobe_large.glb | Q10: KHONG_AP_DUNG | R10: Builds/scan/adobe_large.png | S10: pending | T10: Assets/MachineBrigade/Resources/Models/adobe_large.glb | U10: {"triangles":3946}
A11: aim9 | B11: unlisted | D11: 238 | E11: 10 | F11: 0 | G11: 0 | H11: 0 | I11: FALSE | J11: FALSE | K11: Glass;MetalSheet;Fuel;Hazard;LogWood;Undercarriage;Alloy;Steel | L11: Seeker;Seeker_section;Body;Band;Band_motor;Nozzle;Motor;Canards;Wings;Rollerons | M11: 2.2 | N11: 0.287 | O11: 0.287 | P11: Assets/MachineBrigade/Resources/Models/aim9.glb | Q11: KHONG_AP_DUNG | R11: Builds/scan/aim9.png | S11: pending | T11: Assets/MachineBrigade/Resources/Models/aim9.glb | U11: {"triangles":238}
A12: aim120 | B12: munition | C12: munition | D12: 222 | E12: 8 | F12: 0 | G12: 0 | H12: 0 | I12: FALSE | J12: FALSE | K12: MetalSheet;Fuel;Hazard;LogWood;Undercarriage;Alloy | L12: Radome;Body;Band;Band_motor;Nozzle;Motor;Wings;Fins | M12: 2.6 | N12: 0.235 | O12: 0.235 | P12: Assets/MachineBrigade/Resources/Models/aim120.glb | Q12: KHONG_AP_DUNG | R12: Builds/scan/aim120.png | S12: pending | T12: Assets/MachineBrigade/Resources/Models/aim120.glb | U12: {"triangles":222}
A13: aircraft_hangar | B13: structure | C13: structure | D13: 10154 | E13: 93 | F13: 0 | G13: 0 | H13: 0 | I13: FALSE | J13: FALSE | K13: Concrete;Undercarriage;PlasterWhite;Hazard;SignalGreen;Steel;Armor;Alloy;Sandbag;Fuel;BarrelRed;Rubber;Team;CraneYellow;Canvas;Crate;Glass;Lamp | L13: Base;Base_joints;Pad_marks;Taxi_line;Pad_edge;Edge_lights;Tie_downs;Mast;Mast_bands;Windsock;Beacon_base;Beacons;Kit_guys;Mast_legs;Mast_bracing;Antennas;Link_dish;Link_feed;Cones;Revetment;Fuel_tank;Tank_cradle;Fuel_pump;Hazard_marks;Hose_reel;Kit_cables;Spill_kit;Ground_power;Grille_frames;Grilles;Tyres;Fire_cart;Fire_cart_frame;Chocks;Roof;Arch_ribs;Fabric_seams;Walls;Interior;Purlins;Ventilators;Lightning_rods;Cable_tray;Door_frames;Doors;Door_slots;Kit_hinges;Ladders;Aircon;Aircon_fan;Hvac_duct;Anchors;Team_band;Kit_straps;Doors.001;Door_guides;Door_rollers;Side_door;Side_step;Work_stand;Work_stand_rails;Work_stand_steps;Tool_chests;Spares;Gantry;Hoist_trolley;Hoist_chain;Hoist_hook;Spare_engine;Engine_dolly;Tug;Glass;Tug_beacon;Tow_bar;Light_poles;Light_housing;Lamps;Kit_cables.001;Sandbags;Small_parts;Front_band;Light_arms;Shelving;Bins;Drums;Drum_bands;Wheel_dollies;Blade_rack;Rotor_blades;Blade_covers;Tool_cart;Lamp_rims;Lamp_guards | M13: 8.512 | N13: 8.334 | O13: 5.585 | P13: Assets/MachineBrigade/Resources/Models/aircraft_hangar.glb | Q13: KHONG_AP_DUNG | R13: Docs/models/rebuild/aircraft_hangar/unity_scan.png | S13: present | T13: Assets/MachineBrigade/Resources/Models/aircraft_hangar.glb | U13: {"triangles":10154}
A14: ammo_carrier | B14: ground | C14: ground | D14: 7492 | E14: 63 | F14: 0 | G14: 0 | H14: 2 | I14: FALSE | J14: FALSE | K14: Crate;Armor;Steel;Undercarriage;Rubber;Team;Alloy;Lamp;Glass;MetalSheet;LavaGlow;Wood;Hazard | L14: Ammo_can;Cradle;Gun_carriage;Gun_fit;Gun_shield;Main_cannon;Muzzle_brake;Receiver;Chassis;Suspension;Tyres;Wheels;Hubs;Axles;Fenders;Mudflaps;Kit_hooks;Fuel_tanks;Kit_straps;Toolbox;Kit_latches;Cab;Cab_dark;Marker_lamps;Grille_frames;Grilles;Bumper;Lamp_rims;Lamps;Lamps.001;Glass;Window_frames;Wipers;Cab_fit;Steps;Mirrors;Team_band;Engine_housing;Grille_frames.001;Air_cleaner;Exhaust;Exhaust_caps;Bed;Bed_floor;Bed_sides;Rack;Crane_platform;Tail_lamps;Tail_lenses;Pallets;Ammo_boxes;Crane;Crane_boom;Crane_rams;Crane_hazard;Kit_cables;Crane_controls;Gun_ring;Gun_ring_fit | M14: 8.739 | N14: 2.173 | O14: 2.689 | P14: Assets/MachineBrigade/Resources/Models/ammo_carrier.glb | Q14: KHONG_AP_DUNG | R14: Docs/models/rebuild/ammo_carrier/unity_scan.png | S14: present | T14: Assets/MachineBrigade/Resources/Models/ammo_carrier.glb | U14: {"triangles":7492}
A15: ammo_crate | B15: prop | C15: prop | D15: 496 | E15: 3 | F15: 0 | G15: 0 | H15: 0 | I15: FALSE | J15: FALSE | K15: Crate;Steel;Hazard | L15: Body;Frame;Band | M15: 1.163 | N15: 1.33 | O15: 1.26 | P15: Assets/MachineBrigade/Resources/Models/ammo_crate.glb | Q15: KHONG_AP_DUNG | R15: Builds/scan/ammo_crate.png | S15: pending | T15: Assets/MachineBrigade/Resources/Models/ammo_crate.glb | U15: {"triangles":496}
A16: ammo_dump | B16: prop | C16: prop | D16: 5284 | E16: 41 | F16: 0 | G16: 0 | H16: 0 | I16: FALSE | J16: FALSE | K16: Dirt;Wood;Steel;Armor;Undercarriage;Corrugated;Sandbag;Lamp;Foliage;Hazard;Charred;Crate;Gilded;Canvas;BarrelRed;PlasterWhite | L16: Base;Berm;Revetment;Door_frames;Doors;Door_slots;Kit_hinges;Roof;Sandbags;Antennas;Vent;Lamp_rims;Lamps;Lamp_guards;Turf;Wattle;Ditch;Steps;Signs;Sign_marks;Crates;Crate_bands;Pallets;Traverse;Traverse_fill;Shell_cases;Shell_heads;Net_poles;Camo_net;Camo_garnish;Guy_ropes;Flag_pole;Flag;Extinguisher_stand;Extinguishers;Fire_bucket;Loose_rounds;Trolley;Phone_post;Field_phone;Tally_board | M16: 5 | N16: 6.269 | O16: 3.5 | P16: Assets/MachineBrigade/Resources/Models/ammo_dump.glb | Q16: KHONG_AP_DUNG | R16: Docs/models/rebuild/ammo_dump/unity_scan.png | S16: present | T16: Assets/MachineBrigade/Resources/Models/ammo_dump.glb | U16: {"triangles":5284}
A17: apartment | B17: prop | C17: prop | D17: 6128 | E17: 20 | F17: 0 | G17: 0 | H17: 0 | I17: FALSE | J17: FALSE | K17: Brick;Concrete;RoofSlate;PlasterWhite;Glass;Lamp;Steel;Fuel;Rubber;Armor;MetalSheet | L17: Walls;Trim;Roof_deck;Frames;Windows;Sills;Lit_windows;Balcony_panels;Frames.001;Posts;Door_lamp;AC;AC_fan;Pipes;Door_frame;Door;Roof_steel;Tank;Tank_lid;Roof_AC | M17: 10.395 | N17: 13.825 | O17: 14.76 | P17: Assets/MachineBrigade/Resources/Models/apartment.glb | Q17: KHONG_AP_DUNG | R17: Builds/scan/apartment.png | S17: pending | T17: Assets/MachineBrigade/Resources/Models/apartment.glb | U17: {"triangles":6128}
A18: apc | B18: unlisted | D18: 7006 | E18: 44 | F18: 0 | G18: 0 | H18: 4 | I18: FALSE | J18: FALSE | K18: Steel;Armor;Undercarriage;Glass;Team;Rubber;Lamp;Alloy;Canvas;TeamGlow | L18: Coax;Hatch_fittings.001;Hatches.001;Launcher;Main_cannon;Muzzle_brake;Sight;Tubes;Tubes_bore;Turret_armor;Turret_body;Turret_steel;Hull;Armor;Steel;Chassis;Tyres;Hubs;Mud_flaps;Light_housing;Lamps;Light_guards;Tail_lights;Grab_rails;Periscope_hoods;Periscope;Stowage;Stowage_lid;Latches;Slat_armour;Hatches;Hatch_fittings;Vision_blocks;Deck;Grille_frames;Tarp;Straps;Tow_cable;Antenna;Beacon | M18: 7.153 | N18: 2.842 | O18: 3.306 | P18: Assets/MachineBrigade/Resources/Models/apc.glb | Q18: KHONG_AP_DUNG | R18: Builds/scan/apc.png | S18: pending | T18: Assets/MachineBrigade/Resources/Models/apc.glb | U18: {"triangles":7006}
A19: apc_hd | B19: unlisted | D19: 14968 | E19: 60 | F19: 0 | G19: 0 | H19: 4 | I19: FALSE | J19: FALSE | K19: Steel;Armor;Undercarriage;Glass;Team;Rubber;Lamp;Alloy;Canvas;TeamGlow | L19: Coax;Hatch_fittings.001;Hatches.001;Launcher;Lifting_eyes;Main_cannon;Muzzle_brake;Sight;Smoke_bores;Tubes;Tubes_bore;Turret_armor;Turret_body;Turret_bolts;Turret_steel;Vents;Hull;Armor;Steel;Chassis;Tyres;Tread;Hubs;Wheel_nuts;Mud_flaps;Light_housing;Lamps;Light_bezels;Light_guards;Tail_lights;Grab_rails;Rail_feet;Periscope_hoods;Periscope;Periscope_guards;Stowage;Stowage_lid;Latches;Stowage_ribs;Slat_armour;Hatches;Hatch_fittings;Vision_blocks;Deck;Grille_frames;Grille_bolts;Tarp;Straps;Strap_buckles;Tow_cable;Cable_clamps;Antenna;Beacon;Antenna_base;Hull_bolts;Shackles | M19: 7.153 | N19: 2.842 | O19: 3.314 | P19: Assets/MachineBrigade/Resources/Models/apc_hd.glb | Q19: KHONG_AP_DUNG | R19: Builds/scan/apc_hd.png | S19: pending | T19: Assets/MachineBrigade/Resources/Models/apc_hd.glb | U19: {"triangles":14968}
A20: apfsds | B20: unlisted | D20: 94 | E20: 5 | F20: 0 | G20: 0 | H20: 0 | I20: FALSE | J20: FALSE | K20: Steel;Undercarriage;Lamp | L20: Tip;Rod;Nozzle;Motor;Fins | M20: 1 | N20: 0.097 | O20: 0.112 | P20: Assets/MachineBrigade/Resources/Models/apfsds.glb | Q20: KHONG_AP_DUNG | R20: Builds/scan/apfsds.png | S20: pending | T20: Assets/MachineBrigade/Resources/Models/apfsds.glb | U20: {"triangles":94}
A21: aps_tank | B21: unlisted | D21: 7958 | E21: 55 | F21: 0 | G21: 1 | H21: 4 | I21: FALSE | J21: FALSE | K21: Crate;Steel;Armor;Undercarriage;TeamGlow;Glass;Canvas;Team;Lamp;Alloy | L21: Ammo_boxes;Antenna;Aps_launcher;Aps_radar;Aps_radar_face;Aps_tube;Aps_tube_bore;Basket.001;Basket_floor.001;Beacon;Chains;Coax;Cupola_top;Hatch_fittings.001;Hatches.001;Main_cannon;MG;MG_ammo;MG_shield;Muzzle_brake;Periscope;Sight;Straps;Tarp;Turret_armor;Turret_body;Turret_steel;Tracks;Tyres;Wheels;Sprockets;Hubs;Hull;Armor;Steel;Deck;Skirts;Skirt_edge;Lamps;Light_housing;Tail_lights;Basket;Basket_floor;Hatches;Hatch_fittings;Vision_blocks;Grille_frames;Tow_cable | M21: 9.5 | N21: 3.73 | O21: 4.102 | P21: Assets/MachineBrigade/Resources/Models/aps_tank.glb | Q21: KHONG_AP_DUNG | R21: Builds/scan/aps_tank.png | S21: pending | T21: Assets/MachineBrigade/Resources/Models/aps_tank.glb | U21: {"triangles":7958}
A22: armed_truck | B22: unlisted | D22: 3216 | E22: 25 | F22: 0 | G22: 0 | H22: 1 | I22: FALSE | J22: FALSE | K22: Armor;Steel;Team;Undercarriage;Glass;Rubber;Lamp;Alloy;PlasterWhite;Fuel;BarrelRed | L22: RWS_body;RWS_gun;RWS_ring;Cab;Chassis;Glass;Rubber_trim;Trim;Ribs;Headlights;Handles;Marker_lights;Plate;Cargo;Stripe;Mud_flaps;Taillights;Fuel_tank;Wheels;Hubs;Hub_caps;Arches;Ring_mount | M22: 7.615 | N22: 2.72 | O22: 3.51 | P22: Assets/MachineBrigade/Resources/Models/armed_truck.glb | Q22: KHONG_AP_DUNG | R22: Builds/scan/armed_truck.png | S22: pending | T22: Assets/MachineBrigade/Resources/Models/armed_truck.glb | U22: {"triangles":3216}
A23: armored_bulldozer | B23: ground | C23: ground | D23: 9246 | E23: 65 | F23: 0 | G23: 1 | H23: 1 | I23: FALSE | J23: FALSE | K23: Crate;Armor;Glass;Steel;Undercarriage;Hazard;Team;Lamp;LavaGlow;Fuel | L23: Ammo_boxes;Cradle;Glass.001;Gun_belt;Gun_bracket;Gun_shield;MG_barrel;MG_brake;MG_receiver;Sight;Blade_arms;Blade_back;Blade_edge;Blade_marks;Blade_moldboard;Blade_pins;Blade_rams;Tracks;Track_links;Tyres;Wheels;Hubs;Sprockets;Idlers;Rollers;Track_frames;Skirts;Kit_steel;Equaliser;Hull;Grille_frames;Grilles;Hood_plates;Lamp_rims;Lamps;Lamp_guards;Exhaust_stack;Exhaust_shield;Chassis;Fuel_tank;Ripper;Ripper_shank;Ripper_tooth;Tail_lamps;Casemate;Cab_roof;Glass;Grilles.001;Smoke_launchers;Sensor;Hatches;Gun_post;Antennas;Team_band;Stowage;Kit_latches;Jerrycans;Kit_racks;Tow_cable;Kit_reel | M23: 6.283 | N23: 3.7 | O23: 3.525 | P23: Assets/MachineBrigade/Resources/Models/armored_bulldozer.glb | Q23: KHONG_AP_DUNG | R23: Docs/models/rebuild/armored_bulldozer/unity_scan.png | S23: present | T23: Assets/MachineBrigade/Resources/Models/armored_bulldozer.glb | U23: {"triangles":9246}
A24: armored_car | B24: ground | C24: ground | D24: 6804 | E24: 53 | F24: 2 | G24: 0 | H24: 3 | I24: FALSE | J24: FALSE | K24: Steel;Glass;Armor;Team;Rubber;Lamp;LavaGlow;Undercarriage | L24: Coax;Glass.001;Hatches.001;Kit_steel.001;Main_cannon;Mantlet;Muzzle_brake;Sight;Smoke_launchers;Team_band.001;Turret_body;Turret_roof;Hubs.001;Tyres.001;Wheel_nuts.001;Wheels.001;Hubs.002;Tyres.002;Wheel_nuts.002;Wheels.002;Hull;Hull_lower;Team_band;Hatches;Kit_steel;Glass;Lamp_rims;Lamps;Lamp_guards;Tail_lamps;Trim_plate;Doors;Steps;Grille_frames;Grilles;Stowage;Kit_latches;Antennas;Axles;Tyres;Wheels;Wheel_nuts;Hubs;Suspension;Fender_flares;Turret_ring | M24: 4.874 | N24: 2.038 | O24: 1.555 | P24: Assets/MachineBrigade/Resources/Models/armored_car.glb | Q24: KHONG_AP_DUNG | R24: Docs/models/rebuild/armored_car/unity_scan.png | S24: present | T24: Assets/MachineBrigade/Resources/Models/armored_car.glb | U24: {"triangles":6804}
A25: armored_train | B25: boss | C25: boss_m | D25: 56714 | E25: 176 | F25: 1 | G25: 5 | H25: 8 | I25: FALSE | J25: FALSE | K25: Crate;Armor;Steel;Rubber;Glass;Undercarriage;Team;PlasterWhite;Fuel;Charred;Hazard;Lamp;Alloy;Sandbag;BarrelRed;Wood;SafetyStripe;CraneYellow;Canvas;LavaGlow | L25: Quad_ammo_001;Quad_base_001;Quad_frame_001;Quad_grips_001;Quad_guns_001;Quad_jackets_001;Quad_sight_001;Antenna.001;Glass;Kit_rivets.001;Main_cannon;Main_cannon_jacket;Muzzle_brake;Team_band;Turret_armor;Turret_body;Turret_cupola;Turret_handles;Turret_hatch;Turret_port;Turret_rangefinder;Turret_ring;Turret_seams;Kit_rivets.002;MG_ball;MG_cupola;MG_glass;MG_gun;MG_roof;Launcher_base;Launcher_frame;Rocket_bodies;Rocket_heads;Rocket_rails;Kit_rivets.003;Mortar_racks;Mortar_rounds;Mortar_tub;Mortar_tub_rim;Mortar_tub_seams;Glass.001;Mortar_base;Mortar_bipods;Mortar_bore;Mortar_collars;Mortar_sight;Mortar_tube;Mortar_tube_2;Mortar_turntable;Quad_ammo_002;Quad_base_002;Quad_frame_002;Quad_grips_002;Quad_guns_002;Quad_jackets_002;Quad_sight_002;Underframe;Bogies;Bogie_springs;Rail_wheels;Headstocks;Headstock_bars;Buffers;Couplers;Wheel_flanges;Hull;Armor;Kit_rivets;Car_band;Vision_slits;Lamp_rims;Lamps;Lamp_guards;Lamp_hoods;Searchlight;Cupola_top;Periscope;Fans;Fans.001;Stacks;Grille_frames;Grilles;Deck;Antenna;Beacon_base;Beacons;Car_body;Car_deck;Ammo_boxes;Kit_latches;Vents;Mortar_crates;Skirt_plates;Kit_handles;Steps;Sandbags;Tool_boxes;Spare_rails;Running_board;Fire_buckets;Rear_casemate;Rear_ball;Rear_gun;Rear_gun_brake;Rear_casemate_hatch;Deck_planks;Loopholes;Loophole_covers;Deflector;Chevrons;Hazard_board;Hazard_bars;Lamp_posts;Sleepers;Rail_bearers;Track_jack;Track_jack.001;Spike_keg;Keg_bands;Tool_chests;Tool_chests.001;Derrick;Derrick_base;Derrick_steel;Kit_cables;Hook_block;Roof_deck;Car_doors;Kit_hinges;Pistol_ports;Pistol_ports.001;Gangway;Ladders;Tower_ring;Cmd_tower;Cmd_tower_roof;Rangefinder;Rangefinder_heads;Rangefinder_hood;Sight;Glass.002;Hatches;Hatch_fittings;Frame_antenna;Insulators;Kit_cables.001;Antennas;Vents.001;Phone_box;Cable_drums;Drum_cable;Drum_axles;Spare_wheelset;Chocks;Drums;Drum_bands;Tarpaulin;Kit_straps;Lamps.001;Tail_discs | M25: 49.18 | N25: 3.645 | O25: 5.056 | P25: Assets/MachineBrigade/Resources/Models/armored_train.glb | Q25: KHONG_AP_DUNG | R25: Docs/models/rebuild/armored_train/unity_scan.png | S25: present | T25: Assets/MachineBrigade/Resources/Models/armored_train.glb | U25: {"triangles":56714}
A26: artillery | B26: ground | C26: ground | D26: 9958 | E26: 63 | F26: 0 | G26: 1 | H26: 3 | I26: FALSE | J26: FALSE | K26: Crate;Steel;Armor;Glass;Undercarriage;Team;Lamp;LavaGlow | L26: Ammo_boxes;Antennas;Cupola;Glass.001;Grille_frames.001;Grilles.001;Hatches.001;Kit_handles;Kit_steel.001;Main_cannon;Main_cannon_cradle;Main_cannon_evacuator;Mantlet;MG_post;MG;MG_ammo;MG_cradle;MG_shield;Muzzle_brake;Racks;Sight.001;Smoke_brackets;Smoke_launchers;Team_band.001;Team_roof;Turret_body;Turret_doors;Turret_roof;Hull;Hull_lower;Fenders;Skirts;Team_band;Hatches;Kit_steel;Sight;Glass;Grille_frames;Grilles;Exhaust;Lamp_rims;Lamps;Lamp_guards;Travel_lock;Spades;Tail_lamps;Tow_cable;Kit_reel;Tracks;Track_links;Tyres;Wheels;Hubs;Sprockets;Idlers;Rollers;Turret_ring | M26: 8.013 | N26: 2.966 | O26: 3.027 | P26: Assets/MachineBrigade/Resources/Models/artillery.glb | Q26: KHONG_AP_DUNG | R26: Docs/models/rebuild/artillery/unity_scan.png | S26: present | T26: Assets/MachineBrigade/Resources/Models/artillery.glb | U26: {"triangles":9958}
A27: artillery_hd | B27: ground | C27: ground | D27: 9958 | E27: 63 | F27: 0 | G27: 1 | H27: 3 | I27: FALSE | J27: FALSE | K27: Crate;Steel;Armor;Glass;Undercarriage;Team;Lamp;LavaGlow | L27: Ammo_boxes;Antennas;Cupola;Glass.001;Grille_frames.001;Grilles.001;Hatches.001;Kit_handles;Kit_steel.001;Main_cannon;Main_cannon_cradle;Main_cannon_evacuator;Mantlet;MG_post;MG;MG_ammo;MG_cradle;MG_shield;Muzzle_brake;Racks;Sight.001;Smoke_brackets;Smoke_launchers;Team_band.001;Team_roof;Turret_body;Turret_doors;Turret_roof;Hull;Hull_lower;Fenders;Skirts;Team_band;Hatches;Kit_steel;Sight;Glass;Grille_frames;Grilles;Exhaust;Lamp_rims;Lamps;Lamp_guards;Travel_lock;Spades;Tail_lamps;Tow_cable;Kit_reel;Tracks;Track_links;Tyres;Wheels;Hubs;Sprockets;Idlers;Rollers;Turret_ring | M27: 8.013 | N27: 2.966 | O27: 3.027 | P27: Assets/MachineBrigade/Resources/Models/artillery_hd.glb | Q27: KHONG_AP_DUNG | R27: Builds/scan/artillery_hd.png | S27: pending | T27: Assets/MachineBrigade/Resources/Models/artillery_hd.glb | U27: {"triangles":9958}
A28: artillery_wreck | B28: prop | C28: prop | D28: 2488 | E28: 7 | F28: 0 | G28: 0 | H28: 0 | I28: FALSE | J28: FALSE | K28: Charred;Rust;Undercarriage;Gilded;Armor | L28: Gun_carriage;Gun_rust;Gun_soot;Gun_tube;Cases;Shell_cases;Shell_heads | M28: 6.483 | N28: 3.07 | O28: 1.663 | P28: Assets/MachineBrigade/Resources/Models/artillery_wreck.glb | Q28: KHONG_AP_DUNG | R28: Builds/scan/artillery_wreck.png | S28: pending | T28: Assets/MachineBrigade/Resources/Models/artillery_wreck.glb | U28: {"triangles":2488}
A29: atgm_ataka | B29: munition | C29: munition | D29: 174 | E29: 7 | F29: 0 | G29: 0 | H29: 0 | I29: FALSE | J29: FALSE | K29: RoofGreen;Undercarriage;Alloy;MetalSheet | L29: Body;Band;Nozzle;Motor;Canards;Fins;Studs | M29: 1.5 | N29: 0.205 | O29: 0.205 | P29: Assets/MachineBrigade/Resources/Models/atgm_ataka.glb | Q29: KHONG_AP_DUNG | R29: Builds/scan/atgm_ataka.png | S29: pending | T29: Assets/MachineBrigade/Resources/Models/atgm_ataka.glb | U29: {"triangles":174}
A30: atgm_carrier | B30: unlisted | D30: 7164 | E30: 46 | F30: 0 | G30: 1 | H30: 2 | I30: FALSE | J30: FALSE | K30: Armor;Steel;Glass;Team;Undercarriage;Rubber;Lamp;Alloy;TeamGlow;Crate | L30: RWS;RWS_gun;RWS_sensor;Hatch_fittings.001;Hatches.001;Launcher;Launcher_frame;Launcher_sight;Launcher_tubes;Launcher_tubes_bore;Missile_arm;Turret_armor;Turret_body;Turret_steel;Hull;Armor;Steel;Chassis;Tyres;Hubs;Tiles;Tile_bolts;Light_housing;Lamps;Light_guards;Marker_lights;Tail_lights;Mud_flaps;Hatches;Hatch_fittings;Periscope_hoods;Periscope;Grille_frames;Antenna;Beacon;Tow_cable;Stowage;Stowage_lid;Latches;Grab_rails;Jerrycans;Jerrycan_rack | M30: 7.315 | N30: 2.894 | O30: 3.816 | P30: Assets/MachineBrigade/Resources/Models/atgm_carrier.glb | Q30: KHONG_AP_DUNG | R30: Builds/scan/atgm_carrier.png | S30: pending | T30: Assets/MachineBrigade/Resources/Models/atgm_carrier.glb | U30: {"triangles":7164}
A31: atgm_kornet | B31: munition | C31: munition | D31: 246 | E31: 8 | F31: 0 | G31: 0 | H31: 0 | I31: FALSE | J31: FALSE | K31: RoofGreen;Undercarriage;Alloy;Steel;MetalSheet | L31: Body;Band;Nozzle;Motor;Canards;Wings;Nozzles;Studs | M31: 1.3 | N31: 0.334 | O31: 0.334 | P31: Assets/MachineBrigade/Resources/Models/atgm_kornet.glb | Q31: KHONG_AP_DUNG | R31: Builds/scan/atgm_kornet.png | S31: pending | T31: Assets/MachineBrigade/Resources/Models/atgm_kornet.glb | U31: {"triangles":246}
A32: atgm_tow | B32: munition | C32: munition | D32: 246 | E32: 8 | F32: 0 | G32: 0 | H32: 0 | I32: FALSE | J32: FALSE | K32: Steel;Crate;Hazard;Undercarriage;Alloy;MetalSheet | L32: Probe;Body;Band;Nozzle;Motor;Fins;Nozzles;Studs | M32: 1.3 | N32: 0.275 | O32: 0.275 | P32: Assets/MachineBrigade/Resources/Models/atgm_tow.glb | Q32: KHONG_AP_DUNG | R32: Builds/scan/atgm_tow.png | S32: pending | T32: Assets/MachineBrigade/Resources/Models/atgm_tow.glb | U32: {"triangles":246}
A33: atgm_tower | B33: structure | C33: tower | D33: 5408 | E33: 80 | F33: 0 | G33: 0 | H33: 3 | I33: FALSE | J33: FALSE | K33: Team;Undercarriage;Steel;Armor;Glass;Concrete;Charred;Hazard;SafetyStripe;Plaster;Sandbag;Alloy;Lamp;Crate;Wood;Fuel;Rubber;BarrelRed;PlasterWhite | L33: ATGM_pod;Kit_cables.001;Kit_handles;Kit_rivets;Launcher;Launcher_bands;Launcher_bores;Launcher_frame;Launcher_lens;Launcher_sight;Turret_armor;Turret_band;Turret_glass;Turret_socket;Turret_steel;Base;Base_joints;Stains;Hazard_marks;Barriers;Kit_bolts;Barrier_stripes;Walls;Lift_joints;Slits;Slit_frames;Door_porch;Door_frames;Doors;Door_slots;Kit_hinges;Door_hazard;Steps;Base_ties;Team_band;Roof;Kit_hooks;Parapet;Drain_spouts;Sandbags;Railings;Deck_joints;Ladders;Ladder_cage;Vents;Sight;Glass;Beacon_base;Beacons;Grille_frames;Grilles;Antennas;Radio_box;Lamps;Lamp_rims;Kit_cables;Conduit;Junction_box;Crates;Kit_straps;Ammo_boxes;Kit_latches;Rocket_rack;Spare_rounds;Spare_round_caps;Cable_reel;Cable_reel_core;Jerrycans;Fuel_drums;Drum_bands;Light_poles;Light_housing;Extinguishers;Signs;Sign_posts;Race | M33: 5.426 | N33: 5.2 | O33: 5.14 | P33: Assets/MachineBrigade/Resources/Models/atgm_tower.glb | Q33: KHONG_AP_DUNG | R33: Docs/models/rebuild/atgm_tower/unity_scan.png | S33: present | T33: Assets/MachineBrigade/Resources/Models/atgm_tower.glb | U33: {"triangles":5408}
A34: atgm_tower_a | B34: structure | C34: tower | D34: 5744 | E34: 85 | F34: 0 | G34: 0 | H34: 3 | I34: FALSE | J34: FALSE | K34: Steel;Team;Fuel;Undercarriage;Armor;Glass;Concrete;Charred;Hazard;SafetyStripe;Plaster;Sandbag;Alloy;Lamp;Crate;Wood;Rubber;BarrelRed;PlasterWhite | L34: Antennas.001;ATGM_pod;Clu_battery;Kit_cables.001;Kit_handles;Launcher;Launcher_bands;Launcher_bores;Launcher_frame;Launcher_lens;Launcher_sight;Turret_armor;Turret_socket;Turret_steel;Base;Base_joints;Stains;Hazard_marks;Barriers;Kit_bolts;Barrier_stripes;Walls;Lift_joints;Slits;Slit_frames;Door_porch;Door_frames;Doors;Door_slots;Kit_hinges;Door_hazard;Steps;Base_ties;Team_band;Roof;Kit_hooks;Parapet;Drain_spouts;Sandbags;Railings;Deck_joints;Ladders;Ladder_cage;Vents;Sight;Glass;Beacon_base;Beacons;Grille_frames;Grilles;Antennas;Radio_box;Lamps;Lamp_rims;Kit_cables;Conduit;Junction_box;Crates;Kit_straps;Ammo_boxes;Kit_latches;Rocket_rack;Spare_rounds;Spare_round_caps;Cable_reel;Cable_reel_core;Jerrycans;Fuel_drums;Drum_bands;Light_poles;Light_housing;Extinguishers;Signs;Sign_posts;Race;Launch_column;Launch_column_band;Launch_collar;Column_gussets;Guy_wires;Guy_anchors | M34: 5.426 | N34: 5.2 | O34: 6.56 | P34: Assets/MachineBrigade/Resources/Models/atgm_tower_a.glb | Q34: KHONG_AP_DUNG | R34: Docs/models/rebuild/atgm_tower_a/unity_scan.png | S34: present | T34: Assets/MachineBrigade/Resources/Models/atgm_tower_a.glb | U34: {"triangles":5744}
A35: atgm_tower_b | B35: structure | C35: tower | D35: 5788 | E35: 87 | F35: 0 | G35: 0 | H35: 5 | I35: FALSE | J35: FALSE | K35: Team;Undercarriage;Steel;Armor;Glass;Concrete;Charred;Hazard;SafetyStripe;Plaster;Sandbag;Alloy;Lamp;Crate;Wood;Fuel;Rubber;BarrelRed;PlasterWhite | L35: ATGM_pod;Kit_cables.001;Kit_handles;Kit_rivets;Launcher;Launcher_bands;Launcher_bores;Launcher_frame;Launcher_lens;Launcher_sight;Radar_array;Radar_face;Radar_frame;Radar_post;Turret_armor;Turret_band;Turret_glass;Turret_socket;Turret_steel;Base;Base_joints;Stains;Hazard_marks;Barriers;Kit_bolts;Barrier_stripes;Walls;Lift_joints;Slits;Slit_frames;Door_porch;Door_frames;Doors;Door_slots;Kit_hinges;Door_hazard;Steps;Base_ties;Team_band;Roof;Kit_hooks;Parapet;Drain_spouts;Sandbags;Railings;Deck_joints;Ladders;Ladder_cage;Vents;Sight;Glass;Beacon_base;Beacons;Grille_frames;Grilles;Antennas;Radio_box;Lamps;Lamp_rims;Kit_cables;Conduit;Junction_box;Crates;Kit_straps;Ammo_boxes;Kit_latches;Rocket_rack;Spare_rounds;Spare_round_caps;Cable_reel;Cable_reel_core;Jerrycans;Fuel_drums;Drum_bands;Light_poles;Light_housing;Extinguishers;Signs;Sign_posts;Race | M35: 5.426 | N35: 5.2 | O35: 5.14 | P35: Assets/MachineBrigade/Resources/Models/atgm_tower_b.glb | Q35: KHONG_AP_DUNG | R35: Docs/models/rebuild/atgm_tower_b/unity_scan.png | S35: present | T35: Assets/MachineBrigade/Resources/Models/atgm_tower_b.glb | U35: {"triangles":5788}
A36: attack_helicopter | B36: air | C36: helicopter | D36: 4722 | E36: 43 | F36: 0 | G36: 5 | H36: 4 | I36: TRUE | J36: FALSE | K36: Armor;Steel;Hazard;Team;Undercarriage;Glass;Fuel;TeamGlow;Rubber | L36: Rotor_blades;Rotor_grips;Rotor_hub;Rotor_tips;Gun;Gun_turret;Tail_rotor_blades;Tail_rotor_hub;Tail_rotor_tips;Fuselage;Armor;Steel;Undercarriage;Canopy;Exhausts;Exhaust_vanes;Sensor;Pylons;Stinger_tubes;Pods;Pod_face;Pod_bands;Missiles;Missile_seekers;Wing_lights;Tyres;Beacon;Antennas;Flares;Flares_glow | M36: 6.348 | N36: 4.437 | O36: 2.02 | P36: Assets/MachineBrigade/Resources/Models/attack_helicopter.glb | Q36: KHONG_AP_DUNG | R36: Builds/scan/attack_helicopter.png | S36: pending | T36: Assets/MachineBrigade/Resources/Models/attack_helicopter.glb | U36: {"triangles":4722}
A37: attack_helicopter_hd | B37: air | C37: helicopter | D37: 6902 | E37: 51 | F37: 0 | G37: 5 | H37: 4 | I37: TRUE | J37: FALSE | K37: Armor;Steel;Hazard;Team;Undercarriage;Glass;Fuel;TeamGlow;Rubber | L37: Rotor_blades;Rotor_bolts;Rotor_grips;Rotor_hub;Rotor_tips;Gun;Gun_turret;Tail_rotor_blades;Tail_rotor_hub;Tail_rotor_links;Tail_rotor_tips;Fuselage;Armor;Steel;Undercarriage;Canopy;Canopy_frames;Exhausts;Exhaust_vanes;Exhaust_ribs;Exhaust_bolts;Sensor;Pylons;Stinger_tubes;Pods;Pod_face;Pod_bands;Missiles;Missile_seekers;Missile_bands;Missile_fins;Wing_lights;Tyres;Beacon;Antennas;Rivets;Flares;Flares_glow | M37: 6.348 | N37: 4.437 | O37: 2.02 | P37: Assets/MachineBrigade/Resources/Models/attack_helicopter_hd.glb | Q37: KHONG_AP_DUNG | R37: Builds/scan/attack_helicopter_hd.png | S37: pending | T37: Assets/MachineBrigade/Resources/Models/attack_helicopter_hd.glb | U37: {"triangles":6902}
A38: attack_jet | B38: air | C38: jet | D38: 4914 | E38: 57 | F38: 1 | G38: 7 | H38: 7 | I38: TRUE | J38: FALSE | K38: Steel;Fuel;Undercarriage;Armor;Team;Hazard;Lamp;Glass | L38: Missile_fins.001;Missiles.001;Flare_mouths.001;Flares.001;Intake_ducts.001;Intakes.001;Missile_fins.002;Missiles.002;Nacelles.001;Pod_bands.001;Pod_face.001;Pods.001;Pylons.001;Wing.001;Wing_lights.001;Wingtip_pods.001;Fuselage;Glass;Antennas;Canopy;Canopy_frames;Nacelles;Intakes;Intake_ducts;Nozzles;Flares;Flare_mouths;Gun;Tail;Tailplane;Wing;Wingtip_pods;Wing_lights;Pylons;Bombs_body;Missile_fins;Pods;Pod_face;Pod_bands;Missiles | M38: 6.44 | N38: 6.04 | O38: 1.84 | P38: Assets/MachineBrigade/Resources/Models/attack_jet.glb | Q38: KHONG_AP_DUNG | R38: Docs/models/rebuild/attack_jet/unity_scan.png | S38: present | T38: Assets/MachineBrigade/Resources/Models/attack_jet.glb | U38: {"triangles":4914}
