Workbook

Sheet Chien_thuat
A1: id | B1: counters | C1: countered_by | D1: prefer | E1: commanders | F1: chapter | G1: check_with | H1: cp | I1: interlude | J1: modules | K1: modules_artillery_prep | L1: modules_attack_threshold | M1: modules_bounding | N1: modules_cohesion | O1: modules_counterattack | P1: modules_cp_saving | Q1: modules_drop_secondary | R1: modules_engage | S1: modules_fallback | T1: modules_flank | U1: modules_focus | V1: modules_heavy_lead | W1: modules_hold | X1: modules_hold_base | Y1: modules_hold_fire | Z1: modules_kite | AA1: modules_main_effort | AB1: modules_mass_support | AC1: modules_pace | AD1: modules_pincer | AE1: modules_sead_cards | AF1: modules_spread | AG1: modules_stance | AH1: modules_standoff_m | AI1: modules_targets | AJ1: modules_together | AK1: modules_tower_mode | AL1: modules_wait_air | AM1: name | AN1: nguon | AO1: raw_json
A2: air_superiority | B2: hit_and_run | C2: blitz | D2: fighter_jet;stealth_fighter;sam_launcher;long_sam;heavy_aa | E2: reyes | F2: 3 | G2: sead | H2: 0.15;0.12;0.08;0.08;0.2;0.1;0.22;0.05 | I2: 0 | AL2: 1 | AM2: Ưu thế trên không | AN2: Assets/MachineBrigade/Resources/Data/balance.json: aiBehaviour.tactics[10] | AO2: {"id":"air_superiority","name":"Ưu thế trên không","cp":[0.15,0.12,0.08,0.08,0.2,0.1,0.22,0.05],"prefer":["fighter_jet","stealth_fighter","sam_launcher","long_sam","heavy_aa"],"counters":["hit_and_run"],"counteredBy":["blitz"],"chapter":3,"interlude":0,"commanders":["reyes"],"checkWith":"sead","modules":{"waitAir":1}}
A3: all_out | B3: depth | C3: blitz | D3: main_battle_tank;heavy_tank;attack_jet;heavy_bomber | E3: okoye | F3: 10 | G3: breakthrough | H3: 0.3;0.2;0.1;0.1;0.1;0.08;0.07;0.05 | I3: 0 | P3: 1 | AB3: 1 | AJ3: 1 | AM3: Tổng tấn công | AN3: Assets/MachineBrigade/Resources/Data/balance.json: aiBehaviour.tactics[15] | AO3: {"id":"all_out","name":"Tổng tấn công","cp":[0.3,0.2,0.1,0.1,0.1,0.08,0.07,0.05],"prefer":["main_battle_tank","heavy_tank","attack_jet","heavy_bomber"],"counters":["depth"],"counteredBy":["blitz"],"chapter":10,"interlude":0,"commanders":["okoye"],"checkWith":"breakthrough","modules":{"cpSaving":1,"together":1,"massSupport":1}}
A4: ambush | B4: blitz | C4: bounding | D4: tank_destroyer;railgun_truck;fpv_carrier;scout_jeep;ew_jammer | E4: kerr | F4: 0 | H4: 0.15;0.15;0.3;0.1;0.12;0.08;0.02;0.08 | I4: 1 | Y4: 0.6 | AG4: HoldFire | AM4: Phục kích | AN4: Assets/MachineBrigade/Resources/Data/balance.json: aiBehaviour.tactics[6] | AO4: {"id":"ambush","name":"Phục kích","cp":[0.15,0.15,0.3,0.1,0.12,0.08,0.02,0.08],"prefer":["tank_destroyer","railgun_truck","fpv_carrier","scout_jeep","ew_jammer"],"counters":["blitz"],"counteredBy":["bounding"],"chapter":0,"interlude":1,"commanders":["kerr"],"checkWith":"","modules":{"holdFire":0.6,"stance":"HoldFire"}}
A5: attrition | B5: breakthrough | C5: blitz;encircle | D5: mlrs;shahed_truck;ballistic_launcher;recon_drone | E5: quist | F5: 8 | H5: 0.1;0.1;0.2;0.3;0.1;0.05;0.05;0.1 | I5: 0 | L5: 1.5 | R5: 0.9;1.0 | AH5: 1 | AM5: Tiêu hao | AN5: Assets/MachineBrigade/Resources/Data/balance.json: aiBehaviour.tactics[12] | AO5: {"id":"attrition","name":"Tiêu hao","cp":[0.1,0.1,0.2,0.3,0.1,0.05,0.05,0.1],"prefer":["mlrs","shahed_truck","ballistic_launcher","recon_drone"],"counters":["breakthrough"],"counteredBy":["blitz","encircle"],"chapter":8,"interlude":0,"commanders":["quist"],"checkWith":"","modules":{"attackThreshold":1.5,"engage":[0.9,1.0],"standoff":1}}
A6: balanced | E6: kade | F6: 0 | H6: 0.25;0.2;0.12;0.12;0.1;0.08;0.05;0.08 | I6: 0 | AM6: Cân bằng | AN6: Assets/MachineBrigade/Resources/Data/balance.json: aiBehaviour.tactics[0] | AO6: {"id":"balanced","name":"Cân bằng","cp":[0.25,0.2,0.12,0.12,0.1,0.08,0.05,0.08],"prefer":[],"counters":[],"counteredBy":[],"chapter":0,"interlude":0,"commanders":["kade"],"checkWith":"","modules":{}}
A7: base_defence | B7: blitz | C7: firepower;attrition | D7: tank_destroyer;aa_vehicle;mine_layer;engineer_vehicle | E7: brandt | F7: 1 | H7: 0.25;0.15;0.2;0.15;0.15;0.02;0.0;0.08 | I7: 0 | W7: 1 | X7: 1 | AK7: Lead | AM7: Bảo vệ căn cứ | AN7: Assets/MachineBrigade/Resources/Data/balance.json: aiBehaviour.tactics[14] | AO7: {"id":"base_defence","name":"Bảo vệ căn cứ","cp":[0.25,0.15,0.2,0.15,0.15,0.02,0.0,0.08],"prefer":["tank_destroyer","aa_vehicle","mine_layer","engineer_vehicle"],"counters":["blitz"],"counteredBy":["firepower","attrition"],"chapter":1,"interlude":0,"commanders":["brandt"],"checkWith":"","modules":{"hold":1,"holdBase":1,"towerMode":"Lead"}}
A8: blitz | B8: firepower | C8: depth;ambush | D8: armored_car;ifv;wheeled_gun;main_battle_tank;attack_helicopter | E8: mendez | F8: 2 | H8: 0.25;0.3;0.1;0.05;0.08;0.1;0.04;0.08 | I8: 0 | L8: 0.9 | N8: 0 | AM8: Tấn công chớp nhoáng | AN8: Assets/MachineBrigade/Resources/Data/balance.json: aiBehaviour.tactics[1] | AO8: {"id":"blitz","name":"Tấn công chớp nhoáng","cp":[0.25,0.3,0.1,0.05,0.08,0.1,0.04,0.08],"prefer":["armored_car","ifv","wheeled_gun","main_battle_tank","attack_helicopter"],"counters":["firepower"],"counteredBy":["depth","ambush"],"chapter":2,"interlude":0,"commanders":["mendez"],"checkWith":"","modules":{"attackThreshold":0.9,"cohesion":0}}
A9: bounding | B9: ambush | C9: blitz;firepower | D9: main_battle_tank;ifv | E9: kade | F9: 3 | H9: 0.3;0.25;0.12;0.1;0.1;0.05;0.0;0.08 | I9: 0 | M9: 1 | AC9: 0.7 | AM9: Yểm hộ luân phiên | AN9: Assets/MachineBrigade/Resources/Data/balance.json: aiBehaviour.tactics[5] | AO9: {"id":"bounding","name":"Yểm hộ luân phiên","cp":[0.3,0.25,0.12,0.1,0.1,0.05,0.0,0.08],"prefer":["main_battle_tank","ifv"],"counters":["ambush"],"counteredBy":["blitz","firepower"],"chapter":3,"interlude":0,"commanders":["kade"],"checkWith":"","modules":{"pace":0.7,"bounding":1}}
A10: breakthrough | B10: depth;encircle | C10: encircle;dispersal | D10: heavy_tank;titan_tank;twin_tank;armored_bulldozer;engineer_vehicle;thermobaric_launcher | E10: reyn | F10: 6 | G10: all_out | H10: 0.4;0.15;0.08;0.12;0.1;0.05;0.02;0.08 | I10: 0 | Q10: 1 | V10: 1 | AA10: 0.7 | AM10: Tập trung đột phá | AN10: Assets/MachineBrigade/Resources/Data/balance.json: aiBehaviour.tactics[8] | AO10: {"id":"breakthrough","name":"Tập trung đột phá","cp":[0.4,0.15,0.08,0.12,0.1,0.05,0.02,0.08],"prefer":["heavy_tank","titan_tank","twin_tank","armored_bulldozer","engineer_vehicle","thermobaric_launcher"],"counters":["depth","encircle"],"counteredBy":["encircle","dispersal"],"chapter":6,"interlude":0,"commanders":["reyn"],"checkWith":"all_out","modules":{"mainEffort":0.7,"heavyLead":1,"dropSecondary":1}}
A11: decapitation | B11: firepower | C11: depth | D11: armored_car;scout_heli;attack_helicopter;stealth_fighter | E11: kerr | F11: 9 | H11: 0.12;0.28;0.15;0.1;0.08;0.15;0.07;0.05 | I11: 0 | T11: 1.6 | AI11: Support;Artillery | AM11: Săn đầu | AN11: Assets/MachineBrigade/Resources/Data/balance.json: aiBehaviour.tactics[13] | AO11: {"id":"decapitation","name":"Săn đầu","cp":[0.12,0.28,0.15,0.1,0.08,0.15,0.07,0.05],"prefer":["armored_car","scout_heli","attack_helicopter","stealth_fighter"],"counters":["firepower"],"counteredBy":["depth"],"chapter":9,"interlude":0,"commanders":["kerr"],"checkWith":"","modules":{"flank":1.6,"targets":["Support","Artillery"]}}
A12: depth | B12: blitz;breakthrough | C12: firepower;encircle | D12: tank_destroyer;main_battle_tank;mine_layer;mortar_carrier;sam_launcher | E12: brandt | F12: 1 | H12: 0.25;0.15;0.18;0.15;0.12;0.05;0.02;0.08 | I12: 0 | O12: 1.3 | S12: 0.6 | W12: 1 | AM12: Phòng thủ chiều sâu | AN12: Assets/MachineBrigade/Resources/Data/balance.json: aiBehaviour.tactics[3] | AO12: {"id":"depth","name":"Phòng thủ chiều sâu","cp":[0.25,0.15,0.18,0.15,0.12,0.05,0.02,0.08],"prefer":["tank_destroyer","main_battle_tank","mine_layer","mortar_carrier","sam_launcher"],"counters":["blitz","breakthrough"],"counteredBy":["firepower","encircle"],"chapter":1,"interlude":0,"commanders":["brandt"],"checkWith":"","modules":{"fallback":0.6,"counterattack":1.3,"hold":1}}
A13: dispersal | B13: firepower;breakthrough | C13: blitz | D13: armored_car;light_tank;fpv_carrier;mortar_carrier | E13: venn | F13: 6 | G13: hit_and_run | H13: 0.15;0.25;0.15;0.15;0.1;0.1;0.03;0.07 | I13: 0 | U13: 0.5 | AF13: 2 | AM13: Phân tán | AN13: Assets/MachineBrigade/Resources/Data/balance.json: aiBehaviour.tactics[9] | AO13: {"id":"dispersal","name":"Phân tán","cp":[0.15,0.25,0.15,0.15,0.1,0.1,0.03,0.07],"prefer":["armored_car","light_tank","fpv_carrier","mortar_carrier"],"counters":["firepower","breakthrough"],"counteredBy":["blitz"],"chapter":6,"interlude":0,"commanders":["venn"],"checkWith":"hit_and_run","modules":{"focus":0.5,"spread":2.0}}
A14: encircle | B14: depth;base_defence | C14: breakthrough | D14: armored_car;ifv;wheeled_gun;light_tank;attack_helicopter | E14: adler | F14: 4 | H14: 0.22;0.28;0.15;0.08;0.1;0.1;0.02;0.05 | I14: 0 | T14: 1.6 | AD14: 1 | AM14: Bao vây | AN14: Assets/MachineBrigade/Resources/Data/balance.json: aiBehaviour.tactics[4] | AO14: {"id":"encircle","name":"Bao vây","cp":[0.22,0.28,0.15,0.08,0.1,0.1,0.02,0.05],"prefer":["armored_car","ifv","wheeled_gun","light_tank","attack_helicopter"],"counters":["depth","base_defence"],"counteredBy":["breakthrough"],"chapter":4,"interlude":0,"commanders":["adler"],"checkWith":"","modules":{"flank":1.6,"pincer":1}}
A15: firepower | B15: depth;base_defence | C15: blitz;hit_and_run;dispersal | D15: artillery;mlrs;heavy_rocket_artillery;mortar_carrier;ammo_carrier | E15: dahl | F15: 3 | H15: 0.2;0.12;0.08;0.3;0.12;0.05;0.05;0.08 | I15: 0 | K15: 1 | AM15: Hỏa lực áp đảo | AN15: Assets/MachineBrigade/Resources/Data/balance.json: aiBehaviour.tactics[2] | AO15: {"id":"firepower","name":"Hỏa lực áp đảo","cp":[0.2,0.12,0.08,0.3,0.12,0.05,0.05,0.08],"prefer":["artillery","mlrs","heavy_rocket_artillery","mortar_carrier","ammo_carrier"],"counters":["depth","base_defence"],"counteredBy":["blitz","hit_and_run","dispersal"],"chapter":3,"interlude":0,"commanders":["dahl"],"checkWith":"","modules":{"artilleryPrep":1.0}}
A16: hit_and_run | B16: firepower | C16: blitz;air_superiority | D16: wheeled_gun;armored_car;tank_destroyer;attack_helicopter;strike_drone | E16: mendez | F16: 5 | G16: dispersal | H16: 0.1;0.25;0.25;0.1;0.1;0.12;0.03;0.05 | I16: 0 | R16: 0.9;1.0 | Z16: 0.7 | AM16: Bắn và chạy | AN16: Assets/MachineBrigade/Resources/Data/balance.json: aiBehaviour.tactics[7] | AO16: {"id":"hit_and_run","name":"Bắn và chạy","cp":[0.1,0.25,0.25,0.1,0.1,0.12,0.03,0.05],"prefer":["wheeled_gun","armored_car","tank_destroyer","attack_helicopter","strike_drone"],"counters":["firepower"],"counteredBy":["blitz","air_superiority"],"chapter":5,"interlude":0,"commanders":["mendez"],"checkWith":"dispersal","modules":{"engage":[0.9,1.0],"kite":0.7}}
A17: sead | D17: attack_jet;stealth_fighter;ew_jammer;ballistic_launcher | E17: reyes | F17: 7 | G17: air_superiority | H17: 0.15;0.12;0.1;0.15;0.1;0.1;0.2;0.08 | I17: 0 | AE17: 1 | AI17: AntiAir | AM17: Chế áp phòng không trước | AN17: Assets/MachineBrigade/Resources/Data/balance.json: aiBehaviour.tactics[11] | AO17: {"id":"sead","name":"Chế áp phòng không trước","cp":[0.15,0.12,0.1,0.15,0.1,0.1,0.2,0.08],"prefer":["attack_jet","stealth_fighter","ew_jammer","ballistic_launcher"],"counters":[],"counteredBy":[],"chapter":7,"interlude":0,"commanders":["reyes"],"checkWith":"air_superiority","modules":{"targets":["AntiAir"],"seadCards":1}}

Sheet AI_ho_so_che_do
A1: id | B1: tactics | C1: advance | D1: auto_ai | E1: auto_ai_note | F1: controllers | G1: defender | H1: engagement | I1: escort_anchor | J1: escort_max_advance_distance | K1: escort_no_chase_outside_leash | L1: escort_rear_guard_weight | M1: escort_safe_zone_radius | N1: escort_threat_to_convoy_weight | O1: flags | P1: general_tactic | Q1: hq_skill_threat | R1: inherits | S1: leash_distance | T1: leash_region | U1: name | V1: no_chase | W1: objective_policy | X1: phased | Y1: spend | Z1: stall | AA1: support | AB1: target_mask | AC1: wall_route_breach | AD1: wall_route_route | AE1: wall_route_threat | AF1: nguon | AG1: raw_json
A2: assault | B2: depth;base_defence;attrition;ambush;balanced | C2: FALSE | E2: Khu kế tiếp, quỹ thời gian | F2: Commander;Static | G2: ai | H2: Normal | P2: FALSE | Q2: 10 | S2: 40 | T2: zone | U2: Công phá | W2: Mất khu thì lùi về khu sau (leashRegion theo khu) | Y2: TRUE | Z2: AttackerOnly | AA2: Normal | AB2: enemy | AC2: 0.9 | AD2: 1 | AE2: 1.2 | AF2: Assets/MachineBrigade/Resources/Data/balance.json: aiModeProfiles.profiles.assault | AG2: {"name":"Công phá","controllers":["Commander","Static"],"tactics":["depth","base_defence","attrition","ambush","balanced"],"generalTactic":false,"stall":"AttackerOnly","spend":true,"advance":false,"support":"Normal","engagement":"Normal","defender":"ai","hqSkillThreat":10,"wallRoute":{"route":1,"threat":1.2,"breach":0.9},"targetMask":["enemy"],"objectivePolicy":"Mất khu thì lùi về khu sau (leashRegion theo khu)","autoAiNote":"Khu kế tiếp, quỹ thời gian","leashRegion":"zone","leashDistance":40}
A3: bossrush | C3: FALSE | E3: 1) né cảnh báo chết người 2) bộ phận boss nguy hiểm 3) bộ phận lộ ra 4) thân | F3: Boss | G3: none | H3: Normal | O3: noGeneralTactic | P3: FALSE | U3: Săn trùm | Y3: FALSE | Z3: Off | AA3: Normal | AB3: enemy | AF3: Assets/MachineBrigade/Resources/Data/balance.json: aiModeProfiles.profiles.bossrush | AG3: {"name":"Săn trùm","controllers":["Boss"],"tactics":[],"generalTactic":false,"stall":"Off","spend":false,"advance":false,"support":"Normal","engagement":"Normal","defender":"none","targetMask":["enemy"],"objectivePolicy":"","autoAiNote":"1) né cảnh báo chết người 2) bộ phận boss nguy hiểm 3) bộ phận lộ ra 4) thân","flags":["noGeneralTactic"]}
A4: capture | B4: * | C4: TRUE | E4: Mục tiêu màn | F4: Commander | G4: none | H4: Normal | P4: TRUE | U4: Chiến dịch: chiếm | W4: Chiếm / tranh | Y4: TRUE | Z4: Both | AA4: Normal | AB4: enemy | AF4: Assets/MachineBrigade/Resources/Data/balance.json: aiModeProfiles.profiles.capture | AG4: {"name":"Chiến dịch: chiếm","controllers":["Commander"],"tactics":["*"],"generalTactic":true,"stall":"Both","spend":true,"advance":true,"support":"Normal","engagement":"Normal","defender":"none","targetMask":["enemy"],"objectivePolicy":"Chiếm / tranh","autoAiNote":"Mục tiêu màn"}
A5: conquest | B5: * | C5: TRUE | E5: Giữ cứ điểm đang mất nhanh nhất | F5: Commander | G5: none | H5: Normal | P5: FALSE | Q5: 8 | U5: Giữ cứ điểm | W5: Chặn mất điểm nhanh nhất; mục tiêu chế độ thắng sở thích chiến thuật | Y5: TRUE | Z5: Both | AA5: Normal | AB5: enemy | AC5: 1 | AD5: 1 | AE5: 1 | AF5: Assets/MachineBrigade/Resources/Data/balance.json: aiModeProfiles.profiles.conquest | AG5: {"name":"Giữ cứ điểm","controllers":["Commander"],"tactics":["*"],"generalTactic":false,"stall":"Both","spend":true,"advance":true,"support":"Normal","engagement":"Normal","defender":"none","hqSkillThreat":8,"wallRoute":{"route":1,"threat":1,"breach":1},"targetMask":["enemy"],"objectivePolicy":"Chặn mất điểm nhanh nhất; mục tiêu chế độ thắng sở thích chiến thuật","autoAiNote":"Giữ cứ điểm đang mất nhanh nhất"}
A6: deathmatch | B6: * | C6: TRUE | E6: Dồn hỏa lực, tránh biếu xe đắt | F6: Commander | G6: none | H6: Normal | O6: riskWeightByUnitValue | P6: FALSE | Q6: 8 | U6: Tử chiến | W6: riskWeightByUnitValue: tránh "biếu" xe đắt; dẫn điểm gần hết giờ thì giảm hung hăng (không rút hẳn) | Y6: TRUE | Z6: Both | AA6: Normal | AB6: enemy | AC6: 1 | AD6: 1 | AE6: 1 | AF6: Assets/MachineBrigade/Resources/Data/balance.json: aiModeProfiles.profiles.deathmatch | AG6: {"name":"Tử chiến","controllers":["Commander"],"tactics":["*"],"generalTactic":false,"stall":"Both","spend":true,"advance":true,"support":"Normal","engagement":"Normal","defender":"none","hqSkillThreat":8,"wallRoute":{"route":1,"threat":1,"breach":1},"targetMask":["enemy"],"objectivePolicy":"riskWeightByUnitValue: tránh \"biếu\" xe đắt; dẫn điểm gần hết giờ thì giảm hung hăng (không rút hẳn)","autoAiNote":"Dồn hỏa lực, tránh biếu xe đắt","flags":["riskWeightByUnitValue"]}
A7: defend | C7: FALSE | E7: Giữ tuyến, lùi tuyến có trật tự | F7: WaveDirector | G7: player | H7: Normal | P7: FALSE | U7: Phòng thủ / Vô tận | W7: Đội trong đợt vẫn dùng hành vi cấp đội (chọc thủng, che chắn, bảo vệ pháo, chọn mục tiêu) | Y7: FALSE | Z7: Off | AA7: Normal | AB7: enemy | AF7: Assets/MachineBrigade/Resources/Data/balance.json: aiModeProfiles.profiles.defend | AG7: {"name":"Phòng thủ / Vô tận","controllers":["WaveDirector"],"tactics":[],"generalTactic":false,"stall":"Off","spend":false,"advance":false,"support":"Normal","engagement":"Normal","defender":"player","targetMask":["enemy"],"objectivePolicy":"Đội trong đợt vẫn dùng hành vi cấp đội (chọc thủng, che chắn, bảo vệ pháo, chọn mục tiêu)","autoAiNote":"Giữ tuyến, lùi tuyến có trật tự"}
A8: escort | B8: * | C8: TRUE | D8: escort | E8: Ở quanh đoàn xe; mối đe dọa với đoàn trước; hỗ trợ không gọi đòn nổ lan chồng lên vùng an toàn của đoàn | F8: Commander | G8: none | H8: Normal | I8: convoyCentre | J8: 30 | K8: TRUE | L8: 0.3 | M8: 12 | N8: 2 | P8: TRUE | U8: Chiến dịch: hộ tống / di tản | W8: escortAnchor = tâm đoàn xe; maxAdvanceDistance; rearGuardWeight; threatToConvoyWeight; noChaseOutsideLeash | Y8: TRUE | Z8: Off | AA8: Normal | AB8: enemy | AF8: Assets/MachineBrigade/Resources/Data/balance.json: aiModeProfiles.profiles.escort | AG8: {"name":"Chiến dịch: hộ tống / di tản","controllers":["Commander"],"tactics":["*"],"generalTactic":true,"stall":"Off","spend":true,"advance":true,"support":"Normal","engagement":"Normal","defender":"none","targetMask":["enemy"],"objectivePolicy":"escortAnchor = tâm đoàn xe; maxAdvanceDistance; rearGuardWeight; threatToConvoyWeight; noChaseOutsideLeash","autoAiNote":"Ở quanh đoàn xe; mối đe dọa với đoàn trước; hỗ trợ không gọi đòn nổ lan chồng lên vùng an toàn của đoàn","escort":{"anchor":"convoyCentre","maxAdvanceDistance":30,"rearGuardWeight":0.3,"threatToConvoyWeight":2.0,"noChaseOutsideLeash":true,"safeZoneRadius":12},"autoAi":"escort"}
A9: fixed_deck | B9: * | C9: FALSE | E9: Theo special_rules; placed_allies theo lệnh Tấn công/Phòng thủ | G9: none | H9: Normal | P9: FALSE | R9: TRUE | U9: Màn bộ bài game | W9: Chỉ ghi đè bằng special_rules; ngừng bắn: targetFactionMask loại phe CEASEFIRE ở cấp sát thương (cả hỗ trợ, nổ lan), không chỉ ở AI | X9: TRUE | Y9: FALSE | Z9: Inherit | AA9: Normal | AB9: enemy | AF9: Assets/MachineBrigade/Resources/Data/balance.json: aiModeProfiles.profiles.fixed_deck | AG9: {"name":"Màn bộ bài game","controllers":[],"tactics":["*"],"generalTactic":false,"stall":"Inherit","spend":false,"advance":false,"support":"Normal","engagement":"Normal","defender":"none","targetMask":["enemy"],"objectivePolicy":"Chỉ ghi đè bằng special_rules; ngừng bắn: targetFactionMask loại phe CEASEFIRE ở cấp sát thương (cả hỗ trợ, nổ lan), không chỉ ở AI","autoAiNote":"Theo special_rules; placed_allies theo lệnh Tấn công/Phòng thủ","phased":true,"inherits":true}
A10: hill | B10: * | C10: TRUE | E10: Giữ đồi | F10: Commander | G10: none | H10: Normal | P10: FALSE | Q10: 8 | U10: Vua đồi | W10: Sàn cứng: không để đồi trống khi đủ quân tranh; 60 s cuối ưu tiên đồi cao hơn | Y10: TRUE | Z10: Both | AA10: Normal | AB10: enemy | AC10: 1 | AD10: 1 | AE10: 1 | AF10: Assets/MachineBrigade/Resources/Data/balance.json: aiModeProfiles.profiles.hill | AG10: {"name":"Vua đồi","controllers":["Commander"],"tactics":["*"],"generalTactic":false,"stall":"Both","spend":true,"advance":true,"support":"Normal","engagement":"Normal","defender":"none","hqSkillThreat":8,"wallRoute":{"route":1,"threat":1,"breach":1},"targetMask":["enemy"],"objectivePolicy":"Sàn cứng: không để đồi trống khi đủ quân tranh; 60 s cuối ưu tiên đồi cao hơn","autoAiNote":"Giữ đồi"}
A11: hold | B11: * | C11: TRUE | E11: Giữ mục tiêu | F11: Commander | G11: player | H11: Normal | P11: TRUE | U11: Chiến dịch: giữ / trụ | W11: Không ép người chơi rời mục tiêu | Y11: TRUE | Z11: AttackerOnly | AA11: Normal | AB11: enemy | AF11: Assets/MachineBrigade/Resources/Data/balance.json: aiModeProfiles.profiles.hold | AG11: {"name":"Chiến dịch: giữ / trụ","controllers":["Commander"],"tactics":["*"],"generalTactic":true,"stall":"AttackerOnly","spend":true,"advance":true,"support":"Normal","engagement":"Normal","defender":"player","targetMask":["enemy"],"objectivePolicy":"Không ép người chơi rời mục tiêu","autoAiNote":"Giữ mục tiêu"}
A12: hunt | B12: * | C12: TRUE | E12: Như cột trước | F12: Commander | G12: none | H12: Normal | P12: TRUE | U12: Chiến dịch: săn mục tiêu / chặn tàu | W12: Mục tiêu đánh dấu > hộ tống của nó > quân thường | Y12: TRUE | Z12: Both | AA12: Normal | AB12: enemy | AF12: Assets/MachineBrigade/Resources/Data/balance.json: aiModeProfiles.profiles.hunt | AG12: {"name":"Chiến dịch: săn mục tiêu / chặn tàu","controllers":["Commander"],"tactics":["*"],"generalTactic":true,"stall":"Both","spend":true,"advance":true,"support":"Normal","engagement":"Normal","defender":"none","targetMask":["enemy"],"objectivePolicy":"Mục tiêu đánh dấu > hộ tống của nó > quân thường","autoAiNote":"Như cột trước"}
A13: operation | B13: * | C13: TRUE | E13: Mục tiêu giai đoạn | F13: Commander;WaveDirector;Fortress;Boss;Static | G13: none | H13: Normal | P13: TRUE | U13: Chiến dịch lớn | W13: Mỗi giai đoạn có thể đổi controller, chiến thuật, áp lực, mục tiêu, supportPolicy; đồng minh (Thorne) dùng AI đồng minh | X13: TRUE | Y13: TRUE | Z13: Both | AA13: Normal | AB13: enemy | AF13: Assets/MachineBrigade/Resources/Data/balance.json: aiModeProfiles.profiles.operation | AG13: {"name":"Chiến dịch lớn","controllers":["Commander","WaveDirector","Fortress","Boss","Static"],"tactics":["*"],"generalTactic":true,"stall":"Both","spend":true,"advance":true,"support":"Normal","engagement":"Normal","defender":"none","targetMask":["enemy"],"objectivePolicy":"Mỗi giai đoạn có thể đổi controller, chiến thuật, áp lực, mục tiêu, supportPolicy; đồng minh (Thorne) dùng AI đồng minh","autoAiNote":"Mục tiêu giai đoạn","phased":true}
A14: outpost | B14: * | C14: TRUE | E14: Theo bước | F14: Commander | G14: none | H14: Normal | P14: TRUE | U14: Chiến dịch: lập tiền đồn | W14: Bước: dọn vùng → chiếm → dựng → giữ (phaseOverrides) | Y14: TRUE | Z14: ObjectiveStallOnly | AA14: Normal | AB14: enemy | AF14: Assets/MachineBrigade/Resources/Data/balance.json: aiModeProfiles.profiles.outpost | AG14: {"name":"Chiến dịch: lập tiền đồn","controllers":["Commander"],"tactics":["*"],"generalTactic":true,"stall":"ObjectiveStallOnly","spend":true,"advance":true,"support":"Normal","engagement":"Normal","defender":"none","targetMask":["enemy"],"objectivePolicy":"Bước: dọn vùng → chiếm → dựng → giữ (phaseOverrides)","autoAiNote":"Theo bước","phaseOverrides":[{"when":"step:clear","stall":"Both"},{"when":"step:capture","stall":"Both"},{"when":"step:build","stall":"ObjectiveStallOnly"},{"when":"step:hold","stall":"AttackerOnly"}]}
A15: protect | B15: * | C15: TRUE | D15: protectTarget | E15: Mối đe dọa trực tiếp lớn nhất với công trình được bảo vệ (không chỉ "công trình yếu nhất") | F15: Commander | G15: player | H15: Normal | P15: TRUE | U15: Chiến dịch: bảo vệ | Y15: TRUE | Z15: AttackerOnly | AA15: Normal | AB15: enemy | AF15: Assets/MachineBrigade/Resources/Data/balance.json: aiModeProfiles.profiles.protect | AG15: {"name":"Chiến dịch: bảo vệ","controllers":["Commander"],"tactics":["*"],"generalTactic":true,"stall":"AttackerOnly","spend":true,"advance":true,"support":"Normal","engagement":"Normal","defender":"player","targetMask":["enemy"],"objectivePolicy":"","autoAiNote":"Mối đe dọa trực tiếp lớn nhất với công trình được bảo vệ (không chỉ \"công trình yếu nhất\")","autoAi":"protectTarget"}
A16: recon | B16: ambush;base_defence | C16: FALSE | E16: engagementPolicy = AVOID_UNLESS_BLOCKING; không đuổi; ưu tiên đường tới điểm; Yểm trợ tự động không gọi pháo trước báo động | F16: Commander | G16: none | H16: AvoidUnlessBlocking | P16: FALSE | U16: Chiến dịch: trinh sát / thâm nhập | V16: TRUE | W16: supportPolicy = DISABLED_UNTIL_ALERT; sau báo động: phaseOverride sang hồ sơ chiến đấu | Y16: FALSE | Z16: Off | AA16: DisabledUntilAlert | AB16: enemy | AF16: Assets/MachineBrigade/Resources/Data/balance.json: aiModeProfiles.profiles.recon | AG16: {"name":"Chiến dịch: trinh sát / thâm nhập","controllers":["Commander"],"tactics":["ambush","base_defence"],"generalTactic":false,"stall":"Off","spend":false,"advance":false,"support":"DisabledUntilAlert","engagement":"AvoidUnlessBlocking","defender":"none","targetMask":["enemy"],"objectivePolicy":"supportPolicy = DISABLED_UNTIL_ALERT; sau báo động: phaseOverride sang hồ sơ chiến đấu","autoAiNote":"engagementPolicy = AVOID_UNLESS_BLOCKING; không đuổi; ưu tiên đường tới điểm; Yểm trợ tự động không gọi pháo trước báo động","noChase":true,"phaseOverrides":[{"when":"alert","profile":"capture"}]}
A17: relieve | B17: * | C17: TRUE | D17: breakSiege | E17: Phá vòng vây → bảo vệ quân được giải vây → rồi mới đuổi | F17: Commander | G17: none | H17: Normal | P17: TRUE | U17: Chiến dịch: giải vây | Y17: TRUE | Z17: Both | AA17: Normal | AB17: enemy | AF17: Assets/MachineBrigade/Resources/Data/balance.json: aiModeProfiles.profiles.relieve | AG17: {"name":"Chiến dịch: giải vây","controllers":["Commander"],"tactics":["*"],"generalTactic":true,"stall":"Both","spend":true,"advance":true,"support":"Normal","engagement":"Normal","defender":"none","targetMask":["enemy"],"objectivePolicy":"","autoAiNote":"Phá vòng vây → bảo vệ quân được giải vây → rồi mới đuổi","autoAi":"breakSiege"}
A18: shootdown | B18: * | C18: TRUE | E18: Giữ mạng phòng không và vùng phủ; không đuổi mục tiêu mặt đất vô ích | F18: Commander | G18: none | H18: Normal | P18: TRUE | U18: Chiến dịch: bắn hạ máy bay | Y18: TRUE | Z18: Both | AA18: Normal | AB18: enemy | AF18: Assets/MachineBrigade/Resources/Data/balance.json: aiModeProfiles.profiles.shootdown | AG18: {"name":"Chiến dịch: bắn hạ máy bay","controllers":["Commander"],"tactics":["*"],"generalTactic":true,"stall":"Both","spend":true,"advance":true,"support":"Normal","engagement":"Normal","defender":"none","targetMask":["enemy"],"objectivePolicy":"","autoAiNote":"Giữ mạng phòng không và vùng phủ; không đuổi mục tiêu mặt đất vô ích"}
A19: showdown | B19: * | C19: TRUE | E19: Thủ nhà, phá tuyến ngoài, đánh nhà chính | F19: Commander | G19: none | H19: Normal | P19: FALSE | Q19: 8 | U19: Đối công | W19: (1) thủ căn cứ khi có mối đe dọa đáng kể; (2) phá phòng tuyến ngoài (cổng hoặc phá tường theo routeCost + threatCost + breachTimeCost); (3) đánh nhà chính; (4) trung lập khi có lợi; dùng kỹ năng nhà chính | Y19: TRUE | Z19: Both | AA19: Normal | AB19: enemy | AC19: 0.9 | AD19: 1 | AE19: 1 | AF19: Assets/MachineBrigade/Resources/Data/balance.json: aiModeProfiles.profiles.showdown | AG19: {"name":"Đối công","controllers":["Commander"],"tactics":["*"],"generalTactic":false,"stall":"Both","spend":true,"advance":true,"support":"Normal","engagement":"Normal","defender":"none","hqSkillThreat":8,"wallRoute":{"route":1,"threat":1,"breach":0.9},"targetMask":["enemy"],"objectivePolicy":"(1) thủ căn cứ khi có mối đe dọa đáng kể; (2) phá phòng tuyến ngoài (cổng hoặc phá tường theo routeCost + threatCost + breachTimeCost); (3) đánh nhà chính; (4) trung lập khi có lợi; dùng kỹ năng nhà chính","autoAiNote":"Thủ nhà, phá tuyến ngoài, đánh nhà chính"}
A20: siege | B20: depth;base_defence;attrition;ambush;balanced | C20: FALSE | E20: Mục tiêu giai đoạn; né vùng siêu pháo | F20: WaveDirector;Fortress | G20: ai | H20: Normal | P20: FALSE | Q20: 12 | S20: 30 | T20: defenceLayer | U20: Công thành / Pháo đài tuần | W20: Đồn trú leash theo lớp phòng thủ; áp lực cho phe công là giờ, siêu pháo, mục tiêu | Y20: TRUE | Z20: Off | AA20: Normal | AB20: enemy | AC20: 0.8 | AD20: 1 | AE20: 1.2 | AF20: Assets/MachineBrigade/Resources/Data/balance.json: aiModeProfiles.profiles.siege | AG20: {"name":"Công thành / Pháo đài tuần","controllers":["WaveDirector","Fortress"],"tactics":["depth","base_defence","attrition","ambush","balanced"],"generalTactic":false,"stall":"Off","spend":true,"advance":false,"support":"Normal","engagement":"Normal","defender":"ai","hqSkillThreat":12,"wallRoute":{"route":1,"threat":1.2,"breach":0.8},"targetMask":["enemy"],"objectivePolicy":"Đồn trú leash theo lớp phòng thủ; áp lực cho phe công là giờ, siêu pháo, mục tiêu","autoAiNote":"Mục tiêu giai đoạn; né vùng siêu pháo","leashRegion":"defenceLayer","leashDistance":30}
A21: survival | C21: FALSE | E21: Giữ bãi thả; chặn mối đe dọa gần; không đuổi xa | F21: WaveDirector;Boss | G21: player | H21: Normal | P21: FALSE | U21: Sinh tồn | Y21: FALSE | Z21: Off | AA21: Normal | AB21: enemy | AF21: Assets/MachineBrigade/Resources/Data/balance.json: aiModeProfiles.profiles.survival | AG21: {"name":"Sinh tồn","controllers":["WaveDirector","Boss"],"tactics":[],"generalTactic":false,"stall":"Off","spend":false,"advance":false,"support":"Normal","engagement":"Normal","defender":"player","targetMask":["enemy"],"objectivePolicy":"","autoAiNote":"Giữ bãi thả; chặn mối đe dọa gần; không đuổi xa"}

Sheet AI_ho_so_pha
A1: id | B1: ai_ho_so_che_do_id | C1: thu_tu | D1: profile | E1: stall | F1: when | G1: nguon | H1: raw_json
A2: outpost/0 | B2: outpost | C2: 0 | E2: Both | F2: step:clear | G2: Assets/MachineBrigade/Resources/Data/balance.json: aiModeProfiles.profiles.outpost.phaseOverrides[0] | H2: {"when":"step:clear","stall":"Both"}
A3: outpost/1 | B3: outpost | C3: 1 | E3: Both | F3: step:capture | G3: Assets/MachineBrigade/Resources/Data/balance.json: aiModeProfiles.profiles.outpost.phaseOverrides[1] | H3: {"when":"step:capture","stall":"Both"}
A4: outpost/2 | B4: outpost | C4: 2 | E4: ObjectiveStallOnly | F4: step:build | G4: Assets/MachineBrigade/Resources/Data/balance.json: aiModeProfiles.profiles.outpost.phaseOverrides[2] | H4: {"when":"step:build","stall":"ObjectiveStallOnly"}
A5: outpost/3 | B5: outpost | C5: 3 | E5: AttackerOnly | F5: step:hold | G5: Assets/MachineBrigade/Resources/Data/balance.json: aiModeProfiles.profiles.outpost.phaseOverrides[3] | H5: {"when":"step:hold","stall":"AttackerOnly"}
A6: recon/0 | B6: recon | C6: 0 | D6: capture | F6: alert | G6: Assets/MachineBrigade/Resources/Data/balance.json: aiModeProfiles.profiles.recon.phaseOverrides[0] | H6: {"when":"alert","profile":"capture"}

Sheet AI_ho_so_anh_xa
A1: id | B1: loai | C1: khoa | D1: ho_so | E1: nguon | F1: raw_json
A2: goal.Boss | B2: goal | C2: Boss | D2: bossrush | E2: Assets/MachineBrigade/Resources/Data/balance.json: aiModeProfiles.goals.Boss | F2: "bossrush"
A3: goal.Capture | B3: goal | C3: Capture | D3: capture | E3: Assets/MachineBrigade/Resources/Data/balance.json: aiModeProfiles.goals.Capture | F3: "capture"
A4: goal.Destroy | B4: goal | C4: Destroy | D4: capture | E4: Assets/MachineBrigade/Resources/Data/balance.json: aiModeProfiles.goals.Destroy | F4: "capture"
A5: goal.Duel | B5: goal | C5: Duel | D5: capture | E5: Assets/MachineBrigade/Resources/Data/balance.json: aiModeProfiles.goals.Duel | F5: "capture"
A6: goal.Escort | B6: goal | C6: Escort | D6: escort | E6: Assets/MachineBrigade/Resources/Data/balance.json: aiModeProfiles.goals.Escort | F6: "escort"
A7: goal.Evacuate | B7: goal | C7: Evacuate | D7: escort | E7: Assets/MachineBrigade/Resources/Data/balance.json: aiModeProfiles.goals.Evacuate | F7: "escort"
A8: goal.Hold | B8: goal | C8: Hold | D8: hold | E8: Assets/MachineBrigade/Resources/Data/balance.json: aiModeProfiles.goals.Hold | F8: "hold"
A9: goal.Hunt | B9: goal | C9: Hunt | D9: hunt | E9: Assets/MachineBrigade/Resources/Data/balance.json: aiModeProfiles.goals.Hunt | F9: "hunt"
A10: goal.Intercept | B10: goal | C10: Intercept | D10: hunt | E10: Assets/MachineBrigade/Resources/Data/balance.json: aiModeProfiles.goals.Intercept | F10: "hunt"
A11: goal.Outpost | B11: goal | C11: Outpost | D11: outpost | E11: Assets/MachineBrigade/Resources/Data/balance.json: aiModeProfiles.goals.Outpost | F11: "outpost"
A12: goal.Protect | B12: goal | C12: Protect | D12: protect | E12: Assets/MachineBrigade/Resources/Data/balance.json: aiModeProfiles.goals.Protect | F12: "protect"
... A30: mode.Weekly | B30: mode | C30: Weekly | D30: siege | E30: Assets/MachineBrigade/Resources/Data/balance.json: aiModeProfiles.modes.Weekly | F30: "siege"

Sheet AI_tuong
A1: id | B1: chien_thuat_ua_thich | C1: chien_dich_deck | D1: chien_dich_supports | E1: noi_tai | F1: can_bang_deck | G1: can_bang_elites | H1: chien_dich_stance | I1: chien_dich_style | J1: nguon | K1: raw_json
A2: aurel | B2: all_out | C2: heavy_tank;ifv;railgun_truck;attack_helicopter;long_sam;heavy_rocket_artillery;titan_tank;fighter_jet | D2: cruise_missile;airstrike;napalm_strike | E2: gen.aurel | H2: Attack | I2: aurel | J2: Assets/MachineBrigade/Resources/Data/campaign.json: generals / Assets/MachineBrigade/Resources/Data/balance.json: generals, aiBehaviour.generals | K2: {"id":"aurel","deck":["heavy_tank","ifv","railgun_truck","attack_helicopter","long_sam","heavy_rocket_artillery","titan_tank","fighter_jet"],"supports":["cruise_missile","airstrike","napalm_strike"],"style":"aurel","stance":"Attack"}
A3: brandt | B3: depth | E3: gen.brandt | J3: Assets/MachineBrigade/Resources/Data/campaign.json: generals / Assets/MachineBrigade/Resources/Data/balance.json: generals, aiBehaviour.generals
A4: default | B4: balanced | E4: gen.default | J4: Assets/MachineBrigade/Resources/Data/campaign.json: generals / Assets/MachineBrigade/Resources/Data/balance.json: generals, aiBehaviour.generals
A5: hung | C5: main_battle_tank;heavy_tank;titan_tank;ifv;aa_vehicle;mlrs;tank_destroyer | D5: artillery_barrage;airstrike;cruise_missile | E5: gen.hung | H5: Attack | I5: aurel | J5: Assets/MachineBrigade/Resources/Data/campaign.json: generals / Assets/MachineBrigade/Resources/Data/balance.json: generals, aiBehaviour.generals | K5: {"id":"hung","deck":["main_battle_tank","heavy_tank","titan_tank","ifv","aa_vehicle","mlrs","tank_destroyer"],"supports":["artillery_barrage","airstrike","cruise_missile"],"style":"aurel","stance":"Attack"}
A6: kessler | B6: attrition | C6: wheeled_gun;ifv;main_battle_tank;heavy_tank;sam_launcher;fpv_carrier;mine_layer;mlrs | D6: remote_mines;artillery_barrage;repair_drop | E6: gen.kessler | H6: Defend | I6: kessler | J6: Assets/MachineBrigade/Resources/Data/campaign.json: generals / Assets/MachineBrigade/Resources/Data/balance.json: generals, aiBehaviour.generals | K6: {"id":"kessler","deck":["wheeled_gun","ifv","main_battle_tank","heavy_tank","sam_launcher","fpv_carrier","mine_layer","mlrs"],"supports":["remote_mines","artillery_barrage","repair_drop"],"style":"kessler","stance":"Defend"}
A7: orlov | B7: firepower | C7: mlrs;artillery;mortar_carrier;heavy_rocket_artillery;sam_launcher;main_battle_tank;aa_vehicle;command_vehicle | D7: artillery_barrage;cruise_missile;airstrike | E7: gen.orlov | G7: Artillery | H7: Defend | I7: orlov | J7: Assets/MachineBrigade/Resources/Data/campaign.json: generals / Assets/MachineBrigade/Resources/Data/balance.json: generals, aiBehaviour.generals | K7: {"id":"orlov","deck":["mlrs","artillery","mortar_carrier","heavy_rocket_artillery","sam_launcher","main_battle_tank","aa_vehicle","command_vehicle"],"supports":["artillery_barrage","cruise_missile","airstrike"],"style":"orlov","stance":"Defend"}
A8: quaden | C8: attack_helicopter;attack_jet;fighter_jet;strike_drone;aa_vehicle;main_battle_tank;sam_launcher | D8: airstrike;cruise_missile;napalm_strike | E8: gen.quaden | G8: Air | H8: Attack | I8: quaden | J8: Assets/MachineBrigade/Resources/Data/campaign.json: generals / Assets/MachineBrigade/Resources/Data/balance.json: generals, aiBehaviour.generals | K8: {"id":"quaden","deck":["attack_helicopter","attack_jet","fighter_jet","strike_drone","aa_vehicle","main_battle_tank","sam_launcher"],"supports":["airstrike","cruise_missile","napalm_strike"],"style":"quaden","stance":"Attack"}
A9: sen | C9: strike_drone;fpv_carrier;recon_drone;ew_jammer;ifv;main_battle_tank;aa_vehicle | D9: airstrike;cruise_missile;repair_drop | E9: gen.sen | G9: Drone | H9: Attack | I9: sen | J9: Assets/MachineBrigade/Resources/Data/campaign.json: generals / Assets/MachineBrigade/Resources/Data/balance.json: generals, aiBehaviour.generals | K9: {"id":"sen","deck":["strike_drone","fpv_carrier","recon_drone","ew_jammer","ifv","main_battle_tank","aa_vehicle"],"supports":["airstrike","cruise_missile","repair_drop"],"style":"sen","stance":"Attack"}
A10: thorne | B10: balanced | E10: gen.thorne | J10: Assets/MachineBrigade/Resources/Data/campaign.json: generals / Assets/MachineBrigade/Resources/Data/balance.json: generals, aiBehaviour.generals
A11: varga | B11: breakthrough | C11: light_tank;main_battle_tank;heavy_tank;tank_destroyer;ifv;flame_tank;twin_tank;fpv_carrier | D11: artillery_barrage;airstrike;repair_drop | E11: gen.varga | F11: armored_bulldozer | G11: Tank;Heavy | H11: Attack | I11: varga | J11: Assets/MachineBrigade/Resources/Data/campaign.json: generals / Assets/MachineBrigade/Resources/Data/balance.json: generals, aiBehaviour.generals | K11: {"id":"varga","deck":["light_tank","main_battle_tank","heavy_tank","tank_destroyer","ifv","flame_tank","twin_tank","fpv_carrier"],"supports":["artillery_barrage","airstrike","repair_drop"],"style":"varga","stance":"Attack"}
A12: venn | B12: dispersal | E12: gen.venn | J12: Assets/MachineBrigade/Resources/Data/campaign.json: generals / Assets/MachineBrigade/Resources/Data/balance.json: generals, aiBehaviour.generals
A13: wolff | B13: air_superiority | E13: gen.wolff | J13: Assets/MachineBrigade/Resources/Data/campaign.json: generals / Assets/MachineBrigade/Resources/Data/balance.json: generals, aiBehaviour.generals

Sheet AI_tham_so
A1: id | B1: khoi | C1: tham_so | D1: bac | E1: max | F1: metric | G1: min | H1: reason | I1: value | J1: nguon | K1: raw_json
A2: economy.airCap | B2: economy | C2: airCap | E2: 6 | F2: FPS ở trần quân | G2: 6 | I2: 6 | J2: Assets/MachineBrigade/Resources/Data/balance.json: ai.economy.airCap | K2: {"value":6.0,"min":6.0,"max":6.0,"metric":"FPS ở trần quân","reason":""}
A3: economy.attackThreshold | B3: economy | C3: attackThreshold | E3: 1.2 | F3: Tỷ lệ thời gian có giao tranh | G3: 1.2 | H3: Tỷ lệ sức mạnh ta / địch tối thiểu | I3: 1.2 | J3: Assets/MachineBrigade/Resources/Data/balance.json: ai.economy.attackThreshold | K3: {"value":1.2,"min":1.2,"max":1.2,"metric":"Tỷ lệ thời gian có giao tranh","reason":"Tỷ lệ sức mạnh ta / địch tối thiểu"}
A4: economy.baseIncome | B4: economy | C4: baseIncome | E4: 1 | F4: Số quân trung bình còn sống mỗi phe | G4: 1 | H4: Thu nhập khi chưa có cứ điểm | I4: 1 | J4: Assets/MachineBrigade/Resources/Data/balance.json: ai.economy.baseIncome | K4: {"value":1.0,"min":1.0,"max":1.0,"metric":"Số quân trung bình còn sống mỗi phe","reason":"Thu nhập khi chưa có cứ điểm"}
A5: economy.escalation/0 | B5: economy | C5: escalation | D5: 0 | E5: 30 | F5: Tỷ lệ thời gian có giao tranh | G5: 30 | H5: Các bậc sau: khoảng 50, 70, 90 s (bảng luật bên dưới) | I5: 30 | J5: Assets/MachineBrigade/Resources/Data/balance.json: ai.economy.escalation[0] | K5: {"value":30.0,"min":30.0,"max":30.0,"metric":"Tỷ lệ thời gian có giao tranh","reason":"Các bậc sau: khoảng 50, 70, 90 s (bảng luật bên dưới)"}
A6: economy.escalation/1 | B6: economy | C6: escalation | D6: 1 | E6: 50 | F6: Tỷ lệ thời gian có giao tranh | G6: 50 | H6: Các bậc sau: khoảng 50, 70, 90 s (bảng luật bên dưới) | I6: 50 | J6: Assets/MachineBrigade/Resources/Data/balance.json: ai.economy.escalation[1] | K6: {"value":50.0,"min":50.0,"max":50.0,"metric":"Tỷ lệ thời gian có giao tranh","reason":"Các bậc sau: khoảng 50, 70, 90 s (bảng luật bên dưới)"}
A7: economy.escalation/2 | B7: economy | C7: escalation | D7: 2 | E7: 70 | F7: Tỷ lệ thời gian có giao tranh | G7: 70 | H7: Các bậc sau: khoảng 50, 70, 90 s (bảng luật bên dưới) | I7: 70 | J7: Assets/MachineBrigade/Resources/Data/balance.json: ai.economy.escalation[2] | K7: {"value":70.0,"min":70.0,"max":70.0,"metric":"Tỷ lệ thời gian có giao tranh","reason":"Các bậc sau: khoảng 50, 70, 90 s (bảng luật bên dưới)"}
A8: economy.escalation/3 | B8: economy | C8: escalation | D8: 3 | E8: 90 | F8: Tỷ lệ thời gian có giao tranh | G8: 90 | H8: Các bậc sau: khoảng 50, 70, 90 s (bảng luật bên dưới) | I8: 90 | J8: Assets/MachineBrigade/Resources/Data/balance.json: ai.economy.escalation[3] | K8: {"value":90.0,"min":90.0,"max":90.0,"metric":"Tỷ lệ thời gian có giao tranh","reason":"Các bậc sau: khoảng 50, 70, 90 s (bảng luật bên dưới)"}
A9: economy.finalPhase | B9: economy | C9: finalPhase | E9: 120 | F9: Tỷ lệ thời gian có giao tranh | G9: 120 | H9: Chế độ giao tranh có pha cuối (ví dụ 2 phút cuối, điểm từ cứ điểm ×2) để trận luôn kết thúc. | I9: 120 | J9: Assets/MachineBrigade/Resources/Data/balance.json: ai.economy.finalPhase | K9: {"value":120,"min":120,"max":120,"metric":"Tỷ lệ thời gian có giao tranh","reason":"Chế độ giao tranh có pha cuối (ví dụ 2 phút cuối, điểm từ cứ điểm ×2) để trận luôn kết thúc."}
A10: economy.finalPhaseScale | B10: economy | C10: finalPhaseScale | E10: 2 | F10: Tỷ lệ thời gian có giao tranh | G10: 2 | H10: Chế độ giao tranh có pha cuối (ví dụ 2 phút cuối, điểm từ cứ điểm ×2) để trận luôn kết thúc. | I10: 2 | J10: Assets/MachineBrigade/Resources/Data/balance.json: ai.economy.finalPhaseScale | K10: {"value":2,"min":2,"max":2,"metric":"Tỷ lệ thời gian có giao tranh","reason":"Chế độ giao tranh có pha cuối (ví dụ 2 phút cuối, điểm từ cứ điểm ×2) để trận luôn kết thúc."}
A11: economy.groundCap | B11: economy | C11: groundCap | E11: 32 | F11: FPS ở trần quân | G11: 32 | H11: Không chiến thuật nào được nới | I11: 32 | J11: Assets/MachineBrigade/Resources/Data/balance.json: ai.economy.groundCap | K11: {"value":32.0,"min":32.0,"max":32.0,"metric":"FPS ở trần quân","reason":"Không chiến thuật nào được nới"}
A12: economy.perPoint | B12: economy | C12: perPoint | E12: 0.25 | F12: Số quân trung bình còn sống mỗi phe | G12: 0.25 | H12: Như hiện tại; chỉnh theo dữ liệu game | I12: 0.25 | J12: Assets/MachineBrigade/Resources/Data/balance.json: ai.economy.perPoint | K12: {"value":0.25,"min":0.25,"max":0.25,"metric":"Số quân trung bình còn sống mỗi phe","reason":"Như hiện tại; chỉnh theo dữ liệu game"}
A13: economy.stockCap | B13: economy | C13: stockCap | E13: 30 | F13: Số quân trung bình còn sống mỗi phe | G13: 30 | H13: Chỉ huy Vault: 45 | I13: 30 | J13: Assets/MachineBrigade/Resources/Data/balance.json: ai.economy.stockCap | K13: {"value":30.0,"min":30.0,"max":30.0,"metric":"Số quân trung bình còn sống mỗi phe","reason":"Chỉ huy Vault: 45"}
A14: economy.stockCapVault | B14: economy | C14: stockCapVault | E14: 45 | F14: Số quân trung bình còn sống mỗi phe | G14: 45 | H14: Chỉ huy Vault: 45 | I14: 45 | J14: Assets/MachineBrigade/Resources/Data/balance.json: ai.economy.stockCapVault | K14: {"value":45.0,"min":45.0,"max":45.0,"metric":"Số quân trung bình còn sống mỗi phe","reason":"Chỉ huy Vault: 45"}
A15: economy.useOrLoseRamp | B15: economy | C15: useOrLoseRamp | E15: 30 | F15: Số quân trung bình còn sống mỗi phe | G15: 30 | H15: Từ ngưỡng mặc định xuống ngưỡng thấp nhất | I15: 30 | J15: Assets/MachineBrigade/Resources/Data/balance.json: ai.economy.useOrLoseRamp | K15: {"value":30.0,"min":30.0,"max":30.0,"metric":"Số quân trung bình còn sống mỗi phe","reason":"Từ ngưỡng mặc định xuống ngưỡng thấp nhất"}
A16: economy.useOrLoseThreshold | B16: economy | C16: useOrLoseThreshold | E16: 0.9 | F16: Số quân trung bình còn sống mỗi phe | G16: 0.9 | H16: Khi đã chạm trần quân và CP đầy | I16: 0.9 | J16: Assets/MachineBrigade/Resources/Data/balance.json: ai.economy.useOrLoseThreshold | K16: {"value":0.9,"min":0.9,"max":0.9,"metric":"Số quân trung bình còn sống mỗi phe","reason":"Khi đã chạm trần quân và CP đầy"}
A17: params.airAaLimit | B17: params | C17: airAaLimit | E17: 1.5 | F17: Số máy bay bị hạ mỗi lượt | G17: 0.5 | I17: 1 | J17: Assets/MachineBrigade/Resources/Data/balance.json: ai.params.airAaLimit | K17: {"value":1.0,"min":0.5,"max":1.5,"metric":"Số máy bay bị hạ mỗi lượt","reason":""}
A18: params.artilleryPrep | B18: params | C18: artilleryPrep | E18: 2 | F18: Thời điểm đợt tấn công đầu tiên | G18: 0 | I18: 0 | J18: Assets/MachineBrigade/Resources/Data/balance.json: ai.params.artilleryPrep | K18: {"value":0.0,"min":0.0,"max":2.0,"metric":"Thời điểm đợt tấn công đầu tiên","reason":""}
A19: params.attackThreshold | B19: params | C19: attackThreshold | E19: 1.6 | F19: Tỷ lệ thời gian có giao tranh; số đợt tấn công thất bại | G19: 0.8 | H19: Thấp quá: lao vào chỗ chết; cao quá: trận đứng yên | I19: 1.2 | J19: Assets/MachineBrigade/Resources/Data/balance.json: ai.params.attackThreshold | K19: {"value":1.2,"min":0.8,"max":1.6,"metric":"Tỷ lệ thời gian có giao tranh; số đợt tấn công thất bại","reason":"Thấp quá: lao vào chỗ chết; cao quá: trận đứng yên"}
A20: params.cohesion | B20: params | C20: cohesion | E20: 1 | F20: Vi phạm đội hình mỗi phút | G20: 0 | I20: 1 | J20: Assets/MachineBrigade/Resources/Data/balance.json: ai.params.cohesion | K20: {"value":1.0,"min":0.0,"max":1.0,"metric":"Vi phạm đội hình mỗi phút","reason":""}
A21: params.confidenceDecay | B21: params | C21: confidenceDecay | E21: 0.12 | F21: Số lần AI đánh vào nơi địch đã đi; số lần bị bất ngờ | G21: 0.03 | H21: Theo độ khó: Cực khó giảm chậm hơn | I21: 0.06 | J21: Assets/MachineBrigade/Resources/Data/balance.json: ai.params.confidenceDecay | K21: {"value":0.06,"min":0.03,"max":0.12,"metric":"Số lần AI đánh vào nơi địch đã đi; số lần bị bất ngờ","reason":"Theo độ khó: Cực khó giảm chậm hơn"}
A22: params.cpSaving | B22: params | C22: cpSaving | E22: 1 | F22: CP trung bình tích trữ | G22: 0 | H22: Tổng tấn công | I22: 0 | J22: Assets/MachineBrigade/Resources/Data/balance.json: ai.params.cpSaving | K22: {"value":0.0,"min":0.0,"max":1.0,"metric":"CP trung bình tích trữ","reason":"Tổng tấn công"}
A23: params.emergencyCooldown | B23: params | C23: emergencyCooldown | E23: 40 | F23: Số lần dùng khẩn cấp mỗi phút; chỉ số đổi quyết định | G23: 15 | H23: Ngăn dùng khẩn cấp để lách luật cam kết | I23: 25 | J23: Assets/MachineBrigade/Resources/Data/balance.json: ai.params.emergencyCooldown | K23: {"value":25.0,"min":15.0,"max":40.0,"metric":"Số lần dùng khẩn cấp mỗi phút; chỉ số đổi quyết định","reason":"Ngăn dùng khẩn cấp để lách luật cam kết"}
A24: params.fallbackRatio | B24: params | C24: fallbackRatio | E24: 0.7 | F24: Số tuyến mất; thời lượng trận Phòng thủ | G24: 0.5 | H24: Không áp cho từng xe theo máu | I24: 0.6 | J24: Assets/MachineBrigade/Resources/Data/balance.json: ai.params.fallbackRatio | K24: {"value":0.6,"min":0.5,"max":0.7,"metric":"Số tuyến mất; thời lượng trận Phòng thủ","reason":"Không áp cho từng xe theo máu"}
A25: params.flankWeight | B25: params | C25: flankWeight | E25: 2 | F25: Tỷ lệ thời gian đánh sườn | G25: 0.5 | H25: Dấu vân hành vi | I25: 1 | J25: Assets/MachineBrigade/Resources/Data/balance.json: ai.params.flankWeight | K25: {"value":1.0,"min":0.5,"max":2.0,"metric":"Tỷ lệ thời gian đánh sườn","reason":"Dấu vân hành vi"}
A26: params.focusWeight | B26: params | C26: focusWeight | E26: 2 | F26: Số mục tiêu đổi mỗi phút; thời gian hạ mục tiêu | G26: 0.5 | I26: 1 | J26: Assets/MachineBrigade/Resources/Data/balance.json: ai.params.focusWeight | K26: {"value":1.0,"min":0.5,"max":2.0,"metric":"Số mục tiêu đổi mỗi phút; thời gian hạ mục tiêu","reason":""}
A27: params.holdFire | B27: params | C27: holdFire | E27: 0.6 | F27: Tỷ lệ thời gian giữ lửa; sát thương phát đầu | G27: 0 | H27: Phục kích | I27: 0 | J27: Assets/MachineBrigade/Resources/Data/balance.json: ai.params.holdFire | K27: {"value":0.0,"min":0.0,"max":0.6,"metric":"Tỷ lệ thời gian giữ lửa; sát thương phát đầu","reason":"Phục kích"}
A28: params.idleReassess | B28: params | C28: idleReassess | E28: 10 | F28: Tỷ lệ thời gian đứng yên không lý do | G28: 3 | I28: 5 | J28: Assets/MachineBrigade/Resources/Data/balance.json: ai.params.idleReassess | K28: {"value":5.0,"min":3.0,"max":10.0,"metric":"Tỷ lệ thời gian đứng yên không lý do","reason":""}
A29: params.mainEffort | B29: params | C29: mainEffort | E29: 0.8 | F29: Độ tập trung lực lượng | G29: 0.3 | I29: 0.5 | J29: Assets/MachineBrigade/Resources/Data/balance.json: ai.params.mainEffort | K29: {"value":0.5,"min":0.3,"max":0.8,"metric":"Độ tập trung lực lượng","reason":""}
A30: params.minCommit | B30: params | C30: minCommit | E30: 8 | F30: Số lần đổi trạng thái mỗi phút; tỷ lệ hành động bị bỏ dở | G30: 2 | H30: Như trên | I30: 4 | J30: Assets/MachineBrigade/Resources/Data/balance.json: ai.params.minCommit | K30: {"value":4.0,"min":2.0,"max":8.0,"metric":"Số lần đổi trạng thái mỗi phút; tỷ lệ hành động bị bỏ dở","reason":"Như trên"}
A31: params.overwhelmRatio | B31: params | C31: overwhelmRatio | E31: 3 | F31: Số xe bị hạ khi bị áp đảo; số lần gom | G31: 1.6 | I31: 2 | J31: Assets/MachineBrigade/Resources/Data/balance.json: ai.params.overwhelmRatio | K31: {"value":2.0,"min":1.6,"max":3.0,"metric":"Số xe bị hạ khi bị áp đảo; số lần gom","reason":""}
A32: params.reactionDelay | B32: params | C32: reactionDelay | E32: 1.5 | F32: Tỷ lệ né đòn có cảnh báo | G32: 0.3 | H32: Theo độ khó | I32: 0.8 | J32: Assets/MachineBrigade/Resources/Data/balance.json: ai.params.reactionDelay | K32: {"value":0.8,"min":0.3,"max":1.5,"metric":"Tỷ lệ né đòn có cảnh báo","reason":"Theo độ khó"}
A33: params.splashSpread | B33: params | C33: splashSpread | E33: 2 | F33: Số xe bị hạ bởi bắn lan mỗi phút; độ dàn trải đội | G33: 0.5 | I33: 1 | J33: Assets/MachineBrigade/Resources/Data/balance.json: ai.params.splashSpread | K33: {"value":1.0,"min":0.5,"max":2.0,"metric":"Số xe bị hạ bởi bắn lan mỗi phút; độ dàn trải đội","reason":""}
A34: params.stuckTime | B34: params | C34: stuckTime | E34: 5 | F34: Số lần kẹt mỗi phút, thời gian kẹt trung bình | G34: 2 | I34: 3 | J34: Assets/MachineBrigade/Resources/Data/balance.json: ai.params.stuckTime | K34: {"value":3.0,"min":2.0,"max":5.0,"metric":"Số lần kẹt mỗi phút, thời gian kẹt trung bình","reason":""}
A35: params.switchMargin | B35: params | C35: switchMargin | E35: 15 | F35: Số lần đổi hành động mỗi phút của đội | G35: 4 | H35: Thấp: đổi ý liên tục; cao: không phản ứng kịp | I35: 8 | J35: Assets/MachineBrigade/Resources/Data/balance.json: ai.params.switchMargin | K35: {"value":8.0,"min":4.0,"max":15.0,"metric":"Số lần đổi hành động mỗi phút của đội","reason":"Thấp: đổi ý liên tục; cao: không phản ứng kịp"}
A36: params.tacticCooldown | B36: params | C36: tacticCooldown | E36: 60 | F36: Số lần đổi mỗi trận; tỷ lệ thắng sau khi đổi | G36: 45 | I36: 50 | J36: Assets/MachineBrigade/Resources/Data/balance.json: ai.params.tacticCooldown | K36: {"value":50.0,"min":45.0,"max":60.0,"metric":"Số lần đổi mỗi trận; tỷ lệ thắng sau khi đổi","reason":""}
A37: params.tacticTransition | B37: params | C37: tacticTransition | E37: 8 | F37: Sát thương mất trong lúc chuyển | G37: 3 | H37: Cái giá của việc đổi | I37: 5 | J37: Assets/MachineBrigade/Resources/Data/balance.json: ai.params.tacticTransition | K37: {"value":5.0,"min":3.0,"max":8.0,"metric":"Sát thương mất trong lúc chuyển","reason":"Cái giá của việc đổi"}
A38: world.aaShare | B38: world | C38: aaShare | E38: 0.2 | F38: Số máy bay bị hạ mỗi lượt | G38: 0.05 | H38: MISMATCH: own anti-air share below this | I38: 0.1 | J38: Assets/MachineBrigade/Resources/Data/balance.json: ai.world.aaShare | K38: {"value":0.1,"min":0.05,"max":0.2,"metric":"Số máy bay bị hạ mỗi lượt","reason":"MISMATCH: own anti-air share below this"}
A39: world.airShare | B39: world | C39: airShare | E39: 0.4 | F39: Số máy bay bị hạ mỗi lượt | G39: 0.15 | H39: MISMATCH: enemy aircraft share of its strength | I39: 0.25 | J39: Assets/MachineBrigade/Resources/Data/balance.json: ai.world.airShare | K39: {"value":0.25,"min":0.15,"max":0.4,"metric":"Số máy bay bị hạ mỗi lượt","reason":"MISMATCH: enemy aircraft share of its strength"}
A40: world.armourShare | B40: world | C40: armourShare | E40: 0.6 | F40: Thời gian hạ mục tiêu | G40: 0.3 | H40: MISMATCH: enemy armour share of its strength | I40: 0.4 | J40: Assets/MachineBrigade/Resources/Data/balance.json: ai.world.armourShare | K40: {"value":0.4,"min":0.3,"max":0.6,"metric":"Thời gian hạ mục tiêu","reason":"MISMATCH: enemy armour share of its strength"}
A41: world.atShare | B41: world | C41: atShare | E41: 0.3 | F41: Thời gian hạ mục tiêu | G41: 0.1 | H41: MISMATCH: own anti-tank share below this | I41: 0.15 | J41: Assets/MachineBrigade/Resources/Data/balance.json: ai.world.atShare | K41: {"value":0.15,"min":0.1,"max":0.3,"metric":"Thời gian hạ mục tiêu","reason":"MISMATCH: own anti-tank share below this"}
A42: world.bigFight | B42: world | C42: bigFight | E42: 1500 | F42: Tỷ lệ thời gian có giao tranh | G42: 300 | H42: health lost by both sides in 5 s that resets the pressure tiers | I42: 600 | J42: Assets/MachineBrigade/Resources/Data/balance.json: ai.world.bigFight | K42: {"value":600,"min":300,"max":1500,"metric":"Tỷ lệ thời gian có giao tranh","reason":"health lost by both sides in 5 s that resets the pressure tiers"}
A43: world.cell | B43: world | C43: cell | E43: 16 | F43: AI tick time (M.5) | G43: 6 | H43: 10 m cells to start | I43: 10 | J43: Assets/MachineBrigade/Resources/Data/balance.json: ai.world.cell | K43: {"value":10,"min":6,"max":16,"metric":"AI tick time (M.5)","reason":"10 m cells to start"}
A44: world.churnWarn | B44: world | C44: churnWarn | E44: 12 | F44: Số lần đổi hành động mỗi phút của đội | G44: 3 | H44: switches a minute per squad above which the viewer warns (J.3) | I44: 6 | J44: Assets/MachineBrigade/Resources/Data/balance.json: ai.world.churnWarn | K44: {"value":6,"min":3,"max":12,"metric":"Số lần đổi hành động mỗi phút của đội","reason":"switches a minute per squad above which the viewer warns (J.3)"}
A45: world.escalationPoints | B45: world | C45: escalationPoints | E45: 2 | F45: Tỷ lệ thời gian có giao tranh | G45: 1.25 | H45: tier 1: points' income and bleed x this | I45: 1.5 | J45: Assets/MachineBrigade/Resources/Data/balance.json: ai.world.escalationPoints | K45: {"value":1.5,"min":1.25,"max":2,"metric":"Tỷ lệ thời gian có giao tranh","reason":"tier 1: points' income and bleed x this"}
A46: world.eventLife | B46: world | C46: eventLife | E46: 15 | F46: Số lần đổi hành động mỗi phút của đội | G46: 4 | H46: seconds an event lasts unless refreshed | I46: 8 | J46: Assets/MachineBrigade/Resources/Data/balance.json: ai.world.eventLife | K46: {"value":8,"min":4,"max":15,"metric":"Số lần đổi hành động mỗi phút của đội","reason":"seconds an event lasts unless refreshed"}
A47: world.highValue | B47: world | C47: highValue | E47: 2.5 | F47: Số mục tiêu giá trị bị hạ | G47: 1.2 | H47: a contact this many times the mean known strength is high value | I47: 1.5 | J47: Assets/MachineBrigade/Resources/Data/balance.json: ai.world.highValue | K47: {"value":1.5,"min":1.2,"max":2.5,"metric":"Số mục tiêu giá trị bị hạ","reason":"a contact this many times the mean known strength is high value"}
A48: world.mergeThreshold | B48: world | C48: mergeThreshold | E48: 0.25 | F48: Khoảng cách dấu vân giữa các cặp | G48: 0.1 | H48: H.3: pairs closer than this merge | I48: 0.15 | J48: Assets/MachineBrigade/Resources/Data/balance.json: ai.world.mergeThreshold | K48: {"value":0.15,"min":0.1,"max":0.25,"metric":"Khoảng cách dấu vân giữa các cặp","reason":"H.3: pairs closer than this merge"}
... A50: world.splashMin | B50: world | C50: splashMin | E50: 4 | F50: Số xe bị hạ bởi bắn lan mỗi phút | G50: 1 | H50: a weapon with a blast this wide (m) paints the splash threat | I50: 2 | J50: Assets/MachineBrigade/Resources/Data/balance.json: ai.world.splashMin | K50: {"value":2,"min":1,"max":4,"metric":"Số xe bị hạ bởi bắn lan mỗi phút","reason":"a weapon with a blast this wide (m) paints the splash threat"}

Sheet AI_vai_tro
A1: id | B1: engage | C1: overwhelmed | D1: nguon | E1: raw_json
A2: Arty | C2: Scoot | D2: Assets/MachineBrigade/Resources/Data/balance.json: aiBehaviour.roles.Arty | E2: {"engage":[],"overwhelmed":"Scoot"}
A3: AttackHeli | B3: 0.85;1.0 | C3: Rearm | D3: Assets/MachineBrigade/Resources/Data/balance.json: aiBehaviour.roles.AttackHeli | E3: {"engage":[0.85,1.0],"overwhelmed":"Rearm"}
A4: Bomber | C4: Hold | D4: Assets/MachineBrigade/Resources/Data/balance.json: aiBehaviour.roles.Bomber | E4: {"engage":[],"overwhelmed":"Hold"}
A5: Bunker | C5: Hold | D5: Assets/MachineBrigade/Resources/Data/balance.json: aiBehaviour.roles.Bunker | E5: {"engage":[],"overwhelmed":"Hold"}
A6: CAS | B6: 0.6;1.0 | C6: Rearm | D6: Assets/MachineBrigade/Resources/Data/balance.json: aiBehaviour.roles.CAS | E6: {"engage":[0.6,1.0],"overwhelmed":"Rearm"}
A7: Drone | C7: Hold | D7: Assets/MachineBrigade/Resources/Data/balance.json: aiBehaviour.roles.Drone | E7: {"engage":[],"overwhelmed":"Hold"}
A8: Fighter | B8: 0.8;1.0 | C8: Rearm | D8: Assets/MachineBrigade/Resources/Data/balance.json: aiBehaviour.roles.Fighter | E8: {"engage":[0.8,1.0],"overwhelmed":"Rearm"}
A9: Flame | C9: Hold | D9: Assets/MachineBrigade/Resources/Data/balance.json: aiBehaviour.roles.Flame | E9: {"engage":[],"overwhelmed":"Hold"}
A10: Gunship | C10: Shift | D10: Assets/MachineBrigade/Resources/Data/balance.json: aiBehaviour.roles.Gunship | E10: {"engage":[],"overwhelmed":"Shift"}
A11: GunshipHeli | B11: 0.7;0.9 | C11: Rearm | D11: Assets/MachineBrigade/Resources/Data/balance.json: aiBehaviour.roles.GunshipHeli | E11: {"engage":[0.7,0.9],"overwhelmed":"Rearm"}
A12: Heavy | B12: 0.6;0.8 | C12: Hold | D12: Assets/MachineBrigade/Resources/Data/balance.json: aiBehaviour.roles.Heavy | E12: {"engage":[0.6,0.8],"overwhelmed":"Hold"}
A13: IFV | B13: 0.7;0.9 | C13: Shift | D13: Assets/MachineBrigade/Resources/Data/balance.json: aiBehaviour.roles.IFV | E13: {"engage":[0.7,0.9],"overwhelmed":"Shift"}
A14: Laser | C14: Shift | D14: Assets/MachineBrigade/Resources/Data/balance.json: aiBehaviour.roles.Laser | E14: {"engage":[],"overwhelmed":"Shift"}
A15: Light | B15: 0.85;1.0 | C15: Hold | D15: Assets/MachineBrigade/Resources/Data/balance.json: aiBehaviour.roles.Light | E15: {"engage":[0.85,1.0],"overwhelmed":"Hold"}
A16: MBT | B16: 0.75;0.9 | C16: Cover | D16: Assets/MachineBrigade/Resources/Data/balance.json: aiBehaviour.roles.MBT | E16: {"engage":[0.75,0.9],"overwhelmed":"Cover"}
A17: MLRS | C17: Scoot | D17: Assets/MachineBrigade/Resources/Data/balance.json: aiBehaviour.roles.MLRS | E17: {"engage":[],"overwhelmed":"Scoot"}
A18: Rail | B18: 0.9;1.0 | C18: Shift | D18: Assets/MachineBrigade/Resources/Data/balance.json: aiBehaviour.roles.Rail | E18: {"engage":[0.9,1.0],"overwhelmed":"Shift"}
A19: Recon | C19: Shift | D19: Assets/MachineBrigade/Resources/Data/balance.json: aiBehaviour.roles.Recon | E19: {"engage":[],"overwhelmed":"Shift"}
A20: SAM | B20: 0.8;1.0 | C20: Shift | D20: Assets/MachineBrigade/Resources/Data/balance.json: aiBehaviour.roles.SAM | E20: {"engage":[0.8,1.0],"overwhelmed":"Shift"}
A21: SPAAG | B21: 0.7;0.9 | C21: Hold | D21: Assets/MachineBrigade/Resources/Data/balance.json: aiBehaviour.roles.SPAAG | E21: {"engage":[0.7,0.9],"overwhelmed":"Hold"}
A22: ScoutHeli | B22: 0.9;1.0 | C22: Rearm | D22: Assets/MachineBrigade/Resources/Data/balance.json: aiBehaviour.roles.ScoutHeli | E22: {"engage":[0.9,1.0],"overwhelmed":"Rearm"}
A23: Siege | C23: Hold | D23: Assets/MachineBrigade/Resources/Data/balance.json: aiBehaviour.roles.Siege | E23: {"engage":[],"overwhelmed":"Hold"}
A24: Stealth | B24: 0.9;1.0 | C24: Shift | D24: Assets/MachineBrigade/Resources/Data/balance.json: aiBehaviour.roles.Stealth | E24: {"engage":[0.9,1.0],"overwhelmed":"Shift"}
A25: Strike | C25: Scoot | D25: Assets/MachineBrigade/Resources/Data/balance.json: aiBehaviour.roles.Strike | E25: {"engage":[],"overwhelmed":"Scoot"}
A26: Support | C26: Hold | D26: Assets/MachineBrigade/Resources/Data/balance.json: aiBehaviour.roles.Support | E26: {"engage":[],"overwhelmed":"Hold"}
A27: TD | B27: 0.9;1.0 | C27: Shift | D27: Assets/MachineBrigade/Resources/Data/balance.json: aiBehaviour.roles.TD | E27: {"engage":[0.9,1.0],"overwhelmed":"Shift"}
A28: UAV | B28: 0.9;1.0 | C28: Shift | D28: Assets/MachineBrigade/Resources/Data/balance.json: aiBehaviour.roles.UAV | E28: {"engage":[0.9,1.0],"overwhelmed":"Shift"}
A29: VBIED | C29: Hold | D29: Assets/MachineBrigade/Resources/Data/balance.json: aiBehaviour.roles.VBIED | E29: {"engage":[],"overwhelmed":"Hold"}

Sheet AI_don_vi
A1: id | B1: don_vi | C1: vai_tro | D1: nguon | E1: raw_json
A2: aa_corvette | B2: aa_corvette | C2: SAM | D2: Assets/MachineBrigade/Resources/Data/balance.json: aiBehaviour.units.aa_corvette | E2: "SAM"
A3: aa_destroyer | B3: aa_destroyer | C3: SAM | D3: Assets/MachineBrigade/Resources/Data/balance.json: aiBehaviour.units.aa_destroyer | E3: "SAM"
A4: aa_frigate | B4: aa_frigate | C4: SAM | D4: Assets/MachineBrigade/Resources/Data/balance.json: aiBehaviour.units.aa_frigate | E4: "SAM"
A5: aa_vehicle | B5: aa_vehicle | C5: SPAAG | D5: Assets/MachineBrigade/Resources/Data/balance.json: aiBehaviour.units.aa_vehicle | E5: "SPAAG"
A6: ammo_carrier | B6: ammo_carrier | C6: Support | D6: Assets/MachineBrigade/Resources/Data/balance.json: aiBehaviour.units.ammo_carrier | E6: "Support"
A7: armored_bulldozer | B7: armored_bulldozer | C7: Bunker | D7: Assets/MachineBrigade/Resources/Data/balance.json: aiBehaviour.units.armored_bulldozer | E7: "Bunker"
A8: armored_car | B8: armored_car | C8: Light | D8: Assets/MachineBrigade/Resources/Data/balance.json: aiBehaviour.units.armored_car | E8: "Light"
A9: artillery | B9: artillery | C9: Arty | D9: Assets/MachineBrigade/Resources/Data/balance.json: aiBehaviour.units.artillery | E9: "Arty"
A10: ashm_corvette | B10: ashm_corvette | C10: TD | D10: Assets/MachineBrigade/Resources/Data/balance.json: aiBehaviour.units.ashm_corvette | E10: "TD"
A11: attack_helicopter | B11: attack_helicopter | C11: AttackHeli | D11: Assets/MachineBrigade/Resources/Data/balance.json: aiBehaviour.units.attack_helicopter | E11: "AttackHeli"
A12: attack_jet | B12: attack_jet | C12: CAS | D12: Assets/MachineBrigade/Resources/Data/balance.json: aiBehaviour.units.attack_jet | E12: "CAS"
... A68: zu23_technical | B68: zu23_technical | C68: SPAAG | D68: Assets/MachineBrigade/Resources/Data/balance.json: aiBehaviour.units.zu23_technical | E68: "SPAAG"

Sheet AI_trang_thai
A1: id | B1: commit | C1: priority | D1: nguon | E1: raw_json
A2: APPROACH | B2: 3 | C2: 2 | D2: Assets/MachineBrigade/Resources/Data/balance.json: aiBehaviour.states.APPROACH | E2: {"priority":2,"commit":3.0}
A3: COMBAT | B3: 4 | C3: 3 | D3: Assets/MachineBrigade/Resources/Data/balance.json: aiBehaviour.states.COMBAT | E3: {"priority":3,"commit":4.0}
A4: FLANK | B4: 6 | C4: 2 | D4: Assets/MachineBrigade/Resources/Data/balance.json: aiBehaviour.states.FLANK | E4: {"priority":2,"commit":6.0}
A5: HOLD | B5: 5 | C5: 2 | D5: Assets/MachineBrigade/Resources/Data/balance.json: aiBehaviour.states.HOLD | E5: {"priority":2,"commit":5.0}
A6: OVERWATCH | B6: 4 | C6: 2 | D6: Assets/MachineBrigade/Resources/Data/balance.json: aiBehaviour.states.OVERWATCH | E6: {"priority":2,"commit":4.0}
A7: REGROUP | B7: 3 | C7: 3 | D7: Assets/MachineBrigade/Resources/Data/balance.json: aiBehaviour.states.REGROUP | E7: {"priority":3,"commit":3.0}
A8: TRAVEL | B8: 4 | C8: 1 | D8: Assets/MachineBrigade/Resources/Data/balance.json: aiBehaviour.states.TRAVEL | E8: {"priority":1,"commit":4.0}

Sheet AI_thap
A1: id | B1: thap | C1: mode | D1: modes | E1: nguon | F1: raw_json
A2: aa_gun_tower | B2: aa_gun_tower | C2: AirFirst | D2: Nearest | E2: Assets/MachineBrigade/Resources/Data/balance.json: aiBehaviour.towers.aa_gun_tower | F2: {"mode":"AirFirst","modes":["Nearest"]}
A3: aa_turret | B3: aa_turret | C3: AirFirst | D3: Nearest | E3: Assets/MachineBrigade/Resources/Data/balance.json: aiBehaviour.towers.aa_turret | F3: {"mode":"AirFirst","modes":["Nearest"]}
A4: atgm_tower | B4: atgm_tower | C4: Strongest | D4: Lead | E4: Assets/MachineBrigade/Resources/Data/balance.json: aiBehaviour.towers.atgm_tower | F4: {"mode":"Strongest","modes":["Lead"]}
A5: c_ram | B5: c_ram | C5: ShieldKey | D5: NearestRound | E5: Assets/MachineBrigade/Resources/Data/balance.json: aiBehaviour.towers.c_ram | F5: {"mode":"ShieldKey","modes":["NearestRound"]}
A6: coastal_battery | B6: coastal_battery | C6: Strongest | D6: Lead | E6: Assets/MachineBrigade/Resources/Data/balance.json: aiBehaviour.towers.coastal_battery | F6: {"mode":"Strongest","modes":["Lead"]}
A7: drone_hangar | B7: drone_hangar | C7: Strongest | D7: ArtilleryFirst | E7: Assets/MachineBrigade/Resources/Data/balance.json: aiBehaviour.towers.drone_hangar | F7: {"mode":"Strongest","modes":["ArtilleryFirst"]}
A8: ew_tower | B8: ew_tower | C8: None | E8: Assets/MachineBrigade/Resources/Data/balance.json: aiBehaviour.towers.ew_tower | F8: {"mode":"None","modes":[]}
A9: guard_tower | B9: guard_tower | C9: Nearest | D9: Weakest;AirFirst | E9: Assets/MachineBrigade/Resources/Data/balance.json: aiBehaviour.towers.guard_tower | F9: {"mode":"Nearest","modes":["Weakest","AirFirst"]}
A10: gun_turret | B10: gun_turret | C10: Strongest | D10: Nearest;Lead | E10: Assets/MachineBrigade/Resources/Data/balance.json: aiBehaviour.towers.gun_turret | F10: {"mode":"Strongest","modes":["Nearest","Lead"]}
A11: heavy_turret | B11: heavy_turret | C11: Strongest | D11: Lead | E11: Assets/MachineBrigade/Resources/Data/balance.json: aiBehaviour.towers.heavy_turret | F11: {"mode":"Strongest","modes":["Lead"]}
A12: laser_ad_station | B12: laser_ad_station | C12: ShieldKey | D12: NearestRound | E12: Assets/MachineBrigade/Resources/Data/balance.json: aiBehaviour.towers.laser_ad_station | F12: {"mode":"ShieldKey","modes":["NearestRound"]}
A13: manpads_tower | B13: manpads_tower | C13: AirFirst | D13: Nearest | E13: Assets/MachineBrigade/Resources/Data/balance.json: aiBehaviour.towers.manpads_tower | F13: {"mode":"AirFirst","modes":["Nearest"]}
A14: mg_bunker | B14: mg_bunker | C14: Nearest | D14: Weakest | E14: Assets/MachineBrigade/Resources/Data/balance.json: aiBehaviour.towers.mg_bunker | F14: {"mode":"Nearest","modes":["Weakest"]}
A15: missile_battery | B15: missile_battery | C15: BiggestAircraft | D15: AirFirst;MissilesFirst | E15: Assets/MachineBrigade/Resources/Data/balance.json: aiBehaviour.towers.missile_battery | F15: {"mode":"BiggestAircraft","modes":["AirFirst","MissilesFirst"]}
A16: one_shot_atgm_tower | B16: one_shot_atgm_tower | C16: Strongest | D16: Lead | E16: Assets/MachineBrigade/Resources/Data/balance.json: aiBehaviour.towers.one_shot_atgm_tower | F16: {"mode":"Strongest","modes":["Lead"]}
A17: recoilless_gun_tower | B17: recoilless_gun_tower | C17: Strongest | D17: Lead | E17: Assets/MachineBrigade/Resources/Data/balance.json: aiBehaviour.towers.recoilless_gun_tower | F17: {"mode":"Strongest","modes":["Lead"]}
A18: rocket_turret | B18: rocket_turret | C18: Cluster | D18: Nearest | E18: Assets/MachineBrigade/Resources/Data/balance.json: aiBehaviour.towers.rocket_turret | F18: {"mode":"Cluster","modes":["Nearest"]}
A19: shield_tower | B19: shield_tower | C19: None | E19: Assets/MachineBrigade/Resources/Data/balance.json: aiBehaviour.towers.shield_tower | F19: {"mode":"None","modes":[]}

Sheet AI_boss
A1: id | B1: boss | C1: hanh_vi | D1: nguon | E1: raw_json
A2: behemoth | B2: behemoth | C2: AntiBlob;FlankPunishment | D2: Assets/MachineBrigade/Resources/Data/balance.json: aiBehaviour.bosses.behemoth | E2: ["AntiBlob","FlankPunishment"]
A3: command_airship | B3: command_airship | C3: AntiAir;AntiBlob | D3: Assets/MachineBrigade/Resources/Data/balance.json: aiBehaviour.bosses.command_airship | E3: ["AntiAir","AntiBlob"]
A4: daedalus | B4: daedalus | C4: AntiBlob | D4: Assets/MachineBrigade/Resources/Data/balance.json: aiBehaviour.bosses.daedalus | E4: ["AntiBlob"]
A5: drone_mothership | B5: drone_mothership | C5: AntiBlob | D5: Assets/MachineBrigade/Resources/Data/balance.json: aiBehaviour.bosses.drone_mothership | E5: ["AntiBlob"]
A6: fortress_bastion | B6: fortress_bastion | C6: AreaDenial | D6: Assets/MachineBrigade/Resources/Data/balance.json: aiBehaviour.bosses.fortress_bastion | E6: ["AreaDenial"]
A7: leviathan | B7: leviathan | C7: AreaDenial;AntiAir | D7: Assets/MachineBrigade/Resources/Data/balance.json: aiBehaviour.bosses.leviathan | E7: ["AreaDenial","AntiAir"]
A8: mobile_fortress | B8: mobile_fortress | C8: AntiArtillery;AreaDenial | D8: Assets/MachineBrigade/Resources/Data/balance.json: aiBehaviour.bosses.mobile_fortress | E8: ["AntiArtillery","AreaDenial"]
A9: moloch | B9: moloch | C9: CoreProtection;FlankPunishment | D9: Assets/MachineBrigade/Resources/Data/balance.json: aiBehaviour.bosses.moloch | E9: ["CoreProtection","FlankPunishment"]
A10: nuke_train | B10: nuke_train | C10: AreaDenial | D10: Assets/MachineBrigade/Resources/Data/balance.json: aiBehaviour.bosses.nuke_train | E10: ["AreaDenial"]
A11: silver_bug | B11: silver_bug | C11: AntiBlob;CoreProtection | D11: Assets/MachineBrigade/Resources/Data/balance.json: aiBehaviour.bosses.silver_bug | E11: ["AntiBlob","CoreProtection"]
A12: typhon | B12: typhon | C12: AntiArtillery;AntiAir | D12: Assets/MachineBrigade/Resources/Data/balance.json: aiBehaviour.bosses.typhon | E12: ["AntiArtillery","AntiAir"]

Sheet AI_xung_dot
A1: id | B1: anh_xa | C1: tuong | D1: ho_so | E1: chien_thuat_cho_phep | F1: ho_so_dung_tuong | G1: co_khong_tuong | H1: ua_thich_tuong | I1: ua_thich_tuong_game | J1: dung_tuong | K1: dung_tuong_game | L1: yeu_cau | M1: yeu_cau_game | N1: vao_tran | O1: vao_tran_game | P1: trang_thai | Q1: nguon | R1: raw_json
A2: goal.Boss/aurel | B2: goal.Boss | C2: aurel | D2: =AI_ho_so_anh_xa!$D$2 | E2: =INDEX(AI_ho_so_che_do!$B$2:$B$21,MATCH($D$2,AI_ho_so_che_do!$A$2:$A$21,0))&"" | F2: =INDEX(AI_ho_so_che_do!$P$2:$P$21,MATCH($D$2,AI_ho_so_che_do!$A$2:$A$21,0))=TRUE | G2: =ISNUMBER(FIND(";noGeneralTactic;",";"&INDEX(AI_ho_so_che_do!$O$2:$O$21,MATCH($D$2,AI_ho_so_che_do!$A$2:$A$21,0))&";")) | H2: =IF(AI_tuong!$B$2&""<>"",AI_tuong!$B$2,IF(AI_tuong!$B$4&""<>"",AI_tuong!$B$4,"balanced")) | I2: all_out | J2: =OR($F$2,AND(AI_ho_so_anh_xa!$B$2="mode",OR(AI_ho_so_anh_xa!$C$2="Weekly",AI_ho_so_anh_xa!$C$2="Operation"))) | K2: FALSE | L2: =IF($J$2,$H$2,"balanced") | M2: balanced | N2: =IF(OR($E$2="",$G$2),"balanced",IF(OR($E$2="*",ISNUMBER(FIND(";"&$L$2&";",";"&$E$2&";"))),$L$2,IF(ISNUMBER(FIND(";"&"balanced"&";",";"&$E$2&";")),"balanced",LEFT($E$2,FIND(";",$E$2&";")-1)))) | O2: balanced | P2: =IF(OR($E$2="",$G$2),"KHONG_CHIEN_THUAT",IF(NOT($J$2),IF($H$2="balanced","GIU","CHE_DO_BO_QUA"),IF($N$2=$H$2,"GIU","HO_SO_GHI_DE"))) | Q2: Sim/AI/ConquestAi.P28.cs TickLayered + Sim/AI/Commander.cs AllowedTactic (goal.Boss, aurel)
A3: goal.Boss/brandt | B3: goal.Boss | C3: brandt | D3: =AI_ho_so_anh_xa!$D$2 | E3: =INDEX(AI_ho_so_che_do!$B$2:$B$21,MATCH($D$3,AI_ho_so_che_do!$A$2:$A$21,0))&"" | F3: =INDEX(AI_ho_so_che_do!$P$2:$P$21,MATCH($D$3,AI_ho_so_che_do!$A$2:$A$21,0))=TRUE | G3: =ISNUMBER(FIND(";noGeneralTactic;",";"&INDEX(AI_ho_so_che_do!$O$2:$O$21,MATCH($D$3,AI_ho_so_che_do!$A$2:$A$21,0))&";")) | H3: =IF(AI_tuong!$B$3&""<>"",AI_tuong!$B$3,IF(AI_tuong!$B$4&""<>"",AI_tuong!$B$4,"balanced")) | I3: depth | J3: =OR($F$3,AND(AI_ho_so_anh_xa!$B$2="mode",OR(AI_ho_so_anh_xa!$C$2="Weekly",AI_ho_so_anh_xa!$C$2="Operation"))) | K3: FALSE | L3: =IF($J$3,$H$3,"balanced") | M3: balanced | N3: =IF(OR($E$3="",$G$3),"balanced",IF(OR($E$3="*",ISNUMBER(FIND(";"&$L$3&";",";"&$E$3&";"))),$L$3,IF(ISNUMBER(FIND(";"&"balanced"&";",";"&$E$3&";")),"balanced",LEFT($E$3,FIND(";",$E$3&";")-1)))) | O3: balanced | P3: =IF(OR($E$3="",$G$3),"KHONG_CHIEN_THUAT",IF(NOT($J$3),IF($H$3="balanced","GIU","CHE_DO_BO_QUA"),IF($N$3=$H$3,"GIU","HO_SO_GHI_DE"))) | Q3: Sim/AI/ConquestAi.P28.cs TickLayered + Sim/AI/Commander.cs AllowedTactic (goal.Boss, brandt)
A4: goal.Boss/default | B4: goal.Boss | C4: default | D4: =AI_ho_so_anh_xa!$D$2 | E4: =INDEX(AI_ho_so_che_do!$B$2:$B$21,MATCH($D$4,AI_ho_so_che_do!$A$2:$A$21,0))&"" | F4: =INDEX(AI_ho_so_che_do!$P$2:$P$21,MATCH($D$4,AI_ho_so_che_do!$A$2:$A$21,0))=TRUE | G4: =ISNUMBER(FIND(";noGeneralTactic;",";"&INDEX(AI_ho_so_che_do!$O$2:$O$21,MATCH($D$4,AI_ho_so_che_do!$A$2:$A$21,0))&";")) | H4: =IF(AI_tuong!$B$4&""<>"",AI_tuong!$B$4,IF(AI_tuong!$B$4&""<>"",AI_tuong!$B$4,"balanced")) | I4: balanced | J4: =OR($F$4,AND(AI_ho_so_anh_xa!$B$2="mode",OR(AI_ho_so_anh_xa!$C$2="Weekly",AI_ho_so_anh_xa!$C$2="Operation"))) | K4: FALSE | L4: =IF($J$4,$H$4,"balanced") | M4: balanced | N4: =IF(OR($E$4="",$G$4),"balanced",IF(OR($E$4="*",ISNUMBER(FIND(";"&$L$4&";",";"&$E$4&";"))),$L$4,IF(ISNUMBER(FIND(";"&"balanced"&";",";"&$E$4&";")),"balanced",LEFT($E$4,FIND(";",$E$4&";")-1)))) | O4: balanced | P4: =IF(OR($E$4="",$G$4),"KHONG_CHIEN_THUAT",IF(NOT($J$4),IF($H$4="balanced","GIU","CHE_DO_BO_QUA"),IF($N$4=$H$4,"GIU","HO_SO_GHI_DE"))) | Q4: Sim/AI/ConquestAi.P28.cs TickLayered + Sim/AI/Commander.cs AllowedTactic (goal.Boss, default)
A5: goal.Boss/hung | B5: goal.Boss | C5: hung | D5: =AI_ho_so_anh_xa!$D$2 | E5: =INDEX(AI_ho_so_che_do!$B$2:$B$21,MATCH($D$5,AI_ho_so_che_do!$A$2:$A$21,0))&"" | F5: =INDEX(AI_ho_so_che_do!$P$2:$P$21,MATCH($D$5,AI_ho_so_che_do!$A$2:$A$21,0))=TRUE | G5: =ISNUMBER(FIND(";noGeneralTactic;",";"&INDEX(AI_ho_so_che_do!$O$2:$O$21,MATCH($D$5,AI_ho_so_che_do!$A$2:$A$21,0))&";")) | H5: =IF(AI_tuong!$B$5&""<>"",AI_tuong!$B$5,IF(AI_tuong!$B$4&""<>"",AI_tuong!$B$4,"balanced")) | I5: balanced | J5: =OR($F$5,AND(AI_ho_so_anh_xa!$B$2="mode",OR(AI_ho_so_anh_xa!$C$2="Weekly",AI_ho_so_anh_xa!$C$2="Operation"))) | K5: FALSE | L5: =IF($J$5,$H$5,"balanced") | M5: balanced | N5: =IF(OR($E$5="",$G$5),"balanced",IF(OR($E$5="*",ISNUMBER(FIND(";"&$L$5&";",";"&$E$5&";"))),$L$5,IF(ISNUMBER(FIND(";"&"balanced"&";",";"&$E$5&";")),"balanced",LEFT($E$5,FIND(";",$E$5&";")-1)))) | O5: balanced | P5: =IF(OR($E$5="",$G$5),"KHONG_CHIEN_THUAT",IF(NOT($J$5),IF($H$5="balanced","GIU","CHE_DO_BO_QUA"),IF($N$5=$H$5,"GIU","HO_SO_GHI_DE"))) | Q5: Sim/AI/ConquestAi.P28.cs TickLayered + Sim/AI/Commander.cs AllowedTactic (goal.Boss, hung)
A6: goal.Boss/kessler | B6: goal.Boss | C6: kessler | D6: =AI_ho_so_anh_xa!$D$2 | E6: =INDEX(AI_ho_so_che_do!$B$2:$B$21,MATCH($D$6,AI_ho_so_che_do!$A$2:$A$21,0))&"" | F6: =INDEX(AI_ho_so_che_do!$P$2:$P$21,MATCH($D$6,AI_ho_so_che_do!$A$2:$A$21,0))=TRUE | G6: =ISNUMBER(FIND(";noGeneralTactic;",";"&INDEX(AI_ho_so_che_do!$O$2:$O$21,MATCH($D$6,AI_ho_so_che_do!$A$2:$A$21,0))&";")) | H6: =IF(AI_tuong!$B$6&""<>"",AI_tuong!$B$6,IF(AI_tuong!$B$4&""<>"",AI_tuong!$B$4,"balanced")) | I6: attrition | J6: =OR($F$6,AND(AI_ho_so_anh_xa!$B$2="mode",OR(AI_ho_so_anh_xa!$C$2="Weekly",AI_ho_so_anh_xa!$C$2="Operation"))) | K6: FALSE | L6: =IF($J$6,$H$6,"balanced") | M6: balanced | N6: =IF(OR($E$6="",$G$6),"balanced",IF(OR($E$6="*",ISNUMBER(FIND(";"&$L$6&";",";"&$E$6&";"))),$L$6,IF(ISNUMBER(FIND(";"&"balanced"&";",";"&$E$6&";")),"balanced",LEFT($E$6,FIND(";",$E$6&";")-1)))) | O6: balanced | P6: =IF(OR($E$6="",$G$6),"KHONG_CHIEN_THUAT",IF(NOT($J$6),IF($H$6="balanced","GIU","CHE_DO_BO_QUA"),IF($N$6=$H$6,"GIU","HO_SO_GHI_DE"))) | Q6: Sim/AI/ConquestAi.P28.cs TickLayered + Sim/AI/Commander.cs AllowedTactic (goal.Boss, kessler)
A7: goal.Boss/orlov | B7: goal.Boss | C7: orlov | D7: =AI_ho_so_anh_xa!$D$2 | E7: =INDEX(AI_ho_so_che_do!$B$2:$B$21,MATCH($D$7,AI_ho_so_che_do!$A$2:$A$21,0))&"" | F7: =INDEX(AI_ho_so_che_do!$P$2:$P$21,MATCH($D$7,AI_ho_so_che_do!$A$2:$A$21,0))=TRUE | G7: =ISNUMBER(FIND(";noGeneralTactic;",";"&INDEX(AI_ho_so_che_do!$O$2:$O$21,MATCH($D$7,AI_ho_so_che_do!$A$2:$A$21,0))&";")) | H7: =IF(AI_tuong!$B$7&""<>"",AI_tuong!$B$7,IF(AI_tuong!$B$4&""<>"",AI_tuong!$B$4,"balanced")) | I7: firepower | J7: =OR($F$7,AND(AI_ho_so_anh_xa!$B$2="mode",OR(AI_ho_so_anh_xa!$C$2="Weekly",AI_ho_so_anh_xa!$C$2="Operation"))) | K7: FALSE | L7: =IF($J$7,$H$7,"balanced") | M7: balanced | N7: =IF(OR($E$7="",$G$7),"balanced",IF(OR($E$7="*",ISNUMBER(FIND(";"&$L$7&";",";"&$E$7&";"))),$L$7,IF(ISNUMBER(FIND(";"&"balanced"&";",";"&$E$7&";")),"balanced",LEFT($E$7,FIND(";",$E$7&";")-1)))) | O7: balanced | P7: =IF(OR($E$7="",$G$7),"KHONG_CHIEN_THUAT",IF(NOT($J$7),IF($H$7="balanced","GIU","CHE_DO_BO_QUA"),IF($N$7=$H$7,"GIU","HO_SO_GHI_DE"))) | Q7: Sim/AI/ConquestAi.P28.cs TickLayered + Sim/AI/Commander.cs AllowedTactic (goal.Boss, orlov)
A8: goal.Boss/quaden | B8: goal.Boss | C8: quaden | D8: =AI_ho_so_anh_xa!$D$2 | E8: =INDEX(AI_ho_so_che_do!$B$2:$B$21,MATCH($D$8,AI_ho_so_che_do!$A$2:$A$21,0))&"" | F8: =INDEX(AI_ho_so_che_do!$P$2:$P$21,MATCH($D$8,AI_ho_so_che_do!$A$2:$A$21,0))=TRUE | G8: =ISNUMBER(FIND(";noGeneralTactic;",";"&INDEX(AI_ho_so_che_do!$O$2:$O$21,MATCH($D$8,AI_ho_so_che_do!$A$2:$A$21,0))&";")) | H8: =IF(AI_tuong!$B$8&""<>"",AI_tuong!$B$8,IF(AI_tuong!$B$4&""<>"",AI_tuong!$B$4,"balanced")) | I8: balanced | J8: =OR($F$8,AND(AI_ho_so_anh_xa!$B$2="mode",OR(AI_ho_so_anh_xa!$C$2="Weekly",AI_ho_so_anh_xa!$C$2="Operation"))) | K8: FALSE | L8: =IF($J$8,$H$8,"balanced") | M8: balanced | N8: =IF(OR($E$8="",$G$8),"balanced",IF(OR($E$8="*",ISNUMBER(FIND(";"&$L$8&";",";"&$E$8&";"))),$L$8,IF(ISNUMBER(FIND(";"&"balanced"&";",";"&$E$8&";")),"balanced",LEFT($E$8,FIND(";",$E$8&";")-1)))) | O8: balanced | P8: =IF(OR($E$8="",$G$8),"KHONG_CHIEN_THUAT",IF(NOT($J$8),IF($H$8="balanced","GIU","CHE_DO_BO_QUA"),IF($N$8=$H$8,"GIU","HO_SO_GHI_DE"))) | Q8: Sim/AI/ConquestAi.P28.cs TickLayered + Sim/AI/Commander.cs AllowedTactic (goal.Boss, quaden)
A9: goal.Boss/sen | B9: goal.Boss | C9: sen | D9: =AI_ho_so_anh_xa!$D$2 | E9: =INDEX(AI_ho_so_che_do!$B$2:$B$21,MATCH($D$9,AI_ho_so_che_do!$A$2:$A$21,0))&"" | F9: =INDEX(AI_ho_so_che_do!$P$2:$P$21,MATCH($D$9,AI_ho_so_che_do!$A$2:$A$21,0))=TRUE | G9: =ISNUMBER(FIND(";noGeneralTactic;",";"&INDEX(AI_ho_so_che_do!$O$2:$O$21,MATCH($D$9,AI_ho_so_che_do!$A$2:$A$21,0))&";")) | H9: =IF(AI_tuong!$B$9&""<>"",AI_tuong!$B$9,IF(AI_tuong!$B$4&""<>"",AI_tuong!$B$4,"balanced")) | I9: balanced | J9: =OR($F$9,AND(AI_ho_so_anh_xa!$B$2="mode",OR(AI_ho_so_anh_xa!$C$2="Weekly",AI_ho_so_anh_xa!$C$2="Operation"))) | K9: FALSE | L9: =IF($J$9,$H$9,"balanced") | M9: balanced | N9: =IF(OR($E$9="",$G$9),"balanced",IF(OR($E$9="*",ISNUMBER(FIND(";"&$L$9&";",";"&$E$9&";"))),$L$9,IF(ISNUMBER(FIND(";"&"balanced"&";",";"&$E$9&";")),"balanced",LEFT($E$9,FIND(";",$E$9&";")-1)))) | O9: balanced | P9: =IF(OR($E$9="",$G$9),"KHONG_CHIEN_THUAT",IF(NOT($J$9),IF($H$9="balanced","GIU","CHE_DO_BO_QUA"),IF($N$9=$H$9,"GIU","HO_SO_GHI_DE"))) | Q9: Sim/AI/ConquestAi.P28.cs TickLayered + Sim/AI/Commander.cs AllowedTactic (goal.Boss, sen)
A10: goal.Boss/thorne | B10: goal.Boss | C10: thorne | D10: =AI_ho_so_anh_xa!$D$2 | E10: =INDEX(AI_ho_so_che_do!$B$2:$B$21,MATCH($D$10,AI_ho_so_che_do!$A$2:$A$21,0))&"" | F10: =INDEX(AI_ho_so_che_do!$P$2:$P$21,MATCH($D$10,AI_ho_so_che_do!$A$2:$A$21,0))=TRUE | G10: =ISNUMBER(FIND(";noGeneralTactic;",";"&INDEX(AI_ho_so_che_do!$O$2:$O$21,MATCH($D$10,AI_ho_so_che_do!$A$2:$A$21,0))&";")) | H10: =IF(AI_tuong!$B$10&""<>"",AI_tuong!$B$10,IF(AI_tuong!$B$4&""<>"",AI_tuong!$B$4,"balanced")) | I10: balanced | J10: =OR($F$10,AND(AI_ho_so_anh_xa!$B$2="mode",OR(AI_ho_so_anh_xa!$C$2="Weekly",AI_ho_so_anh_xa!$C$2="Operation"))) | K10: FALSE | L10: =IF($J$10,$H$10,"balanced") | M10: balanced | N10: =IF(OR($E$10="",$G$10),"balanced",IF(OR($E$10="*",ISNUMBER(FIND(";"&$L$10&";",";"&$E$10&";"))),$L$10,IF(ISNUMBER(FIND(";"&"balanced"&";",";"&$E$10&";")),"balanced",LEFT($E$10,FIND(";",$E$10&";")-1)))) | O10: balanced | P10: =IF(OR($E$10="",$G$10),"KHONG_CHIEN_THUAT",IF(NOT($J$10),IF($H$10="balanced","GIU","CHE_DO_BO_QUA"),IF($N$10=$H$10,"GIU","HO_SO_GHI_DE"))) | Q10: Sim/AI/ConquestAi.P28.cs TickLayered + Sim/AI/Commander.cs AllowedTactic (goal.Boss, thorne)
A11: goal.Boss/varga | B11: goal.Boss | C11: varga | D11: =AI_ho_so_anh_xa!$D$2 | E11: =INDEX(AI_ho_so_che_do!$B$2:$B$21,MATCH($D$11,AI_ho_so_che_do!$A$2:$A$21,0))&"" | F11: =INDEX(AI_ho_so_che_do!$P$2:$P$21,MATCH($D$11,AI_ho_so_che_do!$A$2:$A$21,0))=TRUE | G11: =ISNUMBER(FIND(";noGeneralTactic;",";"&INDEX(AI_ho_so_che_do!$O$2:$O$21,MATCH($D$11,AI_ho_so_che_do!$A$2:$A$21,0))&";")) | H11: =IF(AI_tuong!$B$11&""<>"",AI_tuong!$B$11,IF(AI_tuong!$B$4&""<>"",AI_tuong!$B$4,"balanced")) | I11: breakthrough | J11: =OR($F$11,AND(AI_ho_so_anh_xa!$B$2="mode",OR(AI_ho_so_anh_xa!$C$2="Weekly",AI_ho_so_anh_xa!$C$2="Operation"))) | K11: FALSE | L11: =IF($J$11,$H$11,"balanced") | M11: balanced | N11: =IF(OR($E$11="",$G$11),"balanced",IF(OR($E$11="*",ISNUMBER(FIND(";"&$L$11&";",";"&$E$11&";"))),$L$11,IF(ISNUMBER(FIND(";"&"balanced"&";",";"&$E$11&";")),"balanced",LEFT($E$11,FIND(";",$E$11&";")-1)))) | O11: balanced | P11: =IF(OR($E$11="",$G$11),"KHONG_CHIEN_THUAT",IF(NOT($J$11),IF($H$11="balanced","GIU","CHE_DO_BO_QUA"),IF($N$11=$H$11,"GIU","HO_SO_GHI_DE"))) | Q11: Sim/AI/ConquestAi.P28.cs TickLayered + Sim/AI/Commander.cs AllowedTactic (goal.Boss, varga)
A12: goal.Boss/venn | B12: goal.Boss | C12: venn | D12: =AI_ho_so_anh_xa!$D$2 | E12: =INDEX(AI_ho_so_che_do!$B$2:$B$21,MATCH($D$12,AI_ho_so_che_do!$A$2:$A$21,0))&"" | F12: =INDEX(AI_ho_so_che_do!$P$2:$P$21,MATCH($D$12,AI_ho_so_che_do!$A$2:$A$21,0))=TRUE | G12: =ISNUMBER(FIND(";noGeneralTactic;",";"&INDEX(AI_ho_so_che_do!$O$2:$O$21,MATCH($D$12,AI_ho_so_che_do!$A$2:$A$21,0))&";")) | H12: =IF(AI_tuong!$B$12&""<>"",AI_tuong!$B$12,IF(AI_tuong!$B$4&""<>"",AI_tuong!$B$4,"balanced")) | I12: dispersal | J12: =OR($F$12,AND(AI_ho_so_anh_xa!$B$2="mode",OR(AI_ho_so_anh_xa!$C$2="Weekly",AI_ho_so_anh_xa!$C$2="Operation"))) | K12: FALSE | L12: =IF($J$12,$H$12,"balanced") | M12: balanced | N12: =IF(OR($E$12="",$G$12),"balanced",IF(OR($E$12="*",ISNUMBER(FIND(";"&$L$12&";",";"&$E$12&";"))),$L$12,IF(ISNUMBER(FIND(";"&"balanced"&";",";"&$E$12&";")),"balanced",LEFT($E$12,FIND(";",$E$12&";")-1)))) | O12: balanced | P12: =IF(OR($E$12="",$G$12),"KHONG_CHIEN_THUAT",IF(NOT($J$12),IF($H$12="balanced","GIU","CHE_DO_BO_QUA"),IF($N$12=$H$12,"GIU","HO_SO_GHI_DE"))) | Q12: Sim/AI/ConquestAi.P28.cs TickLayered + Sim/AI/Commander.cs AllowedTactic (goal.Boss, venn)
A13: goal.Boss/wolff | B13: goal.Boss | C13: wolff | D13: =AI_ho_so_anh_xa!$D$2 | E13: =INDEX(AI_ho_so_che_do!$B$2:$B$21,MATCH($D$13,AI_ho_so_che_do!$A$2:$A$21,0))&"" | F13: =INDEX(AI_ho_so_che_do!$P$2:$P$21,MATCH($D$13,AI_ho_so_che_do!$A$2:$A$21,0))=TRUE | G13: =ISNUMBER(FIND(";noGeneralTactic;",";"&INDEX(AI_ho_so_che_do!$O$2:$O$21,MATCH($D$13,AI_ho_so_che_do!$A$2:$A$21,0))&";")) | H13: =IF(AI_tuong!$B$13&""<>"",AI_tuong!$B$13,IF(AI_tuong!$B$4&""<>"",AI_tuong!$B$4,"balanced")) | I13: air_superiority | J13: =OR($F$13,AND(AI_ho_so_anh_xa!$B$2="mode",OR(AI_ho_so_anh_xa!$C$2="Weekly",AI_ho_so_anh_xa!$C$2="Operation"))) | K13: FALSE | L13: =IF($J$13,$H$13,"balanced") | M13: balanced | N13: =IF(OR($E$13="",$G$13),"balanced",IF(OR($E$13="*",ISNUMBER(FIND(";"&$L$13&";",";"&$E$13&";"))),$L$13,IF(ISNUMBER(FIND(";"&"balanced"&";",";"&$E$13&";")),"balanced",LEFT($E$13,FIND(";",$E$13&";")-1)))) | O13: balanced | P13: =IF(OR($E$13="",$G$13),"KHONG_CHIEN_THUAT",IF(NOT($J$13),IF($H$13="balanced","GIU","CHE_DO_BO_QUA"),IF($N$13=$H$13,"GIU","HO_SO_GHI_DE"))) | Q13: Sim/AI/ConquestAi.P28.cs TickLayered + Sim/AI/Commander.cs AllowedTactic (goal.Boss, wolff)
A14: goal.Capture/aurel | B14: goal.Capture | C14: aurel | D14: =AI_ho_so_anh_xa!$D$3 | E14: =INDEX(AI_ho_so_che_do!$B$2:$B$21,MATCH($D$14,AI_ho_so_che_do!$A$2:$A$21,0))&"" | F14: =INDEX(AI_ho_so_che_do!$P$2:$P$21,MATCH($D$14,AI_ho_so_che_do!$A$2:$A$21,0))=TRUE | G14: =ISNUMBER(FIND(";noGeneralTactic;",";"&INDEX(AI_ho_so_che_do!$O$2:$O$21,MATCH($D$14,AI_ho_so_che_do!$A$2:$A$21,0))&";")) | H14: =IF(AI_tuong!$B$2&""<>"",AI_tuong!$B$2,IF(AI_tuong!$B$4&""<>"",AI_tuong!$B$4,"balanced")) | I14: all_out | J14: =OR($F$14,AND(AI_ho_so_anh_xa!$B$3="mode",OR(AI_ho_so_anh_xa!$C$3="Weekly",AI_ho_so_anh_xa!$C$3="Operation"))) | K14: TRUE | L14: =IF($J$14,$H$14,"balanced") | M14: all_out | N14: =IF(OR($E$14="",$G$14),"balanced",IF(OR($E$14="*",ISNUMBER(FIND(";"&$L$14&";",";"&$E$14&";"))),$L$14,IF(ISNUMBER(FIND(";"&"balanced"&";",";"&$E$14&";")),"balanced",LEFT($E$14,FIND(";",$E$14&";")-1)))) | O14: all_out | P14: =IF(OR($E$14="",$G$14),"KHONG_CHIEN_THUAT",IF(NOT($J$14),IF($H$14="balanced","GIU","CHE_DO_BO_QUA"),IF($N$14=$H$14,"GIU","HO_SO_GHI_DE"))) | Q14: Sim/AI/ConquestAi.P28.cs TickLayered + Sim/AI/Commander.cs AllowedTactic (goal.Capture, aurel)
A15: goal.Capture/brandt | B15: goal.Capture | C15: brandt | D15: =AI_ho_so_anh_xa!$D$3 | E15: =INDEX(AI_ho_so_che_do!$B$2:$B$21,MATCH($D$15,AI_ho_so_che_do!$A$2:$A$21,0))&"" | F15: =INDEX(AI_ho_so_che_do!$P$2:$P$21,MATCH($D$15,AI_ho_so_che_do!$A$2:$A$21,0))=TRUE | G15: =ISNUMBER(FIND(";noGeneralTactic;",";"&INDEX(AI_ho_so_che_do!$O$2:$O$21,MATCH($D$15,AI_ho_so_che_do!$A$2:$A$21,0))&";")) | H15: =IF(AI_tuong!$B$3&""<>"",AI_tuong!$B$3,IF(AI_tuong!$B$4&""<>"",AI_tuong!$B$4,"balanced")) | I15: depth | J15: =OR($F$15,AND(AI_ho_so_anh_xa!$B$3="mode",OR(AI_ho_so_anh_xa!$C$3="Weekly",AI_ho_so_anh_xa!$C$3="Operation"))) | K15: TRUE | L15: =IF($J$15,$H$15,"balanced") | M15: depth | N15: =IF(OR($E$15="",$G$15),"balanced",IF(OR($E$15="*",ISNUMBER(FIND(";"&$L$15&";",";"&$E$15&";"))),$L$15,IF(ISNUMBER(FIND(";"&"balanced"&";",";"&$E$15&";")),"balanced",LEFT($E$15,FIND(";",$E$15&";")-1)))) | O15: depth | P15: =IF(OR($E$15="",$G$15),"KHONG_CHIEN_THUAT",IF(NOT($J$15),IF($H$15="balanced","GIU","CHE_DO_BO_QUA"),IF($N$15=$H$15,"GIU","HO_SO_GHI_DE"))) | Q15: Sim/AI/ConquestAi.P28.cs TickLayered + Sim/AI/Commander.cs AllowedTactic (goal.Capture, brandt)
A16: goal.Capture/default | B16: goal.Capture | C16: default | D16: =AI_ho_so_anh_xa!$D$3 | E16: =INDEX(AI_ho_so_che_do!$B$2:$B$21,MATCH($D$16,AI_ho_so_che_do!$A$2:$A$21,0))&"" | F16: =INDEX(AI_ho_so_che_do!$P$2:$P$21,MATCH($D$16,AI_ho_so_che_do!$A$2:$A$21,0))=TRUE | G16: =ISNUMBER(FIND(";noGeneralTactic;",";"&INDEX(AI_ho_so_che_do!$O$2:$O$21,MATCH($D$16,AI_ho_so_che_do!$A$2:$A$21,0))&";")) | H16: =IF(AI_tuong!$B$4&""<>"",AI_tuong!$B$4,IF(AI_tuong!$B$4&""<>"",AI_tuong!$B$4,"balanced")) | I16: balanced | J16: =OR($F$16,AND(AI_ho_so_anh_xa!$B$3="mode",OR(AI_ho_so_anh_xa!$C$3="Weekly",AI_ho_so_anh_xa!$C$3="Operation"))) | K16: TRUE | L16: =IF($J$16,$H$16,"balanced") | M16: balanced | N16: =IF(OR($E$16="",$G$16),"balanced",IF(OR($E$16="*",ISNUMBER(FIND(";"&$L$16&";",";"&$E$16&";"))),$L$16,IF(ISNUMBER(FIND(";"&"balanced"&";",";"&$E$16&";")),"balanced",LEFT($E$16,FIND(";",$E$16&";")-1)))) | O16: balanced | P16: =IF(OR($E$16="",$G$16),"KHONG_CHIEN_THUAT",IF(NOT($J$16),IF($H$16="balanced","GIU","CHE_DO_BO_QUA"),IF($N$16=$H$16,"GIU","HO_SO_GHI_DE"))) | Q16: Sim/AI/ConquestAi.P28.cs TickLayered + Sim/AI/Commander.cs AllowedTactic (goal.Capture, default)
A17: goal.Capture/hung | B17: goal.Capture | C17: hung | D17: =AI_ho_so_anh_xa!$D$3 | E17: =INDEX(AI_ho_so_che_do!$B$2:$B$21,MATCH($D$17,AI_ho_so_che_do!$A$2:$A$21,0))&"" | F17: =INDEX(AI_ho_so_che_do!$P$2:$P$21,MATCH($D$17,AI_ho_so_che_do!$A$2:$A$21,0))=TRUE | G17: =ISNUMBER(FIND(";noGeneralTactic;",";"&INDEX(AI_ho_so_che_do!$O$2:$O$21,MATCH($D$17,AI_ho_so_che_do!$A$2:$A$21,0))&";")) | H17: =IF(AI_tuong!$B$5&""<>"",AI_tuong!$B$5,IF(AI_tuong!$B$4&""<>"",AI_tuong!$B$4,"balanced")) | I17: balanced | J17: =OR($F$17,AND(AI_ho_so_anh_xa!$B$3="mode",OR(AI_ho_so_anh_xa!$C$3="Weekly",AI_ho_so_anh_xa!$C$3="Operation"))) | K17: TRUE | L17: =IF($J$17,$H$17,"balanced") | M17: balanced | N17: =IF(OR($E$17="",$G$17),"balanced",IF(OR($E$17="*",ISNUMBER(FIND(";"&$L$17&";",";"&$E$17&";"))),$L$17,IF(ISNUMBER(FIND(";"&"balanced"&";",";"&$E$17&";")),"balanced",LEFT($E$17,FIND(";",$E$17&";")-1)))) | O17: balanced | P17: =IF(OR($E$17="",$G$17),"KHONG_CHIEN_THUAT",IF(NOT($J$17),IF($H$17="balanced","GIU","CHE_DO_BO_QUA"),IF($N$17=$H$17,"GIU","HO_SO_GHI_DE"))) | Q17: Sim/AI/ConquestAi.P28.cs TickLayered + Sim/AI/Commander.cs AllowedTactic (goal.Capture, hung)
A18: goal.Capture/kessler | B18: goal.Capture | C18: kessler | D18: =AI_ho_so_anh_xa!$D$3 | E18: =INDEX(AI_ho_so_che_do!$B$2:$B$21,MATCH($D$18,AI_ho_so_che_do!$A$2:$A$21,0))&"" | F18: =INDEX(AI_ho_so_che_do!$P$2:$P$21,MATCH($D$18,AI_ho_so_che_do!$A$2:$A$21,0))=TRUE | G18: =ISNUMBER(FIND(";noGeneralTactic;",";"&INDEX(AI_ho_so_che_do!$O$2:$O$21,MATCH($D$18,AI_ho_so_che_do!$A$2:$A$21,0))&";")) | H18: =IF(AI_tuong!$B$6&""<>"",AI_tuong!$B$6,IF(AI_tuong!$B$4&""<>"",AI_tuong!$B$4,"balanced")) | I18: attrition | J18: =OR($F$18,AND(AI_ho_so_anh_xa!$B$3="mode",OR(AI_ho_so_anh_xa!$C$3="Weekly",AI_ho_so_anh_xa!$C$3="Operation"))) | K18: TRUE | L18: =IF($J$18,$H$18,"balanced") | M18: attrition | N18: =IF(OR($E$18="",$G$18),"balanced",IF(OR($E$18="*",ISNUMBER(FIND(";"&$L$18&";",";"&$E$18&";"))),$L$18,IF(ISNUMBER(FIND(";"&"balanced"&";",";"&$E$18&";")),"balanced",LEFT($E$18,FIND(";",$E$18&";")-1)))) | O18: attrition | P18: =IF(OR($E$18="",$G$18),"KHONG_CHIEN_THUAT",IF(NOT($J$18),IF($H$18="balanced","GIU","CHE_DO_BO_QUA"),IF($N$18=$H$18,"GIU","HO_SO_GHI_DE"))) | Q18: Sim/AI/ConquestAi.P28.cs TickLayered + Sim/AI/Commander.cs AllowedTactic (goal.Capture, kessler)
A19: goal.Capture/orlov | B19: goal.Capture | C19: orlov | D19: =AI_ho_so_anh_xa!$D$3 | E19: =INDEX(AI_ho_so_che_do!$B$2:$B$21,MATCH($D$19,AI_ho_so_che_do!$A$2:$A$21,0))&"" | F19: =INDEX(AI_ho_so_che_do!$P$2:$P$21,MATCH($D$19,AI_ho_so_che_do!$A$2:$A$21,0))=TRUE | G19: =ISNUMBER(FIND(";noGeneralTactic;",";"&INDEX(AI_ho_so_che_do!$O$2:$O$21,MATCH($D$19,AI_ho_so_che_do!$A$2:$A$21,0))&";")) | H19: =IF(AI_tuong!$B$7&""<>"",AI_tuong!$B$7,IF(AI_tuong!$B$4&""<>"",AI_tuong!$B$4,"balanced")) | I19: firepower | J19: =OR($F$19,AND(AI_ho_so_anh_xa!$B$3="mode",OR(AI_ho_so_anh_xa!$C$3="Weekly",AI_ho_so_anh_xa!$C$3="Operation"))) | K19: TRUE | L19: =IF($J$19,$H$19,"balanced") | M19: firepower | N19: =IF(OR($E$19="",$G$19),"balanced",IF(OR($E$19="*",ISNUMBER(FIND(";"&$L$19&";",";"&$E$19&";"))),$L$19,IF(ISNUMBER(FIND(";"&"balanced"&";",";"&$E$19&";")),"balanced",LEFT($E$19,FIND(";",$E$19&";")-1)))) | O19: firepower | P19: =IF(OR($E$19="",$G$19),"KHONG_CHIEN_THUAT",IF(NOT($J$19),IF($H$19="balanced","GIU","CHE_DO_BO_QUA"),IF($N$19=$H$19,"GIU","HO_SO_GHI_DE"))) | Q19: Sim/AI/ConquestAi.P28.cs TickLayered + Sim/AI/Commander.cs AllowedTactic (goal.Capture, orlov)
A20: goal.Capture/quaden | B20: goal.Capture | C20: quaden | D20: =AI_ho_so_anh_xa!$D$3 | E20: =INDEX(AI_ho_so_che_do!$B$2:$B$21,MATCH($D$20,AI_ho_so_che_do!$A$2:$A$21,0))&"" | F20: =INDEX(AI_ho_so_che_do!$P$2:$P$21,MATCH($D$20,AI_ho_so_che_do!$A$2:$A$21,0))=TRUE | G20: =ISNUMBER(FIND(";noGeneralTactic;",";"&INDEX(AI_ho_so_che_do!$O$2:$O$21,MATCH($D$20,AI_ho_so_che_do!$A$2:$A$21,0))&";")) | H20: =IF(AI_tuong!$B$8&""<>"",AI_tuong!$B$8,IF(AI_tuong!$B$4&""<>"",AI_tuong!$B$4,"balanced")) | I20: balanced | J20: =OR($F$20,AND(AI_ho_so_anh_xa!$B$3="mode",OR(AI_ho_so_anh_xa!$C$3="Weekly",AI_ho_so_anh_xa!$C$3="Operation"))) | K20: TRUE | L20: =IF($J$20,$H$20,"balanced") | M20: balanced | N20: =IF(OR($E$20="",$G$20),"balanced",IF(OR($E$20="*",ISNUMBER(FIND(";"&$L$20&";",";"&$E$20&";"))),$L$20,IF(ISNUMBER(FIND(";"&"balanced"&";",";"&$E$20&";")),"balanced",LEFT($E$20,FIND(";",$E$20&";")-1)))) | O20: balanced | P20: =IF(OR($E$20="",$G$20),"KHONG_CHIEN_THUAT",IF(NOT($J$20),IF($H$20="balanced","GIU","CHE_DO_BO_QUA"),IF($N$20=$H$20,"GIU","HO_SO_GHI_DE"))) | Q20: Sim/AI/ConquestAi.P28.cs TickLayered + Sim/AI/Commander.cs AllowedTactic (goal.Capture, quaden)
A21: goal.Capture/sen | B21: goal.Capture | C21: sen | D21: =AI_ho_so_anh_xa!$D$3 | E21: =INDEX(AI_ho_so_che_do!$B$2:$B$21,MATCH($D$21,AI_ho_so_che_do!$A$2:$A$21,0))&"" | F21: =INDEX(AI_ho_so_che_do!$P$2:$P$21,MATCH($D$21,AI_ho_so_che_do!$A$2:$A$21,0))=TRUE | G21: =ISNUMBER(FIND(";noGeneralTactic;",";"&INDEX(AI_ho_so_che_do!$O$2:$O$21,MATCH($D$21,AI_ho_so_che_do!$A$2:$A$21,0))&";")) | H21: =IF(AI_tuong!$B$9&""<>"",AI_tuong!$B$9,IF(AI_tuong!$B$4&""<>"",AI_tuong!$B$4,"balanced")) | I21: balanced | J21: =OR($F$21,AND(AI_ho_so_anh_xa!$B$3="mode",OR(AI_ho_so_anh_xa!$C$3="Weekly",AI_ho_so_anh_xa!$C$3="Operation"))) | K21: TRUE | L21: =IF($J$21,$H$21,"balanced") | M21: balanced | N21: =IF(OR($E$21="",$G$21),"balanced",IF(OR($E$21="*",ISNUMBER(FIND(";"&$L$21&";",";"&$E$21&";"))),$L$21,IF(ISNUMBER(FIND(";"&"balanced"&";",";"&$E$21&";")),"balanced",LEFT($E$21,FIND(";",$E$21&";")-1)))) | O21: balanced | P21: =IF(OR($E$21="",$G$21),"KHONG_CHIEN_THUAT",IF(NOT($J$21),IF($H$21="balanced","GIU","CHE_DO_BO_QUA"),IF($N$21=$H$21,"GIU","HO_SO_GHI_DE"))) | Q21: Sim/AI/ConquestAi.P28.cs TickLayered + Sim/AI/Commander.cs AllowedTactic (goal.Capture, sen)
A22: goal.Capture/thorne | B22: goal.Capture | C22: thorne | D22: =AI_ho_so_anh_xa!$D$3 | E22: =INDEX(AI_ho_so_che_do!$B$2:$B$21,MATCH($D$22,AI_ho_so_che_do!$A$2:$A$21,0))&"" | F22: =INDEX(AI_ho_so_che_do!$P$2:$P$21,MATCH($D$22,AI_ho_so_che_do!$A$2:$A$21,0))=TRUE | G22: =ISNUMBER(FIND(";noGeneralTactic;",";"&INDEX(AI_ho_so_che_do!$O$2:$O$21,MATCH($D$22,AI_ho_so_che_do!$A$2:$A$21,0))&";")) | H22: =IF(AI_tuong!$B$10&""<>"",AI_tuong!$B$10,IF(AI_tuong!$B$4&""<>"",AI_tuong!$B$4,"balanced")) | I22: balanced | J22: =OR($F$22,AND(AI_ho_so_anh_xa!$B$3="mode",OR(AI_ho_so_anh_xa!$C$3="Weekly",AI_ho_so_anh_xa!$C$3="Operation"))) | K22: TRUE | L22: =IF($J$22,$H$22,"balanced") | M22: balanced | N22: =IF(OR($E$22="",$G$22),"balanced",IF(OR($E$22="*",ISNUMBER(FIND(";"&$L$22&";",";"&$E$22&";"))),$L$22,IF(ISNUMBER(FIND(";"&"balanced"&";",";"&$E$22&";")),"balanced",LEFT($E$22,FIND(";",$E$22&";")-1)))) | O22: balanced | P22: =IF(OR($E$22="",$G$22),"KHONG_CHIEN_THUAT",IF(NOT($J$22),IF($H$22="balanced","GIU","CHE_DO_BO_QUA"),IF($N$22=$H$22,"GIU","HO_SO_GHI_DE"))) | Q22: Sim/AI/ConquestAi.P28.cs TickLayered + Sim/AI/Commander.cs AllowedTactic (goal.Capture, thorne)
A23: goal.Capture/varga | B23: goal.Capture | C23: varga | D23: =AI_ho_so_anh_xa!$D$3 | E23: =INDEX(AI_ho_so_che_do!$B$2:$B$21,MATCH($D$23,AI_ho_so_che_do!$A$2:$A$21,0))&"" | F23: =INDEX(AI_ho_so_che_do!$P$2:$P$21,MATCH($D$23,AI_ho_so_che_do!$A$2:$A$21,0))=TRUE | G23: =ISNUMBER(FIND(";noGeneralTactic;",";"&INDEX(AI_ho_so_che_do!$O$2:$O$21,MATCH($D$23,AI_ho_so_che_do!$A$2:$A$21,0))&";")) | H23: =IF(AI_tuong!$B$11&""<>"",AI_tuong!$B$11,IF(AI_tuong!$B$4&""<>"",AI_tuong!$B$4,"balanced")) | I23: breakthrough | J23: =OR($F$23,AND(AI_ho_so_anh_xa!$B$3="mode",OR(AI_ho_so_anh_xa!$C$3="Weekly",AI_ho_so_anh_xa!$C$3="Operation"))) | K23: TRUE | L23: =IF($J$23,$H$23,"balanced") | M23: breakthrough | N23: =IF(OR($E$23="",$G$23),"balanced",IF(OR($E$23="*",ISNUMBER(FIND(";"&$L$23&";",";"&$E$23&";"))),$L$23,IF(ISNUMBER(FIND(";"&"balanced"&";",";"&$E$23&";")),"balanced",LEFT($E$23,FIND(";",$E$23&";")-1)))) | O23: breakthrough | P23: =IF(OR($E$23="",$G$23),"KHONG_CHIEN_THUAT",IF(NOT($J$23),IF($H$23="balanced","GIU","CHE_DO_BO_QUA"),IF($N$23=$H$23,"GIU","HO_SO_GHI_DE"))) | Q23: Sim/AI/ConquestAi.P28.cs TickLayered + Sim/AI/Commander.cs AllowedTactic (goal.Capture, varga)
A24: goal.Capture/venn | B24: goal.Capture | C24: venn | D24: =AI_ho_so_anh_xa!$D$3 | E24: =INDEX(AI_ho_so_che_do!$B$2:$B$21,MATCH($D$24,AI_ho_so_che_do!$A$2:$A$21,0))&"" | F24: =INDEX(AI_ho_so_che_do!$P$2:$P$21,MATCH($D$24,AI_ho_so_che_do!$A$2:$A$21,0))=TRUE | G24: =ISNUMBER(FIND(";noGeneralTactic;",";"&INDEX(AI_ho_so_che_do!$O$2:$O$21,MATCH($D$24,AI_ho_so_che_do!$A$2:$A$21,0))&";")) | H24: =IF(AI_tuong!$B$12&""<>"",AI_tuong!$B$12,IF(AI_tuong!$B$4&""<>"",AI_tuong!$B$4,"balanced")) | I24: dispersal | J24: =OR($F$24,AND(AI_ho_so_anh_xa!$B$3="mode",OR(AI_ho_so_anh_xa!$C$3="Weekly",AI_ho_so_anh_xa!$C$3="Operation"))) | K24: TRUE | L24: =IF($J$24,$H$24,"balanced") | M24: dispersal | N24: =IF(OR($E$24="",$G$24),"balanced",IF(OR($E$24="*",ISNUMBER(FIND(";"&$L$24&";",";"&$E$24&";"))),$L$24,IF(ISNUMBER(FIND(";"&"balanced"&";",";"&$E$24&";")),"balanced",LEFT($E$24,FIND(";",$E$24&";")-1)))) | O24: dispersal | P24: =IF(OR($E$24="",$G$24),"KHONG_CHIEN_THUAT",IF(NOT($J$24),IF($H$24="balanced","GIU","CHE_DO_BO_QUA"),IF($N$24=$H$24,"GIU","HO_SO_GHI_DE"))) | Q24: Sim/AI/ConquestAi.P28.cs TickLayered + Sim/AI/Commander.cs AllowedTactic (goal.Capture, venn)
A25: goal.Capture/wolff | B25: goal.Capture | C25: wolff | D25: =AI_ho_so_anh_xa!$D$3 | E25: =INDEX(AI_ho_so_che_do!$B$2:$B$21,MATCH($D$25,AI_ho_so_che_do!$A$2:$A$21,0))&"" | F25: =INDEX(AI_ho_so_che_do!$P$2:$P$21,MATCH($D$25,AI_ho_so_che_do!$A$2:$A$21,0))=TRUE | G25: =ISNUMBER(FIND(";noGeneralTactic;",";"&INDEX(AI_ho_so_che_do!$O$2:$O$21,MATCH($D$25,AI_ho_so_che_do!$A$2:$A$21,0))&";")) | H25: =IF(AI_tuong!$B$13&""<>"",AI_tuong!$B$13,IF(AI_tuong!$B$4&""<>"",AI_tuong!$B$4,"balanced")) | I25: air_superiority | J25: =OR($F$25,AND(AI_ho_so_anh_xa!$B$3="mode",OR(AI_ho_so_anh_xa!$C$3="Weekly",AI_ho_so_anh_xa!$C$3="Operation"))) | K25: TRUE | L25: =IF($J$25,$H$25,"balanced") | M25: air_superiority | N25: =IF(OR($E$25="",$G$25),"balanced",IF(OR($E$25="*",ISNUMBER(FIND(";"&$L$25&";",";"&$E$25&";"))),$L$25,IF(ISNUMBER(FIND(";"&"balanced"&";",";"&$E$25&";")),"balanced",LEFT($E$25,FIND(";",$E$25&";")-1)))) | O25: air_superiority | P25: =IF(OR($E$25="",$G$25),"KHONG_CHIEN_THUAT",IF(NOT($J$25),IF($H$25="balanced","GIU","CHE_DO_BO_QUA"),IF($N$25=$H$25,"GIU","HO_SO_GHI_DE"))) | Q25: Sim/AI/ConquestAi.P28.cs TickLayered + Sim/AI/Commander.cs AllowedTactic (goal.Capture, wolff)
A26: goal.Destroy/aurel | B26: goal.Destroy | C26: aurel | D26: =AI_ho_so_anh_xa!$D$4 | E26: =INDEX(AI_ho_so_che_do!$B$2:$B$21,MATCH($D$26,AI_ho_so_che_do!$A$2:$A$21,0))&"" | F26: =INDEX(AI_ho_so_che_do!$P$2:$P$21,MATCH($D$26,AI_ho_so_che_do!$A$2:$A$21,0))=TRUE | G26: =ISNUMBER(FIND(";noGeneralTactic;",";"&INDEX(AI_ho_so_che_do!$O$2:$O$21,MATCH($D$26,AI_ho_so_che_do!$A$2:$A$21,0))&";")) | H26: =IF(AI_tuong!$B$2&""<>"",AI_tuong!$B$2,IF(AI_tuong!$B$4&""<>"",AI_tuong!$B$4,"balanced")) | I26: all_out | J26: =OR($F$26,AND(AI_ho_so_anh_xa!$B$4="mode",OR(AI_ho_so_anh_xa!$C$4="Weekly",AI_ho_so_anh_xa!$C$4="Operation"))) | K26: TRUE | L26: =IF($J$26,$H$26,"balanced") | M26: all_out | N26: =IF(OR($E$26="",$G$26),"balanced",IF(OR($E$26="*",ISNUMBER(FIND(";"&$L$26&";",";"&$E$26&";"))),$L$26,IF(ISNUMBER(FIND(";"&"balanced"&";",";"&$E$26&";")),"balanced",LEFT($E$26,FIND(";",$E$26&";")-1)))) | O26: all_out | P26: =IF(OR($E$26="",$G$26),"KHONG_CHIEN_THUAT",IF(NOT($J$26),IF($H$26="balanced","GIU","CHE_DO_BO_QUA"),IF($N$26=$H$26,"GIU","HO_SO_GHI_DE"))) | Q26: Sim/AI/ConquestAi.P28.cs TickLayered + Sim/AI/Commander.cs AllowedTactic (goal.Destroy, aurel)
A27: goal.Destroy/brandt | B27: goal.Destroy | C27: brandt | D27: =AI_ho_so_anh_xa!$D$4 | E27: =INDEX(AI_ho_so_che_do!$B$2:$B$21,MATCH($D$27,AI_ho_so_che_do!$A$2:$A$21,0))&"" | F27: =INDEX(AI_ho_so_che_do!$P$2:$P$21,MATCH($D$27,AI_ho_so_che_do!$A$2:$A$21,0))=TRUE | G27: =ISNUMBER(FIND(";noGeneralTactic;",";"&INDEX(AI_ho_so_che_do!$O$2:$O$21,MATCH($D$27,AI_ho_so_che_do!$A$2:$A$21,0))&";")) | H27: =IF(AI_tuong!$B$3&""<>"",AI_tuong!$B$3,IF(AI_tuong!$B$4&""<>"",AI_tuong!$B$4,"balanced")) | I27: depth | J27: =OR($F$27,AND(AI_ho_so_anh_xa!$B$4="mode",OR(AI_ho_so_anh_xa!$C$4="Weekly",AI_ho_so_anh_xa!$C$4="Operation"))) | K27: TRUE | L27: =IF($J$27,$H$27,"balanced") | M27: depth | N27: =IF(OR($E$27="",$G$27),"balanced",IF(OR($E$27="*",ISNUMBER(FIND(";"&$L$27&";",";"&$E$27&";"))),$L$27,IF(ISNUMBER(FIND(";"&"balanced"&";",";"&$E$27&";")),"balanced",LEFT($E$27,FIND(";",$E$27&";")-1)))) | O27: depth | P27: =IF(OR($E$27="",$G$27),"KHONG_CHIEN_THUAT",IF(NOT($J$27),IF($H$27="balanced","GIU","CHE_DO_BO_QUA"),IF($N$27=$H$27,"GIU","HO_SO_GHI_DE"))) | Q27: Sim/AI/ConquestAi.P28.cs TickLayered + Sim/AI/Commander.cs AllowedTactic (goal.Destroy, brandt)
A28: goal.Destroy/default | B28: goal.Destroy | C28: default | D28: =AI_ho_so_anh_xa!$D$4 | E28: =INDEX(AI_ho_so_che_do!$B$2:$B$21,MATCH($D$28,AI_ho_so_che_do!$A$2:$A$21,0))&"" | F28: =INDEX(AI_ho_so_che_do!$P$2:$P$21,MATCH($D$28,AI_ho_so_che_do!$A$2:$A$21,0))=TRUE | G28: =ISNUMBER(FIND(";noGeneralTactic;",";"&INDEX(AI_ho_so_che_do!$O$2:$O$21,MATCH($D$28,AI_ho_so_che_do!$A$2:$A$21,0))&";")) | H28: =IF(AI_tuong!$B$4&""<>"",AI_tuong!$B$4,IF(AI_tuong!$B$4&""<>"",AI_tuong!$B$4,"balanced")) | I28: balanced | J28: =OR($F$28,AND(AI_ho_so_anh_xa!$B$4="mode",OR(AI_ho_so_anh_xa!$C$4="Weekly",AI_ho_so_anh_xa!$C$4="Operation"))) | K28: TRUE | L28: =IF($J$28,$H$28,"balanced") | M28: balanced | N28: =IF(OR($E$28="",$G$28),"balanced",IF(OR($E$28="*",ISNUMBER(FIND(";"&$L$28&";",";"&$E$28&";"))),$L$28,IF(ISNUMBER(FIND(";"&"balanced"&";",";"&$E$28&";")),"balanced",LEFT($E$28,FIND(";",$E$28&";")-1)))) | O28: balanced | P28: =IF(OR($E$28="",$G$28),"KHONG_CHIEN_THUAT",IF(NOT($J$28),IF($H$28="balanced","GIU","CHE_DO_BO_QUA"),IF($N$28=$H$28,"GIU","HO_SO_GHI_DE"))) | Q28: Sim/AI/ConquestAi.P28.cs TickLayered + Sim/AI/Commander.cs AllowedTactic (goal.Destroy, default)
A29: goal.Destroy/hung | B29: goal.Destroy | C29: hung | D29: =AI_ho_so_anh_xa!$D$4 | E29: =INDEX(AI_ho_so_che_do!$B$2:$B$21,MATCH($D$29,AI_ho_so_che_do!$A$2:$A$21,0))&"" | F29: =INDEX(AI_ho_so_che_do!$P$2:$P$21,MATCH($D$29,AI_ho_so_che_do!$A$2:$A$21,0))=TRUE | G29: =ISNUMBER(FIND(";noGeneralTactic;",";"&INDEX(AI_ho_so_che_do!$O$2:$O$21,MATCH($D$29,AI_ho_so_che_do!$A$2:$A$21,0))&";")) | H29: =IF(AI_tuong!$B$5&""<>"",AI_tuong!$B$5,IF(AI_tuong!$B$4&""<>"",AI_tuong!$B$4,"balanced")) | I29: balanced | J29: =OR($F$29,AND(AI_ho_so_anh_xa!$B$4="mode",OR(AI_ho_so_anh_xa!$C$4="Weekly",AI_ho_so_anh_xa!$C$4="Operation"))) | K29: TRUE | L29: =IF($J$29,$H$29,"balanced") | M29: balanced | N29: =IF(OR($E$29="",$G$29),"balanced",IF(OR($E$29="*",ISNUMBER(FIND(";"&$L$29&";",";"&$E$29&";"))),$L$29,IF(ISNUMBER(FIND(";"&"balanced"&";",";"&$E$29&";")),"balanced",LEFT($E$29,FIND(";",$E$29&";")-1)))) | O29: balanced | P29: =IF(OR($E$29="",$G$29),"KHONG_CHIEN_THUAT",IF(NOT($J$29),IF($H$29="balanced","GIU","CHE_DO_BO_QUA"),IF($N$29=$H$29,"GIU","HO_SO_GHI_DE"))) | Q29: Sim/AI/ConquestAi.P28.cs TickLayered + Sim/AI/Commander.cs AllowedTactic (goal.Destroy, hung)
A30: goal.Destroy/kessler | B30: goal.Destroy | C30: kessler | D30: =AI_ho_so_anh_xa!$D$4 | E30: =INDEX(AI_ho_so_che_do!$B$2:$B$21,MATCH($D$30,AI_ho_so_che_do!$A$2:$A$21,0))&"" | F30: =INDEX(AI_ho_so_che_do!$P$2:$P$21,MATCH($D$30,AI_ho_so_che_do!$A$2:$A$21,0))=TRUE | G30: =ISNUMBER(FIND(";noGeneralTactic;",";"&INDEX(AI_ho_so_che_do!$O$2:$O$21,MATCH($D$30,AI_ho_so_che_do!$A$2:$A$21,0))&";")) | H30: =IF(AI_tuong!$B$6&""<>"",AI_tuong!$B$6,IF(AI_tuong!$B$4&""<>"",AI_tuong!$B$4,"balanced")) | I30: attrition | J30: =OR($F$30,AND(AI_ho_so_anh_xa!$B$4="mode",OR(AI_ho_so_anh_xa!$C$4="Weekly",AI_ho_so_anh_xa!$C$4="Operation"))) | K30: TRUE | L30: =IF($J$30,$H$30,"balanced") | M30: attrition | N30: =IF(OR($E$30="",$G$30),"balanced",IF(OR($E$30="*",ISNUMBER(FIND(";"&$L$30&";",";"&$E$30&";"))),$L$30,IF(ISNUMBER(FIND(";"&"balanced"&";",";"&$E$30&";")),"balanced",LEFT($E$30,FIND(";",$E$30&";")-1)))) | O30: attrition | P30: =IF(OR($E$30="",$G$30),"KHONG_CHIEN_THUAT",IF(NOT($J$30),IF($H$30="balanced","GIU","CHE_DO_BO_QUA"),IF($N$30=$H$30,"GIU","HO_SO_GHI_DE"))) | Q30: Sim/AI/ConquestAi.P28.cs TickLayered + Sim/AI/Commander.cs AllowedTactic (goal.Destroy, kessler)
A31: goal.Destroy/orlov | B31: goal.Destroy | C31: orlov | D31: =AI_ho_so_anh_xa!$D$4 | E31: =INDEX(AI_ho_so_che_do!$B$2:$B$21,MATCH($D$31,AI_ho_so_che_do!$A$2:$A$21,0))&"" | F31: =INDEX(AI_ho_so_che_do!$P$2:$P$21,MATCH($D$31,AI_ho_so_che_do!$A$2:$A$21,0))=TRUE | G31: =ISNUMBER(FIND(";noGeneralTactic;",";"&INDEX(AI_ho_so_che_do!$O$2:$O$21,MATCH($D$31,AI_ho_so_che_do!$A$2:$A$21,0))&";")) | H31: =IF(AI_tuong!$B$7&""<>"",AI_tuong!$B$7,IF(AI_tuong!$B$4&""<>"",AI_tuong!$B$4,"balanced")) | I31: firepower | J31: =OR($F$31,AND(AI_ho_so_anh_xa!$B$4="mode",OR(AI_ho_so_anh_xa!$C$4="Weekly",AI_ho_so_anh_xa!$C$4="Operation"))) | K31: TRUE | L31: =IF($J$31,$H$31,"balanced") | M31: firepower | N31: =IF(OR($E$31="",$G$31),"balanced",IF(OR($E$31="*",ISNUMBER(FIND(";"&$L$31&";",";"&$E$31&";"))),$L$31,IF(ISNUMBER(FIND(";"&"balanced"&";",";"&$E$31&";")),"balanced",LEFT($E$31,FIND(";",$E$31&";")-1)))) | O31: firepower | P31: =IF(OR($E$31="",$G$31),"KHONG_CHIEN_THUAT",IF(NOT($J$31),IF($H$31="balanced","GIU","CHE_DO_BO_QUA"),IF($N$31=$H$31,"GIU","HO_SO_GHI_DE"))) | Q31: Sim/AI/ConquestAi.P28.cs TickLayered + Sim/AI/Commander.cs AllowedTactic (goal.Destroy, orlov)
A32: goal.Destroy/quaden | B32: goal.Destroy | C32: quaden | D32: =AI_ho_so_anh_xa!$D$4 | E32: =INDEX(AI_ho_so_che_do!$B$2:$B$21,MATCH($D$32,AI_ho_so_che_do!$A$2:$A$21,0))&"" | F32: =INDEX(AI_ho_so_che_do!$P$2:$P$21,MATCH($D$32,AI_ho_so_che_do!$A$2:$A$21,0))=TRUE | G32: =ISNUMBER(FIND(";noGeneralTactic;",";"&INDEX(AI_ho_so_che_do!$O$2:$O$21,MATCH($D$32,AI_ho_so_che_do!$A$2:$A$21,0))&";")) | H32: =IF(AI_tuong!$B$8&""<>"",AI_tuong!$B$8,IF(AI_tuong!$B$4&""<>"",AI_tuong!$B$4,"balanced")) | I32: balanced | J32: =OR($F$32,AND(AI_ho_so_anh_xa!$B$4="mode",OR(AI_ho_so_anh_xa!$C$4="Weekly",AI_ho_so_anh_xa!$C$4="Operation"))) | K32: TRUE | L32: =IF($J$32,$H$32,"balanced") | M32: balanced | N32: =IF(OR($E$32="",$G$32),"balanced",IF(OR($E$32="*",ISNUMBER(FIND(";"&$L$32&";",";"&$E$32&";"))),$L$32,IF(ISNUMBER(FIND(";"&"balanced"&";",";"&$E$32&";")),"balanced",LEFT($E$32,FIND(";",$E$32&";")-1)))) | O32: balanced | P32: =IF(OR($E$32="",$G$32),"KHONG_CHIEN_THUAT",IF(NOT($J$32),IF($H$32="balanced","GIU","CHE_DO_BO_QUA"),IF($N$32=$H$32,"GIU","HO_SO_GHI_DE"))) | Q32: Sim/AI/ConquestAi.P28.cs TickLayered + Sim/AI/Commander.cs AllowedTactic (goal.Destroy, quaden)
A33: goal.Destroy/sen | B33: goal.Destroy | C33: sen | D33: =AI_ho_so_anh_xa!$D$4 | E33: =INDEX(AI_ho_so_che_do!$B$2:$B$21,MATCH($D$33,AI_ho_so_che_do!$A$2:$A$21,0))&"" | F33: =INDEX(AI_ho_so_che_do!$P$2:$P$21,MATCH($D$33,AI_ho_so_che_do!$A$2:$A$21,0))=TRUE | G33: =ISNUMBER(FIND(";noGeneralTactic;",";"&INDEX(AI_ho_so_che_do!$O$2:$O$21,MATCH($D$33,AI_ho_so_che_do!$A$2:$A$21,0))&";")) | H33: =IF(AI_tuong!$B$9&""<>"",AI_tuong!$B$9,IF(AI_tuong!$B$4&""<>"",AI_tuong!$B$4,"balanced")) | I33: balanced | J33: =OR($F$33,AND(AI_ho_so_anh_xa!$B$4="mode",OR(AI_ho_so_anh_xa!$C$4="Weekly",AI_ho_so_anh_xa!$C$4="Operation"))) | K33: TRUE | L33: =IF($J$33,$H$33,"balanced") | M33: balanced | N33: =IF(OR($E$33="",$G$33),"balanced",IF(OR($E$33="*",ISNUMBER(FIND(";"&$L$33&";",";"&$E$33&";"))),$L$33,IF(ISNUMBER(FIND(";"&"balanced"&";",";"&$E$33&";")),"balanced",LEFT($E$33,FIND(";",$E$33&";")-1)))) | O33: balanced | P33: =IF(OR($E$33="",$G$33),"KHONG_CHIEN_THUAT",IF(NOT($J$33),IF($H$33="balanced","GIU","CHE_DO_BO_QUA"),IF($N$33=$H$33,"GIU","HO_SO_GHI_DE"))) | Q33: Sim/AI/ConquestAi.P28.cs TickLayered + Sim/AI/Commander.cs AllowedTactic (goal.Destroy, sen)
A34: goal.Destroy/thorne | B34: goal.Destroy | C34: thorne | D34: =AI_ho_so_anh_xa!$D$4 | E34: =INDEX(AI_ho_so_che_do!$B$2:$B$21,MATCH($D$34,AI_ho_so_che_do!$A$2:$A$21,0))&"" | F34: =INDEX(AI_ho_so_che_do!$P$2:$P$21,MATCH($D$34,AI_ho_so_che_do!$A$2:$A$21,0))=TRUE | G34: =ISNUMBER(FIND(";noGeneralTactic;",";"&INDEX(AI_ho_so_che_do!$O$2:$O$21,MATCH($D$34,AI_ho_so_che_do!$A$2:$A$21,0))&";")) | H34: =IF(AI_tuong!$B$10&""<>"",AI_tuong!$B$10,IF(AI_tuong!$B$4&""<>"",AI_tuong!$B$4,"balanced")) | I34: balanced | J34: =OR($F$34,AND(AI_ho_so_anh_xa!$B$4="mode",OR(AI_ho_so_anh_xa!$C$4="Weekly",AI_ho_so_anh_xa!$C$4="Operation"))) | K34: TRUE | L34: =IF($J$34,$H$34,"balanced") | M34: balanced | N34: =IF(OR($E$34="",$G$34),"balanced",IF(OR($E$34="*",ISNUMBER(FIND(";"&$L$34&";",";"&$E$34&";"))),$L$34,IF(ISNUMBER(FIND(";"&"balanced"&";",";"&$E$34&";")),"balanced",LEFT($E$34,FIND(";",$E$34&";")-1)))) | O34: balanced | P34: =IF(OR($E$34="",$G$34),"KHONG_CHIEN_THUAT",IF(NOT($J$34),IF($H$34="balanced","GIU","CHE_DO_BO_QUA"),IF($N$34=$H$34,"GIU","HO_SO_GHI_DE"))) | Q34: Sim/AI/ConquestAi.P28.cs TickLayered + Sim/AI/Commander.cs AllowedTactic (goal.Destroy, thorne)
A35: goal.Destroy/varga | B35: goal.Destroy | C35: varga | D35: =AI_ho_so_anh_xa!$D$4 | E35: =INDEX(AI_ho_so_che_do!$B$2:$B$21,MATCH($D$35,AI_ho_so_che_do!$A$2:$A$21,0))&"" | F35: =INDEX(AI_ho_so_che_do!$P$2:$P$21,MATCH($D$35,AI_ho_so_che_do!$A$2:$A$21,0))=TRUE | G35: =ISNUMBER(FIND(";noGeneralTactic;",";"&INDEX(AI_ho_so_che_do!$O$2:$O$21,MATCH($D$35,AI_ho_so_che_do!$A$2:$A$21,0))&";")) | H35: =IF(AI_tuong!$B$11&""<>"",AI_tuong!$B$11,IF(AI_tuong!$B$4&""<>"",AI_tuong!$B$4,"balanced")) | I35: breakthrough | J35: =OR($F$35,AND(AI_ho_so_anh_xa!$B$4="mode",OR(AI_ho_so_anh_xa!$C$4="Weekly",AI_ho_so_anh_xa!$C$4="Operation"))) | K35: TRUE | L35: =IF($J$35,$H$35,"balanced") | M35: breakthrough | N35: =IF(OR($E$35="",$G$35),"balanced",IF(OR($E$35="*",ISNUMBER(FIND(";"&$L$35&";",";"&$E$35&";"))),$L$35,IF(ISNUMBER(FIND(";"&"balanced"&";",";"&$E$35&";")),"balanced",LEFT($E$35,FIND(";",$E$35&";")-1)))) | O35: breakthrough | P35: =IF(OR($E$35="",$G$35),"KHONG_CHIEN_THUAT",IF(NOT($J$35),IF($H$35="balanced","GIU","CHE_DO_BO_QUA"),IF($N$35=$H$35,"GIU","HO_SO_GHI_DE"))) | Q35: Sim/AI/ConquestAi.P28.cs TickLayered + Sim/AI/Commander.cs AllowedTactic (goal.Destroy, varga)
A36: goal.Destroy/venn | B36: goal.Destroy | C36: venn | D36: =AI_ho_so_anh_xa!$D$4 | E36: =INDEX(AI_ho_so_che_do!$B$2:$B$21,MATCH($D$36,AI_ho_so_che_do!$A$2:$A$21,0))&"" | F36: =INDEX(AI_ho_so_che_do!$P$2:$P$21,MATCH($D$36,AI_ho_so_che_do!$A$2:$A$21,0))=TRUE | G36: =ISNUMBER(FIND(";noGeneralTactic;",";"&INDEX(AI_ho_so_che_do!$O$2:$O$21,MATCH($D$36,AI_ho_so_che_do!$A$2:$A$21,0))&";")) | H36: =IF(AI_tuong!$B$12&""<>"",AI_tuong!$B$12,IF(AI_tuong!$B$4&""<>"",AI_tuong!$B$4,"balanced")) | I36: dispersal | J36: =OR($F$36,AND(AI_ho_so_anh_xa!$B$4="mode",OR(AI_ho_so_anh_xa!$C$4="Weekly",AI_ho_so_anh_xa!$C$4="Operation"))) | K36: TRUE | L36: =IF($J$36,$H$36,"balanced") | M36: dispersal | N36: =IF(OR($E$36="",$G$36),"balanced",IF(OR($E$36="*",ISNUMBER(FIND(";"&$L$36&";",";"&$E$36&";"))),$L$36,IF(ISNUMBER(FIND(";"&"balanced"&";",";"&$E$36&";")),"balanced",LEFT($E$36,FIND(";",$E$36&";")-1)))) | O36: dispersal | P36: =IF(OR($E$36="",$G$36),"KHONG_CHIEN_THUAT",IF(NOT($J$36),IF($H$36="balanced","GIU","CHE_DO_BO_QUA"),IF($N$36=$H$36,"GIU","HO_SO_GHI_DE"))) | Q36: Sim/AI/ConquestAi.P28.cs TickLayered + Sim/AI/Commander.cs AllowedTactic (goal.Destroy, venn)
A37: goal.Destroy/wolff | B37: goal.Destroy | C37: wolff | D37: =AI_ho_so_anh_xa!$D$4 | E37: =INDEX(AI_ho_so_che_do!$B$2:$B$21,MATCH($D$37,AI_ho_so_che_do!$A$2:$A$21,0))&"" | F37: =INDEX(AI_ho_so_che_do!$P$2:$P$21,MATCH($D$37,AI_ho_so_che_do!$A$2:$A$21,0))=TRUE | G37: =ISNUMBER(FIND(";noGeneralTactic;",";"&INDEX(AI_ho_so_che_do!$O$2:$O$21,MATCH($D$37,AI_ho_so_che_do!$A$2:$A$21,0))&";")) | H37: =IF(AI_tuong!$B$13&""<>"",AI_tuong!$B$13,IF(AI_tuong!$B$4&""<>"",AI_tuong!$B$4,"balanced")) | I37: air_superiority | J37: =OR($F$37,AND(AI_ho_so_anh_xa!$B$4="mode",OR(AI_ho_so_anh_xa!$C$4="Weekly",AI_ho_so_anh_xa!$C$4="Operation"))) | K37: TRUE | L37: =IF($J$37,$H$37,"balanced") | M37: air_superiority | N37: =IF(OR($E$37="",$G$37),"balanced",IF(OR($E$37="*",ISNUMBER(FIND(";"&$L$37&";",";"&$E$37&";"))),$L$37,IF(ISNUMBER(FIND(";"&"balanced"&";",";"&$E$37&";")),"balanced",LEFT($E$37,FIND(";",$E$37&";")-1)))) | O37: air_superiority | P37: =IF(OR($E$37="",$G$37),"KHONG_CHIEN_THUAT",IF(NOT($J$37),IF($H$37="balanced","GIU","CHE_DO_BO_QUA"),IF($N$37=$H$37,"GIU","HO_SO_GHI_DE"))) | Q37: Sim/AI/ConquestAi.P28.cs TickLayered + Sim/AI/Commander.cs AllowedTactic (goal.Destroy, wolff)
A38: goal.Duel/aurel | B38: goal.Duel | C38: aurel | D38: =AI_ho_so_anh_xa!$D$5 | E38: =INDEX(AI_ho_so_che_do!$B$2:$B$21,MATCH($D$38,AI_ho_so_che_do!$A$2:$A$21,0))&"" | F38: =INDEX(AI_ho_so_che_do!$P$2:$P$21,MATCH($D$38,AI_ho_so_che_do!$A$2:$A$21,0))=TRUE | G38: =ISNUMBER(FIND(";noGeneralTactic;",";"&INDEX(AI_ho_so_che_do!$O$2:$O$21,MATCH($D$38,AI_ho_so_che_do!$A$2:$A$21,0))&";")) | H38: =IF(AI_tuong!$B$2&""<>"",AI_tuong!$B$2,IF(AI_tuong!$B$4&""<>"",AI_tuong!$B$4,"balanced")) | I38: all_out | J38: =OR($F$38,AND(AI_ho_so_anh_xa!$B$5="mode",OR(AI_ho_so_anh_xa!$C$5="Weekly",AI_ho_so_anh_xa!$C$5="Operation"))) | K38: TRUE | L38: =IF($J$38,$H$38,"balanced") | M38: all_out | N38: =IF(OR($E$38="",$G$38),"balanced",IF(OR($E$38="*",ISNUMBER(FIND(";"&$L$38&";",";"&$E$38&";"))),$L$38,IF(ISNUMBER(FIND(";"&"balanced"&";",";"&$E$38&";")),"balanced",LEFT($E$38,FIND(";",$E$38&";")-1)))) | O38: all_out | P38: =IF(OR($E$38="",$G$38),"KHONG_CHIEN_THUAT",IF(NOT($J$38),IF($H$38="balanced","GIU","CHE_DO_BO_QUA"),IF($N$38=$H$38,"GIU","HO_SO_GHI_DE"))) | Q38: Sim/AI/ConquestAi.P28.cs TickLayered + Sim/AI/Commander.cs AllowedTactic (goal.Duel, aurel)
A39: goal.Duel/brandt | B39: goal.Duel | C39: brandt | D39: =AI_ho_so_anh_xa!$D$5 | E39: =INDEX(AI_ho_so_che_do!$B$2:$B$21,MATCH($D$39,AI_ho_so_che_do!$A$2:$A$21,0))&"" | F39: =INDEX(AI_ho_so_che_do!$P$2:$P$21,MATCH($D$39,AI_ho_so_che_do!$A$2:$A$21,0))=TRUE | G39: =ISNUMBER(FIND(";noGeneralTactic;",";"&INDEX(AI_ho_so_che_do!$O$2:$O$21,MATCH($D$39,AI_ho_so_che_do!$A$2:$A$21,0))&";")) | H39: =IF(AI_tuong!$B$3&""<>"",AI_tuong!$B$3,IF(AI_tuong!$B$4&""<>"",AI_tuong!$B$4,"balanced")) | I39: depth | J39: =OR($F$39,AND(AI_ho_so_anh_xa!$B$5="mode",OR(AI_ho_so_anh_xa!$C$5="Weekly",AI_ho_so_anh_xa!$C$5="Operation"))) | K39: TRUE | L39: =IF($J$39,$H$39,"balanced") | M39: depth | N39: =IF(OR($E$39="",$G$39),"balanced",IF(OR($E$39="*",ISNUMBER(FIND(";"&$L$39&";",";"&$E$39&";"))),$L$39,IF(ISNUMBER(FIND(";"&"balanced"&";",";"&$E$39&";")),"balanced",LEFT($E$39,FIND(";",$E$39&";")-1)))) | O39: depth | P39: =IF(OR($E$39="",$G$39),"KHONG_CHIEN_THUAT",IF(NOT($J$39),IF($H$39="balanced","GIU","CHE_DO_BO_QUA"),IF($N$39=$H$39,"GIU","HO_SO_GHI_DE"))) | Q39: Sim/AI/ConquestAi.P28.cs TickLayered + Sim/AI/Commander.cs AllowedTactic (goal.Duel, brandt)
A40: goal.Duel/default | B40: goal.Duel | C40: default | D40: =AI_ho_so_anh_xa!$D$5 | E40: =INDEX(AI_ho_so_che_do!$B$2:$B$21,MATCH($D$40,AI_ho_so_che_do!$A$2:$A$21,0))&"" | F40: =INDEX(AI_ho_so_che_do!$P$2:$P$21,MATCH($D$40,AI_ho_so_che_do!$A$2:$A$21,0))=TRUE | G40: =ISNUMBER(FIND(";noGeneralTactic;",";"&INDEX(AI_ho_so_che_do!$O$2:$O$21,MATCH($D$40,AI_ho_so_che_do!$A$2:$A$21,0))&";")) | H40: =IF(AI_tuong!$B$4&""<>"",AI_tuong!$B$4,IF(AI_tuong!$B$4&""<>"",AI_tuong!$B$4,"balanced")) | I40: balanced | J40: =OR($F$40,AND(AI_ho_so_anh_xa!$B$5="mode",OR(AI_ho_so_anh_xa!$C$5="Weekly",AI_ho_so_anh_xa!$C$5="Operation"))) | K40: TRUE | L40: =IF($J$40,$H$40,"balanced") | M40: balanced | N40: =IF(OR($E$40="",$G$40),"balanced",IF(OR($E$40="*",ISNUMBER(FIND(";"&$L$40&";",";"&$E$40&";"))),$L$40,IF(ISNUMBER(FIND(";"&"balanced"&";",";"&$E$40&";")),"balanced",LEFT($E$40,FIND(";",$E$40&";")-1)))) | O40: balanced | P40: =IF(OR($E$40="",$G$40),"KHONG_CHIEN_THUAT",IF(NOT($J$40),IF($H$40="balanced","GIU","CHE_DO_BO_QUA"),IF($N$40=$H$40,"GIU","HO_SO_GHI_DE"))) | Q40: Sim/AI/ConquestAi.P28.cs TickLayered + Sim/AI/Commander.cs AllowedTactic (goal.Duel, default)
A41: goal.Duel/hung | B41: goal.Duel | C41: hung | D41: =AI_ho_so_anh_xa!$D$5 | E41: =INDEX(AI_ho_so_che_do!$B$2:$B$21,MATCH($D$41,AI_ho_so_che_do!$A$2:$A$21,0))&"" | F41: =INDEX(AI_ho_so_che_do!$P$2:$P$21,MATCH($D$41,AI_ho_so_che_do!$A$2:$A$21,0))=TRUE | G41: =ISNUMBER(FIND(";noGeneralTactic;",";"&INDEX(AI_ho_so_che_do!$O$2:$O$21,MATCH($D$41,AI_ho_so_che_do!$A$2:$A$21,0))&";")) | H41: =IF(AI_tuong!$B$5&""<>"",AI_tuong!$B$5,IF(AI_tuong!$B$4&""<>"",AI_tuong!$B$4,"balanced")) | I41: balanced | J41: =OR($F$41,AND(AI_ho_so_anh_xa!$B$5="mode",OR(AI_ho_so_anh_xa!$C$5="Weekly",AI_ho_so_anh_xa!$C$5="Operation"))) | K41: TRUE | L41: =IF($J$41,$H$41,"balanced") | M41: balanced | N41: =IF(OR($E$41="",$G$41),"balanced",IF(OR($E$41="*",ISNUMBER(FIND(";"&$L$41&";",";"&$E$41&";"))),$L$41,IF(ISNUMBER(FIND(";"&"balanced"&";",";"&$E$41&";")),"balanced",LEFT($E$41,FIND(";",$E$41&";")-1)))) | O41: balanced | P41: =IF(OR($E$41="",$G$41),"KHONG_CHIEN_THUAT",IF(NOT($J$41),IF($H$41="balanced","GIU","CHE_DO_BO_QUA"),IF($N$41=$H$41,"GIU","HO_SO_GHI_DE"))) | Q41: Sim/AI/ConquestAi.P28.cs TickLayered + Sim/AI/Commander.cs AllowedTactic (goal.Duel, hung)
A42: goal.Duel/kessler | B42: goal.Duel | C42: kessler | D42: =AI_ho_so_anh_xa!$D$5 | E42: =INDEX(AI_ho_so_che_do!$B$2:$B$21,MATCH($D$42,AI_ho_so_che_do!$A$2:$A$21,0))&"" | F42: =INDEX(AI_ho_so_che_do!$P$2:$P$21,MATCH($D$42,AI_ho_so_che_do!$A$2:$A$21,0))=TRUE | G42: =ISNUMBER(FIND(";noGeneralTactic;",";"&INDEX(AI_ho_so_che_do!$O$2:$O$21,MATCH($D$42,AI_ho_so_che_do!$A$2:$A$21,0))&";")) | H42: =IF(AI_tuong!$B$6&""<>"",AI_tuong!$B$6,IF(AI_tuong!$B$4&""<>"",AI_tuong!$B$4,"balanced")) | I42: attrition | J42: =OR($F$42,AND(AI_ho_so_anh_xa!$B$5="mode",OR(AI_ho_so_anh_xa!$C$5="Weekly",AI_ho_so_anh_xa!$C$5="Operation"))) | K42: TRUE | L42: =IF($J$42,$H$42,"balanced") | M42: attrition | N42: =IF(OR($E$42="",$G$42),"balanced",IF(OR($E$42="*",ISNUMBER(FIND(";"&$L$42&";",";"&$E$42&";"))),$L$42,IF(ISNUMBER(FIND(";"&"balanced"&";",";"&$E$42&";")),"balanced",LEFT($E$42,FIND(";",$E$42&";")-1)))) | O42: attrition | P42: =IF(OR($E$42="",$G$42),"KHONG_CHIEN_THUAT",IF(NOT($J$42),IF($H$42="balanced","GIU","CHE_DO_BO_QUA"),IF($N$42=$H$42,"GIU","HO_SO_GHI_DE"))) | Q42: Sim/AI/ConquestAi.P28.cs TickLayered + Sim/AI/Commander.cs AllowedTactic (goal.Duel, kessler)
A43: goal.Duel/orlov | B43: goal.Duel | C43: orlov | D43: =AI_ho_so_anh_xa!$D$5 | E43: =INDEX(AI_ho_so_che_do!$B$2:$B$21,MATCH($D$43,AI_ho_so_che_do!$A$2:$A$21,0))&"" | F43: =INDEX(AI_ho_so_che_do!$P$2:$P$21,MATCH($D$43,AI_ho_so_che_do!$A$2:$A$21,0))=TRUE | G43: =ISNUMBER(FIND(";noGeneralTactic;",";"&INDEX(AI_ho_so_che_do!$O$2:$O$21,MATCH($D$43,AI_ho_so_che_do!$A$2:$A$21,0))&";")) | H43: =IF(AI_tuong!$B$7&""<>"",AI_tuong!$B$7,IF(AI_tuong!$B$4&""<>"",AI_tuong!$B$4,"balanced")) | I43: firepower | J43: =OR($F$43,AND(AI_ho_so_anh_xa!$B$5="mode",OR(AI_ho_so_anh_xa!$C$5="Weekly",AI_ho_so_anh_xa!$C$5="Operation"))) | K43: TRUE | L43: =IF($J$43,$H$43,"balanced") | M43: firepower | N43: =IF(OR($E$43="",$G$43),"balanced",IF(OR($E$43="*",ISNUMBER(FIND(";"&$L$43&";",";"&$E$43&";"))),$L$43,IF(ISNUMBER(FIND(";"&"balanced"&";",";"&$E$43&";")),"balanced",LEFT($E$43,FIND(";",$E$43&";")-1)))) | O43: firepower | P43: =IF(OR($E$43="",$G$43),"KHONG_CHIEN_THUAT",IF(NOT($J$43),IF($H$43="balanced","GIU","CHE_DO_BO_QUA"),IF($N$43=$H$43,"GIU","HO_SO_GHI_DE"))) | Q43: Sim/AI/ConquestAi.P28.cs TickLayered + Sim/AI/Commander.cs AllowedTactic (goal.Duel, orlov)
A44: goal.Duel/quaden | B44: goal.Duel | C44: quaden | D44: =AI_ho_so_anh_xa!$D$5 | E44: =INDEX(AI_ho_so_che_do!$B$2:$B$21,MATCH($D$44,AI_ho_so_che_do!$A$2:$A$21,0))&"" | F44: =INDEX(AI_ho_so_che_do!$P$2:$P$21,MATCH($D$44,AI_ho_so_che_do!$A$2:$A$21,0))=TRUE | G44: =ISNUMBER(FIND(";noGeneralTactic;",";"&INDEX(AI_ho_so_che_do!$O$2:$O$21,MATCH($D$44,AI_ho_so_che_do!$A$2:$A$21,0))&";")) | H44: =IF(AI_tuong!$B$8&""<>"",AI_tuong!$B$8,IF(AI_tuong!$B$4&""<>"",AI_tuong!$B$4,"balanced")) | I44: balanced | J44: =OR($F$44,AND(AI_ho_so_anh_xa!$B$5="mode",OR(AI_ho_so_anh_xa!$C$5="Weekly",AI_ho_so_anh_xa!$C$5="Operation"))) | K44: TRUE | L44: =IF($J$44,$H$44,"balanced") | M44: balanced | N44: =IF(OR($E$44="",$G$44),"balanced",IF(OR($E$44="*",ISNUMBER(FIND(";"&$L$44&";",";"&$E$44&";"))),$L$44,IF(ISNUMBER(FIND(";"&"balanced"&";",";"&$E$44&";")),"balanced",LEFT($E$44,FIND(";",$E$44&";")-1)))) | O44: balanced | P44: =IF(OR($E$44="",$G$44),"KHONG_CHIEN_THUAT",IF(NOT($J$44),IF($H$44="balanced","GIU","CHE_DO_BO_QUA"),IF($N$44=$H$44,"GIU","HO_SO_GHI_DE"))) | Q44: Sim/AI/ConquestAi.P28.cs TickLayered + Sim/AI/Commander.cs AllowedTactic (goal.Duel, quaden)
A45: goal.Duel/sen | B45: goal.Duel | C45: sen | D45: =AI_ho_so_anh_xa!$D$5 | E45: =INDEX(AI_ho_so_che_do!$B$2:$B$21,MATCH($D$45,AI_ho_so_che_do!$A$2:$A$21,0))&"" | F45: =INDEX(AI_ho_so_che_do!$P$2:$P$21,MATCH($D$45,AI_ho_so_che_do!$A$2:$A$21,0))=TRUE | G45: =ISNUMBER(FIND(";noGeneralTactic;",";"&INDEX(AI_ho_so_che_do!$O$2:$O$21,MATCH($D$45,AI_ho_so_che_do!$A$2:$A$21,0))&";")) | H45: =IF(AI_tuong!$B$9&""<>"",AI_tuong!$B$9,IF(AI_tuong!$B$4&""<>"",AI_tuong!$B$4,"balanced")) | I45: balanced | J45: =OR($F$45,AND(AI_ho_so_anh_xa!$B$5="mode",OR(AI_ho_so_anh_xa!$C$5="Weekly",AI_ho_so_anh_xa!$C$5="Operation"))) | K45: TRUE | L45: =IF($J$45,$H$45,"balanced") | M45: balanced | N45: =IF(OR($E$45="",$G$45),"balanced",IF(OR($E$45="*",ISNUMBER(FIND(";"&$L$45&";",";"&$E$45&";"))),$L$45,IF(ISNUMBER(FIND(";"&"balanced"&";",";"&$E$45&";")),"balanced",LEFT($E$45,FIND(";",$E$45&";")-1)))) | O45: balanced | P45: =IF(OR($E$45="",$G$45),"KHONG_CHIEN_THUAT",IF(NOT($J$45),IF($H$45="balanced","GIU","CHE_DO_BO_QUA"),IF($N$45=$H$45,"GIU","HO_SO_GHI_DE"))) | Q45: Sim/AI/ConquestAi.P28.cs TickLayered + Sim/AI/Commander.cs AllowedTactic (goal.Duel, sen)
A46: goal.Duel/thorne | B46: goal.Duel | C46: thorne | D46: =AI_ho_so_anh_xa!$D$5 | E46: =INDEX(AI_ho_so_che_do!$B$2:$B$21,MATCH($D$46,AI_ho_so_che_do!$A$2:$A$21,0))&"" | F46: =INDEX(AI_ho_so_che_do!$P$2:$P$21,MATCH($D$46,AI_ho_so_che_do!$A$2:$A$21,0))=TRUE | G46: =ISNUMBER(FIND(";noGeneralTactic;",";"&INDEX(AI_ho_so_che_do!$O$2:$O$21,MATCH($D$46,AI_ho_so_che_do!$A$2:$A$21,0))&";")) | H46: =IF(AI_tuong!$B$10&""<>"",AI_tuong!$B$10,IF(AI_tuong!$B$4&""<>"",AI_tuong!$B$4,"balanced")) | I46: balanced | J46: =OR($F$46,AND(AI_ho_so_anh_xa!$B$5="mode",OR(AI_ho_so_anh_xa!$C$5="Weekly",AI_ho_so_anh_xa!$C$5="Operation"))) | K46: TRUE | L46: =IF($J$46,$H$46,"balanced") | M46: balanced | N46: =IF(OR($E$46="",$G$46),"balanced",IF(OR($E$46="*",ISNUMBER(FIND(";"&$L$46&";",";"&$E$46&";"))),$L$46,IF(ISNUMBER(FIND(";"&"balanced"&";",";"&$E$46&";")),"balanced",LEFT($E$46,FIND(";",$E$46&";")-1)))) | O46: balanced | P46: =IF(OR($E$46="",$G$46),"KHONG_CHIEN_THUAT",IF(NOT($J$46),IF($H$46="balanced","GIU","CHE_DO_BO_QUA"),IF($N$46=$H$46,"GIU","HO_SO_GHI_DE"))) | Q46: Sim/AI/ConquestAi.P28.cs TickLayered + Sim/AI/Commander.cs AllowedTactic (goal.Duel, thorne)
A47: goal.Duel/varga | B47: goal.Duel | C47: varga | D47: =AI_ho_so_anh_xa!$D$5 | E47: =INDEX(AI_ho_so_che_do!$B$2:$B$21,MATCH($D$47,AI_ho_so_che_do!$A$2:$A$21,0))&"" | F47: =INDEX(AI_ho_so_che_do!$P$2:$P$21,MATCH($D$47,AI_ho_so_che_do!$A$2:$A$21,0))=TRUE | G47: =ISNUMBER(FIND(";noGeneralTactic;",";"&INDEX(AI_ho_so_che_do!$O$2:$O$21,MATCH($D$47,AI_ho_so_che_do!$A$2:$A$21,0))&";")) | H47: =IF(AI_tuong!$B$11&""<>"",AI_tuong!$B$11,IF(AI_tuong!$B$4&""<>"",AI_tuong!$B$4,"balanced")) | I47: breakthrough | J47: =OR($F$47,AND(AI_ho_so_anh_xa!$B$5="mode",OR(AI_ho_so_anh_xa!$C$5="Weekly",AI_ho_so_anh_xa!$C$5="Operation"))) | K47: TRUE | L47: =IF($J$47,$H$47,"balanced") | M47: breakthrough | N47: =IF(OR($E$47="",$G$47),"balanced",IF(OR($E$47="*",ISNUMBER(FIND(";"&$L$47&";",";"&$E$47&";"))),$L$47,IF(ISNUMBER(FIND(";"&"balanced"&";",";"&$E$47&";")),"balanced",LEFT($E$47,FIND(";",$E$47&";")-1)))) | O47: breakthrough | P47: =IF(OR($E$47="",$G$47),"KHONG_CHIEN_THUAT",IF(NOT($J$47),IF($H$47="balanced","GIU","CHE_DO_BO_QUA"),IF($N$47=$H$47,"GIU","HO_SO_GHI_DE"))) | Q47: Sim/AI/ConquestAi.P28.cs TickLayered + Sim/AI/Commander.cs AllowedTactic (goal.Duel, varga)
A48: goal.Duel/venn | B48: goal.Duel | C48: venn | D48: =AI_ho_so_anh_xa!$D$5 | E48: =INDEX(AI_ho_so_che_do!$B$2:$B$21,MATCH($D$48,AI_ho_so_che_do!$A$2:$A$21,0))&"" | F48: =INDEX(AI_ho_so_che_do!$P$2:$P$21,MATCH($D$48,AI_ho_so_che_do!$A$2:$A$21,0))=TRUE | G48: =ISNUMBER(FIND(";noGeneralTactic;",";"&INDEX(AI_ho_so_che_do!$O$2:$O$21,MATCH($D$48,AI_ho_so_che_do!$A$2:$A$21,0))&";")) | H48: =IF(AI_tuong!$B$12&""<>"",AI_tuong!$B$12,IF(AI_tuong!$B$4&""<>"",AI_tuong!$B$4,"balanced")) | I48: dispersal | J48: =OR($F$48,AND(AI_ho_so_anh_xa!$B$5="mode",OR(AI_ho_so_anh_xa!$C$5="Weekly",AI_ho_so_anh_xa!$C$5="Operation"))) | K48: TRUE | L48: =IF($J$48,$H$48,"balanced") | M48: dispersal | N48: =IF(OR($E$48="",$G$48),"balanced",IF(OR($E$48="*",ISNUMBER(FIND(";"&$L$48&";",";"&$E$48&";"))),$L$48,IF(ISNUMBER(FIND(";"&"balanced"&";",";"&$E$48&";")),"balanced",LEFT($E$48,FIND(";",$E$48&";")-1)))) | O48: dispersal | P48: =IF(OR($E$48="",$G$48),"KHONG_CHIEN_THUAT",IF(NOT($J$48),IF($H$48="balanced","GIU","CHE_DO_BO_QUA"),IF($N$48=$H$48,"GIU","HO_SO_GHI_DE"))) | Q48: Sim/AI/ConquestAi.P28.cs TickLayered + Sim/AI/Commander.cs AllowedTactic (goal.Duel, venn)
A49: goal.Duel/wolff | B49: goal.Duel | C49: wolff | D49: =AI_ho_so_anh_xa!$D$5 | E49: =INDEX(AI_ho_so_che_do!$B$2:$B$21,MATCH($D$49,AI_ho_so_che_do!$A$2:$A$21,0))&"" | F49: =INDEX(AI_ho_so_che_do!$P$2:$P$21,MATCH($D$49,AI_ho_so_che_do!$A$2:$A$21,0))=TRUE | G49: =ISNUMBER(FIND(";noGeneralTactic;",";"&INDEX(AI_ho_so_che_do!$O$2:$O$21,MATCH($D$49,AI_ho_so_che_do!$A$2:$A$21,0))&";")) | H49: =IF(AI_tuong!$B$13&""<>"",AI_tuong!$B$13,IF(AI_tuong!$B$4&""<>"",AI_tuong!$B$4,"balanced")) | I49: air_superiority | J49: =OR($F$49,AND(AI_ho_so_anh_xa!$B$5="mode",OR(AI_ho_so_anh_xa!$C$5="Weekly",AI_ho_so_anh_xa!$C$5="Operation"))) | K49: TRUE | L49: =IF($J$49,$H$49,"balanced") | M49: air_superiority | N49: =IF(OR($E$49="",$G$49),"balanced",IF(OR($E$49="*",ISNUMBER(FIND(";"&$L$49&";",";"&$E$49&";"))),$L$49,IF(ISNUMBER(FIND(";"&"balanced"&";",";"&$E$49&";")),"balanced",LEFT($E$49,FIND(";",$E$49&";")-1)))) | O49: air_superiority | P49: =IF(OR($E$49="",$G$49),"KHONG_CHIEN_THUAT",IF(NOT($J$49),IF($H$49="balanced","GIU","CHE_DO_BO_QUA"),IF($N$49=$H$49,"GIU","HO_SO_GHI_DE"))) | Q49: Sim/AI/ConquestAi.P28.cs TickLayered + Sim/AI/Commander.cs AllowedTactic (goal.Duel, wolff)
A50: goal.Escort/aurel | B50: goal.Escort | C50: aurel | D50: =AI_ho_so_anh_xa!$D$6 | E50: =INDEX(AI_ho_so_che_do!$B$2:$B$21,MATCH($D$50,AI_ho_so_che_do!$A$2:$A$21,0))&"" | F50: =INDEX(AI_ho_so_che_do!$P$2:$P$21,MATCH($D$50,AI_ho_so_che_do!$A$2:$A$21,0))=TRUE | G50: =ISNUMBER(FIND(";noGeneralTactic;",";"&INDEX(AI_ho_so_che_do!$O$2:$O$21,MATCH($D$50,AI_ho_so_che_do!$A$2:$A$21,0))&";")) | H50: =IF(AI_tuong!$B$2&""<>"",AI_tuong!$B$2,IF(AI_tuong!$B$4&""<>"",AI_tuong!$B$4,"balanced")) | I50: all_out | J50: =OR($F$50,AND(AI_ho_so_anh_xa!$B$6="mode",OR(AI_ho_so_anh_xa!$C$6="Weekly",AI_ho_so_anh_xa!$C$6="Operation"))) | K50: TRUE | L50: =IF($J$50,$H$50,"balanced") | M50: all_out | N50: =IF(OR($E$50="",$G$50),"balanced",IF(OR($E$50="*",ISNUMBER(FIND(";"&$L$50&";",";"&$E$50&";"))),$L$50,IF(ISNUMBER(FIND(";"&"balanced"&";",";"&$E$50&";")),"balanced",LEFT($E$50,FIND(";",$E$50&";")-1)))) | O50: all_out | P50: =IF(OR($E$50="",$G$50),"KHONG_CHIEN_THUAT",IF(NOT($J$50),IF($H$50="balanced","GIU","CHE_DO_BO_QUA"),IF($N$50=$H$50,"GIU","HO_SO_GHI_DE"))) | Q50: Sim/AI/ConquestAi.P28.cs TickLayered + Sim/AI/Commander.cs AllowedTactic (goal.Escort, aurel)
A51: goal.Escort/brandt | B51: goal.Escort | C51: brandt | D51: =AI_ho_so_anh_xa!$D$6 | E51: =INDEX(AI_ho_so_che_do!$B$2:$B$21,MATCH($D$51,AI_ho_so_che_do!$A$2:$A$21,0))&"" | F51: =INDEX(AI_ho_so_che_do!$P$2:$P$21,MATCH($D$51,AI_ho_so_che_do!$A$2:$A$21,0))=TRUE | G51: =ISNUMBER(FIND(";noGeneralTactic;",";"&INDEX(AI_ho_so_che_do!$O$2:$O$21,MATCH($D$51,AI_ho_so_che_do!$A$2:$A$21,0))&";")) | H51: =IF(AI_tuong!$B$3&""<>"",AI_tuong!$B$3,IF(AI_tuong!$B$4&""<>"",AI_tuong!$B$4,"balanced")) | I51: depth | J51: =OR($F$51,AND(AI_ho_so_anh_xa!$B$6="mode",OR(AI_ho_so_anh_xa!$C$6="Weekly",AI_ho_so_anh_xa!$C$6="Operation"))) | K51: TRUE | L51: =IF($J$51,$H$51,"balanced") | M51: depth | N51: =IF(OR($E$51="",$G$51),"balanced",IF(OR($E$51="*",ISNUMBER(FIND(";"&$L$51&";",";"&$E$51&";"))),$L$51,IF(ISNUMBER(FIND(";"&"balanced"&";",";"&$E$51&";")),"balanced",LEFT($E$51,FIND(";",$E$51&";")-1)))) | O51: depth | P51: =IF(OR($E$51="",$G$51),"KHONG_CHIEN_THUAT",IF(NOT($J$51),IF($H$51="balanced","GIU","CHE_DO_BO_QUA"),IF($N$51=$H$51,"GIU","HO_SO_GHI_DE"))) | Q51: Sim/AI/ConquestAi.P28.cs TickLayered + Sim/AI/Commander.cs AllowedTactic (goal.Escort, brandt)
A52: goal.Escort/default | B52: goal.Escort | C52: default | D52: =AI_ho_so_anh_xa!$D$6 | E52: =INDEX(AI_ho_so_che_do!$B$2:$B$21,MATCH($D$52,AI_ho_so_che_do!$A$2:$A$21,0))&"" | F52: =INDEX(AI_ho_so_che_do!$P$2:$P$21,MATCH($D$52,AI_ho_so_che_do!$A$2:$A$21,0))=TRUE | G52: =ISNUMBER(FIND(";noGeneralTactic;",";"&INDEX(AI_ho_so_che_do!$O$2:$O$21,MATCH($D$52,AI_ho_so_che_do!$A$2:$A$21,0))&";")) | H52: =IF(AI_tuong!$B$4&""<>"",AI_tuong!$B$4,IF(AI_tuong!$B$4&""<>"",AI_tuong!$B$4,"balanced")) | I52: balanced | J52: =OR($F$52,AND(AI_ho_so_anh_xa!$B$6="mode",OR(AI_ho_so_anh_xa!$C$6="Weekly",AI_ho_so_anh_xa!$C$6="Operation"))) | K52: TRUE | L52: =IF($J$52,$H$52,"balanced") | M52: balanced | N52: =IF(OR($E$52="",$G$52),"balanced",IF(OR($E$52="*",ISNUMBER(FIND(";"&$L$52&";",";"&$E$52&";"))),$L$52,IF(ISNUMBER(FIND(";"&"balanced"&";",";"&$E$52&";")),"balanced",LEFT($E$52,FIND(";",$E$52&";")-1)))) | O52: balanced | P52: =IF(OR($E$52="",$G$52),"KHONG_CHIEN_THUAT",IF(NOT($J$52),IF($H$52="balanced","GIU","CHE_DO_BO_QUA"),IF($N$52=$H$52,"GIU","HO_SO_GHI_DE"))) | Q52: Sim/AI/ConquestAi.P28.cs TickLayered + Sim/AI/Commander.cs AllowedTactic (goal.Escort, default)
A53: goal.Escort/hung | B53: goal.Escort | C53: hung | D53: =AI_ho_so_anh_xa!$D$6 | E53: =INDEX(AI_ho_so_che_do!$B$2:$B$21,MATCH($D$53,AI_ho_so_che_do!$A$2:$A$21,0))&"" | F53: =INDEX(AI_ho_so_che_do!$P$2:$P$21,MATCH($D$53,AI_ho_so_che_do!$A$2:$A$21,0))=TRUE | G53: =ISNUMBER(FIND(";noGeneralTactic;",";"&INDEX(AI_ho_so_che_do!$O$2:$O$21,MATCH($D$53,AI_ho_so_che_do!$A$2:$A$21,0))&";")) | H53: =IF(AI_tuong!$B$5&""<>"",AI_tuong!$B$5,IF(AI_tuong!$B$4&""<>"",AI_tuong!$B$4,"balanced")) | I53: balanced | J53: =OR($F$53,AND(AI_ho_so_anh_xa!$B$6="mode",OR(AI_ho_so_anh_xa!$C$6="Weekly",AI_ho_so_anh_xa!$C$6="Operation"))) | K53: TRUE | L53: =IF($J$53,$H$53,"balanced") | M53: balanced | N53: =IF(OR($E$53="",$G$53),"balanced",IF(OR($E$53="*",ISNUMBER(FIND(";"&$L$53&";",";"&$E$53&";"))),$L$53,IF(ISNUMBER(FIND(";"&"balanced"&";",";"&$E$53&";")),"balanced",LEFT($E$53,FIND(";",$E$53&";")-1)))) | O53: balanced | P53: =IF(OR($E$53="",$G$53),"KHONG_CHIEN_THUAT",IF(NOT($J$53),IF($H$53="balanced","GIU","CHE_DO_BO_QUA"),IF($N$53=$H$53,"GIU","HO_SO_GHI_DE"))) | Q53: Sim/AI/ConquestAi.P28.cs TickLayered + Sim/AI/Commander.cs AllowedTactic (goal.Escort, hung)
A54: goal.Escort/kessler | B54: goal.Escort | C54: kessler | D54: =AI_ho_so_anh_xa!$D$6 | E54: =INDEX(AI_ho_so_che_do!$B$2:$B$21,MATCH($D$54,AI_ho_so_che_do!$A$2:$A$21,0))&"" | F54: =INDEX(AI_ho_so_che_do!$P$2:$P$21,MATCH($D$54,AI_ho_so_che_do!$A$2:$A$21,0))=TRUE | G54: =ISNUMBER(FIND(";noGeneralTactic;",";"&INDEX(AI_ho_so_che_do!$O$2:$O$21,MATCH($D$54,AI_ho_so_che_do!$A$2:$A$21,0))&";")) | H54: =IF(AI_tuong!$B$6&""<>"",AI_tuong!$B$6,IF(AI_tuong!$B$4&""<>"",AI_tuong!$B$4,"balanced")) | I54: attrition | J54: =OR($F$54,AND(AI_ho_so_anh_xa!$B$6="mode",OR(AI_ho_so_anh_xa!$C$6="Weekly",AI_ho_so_anh_xa!$C$6="Operation"))) | K54: TRUE | L54: =IF($J$54,$H$54,"balanced") | M54: attrition | N54: =IF(OR($E$54="",$G$54),"balanced",IF(OR($E$54="*",ISNUMBER(FIND(";"&$L$54&";",";"&$E$54&";"))),$L$54,IF(ISNUMBER(FIND(";"&"balanced"&";",";"&$E$54&";")),"balanced",LEFT($E$54,FIND(";",$E$54&";")-1)))) | O54: attrition | P54: =IF(OR($E$54="",$G$54),"KHONG_CHIEN_THUAT",IF(NOT($J$54),IF($H$54="balanced","GIU","CHE_DO_BO_QUA"),IF($N$54=$H$54,"GIU","HO_SO_GHI_DE"))) | Q54: Sim/AI/ConquestAi.P28.cs TickLayered + Sim/AI/Commander.cs AllowedTactic (goal.Escort, kessler)
A55: goal.Escort/orlov | B55: goal.Escort | C55: orlov | D55: =AI_ho_so_anh_xa!$D$6 | E55: =INDEX(AI_ho_so_che_do!$B$2:$B$21,MATCH($D$55,AI_ho_so_che_do!$A$2:$A$21,0))&"" | F55: =INDEX(AI_ho_so_che_do!$P$2:$P$21,MATCH($D$55,AI_ho_so_che_do!$A$2:$A$21,0))=TRUE | G55: =ISNUMBER(FIND(";noGeneralTactic;",";"&INDEX(AI_ho_so_che_do!$O$2:$O$21,MATCH($D$55,AI_ho_so_che_do!$A$2:$A$21,0))&";")) | H55: =IF(AI_tuong!$B$7&""<>"",AI_tuong!$B$7,IF(AI_tuong!$B$4&""<>"",AI_tuong!$B$4,"balanced")) | I55: firepower | J55: =OR($F$55,AND(AI_ho_so_anh_xa!$B$6="mode",OR(AI_ho_so_anh_xa!$C$6="Weekly",AI_ho_so_anh_xa!$C$6="Operation"))) | K55: TRUE | L55: =IF($J$55,$H$55,"balanced") | M55: firepower | N55: =IF(OR($E$55="",$G$55),"balanced",IF(OR($E$55="*",ISNUMBER(FIND(";"&$L$55&";",";"&$E$55&";"))),$L$55,IF(ISNUMBER(FIND(";"&"balanced"&";",";"&$E$55&";")),"balanced",LEFT($E$55,FIND(";",$E$55&";")-1)))) | O55: firepower | P55: =IF(OR($E$55="",$G$55),"KHONG_CHIEN_THUAT",IF(NOT($J$55),IF($H$55="balanced","GIU","CHE_DO_BO_QUA"),IF($N$55=$H$55,"GIU","HO_SO_GHI_DE"))) | Q55: Sim/AI/ConquestAi.P28.cs TickLayered + Sim/AI/Commander.cs AllowedTactic (goal.Escort, orlov)
A56: goal.Escort/quaden | B56: goal.Escort | C56: quaden | D56: =AI_ho_so_anh_xa!$D$6 | E56: =INDEX(AI_ho_so_che_do!$B$2:$B$21,MATCH($D$56,AI_ho_so_che_do!$A$2:$A$21,0))&"" | F56: =INDEX(AI_ho_so_che_do!$P$2:$P$21,MATCH($D$56,AI_ho_so_che_do!$A$2:$A$21,0))=TRUE | G56: =ISNUMBER(FIND(";noGeneralTactic;",";"&INDEX(AI_ho_so_che_do!$O$2:$O$21,MATCH($D$56,AI_ho_so_che_do!$A$2:$A$21,0))&";")) | H56: =IF(AI_tuong!$B$8&""<>"",AI_tuong!$B$8,IF(AI_tuong!$B$4&""<>"",AI_tuong!$B$4,"balanced")) | I56: balanced | J56: =OR($F$56,AND(AI_ho_so_anh_xa!$B$6="mode",OR(AI_ho_so_anh_xa!$C$6="Weekly",AI_ho_so_anh_xa!$C$6="Operation"))) | K56: TRUE | L56: =IF($J$56,$H$56,"balanced") | M56: balanced | N56: =IF(OR($E$56="",$G$56),"balanced",IF(OR($E$56="*",ISNUMBER(FIND(";"&$L$56&";",";"&$E$56&";"))),$L$56,IF(ISNUMBER(FIND(";"&"balanced"&";",";"&$E$56&";")),"balanced",LEFT($E$56,FIND(";",$E$56&";")-1)))) | O56: balanced | P56: =IF(OR($E$56="",$G$56),"KHONG_CHIEN_THUAT",IF(NOT($J$56),IF($H$56="balanced","GIU","CHE_DO_BO_QUA"),IF($N$56=$H$56,"GIU","HO_SO_GHI_DE"))) | Q56: Sim/AI/ConquestAi.P28.cs TickLayered + Sim/AI/Commander.cs AllowedTactic (goal.Escort, quaden)
A57: goal.Escort/sen | B57: goal.Escort | C57: sen | D57: =AI_ho_so_anh_xa!$D$6 | E57: =INDEX(AI_ho_so_che_do!$B$2:$B$21,MATCH($D$57,AI_ho_so_che_do!$A$2:$A$21,0))&"" | F57: =INDEX(AI_ho_so_che_do!$P$2:$P$21,MATCH($D$57,AI_ho_so_che_do!$A$2:$A$21,0))=TRUE | G57: =ISNUMBER(FIND(";noGeneralTactic;",";"&INDEX(AI_ho_so_che_do!$O$2:$O$21,MATCH($D$57,AI_ho_so_che_do!$A$2:$A$21,0))&";")) | H57: =IF(AI_tuong!$B$9&""<>"",AI_tuong!$B$9,IF(AI_tuong!$B$4&""<>"",AI_tuong!$B$4,"balanced")) | I57: balanced | J57: =OR($F$57,AND(AI_ho_so_anh_xa!$B$6="mode",OR(AI_ho_so_anh_xa!$C$6="Weekly",AI_ho_so_anh_xa!$C$6="Operation"))) | K57: TRUE | L57: =IF($J$57,$H$57,"balanced") | M57: balanced | N57: =IF(OR($E$57="",$G$57),"balanced",IF(OR($E$57="*",ISNUMBER(FIND(";"&$L$57&";",";"&$E$57&";"))),$L$57,IF(ISNUMBER(FIND(";"&"balanced"&";",";"&$E$57&";")),"balanced",LEFT($E$57,FIND(";",$E$57&";")-1)))) | O57: balanced | P57: =IF(OR($E$57="",$G$57),"KHONG_CHIEN_THUAT",IF(NOT($J$57),IF($H$57="balanced","GIU","CHE_DO_BO_QUA"),IF($N$57=$H$57,"GIU","HO_SO_GHI_DE"))) | Q57: Sim/AI/ConquestAi.P28.cs TickLayered + Sim/AI/Commander.cs AllowedTactic (goal.Escort, sen)
A58: goal.Escort/thorne | B58: goal.Escort | C58: thorne | D58: =AI_ho_so_anh_xa!$D$6 | E58: =INDEX(AI_ho_so_che_do!$B$2:$B$21,MATCH($D$58,AI_ho_so_che_do!$A$2:$A$21,0))&"" | F58: =INDEX(AI_ho_so_che_do!$P$2:$P$21,MATCH($D$58,AI_ho_so_che_do!$A$2:$A$21,0))=TRUE | G58: =ISNUMBER(FIND(";noGeneralTactic;",";"&INDEX(AI_ho_so_che_do!$O$2:$O$21,MATCH($D$58,AI_ho_so_che_do!$A$2:$A$21,0))&";")) | H58: =IF(AI_tuong!$B$10&""<>"",AI_tuong!$B$10,IF(AI_tuong!$B$4&""<>"",AI_tuong!$B$4,"balanced")) | I58: balanced | J58: =OR($F$58,AND(AI_ho_so_anh_xa!$B$6="mode",OR(AI_ho_so_anh_xa!$C$6="Weekly",AI_ho_so_anh_xa!$C$6="Operation"))) | K58: TRUE | L58: =IF($J$58,$H$58,"balanced") | M58: balanced | N58: =IF(OR($E$58="",$G$58),"balanced",IF(OR($E$58="*",ISNUMBER(FIND(";"&$L$58&";",";"&$E$58&";"))),$L$58,IF(ISNUMBER(FIND(";"&"balanced"&";",";"&$E$58&";")),"balanced",LEFT($E$58,FIND(";",$E$58&";")-1)))) | O58: balanced | P58: =IF(OR($E$58="",$G$58),"KHONG_CHIEN_THUAT",IF(NOT($J$58),IF($H$58="balanced","GIU","CHE_DO_BO_QUA"),IF($N$58=$H$58,"GIU","HO_SO_GHI_DE"))) | Q58: Sim/AI/ConquestAi.P28.cs TickLayered + Sim/AI/Commander.cs AllowedTactic (goal.Escort, thorne)
A59: goal.Escort/varga | B59: goal.Escort | C59: varga | D59: =AI_ho_so_anh_xa!$D$6 | E59: =INDEX(AI_ho_so_che_do!$B$2:$B$21,MATCH($D$59,AI_ho_so_che_do!$A$2:$A$21,0))&"" | F59: =INDEX(AI_ho_so_che_do!$P$2:$P$21,MATCH($D$59,AI_ho_so_che_do!$A$2:$A$21,0))=TRUE | G59: =ISNUMBER(FIND(";noGeneralTactic;",";"&INDEX(AI_ho_so_che_do!$O$2:$O$21,MATCH($D$59,AI_ho_so_che_do!$A$2:$A$21,0))&";")) | H59: =IF(AI_tuong!$B$11&""<>"",AI_tuong!$B$11,IF(AI_tuong!$B$4&""<>"",AI_tuong!$B$4,"balanced")) | I59: breakthrough | J59: =OR($F$59,AND(AI_ho_so_anh_xa!$B$6="mode",OR(AI_ho_so_anh_xa!$C$6="Weekly",AI_ho_so_anh_xa!$C$6="Operation"))) | K59: TRUE | L59: =IF($J$59,$H$59,"balanced") | M59: breakthrough | N59: =IF(OR($E$59="",$G$59),"balanced",IF(OR($E$59="*",ISNUMBER(FIND(";"&$L$59&";",";"&$E$59&";"))),$L$59,IF(ISNUMBER(FIND(";"&"balanced"&";",";"&$E$59&";")),"balanced",LEFT($E$59,FIND(";",$E$59&";")-1)))) | O59: breakthrough | P59: =IF(OR($E$59="",$G$59),"KHONG_CHIEN_THUAT",IF(NOT($J$59),IF($H$59="balanced","GIU","CHE_DO_BO_QUA"),IF($N$59=$H$59,"GIU","HO_SO_GHI_DE"))) | Q59: Sim/AI/ConquestAi.P28.cs TickLayered + Sim/AI/Commander.cs AllowedTactic (goal.Escort, varga)
A60: goal.Escort/venn | B60: goal.Escort | C60: venn | D60: =AI_ho_so_anh_xa!$D$6 | E60: =INDEX(AI_ho_so_che_do!$B$2:$B$21,MATCH($D$60,AI_ho_so_che_do!$A$2:$A$21,0))&"" | F60: =INDEX(AI_ho_so_che_do!$P$2:$P$21,MATCH($D$60,AI_ho_so_che_do!$A$2:$A$21,0))=TRUE | G60: =ISNUMBER(FIND(";noGeneralTactic;",";"&INDEX(AI_ho_so_che_do!$O$2:$O$21,MATCH($D$60,AI_ho_so_che_do!$A$2:$A$21,0))&";")) | H60: =IF(AI_tuong!$B$12&""<>"",AI_tuong!$B$12,IF(AI_tuong!$B$4&""<>"",AI_tuong!$B$4,"balanced")) | I60: dispersal | J60: =OR($F$60,AND(AI_ho_so_anh_xa!$B$6="mode",OR(AI_ho_so_anh_xa!$C$6="Weekly",AI_ho_so_anh_xa!$C$6="Operation"))) | K60: TRUE | L60: =IF($J$60,$H$60,"balanced") | M60: dispersal | N60: =IF(OR($E$60="",$G$60),"balanced",IF(OR($E$60="*",ISNUMBER(FIND(";"&$L$60&";",";"&$E$60&";"))),$L$60,IF(ISNUMBER(FIND(";"&"balanced"&";",";"&$E$60&";")),"balanced",LEFT($E$60,FIND(";",$E$60&";")-1)))) | O60: dispersal | P60: =IF(OR($E$60="",$G$60),"KHONG_CHIEN_THUAT",IF(NOT($J$60),IF($H$60="balanced","GIU","CHE_DO_BO_QUA"),IF($N$60=$H$60,"GIU","HO_SO_GHI_DE"))) | Q60: Sim/AI/ConquestAi.P28.cs TickLayered + Sim/AI/Commander.cs AllowedTactic (goal.Escort, venn)
A61: goal.Escort/wolff | B61: goal.Escort | C61: wolff | D61: =AI_ho_so_anh_xa!$D$6 | E61: =INDEX(AI_ho_so_che_do!$B$2:$B$21,MATCH($D$61,AI_ho_so_che_do!$A$2:$A$21,0))&"" | F61: =INDEX(AI_ho_so_che_do!$P$2:$P$21,MATCH($D$61,AI_ho_so_che_do!$A$2:$A$21,0))=TRUE | G61: =ISNUMBER(FIND(";noGeneralTactic;",";"&INDEX(AI_ho_so_che_do!$O$2:$O$21,MATCH($D$61,AI_ho_so_che_do!$A$2:$A$21,0))&";")) | H61: =IF(AI_tuong!$B$13&""<>"",AI_tuong!$B$13,IF(AI_tuong!$B$4&""<>"",AI_tuong!$B$4,"balanced")) | I61: air_superiority | J61: =OR($F$61,AND(AI_ho_so_anh_xa!$B$6="mode",OR(AI_ho_so_anh_xa!$C$6="Weekly",AI_ho_so_anh_xa!$C$6="Operation"))) | K61: TRUE | L61: =IF($J$61,$H$61,"balanced") | M61: air_superiority | N61: =IF(OR($E$61="",$G$61),"balanced",IF(OR($E$61="*",ISNUMBER(FIND(";"&$L$61&";",";"&$E$61&";"))),$L$61,IF(ISNUMBER(FIND(";"&"balanced"&";",";"&$E$61&";")),"balanced",LEFT($E$61,FIND(";",$E$61&";")-1)))) | O61: air_superiority | P61: =IF(OR($E$61="",$G$61),"KHONG_CHIEN_THUAT",IF(NOT($J$61),IF($H$61="balanced","GIU","CHE_DO_BO_QUA"),IF($N$61=$H$61,"GIU","HO_SO_GHI_DE"))) | Q61: Sim/AI/ConquestAi.P28.cs TickLayered + Sim/AI/Commander.cs AllowedTactic (goal.Escort, wolff)
A62: goal.Evacuate/aurel | B62: goal.Evacuate | C62: aurel | D62: =AI_ho_so_anh_xa!$D$7 | E62: =INDEX(AI_ho_so_che_do!$B$2:$B$21,MATCH($D$62,AI_ho_so_che_do!$A$2:$A$21,0))&"" | F62: =INDEX(AI_ho_so_che_do!$P$2:$P$21,MATCH($D$62,AI_ho_so_che_do!$A$2:$A$21,0))=TRUE | G62: =ISNUMBER(FIND(";noGeneralTactic;",";"&INDEX(AI_ho_so_che_do!$O$2:$O$21,MATCH($D$62,AI_ho_so_che_do!$A$2:$A$21,0))&";")) | H62: =IF(AI_tuong!$B$2&""<>"",AI_tuong!$B$2,IF(AI_tuong!$B$4&""<>"",AI_tuong!$B$4,"balanced")) | I62: all_out | J62: =OR($F$62,AND(AI_ho_so_anh_xa!$B$7="mode",OR(AI_ho_so_anh_xa!$C$7="Weekly",AI_ho_so_anh_xa!$C$7="Operation"))) | K62: TRUE | L62: =IF($J$62,$H$62,"balanced") | M62: all_out | N62: =IF(OR($E$62="",$G$62),"balanced",IF(OR($E$62="*",ISNUMBER(FIND(";"&$L$62&";",";"&$E$62&";"))),$L$62,IF(ISNUMBER(FIND(";"&"balanced"&";",";"&$E$62&";")),"balanced",LEFT($E$62,FIND(";",$E$62&";")-1)))) | O62: all_out | P62: =IF(OR($E$62="",$G$62),"KHONG_CHIEN_THUAT",IF(NOT($J$62),IF($H$62="balanced","GIU","CHE_DO_BO_QUA"),IF($N$62=$H$62,"GIU","HO_SO_GHI_DE"))) | Q62: Sim/AI/ConquestAi.P28.cs TickLayered + Sim/AI/Commander.cs AllowedTactic (goal.Evacuate, aurel)
A63: goal.Evacuate/brandt | B63: goal.Evacuate | C63: brandt | D63: =AI_ho_so_anh_xa!$D$7 | E63: =INDEX(AI_ho_so_che_do!$B$2:$B$21,MATCH($D$63,AI_ho_so_che_do!$A$2:$A$21,0))&"" | F63: =INDEX(AI_ho_so_che_do!$P$2:$P$21,MATCH($D$63,AI_ho_so_che_do!$A$2:$A$21,0))=TRUE | G63: =ISNUMBER(FIND(";noGeneralTactic;",";"&INDEX(AI_ho_so_che_do!$O$2:$O$21,MATCH($D$63,AI_ho_so_che_do!$A$2:$A$21,0))&";")) | H63: =IF(AI_tuong!$B$3&""<>"",AI_tuong!$B$3,IF(AI_tuong!$B$4&""<>"",AI_tuong!$B$4,"balanced")) | I63: depth | J63: =OR($F$63,AND(AI_ho_so_anh_xa!$B$7="mode",OR(AI_ho_so_anh_xa!$C$7="Weekly",AI_ho_so_anh_xa!$C$7="Operation"))) | K63: TRUE | L63: =IF($J$63,$H$63,"balanced") | M63: depth | N63: =IF(OR($E$63="",$G$63),"balanced",IF(OR($E$63="*",ISNUMBER(FIND(";"&$L$63&";",";"&$E$63&";"))),$L$63,IF(ISNUMBER(FIND(";"&"balanced"&";",";"&$E$63&";")),"balanced",LEFT($E$63,FIND(";",$E$63&";")-1)))) | O63: depth | P63: =IF(OR($E$63="",$G$63),"KHONG_CHIEN_THUAT",IF(NOT($J$63),IF($H$63="balanced","GIU","CHE_DO_BO_QUA"),IF($N$63=$H$63,"GIU","HO_SO_GHI_DE"))) | Q63: Sim/AI/ConquestAi.P28.cs TickLayered + Sim/AI/Commander.cs AllowedTactic (goal.Evacuate, brandt)
A64: goal.Evacuate/default | B64: goal.Evacuate | C64: default | D64: =AI_ho_so_anh_xa!$D$7 | E64: =INDEX(AI_ho_so_che_do!$B$2:$B$21,MATCH($D$64,AI_ho_so_che_do!$A$2:$A$21,0))&"" | F64: =INDEX(AI_ho_so_che_do!$P$2:$P$21,MATCH($D$64,AI_ho_so_che_do!$A$2:$A$21,0))=TRUE | G64: =ISNUMBER(FIND(";noGeneralTactic;",";"&INDEX(AI_ho_so_che_do!$O$2:$O$21,MATCH($D$64,AI_ho_so_che_do!$A$2:$A$21,0))&";")) | H64: =IF(AI_tuong!$B$4&""<>"",AI_tuong!$B$4,IF(AI_tuong!$B$4&""<>"",AI_tuong!$B$4,"balanced")) | I64: balanced | J64: =OR($F$64,AND(AI_ho_so_anh_xa!$B$7="mode",OR(AI_ho_so_anh_xa!$C$7="Weekly",AI_ho_so_anh_xa!$C$7="Operation"))) | K64: TRUE | L64: =IF($J$64,$H$64,"balanced") | M64: balanced | N64: =IF(OR($E$64="",$G$64),"balanced",IF(OR($E$64="*",ISNUMBER(FIND(";"&$L$64&";",";"&$E$64&";"))),$L$64,IF(ISNUMBER(FIND(";"&"balanced"&";",";"&$E$64&";")),"balanced",LEFT($E$64,FIND(";",$E$64&";")-1)))) | O64: balanced | P64: =IF(OR($E$64="",$G$64),"KHONG_CHIEN_THUAT",IF(NOT($J$64),IF($H$64="balanced","GIU","CHE_DO_BO_QUA"),IF($N$64=$H$64,"GIU","HO_SO_GHI_DE"))) | Q64: Sim/AI/ConquestAi.P28.cs TickLayered + Sim/AI/Commander.cs AllowedTactic (goal.Evacuate, default)
A65: goal.Evacuate/hung | B65: goal.Evacuate | C65: hung | D65: =AI_ho_so_anh_xa!$D$7 | E65: =INDEX(AI_ho_so_che_do!$B$2:$B$21,MATCH($D$65,AI_ho_so_che_do!$A$2:$A$21,0))&"" | F65: =INDEX(AI_ho_so_che_do!$P$2:$P$21,MATCH($D$65,AI_ho_so_che_do!$A$2:$A$21,0))=TRUE | G65: =ISNUMBER(FIND(";noGeneralTactic;",";"&INDEX(AI_ho_so_che_do!$O$2:$O$21,MATCH($D$65,AI_ho_so_che_do!$A$2:$A$21,0))&";")) | H65: =IF(AI_tuong!$B$5&""<>"",AI_tuong!$B$5,IF(AI_tuong!$B$4&""<>"",AI_tuong!$B$4,"balanced")) | I65: balanced | J65: =OR($F$65,AND(AI_ho_so_anh_xa!$B$7="mode",OR(AI_ho_so_anh_xa!$C$7="Weekly",AI_ho_so_anh_xa!$C$7="Operation"))) | K65: TRUE | L65: =IF($J$65,$H$65,"balanced") | M65: balanced | N65: =IF(OR($E$65="",$G$65),"balanced",IF(OR($E$65="*",ISNUMBER(FIND(";"&$L$65&";",";"&$E$65&";"))),$L$65,IF(ISNUMBER(FIND(";"&"balanced"&";",";"&$E$65&";")),"balanced",LEFT($E$65,FIND(";",$E$65&";")-1)))) | O65: balanced | P65: =IF(OR($E$65="",$G$65),"KHONG_CHIEN_THUAT",IF(NOT($J$65),IF($H$65="balanced","GIU","CHE_DO_BO_QUA"),IF($N$65=$H$65,"GIU","HO_SO_GHI_DE"))) | Q65: Sim/AI/ConquestAi.P28.cs TickLayered + Sim/AI/Commander.cs AllowedTactic (goal.Evacuate, hung)
A66: goal.Evacuate/kessler | B66: goal.Evacuate | C66: kessler | D66: =AI_ho_so_anh_xa!$D$7 | E66: =INDEX(AI_ho_so_che_do!$B$2:$B$21,MATCH($D$66,AI_ho_so_che_do!$A$2:$A$21,0))&"" | F66: =INDEX(AI_ho_so_che_do!$P$2:$P$21,MATCH($D$66,AI_ho_so_che_do!$A$2:$A$21,0))=TRUE | G66: =ISNUMBER(FIND(";noGeneralTactic;",";"&INDEX(AI_ho_so_che_do!$O$2:$O$21,MATCH($D$66,AI_ho_so_che_do!$A$2:$A$21,0))&";")) | H66: =IF(AI_tuong!$B$6&""<>"",AI_tuong!$B$6,IF(AI_tuong!$B$4&""<>"",AI_tuong!$B$4,"balanced")) | I66: attrition | J66: =OR($F$66,AND(AI_ho_so_anh_xa!$B$7="mode",OR(AI_ho_so_anh_xa!$C$7="Weekly",AI_ho_so_anh_xa!$C$7="Operation"))) | K66: TRUE | L66: =IF($J$66,$H$66,"balanced") | M66: attrition | N66: =IF(OR($E$66="",$G$66),"balanced",IF(OR($E$66="*",ISNUMBER(FIND(";"&$L$66&";",";"&$E$66&";"))),$L$66,IF(ISNUMBER(FIND(";"&"balanced"&";",";"&$E$66&";")),"balanced",LEFT($E$66,FIND(";",$E$66&";")-1)))) | O66: attrition | P66: =IF(OR($E$66="",$G$66),"KHONG_CHIEN_THUAT",IF(NOT($J$66),IF($H$66="balanced","GIU","CHE_DO_BO_QUA"),IF($N$66=$H$66,"GIU","HO_SO_GHI_DE"))) | Q66: Sim/AI/ConquestAi.P28.cs TickLayered + Sim/AI/Commander.cs AllowedTactic (goal.Evacuate, kessler)
A67: goal.Evacuate/orlov | B67: goal.Evacuate | C67: orlov | D67: =AI_ho_so_anh_xa!$D$7 | E67: =INDEX(AI_ho_so_che_do!$B$2:$B$21,MATCH($D$67,AI_ho_so_che_do!$A$2:$A$21,0))&"" | F67: =INDEX(AI_ho_so_che_do!$P$2:$P$21,MATCH($D$67,AI_ho_so_che_do!$A$2:$A$21,0))=TRUE | G67: =ISNUMBER(FIND(";noGeneralTactic;",";"&INDEX(AI_ho_so_che_do!$O$2:$O$21,MATCH($D$67,AI_ho_so_che_do!$A$2:$A$21,0))&";")) | H67: =IF(AI_tuong!$B$7&""<>"",AI_tuong!$B$7,IF(AI_tuong!$B$4&""<>"",AI_tuong!$B$4,"balanced")) | I67: firepower | J67: =OR($F$67,AND(AI_ho_so_anh_xa!$B$7="mode",OR(AI_ho_so_anh_xa!$C$7="Weekly",AI_ho_so_anh_xa!$C$7="Operation"))) | K67: TRUE | L67: =IF($J$67,$H$67,"balanced") | M67: firepower | N67: =IF(OR($E$67="",$G$67),"balanced",IF(OR($E$67="*",ISNUMBER(FIND(";"&$L$67&";",";"&$E$67&";"))),$L$67,IF(ISNUMBER(FIND(";"&"balanced"&";",";"&$E$67&";")),"balanced",LEFT($E$67,FIND(";",$E$67&";")-1)))) | O67: firepower | P67: =IF(OR($E$67="",$G$67),"KHONG_CHIEN_THUAT",IF(NOT($J$67),IF($H$67="balanced","GIU","CHE_DO_BO_QUA"),IF($N$67=$H$67,"GIU","HO_SO_GHI_DE"))) | Q67: Sim/AI/ConquestAi.P28.cs TickLayered + Sim/AI/Commander.cs AllowedTactic (goal.Evacuate, orlov)
A68: goal.Evacuate/quaden | B68: goal.Evacuate | C68: quaden | D68: =AI_ho_so_anh_xa!$D$7 | E68: =INDEX(AI_ho_so_che_do!$B$2:$B$21,MATCH($D$68,AI_ho_so_che_do!$A$2:$A$21,0))&"" | F68: =INDEX(AI_ho_so_che_do!$P$2:$P$21,MATCH($D$68,AI_ho_so_che_do!$A$2:$A$21,0))=TRUE | G68: =ISNUMBER(FIND(";noGeneralTactic;",";"&INDEX(AI_ho_so_che_do!$O$2:$O$21,MATCH($D$68,AI_ho_so_che_do!$A$2:$A$21,0))&";")) | H68: =IF(AI_tuong!$B$8&""<>"",AI_tuong!$B$8,IF(AI_tuong!$B$4&""<>"",AI_tuong!$B$4,"balanced")) | I68: balanced | J68: =OR($F$68,AND(AI_ho_so_anh_xa!$B$7="mode",OR(AI_ho_so_anh_xa!$C$7="Weekly",AI_ho_so_anh_xa!$C$7="Operation"))) | K68: TRUE | L68: =IF($J$68,$H$68,"balanced") | M68: balanced | N68: =IF(OR($E$68="",$G$68),"balanced",IF(OR($E$68="*",ISNUMBER(FIND(";"&$L$68&";",";"&$E$68&";"))),$L$68,IF(ISNUMBER(FIND(";"&"balanced"&";",";"&$E$68&";")),"balanced",LEFT($E$68,FIND(";",$E$68&";")-1)))) | O68: balanced | P68: =IF(OR($E$68="",$G$68),"KHONG_CHIEN_THUAT",IF(NOT($J$68),IF($H$68="balanced","GIU","CHE_DO_BO_QUA"),IF($N$68=$H$68,"GIU","HO_SO_GHI_DE"))) | Q68: Sim/AI/ConquestAi.P28.cs TickLayered + Sim/AI/Commander.cs AllowedTactic (goal.Evacuate, quaden)
A69: goal.Evacuate/sen | B69: goal.Evacuate | C69: sen | D69: =AI_ho_so_anh_xa!$D$7 | E69: =INDEX(AI_ho_so_che_do!$B$2:$B$21,MATCH($D$69,AI_ho_so_che_do!$A$2:$A$21,0))&"" | F69: =INDEX(AI_ho_so_che_do!$P$2:$P$21,MATCH($D$69,AI_ho_so_che_do!$A$2:$A$21,0))=TRUE | G69: =ISNUMBER(FIND(";noGeneralTactic;",";"&INDEX(AI_ho_so_che_do!$O$2:$O$21,MATCH($D$69,AI_ho_so_che_do!$A$2:$A$21,0))&";")) | H69: =IF(AI_tuong!$B$9&""<>"",AI_tuong!$B$9,IF(AI_tuong!$B$4&""<>"",AI_tuong!$B$4,"balanced")) | I69: balanced | J69: =OR($F$69,AND(AI_ho_so_anh_xa!$B$7="mode",OR(AI_ho_so_anh_xa!$C$7="Weekly",AI_ho_so_anh_xa!$C$7="Operation"))) | K69: TRUE | L69: =IF($J$69,$H$69,"balanced") | M69: balanced | N69: =IF(OR($E$69="",$G$69),"balanced",IF(OR($E$69="*",ISNUMBER(FIND(";"&$L$69&";",";"&$E$69&";"))),$L$69,IF(ISNUMBER(FIND(";"&"balanced"&";",";"&$E$69&";")),"balanced",LEFT($E$69,FIND(";",$E$69&";")-1)))) | O69: balanced | P69: =IF(OR($E$69="",$G$69),"KHONG_CHIEN_THUAT",IF(NOT($J$69),IF($H$69="balanced","GIU","CHE_DO_BO_QUA"),IF($N$69=$H$69,"GIU","HO_SO_GHI_DE"))) | Q69: Sim/AI/ConquestAi.P28.cs TickLayered + Sim/AI/Commander.cs AllowedTactic (goal.Evacuate, sen)
A70: goal.Evacuate/thorne | B70: goal.Evacuate | C70: thorne | D70: =AI_ho_so_anh_xa!$D$7 | E70: =INDEX(AI_ho_so_che_do!$B$2:$B$21,MATCH($D$70,AI_ho_so_che_do!$A$2:$A$21,0))&"" | F70: =INDEX(AI_ho_so_che_do!$P$2:$P$21,MATCH($D$70,AI_ho_so_che_do!$A$2:$A$21,0))=TRUE | G70: =ISNUMBER(FIND(";noGeneralTactic;",";"&INDEX(AI_ho_so_che_do!$O$2:$O$21,MATCH($D$70,AI_ho_so_che_do!$A$2:$A$21,0))&";")) | H70: =IF(AI_tuong!$B$10&""<>"",AI_tuong!$B$10,IF(AI_tuong!$B$4&""<>"",AI_tuong!$B$4,"balanced")) | I70: balanced | J70: =OR($F$70,AND(AI_ho_so_anh_xa!$B$7="mode",OR(AI_ho_so_anh_xa!$C$7="Weekly",AI_ho_so_anh_xa!$C$7="Operation"))) | K70: TRUE | L70: =IF($J$70,$H$70,"balanced") | M70: balanced | N70: =IF(OR($E$70="",$G$70),"balanced",IF(OR($E$70="*",ISNUMBER(FIND(";"&$L$70&";",";"&$E$70&";"))),$L$70,IF(ISNUMBER(FIND(";"&"balanced"&";",";"&$E$70&";")),"balanced",LEFT($E$70,FIND(";",$E$70&";")-1)))) | O70: balanced | P70: =IF(OR($E$70="",$G$70),"KHONG_CHIEN_THUAT",IF(NOT($J$70),IF($H$70="balanced","GIU","CHE_DO_BO_QUA"),IF($N$70=$H$70,"GIU","HO_SO_GHI_DE"))) | Q70: Sim/AI/ConquestAi.P28.cs TickLayered + Sim/AI/Commander.cs AllowedTactic (goal.Evacuate, thorne)
A71: goal.Evacuate/varga | B71: goal.Evacuate | C71: varga | D71: =AI_ho_so_anh_xa!$D$7 | E71: =INDEX(AI_ho_so_che_do!$B$2:$B$21,MATCH($D$71,AI_ho_so_che_do!$A$2:$A$21,0))&"" | F71: =INDEX(AI_ho_so_che_do!$P$2:$P$21,MATCH($D$71,AI_ho_so_che_do!$A$2:$A$21,0))=TRUE | G71: =ISNUMBER(FIND(";noGeneralTactic;",";"&INDEX(AI_ho_so_che_do!$O$2:$O$21,MATCH($D$71,AI_ho_so_che_do!$A$2:$A$21,0))&";")) | H71: =IF(AI_tuong!$B$11&""<>"",AI_tuong!$B$11,IF(AI_tuong!$B$4&""<>"",AI_tuong!$B$4,"balanced")) | I71: breakthrough | J71: =OR($F$71,AND(AI_ho_so_anh_xa!$B$7="mode",OR(AI_ho_so_anh_xa!$C$7="Weekly",AI_ho_so_anh_xa!$C$7="Operation"))) | K71: TRUE | L71: =IF($J$71,$H$71,"balanced") | M71: breakthrough | N71: =IF(OR($E$71="",$G$71),"balanced",IF(OR($E$71="*",ISNUMBER(FIND(";"&$L$71&";",";"&$E$71&";"))),$L$71,IF(ISNUMBER(FIND(";"&"balanced"&";",";"&$E$71&";")),"balanced",LEFT($E$71,FIND(";",$E$71&";")-1)))) | O71: breakthrough | P71: =IF(OR($E$71="",$G$71),"KHONG_CHIEN_THUAT",IF(NOT($J$71),IF($H$71="balanced","GIU","CHE_DO_BO_QUA"),IF($N$71=$H$71,"GIU","HO_SO_GHI_DE"))) | Q71: Sim/AI/ConquestAi.P28.cs TickLayered + Sim/AI/Commander.cs AllowedTactic (goal.Evacuate, varga)
A72: goal.Evacuate/venn | B72: goal.Evacuate | C72: venn | D72: =AI_ho_so_anh_xa!$D$7 | E72: =INDEX(AI_ho_so_che_do!$B$2:$B$21,MATCH($D$72,AI_ho_so_che_do!$A$2:$A$21,0))&"" | F72: =INDEX(AI_ho_so_che_do!$P$2:$P$21,MATCH($D$72,AI_ho_so_che_do!$A$2:$A$21,0))=TRUE | G72: =ISNUMBER(FIND(";noGeneralTactic;",";"&INDEX(AI_ho_so_che_do!$O$2:$O$21,MATCH($D$72,AI_ho_so_che_do!$A$2:$A$21,0))&";")) | H72: =IF(AI_tuong!$B$12&""<>"",AI_tuong!$B$12,IF(AI_tuong!$B$4&""<>"",AI_tuong!$B$4,"balanced")) | I72: dispersal | J72: =OR($F$72,AND(AI_ho_so_anh_xa!$B$7="mode",OR(AI_ho_so_anh_xa!$C$7="Weekly",AI_ho_so_anh_xa!$C$7="Operation"))) | K72: TRUE | L72: =IF($J$72,$H$72,"balanced") | M72: dispersal | N72: =IF(OR($E$72="",$G$72),"balanced",IF(OR($E$72="*",ISNUMBER(FIND(";"&$L$72&";",";"&$E$72&";"))),$L$72,IF(ISNUMBER(FIND(";"&"balanced"&";",";"&$E$72&";")),"balanced",LEFT($E$72,FIND(";",$E$72&";")-1)))) | O72: dispersal | P72: =IF(OR($E$72="",$G$72),"KHONG_CHIEN_THUAT",IF(NOT($J$72),IF($H$72="balanced","GIU","CHE_DO_BO_QUA"),IF($N$72=$H$72,"GIU","HO_SO_GHI_DE"))) | Q72: Sim/AI/ConquestAi.P28.cs TickLayered + Sim/AI/Commander.cs AllowedTactic (goal.Evacuate, venn)
A73: goal.Evacuate/wolff | B73: goal.Evacuate | C73: wolff | D73: =AI_ho_so_anh_xa!$D$7 | E73: =INDEX(AI_ho_so_che_do!$B$2:$B$21,MATCH($D$73,AI_ho_so_che_do!$A$2:$A$21,0))&"" | F73: =INDEX(AI_ho_so_che_do!$P$2:$P$21,MATCH($D$73,AI_ho_so_che_do!$A$2:$A$21,0))=TRUE | G73: =ISNUMBER(FIND(";noGeneralTactic;",";"&INDEX(AI_ho_so_che_do!$O$2:$O$21,MATCH($D$73,AI_ho_so_che_do!$A$2:$A$21,0))&";")) | H73: =IF(AI_tuong!$B$13&""<>"",AI_tuong!$B$13,IF(AI_tuong!$B$4&""<>"",AI_tuong!$B$4,"balanced")) | I73: air_superiority | J73: =OR($F$73,AND(AI_ho_so_anh_xa!$B$7="mode",OR(AI_ho_so_anh_xa!$C$7="Weekly",AI_ho_so_anh_xa!$C$7="Operation"))) | K73: TRUE | L73: =IF($J$73,$H$73,"balanced") | M73: air_superiority | N73: =IF(OR($E$73="",$G$73),"balanced",IF(OR($E$73="*",ISNUMBER(FIND(";"&$L$73&";",";"&$E$73&";"))),$L$73,IF(ISNUMBER(FIND(";"&"balanced"&";",";"&$E$73&";")),"balanced",LEFT($E$73,FIND(";",$E$73&";")-1)))) | O73: air_superiority | P73: =IF(OR($E$73="",$G$73),"KHONG_CHIEN_THUAT",IF(NOT($J$73),IF($H$73="balanced","GIU","CHE_DO_BO_QUA"),IF($N$73=$H$73,"GIU","HO_SO_GHI_DE"))) | Q73: Sim/AI/ConquestAi.P28.cs TickLayered + Sim/AI/Commander.cs AllowedTactic (goal.Evacuate, wolff)
A74: goal.Hold/aurel | B74: goal.Hold | C74: aurel | D74: =AI_ho_so_anh_xa!$D$8 | E74: =INDEX(AI_ho_so_che_do!$B$2:$B$21,MATCH($D$74,AI_ho_so_che_do!$A$2:$A$21,0))&"" | F74: =INDEX(AI_ho_so_che_do!$P$2:$P$21,MATCH($D$74,AI_ho_so_che_do!$A$2:$A$21,0))=TRUE | G74: =ISNUMBER(FIND(";noGeneralTactic;",";"&INDEX(AI_ho_so_che_do!$O$2:$O$21,MATCH($D$74,AI_ho_so_che_do!$A$2:$A$21,0))&";")) | H74: =IF(AI_tuong!$B$2&""<>"",AI_tuong!$B$2,IF(AI_tuong!$B$4&""<>"",AI_tuong!$B$4,"balanced")) | I74: all_out | J74: =OR($F$74,AND(AI_ho_so_anh_xa!$B$8="mode",OR(AI_ho_so_anh_xa!$C$8="Weekly",AI_ho_so_anh_xa!$C$8="Operation"))) | K74: TRUE | L74: =IF($J$74,$H$74,"balanced") | M74: all_out | N74: =IF(OR($E$74="",$G$74),"balanced",IF(OR($E$74="*",ISNUMBER(FIND(";"&$L$74&";",";"&$E$74&";"))),$L$74,IF(ISNUMBER(FIND(";"&"balanced"&";",";"&$E$74&";")),"balanced",LEFT($E$74,FIND(";",$E$74&";")-1)))) | O74: all_out | P74: =IF(OR($E$74="",$G$74),"KHONG_CHIEN_THUAT",IF(NOT($J$74),IF($H$74="balanced","GIU","CHE_DO_BO_QUA"),IF($N$74=$H$74,"GIU","HO_SO_GHI_DE"))) | Q74: Sim/AI/ConquestAi.P28.cs TickLayered + Sim/AI/Commander.cs AllowedTactic (goal.Hold, aurel)
A75: goal.Hold/brandt | B75: goal.Hold | C75: brandt | D75: =AI_ho_so_anh_xa!$D$8 | E75: =INDEX(AI_ho_so_che_do!$B$2:$B$21,MATCH($D$75,AI_ho_so_che_do!$A$2:$A$21,0))&"" | F75: =INDEX(AI_ho_so_che_do!$P$2:$P$21,MATCH($D$75,AI_ho_so_che_do!$A$2:$A$21,0))=TRUE | G75: =ISNUMBER(FIND(";noGeneralTactic;",";"&INDEX(AI_ho_so_che_do!$O$2:$O$21,MATCH($D$75,AI_ho_so_che_do!$A$2:$A$21,0))&";")) | H75: =IF(AI_tuong!$B$3&""<>"",AI_tuong!$B$3,IF(AI_tuong!$B$4&""<>"",AI_tuong!$B$4,"balanced")) | I75: depth | J75: =OR($F$75,AND(AI_ho_so_anh_xa!$B$8="mode",OR(AI_ho_so_anh_xa!$C$8="Weekly",AI_ho_so_anh_xa!$C$8="Operation"))) | K75: TRUE | L75: =IF($J$75,$H$75,"balanced") | M75: depth | N75: =IF(OR($E$75="",$G$75),"balanced",IF(OR($E$75="*",ISNUMBER(FIND(";"&$L$75&";",";"&$E$75&";"))),$L$75,IF(ISNUMBER(FIND(";"&"balanced"&";",";"&$E$75&";")),"balanced",LEFT($E$75,FIND(";",$E$75&";")-1)))) | O75: depth | P75: =IF(OR($E$75="",$G$75),"KHONG_CHIEN_THUAT",IF(NOT($J$75),IF($H$75="balanced","GIU","CHE_DO_BO_QUA"),IF($N$75=$H$75,"GIU","HO_SO_GHI_DE"))) | Q75: Sim/AI/ConquestAi.P28.cs TickLayered + Sim/AI/Commander.cs AllowedTactic (goal.Hold, brandt)
A76: goal.Hold/default | B76: goal.Hold | C76: default | D76: =AI_ho_so_anh_xa!$D$8 | E76: =INDEX(AI_ho_so_che_do!$B$2:$B$21,MATCH($D$76,AI_ho_so_che_do!$A$2:$A$21,0))&"" | F76: =INDEX(AI_ho_so_che_do!$P$2:$P$21,MATCH($D$76,AI_ho_so_che_do!$A$2:$A$21,0))=TRUE | G76: =ISNUMBER(FIND(";noGeneralTactic;",";"&INDEX(AI_ho_so_che_do!$O$2:$O$21,MATCH($D$76,AI_ho_so_che_do!$A$2:$A$21,0))&";")) | H76: =IF(AI_tuong!$B$4&""<>"",AI_tuong!$B$4,IF(AI_tuong!$B$4&""<>"",AI_tuong!$B$4,"balanced")) | I76: balanced | J76: =OR($F$76,AND(AI_ho_so_anh_xa!$B$8="mode",OR(AI_ho_so_anh_xa!$C$8="Weekly",AI_ho_so_anh_xa!$C$8="Operation"))) | K76: TRUE | L76: =IF($J$76,$H$76,"balanced") | M76: balanced | N76: =IF(OR($E$76="",$G$76),"balanced",IF(OR($E$76="*",ISNUMBER(FIND(";"&$L$76&";",";"&$E$76&";"))),$L$76,IF(ISNUMBER(FIND(";"&"balanced"&";",";"&$E$76&";")),"balanced",LEFT($E$76,FIND(";",$E$76&";")-1)))) | O76: balanced | P76: =IF(OR($E$76="",$G$76),"KHONG_CHIEN_THUAT",IF(NOT($J$76),IF($H$76="balanced","GIU","CHE_DO_BO_QUA"),IF($N$76=$H$76,"GIU","HO_SO_GHI_DE"))) | Q76: Sim/AI/ConquestAi.P28.cs TickLayered + Sim/AI/Commander.cs AllowedTactic (goal.Hold, default)
A77: goal.Hold/hung | B77: goal.Hold | C77: hung | D77: =AI_ho_so_anh_xa!$D$8 | E77: =INDEX(AI_ho_so_che_do!$B$2:$B$21,MATCH($D$77,AI_ho_so_che_do!$A$2:$A$21,0))&"" | F77: =INDEX(AI_ho_so_che_do!$P$2:$P$21,MATCH($D$77,AI_ho_so_che_do!$A$2:$A$21,0))=TRUE | G77: =ISNUMBER(FIND(";noGeneralTactic;",";"&INDEX(AI_ho_so_che_do!$O$2:$O$21,MATCH($D$77,AI_ho_so_che_do!$A$2:$A$21,0))&";")) | H77: =IF(AI_tuong!$B$5&""<>"",AI_tuong!$B$5,IF(AI_tuong!$B$4&""<>"",AI_tuong!$B$4,"balanced")) | I77: balanced | J77: =OR($F$77,AND(AI_ho_so_anh_xa!$B$8="mode",OR(AI_ho_so_anh_xa!$C$8="Weekly",AI_ho_so_anh_xa!$C$8="Operation"))) | K77: TRUE | L77: =IF($J$77,$H$77,"balanced") | M77: balanced | N77: =IF(OR($E$77="",$G$77),"balanced",IF(OR($E$77="*",ISNUMBER(FIND(";"&$L$77&";",";"&$E$77&";"))),$L$77,IF(ISNUMBER(FIND(";"&"balanced"&";",";"&$E$77&";")),"balanced",LEFT($E$77,FIND(";",$E$77&";")-1)))) | O77: balanced | P77: =IF(OR($E$77="",$G$77),"KHONG_CHIEN_THUAT",IF(NOT($J$77),IF($H$77="balanced","GIU","CHE_DO_BO_QUA"),IF($N$77=$H$77,"GIU","HO_SO_GHI_DE"))) | Q77: Sim/AI/ConquestAi.P28.cs TickLayered + Sim/AI/Commander.cs AllowedTactic (goal.Hold, hung)
A78: goal.Hold/kessler | B78: goal.Hold | C78: kessler | D78: =AI_ho_so_anh_xa!$D$8 | E78: =INDEX(AI_ho_so_che_do!$B$2:$B$21,MATCH($D$78,AI_ho_so_che_do!$A$2:$A$21,0))&"" | F78: =INDEX(AI_ho_so_che_do!$P$2:$P$21,MATCH($D$78,AI_ho_so_che_do!$A$2:$A$21,0))=TRUE | G78: =ISNUMBER(FIND(";noGeneralTactic;",";"&INDEX(AI_ho_so_che_do!$O$2:$O$21,MATCH($D$78,AI_ho_so_che_do!$A$2:$A$21,0))&";")) | H78: =IF(AI_tuong!$B$6&""<>"",AI_tuong!$B$6,IF(AI_tuong!$B$4&""<>"",AI_tuong!$B$4,"balanced")) | I78: attrition | J78: =OR($F$78,AND(AI_ho_so_anh_xa!$B$8="mode",OR(AI_ho_so_anh_xa!$C$8="Weekly",AI_ho_so_anh_xa!$C$8="Operation"))) | K78: TRUE | L78: =IF($J$78,$H$78,"balanced") | M78: attrition | N78: =IF(OR($E$78="",$G$78),"balanced",IF(OR($E$78="*",ISNUMBER(FIND(";"&$L$78&";",";"&$E$78&";"))),$L$78,IF(ISNUMBER(FIND(";"&"balanced"&";",";"&$E$78&";")),"balanced",LEFT($E$78,FIND(";",$E$78&";")-1)))) | O78: attrition | P78: =IF(OR($E$78="",$G$78),"KHONG_CHIEN_THUAT",IF(NOT($J$78),IF($H$78="balanced","GIU","CHE_DO_BO_QUA"),IF($N$78=$H$78,"GIU","HO_SO_GHI_DE"))) | Q78: Sim/AI/ConquestAi.P28.cs TickLayered + Sim/AI/Commander.cs AllowedTactic (goal.Hold, kessler)
A79: goal.Hold/orlov | B79: goal.Hold | C79: orlov | D79: =AI_ho_so_anh_xa!$D$8 | E79: =INDEX(AI_ho_so_che_do!$B$2:$B$21,MATCH($D$79,AI_ho_so_che_do!$A$2:$A$21,0))&"" | F79: =INDEX(AI_ho_so_che_do!$P$2:$P$21,MATCH($D$79,AI_ho_so_che_do!$A$2:$A$21,0))=TRUE | G79: =ISNUMBER(FIND(";noGeneralTactic;",";"&INDEX(AI_ho_so_che_do!$O$2:$O$21,MATCH($D$79,AI_ho_so_che_do!$A$2:$A$21,0))&";")) | H79: =IF(AI_tuong!$B$7&""<>"",AI_tuong!$B$7,IF(AI_tuong!$B$4&""<>"",AI_tuong!$B$4,"balanced")) | I79: firepower | J79: =OR($F$79,AND(AI_ho_so_anh_xa!$B$8="mode",OR(AI_ho_so_anh_xa!$C$8="Weekly",AI_ho_so_anh_xa!$C$8="Operation"))) | K79: TRUE | L79: =IF($J$79,$H$79,"balanced") | M79: firepower | N79: =IF(OR($E$79="",$G$79),"balanced",IF(OR($E$79="*",ISNUMBER(FIND(";"&$L$79&";",";"&$E$79&";"))),$L$79,IF(ISNUMBER(FIND(";"&"balanced"&";",";"&$E$79&";")),"balanced",LEFT($E$79,FIND(";",$E$79&";")-1)))) | O79: firepower | P79: =IF(OR($E$79="",$G$79),"KHONG_CHIEN_THUAT",IF(NOT($J$79),IF($H$79="balanced","GIU","CHE_DO_BO_QUA"),IF($N$79=$H$79,"GIU","HO_SO_GHI_DE"))) | Q79: Sim/AI/ConquestAi.P28.cs TickLayered + Sim/AI/Commander.cs AllowedTactic (goal.Hold, orlov)
A80: goal.Hold/quaden | B80: goal.Hold | C80: quaden | D80: =AI_ho_so_anh_xa!$D$8 | E80: =INDEX(AI_ho_so_che_do!$B$2:$B$21,MATCH($D$80,AI_ho_so_che_do!$A$2:$A$21,0))&"" | F80: =INDEX(AI_ho_so_che_do!$P$2:$P$21,MATCH($D$80,AI_ho_so_che_do!$A$2:$A$21,0))=TRUE | G80: =ISNUMBER(FIND(";noGeneralTactic;",";"&INDEX(AI_ho_so_che_do!$O$2:$O$21,MATCH($D$80,AI_ho_so_che_do!$A$2:$A$21,0))&";")) | H80: =IF(AI_tuong!$B$8&""<>"",AI_tuong!$B$8,IF(AI_tuong!$B$4&""<>"",AI_tuong!$B$4,"balanced")) | I80: balanced | J80: =OR($F$80,AND(AI_ho_so_anh_xa!$B$8="mode",OR(AI_ho_so_anh_xa!$C$8="Weekly",AI_ho_so_anh_xa!$C$8="Operation"))) | K80: TRUE | L80: =IF($J$80,$H$80,"balanced") | M80: balanced | N80: =IF(OR($E$80="",$G$80),"balanced",IF(OR($E$80="*",ISNUMBER(FIND(";"&$L$80&";",";"&$E$80&";"))),$L$80,IF(ISNUMBER(FIND(";"&"balanced"&";",";"&$E$80&";")),"balanced",LEFT($E$80,FIND(";",$E$80&";")-1)))) | O80: balanced | P80: =IF(OR($E$80="",$G$80),"KHONG_CHIEN_THUAT",IF(NOT($J$80),IF($H$80="balanced","GIU","CHE_DO_BO_QUA"),IF($N$80=$H$80,"GIU","HO_SO_GHI_DE"))) | Q80: Sim/AI/ConquestAi.P28.cs TickLayered + Sim/AI/Commander.cs AllowedTactic (goal.Hold, quaden)
A81: goal.Hold/sen | B81: goal.Hold | C81: sen | D81: =AI_ho_so_anh_xa!$D$8 | E81: =INDEX(AI_ho_so_che_do!$B$2:$B$21,MATCH($D$81,AI_ho_so_che_do!$A$2:$A$21,0))&"" | F81: =INDEX(AI_ho_so_che_do!$P$2:$P$21,MATCH($D$81,AI_ho_so_che_do!$A$2:$A$21,0))=TRUE | G81: =ISNUMBER(FIND(";noGeneralTactic;",";"&INDEX(AI_ho_so_che_do!$O$2:$O$21,MATCH($D$81,AI_ho_so_che_do!$A$2:$A$21,0))&";")) | H81: =IF(AI_tuong!$B$9&""<>"",AI_tuong!$B$9,IF(AI_tuong!$B$4&""<>"",AI_tuong!$B$4,"balanced")) | I81: balanced | J81: =OR($F$81,AND(AI_ho_so_anh_xa!$B$8="mode",OR(AI_ho_so_anh_xa!$C$8="Weekly",AI_ho_so_anh_xa!$C$8="Operation"))) | K81: TRUE | L81: =IF($J$81,$H$81,"balanced") | M81: balanced | N81: =IF(OR($E$81="",$G$81),"balanced",IF(OR($E$81="*",ISNUMBER(FIND(";"&$L$81&";",";"&$E$81&";"))),$L$81,IF(ISNUMBER(FIND(";"&"balanced"&";",";"&$E$81&";")),"balanced",LEFT($E$81,FIND(";",$E$81&";")-1)))) | O81: balanced | P81: =IF(OR($E$81="",$G$81),"KHONG_CHIEN_THUAT",IF(NOT($J$81),IF($H$81="balanced","GIU","CHE_DO_BO_QUA"),IF($N$81=$H$81,"GIU","HO_SO_GHI_DE"))) | Q81: Sim/AI/ConquestAi.P28.cs TickLayered + Sim/AI/Commander.cs AllowedTactic (goal.Hold, sen)
A82: goal.Hold/thorne | B82: goal.Hold | C82: thorne | D82: =AI_ho_so_anh_xa!$D$8 | E82: =INDEX(AI_ho_so_che_do!$B$2:$B$21,MATCH($D$82,AI_ho_so_che_do!$A$2:$A$21,0))&"" | F82: =INDEX(AI_ho_so_che_do!$P$2:$P$21,MATCH($D$82,AI_ho_so_che_do!$A$2:$A$21,0))=TRUE | G82: =ISNUMBER(FIND(";noGeneralTactic;",";"&INDEX(AI_ho_so_che_do!$O$2:$O$21,MATCH($D$82,AI_ho_so_che_do!$A$2:$A$21,0))&";")) | H82: =IF(AI_tuong!$B$10&""<>"",AI_tuong!$B$10,IF(AI_tuong!$B$4&""<>"",AI_tuong!$B$4,"balanced")) | I82: balanced | J82: =OR($F$82,AND(AI_ho_so_anh_xa!$B$8="mode",OR(AI_ho_so_anh_xa!$C$8="Weekly",AI_ho_so_anh_xa!$C$8="Operation"))) | K82: TRUE | L82: =IF($J$82,$H$82,"balanced") | M82: balanced | N82: =IF(OR($E$82="",$G$82),"balanced",IF(OR($E$82="*",ISNUMBER(FIND(";"&$L$82&";",";"&$E$82&";"))),$L$82,IF(ISNUMBER(FIND(";"&"balanced"&";",";"&$E$82&";")),"balanced",LEFT($E$82,FIND(";",$E$82&";")-1)))) | O82: balanced | P82: =IF(OR($E$82="",$G$82),"KHONG_CHIEN_THUAT",IF(NOT($J$82),IF($H$82="balanced","GIU","CHE_DO_BO_QUA"),IF($N$82=$H$82,"GIU","HO_SO_GHI_DE"))) | Q82: Sim/AI/ConquestAi.P28.cs TickLayered + Sim/AI/Commander.cs AllowedTactic (goal.Hold, thorne)
A83: goal.Hold/varga | B83: goal.Hold | C83: varga | D83: =AI_ho_so_anh_xa!$D$8 | E83: =INDEX(AI_ho_so_che_do!$B$2:$B$21,MATCH($D$83,AI_ho_so_che_do!$A$2:$A$21,0))&"" | F83: =INDEX(AI_ho_so_che_do!$P$2:$P$21,MATCH($D$83,AI_ho_so_che_do!$A$2:$A$21,0))=TRUE | G83: =ISNUMBER(FIND(";noGeneralTactic;",";"&INDEX(AI_ho_so_che_do!$O$2:$O$21,MATCH($D$83,AI_ho_so_che_do!$A$2:$A$21,0))&";")) | H83: =IF(AI_tuong!$B$11&""<>"",AI_tuong!$B$11,IF(AI_tuong!$B$4&""<>"",AI_tuong!$B$4,"balanced")) | I83: breakthrough | J83: =OR($F$83,AND(AI_ho_so_anh_xa!$B$8="mode",OR(AI_ho_so_anh_xa!$C$8="Weekly",AI_ho_so_anh_xa!$C$8="Operation"))) | K83: TRUE | L83: =IF($J$83,$H$83,"balanced") | M83: breakthrough | N83: =IF(OR($E$83="",$G$83),"balanced",IF(OR($E$83="*",ISNUMBER(FIND(";"&$L$83&";",";"&$E$83&";"))),$L$83,IF(ISNUMBER(FIND(";"&"balanced"&";",";"&$E$83&";")),"balanced",LEFT($E$83,FIND(";",$E$83&";")-1)))) | O83: breakthrough | P83: =IF(OR($E$83="",$G$83),"KHONG_CHIEN_THUAT",IF(NOT($J$83),IF($H$83="balanced","GIU","CHE_DO_BO_QUA"),IF($N$83=$H$83,"GIU","HO_SO_GHI_DE"))) | Q83: Sim/AI/ConquestAi.P28.cs TickLayered + Sim/AI/Commander.cs AllowedTactic (goal.Hold, varga)
A84: goal.Hold/venn | B84: goal.Hold | C84: venn | D84: =AI_ho_so_anh_xa!$D$8 | E84: =INDEX(AI_ho_so_che_do!$B$2:$B$21,MATCH($D$84,AI_ho_so_che_do!$A$2:$A$21,0))&"" | F84: =INDEX(AI_ho_so_che_do!$P$2:$P$21,MATCH($D$84,AI_ho_so_che_do!$A$2:$A$21,0))=TRUE | G84: =ISNUMBER(FIND(";noGeneralTactic;",";"&INDEX(AI_ho_so_che_do!$O$2:$O$21,MATCH($D$84,AI_ho_so_che_do!$A$2:$A$21,0))&";")) | H84: =IF(AI_tuong!$B$12&""<>"",AI_tuong!$B$12,IF(AI_tuong!$B$4&""<>"",AI_tuong!$B$4,"balanced")) | I84: dispersal | J84: =OR($F$84,AND(AI_ho_so_anh_xa!$B$8="mode",OR(AI_ho_so_anh_xa!$C$8="Weekly",AI_ho_so_anh_xa!$C$8="Operation"))) | K84: TRUE | L84: =IF($J$84,$H$84,"balanced") | M84: dispersal | N84: =IF(OR($E$84="",$G$84),"balanced",IF(OR($E$84="*",ISNUMBER(FIND(";"&$L$84&";",";"&$E$84&";"))),$L$84,IF(ISNUMBER(FIND(";"&"balanced"&";",";"&$E$84&";")),"balanced",LEFT($E$84,FIND(";",$E$84&";")-1)))) | O84: dispersal | P84: =IF(OR($E$84="",$G$84),"KHONG_CHIEN_THUAT",IF(NOT($J$84),IF($H$84="balanced","GIU","CHE_DO_BO_QUA"),IF($N$84=$H$84,"GIU","HO_SO_GHI_DE"))) | Q84: Sim/AI/ConquestAi.P28.cs TickLayered + Sim/AI/Commander.cs AllowedTactic (goal.Hold, venn)
A85: goal.Hold/wolff | B85: goal.Hold | C85: wolff | D85: =AI_ho_so_anh_xa!$D$8 | E85: =INDEX(AI_ho_so_che_do!$B$2:$B$21,MATCH($D$85,AI_ho_so_che_do!$A$2:$A$21,0))&"" | F85: =INDEX(AI_ho_so_che_do!$P$2:$P$21,MATCH($D$85,AI_ho_so_che_do!$A$2:$A$21,0))=TRUE | G85: =ISNUMBER(FIND(";noGeneralTactic;",";"&INDEX(AI_ho_so_che_do!$O$2:$O$21,MATCH($D$85,AI_ho_so_che_do!$A$2:$A$21,0))&";")) | H85: =IF(AI_tuong!$B$13&""<>"",AI_tuong!$B$13,IF(AI_tuong!$B$4&""<>"",AI_tuong!$B$4,"balanced")) | I85: air_superiority | J85: =OR($F$85,AND(AI_ho_so_anh_xa!$B$8="mode",OR(AI_ho_so_anh_xa!$C$8="Weekly",AI_ho_so_anh_xa!$C$8="Operation"))) | K85: TRUE | L85: =IF($J$85,$H$85,"balanced") | M85: air_superiority | N85: =IF(OR($E$85="",$G$85),"balanced",IF(OR($E$85="*",ISNUMBER(FIND(";"&$L$85&";",";"&$E$85&";"))),$L$85,IF(ISNUMBER(FIND(";"&"balanced"&";",";"&$E$85&";")),"balanced",LEFT($E$85,FIND(";",$E$85&";")-1)))) | O85: air_superiority | P85: =IF(OR($E$85="",$G$85),"KHONG_CHIEN_THUAT",IF(NOT($J$85),IF($H$85="balanced","GIU","CHE_DO_BO_QUA"),IF($N$85=$H$85,"GIU","HO_SO_GHI_DE"))) | Q85: Sim/AI/ConquestAi.P28.cs TickLayered + Sim/AI/Commander.cs AllowedTactic (goal.Hold, wolff)
A86: goal.Hunt/aurel | B86: goal.Hunt | C86: aurel | D86: =AI_ho_so_anh_xa!$D$9 | E86: =INDEX(AI_ho_so_che_do!$B$2:$B$21,MATCH($D$86,AI_ho_so_che_do!$A$2:$A$21,0))&"" | F86: =INDEX(AI_ho_so_che_do!$P$2:$P$21,MATCH($D$86,AI_ho_so_che_do!$A$2:$A$21,0))=TRUE | G86: =ISNUMBER(FIND(";noGeneralTactic;",";"&INDEX(AI_ho_so_che_do!$O$2:$O$21,MATCH($D$86,AI_ho_so_che_do!$A$2:$A$21,0))&";")) | H86: =IF(AI_tuong!$B$2&""<>"",AI_tuong!$B$2,IF(AI_tuong!$B$4&""<>"",AI_tuong!$B$4,"balanced")) | I86: all_out | J86: =OR($F$86,AND(AI_ho_so_anh_xa!$B$9="mode",OR(AI_ho_so_anh_xa!$C$9="Weekly",AI_ho_so_anh_xa!$C$9="Operation"))) | K86: TRUE | L86: =IF($J$86,$H$86,"balanced") | M86: all_out | N86: =IF(OR($E$86="",$G$86),"balanced",IF(OR($E$86="*",ISNUMBER(FIND(";"&$L$86&";",";"&$E$86&";"))),$L$86,IF(ISNUMBER(FIND(";"&"balanced"&";",";"&$E$86&";")),"balanced",LEFT($E$86,FIND(";",$E$86&";")-1)))) | O86: all_out | P86: =IF(OR($E$86="",$G$86),"KHONG_CHIEN_THUAT",IF(NOT($J$86),IF($H$86="balanced","GIU","CHE_DO_BO_QUA"),IF($N$86=$H$86,"GIU","HO_SO_GHI_DE"))) | Q86: Sim/AI/ConquestAi.P28.cs TickLayered + Sim/AI/Commander.cs AllowedTactic (goal.Hunt, aurel)
A87: goal.Hunt/brandt | B87: goal.Hunt | C87: brandt | D87: =AI_ho_so_anh_xa!$D$9 | E87: =INDEX(AI_ho_so_che_do!$B$2:$B$21,MATCH($D$87,AI_ho_so_che_do!$A$2:$A$21,0))&"" | F87: =INDEX(AI_ho_so_che_do!$P$2:$P$21,MATCH($D$87,AI_ho_so_che_do!$A$2:$A$21,0))=TRUE | G87: =ISNUMBER(FIND(";noGeneralTactic;",";"&INDEX(AI_ho_so_che_do!$O$2:$O$21,MATCH($D$87,AI_ho_so_che_do!$A$2:$A$21,0))&";")) | H87: =IF(AI_tuong!$B$3&""<>"",AI_tuong!$B$3,IF(AI_tuong!$B$4&""<>"",AI_tuong!$B$4,"balanced")) | I87: depth | J87: =OR($F$87,AND(AI_ho_so_anh_xa!$B$9="mode",OR(AI_ho_so_anh_xa!$C$9="Weekly",AI_ho_so_anh_xa!$C$9="Operation"))) | K87: TRUE | L87: =IF($J$87,$H$87,"balanced") | M87: depth | N87: =IF(OR($E$87="",$G$87),"balanced",IF(OR($E$87="*",ISNUMBER(FIND(";"&$L$87&";",";"&$E$87&";"))),$L$87,IF(ISNUMBER(FIND(";"&"balanced"&";",";"&$E$87&";")),"balanced",LEFT($E$87,FIND(";",$E$87&";")-1)))) | O87: depth | P87: =IF(OR($E$87="",$G$87),"KHONG_CHIEN_THUAT",IF(NOT($J$87),IF($H$87="balanced","GIU","CHE_DO_BO_QUA"),IF($N$87=$H$87,"GIU","HO_SO_GHI_DE"))) | Q87: Sim/AI/ConquestAi.P28.cs TickLayered + Sim/AI/Commander.cs AllowedTactic (goal.Hunt, brandt)
A88: goal.Hunt/default | B88: goal.Hunt | C88: default | D88: =AI_ho_so_anh_xa!$D$9 | E88: =INDEX(AI_ho_so_che_do!$B$2:$B$21,MATCH($D$88,AI_ho_so_che_do!$A$2:$A$21,0))&"" | F88: =INDEX(AI_ho_so_che_do!$P$2:$P$21,MATCH($D$88,AI_ho_so_che_do!$A$2:$A$21,0))=TRUE | G88: =ISNUMBER(FIND(";noGeneralTactic;",";"&INDEX(AI_ho_so_che_do!$O$2:$O$21,MATCH($D$88,AI_ho_so_che_do!$A$2:$A$21,0))&";")) | H88: =IF(AI_tuong!$B$4&""<>"",AI_tuong!$B$4,IF(AI_tuong!$B$4&""<>"",AI_tuong!$B$4,"balanced")) | I88: balanced | J88: =OR($F$88,AND(AI_ho_so_anh_xa!$B$9="mode",OR(AI_ho_so_anh_xa!$C$9="Weekly",AI_ho_so_anh_xa!$C$9="Operation"))) | K88: TRUE | L88: =IF($J$88,$H$88,"balanced") | M88: balanced | N88: =IF(OR($E$88="",$G$88),"balanced",IF(OR($E$88="*",ISNUMBER(FIND(";"&$L$88&";",";"&$E$88&";"))),$L$88,IF(ISNUMBER(FIND(";"&"balanced"&";",";"&$E$88&";")),"balanced",LEFT($E$88,FIND(";",$E$88&";")-1)))) | O88: balanced | P88: =IF(OR($E$88="",$G$88),"KHONG_CHIEN_THUAT",IF(NOT($J$88),IF($H$88="balanced","GIU","CHE_DO_BO_QUA"),IF($N$88=$H$88,"GIU","HO_SO_GHI_DE"))) | Q88: Sim/AI/ConquestAi.P28.cs TickLayered + Sim/AI/Commander.cs AllowedTactic (goal.Hunt, default)
A89: goal.Hunt/hung | B89: goal.Hunt | C89: hung | D89: =AI_ho_so_anh_xa!$D$9 | E89: =INDEX(AI_ho_so_che_do!$B$2:$B$21,MATCH($D$89,AI_ho_so_che_do!$A$2:$A$21,0))&"" | F89: =INDEX(AI_ho_so_che_do!$P$2:$P$21,MATCH($D$89,AI_ho_so_che_do!$A$2:$A$21,0))=TRUE | G89: =ISNUMBER(FIND(";noGeneralTactic;",";"&INDEX(AI_ho_so_che_do!$O$2:$O$21,MATCH($D$89,AI_ho_so_che_do!$A$2:$A$21,0))&";")) | H89: =IF(AI_tuong!$B$5&""<>"",AI_tuong!$B$5,IF(AI_tuong!$B$4&""<>"",AI_tuong!$B$4,"balanced")) | I89: balanced | J89: =OR($F$89,AND(AI_ho_so_anh_xa!$B$9="mode",OR(AI_ho_so_anh_xa!$C$9="Weekly",AI_ho_so_anh_xa!$C$9="Operation"))) | K89: TRUE | L89: =IF($J$89,$H$89,"balanced") | M89: balanced | N89: =IF(OR($E$89="",$G$89),"balanced",IF(OR($E$89="*",ISNUMBER(FIND(";"&$L$89&";",";"&$E$89&";"))),$L$89,IF(ISNUMBER(FIND(";"&"balanced"&";",";"&$E$89&";")),"balanced",LEFT($E$89,FIND(";",$E$89&";")-1)))) | O89: balanced | P89: =IF(OR($E$89="",$G$89),"KHONG_CHIEN_THUAT",IF(NOT($J$89),IF($H$89="balanced","GIU","CHE_DO_BO_QUA"),IF($N$89=$H$89,"GIU","HO_SO_GHI_DE"))) | Q89: Sim/AI/ConquestAi.P28.cs TickLayered + Sim/AI/Commander.cs AllowedTactic (goal.Hunt, hung)
A90: goal.Hunt/kessler | B90: goal.Hunt | C90: kessler | D90: =AI_ho_so_anh_xa!$D$9 | E90: =INDEX(AI_ho_so_che_do!$B$2:$B$21,MATCH($D$90,AI_ho_so_che_do!$A$2:$A$21,0))&"" | F90: =INDEX(AI_ho_so_che_do!$P$2:$P$21,MATCH($D$90,AI_ho_so_che_do!$A$2:$A$21,0))=TRUE | G90: =ISNUMBER(FIND(";noGeneralTactic;",";"&INDEX(AI_ho_so_che_do!$O$2:$O$21,MATCH($D$90,AI_ho_so_che_do!$A$2:$A$21,0))&";")) | H90: =IF(AI_tuong!$B$6&""<>"",AI_tuong!$B$6,IF(AI_tuong!$B$4&""<>"",AI_tuong!$B$4,"balanced")) | I90: attrition | J90: =OR($F$90,AND(AI_ho_so_anh_xa!$B$9="mode",OR(AI_ho_so_anh_xa!$C$9="Weekly",AI_ho_so_anh_xa!$C$9="Operation"))) | K90: TRUE | L90: =IF($J$90,$H$90,"balanced") | M90: attrition | N90: =IF(OR($E$90="",$G$90),"balanced",IF(OR($E$90="*",ISNUMBER(FIND(";"&$L$90&";",";"&$E$90&";"))),$L$90,IF(ISNUMBER(FIND(";"&"balanced"&";",";"&$E$90&";")),"balanced",LEFT($E$90,FIND(";",$E$90&";")-1)))) | O90: attrition | P90: =IF(OR($E$90="",$G$90),"KHONG_CHIEN_THUAT",IF(NOT($J$90),IF($H$90="balanced","GIU","CHE_DO_BO_QUA"),IF($N$90=$H$90,"GIU","HO_SO_GHI_DE"))) | Q90: Sim/AI/ConquestAi.P28.cs TickLayered + Sim/AI/Commander.cs AllowedTactic (goal.Hunt, kessler)
A91: goal.Hunt/orlov | B91: goal.Hunt | C91: orlov | D91: =AI_ho_so_anh_xa!$D$9 | E91: =INDEX(AI_ho_so_che_do!$B$2:$B$21,MATCH($D$91,AI_ho_so_che_do!$A$2:$A$21,0))&"" | F91: =INDEX(AI_ho_so_che_do!$P$2:$P$21,MATCH($D$91,AI_ho_so_che_do!$A$2:$A$21,0))=TRUE | G91: =ISNUMBER(FIND(";noGeneralTactic;",";"&INDEX(AI_ho_so_che_do!$O$2:$O$21,MATCH($D$91,AI_ho_so_che_do!$A$2:$A$21,0))&";")) | H91: =IF(AI_tuong!$B$7&""<>"",AI_tuong!$B$7,IF(AI_tuong!$B$4&""<>"",AI_tuong!$B$4,"balanced")) | I91: firepower | J91: =OR($F$91,AND(AI_ho_so_anh_xa!$B$9="mode",OR(AI_ho_so_anh_xa!$C$9="Weekly",AI_ho_so_anh_xa!$C$9="Operation"))) | K91: TRUE | L91: =IF($J$91,$H$91,"balanced") | M91: firepower | N91: =IF(OR($E$91="",$G$91),"balanced",IF(OR($E$91="*",ISNUMBER(FIND(";"&$L$91&";",";"&$E$91&";"))),$L$91,IF(ISNUMBER(FIND(";"&"balanced"&";",";"&$E$91&";")),"balanced",LEFT($E$91,FIND(";",$E$91&";")-1)))) | O91: firepower | P91: =IF(OR($E$91="",$G$91),"KHONG_CHIEN_THUAT",IF(NOT($J$91),IF($H$91="balanced","GIU","CHE_DO_BO_QUA"),IF($N$91=$H$91,"GIU","HO_SO_GHI_DE"))) | Q91: Sim/AI/ConquestAi.P28.cs TickLayered + Sim/AI/Commander.cs AllowedTactic (goal.Hunt, orlov)
A92: goal.Hunt/quaden | B92: goal.Hunt | C92: quaden | D92: =AI_ho_so_anh_xa!$D$9 | E92: =INDEX(AI_ho_so_che_do!$B$2:$B$21,MATCH($D$92,AI_ho_so_che_do!$A$2:$A$21,0))&"" | F92: =INDEX(AI_ho_so_che_do!$P$2:$P$21,MATCH($D$92,AI_ho_so_che_do!$A$2:$A$21,0))=TRUE | G92: =ISNUMBER(FIND(";noGeneralTactic;",";"&INDEX(AI_ho_so_che_do!$O$2:$O$21,MATCH($D$92,AI_ho_so_che_do!$A$2:$A$21,0))&";")) | H92: =IF(AI_tuong!$B$8&""<>"",AI_tuong!$B$8,IF(AI_tuong!$B$4&""<>"",AI_tuong!$B$4,"balanced")) | I92: balanced | J92: =OR($F$92,AND(AI_ho_so_anh_xa!$B$9="mode",OR(AI_ho_so_anh_xa!$C$9="Weekly",AI_ho_so_anh_xa!$C$9="Operation"))) | K92: TRUE | L92: =IF($J$92,$H$92,"balanced") | M92: balanced | N92: =IF(OR($E$92="",$G$92),"balanced",IF(OR($E$92="*",ISNUMBER(FIND(";"&$L$92&";",";"&$E$92&";"))),$L$92,IF(ISNUMBER(FIND(";"&"balanced"&";",";"&$E$92&";")),"balanced",LEFT($E$92,FIND(";",$E$92&";")-1)))) | O92: balanced | P92: =IF(OR($E$92="",$G$92),"KHONG_CHIEN_THUAT",IF(NOT($J$92),IF($H$92="balanced","GIU","CHE_DO_BO_QUA"),IF($N$92=$H$92,"GIU","HO_SO_GHI_DE"))) | Q92: Sim/AI/ConquestAi.P28.cs TickLayered + Sim/AI/Commander.cs AllowedTactic (goal.Hunt, quaden)
A93: goal.Hunt/sen | B93: goal.Hunt | C93: sen | D93: =AI_ho_so_anh_xa!$D$9 | E93: =INDEX(AI_ho_so_che_do!$B$2:$B$21,MATCH($D$93,AI_ho_so_che_do!$A$2:$A$21,0))&"" | F93: =INDEX(AI_ho_so_che_do!$P$2:$P$21,MATCH($D$93,AI_ho_so_che_do!$A$2:$A$21,0))=TRUE | G93: =ISNUMBER(FIND(";noGeneralTactic;",";"&INDEX(AI_ho_so_che_do!$O$2:$O$21,MATCH($D$93,AI_ho_so_che_do!$A$2:$A$21,0))&";")) | H93: =IF(AI_tuong!$B$9&""<>"",AI_tuong!$B$9,IF(AI_tuong!$B$4&""<>"",AI_tuong!$B$4,"balanced")) | I93: balanced | J93: =OR($F$93,AND(AI_ho_so_anh_xa!$B$9="mode",OR(AI_ho_so_anh_xa!$C$9="Weekly",AI_ho_so_anh_xa!$C$9="Operation"))) | K93: TRUE | L93: =IF($J$93,$H$93,"balanced") | M93: balanced | N93: =IF(OR($E$93="",$G$93),"balanced",IF(OR($E$93="*",ISNUMBER(FIND(";"&$L$93&";",";"&$E$93&";"))),$L$93,IF(ISNUMBER(FIND(";"&"balanced"&";",";"&$E$93&";")),"balanced",LEFT($E$93,FIND(";",$E$93&";")-1)))) | O93: balanced | P93: =IF(OR($E$93="",$G$93),"KHONG_CHIEN_THUAT",IF(NOT($J$93),IF($H$93="balanced","GIU","CHE_DO_BO_QUA"),IF($N$93=$H$93,"GIU","HO_SO_GHI_DE"))) | Q93: Sim/AI/ConquestAi.P28.cs TickLayered + Sim/AI/Commander.cs AllowedTactic (goal.Hunt, sen)
A94: goal.Hunt/thorne | B94: goal.Hunt | C94: thorne | D94: =AI_ho_so_anh_xa!$D$9 | E94: =INDEX(AI_ho_so_che_do!$B$2:$B$21,MATCH($D$94,AI_ho_so_che_do!$A$2:$A$21,0))&"" | F94: =INDEX(AI_ho_so_che_do!$P$2:$P$21,MATCH($D$94,AI_ho_so_che_do!$A$2:$A$21,0))=TRUE | G94: =ISNUMBER(FIND(";noGeneralTactic;",";"&INDEX(AI_ho_so_che_do!$O$2:$O$21,MATCH($D$94,AI_ho_so_che_do!$A$2:$A$21,0))&";")) | H94: =IF(AI_tuong!$B$10&""<>"",AI_tuong!$B$10,IF(AI_tuong!$B$4&""<>"",AI_tuong!$B$4,"balanced")) | I94: balanced | J94: =OR($F$94,AND(AI_ho_so_anh_xa!$B$9="mode",OR(AI_ho_so_anh_xa!$C$9="Weekly",AI_ho_so_anh_xa!$C$9="Operation"))) | K94: TRUE | L94: =IF($J$94,$H$94,"balanced") | M94: balanced | N94: =IF(OR($E$94="",$G$94),"balanced",IF(OR($E$94="*",ISNUMBER(FIND(";"&$L$94&";",";"&$E$94&";"))),$L$94,IF(ISNUMBER(FIND(";"&"balanced"&";",";"&$E$94&";")),"balanced",LEFT($E$94,FIND(";",$E$94&";")-1)))) | O94: balanced | P94: =IF(OR($E$94="",$G$94),"KHONG_CHIEN_THUAT",IF(NOT($J$94),IF($H$94="balanced","GIU","CHE_DO_BO_QUA"),IF($N$94=$H$94,"GIU","HO_SO_GHI_DE"))) | Q94: Sim/AI/ConquestAi.P28.cs TickLayered + Sim/AI/Commander.cs AllowedTactic (goal.Hunt, thorne)
A95: goal.Hunt/varga | B95: goal.Hunt | C95: varga | D95: =AI_ho_so_anh_xa!$D$9 | E95: =INDEX(AI_ho_so_che_do!$B$2:$B$21,MATCH($D$95,AI_ho_so_che_do!$A$2:$A$21,0))&"" | F95: =INDEX(AI_ho_so_che_do!$P$2:$P$21,MATCH($D$95,AI_ho_so_che_do!$A$2:$A$21,0))=TRUE | G95: =ISNUMBER(FIND(";noGeneralTactic;",";"&INDEX(AI_ho_so_che_do!$O$2:$O$21,MATCH($D$95,AI_ho_so_che_do!$A$2:$A$21,0))&";")) | H95: =IF(AI_tuong!$B$11&""<>"",AI_tuong!$B$11,IF(AI_tuong!$B$4&""<>"",AI_tuong!$B$4,"balanced")) | I95: breakthrough | J95: =OR($F$95,AND(AI_ho_so_anh_xa!$B$9="mode",OR(AI_ho_so_anh_xa!$C$9="Weekly",AI_ho_so_anh_xa!$C$9="Operation"))) | K95: TRUE | L95: =IF($J$95,$H$95,"balanced") | M95: breakthrough | N95: =IF(OR($E$95="",$G$95),"balanced",IF(OR($E$95="*",ISNUMBER(FIND(";"&$L$95&";",";"&$E$95&";"))),$L$95,IF(ISNUMBER(FIND(";"&"balanced"&";",";"&$E$95&";")),"balanced",LEFT($E$95,FIND(";",$E$95&";")-1)))) | O95: breakthrough | P95: =IF(OR($E$95="",$G$95),"KHONG_CHIEN_THUAT",IF(NOT($J$95),IF($H$95="balanced","GIU","CHE_DO_BO_QUA"),IF($N$95=$H$95,"GIU","HO_SO_GHI_DE"))) | Q95: Sim/AI/ConquestAi.P28.cs TickLayered + Sim/AI/Commander.cs AllowedTactic (goal.Hunt, varga)
A96: goal.Hunt/venn | B96: goal.Hunt | C96: venn | D96: =AI_ho_so_anh_xa!$D$9 | E96: =INDEX(AI_ho_so_che_do!$B$2:$B$21,MATCH($D$96,AI_ho_so_che_do!$A$2:$A$21,0))&"" | F96: =INDEX(AI_ho_so_che_do!$P$2:$P$21,MATCH($D$96,AI_ho_so_che_do!$A$2:$A$21,0))=TRUE | G96: =ISNUMBER(FIND(";noGeneralTactic;",";"&INDEX(AI_ho_so_che_do!$O$2:$O$21,MATCH($D$96,AI_ho_so_che_do!$A$2:$A$21,0))&";")) | H96: =IF(AI_tuong!$B$12&""<>"",AI_tuong!$B$12,IF(AI_tuong!$B$4&""<>"",AI_tuong!$B$4,"balanced")) | I96: dispersal | J96: =OR($F$96,AND(AI_ho_so_anh_xa!$B$9="mode",OR(AI_ho_so_anh_xa!$C$9="Weekly",AI_ho_so_anh_xa!$C$9="Operation"))) | K96: TRUE | L96: =IF($J$96,$H$96,"balanced") | M96: dispersal | N96: =IF(OR($E$96="",$G$96),"balanced",IF(OR($E$96="*",ISNUMBER(FIND(";"&$L$96&";",";"&$E$96&";"))),$L$96,IF(ISNUMBER(FIND(";"&"balanced"&";",";"&$E$96&";")),"balanced",LEFT($E$96,FIND(";",$E$96&";")-1)))) | O96: dispersal | P96: =IF(OR($E$96="",$G$96),"KHONG_CHIEN_THUAT",IF(NOT($J$96),IF($H$96="balanced","GIU","CHE_DO_BO_QUA"),IF($N$96=$H$96,"GIU","HO_SO_GHI_DE"))) | Q96: Sim/AI/ConquestAi.P28.cs TickLayered + Sim/AI/Commander.cs AllowedTactic (goal.Hunt, venn)
A97: goal.Hunt/wolff | B97: goal.Hunt | C97: wolff | D97: =AI_ho_so_anh_xa!$D$9 | E97: =INDEX(AI_ho_so_che_do!$B$2:$B$21,MATCH($D$97,AI_ho_so_che_do!$A$2:$A$21,0))&"" | F97: =INDEX(AI_ho_so_che_do!$P$2:$P$21,MATCH($D$97,AI_ho_so_che_do!$A$2:$A$21,0))=TRUE | G97: =ISNUMBER(FIND(";noGeneralTactic;",";"&INDEX(AI_ho_so_che_do!$O$2:$O$21,MATCH($D$97,AI_ho_so_che_do!$A$2:$A$21,0))&";")) | H97: =IF(AI_tuong!$B$13&""<>"",AI_tuong!$B$13,IF(AI_tuong!$B$4&""<>"",AI_tuong!$B$4,"balanced")) | I97: air_superiority | J97: =OR($F$97,AND(AI_ho_so_anh_xa!$B$9="mode",OR(AI_ho_so_anh_xa!$C$9="Weekly",AI_ho_so_anh_xa!$C$9="Operation"))) | K97: TRUE | L97: =IF($J$97,$H$97,"balanced") | M97: air_superiority | N97: =IF(OR($E$97="",$G$97),"balanced",IF(OR($E$97="*",ISNUMBER(FIND(";"&$L$97&";",";"&$E$97&";"))),$L$97,IF(ISNUMBER(FIND(";"&"balanced"&";",";"&$E$97&";")),"balanced",LEFT($E$97,FIND(";",$E$97&";")-1)))) | O97: air_superiority | P97: =IF(OR($E$97="",$G$97),"KHONG_CHIEN_THUAT",IF(NOT($J$97),IF($H$97="balanced","GIU","CHE_DO_BO_QUA"),IF($N$97=$H$97,"GIU","HO_SO_GHI_DE"))) | Q97: Sim/AI/ConquestAi.P28.cs TickLayered + Sim/AI/Commander.cs AllowedTactic (goal.Hunt, wolff)
A98: goal.Intercept/aurel | B98: goal.Intercept | C98: aurel | D98: =AI_ho_so_anh_xa!$D$10 | E98: =INDEX(AI_ho_so_che_do!$B$2:$B$21,MATCH($D$98,AI_ho_so_che_do!$A$2:$A$21,0))&"" | F98: =INDEX(AI_ho_so_che_do!$P$2:$P$21,MATCH($D$98,AI_ho_so_che_do!$A$2:$A$21,0))=TRUE | G98: =ISNUMBER(FIND(";noGeneralTactic;",";"&INDEX(AI_ho_so_che_do!$O$2:$O$21,MATCH($D$98,AI_ho_so_che_do!$A$2:$A$21,0))&";")) | H98: =IF(AI_tuong!$B$2&""<>"",AI_tuong!$B$2,IF(AI_tuong!$B$4&""<>"",AI_tuong!$B$4,"balanced")) | I98: all_out | J98: =OR($F$98,AND(AI_ho_so_anh_xa!$B$10="mode",OR(AI_ho_so_anh_xa!$C$10="Weekly",AI_ho_so_anh_xa!$C$10="Operation"))) | K98: TRUE | L98: =IF($J$98,$H$98,"balanced") | M98: all_out | N98: =IF(OR($E$98="",$G$98),"balanced",IF(OR($E$98="*",ISNUMBER(FIND(";"&$L$98&";",";"&$E$98&";"))),$L$98,IF(ISNUMBER(FIND(";"&"balanced"&";",";"&$E$98&";")),"balanced",LEFT($E$98,FIND(";",$E$98&";")-1)))) | O98: all_out | P98: =IF(OR($E$98="",$G$98),"KHONG_CHIEN_THUAT",IF(NOT($J$98),IF($H$98="balanced","GIU","CHE_DO_BO_QUA"),IF($N$98=$H$98,"GIU","HO_SO_GHI_DE"))) | Q98: Sim/AI/ConquestAi.P28.cs TickLayered + Sim/AI/Commander.cs AllowedTactic (goal.Intercept, aurel)
A99: goal.Intercept/brandt | B99: goal.Intercept | C99: brandt | D99: =AI_ho_so_anh_xa!$D$10 | E99: =INDEX(AI_ho_so_che_do!$B$2:$B$21,MATCH($D$99,AI_ho_so_che_do!$A$2:$A$21,0))&"" | F99: =INDEX(AI_ho_so_che_do!$P$2:$P$21,MATCH($D$99,AI_ho_so_che_do!$A$2:$A$21,0))=TRUE | G99: =ISNUMBER(FIND(";noGeneralTactic;",";"&INDEX(AI_ho_so_che_do!$O$2:$O$21,MATCH($D$99,AI_ho_so_che_do!$A$2:$A$21,0))&";")) | H99: =IF(AI_tuong!$B$3&""<>"",AI_tuong!$B$3,IF(AI_tuong!$B$4&""<>"",AI_tuong!$B$4,"balanced")) | I99: depth | J99: =OR($F$99,AND(AI_ho_so_anh_xa!$B$10="mode",OR(AI_ho_so_anh_xa!$C$10="Weekly",AI_ho_so_anh_xa!$C$10="Operation"))) | K99: TRUE | L99: =IF($J$99,$H$99,"balanced") | M99: depth | N99: =IF(OR($E$99="",$G$99),"balanced",IF(OR($E$99="*",ISNUMBER(FIND(";"&$L$99&";",";"&$E$99&";"))),$L$99,IF(ISNUMBER(FIND(";"&"balanced"&";",";"&$E$99&";")),"balanced",LEFT($E$99,FIND(";",$E$99&";")-1)))) | O99: depth | P99: =IF(OR($E$99="",$G$99),"KHONG_CHIEN_THUAT",IF(NOT($J$99),IF($H$99="balanced","GIU","CHE_DO_BO_QUA"),IF($N$99=$H$99,"GIU","HO_SO_GHI_DE"))) | Q99: Sim/AI/ConquestAi.P28.cs TickLayered + Sim/AI/Commander.cs AllowedTactic (goal.Intercept, brandt)
A100: goal.Intercept/default | B100: goal.Intercept | C100: default | D100: =AI_ho_so_anh_xa!$D$10 | E100: =INDEX(AI_ho_so_che_do!$B$2:$B$21,MATCH($D$100,AI_ho_so_che_do!$A$2:$A$21,0))&"" | F100: =INDEX(AI_ho_so_che_do!$P$2:$P$21,MATCH($D$100,AI_ho_so_che_do!$A$2:$A$21,0))=TRUE | G100: =ISNUMBER(FIND(";noGeneralTactic;",";"&INDEX(AI_ho_so_che_do!$O$2:$O$21,MATCH($D$100,AI_ho_so_che_do!$A$2:$A$21,0))&";")) | H100: =IF(AI_tuong!$B$4&""<>"",AI_tuong!$B$4,IF(AI_tuong!$B$4&""<>"",AI_tuong!$B$4,"balanced")) | I100: balanced | J100: =OR($F$100,AND(AI_ho_so_anh_xa!$B$10="mode",OR(AI_ho_so_anh_xa!$C$10="Weekly",AI_ho_so_anh_xa!$C$10="Operation"))) | K100: TRUE | L100: =IF($J$100,$H$100,"balanced") | M100: balanced | N100: =IF(OR($E$100="",$G$100),"balanced",IF(OR($E$100="*",ISNUMBER(FIND(";"&$L$100&";",";"&$E$100&";"))),$L$100,IF(ISNUMBER(FIND(";"&"balanced"&";",";"&$E$100&";")),"balanced",LEFT($E$100,FIND(";",$E$100&";")-1)))) | O100: balanced | P100: =IF(OR($E$100="",$G$100),"KHONG_CHIEN_THUAT",IF(NOT($J$100),IF($H$100="balanced","GIU","CHE_DO_BO_QUA"),IF($N$100=$H$100,"GIU","HO_SO_GHI_DE"))) | Q100: Sim/AI/ConquestAi.P28.cs TickLayered + Sim/AI/Commander.cs AllowedTactic (goal.Intercept, default)
...

Sheet AI_xung_dot_do_kho
A1: id | B1: ho_so | C1: do_kho | D1: doi_chien_thuat_do_kho | E1: so_chien_thuat_cho_phep | F1: hieu_luc | G1: hieu_luc_game | H1: trang_thai | I1: so_ghi_de_pha | J1: nguon | K1: raw_json
A2: assault/Easy | B2: assault | C2: Easy | D2: Never | E2: =IF(INDEX(AI_ho_so_che_do!$B$2:$B$21,MATCH($B$2,AI_ho_so_che_do!$A$2:$A$21,0))&""="*",COUNTIFS(Chien_thuat!$A$2:$A$17,"*"),IF(INDEX(AI_ho_so_che_do!$B$2:$B$21,MATCH($B$2,AI_ho_so_che_do!$A$2:$A$21,0))&""="",0,LEN(INDEX(AI_ho_so_che_do!$B$2:$B$21,MATCH($B$2,AI_ho_so_che_do!$A$2:$A$21,0))&"")-LEN(SUBSTITUTE(INDEX(AI_ho_so_che_do!$B$2:$B$21,MATCH($B$2,AI_ho_so_che_do!$A$2:$A$21,0))&"",";",""))+1)) | F2: =IF(OR($E$2<=1,ISNUMBER(FIND(";noGeneralTactic;",";"&INDEX(AI_ho_so_che_do!$O$2:$O$21,MATCH($B$2,AI_ho_so_che_do!$A$2:$A$21,0))&";"))),"Never",$D$2) | G2: Never | H2: =IF($D$2="Never","KHONG_DOI",IF($F$2="Never","HO_SO_CHAN","DO_KHO_CHO_DOI")) | I2: =COUNTIFS(AI_ho_so_pha!$B$2:$B$6,$B$2) | J2: Sim/AI/Commander.cs:45 (AiSkill.For Easy); balance.json aiModeProfiles.profiles.assault
A3: assault/Hard | B3: assault | C3: Hard | D3: WhenLosing | E3: =IF(INDEX(AI_ho_so_che_do!$B$2:$B$21,MATCH($B$3,AI_ho_so_che_do!$A$2:$A$21,0))&""="*",COUNTIFS(Chien_thuat!$A$2:$A$17,"*"),IF(INDEX(AI_ho_so_che_do!$B$2:$B$21,MATCH($B$3,AI_ho_so_che_do!$A$2:$A$21,0))&""="",0,LEN(INDEX(AI_ho_so_che_do!$B$2:$B$21,MATCH($B$3,AI_ho_so_che_do!$A$2:$A$21,0))&"")-LEN(SUBSTITUTE(INDEX(AI_ho_so_che_do!$B$2:$B$21,MATCH($B$3,AI_ho_so_che_do!$A$2:$A$21,0))&"",";",""))+1)) | F3: =IF(OR($E$3<=1,ISNUMBER(FIND(";noGeneralTactic;",";"&INDEX(AI_ho_so_che_do!$O$2:$O$21,MATCH($B$3,AI_ho_so_che_do!$A$2:$A$21,0))&";"))),"Never",$D$3) | G3: WhenLosing | H3: =IF($D$3="Never","KHONG_DOI",IF($F$3="Never","HO_SO_CHAN","DO_KHO_CHO_DOI")) | I3: =COUNTIFS(AI_ho_so_pha!$B$2:$B$6,$B$3) | J3: Sim/AI/Commander.cs:46 (AiSkill.For Hard); balance.json aiModeProfiles.profiles.assault
A4: assault/Normal | B4: assault | C4: Normal | D4: Never | E4: =IF(INDEX(AI_ho_so_che_do!$B$2:$B$21,MATCH($B$4,AI_ho_so_che_do!$A$2:$A$21,0))&""="*",COUNTIFS(Chien_thuat!$A$2:$A$17,"*"),IF(INDEX(AI_ho_so_che_do!$B$2:$B$21,MATCH($B$4,AI_ho_so_che_do!$A$2:$A$21,0))&""="",0,LEN(INDEX(AI_ho_so_che_do!$B$2:$B$21,MATCH($B$4,AI_ho_so_che_do!$A$2:$A$21,0))&"")-LEN(SUBSTITUTE(INDEX(AI_ho_so_che_do!$B$2:$B$21,MATCH($B$4,AI_ho_so_che_do!$A$2:$A$21,0))&"",";",""))+1)) | F4: =IF(OR($E$4<=1,ISNUMBER(FIND(";noGeneralTactic;",";"&INDEX(AI_ho_so_che_do!$O$2:$O$21,MATCH($B$4,AI_ho_so_che_do!$A$2:$A$21,0))&";"))),"Never",$D$4) | G4: Never | H4: =IF($D$4="Never","KHONG_DOI",IF($F$4="Never","HO_SO_CHAN","DO_KHO_CHO_DOI")) | I4: =COUNTIFS(AI_ho_so_pha!$B$2:$B$6,$B$4) | J4: Sim/AI/Commander.cs:57 (AiSkill.For Normal); balance.json aiModeProfiles.profiles.assault
A5: assault/VeryHard | B5: assault | C5: VeryHard | D5: Counter | E5: =IF(INDEX(AI_ho_so_che_do!$B$2:$B$21,MATCH($B$5,AI_ho_so_che_do!$A$2:$A$21,0))&""="*",COUNTIFS(Chien_thuat!$A$2:$A$17,"*"),IF(INDEX(AI_ho_so_che_do!$B$2:$B$21,MATCH($B$5,AI_ho_so_che_do!$A$2:$A$21,0))&""="",0,LEN(INDEX(AI_ho_so_che_do!$B$2:$B$21,MATCH($B$5,AI_ho_so_che_do!$A$2:$A$21,0))&"")-LEN(SUBSTITUTE(INDEX(AI_ho_so_che_do!$B$2:$B$21,MATCH($B$5,AI_ho_so_che_do!$A$2:$A$21,0))&"",";",""))+1)) | F5: =IF(OR($E$5<=1,ISNUMBER(FIND(";noGeneralTactic;",";"&INDEX(AI_ho_so_che_do!$O$2:$O$21,MATCH($B$5,AI_ho_so_che_do!$A$2:$A$21,0))&";"))),"Never",$D$5) | G5: Counter | H5: =IF($D$5="Never","KHONG_DOI",IF($F$5="Never","HO_SO_CHAN","DO_KHO_CHO_DOI")) | I5: =COUNTIFS(AI_ho_so_pha!$B$2:$B$6,$B$5) | J5: Sim/AI/Commander.cs:52 (AiSkill.For VeryHard); balance.json aiModeProfiles.profiles.assault
A6: bossrush/Easy | B6: bossrush | C6: Easy | D6: Never | E6: =IF(INDEX(AI_ho_so_che_do!$B$2:$B$21,MATCH($B$6,AI_ho_so_che_do!$A$2:$A$21,0))&""="*",COUNTIFS(Chien_thuat!$A$2:$A$17,"*"),IF(INDEX(AI_ho_so_che_do!$B$2:$B$21,MATCH($B$6,AI_ho_so_che_do!$A$2:$A$21,0))&""="",0,LEN(INDEX(AI_ho_so_che_do!$B$2:$B$21,MATCH($B$6,AI_ho_so_che_do!$A$2:$A$21,0))&"")-LEN(SUBSTITUTE(INDEX(AI_ho_so_che_do!$B$2:$B$21,MATCH($B$6,AI_ho_so_che_do!$A$2:$A$21,0))&"",";",""))+1)) | F6: =IF(OR($E$6<=1,ISNUMBER(FIND(";noGeneralTactic;",";"&INDEX(AI_ho_so_che_do!$O$2:$O$21,MATCH($B$6,AI_ho_so_che_do!$A$2:$A$21,0))&";"))),"Never",$D$6) | G6: Never | H6: =IF($D$6="Never","KHONG_DOI",IF($F$6="Never","HO_SO_CHAN","DO_KHO_CHO_DOI")) | I6: =COUNTIFS(AI_ho_so_pha!$B$2:$B$6,$B$6) | J6: Sim/AI/Commander.cs:45 (AiSkill.For Easy); balance.json aiModeProfiles.profiles.bossrush
A7: bossrush/Hard | B7: bossrush | C7: Hard | D7: WhenLosing | E7: =IF(INDEX(AI_ho_so_che_do!$B$2:$B$21,MATCH($B$7,AI_ho_so_che_do!$A$2:$A$21,0))&""="*",COUNTIFS(Chien_thuat!$A$2:$A$17,"*"),IF(INDEX(AI_ho_so_che_do!$B$2:$B$21,MATCH($B$7,AI_ho_so_che_do!$A$2:$A$21,0))&""="",0,LEN(INDEX(AI_ho_so_che_do!$B$2:$B$21,MATCH($B$7,AI_ho_so_che_do!$A$2:$A$21,0))&"")-LEN(SUBSTITUTE(INDEX(AI_ho_so_che_do!$B$2:$B$21,MATCH($B$7,AI_ho_so_che_do!$A$2:$A$21,0))&"",";",""))+1)) | F7: =IF(OR($E$7<=1,ISNUMBER(FIND(";noGeneralTactic;",";"&INDEX(AI_ho_so_che_do!$O$2:$O$21,MATCH($B$7,AI_ho_so_che_do!$A$2:$A$21,0))&";"))),"Never",$D$7) | G7: Never | H7: =IF($D$7="Never","KHONG_DOI",IF($F$7="Never","HO_SO_CHAN","DO_KHO_CHO_DOI")) | I7: =COUNTIFS(AI_ho_so_pha!$B$2:$B$6,$B$7) | J7: Sim/AI/Commander.cs:46 (AiSkill.For Hard); balance.json aiModeProfiles.profiles.bossrush
A8: bossrush/Normal | B8: bossrush | C8: Normal | D8: Never | E8: =IF(INDEX(AI_ho_so_che_do!$B$2:$B$21,MATCH($B$8,AI_ho_so_che_do!$A$2:$A$21,0))&""="*",COUNTIFS(Chien_thuat!$A$2:$A$17,"*"),IF(INDEX(AI_ho_so_che_do!$B$2:$B$21,MATCH($B$8,AI_ho_so_che_do!$A$2:$A$21,0))&""="",0,LEN(INDEX(AI_ho_so_che_do!$B$2:$B$21,MATCH($B$8,AI_ho_so_che_do!$A$2:$A$21,0))&"")-LEN(SUBSTITUTE(INDEX(AI_ho_so_che_do!$B$2:$B$21,MATCH($B$8,AI_ho_so_che_do!$A$2:$A$21,0))&"",";",""))+1)) | F8: =IF(OR($E$8<=1,ISNUMBER(FIND(";noGeneralTactic;",";"&INDEX(AI_ho_so_che_do!$O$2:$O$21,MATCH($B$8,AI_ho_so_che_do!$A$2:$A$21,0))&";"))),"Never",$D$8) | G8: Never | H8: =IF($D$8="Never","KHONG_DOI",IF($F$8="Never","HO_SO_CHAN","DO_KHO_CHO_DOI")) | I8: =COUNTIFS(AI_ho_so_pha!$B$2:$B$6,$B$8) | J8: Sim/AI/Commander.cs:57 (AiSkill.For Normal); balance.json aiModeProfiles.profiles.bossrush
A9: bossrush/VeryHard | B9: bossrush | C9: VeryHard | D9: Counter | E9: =IF(INDEX(AI_ho_so_che_do!$B$2:$B$21,MATCH($B$9,AI_ho_so_che_do!$A$2:$A$21,0))&""="*",COUNTIFS(Chien_thuat!$A$2:$A$17,"*"),IF(INDEX(AI_ho_so_che_do!$B$2:$B$21,MATCH($B$9,AI_ho_so_che_do!$A$2:$A$21,0))&""="",0,LEN(INDEX(AI_ho_so_che_do!$B$2:$B$21,MATCH($B$9,AI_ho_so_che_do!$A$2:$A$21,0))&"")-LEN(SUBSTITUTE(INDEX(AI_ho_so_che_do!$B$2:$B$21,MATCH($B$9,AI_ho_so_che_do!$A$2:$A$21,0))&"",";",""))+1)) | F9: =IF(OR($E$9<=1,ISNUMBER(FIND(";noGeneralTactic;",";"&INDEX(AI_ho_so_che_do!$O$2:$O$21,MATCH($B$9,AI_ho_so_che_do!$A$2:$A$21,0))&";"))),"Never",$D$9) | G9: Never | H9: =IF($D$9="Never","KHONG_DOI",IF($F$9="Never","HO_SO_CHAN","DO_KHO_CHO_DOI")) | I9: =COUNTIFS(AI_ho_so_pha!$B$2:$B$6,$B$9) | J9: Sim/AI/Commander.cs:52 (AiSkill.For VeryHard); balance.json aiModeProfiles.profiles.bossrush
A10: capture/Easy | B10: capture | C10: Easy | D10: Never | E10: =IF(INDEX(AI_ho_so_che_do!$B$2:$B$21,MATCH($B$10,AI_ho_so_che_do!$A$2:$A$21,0))&""="*",COUNTIFS(Chien_thuat!$A$2:$A$17,"*"),IF(INDEX(AI_ho_so_che_do!$B$2:$B$21,MATCH($B$10,AI_ho_so_che_do!$A$2:$A$21,0))&""="",0,LEN(INDEX(AI_ho_so_che_do!$B$2:$B$21,MATCH($B$10,AI_ho_so_che_do!$A$2:$A$21,0))&"")-LEN(SUBSTITUTE(INDEX(AI_ho_so_che_do!$B$2:$B$21,MATCH($B$10,AI_ho_so_che_do!$A$2:$A$21,0))&"",";",""))+1)) | F10: =IF(OR($E$10<=1,ISNUMBER(FIND(";noGeneralTactic;",";"&INDEX(AI_ho_so_che_do!$O$2:$O$21,MATCH($B$10,AI_ho_so_che_do!$A$2:$A$21,0))&";"))),"Never",$D$10) | G10: Never | H10: =IF($D$10="Never","KHONG_DOI",IF($F$10="Never","HO_SO_CHAN","DO_KHO_CHO_DOI")) | I10: =COUNTIFS(AI_ho_so_pha!$B$2:$B$6,$B$10) | J10: Sim/AI/Commander.cs:45 (AiSkill.For Easy); balance.json aiModeProfiles.profiles.capture
A11: capture/Hard | B11: capture | C11: Hard | D11: WhenLosing | E11: =IF(INDEX(AI_ho_so_che_do!$B$2:$B$21,MATCH($B$11,AI_ho_so_che_do!$A$2:$A$21,0))&""="*",COUNTIFS(Chien_thuat!$A$2:$A$17,"*"),IF(INDEX(AI_ho_so_che_do!$B$2:$B$21,MATCH($B$11,AI_ho_so_che_do!$A$2:$A$21,0))&""="",0,LEN(INDEX(AI_ho_so_che_do!$B$2:$B$21,MATCH($B$11,AI_ho_so_che_do!$A$2:$A$21,0))&"")-LEN(SUBSTITUTE(INDEX(AI_ho_so_che_do!$B$2:$B$21,MATCH($B$11,AI_ho_so_che_do!$A$2:$A$21,0))&"",";",""))+1)) | F11: =IF(OR($E$11<=1,ISNUMBER(FIND(";noGeneralTactic;",";"&INDEX(AI_ho_so_che_do!$O$2:$O$21,MATCH($B$11,AI_ho_so_che_do!$A$2:$A$21,0))&";"))),"Never",$D$11) | G11: WhenLosing | H11: =IF($D$11="Never","KHONG_DOI",IF($F$11="Never","HO_SO_CHAN","DO_KHO_CHO_DOI")) | I11: =COUNTIFS(AI_ho_so_pha!$B$2:$B$6,$B$11) | J11: Sim/AI/Commander.cs:46 (AiSkill.For Hard); balance.json aiModeProfiles.profiles.capture
A12: capture/Normal | B12: capture | C12: Normal | D12: Never | E12: =IF(INDEX(AI_ho_so_che_do!$B$2:$B$21,MATCH($B$12,AI_ho_so_che_do!$A$2:$A$21,0))&""="*",COUNTIFS(Chien_thuat!$A$2:$A$17,"*"),IF(INDEX(AI_ho_so_che_do!$B$2:$B$21,MATCH($B$12,AI_ho_so_che_do!$A$2:$A$21,0))&""="",0,LEN(INDEX(AI_ho_so_che_do!$B$2:$B$21,MATCH($B$12,AI_ho_so_che_do!$A$2:$A$21,0))&"")-LEN(SUBSTITUTE(INDEX(AI_ho_so_che_do!$B$2:$B$21,MATCH($B$12,AI_ho_so_che_do!$A$2:$A$21,0))&"",";",""))+1)) | F12: =IF(OR($E$12<=1,ISNUMBER(FIND(";noGeneralTactic;",";"&INDEX(AI_ho_so_che_do!$O$2:$O$21,MATCH($B$12,AI_ho_so_che_do!$A$2:$A$21,0))&";"))),"Never",$D$12) | G12: Never | H12: =IF($D$12="Never","KHONG_DOI",IF($F$12="Never","HO_SO_CHAN","DO_KHO_CHO_DOI")) | I12: =COUNTIFS(AI_ho_so_pha!$B$2:$B$6,$B$12) | J12: Sim/AI/Commander.cs:57 (AiSkill.For Normal); balance.json aiModeProfiles.profiles.capture
A13: capture/VeryHard | B13: capture | C13: VeryHard | D13: Counter | E13: =IF(INDEX(AI_ho_so_che_do!$B$2:$B$21,MATCH($B$13,AI_ho_so_che_do!$A$2:$A$21,0))&""="*",COUNTIFS(Chien_thuat!$A$2:$A$17,"*"),IF(INDEX(AI_ho_so_che_do!$B$2:$B$21,MATCH($B$13,AI_ho_so_che_do!$A$2:$A$21,0))&""="",0,LEN(INDEX(AI_ho_so_che_do!$B$2:$B$21,MATCH($B$13,AI_ho_so_che_do!$A$2:$A$21,0))&"")-LEN(SUBSTITUTE(INDEX(AI_ho_so_che_do!$B$2:$B$21,MATCH($B$13,AI_ho_so_che_do!$A$2:$A$21,0))&"",";",""))+1)) | F13: =IF(OR($E$13<=1,ISNUMBER(FIND(";noGeneralTactic;",";"&INDEX(AI_ho_so_che_do!$O$2:$O$21,MATCH($B$13,AI_ho_so_che_do!$A$2:$A$21,0))&";"))),"Never",$D$13) | G13: Counter | H13: =IF($D$13="Never","KHONG_DOI",IF($F$13="Never","HO_SO_CHAN","DO_KHO_CHO_DOI")) | I13: =COUNTIFS(AI_ho_so_pha!$B$2:$B$6,$B$13) | J13: Sim/AI/Commander.cs:52 (AiSkill.For VeryHard); balance.json aiModeProfiles.profiles.capture
A14: conquest/Easy | B14: conquest | C14: Easy | D14: Never | E14: =IF(INDEX(AI_ho_so_che_do!$B$2:$B$21,MATCH($B$14,AI_ho_so_che_do!$A$2:$A$21,0))&""="*",COUNTIFS(Chien_thuat!$A$2:$A$17,"*"),IF(INDEX(AI_ho_so_che_do!$B$2:$B$21,MATCH($B$14,AI_ho_so_che_do!$A$2:$A$21,0))&""="",0,LEN(INDEX(AI_ho_so_che_do!$B$2:$B$21,MATCH($B$14,AI_ho_so_che_do!$A$2:$A$21,0))&"")-LEN(SUBSTITUTE(INDEX(AI_ho_so_che_do!$B$2:$B$21,MATCH($B$14,AI_ho_so_che_do!$A$2:$A$21,0))&"",";",""))+1)) | F14: =IF(OR($E$14<=1,ISNUMBER(FIND(";noGeneralTactic;",";"&INDEX(AI_ho_so_che_do!$O$2:$O$21,MATCH($B$14,AI_ho_so_che_do!$A$2:$A$21,0))&";"))),"Never",$D$14) | G14: Never | H14: =IF($D$14="Never","KHONG_DOI",IF($F$14="Never","HO_SO_CHAN","DO_KHO_CHO_DOI")) | I14: =COUNTIFS(AI_ho_so_pha!$B$2:$B$6,$B$14) | J14: Sim/AI/Commander.cs:45 (AiSkill.For Easy); balance.json aiModeProfiles.profiles.conquest
A15: conquest/Hard | B15: conquest | C15: Hard | D15: WhenLosing | E15: =IF(INDEX(AI_ho_so_che_do!$B$2:$B$21,MATCH($B$15,AI_ho_so_che_do!$A$2:$A$21,0))&""="*",COUNTIFS(Chien_thuat!$A$2:$A$17,"*"),IF(INDEX(AI_ho_so_che_do!$B$2:$B$21,MATCH($B$15,AI_ho_so_che_do!$A$2:$A$21,0))&""="",0,LEN(INDEX(AI_ho_so_che_do!$B$2:$B$21,MATCH($B$15,AI_ho_so_che_do!$A$2:$A$21,0))&"")-LEN(SUBSTITUTE(INDEX(AI_ho_so_che_do!$B$2:$B$21,MATCH($B$15,AI_ho_so_che_do!$A$2:$A$21,0))&"",";",""))+1)) | F15: =IF(OR($E$15<=1,ISNUMBER(FIND(";noGeneralTactic;",";"&INDEX(AI_ho_so_che_do!$O$2:$O$21,MATCH($B$15,AI_ho_so_che_do!$A$2:$A$21,0))&";"))),"Never",$D$15) | G15: WhenLosing | H15: =IF($D$15="Never","KHONG_DOI",IF($F$15="Never","HO_SO_CHAN","DO_KHO_CHO_DOI")) | I15: =COUNTIFS(AI_ho_so_pha!$B$2:$B$6,$B$15) | J15: Sim/AI/Commander.cs:46 (AiSkill.For Hard); balance.json aiModeProfiles.profiles.conquest
A16: conquest/Normal | B16: conquest | C16: Normal | D16: Never | E16: =IF(INDEX(AI_ho_so_che_do!$B$2:$B$21,MATCH($B$16,AI_ho_so_che_do!$A$2:$A$21,0))&""="*",COUNTIFS(Chien_thuat!$A$2:$A$17,"*"),IF(INDEX(AI_ho_so_che_do!$B$2:$B$21,MATCH($B$16,AI_ho_so_che_do!$A$2:$A$21,0))&""="",0,LEN(INDEX(AI_ho_so_che_do!$B$2:$B$21,MATCH($B$16,AI_ho_so_che_do!$A$2:$A$21,0))&"")-LEN(SUBSTITUTE(INDEX(AI_ho_so_che_do!$B$2:$B$21,MATCH($B$16,AI_ho_so_che_do!$A$2:$A$21,0))&"",";",""))+1)) | F16: =IF(OR($E$16<=1,ISNUMBER(FIND(";noGeneralTactic;",";"&INDEX(AI_ho_so_che_do!$O$2:$O$21,MATCH($B$16,AI_ho_so_che_do!$A$2:$A$21,0))&";"))),"Never",$D$16) | G16: Never | H16: =IF($D$16="Never","KHONG_DOI",IF($F$16="Never","HO_SO_CHAN","DO_KHO_CHO_DOI")) | I16: =COUNTIFS(AI_ho_so_pha!$B$2:$B$6,$B$16) | J16: Sim/AI/Commander.cs:57 (AiSkill.For Normal); balance.json aiModeProfiles.profiles.conquest
A17: conquest/VeryHard | B17: conquest | C17: VeryHard | D17: Counter | E17: =IF(INDEX(AI_ho_so_che_do!$B$2:$B$21,MATCH($B$17,AI_ho_so_che_do!$A$2:$A$21,0))&""="*",COUNTIFS(Chien_thuat!$A$2:$A$17,"*"),IF(INDEX(AI_ho_so_che_do!$B$2:$B$21,MATCH($B$17,AI_ho_so_che_do!$A$2:$A$21,0))&""="",0,LEN(INDEX(AI_ho_so_che_do!$B$2:$B$21,MATCH($B$17,AI_ho_so_che_do!$A$2:$A$21,0))&"")-LEN(SUBSTITUTE(INDEX(AI_ho_so_che_do!$B$2:$B$21,MATCH($B$17,AI_ho_so_che_do!$A$2:$A$21,0))&"",";",""))+1)) | F17: =IF(OR($E$17<=1,ISNUMBER(FIND(";noGeneralTactic;",";"&INDEX(AI_ho_so_che_do!$O$2:$O$21,MATCH($B$17,AI_ho_so_che_do!$A$2:$A$21,0))&";"))),"Never",$D$17) | G17: Counter | H17: =IF($D$17="Never","KHONG_DOI",IF($F$17="Never","HO_SO_CHAN","DO_KHO_CHO_DOI")) | I17: =COUNTIFS(AI_ho_so_pha!$B$2:$B$6,$B$17) | J17: Sim/AI/Commander.cs:52 (AiSkill.For VeryHard); balance.json aiModeProfiles.profiles.conquest
A18: deathmatch/Easy | B18: deathmatch | C18: Easy | D18: Never | E18: =IF(INDEX(AI_ho_so_che_do!$B$2:$B$21,MATCH($B$18,AI_ho_so_che_do!$A$2:$A$21,0))&""="*",COUNTIFS(Chien_thuat!$A$2:$A$17,"*"),IF(INDEX(AI_ho_so_che_do!$B$2:$B$21,MATCH($B$18,AI_ho_so_che_do!$A$2:$A$21,0))&""="",0,LEN(INDEX(AI_ho_so_che_do!$B$2:$B$21,MATCH($B$18,AI_ho_so_che_do!$A$2:$A$21,0))&"")-LEN(SUBSTITUTE(INDEX(AI_ho_so_che_do!$B$2:$B$21,MATCH($B$18,AI_ho_so_che_do!$A$2:$A$21,0))&"",";",""))+1)) | F18: =IF(OR($E$18<=1,ISNUMBER(FIND(";noGeneralTactic;",";"&INDEX(AI_ho_so_che_do!$O$2:$O$21,MATCH($B$18,AI_ho_so_che_do!$A$2:$A$21,0))&";"))),"Never",$D$18) | G18: Never | H18: =IF($D$18="Never","KHONG_DOI",IF($F$18="Never","HO_SO_CHAN","DO_KHO_CHO_DOI")) | I18: =COUNTIFS(AI_ho_so_pha!$B$2:$B$6,$B$18) | J18: Sim/AI/Commander.cs:45 (AiSkill.For Easy); balance.json aiModeProfiles.profiles.deathmatch
A19: deathmatch/Hard | B19: deathmatch | C19: Hard | D19: WhenLosing | E19: =IF(INDEX(AI_ho_so_che_do!$B$2:$B$21,MATCH($B$19,AI_ho_so_che_do!$A$2:$A$21,0))&""="*",COUNTIFS(Chien_thuat!$A$2:$A$17,"*"),IF(INDEX(AI_ho_so_che_do!$B$2:$B$21,MATCH($B$19,AI_ho_so_che_do!$A$2:$A$21,0))&""="",0,LEN(INDEX(AI_ho_so_che_do!$B$2:$B$21,MATCH($B$19,AI_ho_so_che_do!$A$2:$A$21,0))&"")-LEN(SUBSTITUTE(INDEX(AI_ho_so_che_do!$B$2:$B$21,MATCH($B$19,AI_ho_so_che_do!$A$2:$A$21,0))&"",";",""))+1)) | F19: =IF(OR($E$19<=1,ISNUMBER(FIND(";noGeneralTactic;",";"&INDEX(AI_ho_so_che_do!$O$2:$O$21,MATCH($B$19,AI_ho_so_che_do!$A$2:$A$21,0))&";"))),"Never",$D$19) | G19: WhenLosing | H19: =IF($D$19="Never","KHONG_DOI",IF($F$19="Never","HO_SO_CHAN","DO_KHO_CHO_DOI")) | I19: =COUNTIFS(AI_ho_so_pha!$B$2:$B$6,$B$19) | J19: Sim/AI/Commander.cs:46 (AiSkill.For Hard); balance.json aiModeProfiles.profiles.deathmatch
